Workbook

Sheet ASSUMPTIONS
A1: Assumption | B1: Value | C1: Note
A2: Days in Quarter | B2: 91 | C2: Used by DSO/DIO/DPO ratios. Approximation; varies 89-92 by quarter.

Sheet ANNL P&L
B1: FY2019 | C1: FY2020 | D1: FY2021 | E1: FY2022 | F1: FY2023 | G1: FY2024 | H1: FY2025 | I1: FY2026E | J1: FY2027E | K1: FY2028E | L1: FY2029E | M1: FY2030E | N1: FY2031E
A2: Net Sales / Revenue | B2: 4200819 | C2: 4598638 | D2: 5541352 | E2: 6311050 | F2: 7140027 | G2: 7492709 | H2: 8294343 | I2: ='QTR P&L'!Z2+'QTR P&L'!AA2+'QTR P&L'!AB2+'QTR P&L'!AC2 -> 9754572.1 | J2: ='QTR P&L'!AD2+'QTR P&L'!AE2+'QTR P&L'!AF2+'QTR P&L'!AG2 -> 11471876 | K2: ='QTR P&L'!AH2+'QTR P&L'!AI2+'QTR P&L'!AJ2+'QTR P&L'!AK2 -> 13491514 | L2: ='QTR P&L'!AL2+'QTR P&L'!AM2+'QTR P&L'!AN2+'QTR P&L'!AO2 -> 15866711 | M2: ='QTR P&L'!AP2+'QTR P&L'!AQ2+'QTR P&L'!AR2+'QTR P&L'!AS2 -> 18660065
A3: COGS | B3: -1682234 | C3: -1874758 | D3: -2432839 | E3: -3136483 | F3: -3345821 | G3: -3443831 | H3: -3662148 | I3: ='QTR P&L'!Z3+'QTR P&L'!AA3+'QTR P&L'!AB3+'QTR P&L'!AC3 -> -4338044.6 | J3: ='QTR P&L'!AD3+'QTR P&L'!AE3+'QTR P&L'!AF3+'QTR P&L'!AG3 -> -5101762.6 | K3: ='QTR P&L'!AH3+'QTR P&L'!AI3+'QTR P&L'!AJ3+'QTR P&L'!AK3 -> -5999934.1 | L3: ='QTR P&L'!AL3+'QTR P&L'!AM3+'QTR P&L'!AN3+'QTR P&L'!AO3 -> -7056229.7 | M3: ='QTR P&L'!AP3+'QTR P&L'!AQ3+'QTR P&L'!AR3+'QTR P&L'!AS3 -> -8298487.4
A4: Gross Profit (Loss) | B4: =B2+B3 -> 2518585 | C4: =C2+C3 -> 2723880 | D4: =D2+D3 -> 3108513 | E4: =E2+E3 -> 3174567 | F4: =F2+F3 -> 3794206 | G4: =G2+G3 -> 4048878 | H4: =H2+H3 -> 4632195 | I4: =I2+I3 -> 5416527.4 | ... N4: =N2+N3 -> 0
A5: Operating Expenses | B5: -1115646 | C5: -1090727 | D5: -1311046 | E5: -1589846 | F5: -1840851 | G5: -2118584 | H5: -2212841 | I5: ='QTR P&L'!Z5+'QTR P&L'!AA5+'QTR P&L'!AB5+'QTR P&L'!AC5 -> -2932702.6 | J5: ='QTR P&L'!AD5+'QTR P&L'!AE5+'QTR P&L'!AF5+'QTR P&L'!AG5 -> -3449008.4 | K5: ='QTR P&L'!AH5+'QTR P&L'!AI5+'QTR P&L'!AJ5+'QTR P&L'!AK5 -> -4056210.4 | L5: ='QTR P&L'!AL5+'QTR P&L'!AM5+'QTR P&L'!AN5+'QTR P&L'!AO5 -> -4770311.2 | M5: ='QTR P&L'!AP5+'QTR P&L'!AQ5+'QTR P&L'!AR5+'QTR P&L'!AS5 -> -5610130.2
A6: Income (Loss) from Operations | B6: =B4+B5 -> 1402939 | C6: =C4+C5 -> 1633153 | D6: =D4+D5 -> 1797467 | E6: =E4+E5 -> 1584721 | F6: =F4+F5 -> 1953355 | G6: =G4+G5 -> 1930294 | H6: =H4+H5 -> 2419354 | I6: =I4+I5 -> 2483824.9 | ... N6: =N4+N5 -> 0
A7: Interest Income (Expense) | B7: 0 | C7: 0 | D7: 0 | E7: 0 | F7: 115127 | G7: 59165 | H7: 0 | I7: ='QTR P&L'!Z8+'QTR P&L'!AA8+'QTR P&L'!AB8+'QTR P&L'!AC8 -> -150088 | J7: ='QTR P&L'!AD8+'QTR P&L'!AE8+'QTR P&L'!AF8+'QTR P&L'!AG8 -> -150088 | K7: ='QTR P&L'!AH8+'QTR P&L'!AI8+'QTR P&L'!AJ8+'QTR P&L'!AK8 -> -150088 | L7: ='QTR P&L'!AL8+'QTR P&L'!AM8+'QTR P&L'!AN8+'QTR P&L'!AO8 -> -150088 | M7: ='QTR P&L'!AP8+'QTR P&L'!AQ8+'QTR P&L'!AR8+'QTR P&L'!AS8 -> -150088
A8: Other Income (Expense) | B8: 13023 | C8: -6996 | D8: 3952 | E8: -12757 | F8: 0 | G8: 0 | H8: 63175 | I8: ='QTR P&L'!Z7+'QTR P&L'!AA7+'QTR P&L'!AB7+'QTR P&L'!AC7 -> 252700 | J8: ='QTR P&L'!AD7+'QTR P&L'!AE7+'QTR P&L'!AF7+'QTR P&L'!AG7 -> 252700 | K8: ='QTR P&L'!AH7+'QTR P&L'!AI7+'QTR P&L'!AJ7+'QTR P&L'!AK7 -> 252700 | L8: ='QTR P&L'!AL7+'QTR P&L'!AM7+'QTR P&L'!AN7+'QTR P&L'!AO7 -> 252700 | M8: ='QTR P&L'!AP7+'QTR P&L'!AQ7+'QTR P&L'!AR7+'QTR P&L'!AS7 -> 252700
A9: Pre-Tax Income (Loss) | B9: =B6+SUM(B7:B8) -> 1415962 | C9: =C6+SUM(C7:C8) -> 1626157 | D9: =D6+SUM(D7:D8) -> 1801419 | E9: =E6+SUM(E7:E8) -> 1571964 | F9: =F6+SUM(F7:F8) -> 2068482 | G9: =G6+SUM(G7:G8) -> 1989459 | H9: =H6+SUM(H7:H8) -> 2482529 | I9: =I6+SUM(I7:I8) -> 2586436.9 | ... N9: =N6+SUM(N7:N8) -> 0
A10: Income Tax (Expense) Benefit | B10: -308127 | C10: -216563 | D10: -423944 | E10: -380340 | F10: -437494 | G10: -480411 | H10: -577097 | I10: ='QTR P&L'!Z10+'QTR P&L'!AA10+'QTR P&L'!AB10+'QTR P&L'!AC10 -> -542044.55 | J10: ='QTR P&L'!AD10+'QTR P&L'!AE10+'QTR P&L'!AF10+'QTR P&L'!AG10 -> -633686.24 | K10: ='QTR P&L'!AH10+'QTR P&L'!AI10+'QTR P&L'!AJ10+'QTR P&L'!AK10 -> -741461.56 | L10: ='QTR P&L'!AL10+'QTR P&L'!AM10+'QTR P&L'!AN10+'QTR P&L'!AO10 -> -868210.85 | M10: ='QTR P&L'!AP10+'QTR P&L'!AQ10+'QTR P&L'!AR10+'QTR P&L'!AS10 -> -1017274.5
A11: Net Income (Loss) | B11: =B9+B10 -> 1107835 | C11: =C9+C10 -> 1409594 | D11: =D9+D10 -> 1377475 | E11: =E9+E10 -> 1191624 | F11: =F9+F10 -> 1630988 | G11: =G9+G10 -> 1509048 | H11: =H9+H10 -> 1905432 | I11: =I9+I10 -> 2044392.3 | ... N11: =N9+N10 -> 0
A12: Basic Earnings (Loss) per Share | B12: 2.04 | C12: 2.66 | D12: 2.61 | E12: 2.26 | F12: 1.56 | G12: 1.5 | H12: 1.95
A13: Diluted Earnings (Loss) per Share | B13: 2.03 | C13: 2.64 | D13: 2.57 | E13: 2.23 | F13: 1.54 | G13: 1.49 | H13: 1.94
A14: Weighted Average Shares Outstanding (Basic) | B14: 542191000 | C14: 529639000 | D14: 528763000 | E14: 526779000 | F14: 1044887000 | G14: 1004566000 | H14: 975887000
A15: Weighted Average Shares Outstanding (Diluted) | B15: 546608000 | C15: 534807000 | D15: 535639000 | E15: 533221000 | F15: 1057981000 | G15: 1013107000 | H15: 984451000
A16: Net Income (Loss) Attributable to Common Shareholders | B16: =B11 -> 1107835 | C16: =C11 -> 1409594 | D16: =D11 -> 1377475 | E16: =E11 -> 1191624 | F16: =F11 -> 1630988 | G16: =G11 -> 1509048 | H16: =H11 -> 1905432 | I16: =I11 -> 2044392.3 | ... N16: =N11 -> 0

Sheet BALANCE SHEET
B1: FY2020 | C1: FY2021 | D1: FY2022 | E1: FY2023 | F1: FY2024 | G1: FY2025 | H1: FY2026E | I1: FY2027E | J1: FY2028E | K1: FY2029E | L1: FY2030E | M1: FY2031E
A2: Cash & Cash Equivalents | B2: 1180413 | C2: 1326462 | D2: 1307141 | E2: 2297675 | F2: 1533287 | G2: 2088117 | H2: ='QTR BS'!Z2 -> 4144447.2 | I2: ='QTR BS'!AD2 -> 6528188 | J2: ='QTR BS'!AH2 -> 9296980.6 | K2: ='QTR BS'!AL2 -> 12518614 | L2: ='QTR BS'!AP2 -> 16272810
A3: Short-Term Investments | B3: 881354 | C3: 1749727 | D3: 1362314 | E3: 955605 | F3: 0 | G3: 677084 | H3: ='QTR BS'!Z3 -> 677084 | I3: ='QTR BS'!AD3 -> 677084 | J3: ='QTR BS'!AH3 -> 677084 | K3: ='QTR BS'!AL3 -> 677084 | L3: ='QTR BS'!AP3 -> 677084
A4: Accounts Receivable | B4: 666012 | C4: 896658 | D4: 1016203 | E4: 1193964 | F4: 1221646 | G4: 1618072 | H4: ='QTR BS'!Z4 -> 1902935.5 | I4: ='QTR BS'!AD4 -> 2237949.6 | J4: ='QTR BS'!AH4 -> 2631943.3 | K4: ='QTR BS'!AL4 -> 3095300.1 | L4: ='QTR BS'!AP4 -> 3640231.4
A5: Inventories | B5: 333085 | C5: 593357 | D5: 935631 | E5: 971406 | F5: 737107 | G5: 799623 | H5: ='QTR BS'!Z5 -> 940397.59 | I5: ='QTR BS'!AD5 -> 1105955.7 | J5: ='QTR BS'!AH5 -> 1300660.6 | K5: ='QTR BS'!AL5 -> 1529643.4 | L5: ='QTR BS'!AP5 -> 1798939
A6: Prepaid Expenses | B6: 55358 | C6: 82668 | D6: 109823 | E6: 116195 | F6: 107262 | G6: 103551 | H6: ='QTR BS'!Z6 -> 121781.28 | I6: ='QTR BS'!AD6 -> 143221.02 | J6: ='QTR BS'!AH6 -> 168435.25 | K6: ='QTR BS'!AL6 -> 198088.48 | L6: ='QTR BS'!AP6 -> 232962.2
A7: Prepaid Income Taxes | B7: 24733 | C7: 33238 | D7: 33785 | E7: 54151 | F7: 42202 | G7: 74637 | H7: ='QTR BS'!Z7 -> 87776.934 | I7: ='QTR BS'!AD7 -> 103230.17 | J7: ='QTR BS'!AH7 -> 121403.96 | K7: ='QTR BS'!AL7 -> 142777.28 | L7: ='QTR BS'!AP7 -> 167913.39
A8: Total Current Assets | B8: =SUM(B2:B7) -> 3140955 | C8: =SUM(C2:C7) -> 4682110 | D8: =SUM(D2:D7) -> 4764897 | E8: =SUM(E2:E7) -> 5588996 | F8: =SUM(F2:F7) -> 3641504 | G8: =SUM(G2:G7) -> 5361084 | H8: =SUM(H2:H7) -> 7874422.5 | I8: =SUM(I2:I7) -> 10795629 | ... M8: =SUM(M2:M7) -> 0
A9: Long-Term Investments | B9: 44291 | C9: 99419 | D9: 61443 | E9: 76431 | F9: 0 | G9: 487329 | H9: ='QTR BS'!Z9 -> 573123.86 | I9: ='QTR BS'!AD9 -> 674023 | J9: ='QTR BS'!AH9 -> 792685.56 | K9: ='QTR BS'!AL9 -> 932238.81 | L9: ='QTR BS'!AP9 -> 1096360.6
A10: Net PP&E | B10: 314656 | C10: 313753 | D10: 516897 | E10: 890796 | F10: 1047024 | G10: 1081544 | H10: ='QTR BS'!Z10 -> 1062117.7 | I10: ='QTR BS'!AD10 -> 1039271.4 | J10: ='QTR BS'!AH10 -> 1012403 | K10: ='QTR BS'!AL10 -> 980804.43 | L10: ='QTR BS'!AP10 -> 943642.85
A11: Deferred Tax Assets | B11: 241650 | C11: 225221 | D11: 177039 | E11: 175003 | F11: 184260 | G11: 188646 | H11: ='QTR BS'!Z11 -> 173626 | I11: ='QTR BS'!AD11 -> 158606 | J11: ='QTR BS'!AH11 -> 143586 | K11: ='QTR BS'!AL11 -> 128566 | L11: ='QTR BS'!AP11 -> 113546
A12: Goodwill | B12: 1331643 | C12: 1331643 | D12: 1417941 | E12: 1417941 | F12: 1331643 | G12: 1331643 | H12: ='QTR BS'!Z12 -> 1331643 | I12: ='QTR BS'!AD12 -> 1331643 | J12: ='QTR BS'!AH12 -> 1331643 | K12: ='QTR BS'!AL12 -> 1331643 | L12: ='QTR BS'!AP12 -> 1331643
A13: Intangible Assets | B13: 1059046 | C13: 1072386 | D13: 1220410 | E13: 1427139 | F13: 1414252 | G13: 1379268 | H13: ='QTR BS'!Z13 -> 1379268 | I13: ='QTR BS'!AD13 -> 1379268 | J13: ='QTR BS'!AH13 -> 1379268 | K13: ='QTR BS'!AL13 -> 1379268 | L13: ='QTR BS'!AP13 -> 1379268
A14: Other Non-Current Assets | B14: 70475 | C14: 80252 | D14: 134478 | E14: 110216 | F14: 100406 | G14: 159431 | H14: ='QTR BS'!Z14 -> 187499.02 | I14: ='QTR BS'!AD14 -> 220508.45 | J14: ='QTR BS'!AH14 -> 259329.23 | K14: ='QTR BS'!AL14 -> 304984.45 | L14: ='QTR BS'!AP14 -> 358677.33
A15: Total Assets | B15: =B8+SUM(B9:B14) -> 6202716 | C15: =C8+SUM(C9:C14) -> 7804784 | D15: =D8+SUM(D9:D14) -> 8293105 | E15: =E8+SUM(E9:E14) -> 9686522 | F15: =F8+SUM(F9:F14) -> 7719089 | G15: =G8+SUM(G9:G14) -> 9988945 | H15: =H8+SUM(H9:H14) -> 12581700 | I15: =I8+SUM(I9:I14) -> 15598948 | ... M15: =M8+SUM(M9:M14) -> 0
A16: Accounts Payable | B16: 296800 | C16: 404263 | D16: 444265 | E16: 564379 | F16: 466775 | G16: 565974 | H16: ='QTR BS'!Z16 -> 665614.4 | I16: ='QTR BS'!AD16 -> 782796.62 | J16: ='QTR BS'!AH16 -> 920608.91 | K16: ='QTR BS'!AL16 -> 1082683.2 | L16: ='QTR BS'!AP16 -> 1273290.9
A17: Accrued Expenses | B17: 142653 | C17: 210964 | D17: 172991 | E17: 183988 | F17: 220764 | G17: 306085 | H17: ='QTR BS'!Z17 -> 359971.63 | I17: ='QTR BS'!AD17 -> 423345.07 | J17: ='QTR BS'!AH17 -> 497875.48 | K17: ='QTR BS'!AL17 -> 585527.06 | L17: ='QTR BS'!AP17 -> 688609.8
A18: Accrued Promotional Allowance | B18: 186658 | C18: 211461 | D18: 255631 | E18: 269061 | F18: 267711 | G18: 384070 | H18: ='QTR BS'!Z18 -> 451685.99 | I18: ='QTR BS'!AD18 -> 531205.85 | J18: ='QTR BS'!AH18 -> 624725.28 | K18: ='QTR BS'!AL18 -> 734708.91 | L18: ='QTR BS'!AP18 -> 864055.3
A19: Deferred Revenue - Current | B19: 45429 | C19: 42530 | D19: 43311 | E19: 41914 | F19: 45809 | G19: 45323 | H19: ='QTR BS'!Z19 -> 53302.169 | I19: ='QTR BS'!AD19 -> 62686.08 | J19: ='QTR BS'!AH19 -> 73722.04 | K19: ='QTR BS'!AL19 -> 86700.893 | L19: ='QTR BS'!AP19 -> 101964.69
A20: Accrued Compensation | B20: 55015 | C20: 65459 | D20: 72463 | E20: 87392 | F20: 92454 | G20: 114023 | H20: ='QTR BS'!Z20 -> 134096.89 | I20: ='QTR BS'!AD20 -> 157704.8 | J20: ='QTR BS'!AH20 -> 185468.93 | K20: ='QTR BS'!AL20 -> 218120.95 | L20: ='QTR BS'!AP20 -> 256521.41
A21: Income Taxes Payable | B21: 23433 | C21: 30399 | D21: 13317 | E21: 14955 | F21: 4006 | G21: 32305 | H21: ='QTR BS'!Z21 -> 37992.334 | I21: ='QTR BS'!AD21 -> 44680.93 | J21: ='QTR BS'!AH21 -> 52547.062 | K21: ='QTR BS'!AL21 -> 61798.035 | L21: ='QTR BS'!AP21 -> 72677.654
A22: Total Current Liabilities | B22: =SUM(B16:B21) -> 749988 | C22: =SUM(C16:C21) -> 965076 | D22: =SUM(D16:D21) -> 1001978 | E22: =SUM(E16:E21) -> 1161689 | F22: =SUM(F16:F21) -> 1097519 | G22: =SUM(G16:G21) -> 1447780 | H22: =SUM(H16:H21) -> 1702663.4 | I22: =SUM(I16:I21) -> 2002419.4 | ... M22: =SUM(M16:M21) -> 0
A23: Deferred Revenue - Non-Current | B23: 264436 | C23: 243249 | D23: 223800 | E23: 204251 | F23: 179008 | G23: 159991 | H23: ='QTR BS'!Z23 -> 188157.61 | I23: ='QTR BS'!AD23 -> 221282.98 | J23: ='QTR BS'!AH23 -> 260240.12 | K23: ='QTR BS'!AL23 -> 306055.7 | L23: ='QTR BS'!AP23 -> 359937.18
A24: Other Non-Current Liabilities | B24: 27432 | C24: 29508 | D24: 42286 | E24: 91838 | F24: 110893 | G24: 127066 | H24: ='QTR BS'!Z25 -> 149436.12 | I24: ='QTR BS'!AD25 -> 175744.53 | J24: ='QTR BS'!AH25 -> 206684.57 | K24: ='QTR BS'!AL25 -> 243071.64 | L24: ='QTR BS'!AP25 -> 285864.69
A25: Long-Term Debt | B25: 0 | C25: 0 | D25: 0 | E25: 0 | F25: 373951 | G25: 0 | H25: ='QTR BS'!Z26 -> 0 | I25: ='QTR BS'!AD26 -> 0 | J25: ='QTR BS'!AH26 -> 0 | K25: ='QTR BS'!AL26 -> 0 | L25: ='QTR BS'!AP26 -> 0
A26: Total Liabilities | B26: =B22+SUM(B23:B25) -> 1041856 | C26: =C22+SUM(C23:C25) -> 1237833 | D26: =D22+SUM(D23:D25) -> 1268064 | E26: =E22+SUM(E23:E25) -> 1457778 | F26: =F22+SUM(F23:F25) -> 1761371 | G26: =G22+SUM(G23:G25) -> 1734837 | H26: =H22+SUM(H23:H25) -> 2040257.1 | I26: =I22+SUM(I23:I25) -> 2399446.9 | ... M26: =M22+SUM(M23:M25) -> 0
A27: Common Stock | B27: 3193 | C27: 3200 | D27: 3209 | E27: 5613 | F27: 5632 | G27: 5665 | H27: ='QTR BS'!Z28 -> 5665 | I27: ='QTR BS'!AD28 -> 5665 | J27: ='QTR BS'!AH28 -> 5665 | K27: ='QTR BS'!AL28 -> 5665 | L27: ='QTR BS'!AP28 -> 5665
A28: Additional Paid-in Capital | B28: 4537982 | C28: 4652620 | D28: 4780013 | E28: 4975115 | F28: 5144922 | G28: 5430847 | H28: ='QTR BS'!Z29 -> 5609468.9 | I28: ='QTR BS'!AD29 -> 5819537.3 | J28: ='QTR BS'!AH29 -> 6066588.6 | K28: ='QTR BS'!AL29 -> 6357133.5 | L28: ='QTR BS'!AP29 -> 6698829.3
A29: Retained Earnings (Accumulated Deficit) | B29: 6432074 | C29: 7809549 | D29: 9001173 | E29: 5939736 | F29: 7448784 | G29: 9354216 | H29: ='QTR BS'!Z30 -> 11398608 | I29: ='QTR BS'!AD30 -> 13788639 | J29: ='QTR BS'!AH30 -> 16585159 | K29: ='QTR BS'!AL30 -> 19859731 | L29: ='QTR BS'!AP30 -> 23696515
A30: Accumulated Other Comprehensive Income (Loss) | B30: 3034 | C30: -69165 | D30: -159073 | E30: -125337 | F30: -269487 | G30: -60841 | H30: ='QTR BS'!Z31 -> 39615 | I30: ='QTR BS'!AD31 -> 140071 | J30: ='QTR BS'!AH31 -> 240527 | K30: ='QTR BS'!AL31 -> 340983 | L30: ='QTR BS'!AP31 -> 441439
A31: Treasury Stock | B31: -5815423 | C31: -5829253 | D31: -6600281 | E31: -2566383 | F31: -6372133 | G31: -6475779 | H31: ='QTR BS'!Z32 -> -6475779 | I31: ='QTR BS'!AD32 -> -6475779 | J31: ='QTR BS'!AH32 -> -6475779 | K31: ='QTR BS'!AL32 -> -6475779 | L31: ='QTR BS'!AP32 -> -6475779
A32: Total Stockholders' Equity | B32: =SUM(B27:B31) -> 5160860 | C32: =SUM(C27:C31) -> 6566951 | D32: =SUM(D27:D31) -> 7025041 | E32: =SUM(E27:E31) -> 8228744 | F32: =SUM(F27:F31) -> 5957718 | G32: =SUM(G27:G31) -> 8254108 | H32: =SUM(H27:H31) -> 10577578 | I32: =SUM(I27:I31) -> 13278134 | ... M32: =SUM(M27:M31) -> 0
A33: Total Liabilities, Mezzanine & Stockholders' Equity | B33: =B26+B32 -> 6202716 | C33: =C26+C32 -> 7804784 | D33: =D26+D32 -> 8293105 | E33: =E26+E32 -> 9686522 | F33: =F26+F32 -> 7719089 | G33: =G26+G32 -> 9988945 | H33: =H26+H32 -> 12617835 | I33: =I26+I32 -> 15677581 | ... M33: =M26+M32 -> 0

Sheet CASH FLOW
B1: FY2019 | C1: FY2020 | D1: FY2021 | E1: FY2022 | F1: FY2023 | G1: FY2024 | H1: FY2025 | I1: FY2026E | J1: FY2027E | K1: FY2028E | L1: FY2029E | M1: FY2030E | N1: FY2031E
A2: Net Income (Loss) | B2: 1107835 | C2: 1409594 | D2: 1377475 | E2: 1191624 | F2: 1630988 | G2: 1509048 | H2: 1905432 | I2: ='QTR CF'!Z2+'QTR CF'!AA2+'QTR CF'!AB2+'QTR CF'!AC2 -> 2044392.3 | J2: ='QTR CF'!AD2+'QTR CF'!AE2+'QTR CF'!AF2+'QTR CF'!AG2 -> 2390031 | K2: ='QTR CF'!AH2+'QTR CF'!AI2+'QTR CF'!AJ2+'QTR CF'!AK2 -> 2796519.8 | L2: ='QTR CF'!AL2+'QTR CF'!AM2+'QTR CF'!AN2+'QTR CF'!AO2 -> 3274571.4 | M2: ='QTR CF'!AP2+'QTR CF'!AQ2+'QTR CF'!AR2+'QTR CF'!AS2 -> 3836784.6
A3: Depreciation & Amortization | B3: 60727 | C3: 57030 | D3: 50155 | E3: 61241 | F3: 68898 | G3: 80434 | H3: 114441 | I3: ='QTR CF'!Z3+'QTR CF'!AA3+'QTR CF'!AB3+'QTR CF'!AC3 -> 148388.48 | J3: ='QTR CF'!AD3+'QTR CF'!AE3+'QTR CF'!AF3+'QTR CF'!AG3 -> 174512.45 | K3: ='QTR CF'!AH3+'QTR CF'!AI3+'QTR CF'!AJ3+'QTR CF'!AK3 -> 205235.58 | L3: ='QTR CF'!AL3+'QTR CF'!AM3+'QTR CF'!AN3+'QTR CF'!AO3 -> 241367.55 | M3: ='QTR CF'!AP3+'QTR CF'!AQ3+'QTR CF'!AR3+'QTR CF'!AS3 -> 283860.6
A4: Non-Cash Lease Expense | B4: 4087 | C4: 3943 | D4: 4107 | E4: 7337 | F4: 9043 | G4: 13521 | H4: 15398 | I4: ='QTR CF'!Z4+'QTR CF'!AA4+'QTR CF'!AB4+'QTR CF'!AC4 -> 0 | J4: ='QTR CF'!AD4+'QTR CF'!AE4+'QTR CF'!AF4+'QTR CF'!AG4 -> 0 | K4: ='QTR CF'!AH4+'QTR CF'!AI4+'QTR CF'!AJ4+'QTR CF'!AK4 -> 0 | L4: ='QTR CF'!AL4+'QTR CF'!AM4+'QTR CF'!AN4+'QTR CF'!AO4 -> 0 | M4: ='QTR CF'!AP4+'QTR CF'!AQ4+'QTR CF'!AR4+'QTR CF'!AS4 -> 0
A5: Gain (Loss) on Disposal of PP&E | B5: -252 | C5: -350 | D5: -1013 | E5: -185 | F5: 166 | G5: 3328 | H5: 2781 | I5: ='QTR CF'!Z5+'QTR CF'!AA5+'QTR CF'!AB5+'QTR CF'!AC5 -> 0 | J5: ='QTR CF'!AD5+'QTR CF'!AE5+'QTR CF'!AF5+'QTR CF'!AG5 -> 0 | K5: ='QTR CF'!AH5+'QTR CF'!AI5+'QTR CF'!AJ5+'QTR CF'!AK5 -> 0 | L5: ='QTR CF'!AL5+'QTR CF'!AM5+'QTR CF'!AN5+'QTR CF'!AO5 -> 0 | M5: ='QTR CF'!AP5+'QTR CF'!AQ5+'QTR CF'!AR5+'QTR CF'!AS5 -> 0
A6: Gain on Bang Transaction | B6: 0 | C6: 0 | D6: 0 | E6: 0 | F6: -45382 | G6: 0 | H6: 0 | I6: ='QTR CF'!Z6+'QTR CF'!AA6+'QTR CF'!AB6+'QTR CF'!AC6 -> 0 | J6: ='QTR CF'!AD6+'QTR CF'!AE6+'QTR CF'!AF6+'QTR CF'!AG6 -> 0 | K6: ='QTR CF'!AH6+'QTR CF'!AI6+'QTR CF'!AJ6+'QTR CF'!AK6 -> 0 | L6: ='QTR CF'!AL6+'QTR CF'!AM6+'QTR CF'!AN6+'QTR CF'!AO6 -> 0 | M6: ='QTR CF'!AP6+'QTR CF'!AQ6+'QTR CF'!AR6+'QTR CF'!AS6 -> 0
A7: Impairment of Intangibles | B7: 0 | C7: 8700 | D7: 0 | E7: 2200 | F7: 38700 | G7: 127098 | H7: 38411 | I7: ='QTR CF'!Z7+'QTR CF'!AA7+'QTR CF'!AB7+'QTR CF'!AC7 -> 0 | J7: ='QTR CF'!AD7+'QTR CF'!AE7+'QTR CF'!AF7+'QTR CF'!AG7 -> 0 | K7: ='QTR CF'!AH7+'QTR CF'!AI7+'QTR CF'!AJ7+'QTR CF'!AK7 -> 0 | L7: ='QTR CF'!AL7+'QTR CF'!AM7+'QTR CF'!AN7+'QTR CF'!AO7 -> 0 | M7: ='QTR CF'!AP7+'QTR CF'!AQ7+'QTR CF'!AR7+'QTR CF'!AS7 -> 0
A8: Impairment of Long-Lived Assets (PP&E) | B8: 0 | C8: 0 | D8: 0 | E8: 0 | F8: 4336 | G8: 8184 | H8: 12029 | I8: ='QTR CF'!Z8+'QTR CF'!AA8+'QTR CF'!AB8+'QTR CF'!AC8 -> 0 | J8: ='QTR CF'!AD8+'QTR CF'!AE8+'QTR CF'!AF8+'QTR CF'!AG8 -> 0 | K8: ='QTR CF'!AH8+'QTR CF'!AI8+'QTR CF'!AJ8+'QTR CF'!AK8 -> 0 | L8: ='QTR CF'!AL8+'QTR CF'!AM8+'QTR CF'!AN8+'QTR CF'!AO8 -> 0 | M8: ='QTR CF'!AP8+'QTR CF'!AQ8+'QTR CF'!AR8+'QTR CF'!AS8 -> 0
A9: Stock-Based Compensation | B9: 63356 | C9: 70289 | D9: 70483 | E9: 64109 | F9: 68836 | G9: 90985 | H9: 125687 | I9: ='QTR CF'!Z9+'QTR CF'!AA9+'QTR CF'!AB9+'QTR CF'!AC9 -> 178621.87 | J9: ='QTR CF'!AD9+'QTR CF'!AE9+'QTR CF'!AF9+'QTR CF'!AG9 -> 210068.46 | K9: ='QTR CF'!AH9+'QTR CF'!AI9+'QTR CF'!AJ9+'QTR CF'!AK9 -> 247051.27 | L9: ='QTR CF'!AL9+'QTR CF'!AM9+'QTR CF'!AN9+'QTR CF'!AO9 -> 290544.94 | M9: ='QTR CF'!AP9+'QTR CF'!AQ9+'QTR CF'!AR9+'QTR CF'!AS9 -> 341695.73
A10: (Benefit) Provision for Deferred Income Taxes | B10: 1263 | C10: -156873 | D10: 16429 | E10: 48182 | F10: 2040 | G10: -11705 | H10: 4210 | I10: ='QTR CF'!Z10+'QTR CF'!AA10+'QTR CF'!AB10+'QTR CF'!AC10 -> 15020 | J10: ='QTR CF'!AD10+'QTR CF'!AE10+'QTR CF'!AF10+'QTR CF'!AG10 -> 15020 | K10: ='QTR CF'!AH10+'QTR CF'!AI10+'QTR CF'!AJ10+'QTR CF'!AK10 -> 15020 | L10: ='QTR CF'!AL10+'QTR CF'!AM10+'QTR CF'!AN10+'QTR CF'!AO10 -> 15020 | M10: ='QTR CF'!AP10+'QTR CF'!AQ10+'QTR CF'!AR10+'QTR CF'!AS10 -> 15020
A11: Accounts Receivable | B11: -59941 | C11: -119672 | D11: -254228 | E11: -128981 | F11: -163158 | G11: -93915 | H11: -300600 | I11: ='QTR CF'!Z11+'QTR CF'!AA11+'QTR CF'!AB11+'QTR CF'!AC11 -> -284863.52 | J11: ='QTR CF'!AD11+'QTR CF'!AE11+'QTR CF'!AF11+'QTR CF'!AG11 -> -335014.09 | K11: ='QTR CF'!AH11+'QTR CF'!AI11+'QTR CF'!AJ11+'QTR CF'!AK11 -> -393993.72 | L11: ='QTR CF'!AL11+'QTR CF'!AM11+'QTR CF'!AN11+'QTR CF'!AO11 -> -463356.79 | M11: ='QTR CF'!AP11+'QTR CF'!AQ11+'QTR CF'!AR11+'QTR CF'!AS11 -> -544931.32
A12: Inventories | B12: -85222 | C12: 30304 | D12: -277793 | E12: -347712 | F12: 7898 | G12: 211503 | H12: -34918 | I12: ='QTR CF'!Z13+'QTR CF'!AA13+'QTR CF'!AB13+'QTR CF'!AC13 -> -140774.59 | J12: ='QTR CF'!AD13+'QTR CF'!AE13+'QTR CF'!AF13+'QTR CF'!AG13 -> -165558.13 | K12: ='QTR CF'!AH13+'QTR CF'!AI13+'QTR CF'!AJ13+'QTR CF'!AK13 -> -194704.84 | L12: ='QTR CF'!AL13+'QTR CF'!AM13+'QTR CF'!AN13+'QTR CF'!AO13 -> -228982.86 | M12: ='QTR CF'!AP13+'QTR CF'!AQ13+'QTR CF'!AR13+'QTR CF'!AS13 -> -269295.56
A13: Prepaid Expenses | B13: -13774 | C13: 1024 | D13: -29341 | E13: -38268 | F13: -10215 | G13: 8959 | H13: -39307 | I13: ='QTR CF'!Z14+'QTR CF'!AA14+'QTR CF'!AB14+'QTR CF'!AC14 -> -18230.278 | J13: ='QTR CF'!AD14+'QTR CF'!AE14+'QTR CF'!AF14+'QTR CF'!AG14 -> -21439.741 | K13: ='QTR CF'!AH14+'QTR CF'!AI14+'QTR CF'!AJ14+'QTR CF'!AK14 -> -25214.233 | L13: ='QTR CF'!AL14+'QTR CF'!AM14+'QTR CF'!AN14+'QTR CF'!AO14 -> -29653.229 | M13: ='QTR CF'!AP14+'QTR CF'!AQ14+'QTR CF'!AR14+'QTR CF'!AS14 -> -34873.716
A14: Change in Prepaid Income Taxes | B14: 9481 | C14: 5516 | D14: -10919 | E14: -4439 | F14: -18833 | G14: 3062 | H14: -21094 | I14: ='QTR CF'!Z15+'QTR CF'!AA15+'QTR CF'!AB15+'QTR CF'!AC15 -> -13139.934 | J14: ='QTR CF'!AD15+'QTR CF'!AE15+'QTR CF'!AF15+'QTR CF'!AG15 -> -15453.235 | K14: ='QTR CF'!AH15+'QTR CF'!AI15+'QTR CF'!AJ15+'QTR CF'!AK15 -> -18173.795 | L14: ='QTR CF'!AL15+'QTR CF'!AM15+'QTR CF'!AN15+'QTR CF'!AO15 -> -21373.314 | M14: ='QTR CF'!AP15+'QTR CF'!AQ15+'QTR CF'!AR15+'QTR CF'!AS15 -> -25136.112
A15: Accounts Payable | B15: 28832 | C15: 18696 | D15: 114297 | E15: 49765 | F15: 112786 | G15: -61491 | H15: 78460 | I15: ='QTR CF'!Z16+'QTR CF'!AA16+'QTR CF'!AB16+'QTR CF'!AC16 -> 99640.404 | J15: ='QTR CF'!AD16+'QTR CF'!AE16+'QTR CF'!AF16+'QTR CF'!AG16 -> 117182.22 | K15: ='QTR CF'!AH16+'QTR CF'!AI16+'QTR CF'!AJ16+'QTR CF'!AK16 -> 137812.29 | L15: ='QTR CF'!AL16+'QTR CF'!AM16+'QTR CF'!AN16+'QTR CF'!AO16 -> 162074.31 | M15: ='QTR CF'!AP16+'QTR CF'!AQ16+'QTR CF'!AR16+'QTR CF'!AS16 -> 190607.68
A16: Accrued Expenses | B16: -14018 | C16: 26113 | D16: 71586 | E16: -30419 | F16: -10393 | G16: 18371 | H16: 81341 | I16: ='QTR CF'!Z17+'QTR CF'!AA17+'QTR CF'!AB17+'QTR CF'!AC17 -> 53886.633 | J16: ='QTR CF'!AD17+'QTR CF'!AE17+'QTR CF'!AF17+'QTR CF'!AG17 -> 63373.439 | K16: ='QTR CF'!AH17+'QTR CF'!AI17+'QTR CF'!AJ17+'QTR CF'!AK17 -> 74530.41 | L16: ='QTR CF'!AL17+'QTR CF'!AM17+'QTR CF'!AN17+'QTR CF'!AO17 -> 87651.578 | M16: ='QTR CF'!AP17+'QTR CF'!AQ17+'QTR CF'!AR17+'QTR CF'!AS17 -> 103082.74
A17: Accrued Promotional Allowance | B17: 21943 | C17: 13762 | D17: 31498 | E17: 50821 | F17: 8418 | G17: 9736 | H17: 98266 | I17: ='QTR CF'!Z18+'QTR CF'!AA18+'QTR CF'!AB18+'QTR CF'!AC18 -> 67615.986 | J17: ='QTR CF'!AD18+'QTR CF'!AE18+'QTR CF'!AF18+'QTR CF'!AG18 -> 79519.862 | K17: ='QTR CF'!AH18+'QTR CF'!AI18+'QTR CF'!AJ18+'QTR CF'!AK18 -> 93519.429 | L17: ='QTR CF'!AL18+'QTR CF'!AM18+'QTR CF'!AN18+'QTR CF'!AO18 -> 109983.64 | M17: ='QTR CF'!AP18+'QTR CF'!AQ18+'QTR CF'!AR18+'QTR CF'!AS18 -> 129346.39
A18: Change in Accrued Compensation | B18: 7228 | C18: 7501 | D18: 7950 | E18: 3729 | F18: 13398 | G18: 5947 | H18: 17801 | I18: ='QTR CF'!Z20+'QTR CF'!AA20+'QTR CF'!AB20+'QTR CF'!AC20 -> 20073.886 | J18: ='QTR CF'!AD20+'QTR CF'!AE20+'QTR CF'!AF20+'QTR CF'!AG20 -> 23607.918 | K18: ='QTR CF'!AH20+'QTR CF'!AI20+'QTR CF'!AJ20+'QTR CF'!AK20 -> 27764.121 | L18: ='QTR CF'!AL20+'QTR CF'!AM20+'QTR CF'!AN20+'QTR CF'!AO20 -> 32652.028 | M18: ='QTR CF'!AP20+'QTR CF'!AQ20+'QTR CF'!AR20+'QTR CF'!AS20 -> 38400.456
A19: Other Current Liabilities | B19: 8105 | C19: 10422 | D19: 7221 | E19: -16860 | F19: 1748 | G19: 9438 | H19: 27779 | I19: ='QTR CF'!Z21+'QTR CF'!AA21+'QTR CF'!AB21+'QTR CF'!AC21 -> 0 | J19: ='QTR CF'!AD21+'QTR CF'!AE21+'QTR CF'!AF21+'QTR CF'!AG21 -> 0 | K19: ='QTR CF'!AH21+'QTR CF'!AI21+'QTR CF'!AJ21+'QTR CF'!AK21 -> 0 | L19: ='QTR CF'!AL21+'QTR CF'!AM21+'QTR CF'!AN21+'QTR CF'!AO21 -> 0 | M19: ='QTR CF'!AP21+'QTR CF'!AQ21+'QTR CF'!AR21+'QTR CF'!AS21 -> 0
A20: Net Change in Other Working Capital | B20: -1030 | C20: -356 | D20: 492 | E20: -4540 | F20: 22951 | G20: 13390 | H20: -4935 | I20: ='QTR CF'!Z22+'QTR CF'!AA22+'QTR CF'!AB22+'QTR CF'!AC22 -> 0 | J20: ='QTR CF'!AD22+'QTR CF'!AE22+'QTR CF'!AF22+'QTR CF'!AG22 -> 0 | K20: ='QTR CF'!AH22+'QTR CF'!AI22+'QTR CF'!AJ22+'QTR CF'!AK22 -> 0 | L20: ='QTR CF'!AL22+'QTR CF'!AM22+'QTR CF'!AN22+'QTR CF'!AO22 -> 0 | M20: ='QTR CF'!AP22+'QTR CF'!AQ22+'QTR CF'!AR22+'QTR CF'!AS22 -> 0
A21: Deferred Revenue | B21: -24858 | C21: -21480 | D21: -22658 | E21: -19905 | F21: -24472 | G21: -17360 | H21: -23005 | I21: ='QTR CF'!Z23+'QTR CF'!AA23+'QTR CF'!AB23+'QTR CF'!AC23 -> 0 | J21: ='QTR CF'!AD23+'QTR CF'!AE23+'QTR CF'!AF23+'QTR CF'!AG23 -> 0 | K21: ='QTR CF'!AH23+'QTR CF'!AI23+'QTR CF'!AJ23+'QTR CF'!AK23 -> 0 | L21: ='QTR CF'!AL23+'QTR CF'!AM23+'QTR CF'!AN23+'QTR CF'!AO23 -> 0 | M21: ='QTR CF'!AP23+'QTR CF'!AQ23+'QTR CF'!AR23+'QTR CF'!AS23 -> 0
A22: Cash Flow from Operations | B22: =SUM(B2:B21) -> 1113762 | C22: =SUM(C2:C21) -> 1364163 | D22: =SUM(D2:D21) -> 1155741 | E22: =SUM(E2:E21) -> 887699 | F22: =SUM(F2:F21) -> 1717753 | G22: =SUM(G2:G21) -> 1928533 | H22: =SUM(H2:H21) -> 2098177 | I22: =SUM(I2:I21) -> 2170631.3 | ... N22: =SUM(N2:N21) -> 0
A23: Net Change in Long-Term Investments | B23: -216300 | C23: -379785 | D23: -924544 | E23: 405288 | F23: 409019 | G23: 1035794 | H23: -1163150 | I23: ='QTR CF'!Z25+'QTR CF'!AA25+'QTR CF'!AB25+'QTR CF'!AC25 -> -85794.857 | J23: ='QTR CF'!AD25+'QTR CF'!AE25+'QTR CF'!AF25+'QTR CF'!AG25 -> -100899.15 | K23: ='QTR CF'!AH25+'QTR CF'!AI25+'QTR CF'!AJ25+'QTR CF'!AK25 -> -118662.56 | L23: ='QTR CF'!AL25+'QTR CF'!AM25+'QTR CF'!AN25+'QTR CF'!AO25 -> -139553.25 | M23: ='QTR CF'!AP25+'QTR CF'!AQ25+'QTR CF'!AR25+'QTR CF'!AS25 -> -164121.77
A24: Acquisition of CANarchy | B24: 0 | C24: 0 | D24: 0 | E24: -329472 | F24: 0 | G24: 0 | H24: 0 | I24: ='QTR CF'!Z26+'QTR CF'!AA26+'QTR CF'!AB26+'QTR CF'!AC26 -> 0 | J24: ='QTR CF'!AD26+'QTR CF'!AE26+'QTR CF'!AF26+'QTR CF'!AG26 -> 0 | K24: ='QTR CF'!AH26+'QTR CF'!AI26+'QTR CF'!AJ26+'QTR CF'!AK26 -> 0 | L24: ='QTR CF'!AL26+'QTR CF'!AM26+'QTR CF'!AN26+'QTR CF'!AO26 -> 0 | M24: ='QTR CF'!AP26+'QTR CF'!AQ26+'QTR CF'!AR26+'QTR CF'!AS26 -> 0
A25: Acquisition of Monster Brewing | B25: 0 | C25: 0 | D25: 0 | E25: 0 | F25: 0 | G25: 0 | H25: 0 | I25: ='QTR CF'!Z27+'QTR CF'!AA27+'QTR CF'!AB27+'QTR CF'!AC27 -> 0 | J25: ='QTR CF'!AD27+'QTR CF'!AE27+'QTR CF'!AF27+'QTR CF'!AG27 -> 0 | K25: ='QTR CF'!AH27+'QTR CF'!AI27+'QTR CF'!AJ27+'QTR CF'!AK27 -> 0 | L25: ='QTR CF'!AL27+'QTR CF'!AM27+'QTR CF'!AN27+'QTR CF'!AO27 -> 0 | M25: ='QTR CF'!AP27+'QTR CF'!AQ27+'QTR CF'!AR27+'QTR CF'!AS27 -> 0
A26: Acquisition of Bang Energy | B26: 0 | C26: 0 | D26: 0 | E26: 0 | F26: -363385 | G26: 0 | H26: 0 | I26: ='QTR CF'!Z28+'QTR CF'!AA28+'QTR CF'!AB28+'QTR CF'!AC28 -> 0 | J26: ='QTR CF'!AD28+'QTR CF'!AE28+'QTR CF'!AF28+'QTR CF'!AG28 -> 0 | K26: ='QTR CF'!AH28+'QTR CF'!AI28+'QTR CF'!AJ28+'QTR CF'!AK28 -> 0 | L26: ='QTR CF'!AL28+'QTR CF'!AM28+'QTR CF'!AN28+'QTR CF'!AO28 -> 0 | M26: ='QTR CF'!AP28+'QTR CF'!AQ28+'QTR CF'!AR28+'QTR CF'!AS28 -> 0
A27: Purchase of PP&E | B27: -101661 | C27: -48722 | D27: -43868 | E27: -188726 | F27: -221428 | G27: -264074 | H27: -132275 | I27: ='QTR CF'!Z29+'QTR CF'!AA29+'QTR CF'!AB29+'QTR CF'!AC29 -> -128962.21 | J27: ='QTR CF'!AD29+'QTR CF'!AE29+'QTR CF'!AF29+'QTR CF'!AG29 -> -151666.17 | K27: ='QTR CF'!AH29+'QTR CF'!AI29+'QTR CF'!AJ29+'QTR CF'!AK29 -> -178367.18 | L27: ='QTR CF'!AL29+'QTR CF'!AM29+'QTR CF'!AN29+'QTR CF'!AO29 -> -209768.94 | M27: ='QTR CF'!AP29+'QTR CF'!AQ29+'QTR CF'!AR29+'QTR CF'!AS29 -> -246699.01
A28: Proceeds from Sale of Assets | B28: 1239 | C28: 993 | D28: 1328 | E28: 1313 | F28: 2520 | G28: 2732 | H28: 4299 | I28: ='QTR CF'!Z30+'QTR CF'!AA30+'QTR CF'!AB30+'QTR CF'!AC30 -> 0 | J28: ='QTR CF'!AD30+'QTR CF'!AE30+'QTR CF'!AF30+'QTR CF'!AG30 -> 0 | K28: ='QTR CF'!AH30+'QTR CF'!AI30+'QTR CF'!AJ30+'QTR CF'!AK30 -> 0 | L28: ='QTR CF'!AL30+'QTR CF'!AM30+'QTR CF'!AN30+'QTR CF'!AO30 -> 0 | M28: ='QTR CF'!AP30+'QTR CF'!AQ30+'QTR CF'!AR30+'QTR CF'!AS30 -> 0
A29: Additions to Intangibles | B29: -8737 | C29: -18550 | D29: -13585 | E29: -23427 | F29: -13296 | G29: -42360 | H29: -25254 | I29: ='QTR CF'!Z31+'QTR CF'!AA31+'QTR CF'!AB31+'QTR CF'!AC31 -> 0 | J29: ='QTR CF'!AD31+'QTR CF'!AE31+'QTR CF'!AF31+'QTR CF'!AG31 -> 0 | K29: ='QTR CF'!AH31+'QTR CF'!AI31+'QTR CF'!AJ31+'QTR CF'!AK31 -> 0 | L29: ='QTR CF'!AL31+'QTR CF'!AM31+'QTR CF'!AN31+'QTR CF'!AO31 -> 0 | M29: ='QTR CF'!AP31+'QTR CF'!AQ31+'QTR CF'!AR31+'QTR CF'!AS31 -> 0
A30: Other Investing Activities | B30: -1265 | C30: -26423 | D30: -11353 | E30: -26343 | F30: -6825 | G30: 1635 | H30: -398 | I30: ='QTR CF'!Z32+'QTR CF'!AA32+'QTR CF'!AB32+'QTR CF'!AC32 -> 0 | J30: ='QTR CF'!AD32+'QTR CF'!AE32+'QTR CF'!AF32+'QTR CF'!AG32 -> 0 | K30: ='QTR CF'!AH32+'QTR CF'!AI32+'QTR CF'!AJ32+'QTR CF'!AK32 -> 0 | L30: ='QTR CF'!AL32+'QTR CF'!AM32+'QTR CF'!AN32+'QTR CF'!AO32 -> 0 | M30: ='QTR CF'!AP32+'QTR CF'!AQ32+'QTR CF'!AR32+'QTR CF'!AS32 -> 0
A31: Cash Flow from Investing | B31: =SUM(B23:B30) -> -326724 | C31: =SUM(C23:C30) -> -472487 | D31: =SUM(D23:D30) -> -992022 | E31: =SUM(E23:E30) -> -161367 | F31: =SUM(F23:F30) -> -193395 | G31: =SUM(G23:G30) -> 733727 | H31: =SUM(H23:H30) -> -1316778 | I31: =SUM(I23:I30) -> -214757.07 | ... N31: =SUM(N23:N30) -> 0
A32: Net Change in Other Short-Term Debt | B32: -13569 | C32: -3086 | D32: 2928 | E32: 75 | F32: -13914 | G32: -8223 | H32: -10344 | I32: ='QTR CF'!Z35+'QTR CF'!AA35+'QTR CF'!AB35+'QTR CF'!AC35 -> 0 | J32: ='QTR CF'!AD35+'QTR CF'!AE35+'QTR CF'!AF35+'QTR CF'!AG35 -> 0 | K32: ='QTR CF'!AH35+'QTR CF'!AI35+'QTR CF'!AJ35+'QTR CF'!AK35 -> 0 | L32: ='QTR CF'!AL35+'QTR CF'!AM35+'QTR CF'!AN35+'QTR CF'!AO35 -> 0 | M32: ='QTR CF'!AP35+'QTR CF'!AQ35+'QTR CF'!AR35+'QTR CF'!AS35 -> 0
A33: Proceeds from Issuance of Long-Term Debt | B33: 0 | C33: 0 | D33: 0 | E33: 0 | F33: 0 | G33: 750000 | H33: 0 | I33: ='QTR CF'!Z36+'QTR CF'!AA36+'QTR CF'!AB36+'QTR CF'!AC36 -> 0 | J33: ='QTR CF'!AD36+'QTR CF'!AE36+'QTR CF'!AF36+'QTR CF'!AG36 -> 0 | K33: ='QTR CF'!AH36+'QTR CF'!AI36+'QTR CF'!AJ36+'QTR CF'!AK36 -> 0 | L33: ='QTR CF'!AL36+'QTR CF'!AM36+'QTR CF'!AN36+'QTR CF'!AO36 -> 0 | M33: ='QTR CF'!AP36+'QTR CF'!AQ36+'QTR CF'!AR36+'QTR CF'!AS36 -> 0
A34: Repayments of Long-Term Debt | B34: 0 | C34: 0 | D34: 0 | E34: 0 | F34: 0 | G34: -375000 | H34: -375000 | I34: ='QTR CF'!Z38+'QTR CF'!AA38+'QTR CF'!AB38+'QTR CF'!AC38 -> 0 | J34: ='QTR CF'!AD38+'QTR CF'!AE38+'QTR CF'!AF38+'QTR CF'!AG38 -> 0 | K34: ='QTR CF'!AH38+'QTR CF'!AI38+'QTR CF'!AJ38+'QTR CF'!AK38 -> 0 | L34: ='QTR CF'!AL38+'QTR CF'!AM38+'QTR CF'!AN38+'QTR CF'!AO38 -> 0 | M34: ='QTR CF'!AP38+'QTR CF'!AQ38+'QTR CF'!AR38+'QTR CF'!AS38 -> 0
A35: Debt Issuance Fees | B35: 0 | C35: 0 | D35: 0 | E35: 0 | F35: 0 | G35: -2904 | H35: 0 | I35: ='QTR CF'!Z37+'QTR CF'!AA37+'QTR CF'!AB37+'QTR CF'!AC37 -> 0 | J35: ='QTR CF'!AD37+'QTR CF'!AE37+'QTR CF'!AF37+'QTR CF'!AG37 -> 0 | K35: ='QTR CF'!AH37+'QTR CF'!AI37+'QTR CF'!AJ37+'QTR CF'!AK37 -> 0 | L35: ='QTR CF'!AL37+'QTR CF'!AM37+'QTR CF'!AN37+'QTR CF'!AO37 -> 0 | M35: ='QTR CF'!AP37+'QTR CF'!AQ37+'QTR CF'!AR37+'QTR CF'!AS37 -> 0
A36: Proceeds from Issuance of Common Stock | B36: 92363 | C36: 72936 | D36: 45723 | E36: 64015 | F36: 130267 | G36: 78973 | H36: 164568 | I36: ='QTR CF'!Z39+'QTR CF'!AA39+'QTR CF'!AB39+'QTR CF'!AC39 -> 0 | J36: ='QTR CF'!AD39+'QTR CF'!AE39+'QTR CF'!AF39+'QTR CF'!AG39 -> 0 | K36: ='QTR CF'!AH39+'QTR CF'!AI39+'QTR CF'!AJ39+'QTR CF'!AK39 -> 0 | L36: ='QTR CF'!AL39+'QTR CF'!AM39+'QTR CF'!AN39+'QTR CF'!AO39 -> 0 | M36: ='QTR CF'!AP39+'QTR CF'!AQ39+'QTR CF'!AR39+'QTR CF'!AS39 -> 0
A37: Share Repurchases | B37: -707300 | C37: -595918 | D37: -13830 | E37: -771028 | F37: -658952 | G37: -3771875 | H37: -103646 | I37: ='QTR CF'!Z40+'QTR CF'!AA40+'QTR CF'!AB40+'QTR CF'!AC40 -> 0 | J37: ='QTR CF'!AD40+'QTR CF'!AE40+'QTR CF'!AF40+'QTR CF'!AG40 -> 0 | K37: ='QTR CF'!AH40+'QTR CF'!AI40+'QTR CF'!AJ40+'QTR CF'!AK40 -> 0 | L37: ='QTR CF'!AL40+'QTR CF'!AM40+'QTR CF'!AN40+'QTR CF'!AO40 -> 0 | M37: ='QTR CF'!AP40+'QTR CF'!AQ40+'QTR CF'!AR40+'QTR CF'!AS40 -> 0
A38: Cash Flow from Financing | B38: =SUM(B32:B37) -> -628506 | C38: =SUM(C32:C37) -> -526068 | D38: =SUM(D32:D37) -> 34821 | E38: =SUM(E32:E37) -> -706938 | F38: =SUM(F32:F37) -> -542599 | G38: =SUM(G32:G37) -> -3329029 | H38: =SUM(H32:H37) -> -324422 | I38: =SUM(I32:I37) -> 0 | ... N38: =SUM(N32:N37) -> 0
A39: FX Effect on Cash | B39: 1912 | C39: 16848 | D39: -52491 | E39: -38715 | F39: 8775 | G39: -97619 | H39: 97853 | I39: ='QTR CF'!Z42+'QTR CF'!AA42+'QTR CF'!AB42+'QTR CF'!AC42 -> 100456 | J39: ='QTR CF'!AD42+'QTR CF'!AE42+'QTR CF'!AF42+'QTR CF'!AG42 -> 100456 | K39: ='QTR CF'!AH42+'QTR CF'!AI42+'QTR CF'!AJ42+'QTR CF'!AK42 -> 100456 | L39: ='QTR CF'!AL42+'QTR CF'!AM42+'QTR CF'!AN42+'QTR CF'!AO42 -> 100456 | M39: ='QTR CF'!AP42+'QTR CF'!AQ42+'QTR CF'!AR42+'QTR CF'!AS42 -> 100456
A40: Net Change in Cash | B40: =B22+B31+B38+B39 -> 160444 | C40: =C22+C31+C38+C39 -> 382456 | D40: =D22+D31+D38+D39 -> 146049 | E40: =E22+E31+E38+E39 -> -19321 | F40: =F22+F31+F38+F39 -> 990534 | G40: =G22+G31+G38+G39 -> -764388 | H40: =H22+H31+H38+H39 -> 554830 | I40: =I22+I31+I38+I39 -> 2056330.2 | ... N40: =N22+N31+N38+N39 -> 0

Sheet YTD P&L
B1: Q1 FY2020 | C1: Q2 FY2020 | D1: Q3 FY2020 | E1: Q1 FY2021 | F1: Q2 FY2021 | G1: Q3 FY2021 | H1: Q1 FY2022 | I1: Q2 FY2022 | J1: Q3 FY2022 | K1: Q1 FY2023 | L1: Q2 FY2023 | M1: Q3 FY2023 | N1: Q1 FY2024 | O1: Q2 FY2024 | P1: Q3 FY2024 | Q1: Q1 FY2025 | R1: Q2 FY2025 | S1: Q3 FY2025
A2: Net Sales / Revenue | B2: 1062097 | C2: 2155993 | D2: 3402355 | E2: 1243816 | F2: 2705751 | G2: 4116308 | H2: 1518574 | I2: 3173833 | J2: 4798119 | K2: 1698930 | L2: 3553891 | M2: 5409919 | N2: 1899098 | O2: 3799695 | P2: 5680668 | Q2: 1854558 | R2: 3966150 | S2: 6163290
A3: COGS | B3: -424901 | C3: -859329 | D3: -1369160 | E3: -528881 | F3: -1153976 | G3: -1775375 | H3: -741907 | I3: -1617306 | J3: -2407867 | K3: -801081 | L3: -1681820 | M3: -2554086 | N3: -871969 | O3: -1753061 | P3: -2634235 | Q3: -806596 | R3: -1741775 | S3: -2714428
A4: Gross Profit (Loss) | B4: =B2+B3 -> 637196 | C4: =C2+C3 -> 1296664 | D4: =D2+D3 -> 2033195 | E4: =E2+E3 -> 714935 | F4: =F2+F3 -> 1551775 | G4: =G2+G3 -> 2340933 | H4: =H2+H3 -> 776667 | I4: =I2+I3 -> 1556527 | ... S4: =S2+S3 -> 3448862
A5: Operating Expenses | B5: -272208 | C5: -524412 | D5: -802343 | E5: -300789 | F5: -611652 | G5: -956346 | H5: -377178 | I5: -784088 | J5: -1199883 | K5: -412785 | L5: -863201 | M5: -1336437 | N5: -485138 | O5: -977480 | P5: -1497363 | Q5: -478217 | R5: -1023008 | S5: -1572142
A6: Income (Loss) from Operations | B6: =B4+B5 -> 364988 | C6: =C4+C5 -> 772252 | D6: =D4+D5 -> 1230852 | E6: =E4+E5 -> 414146 | F6: =F4+F5 -> 940123 | G6: =G4+G5 -> 1384587 | H6: =H4+H5 -> 399489 | I6: =I4+I5 -> 772439 | ... S6: =S4+S5 -> 1876720
A7: Other Income (Expense) | B7: 0 | C7: 0 | D7: 0 | E7: 0 | F7: 0 | G7: 0 | H7: 0 | I7: 0 | J7: 0 | K7: 0 | L7: 0 | M7: 0 | N7: 35754 | O7: 60131 | P7: 0 | Q7: 8272 | R7: 23337 | S7: 0
A8: Interest Income (Expense) | B8: 872 | C8: -923 | D8: -5491 | E8: -759 | F8: 111 | G8: -2179 | H8: -7300 | I8: -14080 | J8: -11932 | K8: 12496 | L8: 27653 | M8: 99010 | N8: 0 | O8: 0 | P8: 54311 | Q8: 0 | R8: 0 | S8: 37522
A9: Pre-Tax Income (Loss) | B9: =B6+SUM(B7:B8) -> 365860 | C9: =C6+SUM(C7:C8) -> 771329 | D9: =D6+SUM(D7:D8) -> 1225361 | E9: =E6+SUM(E7:E8) -> 413387 | F9: =F6+SUM(F7:F8) -> 940234 | G9: =G6+SUM(G7:G8) -> 1382408 | H9: =H6+SUM(H7:H8) -> 392189 | I9: =I6+SUM(I7:I8) -> 758359 | ... S9: =S6+SUM(S7:S8) -> 1914242
A10: Income Tax (Expense) Benefit | B10: -87025 | C10: -181125 | D10: -287503 | E10: -98193 | F10: -221278 | G10: -326247 | H10: -97986 | I10: -190796 | J10: -288487 | K10: -100116 | L10: -225208 | M10: -354397 | N10: -135696 | O10: -261867 | P10: -365044 | Q10: -135024 | R10: -292917 | S10: -458000
A11: Net Income (Loss) | B11: =B9+B10 -> 278835 | C11: =C9+C10 -> 590204 | D11: =D9+D10 -> 937858 | E11: =E9+E10 -> 315194 | F11: =F9+F10 -> 718956 | G11: =G9+G10 -> 1056161 | H11: =H9+H10 -> 294203 | I11: =I9+I10 -> 567563 | ... S11: =S9+S10 -> 1456242
A12: Basic Earnings (Loss) per Share | B12: 0.52 | C12: 1.11 | D12: 1.77 | E12: 0.6 | F12: 1.36 | G12: 2 | H12: 0.56 | I12: 1.07 | J12: 1.68 | K12: 0.38 | L12: 0.78 | M12: 1.21 | N12: 0.42 | O12: 0.84 | P12: 1.22 | Q12: 0.45 | R12: 0.96 | S12: 1.49
A13: Diluted Earnings (Loss) per Share | B13: 0.52 | C13: 1.1 | D13: 1.75 | E13: 0.59 | F13: 1.34 | G13: 1.97 | H13: 0.55 | I13: 1.06 | J13: 1.66 | K13: 0.38 | L13: 0.77 | M13: 1.19 | N13: 0.42 | O13: 0.83 | P13: 1.21 | Q13: 0.45 | R13: 0.95 | S13: 1.48
A14: Weighted Average Shares Outstanding (Basic) | B14: 536061000 | C14: 531486000 | D14: 530194000 | E14: 528195000 | F14: 528425000 | G14: 528618000 | H14: 529405000 | I14: 529009000 | J14: 528263000 | K14: 1044909000 | L14: 1045993000 | M14: 1046337000 | N14: 1041081000 | O14: 1035175000 | P14: 1015252000 | Q14: 973622000 | R14: 974691000 | S14: 975337000
A15: Weighted Average Shares Outstanding (Diluted) | B15: 540518000 | C15: 535897000 | D15: 535011000 | E15: 534982000 | F15: 535324000 | G15: 535554000 | H15: 535554000 | I15: 535209000 | J15: 534599000 | K15: 1059069000 | L15: 1059667000 | M15: 1059809000 | N15: 1051282000 | O15: 1044363000 | P15: 1023912000 | Q15: 981282000 | R15: 982748000 | S15: 983532000
A16: Net Income (Loss) Attributable to Common Shareholders | B16: =B11 -> 278835 | C16: =C11 -> 590204 | D16: =D11 -> 937858 | E16: =E11 -> 315194 | F16: =F11 -> 718956 | G16: =G11 -> 1056161 | H16: =H11 -> 294203 | I16: =I11 -> 567563 | ... S16: =S11 -> 1456242

Sheet YTD BS
B1: Q4 FY2020 | C1: Q1 FY2021 | D1: Q2 FY2021 | E1: Q3 FY2021 | F1: Q4 FY2021 | G1: Q1 FY2022 | H1: Q2 FY2022 | I1: Q3 FY2022 | J1: Q4 FY2022 | K1: Q1 FY2023 | L1: Q2 FY2023 | M1: Q3 FY2023 | N1: Q4 FY2023 | O1: Q1 FY2024 | P1: Q2 FY2024 | Q1: Q3 FY2024 | R1: Q4 FY2024 | S1: Q1 FY2025 | T1: Q2 FY2025 | U1: Q3 FY2025
A2: Cash & Cash Equivalents | B2: 1180413 | C2: 1178879 | D2: 1584239 | E2: 1712671 | F2: 1326462 | G2: 1014786 | H2: 1132039 | I2: 1303048 | J2: 1307141 | K2: 1672660 | L2: 1869774 | M2: 1773849 | N2: 2297675 | O2: 2576524 | P2: 1564734 | Q2: 1625339 | R2: 1533287 | S2: 1903419 | T2: 1926927 | U2: 2292939
A3: Short-Term Investments | B3: 881354 | C3: 980108 | D3: 968952 | E3: 1224066 | F3: 1749727 | G3: 1717648 | H3: 1337792 | I3: 1346781 | J3: 1362314 | K3: 1383028 | L3: 1417239 | M3: 1236752 | N3: 955605 | O3: 984201 | P3: 0 | Q3: 0 | R3: 0 | S3: 0 | T3: 145253 | U3: 286391
A4: Accounts Receivable | B4: 666012 | C4: 802509 | D4: 909169 | E4: 849157 | F4: 896658 | G4: 1039780 | H4: 1175587 | I4: 1051642 | J4: 1016203 | K4: 1190351 | L4: 1333004 | M4: 1231188 | N4: 1193964 | O4: 1370239 | P4: 1362398 | Q4: 1285397 | R4: 1221646 | S4: 1360233 | T4: 1522702 | U4: 1601216
A5: Inventories | B5: 333085 | C5: 368402 | D5: 382890 | E5: 471553 | F5: 593357 | G5: 821132 | H5: 885948 | I5: 862977 | J5: 935631 | K5: 906723 | L5: 846812 | M5: 883582 | N5: 971406 | O5: 939630 | P5: 834404 | Q5: 770338 | R5: 737107 | S5: 725129 | T5: 658167 | U5: 704586
A6: Prepaid Expenses | B6: 55358 | C6: 72803 | D6: 83086 | E6: 95607 | F6: 82668 | G6: 110327 | H6: 132273 | I6: 112294 | J6: 109823 | K6: 110958 | L6: 148750 | M6: 162676 | N6: 116195 | O6: 124580 | P6: 129303 | Q6: 124656 | R6: 107262 | S6: 112525 | T6: 137257 | U6: 142713
A7: Prepaid Income Taxes | B7: 24733 | C7: 31171 | D7: 22339 | E7: 30619 | F7: 33238 | G7: 39993 | H7: 32981 | I7: 19949 | J7: 33785 | K7: 30889 | L7: 38534 | M7: 23468 | N7: 54151 | O7: 40340 | P7: 63458 | Q7: 92028 | R7: 42202 | S7: 34113 | T7: 39034 | U7: 38372
A8: Total Current Assets | B8: =SUM(B2:B7) -> 3140955 | C8: =SUM(C2:C7) -> 3433872 | D8: =SUM(D2:D7) -> 3950675 | E8: =SUM(E2:E7) -> 4383673 | F8: =SUM(F2:F7) -> 4682110 | G8: =SUM(G2:G7) -> 4743666 | H8: =SUM(H2:H7) -> 4696620 | I8: =SUM(I2:I7) -> 4696691 | ... U8: =SUM(U2:U7) -> 5066217
A9: Long-Term Investments | B9: 44291 | C9: 63751 | D9: 91033 | E9: 28255 | F9: 99419 | G9: 65652 | H9: 64119 | I9: 72373 | J9: 61443 | K9: 41152 | L9: 62248 | M9: 52636 | N9: 76431 | O9: 8162 | P9: 0 | Q9: 0 | R9: 0 | S9: 0 | T9: 138058 | U9: 359174
A10: Net PP&E | B10: 314656 | C10: 312155 | D10: 309178 | E10: 309574 | F10: 313753 | G10: 407391 | H10: 464541 | I10: 485550 | J10: 516897 | K10: 545922 | L10: 576645 | M10: 731208 | N10: 890796 | O10: 923290 | P10: 960962 | Q10: 1006788 | R10: 1047024 | S10: 1064008 | T10: 1090898 | U10: 1110705
A11: Deferred Tax Assets | B11: 241650 | C11: 241650 | D11: 241297 | E11: 241297 | F11: 225221 | G11: 225221 | H11: 203287 | I11: 195511 | J11: 177039 | K11: 177039 | L11: 177039 | M11: 176724 | N11: 175003 | O11: 175271 | P11: 187269 | Q11: 183430 | R11: 184260 | S11: 184358 | T11: 184791 | U11: 185321
A12: Goodwill | B12: 1331643 | C12: 1331643 | D12: 1331643 | E12: 1331643 | F12: 1331643 | G12: 1411928 | H12: 1412941 | I12: 1412941 | J12: 1417941 | K12: 1417941 | L12: 1417941 | M12: 1417941 | N12: 1417941 | O12: 1417941 | P12: 1417941 | Q12: 1417941 | R12: 1331643 | S12: 1331643 | T12: 1331643 | U12: 1331643
A13: Intangible Assets | B13: 1059046 | C13: 1063092 | D13: 1058323 | E13: 1066083 | F13: 1072386 | G13: 1232113 | H13: 1223114 | I13: 1225826 | J13: 1220410 | K13: 1222598 | L13: 1224100 | M13: 1459447 | N13: 1427139 | O13: 1430762 | P13: 1433326 | Q13: 1442426 | R13: 1414252 | S13: 1415958 | T13: 1418827 | U13: 1419306
A14: Other Non-Current Assets | B14: 70475 | C14: 88203 | D14: 89394 | E14: 88883 | F14: 80252 | G14: 101488 | H14: 110390 | I14: 115913 | J14: 134478 | K14: 145101 | L14: 151252 | M14: 164867 | N14: 110216 | O14: 107126 | P14: 107109 | Q14: 104958 | R14: 100406 | S14: 95642 | T14: 136331 | U14: 138907
A15: Total Assets | B15: =B8+SUM(B9:B14) -> 6202716 | C15: =C8+SUM(C9:C14) -> 6534366 | D15: =D8+SUM(D9:D14) -> 7071543 | E15: =E8+SUM(E9:E14) -> 7449408 | F15: =F8+SUM(F9:F14) -> 7804784 | G15: =G8+SUM(G9:G14) -> 8187459 | H15: =H8+SUM(H9:H14) -> 8175012 | I15: =I8+SUM(I9:I14) -> 8204805 | ... U15: =U8+SUM(U9:U14) -> 9611273
A16: Accounts Payable | B16: 296800 | C16: 334076 | D16: 362900 | E16: 396229 | F16: 404263 | G16: 438256 | H16: 492858 | I16: 520198 | J16: 444265 | K16: 491249 | L16: 568613 | M16: 539892 | N16: 564379 | O16: 533729 | P16: 511137 | Q16: 549028 | R16: 466775 | S16: 486951 | T16: 489037 | U16: 683030
A17: Accrued Expenses | B17: 142653 | C17: 170954 | D17: 172498 | E17: 180719 | F17: 210964 | G17: 234111 | H17: 209154 | I17: 198692 | J17: 172991 | K17: 245932 | L17: 198656 | M17: 207727 | N17: 183988 | O17: 204679 | P17: 213905 | Q17: 259088 | R17: 220764 | S17: 262545 | T17: 258937 | U17: 325450
A18: Accrued Promotional Allowance | B18: 186658 | C18: 197380 | D18: 227414 | E18: 232394 | F18: 211461 | G18: 270785 | H18: 277618 | I18: 281650 | J18: 255631 | K18: 308094 | L18: 283647 | M18: 296577 | N18: 269061 | O18: 318895 | P18: 319757 | Q18: 301973 | R18: 267711 | S18: 304670 | T18: 360406 | U18: 392628
A19: Deferred Revenue - Current | B19: 45429 | C19: 45961 | D19: 46656 | E19: 45278 | F19: 42530 | G19: 42540 | H19: 44344 | I19: 42608 | J19: 43311 | K19: 44440 | L19: 42765 | M19: 40127 | N19: 41914 | O19: 43776 | P19: 44377 | Q19: 45627 | R19: 45809 | S19: 47542 | T19: 49279 | U19: 47158
A20: Accrued Compensation | B20: 55015 | C20: 30499 | D20: 46770 | E20: 54507 | F20: 65459 | G20: 37551 | H20: 53717 | I20: 61426 | J20: 72463 | K20: 42673 | L20: 56195 | M20: 76835 | N20: 87392 | O20: 52638 | P20: 60357 | Q20: 81787 | R20: 92454 | S20: 55812 | T20: 72838 | U20: 102131
A21: Income Taxes Payable | B21: 23433 | C21: 9991 | D21: 31289 | E21: 23113 | F21: 30399 | G21: 21118 | H21: 15917 | I21: 17143 | J21: 13317 | K21: 55123 | L21: 12704 | M21: 17644 | N21: 14955 | O21: 75111 | P21: 10990 | Q21: 7641 | R21: 4006 | S21: 67837 | T21: 28121 | U21: 40023
A22: Total Current Liabilities | B22: =SUM(B16:B21) -> 749988 | C22: =SUM(C16:C21) -> 788861 | D22: =SUM(D16:D21) -> 887527 | E22: =SUM(E16:E21) -> 932240 | F22: =SUM(F16:F21) -> 965076 | G22: =SUM(G16:G21) -> 1044361 | H22: =SUM(H16:H21) -> 1093608 | I22: =SUM(I16:I21) -> 1121717 | ... U22: =SUM(U16:U21) -> 1590420
A23: Deferred Revenue - Non-Current | B23: 264436 | C23: 257730 | D23: 252056 | E23: 245621 | F23: 243249 | G23: 238241 | H23: 232170 | I23: 226294 | J23: 223800 | K23: 219764 | L23: 215039 | M23: 209136 | N23: 204251 | O23: 198759 | P23: 192354 | Q23: 186135 | R23: 179008 | S23: 173921 | T23: 169763 | U23: 164701
A24: Deferred Tax Liability | B24: 0 | C24: 0 | D24: 0 | E24: 0 | F24: 0 | G24: 0 | H24: 0 | I24: 0 | J24: 0 | K24: 0 | L24: 0 | M24: 0 | N24: 0 | O24: 0 | P24: 28896 | Q24: 28896 | R24: 0 | S24: 0 | T24: 0 | U24: 0
A25: Other Non-Current Liabilities | B25: 27432 | C25: 28338 | D25: 26462 | E25: 26550 | F25: 29508 | G25: 38185 | H25: 40056 | I25: 41034 | J25: 42286 | K25: 41727 | L25: 44255 | M25: 53251 | N25: 91838 | O25: 92690 | P25: 64068 | Q25: 64884 | R25: 110893 | S25: 109252 | T25: 110203 | U25: 110992
A26: Long-Term Debt | B26: 0 | C26: 0 | D26: 0 | E26: 0 | F26: 0 | G26: 0 | H26: 0 | I26: 0 | J26: 0 | K26: 0 | L26: 0 | M26: 0 | N26: 0 | O26: 0 | P26: 748740 | Q26: 748842 | R26: 373951 | S26: 199059 | T26: 0 | U26: 0
A27: Total Liabilities | B27: =B22+SUM(B23:B26) -> 1041856 | C27: =C22+SUM(C23:C26) -> 1074929 | D27: =D22+SUM(D23:D26) -> 1166045 | E27: =E22+SUM(E23:E26) -> 1204411 | F27: =F22+SUM(F23:F26) -> 1237833 | G27: =G22+SUM(G23:G26) -> 1320787 | H27: =H22+SUM(H23:H26) -> 1365834 | I27: =I22+SUM(I23:I26) -> 1389045 | ... U27: =U22+SUM(U23:U26) -> 1866113
A28: Common Stock | B28: 3193 | C28: 3196 | D28: 3198 | E28: 3199 | F28: 3200 | G28: 3203 | H28: 3205 | I28: 3206 | J28: 6418 | K28: 5587 | L28: 5591 | M28: 5592 | N28: 5613 | O28: 5624 | P28: 5627 | Q28: 5628 | R28: 5632 | S28: 5643 | T28: 5650 | U28: 5655
A29: Additional Paid-in Capital | B29: 4537982 | C29: 4562689 | D29: 4597333 | E29: 4626299 | F29: 4652620 | G29: 4673302 | H29: 4707569 | I29: 4736141 | J29: 4776804 | K29: 4829301 | L29: 4869791 | M29: 4893289 | N29: 4975115 | O29: 5034948 | P29: 5068291 | Q29: 5105957 | R29: 5144922 | S29: 5213731 | T29: 5285157 | U29: 5343915
A30: Retained Earnings (Accumulated Deficit) | B30: 6432074 | C30: 6747268 | D30: 7151030 | E30: 7488235 | F30: 7809549 | G30: 8103752 | H30: 8377112 | I30: 8699499 | J30: 9001173 | K30: 4706192 | L30: 5120063 | M30: 5572757 | N30: 5939736 | O30: 6381785 | P30: 6807154 | Q30: 7178073 | R30: 7448784 | S30: 7891777 | T30: 8380571 | U30: 8905026
A31: Accumulated Other Comprehensive Income (Loss) | B31: 3034 | C31: -24874 | D31: -16822 | E31: -43495 | F31: -69165 | G31: -72145 | H31: -152957 | I31: -224455 | J31: -159073 | K31: -147911 | L31: -155725 | M31: -198033 | N31: -125337 | O31: -157940 | P31: -182304 | Q31: -137842 | R31: -269487 | S31: -202946 | T31: -91308 | U31: -93382
A32: Treasury Stock | B32: -5815423 | C32: -5828842 | D32: -5829241 | E32: -5829241 | F32: -5829253 | G32: -5841440 | H32: -6125751 | I32: -6398631 | J32: -6600281 | K32: -1997809 | L32: -1998256 | M32: -2400456 | N32: -2566383 | O32: -2686628 | P32: -5832445 | Q32: -6372416 | R32: -6372133 | S32: -6388766 | T32: -6388766 | U32: -6416054
A33: Total Stockholders' Equity | B33: =SUM(B28:B32) -> 5160860 | C33: =SUM(C28:C32) -> 5459437 | D33: =SUM(D28:D32) -> 5905498 | E33: =SUM(E28:E32) -> 6244997 | F33: =SUM(F28:F32) -> 6566951 | G33: =SUM(G28:G32) -> 6866672 | H33: =SUM(H28:H32) -> 6809178 | I33: =SUM(I28:I32) -> 6815760 | ... U33: =SUM(U28:U32) -> 7745160
A34: Total Liabilities, Mezzanine & Stockholders' Equity | B34: =B27+B33 -> 6202716 | C34: =C27+C33 -> 6534366 | D34: =D27+D33 -> 7071543 | E34: =E27+E33 -> 7449408 | F34: =F27+F33 -> 7804784 | G34: =G27+G33 -> 8187459 | H34: =H27+H33 -> 8175012 | I34: =I27+I33 -> 8204805 | ... U34: =U27+U33 -> 9611273

Sheet YTD CF
B1: Q1 FY2020 | C1: Q2 FY2020 | D1: Q3 FY2020 | E1: Q1 FY2021 | F1: Q2 FY2021 | G1: Q3 FY2021 | H1: Q1 FY2022 | I1: Q2 FY2022 | J1: Q3 FY2022 | K1: Q1 FY2023 | L1: Q2 FY2023 | M1: Q3 FY2023 | N1: Q1 FY2024 | O1: Q2 FY2024 | P1: Q3 FY2024 | Q1: Q1 FY2025 | R1: Q2 FY2025 | S1: Q3 FY2025
A2: Net Income (Loss) | B2: 278835 | C2: 590204 | D2: 937858 | E2: 315194 | F2: 718956 | G2: 1056161 | H2: 294203 | I2: 567563 | J2: 889950 | K2: 397444 | L2: 811315 | M2: 1264009 | N2: 442049 | O2: 867418 | P2: 1238337 | Q2: 442993 | R2: 931787 | S2: 1456242
A3: Depreciation & Amortization | B3: 16546 | C3: 32057 | D3: 45879 | E3: 13777 | F3: 27489 | G3: 40716 | H3: 14599 | I3: 30432 | J3: 46040 | K3: 16808 | L3: 32384 | M3: 50364 | N3: 20475 | O3: 39913 | P3: 59822 | Q3: 24848 | R3: 52405 | S3: 82023
A4: Non-Cash Lease Expense | B4: 0 | C4: 0 | D4: 0 | E4: 0 | F4: 0 | G4: 0 | H4: 1481 | I4: 3222 | J4: 5180 | K4: 2160 | L4: 2828 | M4: 6471 | N4: 3185 | O4: 6599 | P4: 9801 | Q4: 4014 | R4: 6966 | S4: 10266
A5: Gain (Loss) on Disposal of PP&E | B5: -58 | C5: -179 | D5: -210 | E5: -88 | F5: -822 | G5: -984 | H5: -6 | I5: -69 | J5: -253 | K5: -385 | L5: -767 | M5: -686 | N5: -177 | O5: 1849 | P5: 2070 | Q5: 324 | R5: -641 | S5: -916
A6: Gain on Bang Transaction | B6: 0 | C6: 0 | D6: 0 | E6: 0 | F6: 0 | G6: 0 | H6: 0 | I6: 0 | J6: 0 | K6: 0 | L6: 0 | M6: -45382 | N6: 0 | O6: 0 | P6: 0 | Q6: 0 | R6: 0 | S6: 0
A7: Impairment of Intangibles | B7: 3000 | C7: 4000 | D7: 7000 | E7: 0 | F7: 0 | G7: 0 | H7: 0 | I7: 0 | J7: 0 | K7: 0 | L7: 2800 | M7: 2800 | N7: 0 | O7: 0 | P7: 0 | Q7: 0 | R7: 0 | S7: 0
A8: Impairment of Long-Lived Assets (PP&E) | B8: 0 | C8: 0 | D8: 0 | E8: 0 | F8: 0 | G8: 0 | H8: 0 | I8: 0 | J8: 0 | K8: 0 | L8: 0 | M8: 0 | N8: 0 | O8: 6067 | P8: 6067 | Q8: 2279 | R8: 2279 | S8: 2279
A9: Stock-Based Compensation | B9: 17098 | C9: 33034 | D9: 53042 | E9: 18362 | F9: 35691 | G9: 52391 | H9: 16332 | I9: 32609 | J9: 49167 | K9: 16051 | L9: 34603 | M9: 52465 | N9: 22472 | O9: 41262 | P9: 68793 | Q9: 20727 | R9: 53854 | S9: 86664
A10: (Benefit) Provision for Deferred Income Taxes | B10: 0 | C10: 0 | D10: 0 | E10: 0 | F10: 353 | G10: 353 | H10: 0 | I10: 21934 | J10: 29710 | K10: 0 | L10: 0 | M10: 0 | N10: 9 | O10: -13294 | P10: -10242 | Q10: 135 | R10: 646 | S10: 455
A11: Accounts Receivable | B11: -147660 | C11: -231782 | D11: -201677 | E11: -147544 | F11: -239700 | G11: -199709 | H11: -134433 | I11: -289236 | J11: -202447 | K11: -167512 | L11: -317808 | M11: -218804 | N11: -195081 | O11: -197227 | P11: -106404 | Q11: -109557 | R11: -222239 | S11: -299139
A12: Distributor Receivables | B12: 176 | C12: 188 | D12: 341 | E12: 92 | F12: 160 | G12: 228 | H12: 0 | I12: 0 | J12: 0 | K12: 0 | L12: 0 | M12: 0 | N12: 0 | O12: 0 | P12: 0 | Q12: 0 | R12: 0 | S12: 0
A13: Inventories | B13: 1037 | C13: 14181 | D13: 39490 | E13: -39546 | F13: -52541 | G13: -149414 | H13: -208673 | I13: -299076 | J13: -297140 | K13: 35495 | L13: 93077 | M13: 69796 | N13: 22708 | O13: 123484 | P13: 197107 | Q13: 19594 | R13: 104633 | S13: 58387
... A23: Deferred Revenue | B23: -4273 | C23: -10383 | D23: -15236 | E23: -5250 | F23: -10922 | G23: -17784 | H23: -5915 | I23: -9101 | J23: -16060 | K23: -5046 | L23: -12361 | M23: -19320 | N23: -3036 | O23: -7731 | P23: -12652 | Q23: -4339 | R23: -8598 | S23: -15907
A24: Cash Flow from Operations | B24: =SUM(B2:B23) -> 191132 | C24: =SUM(C2:C23) -> 440458 | D24: =SUM(D2:D23) -> 949236 | E24: =SUM(E2:E23) -> 175473 | F24: =SUM(F2:F23) -> 586586 | G24: =SUM(G2:G23) -> 927982 | H24: =SUM(H2:H23) -> -351 | I24: =SUM(I2:I23) -> 130663 | ... S24: =SUM(S2:S23) -> 1718762
A25: Net Change in Long-Term Investments | B25: 298837 | C25: 293643 | D25: -53418 | E25: -114819 | F25: -134502 | G25: -326795 | H25: 62883 | I25: 445440 | J25: 430033 | K25: 3750 | L25: -53323 | M25: 140805 | N25: 39897 | O25: 1035794 | P25: 1035794 | Q25: 0 | R25: -283097 | S25: -597703
A26: Acquisition of CANarchy | B26: 0 | C26: 0 | D26: 0 | E26: 0 | F26: 0 | G26: 0 | H26: -330356 | I26: -329472 | J26: -329472 | K26: 0 | L26: 0 | M26: 0 | N26: 0 | O26: 0 | P26: 0 | Q26: 0 | R26: 0 | S26: 0
A27: Acquisition of Monster Brewing | B27: 0 | C27: 0 | D27: 0 | E27: 0 | F27: 0 | G27: 0 | H27: 0 | I27: 0 | J27: 0 | K27: 0 | L27: 0 | M27: 0 | N27: 0 | O27: 0 | P27: 0 | Q27: 0 | R27: 0 | S27: 0
A28: Acquisition of Bang Energy | B28: 0 | C28: 0 | D28: 0 | E28: 0 | F28: 0 | G28: 0 | H28: 0 | I28: 0 | J28: 0 | K28: 0 | L28: 0 | M28: -363385 | N28: 0 | O28: 0 | P28: 0 | Q28: 0 | R28: 0 | S28: 0
A29: Purchase of PP&E | B29: -11119 | C29: -29116 | D29: -42062 | E29: -8400 | F29: -15522 | G29: -28131 | H29: -21511 | I29: -99446 | J29: -136158 | K29: -40100 | L29: -82425 | M29: -110224 | N29: -66044 | O29: -125812 | P29: -172795 | Q29: -29056 | R29: -60460 | S29: -104101
A30: Proceeds from Sale of Assets | B30: 217 | C30: 590 | D30: 880 | E30: 231 | F30: 1024 | G30: 1246 | H30: 14 | I30: 372 | J30: 603 | K30: 564 | L30: 1035 | M30: 1753 | N30: 422 | O30: 1052 | P30: 2095 | Q30: 1147 | R30: 2334 | S30: 2744
A31: Additions to Intangibles | B31: -6811 | C31: -13085 | D31: -19686 | E31: -7239 | F31: -9926 | G31: -5211 | H31: -8419 | I31: -9894 | J31: -3578 | K31: -3952 | L31: -5926 | M31: -9110 | N31: -8612 | O31: -6364 | P31: -21473 | Q31: -5343 | R31: -15399 | S31: -19681
A32: Other Investing Activities | B32: -1148 | C32: -1338 | D32: -26228 | E32: -18856 | F32: -21236 | G32: -22809 | H32: -6241 | I32: -12738 | J32: -19171 | K32: -13028 | L32: -17570 | M32: -19862 | N32: -985 | O32: -1366 | P32: -603 | Q32: 2397 | R32: -1107 | S32: -507
A33: Cash Flow from Investing | B33: =SUM(B25:B32) -> 279976 | C33: =SUM(C25:C32) -> 250694 | D33: =SUM(D25:D32) -> -140514 | E33: =SUM(E25:E32) -> -149083 | F33: =SUM(F25:F32) -> -180162 | G33: =SUM(G25:G32) -> -381700 | H33: =SUM(H25:H32) -> -303630 | I33: =SUM(I25:I32) -> -5738 | ... S33: =SUM(S25:S32) -> -719248
A34: Repayments of Short-Term Debt | B34: 0 | C34: 0 | D34: 0 | E34: 0 | F34: 0 | G34: 0 | H34: 0 | I34: 0 | J34: 0 | K34: 0 | L34: 0 | M34: 0 | N34: 0 | O34: -5269 | P34: -6717 | Q34: 0 | R34: 0 | S34: 0
A35: Net Change in Other Short-Term Debt | B35: -733 | C35: -1680 | D35: -2500 | E35: 957 | F35: 3624 | G35: -1814 | H35: 3454 | I35: 4924 | J35: -719 | K35: -7271 | L35: -6661 | M35: -11273 | N35: -2896 | O35: 0 | P35: 0 | Q35: -2045 | R35: -5023 | S35: -8043
A36: Proceeds from Issuance of Long-Term Debt | B36: 0 | C36: 0 | D36: 0 | E36: 0 | F36: 0 | G36: 0 | H36: 0 | I36: 0 | J36: 0 | K36: 0 | L36: 0 | M36: 0 | N36: 0 | O36: 750000 | P36: 750000 | Q36: 0 | R36: 0 | S36: 0
A37: Debt Issuance Fees | B37: 0 | C37: 0 | D37: 0 | E37: 0 | F37: 0 | G37: 0 | H37: 0 | I37: 0 | J37: 0 | K37: 0 | L37: 0 | M37: 0 | N37: 0 | O37: -2776 | P37: -2904 | Q37: 0 | R37: 0 | S37: 0
A38: Repayments of Long-Term Debt | B38: 0 | C38: 0 | D38: 0 | E38: 0 | F38: 0 | G38: 0 | H38: 0 | I38: 0 | J38: 0 | K38: 0 | L38: 0 | M38: 0 | N38: 0 | O38: 0 | P38: 0 | Q38: -175000 | R38: -375000 | S38: -375000
A39: Proceeds from Issuance of Common Stock | B39: 13975 | C39: 43842 | D39: 65540 | E39: 6761 | F39: 24486 | G39: 37160 | H39: 4510 | I39: 22622 | J39: 34759 | K39: 36348 | L39: 59666 | M39: 65560 | N39: 38392 | O39: 52093 | P39: 62101 | Q39: 48093 | R39: 87684 | S39: 114363
A40: Share Repurchases | B40: -559210 | C40: -595770 | D40: -595918 | E40: -13419 | F40: -13818 | G40: -13818 | H40: -12187 | I40: -296499 | J40: -493315 | K40: -35126 | L40: -90825 | M40: -488080 | N40: -120245 | O40: -3234523 | P40: -3770184 | Q40: -16633 | R40: -16633 | S40: -43921
A41: Cash Flow from Financing | B41: =SUM(B34:B40) -> -545968 | C41: =SUM(C34:C40) -> -553608 | D41: =SUM(D34:D40) -> -532878 | E41: =SUM(E34:E40) -> -5701 | F41: =SUM(F34:F40) -> 14292 | G41: =SUM(G34:G40) -> 21528 | H41: =SUM(H34:H40) -> -4223 | I41: =SUM(I34:I40) -> -268953 | ... S41: =SUM(S34:S40) -> -312601
A42: FX Effect on Cash | B42: -21261 | C42: -14175 | D42: 929 | E42: -22223 | F42: -16890 | G42: -35552 | H42: -3472 | I42: -50395 | J42: -95582 | K42: -141 | L42: -4500 | M42: -22902 | N42: -13222 | O42: -44203 | P42: -14482 | Q42: 38972 | R42: 86725 | S42: 72739
A43: Net Change in Cash | B43: =B24+B33+B41+B42 -> -96121 | C43: =C24+C33+C41+C42 -> 123369 | D43: =D24+D33+D41+D42 -> 276773 | E43: =E24+E33+E41+E42 -> -1534 | F43: =F24+F33+F41+F42 -> 403826 | G43: =G24+G33+G41+G42 -> 532258 | H43: =H24+H33+H41+H42 -> -311676 | I43: =I24+I33+I41+I42 -> -194423 | ... S43: =S24+S33+S41+S42 -> 759652

Sheet QTR P&L
B1: Q1 FY2020 | C1: Q2 FY2020 | D1: Q3 FY2020 | E1: Q4 FY2020 | F1: Q1 FY2021 | G1: Q2 FY2021 | H1: Q3 FY2021 | I1: Q4 FY2021 | J1: Q1 FY2022 | K1: Q2 FY2022 | L1: Q3 FY2022 | M1: Q4 FY2022 | N1: Q1 FY2023 | O1: Q2 FY2023 | P1: Q3 FY2023 | Q1: Q4 FY2023 | R1: Q1 FY2024 | S1: Q2 FY2024 | T1: Q3 FY2024 | U1: Q4 FY2024 | V1: Q1 FY2025 | W1: Q2 FY2025 | X1: Q3 FY2025 | Y1: Q4 FY2025 | Z1: Q1 FY2026E | AA1: Q2 FY2026E | AB1: Q3 FY2026E | AC1: Q4 FY2026E | AD1: Q1 FY2027E | AE1: Q2 FY2027E | AF1: Q3 FY2027E | AG1: Q4 FY2027E | AH1: Q1 FY2028E | AI1: Q2 FY2028E | AJ1: Q3 FY2028E | AK1: Q4 FY2028E | AL1: Q1 FY2029E | AM1: Q2 FY2029E | AN1: Q3 FY2029E | AO1: Q4 FY2029E | AP1: Q1 FY2030E | AQ1: Q2 FY2030E | AR1: Q3 FY2030E | AS1: Q4 FY2030E
A2: Net Sales / Revenue | B2: ='YTD P&L'!B2 -> 1062097 | C2: ='YTD P&L'!C2-'YTD P&L'!B2 -> 1093896 | D2: ='YTD P&L'!D2-'YTD P&L'!C2 -> 1246362 | E2: ='ANNL P&L'!C2-'YTD P&L'!D2 -> 1196283 | F2: ='YTD P&L'!E2 -> 1243816 | G2: ='YTD P&L'!F2-'YTD P&L'!E2 -> 1461935 | H2: ='YTD P&L'!G2-'YTD P&L'!F2 -> 1410557 | I2: ='ANNL P&L'!D2-'YTD P&L'!G2 -> 1425044 | J2: ='YTD P&L'!H2 -> 1518574 | K2: ='YTD P&L'!I2-'YTD P&L'!H2 -> 1655259 | L2: ='YTD P&L'!J2-'YTD P&L'!I2 -> 1624286 | M2: ='ANNL P&L'!E2-'YTD P&L'!J2 -> 1512931 | N2: ='YTD P&L'!K2 -> 1698930 | O2: ='YTD P&L'!L2-'YTD P&L'!K2 -> 1854961 | P2: ='YTD P&L'!M2-'YTD P&L'!L2 -> 1856028 | Q2: ='ANNL P&L'!F2-'YTD P&L'!M2 -> 1730108 | R2: ='YTD P&L'!N2 -> 1899098 | S2: ='YTD P&L'!O2-'YTD P&L'!N2 -> 1900597 | T2: ='YTD P&L'!P2-'YTD P&L'!O2 -> 1880973 | U2: ='ANNL P&L'!G2-'YTD P&L'!P2 -> 1812041 | V2: ='YTD P&L'!Q2 -> 1854558 | W2: ='YTD P&L'!R2-'YTD P&L'!Q2 -> 2111592 | X2: ='YTD P&L'!S2-'YTD P&L'!R2 -> 2197140 | Y2: ='ANNL P&L'!H2-'YTD P&L'!S2 -> 2131053 | Z2: =IF('IS DRIVERS'!$B2="QoQ",'QTR P&L'!Y2,'QTR P&L'!V2)*(1+'IS DRIVERS'!AA2) -> 2181055.2 | AA2: =IF('IS DRIVERS'!$B2="QoQ",'QTR P&L'!Z2,'QTR P&L'!W2)*(1+'IS DRIVERS'!AB2) -> 2483340.3 | AB2: =IF('IS DRIVERS'!$B2="QoQ",'QTR P&L'!AA2,'QTR P&L'!X2)*(1+'IS DRIVERS'!AC2) -> 2583949.1 | AC2: =IF('IS DRIVERS'!$B2="QoQ",'QTR P&L'!AB2,'QTR P&L'!Y2)*(1+'IS DRIVERS'!AD2) -> 2506227.4 | AD2: =IF('IS DRIVERS'!$B2="QoQ",'QTR P&L'!AC2,'QTR P&L'!Z2)*(1+'IS DRIVERS'!AE2) -> 2565032.6 | AE2: =IF('IS DRIVERS'!$B2="QoQ",'QTR P&L'!AD2,'QTR P&L'!AA2)*(1+'IS DRIVERS'!AF2) -> 2920535.4 | AF2: =IF('IS DRIVERS'!$B2="QoQ",'QTR P&L'!AE2,'QTR P&L'!AB2)*(1+'IS DRIVERS'!AG2) -> 3038856.5 | AG2: =IF('IS DRIVERS'!$B2="QoQ",'QTR P&L'!AF2,'QTR P&L'!AC2)*(1+'IS DRIVERS'!AH2) -> 2947451.8 | ... AS2: =IF('IS DRIVERS'!$B2="QoQ",'QTR P&L'!AR2,'QTR P&L'!AO2)*(1+'IS DRIVERS'!AT2) -> 4794302.2
A3: COGS | B3: ='YTD P&L'!B3 -> -424901 | C3: ='YTD P&L'!C3-'YTD P&L'!B3 -> -434428 | D3: ='YTD P&L'!D3-'YTD P&L'!C3 -> -509831 | E3: ='ANNL P&L'!C3-'YTD P&L'!D3 -> -505598 | F3: ='YTD P&L'!E3 -> -528881 | G3: ='YTD P&L'!F3-'YTD P&L'!E3 -> -625095 | H3: ='YTD P&L'!G3-'YTD P&L'!F3 -> -621399 | I3: ='ANNL P&L'!D3-'YTD P&L'!G3 -> -657464 | J3: ='YTD P&L'!H3 -> -741907 | K3: ='YTD P&L'!I3-'YTD P&L'!H3 -> -875399 | L3: ='YTD P&L'!J3-'YTD P&L'!I3 -> -790561 | M3: ='ANNL P&L'!E3-'YTD P&L'!J3 -> -728616 | N3: ='YTD P&L'!K3 -> -801081 | O3: ='YTD P&L'!L3-'YTD P&L'!K3 -> -880739 | P3: ='YTD P&L'!M3-'YTD P&L'!L3 -> -872266 | Q3: ='ANNL P&L'!F3-'YTD P&L'!M3 -> -791735 | R3: ='YTD P&L'!N3 -> -871969 | S3: ='YTD P&L'!O3-'YTD P&L'!N3 -> -881092 | T3: ='YTD P&L'!P3-'YTD P&L'!O3 -> -881174 | U3: ='ANNL P&L'!G3-'YTD P&L'!P3 -> -809596 | V3: ='YTD P&L'!Q3 -> -806596 | W3: ='YTD P&L'!R3-'YTD P&L'!Q3 -> -935179 | X3: ='YTD P&L'!S3-'YTD P&L'!R3 -> -972653 | Y3: ='ANNL P&L'!H3-'YTD P&L'!S3 -> -947720 | Z3: ='QTR P&L'!Z2*'IS DRIVERS'!AA3 -> -969956.92 | AA3: ='QTR P&L'!AA2*'IS DRIVERS'!AB3 -> -1104388.9 | AB3: ='QTR P&L'!AB2*'IS DRIVERS'!AC3 -> -1149131.6 | AC3: ='QTR P&L'!AC2*'IS DRIVERS'!AD3 -> -1114567.2 | AD3: ='QTR P&L'!AD2*'IS DRIVERS'!AE3 -> -1140719 | AE3: ='QTR P&L'!AE2*'IS DRIVERS'!AF3 -> -1298817.9 | AF3: ='QTR P&L'!AF2*'IS DRIVERS'!AG3 -> -1351437.6 | AG3: ='QTR P&L'!AG2*'IS DRIVERS'!AH3 -> -1310788.2 | ... AS3: ='QTR P&L'!AS2*'IS DRIVERS'!AT3 -> -2132117.8
A4: Gross Profit (Loss) | B4: ='YTD P&L'!B4 -> 637196 | C4: ='YTD P&L'!C4-'YTD P&L'!B4 -> 659468 | D4: ='YTD P&L'!D4-'YTD P&L'!C4 -> 736531 | E4: ='ANNL P&L'!C4-'YTD P&L'!D4 -> 690685 | F4: ='YTD P&L'!E4 -> 714935 | G4: ='YTD P&L'!F4-'YTD P&L'!E4 -> 836840 | H4: ='YTD P&L'!G4-'YTD P&L'!F4 -> 789158 | I4: ='ANNL P&L'!D4-'YTD P&L'!G4 -> 767580 | J4: ='YTD P&L'!H4 -> 776667 | K4: ='YTD P&L'!I4-'YTD P&L'!H4 -> 779860 | L4: ='YTD P&L'!J4-'YTD P&L'!I4 -> 833725 | M4: ='ANNL P&L'!E4-'YTD P&L'!J4 -> 784315 | N4: ='YTD P&L'!K4 -> 897849 | O4: ='YTD P&L'!L4-'YTD P&L'!K4 -> 974222 | P4: ='YTD P&L'!M4-'YTD P&L'!L4 -> 983762 | Q4: ='ANNL P&L'!F4-'YTD P&L'!M4 -> 938373 | R4: ='YTD P&L'!N4 -> 1027129 | S4: ='YTD P&L'!O4-'YTD P&L'!N4 -> 1019505 | T4: ='YTD P&L'!P4-'YTD P&L'!O4 -> 999799 | U4: ='ANNL P&L'!G4-'YTD P&L'!P4 -> 1002445 | V4: ='YTD P&L'!Q4 -> 1047962 | W4: ='YTD P&L'!R4-'YTD P&L'!Q4 -> 1176413 | X4: ='YTD P&L'!S4-'YTD P&L'!R4 -> 1224487 | Y4: ='ANNL P&L'!H4-'YTD P&L'!S4 -> 1183333 | Z4: =Z2+Z3 -> 1211098.2 | AA4: =AA2+AA3 -> 1378951.4 | AB4: =AB2+AB3 -> 1434817.6 | AC4: =AC2+AC3 -> 1391660.2 | AD4: =AD2+AD3 -> 1424313.6 | AE4: =AE2+AE3 -> 1621717.5 | AF4: =AF2+AF3 -> 1687418.9 | AG4: =AG2+AG3 -> 1636663.7 | ... AS4: =AS2+AS3 -> 2662184.4
A5: Operating Expenses | B5: ='YTD P&L'!B5 -> -272208 | C5: ='YTD P&L'!C5-'YTD P&L'!B5 -> -252204 | D5: ='YTD P&L'!D5-'YTD P&L'!C5 -> -277931 | E5: ='ANNL P&L'!C5-'YTD P&L'!D5 -> -288384 | F5: ='YTD P&L'!E5 -> -300789 | G5: ='YTD P&L'!F5-'YTD P&L'!E5 -> -310863 | H5: ='YTD P&L'!G5-'YTD P&L'!F5 -> -344694 | I5: ='ANNL P&L'!D5-'YTD P&L'!G5 -> -354700 | J5: ='YTD P&L'!H5 -> -377178 | K5: ='YTD P&L'!I5-'YTD P&L'!H5 -> -406910 | L5: ='YTD P&L'!J5-'YTD P&L'!I5 -> -415795 | M5: ='ANNL P&L'!E5-'YTD P&L'!J5 -> -389963 | N5: ='YTD P&L'!K5 -> -412785 | O5: ='YTD P&L'!L5-'YTD P&L'!K5 -> -450416 | P5: ='YTD P&L'!M5-'YTD P&L'!L5 -> -473236 | Q5: ='ANNL P&L'!F5-'YTD P&L'!M5 -> -504414 | R5: ='YTD P&L'!N5 -> -485138 | S5: ='YTD P&L'!O5-'YTD P&L'!N5 -> -492342 | T5: ='YTD P&L'!P5-'YTD P&L'!O5 -> -519883 | U5: ='ANNL P&L'!G5-'YTD P&L'!P5 -> -621221 | V5: ='YTD P&L'!Q5 -> -478217 | W5: ='YTD P&L'!R5-'YTD P&L'!Q5 -> -544791 | X5: ='YTD P&L'!S5-'YTD P&L'!R5 -> -549134 | Y5: ='ANNL P&L'!H5-'YTD P&L'!S5 -> -640699 | Z5: ='QTR P&L'!Z2*'IS DRIVERS'!AA4 -> -655732.1 | AA5: ='QTR P&L'!AA2*'IS DRIVERS'!AB4 -> -746613.84 | AB5: ='QTR P&L'!AB2*'IS DRIVERS'!AC4 -> -776861.78 | AC5: ='QTR P&L'!AC2*'IS DRIVERS'!AD4 -> -753494.83 | AD5: ='QTR P&L'!AD2*'IS DRIVERS'!AE4 -> -771174.53 | AE5: ='QTR P&L'!AE2*'IS DRIVERS'!AF4 -> -878056.1 | AF5: ='QTR P&L'!AF2*'IS DRIVERS'!AG4 -> -913629.23 | AG5: ='QTR P&L'!AG2*'IS DRIVERS'!AH4 -> -886148.5 | ... AS5: ='QTR P&L'!AS2*'IS DRIVERS'!AT4 -> -1441402.3
A6: Income (Loss) from Operations | B6: ='YTD P&L'!B6 -> 364988 | C6: ='YTD P&L'!C6-'YTD P&L'!B6 -> 407264 | D6: ='YTD P&L'!D6-'YTD P&L'!C6 -> 458600 | E6: ='ANNL P&L'!C6-'YTD P&L'!D6 -> 402301 | F6: ='YTD P&L'!E6 -> 414146 | G6: ='YTD P&L'!F6-'YTD P&L'!E6 -> 525977 | H6: ='YTD P&L'!G6-'YTD P&L'!F6 -> 444464 | I6: ='ANNL P&L'!D6-'YTD P&L'!G6 -> 412880 | J6: ='YTD P&L'!H6 -> 399489 | K6: ='YTD P&L'!I6-'YTD P&L'!H6 -> 372950 | L6: ='YTD P&L'!J6-'YTD P&L'!I6 -> 417930 | M6: ='ANNL P&L'!E6-'YTD P&L'!J6 -> 394352 | N6: ='YTD P&L'!K6 -> 485064 | O6: ='YTD P&L'!L6-'YTD P&L'!K6 -> 523806 | P6: ='YTD P&L'!M6-'YTD P&L'!L6 -> 510526 | Q6: ='ANNL P&L'!F6-'YTD P&L'!M6 -> 433959 | R6: ='YTD P&L'!N6 -> 541991 | S6: ='YTD P&L'!O6-'YTD P&L'!N6 -> 527163 | T6: ='YTD P&L'!P6-'YTD P&L'!O6 -> 479916 | U6: ='ANNL P&L'!G6-'YTD P&L'!P6 -> 381224 | V6: ='YTD P&L'!Q6 -> 569745 | W6: ='YTD P&L'!R6-'YTD P&L'!Q6 -> 631622 | X6: ='YTD P&L'!S6-'YTD P&L'!R6 -> 675353 | Y6: ='ANNL P&L'!H6-'YTD P&L'!S6 -> 542634 | Z6: =Z4+Z5 -> 555366.15 | AA6: =AA4+AA5 -> 632337.58 | AB6: =AB4+AB5 -> 657955.79 | AC6: =AC4+AC5 -> 638165.37 | AD6: =AD4+AD5 -> 653139.02 | AE6: =AE4+AE5 -> 743661.37 | AF6: =AF4+AF5 -> 773789.7 | AG6: =AG4+AG5 -> 750515.15 | ... AS6: =AS4+AS5 -> 1220782.1
A7: Other Income (Expense) | B7: ='YTD P&L'!B7 -> 0 | C7: ='YTD P&L'!C7-'YTD P&L'!B7 -> 0 | D7: ='YTD P&L'!D7-'YTD P&L'!C7 -> 0 | E7: ='ANNL P&L'!C8-'YTD P&L'!D7 -> -6996 | F7: ='YTD P&L'!E7 -> 0 | G7: ='YTD P&L'!F7-'YTD P&L'!E7 -> 0 | H7: ='YTD P&L'!G7-'YTD P&L'!F7 -> 0 | I7: ='ANNL P&L'!D8-'YTD P&L'!G7 -> 3952 | J7: ='YTD P&L'!H7 -> 0 | K7: ='YTD P&L'!I7-'YTD P&L'!H7 -> 0 | L7: ='YTD P&L'!J7-'YTD P&L'!I7 -> 0 | M7: ='ANNL P&L'!E8-'YTD P&L'!J7 -> -12757 | N7: ='YTD P&L'!K7 -> 0 | O7: ='YTD P&L'!L7-'YTD P&L'!K7 -> 0 | P7: ='YTD P&L'!M7-'YTD P&L'!L7 -> 0 | Q7: ='ANNL P&L'!F8-'YTD P&L'!M7 -> 0 | R7: ='YTD P&L'!N7 -> 35754 | S7: ='YTD P&L'!O7-'YTD P&L'!N7 -> 24377 | T7: ='YTD P&L'!P7-'YTD P&L'!O7 -> -60131 | U7: ='ANNL P&L'!G8-'YTD P&L'!P7 -> 0 | V7: ='YTD P&L'!Q7 -> 8272 | W7: ='YTD P&L'!R7-'YTD P&L'!Q7 -> 15065 | X7: ='YTD P&L'!S7-'YTD P&L'!R7 -> -23337 | Y7: ='ANNL P&L'!H8-'YTD P&L'!S7 -> 63175 | Z7: ='IS DRIVERS'!AA5 -> 63175 | AA7: ='IS DRIVERS'!AB5 -> 63175 | AB7: ='IS DRIVERS'!AC5 -> 63175 | AC7: ='IS DRIVERS'!AD5 -> 63175 | AD7: ='IS DRIVERS'!AE5 -> 63175 | AE7: ='IS DRIVERS'!AF5 -> 63175 | AF7: ='IS DRIVERS'!AG5 -> 63175 | AG7: ='IS DRIVERS'!AH5 -> 63175 | ... AS7: ='IS DRIVERS'!AT5 -> 63175
A8: Interest Income (Expense) | B8: ='YTD P&L'!B8 -> 872 | C8: ='YTD P&L'!C8-'YTD P&L'!B8 -> -1795 | D8: ='YTD P&L'!D8-'YTD P&L'!C8 -> -4568 | E8: ='ANNL P&L'!C7-'YTD P&L'!D8 -> 5491 | F8: ='YTD P&L'!E8 -> -759 | G8: ='YTD P&L'!F8-'YTD P&L'!E8 -> 870 | H8: ='YTD P&L'!G8-'YTD P&L'!F8 -> -2290 | I8: ='ANNL P&L'!D7-'YTD P&L'!G8 -> 2179 | J8: ='YTD P&L'!H8 -> -7300 | K8: ='YTD P&L'!I8-'YTD P&L'!H8 -> -6780 | L8: ='YTD P&L'!J8-'YTD P&L'!I8 -> 2148 | M8: ='ANNL P&L'!E7-'YTD P&L'!J8 -> 11932 | N8: ='YTD P&L'!K8 -> 12496 | O8: ='YTD P&L'!L8-'YTD P&L'!K8 -> 15157 | P8: ='YTD P&L'!M8-'YTD P&L'!L8 -> 71357 | Q8: ='ANNL P&L'!F7-'YTD P&L'!M8 -> 16117 | R8: ='YTD P&L'!N8 -> 0 | S8: ='YTD P&L'!O8-'YTD P&L'!N8 -> 0 | T8: ='YTD P&L'!P8-'YTD P&L'!O8 -> 54311 | U8: ='ANNL P&L'!G7-'YTD P&L'!P8 -> 4854 | V8: ='YTD P&L'!Q8 -> 0 | W8: ='YTD P&L'!R8-'YTD P&L'!Q8 -> 0 | X8: ='YTD P&L'!S8-'YTD P&L'!R8 -> 37522 | Y8: ='ANNL P&L'!H7-'YTD P&L'!S8 -> -37522 | Z8: ='IS DRIVERS'!AA6 -> -37522 | AA8: ='IS DRIVERS'!AB6 -> -37522 | AB8: ='IS DRIVERS'!AC6 -> -37522 | AC8: ='IS DRIVERS'!AD6 -> -37522 | AD8: ='IS DRIVERS'!AE6 -> -37522 | AE8: ='IS DRIVERS'!AF6 -> -37522 | AF8: ='IS DRIVERS'!AG6 -> -37522 | AG8: ='IS DRIVERS'!AH6 -> -37522 | ... AS8: ='IS DRIVERS'!AT6 -> -37522
A9: Pre-Tax Income (Loss) | B9: ='YTD P&L'!B9 -> 365860 | C9: ='YTD P&L'!C9-'YTD P&L'!B9 -> 405469 | D9: ='YTD P&L'!D9-'YTD P&L'!C9 -> 454032 | E9: ='ANNL P&L'!C9-'YTD P&L'!D9 -> 400796 | F9: ='YTD P&L'!E9 -> 413387 | G9: ='YTD P&L'!F9-'YTD P&L'!E9 -> 526847 | H9: ='YTD P&L'!G9-'YTD P&L'!F9 -> 442174 | I9: ='ANNL P&L'!D9-'YTD P&L'!G9 -> 419011 | J9: ='YTD P&L'!H9 -> 392189 | K9: ='YTD P&L'!I9-'YTD P&L'!H9 -> 366170 | L9: ='YTD P&L'!J9-'YTD P&L'!I9 -> 420078 | M9: ='ANNL P&L'!E9-'YTD P&L'!J9 -> 393527 | N9: ='YTD P&L'!K9 -> 497560 | O9: ='YTD P&L'!L9-'YTD P&L'!K9 -> 538963 | P9: ='YTD P&L'!M9-'YTD P&L'!L9 -> 581883 | Q9: ='ANNL P&L'!F9-'YTD P&L'!M9 -> 450076 | R9: ='YTD P&L'!N9 -> 577745 | S9: ='YTD P&L'!O9-'YTD P&L'!N9 -> 551540 | T9: ='YTD P&L'!P9-'YTD P&L'!O9 -> 474096 | U9: ='ANNL P&L'!G9-'YTD P&L'!P9 -> 386078 | V9: ='YTD P&L'!Q9 -> 578017 | W9: ='YTD P&L'!R9-'YTD P&L'!Q9 -> 646687 | X9: ='YTD P&L'!S9-'YTD P&L'!R9 -> 689538 | Y9: ='ANNL P&L'!H9-'YTD P&L'!S9 -> 568287 | Z9: =Z6+SUM(Z7:Z8) -> 581019.15 | AA9: =AA6+SUM(AA7:AA8) -> 657990.58 | AB9: =AB6+SUM(AB7:AB8) -> 683608.79 | AC9: =AC6+SUM(AC7:AC8) -> 663818.37 | AD9: =AD6+SUM(AD7:AD8) -> 678792.02 | AE9: =AE6+SUM(AE7:AE8) -> 769314.37 | AF9: =AF6+SUM(AF7:AF8) -> 799442.7 | AG9: =AG6+SUM(AG7:AG8) -> 776168.15 | ... AS9: =AS6+SUM(AS7:AS8) -> 1246435.1
A10: Income Tax (Expense) Benefit | B10: ='YTD P&L'!B10 -> -87025 | C10: ='YTD P&L'!C10-'YTD P&L'!B10 -> -94100 | D10: ='YTD P&L'!D10-'YTD P&L'!C10 -> -106378 | E10: ='ANNL P&L'!C10-'YTD P&L'!D10 -> 70940 | F10: ='YTD P&L'!E10 -> -98193 | G10: ='YTD P&L'!F10-'YTD P&L'!E10 -> -123085 | H10: ='YTD P&L'!G10-'YTD P&L'!F10 -> -104969 | I10: ='ANNL P&L'!D10-'YTD P&L'!G10 -> -97697 | J10: ='YTD P&L'!H10 -> -97986 | K10: ='YTD P&L'!I10-'YTD P&L'!H10 -> -92810 | L10: ='YTD P&L'!J10-'YTD P&L'!I10 -> -97691 | M10: ='ANNL P&L'!E10-'YTD P&L'!J10 -> -91853 | N10: ='YTD P&L'!K10 -> -100116 | O10: ='YTD P&L'!L10-'YTD P&L'!K10 -> -125092 | P10: ='YTD P&L'!M10-'YTD P&L'!L10 -> -129189 | Q10: ='ANNL P&L'!F10-'YTD P&L'!M10 -> -83097 | R10: ='YTD P&L'!N10 -> -135696 | S10: ='YTD P&L'!O10-'YTD P&L'!N10 -> -126171 | T10: ='YTD P&L'!P10-'YTD P&L'!O10 -> -103177 | U10: ='ANNL P&L'!G10-'YTD P&L'!P10 -> -115367 | V10: ='YTD P&L'!Q10 -> -135024 | W10: ='YTD P&L'!R10-'YTD P&L'!Q10 -> -157893 | X10: ='YTD P&L'!S10-'YTD P&L'!R10 -> -165083 | Y10: ='ANNL P&L'!H10-'YTD P&L'!S10 -> -119097 | Z10: ='QTR P&L'!Z9*'IS DRIVERS'!AA7 -> -121765.3 | AA10: ='QTR P&L'!AA9*'IS DRIVERS'!AB7 -> -137896.35 | AB10: ='QTR P&L'!AB9*'IS DRIVERS'!AC7 -> -143265.21 | AC10: ='QTR P&L'!AC9*'IS DRIVERS'!AD7 -> -139117.69 | AD10: ='QTR P&L'!AD9*'IS DRIVERS'!AE7 -> -142255.75 | AE10: ='QTR P&L'!AE9*'IS DRIVERS'!AF7 -> -161226.69 | AF10: ='QTR P&L'!AF9*'IS DRIVERS'!AG7 -> -167540.74 | AG10: ='QTR P&L'!AG9*'IS DRIVERS'!AH7 -> -162663.05 | ... AS10: ='QTR P&L'!AS9*'IS DRIVERS'!AT7 -> -261217.8
A11: Net Income (Loss) | B11: ='YTD P&L'!B11 -> 278835 | C11: ='YTD P&L'!C11-'YTD P&L'!B11 -> 311369 | D11: ='YTD P&L'!D11-'YTD P&L'!C11 -> 347654 | E11: ='ANNL P&L'!C11-'YTD P&L'!D11 -> 471736 | F11: ='YTD P&L'!E11 -> 315194 | G11: ='YTD P&L'!F11-'YTD P&L'!E11 -> 403762 | H11: ='YTD P&L'!G11-'YTD P&L'!F11 -> 337205 | I11: ='ANNL P&L'!D11-'YTD P&L'!G11 -> 321314 | J11: ='YTD P&L'!H11 -> 294203 | K11: ='YTD P&L'!I11-'YTD P&L'!H11 -> 273360 | L11: ='YTD P&L'!J11-'YTD P&L'!I11 -> 322387 | M11: ='ANNL P&L'!E11-'YTD P&L'!J11 -> 301674 | N11: ='YTD P&L'!K11 -> 397444 | O11: ='YTD P&L'!L11-'YTD P&L'!K11 -> 413871 | P11: ='YTD P&L'!M11-'YTD P&L'!L11 -> 452694 | Q11: ='ANNL P&L'!F11-'YTD P&L'!M11 -> 366979 | R11: ='YTD P&L'!N11 -> 442049 | S11: ='YTD P&L'!O11-'YTD P&L'!N11 -> 425369 | T11: ='YTD P&L'!P11-'YTD P&L'!O11 -> 370919 | U11: ='ANNL P&L'!G11-'YTD P&L'!P11 -> 270711 | V11: ='YTD P&L'!Q11 -> 442993 | W11: ='YTD P&L'!R11-'YTD P&L'!Q11 -> 488794 | X11: ='YTD P&L'!S11-'YTD P&L'!R11 -> 524455 | Y11: ='ANNL P&L'!H11-'YTD P&L'!S11 -> 449190 | Z11: =Z9+Z10 -> 459253.85 | AA11: =AA9+AA10 -> 520094.22 | AB11: =AB9+AB10 -> 540343.58 | AC11: =AC9+AC10 -> 524700.68 | AD11: =AD9+AD10 -> 536536.27 | AE11: =AE9+AE10 -> 608087.68 | AF11: =AF9+AF10 -> 631901.95 | AG11: =AG9+AG10 -> 613505.1 | ... AS11: =AS9+AS10 -> 985217.31
A12: Basic Earnings (Loss) per Share
A13: Diluted Earnings (Loss) per Share
A14: Weighted Average Shares Outstanding (Basic)
A15: Weighted Average Shares Outstanding (Diluted)
A16: Net Income (Loss) Attributable to Common Shareholders | B16: ='YTD P&L'!B16 -> 278835 | C16: ='YTD P&L'!C16-'YTD P&L'!B16 -> 311369 | D16: ='YTD P&L'!D16-'YTD P&L'!C16 -> 347654 | E16: ='ANNL P&L'!C16-'YTD P&L'!D16 -> 471736 | F16: ='YTD P&L'!E16 -> 315194 | G16: ='YTD P&L'!F16-'YTD P&L'!E16 -> 403762 | H16: ='YTD P&L'!G16-'YTD P&L'!F16 -> 337205 | I16: ='ANNL P&L'!D16-'YTD P&L'!G16 -> 321314 | J16: ='YTD P&L'!H16 -> 294203 | K16: ='YTD P&L'!I16-'YTD P&L'!H16 -> 273360 | L16: ='YTD P&L'!J16-'YTD P&L'!I16 -> 322387 | M16: ='ANNL P&L'!E16-'YTD P&L'!J16 -> 301674 | N16: ='YTD P&L'!K16 -> 397444 | O16: ='YTD P&L'!L16-'YTD P&L'!K16 -> 413871 | P16: ='YTD P&L'!M16-'YTD P&L'!L16 -> 452694 | Q16: ='ANNL P&L'!F16-'YTD P&L'!M16 -> 366979 | R16: ='YTD P&L'!N16 -> 442049 | S16: ='YTD P&L'!O16-'YTD P&L'!N16 -> 425369 | T16: ='YTD P&L'!P16-'YTD P&L'!O16 -> 370919 | U16: ='ANNL P&L'!G16-'YTD P&L'!P16 -> 270711 | V16: ='YTD P&L'!Q16 -> 442993 | W16: ='YTD P&L'!R16-'YTD P&L'!Q16 -> 488794 | X16: ='YTD P&L'!S16-'YTD P&L'!R16 -> 524455 | Y16: ='ANNL P&L'!H16-'YTD P&L'!S16 -> 449190

Sheet QTR BS
B1: Q4 FY2020 | C1: Q1 FY2021 | D1: Q2 FY2021 | E1: Q3 FY2021 | F1: Q4 FY2021 | G1: Q1 FY2022 | H1: Q2 FY2022 | I1: Q3 FY2022 | J1: Q4 FY2022 | K1: Q1 FY2023 | L1: Q2 FY2023 | M1: Q3 FY2023 | N1: Q4 FY2023 | O1: Q1 FY2024 | P1: Q2 FY2024 | Q1: Q3 FY2024 | R1: Q4 FY2024 | S1: Q1 FY2025 | T1: Q2 FY2025 | U1: Q3 FY2025 | V1: Q4 FY2025 | W1: Q1 FY2026E | X1: Q2 FY2026E | Y1: Q3 FY2026E | Z1: Q4 FY2026E | AA1: Q1 FY2027E | AB1: Q2 FY2027E | AC1: Q3 FY2027E | AD1: Q4 FY2027E | AE1: Q1 FY2028E | AF1: Q2 FY2028E | AG1: Q3 FY2028E | AH1: Q4 FY2028E | AI1: Q1 FY2029E | AJ1: Q2 FY2029E | AK1: Q3 FY2029E | AL1: Q4 FY2029E | AM1: Q1 FY2030E | AN1: Q2 FY2030E | AO1: Q3 FY2030E | AP1: Q4 FY2030E
A2: Cash & Cash Equivalents | B2: ='BALANCE SHEET'!B2 -> 1180413 | C2: ='YTD BS'!C2 -> 1178879 | D2: ='YTD BS'!D2 -> 1584239 | E2: ='YTD BS'!E2 -> 1712671 | F2: ='BALANCE SHEET'!C2 -> 1326462 | G2: ='YTD BS'!G2 -> 1014786 | H2: ='YTD BS'!H2 -> 1132039 | I2: ='YTD BS'!I2 -> 1303048 | J2: ='BALANCE SHEET'!D2 -> 1307141 | K2: ='YTD BS'!K2 -> 1672660 | L2: ='YTD BS'!L2 -> 1869774 | M2: ='YTD BS'!M2 -> 1773849 | N2: ='BALANCE SHEET'!E2 -> 2297675 | O2: ='YTD BS'!O2 -> 2576524 | P2: ='YTD BS'!P2 -> 1564734 | Q2: ='YTD BS'!Q2 -> 1625339 | R2: ='BALANCE SHEET'!F2 -> 1533287 | S2: ='YTD BS'!S2 -> 1903419 | T2: ='YTD BS'!T2 -> 1926927 | U2: ='YTD BS'!U2 -> 2292939 | V2: ='BALANCE SHEET'!G2 -> 2088117 | W2: ='BS DRIVERS'!W2 -> 2580327.5 | X2: ='BS DRIVERS'!X2 -> 2936716.5 | Y2: ='BS DRIVERS'!Y2 -> 3477516.2 | Z2: ='BS DRIVERS'!Z2 -> 4144447.2 | AA2: ='BS DRIVERS'!AA2 -> 4714659.7 | AB2: ='BS DRIVERS'!AB2 -> 5125139.3 | AC2: ='BS DRIVERS'!AC2 -> 5752495.3 | AD2: ='BS DRIVERS'!AD2 -> 6528188 | ... AP2: ='BS DRIVERS'!AP2 -> 16272810
A3: Short-Term Investments | B3: ='BALANCE SHEET'!B3 -> 881354 | C3: ='YTD BS'!C3 -> 980108 | D3: ='YTD BS'!D3 -> 968952 | E3: ='YTD BS'!E3 -> 1224066 | F3: ='BALANCE SHEET'!C3 -> 1749727 | G3: ='YTD BS'!G3 -> 1717648 | H3: ='YTD BS'!H3 -> 1337792 | I3: ='YTD BS'!I3 -> 1346781 | J3: ='BALANCE SHEET'!D3 -> 1362314 | K3: ='YTD BS'!K3 -> 1383028 | L3: ='YTD BS'!L3 -> 1417239 | M3: ='YTD BS'!M3 -> 1236752 | N3: ='BALANCE SHEET'!E3 -> 955605 | O3: ='YTD BS'!O3 -> 984201 | P3: ='YTD BS'!P3 -> 0 | Q3: ='YTD BS'!Q3 -> 0 | R3: ='BALANCE SHEET'!F3 -> 0 | S3: ='YTD BS'!S3 -> 0 | T3: ='YTD BS'!T3 -> 145253 | U3: ='YTD BS'!U3 -> 286391 | V3: ='BALANCE SHEET'!G3 -> 677084 | W3: ='BS DRIVERS'!W3 -> 677084 | X3: ='BS DRIVERS'!X3 -> 677084 | Y3: ='BS DRIVERS'!Y3 -> 677084 | Z3: ='BS DRIVERS'!Z3 -> 677084 | AA3: ='BS DRIVERS'!AA3 -> 677084 | AB3: ='BS DRIVERS'!AB3 -> 677084 | AC3: ='BS DRIVERS'!AC3 -> 677084 | AD3: ='BS DRIVERS'!AD3 -> 677084 | ... AP3: ='BS DRIVERS'!AP3 -> 677084
A4: Accounts Receivable | B4: ='BALANCE SHEET'!B4 -> 666012 | C4: ='YTD BS'!C4 -> 802509 | D4: ='YTD BS'!D4 -> 909169 | E4: ='YTD BS'!E4 -> 849157 | F4: ='BALANCE SHEET'!C4 -> 896658 | G4: ='YTD BS'!G4 -> 1039780 | H4: ='YTD BS'!H4 -> 1175587 | I4: ='YTD BS'!I4 -> 1051642 | J4: ='BALANCE SHEET'!D4 -> 1016203 | K4: ='YTD BS'!K4 -> 1190351 | L4: ='YTD BS'!L4 -> 1333004 | M4: ='YTD BS'!M4 -> 1231188 | N4: ='BALANCE SHEET'!E4 -> 1193964 | O4: ='YTD BS'!O4 -> 1370239 | P4: ='YTD BS'!P4 -> 1362398 | Q4: ='YTD BS'!Q4 -> 1285397 | R4: ='BALANCE SHEET'!F4 -> 1221646 | S4: ='YTD BS'!S4 -> 1360233 | T4: ='YTD BS'!T4 -> 1522702 | U4: ='YTD BS'!U4 -> 1601216 | V4: ='BALANCE SHEET'!G4 -> 1618072 | W4: ='QTR P&L'!Z2*'BS DRIVERS'!W4/ASSUMPTIONS!$B$2 -> 1656037.8 | X4: ='QTR P&L'!AA2*'BS DRIVERS'!X4/ASSUMPTIONS!$B$2 -> 1885557.7 | Y4: ='QTR P&L'!AB2*'BS DRIVERS'!Y4/ASSUMPTIONS!$B$2 -> 1961948.3 | Z4: ='QTR P&L'!AC2*'BS DRIVERS'!Z4/ASSUMPTIONS!$B$2 -> 1902935.5 | AA4: ='QTR P&L'!AD2*'BS DRIVERS'!AA4/ASSUMPTIONS!$B$2 -> 1947585.2 | AB4: ='QTR P&L'!AE2*'BS DRIVERS'!AB4/ASSUMPTIONS!$B$2 -> 2217512.4 | AC4: ='QTR P&L'!AF2*'BS DRIVERS'!AC4/ASSUMPTIONS!$B$2 -> 2307351.6 | AD4: ='QTR P&L'!AG2*'BS DRIVERS'!AD4/ASSUMPTIONS!$B$2 -> 2237949.6 | ... AP4: ='QTR P&L'!AS2*'BS DRIVERS'!AP4/ASSUMPTIONS!$B$2 -> 3640231.4
A5: Inventories | B5: ='BALANCE SHEET'!B5 -> 333085 | C5: ='YTD BS'!C5 -> 368402 | D5: ='YTD BS'!D5 -> 382890 | E5: ='YTD BS'!E5 -> 471553 | F5: ='BALANCE SHEET'!C5 -> 593357 | G5: ='YTD BS'!G5 -> 821132 | H5: ='YTD BS'!H5 -> 885948 | I5: ='YTD BS'!I5 -> 862977 | J5: ='BALANCE SHEET'!D5 -> 935631 | K5: ='YTD BS'!K5 -> 906723 | L5: ='YTD BS'!L5 -> 846812 | M5: ='YTD BS'!M5 -> 883582 | N5: ='BALANCE SHEET'!E5 -> 971406 | O5: ='YTD BS'!O5 -> 939630 | P5: ='YTD BS'!P5 -> 834404 | Q5: ='YTD BS'!Q5 -> 770338 | R5: ='BALANCE SHEET'!F5 -> 737107 | S5: ='YTD BS'!S5 -> 725129 | T5: ='YTD BS'!T5 -> 658167 | U5: ='YTD BS'!U5 -> 704586 | V5: ='BALANCE SHEET'!G5 -> 799623 | W5: ='QTR P&L'!Z3*'BS DRIVERS'!W5/ASSUMPTIONS!$B$2 -> 818385.03 | X5: ='QTR P&L'!AA3*'BS DRIVERS'!X5/ASSUMPTIONS!$B$2 -> 931809.78 | Y5: ='QTR P&L'!AB3*'BS DRIVERS'!Y5/ASSUMPTIONS!$B$2 -> 969560.67 | Z5: ='QTR P&L'!AC3*'BS DRIVERS'!Z5/ASSUMPTIONS!$B$2 -> 940397.59 | AA5: ='QTR P&L'!AD3*'BS DRIVERS'!AA5/ASSUMPTIONS!$B$2 -> 962462.7 | AB5: ='QTR P&L'!AE3*'BS DRIVERS'!AB5/ASSUMPTIONS!$B$2 -> 1095856 | AC5: ='QTR P&L'!AF3*'BS DRIVERS'!AC5/ASSUMPTIONS!$B$2 -> 1140253 | AD5: ='QTR P&L'!AG3*'BS DRIVERS'!AD5/ASSUMPTIONS!$B$2 -> 1105955.7 | ... AP5: ='QTR P&L'!AS3*'BS DRIVERS'!AP5/ASSUMPTIONS!$B$2 -> 1798939
A6: Prepaid Expenses | B6: ='BALANCE SHEET'!B6 -> 55358 | C6: ='YTD BS'!C6 -> 72803 | D6: ='YTD BS'!D6 -> 83086 | E6: ='YTD BS'!E6 -> 95607 | F6: ='BALANCE SHEET'!C6 -> 82668 | G6: ='YTD BS'!G6 -> 110327 | H6: ='YTD BS'!H6 -> 132273 | I6: ='YTD BS'!I6 -> 112294 | J6: ='BALANCE SHEET'!D6 -> 109823 | K6: ='YTD BS'!K6 -> 110958 | L6: ='YTD BS'!L6 -> 148750 | M6: ='YTD BS'!M6 -> 162676 | N6: ='BALANCE SHEET'!E6 -> 116195 | O6: ='YTD BS'!O6 -> 124580 | P6: ='YTD BS'!P6 -> 129303 | Q6: ='YTD BS'!Q6 -> 124656 | R6: ='BALANCE SHEET'!F6 -> 107262 | S6: ='YTD BS'!S6 -> 112525 | T6: ='YTD BS'!T6 -> 137257 | U6: ='YTD BS'!U6 -> 142713 | V6: ='BALANCE SHEET'!G6 -> 103551 | W6: ='QTR P&L'!Z2*'BS DRIVERS'!W6 -> 105980.68 | X6: ='QTR P&L'!AA2*'BS DRIVERS'!X6 -> 120669.16 | Y6: ='QTR P&L'!AB2*'BS DRIVERS'!Y6 -> 125557.89 | Z6: ='QTR P&L'!AC2*'BS DRIVERS'!Z6 -> 121781.28 | AA6: ='QTR P&L'!AD2*'BS DRIVERS'!AA6 -> 124638.71 | AB6: ='QTR P&L'!AE2*'BS DRIVERS'!AB6 -> 141913.11 | AC6: ='QTR P&L'!AF2*'BS DRIVERS'!AC6 -> 147662.51 | AD6: ='QTR P&L'!AG2*'BS DRIVERS'!AD6 -> 143221.02 | ... AP6: ='QTR P&L'!AS2*'BS DRIVERS'!AP6 -> 232962.2
A7: Prepaid Income Taxes | B7: ='BALANCE SHEET'!B7 -> 24733 | C7: ='YTD BS'!C7 -> 31171 | D7: ='YTD BS'!D7 -> 22339 | E7: ='YTD BS'!E7 -> 30619 | F7: ='BALANCE SHEET'!C7 -> 33238 | G7: ='YTD BS'!G7 -> 39993 | H7: ='YTD BS'!H7 -> 32981 | I7: ='YTD BS'!I7 -> 19949 | J7: ='BALANCE SHEET'!D7 -> 33785 | K7: ='YTD BS'!K7 -> 30889 | L7: ='YTD BS'!L7 -> 38534 | M7: ='YTD BS'!M7 -> 23468 | N7: ='BALANCE SHEET'!E7 -> 54151 | O7: ='YTD BS'!O7 -> 40340 | P7: ='YTD BS'!P7 -> 63458 | Q7: ='YTD BS'!Q7 -> 92028 | R7: ='BALANCE SHEET'!F7 -> 42202 | S7: ='YTD BS'!S7 -> 34113 | T7: ='YTD BS'!T7 -> 39034 | U7: ='YTD BS'!U7 -> 38372 | V7: ='BALANCE SHEET'!G7 -> 74637 | W7: ='QTR P&L'!Z2*'BS DRIVERS'!W7 -> 76388.252 | X7: ='QTR P&L'!AA2*'BS DRIVERS'!X7 -> 86975.346 | Y7: ='QTR P&L'!AB2*'BS DRIVERS'!Y7 -> 90499.022 | Z7: ='QTR P&L'!AC2*'BS DRIVERS'!Z7 -> 87776.934 | AA7: ='QTR P&L'!AD2*'BS DRIVERS'!AA7 -> 89836.496 | AB7: ='QTR P&L'!AE2*'BS DRIVERS'!AB7 -> 102287.46 | AC7: ='QTR P&L'!AF2*'BS DRIVERS'!AC7 -> 106431.48 | AD7: ='QTR P&L'!AG2*'BS DRIVERS'!AD7 -> 103230.17 | ... AP7: ='QTR P&L'!AS2*'BS DRIVERS'!AP7 -> 167913.39
A8: Total Current Assets | B8: ='BALANCE SHEET'!B8 -> 3140955 | C8: ='YTD BS'!C8 -> 3433872 | D8: ='YTD BS'!D8 -> 3950675 | E8: ='YTD BS'!E8 -> 4383673 | F8: ='BALANCE SHEET'!C8 -> 4682110 | G8: ='YTD BS'!G8 -> 4743666 | H8: ='YTD BS'!H8 -> 4696620 | I8: ='YTD BS'!I8 -> 4696691 | J8: ='BALANCE SHEET'!D8 -> 4764897 | K8: ='YTD BS'!K8 -> 5294609 | L8: ='YTD BS'!L8 -> 5654113 | M8: ='YTD BS'!M8 -> 5311515 | N8: ='BALANCE SHEET'!E8 -> 5588996 | O8: ='YTD BS'!O8 -> 6035514 | P8: ='YTD BS'!P8 -> 3954297 | Q8: ='YTD BS'!Q8 -> 3897758 | R8: ='BALANCE SHEET'!F8 -> 3641504 | S8: ='YTD BS'!S8 -> 4135419 | T8: ='YTD BS'!T8 -> 4429340 | U8: ='YTD BS'!U8 -> 5066217 | V8: ='BALANCE SHEET'!G8 -> 5361084 | W8: =SUM(W2:W7) -> 5914203.2 | X8: =SUM(X2:X7) -> 6638812.5 | Y8: =SUM(Y2:Y7) -> 7302166.1 | Z8: =SUM(Z2:Z7) -> 7874422.5 | AA8: =SUM(AA2:AA7) -> 8516266.9 | AB8: =SUM(AB2:AB7) -> 9359792.3 | AC8: =SUM(AC2:AC7) -> 10131278 | AD8: =SUM(AD2:AD7) -> 10795629 | ... AP8: =SUM(AP2:AP7) -> 22789940
A9: Long-Term Investments | B9: ='BALANCE SHEET'!B9 -> 44291 | C9: ='YTD BS'!C9 -> 63751 | D9: ='YTD BS'!D9 -> 91033 | E9: ='YTD BS'!E9 -> 28255 | F9: ='BALANCE SHEET'!C9 -> 99419 | G9: ='YTD BS'!G9 -> 65652 | H9: ='YTD BS'!H9 -> 64119 | I9: ='YTD BS'!I9 -> 72373 | J9: ='BALANCE SHEET'!D9 -> 61443 | K9: ='YTD BS'!K9 -> 41152 | L9: ='YTD BS'!L9 -> 62248 | M9: ='YTD BS'!M9 -> 52636 | N9: ='BALANCE SHEET'!E9 -> 76431 | O9: ='YTD BS'!O9 -> 8162 | P9: ='YTD BS'!P9 -> 0 | Q9: ='YTD BS'!Q9 -> 0 | R9: ='BALANCE SHEET'!F9 -> 0 | S9: ='YTD BS'!S9 -> 0 | T9: ='YTD BS'!T9 -> 138058 | U9: ='YTD BS'!U9 -> 359174 | V9: ='BALANCE SHEET'!G9 -> 487329 | W9: ='QTR P&L'!Z2*'BS DRIVERS'!W8 -> 498763.49 | X9: ='QTR P&L'!AA2*'BS DRIVERS'!X8 -> 567890.03 | Y9: ='QTR P&L'!AB2*'BS DRIVERS'!Y8 -> 590897.25 | Z9: ='QTR P&L'!AC2*'BS DRIVERS'!Z8 -> 573123.86 | AA9: ='QTR P&L'!AD2*'BS DRIVERS'!AA8 -> 586571.4 | AB9: ='QTR P&L'!AE2*'BS DRIVERS'!AB8 -> 667867.75 | AC9: ='QTR P&L'!AF2*'BS DRIVERS'!AC8 -> 694925.42 | AD9: ='QTR P&L'!AG2*'BS DRIVERS'!AD8 -> 674023 | ... AP9: ='QTR P&L'!AS2*'BS DRIVERS'!AP8 -> 1096360.6
A10: Net PP&E | B10: ='BALANCE SHEET'!B10 -> 314656 | C10: ='YTD BS'!C10 -> 312155 | D10: ='YTD BS'!D10 -> 309178 | E10: ='YTD BS'!E10 -> 309574 | F10: ='BALANCE SHEET'!C10 -> 313753 | G10: ='YTD BS'!G10 -> 407391 | H10: ='YTD BS'!H10 -> 464541 | I10: ='YTD BS'!I10 -> 485550 | J10: ='BALANCE SHEET'!D10 -> 516897 | K10: ='YTD BS'!K10 -> 545922 | L10: ='YTD BS'!L10 -> 576645 | M10: ='YTD BS'!M10 -> 731208 | N10: ='BALANCE SHEET'!E10 -> 890796 | O10: ='YTD BS'!O10 -> 923290 | P10: ='YTD BS'!P10 -> 960962 | Q10: ='YTD BS'!Q10 -> 1006788 | R10: ='BALANCE SHEET'!F10 -> 1047024 | S10: ='YTD BS'!S10 -> 1064008 | T10: ='YTD BS'!T10 -> 1090898 | U10: ='YTD BS'!U10 -> 1110705 | V10: ='BALANCE SHEET'!G10 -> 1081544 | W10: ='BS DRIVERS'!W9 -> 1077200.4 | X10: ='BS DRIVERS'!X9 -> 1072254.8 | Y10: ='BS DRIVERS'!Y9 -> 1067108.9 | Z10: ='BS DRIVERS'!Z9 -> 1062117.7 | AA10: ='BS DRIVERS'!AA9 -> 1057009.5 | AB10: ='BS DRIVERS'!AB9 -> 1051193.2 | AC10: ='BS DRIVERS'!AC9 -> 1045141.3 | AD10: ='BS DRIVERS'!AD9 -> 1039271.4 | ... AP10: ='BS DRIVERS'!AP9 -> 943642.85
A11: Deferred Tax Assets | B11: ='BALANCE SHEET'!B11 -> 241650 | C11: ='YTD BS'!C11 -> 241650 | D11: ='YTD BS'!D11 -> 241297 | E11: ='YTD BS'!E11 -> 241297 | F11: ='BALANCE SHEET'!C11 -> 225221 | G11: ='YTD BS'!G11 -> 225221 | H11: ='YTD BS'!H11 -> 203287 | I11: ='YTD BS'!I11 -> 195511 | J11: ='BALANCE SHEET'!D11 -> 177039 | K11: ='YTD BS'!K11 -> 177039 | L11: ='YTD BS'!L11 -> 177039 | M11: ='YTD BS'!M11 -> 176724 | N11: ='BALANCE SHEET'!E11 -> 175003 | O11: ='YTD BS'!O11 -> 175271 | P11: ='YTD BS'!P11 -> 187269 | Q11: ='YTD BS'!Q11 -> 183430 | R11: ='BALANCE SHEET'!F11 -> 184260 | S11: ='YTD BS'!S11 -> 184358 | T11: ='YTD BS'!T11 -> 184791 | U11: ='YTD BS'!U11 -> 185321 | V11: ='BALANCE SHEET'!G11 -> 188646 | W11: ='BS DRIVERS'!W10 -> 184891 | X11: ='BS DRIVERS'!X10 -> 181136 | Y11: ='BS DRIVERS'!Y10 -> 177381 | Z11: ='BS DRIVERS'!Z10 -> 173626 | AA11: ='BS DRIVERS'!AA10 -> 169871 | AB11: ='BS DRIVERS'!AB10 -> 166116 | AC11: ='BS DRIVERS'!AC10 -> 162361 | AD11: ='BS DRIVERS'!AD10 -> 158606 | ... AP11: ='BS DRIVERS'!AP10 -> 113546
A12: Goodwill | B12: ='BALANCE SHEET'!B12 -> 1331643 | C12: ='YTD BS'!C12 -> 1331643 | D12: ='YTD BS'!D12 -> 1331643 | E12: ='YTD BS'!E12 -> 1331643 | F12: ='BALANCE SHEET'!C12 -> 1331643 | G12: ='YTD BS'!G12 -> 1411928 | H12: ='YTD BS'!H12 -> 1412941 | I12: ='YTD BS'!I12 -> 1412941 | J12: ='BALANCE SHEET'!D12 -> 1417941 | K12: ='YTD BS'!K12 -> 1417941 | L12: ='YTD BS'!L12 -> 1417941 | M12: ='YTD BS'!M12 -> 1417941 | N12: ='BALANCE SHEET'!E12 -> 1417941 | O12: ='YTD BS'!O12 -> 1417941 | P12: ='YTD BS'!P12 -> 1417941 | Q12: ='YTD BS'!Q12 -> 1417941 | R12: ='BALANCE SHEET'!F12 -> 1331643 | S12: ='YTD BS'!S12 -> 1331643 | T12: ='YTD BS'!T12 -> 1331643 | U12: ='YTD BS'!U12 -> 1331643 | V12: ='BALANCE SHEET'!G12 -> 1331643 | W12: ='BS DRIVERS'!W11 -> 1331643 | X12: ='BS DRIVERS'!X11 -> 1331643 | Y12: ='BS DRIVERS'!Y11 -> 1331643 | Z12: ='BS DRIVERS'!Z11 -> 1331643 | AA12: ='BS DRIVERS'!AA11 -> 1331643 | AB12: ='BS DRIVERS'!AB11 -> 1331643 | AC12: ='BS DRIVERS'!AC11 -> 1331643 | AD12: ='BS DRIVERS'!AD11 -> 1331643 | ... AP12: ='BS DRIVERS'!AP11 -> 1331643
A13: Intangible Assets | B13: ='BALANCE SHEET'!B13 -> 1059046 | C13: ='YTD BS'!C13 -> 1063092 | D13: ='YTD BS'!D13 -> 1058323 | E13: ='YTD BS'!E13 -> 1066083 | F13: ='BALANCE SHEET'!C13 -> 1072386 | G13: ='YTD BS'!G13 -> 1232113 | H13: ='YTD BS'!H13 -> 1223114 | I13: ='YTD BS'!I13 -> 1225826 | J13: ='BALANCE SHEET'!D13 -> 1220410 | K13: ='YTD BS'!K13 -> 1222598 | L13: ='YTD BS'!L13 -> 1224100 | M13: ='YTD BS'!M13 -> 1459447 | N13: ='BALANCE SHEET'!E13 -> 1427139 | O13: ='YTD BS'!O13 -> 1430762 | P13: ='YTD BS'!P13 -> 1433326 | Q13: ='YTD BS'!Q13 -> 1442426 | R13: ='BALANCE SHEET'!F13 -> 1414252 | S13: ='YTD BS'!S13 -> 1415958 | T13: ='YTD BS'!T13 -> 1418827 | U13: ='YTD BS'!U13 -> 1419306 | V13: ='BALANCE SHEET'!G13 -> 1379268 | W13: ='BS DRIVERS'!W12 -> 1379268 | X13: ='BS DRIVERS'!X12 -> 1379268 | Y13: ='BS DRIVERS'!Y12 -> 1379268 | Z13: ='BS DRIVERS'!Z12 -> 1379268 | AA13: ='BS DRIVERS'!AA12 -> 1379268 | AB13: ='BS DRIVERS'!AB12 -> 1379268 | AC13: ='BS DRIVERS'!AC12 -> 1379268 | AD13: ='BS DRIVERS'!AD12 -> 1379268 | ... AP13: ='BS DRIVERS'!AP12 -> 1379268
A14: Other Non-Current Assets | B14: ='BALANCE SHEET'!B14 -> 70475 | C14: ='YTD BS'!C14 -> 88203 | D14: ='YTD BS'!D14 -> 89394 | E14: ='YTD BS'!E14 -> 88883 | F14: ='BALANCE SHEET'!C14 -> 80252 | G14: ='YTD BS'!G14 -> 101488 | H14: ='YTD BS'!H14 -> 110390 | I14: ='YTD BS'!I14 -> 115913 | J14: ='BALANCE SHEET'!D14 -> 134478 | K14: ='YTD BS'!K14 -> 145101 | L14: ='YTD BS'!L14 -> 151252 | M14: ='YTD BS'!M14 -> 164867 | N14: ='BALANCE SHEET'!E14 -> 110216 | O14: ='YTD BS'!O14 -> 107126 | P14: ='YTD BS'!P14 -> 107109 | Q14: ='YTD BS'!Q14 -> 104958 | R14: ='BALANCE SHEET'!F14 -> 100406 | S14: ='YTD BS'!S14 -> 95642 | T14: ='YTD BS'!T14 -> 136331 | U14: ='YTD BS'!U14 -> 138907 | V14: ='BALANCE SHEET'!G14 -> 159431 | W14: ='QTR P&L'!Z2*'BS DRIVERS'!W13 -> 163171.82 | X14: ='QTR P&L'!AA2*'BS DRIVERS'!X13 -> 185786.76 | Y14: ='QTR P&L'!AB2*'BS DRIVERS'!Y13 -> 193313.63 | Z14: ='QTR P&L'!AC2*'BS DRIVERS'!Z13 -> 187499.02 | AA14: ='QTR P&L'!AD2*'BS DRIVERS'!AA13 -> 191898.42 | AB14: ='QTR P&L'!AE2*'BS DRIVERS'!AB13 -> 218494.74 | AC14: ='QTR P&L'!AF2*'BS DRIVERS'!AC13 -> 227346.73 | AD14: ='QTR P&L'!AG2*'BS DRIVERS'!AD13 -> 220508.45 | ... AP14: ='QTR P&L'!AS2*'BS DRIVERS'!AP13 -> 358677.33
A15: Total Assets | B15: ='BALANCE SHEET'!B15 -> 6202716 | C15: ='YTD BS'!C15 -> 6534366 | D15: ='YTD BS'!D15 -> 7071543 | E15: ='YTD BS'!E15 -> 7449408 | F15: ='BALANCE SHEET'!C15 -> 7804784 | G15: ='YTD BS'!G15 -> 8187459 | H15: ='YTD BS'!H15 -> 8175012 | I15: ='YTD BS'!I15 -> 8204805 | J15: ='BALANCE SHEET'!D15 -> 8293105 | K15: ='YTD BS'!K15 -> 8844362 | L15: ='YTD BS'!L15 -> 9263338 | M15: ='YTD BS'!M15 -> 9314338 | N15: ='BALANCE SHEET'!E15 -> 9686522 | O15: ='YTD BS'!O15 -> 10098066 | P15: ='YTD BS'!P15 -> 8060904 | Q15: ='YTD BS'!Q15 -> 8053301 | R15: ='BALANCE SHEET'!F15 -> 7719089 | S15: ='YTD BS'!S15 -> 8227028 | T15: ='YTD BS'!T15 -> 8729888 | U15: ='YTD BS'!U15 -> 9611273 | V15: ='BALANCE SHEET'!G15 -> 9988945 | W15: =W8+SUM(W9:W14) -> 10549141 | X15: =X8+SUM(X9:X14) -> 11356791 | Y15: =Y8+SUM(Y9:Y14) -> 12041778 | Z15: =Z8+SUM(Z9:Z14) -> 12581700 | AA15: =AA8+SUM(AA9:AA14) -> 13232528 | AB15: =AB8+SUM(AB9:AB14) -> 14174375 | AC15: =AC8+SUM(AC9:AC14) -> 14971963 | AD15: =AD8+SUM(AD9:AD14) -> 15598948 | ... AP15: =AP8+SUM(AP9:AP14) -> 28013078
A16: Accounts Payable | B16: ='BALANCE SHEET'!B16 -> 296800 | C16: ='YTD BS'!C16 -> 334076 | D16: ='YTD BS'!D16 -> 362900 | E16: ='YTD BS'!E16 -> 396229 | F16: ='BALANCE SHEET'!C16 -> 404263 | G16: ='YTD BS'!G16 -> 438256 | H16: ='YTD BS'!H16 -> 492858 | I16: ='YTD BS'!I16 -> 520198 | J16: ='BALANCE SHEET'!D16 -> 444265 | K16: ='YTD BS'!K16 -> 491249 | L16: ='YTD BS'!L16 -> 568613 | M16: ='YTD BS'!M16 -> 539892 | N16: ='BALANCE SHEET'!E16 -> 564379 | O16: ='YTD BS'!O16 -> 533729 | P16: ='YTD BS'!P16 -> 511137 | Q16: ='YTD BS'!Q16 -> 549028 | R16: ='BALANCE SHEET'!F16 -> 466775 | S16: ='YTD BS'!S16 -> 486951 | T16: ='YTD BS'!T16 -> 489037 | U16: ='YTD BS'!U16 -> 683030 | V16: ='BALANCE SHEET'!G16 -> 565974 | W16: ='QTR P&L'!Z3*'BS DRIVERS'!W14/ASSUMPTIONS!$B$2 -> 579253.79 | X16: ='QTR P&L'!AA3*'BS DRIVERS'!X14/ASSUMPTIONS!$B$2 -> 659535.94 | Y16: ='QTR P&L'!AB3*'BS DRIVERS'!Y14/ASSUMPTIONS!$B$2 -> 686256.06 | Z16: ='QTR P&L'!AC3*'BS DRIVERS'!Z14/ASSUMPTIONS!$B$2 -> 665614.4 | AA16: ='QTR P&L'!AD3*'BS DRIVERS'!AA14/ASSUMPTIONS!$B$2 -> 681232.11 | AB16: ='QTR P&L'!AE3*'BS DRIVERS'!AB14/ASSUMPTIONS!$B$2 -> 775648.04 | AC16: ='QTR P&L'!AF3*'BS DRIVERS'!AC14/ASSUMPTIONS!$B$2 -> 807072.26 | AD16: ='QTR P&L'!AG3*'BS DRIVERS'!AD14/ASSUMPTIONS!$B$2 -> 782796.62 | ... AP16: ='QTR P&L'!AS3*'BS DRIVERS'!AP14/ASSUMPTIONS!$B$2 -> 1273290.9
A17: Accrued Expenses | B17: ='BALANCE SHEET'!B17 -> 142653 | C17: ='YTD BS'!C17 -> 170954 | D17: ='YTD BS'!D17 -> 172498 | E17: ='YTD BS'!E17 -> 180719 | F17: ='BALANCE SHEET'!C17 -> 210964 | G17: ='YTD BS'!G17 -> 234111 | H17: ='YTD BS'!H17 -> 209154 | I17: ='YTD BS'!I17 -> 198692 | J17: ='BALANCE SHEET'!D17 -> 172991 | K17: ='YTD BS'!K17 -> 245932 | L17: ='YTD BS'!L17 -> 198656 | M17: ='YTD BS'!M17 -> 207727 | N17: ='BALANCE SHEET'!E17 -> 183988 | O17: ='YTD BS'!O17 -> 204679 | P17: ='YTD BS'!P17 -> 213905 | Q17: ='YTD BS'!Q17 -> 259088 | R17: ='BALANCE SHEET'!F17 -> 220764 | S17: ='YTD BS'!S17 -> 262545 | T17: ='YTD BS'!T17 -> 258937 | U17: ='YTD BS'!U17 -> 325450 | V17: ='BALANCE SHEET'!G17 -> 306085 | W17: ='QTR P&L'!Z2*'BS DRIVERS'!W15 -> 313266.86 | X17: ='QTR P&L'!AA2*'BS DRIVERS'!X15 -> 356684.33 | Y17: ='QTR P&L'!AB2*'BS DRIVERS'!Y15 -> 371134.87 | Z17: ='QTR P&L'!AC2*'BS DRIVERS'!Z15 -> 359971.63 | AA17: ='QTR P&L'!AD2*'BS DRIVERS'!AA15 -> 368417.86 | AB17: ='QTR P&L'!AE2*'BS DRIVERS'!AB15 -> 419479.04 | AC17: ='QTR P&L'!AF2*'BS DRIVERS'!AC15 -> 436473.61 | AD17: ='QTR P&L'!AG2*'BS DRIVERS'!AD15 -> 423345.07 | ... AP17: ='QTR P&L'!AS2*'BS DRIVERS'!AP15 -> 688609.8
A18: Accrued Promotional Allowance | B18: ='BALANCE SHEET'!B18 -> 186658 | C18: ='YTD BS'!C18 -> 197380 | D18: ='YTD BS'!D18 -> 227414 | E18: ='YTD BS'!E18 -> 232394 | F18: ='BALANCE SHEET'!C18 -> 211461 | G18: ='YTD BS'!G18 -> 270785 | H18: ='YTD BS'!H18 -> 277618 | I18: ='YTD BS'!I18 -> 281650 | J18: ='BALANCE SHEET'!D18 -> 255631 | K18: ='YTD BS'!K18 -> 308094 | L18: ='YTD BS'!L18 -> 283647 | M18: ='YTD BS'!M18 -> 296577 | N18: ='BALANCE SHEET'!E18 -> 269061 | O18: ='YTD BS'!O18 -> 318895 | P18: ='YTD BS'!P18 -> 319757 | Q18: ='YTD BS'!Q18 -> 301973 | R18: ='BALANCE SHEET'!F18 -> 267711 | S18: ='YTD BS'!S18 -> 304670 | T18: ='YTD BS'!T18 -> 360406 | U18: ='YTD BS'!U18 -> 392628 | V18: ='BALANCE SHEET'!G18 -> 384070 | W18: ='QTR P&L'!Z2*'BS DRIVERS'!W16 -> 393081.66 | X18: ='QTR P&L'!AA2*'BS DRIVERS'!X16 -> 447561.14 | Y18: ='QTR P&L'!AB2*'BS DRIVERS'!Y16 -> 465693.41 | Z18: ='QTR P&L'!AC2*'BS DRIVERS'!Z16 -> 451685.99 | AA18: ='QTR P&L'!AD2*'BS DRIVERS'!AA16 -> 462284.16 | AB18: ='QTR P&L'!AE2*'BS DRIVERS'!AB16 -> 526354.82 | AC18: ='QTR P&L'!AF2*'BS DRIVERS'!AC16 -> 547679.3 | AD18: ='QTR P&L'!AG2*'BS DRIVERS'!AD16 -> 531205.85 | ... AP18: ='QTR P&L'!AS2*'BS DRIVERS'!AP16 -> 864055.3
A19: Deferred Revenue - Current | B19: ='BALANCE SHEET'!B19 -> 45429 | C19: ='YTD BS'!C19 -> 45961 | D19: ='YTD BS'!D19 -> 46656 | E19: ='YTD BS'!E19 -> 45278 | F19: ='BALANCE SHEET'!C19 -> 42530 | G19: ='YTD BS'!G19 -> 42540 | H19: ='YTD BS'!H19 -> 44344 | I19: ='YTD BS'!I19 -> 42608 | J19: ='BALANCE SHEET'!D19 -> 43311 | K19: ='YTD BS'!K19 -> 44440 | L19: ='YTD BS'!L19 -> 42765 | M19: ='YTD BS'!M19 -> 40127 | N19: ='BALANCE SHEET'!E19 -> 41914 | O19: ='YTD BS'!O19 -> 43776 | P19: ='YTD BS'!P19 -> 44377 | Q19: ='YTD BS'!Q19 -> 45627 | R19: ='BALANCE SHEET'!F19 -> 45809 | S19: ='YTD BS'!S19 -> 47542 | T19: ='YTD BS'!T19 -> 49279 | U19: ='YTD BS'!U19 -> 47158 | V19: ='BALANCE SHEET'!G19 -> 45323 | W19: ='QTR P&L'!Z2*'BS DRIVERS'!W17 -> 46386.441 | X19: ='QTR P&L'!AA2*'BS DRIVERS'!X17 -> 52815.408 | Y19: ='QTR P&L'!AB2*'BS DRIVERS'!Y17 -> 54955.145 | Z19: ='QTR P&L'!AC2*'BS DRIVERS'!Z17 -> 53302.169 | AA19: ='QTR P&L'!AD2*'BS DRIVERS'!AA17 -> 54552.829 | AB19: ='QTR P&L'!AE2*'BS DRIVERS'!AB17 -> 62113.624 | AC19: ='QTR P&L'!AF2*'BS DRIVERS'!AC17 -> 64630.065 | AD19: ='QTR P&L'!AG2*'BS DRIVERS'!AD17 -> 62686.08 | ... AP19: ='QTR P&L'!AS2*'BS DRIVERS'!AP17 -> 101964.69
A20: Accrued Compensation | B20: ='BALANCE SHEET'!B20 -> 55015 | C20: ='YTD BS'!C20 -> 30499 | D20: ='YTD BS'!D20 -> 46770 | E20: ='YTD BS'!E20 -> 54507 | F20: ='BALANCE SHEET'!C20 -> 65459 | G20: ='YTD BS'!G20 -> 37551 | H20: ='YTD BS'!H20 -> 53717 | I20: ='YTD BS'!I20 -> 61426 | J20: ='BALANCE SHEET'!D20 -> 72463 | K20: ='YTD BS'!K20 -> 42673 | L20: ='YTD BS'!L20 -> 56195 | M20: ='YTD BS'!M20 -> 76835 | N20: ='BALANCE SHEET'!E20 -> 87392 | O20: ='YTD BS'!O20 -> 52638 | P20: ='YTD BS'!P20 -> 60357 | Q20: ='YTD BS'!Q20 -> 81787 | R20: ='BALANCE SHEET'!F20 -> 92454 | S20: ='YTD BS'!S20 -> 55812 | T20: ='YTD BS'!T20 -> 72838 | U20: ='YTD BS'!U20 -> 102131 | V20: ='BALANCE SHEET'!G20 -> 114023 | W20: ='QTR P&L'!Z2*'BS DRIVERS'!W18 -> 116698.39 | X20: ='QTR P&L'!AA2*'BS DRIVERS'!X18 -> 132872.3 | Y20: ='QTR P&L'!AB2*'BS DRIVERS'!Y18 -> 138255.42 | Z20: ='QTR P&L'!AC2*'BS DRIVERS'!Z18 -> 134096.89 | AA20: ='QTR P&L'!AD2*'BS DRIVERS'!AA18 -> 137243.28 | AB20: ='QTR P&L'!AE2*'BS DRIVERS'!AB18 -> 156264.63 | AC20: ='QTR P&L'!AF2*'BS DRIVERS'!AC18 -> 162595.46 | AD20: ='QTR P&L'!AG2*'BS DRIVERS'!AD18 -> 157704.8 | ... AP20: ='QTR P&L'!AS2*'BS DRIVERS'!AP18 -> 256521.41
A21: Income Taxes Payable | B21: ='BALANCE SHEET'!B21 -> 23433 | C21: ='YTD BS'!C21 -> 9991 | D21: ='YTD BS'!D21 -> 31289 | E21: ='YTD BS'!E21 -> 23113 | F21: ='BALANCE SHEET'!C21 -> 30399 | G21: ='YTD BS'!G21 -> 21118 | H21: ='YTD BS'!H21 -> 15917 | I21: ='YTD BS'!I21 -> 17143 | J21: ='BALANCE SHEET'!D21 -> 13317 | K21: ='YTD BS'!K21 -> 55123 | L21: ='YTD BS'!L21 -> 12704 | M21: ='YTD BS'!M21 -> 17644 | N21: ='BALANCE SHEET'!E21 -> 14955 | O21: ='YTD BS'!O21 -> 75111 | P21: ='YTD BS'!P21 -> 10990 | Q21: ='YTD BS'!Q21 -> 7641 | R21: ='BALANCE SHEET'!F21 -> 4006 | S21: ='YTD BS'!S21 -> 67837 | T21: ='YTD BS'!T21 -> 28121 | U21: ='YTD BS'!U21 -> 40023 | V21: ='BALANCE SHEET'!G21 -> 32305 | W21: ='QTR P&L'!Z2*'BS DRIVERS'!W19 -> 33062.992 | X21: ='QTR P&L'!AA2*'BS DRIVERS'!X19 -> 37645.384 | Y21: ='QTR P&L'!AB2*'BS DRIVERS'!Y19 -> 39170.531 | Z21: ='QTR P&L'!AC2*'BS DRIVERS'!Z19 -> 37992.334 | AA21: ='QTR P&L'!AD2*'BS DRIVERS'!AA19 -> 38883.771 | AB21: ='QTR P&L'!AE2*'BS DRIVERS'!AB19 -> 44272.899 | AC21: ='QTR P&L'!AF2*'BS DRIVERS'!AC19 -> 46066.55 | AD21: ='QTR P&L'!AG2*'BS DRIVERS'!AD19 -> 44680.93 | ... AP21: ='QTR P&L'!AS2*'BS DRIVERS'!AP19 -> 72677.654
A22: Total Current Liabilities | B22: ='BALANCE SHEET'!B22 -> 749988 | C22: ='YTD BS'!C22 -> 788861 | D22: ='YTD BS'!D22 -> 887527 | E22: ='YTD BS'!E22 -> 932240 | F22: ='BALANCE SHEET'!C22 -> 965076 | G22: ='YTD BS'!G22 -> 1044361 | H22: ='YTD BS'!H22 -> 1093608 | I22: ='YTD BS'!I22 -> 1121717 | J22: ='BALANCE SHEET'!D22 -> 1001978 | K22: ='YTD BS'!K22 -> 1187511 | L22: ='YTD BS'!L22 -> 1162580 | M22: ='YTD BS'!M22 -> 1178802 | N22: ='BALANCE SHEET'!E22 -> 1161689 | O22: ='YTD BS'!O22 -> 1228828 | P22: ='YTD BS'!P22 -> 1160523 | Q22: ='YTD BS'!Q22 -> 1245144 | R22: ='BALANCE SHEET'!F22 -> 1097519 | S22: ='YTD BS'!S22 -> 1225357 | T22: ='YTD BS'!T22 -> 1258618 | U22: ='YTD BS'!U22 -> 1590420 | V22: ='BALANCE SHEET'!G22 -> 1447780 | W22: =SUM(W16:W21) -> 1481750.1 | X22: =SUM(X16:X21) -> 1687114.5 | Y22: =SUM(Y16:Y21) -> 1755465.4 | Z22: =SUM(Z16:Z21) -> 1702663.4 | AA22: =SUM(AA16:AA21) -> 1742614 | AB22: =SUM(AB16:AB21) -> 1984133.1 | AC22: =SUM(AC16:AC21) -> 2064517.2 | AD22: =SUM(AD16:AD21) -> 2002419.4 | ... AP22: =SUM(AP16:AP21) -> 3257119.8
A23: Deferred Revenue - Non-Current | B23: ='BALANCE SHEET'!B23 -> 264436 | C23: ='YTD BS'!C23 -> 257730 | D23: ='YTD BS'!D23 -> 252056 | E23: ='YTD BS'!E23 -> 245621 | F23: ='BALANCE SHEET'!C23 -> 243249 | G23: ='YTD BS'!G23 -> 238241 | H23: ='YTD BS'!H23 -> 232170 | I23: ='YTD BS'!I23 -> 226294 | J23: ='BALANCE SHEET'!D23 -> 223800 | K23: ='YTD BS'!K23 -> 219764 | L23: ='YTD BS'!L23 -> 215039 | M23: ='YTD BS'!M23 -> 209136 | N23: ='BALANCE SHEET'!E23 -> 204251 | O23: ='YTD BS'!O23 -> 198759 | P23: ='YTD BS'!P23 -> 192354 | Q23: ='YTD BS'!Q23 -> 186135 | R23: ='BALANCE SHEET'!F23 -> 179008 | S23: ='YTD BS'!S23 -> 173921 | T23: ='YTD BS'!T23 -> 169763 | U23: ='YTD BS'!U23 -> 164701 | V23: ='BALANCE SHEET'!G23 -> 159991 | W23: ='QTR P&L'!Z2*'BS DRIVERS'!W20 -> 163744.96 | X23: ='QTR P&L'!AA2*'BS DRIVERS'!X20 -> 186439.33 | Y23: ='QTR P&L'!AB2*'BS DRIVERS'!Y20 -> 193992.64 | Z23: ='QTR P&L'!AC2*'BS DRIVERS'!Z20 -> 188157.61 | AA23: ='QTR P&L'!AD2*'BS DRIVERS'!AA20 -> 192572.46 | AB23: ='QTR P&L'!AE2*'BS DRIVERS'!AB20 -> 219262.2 | AC23: ='QTR P&L'!AF2*'BS DRIVERS'!AC20 -> 228145.28 | AD23: ='QTR P&L'!AG2*'BS DRIVERS'!AD20 -> 221282.98 | ... AP23: ='QTR P&L'!AS2*'BS DRIVERS'!AP20 -> 359937.18
A24: Deferred Tax Liability | C24: ='YTD BS'!C24 -> 0 | D24: ='YTD BS'!D24 -> 0 | E24: ='YTD BS'!E24 -> 0 | G24: ='YTD BS'!G24 -> 0 | H24: ='YTD BS'!H24 -> 0 | I24: ='YTD BS'!I24 -> 0 | K24: ='YTD BS'!K24 -> 0 | L24: ='YTD BS'!L24 -> 0 | M24: ='YTD BS'!M24 -> 0 | O24: ='YTD BS'!O24 -> 0 | P24: ='YTD BS'!P24 -> 28896 | Q24: ='YTD BS'!Q24 -> 28896 | S24: ='YTD BS'!S24 -> 0 | T24: ='YTD BS'!T24 -> 0 | U24: ='YTD BS'!U24 -> 0 | W24: ='BS DRIVERS'!W21 -> 0 | X24: ='BS DRIVERS'!X21 -> 0 | Y24: ='BS DRIVERS'!Y21 -> 0 | Z24: ='BS DRIVERS'!Z21 -> 0 | AA24: ='BS DRIVERS'!AA21 -> 0 | AB24: ='BS DRIVERS'!AB21 -> 0 | AC24: ='BS DRIVERS'!AC21 -> 0 | AD24: ='BS DRIVERS'!AD21 -> 0 | ... AP24: ='BS DRIVERS'!AP21 -> 0
A25: Other Non-Current Liabilities | B25: ='BALANCE SHEET'!B24 -> 27432 | C25: ='YTD BS'!C25 -> 28338 | D25: ='YTD BS'!D25 -> 26462 | E25: ='YTD BS'!E25 -> 26550 | F25: ='BALANCE SHEET'!C24 -> 29508 | G25: ='YTD BS'!G25 -> 38185 | H25: ='YTD BS'!H25 -> 40056 | I25: ='YTD BS'!I25 -> 41034 | J25: ='BALANCE SHEET'!D24 -> 42286 | K25: ='YTD BS'!K25 -> 41727 | L25: ='YTD BS'!L25 -> 44255 | M25: ='YTD BS'!M25 -> 53251 | N25: ='BALANCE SHEET'!E24 -> 91838 | O25: ='YTD BS'!O25 -> 92690 | P25: ='YTD BS'!P25 -> 64068 | Q25: ='YTD BS'!Q25 -> 64884 | R25: ='BALANCE SHEET'!F24 -> 110893 | S25: ='YTD BS'!S25 -> 109252 | T25: ='YTD BS'!T25 -> 110203 | U25: ='YTD BS'!U25 -> 110992 | V25: ='BALANCE SHEET'!G24 -> 127066 | W25: ='QTR P&L'!Z2*'BS DRIVERS'!W22 -> 130047.43 | X25: ='QTR P&L'!AA2*'BS DRIVERS'!X22 -> 148071.46 | Y25: ='QTR P&L'!AB2*'BS DRIVERS'!Y22 -> 154070.35 | Z25: ='QTR P&L'!AC2*'BS DRIVERS'!Z22 -> 149436.12 | AA25: ='QTR P&L'!AD2*'BS DRIVERS'!AA22 -> 152942.43 | AB25: ='QTR P&L'!AE2*'BS DRIVERS'!AB22 -> 174139.61 | AC25: ='QTR P&L'!AF2*'BS DRIVERS'!AC22 -> 181194.62 | AD25: ='QTR P&L'!AG2*'BS DRIVERS'!AD22 -> 175744.53 | ... AP25: ='QTR P&L'!AS2*'BS DRIVERS'!AP22 -> 285864.69
A26: Long-Term Debt | B26: ='BALANCE SHEET'!B25 -> 0 | C26: ='YTD BS'!C26 -> 0 | D26: ='YTD BS'!D26 -> 0 | E26: ='YTD BS'!E26 -> 0 | F26: ='BALANCE SHEET'!C25 -> 0 | G26: ='YTD BS'!G26 -> 0 | H26: ='YTD BS'!H26 -> 0 | I26: ='YTD BS'!I26 -> 0 | J26: ='BALANCE SHEET'!D25 -> 0 | K26: ='YTD BS'!K26 -> 0 | L26: ='YTD BS'!L26 -> 0 | M26: ='YTD BS'!M26 -> 0 | N26: ='BALANCE SHEET'!E25 -> 0 | O26: ='YTD BS'!O26 -> 0 | P26: ='YTD BS'!P26 -> 748740 | Q26: ='YTD BS'!Q26 -> 748842 | R26: ='BALANCE SHEET'!F25 -> 373951 | S26: ='YTD BS'!S26 -> 199059 | T26: ='YTD BS'!T26 -> 0 | U26: ='YTD BS'!U26 -> 0 | V26: ='BALANCE SHEET'!G25 -> 0 | W26: ='BS DRIVERS'!W23 -> 0 | X26: ='BS DRIVERS'!X23 -> 0 | Y26: ='BS DRIVERS'!Y23 -> 0 | Z26: ='BS DRIVERS'!Z23 -> 0 | AA26: ='BS DRIVERS'!AA23 -> 0 | AB26: ='BS DRIVERS'!AB23 -> 0 | AC26: ='BS DRIVERS'!AC23 -> 0 | AD26: ='BS DRIVERS'!AD23 -> 0 | ... AP26: ='BS DRIVERS'!AP23 -> 0
A27: Total Liabilities | B27: ='BALANCE SHEET'!B26 -> 1041856 | C27: ='YTD BS'!C27 -> 1074929 | D27: ='YTD BS'!D27 -> 1166045 | E27: ='YTD BS'!E27 -> 1204411 | F27: ='BALANCE SHEET'!C26 -> 1237833 | G27: ='YTD BS'!G27 -> 1320787 | H27: ='YTD BS'!H27 -> 1365834 | I27: ='YTD BS'!I27 -> 1389045 | J27: ='BALANCE SHEET'!D26 -> 1268064 | K27: ='YTD BS'!K27 -> 1449002 | L27: ='YTD BS'!L27 -> 1421874 | M27: ='YTD BS'!M27 -> 1441189 | N27: ='BALANCE SHEET'!E26 -> 1457778 | O27: ='YTD BS'!O27 -> 1520277 | P27: ='YTD BS'!P27 -> 2194581 | Q27: ='YTD BS'!Q27 -> 2273901 | R27: ='BALANCE SHEET'!F26 -> 1761371 | S27: ='YTD BS'!S27 -> 1707589 | T27: ='YTD BS'!T27 -> 1538584 | U27: ='YTD BS'!U27 -> 1866113 | V27: ='BALANCE SHEET'!G26 -> 1734837 | W27: =W22+SUM(W23:W26) -> 1775542.5 | X27: =X22+SUM(X23:X26) -> 2021625.3 | Y27: =Y22+SUM(Y23:Y26) -> 2103528.4 | Z27: =Z22+SUM(Z23:Z26) -> 2040257.1 | AA27: =AA22+SUM(AA23:AA26) -> 2088128.9 | AB27: =AB22+SUM(AB23:AB26) -> 2377534.9 | AC27: =AC22+SUM(AC23:AC26) -> 2473857.1 | AD27: =AD22+SUM(AD23:AD26) -> 2399446.9 | ... AP27: =AP22+SUM(AP23:AP26) -> 3902921.6
A28: Common Stock | B28: ='BALANCE SHEET'!B27 -> 3193 | C28: ='YTD BS'!C28 -> 3196 | D28: ='YTD BS'!D28 -> 3198 | E28: ='YTD BS'!E28 -> 3199 | F28: ='BALANCE SHEET'!C27 -> 3200 | G28: ='YTD BS'!G28 -> 3203 | H28: ='YTD BS'!H28 -> 3205 | I28: ='YTD BS'!I28 -> 3206 | J28: ='BALANCE SHEET'!D27 -> 3209 | K28: ='YTD BS'!K28 -> 5587 | L28: ='YTD BS'!L28 -> 5591 | M28: ='YTD BS'!M28 -> 5592 | N28: ='BALANCE SHEET'!E27 -> 5613 | O28: ='YTD BS'!O28 -> 5624 | P28: ='YTD BS'!P28 -> 5627 | Q28: ='YTD BS'!Q28 -> 5628 | R28: ='BALANCE SHEET'!F27 -> 5632 | S28: ='YTD BS'!S28 -> 5643 | T28: ='YTD BS'!T28 -> 5650 | U28: ='YTD BS'!U28 -> 5655 | V28: ='BALANCE SHEET'!G27 -> 5665 | W28: ='BS DRIVERS'!W24 -> 5665 | X28: ='BS DRIVERS'!X24 -> 5665 | Y28: ='BS DRIVERS'!Y24 -> 5665 | Z28: ='BS DRIVERS'!Z24 -> 5665 | AA28: ='BS DRIVERS'!AA24 -> 5665 | AB28: ='BS DRIVERS'!AB24 -> 5665 | AC28: ='BS DRIVERS'!AC24 -> 5665 | AD28: ='BS DRIVERS'!AD24 -> 5665 | ... AP28: ='BS DRIVERS'!AP24 -> 5665
A29: Additional Paid-in Capital | B29: ='BALANCE SHEET'!B28 -> 4537982 | C29: ='YTD BS'!C29 -> 4562689 | D29: ='YTD BS'!D29 -> 4597333 | E29: ='YTD BS'!E29 -> 4626299 | F29: ='BALANCE SHEET'!C28 -> 4652620 | G29: ='YTD BS'!G29 -> 4673302 | H29: ='YTD BS'!H29 -> 4707569 | I29: ='YTD BS'!I29 -> 4736141 | J29: ='BALANCE SHEET'!D28 -> 4780013 | K29: ='YTD BS'!K29 -> 4829301 | L29: ='YTD BS'!L29 -> 4869791 | M29: ='YTD BS'!M29 -> 4893289 | N29: ='BALANCE SHEET'!E28 -> 4975115 | O29: ='YTD BS'!O29 -> 5034948 | P29: ='YTD BS'!P29 -> 5068291 | Q29: ='YTD BS'!Q29 -> 5105957 | R29: ='BALANCE SHEET'!F28 -> 5144922 | S29: ='YTD BS'!S29 -> 5213731 | T29: ='YTD BS'!T29 -> 5285157 | U29: ='YTD BS'!U29 -> 5343915 | V29: ='BALANCE SHEET'!G28 -> 5430847 | W29: ='BS DRIVERS'!W25 -> 5470785.6 | X29: ='BS DRIVERS'!X25 -> 5516259.6 | Y29: ='BS DRIVERS'!Y25 -> 5563575.8 | Z29: ='BS DRIVERS'!Z25 -> 5609468.9 | AA29: ='BS DRIVERS'!AA25 -> 5656438.7 | AB29: ='BS DRIVERS'!AB25 -> 5709918.4 | AC29: ='BS DRIVERS'!AC25 -> 5765564.8 | AD29: ='BS DRIVERS'!AD25 -> 5819537.3 | ... AP29: ='BS DRIVERS'!AP25 -> 6698829.3
A30: Retained Earnings (Accumulated Deficit) | B30: ='BALANCE SHEET'!B29 -> 6432074 | C30: ='YTD BS'!C30 -> 6747268 | D30: ='YTD BS'!D30 -> 7151030 | E30: ='YTD BS'!E30 -> 7488235 | F30: ='BALANCE SHEET'!C29 -> 7809549 | G30: ='YTD BS'!G30 -> 8103752 | H30: ='YTD BS'!H30 -> 8377112 | I30: ='YTD BS'!I30 -> 8699499 | J30: ='BALANCE SHEET'!D29 -> 9001173 | K30: ='YTD BS'!K30 -> 4706192 | L30: ='YTD BS'!L30 -> 5120063 | M30: ='YTD BS'!M30 -> 5572757 | N30: ='BALANCE SHEET'!E29 -> 5939736 | O30: ='YTD BS'!O30 -> 6381785 | P30: ='YTD BS'!P30 -> 6807154 | Q30: ='YTD BS'!Q30 -> 7178073 | R30: ='BALANCE SHEET'!F29 -> 7448784 | S30: ='YTD BS'!S30 -> 7891777 | T30: ='YTD BS'!T30 -> 8380571 | U30: ='YTD BS'!U30 -> 8905026 | V30: ='BALANCE SHEET'!G29 -> 9354216 | W30: ='BS DRIVERS'!W26 -> 9813469.8 | X30: ='BS DRIVERS'!X26 -> 10333564 | Y30: ='BS DRIVERS'!Y26 -> 10873908 | Z30: ='BS DRIVERS'!Z26 -> 11398608 | AA30: ='BS DRIVERS'!AA26 -> 11935145 | AB30: ='BS DRIVERS'!AB26 -> 12543232 | AC30: ='BS DRIVERS'!AC26 -> 13175134 | AD30: ='BS DRIVERS'!AD26 -> 13788639 | ... AP30: ='BS DRIVERS'!AP26 -> 23696515
A31: Accumulated Other Comprehensive Income (Loss) | B31: ='BALANCE SHEET'!B30 -> 3034 | C31: ='YTD BS'!C31 -> -24874 | D31: ='YTD BS'!D31 -> -16822 | E31: ='YTD BS'!E31 -> -43495 | F31: ='BALANCE SHEET'!C30 -> -69165 | G31: ='YTD BS'!G31 -> -72145 | H31: ='YTD BS'!H31 -> -152957 | I31: ='YTD BS'!I31 -> -224455 | J31: ='BALANCE SHEET'!D30 -> -159073 | K31: ='YTD BS'!K31 -> -147911 | L31: ='YTD BS'!L31 -> -155725 | M31: ='YTD BS'!M31 -> -198033 | N31: ='BALANCE SHEET'!E30 -> -125337 | O31: ='YTD BS'!O31 -> -157940 | P31: ='YTD BS'!P31 -> -182304 | Q31: ='YTD BS'!Q31 -> -137842 | R31: ='BALANCE SHEET'!F30 -> -269487 | S31: ='YTD BS'!S31 -> -202946 | T31: ='YTD BS'!T31 -> -91308 | U31: ='YTD BS'!U31 -> -93382 | V31: ='BALANCE SHEET'!G30 -> -60841 | W31: ='BS DRIVERS'!W27 -> -35727 | X31: ='BS DRIVERS'!X27 -> -10613 | Y31: ='BS DRIVERS'!Y27 -> 14501 | Z31: ='BS DRIVERS'!Z27 -> 39615 | AA31: ='BS DRIVERS'!AA27 -> 64729 | AB31: ='BS DRIVERS'!AB27 -> 89843 | AC31: ='BS DRIVERS'!AC27 -> 114957 | AD31: ='BS DRIVERS'!AD27 -> 140071 | ... AP31: ='BS DRIVERS'!AP27 -> 441439
A32: Treasury Stock | B32: ='BALANCE SHEET'!B31 -> -5815423 | C32: ='YTD BS'!C32 -> -5828842 | D32: ='YTD BS'!D32 -> -5829241 | E32: ='YTD BS'!E32 -> -5829241 | F32: ='BALANCE SHEET'!C31 -> -5829253 | G32: ='YTD BS'!G32 -> -5841440 | H32: ='YTD BS'!H32 -> -6125751 | I32: ='YTD BS'!I32 -> -6398631 | J32: ='BALANCE SHEET'!D31 -> -6600281 | K32: ='YTD BS'!K32 -> -1997809 | L32: ='YTD BS'!L32 -> -1998256 | M32: ='YTD BS'!M32 -> -2400456 | N32: ='BALANCE SHEET'!E31 -> -2566383 | O32: ='YTD BS'!O32 -> -2686628 | P32: ='YTD BS'!P32 -> -5832445 | Q32: ='YTD BS'!Q32 -> -6372416 | R32: ='BALANCE SHEET'!F31 -> -6372133 | S32: ='YTD BS'!S32 -> -6388766 | T32: ='YTD BS'!T32 -> -6388766 | U32: ='YTD BS'!U32 -> -6416054 | V32: ='BALANCE SHEET'!G31 -> -6475779 | W32: ='BS DRIVERS'!W28 -> -6475779 | X32: ='BS DRIVERS'!X28 -> -6475779 | Y32: ='BS DRIVERS'!Y28 -> -6475779 | Z32: ='BS DRIVERS'!Z28 -> -6475779 | AA32: ='BS DRIVERS'!AA28 -> -6475779 | AB32: ='BS DRIVERS'!AB28 -> -6475779 | AC32: ='BS DRIVERS'!AC28 -> -6475779 | AD32: ='BS DRIVERS'!AD28 -> -6475779 | ... AP32: ='BS DRIVERS'!AP28 -> -6475779
A33: Total Stockholders' Equity | B33: ='BALANCE SHEET'!B32 -> 5160860 | C33: ='YTD BS'!C33 -> 5459437 | D33: ='YTD BS'!D33 -> 5905498 | E33: ='YTD BS'!E33 -> 6244997 | F33: ='BALANCE SHEET'!C32 -> 6566951 | G33: ='YTD BS'!G33 -> 6866672 | H33: ='YTD BS'!H33 -> 6809178 | I33: ='YTD BS'!I33 -> 6815760 | J33: ='BALANCE SHEET'!D32 -> 7025041 | K33: ='YTD BS'!K33 -> 7395360 | L33: ='YTD BS'!L33 -> 7841464 | M33: ='YTD BS'!M33 -> 7873149 | N33: ='BALANCE SHEET'!E32 -> 8228744 | O33: ='YTD BS'!O33 -> 8577789 | P33: ='YTD BS'!P33 -> 5866323 | Q33: ='YTD BS'!Q33 -> 5779400 | R33: ='BALANCE SHEET'!F32 -> 5957718 | S33: ='YTD BS'!S33 -> 6519439 | T33: ='YTD BS'!T33 -> 7191304 | U33: ='YTD BS'!U33 -> 7745160 | V33: ='BALANCE SHEET'!G32 -> 8254108 | W33: =SUM(W28:W32) -> 8778414.5 | X33: =SUM(X28:X32) -> 9369096.6 | Y33: =SUM(Y28:Y32) -> 9981870.5 | Z33: =SUM(Z28:Z32) -> 10577578 | AA33: =SUM(AA28:AA32) -> 11186198 | AB33: =SUM(AB28:AB32) -> 11872880 | AC33: =SUM(AC28:AC32) -> 12585542 | AD33: =SUM(AD28:AD32) -> 13278134 | ... AP33: =SUM(AP28:AP32) -> 24366669
A34: Total Liabilities, Mezzanine & Stockholders' Equity | B34: ='BALANCE SHEET'!B33 -> 6202716 | C34: ='YTD BS'!C34 -> 6534366 | D34: ='YTD BS'!D34 -> 7071543 | E34: ='YTD BS'!E34 -> 7449408 | F34: ='BALANCE SHEET'!C33 -> 7804784 | G34: ='YTD BS'!G34 -> 8187459 | H34: ='YTD BS'!H34 -> 8175012 | I34: ='YTD BS'!I34 -> 8204805 | J34: ='BALANCE SHEET'!D33 -> 8293105 | K34: ='YTD BS'!K34 -> 8844362 | L34: ='YTD BS'!L34 -> 9263338 | M34: ='YTD BS'!M34 -> 9314338 | N34: ='BALANCE SHEET'!E33 -> 9686522 | O34: ='YTD BS'!O34 -> 10098066 | P34: ='YTD BS'!P34 -> 8060904 | Q34: ='YTD BS'!Q34 -> 8053301 | R34: ='BALANCE SHEET'!F33 -> 7719089 | S34: ='YTD BS'!S34 -> 8227028 | T34: ='YTD BS'!T34 -> 8729888 | U34: ='YTD BS'!U34 -> 9611273 | V34: ='BALANCE SHEET'!G33 -> 9988945 | W34: =W27+W33 -> 10553957 | X34: =X27+X33 -> 11390722 | Y34: =Y27+Y33 -> 12085399 | Z34: =Z27+Z33 -> 12617835 | AA34: =AA27+AA33 -> 13274327 | AB34: =AB27+AB33 -> 14250415 | AC34: =AC27+AC33 -> 15059399 | AD34: =AD27+AD33 -> 15677581 | ... AP34: =AP27+AP33 -> 28269591

Sheet QTR CF
B1: Q1 FY2020 | C1: Q2 FY2020 | D1: Q3 FY2020 | E1: Q4 FY2020 | F1: Q1 FY2021 | G1: Q2 FY2021 | H1: Q3 FY2021 | I1: Q4 FY2021 | J1: Q1 FY2022 | K1: Q2 FY2022 | L1: Q3 FY2022 | M1: Q4 FY2022 | N1: Q1 FY2023 | O1: Q2 FY2023 | P1: Q3 FY2023 | Q1: Q4 FY2023 | R1: Q1 FY2024 | S1: Q2 FY2024 | T1: Q3 FY2024 | U1: Q4 FY2024 | V1: Q1 FY2025 | W1: Q2 FY2025 | X1: Q3 FY2025 | Y1: Q4 FY2025 | Z1: Q1 FY2026E | AA1: Q2 FY2026E | AB1: Q3 FY2026E | AC1: Q4 FY2026E | AD1: Q1 FY2027E | AE1: Q2 FY2027E | AF1: Q3 FY2027E | AG1: Q4 FY2027E | AH1: Q1 FY2028E | AI1: Q2 FY2028E | AJ1: Q3 FY2028E | AK1: Q4 FY2028E | AL1: Q1 FY2029E | AM1: Q2 FY2029E | AN1: Q3 FY2029E | AO1: Q4 FY2029E | AP1: Q1 FY2030E | AQ1: Q2 FY2030E | AR1: Q3 FY2030E | AS1: Q4 FY2030E
A2: Net Income (Loss) | B2: ='YTD CF'!B2 -> 278835 | C2: ='YTD CF'!C2-'YTD CF'!B2 -> 311369 | D2: ='YTD CF'!D2-'YTD CF'!C2 -> 347654 | E2: ='CASH FLOW'!C2-'YTD CF'!D2 -> 471736 | F2: ='YTD CF'!E2 -> 315194 | G2: ='YTD CF'!F2-'YTD CF'!E2 -> 403762 | H2: ='YTD CF'!G2-'YTD CF'!F2 -> 337205 | I2: ='CASH FLOW'!D2-'YTD CF'!G2 -> 321314 | J2: ='YTD CF'!H2 -> 294203 | K2: ='YTD CF'!I2-'YTD CF'!H2 -> 273360 | L2: ='YTD CF'!J2-'YTD CF'!I2 -> 322387 | M2: ='CASH FLOW'!E2-'YTD CF'!J2 -> 301674 | N2: ='YTD CF'!K2 -> 397444 | O2: ='YTD CF'!L2-'YTD CF'!K2 -> 413871 | P2: ='YTD CF'!M2-'YTD CF'!L2 -> 452694 | Q2: ='CASH FLOW'!F2-'YTD CF'!M2 -> 366979 | R2: ='YTD CF'!N2 -> 442049 | S2: ='YTD CF'!O2-'YTD CF'!N2 -> 425369 | T2: ='YTD CF'!P2-'YTD CF'!O2 -> 370919 | U2: ='CASH FLOW'!G2-'YTD CF'!P2 -> 270711 | V2: ='YTD CF'!Q2 -> 442993 | W2: ='YTD CF'!R2-'YTD CF'!Q2 -> 488794 | X2: ='YTD CF'!S2-'YTD CF'!R2 -> 524455 | Y2: ='CASH FLOW'!H2-'YTD CF'!S2 -> 449190 | Z2: ='CF DRIVERS'!Z2 -> 459253.85 | AA2: ='CF DRIVERS'!AA2 -> 520094.22 | AB2: ='CF DRIVERS'!AB2 -> 540343.58 | AC2: ='CF DRIVERS'!AC2 -> 524700.68 | AD2: ='CF DRIVERS'!AD2 -> 536536.27 | AE2: ='CF DRIVERS'!AE2 -> 608087.68 | AF2: ='CF DRIVERS'!AF2 -> 631901.95 | AG2: ='CF DRIVERS'!AG2 -> 613505.1 | ... AS2: ='CF DRIVERS'!AS2 -> 985217.31
A3: Depreciation & Amortization | B3: ='YTD CF'!B3 -> 16546 | C3: ='YTD CF'!C3-'YTD CF'!B3 -> 15511 | D3: ='YTD CF'!D3-'YTD CF'!C3 -> 13822 | E3: ='CASH FLOW'!C3-'YTD CF'!D3 -> 11151 | F3: ='YTD CF'!E3 -> 13777 | G3: ='YTD CF'!F3-'YTD CF'!E3 -> 13712 | H3: ='YTD CF'!G3-'YTD CF'!F3 -> 13227 | I3: ='CASH FLOW'!D3-'YTD CF'!G3 -> 9439 | J3: ='YTD CF'!H3 -> 14599 | K3: ='YTD CF'!I3-'YTD CF'!H3 -> 15833 | L3: ='YTD CF'!J3-'YTD CF'!I3 -> 15608 | M3: ='CASH FLOW'!E3-'YTD CF'!J3 -> 15201 | N3: ='YTD CF'!K3 -> 16808 | O3: ='YTD CF'!L3-'YTD CF'!K3 -> 15576 | P3: ='YTD CF'!M3-'YTD CF'!L3 -> 17980 | Q3: ='CASH FLOW'!F3-'YTD CF'!M3 -> 18534 | R3: ='YTD CF'!N3 -> 20475 | S3: ='YTD CF'!O3-'YTD CF'!N3 -> 19438 | T3: ='YTD CF'!P3-'YTD CF'!O3 -> 19909 | U3: ='CASH FLOW'!G3-'YTD CF'!P3 -> 20612 | V3: ='YTD CF'!Q3 -> 24848 | W3: ='YTD CF'!R3-'YTD CF'!Q3 -> 27557 | X3: ='YTD CF'!S3-'YTD CF'!R3 -> 29618 | Y3: ='CASH FLOW'!H3-'YTD CF'!S3 -> 32418 | Z3: ='QTR P&L'!Z2*'CF DRIVERS'!Z3 -> 33178.643 | AA3: ='QTR P&L'!AA2*'CF DRIVERS'!AA3 -> 37777.064 | AB3: ='QTR P&L'!AB2*'CF DRIVERS'!AB3 -> 39307.546 | AC3: ='QTR P&L'!AC2*'CF DRIVERS'!AC3 -> 38125.228 | AD3: ='QTR P&L'!AD2*'CF DRIVERS'!AD3 -> 39019.783 | AE3: ='QTR P&L'!AE2*'CF DRIVERS'!AE3 -> 44427.762 | AF3: ='QTR P&L'!AF2*'CF DRIVERS'!AF3 -> 46227.687 | AG3: ='QTR P&L'!AG2*'CF DRIVERS'!AG3 -> 44837.22 | ... AS3: ='QTR P&L'!AS2*'CF DRIVERS'!AS3 -> 72931.874
A4: Non-Cash Lease Expense | B4: ='YTD CF'!B4 -> 0 | C4: ='YTD CF'!C4-'YTD CF'!B4 -> 0 | D4: ='YTD CF'!D4-'YTD CF'!C4 -> 0 | E4: ='CASH FLOW'!C4-'YTD CF'!D4 -> 3943 | F4: ='YTD CF'!E4 -> 0 | G4: ='YTD CF'!F4-'YTD CF'!E4 -> 0 | H4: ='YTD CF'!G4-'YTD CF'!F4 -> 0 | I4: ='CASH FLOW'!D4-'YTD CF'!G4 -> 4107 | J4: ='YTD CF'!H4 -> 1481 | K4: ='YTD CF'!I4-'YTD CF'!H4 -> 1741 | L4: ='YTD CF'!J4-'YTD CF'!I4 -> 1958 | M4: ='CASH FLOW'!E4-'YTD CF'!J4 -> 2157 | N4: ='YTD CF'!K4 -> 2160 | O4: ='YTD CF'!L4-'YTD CF'!K4 -> 668 | P4: ='YTD CF'!M4-'YTD CF'!L4 -> 3643 | Q4: ='CASH FLOW'!F4-'YTD CF'!M4 -> 2572 | R4: ='YTD CF'!N4 -> 3185 | S4: ='YTD CF'!O4-'YTD CF'!N4 -> 3414 | T4: ='YTD CF'!P4-'YTD CF'!O4 -> 3202 | U4: ='CASH FLOW'!G4-'YTD CF'!P4 -> 3720 | V4: ='YTD CF'!Q4 -> 4014 | W4: ='YTD CF'!R4-'YTD CF'!Q4 -> 2952 | X4: ='YTD CF'!S4-'YTD CF'!R4 -> 3300 | Y4: ='CASH FLOW'!H4-'YTD CF'!S4 -> 5132 | Z4: ='CF DRIVERS'!Z4 -> 0 | AA4: ='CF DRIVERS'!AA4 -> 0 | AB4: ='CF DRIVERS'!AB4 -> 0 | AC4: ='CF DRIVERS'!AC4 -> 0 | AD4: ='CF DRIVERS'!AD4 -> 0 | AE4: ='CF DRIVERS'!AE4 -> 0 | AF4: ='CF DRIVERS'!AF4 -> 0 | AG4: ='CF DRIVERS'!AG4 -> 0 | ... AS4: ='CF DRIVERS'!AS4 -> 0
A5: Gain (Loss) on Disposal of PP&E | B5: ='YTD CF'!B5 -> -58 | C5: ='YTD CF'!C5-'YTD CF'!B5 -> -121 | D5: ='YTD CF'!D5-'YTD CF'!C5 -> -31 | E5: ='CASH FLOW'!C5-'YTD CF'!D5 -> -140 | F5: ='YTD CF'!E5 -> -88 | G5: ='YTD CF'!F5-'YTD CF'!E5 -> -734 | H5: ='YTD CF'!G5-'YTD CF'!F5 -> -162 | I5: ='CASH FLOW'!D5-'YTD CF'!G5 -> -29 | J5: ='YTD CF'!H5 -> -6 | K5: ='YTD CF'!I5-'YTD CF'!H5 -> -63 | L5: ='YTD CF'!J5-'YTD CF'!I5 -> -184 | M5: ='CASH FLOW'!E5-'YTD CF'!J5 -> 68 | N5: ='YTD CF'!K5 -> -385 | O5: ='YTD CF'!L5-'YTD CF'!K5 -> -382 | P5: ='YTD CF'!M5-'YTD CF'!L5 -> 81 | Q5: ='CASH FLOW'!F5-'YTD CF'!M5 -> 852 | R5: ='YTD CF'!N5 -> -177 | S5: ='YTD CF'!O5-'YTD CF'!N5 -> 2026 | T5: ='YTD CF'!P5-'YTD CF'!O5 -> 221 | U5: ='CASH FLOW'!G5-'YTD CF'!P5 -> 1258 | V5: ='YTD CF'!Q5 -> 324 | W5: ='YTD CF'!R5-'YTD CF'!Q5 -> -965 | X5: ='YTD CF'!S5-'YTD CF'!R5 -> -275 | Y5: ='CASH FLOW'!H5-'YTD CF'!S5 -> 3697 | Z5: ='CF DRIVERS'!Z5 -> 0 | AA5: ='CF DRIVERS'!AA5 -> 0 | AB5: ='CF DRIVERS'!AB5 -> 0 | AC5: ='CF DRIVERS'!AC5 -> 0 | AD5: ='CF DRIVERS'!AD5 -> 0 | AE5: ='CF DRIVERS'!AE5 -> 0 | AF5: ='CF DRIVERS'!AF5 -> 0 | AG5: ='CF DRIVERS'!AG5 -> 0 | ... AS5: ='CF DRIVERS'!AS5 -> 0
A6: Gain on Bang Transaction | B6: ='YTD CF'!B6 -> 0 | C6: ='YTD CF'!C6-'YTD CF'!B6 -> 0 | D6: ='YTD CF'!D6-'YTD CF'!C6 -> 0 | E6: ='CASH FLOW'!C6-'YTD CF'!D6 -> 0 | F6: ='YTD CF'!E6 -> 0 | G6: ='YTD CF'!F6-'YTD CF'!E6 -> 0 | H6: ='YTD CF'!G6-'YTD CF'!F6 -> 0 | I6: ='CASH FLOW'!D6-'YTD CF'!G6 -> 0 | J6: ='YTD CF'!H6 -> 0 | K6: ='YTD CF'!I6-'YTD CF'!H6 -> 0 | L6: ='YTD CF'!J6-'YTD CF'!I6 -> 0 | M6: ='CASH FLOW'!E6-'YTD CF'!J6 -> 0 | N6: ='YTD CF'!K6 -> 0 | O6: ='YTD CF'!L6-'YTD CF'!K6 -> 0 | P6: ='YTD CF'!M6-'YTD CF'!L6 -> -45382 | Q6: ='CASH FLOW'!F6-'YTD CF'!M6 -> 0 | R6: ='YTD CF'!N6 -> 0 | S6: ='YTD CF'!O6-'YTD CF'!N6 -> 0 | T6: ='YTD CF'!P6-'YTD CF'!O6 -> 0 | U6: ='CASH FLOW'!G6-'YTD CF'!P6 -> 0 | V6: ='YTD CF'!Q6 -> 0 | W6: ='YTD CF'!R6-'YTD CF'!Q6 -> 0 | X6: ='YTD CF'!S6-'YTD CF'!R6 -> 0 | Y6: ='CASH FLOW'!H6-'YTD CF'!S6 -> 0 | Z6: ='CF DRIVERS'!Z6 -> 0 | AA6: ='CF DRIVERS'!AA6 -> 0 | AB6: ='CF DRIVERS'!AB6 -> 0 | AC6: ='CF DRIVERS'!AC6 -> 0 | AD6: ='CF DRIVERS'!AD6 -> 0 | AE6: ='CF DRIVERS'!AE6 -> 0 | AF6: ='CF DRIVERS'!AF6 -> 0 | AG6: ='CF DRIVERS'!AG6 -> 0 | ... AS6: ='CF DRIVERS'!AS6 -> 0
A7: Impairment of Intangibles | B7: ='YTD CF'!B7 -> 3000 | C7: ='YTD CF'!C7-'YTD CF'!B7 -> 1000 | D7: ='YTD CF'!D7-'YTD CF'!C7 -> 3000 | E7: ='CASH FLOW'!C7-'YTD CF'!D7 -> 1700 | F7: ='YTD CF'!E7 -> 0 | G7: ='YTD CF'!F7-'YTD CF'!E7 -> 0 | H7: ='YTD CF'!G7-'YTD CF'!F7 -> 0 | I7: ='CASH FLOW'!D7-'YTD CF'!G7 -> 0 | J7: ='YTD CF'!H7 -> 0 | K7: ='YTD CF'!I7-'YTD CF'!H7 -> 0 | L7: ='YTD CF'!J7-'YTD CF'!I7 -> 0 | M7: ='CASH FLOW'!E7-'YTD CF'!J7 -> 2200 | N7: ='YTD CF'!K7 -> 0 | O7: ='YTD CF'!L7-'YTD CF'!K7 -> 2800 | P7: ='YTD CF'!M7-'YTD CF'!L7 -> 0 | Q7: ='CASH FLOW'!F7-'YTD CF'!M7 -> 35900 | R7: ='YTD CF'!N7 -> 0 | S7: ='YTD CF'!O7-'YTD CF'!N7 -> 0 | T7: ='YTD CF'!P7-'YTD CF'!O7 -> 0 | U7: ='CASH FLOW'!G7-'YTD CF'!P7 -> 127098 | V7: ='YTD CF'!Q7 -> 0 | W7: ='YTD CF'!R7-'YTD CF'!Q7 -> 0 | X7: ='YTD CF'!S7-'YTD CF'!R7 -> 0 | Y7: ='CASH FLOW'!H7-'YTD CF'!S7 -> 38411 | Z7: ='CF DRIVERS'!Z7 -> 0 | AA7: ='CF DRIVERS'!AA7 -> 0 | AB7: ='CF DRIVERS'!AB7 -> 0 | AC7: ='CF DRIVERS'!AC7 -> 0 | AD7: ='CF DRIVERS'!AD7 -> 0 | AE7: ='CF DRIVERS'!AE7 -> 0 | AF7: ='CF DRIVERS'!AF7 -> 0 | AG7: ='CF DRIVERS'!AG7 -> 0 | ... AS7: ='CF DRIVERS'!AS7 -> 0
A8: Impairment of Long-Lived Assets (PP&E) | B8: ='YTD CF'!B8 -> 0 | C8: ='YTD CF'!C8-'YTD CF'!B8 -> 0 | D8: ='YTD CF'!D8-'YTD CF'!C8 -> 0 | E8: ='CASH FLOW'!C8-'YTD CF'!D8 -> 0 | F8: ='YTD CF'!E8 -> 0 | G8: ='YTD CF'!F8-'YTD CF'!E8 -> 0 | H8: ='YTD CF'!G8-'YTD CF'!F8 -> 0 | I8: ='CASH FLOW'!D8-'YTD CF'!G8 -> 0 | J8: ='YTD CF'!H8 -> 0 | K8: ='YTD CF'!I8-'YTD CF'!H8 -> 0 | L8: ='YTD CF'!J8-'YTD CF'!I8 -> 0 | M8: ='CASH FLOW'!E8-'YTD CF'!J8 -> 0 | N8: ='YTD CF'!K8 -> 0 | O8: ='YTD CF'!L8-'YTD CF'!K8 -> 0 | P8: ='YTD CF'!M8-'YTD CF'!L8 -> 0 | Q8: ='CASH FLOW'!F8-'YTD CF'!M8 -> 4336 | R8: ='YTD CF'!N8 -> 0 | S8: ='YTD CF'!O8-'YTD CF'!N8 -> 6067 | T8: ='YTD CF'!P8-'YTD CF'!O8 -> 0 | U8: ='CASH FLOW'!G8-'YTD CF'!P8 -> 2117 | V8: ='YTD CF'!Q8 -> 2279 | W8: ='YTD CF'!R8-'YTD CF'!Q8 -> 0 | X8: ='YTD CF'!S8-'YTD CF'!R8 -> 0 | Y8: ='CASH FLOW'!H8-'YTD CF'!S8 -> 9750 | Z8: ='CF DRIVERS'!Z8 -> 0 | AA8: ='CF DRIVERS'!AA8 -> 0 | AB8: ='CF DRIVERS'!AB8 -> 0 | AC8: ='CF DRIVERS'!AC8 -> 0 | AD8: ='CF DRIVERS'!AD8 -> 0 | AE8: ='CF DRIVERS'!AE8 -> 0 | AF8: ='CF DRIVERS'!AF8 -> 0 | AG8: ='CF DRIVERS'!AG8 -> 0 | ... AS8: ='CF DRIVERS'!AS8 -> 0
A9: Stock-Based Compensation | B9: ='YTD CF'!B9 -> 17098 | C9: ='YTD CF'!C9-'YTD CF'!B9 -> 15936 | D9: ='YTD CF'!D9-'YTD CF'!C9 -> 20008 | E9: ='CASH FLOW'!C9-'YTD CF'!D9 -> 17247 | F9: ='YTD CF'!E9 -> 18362 | G9: ='YTD CF'!F9-'YTD CF'!E9 -> 17329 | H9: ='YTD CF'!G9-'YTD CF'!F9 -> 16700 | I9: ='CASH FLOW'!D9-'YTD CF'!G9 -> 18092 | J9: ='YTD CF'!H9 -> 16332 | K9: ='YTD CF'!I9-'YTD CF'!H9 -> 16277 | L9: ='YTD CF'!J9-'YTD CF'!I9 -> 16558 | M9: ='CASH FLOW'!E9-'YTD CF'!J9 -> 14942 | N9: ='YTD CF'!K9 -> 16051 | O9: ='YTD CF'!L9-'YTD CF'!K9 -> 18552 | P9: ='YTD CF'!M9-'YTD CF'!L9 -> 17862 | Q9: ='CASH FLOW'!F9-'YTD CF'!M9 -> 16371 | R9: ='YTD CF'!N9 -> 22472 | S9: ='YTD CF'!O9-'YTD CF'!N9 -> 18790 | T9: ='YTD CF'!P9-'YTD CF'!O9 -> 27531 | U9: ='CASH FLOW'!G9-'YTD CF'!P9 -> 22192 | V9: ='YTD CF'!Q9 -> 20727 | W9: ='YTD CF'!R9-'YTD CF'!Q9 -> 33127 | X9: ='YTD CF'!S9-'YTD CF'!R9 -> 32810 | Y9: ='CASH FLOW'!H9-'YTD CF'!S9 -> 39023 | Z9: ='QTR P&L'!Z2*'CF DRIVERS'!Z9 -> 39938.62 | AA9: ='QTR P&L'!AA2*'CF DRIVERS'!AA9 -> 45473.946 | AB9: ='QTR P&L'!AB2*'CF DRIVERS'!AB9 -> 47316.255 | AC9: ='QTR P&L'!AC2*'CF DRIVERS'!AC9 -> 45893.046 | AD9: ='QTR P&L'!AD2*'CF DRIVERS'!AD9 -> 46969.862 | AE9: ='QTR P&L'!AE2*'CF DRIVERS'!AE9 -> 53479.689 | AF9: ='QTR P&L'!AF2*'CF DRIVERS'!AF9 -> 55646.339 | AG9: ='QTR P&L'!AG2*'CF DRIVERS'!AG9 -> 53972.572 | ... AS9: ='QTR P&L'!AS2*'CF DRIVERS'!AS9 -> 87791.366
A10: (Benefit) Provision for Deferred Income Taxes | B10: ='YTD CF'!B10 -> 0 | C10: ='YTD CF'!C10-'YTD CF'!B10 -> 0 | D10: ='YTD CF'!D10-'YTD CF'!C10 -> 0 | E10: ='CASH FLOW'!C10-'YTD CF'!D10 -> -156873 | F10: ='YTD CF'!E10 -> 0 | G10: ='YTD CF'!F10-'YTD CF'!E10 -> 353 | H10: ='YTD CF'!G10-'YTD CF'!F10 -> 0 | I10: ='CASH FLOW'!D10-'YTD CF'!G10 -> 16076 | J10: ='YTD CF'!H10 -> 0 | K10: ='YTD CF'!I10-'YTD CF'!H10 -> 21934 | L10: ='YTD CF'!J10-'YTD CF'!I10 -> 7776 | M10: ='CASH FLOW'!E10-'YTD CF'!J10 -> 18472 | N10: ='YTD CF'!K10 -> 0 | O10: ='YTD CF'!L10-'YTD CF'!K10 -> 0 | P10: ='YTD CF'!M10-'YTD CF'!L10 -> 0 | Q10: ='CASH FLOW'!F10-'YTD CF'!M10 -> 2040 | R10: ='YTD CF'!N10 -> 9 | S10: ='YTD CF'!O10-'YTD CF'!N10 -> -13303 | T10: ='YTD CF'!P10-'YTD CF'!O10 -> 3052 | U10: ='CASH FLOW'!G10-'YTD CF'!P10 -> -1463 | V10: ='YTD CF'!Q10 -> 135 | W10: ='YTD CF'!R10-'YTD CF'!Q10 -> 511 | X10: ='YTD CF'!S10-'YTD CF'!R10 -> -191 | Y10: ='CASH FLOW'!H10-'YTD CF'!S10 -> 3755 | Z10: ='CF DRIVERS'!Z10 -> 3755 | AA10: ='CF DRIVERS'!AA10 -> 3755 | AB10: ='CF DRIVERS'!AB10 -> 3755 | AC10: ='CF DRIVERS'!AC10 -> 3755 | AD10: ='CF DRIVERS'!AD10 -> 3755 | AE10: ='CF DRIVERS'!AE10 -> 3755 | AF10: ='CF DRIVERS'!AF10 -> 3755 | AG10: ='CF DRIVERS'!AG10 -> 3755 | ... AS10: ='CF DRIVERS'!AS10 -> 3755
A11: Accounts Receivable | B11: ='YTD CF'!B11 -> -147660 | C11: ='YTD CF'!C11-'YTD CF'!B11 -> -84122 | D11: ='YTD CF'!D11-'YTD CF'!C11 -> 30105 | E11: ='CASH FLOW'!C11-'YTD CF'!D11 -> 82005 | F11: ='YTD CF'!E11 -> -147544 | G11: ='YTD CF'!F11-'YTD CF'!E11 -> -92156 | H11: ='YTD CF'!G11-'YTD CF'!F11 -> 39991 | I11: ='CASH FLOW'!D11-'YTD CF'!G11 -> -54519 | J11: ='YTD CF'!H11 -> -134433 | K11: ='YTD CF'!I11-'YTD CF'!H11 -> -154803 | L11: ='YTD CF'!J11-'YTD CF'!I11 -> 86789 | M11: ='CASH FLOW'!E11-'YTD CF'!J11 -> 73466 | N11: ='YTD CF'!K11 -> -167512 | O11: ='YTD CF'!L11-'YTD CF'!K11 -> -150296 | P11: ='YTD CF'!M11-'YTD CF'!L11 -> 99004 | Q11: ='CASH FLOW'!F11-'YTD CF'!M11 -> 55646 | R11: ='YTD CF'!N11 -> -195081 | S11: ='YTD CF'!O11-'YTD CF'!N11 -> -2146 | T11: ='YTD CF'!P11-'YTD CF'!O11 -> 90823 | U11: ='CASH FLOW'!G11-'YTD CF'!P11 -> 12489 | V11: ='YTD CF'!Q11 -> -109557 | W11: ='YTD CF'!R11-'YTD CF'!Q11 -> -112682 | X11: ='YTD CF'!S11-'YTD CF'!R11 -> -76900 | Y11: ='CASH FLOW'!H11-'YTD CF'!S11 -> -1461 | Z11: ='CF DRIVERS'!Z11 -> -37965.79 | AA11: ='CF DRIVERS'!AA11 -> -229519.93 | AB11: ='CF DRIVERS'!AB11 -> -76390.558 | AC11: ='CF DRIVERS'!AC11 -> 59012.751 | AD11: ='CF DRIVERS'!AD11 -> -44649.712 | AE11: ='CF DRIVERS'!AE11 -> -269927.19 | AF11: ='CF DRIVERS'!AF11 -> -89839.208 | AG11: ='CF DRIVERS'!AG11 -> 69402.017 | ... AS11: ='CF DRIVERS'!AS11 -> 112888.78
A12: Distributor Receivables | B12: ='YTD CF'!B12 -> 176 | C12: ='YTD CF'!C12-'YTD CF'!B12 -> 12 | D12: ='YTD CF'!D12-'YTD CF'!C12 -> 153 | F12: ='YTD CF'!E12 -> 92 | G12: ='YTD CF'!F12-'YTD CF'!E12 -> 68 | H12: ='YTD CF'!G12-'YTD CF'!F12 -> 68 | J12: ='YTD CF'!H12 -> 0 | K12: ='YTD CF'!I12-'YTD CF'!H12 -> 0 | L12: ='YTD CF'!J12-'YTD CF'!I12 -> 0 | N12: ='YTD CF'!K12 -> 0 | O12: ='YTD CF'!L12-'YTD CF'!K12 -> 0 | P12: ='YTD CF'!M12-'YTD CF'!L12 -> 0 | R12: ='YTD CF'!N12 -> 0 | S12: ='YTD CF'!O12-'YTD CF'!N12 -> 0 | T12: ='YTD CF'!P12-'YTD CF'!O12 -> 0 | V12: ='YTD CF'!Q12 -> 0 | W12: ='YTD CF'!R12-'YTD CF'!Q12 -> 0 | X12: ='YTD CF'!S12-'YTD CF'!R12 -> 0 | Z12: ='CF DRIVERS'!Z12 -> 0 | AA12: ='CF DRIVERS'!AA12 -> 0 | AB12: ='CF DRIVERS'!AB12 -> 0 | AC12: ='CF DRIVERS'!AC12 -> 0 | AD12: ='CF DRIVERS'!AD12 -> 0 | AE12: ='CF DRIVERS'!AE12 -> 0 | AF12: ='CF DRIVERS'!AF12 -> 0 | AG12: ='CF DRIVERS'!AG12 -> 0 | ... AS12: ='CF DRIVERS'!AS12 -> 0
A13: Inventories | B13: ='YTD CF'!B13 -> 1037 | C13: ='YTD CF'!C13-'YTD CF'!B13 -> 13144 | D13: ='YTD CF'!D13-'YTD CF'!C13 -> 25309 | E13: ='CASH FLOW'!C12-'YTD CF'!D13 -> -9186 | F13: ='YTD CF'!E13 -> -39546 | G13: ='YTD CF'!F13-'YTD CF'!E13 -> -12995 | H13: ='YTD CF'!G13-'YTD CF'!F13 -> -96873 | I13: ='CASH FLOW'!D12-'YTD CF'!G13 -> -128379 | J13: ='YTD CF'!H13 -> -208673 | K13: ='YTD CF'!I13-'YTD CF'!H13 -> -90403 | L13: ='YTD CF'!J13-'YTD CF'!I13 -> 1936 | M13: ='CASH FLOW'!E12-'YTD CF'!J13 -> -50572 | N13: ='YTD CF'!K13 -> 35495 | O13: ='YTD CF'!L13-'YTD CF'!K13 -> 57582 | P13: ='YTD CF'!M13-'YTD CF'!L13 -> -23281 | Q13: ='CASH FLOW'!F12-'YTD CF'!M13 -> -61898 | R13: ='YTD CF'!N13 -> 22708 | S13: ='YTD CF'!O13-'YTD CF'!N13 -> 100776 | T13: ='YTD CF'!P13-'YTD CF'!O13 -> 73623 | U13: ='CASH FLOW'!G12-'YTD CF'!P13 -> 14396 | V13: ='YTD CF'!Q13 -> 19594 | W13: ='YTD CF'!R13-'YTD CF'!Q13 -> 85039 | X13: ='YTD CF'!S13-'YTD CF'!R13 -> -46246 | Y13: ='CASH FLOW'!H12-'YTD CF'!S13 -> -93305 | Z13: ='CF DRIVERS'!Z13 -> -18762.032 | AA13: ='CF DRIVERS'!AA13 -> -113424.75 | AB13: ='CF DRIVERS'!AB13 -> -37750.883 | AC13: ='CF DRIVERS'!AC13 -> 29163.074 | AD13: ='CF DRIVERS'!AD13 -> -22065.11 | AE13: ='CF DRIVERS'!AE13 -> -133393.31 | AF13: ='CF DRIVERS'!AF13 -> -44396.972 | AG13: ='CF DRIVERS'!AG13 -> 34297.268 | ... AS13: ='CF DRIVERS'!AS13 -> 55787.669
A14: Prepaid Expenses | B14: ='YTD CF'!B14 -> -18081 | C14: ='YTD CF'!C14-'YTD CF'!B14 -> -5313 | D14: ='YTD CF'!D14-'YTD CF'!C14 -> 2948 | E14: ='CASH FLOW'!C13-'YTD CF'!D14 -> 21470 | F14: ='YTD CF'!E14 -> -18487 | G14: ='YTD CF'!F14-'YTD CF'!E14 -> -9745 | H14: ='YTD CF'!G14-'YTD CF'!F14 -> -12930 | I14: ='CASH FLOW'!D13-'YTD CF'!G14 -> 11821 | J14: ='YTD CF'!H14 -> -29621 | K14: ='YTD CF'!I14-'YTD CF'!H14 -> -26042 | L14: ='YTD CF'!J14-'YTD CF'!I14 -> 16459 | M14: ='CASH FLOW'!E13-'YTD CF'!J14 -> 936 | N14: ='YTD CF'!K14 -> 1273 | O14: ='YTD CF'!L14-'YTD CF'!K14 -> -38052 | P14: ='YTD CF'!M14-'YTD CF'!L14 -> -30589 | Q14: ='CASH FLOW'!F13-'YTD CF'!M14 -> 57153 | R14: ='YTD CF'!N14 -> -9507 | S14: ='YTD CF'!O14-'YTD CF'!N14 -> -4486 | T14: ='YTD CF'!P14-'YTD CF'!O14 -> 8132 | U14: ='CASH FLOW'!G13-'YTD CF'!P14 -> 14820 | V14: ='YTD CF'!Q14 -> -3995 | W14: ='YTD CF'!R14-'YTD CF'!Q14 -> -59680 | X14: ='YTD CF'!S14-'YTD CF'!R14 -> -2594 | Y14: ='CASH FLOW'!H13-'YTD CF'!S14 -> 26962 | Z14: ='CF DRIVERS'!Z14 -> -2429.6789 | AA14: ='CF DRIVERS'!AA14 -> -14688.48 | AB14: ='CF DRIVERS'!AB14 -> -4888.731 | AC14: ='CF DRIVERS'!AC14 -> 3776.6115 | AD14: ='CF DRIVERS'!AD14 -> -2857.4269 | AE14: ='CF DRIVERS'!AE14 -> -17274.404 | AF14: ='CF DRIVERS'!AF14 -> -5749.3979 | AG14: ='CF DRIVERS'!AG14 -> 4441.4885 | ... AS14: ='CF DRIVERS'!AS14 -> 7224.4907
A15: Change in Prepaid Income Taxes | B15: ='YTD CF'!B15 -> 8078 | C15: ='YTD CF'!C15-'YTD CF'!B15 -> -833 | D15: ='YTD CF'!D15-'YTD CF'!C15 -> 4215 | E15: ='CASH FLOW'!C14-'YTD CF'!D15 -> -5944 | F15: ='YTD CF'!E15 -> -7076 | G15: ='YTD CF'!F15-'YTD CF'!E15 -> 9528 | H15: ='YTD CF'!G15-'YTD CF'!F15 -> -9817 | I15: ='CASH FLOW'!D14-'YTD CF'!G15 -> -3554 | J15: ='YTD CF'!H15 -> -5885 | K15: ='YTD CF'!I15-'YTD CF'!H15 -> 4665 | L15: ='YTD CF'!J15-'YTD CF'!I15 -> 9087 | M15: ='CASH FLOW'!E14-'YTD CF'!J15 -> -12306 | N15: ='YTD CF'!K15 -> 3986 | O15: ='YTD CF'!L15-'YTD CF'!K15 -> -7331 | P15: ='YTD CF'!M15-'YTD CF'!L15 -> 11377 | Q15: ='CASH FLOW'!F14-'YTD CF'!M15 -> -26865 | R15: ='YTD CF'!N15 -> 11840 | S15: ='YTD CF'!O15-'YTD CF'!N15 -> -24137 | T15: ='YTD CF'!P15-'YTD CF'!O15 -> -27371 | U15: ='CASH FLOW'!G14-'YTD CF'!P15 -> 42730 | V15: ='YTD CF'!Q15 -> 11912 | W15: ='YTD CF'!R15-'YTD CF'!Q15 -> 2600 | X15: ='YTD CF'!S15-'YTD CF'!R15 -> -469 | Y15: ='CASH FLOW'!H14-'YTD CF'!S15 -> -35137 | Z15: ='CF DRIVERS'!Z15 -> -1751.2525 | AA15: ='CF DRIVERS'!AA15 -> -10587.093 | AB15: ='CF DRIVERS'!AB15 -> -3523.6764 | AC15: ='CF DRIVERS'!AC15 -> 2722.0882 | AD15: ='CF DRIVERS'!AD15 -> -2059.5626 | AE15: ='CF DRIVERS'!AE15 -> -12450.964 | AF15: ='CF DRIVERS'!AF15 -> -4144.0239 | AG15: ='CF DRIVERS'!AG15 -> 3201.3151 | ... AS15: ='CF DRIVERS'!AS15 -> 5207.2343
A16: Accounts Payable | B16: ='YTD CF'!B16 -> 19328 | C16: ='YTD CF'!C16-'YTD CF'!B16 -> -26100 | D16: ='YTD CF'!D16-'YTD CF'!C16 -> -2952 | E16: ='CASH FLOW'!C15-'YTD CF'!D16 -> 28420 | F16: ='YTD CF'!E16 -> 36859 | G16: ='YTD CF'!F16-'YTD CF'!E16 -> 26760 | H16: ='YTD CF'!G16-'YTD CF'!F16 -> 42951 | I16: ='CASH FLOW'!D15-'YTD CF'!G16 -> 7727 | J16: ='YTD CF'!H16 -> 18329 | K16: ='YTD CF'!I16-'YTD CF'!H16 -> 67170 | L16: ='YTD CF'!J16-'YTD CF'!I16 -> -32836 | M16: ='CASH FLOW'!E15-'YTD CF'!J16 -> -2898 | N16: ='YTD CF'!K16 -> 51124 | O16: ='YTD CF'!L16-'YTD CF'!K16 -> 81049 | P16: ='YTD CF'!M16-'YTD CF'!L16 -> -22350 | Q16: ='CASH FLOW'!F15-'YTD CF'!M16 -> 2963 | R16: ='YTD CF'!N16 -> -9062 | S16: ='YTD CF'!O16-'YTD CF'!N16 -> -24443 | T16: ='YTD CF'!P16-'YTD CF'!O16 -> 19159 | U16: ='CASH FLOW'!G15-'YTD CF'!P16 -> -47145 | V16: ='YTD CF'!Q16 -> 11768 | W16: ='YTD CF'!R16-'YTD CF'!Q16 -> -7435 | X16: ='YTD CF'!S16-'YTD CF'!R16 -> 144242 | Y16: ='CASH FLOW'!H15-'YTD CF'!S16 -> -70115 | Z16: ='CF DRIVERS'!Z16 -> 13279.786 | AA16: ='CF DRIVERS'!AA16 -> 80282.158 | AB16: ='CF DRIVERS'!AB16 -> 26720.115 | AC16: ='CF DRIVERS'!AC16 -> -20641.654 | AD16: ='CF DRIVERS'!AD16 -> 15617.708 | AE16: ='CF DRIVERS'!AE16 -> 94415.928 | AF16: ='CF DRIVERS'!AF16 -> 31424.223 | AG16: ='CF DRIVERS'!AG16 -> -24275.642 | ... AS16: ='CF DRIVERS'!AS16 -> -39486.571
A17: Accrued Expenses | B17: ='YTD CF'!B17 -> 34500 | C17: ='YTD CF'!C17-'YTD CF'!B17 -> -2809 | D17: ='YTD CF'!D17-'YTD CF'!C17 -> 21810 | E17: ='CASH FLOW'!C16-'YTD CF'!D17 -> -27388 | F17: ='YTD CF'!E17 -> 32441 | G17: ='YTD CF'!F17-'YTD CF'!E17 -> -2558 | H17: ='YTD CF'!G17-'YTD CF'!F17 -> 4202 | I17: ='CASH FLOW'!D16-'YTD CF'!G17 -> 37501 | J17: ='YTD CF'!H17 -> 20603 | K17: ='YTD CF'!I17-'YTD CF'!H17 -> -21392 | L17: ='YTD CF'!J17-'YTD CF'!I17 -> -1783 | M17: ='CASH FLOW'!E16-'YTD CF'!J17 -> -27847 | N17: ='YTD CF'!K17 -> 14207 | O17: ='YTD CF'!L17-'YTD CF'!K17 -> 6284 | P17: ='YTD CF'!M17-'YTD CF'!L17 -> 4206 | Q17: ='CASH FLOW'!F16-'YTD CF'!M17 -> -35090 | R17: ='YTD CF'!N17 -> 28259 | S17: ='YTD CF'!O17-'YTD CF'!N17 -> -25544 | T17: ='YTD CF'!P17-'YTD CF'!O17 -> 44034 | U17: ='CASH FLOW'!G16-'YTD CF'!P17 -> -28378 | V17: ='YTD CF'!Q17 -> 33661 | W17: ='YTD CF'!R17-'YTD CF'!Q17 -> -5151 | X17: ='YTD CF'!S17-'YTD CF'!R17 -> 70025 | Y17: ='CASH FLOW'!H16-'YTD CF'!S17 -> -17194 | Z17: ='CF DRIVERS'!Z17 -> 7181.8551 | AA17: ='CF DRIVERS'!AA17 -> 43417.479 | AB17: ='CF DRIVERS'!AB17 -> 14450.534 | AC17: ='CF DRIVERS'!AC17 -> -11163.235 | AD17: ='CF DRIVERS'!AD17 -> 8446.2294 | AE17: ='CF DRIVERS'!AE17 -> 51061.178 | AF17: ='CF DRIVERS'!AF17 -> 16994.568 | AG17: ='CF DRIVERS'!AG17 -> -13128.536 | ... AS17: ='CF DRIVERS'!AS17 -> -21354.774
A18: Accrued Promotional Allowance | B18: ='YTD CF'!B18 -> 9439 | C18: ='YTD CF'!C18-'YTD CF'!B18 -> -6360 | D18: ='YTD CF'!D18-'YTD CF'!C18 -> 28836 | E18: ='CASH FLOW'!C17-'YTD CF'!D18 -> -18153 | F18: ='YTD CF'!E18 -> 13965 | G18: ='YTD CF'!F18-'YTD CF'!E18 -> 28700 | H18: ='YTD CF'!G18-'YTD CF'!F18 -> 8357 | I18: ='CASH FLOW'!D17-'YTD CF'!G18 -> -19524 | J18: ='YTD CF'!H18 -> 61171 | K18: ='YTD CF'!I18-'YTD CF'!H18 -> 16575 | L18: ='YTD CF'!J18-'YTD CF'!I18 -> 11490 | M18: ='CASH FLOW'!E17-'YTD CF'!J18 -> -38415 | N18: ='YTD CF'!K18 -> 48265 | O18: ='YTD CF'!L18-'YTD CF'!K18 -> -24622 | P18: ='YTD CF'!M18-'YTD CF'!L18 -> 18782 | Q18: ='CASH FLOW'!F17-'YTD CF'!M18 -> -34007 | R18: ='YTD CF'!N18 -> 52814 | S18: ='YTD CF'!O18-'YTD CF'!N18 -> 1428 | T18: ='YTD CF'!P18-'YTD CF'!O18 -> -22750 | U18: ='CASH FLOW'!G17-'YTD CF'!P18 -> -21756 | V18: ='YTD CF'!Q18 -> 30785 | W18: ='YTD CF'!R18-'YTD CF'!Q18 -> 40731 | X18: ='YTD CF'!S18-'YTD CF'!R18 -> 34290 | Y18: ='CASH FLOW'!H17-'YTD CF'!S18 -> -7540 | Z18: ='CF DRIVERS'!Z18 -> 9011.6637 | AA18: ='CF DRIVERS'!AA18 -> 54479.478 | AB18: ='CF DRIVERS'!AB18 -> 18132.272 | AC18: ='CF DRIVERS'!AC18 -> -14007.428 | AD18: ='CF DRIVERS'!AD18 -> 10598.178 | AE18: ='CF DRIVERS'!AE18 -> 64070.656 | AF18: ='CF DRIVERS'!AF18 -> 21324.48 | AG18: ='CF DRIVERS'!AG18 -> -16473.453 | ... AS18: ='CF DRIVERS'!AS18 -> -26795.59
A19: Accrued Distributor Terminations | B19: ='YTD CF'!B19 -> -282 | C19: ='YTD CF'!C19-'YTD CF'!B19 -> 142 | D19: ='YTD CF'!D19-'YTD CF'!C19 -> -10 | F19: ='YTD CF'!E19 -> 0 | G19: ='YTD CF'!F19-'YTD CF'!E19 -> 0 | H19: ='YTD CF'!G19-'YTD CF'!F19 -> 5302 | J19: ='YTD CF'!H19 -> 0 | K19: ='YTD CF'!I19-'YTD CF'!H19 -> 0 | L19: ='YTD CF'!J19-'YTD CF'!I19 -> 0 | N19: ='YTD CF'!K19 -> 0 | O19: ='YTD CF'!L19-'YTD CF'!K19 -> 0 | P19: ='YTD CF'!M19-'YTD CF'!L19 -> 0 | R19: ='YTD CF'!N19 -> 0 | S19: ='YTD CF'!O19-'YTD CF'!N19 -> 0 | T19: ='YTD CF'!P19-'YTD CF'!O19 -> 0 | V19: ='YTD CF'!Q19 -> 0 | W19: ='YTD CF'!R19-'YTD CF'!Q19 -> 0 | X19: ='YTD CF'!S19-'YTD CF'!R19 -> 0 | Z19: ='CF DRIVERS'!Z19 -> 0 | AA19: ='CF DRIVERS'!AA19 -> 0 | AB19: ='CF DRIVERS'!AB19 -> 0 | AC19: ='CF DRIVERS'!AC19 -> 0 | AD19: ='CF DRIVERS'!AD19 -> 0 | AE19: ='CF DRIVERS'!AE19 -> 0 | AF19: ='CF DRIVERS'!AF19 -> 0 | AG19: ='CF DRIVERS'!AG19 -> 0 | ... AS19: ='CF DRIVERS'!AS19 -> 0
A20: Change in Accrued Compensation | B20: ='YTD CF'!B20 -> -24807 | C20: ='YTD CF'!C20-'YTD CF'!B20 -> 13875 | D20: ='YTD CF'!D20-'YTD CF'!C20 -> 9718 | E20: ='CASH FLOW'!C18-'YTD CF'!D20 -> 8715 | F20: ='YTD CF'!E20 -> -24443 | G20: ='YTD CF'!F20-'YTD CF'!E20 -> 13661 | H20: ='YTD CF'!G20-'YTD CF'!F20 -> 7894 | I20: ='CASH FLOW'!D18-'YTD CF'!G20 -> 10838 | J20: ='YTD CF'!H20 -> -32122 | K20: ='YTD CF'!I20-'YTD CF'!H20 -> 16811 | L20: ='YTD CF'!J20-'YTD CF'!I20 -> 8675 | M20: ='CASH FLOW'!E18-'YTD CF'!J20 -> 10365 | N20: ='YTD CF'!K20 -> -30261 | O20: ='YTD CF'!L20-'YTD CF'!K20 -> 12645 | P20: ='YTD CF'!M20-'YTD CF'!L20 -> 21139 | Q20: ='CASH FLOW'!F18-'YTD CF'!M20 -> 9875 | R20: ='YTD CF'!N20 -> -35653 | S20: ='YTD CF'!O20-'YTD CF'!N20 -> 8699 | T20: ='YTD CF'!P20-'YTD CF'!O20 -> 20911 | U20: ='CASH FLOW'!G18-'YTD CF'!P20 -> 11990 | V20: ='YTD CF'!Q20 -> -37338 | W20: ='YTD CF'!R20-'YTD CF'!Q20 -> 15192 | X20: ='YTD CF'!S20-'YTD CF'!R20 -> 28580 | Y20: ='CASH FLOW'!H18-'YTD CF'!S20 -> 11367 | Z20: ='CF DRIVERS'!Z20 -> 2675.3897 | AA20: ='CF DRIVERS'!AA20 -> 16173.91 | AB20: ='CF DRIVERS'!AB20 -> 5383.123 | AC20: ='CF DRIVERS'!AC20 -> -4158.5361 | AD20: ='CF DRIVERS'!AD20 -> 3146.3953 | AE20: ='CF DRIVERS'!AE20 -> 19021.346 | AF20: ='CF DRIVERS'!AF20 -> 6330.8283 | AG20: ='CF DRIVERS'!AG20 -> -4890.6514 | ... AS20: ='CF DRIVERS'!AS20 -> -7955.0956
A21: Other Current Liabilities | B21: ='YTD CF'!B21 -> -1552 | C21: ='YTD CF'!C21-'YTD CF'!B21 -> 9830 | D21: ='YTD CF'!D21-'YTD CF'!C21 -> 9691 | E21: ='CASH FLOW'!C19-'YTD CF'!D21 -> -7547 | F21: ='YTD CF'!E21 -> -13287 | G21: ='YTD CF'!F21-'YTD CF'!E21 -> 20983 | H21: ='YTD CF'!G21-'YTD CF'!F21 -> -7810 | I21: ='CASH FLOW'!D19-'YTD CF'!G21 -> 7335 | J21: ='YTD CF'!H21 -> -9818 | K21: ='YTD CF'!I21-'YTD CF'!H21 -> -4848 | L21: ='YTD CF'!J21-'YTD CF'!I21 -> 1843 | M21: ='CASH FLOW'!E19-'YTD CF'!J21 -> -4037 | N21: ='YTD CF'!K21 -> 41617 | O21: ='YTD CF'!L21-'YTD CF'!K21 -> -42836 | P21: ='YTD CF'!M21-'YTD CF'!L21 -> 5436 | Q21: ='CASH FLOW'!F19-'YTD CF'!M21 -> -2469 | R21: ='YTD CF'!N21 -> 60512 | S21: ='YTD CF'!O21-'YTD CF'!N21 -> -49164 | T21: ='YTD CF'!P21-'YTD CF'!O21 -> -7135 | U21: ='CASH FLOW'!G19-'YTD CF'!P21 -> 5225 | V21: ='YTD CF'!Q21 -> 61674 | W21: ='YTD CF'!R21-'YTD CF'!Q21 -> -40618 | X21: ='YTD CF'!S21-'YTD CF'!R21 -> 12305 | Y21: ='CASH FLOW'!H19-'YTD CF'!S21 -> -5582 | Z21: ='CF DRIVERS'!Z21 -> 0 | AA21: ='CF DRIVERS'!AA21 -> 0 | AB21: ='CF DRIVERS'!AB21 -> 0 | AC21: ='CF DRIVERS'!AC21 -> 0 | AD21: ='CF DRIVERS'!AD21 -> 0 | AE21: ='CF DRIVERS'!AE21 -> 0 | AF21: ='CF DRIVERS'!AF21 -> 0 | AG21: ='CF DRIVERS'!AG21 -> 0 | ... AS21: ='CF DRIVERS'!AS21 -> 0
A22: Net Change in Other Working Capital | B22: ='YTD CF'!B22 -> -192 | C22: ='YTD CF'!C22-'YTD CF'!B22 -> 275 | D22: ='YTD CF'!D22-'YTD CF'!C22 -> -645 | E22: ='CASH FLOW'!C20-'YTD CF'!D22 -> 206 | F22: ='YTD CF'!E22 -> 504 | G22: ='YTD CF'!F22-'YTD CF'!E22 -> 117 | H22: ='YTD CF'!G22-'YTD CF'!F22 -> -47 | I22: ='CASH FLOW'!D20-'YTD CF'!G22 -> -82 | J22: ='YTD CF'!H22 -> -596 | K22: ='YTD CF'!I22-'YTD CF'!H22 -> -2615 | L22: ='YTD CF'!J22-'YTD CF'!I22 -> -281 | M22: ='CASH FLOW'!E20-'YTD CF'!J22 -> -1048 | N22: ='YTD CF'!K22 -> -751 | O22: ='YTD CF'!L22-'YTD CF'!K22 -> 494 | P22: ='YTD CF'!M22-'YTD CF'!L22 -> -3379 | Q22: ='CASH FLOW'!F20-'YTD CF'!M22 -> 26587 | R22: ='YTD CF'!N22 -> 335 | S22: ='YTD CF'!O22-'YTD CF'!N22 -> -1798 | T22: ='YTD CF'!P22-'YTD CF'!O22 -> -940 | U22: ='CASH FLOW'!G20-'YTD CF'!P22 -> 15793 | V22: ='YTD CF'!Q22 -> -1885 | W22: ='YTD CF'!R22-'YTD CF'!Q22 -> 303 | X22: ='YTD CF'!S22-'YTD CF'!R22 -> -495 | Y22: ='CASH FLOW'!H20-'YTD CF'!S22 -> -2858 | Z22: ='CF DRIVERS'!Z22 -> 0 | AA22: ='CF DRIVERS'!AA22 -> 0 | AB22: ='CF DRIVERS'!AB22 -> 0 | AC22: ='CF DRIVERS'!AC22 -> 0 | AD22: ='CF DRIVERS'!AD22 -> 0 | AE22: ='CF DRIVERS'!AE22 -> 0 | AF22: ='CF DRIVERS'!AF22 -> 0 | AG22: ='CF DRIVERS'!AG22 -> 0 | ... AS22: ='CF DRIVERS'!AS22 -> 0
A23: Deferred Revenue | B23: ='YTD CF'!B23 -> -4273 | C23: ='YTD CF'!C23-'YTD CF'!B23 -> -6110 | D23: ='YTD CF'!D23-'YTD CF'!C23 -> -4853 | E23: ='CASH FLOW'!C21-'YTD CF'!D23 -> -6244 | F23: ='YTD CF'!E23 -> -5250 | G23: ='YTD CF'!F23-'YTD CF'!E23 -> -5672 | H23: ='YTD CF'!G23-'YTD CF'!F23 -> -6862 | I23: ='CASH FLOW'!D21-'YTD CF'!G23 -> -4874 | J23: ='YTD CF'!H23 -> -5915 | K23: ='YTD CF'!I23-'YTD CF'!H23 -> -3186 | L23: ='YTD CF'!J23-'YTD CF'!I23 -> -6959 | M23: ='CASH FLOW'!E21-'YTD CF'!J23 -> -3845 | N23: ='YTD CF'!K23 -> -5046 | O23: ='YTD CF'!L23-'YTD CF'!K23 -> -7315 | P23: ='YTD CF'!M23-'YTD CF'!L23 -> -6959 | Q23: ='CASH FLOW'!F21-'YTD CF'!M23 -> -5152 | R23: ='YTD CF'!N23 -> -3036 | S23: ='YTD CF'!O23-'YTD CF'!N23 -> -4695 | T23: ='YTD CF'!P23-'YTD CF'!O23 -> -4921 | U23: ='CASH FLOW'!G21-'YTD CF'!P23 -> -4708 | V23: ='YTD CF'!Q23 -> -4339 | W23: ='YTD CF'!R23-'YTD CF'!Q23 -> -4259 | X23: ='YTD CF'!S23-'YTD CF'!R23 -> -7309 | Y23: ='CASH FLOW'!H21-'YTD CF'!S23 -> -7098 | Z23: ='CF DRIVERS'!Z23 -> 0 | AA23: ='CF DRIVERS'!AA23 -> 0 | AB23: ='CF DRIVERS'!AB23 -> 0 | AC23: ='CF DRIVERS'!AC23 -> 0 | AD23: ='CF DRIVERS'!AD23 -> 0 | AE23: ='CF DRIVERS'!AE23 -> 0 | AF23: ='CF DRIVERS'!AF23 -> 0 | AG23: ='CF DRIVERS'!AG23 -> 0 | ... AS23: ='CF DRIVERS'!AS23 -> 0
A24: Cash Flow from Operations | B24: ='YTD CF'!B24 -> 191132 | C24: ='YTD CF'!C24-'YTD CF'!B24 -> 249326 | D24: ='YTD CF'!D24-'YTD CF'!C24 -> 508778 | E24: ='CASH FLOW'!C22-'YTD CF'!D24 -> 414927 | F24: ='YTD CF'!E24 -> 175473 | G24: ='YTD CF'!F24-'YTD CF'!E24 -> 411113 | H24: ='YTD CF'!G24-'YTD CF'!F24 -> 341396 | I24: ='CASH FLOW'!D22-'YTD CF'!G24 -> 227759 | J24: ='YTD CF'!H24 -> -351 | K24: ='YTD CF'!I24-'YTD CF'!H24 -> 131014 | L24: ='YTD CF'!J24-'YTD CF'!I24 -> 458523 | M24: ='CASH FLOW'!E22-'YTD CF'!J24 -> 298513 | N24: ='YTD CF'!K24 -> 424475 | O24: ='YTD CF'!L24-'YTD CF'!K24 -> 338687 | P24: ='YTD CF'!M24-'YTD CF'!L24 -> 520264 | Q24: ='CASH FLOW'!F22-'YTD CF'!M24 -> 434327 | R24: ='YTD CF'!N24 -> 412142 | S24: ='YTD CF'!O24-'YTD CF'!N24 -> 436291 | T24: ='YTD CF'!P24-'YTD CF'!O24 -> 618399 | U24: ='CASH FLOW'!G22-'YTD CF'!P24 -> 461701 | V24: ='YTD CF'!Q24 -> 507600 | W24: ='YTD CF'!R24-'YTD CF'!Q24 -> 466016 | X24: ='YTD CF'!S24-'YTD CF'!R24 -> 745146 | Y24: ='CASH FLOW'!H22-'YTD CF'!S24 -> 379415 | Z24: =SUM(Z2:Z23) -> 507366.05 | AA24: =SUM(AA2:AA23) -> 433233.01 | AB24: =SUM(AB2:AB23) -> 572854.58 | AC24: =SUM(AC2:AC23) -> 657177.62 | AD24: =SUM(AD2:AD23) -> 592457.62 | AE24: =SUM(AE2:AE23) -> 505273.37 | AF24: =SUM(AF2:AF23) -> 669475.48 | AG24: =SUM(AG2:AG23) -> 768643.7 | ... AS24: =SUM(AS2:AS23) -> 1235211.7
A25: Net Change in Long-Term Investments | B25: ='YTD CF'!B25 -> 298837 | C25: ='YTD CF'!C25-'YTD CF'!B25 -> -5194 | D25: ='YTD CF'!D25-'YTD CF'!C25 -> -347061 | E25: ='CASH FLOW'!C23-'YTD CF'!D25 -> -326367 | F25: ='YTD CF'!E25 -> -114819 | G25: ='YTD CF'!F25-'YTD CF'!E25 -> -19683 | H25: ='YTD CF'!G25-'YTD CF'!F25 -> -192293 | I25: ='CASH FLOW'!D23-'YTD CF'!G25 -> -597749 | J25: ='YTD CF'!H25 -> 62883 | K25: ='YTD CF'!I25-'YTD CF'!H25 -> 382557 | L25: ='YTD CF'!J25-'YTD CF'!I25 -> -15407 | M25: ='CASH FLOW'!E23-'YTD CF'!J25 -> -24745 | N25: ='YTD CF'!K25 -> 3750 | O25: ='YTD CF'!L25-'YTD CF'!K25 -> -57073 | P25: ='YTD CF'!M25-'YTD CF'!L25 -> 194128 | Q25: ='CASH FLOW'!F23-'YTD CF'!M25 -> 268214 | R25: ='YTD CF'!N25 -> 39897 | S25: ='YTD CF'!O25-'YTD CF'!N25 -> 995897 | T25: ='YTD CF'!P25-'YTD CF'!O25 -> 0 | U25: ='CASH FLOW'!G23-'YTD CF'!P25 -> 0 | V25: ='YTD CF'!Q25 -> 0 | W25: ='YTD CF'!R25-'YTD CF'!Q25 -> -283097 | X25: ='YTD CF'!S25-'YTD CF'!R25 -> -314606 | Y25: ='CASH FLOW'!H23-'YTD CF'!S25 -> -565447 | Z25: ='CF DRIVERS'!Z24 -> -11434.491 | AA25: ='CF DRIVERS'!AA24 -> -69126.539 | AB25: ='CF DRIVERS'!AB24 -> -23007.217 | AC25: ='CF DRIVERS'!AC24 -> 17773.39 | AD25: ='CF DRIVERS'!AD24 -> -13447.547 | AE25: ='CF DRIVERS'!AE24 -> -81296.349 | AF25: ='CF DRIVERS'!AF24 -> -27057.666 | AG25: ='CF DRIVERS'!AG24 -> 20902.417 | ... AS25: ='CF DRIVERS'!AS24 -> 33999.709
A26: Acquisition of CANarchy | B26: ='YTD CF'!B26 -> 0 | C26: ='YTD CF'!C26-'YTD CF'!B26 -> 0 | D26: ='YTD CF'!D26-'YTD CF'!C26 -> 0 | E26: ='CASH FLOW'!C24-'YTD CF'!D26 -> 0 | F26: ='YTD CF'!E26 -> 0 | G26: ='YTD CF'!F26-'YTD CF'!E26 -> 0 | H26: ='YTD CF'!G26-'YTD CF'!F26 -> 0 | I26: ='CASH FLOW'!D24-'YTD CF'!G26 -> 0 | J26: ='YTD CF'!H26 -> -330356 | K26: ='YTD CF'!I26-'YTD CF'!H26 -> 884 | L26: ='YTD CF'!J26-'YTD CF'!I26 -> 0 | M26: ='CASH FLOW'!E24-'YTD CF'!J26 -> 0 | N26: ='YTD CF'!K26 -> 0 | O26: ='YTD CF'!L26-'YTD CF'!K26 -> 0 | P26: ='YTD CF'!M26-'YTD CF'!L26 -> 0 | Q26: ='CASH FLOW'!F24-'YTD CF'!M26 -> 0 | R26: ='YTD CF'!N26 -> 0 | S26: ='YTD CF'!O26-'YTD CF'!N26 -> 0 | T26: ='YTD CF'!P26-'YTD CF'!O26 -> 0 | U26: ='CASH FLOW'!G24-'YTD CF'!P26 -> 0 | V26: ='YTD CF'!Q26 -> 0 | W26: ='YTD CF'!R26-'YTD CF'!Q26 -> 0 | X26: ='YTD CF'!S26-'YTD CF'!R26 -> 0 | Y26: ='CASH FLOW'!H24-'YTD CF'!S26 -> 0 | Z26: ='CF DRIVERS'!Z25 -> 0 | AA26: ='CF DRIVERS'!AA25 -> 0 | AB26: ='CF DRIVERS'!AB25 -> 0 | AC26: ='CF DRIVERS'!AC25 -> 0 | AD26: ='CF DRIVERS'!AD25 -> 0 | AE26: ='CF DRIVERS'!AE25 -> 0 | AF26: ='CF DRIVERS'!AF25 -> 0 | AG26: ='CF DRIVERS'!AG25 -> 0 | ... AS26: ='CF DRIVERS'!AS25 -> 0
A27: Acquisition of Monster Brewing | B27: ='YTD CF'!B27 -> 0 | C27: ='YTD CF'!C27-'YTD CF'!B27 -> 0 | D27: ='YTD CF'!D27-'YTD CF'!C27 -> 0 | E27: ='CASH FLOW'!C25-'YTD CF'!D27 -> 0 | F27: ='YTD CF'!E27 -> 0 | G27: ='YTD CF'!F27-'YTD CF'!E27 -> 0 | H27: ='YTD CF'!G27-'YTD CF'!F27 -> 0 | I27: ='CASH FLOW'!D25-'YTD CF'!G27 -> 0 | J27: ='YTD CF'!H27 -> 0 | K27: ='YTD CF'!I27-'YTD CF'!H27 -> 0 | L27: ='YTD CF'!J27-'YTD CF'!I27 -> 0 | M27: ='CASH FLOW'!E25-'YTD CF'!J27 -> 0 | N27: ='YTD CF'!K27 -> 0 | O27: ='YTD CF'!L27-'YTD CF'!K27 -> 0 | P27: ='YTD CF'!M27-'YTD CF'!L27 -> 0 | Q27: ='CASH FLOW'!F25-'YTD CF'!M27 -> 0 | R27: ='YTD CF'!N27 -> 0 | S27: ='YTD CF'!O27-'YTD CF'!N27 -> 0 | T27: ='YTD CF'!P27-'YTD CF'!O27 -> 0 | U27: ='CASH FLOW'!G25-'YTD CF'!P27 -> 0 | V27: ='YTD CF'!Q27 -> 0 | W27: ='YTD CF'!R27-'YTD CF'!Q27 -> 0 | X27: ='YTD CF'!S27-'YTD CF'!R27 -> 0 | Y27: ='CASH FLOW'!H25-'YTD CF'!S27 -> 0 | Z27: ='CF DRIVERS'!Z26 -> 0 | AA27: ='CF DRIVERS'!AA26 -> 0 | AB27: ='CF DRIVERS'!AB26 -> 0 | AC27: ='CF DRIVERS'!AC26 -> 0 | AD27: ='CF DRIVERS'!AD26 -> 0 | AE27: ='CF DRIVERS'!AE26 -> 0 | AF27: ='CF DRIVERS'!AF26 -> 0 | AG27: ='CF DRIVERS'!AG26 -> 0 | ... AS27: ='CF DRIVERS'!AS26 -> 0
A28: Acquisition of Bang Energy | B28: ='YTD CF'!B28 -> 0 | C28: ='YTD CF'!C28-'YTD CF'!B28 -> 0 | D28: ='YTD CF'!D28-'YTD CF'!C28 -> 0 | E28: ='CASH FLOW'!C26-'YTD CF'!D28 -> 0 | F28: ='YTD CF'!E28 -> 0 | G28: ='YTD CF'!F28-'YTD CF'!E28 -> 0 | H28: ='YTD CF'!G28-'YTD CF'!F28 -> 0 | I28: ='CASH FLOW'!D26-'YTD CF'!G28 -> 0 | J28: ='YTD CF'!H28 -> 0 | K28: ='YTD CF'!I28-'YTD CF'!H28 -> 0 | L28: ='YTD CF'!J28-'YTD CF'!I28 -> 0 | M28: ='CASH FLOW'!E26-'YTD CF'!J28 -> 0 | N28: ='YTD CF'!K28 -> 0 | O28: ='YTD CF'!L28-'YTD CF'!K28 -> 0 | P28: ='YTD CF'!M28-'YTD CF'!L28 -> -363385 | Q28: ='CASH FLOW'!F26-'YTD CF'!M28 -> 0 | R28: ='YTD CF'!N28 -> 0 | S28: ='YTD CF'!O28-'YTD CF'!N28 -> 0 | T28: ='YTD CF'!P28-'YTD CF'!O28 -> 0 | U28: ='CASH FLOW'!G26-'YTD CF'!P28 -> 0 | V28: ='YTD CF'!Q28 -> 0 | W28: ='YTD CF'!R28-'YTD CF'!Q28 -> 0 | X28: ='YTD CF'!S28-'YTD CF'!R28 -> 0 | Y28: ='CASH FLOW'!H26-'YTD CF'!S28 -> 0 | Z28: ='CF DRIVERS'!Z27 -> 0 | AA28: ='CF DRIVERS'!AA27 -> 0 | AB28: ='CF DRIVERS'!AB27 -> 0 | AC28: ='CF DRIVERS'!AC27 -> 0 | AD28: ='CF DRIVERS'!AD27 -> 0 | AE28: ='CF DRIVERS'!AE27 -> 0 | AF28: ='CF DRIVERS'!AF27 -> 0 | AG28: ='CF DRIVERS'!AG27 -> 0 | ... AS28: ='CF DRIVERS'!AS27 -> 0
A29: Purchase of PP&E | B29: ='YTD CF'!B29 -> -11119 | C29: ='YTD CF'!C29-'YTD CF'!B29 -> -17997 | D29: ='YTD CF'!D29-'YTD CF'!C29 -> -12946 | E29: ='CASH FLOW'!C27-'YTD CF'!D29 -> -6660 | F29: ='YTD CF'!E29 -> -8400 | G29: ='YTD CF'!F29-'YTD CF'!E29 -> -7122 | H29: ='YTD CF'!G29-'YTD CF'!F29 -> -12609 | I29: ='CASH FLOW'!D27-'YTD CF'!G29 -> -15737 | J29: ='YTD CF'!H29 -> -21511 | K29: ='YTD CF'!I29-'YTD CF'!H29 -> -77935 | L29: ='YTD CF'!J29-'YTD CF'!I29 -> -36712 | M29: ='CASH FLOW'!E27-'YTD CF'!J29 -> -52568 | N29: ='YTD CF'!K29 -> -40100 | O29: ='YTD CF'!L29-'YTD CF'!K29 -> -42325 | P29: ='YTD CF'!M29-'YTD CF'!L29 -> -27799 | Q29: ='CASH FLOW'!F27-'YTD CF'!M29 -> -111204 | R29: ='YTD CF'!N29 -> -66044 | S29: ='YTD CF'!O29-'YTD CF'!N29 -> -59768 | T29: ='YTD CF'!P29-'YTD CF'!O29 -> -46983 | U29: ='CASH FLOW'!G27-'YTD CF'!P29 -> -91279 | V29: ='YTD CF'!Q29 -> -29056 | W29: ='YTD CF'!R29-'YTD CF'!Q29 -> -31404 | X29: ='YTD CF'!S29-'YTD CF'!R29 -> -43641 | Y29: ='CASH FLOW'!H27-'YTD CF'!S29 -> -28174 | Z29: ='QTR P&L'!Z2*'CF DRIVERS'!Z28 -> -28835.063 | AA29: ='QTR P&L'!AA2*'CF DRIVERS'!AA28 -> -32831.483 | AB29: ='QTR P&L'!AB2*'CF DRIVERS'!AB28 -> -34161.601 | AC29: ='QTR P&L'!AC2*'CF DRIVERS'!AC28 -> -33134.067 | AD29: ='QTR P&L'!AD2*'CF DRIVERS'!AD28 -> -33911.511 | AE29: ='QTR P&L'!AE2*'CF DRIVERS'!AE28 -> -38611.505 | AF29: ='QTR P&L'!AF2*'CF DRIVERS'!AF28 -> -40175.792 | AG29: ='QTR P&L'!AG2*'CF DRIVERS'!AG28 -> -38967.359 | ... AS29: ='QTR P&L'!AS2*'CF DRIVERS'!AS28 -> -63384.003
A30: Proceeds from Sale of Assets | B30: ='YTD CF'!B30 -> 217 | C30: ='YTD CF'!C30-'YTD CF'!B30 -> 373 | D30: ='YTD CF'!D30-'YTD CF'!C30 -> 290 | E30: ='CASH FLOW'!C28-'YTD CF'!D30 -> 113 | F30: ='YTD CF'!E30 -> 231 | G30: ='YTD CF'!F30-'YTD CF'!E30 -> 793 | H30: ='YTD CF'!G30-'YTD CF'!F30 -> 222 | I30: ='CASH FLOW'!D28-'YTD CF'!G30 -> 82 | J30: ='YTD CF'!H30 -> 14 | K30: ='YTD CF'!I30-'YTD CF'!H30 -> 358 | L30: ='YTD CF'!J30-'YTD CF'!I30 -> 231 | M30: ='CASH FLOW'!E28-'YTD CF'!J30 -> 710 | N30: ='YTD CF'!K30 -> 564 | O30: ='YTD CF'!L30-'YTD CF'!K30 -> 471 | P30: ='YTD CF'!M30-'YTD CF'!L30 -> 718 | Q30: ='CASH FLOW'!F28-'YTD CF'!M30 -> 767 | R30: ='YTD CF'!N30 -> 422 | S30: ='YTD CF'!O30-'YTD CF'!N30 -> 630 | T30: ='YTD CF'!P30-'YTD CF'!O30 -> 1043 | U30: ='CASH FLOW'!G28-'YTD CF'!P30 -> 637 | V30: ='YTD CF'!Q30 -> 1147 | W30: ='YTD CF'!R30-'YTD CF'!Q30 -> 1187 | X30: ='YTD CF'!S30-'YTD CF'!R30 -> 410 | Y30: ='CASH FLOW'!H28-'YTD CF'!S30 -> 1555 | Z30: ='CF DRIVERS'!Z29 -> 0 | AA30: ='CF DRIVERS'!AA29 -> 0 | AB30: ='CF DRIVERS'!AB29 -> 0 | AC30: ='CF DRIVERS'!AC29 -> 0 | AD30: ='CF DRIVERS'!AD29 -> 0 | AE30: ='CF DRIVERS'!AE29 -> 0 | AF30: ='CF DRIVERS'!AF29 -> 0 | AG30: ='CF DRIVERS'!AG29 -> 0 | ... AS30: ='CF DRIVERS'!AS29 -> 0
A31: Additions to Intangibles | B31: ='YTD CF'!B31 -> -6811 | C31: ='YTD CF'!C31-'YTD CF'!B31 -> -6274 | D31: ='YTD CF'!D31-'YTD CF'!C31 -> -6601 | E31: ='CASH FLOW'!C29-'YTD CF'!D31 -> 1136 | F31: ='YTD CF'!E31 -> -7239 | G31: ='YTD CF'!F31-'YTD CF'!E31 -> -2687 | H31: ='YTD CF'!G31-'YTD CF'!F31 -> 4715 | I31: ='CASH FLOW'!D29-'YTD CF'!G31 -> -8374 | J31: ='YTD CF'!H31 -> -8419 | K31: ='YTD CF'!I31-'YTD CF'!H31 -> -1475 | L31: ='YTD CF'!J31-'YTD CF'!I31 -> 6316 | M31: ='CASH FLOW'!E29-'YTD CF'!J31 -> -19849 | N31: ='YTD CF'!K31 -> -3952 | O31: ='YTD CF'!L31-'YTD CF'!K31 -> -1974 | P31: ='YTD CF'!M31-'YTD CF'!L31 -> -3184 | Q31: ='CASH FLOW'!F29-'YTD CF'!M31 -> -4186 | R31: ='YTD CF'!N31 -> -8612 | S31: ='YTD CF'!O31-'YTD CF'!N31 -> 2248 | T31: ='YTD CF'!P31-'YTD CF'!O31 -> -15109 | U31: ='CASH FLOW'!G29-'YTD CF'!P31 -> -20887 | V31: ='YTD CF'!Q31 -> -5343 | W31: ='YTD CF'!R31-'YTD CF'!Q31 -> -10056 | X31: ='YTD CF'!S31-'YTD CF'!R31 -> -4282 | Y31: ='CASH FLOW'!H29-'YTD CF'!S31 -> -5573 | Z31: ='CF DRIVERS'!Z30 -> 0 | AA31: ='CF DRIVERS'!AA30 -> 0 | AB31: ='CF DRIVERS'!AB30 -> 0 | AC31: ='CF DRIVERS'!AC30 -> 0 | AD31: ='CF DRIVERS'!AD30 -> 0 | AE31: ='CF DRIVERS'!AE30 -> 0 | AF31: ='CF DRIVERS'!AF30 -> 0 | AG31: ='CF DRIVERS'!AG30 -> 0 | ... AS31: ='CF DRIVERS'!AS30 -> 0
A32: Other Investing Activities | B32: ='YTD CF'!B32 -> -1148 | C32: ='YTD CF'!C32-'YTD CF'!B32 -> -190 | D32: ='YTD CF'!D32-'YTD CF'!C32 -> -24890 | E32: ='CASH FLOW'!C30-'YTD CF'!D32 -> -195 | F32: ='YTD CF'!E32 -> -18856 | G32: ='YTD CF'!F32-'YTD CF'!E32 -> -2380 | H32: ='YTD CF'!G32-'YTD CF'!F32 -> -1573 | I32: ='CASH FLOW'!D30-'YTD CF'!G32 -> 11456 | J32: ='YTD CF'!H32 -> -6241 | K32: ='YTD CF'!I32-'YTD CF'!H32 -> -6497 | L32: ='YTD CF'!J32-'YTD CF'!I32 -> -6433 | M32: ='CASH FLOW'!E30-'YTD CF'!J32 -> -7172 | N32: ='YTD CF'!K32 -> -13028 | O32: ='YTD CF'!L32-'YTD CF'!K32 -> -4542 | P32: ='YTD CF'!M32-'YTD CF'!L32 -> -2292 | Q32: ='CASH FLOW'!F30-'YTD CF'!M32 -> 13037 | R32: ='YTD CF'!N32 -> -985 | S32: ='YTD CF'!O32-'YTD CF'!N32 -> -381 | T32: ='YTD CF'!P32-'YTD CF'!O32 -> 763 | U32: ='CASH FLOW'!G30-'YTD CF'!P32 -> 2238 | V32: ='YTD CF'!Q32 -> 2397 | W32: ='YTD CF'!R32-'YTD CF'!Q32 -> -3504 | X32: ='YTD CF'!S32-'YTD CF'!R32 -> 600 | Y32: ='CASH FLOW'!H30-'YTD CF'!S32 -> 109 | Z32: ='CF DRIVERS'!Z31 -> 0 | AA32: ='CF DRIVERS'!AA31 -> 0 | AB32: ='CF DRIVERS'!AB31 -> 0 | AC32: ='CF DRIVERS'!AC31 -> 0 | AD32: ='CF DRIVERS'!AD31 -> 0 | AE32: ='CF DRIVERS'!AE31 -> 0 | AF32: ='CF DRIVERS'!AF31 -> 0 | AG32: ='CF DRIVERS'!AG31 -> 0 | ... AS32: ='CF DRIVERS'!AS31 -> 0
A33: Cash Flow from Investing | B33: ='YTD CF'!B33 -> 279976 | C33: ='YTD CF'!C33-'YTD CF'!B33 -> -29282 | D33: ='YTD CF'!D33-'YTD CF'!C33 -> -391208 | E33: ='CASH FLOW'!C31-'YTD CF'!D33 -> -331973 | F33: ='YTD CF'!E33 -> -149083 | G33: ='YTD CF'!F33-'YTD CF'!E33 -> -31079 | H33: ='YTD CF'!G33-'YTD CF'!F33 -> -201538 | I33: ='CASH FLOW'!D31-'YTD CF'!G33 -> -610322 | J33: ='YTD CF'!H33 -> -303630 | K33: ='YTD CF'!I33-'YTD CF'!H33 -> 297892 | L33: ='YTD CF'!J33-'YTD CF'!I33 -> -52005 | M33: ='CASH FLOW'!E31-'YTD CF'!J33 -> -103624 | N33: ='YTD CF'!K33 -> -52766 | O33: ='YTD CF'!L33-'YTD CF'!K33 -> -105443 | P33: ='YTD CF'!M33-'YTD CF'!L33 -> -201814 | Q33: ='CASH FLOW'!F31-'YTD CF'!M33 -> 166628 | R33: ='YTD CF'!N33 -> -35322 | S33: ='YTD CF'!O33-'YTD CF'!N33 -> 938626 | T33: ='YTD CF'!P33-'YTD CF'!O33 -> -60286 | U33: ='CASH FLOW'!G31-'YTD CF'!P33 -> -109291 | V33: ='YTD CF'!Q33 -> -30855 | W33: ='YTD CF'!R33-'YTD CF'!Q33 -> -326874 | X33: ='YTD CF'!S33-'YTD CF'!R33 -> -361519 | Y33: ='CASH FLOW'!H31-'YTD CF'!S33 -> -597530 | Z33: =SUM(Z25:Z32) -> -40269.555 | AA33: =SUM(AA25:AA32) -> -101958.02 | AB33: =SUM(AB25:AB32) -> -57168.819 | AC33: =SUM(AC25:AC32) -> -15360.676 | AD33: =SUM(AD25:AD32) -> -47359.058 | AE33: =SUM(AE25:AE32) -> -119907.85 | AF33: =SUM(AF25:AF32) -> -67233.458 | AG33: =SUM(AG25:AG32) -> -18064.942 | ... AS33: =SUM(AS25:AS32) -> -29384.294
A34: Repayments of Short-Term Debt | B34: ='YTD CF'!B34 -> 0 | C34: ='YTD CF'!C34-'YTD CF'!B34 -> 0 | D34: ='YTD CF'!D34-'YTD CF'!C34 -> 0 | F34: ='YTD CF'!E34 -> 0 | G34: ='YTD CF'!F34-'YTD CF'!E34 -> 0 | H34: ='YTD CF'!G34-'YTD CF'!F34 -> 0 | J34: ='YTD CF'!H34 -> 0 | K34: ='YTD CF'!I34-'YTD CF'!H34 -> 0 | L34: ='YTD CF'!J34-'YTD CF'!I34 -> 0 | N34: ='YTD CF'!K34 -> 0 | O34: ='YTD CF'!L34-'YTD CF'!K34 -> 0 | P34: ='YTD CF'!M34-'YTD CF'!L34 -> 0 | R34: ='YTD CF'!N34 -> 0 | S34: ='YTD CF'!O34-'YTD CF'!N34 -> -5269 | T34: ='YTD CF'!P34-'YTD CF'!O34 -> -1448 | V34: ='YTD CF'!Q34 -> 0 | W34: ='YTD CF'!R34-'YTD CF'!Q34 -> 0 | X34: ='YTD CF'!S34-'YTD CF'!R34 -> 0 | Z34: ='CF DRIVERS'!Z32 -> 0 | AA34: ='CF DRIVERS'!AA32 -> 0 | AB34: ='CF DRIVERS'!AB32 -> 0 | AC34: ='CF DRIVERS'!AC32 -> 0 | AD34: ='CF DRIVERS'!AD32 -> 0 | AE34: ='CF DRIVERS'!AE32 -> 0 | AF34: ='CF DRIVERS'!AF32 -> 0 | AG34: ='CF DRIVERS'!AG32 -> 0 | ... AS34: ='CF DRIVERS'!AS32 -> 0
A35: Net Change in Other Short-Term Debt | B35: ='YTD CF'!B35 -> -733 | C35: ='YTD CF'!C35-'YTD CF'!B35 -> -947 | D35: ='YTD CF'!D35-'YTD CF'!C35 -> -820 | E35: ='CASH FLOW'!C32-'YTD CF'!D35 -> -586 | F35: ='YTD CF'!E35 -> 957 | G35: ='YTD CF'!F35-'YTD CF'!E35 -> 2667 | H35: ='YTD CF'!G35-'YTD CF'!F35 -> -5438 | I35: ='CASH FLOW'!D32-'YTD CF'!G35 -> 4742 | J35: ='YTD CF'!H35 -> 3454 | K35: ='YTD CF'!I35-'YTD CF'!H35 -> 1470 | L35: ='YTD CF'!J35-'YTD CF'!I35 -> -5643 | M35: ='CASH FLOW'!E32-'YTD CF'!J35 -> 794 | N35: ='YTD CF'!K35 -> -7271 | O35: ='YTD CF'!L35-'YTD CF'!K35 -> 610 | P35: ='YTD CF'!M35-'YTD CF'!L35 -> -4612 | Q35: ='CASH FLOW'!F32-'YTD CF'!M35 -> -2641 | R35: ='YTD CF'!N35 -> -2896 | S35: ='YTD CF'!O35-'YTD CF'!N35 -> 2896 | T35: ='YTD CF'!P35-'YTD CF'!O35 -> 0 | U35: ='CASH FLOW'!G32-'YTD CF'!P35 -> -8223 | V35: ='YTD CF'!Q35 -> -2045 | W35: ='YTD CF'!R35-'YTD CF'!Q35 -> -2978 | X35: ='YTD CF'!S35-'YTD CF'!R35 -> -3020 | Y35: ='CASH FLOW'!H32-'YTD CF'!S35 -> -2301 | Z35: ='CF DRIVERS'!Z33 -> 0 | AA35: ='CF DRIVERS'!AA33 -> 0 | AB35: ='CF DRIVERS'!AB33 -> 0 | AC35: ='CF DRIVERS'!AC33 -> 0 | AD35: ='CF DRIVERS'!AD33 -> 0 | AE35: ='CF DRIVERS'!AE33 -> 0 | AF35: ='CF DRIVERS'!AF33 -> 0 | AG35: ='CF DRIVERS'!AG33 -> 0 | ... AS35: ='CF DRIVERS'!AS33 -> 0
A36: Proceeds from Issuance of Long-Term Debt | B36: ='YTD CF'!B36 -> 0 | C36: ='YTD CF'!C36-'YTD CF'!B36 -> 0 | D36: ='YTD CF'!D36-'YTD CF'!C36 -> 0 | E36: ='CASH FLOW'!C33-'YTD CF'!D36 -> 0 | F36: ='YTD CF'!E36 -> 0 | G36: ='YTD CF'!F36-'YTD CF'!E36 -> 0 | H36: ='YTD CF'!G36-'YTD CF'!F36 -> 0 | I36: ='CASH FLOW'!D33-'YTD CF'!G36 -> 0 | J36: ='YTD CF'!H36 -> 0 | K36: ='YTD CF'!I36-'YTD CF'!H36 -> 0 | L36: ='YTD CF'!J36-'YTD CF'!I36 -> 0 | M36: ='CASH FLOW'!E33-'YTD CF'!J36 -> 0 | N36: ='YTD CF'!K36 -> 0 | O36: ='YTD CF'!L36-'YTD CF'!K36 -> 0 | P36: ='YTD CF'!M36-'YTD CF'!L36 -> 0 | Q36: ='CASH FLOW'!F33-'YTD CF'!M36 -> 0 | R36: ='YTD CF'!N36 -> 0 | S36: ='YTD CF'!O36-'YTD CF'!N36 -> 750000 | T36: ='YTD CF'!P36-'YTD CF'!O36 -> 0 | U36: ='CASH FLOW'!G33-'YTD CF'!P36 -> 0 | V36: ='YTD CF'!Q36 -> 0 | W36: ='YTD CF'!R36-'YTD CF'!Q36 -> 0 | X36: ='YTD CF'!S36-'YTD CF'!R36 -> 0 | Y36: ='CASH FLOW'!H33-'YTD CF'!S36 -> 0 | Z36: ='CF DRIVERS'!Z34 -> 0 | AA36: ='CF DRIVERS'!AA34 -> 0 | AB36: ='CF DRIVERS'!AB34 -> 0 | AC36: ='CF DRIVERS'!AC34 -> 0 | AD36: ='CF DRIVERS'!AD34 -> 0 | AE36: ='CF DRIVERS'!AE34 -> 0 | AF36: ='CF DRIVERS'!AF34 -> 0 | AG36: ='CF DRIVERS'!AG34 -> 0 | ... AS36: ='CF DRIVERS'!AS34 -> 0
A37: Debt Issuance Fees | B37: ='YTD CF'!B37 -> 0 | C37: ='YTD CF'!C37-'YTD CF'!B37 -> 0 | D37: ='YTD CF'!D37-'YTD CF'!C37 -> 0 | E37: ='CASH FLOW'!C35-'YTD CF'!D37 -> 0 | F37: ='YTD CF'!E37 -> 0 | G37: ='YTD CF'!F37-'YTD CF'!E37 -> 0 | H37: ='YTD CF'!G37-'YTD CF'!F37 -> 0 | I37: ='CASH FLOW'!D35-'YTD CF'!G37 -> 0 | J37: ='YTD CF'!H37 -> 0 | K37: ='YTD CF'!I37-'YTD CF'!H37 -> 0 | L37: ='YTD CF'!J37-'YTD CF'!I37 -> 0 | M37: ='CASH FLOW'!E35-'YTD CF'!J37 -> 0 | N37: ='YTD CF'!K37 -> 0 | O37: ='YTD CF'!L37-'YTD CF'!K37 -> 0 | P37: ='YTD CF'!M37-'YTD CF'!L37 -> 0 | Q37: ='CASH FLOW'!F35-'YTD CF'!M37 -> 0 | R37: ='YTD CF'!N37 -> 0 | S37: ='YTD CF'!O37-'YTD CF'!N37 -> -2776 | T37: ='YTD CF'!P37-'YTD CF'!O37 -> -128 | U37: ='CASH FLOW'!G35-'YTD CF'!P37 -> 0 | V37: ='YTD CF'!Q37 -> 0 | W37: ='YTD CF'!R37-'YTD CF'!Q37 -> 0 | X37: ='YTD CF'!S37-'YTD CF'!R37 -> 0 | Y37: ='CASH FLOW'!H35-'YTD CF'!S37 -> 0 | Z37: ='CF DRIVERS'!Z35 -> 0 | AA37: ='CF DRIVERS'!AA35 -> 0 | AB37: ='CF DRIVERS'!AB35 -> 0 | AC37: ='CF DRIVERS'!AC35 -> 0 | AD37: ='CF DRIVERS'!AD35 -> 0 | AE37: ='CF DRIVERS'!AE35 -> 0 | AF37: ='CF DRIVERS'!AF35 -> 0 | AG37: ='CF DRIVERS'!AG35 -> 0 | ... AS37: ='CF DRIVERS'!AS35 -> 0
A38: Repayments of Long-Term Debt | B38: ='YTD CF'!B38 -> 0 | C38: ='YTD CF'!C38-'YTD CF'!B38 -> 0 | D38: ='YTD CF'!D38-'YTD CF'!C38 -> 0 | E38: ='CASH FLOW'!C34-'YTD CF'!D38 -> 0 | F38: ='YTD CF'!E38 -> 0 | G38: ='YTD CF'!F38-'YTD CF'!E38 -> 0 | H38: ='YTD CF'!G38-'YTD CF'!F38 -> 0 | I38: ='CASH FLOW'!D34-'YTD CF'!G38 -> 0 | J38: ='YTD CF'!H38 -> 0 | K38: ='YTD CF'!I38-'YTD CF'!H38 -> 0 | L38: ='YTD CF'!J38-'YTD CF'!I38 -> 0 | M38: ='CASH FLOW'!E34-'YTD CF'!J38 -> 0 | N38: ='YTD CF'!K38 -> 0 | O38: ='YTD CF'!L38-'YTD CF'!K38 -> 0 | P38: ='YTD CF'!M38-'YTD CF'!L38 -> 0 | Q38: ='CASH FLOW'!F34-'YTD CF'!M38 -> 0 | R38: ='YTD CF'!N38 -> 0 | S38: ='YTD CF'!O38-'YTD CF'!N38 -> 0 | T38: ='YTD CF'!P38-'YTD CF'!O38 -> 0 | U38: ='CASH FLOW'!G34-'YTD CF'!P38 -> -375000 | V38: ='YTD CF'!Q38 -> -175000 | W38: ='YTD CF'!R38-'YTD CF'!Q38 -> -200000 | X38: ='YTD CF'!S38-'YTD CF'!R38 -> 0 | Y38: ='CASH FLOW'!H34-'YTD CF'!S38 -> 0 | Z38: ='CF DRIVERS'!Z36 -> 0 | AA38: ='CF DRIVERS'!AA36 -> 0 | AB38: ='CF DRIVERS'!AB36 -> 0 | AC38: ='CF DRIVERS'!AC36 -> 0 | AD38: ='CF DRIVERS'!AD36 -> 0 | AE38: ='CF DRIVERS'!AE36 -> 0 | AF38: ='CF DRIVERS'!AF36 -> 0 | AG38: ='CF DRIVERS'!AG36 -> 0 | ... AS38: ='CF DRIVERS'!AS36 -> 0
A39: Proceeds from Issuance of Common Stock | B39: ='YTD CF'!B39 -> 13975 | C39: ='YTD CF'!C39-'YTD CF'!B39 -> 29867 | D39: ='YTD CF'!D39-'YTD CF'!C39 -> 21698 | E39: ='CASH FLOW'!C36-'YTD CF'!D39 -> 7396 | F39: ='YTD CF'!E39 -> 6761 | G39: ='YTD CF'!F39-'YTD CF'!E39 -> 17725 | H39: ='YTD CF'!G39-'YTD CF'!F39 -> 12674 | I39: ='CASH FLOW'!D36-'YTD CF'!G39 -> 8563 | J39: ='YTD CF'!H39 -> 4510 | K39: ='YTD CF'!I39-'YTD CF'!H39 -> 18112 | L39: ='YTD CF'!J39-'YTD CF'!I39 -> 12137 | M39: ='CASH FLOW'!E36-'YTD CF'!J39 -> 29256 | N39: ='YTD CF'!K39 -> 36348 | O39: ='YTD CF'!L39-'YTD CF'!K39 -> 23318 | P39: ='YTD CF'!M39-'YTD CF'!L39 -> 5894 | Q39: ='CASH FLOW'!F36-'YTD CF'!M39 -> 64707 | R39: ='YTD CF'!N39 -> 38392 | S39: ='YTD CF'!O39-'YTD CF'!N39 -> 13701 | T39: ='YTD CF'!P39-'YTD CF'!O39 -> 10008 | U39: ='CASH FLOW'!G36-'YTD CF'!P39 -> 16872 | V39: ='YTD CF'!Q39 -> 48093 | W39: ='YTD CF'!R39-'YTD CF'!Q39 -> 39591 | X39: ='YTD CF'!S39-'YTD CF'!R39 -> 26679 | Y39: ='CASH FLOW'!H36-'YTD CF'!S39 -> 50205 | Z39: ='CF DRIVERS'!Z37 -> 0 | AA39: ='CF DRIVERS'!AA37 -> 0 | AB39: ='CF DRIVERS'!AB37 -> 0 | AC39: ='CF DRIVERS'!AC37 -> 0 | AD39: ='CF DRIVERS'!AD37 -> 0 | AE39: ='CF DRIVERS'!AE37 -> 0 | AF39: ='CF DRIVERS'!AF37 -> 0 | AG39: ='CF DRIVERS'!AG37 -> 0 | ... AS39: ='CF DRIVERS'!AS37 -> 0
A40: Share Repurchases | B40: ='YTD CF'!B40 -> -559210 | C40: ='YTD CF'!C40-'YTD CF'!B40 -> -36560 | D40: ='YTD CF'!D40-'YTD CF'!C40 -> -148 | E40: ='CASH FLOW'!C37-'YTD CF'!D40 -> 0 | F40: ='YTD CF'!E40 -> -13419 | G40: ='YTD CF'!F40-'YTD CF'!E40 -> -399 | H40: ='YTD CF'!G40-'YTD CF'!F40 -> 0 | I40: ='CASH FLOW'!D37-'YTD CF'!G40 -> -12 | J40: ='YTD CF'!H40 -> -12187 | K40: ='YTD CF'!I40-'YTD CF'!H40 -> -284312 | L40: ='YTD CF'!J40-'YTD CF'!I40 -> -196816 | M40: ='CASH FLOW'!E37-'YTD CF'!J40 -> -277713 | N40: ='YTD CF'!K40 -> -35126 | O40: ='YTD CF'!L40-'YTD CF'!K40 -> -55699 | P40: ='YTD CF'!M40-'YTD CF'!L40 -> -397255 | Q40: ='CASH FLOW'!F37-'YTD CF'!M40 -> -170872 | R40: ='YTD CF'!N40 -> -120245 | S40: ='YTD CF'!O40-'YTD CF'!N40 -> -3114278 | T40: ='YTD CF'!P40-'YTD CF'!O40 -> -535661 | U40: ='CASH FLOW'!G37-'YTD CF'!P40 -> -1691 | V40: ='YTD CF'!Q40 -> -16633 | W40: ='YTD CF'!R40-'YTD CF'!Q40 -> 0 | X40: ='YTD CF'!S40-'YTD CF'!R40 -> -27288 | Y40: ='CASH FLOW'!H37-'YTD CF'!S40 -> -59725 | Z40: ='CF DRIVERS'!Z38 -> 0 | AA40: ='CF DRIVERS'!AA38 -> 0 | AB40: ='CF DRIVERS'!AB38 -> 0 | AC40: ='CF DRIVERS'!AC38 -> 0 | AD40: ='CF DRIVERS'!AD38 -> 0 | AE40: ='CF DRIVERS'!AE38 -> 0 | AF40: ='CF DRIVERS'!AF38 -> 0 | AG40: ='CF DRIVERS'!AG38 -> 0 | ... AS40: ='CF DRIVERS'!AS38 -> 0
A41: Cash Flow from Financing | B41: ='YTD CF'!B41 -> -545968 | C41: ='YTD CF'!C41-'YTD CF'!B41 -> -7640 | D41: ='YTD CF'!D41-'YTD CF'!C41 -> 20730 | E41: ='CASH FLOW'!C38-'YTD CF'!D41 -> 6810 | F41: ='YTD CF'!E41 -> -5701 | G41: ='YTD CF'!F41-'YTD CF'!E41 -> 19993 | H41: ='YTD CF'!G41-'YTD CF'!F41 -> 7236 | I41: ='CASH FLOW'!D38-'YTD CF'!G41 -> 13293 | J41: ='YTD CF'!H41 -> -4223 | K41: ='YTD CF'!I41-'YTD CF'!H41 -> -264730 | L41: ='YTD CF'!J41-'YTD CF'!I41 -> -190322 | M41: ='CASH FLOW'!E38-'YTD CF'!J41 -> -247663 | N41: ='YTD CF'!K41 -> -6049 | O41: ='YTD CF'!L41-'YTD CF'!K41 -> -31771 | P41: ='YTD CF'!M41-'YTD CF'!L41 -> -395973 | Q41: ='CASH FLOW'!F38-'YTD CF'!M41 -> -108806 | R41: ='YTD CF'!N41 -> -84749 | S41: ='YTD CF'!O41-'YTD CF'!N41 -> -2355726 | T41: ='YTD CF'!P41-'YTD CF'!O41 -> -527229 | U41: ='CASH FLOW'!G38-'YTD CF'!P41 -> -361325 | V41: ='YTD CF'!Q41 -> -145585 | W41: ='YTD CF'!R41-'YTD CF'!Q41 -> -163387 | X41: ='YTD CF'!S41-'YTD CF'!R41 -> -3629 | Y41: ='CASH FLOW'!H38-'YTD CF'!S41 -> -11821 | Z41: =SUM(Z34:Z40) -> 0 | AA41: =SUM(AA34:AA40) -> 0 | AB41: =SUM(AB34:AB40) -> 0 | AC41: =SUM(AC34:AC40) -> 0 | AD41: =SUM(AD34:AD40) -> 0 | AE41: =SUM(AE34:AE40) -> 0 | AF41: =SUM(AF34:AF40) -> 0 | AG41: =SUM(AG34:AG40) -> 0 | ... AS41: =SUM(AS34:AS40) -> 0
A42: FX Effect on Cash | B42: ='YTD CF'!B42 -> -21261 | C42: ='YTD CF'!C42-'YTD CF'!B42 -> 7086 | D42: ='YTD CF'!D42-'YTD CF'!C42 -> 15104 | E42: ='CASH FLOW'!C39-'YTD CF'!D42 -> 15919 | F42: ='YTD CF'!E42 -> -22223 | G42: ='YTD CF'!F42-'YTD CF'!E42 -> 5333 | H42: ='YTD CF'!G42-'YTD CF'!F42 -> -18662 | I42: ='CASH FLOW'!D39-'YTD CF'!G42 -> -16939 | J42: ='YTD CF'!H42 -> -3472 | K42: ='YTD CF'!I42-'YTD CF'!H42 -> -46923 | L42: ='YTD CF'!J42-'YTD CF'!I42 -> -45187 | M42: ='CASH FLOW'!E39-'YTD CF'!J42 -> 56867 | N42: ='YTD CF'!K42 -> -141 | O42: ='YTD CF'!L42-'YTD CF'!K42 -> -4359 | P42: ='YTD CF'!M42-'YTD CF'!L42 -> -18402 | Q42: ='CASH FLOW'!F39-'YTD CF'!M42 -> 31677 | R42: ='YTD CF'!N42 -> -13222 | S42: ='YTD CF'!O42-'YTD CF'!N42 -> -30981 | T42: ='YTD CF'!P42-'YTD CF'!O42 -> 29721 | U42: ='CASH FLOW'!G39-'YTD CF'!P42 -> -83137 | V42: ='YTD CF'!Q42 -> 38972 | W42: ='YTD CF'!R42-'YTD CF'!Q42 -> 47753 | X42: ='YTD CF'!S42-'YTD CF'!R42 -> -13986 | Y42: ='CASH FLOW'!H39-'YTD CF'!S42 -> 25114 | Z42: ='CF DRIVERS'!Z39 -> 25114 | AA42: ='CF DRIVERS'!AA39 -> 25114 | AB42: ='CF DRIVERS'!AB39 -> 25114 | AC42: ='CF DRIVERS'!AC39 -> 25114 | AD42: ='CF DRIVERS'!AD39 -> 25114 | AE42: ='CF DRIVERS'!AE39 -> 25114 | AF42: ='CF DRIVERS'!AF39 -> 25114 | AG42: ='CF DRIVERS'!AG39 -> 25114 | ... AS42: ='CF DRIVERS'!AS39 -> 25114
A43: Net Change in Cash | B43: ='YTD CF'!B43 -> -96121 | C43: ='YTD CF'!C43-'YTD CF'!B43 -> 219490 | D43: ='YTD CF'!D43-'YTD CF'!C43 -> 153404 | E43: ='CASH FLOW'!C40-'YTD CF'!D43 -> 105683 | F43: ='YTD CF'!E43 -> -1534 | G43: ='YTD CF'!F43-'YTD CF'!E43 -> 405360 | H43: ='YTD CF'!G43-'YTD CF'!F43 -> 128432 | I43: ='CASH FLOW'!D40-'YTD CF'!G43 -> -386209 | J43: ='YTD CF'!H43 -> -311676 | K43: ='YTD CF'!I43-'YTD CF'!H43 -> 117253 | L43: ='YTD CF'!J43-'YTD CF'!I43 -> 171009 | M43: ='CASH FLOW'!E40-'YTD CF'!J43 -> 4093 | N43: ='YTD CF'!K43 -> 365519 | O43: ='YTD CF'!L43-'YTD CF'!K43 -> 197114 | P43: ='YTD CF'!M43-'YTD CF'!L43 -> -95925 | Q43: ='CASH FLOW'!F40-'YTD CF'!M43 -> 523826 | R43: ='YTD CF'!N43 -> 278849 | S43: ='YTD CF'!O43-'YTD CF'!N43 -> -1011790 | T43: ='YTD CF'!P43-'YTD CF'!O43 -> 60605 | U43: ='CASH FLOW'!G40-'YTD CF'!P43 -> -92052 | V43: ='YTD CF'!Q43 -> 370132 | W43: ='YTD CF'!R43-'YTD CF'!Q43 -> 23508 | X43: ='YTD CF'!S43-'YTD CF'!R43 -> 366012 | Y43: ='CASH FLOW'!H40-'YTD CF'!S43 -> -204822 | Z43: =Z24+Z33+Z41+Z42 -> 492210.5 | AA43: =AA24+AA33+AA41+AA42 -> 356388.99 | AB43: =AB24+AB33+AB41+AB42 -> 540799.76 | AC43: =AC24+AC33+AC41+AC42 -> 666930.94 | AD43: =AD24+AD33+AD41+AD42 -> 570212.56 | AE43: =AE24+AE33+AE41+AE42 -> 410479.51 | AF43: =AF24+AF33+AF41+AF42 -> 627356.02 | AG43: =AG24+AG33+AG41+AG42 -> 775692.75 | ... AS43: =AS24+AS33+AS41+AS42 -> 1230941.4

Sheet IS DRIVERS
A1: Driver | B1: Basis | C1: Q1 FY2020 | D1: Q2 FY2020 | E1: Q3 FY2020 | F1: Q4 FY2020 | G1: Q1 FY2021 | H1: Q2 FY2021 | I1: Q3 FY2021 | J1: Q4 FY2021 | K1: Q1 FY2022 | L1: Q2 FY2022 | M1: Q3 FY2022 | N1: Q4 FY2022 | O1: Q1 FY2023 | P1: Q2 FY2023 | Q1: Q3 FY2023 | R1: Q4 FY2023 | S1: Q1 FY2024 | T1: Q2 FY2024 | U1: Q3 FY2024 | V1: Q4 FY2024 | W1: Q1 FY2025 | X1: Q2 FY2025 | Y1: Q3 FY2025 | Z1: Q4 FY2025 | AA1: Q1 FY2026E | AB1: Q2 FY2026E | AC1: Q3 FY2026E | AD1: Q4 FY2026E | AE1: Q1 FY2027E | AF1: Q2 FY2027E | AG1: Q3 FY2027E | AH1: Q4 FY2027E | AI1: Q1 FY2028E | AJ1: Q2 FY2028E | AK1: Q3 FY2028E | AL1: Q4 FY2028E | AM1: Q1 FY2029E | AN1: Q2 FY2029E | AO1: Q3 FY2029E | AP1: Q4 FY2029E | AQ1: Q1 FY2030E | AR1: Q2 FY2030E | AS1: Q3 FY2030E | AT1: Q4 FY2030E
A2: Net Sales / Revenue — Growth % | B2: YoY | D2: =IFERROR('QTR P&L'!C2/'QTR P&L'!B2-1,"") -> 0.029939827 | E2: =IFERROR('QTR P&L'!D2/'QTR P&L'!C2-1,"") -> 0.13937888 | F2: =IFERROR('QTR P&L'!E2/'QTR P&L'!D2-1,"") -> -0.04018014 | G2: =IFERROR('QTR P&L'!F2/IF($B2="QoQ",'QTR P&L'!E2,'QTR P&L'!B2)-1,"") -> 0.17109454 | H2: =IFERROR('QTR P&L'!G2/IF($B2="QoQ",'QTR P&L'!F2,'QTR P&L'!C2)-1,"") -> 0.33644789 | I2: =IFERROR('QTR P&L'!H2/IF($B2="QoQ",'QTR P&L'!G2,'QTR P&L'!D2)-1,"") -> 0.13173941 | J2: =IFERROR('QTR P&L'!I2/IF($B2="QoQ",'QTR P&L'!H2,'QTR P&L'!E2)-1,"") -> 0.19122649 | K2: =IFERROR('QTR P&L'!J2/IF($B2="QoQ",'QTR P&L'!I2,'QTR P&L'!F2)-1,"") -> 0.22089923 | L2: =IFERROR('QTR P&L'!K2/IF($B2="QoQ",'QTR P&L'!J2,'QTR P&L'!G2)-1,"") -> 0.13223844 | M2: =IFERROR('QTR P&L'!L2/IF($B2="QoQ",'QTR P&L'!K2,'QTR P&L'!H2)-1,"") -> 0.15152099 | N2: =IFERROR('QTR P&L'!M2/IF($B2="QoQ",'QTR P&L'!L2,'QTR P&L'!I2)-1,"") -> 0.061673183 | ... Z2: =IFERROR('QTR P&L'!Y2/IF($B2="QoQ",'QTR P&L'!X2,'QTR P&L'!U2)-1,"") -> 0.1760512 | AA2: =Z2 -> 0.1760512 | AB2: =AA2 -> 0.1760512 | AC2: =AB2 -> 0.1760512 | AD2: =AC2 -> 0.1760512 | AE2: =AD2 -> 0.1760512 | AF2: =AE2 -> 0.1760512 | AG2: =AF2 -> 0.1760512 | AH2: =AG2 -> 0.1760512 | ... AT2: =AS2 -> 0.1760512
A3: COGS — % of Revenue | C3: =IFERROR('QTR P&L'!B3/'QTR P&L'!B2,"") -> -0.40005856 | D3: =IFERROR('QTR P&L'!C3/'QTR P&L'!C2,"") -> -0.3971383 | E3: =IFERROR('QTR P&L'!D3/'QTR P&L'!D2,"") -> -0.40905531 | F3: =IFERROR('QTR P&L'!E3/'QTR P&L'!E2,"") -> -0.4226408 | G3: =IFERROR('QTR P&L'!F3/'QTR P&L'!F2,"") -> -0.42520839 | H3: =IFERROR('QTR P&L'!G3/'QTR P&L'!G2,"") -> -0.42758057 | I3: =IFERROR('QTR P&L'!H3/'QTR P&L'!H2,"") -> -0.44053448 | J3: =IFERROR('QTR P&L'!I3/'QTR P&L'!I2,"") -> -0.461364 | ... Z3: =IFERROR('QTR P&L'!Y3/'QTR P&L'!Y2,"") -> -0.44471911 | AA3: =Z3 -> -0.44471911 | AB3: =AA3 -> -0.44471911 | AC3: =AB3 -> -0.44471911 | AD3: =AC3 -> -0.44471911 | AE3: =AD3 -> -0.44471911 | AF3: =AE3 -> -0.44471911 | AG3: =AF3 -> -0.44471911 | AH3: =AG3 -> -0.44471911 | ... AT3: =AS3 -> -0.44471911
A4: Operating Expenses — % of Revenue | C4: =IFERROR('QTR P&L'!B5/'QTR P&L'!B2,"") -> -0.25629298 | D4: =IFERROR('QTR P&L'!C5/'QTR P&L'!C2,"") -> -0.23055574 | E4: =IFERROR('QTR P&L'!D5/'QTR P&L'!D2,"") -> -0.2229938 | F4: =IFERROR('QTR P&L'!E5/'QTR P&L'!E2,"") -> -0.2410667 | G4: =IFERROR('QTR P&L'!F5/'QTR P&L'!F2,"") -> -0.24182757 | H4: =IFERROR('QTR P&L'!G5/'QTR P&L'!G2,"") -> -0.21263804 | I4: =IFERROR('QTR P&L'!H5/'QTR P&L'!H2,"") -> -0.2443673 | J4: =IFERROR('QTR P&L'!I5/'QTR P&L'!I2,"") -> -0.2489046 | ... Z4: =IFERROR('QTR P&L'!Y5/'QTR P&L'!Y2,"") -> -0.30064902 | AA4: =Z4 -> -0.30064902 | AB4: =AA4 -> -0.30064902 | AC4: =AB4 -> -0.30064902 | AD4: =AC4 -> -0.30064902 | AE4: =AD4 -> -0.30064902 | AF4: =AE4 -> -0.30064902 | AG4: =AF4 -> -0.30064902 | AH4: =AG4 -> -0.30064902 | ... AT4: =AS4 -> -0.30064902
A5: Other Income (Expense) | C5: ='QTR P&L'!B7 -> 0 | D5: ='QTR P&L'!C7 -> 0 | E5: ='QTR P&L'!D7 -> 0 | F5: ='QTR P&L'!E7 -> -6996 | G5: ='QTR P&L'!F7 -> 0 | H5: ='QTR P&L'!G7 -> 0 | I5: ='QTR P&L'!H7 -> 0 | J5: ='QTR P&L'!I7 -> 3952 | ... Z5: ='QTR P&L'!Y7 -> 63175 | AA5: =Z5 -> 63175 | AB5: =AA5 -> 63175 | AC5: =AB5 -> 63175 | AD5: =AC5 -> 63175 | AE5: =AD5 -> 63175 | AF5: =AE5 -> 63175 | AG5: =AF5 -> 63175 | AH5: =AG5 -> 63175 | ... AT5: =AS5 -> 63175
A6: Interest Income (Expense) | C6: ='QTR P&L'!B8 -> 872 | D6: ='QTR P&L'!C8 -> -1795 | E6: ='QTR P&L'!D8 -> -4568 | F6: ='QTR P&L'!E8 -> 5491 | G6: ='QTR P&L'!F8 -> -759 | H6: ='QTR P&L'!G8 -> 870 | I6: ='QTR P&L'!H8 -> -2290 | J6: ='QTR P&L'!I8 -> 2179 | ... Z6: ='QTR P&L'!Y8 -> -37522 | AA6: =Z6 -> -37522 | AB6: =AA6 -> -37522 | AC6: =AB6 -> -37522 | AD6: =AC6 -> -37522 | AE6: =AD6 -> -37522 | AF6: =AE6 -> -37522 | AG6: =AF6 -> -37522 | AH6: =AG6 -> -37522 | ... AT6: =AS6 -> -37522
A7: Income Tax (Expense) Benefit — Effective Tax Rate % | C7: =IFERROR('QTR P&L'!B10/'QTR P&L'!B9,"") -> -0.23786421 | D7: =IFERROR('QTR P&L'!C10/'QTR P&L'!C9,"") -> -0.23207693 | E7: =IFERROR('QTR P&L'!D10/'QTR P&L'!D9,"") -> -0.23429626 | F7: =IFERROR('QTR P&L'!E10/'QTR P&L'!E9,"") -> 0.17699777 | G7: =IFERROR('QTR P&L'!F10/'QTR P&L'!F9,"") -> -0.23753287 | H7: =IFERROR('QTR P&L'!G10/'QTR P&L'!G9,"") -> -0.2336257 | I7: =IFERROR('QTR P&L'!H10/'QTR P&L'!H9,"") -> -0.23739297 | J7: =IFERROR('QTR P&L'!I10/'QTR P&L'!I9,"") -> -0.23316094 | ... Z7: =IFERROR('QTR P&L'!Y10/'QTR P&L'!Y9,"") -> -0.20957192 | AA7: =Z7 -> -0.20957192 | AB7: =AA7 -> -0.20957192 | AC7: =AB7 -> -0.20957192 | AD7: =AC7 -> -0.20957192 | AE7: =AD7 -> -0.20957192 | AF7: =AE7 -> -0.20957192 | AG7: =AF7 -> -0.20957192 | AH7: =AG7 -> -0.20957192 | ... AT7: =AS7 -> -0.20957192

Sheet BS DRIVERS
A1: Driver | B1: Q4 FY2020 | C1: Q1 FY2021 | D1: Q2 FY2021 | E1: Q3 FY2021 | F1: Q4 FY2021 | G1: Q1 FY2022 | H1: Q2 FY2022 | I1: Q3 FY2022 | J1: Q4 FY2022 | K1: Q1 FY2023 | L1: Q2 FY2023 | M1: Q3 FY2023 | N1: Q4 FY2023 | O1: Q1 FY2024 | P1: Q2 FY2024 | Q1: Q3 FY2024 | R1: Q4 FY2024 | S1: Q1 FY2025 | T1: Q2 FY2025 | U1: Q3 FY2025 | V1: Q4 FY2025 | W1: Q1 FY2026E | X1: Q2 FY2026E | Y1: Q3 FY2026E | Z1: Q4 FY2026E | AA1: Q1 FY2027E | AB1: Q2 FY2027E | AC1: Q3 FY2027E | AD1: Q4 FY2027E | AE1: Q1 FY2028E | AF1: Q2 FY2028E | AG1: Q3 FY2028E | AH1: Q4 FY2028E | AI1: Q1 FY2029E | AJ1: Q2 FY2029E | AK1: Q3 FY2029E | AL1: Q4 FY2029E | AM1: Q1 FY2030E | AN1: Q2 FY2030E | AO1: Q3 FY2030E | AP1: Q4 FY2030E
A2: Cash & Cash Equivalents | B2: ='QTR BS'!B2 -> 1180413 | C2: ='QTR BS'!C2 -> 1178879 | D2: ='QTR BS'!D2 -> 1584239 | E2: ='QTR BS'!E2 -> 1712671 | F2: ='QTR BS'!F2 -> 1326462 | G2: ='QTR BS'!G2 -> 1014786 | H2: ='QTR BS'!H2 -> 1132039 | I2: ='QTR BS'!I2 -> 1303048 | ... V2: ='QTR BS'!V2 -> 2088117 | W2: =V2+'QTR CF'!Z43 -> 2580327.5 | X2: =W2+'QTR CF'!AA43 -> 2936716.5 | Y2: =X2+'QTR CF'!AB43 -> 3477516.2 | Z2: =Y2+'QTR CF'!AC43 -> 4144447.2 | AA2: =Z2+'QTR CF'!AD43 -> 4714659.7 | AB2: =AA2+'QTR CF'!AE43 -> 5125139.3 | AC2: =AB2+'QTR CF'!AF43 -> 5752495.3 | AD2: =AC2+'QTR CF'!AG43 -> 6528188 | ... AP2: =AO2+'QTR CF'!AS43 -> 16272810
A3: Short-Term Investments | B3: ='QTR BS'!B3 -> 881354 | C3: ='QTR BS'!C3 -> 980108 | D3: ='QTR BS'!D3 -> 968952 | E3: ='QTR BS'!E3 -> 1224066 | F3: ='QTR BS'!F3 -> 1749727 | G3: ='QTR BS'!G3 -> 1717648 | H3: ='QTR BS'!H3 -> 1337792 | I3: ='QTR BS'!I3 -> 1346781 | ... V3: ='QTR BS'!V3 -> 677084 | W3: =V3 -> 677084 | X3: =W3 -> 677084 | Y3: =X3 -> 677084 | Z3: =Y3 -> 677084 | AA3: =Z3 -> 677084 | AB3: =AA3 -> 677084 | AC3: =AB3 -> 677084 | AD3: =AC3 -> 677084 | ... AP3: =AO3 -> 677084
A4: Accounts Receivable — DSO (days) | B4: =IFERROR('QTR BS'!B4/'QTR P&L'!E2*ASSUMPTIONS!$B$2,"") -> 50.662838 | C4: =IFERROR('QTR BS'!C4/'QTR P&L'!F2*ASSUMPTIONS!$B$2,"") -> 58.713121 | D4: =IFERROR('QTR BS'!D4/'QTR P&L'!G2*ASSUMPTIONS!$B$2,"") -> 56.592379 | E4: =IFERROR('QTR BS'!E4/'QTR P&L'!H2*ASSUMPTIONS!$B$2,"") -> 54.782109 | F4: =IFERROR('QTR BS'!F4/'QTR P&L'!I2*ASSUMPTIONS!$B$2,"") -> 57.258497 | G4: =IFERROR('QTR BS'!G4/'QTR P&L'!J2*ASSUMPTIONS!$B$2,"") -> 62.308442 | H4: =IFERROR('QTR BS'!H4/'QTR P&L'!K2*ASSUMPTIONS!$B$2,"") -> 64.629413 | I4: =IFERROR('QTR BS'!I4/'QTR P&L'!L2*ASSUMPTIONS!$B$2,"") -> 58.91784 | ... V4: =IFERROR('QTR BS'!V4/'QTR P&L'!Y2*ASSUMPTIONS!$B$2,"") -> 69.09474 | W4: =V4 -> 69.09474 | X4: =W4 -> 69.09474 | Y4: =X4 -> 69.09474 | Z4: =Y4 -> 69.09474 | AA4: =Z4 -> 69.09474 | AB4: =AA4 -> 69.09474 | AC4: =AB4 -> 69.09474 | AD4: =AC4 -> 69.09474 | ... AP4: =AO4 -> 69.09474
A5: Inventories — DIO (days) | B5: =IFERROR('QTR BS'!B5/'QTR P&L'!E3*ASSUMPTIONS!$B$2,"") -> -59.950267 | C5: =IFERROR('QTR BS'!C5/'QTR P&L'!F3*ASSUMPTIONS!$B$2,"") -> -63.38776 | D5: =IFERROR('QTR BS'!D5/'QTR P&L'!G3*ASSUMPTIONS!$B$2,"") -> -55.740311 | E5: =IFERROR('QTR BS'!E5/'QTR P&L'!H3*ASSUMPTIONS!$B$2,"") -> -69.05599 | F5: =IFERROR('QTR BS'!F5/'QTR P&L'!I3*ASSUMPTIONS!$B$2,"") -> -82.12691 | G5: =IFERROR('QTR BS'!G5/'QTR P&L'!J3*ASSUMPTIONS!$B$2,"") -> -100.71749 | H5: =IFERROR('QTR BS'!H5/'QTR P&L'!K3*ASSUMPTIONS!$B$2,"") -> -92.096596 | I5: =IFERROR('QTR BS'!I5/'QTR P&L'!L3*ASSUMPTIONS!$B$2,"") -> -99.33567 | ... V5: =IFERROR('QTR BS'!V5/'QTR P&L'!Y3*ASSUMPTIONS!$B$2,"") -> -76.779738 | W5: =V5 -> -76.779738 | X5: =W5 -> -76.779738 | Y5: =X5 -> -76.779738 | Z5: =Y5 -> -76.779738 | AA5: =Z5 -> -76.779738 | AB5: =AA5 -> -76.779738 | AC5: =AB5 -> -76.779738 | AD5: =AC5 -> -76.779738 | ... AP5: =AO5 -> -76.779738
A6: Prepaid Expenses — % of Revenue | B6: =IFERROR('QTR BS'!B6/'QTR P&L'!E2,"") -> 0.046275003 | C6: =IFERROR('QTR BS'!C6/'QTR P&L'!F2,"") -> 0.058531969 | D6: =IFERROR('QTR BS'!D6/'QTR P&L'!G2,"") -> 0.056832896 | E6: =IFERROR('QTR BS'!E6/'QTR P&L'!H2,"") -> 0.067779608 | F6: =IFERROR('QTR BS'!F6/'QTR P&L'!I2,"") -> 0.05801084 | G6: =IFERROR('QTR BS'!G6/'QTR P&L'!J2,"") -> 0.072651711 | H6: =IFERROR('QTR BS'!H6/'QTR P&L'!K2,"") -> 0.079910757 | I6: =IFERROR('QTR BS'!I6/'QTR P&L'!L2,"") -> 0.069134377 | ... V6: =IFERROR('QTR BS'!V6/'QTR P&L'!Y2,"") -> 0.048591471 | W6: =V6 -> 0.048591471 | X6: =W6 -> 0.048591471 | Y6: =X6 -> 0.048591471 | Z6: =Y6 -> 0.048591471 | AA6: =Z6 -> 0.048591471 | AB6: =AA6 -> 0.048591471 | AC6: =AB6 -> 0.048591471 | AD6: =AC6 -> 0.048591471 | ... AP6: =AO6 -> 0.048591471
A7: Prepaid Income Taxes — % of Revenue | B7: =IFERROR('QTR BS'!B7/'QTR P&L'!E2,"") -> 0.020674874 | C7: =IFERROR('QTR BS'!C7/'QTR P&L'!F2,"") -> 0.025060781 | D7: =IFERROR('QTR BS'!D7/'QTR P&L'!G2,"") -> 0.015280433 | E7: =IFERROR('QTR BS'!E7/'QTR P&L'!H2,"") -> 0.021707028 | F7: =IFERROR('QTR BS'!F7/'QTR P&L'!I2,"") -> 0.023324192 | G7: =IFERROR('QTR BS'!G7/'QTR P&L'!J2,"") -> 0.026335891 | H7: =IFERROR('QTR BS'!H7/'QTR P&L'!K2,"") -> 0.019924979 | I7: =IFERROR('QTR BS'!I7/'QTR P&L'!L2,"") -> 0.012281704 | ... V7: =IFERROR('QTR BS'!V7/'QTR P&L'!Y2,"") -> 0.035023531 | W7: =V7 -> 0.035023531 | X7: =W7 -> 0.035023531 | Y7: =X7 -> 0.035023531 | Z7: =Y7 -> 0.035023531 | AA7: =Z7 -> 0.035023531 | AB7: =AA7 -> 0.035023531 | AC7: =AB7 -> 0.035023531 | AD7: =AC7 -> 0.035023531 | ... AP7: =AO7 -> 0.035023531
A8: Long-Term Investments — % of Revenue | B8: =IFERROR('QTR BS'!B9/'QTR P&L'!E2,"") -> 0.037023848 | C8: =IFERROR('QTR BS'!C9/'QTR P&L'!F2,"") -> 0.051254366 | D8: =IFERROR('QTR BS'!D9/'QTR P&L'!G2,"") -> 0.062268842 | E8: =IFERROR('QTR BS'!E9/'QTR P&L'!H2,"") -> 0.020031094 | F8: =IFERROR('QTR BS'!F9/'QTR P&L'!I2,"") -> 0.069765565 | G8: =IFERROR('QTR BS'!G9/'QTR P&L'!J2,"") -> 0.043232664 | H8: =IFERROR('QTR BS'!H9/'QTR P&L'!K2,"") -> 0.038736536 | I8: =IFERROR('QTR BS'!I9/'QTR P&L'!L2,"") -> 0.044556808 | ... V8: =IFERROR('QTR BS'!V9/'QTR P&L'!Y2,"") -> 0.22867991 | W8: =V8 -> 0.22867991 | X8: =W8 -> 0.22867991 | Y8: =X8 -> 0.22867991 | Z8: =Y8 -> 0.22867991 | AA8: =Z8 -> 0.22867991 | AB8: =AA8 -> 0.22867991 | AC8: =AB8 -> 0.22867991 | AD8: =AC8 -> 0.22867991 | ... AP8: =AO8 -> 0.22867991
A9: Net PP&E | B9: ='QTR BS'!B10 -> 314656 | C9: ='QTR BS'!C10 -> 312155 | D9: ='QTR BS'!D10 -> 309178 | E9: ='QTR BS'!E10 -> 309574 | F9: ='QTR BS'!F10 -> 313753 | G9: ='QTR BS'!G10 -> 407391 | H9: ='QTR BS'!H10 -> 464541 | I9: ='QTR BS'!I10 -> 485550 | ... V9: ='QTR BS'!V10 -> 1081544 | W9: =V9-'QTR CF'!Z29-'QTR CF'!Z3 -> 1077200.4 | X9: =W9-'QTR CF'!AA29-'QTR CF'!AA3 -> 1072254.8 | Y9: =X9-'QTR CF'!AB29-'QTR CF'!AB3 -> 1067108.9 | Z9: =Y9-'QTR CF'!AC29-'QTR CF'!AC3 -> 1062117.7 | AA9: =Z9-'QTR CF'!AD29-'QTR CF'!AD3 -> 1057009.5 | AB9: =AA9-'QTR CF'!AE29-'QTR CF'!AE3 -> 1051193.2 | AC9: =AB9-'QTR CF'!AF29-'QTR CF'!AF3 -> 1045141.3 | AD9: =AC9-'QTR CF'!AG29-'QTR CF'!AG3 -> 1039271.4 | ... AP9: =AO9-'QTR CF'!AS29-'QTR CF'!AS3 -> 943642.85
A10: Deferred Tax Assets | B10: ='QTR BS'!B11 -> 241650 | C10: ='QTR BS'!C11 -> 241650 | D10: ='QTR BS'!D11 -> 241297 | E10: ='QTR BS'!E11 -> 241297 | F10: ='QTR BS'!F11 -> 225221 | G10: ='QTR BS'!G11 -> 225221 | H10: ='QTR BS'!H11 -> 203287 | I10: ='QTR BS'!I11 -> 195511 | ... V10: ='QTR BS'!V11 -> 188646 | W10: =V10-'QTR CF'!Z10 -> 184891 | X10: =W10-'QTR CF'!AA10 -> 181136 | Y10: =X10-'QTR CF'!AB10 -> 177381 | Z10: =Y10-'QTR CF'!AC10 -> 173626 | AA10: =Z10-'QTR CF'!AD10 -> 169871 | AB10: =AA10-'QTR CF'!AE10 -> 166116 | AC10: =AB10-'QTR CF'!AF10 -> 162361 | AD10: =AC10-'QTR CF'!AG10 -> 158606 | ... AP10: =AO10-'QTR CF'!AS10 -> 113546
A11: Goodwill | B11: ='QTR BS'!B12 -> 1331643 | C11: ='QTR BS'!C12 -> 1331643 | D11: ='QTR BS'!D12 -> 1331643 | E11: ='QTR BS'!E12 -> 1331643 | F11: ='QTR BS'!F12 -> 1331643 | G11: ='QTR BS'!G12 -> 1411928 | H11: ='QTR BS'!H12 -> 1412941 | I11: ='QTR BS'!I12 -> 1412941 | ... V11: ='QTR BS'!V12 -> 1331643 | W11: =V11 -> 1331643 | X11: =W11 -> 1331643 | Y11: =X11 -> 1331643 | Z11: =Y11 -> 1331643 | AA11: =Z11 -> 1331643 | AB11: =AA11 -> 1331643 | AC11: =AB11 -> 1331643 | AD11: =AC11 -> 1331643 | ... AP11: =AO11 -> 1331643
A12: Intangible Assets | B12: ='QTR BS'!B13 -> 1059046 | C12: ='QTR BS'!C13 -> 1063092 | D12: ='QTR BS'!D13 -> 1058323 | E12: ='QTR BS'!E13 -> 1066083 | F12: ='QTR BS'!F13 -> 1072386 | G12: ='QTR BS'!G13 -> 1232113 | H12: ='QTR BS'!H13 -> 1223114 | I12: ='QTR BS'!I13 -> 1225826 | ... V12: ='QTR BS'!V13 -> 1379268 | W12: =V12 -> 1379268 | X12: =W12 -> 1379268 | Y12: =X12 -> 1379268 | Z12: =Y12 -> 1379268 | AA12: =Z12 -> 1379268 | AB12: =AA12 -> 1379268 | AC12: =AB12 -> 1379268 | AD12: =AC12 -> 1379268 | ... AP12: =AO12 -> 1379268
A13: Other Non-Current Assets — % of Revenue | B13: =IFERROR('QTR BS'!B14/'QTR P&L'!E2,"") -> 0.058911645 | C13: =IFERROR('QTR BS'!C14/'QTR P&L'!F2,"") -> 0.070913222 | D13: =IFERROR('QTR BS'!D14/'QTR P&L'!G2,"") -> 0.061147725 | E13: =IFERROR('QTR BS'!E14/'QTR P&L'!H2,"") -> 0.063012696 | F13: =IFERROR('QTR BS'!F14/'QTR P&L'!I2,"") -> 0.056315454 | G13: =IFERROR('QTR BS'!G14/'QTR P&L'!J2,"") -> 0.066831119 | H13: =IFERROR('QTR BS'!H14/'QTR P&L'!K2,"") -> 0.06669047 | I13: =IFERROR('QTR BS'!I14/'QTR P&L'!L2,"") -> 0.071362432 | ... V13: =IFERROR('QTR BS'!V14/'QTR P&L'!Y2,"") -> 0.07481325 | W13: =V13 -> 0.07481325 | X13: =W13 -> 0.07481325 | Y13: =X13 -> 0.07481325 | Z13: =Y13 -> 0.07481325 | AA13: =Z13 -> 0.07481325 | AB13: =AA13 -> 0.07481325 | AC13: =AB13 -> 0.07481325 | AD13: =AC13 -> 0.07481325 | ... AP13: =AO13 -> 0.07481325
A14: Accounts Payable — DPO (days) | B14: =IFERROR('QTR BS'!B16/'QTR P&L'!E3*ASSUMPTIONS!$B$2,"") -> -53.419515 | C14: =IFERROR('QTR BS'!C16/'QTR P&L'!F3*ASSUMPTIONS!$B$2,"") -> -57.481581 | D14: =IFERROR('QTR BS'!D16/'QTR P&L'!G3*ASSUMPTIONS!$B$2,"") -> -52.83021 | E14: =IFERROR('QTR BS'!E16/'QTR P&L'!H3*ASSUMPTIONS!$B$2,"") -> -58.025261 | F14: =IFERROR('QTR BS'!F16/'QTR P&L'!I3*ASSUMPTIONS!$B$2,"") -> -55.954293 | G14: =IFERROR('QTR BS'!G16/'QTR P&L'!J3*ASSUMPTIONS!$B$2,"") -> -53.755115 | H14: =IFERROR('QTR BS'!H16/'QTR P&L'!K3*ASSUMPTIONS!$B$2,"") -> -51.233869 | I14: =IFERROR('QTR BS'!I16/'QTR P&L'!L3*ASSUMPTIONS!$B$2,"") -> -59.87902 | ... V14: =IFERROR('QTR BS'!V16/'QTR P&L'!Y3*ASSUMPTIONS!$B$2,"") -> -54.344779 | W14: =V14 -> -54.344779 | X14: =W14 -> -54.344779 | Y14: =X14 -> -54.344779 | Z14: =Y14 -> -54.344779 | AA14: =Z14 -> -54.344779 | AB14: =AA14 -> -54.344779 | AC14: =AB14 -> -54.344779 | AD14: =AC14 -> -54.344779 | ... AP14: =AO14 -> -54.344779
A15: Accrued Expenses — % of Revenue | B15: =IFERROR('QTR BS'!B17/'QTR P&L'!E2,"") -> 0.11924687 | C15: =IFERROR('QTR BS'!C17/'QTR P&L'!F2,"") -> 0.13744316 | D15: =IFERROR('QTR BS'!D17/'QTR P&L'!G2,"") -> 0.11799293 | E15: =IFERROR('QTR BS'!E17/'QTR P&L'!H2,"") -> 0.12811889 | F15: =IFERROR('QTR BS'!F17/'QTR P&L'!I2,"") -> 0.14804034 | G15: =IFERROR('QTR BS'!G17/'QTR P&L'!J2,"") -> 0.15416503 | H15: =IFERROR('QTR BS'!H17/'QTR P&L'!K2,"") -> 0.12635726 | I15: =IFERROR('QTR BS'!I17/'QTR P&L'!L2,"") -> 0.12232575 | ... V15: =IFERROR('QTR BS'!V17/'QTR P&L'!Y2,"") -> 0.14363087 | W15: =V15 -> 0.14363087 | X15: =W15 -> 0.14363087 | Y15: =X15 -> 0.14363087 | Z15: =Y15 -> 0.14363087 | AA15: =Z15 -> 0.14363087 | AB15: =AA15 -> 0.14363087 | AC15: =AB15 -> 0.14363087 | AD15: =AC15 -> 0.14363087 | ... AP15: =AO15 -> 0.14363087
A16: Accrued Promotional Allowance — % of Revenue | B16: =IFERROR('QTR BS'!B18/'QTR P&L'!E2,"") -> 0.15603164 | C16: =IFERROR('QTR BS'!C18/'QTR P&L'!F2,"") -> 0.15868907 | D16: =IFERROR('QTR BS'!D18/'QTR P&L'!G2,"") -> 0.15555685 | E16: =IFERROR('QTR BS'!E18/'QTR P&L'!H2,"") -> 0.16475336 | F16: =IFERROR('QTR BS'!F18/'QTR P&L'!I2,"") -> 0.1483891 | G16: =IFERROR('QTR BS'!G18/'QTR P&L'!J2,"") -> 0.17831531 | H16: =IFERROR('QTR BS'!H18/'QTR P&L'!K2,"") -> 0.16771877 | I16: =IFERROR('QTR BS'!I18/'QTR P&L'!L2,"") -> 0.17339927 | ... V16: =IFERROR('QTR BS'!V18/'QTR P&L'!Y2,"") -> 0.18022546 | W16: =V16 -> 0.18022546 | X16: =W16 -> 0.18022546 | Y16: =X16 -> 0.18022546 | Z16: =Y16 -> 0.18022546 | AA16: =Z16 -> 0.18022546 | AB16: =AA16 -> 0.18022546 | AC16: =AB16 -> 0.18022546 | AD16: =AC16 -> 0.18022546 | ... AP16: =AO16 -> 0.18022546
A17: Deferred Revenue - Current — % of Revenue | B17: =IFERROR('QTR BS'!B19/'QTR P&L'!E2,"") -> 0.037975128 | C17: =IFERROR('QTR BS'!C19/'QTR P&L'!F2,"") -> 0.036951607 | D17: =IFERROR('QTR BS'!D19/'QTR P&L'!G2,"") -> 0.031913868 | E17: =IFERROR('QTR BS'!E19/'QTR P&L'!H2,"") -> 0.032099376 | F17: =IFERROR('QTR BS'!F19/'QTR P&L'!I2,"") -> 0.029844693 | G17: =IFERROR('QTR BS'!G19/'QTR P&L'!J2,"") -> 0.028013123 | H17: =IFERROR('QTR BS'!H19/'QTR P&L'!K2,"") -> 0.026789765 | I17: =IFERROR('QTR BS'!I19/'QTR P&L'!L2,"") -> 0.026231834 | ... V17: =IFERROR('QTR BS'!V19/'QTR P&L'!Y2,"") -> 0.02126789 | W17: =V17 -> 0.02126789 | X17: =W17 -> 0.02126789 | Y17: =X17 -> 0.02126789 | Z17: =Y17 -> 0.02126789 | AA17: =Z17 -> 0.02126789 | AB17: =AA17 -> 0.02126789 | AC17: =AB17 -> 0.02126789 | AD17: =AC17 -> 0.02126789 | ... AP17: =AO17 -> 0.02126789
A18: Accrued Compensation — % of Revenue | B18: =IFERROR('QTR BS'!B20/'QTR P&L'!E2,"") -> 0.045988282 | C18: =IFERROR('QTR BS'!C20/'QTR P&L'!F2,"") -> 0.024520508 | D18: =IFERROR('QTR BS'!D20/'QTR P&L'!G2,"") -> 0.031991846 | E18: =IFERROR('QTR BS'!E20/'QTR P&L'!H2,"") -> 0.038642182 | F18: =IFERROR('QTR BS'!F20/'QTR P&L'!I2,"") -> 0.045934722 | G18: =IFERROR('QTR BS'!G20/'QTR P&L'!J2,"") -> 0.024727804 | H18: =IFERROR('QTR BS'!H20/'QTR P&L'!K2,"") -> 0.032452323 | I18: =IFERROR('QTR BS'!I20/'QTR P&L'!L2,"") -> 0.037817232 | ... V18: =IFERROR('QTR BS'!V20/'QTR P&L'!Y2,"") -> 0.053505474 | W18: =V18 -> 0.053505474 | X18: =W18 -> 0.053505474 | Y18: =X18 -> 0.053505474 | Z18: =Y18 -> 0.053505474 | AA18: =Z18 -> 0.053505474 | AB18: =AA18 -> 0.053505474 | AC18: =AB18 -> 0.053505474 | AD18: =AC18 -> 0.053505474 | ... AP18: =AO18 -> 0.053505474
A19: Income Taxes Payable — % of Revenue | B19: =IFERROR('QTR BS'!B21/'QTR P&L'!E2,"") -> 0.019588174 | C19: =IFERROR('QTR BS'!C21/'QTR P&L'!F2,"") -> 0.0080325386 | D19: =IFERROR('QTR BS'!D21/'QTR P&L'!G2,"") -> 0.021402456 | E19: =IFERROR('QTR BS'!E21/'QTR P&L'!H2,"") -> 0.016385726 | F19: =IFERROR('QTR BS'!F21/'QTR P&L'!I2,"") -> 0.021331973 | G19: =IFERROR('QTR BS'!G21/'QTR P&L'!J2,"") -> 0.013906468 | H19: =IFERROR('QTR BS'!H21/'QTR P&L'!K2,"") -> 0.0096160178 | I19: =IFERROR('QTR BS'!I21/'QTR P&L'!L2,"") -> 0.010554176 | ... V19: =IFERROR('QTR BS'!V21/'QTR P&L'!Y2,"") -> 0.015159172 | W19: =V19 -> 0.015159172 | X19: =W19 -> 0.015159172 | Y19: =X19 -> 0.015159172 | Z19: =Y19 -> 0.015159172 | AA19: =Z19 -> 0.015159172 | AB19: =AA19 -> 0.015159172 | AC19: =AB19 -> 0.015159172 | AD19: =AC19 -> 0.015159172 | ... AP19: =AO19 -> 0.015159172
A20: Deferred Revenue - Non-Current — % of Revenue | B20: =IFERROR('QTR BS'!B23/'QTR P&L'!E2,"") -> 0.22104803 | C20: =IFERROR('QTR BS'!C23/'QTR P&L'!F2,"") -> 0.2072091 | D20: =IFERROR('QTR BS'!D23/'QTR P&L'!G2,"") -> 0.17241259 | E20: =IFERROR('QTR BS'!E23/'QTR P&L'!H2,"") -> 0.1741305 | F20: =IFERROR('QTR BS'!F23/'QTR P&L'!I2,"") -> 0.17069578 | G20: =IFERROR('QTR BS'!G23/'QTR P&L'!J2,"") -> 0.15688468 | H20: =IFERROR('QTR BS'!H23/'QTR P&L'!K2,"") -> 0.14026204 | I20: =IFERROR('QTR BS'!I23/'QTR P&L'!L2,"") -> 0.13931906 | ... V20: =IFERROR('QTR BS'!V23/'QTR P&L'!Y2,"") -> 0.07507603 | W20: =V20 -> 0.07507603 | X20: =W20 -> 0.07507603 | Y20: =X20 -> 0.07507603 | Z20: =Y20 -> 0.07507603 | AA20: =Z20 -> 0.07507603 | AB20: =AA20 -> 0.07507603 | AC20: =AB20 -> 0.07507603 | AD20: =AC20 -> 0.07507603 | ... AP20: =AO20 -> 0.07507603
A21: Deferred Tax Liability | B21: ='QTR BS'!B24 -> 0 | C21: ='QTR BS'!C24 -> 0 | D21: ='QTR BS'!D24 -> 0 | E21: ='QTR BS'!E24 -> 0 | F21: ='QTR BS'!F24 -> 0 | G21: ='QTR BS'!G24 -> 0 | H21: ='QTR BS'!H24 -> 0 | I21: ='QTR BS'!I24 -> 0 | ... V21: ='QTR BS'!V24 -> 0 | W21: =V21 -> 0 | X21: =W21 -> 0 | Y21: =X21 -> 0 | Z21: =Y21 -> 0 | AA21: =Z21 -> 0 | AB21: =AA21 -> 0 | AC21: =AB21 -> 0 | AD21: =AC21 -> 0 | ... AP21: =AO21 -> 0
A22: Other Non-Current Liabilities — % of Revenue | B22: =IFERROR('QTR BS'!B25/'QTR P&L'!E2,"") -> 0.022931029 | C22: =IFERROR('QTR BS'!C25/'QTR P&L'!F2,"") -> 0.022783113 | D22: =IFERROR('QTR BS'!D25/'QTR P&L'!G2,"") -> 0.018100668 | E22: =IFERROR('QTR BS'!E25/'QTR P&L'!H2,"") -> 0.018822352 | F22: =IFERROR('QTR BS'!F25/'QTR P&L'!I2,"") -> 0.020706729 | G22: =IFERROR('QTR BS'!G25/'QTR P&L'!J2,"") -> 0.025145301 | H22: =IFERROR('QTR BS'!H25/'QTR P&L'!K2,"") -> 0.024199234 | I22: =IFERROR('QTR BS'!I25/'QTR P&L'!L2,"") -> 0.025262792 | ... V22: =IFERROR('QTR BS'!V25/'QTR P&L'!Y2,"") -> 0.059625922 | W22: =V22 -> 0.059625922 | X22: =W22 -> 0.059625922 | Y22: =X22 -> 0.059625922 | Z22: =Y22 -> 0.059625922 | AA22: =Z22 -> 0.059625922 | AB22: =AA22 -> 0.059625922 | AC22: =AB22 -> 0.059625922 | AD22: =AC22 -> 0.059625922 | ... AP22: =AO22 -> 0.059625922
A23: Long-Term Debt | B23: ='QTR BS'!B26 -> 0 | C23: ='QTR BS'!C26 -> 0 | D23: ='QTR BS'!D26 -> 0 | E23: ='QTR BS'!E26 -> 0 | F23: ='QTR BS'!F26 -> 0 | G23: ='QTR BS'!G26 -> 0 | H23: ='QTR BS'!H26 -> 0 | I23: ='QTR BS'!I26 -> 0 | ... V23: ='QTR BS'!V26 -> 0 | W23: =V23 -> 0 | X23: =W23 -> 0 | Y23: =X23 -> 0 | Z23: =Y23 -> 0 | AA23: =Z23 -> 0 | AB23: =AA23 -> 0 | AC23: =AB23 -> 0 | AD23: =AC23 -> 0 | ... AP23: =AO23 -> 0
A24: Common Stock | B24: ='QTR BS'!B28 -> 3193 | C24: ='QTR BS'!C28 -> 3196 | D24: ='QTR BS'!D28 -> 3198 | E24: ='QTR BS'!E28 -> 3199 | F24: ='QTR BS'!F28 -> 3200 | G24: ='QTR BS'!G28 -> 3203 | H24: ='QTR BS'!H28 -> 3205 | I24: ='QTR BS'!I28 -> 3206 | ... V24: ='QTR BS'!V28 -> 5665 | W24: =V24 -> 5665 | X24: =W24 -> 5665 | Y24: =X24 -> 5665 | Z24: =Y24 -> 5665 | AA24: =Z24 -> 5665 | AB24: =AA24 -> 5665 | AC24: =AB24 -> 5665 | AD24: =AC24 -> 5665 | ... AP24: =AO24 -> 5665
A25: Additional Paid-in Capital | B25: ='QTR BS'!B29 -> 4537982 | C25: ='QTR BS'!C29 -> 4562689 | D25: ='QTR BS'!D29 -> 4597333 | E25: ='QTR BS'!E29 -> 4626299 | F25: ='QTR BS'!F29 -> 4652620 | G25: ='QTR BS'!G29 -> 4673302 | H25: ='QTR BS'!H29 -> 4707569 | I25: ='QTR BS'!I29 -> 4736141 | ... V25: ='QTR BS'!V29 -> 5430847 | W25: =V25+'QTR CF'!Z9 -> 5470785.6 | X25: =W25+'QTR CF'!AA9 -> 5516259.6 | Y25: =X25+'QTR CF'!AB9 -> 5563575.8 | Z25: =Y25+'QTR CF'!AC9 -> 5609468.9 | AA25: =Z25+'QTR CF'!AD9 -> 5656438.7 | AB25: =AA25+'QTR CF'!AE9 -> 5709918.4 | AC25: =AB25+'QTR CF'!AF9 -> 5765564.8 | AD25: =AC25+'QTR CF'!AG9 -> 5819537.3 | ... AP25: =AO25+'QTR CF'!AS9 -> 6698829.3
A26: Retained Earnings (Accumulated Deficit) | B26: ='QTR BS'!B30 -> 6432074 | C26: ='QTR BS'!C30 -> 6747268 | D26: ='QTR BS'!D30 -> 7151030 | E26: ='QTR BS'!E30 -> 7488235 | F26: ='QTR BS'!F30 -> 7809549 | G26: ='QTR BS'!G30 -> 8103752 | H26: ='QTR BS'!H30 -> 8377112 | I26: ='QTR BS'!I30 -> 8699499 | ... V26: ='QTR BS'!V30 -> 9354216 | W26: =V26+'QTR P&L'!Z11 -> 9813469.8 | X26: =W26+'QTR P&L'!AA11 -> 10333564 | Y26: =X26+'QTR P&L'!AB11 -> 10873908 | Z26: =Y26+'QTR P&L'!AC11 -> 11398608 | AA26: =Z26+'QTR P&L'!AD11 -> 11935145 | AB26: =AA26+'QTR P&L'!AE11 -> 12543232 | AC26: =AB26+'QTR P&L'!AF11 -> 13175134 | AD26: =AC26+'QTR P&L'!AG11 -> 13788639 | ... AP26: =AO26+'QTR P&L'!AS11 -> 23696515
A27: Accumulated Other Comprehensive Income (Loss) | B27: ='QTR BS'!B31 -> 3034 | C27: ='QTR BS'!C31 -> -24874 | D27: ='QTR BS'!D31 -> -16822 | E27: ='QTR BS'!E31 -> -43495 | F27: ='QTR BS'!F31 -> -69165 | G27: ='QTR BS'!G31 -> -72145 | H27: ='QTR BS'!H31 -> -152957 | I27: ='QTR BS'!I31 -> -224455 | ... V27: ='QTR BS'!V31 -> -60841 | W27: =V27+'QTR CF'!Z42 -> -35727 | X27: =W27+'QTR CF'!AA42 -> -10613 | Y27: =X27+'QTR CF'!AB42 -> 14501 | Z27: =Y27+'QTR CF'!AC42 -> 39615 | AA27: =Z27+'QTR CF'!AD42 -> 64729 | AB27: =AA27+'QTR CF'!AE42 -> 89843 | AC27: =AB27+'QTR CF'!AF42 -> 114957 | AD27: =AC27+'QTR CF'!AG42 -> 140071 | ... AP27: =AO27+'QTR CF'!AS42 -> 441439
A28: Treasury Stock | B28: ='QTR BS'!B32 -> -5815423 | C28: ='QTR BS'!C32 -> -5828842 | D28: ='QTR BS'!D32 -> -5829241 | E28: ='QTR BS'!E32 -> -5829241 | F28: ='QTR BS'!F32 -> -5829253 | G28: ='QTR BS'!G32 -> -5841440 | H28: ='QTR BS'!H32 -> -6125751 | I28: ='QTR BS'!I32 -> -6398631 | ... V28: ='QTR BS'!V32 -> -6475779 | W28: =V28 -> -6475779 | X28: =W28 -> -6475779 | Y28: =X28 -> -6475779 | Z28: =Y28 -> -6475779 | AA28: =Z28 -> -6475779 | AB28: =AA28 -> -6475779 | AC28: =AB28 -> -6475779 | AD28: =AC28 -> -6475779 | ... AP28: =AO28 -> -6475779

Sheet CF DRIVERS
A1: Driver | B1: Q1 FY2020 | C1: Q2 FY2020 | D1: Q3 FY2020 | E1: Q4 FY2020 | F1: Q1 FY2021 | G1: Q2 FY2021 | H1: Q3 FY2021 | I1: Q4 FY2021 | J1: Q1 FY2022 | K1: Q2 FY2022 | L1: Q3 FY2022 | M1: Q4 FY2022 | N1: Q1 FY2023 | O1: Q2 FY2023 | P1: Q3 FY2023 | Q1: Q4 FY2023 | R1: Q1 FY2024 | S1: Q2 FY2024 | T1: Q3 FY2024 | U1: Q4 FY2024 | V1: Q1 FY2025 | W1: Q2 FY2025 | X1: Q3 FY2025 | Y1: Q4 FY2025 | Z1: Q1 FY2026E | AA1: Q2 FY2026E | AB1: Q3 FY2026E | AC1: Q4 FY2026E | AD1: Q1 FY2027E | AE1: Q2 FY2027E | AF1: Q3 FY2027E | AG1: Q4 FY2027E | AH1: Q1 FY2028E | AI1: Q2 FY2028E | AJ1: Q3 FY2028E | AK1: Q4 FY2028E | AL1: Q1 FY2029E | AM1: Q2 FY2029E | AN1: Q3 FY2029E | AO1: Q4 FY2029E | AP1: Q1 FY2030E | AQ1: Q2 FY2030E | AR1: Q3 FY2030E | AS1: Q4 FY2030E
A2: Net Income (Loss) | B2: ='QTR CF'!B2 -> 278835 | C2: ='QTR CF'!C2 -> 311369 | D2: ='QTR CF'!D2 -> 347654 | E2: ='QTR CF'!E2 -> 471736 | F2: ='QTR CF'!F2 -> 315194 | G2: ='QTR CF'!G2 -> 403762 | H2: ='QTR CF'!H2 -> 337205 | I2: ='QTR CF'!I2 -> 321314 | ... Y2: ='QTR CF'!Y2 -> 449190 | Z2: ='QTR P&L'!Z11 -> 459253.85 | AA2: ='QTR P&L'!AA11 -> 520094.22 | AB2: ='QTR P&L'!AB11 -> 540343.58 | AC2: ='QTR P&L'!AC11 -> 524700.68 | AD2: ='QTR P&L'!AD11 -> 536536.27 | AE2: ='QTR P&L'!AE11 -> 608087.68 | AF2: ='QTR P&L'!AF11 -> 631901.95 | AG2: ='QTR P&L'!AG11 -> 613505.1 | ... AS2: ='QTR P&L'!AS11 -> 985217.31
A3: Depreciation & Amortization — % of Revenue | B3: =IFERROR('QTR CF'!B3/'QTR P&L'!B2,"") -> 0.015578615 | C3: =IFERROR('QTR CF'!C3/'QTR P&L'!C2,"") -> 0.014179593 | D3: =IFERROR('QTR CF'!D3/'QTR P&L'!D2,"") -> 0.011089876 | E3: =IFERROR('QTR CF'!E3/'QTR P&L'!E2,"") -> 0.009321373 | F3: =IFERROR('QTR CF'!F3/'QTR P&L'!F2,"") -> 0.011076397 | G3: =IFERROR('QTR CF'!G3/'QTR P&L'!G2,"") -> 0.00937935 | H3: =IFERROR('QTR CF'!H3/'QTR P&L'!H2,"") -> 0.0093771468 | I3: =IFERROR('QTR CF'!I3/'QTR P&L'!I2,"") -> 0.0066236551 | ... Y3: =IFERROR('QTR CF'!Y3/'QTR P&L'!Y2,"") -> 0.015212198 | Z3: =Y3 -> 0.015212198 | AA3: =Z3 -> 0.015212198 | AB3: =AA3 -> 0.015212198 | AC3: =AB3 -> 0.015212198 | AD3: =AC3 -> 0.015212198 | AE3: =AD3 -> 0.015212198 | AF3: =AE3 -> 0.015212198 | AG3: =AF3 -> 0.015212198 | ... AS3: =AR3 -> 0.015212198
A4: Non-Cash Lease Expense | B4: ='QTR CF'!B4 -> 0 | C4: ='QTR CF'!C4 -> 0 | D4: ='QTR CF'!D4 -> 0 | E4: ='QTR CF'!E4 -> 3943 | F4: ='QTR CF'!F4 -> 0 | G4: ='QTR CF'!G4 -> 0 | H4: ='QTR CF'!H4 -> 0 | I4: ='QTR CF'!I4 -> 4107 | ... Y4: ='QTR CF'!Y4 -> 5132 | Z4: 0 | AA4: 0 | AB4: 0 | AC4: 0 | AD4: 0 | AE4: 0 | AF4: 0 | AG4: 0 | AH4: 0 | AI4: 0 | AJ4: 0 | AK4: 0 | AL4: 0 | AM4: 0 | AN4: 0 | AO4: 0 | AP4: 0 | AQ4: 0 | AR4: 0 | AS4: 0
A5: Gain (Loss) on Disposal of PP&E | B5: ='QTR CF'!B5 -> -58 | C5: ='QTR CF'!C5 -> -121 | D5: ='QTR CF'!D5 -> -31 | E5: ='QTR CF'!E5 -> -140 | F5: ='QTR CF'!F5 -> -88 | G5: ='QTR CF'!G5 -> -734 | H5: ='QTR CF'!H5 -> -162 | I5: ='QTR CF'!I5 -> -29 | ... Y5: ='QTR CF'!Y5 -> 3697 | Z5: 0 | AA5: 0 | AB5: 0 | AC5: 0 | AD5: 0 | AE5: 0 | AF5: 0 | AG5: 0 | AH5: 0 | AI5: 0 | AJ5: 0 | AK5: 0 | AL5: 0 | AM5: 0 | AN5: 0 | AO5: 0 | AP5: 0 | AQ5: 0 | AR5: 0 | AS5: 0
A6: Gain on Bang Transaction | B6: ='QTR CF'!B6 -> 0 | C6: ='QTR CF'!C6 -> 0 | D6: ='QTR CF'!D6 -> 0 | E6: ='QTR CF'!E6 -> 0 | F6: ='QTR CF'!F6 -> 0 | G6: ='QTR CF'!G6 -> 0 | H6: ='QTR CF'!H6 -> 0 | I6: ='QTR CF'!I6 -> 0 | ... Y6: ='QTR CF'!Y6 -> 0 | Z6: 0 | AA6: 0 | AB6: 0 | AC6: 0 | AD6: 0 | AE6: 0 | AF6: 0 | AG6: 0 | AH6: 0 | AI6: 0 | AJ6: 0 | AK6: 0 | AL6: 0 | AM6: 0 | AN6: 0 | AO6: 0 | AP6: 0 | AQ6: 0 | AR6: 0 | AS6: 0
A7: Impairment of Intangibles | B7: ='QTR CF'!B7 -> 3000 | C7: ='QTR CF'!C7 -> 1000 | D7: ='QTR CF'!D7 -> 3000 | E7: ='QTR CF'!E7 -> 1700 | F7: ='QTR CF'!F7 -> 0 | G7: ='QTR CF'!G7 -> 0 | H7: ='QTR CF'!H7 -> 0 | I7: ='QTR CF'!I7 -> 0 | ... Y7: ='QTR CF'!Y7 -> 38411 | Z7: 0 | AA7: 0 | AB7: 0 | AC7: 0 | AD7: 0 | AE7: 0 | AF7: 0 | AG7: 0 | AH7: 0 | AI7: 0 | AJ7: 0 | AK7: 0 | AL7: 0 | AM7: 0 | AN7: 0 | AO7: 0 | AP7: 0 | AQ7: 0 | AR7: 0 | AS7: 0
A8: Impairment of Long-Lived Assets (PP&E) | B8: ='QTR CF'!B8 -> 0 | C8: ='QTR CF'!C8 -> 0 | D8: ='QTR CF'!D8 -> 0 | E8: ='QTR CF'!E8 -> 0 | F8: ='QTR CF'!F8 -> 0 | G8: ='QTR CF'!G8 -> 0 | H8: ='QTR CF'!H8 -> 0 | I8: ='QTR CF'!I8 -> 0 | ... Y8: ='QTR CF'!Y8 -> 9750 | Z8: 0 | AA8: 0 | AB8: 0 | AC8: 0 | AD8: 0 | AE8: 0 | AF8: 0 | AG8: 0 | AH8: 0 | AI8: 0 | AJ8: 0 | AK8: 0 | AL8: 0 | AM8: 0 | AN8: 0 | AO8: 0 | AP8: 0 | AQ8: 0 | AR8: 0 | AS8: 0
A9: Stock-Based Compensation — % of Revenue | B9: =IFERROR('QTR CF'!B9/'QTR P&L'!B2,"") -> 0.016098341 | C9: =IFERROR('QTR CF'!C9/'QTR P&L'!C2,"") -> 0.014568113 | D9: =IFERROR('QTR CF'!D9/'QTR P&L'!D2,"") -> 0.016053121 | E9: =IFERROR('QTR CF'!E9/'QTR P&L'!E2,"") -> 0.014417157 | F9: =IFERROR('QTR CF'!F9/'QTR P&L'!F2,"") -> 0.014762634 | G9: =IFERROR('QTR CF'!G9/'QTR P&L'!G2,"") -> 0.011853468 | H9: =IFERROR('QTR CF'!H9/'QTR P&L'!H2,"") -> 0.011839295 | I9: =IFERROR('QTR CF'!I9/'QTR P&L'!I2,"") -> 0.012695748 | ... Y9: =IFERROR('QTR CF'!Y9/'QTR P&L'!Y2,"") -> 0.018311605 | Z9: =Y9 -> 0.018311605 | AA9: =Z9 -> 0.018311605 | AB9: =AA9 -> 0.018311605 | AC9: =AB9 -> 0.018311605 | AD9: =AC9 -> 0.018311605 | AE9: =AD9 -> 0.018311605 | AF9: =AE9 -> 0.018311605 | AG9: =AF9 -> 0.018311605 | ... AS9: =AR9 -> 0.018311605
A10: (Benefit) Provision for Deferred Income Taxes | B10: ='QTR CF'!B10 -> 0 | C10: ='QTR CF'!C10 -> 0 | D10: ='QTR CF'!D10 -> 0 | E10: ='QTR CF'!E10 -> -156873 | F10: ='QTR CF'!F10 -> 0 | G10: ='QTR CF'!G10 -> 353 | H10: ='QTR CF'!H10 -> 0 | I10: ='QTR CF'!I10 -> 16076 | ... Y10: ='QTR CF'!Y10 -> 3755 | Z10: =Y10 -> 3755 | AA10: =Z10 -> 3755 | AB10: =AA10 -> 3755 | AC10: =AB10 -> 3755 | AD10: =AC10 -> 3755 | AE10: =AD10 -> 3755 | AF10: =AE10 -> 3755 | AG10: =AF10 -> 3755 | ... AS10: =AR10 -> 3755
A11: Accounts Receivable | B11: ='QTR CF'!B11 -> -147660 | C11: ='QTR CF'!C11 -> -84122 | D11: ='QTR CF'!D11 -> 30105 | E11: ='QTR CF'!E11 -> 82005 | F11: ='QTR CF'!F11 -> -147544 | G11: ='QTR CF'!G11 -> -92156 | H11: ='QTR CF'!H11 -> 39991 | I11: ='QTR CF'!I11 -> -54519 | ... Y11: ='QTR CF'!Y11 -> -1461 | Z11: =-('QTR BS'!W4-'QTR BS'!V4) -> -37965.79 | AA11: =-('QTR BS'!X4-'QTR BS'!W4) -> -229519.93 | AB11: =-('QTR BS'!Y4-'QTR BS'!X4) -> -76390.558 | AC11: =-('QTR BS'!Z4-'QTR BS'!Y4) -> 59012.751 | AD11: =-('QTR BS'!AA4-'QTR BS'!Z4) -> -44649.712 | AE11: =-('QTR BS'!AB4-'QTR BS'!AA4) -> -269927.19 | AF11: =-('QTR BS'!AC4-'QTR BS'!AB4) -> -89839.208 | AG11: =-('QTR BS'!AD4-'QTR BS'!AC4) -> 69402.017 | ... AS11: =-('QTR BS'!AP4-'QTR BS'!AO4) -> 112888.78
A12: Distributor Receivables | B12: ='QTR CF'!B12 -> 176 | C12: ='QTR CF'!C12 -> 12 | D12: ='QTR CF'!D12 -> 153 | E12: ='QTR CF'!E12 -> 0 | F12: ='QTR CF'!F12 -> 92 | G12: ='QTR CF'!G12 -> 68 | H12: ='QTR CF'!H12 -> 68 | I12: ='QTR CF'!I12 -> 0 | ... Y12: ='QTR CF'!Y12 -> 0 | Z12: 0 | AA12: 0 | AB12: 0 | AC12: 0 | AD12: 0 | AE12: 0 | AF12: 0 | AG12: 0 | AH12: 0 | AI12: 0 | AJ12: 0 | AK12: 0 | AL12: 0 | AM12: 0 | AN12: 0 | AO12: 0 | AP12: 0 | AQ12: 0 | AR12: 0 | AS12: 0
A13: Inventories | B13: ='QTR CF'!B13 -> 1037 | C13: ='QTR CF'!C13 -> 13144 | D13: ='QTR CF'!D13 -> 25309 | E13: ='QTR CF'!E13 -> -9186 | F13: ='QTR CF'!F13 -> -39546 | G13: ='QTR CF'!G13 -> -12995 | H13: ='QTR CF'!H13 -> -96873 | I13: ='QTR CF'!I13 -> -128379 | ... Y13: ='QTR CF'!Y13 -> -93305 | Z13: =-('QTR BS'!W5-'QTR BS'!V5) -> -18762.032 | AA13: =-('QTR BS'!X5-'QTR BS'!W5) -> -113424.75 | AB13: =-('QTR BS'!Y5-'QTR BS'!X5) -> -37750.883 | AC13: =-('QTR BS'!Z5-'QTR BS'!Y5) -> 29163.074 | AD13: =-('QTR BS'!AA5-'QTR BS'!Z5) -> -22065.11 | AE13: =-('QTR BS'!AB5-'QTR BS'!AA5) -> -133393.31 | AF13: =-('QTR BS'!AC5-'QTR BS'!AB5) -> -44396.972 | AG13: =-('QTR BS'!AD5-'QTR BS'!AC5) -> 34297.268 | ... AS13: =-('QTR BS'!AP5-'QTR BS'!AO5) -> 55787.669
A14: Prepaid Expenses | B14: ='QTR CF'!B14 -> -18081 | C14: ='QTR CF'!C14 -> -5313 | D14: ='QTR CF'!D14 -> 2948 | E14: ='QTR CF'!E14 -> 21470 | F14: ='QTR CF'!F14 -> -18487 | G14: ='QTR CF'!G14 -> -9745 | H14: ='QTR CF'!H14 -> -12930 | I14: ='QTR CF'!I14 -> 11821 | ... Y14: ='QTR CF'!Y14 -> 26962 | Z14: =-('QTR BS'!W6-'QTR BS'!V6) -> -2429.6789 | AA14: =-('QTR BS'!X6-'QTR BS'!W6) -> -14688.48 | AB14: =-('QTR BS'!Y6-'QTR BS'!X6) -> -4888.731 | AC14: =-('QTR BS'!Z6-'QTR BS'!Y6) -> 3776.6115 | AD14: =-('QTR BS'!AA6-'QTR BS'!Z6) -> -2857.4269 | AE14: =-('QTR BS'!AB6-'QTR BS'!AA6) -> -17274.404 | AF14: =-('QTR BS'!AC6-'QTR BS'!AB6) -> -5749.3979 | AG14: =-('QTR BS'!AD6-'QTR BS'!AC6) -> 4441.4885 | ... AS14: =-('QTR BS'!AP6-'QTR BS'!AO6) -> 7224.4907
A15: Change in Prepaid Income Taxes | B15: ='QTR CF'!B15 -> 8078 | C15: ='QTR CF'!C15 -> -833 | D15: ='QTR CF'!D15 -> 4215 | E15: ='QTR CF'!E15 -> -5944 | F15: ='QTR CF'!F15 -> -7076 | G15: ='QTR CF'!G15 -> 9528 | H15: ='QTR CF'!H15 -> -9817 | I15: ='QTR CF'!I15 -> -3554 | ... Y15: ='QTR CF'!Y15 -> -35137 | Z15: =-('QTR BS'!W7-'QTR BS'!V7) -> -1751.2525 | AA15: =-('QTR BS'!X7-'QTR BS'!W7) -> -10587.093 | AB15: =-('QTR BS'!Y7-'QTR BS'!X7) -> -3523.6764 | AC15: =-('QTR BS'!Z7-'QTR BS'!Y7) -> 2722.0882 | AD15: =-('QTR BS'!AA7-'QTR BS'!Z7) -> -2059.5626 | AE15: =-('QTR BS'!AB7-'QTR BS'!AA7) -> -12450.964 | AF15: =-('QTR BS'!AC7-'QTR BS'!AB7) -> -4144.0239 | AG15: =-('QTR BS'!AD7-'QTR BS'!AC7) -> 3201.3151 | ... AS15: =-('QTR BS'!AP7-'QTR BS'!AO7) -> 5207.2343
A16: Accounts Payable | B16: ='QTR CF'!B16 -> 19328 | C16: ='QTR CF'!C16 -> -26100 | D16: ='QTR CF'!D16 -> -2952 | E16: ='QTR CF'!E16 -> 28420 | F16: ='QTR CF'!F16 -> 36859 | G16: ='QTR CF'!G16 -> 26760 | H16: ='QTR CF'!H16 -> 42951 | I16: ='QTR CF'!I16 -> 7727 | ... Y16: ='QTR CF'!Y16 -> -70115 | Z16: =('QTR BS'!W16-'QTR BS'!V16) -> 13279.786 | AA16: =('QTR BS'!X16-'QTR BS'!W16) -> 80282.158 | AB16: =('QTR BS'!Y16-'QTR BS'!X16) -> 26720.115 | AC16: =('QTR BS'!Z16-'QTR BS'!Y16) -> -20641.654 | AD16: =('QTR BS'!AA16-'QTR BS'!Z16) -> 15617.708 | AE16: =('QTR BS'!AB16-'QTR BS'!AA16) -> 94415.928 | AF16: =('QTR BS'!AC16-'QTR BS'!AB16) -> 31424.223 | AG16: =('QTR BS'!AD16-'QTR BS'!AC16) -> -24275.642 | ... AS16: =('QTR BS'!AP16-'QTR BS'!AO16) -> -39486.571
A17: Accrued Expenses | B17: ='QTR CF'!B17 -> 34500 | C17: ='QTR CF'!C17 -> -2809 | D17: ='QTR CF'!D17 -> 21810 | E17: ='QTR CF'!E17 -> -27388 | F17: ='QTR CF'!F17 -> 32441 | G17: ='QTR CF'!G17 -> -2558 | H17: ='QTR CF'!H17 -> 4202 | I17: ='QTR CF'!I17 -> 37501 | ... Y17: ='QTR CF'!Y17 -> -17194 | Z17: =('QTR BS'!W17-'QTR BS'!V17) -> 7181.8551 | AA17: =('QTR BS'!X17-'QTR BS'!W17) -> 43417.479 | AB17: =('QTR BS'!Y17-'QTR BS'!X17) -> 14450.534 | AC17: =('QTR BS'!Z17-'QTR BS'!Y17) -> -11163.235 | AD17: =('QTR BS'!AA17-'QTR BS'!Z17) -> 8446.2294 | AE17: =('QTR BS'!AB17-'QTR BS'!AA17) -> 51061.178 | AF17: =('QTR BS'!AC17-'QTR BS'!AB17) -> 16994.568 | AG17: =('QTR BS'!AD17-'QTR BS'!AC17) -> -13128.536 | ... AS17: =('QTR BS'!AP17-'QTR BS'!AO17) -> -21354.774
