Workbook

Sheet ANNL P&L
B1: FY2021 | C1: FY2022 | D1: FY2023 | E1: FY2024 | F1: FY2025 | G1: FY2026E | H1: FY2027E | I1: FY2028E | J1: FY2029E | K1: FY2030E | L1: FY2031E
A2: Net Sales / Revenue | B2: 79474 | C2: 86392 | D2: 91471 | E2: 91854 | F2: 93925
A3: COGS | B3: -37075 | C3: -40576 | D3: -41881 | E3: -41744 | F3: -43066
A4: Gross Profit (Loss) | B4: =B2+B3 | C4: =C2+C3 | D4: =D2+D3 | E4: =E2+E3 | F4: =F2+F3 | G4: =G2+G3 | H4: =H2+H3 | I4: =I2+I3 | ... L4: =L2+L3
A5: SG&A | B5: -31237 | C5: -34459 | D5: -36677 | E5: -37190 | F5: -37368
A6: Gain on Juice Transaction | B6: 0 | C6: -3321 | D6: 0 | E6: 0 | F6: 0
A7: Impairment of Intangibles | B7: 0 | C7: -3166 | D7: -927 | E7: -33 | F7: -1993
A8: Income (Loss) from Operations | B8: =B4+SUM(B5:B7) | C8: =C4+SUM(C5:C7) | D8: =D4+SUM(D5:D7) | E8: =E4+SUM(E5:E7) | F8: =F4+SUM(F5:F7) | G8: =G4+SUM(G5:G7) | H8: =H4+SUM(H5:H7) | I8: =I4+SUM(I5:I7) | ... L8: =L4+SUM(L5:L7)
A9: Other Pension and OPEB Benefits Income (Expense) | B9: 522 | C9: 132 | D9: 250 | E9: -22 | F9: -133
A10: Interest Income (Expense) | B10: -1863 | C10: -939 | D10: -819 | E10: -919 | F10: -1121
A11: Pre-Tax Income (Loss) | B11: =B8+SUM(B9:B10) | C11: =C8+SUM(C9:C10) | D11: =D8+SUM(D9:D10) | E11: =E8+SUM(E9:E10) | F11: =F8+SUM(F9:F10) | G11: =G8+SUM(G9:G10) | H11: =H8+SUM(H9:H10) | I11: =I8+SUM(I9:I10) | ... L11: =L8+SUM(L9:L10)
A12: Income Tax (Expense) Benefit | B12: -2142 | C12: -1727 | D12: -2262 | E12: -2320 | F12: -1949
A13: Net Income (Loss) | B13: =B11+B12 | C13: =C11+C12 | D13: =D11+D12 | E13: =E11+E12 | F13: =F11+F12 | G13: =G11+G12 | H13: =H11+H12 | I13: =I11+I12 | ... L13: =L11+L12
A14: Net Income (Loss) Attributable to Noncontrolling Interest | B14: 61 | C14: 68 | D14: 81 | E14: 48 | F14: 55
A15: Net Income (Loss) Less NCI | B15: =B13-B14 | C15: =C13-C14 | D15: =D13-D14 | E15: =E13-E14 | F15: =F13-F14 | G15: =G13-G14 | H15: =H13-H14 | I15: =I13-I14 | ... L15: =L13-L14
A16: Basic Earnings (Loss) per Share | B16: 5.51 | C16: 6.45 | D16: 6.59 | E16: 6.97 | F16: 6.02
A17: Diluted Earnings (Loss) per Share | B17: 5.49 | C17: 6.42 | D17: 6.56 | E17: 6.95 | F17: 6
A18: Weighted Average Shares Outstanding (Basic) | B18: 1382000000 | C18: 1380000000 | D18: 1376000000 | E18: 1373000000 | F18: 1369000000
A19: Weighted Average Shares Outstanding (Diluted) | B19: 1389000000 | C19: 1387000000 | D19: 1383000000 | E19: 1378000000 | F19: 1373000000

Sheet BALANCE SHEET
B1: FY2022 | C1: FY2023 | D1: FY2024 | E1: FY2025 | F1: FY2026E | G1: FY2027E | H1: FY2028E | I1: FY2029E | J1: FY2030E | K1: FY2031E
A2: Cash & Cash Equivalents | B2: 4954 | C2: 9711 | D2: 8505 | E2: 9159
A3: Short-Term Investments | B3: 394 | C3: 292 | D3: 761 | E3: 371
A4: Accounts Receivable | B4: 10163 | C4: 10815 | D4: 10333 | E4: 11506
A5: Raw Materials | B5: 2366 | C5: 2388 | D5: 2440 | E5: 2581
A6: Work in Process | B6: 114 | C6: 104 | D6: 104 | E6: 143
A7: Finished Goods | B7: 2742 | C7: 2842 | D7: 2762 | E7: 3121
A8: Inventories | B8: =SUM(B5,B6,B7) | C8: =SUM(C5,C6,C7) | D8: =SUM(D5,D6,D7) | E8: =SUM(E5,E6,E7)
A9: Prepaid Expenses | B9: 806 | C9: 798 | D9: 921 | E9: 1068
A10: Total Current Assets | B10: =SUM(B2:B9) | C10: =SUM(C2:C9) | D10: =SUM(D2:D9) | E10: =SUM(E2:E9) | F10: =SUM(F2:F9) | G10: =SUM(G2:G9) | H10: =SUM(H2:H9) | I10: =SUM(I2:I9) | ... K10: =SUM(K2:K9)
A11: Net PP&E | B11: 24291 | C11: 27039 | D11: 28008 | E11: 29905
A12: Intangible Assets | B12: 15586 | C12: 14929 | D12: 14801 | E12: 15066
A13: Goodwill | B13: 18202 | C13: 17728 | D13: 17534 | E13: 18916
A14: Equity Method Investments | B14: 3073 | C14: 2714 | D14: 1985 | E14: 2038
A15: Deferred Tax Assets | B15: 4204 | C15: 4474 | D15: 4362 | E15: 4541
A16: Other Non-Current Assets | B16: 5292 | C16: 6661 | D16: 6951 | E16: 8984
A17: Total Assets | B17: =B10+SUM(B11:B16) | C17: =C10+SUM(C11:C16) | D17: =D10+SUM(D11:D16) | E17: =E10+SUM(E11:E16) | F17: =F10+SUM(F11:F16) | G17: =G10+SUM(G11:G16) | H17: =H10+SUM(H11:H16) | I17: =I10+SUM(I11:I16) | ... K17: =K10+SUM(K11:K16)
A18: Short-Term Debt Obligations | B18: 3414 | C18: 6510 | D18: 7082 | E18: 6861
A19: Accrued Expenses | B19: 23371 | C19: 25137 | D19: 24454 | E19: 25903
A20: Total Current Liabilities | B20: =SUM(B18:B19) | C20: =SUM(C18:C19) | D20: =SUM(D18:D19) | E20: =SUM(E18:E19) | F20: =SUM(F18:F19) | G20: =SUM(G18:G19) | H20: =SUM(H18:H19) | I20: =SUM(I18:I19) | ... K20: =SUM(K18:K19)
A21: Long-Term Debt | B21: 35657 | C21: 37595 | D21: 37224 | E21: 42321
A22: Deferred Tax Liability | B22: 4133 | C22: 3895 | D22: 3484 | E22: 3802
A23: Other Non-Current Liabilities | B23: 8339 | C23: 8721 | D23: 9052 | E23: 7965
A24: Total Liabilities | B24: =B20+SUM(B21:B23) | C24: =C20+SUM(C21:C23) | D24: =D20+SUM(D21:D23) | E24: =E20+SUM(E21:E23) | F24: =F20+SUM(F21:F23) | G24: =G20+SUM(G21:G23) | H24: =H20+SUM(H21:H23) | I24: =I20+SUM(I21:I23) | ... K24: =K20+SUM(K21:K23)
A25: Common Stock | B25: 23 | C25: 23 | D25: 23 | E25: 23
A26: Additional Paid-in Capital | B26: 4134 | C26: 4261 | D26: 4385 | E26: 4451
A27: Retained Earnings (Accumulated Deficit) | B27: 67800 | C27: 70035 | D27: 72266 | E27: 72788
A28: Accumulated Other Comprehensive Income (Loss) | B28: -15302 | C28: -15534 | D28: -17612 | E28: -15024
A29: Treasury Stock | B29: -39506 | C29: -40282 | D29: -41021 | E29: -41832
A30: Noncontrolling Interest | B30: 124 | C30: 134 | D30: 130 | E30: 141
A31: Total Stockholders' Equity | B31: =SUM(B25:B30) | C31: =SUM(C25:C30) | D31: =SUM(D25:D30) | E31: =SUM(E25:E30) | F31: =SUM(F25:F30) | G31: =SUM(G25:G30) | H31: =SUM(H25:H30) | I31: =SUM(I25:I30) | ... K31: =SUM(K25:K30)
A32: Total Liabilities, Mezzanine & Stockholders' Equity | B32: =B24+B31 | C32: =C24+C31 | D32: =D24+D31 | E32: =E24+E31 | F32: =F24+F31 | G32: =G24+G31 | H32: =H24+H31 | I32: =I24+I31 | ... K32: =K24+K31

Sheet CASH FLOW
B1: FY2021 | C1: FY2022 | D1: FY2023 | E1: FY2024 | F1: FY2025 | G1: FY2026E | H1: FY2027E | I1: FY2028E | J1: FY2029E | K1: FY2030E | L1: FY2031E
A2: Net Income (Loss) | B2: 7679 | C2: 8978 | D2: 9155 | E2: 9626 | F2: 8295
A3: Depreciation & Amortization | B3: 2710 | C3: 2763 | D3: 2948 | E3: 3160 | F3: 3451
A4: Gain on Juice Transaction | B4: 0 | C4: -3321 | D4: 0 | E4: 0 | F4: 0
A5: Impairment and Other Charges | B5: 0 | C5: 3618 | D5: 1230 | E5: 714 | F5: 1946
A6: Indirect Tax Impact | B6: 0 | C6: 0 | D6: 0 | E6: 218 | F6: 0
A7: Product Recall Impact | B7: 0 | C7: 0 | D7: 136 | E7: 187 | F7: 0
A8: Cash Payments for Product Recall | B8: 0 | C8: 0 | D8: 0 | E8: -148 | F8: -6
A9: Non-Cash Lease Expense | B9: 505 | C9: 517 | D9: 570 | E9: 655 | F9: 727
A10: Stock-Based Compensation | B10: 301 | C10: 343 | D10: 380 | E10: 362 | F10: 288
A11: Restructuring and Asset Impairment Charges | B11: 247 | C11: 411 | D11: 445 | E11: 727 | F11: 983
A12: Cash Payments for Restructuring | B12: -256 | C12: -224 | D12: -434 | E12: -436 | F12: -796
A13: Acquisition and Divestiture-Related Charges | B13: -4 | C13: 80 | D13: 41 | E13: 0 | F13: 453
... A25: Other Operating Items | B25: 375 | C25: -359 | D25: 189 | E25: -307 | F25: -712
A26: Cash Flow from Operations | B26: =SUM(B2:B25) | C26: =SUM(C2:C25) | D26: =SUM(D2:D25) | E26: =SUM(E2:E25) | F26: =SUM(F2:F25) | G26: =SUM(G2:G25) | H26: =SUM(H2:H25) | I26: =SUM(I2:I25) | ... L26: =SUM(L2:L25)
A27: Purchase of PP&E | B27: -4625 | C27: -5207 | D27: -5518 | E27: -5318 | F27: -4415
A28: Proceeds from Sale of Assets | B28: 166 | C28: 251 | D28: 198 | E28: 342 | F28: 528
A29: Acquisitions, Net of Cash Acquired | B29: -61 | C29: -873 | D29: -314 | E29: -256 | F29: -3391
A30: Proceeds from Juice Transaction | B30: 0 | C30: 3456 | D30: 0 | E30: 0 | F30: 0
A31: Proceeds from Divestitures of Businesses | B31: 169 | C31: 49 | D31: 75 | E31: 166 | F31: 39
A32: Net Change in Short-Term Investments | B32: 1077 | C32: -117 | D32: 16 | E32: -420 | F32: 460
A33: Other Investing Activities | B33: 5 | C33: 11 | D33: 48 | E33: 14 | F33: -100
A34: Cash Flow from Investing | B34: =SUM(B27:B33) | C34: =SUM(C27:C33) | D34: =SUM(D27:D33) | E34: =SUM(E27:E33) | F34: =SUM(F27:F33) | G34: =SUM(G27:G33) | H34: =SUM(H27:H33) | I34: =SUM(I27:I33) | ... L34: =SUM(L27:L33)
A35: Proceeds from Issuance of Long-Term Debt | B35: 4122 | C35: 3377 | D35: 5482 | E35: 4042 | F35: 8189
A36: Repayments of Long-Term Debt | B36: -8299 | C36: -4174 | D36: -3005 | E36: -3886 | F36: -4082
A37: Proceeds from Short-Term Debt | B37: 8 | C37: 1969 | D37: 5428 | E37: 5786 | F37: 6391
A38: Repayments of Short-Term Debt | B38: -397 | C38: -1951 | D38: -3106 | E38: -5639 | F38: -7920
A39: Net Change in Other Short-Term Debt | B39: 434 | C39: -31 | D39: -29 | E39: 392 | F39: 1170
A40: Payments of Contingent Consideration | B40: -773 | C40: 0 | D40: 0 | E40: 0 | F40: 0
A41: Common Dividends | B41: -5815 | C41: -6172 | D41: -6682 | E41: -7229 | F41: -7638
A42: Share Repurchases | B42: -106 | C42: -1500 | D42: -1000 | E42: -1000 | F42: -1000
A43: Proceeds from Exercise of Stock Options | B43: 185 | C43: 138 | D43: 116 | E43: 166 | F43: 97
A44: Tax Withholdings on RSU/PSU Settlement | B44: -92 | C44: -107 | D44: -140 | E44: -135 | F44: -113
A45: Other Financing Activities | B45: -47 | C45: -72 | D45: -73 | E45: -53 | F45: -73
A46: Cash Flow from Financing | B46: =SUM(B35:B45) | C46: =SUM(C35:C45) | D46: =SUM(D35:D45) | E46: =SUM(E35:E45) | F46: =SUM(F35:F45) | G46: =SUM(G35:G45) | H46: =SUM(H35:H45) | I46: =SUM(I35:I45) | ... L46: =SUM(L35:L45)
A47: FX Effect on Cash | B47: -114 | C47: -465 | D47: -277 | E47: -687 | F47: 422
A48: Net Change in Cash | B48: =B26+B34+B46+B47 | C48: =C26+C34+C46+C47 | D48: =D26+D34+D46+D47 | E48: =E26+E34+E46+E47 | F48: =F26+F34+F46+F47 | G48: =G26+G34+G46+G47 | H48: =H26+H34+H46+H47 | I48: =I26+I34+I46+I47 | ... L48: =L26+L34+L46+L47

Sheet YTD P&L
B1: Q1 FY2022 | C1: Q2 FY2022 | D1: Q3 FY2022 | E1: Q1 FY2023 | F1: Q2 FY2023 | G1: Q3 FY2023 | H1: Q1 FY2024 | I1: Q2 FY2024 | J1: Q3 FY2024 | K1: Q1 FY2025 | L1: Q2 FY2025 | M1: Q3 FY2025 | N1: Q1 FY2026
A2: Net Sales / Revenue | B2: 16200 | C2: 36425 | D2: 58396 | E2: 17846 | F2: 40168 | G2: 63621 | H2: 18250 | I2: 40751 | J2: 64070 | K2: 17919 | L2: 40645 | M2: 64582 | N2: 19443
A3: COGS | B3: -7433 | C3: -16848 | D3: -27156 | E3: -7988 | F3: -18109 | G3: -28784 | H3: -8248 | I3: -18167 | J3: -28563 | K3: -7926 | L3: -18230 | M3: -29343 | N3: -8712
A4: Gross Profit (Loss) | B4: =B2+B3 | C4: =C2+C3 | D4: =D2+D3 | E4: =E2+E3 | F4: =F2+F3 | G4: =G2+G3 | H4: =H2+H3 | I4: =I2+I3 | ... N4: =N2+N3
A5: SG&A | B5: -6580 | C5: -13967 | D5: -22262 | E5: -7229 | F5: -15771 | G5: -24528 | H5: -7285 | I5: -15819 | J5: -24870 | K5: -7410 | L5: -16183 | M5: -25305 | N5: -7518
A6: Gain on Juice Transaction | B6: -3322 | C6: -3335 | D6: -3321 | E6: 0 | F6: 0 | G6: 0 | H6: 0 | I6: 0 | J6: 0 | K6: 0 | L6: 0 | M6: 0 | N6: 0
A7: Impairment of Intangibles | B7: -242 | C7: -1601 | D7: -1602 | E7: 0 | F7: 0 | G7: -6 | H7: 0 | I7: 0 | J7: 0 | K7: 0 | L7: -1860 | M7: -1993 | N7: 0
A8: Income (Loss) from Operations | B8: =B4+SUM(B5:B7) | C8: =C4+SUM(C5:C7) | D8: =D4+SUM(D5:D7) | E8: =E4+SUM(E5:E7) | F8: =F4+SUM(F5:F7) | G8: =G4+SUM(G5:G7) | H8: =H4+SUM(H5:H7) | I8: =I4+SUM(I5:I7) | ... N8: =N4+SUM(N5:N7)
A9: Other Pension and OPEB Benefits Income (Expense) | B9: 134 | C9: 132 | D9: 168 | E9: 61 | F9: 121 | G9: 183 | H9: 58 | I9: 114 | J9: 155 | K9: 23 | L9: 65 | M9: 91 | N9: 58
A10: Interest Income (Expense) | B10: -240 | C10: -476 | D10: -666 | E10: -200 | F10: -401 | G10: -602 | H10: -202 | I10: -436 | J10: -655 | K10: -264 | L10: -524 | M10: -788 | N10: -301
A11: Pre-Tax Income (Loss) | B11: =B8+SUM(B9:B10) | C11: =C8+SUM(C9:C10) | D11: =D8+SUM(D9:D10) | E11: =E8+SUM(E9:E10) | F11: =F8+SUM(F9:F10) | G11: =G8+SUM(G9:G10) | H11: =H8+SUM(H9:H10) | I11: =I8+SUM(I9:I10) | ... N11: =N8+SUM(N9:N10)
A12: Income Tax (Expense) Benefit | B12: -888 | C12: -1281 | D12: -1756 | E12: -546 | F12: -1293 | G12: -2053 | H12: -520 | I12: -1296 | J12: -2045 | K12: -499 | L12: -791 | M12: -1504 | N12: -632
A13: Net Income (Loss) | B13: =B11+B12 | C13: =C11+C12 | D13: =D11+D12 | E13: =E11+E12 | F13: =F11+F12 | G13: =G11+G12 | H13: =H11+H12 | I13: =I11+I12 | ... N13: =N11+N12
A14: Net Income (Loss) Attributable to Noncontrolling Interest | B14: 12 | C14: 29 | D14: 51 | E14: 12 | F14: 35 | G14: 59 | H14: 11 | I14: 22 | J14: 37 | K14: 9 | L14: 25 | M14: 40 | N14: 11
A15: Net Income (Loss) Less NCI | B15: =B13-B14 | C15: =C13-C14 | D15: =D13-D14 | E15: =E13-E14 | F15: =F13-F14 | G15: =G13-G14 | H15: =H13-H14 | I15: =I13-I14 | ... N15: =N13-N14
A16: Basic Earnings (Loss) per Share | B16: 3.08 | C16: 4.11 | D16: 6.07 | E16: 1.4 | F16: 3.4 | G16: 5.64 | H16: 1.49 | I16: 3.73 | J16: 5.86 | K16: 1.34 | L16: 2.26 | M16: 4.16 | N16: 1.7
A17: Diluted Earnings (Loss) per Share | B17: 3.06 | C17: 4.09 | D17: 6.04 | E17: 1.4 | F17: 3.38 | G17: 5.62 | H17: 1.48 | I17: 3.71 | J17: 5.84 | K17: 1.33 | L17: 2.25 | M17: 4.15 | N17: 1.7
A18: Weighted Average Shares Outstanding (Basic) | B18: 1383000000 | C18: 1383000000 | D18: 1382000000 | E18: 1378000000 | F18: 1378000000 | G18: 1377000000 | H18: 1375000000 | I18: 1375000000 | J18: 1374000000 | K18: 1372000000 | L18: 1371000000 | M18: 1370000000 | N18: 1367000000
A19: Weighted Average Shares Outstanding (Diluted) | B19: 1391000000 | C19: 1390000000 | D19: 1389000000 | E19: 1384000000 | F19: 1384000000 | G19: 1384000000 | H19: 1380000000 | I19: 1380000000 | J19: 1379000000 | K19: 1376000000 | L19: 1374000000 | M19: 1373000000 | N19: 1371000000

Sheet YTD BS
B1: Q4 FY2022 | C1: Q1 FY2023 | D1: Q2 FY2023 | E1: Q3 FY2023 | F1: Q4 FY2023 | G1: Q1 FY2024 | H1: Q2 FY2024 | I1: Q3 FY2024 | J1: Q4 FY2024 | K1: Q1 FY2025 | L1: Q2 FY2025 | M1: Q3 FY2025 | N1: Q4 FY2025 | O1: Q1 FY2026
A2: Cash & Cash Equivalents | B2: 4954 | C2: 4770 | D2: 6116 | E2: 10017 | F2: 9711 | G2: 8047 | H2: 6353 | I2: 7308 | J2: 8505 | K2: 8268 | L2: 7631 | M2: 8126 | N2: 9159 | O2: 10475
A3: Short-Term Investments | B3: 394 | C3: 434 | D3: 338 | E3: 266 | F3: 292 | G3: 303 | H3: 315 | I3: 743 | J3: 761 | K3: 314 | L3: 342 | M3: 535 | N3: 371 | O3: 353
A4: Accounts Receivable | B4: 10163 | C4: 10469 | D4: 11456 | E4: 11782 | F4: 10815 | G4: 10938 | H4: 11942 | I4: 12088 | J4: 10333 | K4: 10800 | L4: 12390 | M4: 12634 | N4: 11506 | O4: 12171
A5: Raw Materials | B5: 2366 | C5: 2435 | D5: 2638 | E5: 2456 | F5: 2388 | G5: 2465 | H5: 2635 | I5: 2559 | J5: 2440 | K5: 2673 | L5: 2940 | M5: 2805 | N5: 2581 | O5: 2714
A6: Work in Process | B6: 114 | C6: 115 | D6: 110 | E6: 119 | F6: 104 | G6: 97 | H6: 121 | I6: 131 | J6: 104 | K6: 118 | L6: 135 | M6: 154 | N6: 143 | O6: 133
A7: Finished Goods | B7: 2742 | C7: 3147 | D7: 3221 | E7: 2983 | F7: 2842 | G7: 3007 | H7: 3131 | I7: 2954 | J7: 2762 | K7: 2869 | L7: 3412 | M7: 3134 | N7: 3121 | O7: 3364
A8: Inventories | B8: =SUM(B5,B6,B7) | C8: =SUM(C5,C6,C7) | D8: =SUM(D5,D6,D7) | E8: =SUM(E5,E6,E7) | F8: =SUM(F5,F6,F7) | G8: =SUM(G5,G6,G7) | H8: =SUM(H5,H6,H7) | I8: =SUM(I5,I6,I7) | ... O8: =SUM(O5,O6,O7)
A9: Prepaid Expenses | B9: 806 | C9: 1057 | D9: 1075 | E9: 1026 | F9: 798 | G9: 1148 | H9: 1206 | I9: 1069 | J9: 921 | K9: 1246 | L9: 1360 | M9: 1334 | N9: 1068 | O9: 1706
A10: Total Current Assets | B10: =SUM(B2:B9) | C10: =SUM(C2:C9) | D10: =SUM(D2:D9) | E10: =SUM(E2:E9) | F10: =SUM(F2:F9) | G10: =SUM(G2:G9) | H10: =SUM(H2:H9) | I10: =SUM(I2:I9) | ... O10: =SUM(O2:O9)
A11: Net PP&E | B11: 24291 | C11: 24228 | D11: 24500 | E11: 24853 | F11: 27039 | G11: 26792 | H11: 27042 | I11: 27188 | J11: 28008 | K11: 28213 | L11: 28797 | M11: 29053 | N11: 29905 | O11: 29807
A12: Intangible Assets | B12: 15586 | C12: 15523 | D12: 15562 | E12: 15501 | F12: 14929 | G12: 14853 | H12: 14826 | I12: 14857 | J12: 14801 | K12: 15363 | L12: 15523 | M12: 14852 | N12: 15066 | O12: 15143
A13: Goodwill | B13: 18202 | C13: 18089 | D13: 17997 | E13: 17892 | F13: 17728 | G13: 17646 | H13: 17648 | I13: 17709 | J13: 17534 | K13: 18364 | L13: 18952 | M13: 18845 | N13: 18916 | O13: 19021
A14: Equity Method Investments | B14: 3073 | C14: 3123 | D14: 3038 | E14: 2955 | F14: 2714 | G14: 2734 | H14: 2674 | I14: 2645 | J14: 1985 | K14: 1996 | L14: 2061 | M14: 2084 | N14: 2038 | O14: 2135
A15: Deferred Tax Assets | B15: 4204 | C15: 4211 | D15: 4186 | E15: 4165 | F15: 4474 | G15: 4444 | H15: 4465 | I15: 4321 | J15: 4362 | K15: 4350 | L15: 4293 | M15: 4341 | N15: 4541 | O15: 4560
A16: Other Non-Current Assets | B16: 5292 | C16: 5441 | D16: 5669 | E16: 5938 | F16: 6661 | G16: 7566 | H16: 7175 | I16: 6941 | J16: 6951 | K16: 7163 | L16: 7509 | M16: 8661 | N16: 8984 | O16: 9064
A17: Total Assets | B17: =B10+SUM(B11:B16) | C17: =C10+SUM(C11:C16) | D17: =D10+SUM(D11:D16) | E17: =E10+SUM(E11:E16) | F17: =F10+SUM(F11:F16) | G17: =G10+SUM(G11:G16) | H17: =H10+SUM(H11:H16) | I17: =I10+SUM(I11:I16) | ... O17: =O10+SUM(O11:O16)
A18: Short-Term Debt Obligations | B18: 3414 | C18: 4281 | D18: 7613 | E18: 8937 | F18: 6510 | G18: 8161 | H18: 8289 | I18: 6524 | J18: 7082 | K18: 9099 | L18: 12056 | M18: 6736 | N18: 6861 | O18: 10151
A19: Accrued Expenses | B19: 23371 | C19: 21556 | D19: 22005 | E19: 23723 | F19: 25137 | G19: 22073 | H19: 22859 | I19: 23791 | J19: 24454 | K19: 22412 | L19: 24340 | M19: 24763 | N19: 25903 | O19: 24326
A20: Total Current Liabilities | B20: =SUM(B18:B19) | C20: =SUM(C18:C19) | D20: =SUM(D18:D19) | E20: =SUM(E18:E19) | F20: =SUM(F18:F19) | G20: =SUM(G18:G19) | H20: =SUM(H18:H19) | I20: =SUM(I18:I19) | ... O20: =SUM(O18:O19)
A21: Long-Term Debt | B21: 35657 | C21: 37486 | D21: 36008 | E21: 35837 | F21: 37595 | G21: 37707 | H21: 36638 | I21: 38490 | J21: 37224 | K21: 39419 | L21: 39328 | M21: 44113 | N21: 42321 | O21: 42577
A22: Deferred Tax Liability | B22: 4133 | C22: 4039 | D22: 4113 | E22: 4047 | F22: 3895 | G22: 4087 | H22: 3908 | I22: 3684 | J22: 3484 | K22: 3541 | L22: 3102 | M22: 3474 | N22: 3802 | O22: 4048
A23: Other Non-Current Liabilities | B23: 8339 | C23: 8505 | D23: 8342 | E23: 8439 | F23: 8721 | G23: 8822 | H23: 8259 | I23: 8419 | J23: 9052 | K23: 8737 | L23: 7960 | M23: 7929 | N23: 7965 | O23: 8008
A24: Total Liabilities | B24: =B20+SUM(B21:B23) | C24: =C20+SUM(C21:C23) | D24: =D20+SUM(D21:D23) | E24: =E20+SUM(E21:E23) | F24: =F20+SUM(F21:F23) | G24: =G20+SUM(G21:G23) | H24: =H20+SUM(H21:H23) | I24: =I20+SUM(I21:I23) | ... O24: =O20+SUM(O21:O23)
A25: Common Stock | B25: 23 | C25: 23 | D25: 23 | E25: 23 | F25: 23 | G25: 23 | H25: 23 | I25: 23 | J25: 23 | K25: 23 | L25: 23 | M25: 23 | N25: 23 | O25: 23
A26: Additional Paid-in Capital | B26: 4134 | C26: 3996 | D26: 4082 | E26: 4154 | F26: 4261 | G26: 4132 | H26: 4203 | I26: 4281 | J26: 4385 | K26: 4274 | L26: 4299 | M26: 4374 | N26: 4451 | O26: 4401
A27: Retained Earnings (Accumulated Deficit) | B27: 67800 | C27: 68142 | D27: 69135 | E27: 70479 | F27: 70035 | G27: 70331 | H27: 71545 | I27: 72607 | J27: 72266 | K27: 72238 | L27: 71547 | M27: 72197 | N27: 72788 | O27: 73165
A28: Accumulated Other Comprehensive Income (Loss) | B28: -15302 | C28: -15601 | D28: -15780 | E28: -15794 | F28: -15534 | G28: -15179 | H28: -15786 | I28: -16652 | J28: -17612 | K28: -17078 | L28: -16090 | M28: -15597 | N28: -15024 | O28: -14342
A29: Treasury Stock | B29: -39506 | C29: -39518 | D29: -39775 | E29: -40056 | F29: -40282 | G29: -40260 | H29: -40539 | I29: -40806 | J29: -41021 | K29: -41068 | L29: -41361 | M29: -41609 | N29: -41832 | O29: -41864
A30: Noncontrolling Interest | B30: 124 | C30: 133 | D30: 140 | E30: 164 | F30: 134 | G30: 143 | H30: 134 | I30: 152 | J30: 130 | K30: 140 | L30: 141 | M30: 155 | N30: 141 | O30: 153
A31: Total Stockholders' Equity | B31: =SUM(B25:B30) | C31: =SUM(C25:C30) | D31: =SUM(D25:D30) | E31: =SUM(E25:E30) | F31: =SUM(F25:F30) | G31: =SUM(G25:G30) | H31: =SUM(H25:H30) | I31: =SUM(I25:I30) | ... O31: =SUM(O25:O30)
A32: Total Liabilities, Mezzanine & Stockholders' Equity | B32: =B24+B31 | C32: =C24+C31 | D32: =D24+D31 | E32: =E24+E31 | F32: =F24+F31 | G32: =G24+G31 | H32: =H24+H31 | I32: =I24+I31 | ... O32: =O24+O31

Sheet YTD CF
B1: Q1 FY2022 | C1: Q2 FY2022 | D1: Q3 FY2022 | E1: Q1 FY2023 | F1: Q2 FY2023 | G1: Q3 FY2023 | H1: Q1 FY2024 | I1: Q2 FY2024 | J1: Q3 FY2024 | K1: Q1 FY2025 | L1: Q2 FY2025 | M1: Q3 FY2025 | N1: Q1 FY2026
A2: Net Income (Loss) | B2: 4273 | C2: 5719 | D2: 8443 | E2: 1944 | F2: 4715 | G2: 7831 | H2: 2053 | I2: 5147 | J2: 8092 | K2: 1843 | L2: 3122 | M2: 5740 | N2: 2338
A3: Depreciation & Amortization | B3: 555 | C3: 1195 | D3: 1854 | E3: 590 | F3: 1268 | G3: 1973 | H3: 641 | I3: 1379 | J3: 2118 | K3: 684 | L3: 1491 | M3: 2315 | N3: 742
A4: Gain on Juice Transaction | B4: -3322 | C4: -3335 | D4: -3321 | E4: 0 | F4: 0 | G4: 0 | H4: 0 | I4: 0 | J4: 0 | K4: 0 | L4: 0 | M4: 0 | N4: 0
A5: Impairment and Other Charges | B5: 482 | C5: 1871 | D5: 1877 | E5: -13 | F5: 97 | G5: 102 | H5: 0 | I5: 0 | J5: 10 | K5: 0 | L5: 1860 | M5: 1960 | N5: 0
A6: Indirect Tax Impact | B6: 0 | C6: 0 | D6: 0 | E6: 0 | F6: 0 | G6: 0 | H6: 0 | I6: 0 | J6: 0 | K6: 0 | L6: 0 | M6: 0 | N6: 0
A7: Product Recall Impact | B7: 0 | C7: 0 | D7: 0 | E7: 0 | F7: 0 | G7: 0 | H7: 167 | I7: 182 | J7: 184 | K7: 0 | L7: 0 | M7: 0 | N7: 0
A8: Cash Payments for Product Recall | B8: 0 | C8: 0 | D8: 0 | E8: 0 | F8: 0 | G8: 0 | H8: -108 | I8: -135 | J8: -138 | K8: -2 | L8: -2 | M8: -5 | N8: 0
A9: Non-Cash Lease Expense | B9: 103 | C9: 223 | D9: 346 | E9: 116 | F9: 248 | G9: 384 | H9: 127 | I9: 278 | J9: 438 | K9: 145 | L9: 315 | M9: 489 | N9: 162
A10: Stock-Based Compensation | B10: 81 | C10: 156 | D10: 233 | E10: 93 | F10: 179 | G10: 267 | H10: 97 | I10: 183 | J10: 260 | K10: 77 | L10: 131 | M10: 207 | N10: 93
A11: Restructuring and Asset Impairment Charges | B11: 27 | C11: 75 | D11: 126 | E11: 112 | F11: 204 | G11: 287 | H11: 96 | I11: 170 | J11: 415 | K11: 213 | L11: 426 | M11: 567 | N11: 133
A12: Cash Payments for Restructuring | B12: -32 | C12: -82 | D12: -134 | E12: -64 | F12: -187 | G12: -283 | H12: -60 | I12: -173 | J12: -284 | K12: -232 | L12: -387 | M12: -554 | N12: -145
A13: Acquisition and Divestiture-Related Charges | B13: 56 | C13: 64 | D13: 69 | E13: 2 | F13: 9 | G13: 20 | H13: 0 | I13: 0 | J13: 0 | K13: 0 | L13: 0 | M13: 308 | N13: -113
... A25: Other Operating Items | B25: -133 | C25: -325 | D25: -426 | E25: 46 | F25: -6 | G25: 72 | H25: -68 | I25: -203 | J25: -135 | K25: -232 | L25: -269 | M25: -441 | N25: -157
A26: Cash Flow from Operations | B26: =SUM(B2:B25) | C26: =SUM(C2:C25) | D26: =SUM(D2:D25) | E26: =SUM(E2:E25) | F26: =SUM(F2:F25) | G26: =SUM(G2:G25) | H26: =SUM(H2:H25) | I26: =SUM(I2:I25) | ... N26: =SUM(N2:N25)
A27: Purchase of PP&E | B27: -522 | C27: -1499 | D27: -2556 | E27: -581 | F27: -1513 | G27: -2537 | H27: -614 | I27: -1701 | J27: -2850 | K27: -603 | L27: -1507 | M27: -2499 | N27: -447
A28: Proceeds from Sale of Assets | B28: 3 | C28: 222 | D28: 228 | E28: 19 | F28: 122 | G28: 131 | H28: 7 | I28: 127 | J28: 177 | K28: 132 | L28: 169 | M28: 272 | N28: 13
A29: Acquisitions, Net of Cash Acquired | B29: -13 | C29: -29 | D29: -804 | E29: -16 | F29: -83 | G29: -132 | H29: -6 | I29: -30 | J29: -31 | K29: -1200 | L29: -3130 | M29: -3176 | N29: -67
A30: Proceeds from Juice Transaction | B30: 3456 | C30: 3456 | D30: 3456 | E30: 0 | F30: 0 | G30: 0 | H30: 0 | I30: 0 | J30: 0 | K30: 0 | L30: 0 | M30: 0 | N30: 0
A31: Proceeds from Divestitures of Businesses | B31: 5 | C31: 15 | D31: 15 | E31: 85 | F31: 75 | G31: 75 | H31: 53 | I31: 135 | J31: 145 | K31: 2 | L31: 5 | M31: 5 | N31: 0
A32: Net Change in Short-Term Investments | B32: 22 | C32: 8 | D32: -37 | E32: -39 | F32: -56 | G32: 35 | H32: 8 | I32: 1 | J32: -421 | K32: 441 | L32: 447 | M32: 278 | N32: 5
A33: Other Investing Activities | B33: 4 | C33: -1 | D33: 7 | E33: 0 | F33: 32 | G33: 49 | H33: -10 | I33: 14 | J33: 15 | K33: -4 | L33: -111 | M33: -117 | N33: 19
A34: Cash Flow from Investing | B34: =SUM(B27:B33) | C34: =SUM(C27:C33) | D34: =SUM(D27:D33) | E34: =SUM(E27:E33) | F34: =SUM(F27:F33) | G34: =SUM(G27:G33) | H34: =SUM(H27:H33) | I34: =SUM(I27:I33) | ... N34: =SUM(N27:N33)
A35: Proceeds from Issuance of Long-Term Debt | B35: 0 | C35: 0 | D35: 3377 | E35: 2986 | F35: 2986 | G35: 2986 | H35: 1761 | I35: 1765 | J35: 4014 | K35: 3505 | L35: 3521 | M35: 8179 | N35: 2964
A36: Repayments of Long-Term Debt | B36: -1251 | C36: -3202 | D36: -3203 | E36: -1251 | F36: -2252 | G36: -2253 | H36: -1252 | I36: -2882 | J36: -2883 | K36: -1541 | L36: -2543 | M36: -3245 | N36: -1629
A37: Proceeds from Short-Term Debt | B37: 559 | C37: 1935 | D37: 1947 | E37: 393 | F37: 1660 | G37: 4688 | H37: 2313 | I37: 3080 | J37: 3808 | K37: 3656 | L37: 5251 | M37: 5528 | N37: 1937
A38: Repayments of Short-Term Debt | B38: 0 | C38: 0 | D38: -1932 | E38: -1 | F38: -26 | G38: -1037 | H38: -1631 | I38: -2138 | J38: -4177 | K38: -2119 | L38: -2492 | M38: -5417 | N38: -676
A39: Net Change in Other Short-Term Debt | B39: 647 | C39: 844 | D39: -45 | E39: 491 | F39: 2023 | G39: 1395 | H39: 774 | I39: 1286 | J39: 101 | K39: 373 | L39: 2438 | M39: 445 | N39: 1198
A40: Payments of Contingent Consideration | B40: 0 | C40: 0 | D40: 0 | E40: 0 | F40: 0 | G40: 0 | H40: 0 | I40: 0 | J40: 0 | K40: 0 | L40: 0 | M40: 0 | N40: 0
A41: Common Dividends | B41: -1505 | C41: -2997 | D41: -4586 | E41: -1608 | F41: -3199 | G41: -4941 | H41: -1767 | I41: -3506 | J41: -5369 | K41: -1882 | L41: -3743 | M41: -5692 | N41: -1966
A42: Share Repurchases | B42: -193 | C42: -699 | D42: -1156 | E42: -160 | F42: -453 | G42: -751 | H42: -146 | I42: -461 | J42: -760 | K42: -183 | L42: -494 | M42: -752 | N42: -182
A43: Proceeds from Exercise of Stock Options | B43: 49 | C43: 89 | D43: 113 | E43: 46 | F43: 86 | G43: 100 | H43: 66 | I43: 107 | J43: 138 | K43: 50 | L43: 58 | M43: 76 | N43: 93
A44: Tax Withholdings on RSU/PSU Settlement | B44: -85 | C44: -87 | D44: -97 | E44: -116 | F44: -119 | G44: -135 | H44: -108 | I44: -131 | J44: -132 | K44: -89 | L44: -111 | M44: -112 | N44: -76
A45: Other Financing Activities | B45: -1 | C45: -15 | D45: -25 | E45: -3 | F45: -16 | G45: -18 | H45: 0 | I45: -20 | J45: -22 | K45: -2 | L45: -17 | M45: -18 | N45: -1
A46: Cash Flow from Financing | B46: =SUM(B35:B45) | C46: =SUM(C35:C45) | D46: =SUM(D35:D45) | E46: =SUM(E35:E45) | F46: =SUM(F35:F45) | G46: =SUM(G35:G45) | H46: =SUM(H35:H45) | I46: =SUM(I35:I45) | ... N46: =SUM(N35:N45)
A47: FX Effect on Cash | B47: -17 | C47: -83 | D47: -197 | E47: -116 | F47: -144 | G47: -254 | H47: -38 | I47: -304 | J47: -391 | K47: 203 | L47: 422 | M47: 395 | N47: 121
A48: Net Change in Cash | B48: =B26+B34+B46+B47 | C48: =C26+C34+C46+C47 | D48: =D26+D34+D46+D47 | E48: =E26+E34+E46+E47 | F48: =F26+F34+F46+F47 | G48: =G26+G34+G46+G47 | H48: =H26+H34+H46+H47 | I48: =I26+I34+I46+I47 | ... N48: =N26+N34+N46+N47

Sheet QTR P&L
B1: Q1 FY2022 | C1: Q2 FY2022 | D1: Q3 FY2022 | E1: Q4 FY2022 | F1: Q1 FY2023 | G1: Q2 FY2023 | H1: Q3 FY2023 | I1: Q4 FY2023 | J1: Q1 FY2024 | K1: Q2 FY2024 | L1: Q3 FY2024 | M1: Q4 FY2024 | N1: Q1 FY2025 | O1: Q2 FY2025 | P1: Q3 FY2025 | Q1: Q4 FY2025 | R1: Q1 FY2026
A2: Net Sales / Revenue | B2: ='YTD P&L'!B2 | C2: ='YTD P&L'!C2-'YTD P&L'!B2 | D2: ='YTD P&L'!D2-'YTD P&L'!C2 | E2: ='ANNL P&L'!C2-'YTD P&L'!D2 | F2: ='YTD P&L'!E2 | G2: ='YTD P&L'!F2-'YTD P&L'!E2 | H2: ='YTD P&L'!G2-'YTD P&L'!F2 | I2: ='ANNL P&L'!D2-'YTD P&L'!G2 | J2: ='YTD P&L'!H2 | K2: ='YTD P&L'!I2-'YTD P&L'!H2 | L2: ='YTD P&L'!J2-'YTD P&L'!I2 | M2: ='ANNL P&L'!E2-'YTD P&L'!J2 | N2: ='YTD P&L'!K2 | O2: ='YTD P&L'!L2-'YTD P&L'!K2 | P2: ='YTD P&L'!M2-'YTD P&L'!L2 | Q2: ='ANNL P&L'!F2-'YTD P&L'!M2 | R2: ='YTD P&L'!N2
A3: COGS | B3: ='YTD P&L'!B3 | C3: ='YTD P&L'!C3-'YTD P&L'!B3 | D3: ='YTD P&L'!D3-'YTD P&L'!C3 | E3: ='ANNL P&L'!C3-'YTD P&L'!D3 | F3: ='YTD P&L'!E3 | G3: ='YTD P&L'!F3-'YTD P&L'!E3 | H3: ='YTD P&L'!G3-'YTD P&L'!F3 | I3: ='ANNL P&L'!D3-'YTD P&L'!G3 | J3: ='YTD P&L'!H3 | K3: ='YTD P&L'!I3-'YTD P&L'!H3 | L3: ='YTD P&L'!J3-'YTD P&L'!I3 | M3: ='ANNL P&L'!E3-'YTD P&L'!J3 | N3: ='YTD P&L'!K3 | O3: ='YTD P&L'!L3-'YTD P&L'!K3 | P3: ='YTD P&L'!M3-'YTD P&L'!L3 | Q3: ='ANNL P&L'!F3-'YTD P&L'!M3 | R3: ='YTD P&L'!N3
A4: Gross Profit (Loss) | B4: ='YTD P&L'!B4 | C4: ='YTD P&L'!C4-'YTD P&L'!B4 | D4: ='YTD P&L'!D4-'YTD P&L'!C4 | E4: ='ANNL P&L'!C4-'YTD P&L'!D4 | F4: ='YTD P&L'!E4 | G4: ='YTD P&L'!F4-'YTD P&L'!E4 | H4: ='YTD P&L'!G4-'YTD P&L'!F4 | I4: ='ANNL P&L'!D4-'YTD P&L'!G4 | J4: ='YTD P&L'!H4 | K4: ='YTD P&L'!I4-'YTD P&L'!H4 | L4: ='YTD P&L'!J4-'YTD P&L'!I4 | M4: ='ANNL P&L'!E4-'YTD P&L'!J4 | N4: ='YTD P&L'!K4 | O4: ='YTD P&L'!L4-'YTD P&L'!K4 | P4: ='YTD P&L'!M4-'YTD P&L'!L4 | Q4: ='ANNL P&L'!F4-'YTD P&L'!M4 | R4: ='YTD P&L'!N4
A5: SG&A | B5: ='YTD P&L'!B5 | C5: ='YTD P&L'!C5-'YTD P&L'!B5 | D5: ='YTD P&L'!D5-'YTD P&L'!C5 | E5: ='ANNL P&L'!C5-'YTD P&L'!D5 | F5: ='YTD P&L'!E5 | G5: ='YTD P&L'!F5-'YTD P&L'!E5 | H5: ='YTD P&L'!G5-'YTD P&L'!F5 | I5: ='ANNL P&L'!D5-'YTD P&L'!G5 | J5: ='YTD P&L'!H5 | K5: ='YTD P&L'!I5-'YTD P&L'!H5 | L5: ='YTD P&L'!J5-'YTD P&L'!I5 | M5: ='ANNL P&L'!E5-'YTD P&L'!J5 | N5: ='YTD P&L'!K5 | O5: ='YTD P&L'!L5-'YTD P&L'!K5 | P5: ='YTD P&L'!M5-'YTD P&L'!L5 | Q5: ='ANNL P&L'!F5-'YTD P&L'!M5 | R5: ='YTD P&L'!N5
A6: Gain on Juice Transaction | B6: ='YTD P&L'!B6 | C6: ='YTD P&L'!C6-'YTD P&L'!B6 | D6: ='YTD P&L'!D6-'YTD P&L'!C6 | E6: ='ANNL P&L'!C6-'YTD P&L'!D6 | F6: ='YTD P&L'!E6 | G6: ='YTD P&L'!F6-'YTD P&L'!E6 | H6: ='YTD P&L'!G6-'YTD P&L'!F6 | I6: ='ANNL P&L'!D6-'YTD P&L'!G6 | J6: ='YTD P&L'!H6 | K6: ='YTD P&L'!I6-'YTD P&L'!H6 | L6: ='YTD P&L'!J6-'YTD P&L'!I6 | M6: ='ANNL P&L'!E6-'YTD P&L'!J6 | N6: ='YTD P&L'!K6 | O6: ='YTD P&L'!L6-'YTD P&L'!K6 | P6: ='YTD P&L'!M6-'YTD P&L'!L6 | Q6: ='ANNL P&L'!F6-'YTD P&L'!M6 | R6: ='YTD P&L'!N6
A7: Impairment of Intangibles | B7: ='YTD P&L'!B7 | C7: ='YTD P&L'!C7-'YTD P&L'!B7 | D7: ='YTD P&L'!D7-'YTD P&L'!C7 | E7: ='ANNL P&L'!C7-'YTD P&L'!D7 | F7: ='YTD P&L'!E7 | G7: ='YTD P&L'!F7-'YTD P&L'!E7 | H7: ='YTD P&L'!G7-'YTD P&L'!F7 | I7: ='ANNL P&L'!D7-'YTD P&L'!G7 | J7: ='YTD P&L'!H7 | K7: ='YTD P&L'!I7-'YTD P&L'!H7 | L7: ='YTD P&L'!J7-'YTD P&L'!I7 | M7: ='ANNL P&L'!E7-'YTD P&L'!J7 | N7: ='YTD P&L'!K7 | O7: ='YTD P&L'!L7-'YTD P&L'!K7 | P7: ='YTD P&L'!M7-'YTD P&L'!L7 | Q7: ='ANNL P&L'!F7-'YTD P&L'!M7 | R7: ='YTD P&L'!N7
A8: Income (Loss) from Operations | B8: ='YTD P&L'!B8 | C8: ='YTD P&L'!C8-'YTD P&L'!B8 | D8: ='YTD P&L'!D8-'YTD P&L'!C8 | E8: ='ANNL P&L'!C8-'YTD P&L'!D8 | F8: ='YTD P&L'!E8 | G8: ='YTD P&L'!F8-'YTD P&L'!E8 | H8: ='YTD P&L'!G8-'YTD P&L'!F8 | I8: ='ANNL P&L'!D8-'YTD P&L'!G8 | J8: ='YTD P&L'!H8 | K8: ='YTD P&L'!I8-'YTD P&L'!H8 | L8: ='YTD P&L'!J8-'YTD P&L'!I8 | M8: ='ANNL P&L'!E8-'YTD P&L'!J8 | N8: ='YTD P&L'!K8 | O8: ='YTD P&L'!L8-'YTD P&L'!K8 | P8: ='YTD P&L'!M8-'YTD P&L'!L8 | Q8: ='ANNL P&L'!F8-'YTD P&L'!M8 | R8: ='YTD P&L'!N8
A9: Other Pension and OPEB Benefits Income (Expense) | B9: ='YTD P&L'!B9 | C9: ='YTD P&L'!C9-'YTD P&L'!B9 | D9: ='YTD P&L'!D9-'YTD P&L'!C9 | E9: ='ANNL P&L'!C9-'YTD P&L'!D9 | F9: ='YTD P&L'!E9 | G9: ='YTD P&L'!F9-'YTD P&L'!E9 | H9: ='YTD P&L'!G9-'YTD P&L'!F9 | I9: ='ANNL P&L'!D9-'YTD P&L'!G9 | J9: ='YTD P&L'!H9 | K9: ='YTD P&L'!I9-'YTD P&L'!H9 | L9: ='YTD P&L'!J9-'YTD P&L'!I9 | M9: ='ANNL P&L'!E9-'YTD P&L'!J9 | N9: ='YTD P&L'!K9 | O9: ='YTD P&L'!L9-'YTD P&L'!K9 | P9: ='YTD P&L'!M9-'YTD P&L'!L9 | Q9: ='ANNL P&L'!F9-'YTD P&L'!M9 | R9: ='YTD P&L'!N9
A10: Interest Income (Expense) | B10: ='YTD P&L'!B10 | C10: ='YTD P&L'!C10-'YTD P&L'!B10 | D10: ='YTD P&L'!D10-'YTD P&L'!C10 | E10: ='ANNL P&L'!C10-'YTD P&L'!D10 | F10: ='YTD P&L'!E10 | G10: ='YTD P&L'!F10-'YTD P&L'!E10 | H10: ='YTD P&L'!G10-'YTD P&L'!F10 | I10: ='ANNL P&L'!D10-'YTD P&L'!G10 | J10: ='YTD P&L'!H10 | K10: ='YTD P&L'!I10-'YTD P&L'!H10 | L10: ='YTD P&L'!J10-'YTD P&L'!I10 | M10: ='ANNL P&L'!E10-'YTD P&L'!J10 | N10: ='YTD P&L'!K10 | O10: ='YTD P&L'!L10-'YTD P&L'!K10 | P10: ='YTD P&L'!M10-'YTD P&L'!L10 | Q10: ='ANNL P&L'!F10-'YTD P&L'!M10 | R10: ='YTD P&L'!N10
A11: Pre-Tax Income (Loss) | B11: ='YTD P&L'!B11 | C11: ='YTD P&L'!C11-'YTD P&L'!B11 | D11: ='YTD P&L'!D11-'YTD P&L'!C11 | E11: ='ANNL P&L'!C11-'YTD P&L'!D11 | F11: ='YTD P&L'!E11 | G11: ='YTD P&L'!F11-'YTD P&L'!E11 | H11: ='YTD P&L'!G11-'YTD P&L'!F11 | I11: ='ANNL P&L'!D11-'YTD P&L'!G11 | J11: ='YTD P&L'!H11 | K11: ='YTD P&L'!I11-'YTD P&L'!H11 | L11: ='YTD P&L'!J11-'YTD P&L'!I11 | M11: ='ANNL P&L'!E11-'YTD P&L'!J11 | N11: ='YTD P&L'!K11 | O11: ='YTD P&L'!L11-'YTD P&L'!K11 | P11: ='YTD P&L'!M11-'YTD P&L'!L11 | Q11: ='ANNL P&L'!F11-'YTD P&L'!M11 | R11: ='YTD P&L'!N11
A12: Income Tax (Expense) Benefit | B12: ='YTD P&L'!B12 | C12: ='YTD P&L'!C12-'YTD P&L'!B12 | D12: ='YTD P&L'!D12-'YTD P&L'!C12 | E12: ='ANNL P&L'!C12-'YTD P&L'!D12 | F12: ='YTD P&L'!E12 | G12: ='YTD P&L'!F12-'YTD P&L'!E12 | H12: ='YTD P&L'!G12-'YTD P&L'!F12 | I12: ='ANNL P&L'!D12-'YTD P&L'!G12 | J12: ='YTD P&L'!H12 | K12: ='YTD P&L'!I12-'YTD P&L'!H12 | L12: ='YTD P&L'!J12-'YTD P&L'!I12 | M12: ='ANNL P&L'!E12-'YTD P&L'!J12 | N12: ='YTD P&L'!K12 | O12: ='YTD P&L'!L12-'YTD P&L'!K12 | P12: ='YTD P&L'!M12-'YTD P&L'!L12 | Q12: ='ANNL P&L'!F12-'YTD P&L'!M12 | R12: ='YTD P&L'!N12
A13: Net Income (Loss) | B13: ='YTD P&L'!B13 | C13: ='YTD P&L'!C13-'YTD P&L'!B13 | D13: ='YTD P&L'!D13-'YTD P&L'!C13 | E13: ='ANNL P&L'!C13-'YTD P&L'!D13 | F13: ='YTD P&L'!E13 | G13: ='YTD P&L'!F13-'YTD P&L'!E13 | H13: ='YTD P&L'!G13-'YTD P&L'!F13 | I13: ='ANNL P&L'!D13-'YTD P&L'!G13 | J13: ='YTD P&L'!H13 | K13: ='YTD P&L'!I13-'YTD P&L'!H13 | L13: ='YTD P&L'!J13-'YTD P&L'!I13 | M13: ='ANNL P&L'!E13-'YTD P&L'!J13 | N13: ='YTD P&L'!K13 | O13: ='YTD P&L'!L13-'YTD P&L'!K13 | P13: ='YTD P&L'!M13-'YTD P&L'!L13 | Q13: ='ANNL P&L'!F13-'YTD P&L'!M13 | R13: ='YTD P&L'!N13
... A15: Net Income (Loss) Less NCI | B15: ='YTD P&L'!B15 | C15: ='YTD P&L'!C15-'YTD P&L'!B15 | D15: ='YTD P&L'!D15-'YTD P&L'!C15 | E15: ='ANNL P&L'!C15-'YTD P&L'!D15 | F15: ='YTD P&L'!E15 | G15: ='YTD P&L'!F15-'YTD P&L'!E15 | H15: ='YTD P&L'!G15-'YTD P&L'!F15 | I15: ='ANNL P&L'!D15-'YTD P&L'!G15 | J15: ='YTD P&L'!H15 | K15: ='YTD P&L'!I15-'YTD P&L'!H15 | L15: ='YTD P&L'!J15-'YTD P&L'!I15 | M15: ='ANNL P&L'!E15-'YTD P&L'!J15 | N15: ='YTD P&L'!K15 | O15: ='YTD P&L'!L15-'YTD P&L'!K15 | P15: ='YTD P&L'!M15-'YTD P&L'!L15 | Q15: ='ANNL P&L'!F15-'YTD P&L'!M15 | R15: ='YTD P&L'!N15
A16: Basic Earnings (Loss) per Share
A17: Diluted Earnings (Loss) per Share
A18: Weighted Average Shares Outstanding (Basic)
A19: Weighted Average Shares Outstanding (Diluted)

Sheet QTR BS
B1: Q4 FY2022 | C1: Q1 FY2023 | D1: Q2 FY2023 | E1: Q3 FY2023 | F1: Q4 FY2023 | G1: Q1 FY2024 | H1: Q2 FY2024 | I1: Q3 FY2024 | J1: Q4 FY2024 | K1: Q1 FY2025 | L1: Q2 FY2025 | M1: Q3 FY2025 | N1: Q4 FY2025 | O1: Q1 FY2026
A2: Cash & Cash Equivalents | B2: ='BALANCE SHEET'!B2 | C2: ='YTD BS'!C2 | D2: ='YTD BS'!D2 | E2: ='YTD BS'!E2 | F2: ='BALANCE SHEET'!C2 | G2: ='YTD BS'!G2 | H2: ='YTD BS'!H2 | I2: ='YTD BS'!I2 | J2: ='BALANCE SHEET'!D2 | K2: ='YTD BS'!K2 | L2: ='YTD BS'!L2 | M2: ='YTD BS'!M2 | N2: ='BALANCE SHEET'!E2 | O2: ='YTD BS'!O2
A3: Short-Term Investments | B3: ='BALANCE SHEET'!B3 | C3: ='YTD BS'!C3 | D3: ='YTD BS'!D3 | E3: ='YTD BS'!E3 | F3: ='BALANCE SHEET'!C3 | G3: ='YTD BS'!G3 | H3: ='YTD BS'!H3 | I3: ='YTD BS'!I3 | J3: ='BALANCE SHEET'!D3 | K3: ='YTD BS'!K3 | L3: ='YTD BS'!L3 | M3: ='YTD BS'!M3 | N3: ='BALANCE SHEET'!E3 | O3: ='YTD BS'!O3
A4: Accounts Receivable | B4: ='BALANCE SHEET'!B4 | C4: ='YTD BS'!C4 | D4: ='YTD BS'!D4 | E4: ='YTD BS'!E4 | F4: ='BALANCE SHEET'!C4 | G4: ='YTD BS'!G4 | H4: ='YTD BS'!H4 | I4: ='YTD BS'!I4 | J4: ='BALANCE SHEET'!D4 | K4: ='YTD BS'!K4 | L4: ='YTD BS'!L4 | M4: ='YTD BS'!M4 | N4: ='BALANCE SHEET'!E4 | O4: ='YTD BS'!O4
A5: Raw Materials | B5: ='BALANCE SHEET'!B5 | C5: ='YTD BS'!C5 | D5: ='YTD BS'!D5 | E5: ='YTD BS'!E5 | F5: ='BALANCE SHEET'!C5 | G5: ='YTD BS'!G5 | H5: ='YTD BS'!H5 | I5: ='YTD BS'!I5 | J5: ='BALANCE SHEET'!D5 | K5: ='YTD BS'!K5 | L5: ='YTD BS'!L5 | M5: ='YTD BS'!M5 | N5: ='BALANCE SHEET'!E5 | O5: ='YTD BS'!O5
A6: Work in Process | B6: ='BALANCE SHEET'!B6 | C6: ='YTD BS'!C6 | D6: ='YTD BS'!D6 | E6: ='YTD BS'!E6 | F6: ='BALANCE SHEET'!C6 | G6: ='YTD BS'!G6 | H6: ='YTD BS'!H6 | I6: ='YTD BS'!I6 | J6: ='BALANCE SHEET'!D6 | K6: ='YTD BS'!K6 | L6: ='YTD BS'!L6 | M6: ='YTD BS'!M6 | N6: ='BALANCE SHEET'!E6 | O6: ='YTD BS'!O6
A7: Finished Goods | B7: ='BALANCE SHEET'!B7 | C7: ='YTD BS'!C7 | D7: ='YTD BS'!D7 | E7: ='YTD BS'!E7 | F7: ='BALANCE SHEET'!C7 | G7: ='YTD BS'!G7 | H7: ='YTD BS'!H7 | I7: ='YTD BS'!I7 | J7: ='BALANCE SHEET'!D7 | K7: ='YTD BS'!K7 | L7: ='YTD BS'!L7 | M7: ='YTD BS'!M7 | N7: ='BALANCE SHEET'!E7 | O7: ='YTD BS'!O7
A8: Inventories | B8: ='BALANCE SHEET'!B8 | C8: ='YTD BS'!C8 | D8: ='YTD BS'!D8 | E8: ='YTD BS'!E8 | F8: ='BALANCE SHEET'!C8 | G8: ='YTD BS'!G8 | H8: ='YTD BS'!H8 | I8: ='YTD BS'!I8 | J8: ='BALANCE SHEET'!D8 | K8: ='YTD BS'!K8 | L8: ='YTD BS'!L8 | M8: ='YTD BS'!M8 | N8: ='BALANCE SHEET'!E8 | O8: ='YTD BS'!O8
A9: Prepaid Expenses | B9: ='BALANCE SHEET'!B9 | C9: ='YTD BS'!C9 | D9: ='YTD BS'!D9 | E9: ='YTD BS'!E9 | F9: ='BALANCE SHEET'!C9 | G9: ='YTD BS'!G9 | H9: ='YTD BS'!H9 | I9: ='YTD BS'!I9 | J9: ='BALANCE SHEET'!D9 | K9: ='YTD BS'!K9 | L9: ='YTD BS'!L9 | M9: ='YTD BS'!M9 | N9: ='BALANCE SHEET'!E9 | O9: ='YTD BS'!O9
A10: Total Current Assets | B10: ='BALANCE SHEET'!B10 | C10: ='YTD BS'!C10 | D10: ='YTD BS'!D10 | E10: ='YTD BS'!E10 | F10: ='BALANCE SHEET'!C10 | G10: ='YTD BS'!G10 | H10: ='YTD BS'!H10 | I10: ='YTD BS'!I10 | J10: ='BALANCE SHEET'!D10 | K10: ='YTD BS'!K10 | L10: ='YTD BS'!L10 | M10: ='YTD BS'!M10 | N10: ='BALANCE SHEET'!E10 | O10: ='YTD BS'!O10
A11: Net PP&E | B11: ='BALANCE SHEET'!B11 | C11: ='YTD BS'!C11 | D11: ='YTD BS'!D11 | E11: ='YTD BS'!E11 | F11: ='BALANCE SHEET'!C11 | G11: ='YTD BS'!G11 | H11: ='YTD BS'!H11 | I11: ='YTD BS'!I11 | J11: ='BALANCE SHEET'!D11 | K11: ='YTD BS'!K11 | L11: ='YTD BS'!L11 | M11: ='YTD BS'!M11 | N11: ='BALANCE SHEET'!E11 | O11: ='YTD BS'!O11
A12: Intangible Assets | B12: ='BALANCE SHEET'!B12 | C12: ='YTD BS'!C12 | D12: ='YTD BS'!D12 | E12: ='YTD BS'!E12 | F12: ='BALANCE SHEET'!C12 | G12: ='YTD BS'!G12 | H12: ='YTD BS'!H12 | I12: ='YTD BS'!I12 | J12: ='BALANCE SHEET'!D12 | K12: ='YTD BS'!K12 | L12: ='YTD BS'!L12 | M12: ='YTD BS'!M12 | N12: ='BALANCE SHEET'!E12 | O12: ='YTD BS'!O12
A13: Goodwill | B13: ='BALANCE SHEET'!B13 | C13: ='YTD BS'!C13 | D13: ='YTD BS'!D13 | E13: ='YTD BS'!E13 | F13: ='BALANCE SHEET'!C13 | G13: ='YTD BS'!G13 | H13: ='YTD BS'!H13 | I13: ='YTD BS'!I13 | J13: ='BALANCE SHEET'!D13 | K13: ='YTD BS'!K13 | L13: ='YTD BS'!L13 | M13: ='YTD BS'!M13 | N13: ='BALANCE SHEET'!E13 | O13: ='YTD BS'!O13
... A32: Total Liabilities, Mezzanine & Stockholders' Equity | B32: ='BALANCE SHEET'!B32 | C32: ='YTD BS'!C32 | D32: ='YTD BS'!D32 | E32: ='YTD BS'!E32 | F32: ='BALANCE SHEET'!C32 | G32: ='YTD BS'!G32 | H32: ='YTD BS'!H32 | I32: ='YTD BS'!I32 | J32: ='BALANCE SHEET'!D32 | K32: ='YTD BS'!K32 | L32: ='YTD BS'!L32 | M32: ='YTD BS'!M32 | N32: ='BALANCE SHEET'!E32 | O32: ='YTD BS'!O32

Sheet QTR CF
B1: Q1 FY2022 | C1: Q2 FY2022 | D1: Q3 FY2022 | E1: Q4 FY2022 | F1: Q1 FY2023 | G1: Q2 FY2023 | H1: Q3 FY2023 | I1: Q4 FY2023 | J1: Q1 FY2024 | K1: Q2 FY2024 | L1: Q3 FY2024 | M1: Q4 FY2024 | N1: Q1 FY2025 | O1: Q2 FY2025 | P1: Q3 FY2025 | Q1: Q4 FY2025 | R1: Q1 FY2026
A2: Net Income (Loss) | B2: ='YTD CF'!B2 | C2: ='YTD CF'!C2-'YTD CF'!B2 | D2: ='YTD CF'!D2-'YTD CF'!C2 | E2: ='CASH FLOW'!C2-'YTD CF'!D2 | F2: ='YTD CF'!E2 | G2: ='YTD CF'!F2-'YTD CF'!E2 | H2: ='YTD CF'!G2-'YTD CF'!F2 | I2: ='CASH FLOW'!D2-'YTD CF'!G2 | J2: ='YTD CF'!H2 | K2: ='YTD CF'!I2-'YTD CF'!H2 | L2: ='YTD CF'!J2-'YTD CF'!I2 | M2: ='CASH FLOW'!E2-'YTD CF'!J2 | N2: ='YTD CF'!K2 | O2: ='YTD CF'!L2-'YTD CF'!K2 | P2: ='YTD CF'!M2-'YTD CF'!L2 | Q2: ='CASH FLOW'!F2-'YTD CF'!M2 | R2: ='YTD CF'!N2
A3: Depreciation & Amortization | B3: ='YTD CF'!B3 | C3: ='YTD CF'!C3-'YTD CF'!B3 | D3: ='YTD CF'!D3-'YTD CF'!C3 | E3: ='CASH FLOW'!C3-'YTD CF'!D3 | F3: ='YTD CF'!E3 | G3: ='YTD CF'!F3-'YTD CF'!E3 | H3: ='YTD CF'!G3-'YTD CF'!F3 | I3: ='CASH FLOW'!D3-'YTD CF'!G3 | J3: ='YTD CF'!H3 | K3: ='YTD CF'!I3-'YTD CF'!H3 | L3: ='YTD CF'!J3-'YTD CF'!I3 | M3: ='CASH FLOW'!E3-'YTD CF'!J3 | N3: ='YTD CF'!K3 | O3: ='YTD CF'!L3-'YTD CF'!K3 | P3: ='YTD CF'!M3-'YTD CF'!L3 | Q3: ='CASH FLOW'!F3-'YTD CF'!M3 | R3: ='YTD CF'!N3
A4: Gain on Juice Transaction | B4: ='YTD CF'!B4 | C4: ='YTD CF'!C4-'YTD CF'!B4 | D4: ='YTD CF'!D4-'YTD CF'!C4 | E4: ='CASH FLOW'!C4-'YTD CF'!D4 | F4: ='YTD CF'!E4 | G4: ='YTD CF'!F4-'YTD CF'!E4 | H4: ='YTD CF'!G4-'YTD CF'!F4 | I4: ='CASH FLOW'!D4-'YTD CF'!G4 | J4: ='YTD CF'!H4 | K4: ='YTD CF'!I4-'YTD CF'!H4 | L4: ='YTD CF'!J4-'YTD CF'!I4 | M4: ='CASH FLOW'!E4-'YTD CF'!J4 | N4: ='YTD CF'!K4 | O4: ='YTD CF'!L4-'YTD CF'!K4 | P4: ='YTD CF'!M4-'YTD CF'!L4 | Q4: ='CASH FLOW'!F4-'YTD CF'!M4 | R4: ='YTD CF'!N4
A5: Impairment and Other Charges | B5: ='YTD CF'!B5 | C5: ='YTD CF'!C5-'YTD CF'!B5 | D5: ='YTD CF'!D5-'YTD CF'!C5 | E5: ='CASH FLOW'!C5-'YTD CF'!D5 | F5: ='YTD CF'!E5 | G5: ='YTD CF'!F5-'YTD CF'!E5 | H5: ='YTD CF'!G5-'YTD CF'!F5 | I5: ='CASH FLOW'!D5-'YTD CF'!G5 | J5: ='YTD CF'!H5 | K5: ='YTD CF'!I5-'YTD CF'!H5 | L5: ='YTD CF'!J5-'YTD CF'!I5 | M5: ='CASH FLOW'!E5-'YTD CF'!J5 | N5: ='YTD CF'!K5 | O5: ='YTD CF'!L5-'YTD CF'!K5 | P5: ='YTD CF'!M5-'YTD CF'!L5 | Q5: ='CASH FLOW'!F5-'YTD CF'!M5 | R5: ='YTD CF'!N5
A6: Indirect Tax Impact | B6: ='YTD CF'!B6 | C6: ='YTD CF'!C6-'YTD CF'!B6 | D6: ='YTD CF'!D6-'YTD CF'!C6 | E6: ='CASH FLOW'!C6-'YTD CF'!D6 | F6: ='YTD CF'!E6 | G6: ='YTD CF'!F6-'YTD CF'!E6 | H6: ='YTD CF'!G6-'YTD CF'!F6 | I6: ='CASH FLOW'!D6-'YTD CF'!G6 | J6: ='YTD CF'!H6 | K6: ='YTD CF'!I6-'YTD CF'!H6 | L6: ='YTD CF'!J6-'YTD CF'!I6 | M6: ='CASH FLOW'!E6-'YTD CF'!J6 | N6: ='YTD CF'!K6 | O6: ='YTD CF'!L6-'YTD CF'!K6 | P6: ='YTD CF'!M6-'YTD CF'!L6 | Q6: ='CASH FLOW'!F6-'YTD CF'!M6 | R6: ='YTD CF'!N6
A7: Product Recall Impact | B7: ='YTD CF'!B7 | C7: ='YTD CF'!C7-'YTD CF'!B7 | D7: ='YTD CF'!D7-'YTD CF'!C7 | E7: ='CASH FLOW'!C7-'YTD CF'!D7 | F7: ='YTD CF'!E7 | G7: ='YTD CF'!F7-'YTD CF'!E7 | H7: ='YTD CF'!G7-'YTD CF'!F7 | I7: ='CASH FLOW'!D7-'YTD CF'!G7 | J7: ='YTD CF'!H7 | K7: ='YTD CF'!I7-'YTD CF'!H7 | L7: ='YTD CF'!J7-'YTD CF'!I7 | M7: ='CASH FLOW'!E7-'YTD CF'!J7 | N7: ='YTD CF'!K7 | O7: ='YTD CF'!L7-'YTD CF'!K7 | P7: ='YTD CF'!M7-'YTD CF'!L7 | Q7: ='CASH FLOW'!F7-'YTD CF'!M7 | R7: ='YTD CF'!N7
A8: Cash Payments for Product Recall | B8: ='YTD CF'!B8 | C8: ='YTD CF'!C8-'YTD CF'!B8 | D8: ='YTD CF'!D8-'YTD CF'!C8 | E8: ='CASH FLOW'!C8-'YTD CF'!D8 | F8: ='YTD CF'!E8 | G8: ='YTD CF'!F8-'YTD CF'!E8 | H8: ='YTD CF'!G8-'YTD CF'!F8 | I8: ='CASH FLOW'!D8-'YTD CF'!G8 | J8: ='YTD CF'!H8 | K8: ='YTD CF'!I8-'YTD CF'!H8 | L8: ='YTD CF'!J8-'YTD CF'!I8 | M8: ='CASH FLOW'!E8-'YTD CF'!J8 | N8: ='YTD CF'!K8 | O8: ='YTD CF'!L8-'YTD CF'!K8 | P8: ='YTD CF'!M8-'YTD CF'!L8 | Q8: ='CASH FLOW'!F8-'YTD CF'!M8 | R8: ='YTD CF'!N8
A9: Non-Cash Lease Expense | B9: ='YTD CF'!B9 | C9: ='YTD CF'!C9-'YTD CF'!B9 | D9: ='YTD CF'!D9-'YTD CF'!C9 | E9: ='CASH FLOW'!C9-'YTD CF'!D9 | F9: ='YTD CF'!E9 | G9: ='YTD CF'!F9-'YTD CF'!E9 | H9: ='YTD CF'!G9-'YTD CF'!F9 | I9: ='CASH FLOW'!D9-'YTD CF'!G9 | J9: ='YTD CF'!H9 | K9: ='YTD CF'!I9-'YTD CF'!H9 | L9: ='YTD CF'!J9-'YTD CF'!I9 | M9: ='CASH FLOW'!E9-'YTD CF'!J9 | N9: ='YTD CF'!K9 | O9: ='YTD CF'!L9-'YTD CF'!K9 | P9: ='YTD CF'!M9-'YTD CF'!L9 | Q9: ='CASH FLOW'!F9-'YTD CF'!M9 | R9: ='YTD CF'!N9
A10: Stock-Based Compensation | B10: ='YTD CF'!B10 | C10: ='YTD CF'!C10-'YTD CF'!B10 | D10: ='YTD CF'!D10-'YTD CF'!C10 | E10: ='CASH FLOW'!C10-'YTD CF'!D10 | F10: ='YTD CF'!E10 | G10: ='YTD CF'!F10-'YTD CF'!E10 | H10: ='YTD CF'!G10-'YTD CF'!F10 | I10: ='CASH FLOW'!D10-'YTD CF'!G10 | J10: ='YTD CF'!H10 | K10: ='YTD CF'!I10-'YTD CF'!H10 | L10: ='YTD CF'!J10-'YTD CF'!I10 | M10: ='CASH FLOW'!E10-'YTD CF'!J10 | N10: ='YTD CF'!K10 | O10: ='YTD CF'!L10-'YTD CF'!K10 | P10: ='YTD CF'!M10-'YTD CF'!L10 | Q10: ='CASH FLOW'!F10-'YTD CF'!M10 | R10: ='YTD CF'!N10
A11: Restructuring and Asset Impairment Charges | B11: ='YTD CF'!B11 | C11: ='YTD CF'!C11-'YTD CF'!B11 | D11: ='YTD CF'!D11-'YTD CF'!C11 | E11: ='CASH FLOW'!C11-'YTD CF'!D11 | F11: ='YTD CF'!E11 | G11: ='YTD CF'!F11-'YTD CF'!E11 | H11: ='YTD CF'!G11-'YTD CF'!F11 | I11: ='CASH FLOW'!D11-'YTD CF'!G11 | J11: ='YTD CF'!H11 | K11: ='YTD CF'!I11-'YTD CF'!H11 | L11: ='YTD CF'!J11-'YTD CF'!I11 | M11: ='CASH FLOW'!E11-'YTD CF'!J11 | N11: ='YTD CF'!K11 | O11: ='YTD CF'!L11-'YTD CF'!K11 | P11: ='YTD CF'!M11-'YTD CF'!L11 | Q11: ='CASH FLOW'!F11-'YTD CF'!M11 | R11: ='YTD CF'!N11
A12: Cash Payments for Restructuring | B12: ='YTD CF'!B12 | C12: ='YTD CF'!C12-'YTD CF'!B12 | D12: ='YTD CF'!D12-'YTD CF'!C12 | E12: ='CASH FLOW'!C12-'YTD CF'!D12 | F12: ='YTD CF'!E12 | G12: ='YTD CF'!F12-'YTD CF'!E12 | H12: ='YTD CF'!G12-'YTD CF'!F12 | I12: ='CASH FLOW'!D12-'YTD CF'!G12 | J12: ='YTD CF'!H12 | K12: ='YTD CF'!I12-'YTD CF'!H12 | L12: ='YTD CF'!J12-'YTD CF'!I12 | M12: ='CASH FLOW'!E12-'YTD CF'!J12 | N12: ='YTD CF'!K12 | O12: ='YTD CF'!L12-'YTD CF'!K12 | P12: ='YTD CF'!M12-'YTD CF'!L12 | Q12: ='CASH FLOW'!F12-'YTD CF'!M12 | R12: ='YTD CF'!N12
A13: Acquisition and Divestiture-Related Charges | B13: ='YTD CF'!B13 | C13: ='YTD CF'!C13-'YTD CF'!B13 | D13: ='YTD CF'!D13-'YTD CF'!C13 | E13: ='CASH FLOW'!C13-'YTD CF'!D13 | F13: ='YTD CF'!E13 | G13: ='YTD CF'!F13-'YTD CF'!E13 | H13: ='YTD CF'!G13-'YTD CF'!F13 | I13: ='CASH FLOW'!D13-'YTD CF'!G13 | J13: ='YTD CF'!H13 | K13: ='YTD CF'!I13-'YTD CF'!H13 | L13: ='YTD CF'!J13-'YTD CF'!I13 | M13: ='CASH FLOW'!E13-'YTD CF'!J13 | N13: ='YTD CF'!K13 | O13: ='YTD CF'!L13-'YTD CF'!K13 | P13: ='YTD CF'!M13-'YTD CF'!L13 | Q13: ='CASH FLOW'!F13-'YTD CF'!M13 | R13: ='YTD CF'!N13
... A48: Net Change in Cash | B48: ='YTD CF'!B48 | C48: ='YTD CF'!C48-'YTD CF'!B48 | D48: ='YTD CF'!D48-'YTD CF'!C48 | E48: ='CASH FLOW'!C48-'YTD CF'!D48 | F48: ='YTD CF'!E48 | G48: ='YTD CF'!F48-'YTD CF'!E48 | H48: ='YTD CF'!G48-'YTD CF'!F48 | I48: ='CASH FLOW'!D48-'YTD CF'!G48 | J48: ='YTD CF'!H48 | K48: ='YTD CF'!I48-'YTD CF'!H48 | L48: ='YTD CF'!J48-'YTD CF'!I48 | M48: ='CASH FLOW'!E48-'YTD CF'!J48 | N48: ='YTD CF'!K48 | O48: ='YTD CF'!L48-'YTD CF'!K48 | P48: ='YTD CF'!M48-'YTD CF'!L48 | Q48: ='CASH FLOW'!F48-'YTD CF'!M48 | R48: ='YTD CF'!N48
