Workbook

Sheet ASSUMPTIONS
A1: Assumption | B1: Value | C1: Note
A2: Days in Quarter | B2: 91 | C2: Used by DSO/DIO/DPO ratios. Approximation; varies 89-92 by quarter.

Sheet ANNL P&L
B1: FY2021 | C1: FY2022 | D1: FY2023 | E1: FY2024 | F1: FY2025 | G1: FY2025E | H1: FY2026E | I1: FY2027E | J1: FY2028E | K1: FY2029E | L1: FY2030E
A2: Net Sales / Revenue | B2: 76118 | C2: 80187 | D2: 82006 | E2: 84039 | F2: 84284 | G2: ='QTR P&L'!N2+'QTR P&L'!O2+'QTR P&L'!P2+'QTR P&L'!Q2 | H2: ='QTR P&L'!R2+'QTR P&L'!S2+'QTR P&L'!T2+'QTR P&L'!U2 | I2: ='QTR P&L'!V2+'QTR P&L'!W2+'QTR P&L'!X2+'QTR P&L'!Y2 | J2: ='QTR P&L'!Z2+'QTR P&L'!AA2+'QTR P&L'!AB2+'QTR P&L'!AC2 | K2: ='QTR P&L'!AD2+'QTR P&L'!AE2+'QTR P&L'!AF2+'QTR P&L'!AG2 | L2: ='QTR P&L'!AH2+'QTR P&L'!AI2+'QTR P&L'!AJ2+'QTR P&L'!AK2
A3: COGS | B3: -37108 | C3: -42157 | D3: -42760 | E3: -40848 | F3: -41164 | G3: ='QTR P&L'!N3+'QTR P&L'!O3+'QTR P&L'!P3+'QTR P&L'!Q3 | H3: ='QTR P&L'!R3+'QTR P&L'!S3+'QTR P&L'!T3+'QTR P&L'!U3 | I3: ='QTR P&L'!V3+'QTR P&L'!W3+'QTR P&L'!X3+'QTR P&L'!Y3 | J3: ='QTR P&L'!Z3+'QTR P&L'!AA3+'QTR P&L'!AB3+'QTR P&L'!AC3 | K3: ='QTR P&L'!AD3+'QTR P&L'!AE3+'QTR P&L'!AF3+'QTR P&L'!AG3 | L3: ='QTR P&L'!AH3+'QTR P&L'!AI3+'QTR P&L'!AJ3+'QTR P&L'!AK3
A4: Gross Profit (Loss) | B4: =B2+B3 | C4: =C2+C3 | D4: =D2+D3 | E4: =E2+E3 | F4: =F2+F3 | G4: =G2+G3 | H4: =H2+H3 | I4: =I2+I3 | ... L4: =L2+L3
A5: SG&A | B5: -21024 | C5: -20217 | D5: -21112 | E5: -23305 | F5: -22669 | G5: ='QTR P&L'!N5+'QTR P&L'!O5+'QTR P&L'!P5+'QTR P&L'!Q5 | H5: ='QTR P&L'!R5+'QTR P&L'!S5+'QTR P&L'!T5+'QTR P&L'!U5 | I5: ='QTR P&L'!V5+'QTR P&L'!W5+'QTR P&L'!X5+'QTR P&L'!Y5 | J5: ='QTR P&L'!Z5+'QTR P&L'!AA5+'QTR P&L'!AB5+'QTR P&L'!AC5 | K5: ='QTR P&L'!AD5+'QTR P&L'!AE5+'QTR P&L'!AF5+'QTR P&L'!AG5 | L5: ='QTR P&L'!AH5+'QTR P&L'!AI5+'QTR P&L'!AJ5+'QTR P&L'!AK5
A6: Impairment of Intangibles | B6: 0 | C6: 0 | D6: 0 | E6: -1341 | F6: 0 | G6: ='QTR P&L'!N6+'QTR P&L'!O6+'QTR P&L'!P6+'QTR P&L'!Q6 | H6: ='QTR P&L'!R6+'QTR P&L'!S6+'QTR P&L'!T6+'QTR P&L'!U6 | I6: ='QTR P&L'!V6+'QTR P&L'!W6+'QTR P&L'!X6+'QTR P&L'!Y6 | J6: ='QTR P&L'!Z6+'QTR P&L'!AA6+'QTR P&L'!AB6+'QTR P&L'!AC6 | K6: ='QTR P&L'!AD6+'QTR P&L'!AE6+'QTR P&L'!AF6+'QTR P&L'!AG6 | L6: ='QTR P&L'!AH6+'QTR P&L'!AI6+'QTR P&L'!AJ6+'QTR P&L'!AK6
A7: Income (Loss) from Operations | B7: =B4+SUM(B5:B6) | C7: =C4+SUM(C5:C6) | D7: =D4+SUM(D5:D6) | E7: =E4+SUM(E5:E6) | F7: =F4+SUM(F5:F6) | G7: =G4+SUM(G5:G6) | H7: =H4+SUM(H5:H6) | I7: =I4+SUM(I5:I6) | ... L7: =L4+SUM(L5:L6)
A8: Interest Income (Expense) | B8: -457 | C8: -388 | D8: -449 | E8: -452 | F8: -438 | G8: ='QTR P&L'!N8+'QTR P&L'!O8+'QTR P&L'!P8+'QTR P&L'!Q8 | H8: ='QTR P&L'!R8+'QTR P&L'!S8+'QTR P&L'!T8+'QTR P&L'!U8 | I8: ='QTR P&L'!V8+'QTR P&L'!W8+'QTR P&L'!X8+'QTR P&L'!Y8 | J8: ='QTR P&L'!Z8+'QTR P&L'!AA8+'QTR P&L'!AB8+'QTR P&L'!AC8 | K8: ='QTR P&L'!AD8+'QTR P&L'!AE8+'QTR P&L'!AF8+'QTR P&L'!AG8 | L8: ='QTR P&L'!AH8+'QTR P&L'!AI8+'QTR P&L'!AJ8+'QTR P&L'!AK8
A9: Other Income (Expense) | B9: 86 | C9: 570 | D9: 668 | E9: 668 | F9: 154 | G9: ='QTR P&L'!N9+'QTR P&L'!O9+'QTR P&L'!P9+'QTR P&L'!Q9 | H9: ='QTR P&L'!R9+'QTR P&L'!S9+'QTR P&L'!T9+'QTR P&L'!U9 | I9: ='QTR P&L'!V9+'QTR P&L'!W9+'QTR P&L'!X9+'QTR P&L'!Y9 | J9: ='QTR P&L'!Z9+'QTR P&L'!AA9+'QTR P&L'!AB9+'QTR P&L'!AC9 | K9: ='QTR P&L'!AD9+'QTR P&L'!AE9+'QTR P&L'!AF9+'QTR P&L'!AG9 | L9: ='QTR P&L'!AH9+'QTR P&L'!AI9+'QTR P&L'!AJ9+'QTR P&L'!AK9
A10: Pre-Tax Income (Loss) | B10: =B7+SUM(B8:B9) | C10: =C7+SUM(C8:C9) | D10: =D7+SUM(D8:D9) | E10: =E7+SUM(E8:E9) | F10: =F7+SUM(F8:F9) | G10: =G7+SUM(G8:G9) | H10: =H7+SUM(H8:H9) | I10: =I7+SUM(I8:I9) | ... L10: =L7+SUM(L8:L9)
A11: Income Tax (Expense) Benefit | B11: -3263 | C11: -3202 | D11: -3615 | E11: -3787 | F11: -4102 | G11: ='QTR P&L'!N11+'QTR P&L'!O11+'QTR P&L'!P11+'QTR P&L'!Q11 | H11: ='QTR P&L'!R11+'QTR P&L'!S11+'QTR P&L'!T11+'QTR P&L'!U11 | I11: ='QTR P&L'!V11+'QTR P&L'!W11+'QTR P&L'!X11+'QTR P&L'!Y11 | J11: ='QTR P&L'!Z11+'QTR P&L'!AA11+'QTR P&L'!AB11+'QTR P&L'!AC11 | K11: ='QTR P&L'!AD11+'QTR P&L'!AE11+'QTR P&L'!AF11+'QTR P&L'!AG11 | L11: ='QTR P&L'!AH11+'QTR P&L'!AI11+'QTR P&L'!AJ11+'QTR P&L'!AK11
A12: Net Income (Loss) | B12: =B10+B11 | C12: =C10+C11 | D12: =D10+D11 | E12: =E10+E11 | F12: =F10+F11 | G12: =G10+G11 | H12: =H10+H11 | I12: =I10+I11 | ... L12: =L10+L11
A13: Net Income (Loss) Attributable to Noncontrolling Interest | B13: 46 | C13: 51 | D13: 85 | E13: 95 | F13: 91 | G13: ='QTR P&L'!N13+'QTR P&L'!O13+'QTR P&L'!P13+'QTR P&L'!Q13 | H13: ='QTR P&L'!R13+'QTR P&L'!S13+'QTR P&L'!T13+'QTR P&L'!U13 | I13: ='QTR P&L'!V13+'QTR P&L'!W13+'QTR P&L'!X13+'QTR P&L'!Y13 | J13: ='QTR P&L'!Z13+'QTR P&L'!AA13+'QTR P&L'!AB13+'QTR P&L'!AC13 | K13: ='QTR P&L'!AD13+'QTR P&L'!AE13+'QTR P&L'!AF13+'QTR P&L'!AG13 | L13: ='QTR P&L'!AH13+'QTR P&L'!AI13+'QTR P&L'!AJ13+'QTR P&L'!AK13
A14: Net Income (Loss) Less NCI | B14: =B12-B13 | C14: =C12-C13 | D14: =D12-D13 | E14: =E12-E13 | F14: =F12-F13 | G14: =G12-G13 | H14: =H12-H13 | I14: =I12-I13 | ... L14: =L12-L13
A15: Basic Earnings (Loss) per Share | B15: 5.69 | C15: 6 | D15: 6.07 | E15: 6.18 | F15: 6.67
A16: Diluted Earnings (Loss) per Share | B16: 5.5 | C16: 5.81 | D16: 5.9 | E16: 6.02 | F16: 6.51

Sheet BALANCE SHEET
B1: FY2022 | C1: FY2023 | D1: FY2024 | E1: FY2025 | F1: FY2025E | G1: FY2026E | H1: FY2027E | I1: FY2028E | J1: FY2029E | K1: FY2030E
A2: Cash & Cash Equivalents | B2: 7214 | C2: 8246 | D2: 9482 | E2: 9556 | F2: ='QTR BS'!N2 | G2: ='QTR BS'!R2 | H2: ='QTR BS'!V2 | I2: ='QTR BS'!Z2 | J2: ='QTR BS'!AD2 | K2: ='QTR BS'!AH2
A3: Accounts Receivable | B3: 5143 | C3: 5471 | D3: 6118 | E3: 6185 | F3: ='QTR BS'!N3 | G3: ='QTR BS'!R3 | H3: ='QTR BS'!V3 | I3: ='QTR BS'!Z3 | J3: ='QTR BS'!AD3 | K3: ='QTR BS'!AH3
A4: Inventories | B4: 6924 | C4: 7073 | D4: 7016 | E4: 7551 | F4: ='QTR BS'!N4 | G4: ='QTR BS'!R4 | H4: ='QTR BS'!V4 | I4: ='QTR BS'!Z4 | J4: ='QTR BS'!AD4 | K4: ='QTR BS'!AH4
A5: Prepaid Expenses | B5: 2372 | C5: 1858 | D5: 2095 | E5: 2100 | F5: ='QTR BS'!N5 | G5: ='QTR BS'!R5 | H5: ='QTR BS'!V5 | I5: ='QTR BS'!Z5 | J5: ='QTR BS'!AD5 | K5: ='QTR BS'!AH5
A6: Total Current Assets | B6: =SUM(B2:B5) | C6: =SUM(C2:C5) | D6: =SUM(D2:D5) | E6: =SUM(E2:E5) | F6: =SUM(F2:F5) | G6: =SUM(G2:G5) | H6: =SUM(H2:H5) | I6: =SUM(I2:I5) | ... K6: =SUM(K2:K5)
A7: Net PP&E | B7: 21195 | C7: 21909 | D7: 22152 | E7: 23897 | F7: ='QTR BS'!N7 | G7: ='QTR BS'!R7 | H7: ='QTR BS'!V7 | I7: ='QTR BS'!Z7 | J7: ='QTR BS'!AD7 | K7: ='QTR BS'!AH7
A8: Goodwill | B8: 39700 | C8: 40659 | D8: 40303 | E8: 41650 | F8: ='QTR BS'!N8 | G8: ='QTR BS'!R8 | H8: ='QTR BS'!V8 | I8: ='QTR BS'!Z8 | J8: ='QTR BS'!AD8 | K8: ='QTR BS'!AH8
A9: Intangible Assets | B9: 23679 | C9: 23783 | D9: 22047 | E9: 21910 | F9: ='QTR BS'!N9 | G9: ='QTR BS'!R9 | H9: ='QTR BS'!V9 | I9: ='QTR BS'!Z9 | J9: ='QTR BS'!AD9 | K9: ='QTR BS'!AH9
A10: Other Non-Current Assets | B10: 10981 | C10: 11830 | D10: 13158 | E10: 12381 | F10: ='QTR BS'!N10 | G10: ='QTR BS'!R10 | H10: ='QTR BS'!V10 | I10: ='QTR BS'!Z10 | J10: ='QTR BS'!AD10 | K10: ='QTR BS'!AH10
A11: Total Assets | B11: =B6+SUM(B7:B10) | C11: =C6+SUM(C7:C10) | D11: =D6+SUM(D7:D10) | E11: =E6+SUM(E7:E10) | F11: =F6+SUM(F7:F10) | G11: =G6+SUM(G7:G10) | H11: =H6+SUM(H7:H10) | I11: =I6+SUM(I7:I10) | ... K11: =K6+SUM(K7:K10)
A12: Accounts Payable | B12: 14882 | C12: 14598 | D12: 15364 | E12: 15227 | F12: ='QTR BS'!N12 | G12: ='QTR BS'!R12 | H12: ='QTR BS'!V12 | I12: ='QTR BS'!Z12 | J12: ='QTR BS'!AD12 | K12: ='QTR BS'!AH12
A13: Accrued Expenses | B13: 9554 | C13: 10929 | D13: 11073 | E13: 11318 | F13: ='QTR BS'!N13 | G13: ='QTR BS'!R13 | H13: ='QTR BS'!V13 | I13: ='QTR BS'!Z13 | J13: ='QTR BS'!AD13 | K13: ='QTR BS'!AH13
A14: Current Portion of Long-Term Debt | B14: 8645 | C14: 10229 | D14: 7191 | E14: 9513 | F14: ='QTR BS'!N14 | G14: ='QTR BS'!R14 | H14: ='QTR BS'!V14 | I14: ='QTR BS'!Z14 | J14: ='QTR BS'!AD14 | K14: ='QTR BS'!AH14
A15: Total Current Liabilities | B15: =SUM(B12:B14) | C15: =SUM(C12:C14) | D15: =SUM(D12:D14) | E15: =SUM(E12:E14) | F15: =SUM(F12:F14) | G15: =SUM(G12:G14) | H15: =SUM(H12:H14) | I15: =SUM(I12:I14) | ... K15: =SUM(K12:K14)
A16: Long-Term Debt | B16: 22848 | C16: 24378 | D16: 25269 | E16: 24995 | F16: ='QTR BS'!N16 | G16: ='QTR BS'!R16 | H16: ='QTR BS'!V16 | I16: ='QTR BS'!Z16 | J16: ='QTR BS'!AD16 | K16: ='QTR BS'!AH16
A17: Deferred Tax Liability | B17: 6809 | C17: 6478 | D17: 6516 | E17: 5774 | F17: ='QTR BS'!N17 | G17: ='QTR BS'!R17 | H17: ='QTR BS'!V17 | I17: ='QTR BS'!Z17 | J17: ='QTR BS'!AD17 | K17: ='QTR BS'!AH17
A18: Other Non-Current Liabilities | B18: 7616 | C18: 7152 | D18: 6398 | E18: 6120 | F18: ='QTR BS'!N18 | G18: ='QTR BS'!R18 | H18: ='QTR BS'!V18 | I18: ='QTR BS'!Z18 | J18: ='QTR BS'!AD18 | K18: ='QTR BS'!AH18
A19: Total Liabilities | B19: =B15+SUM(B16:B18) | C19: =C15+SUM(C16:C18) | D19: =D15+SUM(D16:D18) | E19: =E15+SUM(E16:E18) | F19: =F15+SUM(F16:F18) | G19: =G15+SUM(G16:G18) | H19: =H15+SUM(H16:H18) | I19: =I15+SUM(I16:I18) | ... K19: =K15+SUM(K16:K18)
A20: Convertible Preferred Stock | B20: 843 | C20: 819 | D20: 798 | E20: 777 | F20: ='QTR BS'!N20 | G20: ='QTR BS'!R20 | H20: ='QTR BS'!V20 | I20: ='QTR BS'!Z20 | J20: ='QTR BS'!AD20 | K20: ='QTR BS'!AH20
A21: Common Stock | B21: 4009 | C21: 4009 | D21: 4009 | E21: 4009 | F21: ='QTR BS'!N21 | G21: ='QTR BS'!R21 | H21: ='QTR BS'!V21 | I21: ='QTR BS'!Z21 | J21: ='QTR BS'!AD21 | K21: ='QTR BS'!AH21
A22: Additional Paid-in Capital | B22: 65795 | C22: 66556 | D22: 67684 | E22: 68770 | F22: ='QTR BS'!N22 | G22: ='QTR BS'!R22 | H22: ='QTR BS'!V22 | I22: ='QTR BS'!Z22 | J22: ='QTR BS'!AD22 | K22: ='QTR BS'!AH22
A23: ESOP Debt Retirement Reserve | B23: -916 | C23: -821 | D23: -737 | E23: -672 | F23: ='QTR BS'!N23 | G23: ='QTR BS'!R23 | H23: ='QTR BS'!V23 | I23: ='QTR BS'!Z23 | J23: ='QTR BS'!AD23 | K23: ='QTR BS'!AH23
A24: Accumulated Other Comprehensive Income (Loss) | B24: -12189 | C24: -12220 | D24: -11900 | E24: -12143 | F24: ='QTR BS'!N24 | G24: ='QTR BS'!R24 | H24: ='QTR BS'!V24 | I24: ='QTR BS'!Z24 | J24: ='QTR BS'!AD24 | K24: ='QTR BS'!AH24
A25: Treasury Stock | B25: -123382 | C25: -129736 | D25: -133379 | E25: -138702 | F25: ='QTR BS'!N25 | G25: ='QTR BS'!R25 | H25: ='QTR BS'!V25 | I25: ='QTR BS'!Z25 | J25: ='QTR BS'!AD25 | K25: ='QTR BS'!AH25
A26: Retained Earnings (Accumulated Deficit) | B26: 112429 | C26: 118170 | D26: 123811 | E26: 129973 | F26: ='QTR BS'!N26 | G26: ='QTR BS'!R26 | H26: ='QTR BS'!V26 | I26: ='QTR BS'!Z26 | J26: ='QTR BS'!AD26 | K26: ='QTR BS'!AH26
A27: Noncontrolling Interest | B27: 265 | C27: 288 | D27: 272 | E27: 272 | F27: ='QTR BS'!N27 | G27: ='QTR BS'!R27 | H27: ='QTR BS'!V27 | I27: ='QTR BS'!Z27 | J27: ='QTR BS'!AD27 | K27: ='QTR BS'!AH27
A28: Total Stockholders' Equity | B28: =SUM(B20:B27) | C28: =SUM(C20:C27) | D28: =SUM(D20:D27) | E28: =SUM(E20:E27) | F28: =SUM(F20:F27) | G28: =SUM(G20:G27) | H28: =SUM(H20:H27) | I28: =SUM(I20:I27) | ... K28: =SUM(K20:K27)
A29: Total Liabilities, Mezzanine & Stockholders' Equity | B29: =B19+B28 | C29: =C19+C28 | D29: =D19+D28 | E29: =E19+E28 | F29: =F19+F28 | G29: =G19+G28 | H29: =H19+H28 | I29: =I19+I28 | ... K29: =K19+K28

Sheet CASH FLOW
B1: FY2021 | C1: FY2022 | D1: FY2023 | E1: FY2024 | F1: FY2025 | G1: FY2025E | H1: FY2026E | I1: FY2027E | J1: FY2028E | K1: FY2029E | L1: FY2030E
A2: Net Income (Loss) | B2: 14352 | C2: 14793 | D2: 14738 | E2: 14974 | F2: 16065 | G2: ='QTR CF'!N2+'QTR CF'!O2+'QTR CF'!P2+'QTR CF'!Q2 | H2: ='QTR CF'!R2+'QTR CF'!S2+'QTR CF'!T2+'QTR CF'!U2 | I2: ='QTR CF'!V2+'QTR CF'!W2+'QTR CF'!X2+'QTR CF'!Y2 | J2: ='QTR CF'!Z2+'QTR CF'!AA2+'QTR CF'!AB2+'QTR CF'!AC2 | K2: ='QTR CF'!AD2+'QTR CF'!AE2+'QTR CF'!AF2+'QTR CF'!AG2 | L2: ='QTR CF'!AH2+'QTR CF'!AI2+'QTR CF'!AJ2+'QTR CF'!AK2
A3: Depreciation & Amortization | B3: 2735 | C3: 2807 | D3: 2714 | E3: 2896 | F3: 2847 | G3: ='QTR CF'!N3+'QTR CF'!O3+'QTR CF'!P3+'QTR CF'!Q3 | H3: ='QTR CF'!R3+'QTR CF'!S3+'QTR CF'!T3+'QTR CF'!U3 | I3: ='QTR CF'!V3+'QTR CF'!W3+'QTR CF'!X3+'QTR CF'!Y3 | J3: ='QTR CF'!Z3+'QTR CF'!AA3+'QTR CF'!AB3+'QTR CF'!AC3 | K3: ='QTR CF'!AD3+'QTR CF'!AE3+'QTR CF'!AF3+'QTR CF'!AG3 | L3: ='QTR CF'!AH3+'QTR CF'!AI3+'QTR CF'!AJ3+'QTR CF'!AK3
A4: Gain (Loss) on Extinguishment of Debt | B4: 512 | C4: 0 | D4: 0 | E4: 0 | F4: 0
A5: Stock-Based Compensation | B5: 540 | C5: 528 | D5: 545 | E5: 562 | F5: 476 | G5: ='QTR CF'!N4+'QTR CF'!O4+'QTR CF'!P4+'QTR CF'!Q4 | H5: ='QTR CF'!R4+'QTR CF'!S4+'QTR CF'!T4+'QTR CF'!U4 | I5: ='QTR CF'!V4+'QTR CF'!W4+'QTR CF'!X4+'QTR CF'!Y4 | J5: ='QTR CF'!Z4+'QTR CF'!AA4+'QTR CF'!AB4+'QTR CF'!AC4 | K5: ='QTR CF'!AD4+'QTR CF'!AE4+'QTR CF'!AF4+'QTR CF'!AG4 | L5: ='QTR CF'!AH4+'QTR CF'!AI4+'QTR CF'!AJ4+'QTR CF'!AK4
A6: (Benefit) Provision for Deferred Income Taxes | B6: -258 | C6: -402 | D6: -453 | E6: -244 | F6: 149 | G6: ='QTR CF'!N5+'QTR CF'!O5+'QTR CF'!P5+'QTR CF'!Q5 | H6: ='QTR CF'!R5+'QTR CF'!S5+'QTR CF'!T5+'QTR CF'!U5 | I6: ='QTR CF'!V5+'QTR CF'!W5+'QTR CF'!X5+'QTR CF'!Y5 | J6: ='QTR CF'!Z5+'QTR CF'!AA5+'QTR CF'!AB5+'QTR CF'!AC5 | K6: ='QTR CF'!AD5+'QTR CF'!AE5+'QTR CF'!AF5+'QTR CF'!AG5 | L6: ='QTR CF'!AH5+'QTR CF'!AI5+'QTR CF'!AJ5+'QTR CF'!AK5
A7: Gain (Loss) on Disposal of PP&E | B7: -16 | C7: -85 | D7: -40 | E7: -215 | F7: 755 | G7: ='QTR CF'!N6+'QTR CF'!O6+'QTR CF'!P6+'QTR CF'!Q6 | H7: ='QTR CF'!R6+'QTR CF'!S6+'QTR CF'!T6+'QTR CF'!U6 | I7: ='QTR CF'!V6+'QTR CF'!W6+'QTR CF'!X6+'QTR CF'!Y6 | J7: ='QTR CF'!Z6+'QTR CF'!AA6+'QTR CF'!AB6+'QTR CF'!AC6 | K7: ='QTR CF'!AD6+'QTR CF'!AE6+'QTR CF'!AF6+'QTR CF'!AG6 | L7: ='QTR CF'!AH6+'QTR CF'!AI6+'QTR CF'!AJ6+'QTR CF'!AK6
A8: Impairment of Intangibles | B8: 0 | C8: 0 | D8: 0 | E8: 1341 | F8: 0 | G8: ='QTR CF'!N7+'QTR CF'!O7+'QTR CF'!P7+'QTR CF'!Q7 | H8: ='QTR CF'!R7+'QTR CF'!S7+'QTR CF'!T7+'QTR CF'!U7 | I8: ='QTR CF'!V7+'QTR CF'!W7+'QTR CF'!X7+'QTR CF'!Y7 | J8: ='QTR CF'!Z7+'QTR CF'!AA7+'QTR CF'!AB7+'QTR CF'!AC7 | K8: ='QTR CF'!AD7+'QTR CF'!AE7+'QTR CF'!AF7+'QTR CF'!AG7 | L8: ='QTR CF'!AH7+'QTR CF'!AI7+'QTR CF'!AJ7+'QTR CF'!AK7
A9: Accounts Receivable | B9: -342 | C9: -694 | D9: -307 | E9: -766 | F9: 45 | G9: ='QTR CF'!N8+'QTR CF'!O8+'QTR CF'!P8+'QTR CF'!Q8 | H9: ='QTR CF'!R8+'QTR CF'!S8+'QTR CF'!T8+'QTR CF'!U8 | I9: ='QTR CF'!V8+'QTR CF'!W8+'QTR CF'!X8+'QTR CF'!Y8 | J9: ='QTR CF'!Z8+'QTR CF'!AA8+'QTR CF'!AB8+'QTR CF'!AC8 | K9: ='QTR CF'!AD8+'QTR CF'!AE8+'QTR CF'!AF8+'QTR CF'!AG8 | L9: ='QTR CF'!AH8+'QTR CF'!AI8+'QTR CF'!AJ8+'QTR CF'!AK8
A10: Inventories | B10: -309 | C10: -1247 | D10: -119 | E10: -70 | F10: -324 | G10: ='QTR CF'!N9+'QTR CF'!O9+'QTR CF'!P9+'QTR CF'!Q9 | H10: ='QTR CF'!R9+'QTR CF'!S9+'QTR CF'!T9+'QTR CF'!U9 | I10: ='QTR CF'!V9+'QTR CF'!W9+'QTR CF'!X9+'QTR CF'!Y9 | J10: ='QTR CF'!Z9+'QTR CF'!AA9+'QTR CF'!AB9+'QTR CF'!AC9 | K10: ='QTR CF'!AD9+'QTR CF'!AE9+'QTR CF'!AF9+'QTR CF'!AG9 | L10: ='QTR CF'!AH9+'QTR CF'!AI9+'QTR CF'!AJ9+'QTR CF'!AK9
A11: Accounts Payable | B11: 1391 | C11: 1429 | D11: 313 | E11: 1814 | F11: -542 | G11: ='QTR CF'!N10+'QTR CF'!O10+'QTR CF'!P10+'QTR CF'!Q10 | H11: ='QTR CF'!R10+'QTR CF'!S10+'QTR CF'!T10+'QTR CF'!U10 | I11: ='QTR CF'!V10+'QTR CF'!W10+'QTR CF'!X10+'QTR CF'!Y10 | J11: ='QTR CF'!Z10+'QTR CF'!AA10+'QTR CF'!AB10+'QTR CF'!AC10 | K11: ='QTR CF'!AD10+'QTR CF'!AE10+'QTR CF'!AF10+'QTR CF'!AG10 | L11: ='QTR CF'!AH10+'QTR CF'!AI10+'QTR CF'!AJ10+'QTR CF'!AK10
A12: Net Change in Other Working Capital | B12: -369 | C12: -635 | D12: -1107 | E12: -1414 | F12: 0 | G12: ='QTR CF'!N11+'QTR CF'!O11+'QTR CF'!P11+'QTR CF'!Q11 | H12: ='QTR CF'!R11+'QTR CF'!S11+'QTR CF'!T11+'QTR CF'!U11 | I12: ='QTR CF'!V11+'QTR CF'!W11+'QTR CF'!X11+'QTR CF'!Y11 | J12: ='QTR CF'!Z11+'QTR CF'!AA11+'QTR CF'!AB11+'QTR CF'!AC11 | K12: ='QTR CF'!AD11+'QTR CF'!AE11+'QTR CF'!AF11+'QTR CF'!AG11 | L12: ='QTR CF'!AH11+'QTR CF'!AI11+'QTR CF'!AJ11+'QTR CF'!AK11
A13: Other Operating Items | B13: 135 | C13: 229 | D13: 564 | E13: 969 | F13: -1653 | G13: ='QTR CF'!N12+'QTR CF'!O12+'QTR CF'!P12+'QTR CF'!Q12 | H13: ='QTR CF'!R12+'QTR CF'!S12+'QTR CF'!T12+'QTR CF'!U12 | I13: ='QTR CF'!V12+'QTR CF'!W12+'QTR CF'!X12+'QTR CF'!Y12 | J13: ='QTR CF'!Z12+'QTR CF'!AA12+'QTR CF'!AB12+'QTR CF'!AC12 | K13: ='QTR CF'!AD12+'QTR CF'!AE12+'QTR CF'!AF12+'QTR CF'!AG12 | L13: ='QTR CF'!AH12+'QTR CF'!AI12+'QTR CF'!AJ12+'QTR CF'!AK12
A14: Cash Flow from Operations | B14: =SUM(B2:B13) | C14: =SUM(C2:C13) | D14: =SUM(D2:D13) | E14: =SUM(E2:E13) | F14: =SUM(F2:F13) | G14: =SUM(G2:G13) | H14: =SUM(H2:H13) | I14: =SUM(I2:I13) | ... L14: =SUM(L2:L13)
A15: Purchase of PP&E | B15: -2787 | C15: -3156 | D15: -3062 | E15: -3322 | F15: -3773 | G15: ='QTR CF'!N14+'QTR CF'!O14+'QTR CF'!P14+'QTR CF'!Q14 | H15: ='QTR CF'!R14+'QTR CF'!S14+'QTR CF'!T14+'QTR CF'!U14 | I15: ='QTR CF'!V14+'QTR CF'!W14+'QTR CF'!X14+'QTR CF'!Y14 | J15: ='QTR CF'!Z14+'QTR CF'!AA14+'QTR CF'!AB14+'QTR CF'!AC14 | K15: ='QTR CF'!AD14+'QTR CF'!AE14+'QTR CF'!AF14+'QTR CF'!AG14 | L15: ='QTR CF'!AH14+'QTR CF'!AI14+'QTR CF'!AJ14+'QTR CF'!AK14
A16: Proceeds from Sale of Assets | B16: 42 | C16: 110 | D16: 46 | E16: 346 | F16: 107 | G16: ='QTR CF'!N15+'QTR CF'!O15+'QTR CF'!P15+'QTR CF'!Q15 | H16: ='QTR CF'!R15+'QTR CF'!S15+'QTR CF'!T15+'QTR CF'!U15 | I16: ='QTR CF'!V15+'QTR CF'!W15+'QTR CF'!X15+'QTR CF'!Y15 | J16: ='QTR CF'!Z15+'QTR CF'!AA15+'QTR CF'!AB15+'QTR CF'!AC15 | K16: ='QTR CF'!AD15+'QTR CF'!AE15+'QTR CF'!AF15+'QTR CF'!AG15 | L16: ='QTR CF'!AH15+'QTR CF'!AI15+'QTR CF'!AJ15+'QTR CF'!AK15
A17: Acquisitions, Net of Cash Acquired | B17: -34 | C17: -1381 | D17: -765 | E17: -21 | F17: -11 | G17: ='QTR CF'!N16+'QTR CF'!O16+'QTR CF'!P16+'QTR CF'!Q16 | H17: ='QTR CF'!R16+'QTR CF'!S16+'QTR CF'!T16+'QTR CF'!U16 | I17: ='QTR CF'!V16+'QTR CF'!W16+'QTR CF'!X16+'QTR CF'!Y16 | J17: ='QTR CF'!Z16+'QTR CF'!AA16+'QTR CF'!AB16+'QTR CF'!AC16 | K17: ='QTR CF'!AD16+'QTR CF'!AE16+'QTR CF'!AF16+'QTR CF'!AG16 | L17: ='QTR CF'!AH16+'QTR CF'!AI16+'QTR CF'!AJ16+'QTR CF'!AK16
A18: Other Investing Activities | B18: -55 | C18: 3 | D18: 281 | E18: -507 | F18: -141 | G18: ='QTR CF'!N18+'QTR CF'!O18+'QTR CF'!P18+'QTR CF'!Q18 | H18: ='QTR CF'!R18+'QTR CF'!S18+'QTR CF'!T18+'QTR CF'!U18 | I18: ='QTR CF'!V18+'QTR CF'!W18+'QTR CF'!X18+'QTR CF'!Y18 | J18: ='QTR CF'!Z18+'QTR CF'!AA18+'QTR CF'!AB18+'QTR CF'!AC18 | K18: ='QTR CF'!AD18+'QTR CF'!AE18+'QTR CF'!AF18+'QTR CF'!AG18 | L18: ='QTR CF'!AH18+'QTR CF'!AI18+'QTR CF'!AJ18+'QTR CF'!AK18
A19: Cash Flow from Investing | B19: =SUM(B15:B18) | C19: =SUM(C15:C18) | D19: =SUM(D15:D18) | E19: =SUM(E15:E18) | F19: =SUM(F15:F18) | G19: =SUM(G15:G18) | H19: =SUM(H15:H18) | I19: =SUM(I15:I18) | ... L19: =SUM(L15:L18)
A20: Common Dividends | B20: -8263 | C20: -8770 | D20: -8999 | E20: -9312 | F20: -9872 | G20: ='QTR CF'!N20+'QTR CF'!O20+'QTR CF'!P20+'QTR CF'!Q20 | H20: ='QTR CF'!R20+'QTR CF'!S20+'QTR CF'!T20+'QTR CF'!U20 | I20: ='QTR CF'!V20+'QTR CF'!W20+'QTR CF'!X20+'QTR CF'!Y20 | J20: ='QTR CF'!Z20+'QTR CF'!AA20+'QTR CF'!AB20+'QTR CF'!AC20 | K20: ='QTR CF'!AD20+'QTR CF'!AE20+'QTR CF'!AF20+'QTR CF'!AG20 | L20: ='QTR CF'!AH20+'QTR CF'!AI20+'QTR CF'!AJ20+'QTR CF'!AK20
A21: Proceeds from Short-Term Debt | B21: 7675 | C21: 10411 | D21: 17168 | E21: 3528 | F21: 8020 | G21: ='QTR CF'!N21+'QTR CF'!O21+'QTR CF'!P21+'QTR CF'!Q21 | H21: ='QTR CF'!R21+'QTR CF'!S21+'QTR CF'!T21+'QTR CF'!U21 | I21: ='QTR CF'!V21+'QTR CF'!W21+'QTR CF'!X21+'QTR CF'!Y21 | J21: ='QTR CF'!Z21+'QTR CF'!AA21+'QTR CF'!AB21+'QTR CF'!AC21 | K21: ='QTR CF'!AD21+'QTR CF'!AE21+'QTR CF'!AF21+'QTR CF'!AG21 | L21: ='QTR CF'!AH21+'QTR CF'!AI21+'QTR CF'!AJ21+'QTR CF'!AK21
A22: Repayments of Short-Term Debt | B22: -7577 | C22: -11478 | D22: -13031 | E22: -7689 | F22: -6512 | G22: ='QTR CF'!N22+'QTR CF'!O22+'QTR CF'!P22+'QTR CF'!Q22 | H22: ='QTR CF'!R22+'QTR CF'!S22+'QTR CF'!T22+'QTR CF'!U22 | I22: ='QTR CF'!V22+'QTR CF'!W22+'QTR CF'!X22+'QTR CF'!Y22 | J22: ='QTR CF'!Z22+'QTR CF'!AA22+'QTR CF'!AB22+'QTR CF'!AC22 | K22: ='QTR CF'!AD22+'QTR CF'!AE22+'QTR CF'!AF22+'QTR CF'!AG22 | L22: ='QTR CF'!AH22+'QTR CF'!AI22+'QTR CF'!AJ22+'QTR CF'!AK22
A23: Net Change in Other Short-Term Debt | B23: -3431 | C23: 917 | D23: -3319 | E23: 857 | F23: -1138 | G23: ='QTR CF'!N23+'QTR CF'!O23+'QTR CF'!P23+'QTR CF'!Q23 | H23: ='QTR CF'!R23+'QTR CF'!S23+'QTR CF'!T23+'QTR CF'!U23 | I23: ='QTR CF'!V23+'QTR CF'!W23+'QTR CF'!X23+'QTR CF'!Y23 | J23: ='QTR CF'!Z23+'QTR CF'!AA23+'QTR CF'!AB23+'QTR CF'!AC23 | K23: ='QTR CF'!AD23+'QTR CF'!AE23+'QTR CF'!AF23+'QTR CF'!AG23 | L23: ='QTR CF'!AH23+'QTR CF'!AI23+'QTR CF'!AJ23+'QTR CF'!AK23
A24: Proceeds from Issuance of Long-Term Debt | B24: 4417 | C24: 4385 | D24: 3997 | E24: 3197 | F24: 2237 | G24: ='QTR CF'!N24+'QTR CF'!O24+'QTR CF'!P24+'QTR CF'!Q24 | H24: ='QTR CF'!R24+'QTR CF'!S24+'QTR CF'!T24+'QTR CF'!U24 | I24: ='QTR CF'!V24+'QTR CF'!W24+'QTR CF'!X24+'QTR CF'!Y24 | J24: ='QTR CF'!Z24+'QTR CF'!AA24+'QTR CF'!AB24+'QTR CF'!AC24 | K24: ='QTR CF'!AD24+'QTR CF'!AE24+'QTR CF'!AF24+'QTR CF'!AG24 | L24: ='QTR CF'!AH24+'QTR CF'!AI24+'QTR CF'!AJ24+'QTR CF'!AK24
A25: Repayments of Long-Term Debt | B25: -4987 | C25: -2343 | D25: -1878 | E25: -2335 | F25: -1977 | G25: ='QTR CF'!N25+'QTR CF'!O25+'QTR CF'!P25+'QTR CF'!Q25 | H25: ='QTR CF'!R25+'QTR CF'!S25+'QTR CF'!T25+'QTR CF'!U25 | I25: ='QTR CF'!V25+'QTR CF'!W25+'QTR CF'!X25+'QTR CF'!Y25 | J25: ='QTR CF'!Z25+'QTR CF'!AA25+'QTR CF'!AB25+'QTR CF'!AC25 | K25: ='QTR CF'!AD25+'QTR CF'!AE25+'QTR CF'!AF25+'QTR CF'!AG25 | L25: ='QTR CF'!AH25+'QTR CF'!AI25+'QTR CF'!AJ25+'QTR CF'!AK25
A26: Share Repurchases | B26: -11009 | C26: -10003 | D26: -7353 | E26: -5006 | F26: -6500 | G26: ='QTR CF'!N26+'QTR CF'!O26+'QTR CF'!P26+'QTR CF'!Q26 | H26: ='QTR CF'!R26+'QTR CF'!S26+'QTR CF'!T26+'QTR CF'!U26 | I26: ='QTR CF'!V26+'QTR CF'!W26+'QTR CF'!X26+'QTR CF'!Y26 | J26: ='QTR CF'!Z26+'QTR CF'!AA26+'QTR CF'!AB26+'QTR CF'!AC26 | K26: ='QTR CF'!AD26+'QTR CF'!AE26+'QTR CF'!AF26+'QTR CF'!AG26 | L26: ='QTR CF'!AH26+'QTR CF'!AI26+'QTR CF'!AJ26+'QTR CF'!AK26
A27: Stock Options & Other Financing Activities | B27: 1644 | C27: 2005 | D27: 1269 | E27: 1905 | F27: 1707 | G27: ='QTR CF'!N27+'QTR CF'!O27+'QTR CF'!P27+'QTR CF'!Q27 | H27: ='QTR CF'!R27+'QTR CF'!S27+'QTR CF'!T27+'QTR CF'!U27 | I27: ='QTR CF'!V27+'QTR CF'!W27+'QTR CF'!X27+'QTR CF'!Y27 | J27: ='QTR CF'!Z27+'QTR CF'!AA27+'QTR CF'!AB27+'QTR CF'!AC27 | K27: ='QTR CF'!AD27+'QTR CF'!AE27+'QTR CF'!AF27+'QTR CF'!AG27 | L27: ='QTR CF'!AH27+'QTR CF'!AI27+'QTR CF'!AJ27+'QTR CF'!AK27
A28: Cash Flow from Financing | B28: =SUM(B20:B27) | C28: =SUM(C20:C27) | D28: =SUM(D20:D27) | E28: =SUM(E20:E27) | F28: =SUM(F20:F27) | G28: =SUM(G20:G27) | H28: =SUM(H20:H27) | I28: =SUM(I20:I27) | ... L28: =SUM(L20:L27)
A29: FX Effect on Cash | B29: 101 | C29: -497 | D29: -170 | E29: -251 | F29: 112 | G29: ='QTR CF'!N29+'QTR CF'!O29+'QTR CF'!P29+'QTR CF'!Q29 | H29: ='QTR CF'!R29+'QTR CF'!S29+'QTR CF'!T29+'QTR CF'!U29 | I29: ='QTR CF'!V29+'QTR CF'!W29+'QTR CF'!X29+'QTR CF'!Y29 | J29: ='QTR CF'!Z29+'QTR CF'!AA29+'QTR CF'!AB29+'QTR CF'!AC29 | K29: ='QTR CF'!AD29+'QTR CF'!AE29+'QTR CF'!AF29+'QTR CF'!AG29 | L29: ='QTR CF'!AH29+'QTR CF'!AI29+'QTR CF'!AJ29+'QTR CF'!AK29
A30: Net Change in Cash | B30: =B14+B19+B28+B29 | C30: =C14+C19+C28+C29 | D30: =D14+D19+D28+D29 | E30: =E14+E19+E28+E29 | F30: =F14+F19+F28+F29 | G30: =G14+G19+G28+G29 | H30: =H14+H19+H28+H29 | I30: =I14+I19+I28+I29 | ... L30: =L14+L19+L28+L29

Sheet YTD P&L
B1: Q1 FY2022 | C1: Q2 FY2022 | D1: Q3 FY2022 | E1: Q1 FY2023 | F1: Q2 FY2023 | G1: Q3 FY2023 | H1: Q1 FY2024 | I1: Q2 FY2024 | J1: Q3 FY2024 | K1: Q1 FY2025 | L1: Q2 FY2025 | M1: Q3 FY2025 | N1: Q1 FY2026 | O1: Q2 FY2026
A2: Net Sales / Revenue | B2: 20338 | C2: 41291 | D2: 60672 | E2: 20612 | F2: 41385 | G2: 61453 | H2: 21871 | I2: 43312 | J2: 63507 | K2: 21737 | L2: 43619 | M2: 63395 | N2: 22386 | O2: 44594
A3: COGS | B3: -10365 | C3: -21029 | D3: -31355 | E3: -10846 | F3: -21743 | G3: -32147 | H3: -10501 | I3: -20645 | J3: -30500 | K3: -10421 | L3: -20839 | M3: -30533 | N3: -10887 | O3: -21721
A4: Gross Profit (Loss) | B4: =B2+B3 | C4: =C2+C3 | D4: =D2+D3 | E4: =E2+E3 | F4: =F2+F3 | G4: =G2+G3 | H4: =H2+H3 | I4: =I2+I3 | ... O4: =O2+O3
A5: SG&A | B5: -4950 | C5: -10071 | D5: -15102 | E5: -4827 | F5: -9918 | G5: -15334 | H5: -5604 | I5: -11127 | J5: -17006 | K5: -5519 | L5: -11242 | M5: -16765 | N5: -5643 | O5: -11651
A6: Impairment of Intangibles | B6: 0 | C6: 0 | D6: 0 | E6: 0 | F6: 0 | G6: 0 | H6: 0 | I6: -1341 | J6: -1341 | K6: 0 | L6: 0 | M6: 0 | N6: 0 | O6: 0
A7: Income (Loss) from Operations | B7: =B4+SUM(B5:B6) | C7: =C4+SUM(C5:C6) | D7: =D4+SUM(D5:D6) | E7: =E4+SUM(E5:E6) | F7: =F4+SUM(F5:F6) | G7: =G4+SUM(G5:G6) | H7: =H4+SUM(H5:H6) | I7: =I4+SUM(I5:I6) | ... O7: =O4+SUM(O5:O6)
A8: Interest Income (Expense) | B8: -98 | C8: -194 | D8: -294 | E8: -81 | F8: -186 | G8: -325 | H8: -97 | I8: -210 | J8: -339 | K8: -103 | L8: -224 | M8: -330 | N8: -89 | O8: -195
A9: Other Income (Expense) | B9: 110 | C9: 277 | D9: 424 | E9: 139 | F9: 294 | G9: 473 | H9: 132 | I9: 309 | J9: 570 | K9: -554 | L9: -330 | M9: -120 | N9: 268 | O9: 427
A10: Pre-Tax Income (Loss) | B10: =B7+SUM(B8:B9) | C10: =C7+SUM(C8:C9) | D10: =D7+SUM(D8:D9) | E10: =E7+SUM(E8:E9) | F10: =F7+SUM(F8:F9) | G10: =G7+SUM(G8:G9) | H10: =H7+SUM(H8:H9) | I10: =I7+SUM(I8:I9) | ... O10: =O7+SUM(O8:O9)
A11: Income Tax (Expense) Benefit | B11: -909 | C11: -1906 | D11: -2610 | E11: -1034 | F11: -1910 | G11: -2774 | H11: -1246 | I11: -2250 | J11: -3061 | K11: -1152 | L11: -2339 | M11: -3207 | N11: -1253 | O11: -2343
A12: Net Income (Loss) | B12: =B10+B11 | C12: =C10+C11 | D12: =D10+D11 | E12: =E10+E11 | F12: =F10+F11 | G12: =G10+G11 | H12: =H10+H11 | I12: =I10+I11 | ... O12: =O10+O11
A13: Net Income (Loss) Attributable to Noncontrolling Interest | B13: 14 | C13: 33 | D13: 45 | E13: 24 | F13: 50 | G13: 77 | H13: 35 | I13: 60 | J13: 88 | K13: 28 | L13: 56 | M13: 80 | N13: 31 | O13: 42
A14: Net Income (Loss) Less NCI | B14: =B12-B13 | C14: =C12-C13 | D14: =D12-D13 | E14: =E12-E13 | F14: =F12-F13 | G14: =G12-G13 | H14: =H12-H13 | I14: =I12-I13 | ... O14: =O12-O13
A15: Basic Earnings (Loss) per Share | B15: 1.66 | C15: 3.39 | D15: 4.76 | E15: 1.62 | F15: 3.25 | G15: 4.67 | H15: 1.89 | I15: 3.33 | J15: 4.89 | K15: 1.65 | L15: 3.59 | M15: 5.16 | N15: 2 | O15: 3.82
A16: Diluted Earnings (Loss) per Share | B16: 1.61 | C16: 3.27 | D16: 4.59 | E16: 1.57 | F16: 3.16 | G16: 4.53 | H16: 1.83 | I16: 3.23 | J16: 4.75 | K16: 1.61 | L16: 3.49 | M16: 5.03 | N16: 1.95 | O16: 3.73
A17: Weighted Average Shares Outstanding (Basic) | B17: 2558900000 | C17: 2551600000 | D17: 2544400000 | E17: 2503600000 | F17: 2492400000 | G17: 2486000000 | H17: 0 | I17: 0 | J17: 0 | K17: 0 | L17: 0 | M17: 0 | N17: 0 | O17: 0

Sheet YTD BS
B1: Q4 FY2022 | C1: Q1 FY2023 | D1: Q2 FY2023 | E1: Q3 FY2023 | F1: Q4 FY2023 | G1: Q1 FY2024 | H1: Q2 FY2024 | I1: Q3 FY2024 | J1: Q4 FY2024 | K1: Q1 FY2025 | L1: Q2 FY2025 | M1: Q3 FY2025 | N1: Q4 FY2025 | O1: Q1 FY2026 | P1: Q2 FY2026
A2: Cash & Cash Equivalents | B2: 7214 | C2: 6710 | D2: 6854 | E2: 7596 | F2: 8246 | G2: 9733 | H2: 7890 | I2: 6828 | J2: 9482 | K2: 12156 | L2: 10230 | M2: 9116 | N2: 9556 | O2: 11171 | P2: 10825
A3: Accounts Receivable | B3: 5143 | C3: 5720 | D3: 5767 | E3: 5471 | F3: 5471 | G3: 6215 | H3: 6334 | I3: 6124 | J3: 6118 | K3: 6314 | L3: 6234 | M3: 6139 | N3: 6185 | O3: 6487 | P3: 6279
A4: Inventories | B4: 6924 | C4: 7590 | D4: 7541 | E4: 7483 | F4: 7073 | G4: 7117 | H4: 7151 | I4: 7077 | J4: 7016 | K4: 7287 | L4: 7020 | M4: 7400 | N4: 7551 | O4: 7848 | P4: 7817
A5: Prepaid Expenses | B5: 2372 | C5: 2501 | D5: 1704 | E5: 1755 | F5: 1858 | G5: 1875 | H5: 1736 | I5: 2428 | J5: 2095 | K5: 1692 | L5: 2158 | M5: 1780 | N5: 2100 | O5: 1612 | P5: 1666
A6: Total Current Assets | B6: =SUM(B2:B5) | C6: =SUM(C2:C5) | D6: =SUM(D2:D5) | E6: =SUM(E2:E5) | F6: =SUM(F2:F5) | G6: =SUM(G2:G5) | H6: =SUM(H2:H5) | I6: =SUM(I2:I5) | ... P6: =SUM(P2:P5)
A7: Net PP&E | B7: 21195 | C7: 20593 | D7: 21167 | E7: 21564 | F7: 21909 | G7: 21636 | H7: 22132 | I7: 22027 | J7: 22152 | K7: 22506 | L7: 22074 | M7: 22728 | N7: 23897 | O7: 24119 | P7: 24487
A8: Goodwill | B8: 39700 | C8: 38761 | D8: 39951 | E8: 40718 | F8: 40659 | G8: 40239 | H8: 40916 | I8: 40567 | J8: 40303 | K8: 40970 | L8: 39898 | M8: 40476 | N8: 41650 | O8: 41643 | P8: 41665
A9: Intangible Assets | B9: 23679 | C9: 23465 | D9: 23594 | E9: 23832 | F9: 23783 | G9: 23637 | H9: 22302 | I9: 22193 | J9: 22047 | K9: 22053 | L9: 21833 | M9: 21836 | N9: 21910 | O9: 21818 | P9: 21737
A10: Other Non-Current Assets | B10: 10981 | C10: 10942 | D10: 11137 | E10: 11432 | F10: 11830 | G10: 12079 | H10: 12248 | I10: 12353 | J10: 13158 | K10: 13503 | L10: 13192 | M10: 13508 | N10: 12381 | O10: 12901 | P10: 12809
A11: Total Assets | B11: =B6+SUM(B7:B10) | C11: =C6+SUM(C7:C10) | D11: =D6+SUM(D7:D10) | E11: =E6+SUM(E7:E10) | F11: =F6+SUM(F7:F10) | G11: =G6+SUM(G7:G10) | H11: =H6+SUM(H7:H10) | I11: =I6+SUM(I7:I10) | ... P11: =P6+SUM(P7:P10)
A12: Accounts Payable | B12: 14882 | C12: 14845 | D12: 14153 | E12: 13790 | F12: 14598 | G12: 14435 | H12: 14234 | I12: 13691 | J12: 15364 | K12: 15350 | L12: 14495 | M12: 14512 | N12: 15227 | O12: 15609 | P12: 15173
A13: Accrued Expenses | B13: 9554 | C13: 10056 | D13: 10293 | E13: 10523 | F13: 10929 | G13: 10912 | H13: 11100 | I13: 10921 | J13: 11073 | K13: 10661 | L13: 9879 | M13: 9847 | N13: 11318 | O13: 10756 | P13: 10463
A14: Current Portion of Long-Term Debt | B14: 8645 | C14: 11717 | D14: 14300 | E14: 13717 | F14: 10229 | G14: 11811 | H14: 10616 | I14: 7729 | J14: 7191 | K14: 10409 | L14: 9424 | M14: 9889 | N14: 9513 | O14: 11631 | P14: 11062
A15: Total Current Liabilities | B15: =SUM(B12:B14) | C15: =SUM(C12:C14) | D15: =SUM(D12:D14) | E15: =SUM(E12:E14) | F15: =SUM(F12:F14) | G15: =SUM(G12:G14) | H15: =SUM(H12:H14) | I15: =SUM(I12:I14) | ... P15: =SUM(P12:P14)
A16: Long-Term Debt | B16: 22848 | C16: 21286 | D16: 20582 | E16: 22874 | F16: 24378 | G16: 24069 | H16: 23096 | I16: 24253 | J16: 25269 | K16: 25744 | L16: 25263 | M16: 24252 | N16: 24995 | O16: 24315 | P16: 25577
A17: Deferred Tax Liability | B17: 6809 | C17: 6986 | D17: 6462 | E17: 6422 | F17: 6478 | G17: 6814 | H17: 6219 | I17: 6284 | J17: 6516 | K17: 6420 | L17: 6725 | M17: 6481 | N17: 5774 | O17: 5893 | P17: 5974
A18: Other Non-Current Liabilities | B18: 7616 | C18: 7058 | D18: 7200 | E18: 7104 | F18: 7152 | G18: 6477 | H18: 6614 | I18: 6386 | J18: 6398 | K18: 5757 | L18: 5411 | M18: 5458 | N18: 6120 | O18: 5844 | P18: 5719
A19: Total Liabilities | B19: =B15+SUM(B16:B18) | C19: =C15+SUM(C16:C18) | D19: =D15+SUM(D16:D18) | E19: =E15+SUM(E16:E18) | F19: =F15+SUM(F16:F18) | G19: =G15+SUM(G16:G18) | H19: =H15+SUM(H16:H18) | I19: =I15+SUM(I16:I18) | ... P19: =P15+SUM(P16:P18)
A20: Convertible Preferred Stock | B20: 843 | C20: 834 | D20: 831 | E20: 822 | F20: 819 | G20: 812 | H20: 809 | I20: 801 | J20: 798 | K20: 791 | L20: 788 | M20: 781 | N20: 777 | O20: 770 | P20: 767
A21: Common Stock | B21: 4009 | C21: 4009 | D21: 4009 | E21: 4009 | F21: 4009 | G21: 4009 | H21: 4009 | I21: 4009 | J21: 4009 | K21: 4009 | L21: 4009 | M21: 4009 | N21: 4009 | O21: 4009 | P21: 4009
A22: Additional Paid-in Capital | B22: 65795 | C22: 65955 | D22: 66145 | E22: 66316 | F22: 66556 | G22: 66822 | H22: 66935 | I22: 67395 | J22: 67684 | K22: 68102 | L22: 68283 | M22: 68615 | N22: 68770 | O22: 68917 | P22: 69010
A23: ESOP Debt Retirement Reserve | B23: -916 | C23: -870 | D23: -870 | E23: -821 | F23: -821 | G23: -782 | H23: -782 | I23: -737 | J23: -737 | K23: -707 | L23: -707 | M23: -672 | N23: -672 | O23: -637 | P23: -637
A24: Accumulated Other Comprehensive Income (Loss) | B24: -12189 | C24: -12811 | D24: -12506 | E24: -12266 | F24: -12220 | G24: -12583 | H24: -12167 | I24: -12370 | J24: -11900 | K24: -10893 | L24: -11637 | M24: -11307 | N24: -12143 | O24: -12156 | P24: -12108
A25: Treasury Stock | B25: -123382 | C25: -127205 | D25: -129012 | E25: -130002 | F25: -129736 | G25: -131029 | H25: -131887 | I25: -132172 | J25: -133379 | K25: -134823 | L25: -137112 | M25: -138073 | N25: -138702 | O25: -139845 | P25: -141981
A26: Retained Earnings (Accumulated Deficit) | B26: 112429 | C26: 114163 | D26: 115858 | E26: 117082 | F26: 118170 | G26: 120443 | H26: 121617 | I26: 123132 | J26: 123811 | K26: 125361 | L26: 127544 | M26: 128919 | N26: 129973 | O26: 132212 | P26: 133981
A27: Noncontrolling Interest | B27: 265 | C27: 259 | D27: 270 | E27: 281 | F27: 288 | G27: 321 | H27: 294 | I27: 275 | J27: 272 | K27: 300 | L27: 275 | M27: 273 | N27: 272 | O27: 281 | P27: 276
A28: Total Stockholders' Equity | B28: =SUM(B20:B27) | C28: =SUM(C20:C27) | D28: =SUM(D20:D27) | E28: =SUM(E20:E27) | F28: =SUM(F20:F27) | G28: =SUM(G20:G27) | H28: =SUM(H20:H27) | I28: =SUM(I20:I27) | ... P28: =SUM(P20:P27)
A29: Total Liabilities, Mezzanine & Stockholders' Equity | B29: =B19+B28 | C29: =C19+C28 | D29: =D19+D28 | E29: =E19+E28 | F29: =F19+F28 | G29: =G19+G28 | H29: =H19+H28 | I29: =I19+I28 | ... P29: =P19+P28

Sheet YTD CF
B1: Q1 FY2022 | C1: Q2 FY2022 | D1: Q3 FY2022 | E1: Q1 FY2023 | F1: Q2 FY2023 | G1: Q3 FY2023 | H1: Q1 FY2024 | I1: Q2 FY2024 | J1: Q3 FY2024 | K1: Q1 FY2025 | L1: Q2 FY2025 | M1: Q3 FY2025 | N1: Q1 FY2026 | O1: Q2 FY2026
A2: Net Income (Loss) | B2: 4126 | C2: 8368 | D2: 11735 | E2: 3963 | F2: 7922 | G2: 11346 | H2: 4556 | I2: 8049 | J2: 11830 | K2: 3987 | L2: 8646 | M2: 12439 | N2: 4781 | O2: 9112
A3: Depreciation & Amortization | B3: 711 | C3: 1395 | D3: 2085 | E3: 663 | F3: 1316 | G3: 2008 | H3: 702 | I3: 1423 | J3: 2135 | K3: 728 | L3: 1434 | M3: 2124 | N3: 761 | O3: 1563
A4: Stock-Based Compensation | B4: 116 | C4: 268 | D4: 398 | E4: 105 | F4: 250 | G4: 406 | H4: 125 | I4: 275 | J4: 433 | K4: 105 | L4: 241 | M4: 364 | N4: 121 | O4: 262
A5: (Benefit) Provision for Deferred Income Taxes | B5: 57 | C5: -101 | D5: -259 | E5: -130 | F5: -398 | G5: -360 | H5: 102 | I5: -154 | J5: -206 | K5: 184 | L5: 221 | M5: 183 | N5: 53 | O5: 196
A6: Gain (Loss) on Disposal of PP&E | B6: -73 | C6: -82 | D6: -84 | E6: -1 | F6: -3 | G6: -4 | H6: -3 | I6: -3 | J6: -51 | K6: 794 | L6: 787 | M6: 782 | N6: -3 | O6: 1
A7: Impairment of Intangibles | B7: 0 | C7: 0 | D7: 0 | E7: 0 | F7: 0 | G7: 0 | H7: 0 | I7: 1341 | J7: 1341 | K7: 0 | L7: 0 | M7: 0 | N7: 0 | O7: 0
A8: Accounts Receivable | B8: -1012 | C8: -644 | D8: -916 | E8: -740 | F8: -654 | G8: -301 | H8: -830 | I8: -839 | J8: -692 | K8: -134 | L8: -262 | M8: -79 | N8: -305 | O8: -92
A9: Inventories | B9: -409 | C9: -840 | D9: -1252 | E9: -893 | F9: -655 | G9: -503 | H9: -142 | I9: -32 | J9: -47 | K9: -188 | L9: -170 | M9: -409 | N9: -303 | O9: -255
A10: Accounts Payable | B10: 1261 | C10: 1431 | D10: 1347 | E10: 1495 | F10: 177 | G10: -609 | H10: 857 | I10: 302 | J10: 56 | K10: -648 | L10: -1157 | M10: -1666 | N10: 648 | O10: 239
A11: Net Change in Other Working Capital | B11: -178 | C11: -84 | D11: -131 | E11: -454 | F11: -535 | G11: -839 | H11: -671 | I11: -704 | J11: -1196 | K11: -558 | L11: -748 | M11: -1125 | N11: 0 | O11: 0
A12: Other Operating Items | B12: 44 | C12: 53 | D12: 87 | E12: 62 | F12: 224 | G12: 363 | H12: 208 | I12: 346 | J12: 490 | K12: 32 | L12: 135 | M12: 218 | N12: -344 | O12: -645
A13: Cash Flow from Operations | B13: =SUM(B2:B12) | C13: =SUM(C2:C12) | D13: =SUM(D2:D12) | E13: =SUM(E2:E12) | F13: =SUM(F2:F12) | G13: =SUM(G2:G12) | H13: =SUM(H2:H12) | I13: =SUM(I2:I12) | ... O13: =SUM(O2:O12)
A14: Purchase of PP&E | B14: -1091 | C14: -1717 | D14: -2464 | E14: -890 | F14: -1598 | G14: -2328 | H14: -925 | I14: -1742 | J14: -2539 | K14: -993 | L14: -1918 | M14: -2777 | N14: -1200 | O14: -2367
A15: Proceeds from Sale of Assets | B15: 85 | C15: 97 | D15: 99 | E15: 5 | F15: 8 | G15: 9 | H15: 3 | I15: 8 | J15: 77 | K15: 45 | L15: 47 | M15: 64 | N15: 8 | O15: 16
A16: Acquisitions, Net of Cash Acquired | B16: 0 | C16: -349 | D16: -1381 | E16: -2 | F16: -76 | G16: -714 | H16: 0 | I16: 0 | J16: -21 | K16: -6 | L16: -6 | M16: -11 | N16: -5 | O16: -5
A17: Net Change in Short-Term Investments | B17: 0 | C17: 0 | D17: 0 | E17: 55 | F17: 0 | G17: 0 | H17: 0 | I17: 0 | J17: 0 | K17: 0 | L17: 0 | M17: 0 | N17: 0 | O17: 0
A18: Other Investing Activities | B18: 0 | C18: 3 | D18: 4 | E18: 0 | F18: 344 | G18: 331 | H18: -300 | I18: -489 | J18: -503 | K18: -154 | L18: -153 | M18: -33 | N18: -338 | O18: -408
A19: Cash Flow from Investing | B19: =SUM(B14:B18) | C19: =SUM(C14:C18) | D19: =SUM(D14:D18) | E19: =SUM(E14:E18) | F19: =SUM(F14:F18) | G19: =SUM(G14:G18) | H19: =SUM(H14:H18) | I19: =SUM(I14:I18) | ... O19: =SUM(O14:O18)
A20: Common Dividends | B20: -2182 | C20: -4353 | D20: -6508 | E20: -2255 | F20: -4486 | G20: -6710 | H20: -2290 | I20: -4578 | J20: -6863 | K20: -2445 | L20: -4886 | M20: -7319 | N20: -2549 | O20: -5093
A21: Proceeds from Short-Term Debt | B21: 1792 | C21: 6747 | D21: 10146 | E21: 2975 | F21: 10447 | G21: 13778 | H21: 2179 | I21: 2798 | J21: 2961 | K21: 4090 | L21: 5905 | M21: 5905 | N21: 1123 | O21: 4180
A22: Repayments of Short-Term Debt | B22: -1422 | C22: -1730 | D22: -8163 | E22: -265 | F22: -3260 | G22: -9134 | H22: -1906 | I22: -5862 | J22: -7523 | K22: -571 | L22: -571 | M22: -3781 | N22: -1800 | O22: -3270
A23: Net Change in Other Short-Term Debt | B23: 512 | C23: -1124 | D23: -849 | E23: 1727 | F23: -1759 | G23: -387 | H23: 2172 | I23: 3740 | J23: 2331 | K23: -444 | L23: -2705 | M23: -543 | N23: 2108 | O23: -471
A24: Proceeds from Issuance of Long-Term Debt | B24: 0 | C24: 2136 | D24: 4385 | E24: 0 | F24: 0 | G24: 2569 | H24: 0 | I24: 254 | J24: 1598 | K24: 0 | L24: 995 | M24: 995 | N24: 0 | O24: 2652
A25: Repayments of Long-Term Debt | B25: -26 | C25: -1673 | D25: -2776 | E25: -1877 | F25: -1877 | G25: -1877 | H25: -1004 | I25: -2335 | J25: -2335 | K25: -70 | L25: -1478 | M25: -1478 | N25: -3 | O25: -1005
A26: Share Repurchases | B26: -2750 | C26: -7504 | D26: -8753 | E26: -4000 | F26: -6002 | G26: -7353 | H26: -1500 | I26: -2503 | J26: -3490 | K26: -1939 | L26: -4449 | M26: -5800 | N26: -1250 | O26: -3528
A27: Stock Options & Other Financing Activities | B27: 648 | C27: 1215 | D27: 1800 | E27: 188 | F27: 437 | G27: 861 | H27: 312 | I27: 397 | J27: 965 | K27: 745 | L27: 985 | M27: 1601 | N27: 134 | O27: 208
A28: Cash Flow from Financing | B28: =SUM(B20:B27) | C28: =SUM(C20:C27) | D28: =SUM(D20:D27) | E28: =SUM(E20:E27) | F28: =SUM(F20:F27) | G28: =SUM(G20:G27) | H28: =SUM(H20:H27) | I28: =SUM(I20:I27) | ... O28: =SUM(O20:O27)
A29: FX Effect on Cash | B29: -127 | C29: -256 | D29: -312 | E29: -235 | F29: -182 | G29: -170 | H29: -156 | I29: -49 | J29: -168 | K29: 116 | L29: -144 | M29: -22 | N29: -20 | O29: -21
A30: Net Change in Cash | B30: =B13+B19+B28+B29 | C30: =C13+C19+C28+C29 | D30: =D13+D19+D28+D29 | E30: =E13+E19+E28+E29 | F30: =F13+F19+F28+F29 | G30: =G13+G19+G28+G29 | H30: =H13+H19+H28+H29 | I30: =I13+I19+I28+I29 | ... O30: =O13+O19+O28+O29

Sheet QTR P&L
B1: Q1 FY2022 | C1: Q2 FY2022 | D1: Q3 FY2022 | E1: Q4 FY2022 | F1: Q1 FY2023 | G1: Q2 FY2023 | H1: Q3 FY2023 | I1: Q4 FY2023 | J1: Q1 FY2024 | K1: Q2 FY2024 | L1: Q3 FY2024 | M1: Q4 FY2024 | N1: Q1 FY2025 | O1: Q2 FY2025 | P1: Q3 FY2025 | Q1: Q4 FY2025 | R1: Q1 FY2026 | S1: Q2 FY2026 | T1: Q3 FY2026E | U1: Q4 FY2026E | V1: Q1 FY2027E | W1: Q2 FY2027E | X1: Q3 FY2027E | Y1: Q4 FY2027E | Z1: Q1 FY2028E | AA1: Q2 FY2028E | AB1: Q3 FY2028E | AC1: Q4 FY2028E | AD1: Q1 FY2029E | AE1: Q2 FY2029E | AF1: Q3 FY2029E | AG1: Q4 FY2029E | AH1: Q1 FY2030E | AI1: Q2 FY2030E | AJ1: Q3 FY2030E | AK1: Q4 FY2030E
A2: Net Sales / Revenue | B2: ='YTD P&L'!B2 | C2: ='YTD P&L'!C2-'YTD P&L'!B2 | D2: ='YTD P&L'!D2-'YTD P&L'!C2 | E2: ='ANNL P&L'!C2-'YTD P&L'!D2 | F2: ='YTD P&L'!E2 | G2: ='YTD P&L'!F2-'YTD P&L'!E2 | H2: ='YTD P&L'!G2-'YTD P&L'!F2 | I2: ='ANNL P&L'!D2-'YTD P&L'!G2 | J2: ='YTD P&L'!H2 | K2: ='YTD P&L'!I2-'YTD P&L'!H2 | L2: ='YTD P&L'!J2-'YTD P&L'!I2 | M2: ='ANNL P&L'!E2-'YTD P&L'!J2 | N2: ='YTD P&L'!K2 | O2: ='YTD P&L'!L2-'YTD P&L'!K2 | P2: ='YTD P&L'!M2-'YTD P&L'!L2 | Q2: ='ANNL P&L'!F2-'YTD P&L'!M2 | R2: ='YTD P&L'!N2 | S2: ='YTD P&L'!O2-'YTD P&L'!N2 | T2: ='QTR P&L'!P2*(1+'IS DRIVERS'!T2) | U2: ='QTR P&L'!Q2*(1+'IS DRIVERS'!U2) | V2: ='QTR P&L'!R2*(1+'IS DRIVERS'!V2) | W2: ='QTR P&L'!S2*(1+'IS DRIVERS'!W2) | X2: ='QTR P&L'!T2*(1+'IS DRIVERS'!X2) | Y2: ='QTR P&L'!U2*(1+'IS DRIVERS'!Y2) | Z2: ='QTR P&L'!V2*(1+'IS DRIVERS'!Z2) | AA2: ='QTR P&L'!W2*(1+'IS DRIVERS'!AA2) | ... AK2: ='QTR P&L'!AG2*(1+'IS DRIVERS'!AK2)
A3: COGS | B3: ='YTD P&L'!B3 | C3: ='YTD P&L'!C3-'YTD P&L'!B3 | D3: ='YTD P&L'!D3-'YTD P&L'!C3 | E3: ='ANNL P&L'!C3-'YTD P&L'!D3 | F3: ='YTD P&L'!E3 | G3: ='YTD P&L'!F3-'YTD P&L'!E3 | H3: ='YTD P&L'!G3-'YTD P&L'!F3 | I3: ='ANNL P&L'!D3-'YTD P&L'!G3 | J3: ='YTD P&L'!H3 | K3: ='YTD P&L'!I3-'YTD P&L'!H3 | L3: ='YTD P&L'!J3-'YTD P&L'!I3 | M3: ='ANNL P&L'!E3-'YTD P&L'!J3 | N3: ='YTD P&L'!K3 | O3: ='YTD P&L'!L3-'YTD P&L'!K3 | P3: ='YTD P&L'!M3-'YTD P&L'!L3 | Q3: ='ANNL P&L'!F3-'YTD P&L'!M3 | R3: ='YTD P&L'!N3 | S3: ='YTD P&L'!O3-'YTD P&L'!N3 | T3: ='QTR P&L'!T2*'IS DRIVERS'!T3 | U3: ='QTR P&L'!U2*'IS DRIVERS'!U3 | V3: ='QTR P&L'!V2*'IS DRIVERS'!V3 | W3: ='QTR P&L'!W2*'IS DRIVERS'!W3 | X3: ='QTR P&L'!X2*'IS DRIVERS'!X3 | Y3: ='QTR P&L'!Y2*'IS DRIVERS'!Y3 | Z3: ='QTR P&L'!Z2*'IS DRIVERS'!Z3 | AA3: ='QTR P&L'!AA2*'IS DRIVERS'!AA3 | ... AK3: ='QTR P&L'!AK2*'IS DRIVERS'!AK3
A4: Gross Profit (Loss) | B4: ='YTD P&L'!B4 | C4: ='YTD P&L'!C4-'YTD P&L'!B4 | D4: ='YTD P&L'!D4-'YTD P&L'!C4 | E4: ='ANNL P&L'!C4-'YTD P&L'!D4 | F4: ='YTD P&L'!E4 | G4: ='YTD P&L'!F4-'YTD P&L'!E4 | H4: ='YTD P&L'!G4-'YTD P&L'!F4 | I4: ='ANNL P&L'!D4-'YTD P&L'!G4 | J4: ='YTD P&L'!H4 | K4: ='YTD P&L'!I4-'YTD P&L'!H4 | L4: ='YTD P&L'!J4-'YTD P&L'!I4 | M4: ='ANNL P&L'!E4-'YTD P&L'!J4 | N4: ='YTD P&L'!K4 | O4: ='YTD P&L'!L4-'YTD P&L'!K4 | P4: ='YTD P&L'!M4-'YTD P&L'!L4 | Q4: ='ANNL P&L'!F4-'YTD P&L'!M4 | R4: ='YTD P&L'!N4 | S4: ='YTD P&L'!O4-'YTD P&L'!N4 | T4: =T2+T3 | U4: =U2+U3 | V4: =V2+V3 | W4: =W2+W3 | X4: =X2+X3 | Y4: =Y2+Y3 | Z4: =Z2+Z3 | AA4: =AA2+AA3 | ... AK4: =AK2+AK3
A5: SG&A | B5: ='YTD P&L'!B5 | C5: ='YTD P&L'!C5-'YTD P&L'!B5 | D5: ='YTD P&L'!D5-'YTD P&L'!C5 | E5: ='ANNL P&L'!C5-'YTD P&L'!D5 | F5: ='YTD P&L'!E5 | G5: ='YTD P&L'!F5-'YTD P&L'!E5 | H5: ='YTD P&L'!G5-'YTD P&L'!F5 | I5: ='ANNL P&L'!D5-'YTD P&L'!G5 | J5: ='YTD P&L'!H5 | K5: ='YTD P&L'!I5-'YTD P&L'!H5 | L5: ='YTD P&L'!J5-'YTD P&L'!I5 | M5: ='ANNL P&L'!E5-'YTD P&L'!J5 | N5: ='YTD P&L'!K5 | O5: ='YTD P&L'!L5-'YTD P&L'!K5 | P5: ='YTD P&L'!M5-'YTD P&L'!L5 | Q5: ='ANNL P&L'!F5-'YTD P&L'!M5 | R5: ='YTD P&L'!N5 | S5: ='YTD P&L'!O5-'YTD P&L'!N5 | T5: ='QTR P&L'!T2*'IS DRIVERS'!T4 | U5: ='QTR P&L'!U2*'IS DRIVERS'!U4 | V5: ='QTR P&L'!V2*'IS DRIVERS'!V4 | W5: ='QTR P&L'!W2*'IS DRIVERS'!W4 | X5: ='QTR P&L'!X2*'IS DRIVERS'!X4 | Y5: ='QTR P&L'!Y2*'IS DRIVERS'!Y4 | Z5: ='QTR P&L'!Z2*'IS DRIVERS'!Z4 | AA5: ='QTR P&L'!AA2*'IS DRIVERS'!AA4 | ... AK5: ='QTR P&L'!AK2*'IS DRIVERS'!AK4
A6: Impairment of Intangibles | B6: ='YTD P&L'!B6 | C6: ='YTD P&L'!C6-'YTD P&L'!B6 | D6: ='YTD P&L'!D6-'YTD P&L'!C6 | E6: ='ANNL P&L'!C6-'YTD P&L'!D6 | F6: ='YTD P&L'!E6 | G6: ='YTD P&L'!F6-'YTD P&L'!E6 | H6: ='YTD P&L'!G6-'YTD P&L'!F6 | I6: ='ANNL P&L'!D6-'YTD P&L'!G6 | J6: ='YTD P&L'!H6 | K6: ='YTD P&L'!I6-'YTD P&L'!H6 | L6: ='YTD P&L'!J6-'YTD P&L'!I6 | M6: ='ANNL P&L'!E6-'YTD P&L'!J6 | N6: ='YTD P&L'!K6 | O6: ='YTD P&L'!L6-'YTD P&L'!K6 | P6: ='YTD P&L'!M6-'YTD P&L'!L6 | Q6: ='ANNL P&L'!F6-'YTD P&L'!M6 | R6: ='YTD P&L'!N6 | S6: ='YTD P&L'!O6-'YTD P&L'!N6 | T6: ='QTR P&L'!T2*'IS DRIVERS'!T5 | U6: ='QTR P&L'!U2*'IS DRIVERS'!U5 | V6: ='QTR P&L'!V2*'IS DRIVERS'!V5 | W6: ='QTR P&L'!W2*'IS DRIVERS'!W5 | X6: ='QTR P&L'!X2*'IS DRIVERS'!X5 | Y6: ='QTR P&L'!Y2*'IS DRIVERS'!Y5 | Z6: ='QTR P&L'!Z2*'IS DRIVERS'!Z5 | AA6: ='QTR P&L'!AA2*'IS DRIVERS'!AA5 | ... AK6: ='QTR P&L'!AK2*'IS DRIVERS'!AK5
A7: Income (Loss) from Operations | B7: ='YTD P&L'!B7 | C7: ='YTD P&L'!C7-'YTD P&L'!B7 | D7: ='YTD P&L'!D7-'YTD P&L'!C7 | E7: ='ANNL P&L'!C7-'YTD P&L'!D7 | F7: ='YTD P&L'!E7 | G7: ='YTD P&L'!F7-'YTD P&L'!E7 | H7: ='YTD P&L'!G7-'YTD P&L'!F7 | I7: ='ANNL P&L'!D7-'YTD P&L'!G7 | J7: ='YTD P&L'!H7 | K7: ='YTD P&L'!I7-'YTD P&L'!H7 | L7: ='YTD P&L'!J7-'YTD P&L'!I7 | M7: ='ANNL P&L'!E7-'YTD P&L'!J7 | N7: ='YTD P&L'!K7 | O7: ='YTD P&L'!L7-'YTD P&L'!K7 | P7: ='YTD P&L'!M7-'YTD P&L'!L7 | Q7: ='ANNL P&L'!F7-'YTD P&L'!M7 | R7: ='YTD P&L'!N7 | S7: ='YTD P&L'!O7-'YTD P&L'!N7 | T7: =T4+SUM(T5:T6) | U7: =U4+SUM(U5:U6) | V7: =V4+SUM(V5:V6) | W7: =W4+SUM(W5:W6) | X7: =X4+SUM(X5:X6) | Y7: =Y4+SUM(Y5:Y6) | Z7: =Z4+SUM(Z5:Z6) | AA7: =AA4+SUM(AA5:AA6) | ... AK7: =AK4+SUM(AK5:AK6)
A8: Interest Income (Expense) | B8: ='YTD P&L'!B8 | C8: ='YTD P&L'!C8-'YTD P&L'!B8 | D8: ='YTD P&L'!D8-'YTD P&L'!C8 | E8: ='ANNL P&L'!C8-'YTD P&L'!D8 | F8: ='YTD P&L'!E8 | G8: ='YTD P&L'!F8-'YTD P&L'!E8 | H8: ='YTD P&L'!G8-'YTD P&L'!F8 | I8: ='ANNL P&L'!D8-'YTD P&L'!G8 | J8: ='YTD P&L'!H8 | K8: ='YTD P&L'!I8-'YTD P&L'!H8 | L8: ='YTD P&L'!J8-'YTD P&L'!I8 | M8: ='ANNL P&L'!E8-'YTD P&L'!J8 | N8: ='YTD P&L'!K8 | O8: ='YTD P&L'!L8-'YTD P&L'!K8 | P8: ='YTD P&L'!M8-'YTD P&L'!L8 | Q8: ='ANNL P&L'!F8-'YTD P&L'!M8 | R8: ='YTD P&L'!N8 | S8: ='YTD P&L'!O8-'YTD P&L'!N8 | T8: ='IS DRIVERS'!T6 | U8: ='IS DRIVERS'!U6 | V8: ='IS DRIVERS'!V6 | W8: ='IS DRIVERS'!W6 | X8: ='IS DRIVERS'!X6 | Y8: ='IS DRIVERS'!Y6 | Z8: ='IS DRIVERS'!Z6 | AA8: ='IS DRIVERS'!AA6 | ... AK8: ='IS DRIVERS'!AK6
A9: Other Income (Expense) | B9: ='YTD P&L'!B9 | C9: ='YTD P&L'!C9-'YTD P&L'!B9 | D9: ='YTD P&L'!D9-'YTD P&L'!C9 | E9: ='ANNL P&L'!C9-'YTD P&L'!D9 | F9: ='YTD P&L'!E9 | G9: ='YTD P&L'!F9-'YTD P&L'!E9 | H9: ='YTD P&L'!G9-'YTD P&L'!F9 | I9: ='ANNL P&L'!D9-'YTD P&L'!G9 | J9: ='YTD P&L'!H9 | K9: ='YTD P&L'!I9-'YTD P&L'!H9 | L9: ='YTD P&L'!J9-'YTD P&L'!I9 | M9: ='ANNL P&L'!E9-'YTD P&L'!J9 | N9: ='YTD P&L'!K9 | O9: ='YTD P&L'!L9-'YTD P&L'!K9 | P9: ='YTD P&L'!M9-'YTD P&L'!L9 | Q9: ='ANNL P&L'!F9-'YTD P&L'!M9 | R9: ='YTD P&L'!N9 | S9: ='YTD P&L'!O9-'YTD P&L'!N9 | T9: ='IS DRIVERS'!T7 | U9: ='IS DRIVERS'!U7 | V9: ='IS DRIVERS'!V7 | W9: ='IS DRIVERS'!W7 | X9: ='IS DRIVERS'!X7 | Y9: ='IS DRIVERS'!Y7 | Z9: ='IS DRIVERS'!Z7 | AA9: ='IS DRIVERS'!AA7 | ... AK9: ='IS DRIVERS'!AK7
A10: Pre-Tax Income (Loss) | B10: ='YTD P&L'!B10 | C10: ='YTD P&L'!C10-'YTD P&L'!B10 | D10: ='YTD P&L'!D10-'YTD P&L'!C10 | E10: ='ANNL P&L'!C10-'YTD P&L'!D10 | F10: ='YTD P&L'!E10 | G10: ='YTD P&L'!F10-'YTD P&L'!E10 | H10: ='YTD P&L'!G10-'YTD P&L'!F10 | I10: ='ANNL P&L'!D10-'YTD P&L'!G10 | J10: ='YTD P&L'!H10 | K10: ='YTD P&L'!I10-'YTD P&L'!H10 | L10: ='YTD P&L'!J10-'YTD P&L'!I10 | M10: ='ANNL P&L'!E10-'YTD P&L'!J10 | N10: ='YTD P&L'!K10 | O10: ='YTD P&L'!L10-'YTD P&L'!K10 | P10: ='YTD P&L'!M10-'YTD P&L'!L10 | Q10: ='ANNL P&L'!F10-'YTD P&L'!M10 | R10: ='YTD P&L'!N10 | S10: ='YTD P&L'!O10-'YTD P&L'!N10 | T10: =T7+SUM(T8:T9) | U10: =U7+SUM(U8:U9) | V10: =V7+SUM(V8:V9) | W10: =W7+SUM(W8:W9) | X10: =X7+SUM(X8:X9) | Y10: =Y7+SUM(Y8:Y9) | Z10: =Z7+SUM(Z8:Z9) | AA10: =AA7+SUM(AA8:AA9) | ... AK10: =AK7+SUM(AK8:AK9)
A11: Income Tax (Expense) Benefit | B11: ='YTD P&L'!B11 | C11: ='YTD P&L'!C11-'YTD P&L'!B11 | D11: ='YTD P&L'!D11-'YTD P&L'!C11 | E11: ='ANNL P&L'!C11-'YTD P&L'!D11 | F11: ='YTD P&L'!E11 | G11: ='YTD P&L'!F11-'YTD P&L'!E11 | H11: ='YTD P&L'!G11-'YTD P&L'!F11 | I11: ='ANNL P&L'!D11-'YTD P&L'!G11 | J11: ='YTD P&L'!H11 | K11: ='YTD P&L'!I11-'YTD P&L'!H11 | L11: ='YTD P&L'!J11-'YTD P&L'!I11 | M11: ='ANNL P&L'!E11-'YTD P&L'!J11 | N11: ='YTD P&L'!K11 | O11: ='YTD P&L'!L11-'YTD P&L'!K11 | P11: ='YTD P&L'!M11-'YTD P&L'!L11 | Q11: ='ANNL P&L'!F11-'YTD P&L'!M11 | R11: ='YTD P&L'!N11 | S11: ='YTD P&L'!O11-'YTD P&L'!N11 | T11: ='QTR P&L'!T10*'IS DRIVERS'!T8 | U11: ='QTR P&L'!U10*'IS DRIVERS'!U8 | V11: ='QTR P&L'!V10*'IS DRIVERS'!V8 | W11: ='QTR P&L'!W10*'IS DRIVERS'!W8 | X11: ='QTR P&L'!X10*'IS DRIVERS'!X8 | Y11: ='QTR P&L'!Y10*'IS DRIVERS'!Y8 | Z11: ='QTR P&L'!Z10*'IS DRIVERS'!Z8 | AA11: ='QTR P&L'!AA10*'IS DRIVERS'!AA8 | ... AK11: ='QTR P&L'!AK10*'IS DRIVERS'!AK8
A12: Net Income (Loss) | B12: ='YTD P&L'!B12 | C12: ='YTD P&L'!C12-'YTD P&L'!B12 | D12: ='YTD P&L'!D12-'YTD P&L'!C12 | E12: ='ANNL P&L'!C12-'YTD P&L'!D12 | F12: ='YTD P&L'!E12 | G12: ='YTD P&L'!F12-'YTD P&L'!E12 | H12: ='YTD P&L'!G12-'YTD P&L'!F12 | I12: ='ANNL P&L'!D12-'YTD P&L'!G12 | J12: ='YTD P&L'!H12 | K12: ='YTD P&L'!I12-'YTD P&L'!H12 | L12: ='YTD P&L'!J12-'YTD P&L'!I12 | M12: ='ANNL P&L'!E12-'YTD P&L'!J12 | N12: ='YTD P&L'!K12 | O12: ='YTD P&L'!L12-'YTD P&L'!K12 | P12: ='YTD P&L'!M12-'YTD P&L'!L12 | Q12: ='ANNL P&L'!F12-'YTD P&L'!M12 | R12: ='YTD P&L'!N12 | S12: ='YTD P&L'!O12-'YTD P&L'!N12 | T12: =T10+T11 | U12: =U10+U11 | V12: =V10+V11 | W12: =W10+W11 | X12: =X10+X11 | Y12: =Y10+Y11 | Z12: =Z10+Z11 | AA12: =AA10+AA11 | ... AK12: =AK10+AK11
A13: Net Income (Loss) Attributable to Noncontrolling Interest | B13: ='YTD P&L'!B13 | C13: ='YTD P&L'!C13-'YTD P&L'!B13 | D13: ='YTD P&L'!D13-'YTD P&L'!C13 | E13: ='ANNL P&L'!C13-'YTD P&L'!D13 | F13: ='YTD P&L'!E13 | G13: ='YTD P&L'!F13-'YTD P&L'!E13 | H13: ='YTD P&L'!G13-'YTD P&L'!F13 | I13: ='ANNL P&L'!D13-'YTD P&L'!G13 | J13: ='YTD P&L'!H13 | K13: ='YTD P&L'!I13-'YTD P&L'!H13 | L13: ='YTD P&L'!J13-'YTD P&L'!I13 | M13: ='ANNL P&L'!E13-'YTD P&L'!J13 | N13: ='YTD P&L'!K13 | O13: ='YTD P&L'!L13-'YTD P&L'!K13 | P13: ='YTD P&L'!M13-'YTD P&L'!L13 | Q13: ='ANNL P&L'!F13-'YTD P&L'!M13 | R13: ='YTD P&L'!N13 | S13: ='YTD P&L'!O13-'YTD P&L'!N13 | T13: ='IS DRIVERS'!T9 | U13: ='IS DRIVERS'!U9 | V13: ='IS DRIVERS'!V9 | W13: ='IS DRIVERS'!W9 | X13: ='IS DRIVERS'!X9 | Y13: ='IS DRIVERS'!Y9 | Z13: ='IS DRIVERS'!Z9 | AA13: ='IS DRIVERS'!AA9 | ... AK13: ='IS DRIVERS'!AK9
A14: Net Income (Loss) Less NCI | B14: ='YTD P&L'!B14 | C14: ='YTD P&L'!C14-'YTD P&L'!B14 | D14: ='YTD P&L'!D14-'YTD P&L'!C14 | E14: ='ANNL P&L'!C14-'YTD P&L'!D14 | F14: ='YTD P&L'!E14 | G14: ='YTD P&L'!F14-'YTD P&L'!E14 | H14: ='YTD P&L'!G14-'YTD P&L'!F14 | I14: ='ANNL P&L'!D14-'YTD P&L'!G14 | J14: ='YTD P&L'!H14 | K14: ='YTD P&L'!I14-'YTD P&L'!H14 | L14: ='YTD P&L'!J14-'YTD P&L'!I14 | M14: ='ANNL P&L'!E14-'YTD P&L'!J14 | N14: ='YTD P&L'!K14 | O14: ='YTD P&L'!L14-'YTD P&L'!K14 | P14: ='YTD P&L'!M14-'YTD P&L'!L14 | Q14: ='ANNL P&L'!F14-'YTD P&L'!M14 | R14: ='YTD P&L'!N14 | S14: ='YTD P&L'!O14-'YTD P&L'!N14
A15: Basic Earnings (Loss) per Share
A16: Diluted Earnings (Loss) per Share
A17: Weighted Average Shares Outstanding (Basic)

Sheet QTR BS
B1: Q4 FY2022 | C1: Q1 FY2023 | D1: Q2 FY2023 | E1: Q3 FY2023 | F1: Q4 FY2023 | G1: Q1 FY2024 | H1: Q2 FY2024 | I1: Q3 FY2024 | J1: Q4 FY2024 | K1: Q1 FY2025 | L1: Q2 FY2025 | M1: Q3 FY2025 | N1: Q4 FY2025 | O1: Q1 FY2026 | P1: Q2 FY2026 | Q1: Q3 FY2026E | R1: Q4 FY2026E | S1: Q1 FY2027E | T1: Q2 FY2027E | U1: Q3 FY2027E | V1: Q4 FY2027E | W1: Q1 FY2028E | X1: Q2 FY2028E | Y1: Q3 FY2028E | Z1: Q4 FY2028E | AA1: Q1 FY2029E | AB1: Q2 FY2029E | AC1: Q3 FY2029E | AD1: Q4 FY2029E | AE1: Q1 FY2030E | AF1: Q2 FY2030E | AG1: Q3 FY2030E | AH1: Q4 FY2030E
A2: Cash & Cash Equivalents | B2: ='BALANCE SHEET'!B2 | C2: ='YTD BS'!C2 | D2: ='YTD BS'!D2 | E2: ='YTD BS'!E2 | F2: ='BALANCE SHEET'!C2 | G2: ='YTD BS'!G2 | H2: ='YTD BS'!H2 | I2: ='YTD BS'!I2 | J2: ='BALANCE SHEET'!D2 | K2: ='YTD BS'!K2 | L2: ='YTD BS'!L2 | M2: ='YTD BS'!M2 | N2: ='BALANCE SHEET'!E2 | O2: ='YTD BS'!O2 | P2: ='YTD BS'!P2 | Q2: ='BS DRIVERS'!Q2 | R2: ='BS DRIVERS'!R2 | S2: ='BS DRIVERS'!S2 | T2: ='BS DRIVERS'!T2 | U2: ='BS DRIVERS'!U2 | V2: ='BS DRIVERS'!V2 | W2: ='BS DRIVERS'!W2 | X2: ='BS DRIVERS'!X2 | ... AH2: ='BS DRIVERS'!AH2
A3: Accounts Receivable | B3: ='BALANCE SHEET'!B3 | C3: ='YTD BS'!C3 | D3: ='YTD BS'!D3 | E3: ='YTD BS'!E3 | F3: ='BALANCE SHEET'!C3 | G3: ='YTD BS'!G3 | H3: ='YTD BS'!H3 | I3: ='YTD BS'!I3 | J3: ='BALANCE SHEET'!D3 | K3: ='YTD BS'!K3 | L3: ='YTD BS'!L3 | M3: ='YTD BS'!M3 | N3: ='BALANCE SHEET'!E3 | O3: ='YTD BS'!O3 | P3: ='YTD BS'!P3 | Q3: ='QTR P&L'!T2*'BS DRIVERS'!Q3/ASSUMPTIONS!$B$2 | R3: ='QTR P&L'!U2*'BS DRIVERS'!R3/ASSUMPTIONS!$B$2 | S3: ='QTR P&L'!V2*'BS DRIVERS'!S3/ASSUMPTIONS!$B$2 | T3: ='QTR P&L'!W2*'BS DRIVERS'!T3/ASSUMPTIONS!$B$2 | U3: ='QTR P&L'!X2*'BS DRIVERS'!U3/ASSUMPTIONS!$B$2 | V3: ='QTR P&L'!Y2*'BS DRIVERS'!V3/ASSUMPTIONS!$B$2 | W3: ='QTR P&L'!Z2*'BS DRIVERS'!W3/ASSUMPTIONS!$B$2 | X3: ='QTR P&L'!AA2*'BS DRIVERS'!X3/ASSUMPTIONS!$B$2 | ... AH3: ='QTR P&L'!AK2*'BS DRIVERS'!AH3/ASSUMPTIONS!$B$2
A4: Inventories | B4: ='BALANCE SHEET'!B4 | C4: ='YTD BS'!C4 | D4: ='YTD BS'!D4 | E4: ='YTD BS'!E4 | F4: ='BALANCE SHEET'!C4 | G4: ='YTD BS'!G4 | H4: ='YTD BS'!H4 | I4: ='YTD BS'!I4 | J4: ='BALANCE SHEET'!D4 | K4: ='YTD BS'!K4 | L4: ='YTD BS'!L4 | M4: ='YTD BS'!M4 | N4: ='BALANCE SHEET'!E4 | O4: ='YTD BS'!O4 | P4: ='YTD BS'!P4 | Q4: ='QTR P&L'!T3*'BS DRIVERS'!Q4/ASSUMPTIONS!$B$2 | R4: ='QTR P&L'!U3*'BS DRIVERS'!R4/ASSUMPTIONS!$B$2 | S4: ='QTR P&L'!V3*'BS DRIVERS'!S4/ASSUMPTIONS!$B$2 | T4: ='QTR P&L'!W3*'BS DRIVERS'!T4/ASSUMPTIONS!$B$2 | U4: ='QTR P&L'!X3*'BS DRIVERS'!U4/ASSUMPTIONS!$B$2 | V4: ='QTR P&L'!Y3*'BS DRIVERS'!V4/ASSUMPTIONS!$B$2 | W4: ='QTR P&L'!Z3*'BS DRIVERS'!W4/ASSUMPTIONS!$B$2 | X4: ='QTR P&L'!AA3*'BS DRIVERS'!X4/ASSUMPTIONS!$B$2 | ... AH4: ='QTR P&L'!AK3*'BS DRIVERS'!AH4/ASSUMPTIONS!$B$2
A5: Prepaid Expenses | B5: ='BALANCE SHEET'!B5 | C5: ='YTD BS'!C5 | D5: ='YTD BS'!D5 | E5: ='YTD BS'!E5 | F5: ='BALANCE SHEET'!C5 | G5: ='YTD BS'!G5 | H5: ='YTD BS'!H5 | I5: ='YTD BS'!I5 | J5: ='BALANCE SHEET'!D5 | K5: ='YTD BS'!K5 | L5: ='YTD BS'!L5 | M5: ='YTD BS'!M5 | N5: ='BALANCE SHEET'!E5 | O5: ='YTD BS'!O5 | P5: ='YTD BS'!P5 | Q5: ='QTR P&L'!T2*'BS DRIVERS'!Q5 | R5: ='QTR P&L'!U2*'BS DRIVERS'!R5 | S5: ='QTR P&L'!V2*'BS DRIVERS'!S5 | T5: ='QTR P&L'!W2*'BS DRIVERS'!T5 | U5: ='QTR P&L'!X2*'BS DRIVERS'!U5 | V5: ='QTR P&L'!Y2*'BS DRIVERS'!V5 | W5: ='QTR P&L'!Z2*'BS DRIVERS'!W5 | X5: ='QTR P&L'!AA2*'BS DRIVERS'!X5 | ... AH5: ='QTR P&L'!AK2*'BS DRIVERS'!AH5
A6: Total Current Assets | B6: ='BALANCE SHEET'!B6 | C6: ='YTD BS'!C6 | D6: ='YTD BS'!D6 | E6: ='YTD BS'!E6 | F6: ='BALANCE SHEET'!C6 | G6: ='YTD BS'!G6 | H6: ='YTD BS'!H6 | I6: ='YTD BS'!I6 | J6: ='BALANCE SHEET'!D6 | K6: ='YTD BS'!K6 | L6: ='YTD BS'!L6 | M6: ='YTD BS'!M6 | N6: ='BALANCE SHEET'!E6 | O6: ='YTD BS'!O6 | P6: ='YTD BS'!P6 | Q6: =SUM(Q2:Q5) | R6: =SUM(R2:R5) | S6: =SUM(S2:S5) | T6: =SUM(T2:T5) | U6: =SUM(U2:U5) | V6: =SUM(V2:V5) | W6: =SUM(W2:W5) | X6: =SUM(X2:X5) | ... AH6: =SUM(AH2:AH5)
A7: Net PP&E | B7: ='BALANCE SHEET'!B7 | C7: ='YTD BS'!C7 | D7: ='YTD BS'!D7 | E7: ='YTD BS'!E7 | F7: ='BALANCE SHEET'!C7 | G7: ='YTD BS'!G7 | H7: ='YTD BS'!H7 | I7: ='YTD BS'!I7 | J7: ='BALANCE SHEET'!D7 | K7: ='YTD BS'!K7 | L7: ='YTD BS'!L7 | M7: ='YTD BS'!M7 | N7: ='BALANCE SHEET'!E7 | O7: ='YTD BS'!O7 | P7: ='YTD BS'!P7 | Q7: ='BS DRIVERS'!Q6 | R7: ='BS DRIVERS'!R6 | S7: ='BS DRIVERS'!S6 | T7: ='BS DRIVERS'!T6 | U7: ='BS DRIVERS'!U6 | V7: ='BS DRIVERS'!V6 | W7: ='BS DRIVERS'!W6 | X7: ='BS DRIVERS'!X6 | ... AH7: ='BS DRIVERS'!AH6
A8: Goodwill | B8: ='BALANCE SHEET'!B8 | C8: ='YTD BS'!C8 | D8: ='YTD BS'!D8 | E8: ='YTD BS'!E8 | F8: ='BALANCE SHEET'!C8 | G8: ='YTD BS'!G8 | H8: ='YTD BS'!H8 | I8: ='YTD BS'!I8 | J8: ='BALANCE SHEET'!D8 | K8: ='YTD BS'!K8 | L8: ='YTD BS'!L8 | M8: ='YTD BS'!M8 | N8: ='BALANCE SHEET'!E8 | O8: ='YTD BS'!O8 | P8: ='YTD BS'!P8 | Q8: ='BS DRIVERS'!Q7 | R8: ='BS DRIVERS'!R7 | S8: ='BS DRIVERS'!S7 | T8: ='BS DRIVERS'!T7 | U8: ='BS DRIVERS'!U7 | V8: ='BS DRIVERS'!V7 | W8: ='BS DRIVERS'!W7 | X8: ='BS DRIVERS'!X7 | ... AH8: ='BS DRIVERS'!AH7
A9: Intangible Assets | B9: ='BALANCE SHEET'!B9 | C9: ='YTD BS'!C9 | D9: ='YTD BS'!D9 | E9: ='YTD BS'!E9 | F9: ='BALANCE SHEET'!C9 | G9: ='YTD BS'!G9 | H9: ='YTD BS'!H9 | I9: ='YTD BS'!I9 | J9: ='BALANCE SHEET'!D9 | K9: ='YTD BS'!K9 | L9: ='YTD BS'!L9 | M9: ='YTD BS'!M9 | N9: ='BALANCE SHEET'!E9 | O9: ='YTD BS'!O9 | P9: ='YTD BS'!P9 | Q9: ='BS DRIVERS'!Q8 | R9: ='BS DRIVERS'!R8 | S9: ='BS DRIVERS'!S8 | T9: ='BS DRIVERS'!T8 | U9: ='BS DRIVERS'!U8 | V9: ='BS DRIVERS'!V8 | W9: ='BS DRIVERS'!W8 | X9: ='BS DRIVERS'!X8 | ... AH9: ='BS DRIVERS'!AH8
A10: Other Non-Current Assets | B10: ='BALANCE SHEET'!B10 | C10: ='YTD BS'!C10 | D10: ='YTD BS'!D10 | E10: ='YTD BS'!E10 | F10: ='BALANCE SHEET'!C10 | G10: ='YTD BS'!G10 | H10: ='YTD BS'!H10 | I10: ='YTD BS'!I10 | J10: ='BALANCE SHEET'!D10 | K10: ='YTD BS'!K10 | L10: ='YTD BS'!L10 | M10: ='YTD BS'!M10 | N10: ='BALANCE SHEET'!E10 | O10: ='YTD BS'!O10 | P10: ='YTD BS'!P10 | Q10: ='QTR P&L'!T2*'BS DRIVERS'!Q9 | R10: ='QTR P&L'!U2*'BS DRIVERS'!R9 | S10: ='QTR P&L'!V2*'BS DRIVERS'!S9 | T10: ='QTR P&L'!W2*'BS DRIVERS'!T9 | U10: ='QTR P&L'!X2*'BS DRIVERS'!U9 | V10: ='QTR P&L'!Y2*'BS DRIVERS'!V9 | W10: ='QTR P&L'!Z2*'BS DRIVERS'!W9 | X10: ='QTR P&L'!AA2*'BS DRIVERS'!X9 | ... AH10: ='QTR P&L'!AK2*'BS DRIVERS'!AH9
A11: Total Assets | B11: ='BALANCE SHEET'!B11 | C11: ='YTD BS'!C11 | D11: ='YTD BS'!D11 | E11: ='YTD BS'!E11 | F11: ='BALANCE SHEET'!C11 | G11: ='YTD BS'!G11 | H11: ='YTD BS'!H11 | I11: ='YTD BS'!I11 | J11: ='BALANCE SHEET'!D11 | K11: ='YTD BS'!K11 | L11: ='YTD BS'!L11 | M11: ='YTD BS'!M11 | N11: ='BALANCE SHEET'!E11 | O11: ='YTD BS'!O11 | P11: ='YTD BS'!P11 | Q11: =Q6+SUM(Q7:Q10) | R11: =R6+SUM(R7:R10) | S11: =S6+SUM(S7:S10) | T11: =T6+SUM(T7:T10) | U11: =U6+SUM(U7:U10) | V11: =V6+SUM(V7:V10) | W11: =W6+SUM(W7:W10) | X11: =X6+SUM(X7:X10) | ... AH11: =AH6+SUM(AH7:AH10)
A12: Accounts Payable | B12: ='BALANCE SHEET'!B12 | C12: ='YTD BS'!C12 | D12: ='YTD BS'!D12 | E12: ='YTD BS'!E12 | F12: ='BALANCE SHEET'!C12 | G12: ='YTD BS'!G12 | H12: ='YTD BS'!H12 | I12: ='YTD BS'!I12 | J12: ='BALANCE SHEET'!D12 | K12: ='YTD BS'!K12 | L12: ='YTD BS'!L12 | M12: ='YTD BS'!M12 | N12: ='BALANCE SHEET'!E12 | O12: ='YTD BS'!O12 | P12: ='YTD BS'!P12 | Q12: ='QTR P&L'!T3*'BS DRIVERS'!Q10/ASSUMPTIONS!$B$2 | R12: ='QTR P&L'!U3*'BS DRIVERS'!R10/ASSUMPTIONS!$B$2 | S12: ='QTR P&L'!V3*'BS DRIVERS'!S10/ASSUMPTIONS!$B$2 | T12: ='QTR P&L'!W3*'BS DRIVERS'!T10/ASSUMPTIONS!$B$2 | U12: ='QTR P&L'!X3*'BS DRIVERS'!U10/ASSUMPTIONS!$B$2 | V12: ='QTR P&L'!Y3*'BS DRIVERS'!V10/ASSUMPTIONS!$B$2 | W12: ='QTR P&L'!Z3*'BS DRIVERS'!W10/ASSUMPTIONS!$B$2 | X12: ='QTR P&L'!AA3*'BS DRIVERS'!X10/ASSUMPTIONS!$B$2 | ... AH12: ='QTR P&L'!AK3*'BS DRIVERS'!AH10/ASSUMPTIONS!$B$2
A13: Accrued Expenses | B13: ='BALANCE SHEET'!B13 | C13: ='YTD BS'!C13 | D13: ='YTD BS'!D13 | E13: ='YTD BS'!E13 | F13: ='BALANCE SHEET'!C13 | G13: ='YTD BS'!G13 | H13: ='YTD BS'!H13 | I13: ='YTD BS'!I13 | J13: ='BALANCE SHEET'!D13 | K13: ='YTD BS'!K13 | L13: ='YTD BS'!L13 | M13: ='YTD BS'!M13 | N13: ='BALANCE SHEET'!E13 | O13: ='YTD BS'!O13 | P13: ='YTD BS'!P13 | Q13: ='QTR P&L'!T2*'BS DRIVERS'!Q11 | R13: ='QTR P&L'!U2*'BS DRIVERS'!R11 | S13: ='QTR P&L'!V2*'BS DRIVERS'!S11 | T13: ='QTR P&L'!W2*'BS DRIVERS'!T11 | U13: ='QTR P&L'!X2*'BS DRIVERS'!U11 | V13: ='QTR P&L'!Y2*'BS DRIVERS'!V11 | W13: ='QTR P&L'!Z2*'BS DRIVERS'!W11 | X13: ='QTR P&L'!AA2*'BS DRIVERS'!X11 | ... AH13: ='QTR P&L'!AK2*'BS DRIVERS'!AH11
A14: Current Portion of Long-Term Debt | B14: ='BALANCE SHEET'!B14 | C14: ='YTD BS'!C14 | D14: ='YTD BS'!D14 | E14: ='YTD BS'!E14 | F14: ='BALANCE SHEET'!C14 | G14: ='YTD BS'!G14 | H14: ='YTD BS'!H14 | I14: ='YTD BS'!I14 | J14: ='BALANCE SHEET'!D14 | K14: ='YTD BS'!K14 | L14: ='YTD BS'!L14 | M14: ='YTD BS'!M14 | N14: ='BALANCE SHEET'!E14 | O14: ='YTD BS'!O14 | P14: ='YTD BS'!P14 | Q14: ='BS DRIVERS'!Q12 | R14: ='BS DRIVERS'!R12 | S14: ='BS DRIVERS'!S12 | T14: ='BS DRIVERS'!T12 | U14: ='BS DRIVERS'!U12 | V14: ='BS DRIVERS'!V12 | W14: ='BS DRIVERS'!W12 | X14: ='BS DRIVERS'!X12 | ... AH14: ='BS DRIVERS'!AH12
A15: Total Current Liabilities | B15: ='BALANCE SHEET'!B15 | C15: ='YTD BS'!C15 | D15: ='YTD BS'!D15 | E15: ='YTD BS'!E15 | F15: ='BALANCE SHEET'!C15 | G15: ='YTD BS'!G15 | H15: ='YTD BS'!H15 | I15: ='YTD BS'!I15 | J15: ='BALANCE SHEET'!D15 | K15: ='YTD BS'!K15 | L15: ='YTD BS'!L15 | M15: ='YTD BS'!M15 | N15: ='BALANCE SHEET'!E15 | O15: ='YTD BS'!O15 | P15: ='YTD BS'!P15 | Q15: =SUM(Q12:Q14) | R15: =SUM(R12:R14) | S15: =SUM(S12:S14) | T15: =SUM(T12:T14) | U15: =SUM(U12:U14) | V15: =SUM(V12:V14) | W15: =SUM(W12:W14) | X15: =SUM(X12:X14) | ... AH15: =SUM(AH12:AH14)
A16: Long-Term Debt | B16: ='BALANCE SHEET'!B16 | C16: ='YTD BS'!C16 | D16: ='YTD BS'!D16 | E16: ='YTD BS'!E16 | F16: ='BALANCE SHEET'!C16 | G16: ='YTD BS'!G16 | H16: ='YTD BS'!H16 | I16: ='YTD BS'!I16 | J16: ='BALANCE SHEET'!D16 | K16: ='YTD BS'!K16 | L16: ='YTD BS'!L16 | M16: ='YTD BS'!M16 | N16: ='BALANCE SHEET'!E16 | O16: ='YTD BS'!O16 | P16: ='YTD BS'!P16 | Q16: ='BS DRIVERS'!Q13 | R16: ='BS DRIVERS'!R13 | S16: ='BS DRIVERS'!S13 | T16: ='BS DRIVERS'!T13 | U16: ='BS DRIVERS'!U13 | V16: ='BS DRIVERS'!V13 | W16: ='BS DRIVERS'!W13 | X16: ='BS DRIVERS'!X13 | ... AH16: ='BS DRIVERS'!AH13
A17: Deferred Tax Liability | B17: ='BALANCE SHEET'!B17 | C17: ='YTD BS'!C17 | D17: ='YTD BS'!D17 | E17: ='YTD BS'!E17 | F17: ='BALANCE SHEET'!C17 | G17: ='YTD BS'!G17 | H17: ='YTD BS'!H17 | I17: ='YTD BS'!I17 | J17: ='BALANCE SHEET'!D17 | K17: ='YTD BS'!K17 | L17: ='YTD BS'!L17 | M17: ='YTD BS'!M17 | N17: ='BALANCE SHEET'!E17 | O17: ='YTD BS'!O17 | P17: ='YTD BS'!P17 | Q17: ='BS DRIVERS'!Q14 | R17: ='BS DRIVERS'!R14 | S17: ='BS DRIVERS'!S14 | T17: ='BS DRIVERS'!T14 | U17: ='BS DRIVERS'!U14 | V17: ='BS DRIVERS'!V14 | W17: ='BS DRIVERS'!W14 | X17: ='BS DRIVERS'!X14 | ... AH17: ='BS DRIVERS'!AH14
A18: Other Non-Current Liabilities | B18: ='BALANCE SHEET'!B18 | C18: ='YTD BS'!C18 | D18: ='YTD BS'!D18 | E18: ='YTD BS'!E18 | F18: ='BALANCE SHEET'!C18 | G18: ='YTD BS'!G18 | H18: ='YTD BS'!H18 | I18: ='YTD BS'!I18 | J18: ='BALANCE SHEET'!D18 | K18: ='YTD BS'!K18 | L18: ='YTD BS'!L18 | M18: ='YTD BS'!M18 | N18: ='BALANCE SHEET'!E18 | O18: ='YTD BS'!O18 | P18: ='YTD BS'!P18 | Q18: ='QTR P&L'!T2*'BS DRIVERS'!Q15 | R18: ='QTR P&L'!U2*'BS DRIVERS'!R15 | S18: ='QTR P&L'!V2*'BS DRIVERS'!S15 | T18: ='QTR P&L'!W2*'BS DRIVERS'!T15 | U18: ='QTR P&L'!X2*'BS DRIVERS'!U15 | V18: ='QTR P&L'!Y2*'BS DRIVERS'!V15 | W18: ='QTR P&L'!Z2*'BS DRIVERS'!W15 | X18: ='QTR P&L'!AA2*'BS DRIVERS'!X15 | ... AH18: ='QTR P&L'!AK2*'BS DRIVERS'!AH15
A19: Total Liabilities | B19: ='BALANCE SHEET'!B19 | C19: ='YTD BS'!C19 | D19: ='YTD BS'!D19 | E19: ='YTD BS'!E19 | F19: ='BALANCE SHEET'!C19 | G19: ='YTD BS'!G19 | H19: ='YTD BS'!H19 | I19: ='YTD BS'!I19 | J19: ='BALANCE SHEET'!D19 | K19: ='YTD BS'!K19 | L19: ='YTD BS'!L19 | M19: ='YTD BS'!M19 | N19: ='BALANCE SHEET'!E19 | O19: ='YTD BS'!O19 | P19: ='YTD BS'!P19 | Q19: =Q15+SUM(Q16:Q18) | R19: =R15+SUM(R16:R18) | S19: =S15+SUM(S16:S18) | T19: =T15+SUM(T16:T18) | U19: =U15+SUM(U16:U18) | V19: =V15+SUM(V16:V18) | W19: =W15+SUM(W16:W18) | X19: =X15+SUM(X16:X18) | ... AH19: =AH15+SUM(AH16:AH18)
A20: Convertible Preferred Stock | B20: ='BALANCE SHEET'!B20 | C20: ='YTD BS'!C20 | D20: ='YTD BS'!D20 | E20: ='YTD BS'!E20 | F20: ='BALANCE SHEET'!C20 | G20: ='YTD BS'!G20 | H20: ='YTD BS'!H20 | I20: ='YTD BS'!I20 | J20: ='BALANCE SHEET'!D20 | K20: ='YTD BS'!K20 | L20: ='YTD BS'!L20 | M20: ='YTD BS'!M20 | N20: ='BALANCE SHEET'!E20 | O20: ='YTD BS'!O20 | P20: ='YTD BS'!P20 | Q20: ='BS DRIVERS'!Q16 | R20: ='BS DRIVERS'!R16 | S20: ='BS DRIVERS'!S16 | T20: ='BS DRIVERS'!T16 | U20: ='BS DRIVERS'!U16 | V20: ='BS DRIVERS'!V16 | W20: ='BS DRIVERS'!W16 | X20: ='BS DRIVERS'!X16 | ... AH20: ='BS DRIVERS'!AH16
A21: Common Stock | B21: ='BALANCE SHEET'!B21 | C21: ='YTD BS'!C21 | D21: ='YTD BS'!D21 | E21: ='YTD BS'!E21 | F21: ='BALANCE SHEET'!C21 | G21: ='YTD BS'!G21 | H21: ='YTD BS'!H21 | I21: ='YTD BS'!I21 | J21: ='BALANCE SHEET'!D21 | K21: ='YTD BS'!K21 | L21: ='YTD BS'!L21 | M21: ='YTD BS'!M21 | N21: ='BALANCE SHEET'!E21 | O21: ='YTD BS'!O21 | P21: ='YTD BS'!P21 | Q21: ='BS DRIVERS'!Q17 | R21: ='BS DRIVERS'!R17 | S21: ='BS DRIVERS'!S17 | T21: ='BS DRIVERS'!T17 | U21: ='BS DRIVERS'!U17 | V21: ='BS DRIVERS'!V17 | W21: ='BS DRIVERS'!W17 | X21: ='BS DRIVERS'!X17 | ... AH21: ='BS DRIVERS'!AH17
A22: Additional Paid-in Capital | B22: ='BALANCE SHEET'!B22 | C22: ='YTD BS'!C22 | D22: ='YTD BS'!D22 | E22: ='YTD BS'!E22 | F22: ='BALANCE SHEET'!C22 | G22: ='YTD BS'!G22 | H22: ='YTD BS'!H22 | I22: ='YTD BS'!I22 | J22: ='BALANCE SHEET'!D22 | K22: ='YTD BS'!K22 | L22: ='YTD BS'!L22 | M22: ='YTD BS'!M22 | N22: ='BALANCE SHEET'!E22 | O22: ='YTD BS'!O22 | P22: ='YTD BS'!P22 | Q22: ='BS DRIVERS'!Q18 | R22: ='BS DRIVERS'!R18 | S22: ='BS DRIVERS'!S18 | T22: ='BS DRIVERS'!T18 | U22: ='BS DRIVERS'!U18 | V22: ='BS DRIVERS'!V18 | W22: ='BS DRIVERS'!W18 | X22: ='BS DRIVERS'!X18 | ... AH22: ='BS DRIVERS'!AH18
A23: ESOP Debt Retirement Reserve | B23: ='BALANCE SHEET'!B23 | C23: ='YTD BS'!C23 | D23: ='YTD BS'!D23 | E23: ='YTD BS'!E23 | F23: ='BALANCE SHEET'!C23 | G23: ='YTD BS'!G23 | H23: ='YTD BS'!H23 | I23: ='YTD BS'!I23 | J23: ='BALANCE SHEET'!D23 | K23: ='YTD BS'!K23 | L23: ='YTD BS'!L23 | M23: ='YTD BS'!M23 | N23: ='BALANCE SHEET'!E23 | O23: ='YTD BS'!O23 | P23: ='YTD BS'!P23 | Q23: ='BS DRIVERS'!Q19 | R23: ='BS DRIVERS'!R19 | S23: ='BS DRIVERS'!S19 | T23: ='BS DRIVERS'!T19 | U23: ='BS DRIVERS'!U19 | V23: ='BS DRIVERS'!V19 | W23: ='BS DRIVERS'!W19 | X23: ='BS DRIVERS'!X19 | ... AH23: ='BS DRIVERS'!AH19
A24: Accumulated Other Comprehensive Income (Loss) | B24: ='BALANCE SHEET'!B24 | C24: ='YTD BS'!C24 | D24: ='YTD BS'!D24 | E24: ='YTD BS'!E24 | F24: ='BALANCE SHEET'!C24 | G24: ='YTD BS'!G24 | H24: ='YTD BS'!H24 | I24: ='YTD BS'!I24 | J24: ='BALANCE SHEET'!D24 | K24: ='YTD BS'!K24 | L24: ='YTD BS'!L24 | M24: ='YTD BS'!M24 | N24: ='BALANCE SHEET'!E24 | O24: ='YTD BS'!O24 | P24: ='YTD BS'!P24 | Q24: ='BS DRIVERS'!Q20 | R24: ='BS DRIVERS'!R20 | S24: ='BS DRIVERS'!S20 | T24: ='BS DRIVERS'!T20 | U24: ='BS DRIVERS'!U20 | V24: ='BS DRIVERS'!V20 | W24: ='BS DRIVERS'!W20 | X24: ='BS DRIVERS'!X20 | ... AH24: ='BS DRIVERS'!AH20
A25: Treasury Stock | B25: ='BALANCE SHEET'!B25 | C25: ='YTD BS'!C25 | D25: ='YTD BS'!D25 | E25: ='YTD BS'!E25 | F25: ='BALANCE SHEET'!C25 | G25: ='YTD BS'!G25 | H25: ='YTD BS'!H25 | I25: ='YTD BS'!I25 | J25: ='BALANCE SHEET'!D25 | K25: ='YTD BS'!K25 | L25: ='YTD BS'!L25 | M25: ='YTD BS'!M25 | N25: ='BALANCE SHEET'!E25 | O25: ='YTD BS'!O25 | P25: ='YTD BS'!P25 | Q25: ='BS DRIVERS'!Q21 | R25: ='BS DRIVERS'!R21 | S25: ='BS DRIVERS'!S21 | T25: ='BS DRIVERS'!T21 | U25: ='BS DRIVERS'!U21 | V25: ='BS DRIVERS'!V21 | W25: ='BS DRIVERS'!W21 | X25: ='BS DRIVERS'!X21 | ... AH25: ='BS DRIVERS'!AH21
A26: Retained Earnings (Accumulated Deficit) | B26: ='BALANCE SHEET'!B26 | C26: ='YTD BS'!C26 | D26: ='YTD BS'!D26 | E26: ='YTD BS'!E26 | F26: ='BALANCE SHEET'!C26 | G26: ='YTD BS'!G26 | H26: ='YTD BS'!H26 | I26: ='YTD BS'!I26 | J26: ='BALANCE SHEET'!D26 | K26: ='YTD BS'!K26 | L26: ='YTD BS'!L26 | M26: ='YTD BS'!M26 | N26: ='BALANCE SHEET'!E26 | O26: ='YTD BS'!O26 | P26: ='YTD BS'!P26 | Q26: ='BS DRIVERS'!Q22 | R26: ='BS DRIVERS'!R22 | S26: ='BS DRIVERS'!S22 | T26: ='BS DRIVERS'!T22 | U26: ='BS DRIVERS'!U22 | V26: ='BS DRIVERS'!V22 | W26: ='BS DRIVERS'!W22 | X26: ='BS DRIVERS'!X22 | ... AH26: ='BS DRIVERS'!AH22
A27: Noncontrolling Interest | B27: ='BALANCE SHEET'!B27 | C27: ='YTD BS'!C27 | D27: ='YTD BS'!D27 | E27: ='YTD BS'!E27 | F27: ='BALANCE SHEET'!C27 | G27: ='YTD BS'!G27 | H27: ='YTD BS'!H27 | I27: ='YTD BS'!I27 | J27: ='BALANCE SHEET'!D27 | K27: ='YTD BS'!K27 | L27: ='YTD BS'!L27 | M27: ='YTD BS'!M27 | N27: ='BALANCE SHEET'!E27 | O27: ='YTD BS'!O27 | P27: ='YTD BS'!P27 | Q27: ='BS DRIVERS'!Q23 | R27: ='BS DRIVERS'!R23 | S27: ='BS DRIVERS'!S23 | T27: ='BS DRIVERS'!T23 | U27: ='BS DRIVERS'!U23 | V27: ='BS DRIVERS'!V23 | W27: ='BS DRIVERS'!W23 | X27: ='BS DRIVERS'!X23 | ... AH27: ='BS DRIVERS'!AH23
A28: Total Stockholders' Equity | B28: ='BALANCE SHEET'!B28 | C28: ='YTD BS'!C28 | D28: ='YTD BS'!D28 | E28: ='YTD BS'!E28 | F28: ='BALANCE SHEET'!C28 | G28: ='YTD BS'!G28 | H28: ='YTD BS'!H28 | I28: ='YTD BS'!I28 | J28: ='BALANCE SHEET'!D28 | K28: ='YTD BS'!K28 | L28: ='YTD BS'!L28 | M28: ='YTD BS'!M28 | N28: ='BALANCE SHEET'!E28 | O28: ='YTD BS'!O28 | P28: ='YTD BS'!P28 | Q28: =SUM(Q20:Q27) | R28: =SUM(R20:R27) | S28: =SUM(S20:S27) | T28: =SUM(T20:T27) | U28: =SUM(U20:U27) | V28: =SUM(V20:V27) | W28: =SUM(W20:W27) | X28: =SUM(X20:X27) | ... AH28: =SUM(AH20:AH27)
A29: Total Liabilities, Mezzanine & Stockholders' Equity | B29: ='BALANCE SHEET'!B29 | C29: ='YTD BS'!C29 | D29: ='YTD BS'!D29 | E29: ='YTD BS'!E29 | F29: ='BALANCE SHEET'!C29 | G29: ='YTD BS'!G29 | H29: ='YTD BS'!H29 | I29: ='YTD BS'!I29 | J29: ='BALANCE SHEET'!D29 | K29: ='YTD BS'!K29 | L29: ='YTD BS'!L29 | M29: ='YTD BS'!M29 | N29: ='BALANCE SHEET'!E29 | O29: ='YTD BS'!O29 | P29: ='YTD BS'!P29 | Q29: =Q19+Q28 | R29: =R19+R28 | S29: =S19+S28 | T29: =T19+T28 | U29: =U19+U28 | V29: =V19+V28 | W29: =W19+W28 | X29: =X19+X28 | ... AH29: =AH19+AH28

Sheet QTR CF
B1: Q1 FY2022 | C1: Q2 FY2022 | D1: Q3 FY2022 | E1: Q4 FY2022 | F1: Q1 FY2023 | G1: Q2 FY2023 | H1: Q3 FY2023 | I1: Q4 FY2023 | J1: Q1 FY2024 | K1: Q2 FY2024 | L1: Q3 FY2024 | M1: Q4 FY2024 | N1: Q1 FY2025 | O1: Q2 FY2025 | P1: Q3 FY2025 | Q1: Q4 FY2025 | R1: Q1 FY2026 | S1: Q2 FY2026 | T1: Q3 FY2026E | U1: Q4 FY2026E | V1: Q1 FY2027E | W1: Q2 FY2027E | X1: Q3 FY2027E | Y1: Q4 FY2027E | Z1: Q1 FY2028E | AA1: Q2 FY2028E | AB1: Q3 FY2028E | AC1: Q4 FY2028E | AD1: Q1 FY2029E | AE1: Q2 FY2029E | AF1: Q3 FY2029E | AG1: Q4 FY2029E | AH1: Q1 FY2030E | AI1: Q2 FY2030E | AJ1: Q3 FY2030E | AK1: Q4 FY2030E
A2: Net Income (Loss) | B2: ='YTD CF'!B2 | C2: ='YTD CF'!C2-'YTD CF'!B2 | D2: ='YTD CF'!D2-'YTD CF'!C2 | E2: ='CASH FLOW'!C2-'YTD CF'!D2 | F2: ='YTD CF'!E2 | G2: ='YTD CF'!F2-'YTD CF'!E2 | H2: ='YTD CF'!G2-'YTD CF'!F2 | I2: ='CASH FLOW'!D2-'YTD CF'!G2 | J2: ='YTD CF'!H2 | K2: ='YTD CF'!I2-'YTD CF'!H2 | L2: ='YTD CF'!J2-'YTD CF'!I2 | M2: ='CASH FLOW'!E2-'YTD CF'!J2 | N2: ='YTD CF'!K2 | O2: ='YTD CF'!L2-'YTD CF'!K2 | P2: ='YTD CF'!M2-'YTD CF'!L2 | Q2: ='CASH FLOW'!F2-'YTD CF'!M2 | R2: ='YTD CF'!N2 | S2: ='YTD CF'!O2-'YTD CF'!N2 | T2: ='CF DRIVERS'!T2 | U2: ='CF DRIVERS'!U2 | V2: ='CF DRIVERS'!V2 | W2: ='CF DRIVERS'!W2 | X2: ='CF DRIVERS'!X2 | Y2: ='CF DRIVERS'!Y2 | Z2: ='CF DRIVERS'!Z2 | AA2: ='CF DRIVERS'!AA2 | ... AK2: ='CF DRIVERS'!AK2
A3: Depreciation & Amortization | B3: ='YTD CF'!B3 | C3: ='YTD CF'!C3-'YTD CF'!B3 | D3: ='YTD CF'!D3-'YTD CF'!C3 | E3: ='CASH FLOW'!C3-'YTD CF'!D3 | F3: ='YTD CF'!E3 | G3: ='YTD CF'!F3-'YTD CF'!E3 | H3: ='YTD CF'!G3-'YTD CF'!F3 | I3: ='CASH FLOW'!D3-'YTD CF'!G3 | J3: ='YTD CF'!H3 | K3: ='YTD CF'!I3-'YTD CF'!H3 | L3: ='YTD CF'!J3-'YTD CF'!I3 | M3: ='CASH FLOW'!E3-'YTD CF'!J3 | N3: ='YTD CF'!K3 | O3: ='YTD CF'!L3-'YTD CF'!K3 | P3: ='YTD CF'!M3-'YTD CF'!L3 | Q3: ='CASH FLOW'!F3-'YTD CF'!M3 | R3: ='YTD CF'!N3 | S3: ='YTD CF'!O3-'YTD CF'!N3 | T3: ='QTR P&L'!T2*'CF DRIVERS'!T3 | U3: ='QTR P&L'!U2*'CF DRIVERS'!U3 | V3: ='QTR P&L'!V2*'CF DRIVERS'!V3 | W3: ='QTR P&L'!W2*'CF DRIVERS'!W3 | X3: ='QTR P&L'!X2*'CF DRIVERS'!X3 | Y3: ='QTR P&L'!Y2*'CF DRIVERS'!Y3 | Z3: ='QTR P&L'!Z2*'CF DRIVERS'!Z3 | AA3: ='QTR P&L'!AA2*'CF DRIVERS'!AA3 | ... AK3: ='QTR P&L'!AK2*'CF DRIVERS'!AK3
A4: Stock-Based Compensation | B4: ='YTD CF'!B4 | C4: ='YTD CF'!C4-'YTD CF'!B4 | D4: ='YTD CF'!D4-'YTD CF'!C4 | E4: ='CASH FLOW'!C5-'YTD CF'!D4 | F4: ='YTD CF'!E4 | G4: ='YTD CF'!F4-'YTD CF'!E4 | H4: ='YTD CF'!G4-'YTD CF'!F4 | I4: ='CASH FLOW'!D5-'YTD CF'!G4 | J4: ='YTD CF'!H4 | K4: ='YTD CF'!I4-'YTD CF'!H4 | L4: ='YTD CF'!J4-'YTD CF'!I4 | M4: ='CASH FLOW'!E5-'YTD CF'!J4 | N4: ='YTD CF'!K4 | O4: ='YTD CF'!L4-'YTD CF'!K4 | P4: ='YTD CF'!M4-'YTD CF'!L4 | Q4: ='CASH FLOW'!F5-'YTD CF'!M4 | R4: ='YTD CF'!N4 | S4: ='YTD CF'!O4-'YTD CF'!N4 | T4: ='QTR P&L'!T2*'CF DRIVERS'!T4 | U4: ='QTR P&L'!U2*'CF DRIVERS'!U4 | V4: ='QTR P&L'!V2*'CF DRIVERS'!V4 | W4: ='QTR P&L'!W2*'CF DRIVERS'!W4 | X4: ='QTR P&L'!X2*'CF DRIVERS'!X4 | Y4: ='QTR P&L'!Y2*'CF DRIVERS'!Y4 | Z4: ='QTR P&L'!Z2*'CF DRIVERS'!Z4 | AA4: ='QTR P&L'!AA2*'CF DRIVERS'!AA4 | ... AK4: ='QTR P&L'!AK2*'CF DRIVERS'!AK4
A5: (Benefit) Provision for Deferred Income Taxes | B5: ='YTD CF'!B5 | C5: ='YTD CF'!C5-'YTD CF'!B5 | D5: ='YTD CF'!D5-'YTD CF'!C5 | E5: ='CASH FLOW'!C6-'YTD CF'!D5 | F5: ='YTD CF'!E5 | G5: ='YTD CF'!F5-'YTD CF'!E5 | H5: ='YTD CF'!G5-'YTD CF'!F5 | I5: ='CASH FLOW'!D6-'YTD CF'!G5 | J5: ='YTD CF'!H5 | K5: ='YTD CF'!I5-'YTD CF'!H5 | L5: ='YTD CF'!J5-'YTD CF'!I5 | M5: ='CASH FLOW'!E6-'YTD CF'!J5 | N5: ='YTD CF'!K5 | O5: ='YTD CF'!L5-'YTD CF'!K5 | P5: ='YTD CF'!M5-'YTD CF'!L5 | Q5: ='CASH FLOW'!F6-'YTD CF'!M5 | R5: ='YTD CF'!N5 | S5: ='YTD CF'!O5-'YTD CF'!N5 | T5: ='CF DRIVERS'!T5 | U5: ='CF DRIVERS'!U5 | V5: ='CF DRIVERS'!V5 | W5: ='CF DRIVERS'!W5 | X5: ='CF DRIVERS'!X5 | Y5: ='CF DRIVERS'!Y5 | Z5: ='CF DRIVERS'!Z5 | AA5: ='CF DRIVERS'!AA5 | ... AK5: ='CF DRIVERS'!AK5
A6: Gain (Loss) on Disposal of PP&E | B6: ='YTD CF'!B6 | C6: ='YTD CF'!C6-'YTD CF'!B6 | D6: ='YTD CF'!D6-'YTD CF'!C6 | E6: ='CASH FLOW'!C7-'YTD CF'!D6 | F6: ='YTD CF'!E6 | G6: ='YTD CF'!F6-'YTD CF'!E6 | H6: ='YTD CF'!G6-'YTD CF'!F6 | I6: ='CASH FLOW'!D7-'YTD CF'!G6 | J6: ='YTD CF'!H6 | K6: ='YTD CF'!I6-'YTD CF'!H6 | L6: ='YTD CF'!J6-'YTD CF'!I6 | M6: ='CASH FLOW'!E7-'YTD CF'!J6 | N6: ='YTD CF'!K6 | O6: ='YTD CF'!L6-'YTD CF'!K6 | P6: ='YTD CF'!M6-'YTD CF'!L6 | Q6: ='CASH FLOW'!F7-'YTD CF'!M6 | R6: ='YTD CF'!N6 | S6: ='YTD CF'!O6-'YTD CF'!N6 | T6: ='CF DRIVERS'!T6 | U6: ='CF DRIVERS'!U6 | V6: ='CF DRIVERS'!V6 | W6: ='CF DRIVERS'!W6 | X6: ='CF DRIVERS'!X6 | Y6: ='CF DRIVERS'!Y6 | Z6: ='CF DRIVERS'!Z6 | AA6: ='CF DRIVERS'!AA6 | ... AK6: ='CF DRIVERS'!AK6
A7: Impairment of Intangibles | B7: ='YTD CF'!B7 | C7: ='YTD CF'!C7-'YTD CF'!B7 | D7: ='YTD CF'!D7-'YTD CF'!C7 | E7: ='CASH FLOW'!C8-'YTD CF'!D7 | F7: ='YTD CF'!E7 | G7: ='YTD CF'!F7-'YTD CF'!E7 | H7: ='YTD CF'!G7-'YTD CF'!F7 | I7: ='CASH FLOW'!D8-'YTD CF'!G7 | J7: ='YTD CF'!H7 | K7: ='YTD CF'!I7-'YTD CF'!H7 | L7: ='YTD CF'!J7-'YTD CF'!I7 | M7: ='CASH FLOW'!E8-'YTD CF'!J7 | N7: ='YTD CF'!K7 | O7: ='YTD CF'!L7-'YTD CF'!K7 | P7: ='YTD CF'!M7-'YTD CF'!L7 | Q7: ='CASH FLOW'!F8-'YTD CF'!M7 | R7: ='YTD CF'!N7 | S7: ='YTD CF'!O7-'YTD CF'!N7 | T7: ='CF DRIVERS'!T7 | U7: ='CF DRIVERS'!U7 | V7: ='CF DRIVERS'!V7 | W7: ='CF DRIVERS'!W7 | X7: ='CF DRIVERS'!X7 | Y7: ='CF DRIVERS'!Y7 | Z7: ='CF DRIVERS'!Z7 | AA7: ='CF DRIVERS'!AA7 | ... AK7: ='CF DRIVERS'!AK7
A8: Accounts Receivable | B8: ='YTD CF'!B8 | C8: ='YTD CF'!C8-'YTD CF'!B8 | D8: ='YTD CF'!D8-'YTD CF'!C8 | E8: ='CASH FLOW'!C9-'YTD CF'!D8 | F8: ='YTD CF'!E8 | G8: ='YTD CF'!F8-'YTD CF'!E8 | H8: ='YTD CF'!G8-'YTD CF'!F8 | I8: ='CASH FLOW'!D9-'YTD CF'!G8 | J8: ='YTD CF'!H8 | K8: ='YTD CF'!I8-'YTD CF'!H8 | L8: ='YTD CF'!J8-'YTD CF'!I8 | M8: ='CASH FLOW'!E9-'YTD CF'!J8 | N8: ='YTD CF'!K8 | O8: ='YTD CF'!L8-'YTD CF'!K8 | P8: ='YTD CF'!M8-'YTD CF'!L8 | Q8: ='CASH FLOW'!F9-'YTD CF'!M8 | R8: ='YTD CF'!N8 | S8: ='YTD CF'!O8-'YTD CF'!N8 | T8: ='CF DRIVERS'!T8 | U8: ='CF DRIVERS'!U8 | V8: ='CF DRIVERS'!V8 | W8: ='CF DRIVERS'!W8 | X8: ='CF DRIVERS'!X8 | Y8: ='CF DRIVERS'!Y8 | Z8: ='CF DRIVERS'!Z8 | AA8: ='CF DRIVERS'!AA8 | ... AK8: ='CF DRIVERS'!AK8
A9: Inventories | B9: ='YTD CF'!B9 | C9: ='YTD CF'!C9-'YTD CF'!B9 | D9: ='YTD CF'!D9-'YTD CF'!C9 | E9: ='CASH FLOW'!C10-'YTD CF'!D9 | F9: ='YTD CF'!E9 | G9: ='YTD CF'!F9-'YTD CF'!E9 | H9: ='YTD CF'!G9-'YTD CF'!F9 | I9: ='CASH FLOW'!D10-'YTD CF'!G9 | J9: ='YTD CF'!H9 | K9: ='YTD CF'!I9-'YTD CF'!H9 | L9: ='YTD CF'!J9-'YTD CF'!I9 | M9: ='CASH FLOW'!E10-'YTD CF'!J9 | N9: ='YTD CF'!K9 | O9: ='YTD CF'!L9-'YTD CF'!K9 | P9: ='YTD CF'!M9-'YTD CF'!L9 | Q9: ='CASH FLOW'!F10-'YTD CF'!M9 | R9: ='YTD CF'!N9 | S9: ='YTD CF'!O9-'YTD CF'!N9 | T9: ='CF DRIVERS'!T9 | U9: ='CF DRIVERS'!U9 | V9: ='CF DRIVERS'!V9 | W9: ='CF DRIVERS'!W9 | X9: ='CF DRIVERS'!X9 | Y9: ='CF DRIVERS'!Y9 | Z9: ='CF DRIVERS'!Z9 | AA9: ='CF DRIVERS'!AA9 | ... AK9: ='CF DRIVERS'!AK9
A10: Accounts Payable | B10: ='YTD CF'!B10 | C10: ='YTD CF'!C10-'YTD CF'!B10 | D10: ='YTD CF'!D10-'YTD CF'!C10 | E10: ='CASH FLOW'!C11-'YTD CF'!D10 | F10: ='YTD CF'!E10 | G10: ='YTD CF'!F10-'YTD CF'!E10 | H10: ='YTD CF'!G10-'YTD CF'!F10 | I10: ='CASH FLOW'!D11-'YTD CF'!G10 | J10: ='YTD CF'!H10 | K10: ='YTD CF'!I10-'YTD CF'!H10 | L10: ='YTD CF'!J10-'YTD CF'!I10 | M10: ='CASH FLOW'!E11-'YTD CF'!J10 | N10: ='YTD CF'!K10 | O10: ='YTD CF'!L10-'YTD CF'!K10 | P10: ='YTD CF'!M10-'YTD CF'!L10 | Q10: ='CASH FLOW'!F11-'YTD CF'!M10 | R10: ='YTD CF'!N10 | S10: ='YTD CF'!O10-'YTD CF'!N10 | T10: ='CF DRIVERS'!T10 | U10: ='CF DRIVERS'!U10 | V10: ='CF DRIVERS'!V10 | W10: ='CF DRIVERS'!W10 | X10: ='CF DRIVERS'!X10 | Y10: ='CF DRIVERS'!Y10 | Z10: ='CF DRIVERS'!Z10 | AA10: ='CF DRIVERS'!AA10 | ... AK10: ='CF DRIVERS'!AK10
A11: Net Change in Other Working Capital | B11: ='YTD CF'!B11 | C11: ='YTD CF'!C11-'YTD CF'!B11 | D11: ='YTD CF'!D11-'YTD CF'!C11 | E11: ='CASH FLOW'!C12-'YTD CF'!D11 | F11: ='YTD CF'!E11 | G11: ='YTD CF'!F11-'YTD CF'!E11 | H11: ='YTD CF'!G11-'YTD CF'!F11 | I11: ='CASH FLOW'!D12-'YTD CF'!G11 | J11: ='YTD CF'!H11 | K11: ='YTD CF'!I11-'YTD CF'!H11 | L11: ='YTD CF'!J11-'YTD CF'!I11 | M11: ='CASH FLOW'!E12-'YTD CF'!J11 | N11: ='YTD CF'!K11 | O11: ='YTD CF'!L11-'YTD CF'!K11 | P11: ='YTD CF'!M11-'YTD CF'!L11 | Q11: ='CASH FLOW'!F12-'YTD CF'!M11 | R11: ='YTD CF'!N11 | S11: ='YTD CF'!O11-'YTD CF'!N11 | T11: ='CF DRIVERS'!T11 | U11: ='CF DRIVERS'!U11 | V11: ='CF DRIVERS'!V11 | W11: ='CF DRIVERS'!W11 | X11: ='CF DRIVERS'!X11 | Y11: ='CF DRIVERS'!Y11 | Z11: ='CF DRIVERS'!Z11 | AA11: ='CF DRIVERS'!AA11 | ... AK11: ='CF DRIVERS'!AK11
A12: Other Operating Items | B12: ='YTD CF'!B12 | C12: ='YTD CF'!C12-'YTD CF'!B12 | D12: ='YTD CF'!D12-'YTD CF'!C12 | E12: ='CASH FLOW'!C13-'YTD CF'!D12 | F12: ='YTD CF'!E12 | G12: ='YTD CF'!F12-'YTD CF'!E12 | H12: ='YTD CF'!G12-'YTD CF'!F12 | I12: ='CASH FLOW'!D13-'YTD CF'!G12 | J12: ='YTD CF'!H12 | K12: ='YTD CF'!I12-'YTD CF'!H12 | L12: ='YTD CF'!J12-'YTD CF'!I12 | M12: ='CASH FLOW'!E13-'YTD CF'!J12 | N12: ='YTD CF'!K12 | O12: ='YTD CF'!L12-'YTD CF'!K12 | P12: ='YTD CF'!M12-'YTD CF'!L12 | Q12: ='CASH FLOW'!F13-'YTD CF'!M12 | R12: ='YTD CF'!N12 | S12: ='YTD CF'!O12-'YTD CF'!N12 | T12: ='CF DRIVERS'!T12 | U12: ='CF DRIVERS'!U12 | V12: ='CF DRIVERS'!V12 | W12: ='CF DRIVERS'!W12 | X12: ='CF DRIVERS'!X12 | Y12: ='CF DRIVERS'!Y12 | Z12: ='CF DRIVERS'!Z12 | AA12: ='CF DRIVERS'!AA12 | ... AK12: ='CF DRIVERS'!AK12
A13: Cash Flow from Operations | B13: ='YTD CF'!B13 | C13: ='YTD CF'!C13-'YTD CF'!B13 | D13: ='YTD CF'!D13-'YTD CF'!C13 | E13: ='CASH FLOW'!C14-'YTD CF'!D13 | F13: ='YTD CF'!E13 | G13: ='YTD CF'!F13-'YTD CF'!E13 | H13: ='YTD CF'!G13-'YTD CF'!F13 | I13: ='CASH FLOW'!D14-'YTD CF'!G13 | J13: ='YTD CF'!H13 | K13: ='YTD CF'!I13-'YTD CF'!H13 | L13: ='YTD CF'!J13-'YTD CF'!I13 | M13: ='CASH FLOW'!E14-'YTD CF'!J13 | N13: ='YTD CF'!K13 | O13: ='YTD CF'!L13-'YTD CF'!K13 | P13: ='YTD CF'!M13-'YTD CF'!L13 | Q13: ='CASH FLOW'!F14-'YTD CF'!M13 | R13: ='YTD CF'!N13 | S13: ='YTD CF'!O13-'YTD CF'!N13 | T13: =SUM(T2:T12) | U13: =SUM(U2:U12) | V13: =SUM(V2:V12) | W13: =SUM(W2:W12) | X13: =SUM(X2:X12) | Y13: =SUM(Y2:Y12) | Z13: =SUM(Z2:Z12) | AA13: =SUM(AA2:AA12) | ... AK13: =SUM(AK2:AK12)
A14: Purchase of PP&E | B14: ='YTD CF'!B14 | C14: ='YTD CF'!C14-'YTD CF'!B14 | D14: ='YTD CF'!D14-'YTD CF'!C14 | E14: ='CASH FLOW'!C15-'YTD CF'!D14 | F14: ='YTD CF'!E14 | G14: ='YTD CF'!F14-'YTD CF'!E14 | H14: ='YTD CF'!G14-'YTD CF'!F14 | I14: ='CASH FLOW'!D15-'YTD CF'!G14 | J14: ='YTD CF'!H14 | K14: ='YTD CF'!I14-'YTD CF'!H14 | L14: ='YTD CF'!J14-'YTD CF'!I14 | M14: ='CASH FLOW'!E15-'YTD CF'!J14 | N14: ='YTD CF'!K14 | O14: ='YTD CF'!L14-'YTD CF'!K14 | P14: ='YTD CF'!M14-'YTD CF'!L14 | Q14: ='CASH FLOW'!F15-'YTD CF'!M14 | R14: ='YTD CF'!N14 | S14: ='YTD CF'!O14-'YTD CF'!N14 | T14: ='QTR P&L'!T2*'CF DRIVERS'!T13 | U14: ='QTR P&L'!U2*'CF DRIVERS'!U13 | V14: ='QTR P&L'!V2*'CF DRIVERS'!V13 | W14: ='QTR P&L'!W2*'CF DRIVERS'!W13 | X14: ='QTR P&L'!X2*'CF DRIVERS'!X13 | Y14: ='QTR P&L'!Y2*'CF DRIVERS'!Y13 | Z14: ='QTR P&L'!Z2*'CF DRIVERS'!Z13 | AA14: ='QTR P&L'!AA2*'CF DRIVERS'!AA13 | ... AK14: ='QTR P&L'!AK2*'CF DRIVERS'!AK13
A15: Proceeds from Sale of Assets | B15: ='YTD CF'!B15 | C15: ='YTD CF'!C15-'YTD CF'!B15 | D15: ='YTD CF'!D15-'YTD CF'!C15 | E15: ='CASH FLOW'!C16-'YTD CF'!D15 | F15: ='YTD CF'!E15 | G15: ='YTD CF'!F15-'YTD CF'!E15 | H15: ='YTD CF'!G15-'YTD CF'!F15 | I15: ='CASH FLOW'!D16-'YTD CF'!G15 | J15: ='YTD CF'!H15 | K15: ='YTD CF'!I15-'YTD CF'!H15 | L15: ='YTD CF'!J15-'YTD CF'!I15 | M15: ='CASH FLOW'!E16-'YTD CF'!J15 | N15: ='YTD CF'!K15 | O15: ='YTD CF'!L15-'YTD CF'!K15 | P15: ='YTD CF'!M15-'YTD CF'!L15 | Q15: ='CASH FLOW'!F16-'YTD CF'!M15 | R15: ='YTD CF'!N15 | S15: ='YTD CF'!O15-'YTD CF'!N15 | T15: ='CF DRIVERS'!T14 | U15: ='CF DRIVERS'!U14 | V15: ='CF DRIVERS'!V14 | W15: ='CF DRIVERS'!W14 | X15: ='CF DRIVERS'!X14 | Y15: ='CF DRIVERS'!Y14 | Z15: ='CF DRIVERS'!Z14 | AA15: ='CF DRIVERS'!AA14 | ... AK15: ='CF DRIVERS'!AK14
A16: Acquisitions, Net of Cash Acquired | B16: ='YTD CF'!B16 | C16: ='YTD CF'!C16-'YTD CF'!B16 | D16: ='YTD CF'!D16-'YTD CF'!C16 | E16: ='CASH FLOW'!C17-'YTD CF'!D16 | F16: ='YTD CF'!E16 | G16: ='YTD CF'!F16-'YTD CF'!E16 | H16: ='YTD CF'!G16-'YTD CF'!F16 | I16: ='CASH FLOW'!D17-'YTD CF'!G16 | J16: ='YTD CF'!H16 | K16: ='YTD CF'!I16-'YTD CF'!H16 | L16: ='YTD CF'!J16-'YTD CF'!I16 | M16: ='CASH FLOW'!E17-'YTD CF'!J16 | N16: ='YTD CF'!K16 | O16: ='YTD CF'!L16-'YTD CF'!K16 | P16: ='YTD CF'!M16-'YTD CF'!L16 | Q16: ='CASH FLOW'!F17-'YTD CF'!M16 | R16: ='YTD CF'!N16 | S16: ='YTD CF'!O16-'YTD CF'!N16 | T16: ='CF DRIVERS'!T15 | U16: ='CF DRIVERS'!U15 | V16: ='CF DRIVERS'!V15 | W16: ='CF DRIVERS'!W15 | X16: ='CF DRIVERS'!X15 | Y16: ='CF DRIVERS'!Y15 | Z16: ='CF DRIVERS'!Z15 | AA16: ='CF DRIVERS'!AA15 | ... AK16: ='CF DRIVERS'!AK15
A17: Net Change in Short-Term Investments | B17: ='YTD CF'!B17 | C17: ='YTD CF'!C17-'YTD CF'!B17 | D17: ='YTD CF'!D17-'YTD CF'!C17 | F17: ='YTD CF'!E17 | G17: ='YTD CF'!F17-'YTD CF'!E17 | H17: ='YTD CF'!G17-'YTD CF'!F17 | J17: ='YTD CF'!H17 | K17: ='YTD CF'!I17-'YTD CF'!H17 | L17: ='YTD CF'!J17-'YTD CF'!I17 | N17: ='YTD CF'!K17 | O17: ='YTD CF'!L17-'YTD CF'!K17 | P17: ='YTD CF'!M17-'YTD CF'!L17 | R17: ='YTD CF'!N17 | S17: ='YTD CF'!O17-'YTD CF'!N17 | T17: ='CF DRIVERS'!T16 | U17: ='CF DRIVERS'!U16 | V17: ='CF DRIVERS'!V16 | W17: ='CF DRIVERS'!W16 | X17: ='CF DRIVERS'!X16 | Y17: ='CF DRIVERS'!Y16 | Z17: ='CF DRIVERS'!Z16 | AA17: ='CF DRIVERS'!AA16 | ... AK17: ='CF DRIVERS'!AK16
A18: Other Investing Activities | B18: ='YTD CF'!B18 | C18: ='YTD CF'!C18-'YTD CF'!B18 | D18: ='YTD CF'!D18-'YTD CF'!C18 | E18: ='CASH FLOW'!C18-'YTD CF'!D18 | F18: ='YTD CF'!E18 | G18: ='YTD CF'!F18-'YTD CF'!E18 | H18: ='YTD CF'!G18-'YTD CF'!F18 | I18: ='CASH FLOW'!D18-'YTD CF'!G18 | J18: ='YTD CF'!H18 | K18: ='YTD CF'!I18-'YTD CF'!H18 | L18: ='YTD CF'!J18-'YTD CF'!I18 | M18: ='CASH FLOW'!E18-'YTD CF'!J18 | N18: ='YTD CF'!K18 | O18: ='YTD CF'!L18-'YTD CF'!K18 | P18: ='YTD CF'!M18-'YTD CF'!L18 | Q18: ='CASH FLOW'!F18-'YTD CF'!M18 | R18: ='YTD CF'!N18 | S18: ='YTD CF'!O18-'YTD CF'!N18 | T18: ='CF DRIVERS'!T17 | U18: ='CF DRIVERS'!U17 | V18: ='CF DRIVERS'!V17 | W18: ='CF DRIVERS'!W17 | X18: ='CF DRIVERS'!X17 | Y18: ='CF DRIVERS'!Y17 | Z18: ='CF DRIVERS'!Z17 | AA18: ='CF DRIVERS'!AA17 | ... AK18: ='CF DRIVERS'!AK17
A19: Cash Flow from Investing | B19: ='YTD CF'!B19 | C19: ='YTD CF'!C19-'YTD CF'!B19 | D19: ='YTD CF'!D19-'YTD CF'!C19 | E19: ='CASH FLOW'!C19-'YTD CF'!D19 | F19: ='YTD CF'!E19 | G19: ='YTD CF'!F19-'YTD CF'!E19 | H19: ='YTD CF'!G19-'YTD CF'!F19 | I19: ='CASH FLOW'!D19-'YTD CF'!G19 | J19: ='YTD CF'!H19 | K19: ='YTD CF'!I19-'YTD CF'!H19 | L19: ='YTD CF'!J19-'YTD CF'!I19 | M19: ='CASH FLOW'!E19-'YTD CF'!J19 | N19: ='YTD CF'!K19 | O19: ='YTD CF'!L19-'YTD CF'!K19 | P19: ='YTD CF'!M19-'YTD CF'!L19 | Q19: ='CASH FLOW'!F19-'YTD CF'!M19 | R19: ='YTD CF'!N19 | S19: ='YTD CF'!O19-'YTD CF'!N19 | T19: =SUM(T14:T18) | U19: =SUM(U14:U18) | V19: =SUM(V14:V18) | W19: =SUM(W14:W18) | X19: =SUM(X14:X18) | Y19: =SUM(Y14:Y18) | Z19: =SUM(Z14:Z18) | AA19: =SUM(AA14:AA18) | ... AK19: =SUM(AK14:AK18)
A20: Common Dividends | B20: ='YTD CF'!B20 | C20: ='YTD CF'!C20-'YTD CF'!B20 | D20: ='YTD CF'!D20-'YTD CF'!C20 | E20: ='CASH FLOW'!C20-'YTD CF'!D20 | F20: ='YTD CF'!E20 | G20: ='YTD CF'!F20-'YTD CF'!E20 | H20: ='YTD CF'!G20-'YTD CF'!F20 | I20: ='CASH FLOW'!D20-'YTD CF'!G20 | J20: ='YTD CF'!H20 | K20: ='YTD CF'!I20-'YTD CF'!H20 | L20: ='YTD CF'!J20-'YTD CF'!I20 | M20: ='CASH FLOW'!E20-'YTD CF'!J20 | N20: ='YTD CF'!K20 | O20: ='YTD CF'!L20-'YTD CF'!K20 | P20: ='YTD CF'!M20-'YTD CF'!L20 | Q20: ='CASH FLOW'!F20-'YTD CF'!M20 | R20: ='YTD CF'!N20 | S20: ='YTD CF'!O20-'YTD CF'!N20 | T20: ='QTR P&L'!T12*'CF DRIVERS'!T18 | U20: ='QTR P&L'!U12*'CF DRIVERS'!U18 | V20: ='QTR P&L'!V12*'CF DRIVERS'!V18 | W20: ='QTR P&L'!W12*'CF DRIVERS'!W18 | X20: ='QTR P&L'!X12*'CF DRIVERS'!X18 | Y20: ='QTR P&L'!Y12*'CF DRIVERS'!Y18 | Z20: ='QTR P&L'!Z12*'CF DRIVERS'!Z18 | AA20: ='QTR P&L'!AA12*'CF DRIVERS'!AA18 | ... AK20: ='QTR P&L'!AK12*'CF DRIVERS'!AK18
A21: Proceeds from Short-Term Debt | B21: ='YTD CF'!B21 | C21: ='YTD CF'!C21-'YTD CF'!B21 | D21: ='YTD CF'!D21-'YTD CF'!C21 | E21: ='CASH FLOW'!C21-'YTD CF'!D21 | F21: ='YTD CF'!E21 | G21: ='YTD CF'!F21-'YTD CF'!E21 | H21: ='YTD CF'!G21-'YTD CF'!F21 | I21: ='CASH FLOW'!D21-'YTD CF'!G21 | J21: ='YTD CF'!H21 | K21: ='YTD CF'!I21-'YTD CF'!H21 | L21: ='YTD CF'!J21-'YTD CF'!I21 | M21: ='CASH FLOW'!E21-'YTD CF'!J21 | N21: ='YTD CF'!K21 | O21: ='YTD CF'!L21-'YTD CF'!K21 | P21: ='YTD CF'!M21-'YTD CF'!L21 | Q21: ='CASH FLOW'!F21-'YTD CF'!M21 | R21: ='YTD CF'!N21 | S21: ='YTD CF'!O21-'YTD CF'!N21 | T21: ='CF DRIVERS'!T19 | U21: ='CF DRIVERS'!U19 | V21: ='CF DRIVERS'!V19 | W21: ='CF DRIVERS'!W19 | X21: ='CF DRIVERS'!X19 | Y21: ='CF DRIVERS'!Y19 | Z21: ='CF DRIVERS'!Z19 | AA21: ='CF DRIVERS'!AA19 | ... AK21: ='CF DRIVERS'!AK19
A22: Repayments of Short-Term Debt | B22: ='YTD CF'!B22 | C22: ='YTD CF'!C22-'YTD CF'!B22 | D22: ='YTD CF'!D22-'YTD CF'!C22 | E22: ='CASH FLOW'!C22-'YTD CF'!D22 | F22: ='YTD CF'!E22 | G22: ='YTD CF'!F22-'YTD CF'!E22 | H22: ='YTD CF'!G22-'YTD CF'!F22 | I22: ='CASH FLOW'!D22-'YTD CF'!G22 | J22: ='YTD CF'!H22 | K22: ='YTD CF'!I22-'YTD CF'!H22 | L22: ='YTD CF'!J22-'YTD CF'!I22 | M22: ='CASH FLOW'!E22-'YTD CF'!J22 | N22: ='YTD CF'!K22 | O22: ='YTD CF'!L22-'YTD CF'!K22 | P22: ='YTD CF'!M22-'YTD CF'!L22 | Q22: ='CASH FLOW'!F22-'YTD CF'!M22 | R22: ='YTD CF'!N22 | S22: ='YTD CF'!O22-'YTD CF'!N22 | T22: ='CF DRIVERS'!T20 | U22: ='CF DRIVERS'!U20 | V22: ='CF DRIVERS'!V20 | W22: ='CF DRIVERS'!W20 | X22: ='CF DRIVERS'!X20 | Y22: ='CF DRIVERS'!Y20 | Z22: ='CF DRIVERS'!Z20 | AA22: ='CF DRIVERS'!AA20 | ... AK22: ='CF DRIVERS'!AK20
A23: Net Change in Other Short-Term Debt | B23: ='YTD CF'!B23 | C23: ='YTD CF'!C23-'YTD CF'!B23 | D23: ='YTD CF'!D23-'YTD CF'!C23 | E23: ='CASH FLOW'!C23-'YTD CF'!D23 | F23: ='YTD CF'!E23 | G23: ='YTD CF'!F23-'YTD CF'!E23 | H23: ='YTD CF'!G23-'YTD CF'!F23 | I23: ='CASH FLOW'!D23-'YTD CF'!G23 | J23: ='YTD CF'!H23 | K23: ='YTD CF'!I23-'YTD CF'!H23 | L23: ='YTD CF'!J23-'YTD CF'!I23 | M23: ='CASH FLOW'!E23-'YTD CF'!J23 | N23: ='YTD CF'!K23 | O23: ='YTD CF'!L23-'YTD CF'!K23 | P23: ='YTD CF'!M23-'YTD CF'!L23 | Q23: ='CASH FLOW'!F23-'YTD CF'!M23 | R23: ='YTD CF'!N23 | S23: ='YTD CF'!O23-'YTD CF'!N23 | T23: ='CF DRIVERS'!T21 | U23: ='CF DRIVERS'!U21 | V23: ='CF DRIVERS'!V21 | W23: ='CF DRIVERS'!W21 | X23: ='CF DRIVERS'!X21 | Y23: ='CF DRIVERS'!Y21 | Z23: ='CF DRIVERS'!Z21 | AA23: ='CF DRIVERS'!AA21 | ... AK23: ='CF DRIVERS'!AK21
A24: Proceeds from Issuance of Long-Term Debt | B24: ='YTD CF'!B24 | C24: ='YTD CF'!C24-'YTD CF'!B24 | D24: ='YTD CF'!D24-'YTD CF'!C24 | E24: ='CASH FLOW'!C24-'YTD CF'!D24 | F24: ='YTD CF'!E24 | G24: ='YTD CF'!F24-'YTD CF'!E24 | H24: ='YTD CF'!G24-'YTD CF'!F24 | I24: ='CASH FLOW'!D24-'YTD CF'!G24 | J24: ='YTD CF'!H24 | K24: ='YTD CF'!I24-'YTD CF'!H24 | L24: ='YTD CF'!J24-'YTD CF'!I24 | M24: ='CASH FLOW'!E24-'YTD CF'!J24 | N24: ='YTD CF'!K24 | O24: ='YTD CF'!L24-'YTD CF'!K24 | P24: ='YTD CF'!M24-'YTD CF'!L24 | Q24: ='CASH FLOW'!F24-'YTD CF'!M24 | R24: ='YTD CF'!N24 | S24: ='YTD CF'!O24-'YTD CF'!N24 | T24: ='CF DRIVERS'!T22 | U24: ='CF DRIVERS'!U22 | V24: ='CF DRIVERS'!V22 | W24: ='CF DRIVERS'!W22 | X24: ='CF DRIVERS'!X22 | Y24: ='CF DRIVERS'!Y22 | Z24: ='CF DRIVERS'!Z22 | AA24: ='CF DRIVERS'!AA22 | ... AK24: ='CF DRIVERS'!AK22
A25: Repayments of Long-Term Debt | B25: ='YTD CF'!B25 | C25: ='YTD CF'!C25-'YTD CF'!B25 | D25: ='YTD CF'!D25-'YTD CF'!C25 | E25: ='CASH FLOW'!C25-'YTD CF'!D25 | F25: ='YTD CF'!E25 | G25: ='YTD CF'!F25-'YTD CF'!E25 | H25: ='YTD CF'!G25-'YTD CF'!F25 | I25: ='CASH FLOW'!D25-'YTD CF'!G25 | J25: ='YTD CF'!H25 | K25: ='YTD CF'!I25-'YTD CF'!H25 | L25: ='YTD CF'!J25-'YTD CF'!I25 | M25: ='CASH FLOW'!E25-'YTD CF'!J25 | N25: ='YTD CF'!K25 | O25: ='YTD CF'!L25-'YTD CF'!K25 | P25: ='YTD CF'!M25-'YTD CF'!L25 | Q25: ='CASH FLOW'!F25-'YTD CF'!M25 | R25: ='YTD CF'!N25 | S25: ='YTD CF'!O25-'YTD CF'!N25 | T25: ='CF DRIVERS'!T23 | U25: ='CF DRIVERS'!U23 | V25: ='CF DRIVERS'!V23 | W25: ='CF DRIVERS'!W23 | X25: ='CF DRIVERS'!X23 | Y25: ='CF DRIVERS'!Y23 | Z25: ='CF DRIVERS'!Z23 | AA25: ='CF DRIVERS'!AA23 | ... AK25: ='CF DRIVERS'!AK23
A26: Share Repurchases | B26: ='YTD CF'!B26 | C26: ='YTD CF'!C26-'YTD CF'!B26 | D26: ='YTD CF'!D26-'YTD CF'!C26 | E26: ='CASH FLOW'!C26-'YTD CF'!D26 | F26: ='YTD CF'!E26 | G26: ='YTD CF'!F26-'YTD CF'!E26 | H26: ='YTD CF'!G26-'YTD CF'!F26 | I26: ='CASH FLOW'!D26-'YTD CF'!G26 | J26: ='YTD CF'!H26 | K26: ='YTD CF'!I26-'YTD CF'!H26 | L26: ='YTD CF'!J26-'YTD CF'!I26 | M26: ='CASH FLOW'!E26-'YTD CF'!J26 | N26: ='YTD CF'!K26 | O26: ='YTD CF'!L26-'YTD CF'!K26 | P26: ='YTD CF'!M26-'YTD CF'!L26 | Q26: ='CASH FLOW'!F26-'YTD CF'!M26 | R26: ='YTD CF'!N26 | S26: ='YTD CF'!O26-'YTD CF'!N26 | T26: ='CF DRIVERS'!T24 | U26: ='CF DRIVERS'!U24 | V26: ='CF DRIVERS'!V24 | W26: ='CF DRIVERS'!W24 | X26: ='CF DRIVERS'!X24 | Y26: ='CF DRIVERS'!Y24 | Z26: ='CF DRIVERS'!Z24 | AA26: ='CF DRIVERS'!AA24 | ... AK26: ='CF DRIVERS'!AK24
A27: Stock Options & Other Financing Activities | B27: ='YTD CF'!B27 | C27: ='YTD CF'!C27-'YTD CF'!B27 | D27: ='YTD CF'!D27-'YTD CF'!C27 | E27: ='CASH FLOW'!C27-'YTD CF'!D27 | F27: ='YTD CF'!E27 | G27: ='YTD CF'!F27-'YTD CF'!E27 | H27: ='YTD CF'!G27-'YTD CF'!F27 | I27: ='CASH FLOW'!D27-'YTD CF'!G27 | J27: ='YTD CF'!H27 | K27: ='YTD CF'!I27-'YTD CF'!H27 | L27: ='YTD CF'!J27-'YTD CF'!I27 | M27: ='CASH FLOW'!E27-'YTD CF'!J27 | N27: ='YTD CF'!K27 | O27: ='YTD CF'!L27-'YTD CF'!K27 | P27: ='YTD CF'!M27-'YTD CF'!L27 | Q27: ='CASH FLOW'!F27-'YTD CF'!M27 | R27: ='YTD CF'!N27 | S27: ='YTD CF'!O27-'YTD CF'!N27 | T27: ='CF DRIVERS'!T25 | U27: ='CF DRIVERS'!U25 | V27: ='CF DRIVERS'!V25 | W27: ='CF DRIVERS'!W25 | X27: ='CF DRIVERS'!X25 | Y27: ='CF DRIVERS'!Y25 | Z27: ='CF DRIVERS'!Z25 | AA27: ='CF DRIVERS'!AA25 | ... AK27: ='CF DRIVERS'!AK25
A28: Cash Flow from Financing | B28: ='YTD CF'!B28 | C28: ='YTD CF'!C28-'YTD CF'!B28 | D28: ='YTD CF'!D28-'YTD CF'!C28 | E28: ='CASH FLOW'!C28-'YTD CF'!D28 | F28: ='YTD CF'!E28 | G28: ='YTD CF'!F28-'YTD CF'!E28 | H28: ='YTD CF'!G28-'YTD CF'!F28 | I28: ='CASH FLOW'!D28-'YTD CF'!G28 | J28: ='YTD CF'!H28 | K28: ='YTD CF'!I28-'YTD CF'!H28 | L28: ='YTD CF'!J28-'YTD CF'!I28 | M28: ='CASH FLOW'!E28-'YTD CF'!J28 | N28: ='YTD CF'!K28 | O28: ='YTD CF'!L28-'YTD CF'!K28 | P28: ='YTD CF'!M28-'YTD CF'!L28 | Q28: ='CASH FLOW'!F28-'YTD CF'!M28 | R28: ='YTD CF'!N28 | S28: ='YTD CF'!O28-'YTD CF'!N28 | T28: =SUM(T20:T27) | U28: =SUM(U20:U27) | V28: =SUM(V20:V27) | W28: =SUM(W20:W27) | X28: =SUM(X20:X27) | Y28: =SUM(Y20:Y27) | Z28: =SUM(Z20:Z27) | AA28: =SUM(AA20:AA27) | ... AK28: =SUM(AK20:AK27)
A29: FX Effect on Cash | B29: ='YTD CF'!B29 | C29: ='YTD CF'!C29-'YTD CF'!B29 | D29: ='YTD CF'!D29-'YTD CF'!C29 | E29: ='CASH FLOW'!C29-'YTD CF'!D29 | F29: ='YTD CF'!E29 | G29: ='YTD CF'!F29-'YTD CF'!E29 | H29: ='YTD CF'!G29-'YTD CF'!F29 | I29: ='CASH FLOW'!D29-'YTD CF'!G29 | J29: ='YTD CF'!H29 | K29: ='YTD CF'!I29-'YTD CF'!H29 | L29: ='YTD CF'!J29-'YTD CF'!I29 | M29: ='CASH FLOW'!E29-'YTD CF'!J29 | N29: ='YTD CF'!K29 | O29: ='YTD CF'!L29-'YTD CF'!K29 | P29: ='YTD CF'!M29-'YTD CF'!L29 | Q29: ='CASH FLOW'!F29-'YTD CF'!M29 | R29: ='YTD CF'!N29 | S29: ='YTD CF'!O29-'YTD CF'!N29 | T29: ='CF DRIVERS'!T26 | U29: ='CF DRIVERS'!U26 | V29: ='CF DRIVERS'!V26 | W29: ='CF DRIVERS'!W26 | X29: ='CF DRIVERS'!X26 | Y29: ='CF DRIVERS'!Y26 | Z29: ='CF DRIVERS'!Z26 | AA29: ='CF DRIVERS'!AA26 | ... AK29: ='CF DRIVERS'!AK26
A30: Net Change in Cash | B30: ='YTD CF'!B30 | C30: ='YTD CF'!C30-'YTD CF'!B30 | D30: ='YTD CF'!D30-'YTD CF'!C30 | E30: ='CASH FLOW'!C30-'YTD CF'!D30 | F30: ='YTD CF'!E30 | G30: ='YTD CF'!F30-'YTD CF'!E30 | H30: ='YTD CF'!G30-'YTD CF'!F30 | I30: ='CASH FLOW'!D30-'YTD CF'!G30 | J30: ='YTD CF'!H30 | K30: ='YTD CF'!I30-'YTD CF'!H30 | L30: ='YTD CF'!J30-'YTD CF'!I30 | M30: ='CASH FLOW'!E30-'YTD CF'!J30 | N30: ='YTD CF'!K30 | O30: ='YTD CF'!L30-'YTD CF'!K30 | P30: ='YTD CF'!M30-'YTD CF'!L30 | Q30: ='CASH FLOW'!F30-'YTD CF'!M30 | R30: ='YTD CF'!N30 | S30: ='YTD CF'!O30-'YTD CF'!N30 | T30: =T13+T19+T28+T29 | U30: =U13+U19+U28+U29 | V30: =V13+V19+V28+V29 | W30: =W13+W19+W28+W29 | X30: =X13+X19+X28+X29 | Y30: =Y13+Y19+Y28+Y29 | Z30: =Z13+Z19+Z28+Z29 | AA30: =AA13+AA19+AA28+AA29 | ... AK30: =AK13+AK19+AK28+AK29

Sheet IS DRIVERS
A1: Driver | B1: Q1 FY2022 | C1: Q2 FY2022 | D1: Q3 FY2022 | E1: Q4 FY2022 | F1: Q1 FY2023 | G1: Q2 FY2023 | H1: Q3 FY2023 | I1: Q4 FY2023 | J1: Q1 FY2024 | K1: Q2 FY2024 | L1: Q3 FY2024 | M1: Q4 FY2024 | N1: Q1 FY2025 | O1: Q2 FY2025 | P1: Q3 FY2025 | Q1: Q4 FY2025 | R1: Q1 FY2026 | S1: Q2 FY2026 | T1: Q3 FY2026E | U1: Q4 FY2026E | V1: Q1 FY2027E | W1: Q2 FY2027E | X1: Q3 FY2027E | Y1: Q4 FY2027E | Z1: Q1 FY2028E | AA1: Q2 FY2028E | AB1: Q3 FY2028E | AC1: Q4 FY2028E | AD1: Q1 FY2029E | AE1: Q2 FY2029E | AF1: Q3 FY2029E | AG1: Q4 FY2029E | AH1: Q1 FY2030E | AI1: Q2 FY2030E | AJ1: Q3 FY2030E | AK1: Q4 FY2030E
A2: Net Sales / Revenue — Growth % | F2: =IFERROR('QTR P&L'!F2/'QTR P&L'!B2-1,"") | G2: =IFERROR('QTR P&L'!G2/'QTR P&L'!C2-1,"") | H2: =IFERROR('QTR P&L'!H2/'QTR P&L'!D2-1,"") | I2: =IFERROR('QTR P&L'!I2/'QTR P&L'!E2-1,"") | J2: =IFERROR('QTR P&L'!J2/'QTR P&L'!F2-1,"") | K2: =IFERROR('QTR P&L'!K2/'QTR P&L'!G2-1,"") | L2: =IFERROR('QTR P&L'!L2/'QTR P&L'!H2-1,"") | M2: =IFERROR('QTR P&L'!M2/'QTR P&L'!I2-1,"") | ... S2: =IFERROR('QTR P&L'!S2/'QTR P&L'!O2-1,"") | T2: =S2 | U2: =S2 | V2: =S2 | W2: =S2 | X2: =S2 | Y2: =S2 | Z2: =S2 | AA2: =S2 | AB2: =S2 | AC2: =S2 | AD2: =S2 | AE2: =S2 | AF2: =S2 | AG2: =S2 | AH2: =S2 | AI2: =S2 | AJ2: =S2 | AK2: =S2
A3: COGS — % of Revenue | B3: =IFERROR('QTR P&L'!B3/'QTR P&L'!B2,"") | C3: =IFERROR('QTR P&L'!C3/'QTR P&L'!C2,"") | D3: =IFERROR('QTR P&L'!D3/'QTR P&L'!D2,"") | E3: =IFERROR('QTR P&L'!E3/'QTR P&L'!E2,"") | F3: =IFERROR('QTR P&L'!F3/'QTR P&L'!F2,"") | G3: =IFERROR('QTR P&L'!G3/'QTR P&L'!G2,"") | H3: =IFERROR('QTR P&L'!H3/'QTR P&L'!H2,"") | I3: =IFERROR('QTR P&L'!I3/'QTR P&L'!I2,"") | ... S3: =IFERROR('QTR P&L'!S3/'QTR P&L'!S2,"") | T3: =S3 | U3: =S3 | V3: =S3 | W3: =S3 | X3: =S3 | Y3: =S3 | Z3: =S3 | AA3: =S3 | AB3: =S3 | AC3: =S3 | AD3: =S3 | AE3: =S3 | AF3: =S3 | AG3: =S3 | AH3: =S3 | AI3: =S3 | AJ3: =S3 | AK3: =S3
A4: SG&A — % of Revenue | B4: =IFERROR('QTR P&L'!B5/'QTR P&L'!B2,"") | C4: =IFERROR('QTR P&L'!C5/'QTR P&L'!C2,"") | D4: =IFERROR('QTR P&L'!D5/'QTR P&L'!D2,"") | E4: =IFERROR('QTR P&L'!E5/'QTR P&L'!E2,"") | F4: =IFERROR('QTR P&L'!F5/'QTR P&L'!F2,"") | G4: =IFERROR('QTR P&L'!G5/'QTR P&L'!G2,"") | H4: =IFERROR('QTR P&L'!H5/'QTR P&L'!H2,"") | I4: =IFERROR('QTR P&L'!I5/'QTR P&L'!I2,"") | ... S4: =IFERROR('QTR P&L'!S5/'QTR P&L'!S2,"") | T4: =S4 | U4: =S4 | V4: =S4 | W4: =S4 | X4: =S4 | Y4: =S4 | Z4: =S4 | AA4: =S4 | AB4: =S4 | AC4: =S4 | AD4: =S4 | AE4: =S4 | AF4: =S4 | AG4: =S4 | AH4: =S4 | AI4: =S4 | AJ4: =S4 | AK4: =S4
A5: Impairment of Intangibles — % of Revenue | B5: =IFERROR('QTR P&L'!B6/'QTR P&L'!B2,"") | C5: =IFERROR('QTR P&L'!C6/'QTR P&L'!C2,"") | D5: =IFERROR('QTR P&L'!D6/'QTR P&L'!D2,"") | E5: =IFERROR('QTR P&L'!E6/'QTR P&L'!E2,"") | F5: =IFERROR('QTR P&L'!F6/'QTR P&L'!F2,"") | G5: =IFERROR('QTR P&L'!G6/'QTR P&L'!G2,"") | H5: =IFERROR('QTR P&L'!H6/'QTR P&L'!H2,"") | I5: =IFERROR('QTR P&L'!I6/'QTR P&L'!I2,"") | ... S5: =IFERROR('QTR P&L'!S6/'QTR P&L'!S2,"") | T5: =S5 | U5: =S5 | V5: =S5 | W5: =S5 | X5: =S5 | Y5: =S5 | Z5: =S5 | AA5: =S5 | AB5: =S5 | AC5: =S5 | AD5: =S5 | AE5: =S5 | AF5: =S5 | AG5: =S5 | AH5: =S5 | AI5: =S5 | AJ5: =S5 | AK5: =S5
A6: Interest Income (Expense) | B6: ='QTR P&L'!B8 | C6: ='QTR P&L'!C8 | D6: ='QTR P&L'!D8 | E6: ='QTR P&L'!E8 | F6: ='QTR P&L'!F8 | G6: ='QTR P&L'!G8 | H6: ='QTR P&L'!H8 | I6: ='QTR P&L'!I8 | ... S6: ='QTR P&L'!S8 | T6: =S6 | U6: =S6 | V6: =S6 | W6: =S6 | X6: =S6 | Y6: =S6 | Z6: =S6 | AA6: =S6 | AB6: =S6 | AC6: =S6 | AD6: =S6 | AE6: =S6 | AF6: =S6 | AG6: =S6 | AH6: =S6 | AI6: =S6 | AJ6: =S6 | AK6: =S6
A7: Other Income (Expense) | B7: ='QTR P&L'!B9 | C7: ='QTR P&L'!C9 | D7: ='QTR P&L'!D9 | E7: ='QTR P&L'!E9 | F7: ='QTR P&L'!F9 | G7: ='QTR P&L'!G9 | H7: ='QTR P&L'!H9 | I7: ='QTR P&L'!I9 | ... S7: ='QTR P&L'!S9 | T7: =S7 | U7: =S7 | V7: =S7 | W7: =S7 | X7: =S7 | Y7: =S7 | Z7: =S7 | AA7: =S7 | AB7: =S7 | AC7: =S7 | AD7: =S7 | AE7: =S7 | AF7: =S7 | AG7: =S7 | AH7: =S7 | AI7: =S7 | AJ7: =S7 | AK7: =S7
A8: Income Tax (Expense) Benefit — Effective Tax Rate % | B8: =IFERROR('QTR P&L'!B11/'QTR P&L'!B10,"") | C8: =IFERROR('QTR P&L'!C11/'QTR P&L'!C10,"") | D8: =IFERROR('QTR P&L'!D11/'QTR P&L'!D10,"") | E8: =IFERROR('QTR P&L'!E11/'QTR P&L'!E10,"") | F8: =IFERROR('QTR P&L'!F11/'QTR P&L'!F10,"") | G8: =IFERROR('QTR P&L'!G11/'QTR P&L'!G10,"") | H8: =IFERROR('QTR P&L'!H11/'QTR P&L'!H10,"") | I8: =IFERROR('QTR P&L'!I11/'QTR P&L'!I10,"") | ... S8: =IFERROR('QTR P&L'!S11/'QTR P&L'!S10,"") | T8: =S8 | U8: =S8 | V8: =S8 | W8: =S8 | X8: =S8 | Y8: =S8 | Z8: =S8 | AA8: =S8 | AB8: =S8 | AC8: =S8 | AD8: =S8 | AE8: =S8 | AF8: =S8 | AG8: =S8 | AH8: =S8 | AI8: =S8 | AJ8: =S8 | AK8: =S8
A9: Net Income (Loss) Attributable to Noncontrolling Interest | B9: ='QTR P&L'!B13 | C9: ='QTR P&L'!C13 | D9: ='QTR P&L'!D13 | E9: ='QTR P&L'!E13 | F9: ='QTR P&L'!F13 | G9: ='QTR P&L'!G13 | H9: ='QTR P&L'!H13 | I9: ='QTR P&L'!I13 | ... S9: ='QTR P&L'!S13 | T9: =S9 | U9: =S9 | V9: =S9 | W9: =S9 | X9: =S9 | Y9: =S9 | Z9: =S9 | AA9: =S9 | AB9: =S9 | AC9: =S9 | AD9: =S9 | AE9: =S9 | AF9: =S9 | AG9: =S9 | AH9: =S9 | AI9: =S9 | AJ9: =S9 | AK9: =S9

Sheet BS DRIVERS
A1: Driver | B1: Q4 FY2022 | C1: Q1 FY2023 | D1: Q2 FY2023 | E1: Q3 FY2023 | F1: Q4 FY2023 | G1: Q1 FY2024 | H1: Q2 FY2024 | I1: Q3 FY2024 | J1: Q4 FY2024 | K1: Q1 FY2025 | L1: Q2 FY2025 | M1: Q3 FY2025 | N1: Q4 FY2025 | O1: Q1 FY2026 | P1: Q2 FY2026 | Q1: Q3 FY2026E | R1: Q4 FY2026E | S1: Q1 FY2027E | T1: Q2 FY2027E | U1: Q3 FY2027E | V1: Q4 FY2027E | W1: Q1 FY2028E | X1: Q2 FY2028E | Y1: Q3 FY2028E | Z1: Q4 FY2028E | AA1: Q1 FY2029E | AB1: Q2 FY2029E | AC1: Q3 FY2029E | AD1: Q4 FY2029E | AE1: Q1 FY2030E | AF1: Q2 FY2030E | AG1: Q3 FY2030E | AH1: Q4 FY2030E
A2: Cash & Cash Equivalents | B2: ='QTR BS'!B2 | C2: ='QTR BS'!C2 | D2: ='QTR BS'!D2 | E2: ='QTR BS'!E2 | F2: ='QTR BS'!F2 | G2: ='QTR BS'!G2 | H2: ='QTR BS'!H2 | I2: ='QTR BS'!I2 | ... P2: ='QTR BS'!P2 | Q2: =P2+'QTR CF'!T30 | R2: =Q2+'QTR CF'!U30 | S2: =R2+'QTR CF'!V30 | T2: =S2+'QTR CF'!W30 | U2: =T2+'QTR CF'!X30 | V2: =U2+'QTR CF'!Y30 | W2: =V2+'QTR CF'!Z30 | X2: =W2+'QTR CF'!AA30 | ... AH2: =AG2+'QTR CF'!AK30
A3: Accounts Receivable — DSO (days) | B3: =IFERROR('QTR BS'!B3/'QTR P&L'!B2*ASSUMPTIONS!$B$2,"") | C3: =IFERROR('QTR BS'!C3/'QTR P&L'!C2*ASSUMPTIONS!$B$2,"") | D3: =IFERROR('QTR BS'!D3/'QTR P&L'!D2*ASSUMPTIONS!$B$2,"") | E3: =IFERROR('QTR BS'!E3/'QTR P&L'!E2*ASSUMPTIONS!$B$2,"") | F3: =IFERROR('QTR BS'!F3/'QTR P&L'!F2*ASSUMPTIONS!$B$2,"") | G3: =IFERROR('QTR BS'!G3/'QTR P&L'!G2*ASSUMPTIONS!$B$2,"") | H3: =IFERROR('QTR BS'!H3/'QTR P&L'!H2*ASSUMPTIONS!$B$2,"") | I3: =IFERROR('QTR BS'!I3/'QTR P&L'!I2*ASSUMPTIONS!$B$2,"") | ... P3: =IFERROR('QTR BS'!P3/'QTR P&L'!P2*ASSUMPTIONS!$B$2,"") | Q3: =P3 | R3: =P3 | S3: =P3 | T3: =P3 | U3: =P3 | V3: =P3 | W3: =P3 | X3: =P3 | Y3: =P3 | Z3: =P3 | AA3: =P3 | AB3: =P3 | AC3: =P3 | AD3: =P3 | AE3: =P3 | AF3: =P3 | AG3: =P3 | AH3: =P3
A4: Inventories — DIO (days) | B4: =IFERROR('QTR BS'!B4/'QTR P&L'!B3*ASSUMPTIONS!$B$2,"") | C4: =IFERROR('QTR BS'!C4/'QTR P&L'!C3*ASSUMPTIONS!$B$2,"") | D4: =IFERROR('QTR BS'!D4/'QTR P&L'!D3*ASSUMPTIONS!$B$2,"") | E4: =IFERROR('QTR BS'!E4/'QTR P&L'!E3*ASSUMPTIONS!$B$2,"") | F4: =IFERROR('QTR BS'!F4/'QTR P&L'!F3*ASSUMPTIONS!$B$2,"") | G4: =IFERROR('QTR BS'!G4/'QTR P&L'!G3*ASSUMPTIONS!$B$2,"") | H4: =IFERROR('QTR BS'!H4/'QTR P&L'!H3*ASSUMPTIONS!$B$2,"") | I4: =IFERROR('QTR BS'!I4/'QTR P&L'!I3*ASSUMPTIONS!$B$2,"") | ... P4: =IFERROR('QTR BS'!P4/'QTR P&L'!P3*ASSUMPTIONS!$B$2,"") | Q4: =P4 | R4: =P4 | S4: =P4 | T4: =P4 | U4: =P4 | V4: =P4 | W4: =P4 | X4: =P4 | Y4: =P4 | Z4: =P4 | AA4: =P4 | AB4: =P4 | AC4: =P4 | AD4: =P4 | AE4: =P4 | AF4: =P4 | AG4: =P4 | AH4: =P4
A5: Prepaid Expenses — % of Revenue | B5: =IFERROR('QTR BS'!B5/'QTR P&L'!B2,"") | C5: =IFERROR('QTR BS'!C5/'QTR P&L'!C2,"") | D5: =IFERROR('QTR BS'!D5/'QTR P&L'!D2,"") | E5: =IFERROR('QTR BS'!E5/'QTR P&L'!E2,"") | F5: =IFERROR('QTR BS'!F5/'QTR P&L'!F2,"") | G5: =IFERROR('QTR BS'!G5/'QTR P&L'!G2,"") | H5: =IFERROR('QTR BS'!H5/'QTR P&L'!H2,"") | I5: =IFERROR('QTR BS'!I5/'QTR P&L'!I2,"") | ... P5: =IFERROR('QTR BS'!P5/'QTR P&L'!P2,"") | Q5: =P5 | R5: =P5 | S5: =P5 | T5: =P5 | U5: =P5 | V5: =P5 | W5: =P5 | X5: =P5 | Y5: =P5 | Z5: =P5 | AA5: =P5 | AB5: =P5 | AC5: =P5 | AD5: =P5 | AE5: =P5 | AF5: =P5 | AG5: =P5 | AH5: =P5
A6: Net PP&E | B6: ='QTR BS'!B7 | C6: ='QTR BS'!C7 | D6: ='QTR BS'!D7 | E6: ='QTR BS'!E7 | F6: ='QTR BS'!F7 | G6: ='QTR BS'!G7 | H6: ='QTR BS'!H7 | I6: ='QTR BS'!I7 | ... P6: ='QTR BS'!P7 | Q6: =P6-'QTR CF'!T14-'QTR CF'!T3 | R6: =Q6-'QTR CF'!U14-'QTR CF'!U3 | S6: =R6-'QTR CF'!V14-'QTR CF'!V3 | T6: =S6-'QTR CF'!W14-'QTR CF'!W3 | U6: =T6-'QTR CF'!X14-'QTR CF'!X3 | V6: =U6-'QTR CF'!Y14-'QTR CF'!Y3 | W6: =V6-'QTR CF'!Z14-'QTR CF'!Z3 | X6: =W6-'QTR CF'!AA14-'QTR CF'!AA3 | ... AH6: =AG6-'QTR CF'!AK14-'QTR CF'!AK3
A7: Goodwill | B7: ='QTR BS'!B8 | C7: ='QTR BS'!C8 | D7: ='QTR BS'!D8 | E7: ='QTR BS'!E8 | F7: ='QTR BS'!F8 | G7: ='QTR BS'!G8 | H7: ='QTR BS'!H8 | I7: ='QTR BS'!I8 | ... P7: ='QTR BS'!P8 | Q7: =P7 | R7: =P7 | S7: =P7 | T7: =P7 | U7: =P7 | V7: =P7 | W7: =P7 | X7: =P7 | Y7: =P7 | Z7: =P7 | AA7: =P7 | AB7: =P7 | AC7: =P7 | AD7: =P7 | AE7: =P7 | AF7: =P7 | AG7: =P7 | AH7: =P7
A8: Intangible Assets | B8: ='QTR BS'!B9 | C8: ='QTR BS'!C9 | D8: ='QTR BS'!D9 | E8: ='QTR BS'!E9 | F8: ='QTR BS'!F9 | G8: ='QTR BS'!G9 | H8: ='QTR BS'!H9 | I8: ='QTR BS'!I9 | ... P8: ='QTR BS'!P9 | Q8: =P8 | R8: =P8 | S8: =P8 | T8: =P8 | U8: =P8 | V8: =P8 | W8: =P8 | X8: =P8 | Y8: =P8 | Z8: =P8 | AA8: =P8 | AB8: =P8 | AC8: =P8 | AD8: =P8 | AE8: =P8 | AF8: =P8 | AG8: =P8 | AH8: =P8
A9: Other Non-Current Assets — % of Revenue | B9: =IFERROR('QTR BS'!B10/'QTR P&L'!B2,"") | C9: =IFERROR('QTR BS'!C10/'QTR P&L'!C2,"") | D9: =IFERROR('QTR BS'!D10/'QTR P&L'!D2,"") | E9: =IFERROR('QTR BS'!E10/'QTR P&L'!E2,"") | F9: =IFERROR('QTR BS'!F10/'QTR P&L'!F2,"") | G9: =IFERROR('QTR BS'!G10/'QTR P&L'!G2,"") | H9: =IFERROR('QTR BS'!H10/'QTR P&L'!H2,"") | I9: =IFERROR('QTR BS'!I10/'QTR P&L'!I2,"") | ... P9: =IFERROR('QTR BS'!P10/'QTR P&L'!P2,"") | Q9: =P9 | R9: =P9 | S9: =P9 | T9: =P9 | U9: =P9 | V9: =P9 | W9: =P9 | X9: =P9 | Y9: =P9 | Z9: =P9 | AA9: =P9 | AB9: =P9 | AC9: =P9 | AD9: =P9 | AE9: =P9 | AF9: =P9 | AG9: =P9 | AH9: =P9
A10: Accounts Payable — DPO (days) | B10: =IFERROR('QTR BS'!B12/'QTR P&L'!B3*ASSUMPTIONS!$B$2,"") | C10: =IFERROR('QTR BS'!C12/'QTR P&L'!C3*ASSUMPTIONS!$B$2,"") | D10: =IFERROR('QTR BS'!D12/'QTR P&L'!D3*ASSUMPTIONS!$B$2,"") | E10: =IFERROR('QTR BS'!E12/'QTR P&L'!E3*ASSUMPTIONS!$B$2,"") | F10: =IFERROR('QTR BS'!F12/'QTR P&L'!F3*ASSUMPTIONS!$B$2,"") | G10: =IFERROR('QTR BS'!G12/'QTR P&L'!G3*ASSUMPTIONS!$B$2,"") | H10: =IFERROR('QTR BS'!H12/'QTR P&L'!H3*ASSUMPTIONS!$B$2,"") | I10: =IFERROR('QTR BS'!I12/'QTR P&L'!I3*ASSUMPTIONS!$B$2,"") | ... P10: =IFERROR('QTR BS'!P12/'QTR P&L'!P3*ASSUMPTIONS!$B$2,"") | Q10: =P10 | R10: =P10 | S10: =P10 | T10: =P10 | U10: =P10 | V10: =P10 | W10: =P10 | X10: =P10 | Y10: =P10 | Z10: =P10 | AA10: =P10 | AB10: =P10 | AC10: =P10 | AD10: =P10 | AE10: =P10 | AF10: =P10 | AG10: =P10 | AH10: =P10
A11: Accrued Expenses — % of Revenue | B11: =IFERROR('QTR BS'!B13/'QTR P&L'!B2,"") | C11: =IFERROR('QTR BS'!C13/'QTR P&L'!C2,"") | D11: =IFERROR('QTR BS'!D13/'QTR P&L'!D2,"") | E11: =IFERROR('QTR BS'!E13/'QTR P&L'!E2,"") | F11: =IFERROR('QTR BS'!F13/'QTR P&L'!F2,"") | G11: =IFERROR('QTR BS'!G13/'QTR P&L'!G2,"") | H11: =IFERROR('QTR BS'!H13/'QTR P&L'!H2,"") | I11: =IFERROR('QTR BS'!I13/'QTR P&L'!I2,"") | ... P11: =IFERROR('QTR BS'!P13/'QTR P&L'!P2,"") | Q11: =P11 | R11: =P11 | S11: =P11 | T11: =P11 | U11: =P11 | V11: =P11 | W11: =P11 | X11: =P11 | Y11: =P11 | Z11: =P11 | AA11: =P11 | AB11: =P11 | AC11: =P11 | AD11: =P11 | AE11: =P11 | AF11: =P11 | AG11: =P11 | AH11: =P11
A12: Current Portion of Long-Term Debt | B12: ='QTR BS'!B14 | C12: ='QTR BS'!C14 | D12: ='QTR BS'!D14 | E12: ='QTR BS'!E14 | F12: ='QTR BS'!F14 | G12: ='QTR BS'!G14 | H12: ='QTR BS'!H14 | I12: ='QTR BS'!I14 | ... P12: ='QTR BS'!P14 | Q12: =P12 | R12: =P12 | S12: =P12 | T12: =P12 | U12: =P12 | V12: =P12 | W12: =P12 | X12: =P12 | Y12: =P12 | Z12: =P12 | AA12: =P12 | AB12: =P12 | AC12: =P12 | AD12: =P12 | AE12: =P12 | AF12: =P12 | AG12: =P12 | AH12: =P12
A13: Long-Term Debt | B13: ='QTR BS'!B16 | C13: ='QTR BS'!C16 | D13: ='QTR BS'!D16 | E13: ='QTR BS'!E16 | F13: ='QTR BS'!F16 | G13: ='QTR BS'!G16 | H13: ='QTR BS'!H16 | I13: ='QTR BS'!I16 | ... P13: ='QTR BS'!P16 | Q13: =P13 | R13: =P13 | S13: =P13 | T13: =P13 | U13: =P13 | V13: =P13 | W13: =P13 | X13: =P13 | Y13: =P13 | Z13: =P13 | AA13: =P13 | AB13: =P13 | AC13: =P13 | AD13: =P13 | AE13: =P13 | AF13: =P13 | AG13: =P13 | AH13: =P13
A14: Deferred Tax Liability | B14: ='QTR BS'!B17 | C14: ='QTR BS'!C17 | D14: ='QTR BS'!D17 | E14: ='QTR BS'!E17 | F14: ='QTR BS'!F17 | G14: ='QTR BS'!G17 | H14: ='QTR BS'!H17 | I14: ='QTR BS'!I17 | ... P14: ='QTR BS'!P17 | Q14: =P14 | R14: =P14 | S14: =P14 | T14: =P14 | U14: =P14 | V14: =P14 | W14: =P14 | X14: =P14 | Y14: =P14 | Z14: =P14 | AA14: =P14 | AB14: =P14 | AC14: =P14 | AD14: =P14 | AE14: =P14 | AF14: =P14 | AG14: =P14 | AH14: =P14
A15: Other Non-Current Liabilities — % of Revenue | B15: =IFERROR('QTR BS'!B18/'QTR P&L'!B2,"") | C15: =IFERROR('QTR BS'!C18/'QTR P&L'!C2,"") | D15: =IFERROR('QTR BS'!D18/'QTR P&L'!D2,"") | E15: =IFERROR('QTR BS'!E18/'QTR P&L'!E2,"") | F15: =IFERROR('QTR BS'!F18/'QTR P&L'!F2,"") | G15: =IFERROR('QTR BS'!G18/'QTR P&L'!G2,"") | H15: =IFERROR('QTR BS'!H18/'QTR P&L'!H2,"") | I15: =IFERROR('QTR BS'!I18/'QTR P&L'!I2,"") | ... P15: =IFERROR('QTR BS'!P18/'QTR P&L'!P2,"") | Q15: =P15 | R15: =P15 | S15: =P15 | T15: =P15 | U15: =P15 | V15: =P15 | W15: =P15 | X15: =P15 | Y15: =P15 | Z15: =P15 | AA15: =P15 | AB15: =P15 | AC15: =P15 | AD15: =P15 | AE15: =P15 | AF15: =P15 | AG15: =P15 | AH15: =P15
A16: Convertible Preferred Stock | B16: ='QTR BS'!B20 | C16: ='QTR BS'!C20 | D16: ='QTR BS'!D20 | E16: ='QTR BS'!E20 | F16: ='QTR BS'!F20 | G16: ='QTR BS'!G20 | H16: ='QTR BS'!H20 | I16: ='QTR BS'!I20 | ... P16: ='QTR BS'!P20 | Q16: =P16 | R16: =P16 | S16: =P16 | T16: =P16 | U16: =P16 | V16: =P16 | W16: =P16 | X16: =P16 | Y16: =P16 | Z16: =P16 | AA16: =P16 | AB16: =P16 | AC16: =P16 | AD16: =P16 | AE16: =P16 | AF16: =P16 | AG16: =P16 | AH16: =P16
A17: Common Stock | B17: ='QTR BS'!B21 | C17: ='QTR BS'!C21 | D17: ='QTR BS'!D21 | E17: ='QTR BS'!E21 | F17: ='QTR BS'!F21 | G17: ='QTR BS'!G21 | H17: ='QTR BS'!H21 | I17: ='QTR BS'!I21 | ... P17: ='QTR BS'!P21 | Q17: =P17 | R17: =P17 | S17: =P17 | T17: =P17 | U17: =P17 | V17: =P17 | W17: =P17 | X17: =P17 | Y17: =P17 | Z17: =P17 | AA17: =P17 | AB17: =P17 | AC17: =P17 | AD17: =P17 | AE17: =P17 | AF17: =P17 | AG17: =P17 | AH17: =P17
A18: Additional Paid-in Capital | B18: ='QTR BS'!B22 | C18: ='QTR BS'!C22 | D18: ='QTR BS'!D22 | E18: ='QTR BS'!E22 | F18: ='QTR BS'!F22 | G18: ='QTR BS'!G22 | H18: ='QTR BS'!H22 | I18: ='QTR BS'!I22 | ... P18: ='QTR BS'!P22 | Q18: =P18+'QTR CF'!T4 | R18: =Q18+'QTR CF'!U4 | S18: =R18+'QTR CF'!V4 | T18: =S18+'QTR CF'!W4 | U18: =T18+'QTR CF'!X4 | V18: =U18+'QTR CF'!Y4 | W18: =V18+'QTR CF'!Z4 | X18: =W18+'QTR CF'!AA4 | ... AH18: =AG18+'QTR CF'!AK4
A19: ESOP Debt Retirement Reserve | B19: ='QTR BS'!B23 | C19: ='QTR BS'!C23 | D19: ='QTR BS'!D23 | E19: ='QTR BS'!E23 | F19: ='QTR BS'!F23 | G19: ='QTR BS'!G23 | H19: ='QTR BS'!H23 | I19: ='QTR BS'!I23 | ... P19: ='QTR BS'!P23 | Q19: 0 | R19: 0 | S19: 0 | T19: 0 | U19: 0 | V19: 0 | W19: 0 | X19: 0 | Y19: 0 | Z19: 0 | AA19: 0 | AB19: 0 | AC19: 0 | AD19: 0 | AE19: 0 | AF19: 0 | AG19: 0 | AH19: 0
A20: Accumulated Other Comprehensive Income (Loss) | B20: ='QTR BS'!B24 | C20: ='QTR BS'!C24 | D20: ='QTR BS'!D24 | E20: ='QTR BS'!E24 | F20: ='QTR BS'!F24 | G20: ='QTR BS'!G24 | H20: ='QTR BS'!H24 | I20: ='QTR BS'!I24 | ... P20: ='QTR BS'!P24 | Q20: =P20+'QTR CF'!T29 | R20: =Q20+'QTR CF'!U29 | S20: =R20+'QTR CF'!V29 | T20: =S20+'QTR CF'!W29 | U20: =T20+'QTR CF'!X29 | V20: =U20+'QTR CF'!Y29 | W20: =V20+'QTR CF'!Z29 | X20: =W20+'QTR CF'!AA29 | ... AH20: =AG20+'QTR CF'!AK29
A21: Treasury Stock | B21: ='QTR BS'!B25 | C21: ='QTR BS'!C25 | D21: ='QTR BS'!D25 | E21: ='QTR BS'!E25 | F21: ='QTR BS'!F25 | G21: ='QTR BS'!G25 | H21: ='QTR BS'!H25 | I21: ='QTR BS'!I25 | ... P21: ='QTR BS'!P25 | Q21: =P21 | R21: =P21 | S21: =P21 | T21: =P21 | U21: =P21 | V21: =P21 | W21: =P21 | X21: =P21 | Y21: =P21 | Z21: =P21 | AA21: =P21 | AB21: =P21 | AC21: =P21 | AD21: =P21 | AE21: =P21 | AF21: =P21 | AG21: =P21 | AH21: =P21
A22: Retained Earnings (Accumulated Deficit) | B22: ='QTR BS'!B26 | C22: ='QTR BS'!C26 | D22: ='QTR BS'!D26 | E22: ='QTR BS'!E26 | F22: ='QTR BS'!F26 | G22: ='QTR BS'!G26 | H22: ='QTR BS'!H26 | I22: ='QTR BS'!I26 | ... P22: ='QTR BS'!P26 | Q22: =P22+'QTR P&L'!T12+'QTR CF'!T20 | R22: =Q22+'QTR P&L'!U12+'QTR CF'!U20 | S22: =R22+'QTR P&L'!V12+'QTR CF'!V20 | T22: =S22+'QTR P&L'!W12+'QTR CF'!W20 | U22: =T22+'QTR P&L'!X12+'QTR CF'!X20 | V22: =U22+'QTR P&L'!Y12+'QTR CF'!Y20 | W22: =V22+'QTR P&L'!Z12+'QTR CF'!Z20 | X22: =W22+'QTR P&L'!AA12+'QTR CF'!AA20 | ... AH22: =AG22+'QTR P&L'!AK12+'QTR CF'!AK20
A23: Noncontrolling Interest | B23: ='QTR BS'!B27 | C23: ='QTR BS'!C27 | D23: ='QTR BS'!D27 | E23: ='QTR BS'!E27 | F23: ='QTR BS'!F27 | G23: ='QTR BS'!G27 | H23: ='QTR BS'!H27 | I23: ='QTR BS'!I27 | ... P23: ='QTR BS'!P27 | Q23: =P23 | R23: =P23 | S23: =P23 | T23: =P23 | U23: =P23 | V23: =P23 | W23: =P23 | X23: =P23 | Y23: =P23 | Z23: =P23 | AA23: =P23 | AB23: =P23 | AC23: =P23 | AD23: =P23 | AE23: =P23 | AF23: =P23 | AG23: =P23 | AH23: =P23

Sheet CF DRIVERS
A1: Driver | B1: Q1 FY2022 | C1: Q2 FY2022 | D1: Q3 FY2022 | E1: Q4 FY2022 | F1: Q1 FY2023 | G1: Q2 FY2023 | H1: Q3 FY2023 | I1: Q4 FY2023 | J1: Q1 FY2024 | K1: Q2 FY2024 | L1: Q3 FY2024 | M1: Q4 FY2024 | N1: Q1 FY2025 | O1: Q2 FY2025 | P1: Q3 FY2025 | Q1: Q4 FY2025 | R1: Q1 FY2026 | S1: Q2 FY2026 | T1: Q3 FY2026E | U1: Q4 FY2026E | V1: Q1 FY2027E | W1: Q2 FY2027E | X1: Q3 FY2027E | Y1: Q4 FY2027E | Z1: Q1 FY2028E | AA1: Q2 FY2028E | AB1: Q3 FY2028E | AC1: Q4 FY2028E | AD1: Q1 FY2029E | AE1: Q2 FY2029E | AF1: Q3 FY2029E | AG1: Q4 FY2029E | AH1: Q1 FY2030E | AI1: Q2 FY2030E | AJ1: Q3 FY2030E | AK1: Q4 FY2030E
A2: Net Income (Loss) | B2: ='QTR CF'!B2 | C2: ='QTR CF'!C2 | D2: ='QTR CF'!D2 | E2: ='QTR CF'!E2 | F2: ='QTR CF'!F2 | G2: ='QTR CF'!G2 | H2: ='QTR CF'!H2 | I2: ='QTR CF'!I2 | ... S2: ='QTR CF'!S2 | T2: ='QTR P&L'!T12 | U2: ='QTR P&L'!U12 | V2: ='QTR P&L'!V12 | W2: ='QTR P&L'!W12 | X2: ='QTR P&L'!X12 | Y2: ='QTR P&L'!Y12 | Z2: ='QTR P&L'!Z12 | AA2: ='QTR P&L'!AA12 | ... AK2: ='QTR P&L'!AK12
A3: Depreciation & Amortization — % of Revenue | B3: =IFERROR('QTR CF'!B3/'QTR P&L'!B2,"") | C3: =IFERROR('QTR CF'!C3/'QTR P&L'!C2,"") | D3: =IFERROR('QTR CF'!D3/'QTR P&L'!D2,"") | E3: =IFERROR('QTR CF'!E3/'QTR P&L'!E2,"") | F3: =IFERROR('QTR CF'!F3/'QTR P&L'!F2,"") | G3: =IFERROR('QTR CF'!G3/'QTR P&L'!G2,"") | H3: =IFERROR('QTR CF'!H3/'QTR P&L'!H2,"") | I3: =IFERROR('QTR CF'!I3/'QTR P&L'!I2,"") | ... S3: =IFERROR('QTR CF'!S3/'QTR P&L'!S2,"") | T3: =S3 | U3: =S3 | V3: =S3 | W3: =S3 | X3: =S3 | Y3: =S3 | Z3: =S3 | AA3: =S3 | AB3: =S3 | AC3: =S3 | AD3: =S3 | AE3: =S3 | AF3: =S3 | AG3: =S3 | AH3: =S3 | AI3: =S3 | AJ3: =S3 | AK3: =S3
A4: Stock-Based Compensation — % of Revenue | B4: =IFERROR('QTR CF'!B4/'QTR P&L'!B2,"") | C4: =IFERROR('QTR CF'!C4/'QTR P&L'!C2,"") | D4: =IFERROR('QTR CF'!D4/'QTR P&L'!D2,"") | E4: =IFERROR('QTR CF'!E4/'QTR P&L'!E2,"") | F4: =IFERROR('QTR CF'!F4/'QTR P&L'!F2,"") | G4: =IFERROR('QTR CF'!G4/'QTR P&L'!G2,"") | H4: =IFERROR('QTR CF'!H4/'QTR P&L'!H2,"") | I4: =IFERROR('QTR CF'!I4/'QTR P&L'!I2,"") | ... S4: =IFERROR('QTR CF'!S4/'QTR P&L'!S2,"") | T4: =S4 | U4: =S4 | V4: =S4 | W4: =S4 | X4: =S4 | Y4: =S4 | Z4: =S4 | AA4: =S4 | AB4: =S4 | AC4: =S4 | AD4: =S4 | AE4: =S4 | AF4: =S4 | AG4: =S4 | AH4: =S4 | AI4: =S4 | AJ4: =S4 | AK4: =S4
A5: (Benefit) Provision for Deferred Income Taxes | B5: ='QTR CF'!B5 | C5: ='QTR CF'!C5 | D5: ='QTR CF'!D5 | E5: ='QTR CF'!E5 | F5: ='QTR CF'!F5 | G5: ='QTR CF'!G5 | H5: ='QTR CF'!H5 | I5: ='QTR CF'!I5 | ... S5: ='QTR CF'!S5 | T5: 0 | U5: 0 | V5: 0 | W5: 0 | X5: 0 | Y5: 0 | Z5: 0 | AA5: 0 | AB5: 0 | AC5: 0 | AD5: 0 | AE5: 0 | AF5: 0 | AG5: 0 | AH5: 0 | AI5: 0 | AJ5: 0 | AK5: 0
A6: Gain (Loss) on Disposal of PP&E | B6: ='QTR CF'!B6 | C6: ='QTR CF'!C6 | D6: ='QTR CF'!D6 | E6: ='QTR CF'!E6 | F6: ='QTR CF'!F6 | G6: ='QTR CF'!G6 | H6: ='QTR CF'!H6 | I6: ='QTR CF'!I6 | ... S6: ='QTR CF'!S6 | T6: 0 | U6: 0 | V6: 0 | W6: 0 | X6: 0 | Y6: 0 | Z6: 0 | AA6: 0 | AB6: 0 | AC6: 0 | AD6: 0 | AE6: 0 | AF6: 0 | AG6: 0 | AH6: 0 | AI6: 0 | AJ6: 0 | AK6: 0
A7: Impairment of Intangibles | B7: ='QTR CF'!B7 | C7: ='QTR CF'!C7 | D7: ='QTR CF'!D7 | E7: ='QTR CF'!E7 | F7: ='QTR CF'!F7 | G7: ='QTR CF'!G7 | H7: ='QTR CF'!H7 | I7: ='QTR CF'!I7 | ... S7: ='QTR CF'!S7 | T7: 0 | U7: 0 | V7: 0 | W7: 0 | X7: 0 | Y7: 0 | Z7: 0 | AA7: 0 | AB7: 0 | AC7: 0 | AD7: 0 | AE7: 0 | AF7: 0 | AG7: 0 | AH7: 0 | AI7: 0 | AJ7: 0 | AK7: 0
A8: Accounts Receivable | B8: ='QTR CF'!B8 | C8: ='QTR CF'!C8 | D8: ='QTR CF'!D8 | E8: ='QTR CF'!E8 | F8: ='QTR CF'!F8 | G8: ='QTR CF'!G8 | H8: ='QTR CF'!H8 | I8: ='QTR CF'!I8 | ... S8: ='QTR CF'!S8 | T8: =-('QTR BS'!Q3-'QTR BS'!P3) | U8: =-('QTR BS'!R3-'QTR BS'!Q3) | V8: =-('QTR BS'!S3-'QTR BS'!R3) | W8: =-('QTR BS'!T3-'QTR BS'!S3) | X8: =-('QTR BS'!U3-'QTR BS'!T3) | Y8: =-('QTR BS'!V3-'QTR BS'!U3) | Z8: =-('QTR BS'!W3-'QTR BS'!V3) | AA8: =-('QTR BS'!X3-'QTR BS'!W3) | ... AK8: =-('QTR BS'!AH3-'QTR BS'!AG3)
A9: Inventories | B9: ='QTR CF'!B9 | C9: ='QTR CF'!C9 | D9: ='QTR CF'!D9 | E9: ='QTR CF'!E9 | F9: ='QTR CF'!F9 | G9: ='QTR CF'!G9 | H9: ='QTR CF'!H9 | I9: ='QTR CF'!I9 | ... S9: ='QTR CF'!S9 | T9: =-('QTR BS'!Q4-'QTR BS'!P4) | U9: =-('QTR BS'!R4-'QTR BS'!Q4) | V9: =-('QTR BS'!S4-'QTR BS'!R4) | W9: =-('QTR BS'!T4-'QTR BS'!S4) | X9: =-('QTR BS'!U4-'QTR BS'!T4) | Y9: =-('QTR BS'!V4-'QTR BS'!U4) | Z9: =-('QTR BS'!W4-'QTR BS'!V4) | AA9: =-('QTR BS'!X4-'QTR BS'!W4) | ... AK9: =-('QTR BS'!AH4-'QTR BS'!AG4)
A10: Accounts Payable | B10: ='QTR CF'!B10 | C10: ='QTR CF'!C10 | D10: ='QTR CF'!D10 | E10: ='QTR CF'!E10 | F10: ='QTR CF'!F10 | G10: ='QTR CF'!G10 | H10: ='QTR CF'!H10 | I10: ='QTR CF'!I10 | ... S10: ='QTR CF'!S10 | T10: =('QTR BS'!Q12-'QTR BS'!P12) | U10: =('QTR BS'!R12-'QTR BS'!Q12) | V10: =('QTR BS'!S12-'QTR BS'!R12) | W10: =('QTR BS'!T12-'QTR BS'!S12) | X10: =('QTR BS'!U12-'QTR BS'!T12) | Y10: =('QTR BS'!V12-'QTR BS'!U12) | Z10: =('QTR BS'!W12-'QTR BS'!V12) | AA10: =('QTR BS'!X12-'QTR BS'!W12) | ... AK10: =('QTR BS'!AH12-'QTR BS'!AG12)
A11: Net Change in Other Working Capital | B11: ='QTR CF'!B11 | C11: ='QTR CF'!C11 | D11: ='QTR CF'!D11 | E11: ='QTR CF'!E11 | F11: ='QTR CF'!F11 | G11: ='QTR CF'!G11 | H11: ='QTR CF'!H11 | I11: ='QTR CF'!I11 | ... S11: ='QTR CF'!S11 | T11: 0 | U11: 0 | V11: 0 | W11: 0 | X11: 0 | Y11: 0 | Z11: 0 | AA11: 0 | AB11: 0 | AC11: 0 | AD11: 0 | AE11: 0 | AF11: 0 | AG11: 0 | AH11: 0 | AI11: 0 | AJ11: 0 | AK11: 0
A12: Other Operating Items | B12: ='QTR CF'!B12 | C12: ='QTR CF'!C12 | D12: ='QTR CF'!D12 | E12: ='QTR CF'!E12 | F12: ='QTR CF'!F12 | G12: ='QTR CF'!G12 | H12: ='QTR CF'!H12 | I12: ='QTR CF'!I12 | ... S12: ='QTR CF'!S12 | T12: =-('QTR BS'!Q5-'QTR BS'!P5)-('QTR BS'!Q10-'QTR BS'!P10)+('QTR BS'!Q13-'QTR BS'!P13)+('QTR BS'!Q18-'QTR BS'!P18)-('QTR BS'!Q8-'QTR BS'!P8)-('QTR BS'!Q9-'QTR BS'!P9)+('QTR BS'!Q14-'QTR BS'!P14)+('QTR BS'!Q16-'QTR BS'!P16)+('QTR BS'!Q17-'QTR BS'!P17)+('QTR BS'!Q21-'QTR BS'!P21)+('QTR BS'!Q23-'QTR BS'!P23)+('QTR BS'!Q25-'QTR BS'!P25)+('QTR BS'!Q27-'QTR BS'!P27) | U12: =-('QTR BS'!R5-'QTR BS'!Q5)-('QTR BS'!R10-'QTR BS'!Q10)+('QTR BS'!R13-'QTR BS'!Q13)+('QTR BS'!R18-'QTR BS'!Q18)-('QTR BS'!R8-'QTR BS'!Q8)-('QTR BS'!R9-'QTR BS'!Q9)+('QTR BS'!R14-'QTR BS'!Q14)+('QTR BS'!R16-'QTR BS'!Q16)+('QTR BS'!R17-'QTR BS'!Q17)+('QTR BS'!R21-'QTR BS'!Q21)+('QTR BS'!R23-'QTR BS'!Q23)+('QTR BS'!R25-'QTR BS'!Q25)+('QTR BS'!R27-'QTR BS'!Q27) | V12: =-('QTR BS'!S5-'QTR BS'!R5)-('QTR BS'!S10-'QTR BS'!R10)+('QTR BS'!S13-'QTR BS'!R13)+('QTR BS'!S18-'QTR BS'!R18)-('QTR BS'!S8-'QTR BS'!R8)-('QTR BS'!S9-'QTR BS'!R9)+('QTR BS'!S14-'QTR BS'!R14)+('QTR BS'!S16-'QTR BS'!R16)+('QTR BS'!S17-'QTR BS'!R17)+('QTR BS'!S21-'QTR BS'!R21)+('QTR BS'!S23-'QTR BS'!R23)+('QTR BS'!S25-'QTR BS'!R25)+('QTR BS'!S27-'QTR BS'!R27) | W12: =-('QTR BS'!T5-'QTR BS'!S5)-('QTR BS'!T10-'QTR BS'!S10)+('QTR BS'!T13-'QTR BS'!S13)+('QTR BS'!T18-'QTR BS'!S18)-('QTR BS'!T8-'QTR BS'!S8)-('QTR BS'!T9-'QTR BS'!S9)+('QTR BS'!T14-'QTR BS'!S14)+('QTR BS'!T16-'QTR BS'!S16)+('QTR BS'!T17-'QTR BS'!S17)+('QTR BS'!T21-'QTR BS'!S21)+('QTR BS'!T23-'QTR BS'!S23)+('QTR BS'!T25-'QTR BS'!S25)+('QTR BS'!T27-'QTR BS'!S27) | X12: =-('QTR BS'!U5-'QTR BS'!T5)-('QTR BS'!U10-'QTR BS'!T10)+('QTR BS'!U13-'QTR BS'!T13)+('QTR BS'!U18-'QTR BS'!T18)-('QTR BS'!U8-'QTR BS'!T8)-('QTR BS'!U9-'QTR BS'!T9)+('QTR BS'!U14-'QTR BS'!T14)+('QTR BS'!U16-'QTR BS'!T16)+('QTR BS'!U17-'QTR BS'!T17)+('QTR BS'!U21-'QTR BS'!T21)+('QTR BS'!U23-'QTR BS'!T23)+('QTR BS'!U25-'QTR BS'!T25)+('QTR BS'!U27-'QTR BS'!T27) | Y12: =-('QTR BS'!V5-'QTR BS'!U5)-('QTR BS'!V10-'QTR BS'!U10)+('QTR BS'!V13-'QTR BS'!U13)+('QTR BS'!V18-'QTR BS'!U18)-('QTR BS'!V8-'QTR BS'!U8)-('QTR BS'!V9-'QTR BS'!U9)+('QTR BS'!V14-'QTR BS'!U14)+('QTR BS'!V16-'QTR BS'!U16)+('QTR BS'!V17-'QTR BS'!U17)+('QTR BS'!V21-'QTR BS'!U21)+('QTR BS'!V23-'QTR BS'!U23)+('QTR BS'!V25-'QTR BS'!U25)+('QTR BS'!V27-'QTR BS'!U27) | Z12: =-('QTR BS'!W5-'QTR BS'!V5)-('QTR BS'!W10-'QTR BS'!V10)+('QTR BS'!W13-'QTR BS'!V13)+('QTR BS'!W18-'QTR BS'!V18)-('QTR BS'!W8-'QTR BS'!V8)-('QTR BS'!W9-'QTR BS'!V9)+('QTR BS'!W14-'QTR BS'!V14)+('QTR BS'!W16-'QTR BS'!V16)+('QTR BS'!W17-'QTR BS'!V17)+('QTR BS'!W21-'QTR BS'!V21)+('QTR BS'!W23-'QTR BS'!V23)+('QTR BS'!W25-'QTR BS'!V25)+('QTR BS'!W27-'QTR BS'!V27) | AA12: =-('QTR BS'!X5-'QTR BS'!W5)-('QTR BS'!X10-'QTR BS'!W10)+('QTR BS'!X13-'QTR BS'!W13)+('QTR BS'!X18-'QTR BS'!W18)-('QTR BS'!X8-'QTR BS'!W8)-('QTR BS'!X9-'QTR BS'!W9)+('QTR BS'!X14-'QTR BS'!W14)+('QTR BS'!X16-'QTR BS'!W16)+('QTR BS'!X17-'QTR BS'!W17)+('QTR BS'!X21-'QTR BS'!W21)+('QTR BS'!X23-'QTR BS'!W23)+('QTR BS'!X25-'QTR BS'!W25)+('QTR BS'!X27-'QTR BS'!W27) | ... AK12: =-('QTR BS'!AH5-'QTR BS'!AG5)-('QTR BS'!AH10-'QTR BS'!AG10)+('QTR BS'!AH13-'QTR BS'!AG13)+('QTR BS'!AH18-'QTR BS'!AG18)-('QTR BS'!AH8-'QTR BS'!AG8)-('QTR BS'!AH9-'QTR BS'!AG9)+('QTR BS'!AH14-'QTR BS'!AG14)+('QTR BS'!AH16-'QTR BS'!AG16)+('QTR BS'!AH17-'QTR BS'!AG17)+('QTR BS'!AH21-'QTR BS'!AG21)+('QTR BS'!AH23-'QTR BS'!AG23)+('QTR BS'!AH25-'QTR BS'!AG25)+('QTR BS'!AH27-'QTR BS'!AG27)
A13: Purchase of PP&E — % of Revenue | B13: =IFERROR('QTR CF'!B14/'QTR P&L'!B2,"") | C13: =IFERROR('QTR CF'!C14/'QTR P&L'!C2,"") | D13: =IFERROR('QTR CF'!D14/'QTR P&L'!D2,"") | E13: =IFERROR('QTR CF'!E14/'QTR P&L'!E2,"") | F13: =IFERROR('QTR CF'!F14/'QTR P&L'!F2,"") | G13: =IFERROR('QTR CF'!G14/'QTR P&L'!G2,"") | H13: =IFERROR('QTR CF'!H14/'QTR P&L'!H2,"") | I13: =IFERROR('QTR CF'!I14/'QTR P&L'!I2,"") | ... S13: =IFERROR('QTR CF'!S14/'QTR P&L'!S2,"") | T13: =S13 | U13: =S13 | V13: =S13 | W13: =S13 | X13: =S13 | Y13: =S13 | Z13: =S13 | AA13: =S13 | AB13: =S13 | AC13: =S13 | AD13: =S13 | AE13: =S13 | AF13: =S13 | AG13: =S13 | AH13: =S13 | AI13: =S13 | AJ13: =S13 | AK13: =S13
A14: Proceeds from Sale of Assets | B14: ='QTR CF'!B15 | C14: ='QTR CF'!C15 | D14: ='QTR CF'!D15 | E14: ='QTR CF'!E15 | F14: ='QTR CF'!F15 | G14: ='QTR CF'!G15 | H14: ='QTR CF'!H15 | I14: ='QTR CF'!I15 | ... S14: ='QTR CF'!S15 | T14: 0 | U14: 0 | V14: 0 | W14: 0 | X14: 0 | Y14: 0 | Z14: 0 | AA14: 0 | AB14: 0 | AC14: 0 | AD14: 0 | AE14: 0 | AF14: 0 | AG14: 0 | AH14: 0 | AI14: 0 | AJ14: 0 | AK14: 0
A15: Acquisitions, Net of Cash Acquired | B15: ='QTR CF'!B16 | C15: ='QTR CF'!C16 | D15: ='QTR CF'!D16 | E15: ='QTR CF'!E16 | F15: ='QTR CF'!F16 | G15: ='QTR CF'!G16 | H15: ='QTR CF'!H16 | I15: ='QTR CF'!I16 | ... S15: ='QTR CF'!S16 | T15: 0 | U15: 0 | V15: 0 | W15: 0 | X15: 0 | Y15: 0 | Z15: 0 | AA15: 0 | AB15: 0 | AC15: 0 | AD15: 0 | AE15: 0 | AF15: 0 | AG15: 0 | AH15: 0 | AI15: 0 | AJ15: 0 | AK15: 0
A16: Net Change in Short-Term Investments | B16: ='QTR CF'!B17 | C16: ='QTR CF'!C17 | D16: ='QTR CF'!D17 | E16: ='QTR CF'!E17 | F16: ='QTR CF'!F17 | G16: ='QTR CF'!G17 | H16: ='QTR CF'!H17 | I16: ='QTR CF'!I17 | ... S16: ='QTR CF'!S17 | T16: 0 | U16: 0 | V16: 0 | W16: 0 | X16: 0 | Y16: 0 | Z16: 0 | AA16: 0 | AB16: 0 | AC16: 0 | AD16: 0 | AE16: 0 | AF16: 0 | AG16: 0 | AH16: 0 | AI16: 0 | AJ16: 0 | AK16: 0
A17: Other Investing Activities | B17: ='QTR CF'!B18 | C17: ='QTR CF'!C18 | D17: ='QTR CF'!D18 | E17: ='QTR CF'!E18 | F17: ='QTR CF'!F18 | G17: ='QTR CF'!G18 | H17: ='QTR CF'!H18 | I17: ='QTR CF'!I18 | ... S17: ='QTR CF'!S18 | T17: 0 | U17: 0 | V17: 0 | W17: 0 | X17: 0 | Y17: 0 | Z17: 0 | AA17: 0 | AB17: 0 | AC17: 0 | AD17: 0 | AE17: 0 | AF17: 0 | AG17: 0 | AH17: 0 | AI17: 0 | AJ17: 0 | AK17: 0
A18: Common Dividends — % of Net Income | B18: =IFERROR('QTR CF'!B20/'QTR P&L'!B12,"") | C18: =IFERROR('QTR CF'!C20/'QTR P&L'!C12,"") | D18: =IFERROR('QTR CF'!D20/'QTR P&L'!D12,"") | E18: =IFERROR('QTR CF'!E20/'QTR P&L'!E12,"") | F18: =IFERROR('QTR CF'!F20/'QTR P&L'!F12,"") | G18: =IFERROR('QTR CF'!G20/'QTR P&L'!G12,"") | H18: =IFERROR('QTR CF'!H20/'QTR P&L'!H12,"") | I18: =IFERROR('QTR CF'!I20/'QTR P&L'!I12,"") | ... S18: =IFERROR('QTR CF'!S20/'QTR P&L'!S12,"") | T18: =S18 | U18: =S18 | V18: =S18 | W18: =S18 | X18: =S18 | Y18: =S18 | Z18: =S18 | AA18: =S18 | AB18: =S18 | AC18: =S18 | AD18: =S18 | AE18: =S18 | AF18: =S18 | AG18: =S18 | AH18: =S18 | AI18: =S18 | AJ18: =S18 | AK18: =S18
A19: Proceeds from Short-Term Debt | B19: ='QTR CF'!B21 | C19: ='QTR CF'!C21 | D19: ='QTR CF'!D21 | E19: ='QTR CF'!E21 | F19: ='QTR CF'!F21 | G19: ='QTR CF'!G21 | H19: ='QTR CF'!H21 | I19: ='QTR CF'!I21 | ... S19: ='QTR CF'!S21 | T19: 0 | U19: 0 | V19: 0 | W19: 0 | X19: 0 | Y19: 0 | Z19: 0 | AA19: 0 | AB19: 0 | AC19: 0 | AD19: 0 | AE19: 0 | AF19: 0 | AG19: 0 | AH19: 0 | AI19: 0 | AJ19: 0 | AK19: 0
A20: Repayments of Short-Term Debt | B20: ='QTR CF'!B22 | C20: ='QTR CF'!C22 | D20: ='QTR CF'!D22 | E20: ='QTR CF'!E22 | F20: ='QTR CF'!F22 | G20: ='QTR CF'!G22 | H20: ='QTR CF'!H22 | I20: ='QTR CF'!I22 | ... S20: ='QTR CF'!S22 | T20: 0 | U20: 0 | V20: 0 | W20: 0 | X20: 0 | Y20: 0 | Z20: 0 | AA20: 0 | AB20: 0 | AC20: 0 | AD20: 0 | AE20: 0 | AF20: 0 | AG20: 0 | AH20: 0 | AI20: 0 | AJ20: 0 | AK20: 0
A21: Net Change in Other Short-Term Debt | B21: ='QTR CF'!B23 | C21: ='QTR CF'!C23 | D21: ='QTR CF'!D23 | E21: ='QTR CF'!E23 | F21: ='QTR CF'!F23 | G21: ='QTR CF'!G23 | H21: ='QTR CF'!H23 | I21: ='QTR CF'!I23 | ... S21: ='QTR CF'!S23 | T21: 0 | U21: 0 | V21: 0 | W21: 0 | X21: 0 | Y21: 0 | Z21: 0 | AA21: 0 | AB21: 0 | AC21: 0 | AD21: 0 | AE21: 0 | AF21: 0 | AG21: 0 | AH21: 0 | AI21: 0 | AJ21: 0 | AK21: 0
A22: Proceeds from Issuance of Long-Term Debt | B22: ='QTR CF'!B24 | C22: ='QTR CF'!C24 | D22: ='QTR CF'!D24 | E22: ='QTR CF'!E24 | F22: ='QTR CF'!F24 | G22: ='QTR CF'!G24 | H22: ='QTR CF'!H24 | I22: ='QTR CF'!I24 | ... S22: ='QTR CF'!S24 | T22: 0 | U22: 0 | V22: 0 | W22: 0 | X22: 0 | Y22: 0 | Z22: 0 | AA22: 0 | AB22: 0 | AC22: 0 | AD22: 0 | AE22: 0 | AF22: 0 | AG22: 0 | AH22: 0 | AI22: 0 | AJ22: 0 | AK22: 0
A23: Repayments of Long-Term Debt | B23: ='QTR CF'!B25 | C23: ='QTR CF'!C25 | D23: ='QTR CF'!D25 | E23: ='QTR CF'!E25 | F23: ='QTR CF'!F25 | G23: ='QTR CF'!G25 | H23: ='QTR CF'!H25 | I23: ='QTR CF'!I25 | ... S23: ='QTR CF'!S25 | T23: 0 | U23: 0 | V23: 0 | W23: 0 | X23: 0 | Y23: 0 | Z23: 0 | AA23: 0 | AB23: 0 | AC23: 0 | AD23: 0 | AE23: 0 | AF23: 0 | AG23: 0 | AH23: 0 | AI23: 0 | AJ23: 0 | AK23: 0
A24: Share Repurchases | B24: ='QTR CF'!B26 | C24: ='QTR CF'!C26 | D24: ='QTR CF'!D26 | E24: ='QTR CF'!E26 | F24: ='QTR CF'!F26 | G24: ='QTR CF'!G26 | H24: ='QTR CF'!H26 | I24: ='QTR CF'!I26 | ... S24: ='QTR CF'!S26 | T24: 0 | U24: 0 | V24: 0 | W24: 0 | X24: 0 | Y24: 0 | Z24: 0 | AA24: 0 | AB24: 0 | AC24: 0 | AD24: 0 | AE24: 0 | AF24: 0 | AG24: 0 | AH24: 0 | AI24: 0 | AJ24: 0 | AK24: 0
A25: Stock Options & Other Financing Activities | B25: ='QTR CF'!B27 | C25: ='QTR CF'!C27 | D25: ='QTR CF'!D27 | E25: ='QTR CF'!E27 | F25: ='QTR CF'!F27 | G25: ='QTR CF'!G27 | H25: ='QTR CF'!H27 | I25: ='QTR CF'!I27 | ... S25: ='QTR CF'!S27 | T25: 0 | U25: 0 | V25: 0 | W25: 0 | X25: 0 | Y25: 0 | Z25: 0 | AA25: 0 | AB25: 0 | AC25: 0 | AD25: 0 | AE25: 0 | AF25: 0 | AG25: 0 | AH25: 0 | AI25: 0 | AJ25: 0 | AK25: 0
A26: FX Effect on Cash | B26: ='QTR CF'!B29 | C26: ='QTR CF'!C29 | D26: ='QTR CF'!D29 | E26: ='QTR CF'!E29 | F26: ='QTR CF'!F29 | G26: ='QTR CF'!G29 | H26: ='QTR CF'!H29 | I26: ='QTR CF'!I29 | ... S26: ='QTR CF'!S29 | T26: =S26 | U26: =S26 | V26: =S26 | W26: =S26 | X26: =S26 | Y26: =S26 | Z26: =S26 | AA26: =S26 | AB26: =S26 | AC26: =S26 | AD26: =S26 | AE26: =S26 | AF26: =S26 | AG26: =S26 | AH26: =S26 | AI26: =S26 | AJ26: =S26 | AK26: =S26
