Workbook

Sheet ASSUMPTIONS
A1: Assumption | B1: Value | C1: Note
A2: Days in Quarter | B2: 91 | C2: Used by DSO/DIO/DPO ratios. Approximation; varies 89-92 by quarter.

Sheet ANNL P&L
B1: FY2017 | C1: FY2018 | D1: FY2019 | E1: FY2020 | F1: FY2021 | G1: FY2022 | H1: FY2023 | I1: FY2024 | J1: FY2025 | K1: FY2026E | L1: FY2027E | M1: FY2028E | N1: FY2029E | O1: FY2030E | P1: FY2031E
A2: Net Sales / Revenue | B2: 110855 | C2: 136819 | D2: 161857 | E2: 182527 | F2: 257637 | G2: 282836 | H2: 307394 | I2: 350018 | J2: 402836 | K2: ='QTR P&L'!AH2+'QTR P&L'!AI2+'QTR P&L'!AJ2+'QTR P&L'!AK2 | L2: ='QTR P&L'!AL2+'QTR P&L'!AM2+'QTR P&L'!AN2+'QTR P&L'!AO2 | M2: ='QTR P&L'!AP2+'QTR P&L'!AQ2+'QTR P&L'!AR2+'QTR P&L'!AS2 | N2: ='QTR P&L'!AT2+'QTR P&L'!AU2+'QTR P&L'!AV2+'QTR P&L'!AW2 | O2: ='QTR P&L'!AX2+'QTR P&L'!AY2+'QTR P&L'!AZ2+'QTR P&L'!BA2
A3: COGS | B3: -45583 | C3: -59549 | D3: -71896 | E3: -84732 | F3: -110939 | G3: -126203 | H3: -133332 | I3: -146306 | J3: -162535 | K3: ='QTR P&L'!AH3+'QTR P&L'!AI3+'QTR P&L'!AJ3+'QTR P&L'!AK3 | L3: ='QTR P&L'!AL3+'QTR P&L'!AM3+'QTR P&L'!AN3+'QTR P&L'!AO3 | M3: ='QTR P&L'!AP3+'QTR P&L'!AQ3+'QTR P&L'!AR3+'QTR P&L'!AS3 | N3: ='QTR P&L'!AT3+'QTR P&L'!AU3+'QTR P&L'!AV3+'QTR P&L'!AW3 | O3: ='QTR P&L'!AX3+'QTR P&L'!AY3+'QTR P&L'!AZ3+'QTR P&L'!BA3
A4: Gross Profit (Loss) | B4: =B2+B3 | C4: =C2+C3 | D4: =D2+D3 | E4: =E2+E3 | F4: =F2+F3 | G4: =G2+G3 | H4: =H2+H3 | I4: =I2+I3 | ... P4: =P2+P3
A5: Research and Development | B5: -16625 | C5: -21419 | D5: -26018 | E5: -27573 | F5: -31562 | G5: -39500 | H5: -45427 | I5: -49326 | J5: -61087 | K5: ='QTR P&L'!AH5+'QTR P&L'!AI5+'QTR P&L'!AJ5+'QTR P&L'!AK5 | L5: ='QTR P&L'!AL5+'QTR P&L'!AM5+'QTR P&L'!AN5+'QTR P&L'!AO5 | M5: ='QTR P&L'!AP5+'QTR P&L'!AQ5+'QTR P&L'!AR5+'QTR P&L'!AS5 | N5: ='QTR P&L'!AT5+'QTR P&L'!AU5+'QTR P&L'!AV5+'QTR P&L'!AW5 | O5: ='QTR P&L'!AX5+'QTR P&L'!AY5+'QTR P&L'!AZ5+'QTR P&L'!BA5
A6: Sales and Marketing | B6: -12893 | C6: -16333 | D6: -18464 | E6: -17946 | F6: -22912 | G6: -26567 | H6: -27917 | I6: -27808 | J6: -28693 | K6: ='QTR P&L'!AH6+'QTR P&L'!AI6+'QTR P&L'!AJ6+'QTR P&L'!AK6 | L6: ='QTR P&L'!AL6+'QTR P&L'!AM6+'QTR P&L'!AN6+'QTR P&L'!AO6 | M6: ='QTR P&L'!AP6+'QTR P&L'!AQ6+'QTR P&L'!AR6+'QTR P&L'!AS6 | N6: ='QTR P&L'!AT6+'QTR P&L'!AU6+'QTR P&L'!AV6+'QTR P&L'!AW6 | O6: ='QTR P&L'!AX6+'QTR P&L'!AY6+'QTR P&L'!AZ6+'QTR P&L'!BA6
A7: General and Administrative | B7: -6840 | C7: -6923 | D7: -9551 | E7: -11052 | F7: -13510 | G7: -15724 | H7: -16425 | I7: -14188 | J7: -21482 | K7: ='QTR P&L'!AH7+'QTR P&L'!AI7+'QTR P&L'!AJ7+'QTR P&L'!AK7 | L7: ='QTR P&L'!AL7+'QTR P&L'!AM7+'QTR P&L'!AN7+'QTR P&L'!AO7 | M7: ='QTR P&L'!AP7+'QTR P&L'!AQ7+'QTR P&L'!AR7+'QTR P&L'!AS7 | N7: ='QTR P&L'!AT7+'QTR P&L'!AU7+'QTR P&L'!AV7+'QTR P&L'!AW7 | O7: ='QTR P&L'!AX7+'QTR P&L'!AY7+'QTR P&L'!AZ7+'QTR P&L'!BA7
A8: Litigation and Regulatory Charges | B8: -2736 | C8: -5071 | D8: -1697 | E8: 0 | F8: 0 | G8: 0 | H8: 0 | I8: 0 | J8: 0 | K8: ='QTR P&L'!AH8+'QTR P&L'!AI8+'QTR P&L'!AJ8+'QTR P&L'!AK8 | L8: ='QTR P&L'!AL8+'QTR P&L'!AM8+'QTR P&L'!AN8+'QTR P&L'!AO8 | M8: ='QTR P&L'!AP8+'QTR P&L'!AQ8+'QTR P&L'!AR8+'QTR P&L'!AS8 | N8: ='QTR P&L'!AT8+'QTR P&L'!AU8+'QTR P&L'!AV8+'QTR P&L'!AW8 | O8: ='QTR P&L'!AX8+'QTR P&L'!AY8+'QTR P&L'!AZ8+'QTR P&L'!BA8
A9: Income (Loss) from Operations | B9: =B4+SUM(B5:B8) | C9: =C4+SUM(C5:C8) | D9: =D4+SUM(D5:D8) | E9: =E4+SUM(E5:E8) | F9: =F4+SUM(F5:F8) | G9: =G4+SUM(G5:G8) | H9: =H4+SUM(H5:H8) | I9: =I4+SUM(I5:I8) | ... P9: =P4+SUM(P5:P8)
A10: Other Income (Expense) | B10: 1015 | C10: 7389 | D10: 5394 | E10: 6858 | F10: 12020 | G10: -3514 | H10: 1424 | I10: 7425 | J10: 29787 | K10: ='QTR P&L'!AH10+'QTR P&L'!AI10+'QTR P&L'!AJ10+'QTR P&L'!AK10 | L10: ='QTR P&L'!AL10+'QTR P&L'!AM10+'QTR P&L'!AN10+'QTR P&L'!AO10 | M10: ='QTR P&L'!AP10+'QTR P&L'!AQ10+'QTR P&L'!AR10+'QTR P&L'!AS10 | N10: ='QTR P&L'!AT10+'QTR P&L'!AU10+'QTR P&L'!AV10+'QTR P&L'!AW10 | O10: ='QTR P&L'!AX10+'QTR P&L'!AY10+'QTR P&L'!AZ10+'QTR P&L'!BA10
A11: Pre-Tax Income (Loss) | B11: =B9+B10 | C11: =C9+C10 | D11: =D9+D10 | E11: =E9+E10 | F11: =F9+F10 | G11: =G9+G10 | H11: =H9+H10 | I11: =I9+I10 | ... P11: =P9+P10
A12: Income Tax (Expense) Benefit | B12: -14531 | C12: -4177 | D12: -5282 | E12: -7813 | F12: -14701 | G12: -11356 | H12: -11922 | I12: -19697 | J12: -26656 | K12: ='QTR P&L'!AH12+'QTR P&L'!AI12+'QTR P&L'!AJ12+'QTR P&L'!AK12 | L12: ='QTR P&L'!AL12+'QTR P&L'!AM12+'QTR P&L'!AN12+'QTR P&L'!AO12 | M12: ='QTR P&L'!AP12+'QTR P&L'!AQ12+'QTR P&L'!AR12+'QTR P&L'!AS12 | N12: ='QTR P&L'!AT12+'QTR P&L'!AU12+'QTR P&L'!AV12+'QTR P&L'!AW12 | O12: ='QTR P&L'!AX12+'QTR P&L'!AY12+'QTR P&L'!AZ12+'QTR P&L'!BA12
A13: Net Income (Loss) | B13: =B11+B12 | C13: =C11+C12 | D13: =D11+D12 | E13: =E11+E12 | F13: =F11+F12 | G13: =G11+G12 | H13: =H11+H12 | I13: =I11+I12 | ... P13: =P11+P12
A14: Basic Earnings (Loss) per Share | B14: 18.27 | C14: 44.22 | D14: 49.59 | E14: 59.15 | F14: 113.88 | G14: 4.59 | H14: 5.84 | I14: 8.13 | J14: 10.91
A15: Diluted Earnings (Loss) per Share | B15: 18 | C15: 43.7 | D15: 49.16 | E15: 58.61 | F15: 112.2 | G15: 4.56 | H15: 5.8 | I15: 8.04 | J15: 10.81

Sheet BALANCE SHEET
B1: FY2018 | C1: FY2019 | D1: FY2020 | E1: FY2021 | F1: FY2022 | G1: FY2023 | H1: FY2024 | I1: FY2025 | J1: FY2026E | K1: FY2027E | L1: FY2028E | M1: FY2029E | N1: FY2030E | O1: FY2031E
A2: Cash & Cash Equivalents | B2: 16701 | C2: 18498 | D2: 26465 | E2: 20945 | F2: 21879 | G2: 24048 | H2: 23466 | I2: 30708 | J2: ='QTR BS'!AH2 | K2: ='QTR BS'!AL2 | L2: ='QTR BS'!AP2 | M2: ='QTR BS'!AT2 | N2: ='QTR BS'!AX2
A3: Short-Term Investments | B3: 92439 | C3: 101177 | D3: 110229 | E3: 118704 | F3: 91883 | G3: 86868 | H3: 72191 | I3: 96135 | J3: ='QTR BS'!AH3 | K3: ='QTR BS'!AL3 | L3: ='QTR BS'!AP3 | M3: ='QTR BS'!AT3 | N3: ='QTR BS'!AX3
A4: Accounts Receivable | B4: 20838 | C4: 25326 | D4: 30930 | E4: 39304 | F4: 40258 | G4: 47964 | H4: 52340 | I4: 62886 | J4: ='QTR BS'!AH4 | K4: ='QTR BS'!AL4 | L4: ='QTR BS'!AP4 | M4: ='QTR BS'!AT4 | N4: ='QTR BS'!AX4
A5: Note Receivable - Current | B5: 355 | C5: 2166 | D5: 454 | E5: 966 | F5: 0 | G5: 0 | H5: 0 | I5: 0 | J5: ='QTR BS'!AH5 | K5: ='QTR BS'!AL5 | L5: ='QTR BS'!AP5 | M5: ='QTR BS'!AT5 | N5: ='QTR BS'!AX5
A6: Inventories | B6: 1107 | C6: 999 | D6: 728 | E6: 1170 | F6: 2670 | G6: 0 | H6: 0 | I6: 0 | J6: ='QTR BS'!AH6 | K6: ='QTR BS'!AL6 | L6: ='QTR BS'!AP6 | M6: ='QTR BS'!AT6 | N6: ='QTR BS'!AX6
A7: Other Current Assets | B7: 4236 | C7: 4412 | D7: 5490 | E7: 7054 | F7: 8105 | G7: 12650 | H7: 15714 | I7: 16309 | J7: ='QTR BS'!AH7 | K7: ='QTR BS'!AL7 | L7: ='QTR BS'!AP7 | M7: ='QTR BS'!AT7 | N7: ='QTR BS'!AX7
A8: Total Current Assets | B8: =SUM(B2:B7) | C8: =SUM(C2:C7) | D8: =SUM(D2:D7) | E8: =SUM(E2:E7) | F8: =SUM(F2:F7) | G8: =SUM(G2:G7) | H8: =SUM(H2:H7) | I8: =SUM(I2:I7) | ... O8: =SUM(O2:O7)
A9: Long-Term Investments | B9: 13859 | C9: 13078 | D9: 20703 | E9: 29549 | F9: 30492 | G9: 31008 | H9: 37982 | I9: 68687 | J9: ='QTR BS'!AH9 | K9: ='QTR BS'!AL9 | L9: ='QTR BS'!AP9 | M9: ='QTR BS'!AT9 | N9: ='QTR BS'!AX9
A10: Deferred Tax Assets | B10: 737 | C10: 721 | D10: 1084 | E10: 1284 | F10: 5261 | G10: 12169 | H10: 17180 | I10: 9113 | J10: ='QTR BS'!AH10 | K10: ='QTR BS'!AL10 | L10: ='QTR BS'!AP10 | M10: ='QTR BS'!AT10 | N10: ='QTR BS'!AX10
A11: Net PP&E | B11: 59719 | C11: 73646 | D11: 84749 | E11: 97599 | F11: 112668 | G11: 134345 | H11: 171036 | I11: 246597 | J11: ='QTR BS'!AH11 | K11: ='QTR BS'!AL11 | L11: ='QTR BS'!AP11 | M11: ='QTR BS'!AT11 | N11: ='QTR BS'!AX11
A12: ROU Assets - Operating - Non-Current | B12: 0 | C12: 10941 | D12: 12211 | E12: 12959 | F12: 14381 | G12: 14091 | H12: 13588 | I12: 15221 | J12: ='QTR BS'!AH12 | K12: ='QTR BS'!AL12 | L12: ='QTR BS'!AP12 | M12: ='QTR BS'!AT12 | N12: ='QTR BS'!AX12
A13: Intangible Assets | B13: 2220 | C13: 1979 | D13: 1445 | E13: 1417 | F13: 2084 | G13: 0 | H13: 0 | I13: 0 | J13: ='QTR BS'!AH13 | K13: ='QTR BS'!AL13 | L13: ='QTR BS'!AP13 | M13: ='QTR BS'!AT13 | N13: ='QTR BS'!AX13
A14: Goodwill | B14: 17888 | C14: 20624 | D14: 21175 | E14: 22956 | F14: 28960 | G14: 29198 | H14: 31885 | I14: 33380 | J14: ='QTR BS'!AH14 | K14: ='QTR BS'!AL14 | L14: ='QTR BS'!AP14 | M14: ='QTR BS'!AT14 | N14: ='QTR BS'!AX14
A15: Other Non-Current Assets | B15: 2693 | C15: 2342 | D15: 3953 | E15: 5361 | F15: 6623 | G15: 10051 | H15: 14874 | I15: 16245 | J15: ='QTR BS'!AH15 | K15: ='QTR BS'!AL15 | L15: ='QTR BS'!AP15 | M15: ='QTR BS'!AT15 | N15: ='QTR BS'!AX15
A16: Total Assets | B16: =B8+SUM(B9:B15) | C16: =C8+SUM(C9:C15) | D16: =D8+SUM(D9:D15) | E16: =E8+SUM(E9:E15) | F16: =F8+SUM(F9:F15) | G16: =G8+SUM(G9:G15) | H16: =H8+SUM(H9:H15) | I16: =I8+SUM(I9:I15) | ... O16: =O8+SUM(O9:O15)
A17: Accounts Payable | B17: 4378 | C17: 5561 | D17: 5589 | E17: 6037 | F17: 5128 | G17: 7493 | H17: 7987 | I17: 12200 | J17: ='QTR BS'!AH17 | K17: ='QTR BS'!AL17 | L17: ='QTR BS'!AP17 | M17: ='QTR BS'!AT17 | N17: ='QTR BS'!AX17
A18: Accrued Compensation | B18: 6839 | C18: 8495 | D18: 11086 | E18: 13889 | F18: 14028 | G18: 15140 | H18: 15069 | I18: 17546 | J18: ='QTR BS'!AH18 | K18: ='QTR BS'!AL18 | L18: ='QTR BS'!AP18 | M18: ='QTR BS'!AT18 | N18: ='QTR BS'!AX18
A19: Accrued Expenses | B19: 16958 | C19: 23067 | D19: 28631 | E19: 31236 | F19: 37866 | G19: 46168 | H19: 51228 | I19: 55557 | J19: ='QTR BS'!AH19 | K19: ='QTR BS'!AL19 | L19: ='QTR BS'!AP19 | M19: ='QTR BS'!AT19 | N19: ='QTR BS'!AX19
A20: Accrued Revenue Share | B20: 4592 | C20: 5916 | D20: 7500 | E20: 8996 | F20: 8370 | G20: 8876 | H20: 9802 | I20: 10864 | J20: ='QTR BS'!AH20 | K20: ='QTR BS'!AL20 | L20: ='QTR BS'!AP20 | M20: ='QTR BS'!AT20 | N20: ='QTR BS'!AX20
A21: Deferred Revenue - Current | B21: 1784 | C21: 1908 | D21: 2543 | E21: 3288 | F21: 3908 | G21: 4137 | H21: 5036 | I21: 6578 | J21: ='QTR BS'!AH21 | K21: ='QTR BS'!AL21 | L21: ='QTR BS'!AP21 | M21: ='QTR BS'!AT21 | N21: ='QTR BS'!AX21
A22: Income Taxes Payable | B22: 69 | C22: 274 | D22: 1485 | E22: 808 | F22: 0 | G22: 0 | H22: 0 | I22: 0 | J22: ='QTR BS'!AH22 | K22: ='QTR BS'!AL22 | L22: ='QTR BS'!AP22 | M22: ='QTR BS'!AT22 | N22: ='QTR BS'!AX22
A23: Total Current Liabilities | B23: =SUM(B17:B22) | C23: =SUM(C17:C22) | D23: =SUM(D17:D22) | E23: =SUM(E17:E22) | F23: =SUM(F17:F22) | G23: =SUM(G17:G22) | H23: =SUM(H17:H22) | I23: =SUM(I17:I22) | ... O23: =SUM(O17:O22)
A24: Long-Term Debt | B24: 15339 | C24: 14439 | D24: 22781 | E24: 23993 | F24: 23959 | G24: 21727 | H24: 19665 | I24: 56078 | J24: ='QTR BS'!AH24 | K24: ='QTR BS'!AL24 | L24: ='QTR BS'!AP24 | M24: ='QTR BS'!AT24 | N24: ='QTR BS'!AX24
A25: Deferred Revenue - Non-Current | B25: 396 | C25: 358 | D25: 481 | E25: 535 | F25: 599 | G25: 911 | H25: 0 | I25: 0 | J25: ='QTR BS'!AH25 | K25: ='QTR BS'!AL25 | L25: ='QTR BS'!AP25 | M25: ='QTR BS'!AT25 | N25: ='QTR BS'!AX25
A26: Deferred Tax Liability | B26: 1264 | C26: 1701 | D26: 3561 | E26: 5257 | F26: 514 | G26: 485 | H26: 0 | I26: 0 | J26: ='QTR BS'!AH26 | K26: ='QTR BS'!AL26 | L26: ='QTR BS'!AP26 | M26: ='QTR BS'!AT26 | N26: ='QTR BS'!AX26
A27: Lease Liability - Operating - Non-Current | B27: 0 | C27: 10214 | D27: 11146 | E27: 11389 | F27: 12501 | G27: 12460 | H27: 11691 | I27: 12744 | J27: ='QTR BS'!AH27 | K27: ='QTR BS'!AL27 | L27: ='QTR BS'!AP27 | M27: ='QTR BS'!AT27 | N27: ='QTR BS'!AX27
A28: Other Non-Current Liabilities | B28: 3545 | C28: 2534 | D28: 2269 | E28: 2205 | F28: 2247 | G28: 1616 | H28: 4694 | I28: 8449 | J28: ='QTR BS'!AH28 | K28: ='QTR BS'!AL28 | L28: ='QTR BS'!AP28 | M28: ='QTR BS'!AT28 | N28: ='QTR BS'!AX28
A29: Total Liabilities | B29: =B23+SUM(B24:B28) | C29: =C23+SUM(C24:C28) | D29: =D23+SUM(D24:D28) | E29: =E23+SUM(E24:E28) | F29: =F23+SUM(F24:F28) | G29: =G23+SUM(G24:G28) | H29: =H23+SUM(H24:H28) | I29: =I23+SUM(I24:I28) | ... O29: =O23+SUM(O24:O28)
A30: Convertible Preferred Stock | B30: 0 | C30: 0 | D30: 0 | E30: 0 | F30: 0 | G30: 0 | H30: 0 | I30: 0 | J30: ='QTR BS'!AH30 | K30: ='QTR BS'!AL30 | L30: ='QTR BS'!AP30 | M30: ='QTR BS'!AT30 | N30: ='QTR BS'!AX30
A31: Common Stock and Additional Paid-in Capital | B31: 45049 | C31: 50552 | D31: 58510 | E31: 61774 | F31: 68184 | G31: 76534 | H31: 84800 | I31: 93126 | J31: ='QTR BS'!AH31 | K31: ='QTR BS'!AL31 | L31: ='QTR BS'!AP31 | M31: ='QTR BS'!AT31 | N31: ='QTR BS'!AX31
A32: Accumulated Other Comprehensive Income (Loss) | B32: -2306 | C32: -1232 | D32: 633 | E32: -1623 | F32: -7603 | G32: -4402 | H32: -4800 | I32: -1916 | J32: ='QTR BS'!AH32 | K32: ='QTR BS'!AL32 | L32: ='QTR BS'!AP32 | M32: ='QTR BS'!AT32 | N32: ='QTR BS'!AX32
A33: Retained Earnings (Accumulated Deficit) | B33: 134885 | C33: 152122 | D33: 163401 | E33: 191484 | F33: 195563 | G33: 211247 | H33: 245084 | I33: 324055 | J33: ='QTR BS'!AH33 | K33: ='QTR BS'!AL33 | L33: ='QTR BS'!AP33 | M33: ='QTR BS'!AT33 | N33: ='QTR BS'!AX33
A34: Total Stockholders' Equity | B34: =SUM(B30:B33) | C34: =SUM(C30:C33) | D34: =SUM(D30:D33) | E34: =SUM(E30:E33) | F34: =SUM(F30:F33) | G34: =SUM(G30:G33) | H34: =SUM(H30:H33) | I34: =SUM(I30:I33) | ... O34: =SUM(O30:O33)
A35: Total Liabilities, Mezzanine & Stockholders' Equity | B35: =B29+B34 | C35: =C29+C34 | D35: =D29+D34 | E35: =E29+E34 | F35: =F29+F34 | G35: =G29+G34 | H35: =H29+H34 | I35: =I29+I34 | ... O35: =O29+O34

Sheet CASH FLOW
B1: FY2017 | C1: FY2018 | D1: FY2019 | E1: FY2020 | F1: FY2021 | G1: FY2022 | H1: FY2023 | I1: FY2024 | J1: FY2025 | K1: FY2026E | L1: FY2027E | M1: FY2028E | N1: FY2029E | O1: FY2030E | P1: FY2031E
A2: Net Income (Loss) | B2: 12662 | C2: 30736 | D2: 34343 | E2: 40269 | F2: 76033 | G2: 59972 | H2: 73795 | I2: 100118 | J2: 132170 | K2: ='QTR CF'!AH2+'QTR CF'!AI2+'QTR CF'!AJ2+'QTR CF'!AK2 | L2: ='QTR CF'!AL2+'QTR CF'!AM2+'QTR CF'!AN2+'QTR CF'!AO2 | M2: ='QTR CF'!AP2+'QTR CF'!AQ2+'QTR CF'!AR2+'QTR CF'!AS2 | N2: ='QTR CF'!AT2+'QTR CF'!AU2+'QTR CF'!AV2+'QTR CF'!AW2 | O2: ='QTR CF'!AX2+'QTR CF'!AY2+'QTR CF'!AZ2+'QTR CF'!BA2
A3: Depreciation and Impairment of PP&E | B3: 6103 | C3: 8164 | D3: 10856 | E3: 12905 | F3: 11555 | G3: 15287 | H3: 0 | I3: 0 | J3: 0 | K3: ='QTR CF'!AH3+'QTR CF'!AI3+'QTR CF'!AJ3+'QTR CF'!AK3 | L3: ='QTR CF'!AL3+'QTR CF'!AM3+'QTR CF'!AN3+'QTR CF'!AO3 | M3: ='QTR CF'!AP3+'QTR CF'!AQ3+'QTR CF'!AR3+'QTR CF'!AS3 | N3: ='QTR CF'!AT3+'QTR CF'!AU3+'QTR CF'!AV3+'QTR CF'!AW3 | O3: ='QTR CF'!AX3+'QTR CF'!AY3+'QTR CF'!AZ3+'QTR CF'!BA3
A4: Amortization and Impairment of Intangibles | B4: 812 | C4: 871 | D4: 925 | E4: 792 | F4: 886 | G4: 641 | H4: 0 | I4: 0 | J4: 0 | K4: ='QTR CF'!AH4+'QTR CF'!AI4+'QTR CF'!AJ4+'QTR CF'!AK4 | L4: ='QTR CF'!AL4+'QTR CF'!AM4+'QTR CF'!AN4+'QTR CF'!AO4 | M4: ='QTR CF'!AP4+'QTR CF'!AQ4+'QTR CF'!AR4+'QTR CF'!AS4 | N4: ='QTR CF'!AT4+'QTR CF'!AU4+'QTR CF'!AV4+'QTR CF'!AW4 | O4: ='QTR CF'!AX4+'QTR CF'!AY4+'QTR CF'!AZ4+'QTR CF'!BA4
A5: Depreciation | B5: 0 | C5: 0 | D5: 0 | E5: 0 | F5: 0 | G5: 0 | H5: 11946 | I5: 15311 | J5: 21136 | K5: ='QTR CF'!AH5+'QTR CF'!AI5+'QTR CF'!AJ5+'QTR CF'!AK5 | L5: ='QTR CF'!AL5+'QTR CF'!AM5+'QTR CF'!AN5+'QTR CF'!AO5 | M5: ='QTR CF'!AP5+'QTR CF'!AQ5+'QTR CF'!AR5+'QTR CF'!AS5 | N5: ='QTR CF'!AT5+'QTR CF'!AU5+'QTR CF'!AV5+'QTR CF'!AW5 | O5: ='QTR CF'!AX5+'QTR CF'!AY5+'QTR CF'!AZ5+'QTR CF'!BA5
A6: Stock-Based Compensation | B6: 7679 | C6: 9353 | D6: 10794 | E6: 12991 | F6: 15376 | G6: 19362 | H6: 22460 | I6: 22785 | J6: 24953 | K6: ='QTR CF'!AH6+'QTR CF'!AI6+'QTR CF'!AJ6+'QTR CF'!AK6 | L6: ='QTR CF'!AL6+'QTR CF'!AM6+'QTR CF'!AN6+'QTR CF'!AO6 | M6: ='QTR CF'!AP6+'QTR CF'!AQ6+'QTR CF'!AR6+'QTR CF'!AS6 | N6: ='QTR CF'!AT6+'QTR CF'!AU6+'QTR CF'!AV6+'QTR CF'!AW6 | O6: ='QTR CF'!AX6+'QTR CF'!AY6+'QTR CF'!AZ6+'QTR CF'!BA6
A7: (Benefit) Provision for Deferred Income Taxes | B7: 258 | C7: 778 | D7: 173 | E7: 1390 | F7: 1808 | G7: -8081 | H7: -7763 | I7: -5257 | J7: 8348 | K7: ='QTR CF'!AH7+'QTR CF'!AI7+'QTR CF'!AJ7+'QTR CF'!AK7 | L7: ='QTR CF'!AL7+'QTR CF'!AM7+'QTR CF'!AN7+'QTR CF'!AO7 | M7: ='QTR CF'!AP7+'QTR CF'!AQ7+'QTR CF'!AR7+'QTR CF'!AS7 | N7: ='QTR CF'!AT7+'QTR CF'!AU7+'QTR CF'!AV7+'QTR CF'!AW7 | O7: ='QTR CF'!AX7+'QTR CF'!AY7+'QTR CF'!AZ7+'QTR CF'!BA7
A8: Loss (Gain) on Equity and Debt Securities, Net | B8: 37 | C8: -6650 | D8: -2798 | E8: -6317 | F8: -12270 | G8: 5519 | H8: 823 | I8: -2671 | J8: -24620 | K8: ='QTR CF'!AH8+'QTR CF'!AI8+'QTR CF'!AJ8+'QTR CF'!AK8 | L8: ='QTR CF'!AL8+'QTR CF'!AM8+'QTR CF'!AN8+'QTR CF'!AO8 | M8: ='QTR CF'!AP8+'QTR CF'!AQ8+'QTR CF'!AR8+'QTR CF'!AS8 | N8: ='QTR CF'!AT8+'QTR CF'!AU8+'QTR CF'!AV8+'QTR CF'!AW8 | O8: ='QTR CF'!AX8+'QTR CF'!AY8+'QTR CF'!AZ8+'QTR CF'!BA8
A9: Other Operating Items | B9: -1870 | C9: -1396 | D9: -1213 | E9: -63 | F9: -2059 | G9: -4016 | H9: 2187 | I9: 2022 | J9: -2434 | K9: ='QTR CF'!AH9+'QTR CF'!AI9+'QTR CF'!AJ9+'QTR CF'!AK9 | L9: ='QTR CF'!AL9+'QTR CF'!AM9+'QTR CF'!AN9+'QTR CF'!AO9 | M9: ='QTR CF'!AP9+'QTR CF'!AQ9+'QTR CF'!AR9+'QTR CF'!AS9 | N9: ='QTR CF'!AT9+'QTR CF'!AU9+'QTR CF'!AV9+'QTR CF'!AW9 | O9: ='QTR CF'!AX9+'QTR CF'!AY9+'QTR CF'!AZ9+'QTR CF'!BA9
A10: Accounts Receivable | B10: -3768 | C10: -2169 | D10: -4340 | E10: -6524 | F10: -9095 | G10: -2317 | H10: -7833 | I10: -5891 | J10: -8779 | K10: ='QTR CF'!AH10+'QTR CF'!AI10+'QTR CF'!AJ10+'QTR CF'!AK10 | L10: ='QTR CF'!AL10+'QTR CF'!AM10+'QTR CF'!AN10+'QTR CF'!AO10 | M10: ='QTR CF'!AP10+'QTR CF'!AQ10+'QTR CF'!AR10+'QTR CF'!AS10 | N10: ='QTR CF'!AT10+'QTR CF'!AU10+'QTR CF'!AV10+'QTR CF'!AW10 | O10: ='QTR CF'!AX10+'QTR CF'!AY10+'QTR CF'!AZ10+'QTR CF'!BA10
A11: Change in Income Taxes | B11: 8211 | C11: -2251 | D11: -3128 | E11: 1209 | F11: -625 | G11: 584 | H11: 523 | I11: -2418 | J11: -3226 | K11: ='QTR CF'!AH11+'QTR CF'!AI11+'QTR CF'!AJ11+'QTR CF'!AK11 | L11: ='QTR CF'!AL11+'QTR CF'!AM11+'QTR CF'!AN11+'QTR CF'!AO11 | M11: ='QTR CF'!AP11+'QTR CF'!AQ11+'QTR CF'!AR11+'QTR CF'!AS11 | N11: ='QTR CF'!AT11+'QTR CF'!AU11+'QTR CF'!AV11+'QTR CF'!AW11 | O11: ='QTR CF'!AX11+'QTR CF'!AY11+'QTR CF'!AZ11+'QTR CF'!BA11
A12: Accounts Payable | B12: 731 | C12: 1067 | D12: 428 | E12: 694 | F12: 283 | G12: 707 | H12: 664 | I12: 359 | J12: 907 | K12: ='QTR CF'!AH12+'QTR CF'!AI12+'QTR CF'!AJ12+'QTR CF'!AK12 | L12: ='QTR CF'!AL12+'QTR CF'!AM12+'QTR CF'!AN12+'QTR CF'!AO12 | M12: ='QTR CF'!AP12+'QTR CF'!AQ12+'QTR CF'!AR12+'QTR CF'!AS12 | N12: ='QTR CF'!AT12+'QTR CF'!AU12+'QTR CF'!AV12+'QTR CF'!AW12 | O12: ='QTR CF'!AX12+'QTR CF'!AY12+'QTR CF'!AZ12+'QTR CF'!BA12
A13: Accrued Expenses | B13: 4891 | C13: 8614 | D13: 7170 | E13: 5504 | F13: 7304 | G13: 3915 | H13: 3937 | I13: -1161 | J13: 12939 | K13: ='QTR CF'!AH13+'QTR CF'!AI13+'QTR CF'!AJ13+'QTR CF'!AK13 | L13: ='QTR CF'!AL13+'QTR CF'!AM13+'QTR CF'!AN13+'QTR CF'!AO13 | M13: ='QTR CF'!AP13+'QTR CF'!AQ13+'QTR CF'!AR13+'QTR CF'!AS13 | N13: ='QTR CF'!AT13+'QTR CF'!AU13+'QTR CF'!AV13+'QTR CF'!AW13 | O13: ='QTR CF'!AX13+'QTR CF'!AY13+'QTR CF'!AZ13+'QTR CF'!BA13
... A15: Deferred Revenue | B15: 390 | C15: 371 | D15: 37 | E15: 635 | F15: 774 | G15: 367 | H15: 525 | I15: 1043 | J15: 2420 | K15: ='QTR CF'!AH15+'QTR CF'!AI15+'QTR CF'!AJ15+'QTR CF'!AK15 | L15: ='QTR CF'!AL15+'QTR CF'!AM15+'QTR CF'!AN15+'QTR CF'!AO15 | M15: ='QTR CF'!AP15+'QTR CF'!AQ15+'QTR CF'!AR15+'QTR CF'!AS15 | N15: ='QTR CF'!AT15+'QTR CF'!AU15+'QTR CF'!AV15+'QTR CF'!AW15 | O15: ='QTR CF'!AX15+'QTR CF'!AY15+'QTR CF'!AZ15+'QTR CF'!BA15
A16: Cash Flow from Operations | B16: =SUM(B2:B15) | C16: =SUM(C2:C15) | D16: =SUM(D2:D15) | E16: =SUM(E2:E15) | F16: =SUM(F2:F15) | G16: =SUM(G2:G15) | H16: =SUM(H2:H15) | I16: =SUM(I2:I15) | ... P16: =SUM(P2:P15)
A17: Purchase of PP&E | B17: -13184 | C17: -25139 | D17: -23548 | E17: -22281 | F17: -24640 | G17: -31485 | H17: -32251 | I17: -52535 | J17: -91447 | K17: ='QTR CF'!AH17+'QTR CF'!AI17+'QTR CF'!AJ17+'QTR CF'!AK17 | L17: ='QTR CF'!AL17+'QTR CF'!AM17+'QTR CF'!AN17+'QTR CF'!AO17 | M17: ='QTR CF'!AP17+'QTR CF'!AQ17+'QTR CF'!AR17+'QTR CF'!AS17 | N17: ='QTR CF'!AT17+'QTR CF'!AU17+'QTR CF'!AV17+'QTR CF'!AW17 | O17: ='QTR CF'!AX17+'QTR CF'!AY17+'QTR CF'!AZ17+'QTR CF'!BA17
A18: Net Change in Short-Term Investments | B18: -18236 | C18: -1651 | D18: -2490 | E18: -3670 | F18: -6902 | G18: 18948 | H18: 8814 | I18: 16749 | J18: -20533 | K18: ='QTR CF'!AH19+'QTR CF'!AI19+'QTR CF'!AJ19+'QTR CF'!AK19 | L18: ='QTR CF'!AL19+'QTR CF'!AM19+'QTR CF'!AN19+'QTR CF'!AO19 | M18: ='QTR CF'!AP19+'QTR CF'!AQ19+'QTR CF'!AR19+'QTR CF'!AS19 | N18: ='QTR CF'!AT19+'QTR CF'!AU19+'QTR CF'!AV19+'QTR CF'!AW19 | O18: ='QTR CF'!AX19+'QTR CF'!AY19+'QTR CF'!AZ19+'QTR CF'!BA19
A19: Net Change in Long-Term Investments | B19: -1212 | C19: -321 | D19: -1527 | E19: -6152 | F19: -1904 | G19: -2381 | H19: -2080 | I19: -4152 | J19: -4349 | K19: ='QTR CF'!AH20+'QTR CF'!AI20+'QTR CF'!AJ20+'QTR CF'!AK20 | L19: ='QTR CF'!AL20+'QTR CF'!AM20+'QTR CF'!AN20+'QTR CF'!AO20 | M19: ='QTR CF'!AP20+'QTR CF'!AQ20+'QTR CF'!AR20+'QTR CF'!AS20 | N19: ='QTR CF'!AT20+'QTR CF'!AU20+'QTR CF'!AV20+'QTR CF'!AW20 | O19: ='QTR CF'!AX20+'QTR CF'!AY20+'QTR CF'!AZ20+'QTR CF'!BA20
A20: Acquisitions, Net of Cash Acquired | B20: -287 | C20: -1491 | D20: -2515 | E20: -738 | F20: -2618 | G20: -6969 | H20: -495 | I20: -2931 | J20: -1592 | K20: ='QTR CF'!AH21+'QTR CF'!AI21+'QTR CF'!AJ21+'QTR CF'!AK21 | L20: ='QTR CF'!AL21+'QTR CF'!AM21+'QTR CF'!AN21+'QTR CF'!AO21 | M20: ='QTR CF'!AP21+'QTR CF'!AQ21+'QTR CF'!AR21+'QTR CF'!AS21 | N20: ='QTR CF'!AT21+'QTR CF'!AU21+'QTR CF'!AV21+'QTR CF'!AW21 | O20: ='QTR CF'!AX21+'QTR CF'!AY21+'QTR CF'!AZ21+'QTR CF'!BA21
A21: Collections from Note Receivable | B21: 1419 | C21: 0 | D21: 0 | E21: 0 | F21: 0 | G21: 0 | H21: 0 | I21: 0 | J21: 0 | K21: ='QTR CF'!AH22+'QTR CF'!AI22+'QTR CF'!AJ22+'QTR CF'!AK22 | L21: ='QTR CF'!AL22+'QTR CF'!AM22+'QTR CF'!AN22+'QTR CF'!AO22 | M21: ='QTR CF'!AP22+'QTR CF'!AQ22+'QTR CF'!AR22+'QTR CF'!AS22 | N21: ='QTR CF'!AT22+'QTR CF'!AU22+'QTR CF'!AV22+'QTR CF'!AW22 | O21: ='QTR CF'!AX22+'QTR CF'!AY22+'QTR CF'!AZ22+'QTR CF'!BA22
A22: Other Investing Activities | B22: 99 | C22: 98 | D22: 589 | E22: 68 | F22: 541 | G22: 1589 | H22: -1051 | I22: -2667 | J22: -2370 | K22: ='QTR CF'!AH23+'QTR CF'!AI23+'QTR CF'!AJ23+'QTR CF'!AK23 | L22: ='QTR CF'!AL23+'QTR CF'!AM23+'QTR CF'!AN23+'QTR CF'!AO23 | M22: ='QTR CF'!AP23+'QTR CF'!AQ23+'QTR CF'!AR23+'QTR CF'!AS23 | N22: ='QTR CF'!AT23+'QTR CF'!AU23+'QTR CF'!AV23+'QTR CF'!AW23 | O22: ='QTR CF'!AX23+'QTR CF'!AY23+'QTR CF'!AZ23+'QTR CF'!BA23
A23: Cash Flow from Investing | B23: =SUM(B17:B22) | C23: =SUM(C17:C22) | D23: =SUM(D17:D22) | E23: =SUM(E17:E22) | F23: =SUM(F17:F22) | G23: =SUM(G17:G22) | H23: =SUM(H17:H22) | I23: =SUM(I17:I22) | ... P23: =SUM(P17:P22)
A24: Stock-Based Award Activities, Net | B24: -4166 | C24: -4993 | D24: -4765 | E24: -5720 | F24: -10162 | G24: -9300 | H24: -9837 | I24: -12190 | J24: -14167 | K24: ='QTR CF'!AH25+'QTR CF'!AI25+'QTR CF'!AJ25+'QTR CF'!AK25 | L24: ='QTR CF'!AL25+'QTR CF'!AM25+'QTR CF'!AN25+'QTR CF'!AO25 | M24: ='QTR CF'!AP25+'QTR CF'!AQ25+'QTR CF'!AR25+'QTR CF'!AS25 | N24: ='QTR CF'!AT25+'QTR CF'!AU25+'QTR CF'!AV25+'QTR CF'!AW25 | O24: ='QTR CF'!AX25+'QTR CF'!AY25+'QTR CF'!AZ25+'QTR CF'!BA25
A25: Share Repurchases | B25: -4846 | C25: -9075 | D25: -18396 | E25: -31149 | F25: -50274 | G25: -59296 | H25: -61504 | I25: -62222 | J25: -45709 | K25: ='QTR CF'!AH26+'QTR CF'!AI26+'QTR CF'!AJ26+'QTR CF'!AK26 | L25: ='QTR CF'!AL26+'QTR CF'!AM26+'QTR CF'!AN26+'QTR CF'!AO26 | M25: ='QTR CF'!AP26+'QTR CF'!AQ26+'QTR CF'!AR26+'QTR CF'!AS26 | N25: ='QTR CF'!AT26+'QTR CF'!AU26+'QTR CF'!AV26+'QTR CF'!AW26 | O25: ='QTR CF'!AX26+'QTR CF'!AY26+'QTR CF'!AZ26+'QTR CF'!BA26
A26: Common Dividends | B26: 0 | C26: 0 | D26: 0 | E26: 0 | F26: 0 | G26: 0 | H26: 0 | I26: -7363 | J26: -10049 | K26: ='QTR CF'!AH27+'QTR CF'!AI27+'QTR CF'!AJ27+'QTR CF'!AK27 | L26: ='QTR CF'!AL27+'QTR CF'!AM27+'QTR CF'!AN27+'QTR CF'!AO27 | M26: ='QTR CF'!AP27+'QTR CF'!AQ27+'QTR CF'!AR27+'QTR CF'!AS27 | N26: ='QTR CF'!AT27+'QTR CF'!AU27+'QTR CF'!AV27+'QTR CF'!AW27 | O26: ='QTR CF'!AX27+'QTR CF'!AY27+'QTR CF'!AZ27+'QTR CF'!BA27
A27: Proceeds from Issuance of Long-Term Debt | B27: 4291 | C27: 6766 | D27: 317 | E27: 11761 | F27: 20199 | G27: 52872 | H27: 10790 | I27: 13589 | J27: 64564 | K27: ='QTR CF'!AH28+'QTR CF'!AI28+'QTR CF'!AJ28+'QTR CF'!AK28 | L27: ='QTR CF'!AL28+'QTR CF'!AM28+'QTR CF'!AN28+'QTR CF'!AO28 | M27: ='QTR CF'!AP28+'QTR CF'!AQ28+'QTR CF'!AR28+'QTR CF'!AS28 | N27: ='QTR CF'!AT28+'QTR CF'!AU28+'QTR CF'!AV28+'QTR CF'!AW28 | O27: ='QTR CF'!AX28+'QTR CF'!AY28+'QTR CF'!AZ28+'QTR CF'!BA28
A28: Net Change in Other Short-Term Debt | B28: -4377 | C28: -6827 | D28: -585 | E28: -2100 | F28: -21435 | G28: -54068 | H28: -11550 | I28: -12701 | J28: -32427 | K28: ='QTR CF'!AH29+'QTR CF'!AI29+'QTR CF'!AJ29+'QTR CF'!AK29 | L28: ='QTR CF'!AL29+'QTR CF'!AM29+'QTR CF'!AN29+'QTR CF'!AO29 | M28: ='QTR CF'!AP29+'QTR CF'!AQ29+'QTR CF'!AR29+'QTR CF'!AS29 | N28: ='QTR CF'!AT29+'QTR CF'!AU29+'QTR CF'!AV29+'QTR CF'!AW29 | O28: ='QTR CF'!AX29+'QTR CF'!AY29+'QTR CF'!AZ29+'QTR CF'!BA29
A29: Proceeds from Sale of Interest in Consolidated Entities | B29: 800 | C29: 950 | D29: 220 | E29: 2800 | F29: 310 | G29: 35 | H29: 8 | I29: 1154 | J29: 400 | K29: ='QTR CF'!AH30+'QTR CF'!AI30+'QTR CF'!AJ30+'QTR CF'!AK30 | L29: ='QTR CF'!AL30+'QTR CF'!AM30+'QTR CF'!AN30+'QTR CF'!AO30 | M29: ='QTR CF'!AP30+'QTR CF'!AQ30+'QTR CF'!AR30+'QTR CF'!AS30 | N29: ='QTR CF'!AT30+'QTR CF'!AU30+'QTR CF'!AV30+'QTR CF'!AW30 | O29: ='QTR CF'!AX30+'QTR CF'!AY30+'QTR CF'!AZ30+'QTR CF'!BA30
A30: Cash Flow from Financing | B30: =SUM(B24:B29) | C30: =SUM(C24:C29) | D30: =SUM(D24:D29) | E30: =SUM(E24:E29) | F30: =SUM(F24:F29) | G30: =SUM(G24:G29) | H30: =SUM(H24:H29) | I30: =SUM(I24:I29) | ... P30: =SUM(P24:P29)
A31: FX Effect on Cash | B31: 405 | C31: -302 | D31: -23 | E31: 24 | F31: -287 | G31: -506 | H31: -421 | I31: -612 | J31: 208 | K31: ='QTR CF'!AH32+'QTR CF'!AI32+'QTR CF'!AJ32+'QTR CF'!AK32 | L31: ='QTR CF'!AL32+'QTR CF'!AM32+'QTR CF'!AN32+'QTR CF'!AO32 | M31: ='QTR CF'!AP32+'QTR CF'!AQ32+'QTR CF'!AR32+'QTR CF'!AS32 | N31: ='QTR CF'!AT32+'QTR CF'!AU32+'QTR CF'!AV32+'QTR CF'!AW32 | O31: ='QTR CF'!AX32+'QTR CF'!AY32+'QTR CF'!AZ32+'QTR CF'!BA32
A32: Net Change in Cash | B32: =B16+B23+B30+B31 | C32: =C16+C23+C30+C31 | D32: =D16+D23+D30+D31 | E32: =E16+E23+E30+E31 | F32: =F16+F23+F30+F31 | G32: =G16+G23+G30+G31 | H32: =H16+H23+H30+H31 | I32: =I16+I23+I30+I31 | ... P32: =P16+P23+P30+P31

Sheet YTD P&L
B1: Q1 FY2018 | C1: Q2 FY2018 | D1: Q3 FY2018 | E1: Q1 FY2019 | F1: Q2 FY2019 | G1: Q3 FY2019 | H1: Q1 FY2020 | I1: Q2 FY2020 | J1: Q3 FY2020 | K1: Q1 FY2021 | L1: Q2 FY2021 | M1: Q3 FY2021 | N1: Q1 FY2022 | O1: Q2 FY2022 | P1: Q3 FY2022 | Q1: Q1 FY2023 | R1: Q2 FY2023 | S1: Q3 FY2023 | T1: Q1 FY2024 | U1: Q2 FY2024 | V1: Q3 FY2024 | W1: Q1 FY2025 | X1: Q2 FY2025 | Y1: Q3 FY2025
A2: Net Sales / Revenue | B2: 31146 | C2: 63803 | D2: 97543 | E2: 36339 | F2: 75283 | G2: 115782 | H2: 41159 | I2: 79456 | J2: 125629 | K2: 55314 | L2: 117194 | M2: 182312 | N2: 68011 | O2: 137696 | P2: 206788 | Q2: 69787 | R2: 144391 | S2: 221084 | T2: 80539 | U2: 165281 | V2: 253549 | W2: 90234 | X2: 186662 | Y2: 289007
A3: COGS | B3: -13467 | C3: -27350 | D3: -41631 | E3: -16012 | F3: -33308 | G3: -50876 | H3: -18982 | I3: -37535 | J3: -58652 | K3: -24103 | L3: -50330 | M3: -77951 | N3: -29599 | O3: -59703 | P3: -90861 | Q3: -30612 | R3: -62528 | S3: -95757 | T3: -33712 | U3: -69219 | V3: -105693 | W3: -36361 | X3: -75400 | Y3: -116768
A4: Gross Profit (Loss) | B4: =B2+B3 | C4: =C2+C3 | D4: =D2+D3 | E4: =E2+E3 | F4: =F2+F3 | G4: =G2+G3 | H4: =H2+H3 | I4: =I2+I3 | ... Y4: =Y2+Y3
A5: Research and Development | B5: -5039 | C5: -10153 | D5: -15385 | E5: -6029 | F5: -12242 | G5: -18796 | H5: -6820 | I5: -13695 | J5: -20551 | K5: -7485 | L5: -15160 | M5: -22854 | N5: -9119 | O5: -18960 | P5: -29233 | Q5: -11468 | R5: -22056 | S5: -33314 | T5: -11903 | U5: -23763 | V5: -36210 | W5: -13556 | X5: -27364 | Y5: -42515
A6: Sales and Marketing | B6: -3604 | C6: -7384 | D6: -11233 | E6: -3905 | F6: -8117 | G6: -12726 | H6: -4500 | I6: -8401 | J6: -12632 | K6: -4516 | L6: -9792 | M6: -15308 | N6: -5825 | O6: -12455 | P6: -19384 | Q6: -6533 | R6: -13314 | S6: -20198 | T6: -6426 | U6: -13218 | V6: -20445 | W6: -6172 | X6: -13273 | Y6: -20478
A7: General and Administrative | B7: -1403 | C7: -3167 | D7: -4920 | E7: -2088 | F7: -4131 | G7: -6722 | H7: -2880 | I7: -5465 | J7: -8221 | K7: -2773 | L7: -6114 | M7: -9370 | N7: -3374 | O7: -7031 | P7: -10628 | Q7: -3759 | R7: -7240 | S7: -11219 | T7: -3026 | U7: -6184 | V7: -9783 | W7: -3539 | X7: -8748 | Y7: -16141
A8: Litigation and Regulatory Charges | B8: 0 | C8: -5071 | D8: -5071 | E8: -1697 | F8: -1697 | G8: -1697 | H8: 0 | I8: 0 | J8: 0 | K8: 0 | L8: 0 | M8: 0 | N8: 0 | O8: 0 | P8: 0 | Q8: 0 | R8: 0 | S8: 0 | T8: 0 | U8: 0 | V8: 0 | W8: 0 | X8: 0 | Y8: 0
A9: Income (Loss) from Operations | B9: =B4+SUM(B5:B8) | C9: =C4+SUM(C5:C8) | D9: =D4+SUM(D5:D8) | E9: =E4+SUM(E5:E8) | F9: =F4+SUM(F5:F8) | G9: =G4+SUM(G5:G8) | H9: =H4+SUM(H5:H8) | I9: =I4+SUM(I5:I8) | ... Y9: =Y4+SUM(Y5:Y8)
A10: Other Income (Expense) | B10: 2910 | C10: 4080 | D10: 5538 | E10: 1538 | F10: 4505 | G10: 3956 | H10: -220 | I10: 1674 | J10: 3820 | K10: 4846 | L10: 7470 | M10: 9503 | N10: -1160 | O10: -1599 | P10: -2501 | Q10: 790 | R10: 855 | S10: 709 | T10: 2843 | U10: 2969 | V10: 6154 | W10: 11183 | X10: 13845 | Y10: 26604
A11: Pre-Tax Income (Loss) | B11: =B9+B10 | C11: =C9+C10 | D11: =D9+D10 | E11: =E9+E10 | F11: =F9+F10 | G11: =G9+G10 | H11: =H9+H10 | I11: =I9+I10 | ... Y11: =Y9+Y10
A12: Income Tax (Expense) Benefit | B12: -1142 | C12: -2162 | D12: -3053 | E12: -1489 | F12: -3689 | G12: -5249 | H12: -921 | I12: -2239 | J12: -4351 | K12: -3353 | L12: -6813 | M12: -10941 | N12: -2498 | O12: -5510 | P12: -7833 | Q12: -3154 | R12: -6689 | S12: -8197 | T12: -4653 | U12: -8585 | V12: -13990 | W12: -7249 | X12: -12986 | Y12: -21994
A13: Net Income (Loss) | B13: =B11+B12 | C13: =C11+C12 | D13: =D11+D12 | E13: =E11+E12 | F13: =F11+F12 | G13: =G11+G12 | H13: =H11+H12 | I13: =I11+I12 | ... Y13: =Y11+Y12
A14: Basic Earnings (Loss) per Share | B14: 13.53 | C14: 18.13 | D14: 31.34 | E14: 9.58 | F14: 23.91 | G14: 34.12 | H14: 9.96 | I14: 20.16 | J14: 36.69 | K14: 26.63 | L14: 54.32 | M14: 82.76 | N14: 24.9 | O14: 2.46 | P14: 3.53 | Q14: 1.18 | R14: 2.63 | S14: 4.19 | T14: 1.91 | U14: 3.82 | V14: 5.96 | W14: 2.84 | X14: 5.16 | Y14: 8.06
A15: Diluted Earnings (Loss) per Share | B15: 13.33 | C15: 17.89 | D15: 30.95 | E15: 9.5 | F15: 23.71 | G15: 33.83 | H15: 9.87 | I15: 20 | J15: 36.38 | K15: 26.29 | L15: 53.54 | M15: 81.53 | N15: 24.62 | O15: 2.44 | P15: 3.5 | Q15: 1.17 | R15: 2.61 | S15: 4.16 | T15: 1.89 | U15: 3.78 | V15: 5.9 | W15: 2.81 | X15: 5.12 | Y15: 7.99

Sheet YTD BS
B1: Q4 FY2018 | C1: Q1 FY2019 | D1: Q2 FY2019 | E1: Q3 FY2019 | F1: Q4 FY2019 | G1: Q1 FY2020 | H1: Q2 FY2020 | I1: Q3 FY2020 | J1: Q4 FY2020 | K1: Q1 FY2021 | L1: Q2 FY2021 | M1: Q3 FY2021 | N1: Q4 FY2021 | O1: Q1 FY2022 | P1: Q2 FY2022 | Q1: Q3 FY2022 | R1: Q4 FY2022 | S1: Q1 FY2023 | T1: Q2 FY2023 | U1: Q3 FY2023 | V1: Q4 FY2023 | W1: Q1 FY2024 | X1: Q2 FY2024 | Y1: Q3 FY2024 | Z1: Q4 FY2024 | AA1: Q1 FY2025 | AB1: Q2 FY2025 | AC1: Q3 FY2025
A2: Cash & Cash Equivalents | B2: 16701 | C2: 19148 | D2: 16587 | E2: 16032 | F2: 18498 | G2: 19644 | H2: 17742 | I2: 20129 | J2: 26465 | K2: 26622 | L2: 23630 | M2: 23719 | N2: 20945 | O2: 20886 | P2: 17936 | Q2: 21984 | R2: 21879 | S2: 25924 | T2: 25929 | U2: 30702 | V2: 24048 | W2: 24493 | X2: 27225 | Y2: 19959 | Z2: 23466 | AA2: 23264 | AB2: 21036 | AC2: 23090
A3: Short-Term Investments | B3: 92439 | C3: 94340 | D3: 104469 | E3: 105145 | F3: 101177 | G3: 97585 | H3: 103338 | I3: 112467 | J3: 110229 | K3: 108482 | L3: 112233 | M3: 118284 | N3: 118704 | O3: 113084 | P3: 107061 | Q3: 94275 | R3: 91883 | S3: 89178 | T3: 92403 | U3: 89233 | V3: 86868 | W3: 83597 | X3: 73500 | Y3: 73271 | Z3: 72191 | AA3: 72064 | AB3: 74112 | AC3: 75406
A4: Accounts Receivable | B4: 20838 | C4: 19149 | D4: 20965 | E4: 20889 | F4: 25326 | G4: 21825 | H4: 21201 | I4: 24925 | J4: 30930 | K4: 28006 | L4: 31967 | M4: 34047 | N4: 39304 | O4: 34703 | P4: 35707 | Q4: 34697 | R4: 40258 | S4: 36036 | T4: 38804 | U4: 41020 | V4: 47964 | W4: 44552 | X4: 47087 | Y4: 49104 | Z4: 52340 | AA4: 51000 | AB4: 55048 | AC4: 57148
A5: Note Receivable - Current | B5: 355 | C5: 111 | D5: 352 | E5: 192 | F5: 2166 | G5: 1910 | H5: 394 | I5: 588 | J5: 454 | K5: 493 | L5: 884 | M5: 753 | N5: 966 | O5: 919 | P5: 1366 | Q5: 1479 | R5: 0 | S5: 0 | T5: 0 | U5: 0 | V5: 0 | W5: 0 | X5: 0 | Y5: 0 | Z5: 0 | AA5: 0 | AB5: 0 | AC5: 0
A6: Inventories | B6: 1107 | C6: 1053 | D6: 964 | E6: 1401 | F6: 999 | G6: 889 | H6: 815 | I6: 835 | J6: 728 | K6: 888 | L6: 907 | M6: 1278 | N6: 1170 | O6: 1369 | P6: 1980 | Q6: 3156 | R6: 2670 | S6: 2315 | T6: 2231 | U6: 2957 | V6: 0 | W6: 0 | X6: 0 | Y6: 0 | Z6: 0 | AA6: 0 | AB6: 0 | AC6: 0
A7: Other Current Assets | B7: 4236 | C7: 4406 | D7: 4100 | E7: 4699 | F7: 4412 | G7: 5165 | H7: 5579 | I7: 5425 | J7: 5490 | K7: 7646 | L7: 6076 | M7: 6029 | N7: 7054 | O7: 6892 | P7: 8321 | Q7: 10518 | R7: 8105 | S7: 8532 | T7: 9421 | U7: 12398 | V7: 12650 | W7: 12829 | X7: 14183 | Y7: 15207 | Z7: 15714 | AA7: 15724 | AB7: 16020 | AC7: 18303
A8: Total Current Assets | B8: =SUM(B2:B7) | C8: =SUM(C2:C7) | D8: =SUM(D2:D7) | E8: =SUM(E2:E7) | F8: =SUM(F2:F7) | G8: =SUM(G2:G7) | H8: =SUM(H2:H7) | I8: =SUM(I2:I7) | ... AC8: =SUM(AC2:AC7)
A9: Long-Term Investments | B9: 13859 | C9: 14474 | D9: 12112 | E9: 12488 | F9: 13078 | G9: 12367 | H9: 12961 | I9: 14656 | J9: 20703 | K9: 25294 | L9: 25532 | M9: 26101 | N9: 29549 | O9: 30544 | P9: 30665 | Q9: 30419 | R9: 30492 | S9: 31213 | T9: 31224 | U9: 30907 | V9: 31008 | W9: 33994 | X9: 34172 | Y9: 36177 | Z9: 37982 | AA9: 51029 | AB9: 52574 | AC9: 63800
A10: Deferred Tax Assets | B10: 737 | C10: 750 | D10: 585 | E10: 564 | F10: 721 | G10: 730 | H10: 895 | I10: 972 | J10: 1084 | K10: 1129 | L10: 1153 | M10: 1195 | N10: 1284 | O10: 1388 | P10: 1490 | Q10: 2991 | R10: 5261 | S10: 6885 | T10: 9357 | U10: 10983 | V10: 12169 | W10: 11687 | X10: 14958 | Y10: 15915 | Z10: 17180 | AA10: 18386 | AB10: 19289 | AC10: 10331
A11: Net PP&E | B11: 59719 | C11: 60528 | D11: 64891 | E11: 69252 | F11: 73646 | G11: 76747 | H11: 78748 | I11: 81636 | J11: 84749 | K11: 87606 | L11: 91697 | M11: 94631 | N11: 97599 | O11: 104218 | P11: 106223 | Q11: 108363 | R11: 112668 | S11: 117560 | T11: 121208 | U11: 125705 | V11: 134345 | W11: 143182 | X11: 151155 | Y11: 161270 | Z11: 171036 | AA11: 185062 | AB11: 203231 | AC11: 223787
A12: ROU Assets - Operating - Non-Current | B12: 0 | C12: 8837 | D12: 9713 | E12: 10341 | F12: 10941 | G12: 11219 | H12: 11567 | I12: 11946 | J12: 12211 | K12: 12598 | L12: 12978 | M12: 12918 | N12: 12959 | O12: 12992 | P12: 13398 | Q12: 13677 | R12: 14381 | S12: 14447 | T12: 14469 | U12: 14199 | V12: 14091 | W12: 13768 | X12: 13606 | Y12: 13561 | Z12: 13588 | AA12: 13722 | AB12: 14255 | AC12: 14524
A13: Intangible Assets | B13: 2220 | C13: 2063 | D13: 1902 | E13: 1747 | F13: 1979 | G13: 1840 | H13: 1697 | I13: 1520 | J13: 1445 | K13: 1823 | L13: 1626 | M13: 1549 | N13: 1417 | O13: 1313 | P13: 1377 | Q13: 2192 | R13: 2084 | S13: 1968 | T13: 1966 | U13: 1833 | V13: 0 | W13: 0 | X13: 0 | Y13: 0 | Z13: 0 | AA13: 0 | AB13: 0 | AC13: 0
A14: Goodwill | B14: 17888 | C14: 17943 | D14: 18000 | E14: 18069 | F14: 20624 | G14: 20734 | H14: 20824 | I14: 20870 | J14: 21175 | K14: 22341 | L14: 22406 | M14: 22623 | N14: 22956 | O14: 23010 | P14: 23949 | Q14: 28834 | R14: 28960 | S14: 28994 | T14: 29210 | U14: 29146 | V14: 29198 | W14: 29183 | X14: 29185 | Y14: 31935 | Z14: 31885 | AA14: 32173 | AB14: 32335 | AC14: 33269
A15: Other Non-Current Assets | B15: 2693 | C15: 2547 | D15: 2461 | E15: 2225 | F15: 2342 | G15: 2748 | H15: 2731 | I15: 3274 | J15: 3953 | K15: 4167 | L15: 4298 | M15: 4276 | N15: 5361 | O15: 5778 | P15: 5712 | Q15: 5670 | R15: 6623 | S15: 6439 | T15: 6822 | U15: 7628 | V15: 10051 | W15: 10065 | X15: 9699 | Y15: 13867 | Z15: 14874 | AA15: 12950 | AB15: 14153 | AC15: 16811
A16: Total Assets | B16: =B8+SUM(B9:B15) | C16: =C8+SUM(C9:C15) | D16: =D8+SUM(D9:D15) | E16: =E8+SUM(E9:E15) | F16: =F8+SUM(F9:F15) | G16: =G8+SUM(G9:G15) | H16: =H8+SUM(H9:H15) | I16: =I8+SUM(I9:I15) | ... AC16: =AC8+SUM(AC9:AC15)
A17: Accounts Payable | B17: 4378 | C17: 3710 | D17: 3925 | E17: 4142 | F17: 5561 | G17: 4099 | H17: 4064 | I17: 4391 | J17: 5589 | K17: 4801 | L17: 4708 | M17: 4616 | N17: 6037 | O17: 3436 | P17: 4409 | Q17: 6303 | R17: 5128 | S17: 4184 | T17: 5313 | U17: 5803 | V17: 7493 | W17: 6198 | X17: 6092 | Y17: 7049 | Z17: 7987 | AA17: 8497 | AB17: 8347 | AC17: 10546
A18: Accrued Compensation | B18: 6839 | C18: 5072 | D18: 6432 | E18: 7399 | F18: 8495 | G18: 5656 | H18: 7127 | I18: 8747 | J18: 11086 | K18: 8375 | L18: 10088 | M18: 12170 | N18: 13889 | O18: 9803 | P18: 10852 | Q18: 12366 | R18: 14028 | S18: 9954 | T18: 11260 | U18: 12562 | V18: 15140 | W18: 9703 | X18: 11373 | Y18: 12908 | Z18: 15069 | AA18: 9984 | AB18: 12168 | AC18: 13944
A19: Accrued Expenses | B19: 16958 | C19: 19382 | D19: 19823 | E19: 21038 | F19: 23067 | G19: 22601 | H19: 24426 | I19: 25631 | J19: 28631 | K19: 30732 | L19: 28981 | M19: 30113 | N19: 31236 | O19: 33051 | P19: 32976 | Q19: 35038 | R19: 37866 | S19: 43185 | T19: 49300 | U19: 55602 | V19: 46168 | W19: 48603 | X19: 47298 | Y19: 46585 | Z19: 51228 | AA19: 58300 | AB19: 52039 | AC19: 59437
A20: Accrued Revenue Share | B20: 4592 | C20: 4318 | D20: 4567 | E20: 4835 | F20: 5916 | G20: 4982 | H20: 5005 | I20: 6030 | J20: 7500 | K20: 6962 | L20: 7438 | M20: 7745 | N20: 8996 | O20: 8116 | P20: 7889 | Q20: 7662 | R20: 8370 | S20: 7816 | T20: 7990 | U20: 8025 | V20: 8876 | W20: 8520 | X20: 8899 | Y20: 9365 | Z20: 9802 | AA20: 9965 | AB20: 9787 | AC20: 10081
A21: Deferred Revenue - Current | B21: 1784 | C21: 1667 | D21: 1717 | E21: 1679 | F21: 1908 | G21: 1938 | H21: 2061 | I21: 2302 | J21: 2543 | K21: 2690 | L21: 2715 | M21: 2968 | N21: 3288 | O21: 3198 | P21: 3272 | Q21: 3585 | R21: 3908 | S21: 3715 | T21: 3846 | U21: 4303 | V21: 4137 | W21: 3973 | X21: 4251 | Y21: 4896 | Z21: 5036 | AA21: 4908 | AB21: 4969 | AC21: 5542
A22: Income Taxes Payable | B22: 69 | C22: 761 | D22: 536 | E22: 131 | F22: 274 | G22: 913 | H22: 975 | I22: 1099 | J22: 1485 | K22: 1893 | L22: 1811 | M22: 4170 | N22: 808 | O22: 4344 | P22: 1956 | Q22: 1025 | R22: 0 | S22: 0 | T22: 0 | U22: 0 | V22: 0 | W22: 0 | X22: 0 | Y22: 0 | Z22: 0 | AA22: 0 | AB22: 0 | AC22: 0
A23: Total Current Liabilities | B23: =SUM(B17:B22) | C23: =SUM(C17:C22) | D23: =SUM(D17:D22) | E23: =SUM(E17:E22) | F23: =SUM(F17:F22) | G23: =SUM(G17:G22) | H23: =SUM(H17:H22) | I23: =SUM(I17:I22) | ... AC23: =SUM(AC17:AC22)
A24: Long-Term Debt | B24: 15339 | C24: 15671 | D24: 15043 | E24: 15437 | F24: 14439 | G24: 14223 | H24: 12617 | I24: 22518 | J24: 22781 | K24: 23165 | L24: 22979 | M24: 23272 | N24: 23993 | O24: 24197 | P24: 22897 | Q24: 23225 | R24: 23959 | S24: 23419 | T24: 22458 | U24: 21819 | V24: 21727 | W24: 22462 | X24: 20941 | Y24: 20516 | Z24: 19665 | AA24: 20659 | AB24: 33634 | AC24: 31679
A25: Deferred Revenue - Non-Current | B25: 396 | C25: 391 | D25: 387 | E25: 364 | F25: 358 | G25: 350 | H25: 397 | I25: 454 | J25: 481 | K25: 530 | L25: 510 | M25: 510 | N25: 535 | O25: 499 | P25: 472 | Q25: 594 | R25: 599 | S25: 610 | T25: 667 | U25: 884 | V25: 911 | W25: 921 | X25: 985 | Y25: 1015 | Z25: 0 | AA25: 0 | AB25: 0 | AC25: 0
A26: Deferred Tax Liability | B26: 1264 | C26: 1282 | D26: 1892 | E26: 1747 | F26: 1701 | G26: 2079 | H26: 1797 | I26: 1973 | J26: 3561 | K26: 4406 | L26: 4703 | M26: 3551 | N26: 5257 | O26: 2843 | P26: 924 | Q26: 476 | R26: 514 | S26: 542 | T26: 558 | U26: 528 | V26: 485 | W26: 486 | X26: 717 | Y26: 706 | Z26: 0 | AA26: 0 | AB26: 0 | AC26: 0
A27: Lease Liability - Operating - Non-Current | B27: 0 | C27: 8206 | D27: 9088 | E27: 9666 | F27: 10214 | G27: 10476 | H27: 10709 | I27: 10984 | J27: 11146 | K27: 11382 | L27: 11619 | M27: 11471 | N27: 11389 | O27: 11363 | P27: 11697 | Q27: 11984 | R27: 12501 | S27: 12799 | T27: 12746 | U27: 12550 | V27: 12460 | W27: 11957 | X27: 11708 | Y27: 11654 | Z27: 11691 | AA27: 11678 | AB27: 11952 | AC27: 12106
A28: Other Non-Current Liabilities | B28: 3545 | C28: 1417 | D28: 1499 | E28: 1637 | F28: 2534 | G28: 2427 | H28: 1992 | I28: 2194 | J28: 2269 | K28: 2146 | L28: 2270 | M28: 2250 | N28: 2205 | O28: 2242 | P28: 2422 | Q28: 2371 | R28: 2247 | S28: 2373 | T28: 1765 | U28: 1433 | V28: 1616 | W28: 1683 | X28: 1753 | Y28: 1453 | Z28: 4694 | AA28: 6116 | AB28: 6241 | AC28: 6267
A29: Total Liabilities | B29: =B23+SUM(B24:B28) | C29: =C23+SUM(C24:C28) | D29: =D23+SUM(D24:D28) | E29: =E23+SUM(E24:E28) | F29: =F23+SUM(F24:F28) | G29: =G23+SUM(G24:G28) | H29: =H23+SUM(H24:H28) | I29: =I23+SUM(I24:I28) | ... AC29: =AC23+SUM(AC24:AC28)
A30: Convertible Preferred Stock | B30: 0 | C30: 0 | D30: 0 | E30: 0 | F30: 0 | G30: 0 | H30: 0 | I30: 0 | J30: 0 | K30: 0 | L30: 0 | M30: 0 | N30: 0 | O30: 0 | P30: 0 | Q30: 0 | R30: 0 | S30: 0 | T30: 0 | U30: 0 | V30: 0 | W30: 0 | X30: 0 | Y30: 0 | Z30: 0 | AA30: 0 | AB30: 0 | AC30: 0
A31: Common Stock and Additional Paid-in Capital | B31: 45049 | C31: 46532 | D31: 47937 | E31: 49040 | F31: 50552 | G31: 53688 | H31: 55937 | I31: 57307 | J31: 58510 | K31: 59436 | L31: 60436 | M31: 61193 | N31: 61774 | O31: 62832 | P31: 64402 | Q31: 66258 | R31: 68184 | S31: 70269 | T31: 72248 | U31: 74591 | V31: 76534 | W31: 77913 | X31: 79732 | Y31: 82030 | Z31: 84800 | AA31: 86725 | AB31: 89283 | AC31: 91695
A32: Accumulated Other Comprehensive Income (Loss) | B32: -2306 | C32: -1780 | D32: -1091 | E32: -1196 | F32: -1232 | G32: -1097 | H32: -296 | I32: 46 | J32: 633 | K32: -3 | L32: 190 | M32: -408 | N32: -1623 | O32: -4049 | P32: -5828 | Q32: -8852 | R32: -7603 | S32: -6000 | T32: -5991 | U32: -7036 | V32: -4402 | W32: -4839 | X32: -5012 | Y32: -3228 | Z32: -4800 | AA32: -4086 | AB32: -2127 | AC32: -2054
A33: Retained Earnings (Accumulated Deficit) | B33: 134885 | C33: 138720 | D33: 145346 | E33: 147125 | F33: 152122 | G33: 151068 | H33: 151681 | I33: 155567 | J33: 163401 | K33: 170580 | L33: 176939 | M33: 183782 | N33: 191484 | O33: 195221 | P33: 196845 | Q33: 196220 | R33: 195563 | S33: 196625 | T33: 200884 | U33: 205647 | V33: 211247 | W33: 219770 | X33: 226033 | Y33: 235317 | Z33: 245084 | AA33: 262628 | AB33: 275760 | AC33: 297226
A34: Total Stockholders' Equity | B34: =SUM(B30:B33) | C34: =SUM(C30:C33) | D34: =SUM(D30:D33) | E34: =SUM(E30:E33) | F34: =SUM(F30:F33) | G34: =SUM(G30:G33) | H34: =SUM(H30:H33) | I34: =SUM(I30:I33) | ... AC34: =SUM(AC30:AC33)
A35: Total Liabilities, Mezzanine & Stockholders' Equity | B35: =B29+B34 | C35: =C29+C34 | D35: =D29+D34 | E35: =E29+E34 | F35: =F29+F34 | G35: =G29+G34 | H35: =H29+H34 | I35: =I29+I34 | ... AC35: =AC29+AC34

Sheet YTD CF
B1: Q1 FY2018 | C1: Q2 FY2018 | D1: Q3 FY2018 | E1: Q1 FY2019 | F1: Q2 FY2019 | G1: Q3 FY2019 | H1: Q1 FY2020 | I1: Q2 FY2020 | J1: Q3 FY2020 | K1: Q1 FY2021 | L1: Q2 FY2021 | M1: Q3 FY2021 | N1: Q1 FY2022 | O1: Q2 FY2022 | P1: Q3 FY2022 | Q1: Q1 FY2023 | R1: Q2 FY2023 | S1: Q3 FY2023 | T1: Q1 FY2024 | U1: Q2 FY2024 | V1: Q3 FY2024 | W1: Q1 FY2025 | X1: Q2 FY2025 | Y1: Q3 FY2025
A2: Net Income (Loss) | B2: 9401 | C2: 12596 | D2: 21788 | E2: 6657 | F2: 16604 | G2: 23672 | H2: 6836 | I2: 13795 | J2: 25042 | K2: 17930 | L2: 36455 | M2: 55391 | N2: 16436 | O2: 32438 | P2: 46348 | Q2: 15051 | R2: 33419 | S2: 53108 | T2: 23662 | U2: 47281 | V2: 73582 | W2: 34540 | X2: 62736 | Y2: 97715
A3: Depreciation and Impairment of PP&E | B3: 1791 | C3: 3653 | D3: 5791 | E3: 2416 | F3: 5042 | G3: 7774 | H3: 2899 | I3: 6077 | J3: 9366 | K3: 2525 | L3: 5255 | M3: 8340 | N3: 3591 | O3: 7289 | P3: 11222 | Q3: 3060 | R3: 6339 | S3: 10010 | T3: 0 | U3: 0 | V3: 0 | W3: 0 | X3: 0 | Y3: 0
A4: Amortization and Impairment of Intangibles | B4: 195 | C4: 447 | D4: 664 | E4: 197 | F4: 406 | G4: 594 | H4: 209 | I4: 417 | J4: 606 | K4: 228 | L4: 443 | M4: 662 | N4: 191 | O4: 392 | P4: 505 | Q4: 126 | R4: 244 | S4: 373 | T4: 0 | U4: 0 | V4: 0 | W4: 0 | X4: 0 | Y4: 0
A5: Depreciation | B5: 0 | C5: 0 | D5: 0 | E5: 0 | F5: 0 | G5: 0 | H5: 0 | I5: 0 | J5: 0 | K5: 0 | L5: 0 | M5: 0 | N5: 0 | O5: 0 | P5: 0 | Q5: 0 | R5: 0 | S5: 0 | T5: 3413 | U5: 7121 | V5: 11106 | W5: 4487 | X5: 9485 | Y5: 15096
A6: Stock-Based Compensation | B6: 2457 | C6: 4870 | D6: 7100 | E6: 2769 | F6: 5525 | G6: 8149 | H6: 3191 | I6: 6573 | J6: 9768 | K6: 3745 | L6: 7548 | M6: 11422 | N6: 4504 | O6: 9286 | P6: 14262 | Q6: 5284 | R6: 11058 | S6: 16801 | T6: 5264 | U6: 11129 | V6: 16975 | W6: 5516 | X6: 11514 | Y6: 17882
A7: (Benefit) Provision for Deferred Income Taxes | B7: -18 | C7: -157 | D7: 723 | E7: -73 | F7: 620 | G7: 381 | H7: 175 | I7: -416 | J7: -280 | K7: 1100 | L7: 1479 | M7: 192 | N7: -2090 | O7: -4237 | P7: -6157 | Q7: -1854 | R7: -4269 | S7: -6093 | T7: 419 | U7: -2738 | V7: -3809 | W7: -1152 | X7: -1596 | Y7: 7130
A8: Loss (Gain) on Equity and Debt Securities, Net | B8: -2992 | C8: -4060 | D8: -5413 | E8: -1081 | F8: -3878 | G8: -2399 | H8: 802 | I8: -1040 | J8: -3055 | K8: -4751 | L8: -7634 | M8: -9792 | N8: 1437 | O8: 2478 | P8: 3856 | Q8: -84 | R8: 425 | S8: 1294 | T8: -1781 | U8: -757 | V8: -2738 | W8: -9960 | X8: -11411 | Y8: -22266
A9: Other Operating Items | B9: -498 | C9: -876 | D9: -1322 | E9: -243 | F9: -224 | G9: -906 | H9: 182 | I9: 310 | J9: 283 | K9: -248 | L9: -455 | M9: -1646 | N9: -636 | O9: -1419 | P9: -3899 | Q9: -193 | R9: -609 | S9: -1971 | T9: -666 | U9: -347 | V9: 258 | W9: -807 | X9: -1726 | Y9: -3217
A10: Accounts Receivable | B10: 1700 | C10: 1388 | D10: 718 | E10: 1172 | F10: 26 | G10: 25 | H10: 2602 | I10: 2522 | J10: -1079 | K10: 2794 | L10: -867 | M10: -3276 | N10: 4364 | O10: 2395 | P10: 2298 | Q10: 4454 | R10: 1506 | S10: -1315 | T10: 3167 | U10: 110 | V10: -1321 | W10: 1638 | X10: -1201 | Y10: -3582
A11: Change in Income Taxes | B11: 782 | C11: -656 | D11: -1891 | E11: 1068 | F11: 25 | G11: 210 | H11: -245 | I11: 538 | J11: 469 | K11: 785 | L11: -297 | M11: 2744 | N11: 3820 | O11: -253 | P11: -862 | Q11: 4069 | R11: 8520 | S11: 10392 | T11: 3011 | U11: -889 | V11: -2797 | W11: 7197 | X11: -2434 | Y11: -3292
A12: Accounts Payable | B12: 122 | C12: -23 | D12: 293 | E12: -425 | F12: -443 | G12: -386 | H12: -835 | I12: -689 | J12: -269 | K12: -982 | L12: -1112 | M12: -874 | N12: -2373 | O12: -1172 | P12: 735 | Q12: -1105 | R12: 14 | S12: 237 | T12: -2124 | U12: -563 | V12: -42 | W12: -880 | X12: -327 | Y12: -771
A13: Accrued Expenses | B13: -1142 | C13: 4600 | D13: 6457 | E13: -229 | F13: 1074 | G13: 2927 | H13: -3531 | I13: -2099 | J13: 891 | K13: -3530 | L13: 201 | M13: 2763 | N13: -3216 | O13: -1719 | P13: 491 | Q13: -4496 | R13: -4037 | S13: -380 | T13: -5054 | U13: -5176 | V13: -6366 | W13: -5045 | X13: -1560 | Y13: 6199
... A15: Deferred Revenue | B15: 130 | C15: 295 | D15: 272 | E15: -81 | F15: -90 | G15: -149 | H15: 37 | I15: 148 | J15: 428 | K15: 137 | L15: 134 | M15: 406 | N15: -94 | O15: -8 | P15: 104 | Q15: -201 | R15: -17 | S15: 690 | T15: -141 | U15: 220 | V15: 860 | W15: 500 | X15: 636 | Y15: 1317
A16: Cash Flow from Operations | B16: =SUM(B2:B15) | C16: =SUM(C2:C15) | D16: =SUM(D2:D15) | E16: =SUM(E2:E15) | F16: =SUM(F2:F15) | G16: =SUM(G2:G15) | H16: =SUM(H2:H15) | I16: =SUM(I2:I15) | ... Y16: =SUM(Y2:Y15)
A17: Purchase of PP&E | B17: -7299 | C17: -12776 | D17: -18058 | E17: -4638 | F17: -10764 | G17: -17496 | H17: -6005 | I17: -11396 | J17: -16802 | K17: -5942 | L17: -11438 | M17: -18257 | N17: -9786 | O17: -16614 | P17: -23890 | Q17: -6289 | R17: -13177 | S17: -21232 | T17: -12012 | U17: -25198 | V17: -38259 | W17: -17197 | X17: -39643 | Y17: -63596
A18: Proceeds from Sale of Assets | B18: 30 | C18: 0 | D18: 0 | E18: 34 | F18: 0 | G18: 0 | H18: 0 | I18: 0 | J18: 0 | K18: 0 | L18: 0 | M18: 0 | N18: 0 | O18: 0 | P18: 0 | Q18: 0 | R18: 0 | S18: 0 | T18: 0 | U18: 0 | V18: 0 | W18: 0 | X18: 0 | Y18: 0
A19: Net Change in Short-Term Investments | B19: 502 | C19: 2482 | D19: -2414 | E19: 123 | F19: -4032 | G19: -6185 | H19: 4248 | I19: 1763 | J19: -7181 | K19: 2822 | L19: 58 | M19: -2980 | N19: 1317 | O19: 5175 | P19: 16834 | Q19: 4100 | R19: 1460 | S19: 3220 | T19: 4301 | U19: 15566 | V19: 16745 | W19: 1892 | X19: 1060 | Y19: 467
A20: Net Change in Long-Term Investments | B20: 171 | C20: 459 | D20: 227 | E20: -808 | F20: -889 | G20: -1202 | H20: -312 | I20: -838 | J20: -1266 | K20: -627 | L20: -1156 | M20: -1478 | N20: -764 | O20: -1139 | P20: -1497 | Q20: -590 | R20: -1332 | S20: -1433 | T20: -893 | U20: -1594 | V20: -2502 | W20: -699 | X20: -1439 | Y20: -2116
A21: Acquisitions, Net of Cash Acquired | B21: -1250 | C21: -1434 | D21: -1452 | E21: -99 | F21: -247 | G21: -373 | H21: -190 | I21: -355 | J21: -368 | K21: -1666 | L21: -1974 | M21: -2233 | N21: -173 | O21: -1236 | P21: -6885 | Q21: -42 | R21: -340 | S21: -466 | T21: -61 | U21: -87 | V21: -2840 | W21: -340 | X21: -353 | Y21: -1425
A22: Collections from Note Receivable | B22: 0 | C22: 0 | D22: 0 | E22: 0 | F22: 0 | G22: 0 | H22: 0 | I22: 0 | J22: 0 | K22: 0 | L22: 0 | M22: 0 | N22: 0 | O22: 0 | P22: 0 | Q22: 0 | R22: 0 | S22: 0 | T22: 0 | U22: 0 | V22: 0 | W22: 0 | X22: 0 | Y22: 0
A23: Other Investing Activities | B23: 0 | C23: 49 | D23: 69 | E23: 0 | F23: 89 | G23: 468 | H23: 412 | I23: 531 | J23: 125 | K23: 30 | L23: 53 | M23: 441 | N23: 355 | O23: 576 | P23: 1367 | Q23: -125 | R23: -357 | S23: -985 | T23: 101 | U23: -32 | V23: -2500 | W23: 150 | X23: -363 | Y23: -1845
A24: Cash Flow from Investing | B24: =SUM(B17:B23) | C24: =SUM(C17:C23) | D24: =SUM(D17:D23) | E24: =SUM(E17:E23) | F24: =SUM(F17:F23) | G24: =SUM(G17:G23) | H24: =SUM(H17:H23) | I24: =SUM(I17:I23) | ... Y24: =SUM(Y17:Y23)
A25: Stock-Based Award Activities, Net | B25: -1158 | C25: -2699 | D25: -3952 | E25: -1175 | F25: -2435 | G25: -3566 | H25: -1241 | I25: -2716 | J25: -4073 | K25: -2184 | L25: -4637 | M25: -7239 | N25: -2916 | O25: -5180 | P25: -7221 | Q25: -1989 | R25: -4725 | S25: -7157 | T25: -2929 | U25: -6138 | V25: -9141 | W25: -3110 | X25: -5731 | Y25: -9001
A26: Share Repurchases | B26: -2173 | C26: -4225 | D26: -6425 | E26: -3025 | F26: -6602 | G26: -12298 | H26: -8496 | I26: -15348 | J26: -23245 | K26: -11395 | L26: -24191 | M26: -36801 | N26: -13300 | O26: -28497 | P26: -43889 | Q26: -14557 | R26: -29526 | S26: -45313 | T26: -15696 | U26: -31380 | V26: -46671 | W26: -15068 | X26: -28706 | Y26: -40210
A27: Common Dividends | B27: 0 | C27: 0 | D27: 0 | E27: 0 | F27: 0 | G27: 0 | H27: 0 | I27: 0 | J27: 0 | K27: 0 | L27: 0 | M27: 0 | N27: 0 | O27: 0 | P27: 0 | Q27: 0 | R27: 0 | S27: 0 | T27: 0 | U27: -2466 | V27: -4921 | W27: -2434 | X27: -4977 | Y27: -7513
A28: Proceeds from Issuance of Long-Term Debt | B28: 4691 | C28: 6236 | D28: 6766 | E28: 315 | F28: 317 | G28: 317 | H28: 1898 | I28: 1898 | J28: 11761 | K28: 900 | L28: 7599 | M28: 13949 | N28: 16422 | O28: 29228 | P28: 44322 | Q28: 6927 | R28: 8050 | S28: 9298 | T28: 1982 | U28: 4875 | V28: 8694 | W28: 4532 | X28: 31378 | Y28: 38002
A29: Net Change in Other Short-Term Debt | B29: -3378 | C29: -6267 | D29: -6822 | E29: -345 | F29: -393 | G29: -538 | H29: -1947 | I29: -1982 | J29: -2043 | K29: -937 | L29: -8678 | M29: -15070 | N29: -16420 | O29: -29582 | P29: -45350 | Q29: -6952 | R29: -8207 | S29: -9621 | T29: -3079 | U29: -5502 | V29: -8951 | W29: -4521 | X29: -18397 | Y29: -26094
A30: Proceeds from Sale of Interest in Consolidated Entities | B30: 0 | C30: 0 | D30: 0 | E30: 47 | F30: 184 | G30: 202 | H30: 1600 | I30: 2464 | J30: 2462 | K30: 10 | L30: 310 | M30: 310 | N30: 0 | O30: 0 | P30: 10 | Q30: 3 | R30: 5 | S30: 8 | T30: 8 | U30: 8 | V30: 293 | W30: 400 | X30: 400 | Y30: 400
A31: Cash Flow from Financing | B31: =SUM(B25:B30) | C31: =SUM(C25:C30) | D31: =SUM(D25:D30) | E31: =SUM(E25:E30) | F31: =SUM(F25:F30) | G31: =SUM(G25:G30) | H31: =SUM(H25:H30) | I31: =SUM(I25:I30) | ... Y31: =SUM(Y25:Y30)
A32: FX Effect on Cash | B32: 165 | C32: -166 | D32: -195 | E32: 18 | F32: 31 | G32: -91 | H32: -272 | I32: -221 | J32: -186 | K32: -143 | L32: 40 | M32: -106 | N32: 100 | O32: -268 | P32: -643 | Q32: 50 | R32: 24 | S32: -327 | T32: -125 | U32: -363 | V32: -222 | W32: 43 | X32: 444 | Y32: 244
A33: Net Change in Cash | B33: =B16+B24+B31+B32 | C33: =C16+C24+C31+C32 | D33: =D16+D24+D31+D32 | E33: =E16+E24+E31+E32 | F33: =F16+F24+F31+F32 | G33: =G16+G24+G31+G32 | H33: =H16+H24+H31+H32 | I33: =I16+I24+I31+I32 | ... Y33: =Y16+Y24+Y31+Y32

Sheet QTR P&L
B1: Q1 FY2018 | C1: Q2 FY2018 | D1: Q3 FY2018 | E1: Q4 FY2018 | F1: Q1 FY2019 | G1: Q2 FY2019 | H1: Q3 FY2019 | I1: Q4 FY2019 | J1: Q1 FY2020 | K1: Q2 FY2020 | L1: Q3 FY2020 | M1: Q4 FY2020 | N1: Q1 FY2021 | O1: Q2 FY2021 | P1: Q3 FY2021 | Q1: Q4 FY2021 | R1: Q1 FY2022 | S1: Q2 FY2022 | T1: Q3 FY2022 | U1: Q4 FY2022 | V1: Q1 FY2023 | W1: Q2 FY2023 | X1: Q3 FY2023 | Y1: Q4 FY2023 | Z1: Q1 FY2024 | AA1: Q2 FY2024 | AB1: Q3 FY2024 | AC1: Q4 FY2024 | AD1: Q1 FY2025 | AE1: Q2 FY2025 | AF1: Q3 FY2025 | AG1: Q4 FY2025 | AH1: Q1 FY2026E | AI1: Q2 FY2026E | AJ1: Q3 FY2026E | AK1: Q4 FY2026E | AL1: Q1 FY2027E | AM1: Q2 FY2027E | AN1: Q3 FY2027E | AO1: Q4 FY2027E | AP1: Q1 FY2028E | AQ1: Q2 FY2028E | AR1: Q3 FY2028E | AS1: Q4 FY2028E | AT1: Q1 FY2029E | AU1: Q2 FY2029E | AV1: Q3 FY2029E | AW1: Q4 FY2029E | AX1: Q1 FY2030E | AY1: Q2 FY2030E | AZ1: Q3 FY2030E | BA1: Q4 FY2030E
A2: Net Sales / Revenue | B2: ='YTD P&L'!B2 | C2: ='YTD P&L'!C2-'YTD P&L'!B2 | D2: ='YTD P&L'!D2-'YTD P&L'!C2 | E2: ='ANNL P&L'!C2-'YTD P&L'!D2 | F2: ='YTD P&L'!E2 | G2: ='YTD P&L'!F2-'YTD P&L'!E2 | H2: ='YTD P&L'!G2-'YTD P&L'!F2 | I2: ='ANNL P&L'!D2-'YTD P&L'!G2 | J2: ='YTD P&L'!H2 | K2: ='YTD P&L'!I2-'YTD P&L'!H2 | L2: ='YTD P&L'!J2-'YTD P&L'!I2 | M2: ='ANNL P&L'!E2-'YTD P&L'!J2 | N2: ='YTD P&L'!K2 | O2: ='YTD P&L'!L2-'YTD P&L'!K2 | P2: ='YTD P&L'!M2-'YTD P&L'!L2 | Q2: ='ANNL P&L'!F2-'YTD P&L'!M2 | R2: ='YTD P&L'!N2 | S2: ='YTD P&L'!O2-'YTD P&L'!N2 | T2: ='YTD P&L'!P2-'YTD P&L'!O2 | U2: ='ANNL P&L'!G2-'YTD P&L'!P2 | V2: ='YTD P&L'!Q2 | W2: ='YTD P&L'!R2-'YTD P&L'!Q2 | X2: ='YTD P&L'!S2-'YTD P&L'!R2 | Y2: ='ANNL P&L'!H2-'YTD P&L'!S2 | Z2: ='YTD P&L'!T2 | AA2: ='YTD P&L'!U2-'YTD P&L'!T2 | AB2: ='YTD P&L'!V2-'YTD P&L'!U2 | AC2: ='ANNL P&L'!I2-'YTD P&L'!V2 | AD2: ='YTD P&L'!W2 | AE2: ='YTD P&L'!X2-'YTD P&L'!W2 | AF2: ='YTD P&L'!Y2-'YTD P&L'!X2 | AG2: ='ANNL P&L'!J2-'YTD P&L'!Y2 | AH2: =IF('IS DRIVERS'!$B2="QoQ",'QTR P&L'!AG2,'QTR P&L'!AD2)*(1+'IS DRIVERS'!AI2) | AI2: =IF('IS DRIVERS'!$B2="QoQ",'QTR P&L'!AH2,'QTR P&L'!AE2)*(1+'IS DRIVERS'!AJ2) | AJ2: =IF('IS DRIVERS'!$B2="QoQ",'QTR P&L'!AI2,'QTR P&L'!AF2)*(1+'IS DRIVERS'!AK2) | AK2: =IF('IS DRIVERS'!$B2="QoQ",'QTR P&L'!AJ2,'QTR P&L'!AG2)*(1+'IS DRIVERS'!AL2) | AL2: =IF('IS DRIVERS'!$B2="QoQ",'QTR P&L'!AK2,'QTR P&L'!AH2)*(1+'IS DRIVERS'!AM2) | AM2: =IF('IS DRIVERS'!$B2="QoQ",'QTR P&L'!AL2,'QTR P&L'!AI2)*(1+'IS DRIVERS'!AN2) | AN2: =IF('IS DRIVERS'!$B2="QoQ",'QTR P&L'!AM2,'QTR P&L'!AJ2)*(1+'IS DRIVERS'!AO2) | AO2: =IF('IS DRIVERS'!$B2="QoQ",'QTR P&L'!AN2,'QTR P&L'!AK2)*(1+'IS DRIVERS'!AP2) | ... BA2: =IF('IS DRIVERS'!$B2="QoQ",'QTR P&L'!AZ2,'QTR P&L'!AW2)*(1+'IS DRIVERS'!BB2)
A3: COGS | B3: ='YTD P&L'!B3 | C3: ='YTD P&L'!C3-'YTD P&L'!B3 | D3: ='YTD P&L'!D3-'YTD P&L'!C3 | E3: ='ANNL P&L'!C3-'YTD P&L'!D3 | F3: ='YTD P&L'!E3 | G3: ='YTD P&L'!F3-'YTD P&L'!E3 | H3: ='YTD P&L'!G3-'YTD P&L'!F3 | I3: ='ANNL P&L'!D3-'YTD P&L'!G3 | J3: ='YTD P&L'!H3 | K3: ='YTD P&L'!I3-'YTD P&L'!H3 | L3: ='YTD P&L'!J3-'YTD P&L'!I3 | M3: ='ANNL P&L'!E3-'YTD P&L'!J3 | N3: ='YTD P&L'!K3 | O3: ='YTD P&L'!L3-'YTD P&L'!K3 | P3: ='YTD P&L'!M3-'YTD P&L'!L3 | Q3: ='ANNL P&L'!F3-'YTD P&L'!M3 | R3: ='YTD P&L'!N3 | S3: ='YTD P&L'!O3-'YTD P&L'!N3 | T3: ='YTD P&L'!P3-'YTD P&L'!O3 | U3: ='ANNL P&L'!G3-'YTD P&L'!P3 | V3: ='YTD P&L'!Q3 | W3: ='YTD P&L'!R3-'YTD P&L'!Q3 | X3: ='YTD P&L'!S3-'YTD P&L'!R3 | Y3: ='ANNL P&L'!H3-'YTD P&L'!S3 | Z3: ='YTD P&L'!T3 | AA3: ='YTD P&L'!U3-'YTD P&L'!T3 | AB3: ='YTD P&L'!V3-'YTD P&L'!U3 | AC3: ='ANNL P&L'!I3-'YTD P&L'!V3 | AD3: ='YTD P&L'!W3 | AE3: ='YTD P&L'!X3-'YTD P&L'!W3 | AF3: ='YTD P&L'!Y3-'YTD P&L'!X3 | AG3: ='ANNL P&L'!J3-'YTD P&L'!Y3 | AH3: ='QTR P&L'!AH2*'IS DRIVERS'!AI3 | AI3: ='QTR P&L'!AI2*'IS DRIVERS'!AJ3 | AJ3: ='QTR P&L'!AJ2*'IS DRIVERS'!AK3 | AK3: ='QTR P&L'!AK2*'IS DRIVERS'!AL3 | AL3: ='QTR P&L'!AL2*'IS DRIVERS'!AM3 | AM3: ='QTR P&L'!AM2*'IS DRIVERS'!AN3 | AN3: ='QTR P&L'!AN2*'IS DRIVERS'!AO3 | AO3: ='QTR P&L'!AO2*'IS DRIVERS'!AP3 | ... BA3: ='QTR P&L'!BA2*'IS DRIVERS'!BB3
A4: Gross Profit (Loss) | B4: ='YTD P&L'!B4 | C4: ='YTD P&L'!C4-'YTD P&L'!B4 | D4: ='YTD P&L'!D4-'YTD P&L'!C4 | E4: ='ANNL P&L'!C4-'YTD P&L'!D4 | F4: ='YTD P&L'!E4 | G4: ='YTD P&L'!F4-'YTD P&L'!E4 | H4: ='YTD P&L'!G4-'YTD P&L'!F4 | I4: ='ANNL P&L'!D4-'YTD P&L'!G4 | J4: ='YTD P&L'!H4 | K4: ='YTD P&L'!I4-'YTD P&L'!H4 | L4: ='YTD P&L'!J4-'YTD P&L'!I4 | M4: ='ANNL P&L'!E4-'YTD P&L'!J4 | N4: ='YTD P&L'!K4 | O4: ='YTD P&L'!L4-'YTD P&L'!K4 | P4: ='YTD P&L'!M4-'YTD P&L'!L4 | Q4: ='ANNL P&L'!F4-'YTD P&L'!M4 | R4: ='YTD P&L'!N4 | S4: ='YTD P&L'!O4-'YTD P&L'!N4 | T4: ='YTD P&L'!P4-'YTD P&L'!O4 | U4: ='ANNL P&L'!G4-'YTD P&L'!P4 | V4: ='YTD P&L'!Q4 | W4: ='YTD P&L'!R4-'YTD P&L'!Q4 | X4: ='YTD P&L'!S4-'YTD P&L'!R4 | Y4: ='ANNL P&L'!H4-'YTD P&L'!S4 | Z4: ='YTD P&L'!T4 | AA4: ='YTD P&L'!U4-'YTD P&L'!T4 | AB4: ='YTD P&L'!V4-'YTD P&L'!U4 | AC4: ='ANNL P&L'!I4-'YTD P&L'!V4 | AD4: ='YTD P&L'!W4 | AE4: ='YTD P&L'!X4-'YTD P&L'!W4 | AF4: ='YTD P&L'!Y4-'YTD P&L'!X4 | AG4: ='ANNL P&L'!J4-'YTD P&L'!Y4 | AH4: =AH2+AH3 | AI4: =AI2+AI3 | AJ4: =AJ2+AJ3 | AK4: =AK2+AK3 | AL4: =AL2+AL3 | AM4: =AM2+AM3 | AN4: =AN2+AN3 | AO4: =AO2+AO3 | ... BA4: =BA2+BA3
A5: Research and Development | B5: ='YTD P&L'!B5 | C5: ='YTD P&L'!C5-'YTD P&L'!B5 | D5: ='YTD P&L'!D5-'YTD P&L'!C5 | E5: ='ANNL P&L'!C5-'YTD P&L'!D5 | F5: ='YTD P&L'!E5 | G5: ='YTD P&L'!F5-'YTD P&L'!E5 | H5: ='YTD P&L'!G5-'YTD P&L'!F5 | I5: ='ANNL P&L'!D5-'YTD P&L'!G5 | J5: ='YTD P&L'!H5 | K5: ='YTD P&L'!I5-'YTD P&L'!H5 | L5: ='YTD P&L'!J5-'YTD P&L'!I5 | M5: ='ANNL P&L'!E5-'YTD P&L'!J5 | N5: ='YTD P&L'!K5 | O5: ='YTD P&L'!L5-'YTD P&L'!K5 | P5: ='YTD P&L'!M5-'YTD P&L'!L5 | Q5: ='ANNL P&L'!F5-'YTD P&L'!M5 | R5: ='YTD P&L'!N5 | S5: ='YTD P&L'!O5-'YTD P&L'!N5 | T5: ='YTD P&L'!P5-'YTD P&L'!O5 | U5: ='ANNL P&L'!G5-'YTD P&L'!P5 | V5: ='YTD P&L'!Q5 | W5: ='YTD P&L'!R5-'YTD P&L'!Q5 | X5: ='YTD P&L'!S5-'YTD P&L'!R5 | Y5: ='ANNL P&L'!H5-'YTD P&L'!S5 | Z5: ='YTD P&L'!T5 | AA5: ='YTD P&L'!U5-'YTD P&L'!T5 | AB5: ='YTD P&L'!V5-'YTD P&L'!U5 | AC5: ='ANNL P&L'!I5-'YTD P&L'!V5 | AD5: ='YTD P&L'!W5 | AE5: ='YTD P&L'!X5-'YTD P&L'!W5 | AF5: ='YTD P&L'!Y5-'YTD P&L'!X5 | AG5: ='ANNL P&L'!J5-'YTD P&L'!Y5 | AH5: ='QTR P&L'!AH2*'IS DRIVERS'!AI4 | AI5: ='QTR P&L'!AI2*'IS DRIVERS'!AJ4 | AJ5: ='QTR P&L'!AJ2*'IS DRIVERS'!AK4 | AK5: ='QTR P&L'!AK2*'IS DRIVERS'!AL4 | AL5: ='QTR P&L'!AL2*'IS DRIVERS'!AM4 | AM5: ='QTR P&L'!AM2*'IS DRIVERS'!AN4 | AN5: ='QTR P&L'!AN2*'IS DRIVERS'!AO4 | AO5: ='QTR P&L'!AO2*'IS DRIVERS'!AP4 | ... BA5: ='QTR P&L'!BA2*'IS DRIVERS'!BB4
A6: Sales and Marketing | B6: ='YTD P&L'!B6 | C6: ='YTD P&L'!C6-'YTD P&L'!B6 | D6: ='YTD P&L'!D6-'YTD P&L'!C6 | E6: ='ANNL P&L'!C6-'YTD P&L'!D6 | F6: ='YTD P&L'!E6 | G6: ='YTD P&L'!F6-'YTD P&L'!E6 | H6: ='YTD P&L'!G6-'YTD P&L'!F6 | I6: ='ANNL P&L'!D6-'YTD P&L'!G6 | J6: ='YTD P&L'!H6 | K6: ='YTD P&L'!I6-'YTD P&L'!H6 | L6: ='YTD P&L'!J6-'YTD P&L'!I6 | M6: ='ANNL P&L'!E6-'YTD P&L'!J6 | N6: ='YTD P&L'!K6 | O6: ='YTD P&L'!L6-'YTD P&L'!K6 | P6: ='YTD P&L'!M6-'YTD P&L'!L6 | Q6: ='ANNL P&L'!F6-'YTD P&L'!M6 | R6: ='YTD P&L'!N6 | S6: ='YTD P&L'!O6-'YTD P&L'!N6 | T6: ='YTD P&L'!P6-'YTD P&L'!O6 | U6: ='ANNL P&L'!G6-'YTD P&L'!P6 | V6: ='YTD P&L'!Q6 | W6: ='YTD P&L'!R6-'YTD P&L'!Q6 | X6: ='YTD P&L'!S6-'YTD P&L'!R6 | Y6: ='ANNL P&L'!H6-'YTD P&L'!S6 | Z6: ='YTD P&L'!T6 | AA6: ='YTD P&L'!U6-'YTD P&L'!T6 | AB6: ='YTD P&L'!V6-'YTD P&L'!U6 | AC6: ='ANNL P&L'!I6-'YTD P&L'!V6 | AD6: ='YTD P&L'!W6 | AE6: ='YTD P&L'!X6-'YTD P&L'!W6 | AF6: ='YTD P&L'!Y6-'YTD P&L'!X6 | AG6: ='ANNL P&L'!J6-'YTD P&L'!Y6 | AH6: ='QTR P&L'!AH2*'IS DRIVERS'!AI5 | AI6: ='QTR P&L'!AI2*'IS DRIVERS'!AJ5 | AJ6: ='QTR P&L'!AJ2*'IS DRIVERS'!AK5 | AK6: ='QTR P&L'!AK2*'IS DRIVERS'!AL5 | AL6: ='QTR P&L'!AL2*'IS DRIVERS'!AM5 | AM6: ='QTR P&L'!AM2*'IS DRIVERS'!AN5 | AN6: ='QTR P&L'!AN2*'IS DRIVERS'!AO5 | AO6: ='QTR P&L'!AO2*'IS DRIVERS'!AP5 | ... BA6: ='QTR P&L'!BA2*'IS DRIVERS'!BB5
A7: General and Administrative | B7: ='YTD P&L'!B7 | C7: ='YTD P&L'!C7-'YTD P&L'!B7 | D7: ='YTD P&L'!D7-'YTD P&L'!C7 | E7: ='ANNL P&L'!C7-'YTD P&L'!D7 | F7: ='YTD P&L'!E7 | G7: ='YTD P&L'!F7-'YTD P&L'!E7 | H7: ='YTD P&L'!G7-'YTD P&L'!F7 | I7: ='ANNL P&L'!D7-'YTD P&L'!G7 | J7: ='YTD P&L'!H7 | K7: ='YTD P&L'!I7-'YTD P&L'!H7 | L7: ='YTD P&L'!J7-'YTD P&L'!I7 | M7: ='ANNL P&L'!E7-'YTD P&L'!J7 | N7: ='YTD P&L'!K7 | O7: ='YTD P&L'!L7-'YTD P&L'!K7 | P7: ='YTD P&L'!M7-'YTD P&L'!L7 | Q7: ='ANNL P&L'!F7-'YTD P&L'!M7 | R7: ='YTD P&L'!N7 | S7: ='YTD P&L'!O7-'YTD P&L'!N7 | T7: ='YTD P&L'!P7-'YTD P&L'!O7 | U7: ='ANNL P&L'!G7-'YTD P&L'!P7 | V7: ='YTD P&L'!Q7 | W7: ='YTD P&L'!R7-'YTD P&L'!Q7 | X7: ='YTD P&L'!S7-'YTD P&L'!R7 | Y7: ='ANNL P&L'!H7-'YTD P&L'!S7 | Z7: ='YTD P&L'!T7 | AA7: ='YTD P&L'!U7-'YTD P&L'!T7 | AB7: ='YTD P&L'!V7-'YTD P&L'!U7 | AC7: ='ANNL P&L'!I7-'YTD P&L'!V7 | AD7: ='YTD P&L'!W7 | AE7: ='YTD P&L'!X7-'YTD P&L'!W7 | AF7: ='YTD P&L'!Y7-'YTD P&L'!X7 | AG7: ='ANNL P&L'!J7-'YTD P&L'!Y7 | AH7: ='QTR P&L'!AH2*'IS DRIVERS'!AI6 | AI7: ='QTR P&L'!AI2*'IS DRIVERS'!AJ6 | AJ7: ='QTR P&L'!AJ2*'IS DRIVERS'!AK6 | AK7: ='QTR P&L'!AK2*'IS DRIVERS'!AL6 | AL7: ='QTR P&L'!AL2*'IS DRIVERS'!AM6 | AM7: ='QTR P&L'!AM2*'IS DRIVERS'!AN6 | AN7: ='QTR P&L'!AN2*'IS DRIVERS'!AO6 | AO7: ='QTR P&L'!AO2*'IS DRIVERS'!AP6 | ... BA7: ='QTR P&L'!BA2*'IS DRIVERS'!BB6
A8: Litigation and Regulatory Charges | B8: ='YTD P&L'!B8 | C8: ='YTD P&L'!C8-'YTD P&L'!B8 | D8: ='YTD P&L'!D8-'YTD P&L'!C8 | E8: ='ANNL P&L'!C8-'YTD P&L'!D8 | F8: ='YTD P&L'!E8 | G8: ='YTD P&L'!F8-'YTD P&L'!E8 | H8: ='YTD P&L'!G8-'YTD P&L'!F8 | I8: ='ANNL P&L'!D8-'YTD P&L'!G8 | J8: ='YTD P&L'!H8 | K8: ='YTD P&L'!I8-'YTD P&L'!H8 | L8: ='YTD P&L'!J8-'YTD P&L'!I8 | M8: ='ANNL P&L'!E8-'YTD P&L'!J8 | N8: ='YTD P&L'!K8 | O8: ='YTD P&L'!L8-'YTD P&L'!K8 | P8: ='YTD P&L'!M8-'YTD P&L'!L8 | Q8: ='ANNL P&L'!F8-'YTD P&L'!M8 | R8: ='YTD P&L'!N8 | S8: ='YTD P&L'!O8-'YTD P&L'!N8 | T8: ='YTD P&L'!P8-'YTD P&L'!O8 | U8: ='ANNL P&L'!G8-'YTD P&L'!P8 | V8: ='YTD P&L'!Q8 | W8: ='YTD P&L'!R8-'YTD P&L'!Q8 | X8: ='YTD P&L'!S8-'YTD P&L'!R8 | Y8: ='ANNL P&L'!H8-'YTD P&L'!S8 | Z8: ='YTD P&L'!T8 | AA8: ='YTD P&L'!U8-'YTD P&L'!T8 | AB8: ='YTD P&L'!V8-'YTD P&L'!U8 | AC8: ='ANNL P&L'!I8-'YTD P&L'!V8 | AD8: ='YTD P&L'!W8 | AE8: ='YTD P&L'!X8-'YTD P&L'!W8 | AF8: ='YTD P&L'!Y8-'YTD P&L'!X8 | AG8: ='ANNL P&L'!J8-'YTD P&L'!Y8 | AH8: ='QTR P&L'!AH2*'IS DRIVERS'!AI7 | AI8: ='QTR P&L'!AI2*'IS DRIVERS'!AJ7 | AJ8: ='QTR P&L'!AJ2*'IS DRIVERS'!AK7 | AK8: ='QTR P&L'!AK2*'IS DRIVERS'!AL7 | AL8: ='QTR P&L'!AL2*'IS DRIVERS'!AM7 | AM8: ='QTR P&L'!AM2*'IS DRIVERS'!AN7 | AN8: ='QTR P&L'!AN2*'IS DRIVERS'!AO7 | AO8: ='QTR P&L'!AO2*'IS DRIVERS'!AP7 | ... BA8: ='QTR P&L'!BA2*'IS DRIVERS'!BB7
A9: Income (Loss) from Operations | B9: ='YTD P&L'!B9 | C9: ='YTD P&L'!C9-'YTD P&L'!B9 | D9: ='YTD P&L'!D9-'YTD P&L'!C9 | E9: ='ANNL P&L'!C9-'YTD P&L'!D9 | F9: ='YTD P&L'!E9 | G9: ='YTD P&L'!F9-'YTD P&L'!E9 | H9: ='YTD P&L'!G9-'YTD P&L'!F9 | I9: ='ANNL P&L'!D9-'YTD P&L'!G9 | J9: ='YTD P&L'!H9 | K9: ='YTD P&L'!I9-'YTD P&L'!H9 | L9: ='YTD P&L'!J9-'YTD P&L'!I9 | M9: ='ANNL P&L'!E9-'YTD P&L'!J9 | N9: ='YTD P&L'!K9 | O9: ='YTD P&L'!L9-'YTD P&L'!K9 | P9: ='YTD P&L'!M9-'YTD P&L'!L9 | Q9: ='ANNL P&L'!F9-'YTD P&L'!M9 | R9: ='YTD P&L'!N9 | S9: ='YTD P&L'!O9-'YTD P&L'!N9 | T9: ='YTD P&L'!P9-'YTD P&L'!O9 | U9: ='ANNL P&L'!G9-'YTD P&L'!P9 | V9: ='YTD P&L'!Q9 | W9: ='YTD P&L'!R9-'YTD P&L'!Q9 | X9: ='YTD P&L'!S9-'YTD P&L'!R9 | Y9: ='ANNL P&L'!H9-'YTD P&L'!S9 | Z9: ='YTD P&L'!T9 | AA9: ='YTD P&L'!U9-'YTD P&L'!T9 | AB9: ='YTD P&L'!V9-'YTD P&L'!U9 | AC9: ='ANNL P&L'!I9-'YTD P&L'!V9 | AD9: ='YTD P&L'!W9 | AE9: ='YTD P&L'!X9-'YTD P&L'!W9 | AF9: ='YTD P&L'!Y9-'YTD P&L'!X9 | AG9: ='ANNL P&L'!J9-'YTD P&L'!Y9 | AH9: =AH4+SUM(AH5:AH8) | AI9: =AI4+SUM(AI5:AI8) | AJ9: =AJ4+SUM(AJ5:AJ8) | AK9: =AK4+SUM(AK5:AK8) | AL9: =AL4+SUM(AL5:AL8) | AM9: =AM4+SUM(AM5:AM8) | AN9: =AN4+SUM(AN5:AN8) | AO9: =AO4+SUM(AO5:AO8) | ... BA9: =BA4+SUM(BA5:BA8)
A10: Other Income (Expense) | B10: ='YTD P&L'!B10 | C10: ='YTD P&L'!C10-'YTD P&L'!B10 | D10: ='YTD P&L'!D10-'YTD P&L'!C10 | E10: ='ANNL P&L'!C10-'YTD P&L'!D10 | F10: ='YTD P&L'!E10 | G10: ='YTD P&L'!F10-'YTD P&L'!E10 | H10: ='YTD P&L'!G10-'YTD P&L'!F10 | I10: ='ANNL P&L'!D10-'YTD P&L'!G10 | J10: ='YTD P&L'!H10 | K10: ='YTD P&L'!I10-'YTD P&L'!H10 | L10: ='YTD P&L'!J10-'YTD P&L'!I10 | M10: ='ANNL P&L'!E10-'YTD P&L'!J10 | N10: ='YTD P&L'!K10 | O10: ='YTD P&L'!L10-'YTD P&L'!K10 | P10: ='YTD P&L'!M10-'YTD P&L'!L10 | Q10: ='ANNL P&L'!F10-'YTD P&L'!M10 | R10: ='YTD P&L'!N10 | S10: ='YTD P&L'!O10-'YTD P&L'!N10 | T10: ='YTD P&L'!P10-'YTD P&L'!O10 | U10: ='ANNL P&L'!G10-'YTD P&L'!P10 | V10: ='YTD P&L'!Q10 | W10: ='YTD P&L'!R10-'YTD P&L'!Q10 | X10: ='YTD P&L'!S10-'YTD P&L'!R10 | Y10: ='ANNL P&L'!H10-'YTD P&L'!S10 | Z10: ='YTD P&L'!T10 | AA10: ='YTD P&L'!U10-'YTD P&L'!T10 | AB10: ='YTD P&L'!V10-'YTD P&L'!U10 | AC10: ='ANNL P&L'!I10-'YTD P&L'!V10 | AD10: ='YTD P&L'!W10 | AE10: ='YTD P&L'!X10-'YTD P&L'!W10 | AF10: ='YTD P&L'!Y10-'YTD P&L'!X10 | AG10: ='ANNL P&L'!J10-'YTD P&L'!Y10 | AH10: ='IS DRIVERS'!AI8 | AI10: ='IS DRIVERS'!AJ8 | AJ10: ='IS DRIVERS'!AK8 | AK10: ='IS DRIVERS'!AL8 | AL10: ='IS DRIVERS'!AM8 | AM10: ='IS DRIVERS'!AN8 | AN10: ='IS DRIVERS'!AO8 | AO10: ='IS DRIVERS'!AP8 | ... BA10: ='IS DRIVERS'!BB8
A11: Pre-Tax Income (Loss) | B11: ='YTD P&L'!B11 | C11: ='YTD P&L'!C11-'YTD P&L'!B11 | D11: ='YTD P&L'!D11-'YTD P&L'!C11 | E11: ='ANNL P&L'!C11-'YTD P&L'!D11 | F11: ='YTD P&L'!E11 | G11: ='YTD P&L'!F11-'YTD P&L'!E11 | H11: ='YTD P&L'!G11-'YTD P&L'!F11 | I11: ='ANNL P&L'!D11-'YTD P&L'!G11 | J11: ='YTD P&L'!H11 | K11: ='YTD P&L'!I11-'YTD P&L'!H11 | L11: ='YTD P&L'!J11-'YTD P&L'!I11 | M11: ='ANNL P&L'!E11-'YTD P&L'!J11 | N11: ='YTD P&L'!K11 | O11: ='YTD P&L'!L11-'YTD P&L'!K11 | P11: ='YTD P&L'!M11-'YTD P&L'!L11 | Q11: ='ANNL P&L'!F11-'YTD P&L'!M11 | R11: ='YTD P&L'!N11 | S11: ='YTD P&L'!O11-'YTD P&L'!N11 | T11: ='YTD P&L'!P11-'YTD P&L'!O11 | U11: ='ANNL P&L'!G11-'YTD P&L'!P11 | V11: ='YTD P&L'!Q11 | W11: ='YTD P&L'!R11-'YTD P&L'!Q11 | X11: ='YTD P&L'!S11-'YTD P&L'!R11 | Y11: ='ANNL P&L'!H11-'YTD P&L'!S11 | Z11: ='YTD P&L'!T11 | AA11: ='YTD P&L'!U11-'YTD P&L'!T11 | AB11: ='YTD P&L'!V11-'YTD P&L'!U11 | AC11: ='ANNL P&L'!I11-'YTD P&L'!V11 | AD11: ='YTD P&L'!W11 | AE11: ='YTD P&L'!X11-'YTD P&L'!W11 | AF11: ='YTD P&L'!Y11-'YTD P&L'!X11 | AG11: ='ANNL P&L'!J11-'YTD P&L'!Y11 | AH11: =AH9+AH10 | AI11: =AI9+AI10 | AJ11: =AJ9+AJ10 | AK11: =AK9+AK10 | AL11: =AL9+AL10 | AM11: =AM9+AM10 | AN11: =AN9+AN10 | AO11: =AO9+AO10 | ... BA11: =BA9+BA10
A12: Income Tax (Expense) Benefit | B12: ='YTD P&L'!B12 | C12: ='YTD P&L'!C12-'YTD P&L'!B12 | D12: ='YTD P&L'!D12-'YTD P&L'!C12 | E12: ='ANNL P&L'!C12-'YTD P&L'!D12 | F12: ='YTD P&L'!E12 | G12: ='YTD P&L'!F12-'YTD P&L'!E12 | H12: ='YTD P&L'!G12-'YTD P&L'!F12 | I12: ='ANNL P&L'!D12-'YTD P&L'!G12 | J12: ='YTD P&L'!H12 | K12: ='YTD P&L'!I12-'YTD P&L'!H12 | L12: ='YTD P&L'!J12-'YTD P&L'!I12 | M12: ='ANNL P&L'!E12-'YTD P&L'!J12 | N12: ='YTD P&L'!K12 | O12: ='YTD P&L'!L12-'YTD P&L'!K12 | P12: ='YTD P&L'!M12-'YTD P&L'!L12 | Q12: ='ANNL P&L'!F12-'YTD P&L'!M12 | R12: ='YTD P&L'!N12 | S12: ='YTD P&L'!O12-'YTD P&L'!N12 | T12: ='YTD P&L'!P12-'YTD P&L'!O12 | U12: ='ANNL P&L'!G12-'YTD P&L'!P12 | V12: ='YTD P&L'!Q12 | W12: ='YTD P&L'!R12-'YTD P&L'!Q12 | X12: ='YTD P&L'!S12-'YTD P&L'!R12 | Y12: ='ANNL P&L'!H12-'YTD P&L'!S12 | Z12: ='YTD P&L'!T12 | AA12: ='YTD P&L'!U12-'YTD P&L'!T12 | AB12: ='YTD P&L'!V12-'YTD P&L'!U12 | AC12: ='ANNL P&L'!I12-'YTD P&L'!V12 | AD12: ='YTD P&L'!W12 | AE12: ='YTD P&L'!X12-'YTD P&L'!W12 | AF12: ='YTD P&L'!Y12-'YTD P&L'!X12 | AG12: ='ANNL P&L'!J12-'YTD P&L'!Y12 | AH12: ='QTR P&L'!AH11*'IS DRIVERS'!AI9 | AI12: ='QTR P&L'!AI11*'IS DRIVERS'!AJ9 | AJ12: ='QTR P&L'!AJ11*'IS DRIVERS'!AK9 | AK12: ='QTR P&L'!AK11*'IS DRIVERS'!AL9 | AL12: ='QTR P&L'!AL11*'IS DRIVERS'!AM9 | AM12: ='QTR P&L'!AM11*'IS DRIVERS'!AN9 | AN12: ='QTR P&L'!AN11*'IS DRIVERS'!AO9 | AO12: ='QTR P&L'!AO11*'IS DRIVERS'!AP9 | ... BA12: ='QTR P&L'!BA11*'IS DRIVERS'!BB9
A13: Net Income (Loss) | B13: ='YTD P&L'!B13 | C13: ='YTD P&L'!C13-'YTD P&L'!B13 | D13: ='YTD P&L'!D13-'YTD P&L'!C13 | E13: ='ANNL P&L'!C13-'YTD P&L'!D13 | F13: ='YTD P&L'!E13 | G13: ='YTD P&L'!F13-'YTD P&L'!E13 | H13: ='YTD P&L'!G13-'YTD P&L'!F13 | I13: ='ANNL P&L'!D13-'YTD P&L'!G13 | J13: ='YTD P&L'!H13 | K13: ='YTD P&L'!I13-'YTD P&L'!H13 | L13: ='YTD P&L'!J13-'YTD P&L'!I13 | M13: ='ANNL P&L'!E13-'YTD P&L'!J13 | N13: ='YTD P&L'!K13 | O13: ='YTD P&L'!L13-'YTD P&L'!K13 | P13: ='YTD P&L'!M13-'YTD P&L'!L13 | Q13: ='ANNL P&L'!F13-'YTD P&L'!M13 | R13: ='YTD P&L'!N13 | S13: ='YTD P&L'!O13-'YTD P&L'!N13 | T13: ='YTD P&L'!P13-'YTD P&L'!O13 | U13: ='ANNL P&L'!G13-'YTD P&L'!P13 | V13: ='YTD P&L'!Q13 | W13: ='YTD P&L'!R13-'YTD P&L'!Q13 | X13: ='YTD P&L'!S13-'YTD P&L'!R13 | Y13: ='ANNL P&L'!H13-'YTD P&L'!S13 | Z13: ='YTD P&L'!T13 | AA13: ='YTD P&L'!U13-'YTD P&L'!T13 | AB13: ='YTD P&L'!V13-'YTD P&L'!U13 | AC13: ='ANNL P&L'!I13-'YTD P&L'!V13 | AD13: ='YTD P&L'!W13 | AE13: ='YTD P&L'!X13-'YTD P&L'!W13 | AF13: ='YTD P&L'!Y13-'YTD P&L'!X13 | AG13: ='ANNL P&L'!J13-'YTD P&L'!Y13 | AH13: =AH11+AH12 | AI13: =AI11+AI12 | AJ13: =AJ11+AJ12 | AK13: =AK11+AK12 | AL13: =AL11+AL12 | AM13: =AM11+AM12 | AN13: =AN11+AN12 | AO13: =AO11+AO12 | ... BA13: =BA11+BA12
A14: Basic Earnings (Loss) per Share
A15: Diluted Earnings (Loss) per Share

Sheet QTR BS
B1: Q4 FY2018 | C1: Q1 FY2019 | D1: Q2 FY2019 | E1: Q3 FY2019 | F1: Q4 FY2019 | G1: Q1 FY2020 | H1: Q2 FY2020 | I1: Q3 FY2020 | J1: Q4 FY2020 | K1: Q1 FY2021 | L1: Q2 FY2021 | M1: Q3 FY2021 | N1: Q4 FY2021 | O1: Q1 FY2022 | P1: Q2 FY2022 | Q1: Q3 FY2022 | R1: Q4 FY2022 | S1: Q1 FY2023 | T1: Q2 FY2023 | U1: Q3 FY2023 | V1: Q4 FY2023 | W1: Q1 FY2024 | X1: Q2 FY2024 | Y1: Q3 FY2024 | Z1: Q4 FY2024 | AA1: Q1 FY2025 | AB1: Q2 FY2025 | AC1: Q3 FY2025 | AD1: Q4 FY2025 | AE1: Q1 FY2026E | AF1: Q2 FY2026E | AG1: Q3 FY2026E | AH1: Q4 FY2026E | AI1: Q1 FY2027E | AJ1: Q2 FY2027E | AK1: Q3 FY2027E | AL1: Q4 FY2027E | AM1: Q1 FY2028E | AN1: Q2 FY2028E | AO1: Q3 FY2028E | AP1: Q4 FY2028E | AQ1: Q1 FY2029E | AR1: Q2 FY2029E | AS1: Q3 FY2029E | AT1: Q4 FY2029E | AU1: Q1 FY2030E | AV1: Q2 FY2030E | AW1: Q3 FY2030E | AX1: Q4 FY2030E
A2: Cash & Cash Equivalents | B2: ='BALANCE SHEET'!B2 | C2: ='YTD BS'!C2 | D2: ='YTD BS'!D2 | E2: ='YTD BS'!E2 | F2: ='BALANCE SHEET'!C2 | G2: ='YTD BS'!G2 | H2: ='YTD BS'!H2 | I2: ='YTD BS'!I2 | J2: ='BALANCE SHEET'!D2 | K2: ='YTD BS'!K2 | L2: ='YTD BS'!L2 | M2: ='YTD BS'!M2 | N2: ='BALANCE SHEET'!E2 | O2: ='YTD BS'!O2 | P2: ='YTD BS'!P2 | Q2: ='YTD BS'!Q2 | R2: ='BALANCE SHEET'!F2 | S2: ='YTD BS'!S2 | T2: ='YTD BS'!T2 | U2: ='YTD BS'!U2 | V2: ='BALANCE SHEET'!G2 | W2: ='YTD BS'!W2 | X2: ='YTD BS'!X2 | Y2: ='YTD BS'!Y2 | Z2: ='BALANCE SHEET'!H2 | AA2: ='YTD BS'!AA2 | AB2: ='YTD BS'!AB2 | AC2: ='YTD BS'!AC2 | AD2: ='BALANCE SHEET'!I2 | AE2: ='BS DRIVERS'!AE2 | AF2: ='BS DRIVERS'!AF2 | AG2: ='BS DRIVERS'!AG2 | AH2: ='BS DRIVERS'!AH2 | AI2: ='BS DRIVERS'!AI2 | AJ2: ='BS DRIVERS'!AJ2 | AK2: ='BS DRIVERS'!AK2 | AL2: ='BS DRIVERS'!AL2 | ... AX2: ='BS DRIVERS'!AX2
A3: Short-Term Investments | B3: ='BALANCE SHEET'!B3 | C3: ='YTD BS'!C3 | D3: ='YTD BS'!D3 | E3: ='YTD BS'!E3 | F3: ='BALANCE SHEET'!C3 | G3: ='YTD BS'!G3 | H3: ='YTD BS'!H3 | I3: ='YTD BS'!I3 | J3: ='BALANCE SHEET'!D3 | K3: ='YTD BS'!K3 | L3: ='YTD BS'!L3 | M3: ='YTD BS'!M3 | N3: ='BALANCE SHEET'!E3 | O3: ='YTD BS'!O3 | P3: ='YTD BS'!P3 | Q3: ='YTD BS'!Q3 | R3: ='BALANCE SHEET'!F3 | S3: ='YTD BS'!S3 | T3: ='YTD BS'!T3 | U3: ='YTD BS'!U3 | V3: ='BALANCE SHEET'!G3 | W3: ='YTD BS'!W3 | X3: ='YTD BS'!X3 | Y3: ='YTD BS'!Y3 | Z3: ='BALANCE SHEET'!H3 | AA3: ='YTD BS'!AA3 | AB3: ='YTD BS'!AB3 | AC3: ='YTD BS'!AC3 | AD3: ='BALANCE SHEET'!I3 | AE3: ='BS DRIVERS'!AE3 | AF3: ='BS DRIVERS'!AF3 | AG3: ='BS DRIVERS'!AG3 | AH3: ='BS DRIVERS'!AH3 | AI3: ='BS DRIVERS'!AI3 | AJ3: ='BS DRIVERS'!AJ3 | AK3: ='BS DRIVERS'!AK3 | AL3: ='BS DRIVERS'!AL3 | ... AX3: ='BS DRIVERS'!AX3
A4: Accounts Receivable | B4: ='BALANCE SHEET'!B4 | C4: ='YTD BS'!C4 | D4: ='YTD BS'!D4 | E4: ='YTD BS'!E4 | F4: ='BALANCE SHEET'!C4 | G4: ='YTD BS'!G4 | H4: ='YTD BS'!H4 | I4: ='YTD BS'!I4 | J4: ='BALANCE SHEET'!D4 | K4: ='YTD BS'!K4 | L4: ='YTD BS'!L4 | M4: ='YTD BS'!M4 | N4: ='BALANCE SHEET'!E4 | O4: ='YTD BS'!O4 | P4: ='YTD BS'!P4 | Q4: ='YTD BS'!Q4 | R4: ='BALANCE SHEET'!F4 | S4: ='YTD BS'!S4 | T4: ='YTD BS'!T4 | U4: ='YTD BS'!U4 | V4: ='BALANCE SHEET'!G4 | W4: ='YTD BS'!W4 | X4: ='YTD BS'!X4 | Y4: ='YTD BS'!Y4 | Z4: ='BALANCE SHEET'!H4 | AA4: ='YTD BS'!AA4 | AB4: ='YTD BS'!AB4 | AC4: ='YTD BS'!AC4 | AD4: ='BALANCE SHEET'!I4 | AE4: ='QTR P&L'!AH2*'BS DRIVERS'!AE4/ASSUMPTIONS!$B$2 | AF4: ='QTR P&L'!AI2*'BS DRIVERS'!AF4/ASSUMPTIONS!$B$2 | AG4: ='QTR P&L'!AJ2*'BS DRIVERS'!AG4/ASSUMPTIONS!$B$2 | AH4: ='QTR P&L'!AK2*'BS DRIVERS'!AH4/ASSUMPTIONS!$B$2 | AI4: ='QTR P&L'!AL2*'BS DRIVERS'!AI4/ASSUMPTIONS!$B$2 | AJ4: ='QTR P&L'!AM2*'BS DRIVERS'!AJ4/ASSUMPTIONS!$B$2 | AK4: ='QTR P&L'!AN2*'BS DRIVERS'!AK4/ASSUMPTIONS!$B$2 | AL4: ='QTR P&L'!AO2*'BS DRIVERS'!AL4/ASSUMPTIONS!$B$2 | ... AX4: ='QTR P&L'!BA2*'BS DRIVERS'!AX4/ASSUMPTIONS!$B$2
A5: Note Receivable - Current | B5: ='BALANCE SHEET'!B5 | C5: ='YTD BS'!C5 | D5: ='YTD BS'!D5 | E5: ='YTD BS'!E5 | F5: ='BALANCE SHEET'!C5 | G5: ='YTD BS'!G5 | H5: ='YTD BS'!H5 | I5: ='YTD BS'!I5 | J5: ='BALANCE SHEET'!D5 | K5: ='YTD BS'!K5 | L5: ='YTD BS'!L5 | M5: ='YTD BS'!M5 | N5: ='BALANCE SHEET'!E5 | O5: ='YTD BS'!O5 | P5: ='YTD BS'!P5 | Q5: ='YTD BS'!Q5 | R5: ='BALANCE SHEET'!F5 | S5: ='YTD BS'!S5 | T5: ='YTD BS'!T5 | U5: ='YTD BS'!U5 | V5: ='BALANCE SHEET'!G5 | W5: ='YTD BS'!W5 | X5: ='YTD BS'!X5 | Y5: ='YTD BS'!Y5 | Z5: ='BALANCE SHEET'!H5 | AA5: ='YTD BS'!AA5 | AB5: ='YTD BS'!AB5 | AC5: ='YTD BS'!AC5 | AD5: ='BALANCE SHEET'!I5 | AE5: ='QTR P&L'!AH2*'BS DRIVERS'!AE5/ASSUMPTIONS!$B$2 | AF5: ='QTR P&L'!AI2*'BS DRIVERS'!AF5/ASSUMPTIONS!$B$2 | AG5: ='QTR P&L'!AJ2*'BS DRIVERS'!AG5/ASSUMPTIONS!$B$2 | AH5: ='QTR P&L'!AK2*'BS DRIVERS'!AH5/ASSUMPTIONS!$B$2 | AI5: ='QTR P&L'!AL2*'BS DRIVERS'!AI5/ASSUMPTIONS!$B$2 | AJ5: ='QTR P&L'!AM2*'BS DRIVERS'!AJ5/ASSUMPTIONS!$B$2 | AK5: ='QTR P&L'!AN2*'BS DRIVERS'!AK5/ASSUMPTIONS!$B$2 | AL5: ='QTR P&L'!AO2*'BS DRIVERS'!AL5/ASSUMPTIONS!$B$2 | ... AX5: ='QTR P&L'!BA2*'BS DRIVERS'!AX5/ASSUMPTIONS!$B$2
A6: Inventories | B6: ='BALANCE SHEET'!B6 | C6: ='YTD BS'!C6 | D6: ='YTD BS'!D6 | E6: ='YTD BS'!E6 | F6: ='BALANCE SHEET'!C6 | G6: ='YTD BS'!G6 | H6: ='YTD BS'!H6 | I6: ='YTD BS'!I6 | J6: ='BALANCE SHEET'!D6 | K6: ='YTD BS'!K6 | L6: ='YTD BS'!L6 | M6: ='YTD BS'!M6 | N6: ='BALANCE SHEET'!E6 | O6: ='YTD BS'!O6 | P6: ='YTD BS'!P6 | Q6: ='YTD BS'!Q6 | R6: ='BALANCE SHEET'!F6 | S6: ='YTD BS'!S6 | T6: ='YTD BS'!T6 | U6: ='YTD BS'!U6 | V6: ='BALANCE SHEET'!G6 | W6: ='YTD BS'!W6 | X6: ='YTD BS'!X6 | Y6: ='YTD BS'!Y6 | Z6: ='BALANCE SHEET'!H6 | AA6: ='YTD BS'!AA6 | AB6: ='YTD BS'!AB6 | AC6: ='YTD BS'!AC6 | AD6: ='BALANCE SHEET'!I6 | AE6: ='QTR P&L'!AH3*'BS DRIVERS'!AE6/ASSUMPTIONS!$B$2 | AF6: ='QTR P&L'!AI3*'BS DRIVERS'!AF6/ASSUMPTIONS!$B$2 | AG6: ='QTR P&L'!AJ3*'BS DRIVERS'!AG6/ASSUMPTIONS!$B$2 | AH6: ='QTR P&L'!AK3*'BS DRIVERS'!AH6/ASSUMPTIONS!$B$2 | AI6: ='QTR P&L'!AL3*'BS DRIVERS'!AI6/ASSUMPTIONS!$B$2 | AJ6: ='QTR P&L'!AM3*'BS DRIVERS'!AJ6/ASSUMPTIONS!$B$2 | AK6: ='QTR P&L'!AN3*'BS DRIVERS'!AK6/ASSUMPTIONS!$B$2 | AL6: ='QTR P&L'!AO3*'BS DRIVERS'!AL6/ASSUMPTIONS!$B$2 | ... AX6: ='QTR P&L'!BA3*'BS DRIVERS'!AX6/ASSUMPTIONS!$B$2
A7: Other Current Assets | B7: ='BALANCE SHEET'!B7 | C7: ='YTD BS'!C7 | D7: ='YTD BS'!D7 | E7: ='YTD BS'!E7 | F7: ='BALANCE SHEET'!C7 | G7: ='YTD BS'!G7 | H7: ='YTD BS'!H7 | I7: ='YTD BS'!I7 | J7: ='BALANCE SHEET'!D7 | K7: ='YTD BS'!K7 | L7: ='YTD BS'!L7 | M7: ='YTD BS'!M7 | N7: ='BALANCE SHEET'!E7 | O7: ='YTD BS'!O7 | P7: ='YTD BS'!P7 | Q7: ='YTD BS'!Q7 | R7: ='BALANCE SHEET'!F7 | S7: ='YTD BS'!S7 | T7: ='YTD BS'!T7 | U7: ='YTD BS'!U7 | V7: ='BALANCE SHEET'!G7 | W7: ='YTD BS'!W7 | X7: ='YTD BS'!X7 | Y7: ='YTD BS'!Y7 | Z7: ='BALANCE SHEET'!H7 | AA7: ='YTD BS'!AA7 | AB7: ='YTD BS'!AB7 | AC7: ='YTD BS'!AC7 | AD7: ='BALANCE SHEET'!I7 | AE7: ='QTR P&L'!AH2*'BS DRIVERS'!AE7 | AF7: ='QTR P&L'!AI2*'BS DRIVERS'!AF7 | AG7: ='QTR P&L'!AJ2*'BS DRIVERS'!AG7 | AH7: ='QTR P&L'!AK2*'BS DRIVERS'!AH7 | AI7: ='QTR P&L'!AL2*'BS DRIVERS'!AI7 | AJ7: ='QTR P&L'!AM2*'BS DRIVERS'!AJ7 | AK7: ='QTR P&L'!AN2*'BS DRIVERS'!AK7 | AL7: ='QTR P&L'!AO2*'BS DRIVERS'!AL7 | ... AX7: ='QTR P&L'!BA2*'BS DRIVERS'!AX7
A8: Total Current Assets | B8: ='BALANCE SHEET'!B8 | C8: ='YTD BS'!C8 | D8: ='YTD BS'!D8 | E8: ='YTD BS'!E8 | F8: ='BALANCE SHEET'!C8 | G8: ='YTD BS'!G8 | H8: ='YTD BS'!H8 | I8: ='YTD BS'!I8 | J8: ='BALANCE SHEET'!D8 | K8: ='YTD BS'!K8 | L8: ='YTD BS'!L8 | M8: ='YTD BS'!M8 | N8: ='BALANCE SHEET'!E8 | O8: ='YTD BS'!O8 | P8: ='YTD BS'!P8 | Q8: ='YTD BS'!Q8 | R8: ='BALANCE SHEET'!F8 | S8: ='YTD BS'!S8 | T8: ='YTD BS'!T8 | U8: ='YTD BS'!U8 | V8: ='BALANCE SHEET'!G8 | W8: ='YTD BS'!W8 | X8: ='YTD BS'!X8 | Y8: ='YTD BS'!Y8 | Z8: ='BALANCE SHEET'!H8 | AA8: ='YTD BS'!AA8 | AB8: ='YTD BS'!AB8 | AC8: ='YTD BS'!AC8 | AD8: ='BALANCE SHEET'!I8 | AE8: =SUM(AE2:AE7) | AF8: =SUM(AF2:AF7) | AG8: =SUM(AG2:AG7) | AH8: =SUM(AH2:AH7) | AI8: =SUM(AI2:AI7) | AJ8: =SUM(AJ2:AJ7) | AK8: =SUM(AK2:AK7) | AL8: =SUM(AL2:AL7) | ... AX8: =SUM(AX2:AX7)
A9: Long-Term Investments | B9: ='BALANCE SHEET'!B9 | C9: ='YTD BS'!C9 | D9: ='YTD BS'!D9 | E9: ='YTD BS'!E9 | F9: ='BALANCE SHEET'!C9 | G9: ='YTD BS'!G9 | H9: ='YTD BS'!H9 | I9: ='YTD BS'!I9 | J9: ='BALANCE SHEET'!D9 | K9: ='YTD BS'!K9 | L9: ='YTD BS'!L9 | M9: ='YTD BS'!M9 | N9: ='BALANCE SHEET'!E9 | O9: ='YTD BS'!O9 | P9: ='YTD BS'!P9 | Q9: ='YTD BS'!Q9 | R9: ='BALANCE SHEET'!F9 | S9: ='YTD BS'!S9 | T9: ='YTD BS'!T9 | U9: ='YTD BS'!U9 | V9: ='BALANCE SHEET'!G9 | W9: ='YTD BS'!W9 | X9: ='YTD BS'!X9 | Y9: ='YTD BS'!Y9 | Z9: ='BALANCE SHEET'!H9 | AA9: ='YTD BS'!AA9 | AB9: ='YTD BS'!AB9 | AC9: ='YTD BS'!AC9 | AD9: ='BALANCE SHEET'!I9 | AE9: ='QTR P&L'!AH2*'BS DRIVERS'!AE8 | AF9: ='QTR P&L'!AI2*'BS DRIVERS'!AF8 | AG9: ='QTR P&L'!AJ2*'BS DRIVERS'!AG8 | AH9: ='QTR P&L'!AK2*'BS DRIVERS'!AH8 | AI9: ='QTR P&L'!AL2*'BS DRIVERS'!AI8 | AJ9: ='QTR P&L'!AM2*'BS DRIVERS'!AJ8 | AK9: ='QTR P&L'!AN2*'BS DRIVERS'!AK8 | AL9: ='QTR P&L'!AO2*'BS DRIVERS'!AL8 | ... AX9: ='QTR P&L'!BA2*'BS DRIVERS'!AX8
A10: Deferred Tax Assets | B10: ='BALANCE SHEET'!B10 | C10: ='YTD BS'!C10 | D10: ='YTD BS'!D10 | E10: ='YTD BS'!E10 | F10: ='BALANCE SHEET'!C10 | G10: ='YTD BS'!G10 | H10: ='YTD BS'!H10 | I10: ='YTD BS'!I10 | J10: ='BALANCE SHEET'!D10 | K10: ='YTD BS'!K10 | L10: ='YTD BS'!L10 | M10: ='YTD BS'!M10 | N10: ='BALANCE SHEET'!E10 | O10: ='YTD BS'!O10 | P10: ='YTD BS'!P10 | Q10: ='YTD BS'!Q10 | R10: ='BALANCE SHEET'!F10 | S10: ='YTD BS'!S10 | T10: ='YTD BS'!T10 | U10: ='YTD BS'!U10 | V10: ='BALANCE SHEET'!G10 | W10: ='YTD BS'!W10 | X10: ='YTD BS'!X10 | Y10: ='YTD BS'!Y10 | Z10: ='BALANCE SHEET'!H10 | AA10: ='YTD BS'!AA10 | AB10: ='YTD BS'!AB10 | AC10: ='YTD BS'!AC10 | AD10: ='BALANCE SHEET'!I10 | AE10: ='BS DRIVERS'!AE9 | AF10: ='BS DRIVERS'!AF9 | AG10: ='BS DRIVERS'!AG9 | AH10: ='BS DRIVERS'!AH9 | AI10: ='BS DRIVERS'!AI9 | AJ10: ='BS DRIVERS'!AJ9 | AK10: ='BS DRIVERS'!AK9 | AL10: ='BS DRIVERS'!AL9 | ... AX10: ='BS DRIVERS'!AX9
A11: Net PP&E | B11: ='BALANCE SHEET'!B11 | C11: ='YTD BS'!C11 | D11: ='YTD BS'!D11 | E11: ='YTD BS'!E11 | F11: ='BALANCE SHEET'!C11 | G11: ='YTD BS'!G11 | H11: ='YTD BS'!H11 | I11: ='YTD BS'!I11 | J11: ='BALANCE SHEET'!D11 | K11: ='YTD BS'!K11 | L11: ='YTD BS'!L11 | M11: ='YTD BS'!M11 | N11: ='BALANCE SHEET'!E11 | O11: ='YTD BS'!O11 | P11: ='YTD BS'!P11 | Q11: ='YTD BS'!Q11 | R11: ='BALANCE SHEET'!F11 | S11: ='YTD BS'!S11 | T11: ='YTD BS'!T11 | U11: ='YTD BS'!U11 | V11: ='BALANCE SHEET'!G11 | W11: ='YTD BS'!W11 | X11: ='YTD BS'!X11 | Y11: ='YTD BS'!Y11 | Z11: ='BALANCE SHEET'!H11 | AA11: ='YTD BS'!AA11 | AB11: ='YTD BS'!AB11 | AC11: ='YTD BS'!AC11 | AD11: ='BALANCE SHEET'!I11 | AE11: ='BS DRIVERS'!AE10 | AF11: ='BS DRIVERS'!AF10 | AG11: ='BS DRIVERS'!AG10 | AH11: ='BS DRIVERS'!AH10 | AI11: ='BS DRIVERS'!AI10 | AJ11: ='BS DRIVERS'!AJ10 | AK11: ='BS DRIVERS'!AK10 | AL11: ='BS DRIVERS'!AL10 | ... AX11: ='BS DRIVERS'!AX10
A12: ROU Assets - Operating - Non-Current | B12: ='BALANCE SHEET'!B12 | C12: ='YTD BS'!C12 | D12: ='YTD BS'!D12 | E12: ='YTD BS'!E12 | F12: ='BALANCE SHEET'!C12 | G12: ='YTD BS'!G12 | H12: ='YTD BS'!H12 | I12: ='YTD BS'!I12 | J12: ='BALANCE SHEET'!D12 | K12: ='YTD BS'!K12 | L12: ='YTD BS'!L12 | M12: ='YTD BS'!M12 | N12: ='BALANCE SHEET'!E12 | O12: ='YTD BS'!O12 | P12: ='YTD BS'!P12 | Q12: ='YTD BS'!Q12 | R12: ='BALANCE SHEET'!F12 | S12: ='YTD BS'!S12 | T12: ='YTD BS'!T12 | U12: ='YTD BS'!U12 | V12: ='BALANCE SHEET'!G12 | W12: ='YTD BS'!W12 | X12: ='YTD BS'!X12 | Y12: ='YTD BS'!Y12 | Z12: ='BALANCE SHEET'!H12 | AA12: ='YTD BS'!AA12 | AB12: ='YTD BS'!AB12 | AC12: ='YTD BS'!AC12 | AD12: ='BALANCE SHEET'!I12 | AE12: ='QTR P&L'!AH2*'BS DRIVERS'!AE11 | AF12: ='QTR P&L'!AI2*'BS DRIVERS'!AF11 | AG12: ='QTR P&L'!AJ2*'BS DRIVERS'!AG11 | AH12: ='QTR P&L'!AK2*'BS DRIVERS'!AH11 | AI12: ='QTR P&L'!AL2*'BS DRIVERS'!AI11 | AJ12: ='QTR P&L'!AM2*'BS DRIVERS'!AJ11 | AK12: ='QTR P&L'!AN2*'BS DRIVERS'!AK11 | AL12: ='QTR P&L'!AO2*'BS DRIVERS'!AL11 | ... AX12: ='QTR P&L'!BA2*'BS DRIVERS'!AX11
A13: Intangible Assets | B13: ='BALANCE SHEET'!B13 | C13: ='YTD BS'!C13 | D13: ='YTD BS'!D13 | E13: ='YTD BS'!E13 | F13: ='BALANCE SHEET'!C13 | G13: ='YTD BS'!G13 | H13: ='YTD BS'!H13 | I13: ='YTD BS'!I13 | J13: ='BALANCE SHEET'!D13 | K13: ='YTD BS'!K13 | L13: ='YTD BS'!L13 | M13: ='YTD BS'!M13 | N13: ='BALANCE SHEET'!E13 | O13: ='YTD BS'!O13 | P13: ='YTD BS'!P13 | Q13: ='YTD BS'!Q13 | R13: ='BALANCE SHEET'!F13 | S13: ='YTD BS'!S13 | T13: ='YTD BS'!T13 | U13: ='YTD BS'!U13 | V13: ='BALANCE SHEET'!G13 | W13: ='YTD BS'!W13 | X13: ='YTD BS'!X13 | Y13: ='YTD BS'!Y13 | Z13: ='BALANCE SHEET'!H13 | AA13: ='YTD BS'!AA13 | AB13: ='YTD BS'!AB13 | AC13: ='YTD BS'!AC13 | AD13: ='BALANCE SHEET'!I13 | AE13: ='BS DRIVERS'!AE12 | AF13: ='BS DRIVERS'!AF12 | AG13: ='BS DRIVERS'!AG12 | AH13: ='BS DRIVERS'!AH12 | AI13: ='BS DRIVERS'!AI12 | AJ13: ='BS DRIVERS'!AJ12 | AK13: ='BS DRIVERS'!AK12 | AL13: ='BS DRIVERS'!AL12 | ... AX13: ='BS DRIVERS'!AX12
A14: Goodwill | B14: ='BALANCE SHEET'!B14 | C14: ='YTD BS'!C14 | D14: ='YTD BS'!D14 | E14: ='YTD BS'!E14 | F14: ='BALANCE SHEET'!C14 | G14: ='YTD BS'!G14 | H14: ='YTD BS'!H14 | I14: ='YTD BS'!I14 | J14: ='BALANCE SHEET'!D14 | K14: ='YTD BS'!K14 | L14: ='YTD BS'!L14 | M14: ='YTD BS'!M14 | N14: ='BALANCE SHEET'!E14 | O14: ='YTD BS'!O14 | P14: ='YTD BS'!P14 | Q14: ='YTD BS'!Q14 | R14: ='BALANCE SHEET'!F14 | S14: ='YTD BS'!S14 | T14: ='YTD BS'!T14 | U14: ='YTD BS'!U14 | V14: ='BALANCE SHEET'!G14 | W14: ='YTD BS'!W14 | X14: ='YTD BS'!X14 | Y14: ='YTD BS'!Y14 | Z14: ='BALANCE SHEET'!H14 | AA14: ='YTD BS'!AA14 | AB14: ='YTD BS'!AB14 | AC14: ='YTD BS'!AC14 | AD14: ='BALANCE SHEET'!I14 | AE14: ='BS DRIVERS'!AE13 | AF14: ='BS DRIVERS'!AF13 | AG14: ='BS DRIVERS'!AG13 | AH14: ='BS DRIVERS'!AH13 | AI14: ='BS DRIVERS'!AI13 | AJ14: ='BS DRIVERS'!AJ13 | AK14: ='BS DRIVERS'!AK13 | AL14: ='BS DRIVERS'!AL13 | ... AX14: ='BS DRIVERS'!AX13
A15: Other Non-Current Assets | B15: ='BALANCE SHEET'!B15 | C15: ='YTD BS'!C15 | D15: ='YTD BS'!D15 | E15: ='YTD BS'!E15 | F15: ='BALANCE SHEET'!C15 | G15: ='YTD BS'!G15 | H15: ='YTD BS'!H15 | I15: ='YTD BS'!I15 | J15: ='BALANCE SHEET'!D15 | K15: ='YTD BS'!K15 | L15: ='YTD BS'!L15 | M15: ='YTD BS'!M15 | N15: ='BALANCE SHEET'!E15 | O15: ='YTD BS'!O15 | P15: ='YTD BS'!P15 | Q15: ='YTD BS'!Q15 | R15: ='BALANCE SHEET'!F15 | S15: ='YTD BS'!S15 | T15: ='YTD BS'!T15 | U15: ='YTD BS'!U15 | V15: ='BALANCE SHEET'!G15 | W15: ='YTD BS'!W15 | X15: ='YTD BS'!X15 | Y15: ='YTD BS'!Y15 | Z15: ='BALANCE SHEET'!H15 | AA15: ='YTD BS'!AA15 | AB15: ='YTD BS'!AB15 | AC15: ='YTD BS'!AC15 | AD15: ='BALANCE SHEET'!I15 | AE15: ='QTR P&L'!AH2*'BS DRIVERS'!AE14 | AF15: ='QTR P&L'!AI2*'BS DRIVERS'!AF14 | AG15: ='QTR P&L'!AJ2*'BS DRIVERS'!AG14 | AH15: ='QTR P&L'!AK2*'BS DRIVERS'!AH14 | AI15: ='QTR P&L'!AL2*'BS DRIVERS'!AI14 | AJ15: ='QTR P&L'!AM2*'BS DRIVERS'!AJ14 | AK15: ='QTR P&L'!AN2*'BS DRIVERS'!AK14 | AL15: ='QTR P&L'!AO2*'BS DRIVERS'!AL14 | ... AX15: ='QTR P&L'!BA2*'BS DRIVERS'!AX14
A16: Total Assets | B16: ='BALANCE SHEET'!B16 | C16: ='YTD BS'!C16 | D16: ='YTD BS'!D16 | E16: ='YTD BS'!E16 | F16: ='BALANCE SHEET'!C16 | G16: ='YTD BS'!G16 | H16: ='YTD BS'!H16 | I16: ='YTD BS'!I16 | J16: ='BALANCE SHEET'!D16 | K16: ='YTD BS'!K16 | L16: ='YTD BS'!L16 | M16: ='YTD BS'!M16 | N16: ='BALANCE SHEET'!E16 | O16: ='YTD BS'!O16 | P16: ='YTD BS'!P16 | Q16: ='YTD BS'!Q16 | R16: ='BALANCE SHEET'!F16 | S16: ='YTD BS'!S16 | T16: ='YTD BS'!T16 | U16: ='YTD BS'!U16 | V16: ='BALANCE SHEET'!G16 | W16: ='YTD BS'!W16 | X16: ='YTD BS'!X16 | Y16: ='YTD BS'!Y16 | Z16: ='BALANCE SHEET'!H16 | AA16: ='YTD BS'!AA16 | AB16: ='YTD BS'!AB16 | AC16: ='YTD BS'!AC16 | AD16: ='BALANCE SHEET'!I16 | AE16: =AE8+SUM(AE9:AE15) | AF16: =AF8+SUM(AF9:AF15) | AG16: =AG8+SUM(AG9:AG15) | AH16: =AH8+SUM(AH9:AH15) | AI16: =AI8+SUM(AI9:AI15) | AJ16: =AJ8+SUM(AJ9:AJ15) | AK16: =AK8+SUM(AK9:AK15) | AL16: =AL8+SUM(AL9:AL15) | ... AX16: =AX8+SUM(AX9:AX15)
A17: Accounts Payable | B17: ='BALANCE SHEET'!B17 | C17: ='YTD BS'!C17 | D17: ='YTD BS'!D17 | E17: ='YTD BS'!E17 | F17: ='BALANCE SHEET'!C17 | G17: ='YTD BS'!G17 | H17: ='YTD BS'!H17 | I17: ='YTD BS'!I17 | J17: ='BALANCE SHEET'!D17 | K17: ='YTD BS'!K17 | L17: ='YTD BS'!L17 | M17: ='YTD BS'!M17 | N17: ='BALANCE SHEET'!E17 | O17: ='YTD BS'!O17 | P17: ='YTD BS'!P17 | Q17: ='YTD BS'!Q17 | R17: ='BALANCE SHEET'!F17 | S17: ='YTD BS'!S17 | T17: ='YTD BS'!T17 | U17: ='YTD BS'!U17 | V17: ='BALANCE SHEET'!G17 | W17: ='YTD BS'!W17 | X17: ='YTD BS'!X17 | Y17: ='YTD BS'!Y17 | Z17: ='BALANCE SHEET'!H17 | AA17: ='YTD BS'!AA17 | AB17: ='YTD BS'!AB17 | AC17: ='YTD BS'!AC17 | AD17: ='BALANCE SHEET'!I17 | AE17: ='QTR P&L'!AH3*'BS DRIVERS'!AE15/ASSUMPTIONS!$B$2 | AF17: ='QTR P&L'!AI3*'BS DRIVERS'!AF15/ASSUMPTIONS!$B$2 | AG17: ='QTR P&L'!AJ3*'BS DRIVERS'!AG15/ASSUMPTIONS!$B$2 | AH17: ='QTR P&L'!AK3*'BS DRIVERS'!AH15/ASSUMPTIONS!$B$2 | AI17: ='QTR P&L'!AL3*'BS DRIVERS'!AI15/ASSUMPTIONS!$B$2 | AJ17: ='QTR P&L'!AM3*'BS DRIVERS'!AJ15/ASSUMPTIONS!$B$2 | AK17: ='QTR P&L'!AN3*'BS DRIVERS'!AK15/ASSUMPTIONS!$B$2 | AL17: ='QTR P&L'!AO3*'BS DRIVERS'!AL15/ASSUMPTIONS!$B$2 | ... AX17: ='QTR P&L'!BA3*'BS DRIVERS'!AX15/ASSUMPTIONS!$B$2
A18: Accrued Compensation | B18: ='BALANCE SHEET'!B18 | C18: ='YTD BS'!C18 | D18: ='YTD BS'!D18 | E18: ='YTD BS'!E18 | F18: ='BALANCE SHEET'!C18 | G18: ='YTD BS'!G18 | H18: ='YTD BS'!H18 | I18: ='YTD BS'!I18 | J18: ='BALANCE SHEET'!D18 | K18: ='YTD BS'!K18 | L18: ='YTD BS'!L18 | M18: ='YTD BS'!M18 | N18: ='BALANCE SHEET'!E18 | O18: ='YTD BS'!O18 | P18: ='YTD BS'!P18 | Q18: ='YTD BS'!Q18 | R18: ='BALANCE SHEET'!F18 | S18: ='YTD BS'!S18 | T18: ='YTD BS'!T18 | U18: ='YTD BS'!U18 | V18: ='BALANCE SHEET'!G18 | W18: ='YTD BS'!W18 | X18: ='YTD BS'!X18 | Y18: ='YTD BS'!Y18 | Z18: ='BALANCE SHEET'!H18 | AA18: ='YTD BS'!AA18 | AB18: ='YTD BS'!AB18 | AC18: ='YTD BS'!AC18 | AD18: ='BALANCE SHEET'!I18 | AE18: ='QTR P&L'!AH2*'BS DRIVERS'!AE16 | AF18: ='QTR P&L'!AI2*'BS DRIVERS'!AF16 | AG18: ='QTR P&L'!AJ2*'BS DRIVERS'!AG16 | AH18: ='QTR P&L'!AK2*'BS DRIVERS'!AH16 | AI18: ='QTR P&L'!AL2*'BS DRIVERS'!AI16 | AJ18: ='QTR P&L'!AM2*'BS DRIVERS'!AJ16 | AK18: ='QTR P&L'!AN2*'BS DRIVERS'!AK16 | AL18: ='QTR P&L'!AO2*'BS DRIVERS'!AL16 | ... AX18: ='QTR P&L'!BA2*'BS DRIVERS'!AX16
A19: Accrued Expenses | B19: ='BALANCE SHEET'!B19 | C19: ='YTD BS'!C19 | D19: ='YTD BS'!D19 | E19: ='YTD BS'!E19 | F19: ='BALANCE SHEET'!C19 | G19: ='YTD BS'!G19 | H19: ='YTD BS'!H19 | I19: ='YTD BS'!I19 | J19: ='BALANCE SHEET'!D19 | K19: ='YTD BS'!K19 | L19: ='YTD BS'!L19 | M19: ='YTD BS'!M19 | N19: ='BALANCE SHEET'!E19 | O19: ='YTD BS'!O19 | P19: ='YTD BS'!P19 | Q19: ='YTD BS'!Q19 | R19: ='BALANCE SHEET'!F19 | S19: ='YTD BS'!S19 | T19: ='YTD BS'!T19 | U19: ='YTD BS'!U19 | V19: ='BALANCE SHEET'!G19 | W19: ='YTD BS'!W19 | X19: ='YTD BS'!X19 | Y19: ='YTD BS'!Y19 | Z19: ='BALANCE SHEET'!H19 | AA19: ='YTD BS'!AA19 | AB19: ='YTD BS'!AB19 | AC19: ='YTD BS'!AC19 | AD19: ='BALANCE SHEET'!I19 | AE19: ='QTR P&L'!AH2*'BS DRIVERS'!AE17 | AF19: ='QTR P&L'!AI2*'BS DRIVERS'!AF17 | AG19: ='QTR P&L'!AJ2*'BS DRIVERS'!AG17 | AH19: ='QTR P&L'!AK2*'BS DRIVERS'!AH17 | AI19: ='QTR P&L'!AL2*'BS DRIVERS'!AI17 | AJ19: ='QTR P&L'!AM2*'BS DRIVERS'!AJ17 | AK19: ='QTR P&L'!AN2*'BS DRIVERS'!AK17 | AL19: ='QTR P&L'!AO2*'BS DRIVERS'!AL17 | ... AX19: ='QTR P&L'!BA2*'BS DRIVERS'!AX17
A20: Accrued Revenue Share | B20: ='BALANCE SHEET'!B20 | C20: ='YTD BS'!C20 | D20: ='YTD BS'!D20 | E20: ='YTD BS'!E20 | F20: ='BALANCE SHEET'!C20 | G20: ='YTD BS'!G20 | H20: ='YTD BS'!H20 | I20: ='YTD BS'!I20 | J20: ='BALANCE SHEET'!D20 | K20: ='YTD BS'!K20 | L20: ='YTD BS'!L20 | M20: ='YTD BS'!M20 | N20: ='BALANCE SHEET'!E20 | O20: ='YTD BS'!O20 | P20: ='YTD BS'!P20 | Q20: ='YTD BS'!Q20 | R20: ='BALANCE SHEET'!F20 | S20: ='YTD BS'!S20 | T20: ='YTD BS'!T20 | U20: ='YTD BS'!U20 | V20: ='BALANCE SHEET'!G20 | W20: ='YTD BS'!W20 | X20: ='YTD BS'!X20 | Y20: ='YTD BS'!Y20 | Z20: ='BALANCE SHEET'!H20 | AA20: ='YTD BS'!AA20 | AB20: ='YTD BS'!AB20 | AC20: ='YTD BS'!AC20 | AD20: ='BALANCE SHEET'!I20 | AE20: ='QTR P&L'!AH2*'BS DRIVERS'!AE18 | AF20: ='QTR P&L'!AI2*'BS DRIVERS'!AF18 | AG20: ='QTR P&L'!AJ2*'BS DRIVERS'!AG18 | AH20: ='QTR P&L'!AK2*'BS DRIVERS'!AH18 | AI20: ='QTR P&L'!AL2*'BS DRIVERS'!AI18 | AJ20: ='QTR P&L'!AM2*'BS DRIVERS'!AJ18 | AK20: ='QTR P&L'!AN2*'BS DRIVERS'!AK18 | AL20: ='QTR P&L'!AO2*'BS DRIVERS'!AL18 | ... AX20: ='QTR P&L'!BA2*'BS DRIVERS'!AX18
A21: Deferred Revenue - Current | B21: ='BALANCE SHEET'!B21 | C21: ='YTD BS'!C21 | D21: ='YTD BS'!D21 | E21: ='YTD BS'!E21 | F21: ='BALANCE SHEET'!C21 | G21: ='YTD BS'!G21 | H21: ='YTD BS'!H21 | I21: ='YTD BS'!I21 | J21: ='BALANCE SHEET'!D21 | K21: ='YTD BS'!K21 | L21: ='YTD BS'!L21 | M21: ='YTD BS'!M21 | N21: ='BALANCE SHEET'!E21 | O21: ='YTD BS'!O21 | P21: ='YTD BS'!P21 | Q21: ='YTD BS'!Q21 | R21: ='BALANCE SHEET'!F21 | S21: ='YTD BS'!S21 | T21: ='YTD BS'!T21 | U21: ='YTD BS'!U21 | V21: ='BALANCE SHEET'!G21 | W21: ='YTD BS'!W21 | X21: ='YTD BS'!X21 | Y21: ='YTD BS'!Y21 | Z21: ='BALANCE SHEET'!H21 | AA21: ='YTD BS'!AA21 | AB21: ='YTD BS'!AB21 | AC21: ='YTD BS'!AC21 | AD21: ='BALANCE SHEET'!I21 | AE21: ='QTR P&L'!AH2*'BS DRIVERS'!AE19 | AF21: ='QTR P&L'!AI2*'BS DRIVERS'!AF19 | AG21: ='QTR P&L'!AJ2*'BS DRIVERS'!AG19 | AH21: ='QTR P&L'!AK2*'BS DRIVERS'!AH19 | AI21: ='QTR P&L'!AL2*'BS DRIVERS'!AI19 | AJ21: ='QTR P&L'!AM2*'BS DRIVERS'!AJ19 | AK21: ='QTR P&L'!AN2*'BS DRIVERS'!AK19 | AL21: ='QTR P&L'!AO2*'BS DRIVERS'!AL19 | ... AX21: ='QTR P&L'!BA2*'BS DRIVERS'!AX19
A22: Income Taxes Payable | B22: ='BALANCE SHEET'!B22 | C22: ='YTD BS'!C22 | D22: ='YTD BS'!D22 | E22: ='YTD BS'!E22 | F22: ='BALANCE SHEET'!C22 | G22: ='YTD BS'!G22 | H22: ='YTD BS'!H22 | I22: ='YTD BS'!I22 | J22: ='BALANCE SHEET'!D22 | K22: ='YTD BS'!K22 | L22: ='YTD BS'!L22 | M22: ='YTD BS'!M22 | N22: ='BALANCE SHEET'!E22 | O22: ='YTD BS'!O22 | P22: ='YTD BS'!P22 | Q22: ='YTD BS'!Q22 | R22: ='BALANCE SHEET'!F22 | S22: ='YTD BS'!S22 | T22: ='YTD BS'!T22 | U22: ='YTD BS'!U22 | V22: ='BALANCE SHEET'!G22 | W22: ='YTD BS'!W22 | X22: ='YTD BS'!X22 | Y22: ='YTD BS'!Y22 | Z22: ='BALANCE SHEET'!H22 | AA22: ='YTD BS'!AA22 | AB22: ='YTD BS'!AB22 | AC22: ='YTD BS'!AC22 | AD22: ='BALANCE SHEET'!I22 | AE22: ='QTR P&L'!AH2*'BS DRIVERS'!AE20 | AF22: ='QTR P&L'!AI2*'BS DRIVERS'!AF20 | AG22: ='QTR P&L'!AJ2*'BS DRIVERS'!AG20 | AH22: ='QTR P&L'!AK2*'BS DRIVERS'!AH20 | AI22: ='QTR P&L'!AL2*'BS DRIVERS'!AI20 | AJ22: ='QTR P&L'!AM2*'BS DRIVERS'!AJ20 | AK22: ='QTR P&L'!AN2*'BS DRIVERS'!AK20 | AL22: ='QTR P&L'!AO2*'BS DRIVERS'!AL20 | ... AX22: ='QTR P&L'!BA2*'BS DRIVERS'!AX20
A23: Total Current Liabilities | B23: ='BALANCE SHEET'!B23 | C23: ='YTD BS'!C23 | D23: ='YTD BS'!D23 | E23: ='YTD BS'!E23 | F23: ='BALANCE SHEET'!C23 | G23: ='YTD BS'!G23 | H23: ='YTD BS'!H23 | I23: ='YTD BS'!I23 | J23: ='BALANCE SHEET'!D23 | K23: ='YTD BS'!K23 | L23: ='YTD BS'!L23 | M23: ='YTD BS'!M23 | N23: ='BALANCE SHEET'!E23 | O23: ='YTD BS'!O23 | P23: ='YTD BS'!P23 | Q23: ='YTD BS'!Q23 | R23: ='BALANCE SHEET'!F23 | S23: ='YTD BS'!S23 | T23: ='YTD BS'!T23 | U23: ='YTD BS'!U23 | V23: ='BALANCE SHEET'!G23 | W23: ='YTD BS'!W23 | X23: ='YTD BS'!X23 | Y23: ='YTD BS'!Y23 | Z23: ='BALANCE SHEET'!H23 | AA23: ='YTD BS'!AA23 | AB23: ='YTD BS'!AB23 | AC23: ='YTD BS'!AC23 | AD23: ='BALANCE SHEET'!I23 | AE23: =SUM(AE17:AE22) | AF23: =SUM(AF17:AF22) | AG23: =SUM(AG17:AG22) | AH23: =SUM(AH17:AH22) | AI23: =SUM(AI17:AI22) | AJ23: =SUM(AJ17:AJ22) | AK23: =SUM(AK17:AK22) | AL23: =SUM(AL17:AL22) | ... AX23: =SUM(AX17:AX22)
A24: Long-Term Debt | B24: ='BALANCE SHEET'!B24 | C24: ='YTD BS'!C24 | D24: ='YTD BS'!D24 | E24: ='YTD BS'!E24 | F24: ='BALANCE SHEET'!C24 | G24: ='YTD BS'!G24 | H24: ='YTD BS'!H24 | I24: ='YTD BS'!I24 | J24: ='BALANCE SHEET'!D24 | K24: ='YTD BS'!K24 | L24: ='YTD BS'!L24 | M24: ='YTD BS'!M24 | N24: ='BALANCE SHEET'!E24 | O24: ='YTD BS'!O24 | P24: ='YTD BS'!P24 | Q24: ='YTD BS'!Q24 | R24: ='BALANCE SHEET'!F24 | S24: ='YTD BS'!S24 | T24: ='YTD BS'!T24 | U24: ='YTD BS'!U24 | V24: ='BALANCE SHEET'!G24 | W24: ='YTD BS'!W24 | X24: ='YTD BS'!X24 | Y24: ='YTD BS'!Y24 | Z24: ='BALANCE SHEET'!H24 | AA24: ='YTD BS'!AA24 | AB24: ='YTD BS'!AB24 | AC24: ='YTD BS'!AC24 | AD24: ='BALANCE SHEET'!I24 | AE24: ='BS DRIVERS'!AE21 | AF24: ='BS DRIVERS'!AF21 | AG24: ='BS DRIVERS'!AG21 | AH24: ='BS DRIVERS'!AH21 | AI24: ='BS DRIVERS'!AI21 | AJ24: ='BS DRIVERS'!AJ21 | AK24: ='BS DRIVERS'!AK21 | AL24: ='BS DRIVERS'!AL21 | ... AX24: ='BS DRIVERS'!AX21
A25: Deferred Revenue - Non-Current | B25: ='BALANCE SHEET'!B25 | C25: ='YTD BS'!C25 | D25: ='YTD BS'!D25 | E25: ='YTD BS'!E25 | F25: ='BALANCE SHEET'!C25 | G25: ='YTD BS'!G25 | H25: ='YTD BS'!H25 | I25: ='YTD BS'!I25 | J25: ='BALANCE SHEET'!D25 | K25: ='YTD BS'!K25 | L25: ='YTD BS'!L25 | M25: ='YTD BS'!M25 | N25: ='BALANCE SHEET'!E25 | O25: ='YTD BS'!O25 | P25: ='YTD BS'!P25 | Q25: ='YTD BS'!Q25 | R25: ='BALANCE SHEET'!F25 | S25: ='YTD BS'!S25 | T25: ='YTD BS'!T25 | U25: ='YTD BS'!U25 | V25: ='BALANCE SHEET'!G25 | W25: ='YTD BS'!W25 | X25: ='YTD BS'!X25 | Y25: ='YTD BS'!Y25 | Z25: ='BALANCE SHEET'!H25 | AA25: ='YTD BS'!AA25 | AB25: ='YTD BS'!AB25 | AC25: ='YTD BS'!AC25 | AD25: ='BALANCE SHEET'!I25 | AE25: ='QTR P&L'!AH2*'BS DRIVERS'!AE22 | AF25: ='QTR P&L'!AI2*'BS DRIVERS'!AF22 | AG25: ='QTR P&L'!AJ2*'BS DRIVERS'!AG22 | AH25: ='QTR P&L'!AK2*'BS DRIVERS'!AH22 | AI25: ='QTR P&L'!AL2*'BS DRIVERS'!AI22 | AJ25: ='QTR P&L'!AM2*'BS DRIVERS'!AJ22 | AK25: ='QTR P&L'!AN2*'BS DRIVERS'!AK22 | AL25: ='QTR P&L'!AO2*'BS DRIVERS'!AL22 | ... AX25: ='QTR P&L'!BA2*'BS DRIVERS'!AX22
A26: Deferred Tax Liability | B26: ='BALANCE SHEET'!B26 | C26: ='YTD BS'!C26 | D26: ='YTD BS'!D26 | E26: ='YTD BS'!E26 | F26: ='BALANCE SHEET'!C26 | G26: ='YTD BS'!G26 | H26: ='YTD BS'!H26 | I26: ='YTD BS'!I26 | J26: ='BALANCE SHEET'!D26 | K26: ='YTD BS'!K26 | L26: ='YTD BS'!L26 | M26: ='YTD BS'!M26 | N26: ='BALANCE SHEET'!E26 | O26: ='YTD BS'!O26 | P26: ='YTD BS'!P26 | Q26: ='YTD BS'!Q26 | R26: ='BALANCE SHEET'!F26 | S26: ='YTD BS'!S26 | T26: ='YTD BS'!T26 | U26: ='YTD BS'!U26 | V26: ='BALANCE SHEET'!G26 | W26: ='YTD BS'!W26 | X26: ='YTD BS'!X26 | Y26: ='YTD BS'!Y26 | Z26: ='BALANCE SHEET'!H26 | AA26: ='YTD BS'!AA26 | AB26: ='YTD BS'!AB26 | AC26: ='YTD BS'!AC26 | AD26: ='BALANCE SHEET'!I26 | AE26: ='BS DRIVERS'!AE23 | AF26: ='BS DRIVERS'!AF23 | AG26: ='BS DRIVERS'!AG23 | AH26: ='BS DRIVERS'!AH23 | AI26: ='BS DRIVERS'!AI23 | AJ26: ='BS DRIVERS'!AJ23 | AK26: ='BS DRIVERS'!AK23 | AL26: ='BS DRIVERS'!AL23 | ... AX26: ='BS DRIVERS'!AX23
A27: Lease Liability - Operating - Non-Current | B27: ='BALANCE SHEET'!B27 | C27: ='YTD BS'!C27 | D27: ='YTD BS'!D27 | E27: ='YTD BS'!E27 | F27: ='BALANCE SHEET'!C27 | G27: ='YTD BS'!G27 | H27: ='YTD BS'!H27 | I27: ='YTD BS'!I27 | J27: ='BALANCE SHEET'!D27 | K27: ='YTD BS'!K27 | L27: ='YTD BS'!L27 | M27: ='YTD BS'!M27 | N27: ='BALANCE SHEET'!E27 | O27: ='YTD BS'!O27 | P27: ='YTD BS'!P27 | Q27: ='YTD BS'!Q27 | R27: ='BALANCE SHEET'!F27 | S27: ='YTD BS'!S27 | T27: ='YTD BS'!T27 | U27: ='YTD BS'!U27 | V27: ='BALANCE SHEET'!G27 | W27: ='YTD BS'!W27 | X27: ='YTD BS'!X27 | Y27: ='YTD BS'!Y27 | Z27: ='BALANCE SHEET'!H27 | AA27: ='YTD BS'!AA27 | AB27: ='YTD BS'!AB27 | AC27: ='YTD BS'!AC27 | AD27: ='BALANCE SHEET'!I27 | AE27: ='QTR P&L'!AH2*'BS DRIVERS'!AE24 | AF27: ='QTR P&L'!AI2*'BS DRIVERS'!AF24 | AG27: ='QTR P&L'!AJ2*'BS DRIVERS'!AG24 | AH27: ='QTR P&L'!AK2*'BS DRIVERS'!AH24 | AI27: ='QTR P&L'!AL2*'BS DRIVERS'!AI24 | AJ27: ='QTR P&L'!AM2*'BS DRIVERS'!AJ24 | AK27: ='QTR P&L'!AN2*'BS DRIVERS'!AK24 | AL27: ='QTR P&L'!AO2*'BS DRIVERS'!AL24 | ... AX27: ='QTR P&L'!BA2*'BS DRIVERS'!AX24
A28: Other Non-Current Liabilities | B28: ='BALANCE SHEET'!B28 | C28: ='YTD BS'!C28 | D28: ='YTD BS'!D28 | E28: ='YTD BS'!E28 | F28: ='BALANCE SHEET'!C28 | G28: ='YTD BS'!G28 | H28: ='YTD BS'!H28 | I28: ='YTD BS'!I28 | J28: ='BALANCE SHEET'!D28 | K28: ='YTD BS'!K28 | L28: ='YTD BS'!L28 | M28: ='YTD BS'!M28 | N28: ='BALANCE SHEET'!E28 | O28: ='YTD BS'!O28 | P28: ='YTD BS'!P28 | Q28: ='YTD BS'!Q28 | R28: ='BALANCE SHEET'!F28 | S28: ='YTD BS'!S28 | T28: ='YTD BS'!T28 | U28: ='YTD BS'!U28 | V28: ='BALANCE SHEET'!G28 | W28: ='YTD BS'!W28 | X28: ='YTD BS'!X28 | Y28: ='YTD BS'!Y28 | Z28: ='BALANCE SHEET'!H28 | AA28: ='YTD BS'!AA28 | AB28: ='YTD BS'!AB28 | AC28: ='YTD BS'!AC28 | AD28: ='BALANCE SHEET'!I28 | AE28: ='QTR P&L'!AH2*'BS DRIVERS'!AE25 | AF28: ='QTR P&L'!AI2*'BS DRIVERS'!AF25 | AG28: ='QTR P&L'!AJ2*'BS DRIVERS'!AG25 | AH28: ='QTR P&L'!AK2*'BS DRIVERS'!AH25 | AI28: ='QTR P&L'!AL2*'BS DRIVERS'!AI25 | AJ28: ='QTR P&L'!AM2*'BS DRIVERS'!AJ25 | AK28: ='QTR P&L'!AN2*'BS DRIVERS'!AK25 | AL28: ='QTR P&L'!AO2*'BS DRIVERS'!AL25 | ... AX28: ='QTR P&L'!BA2*'BS DRIVERS'!AX25
A29: Total Liabilities | B29: ='BALANCE SHEET'!B29 | C29: ='YTD BS'!C29 | D29: ='YTD BS'!D29 | E29: ='YTD BS'!E29 | F29: ='BALANCE SHEET'!C29 | G29: ='YTD BS'!G29 | H29: ='YTD BS'!H29 | I29: ='YTD BS'!I29 | J29: ='BALANCE SHEET'!D29 | K29: ='YTD BS'!K29 | L29: ='YTD BS'!L29 | M29: ='YTD BS'!M29 | N29: ='BALANCE SHEET'!E29 | O29: ='YTD BS'!O29 | P29: ='YTD BS'!P29 | Q29: ='YTD BS'!Q29 | R29: ='BALANCE SHEET'!F29 | S29: ='YTD BS'!S29 | T29: ='YTD BS'!T29 | U29: ='YTD BS'!U29 | V29: ='BALANCE SHEET'!G29 | W29: ='YTD BS'!W29 | X29: ='YTD BS'!X29 | Y29: ='YTD BS'!Y29 | Z29: ='BALANCE SHEET'!H29 | AA29: ='YTD BS'!AA29 | AB29: ='YTD BS'!AB29 | AC29: ='YTD BS'!AC29 | AD29: ='BALANCE SHEET'!I29 | AE29: =AE23+SUM(AE24:AE28) | AF29: =AF23+SUM(AF24:AF28) | AG29: =AG23+SUM(AG24:AG28) | AH29: =AH23+SUM(AH24:AH28) | AI29: =AI23+SUM(AI24:AI28) | AJ29: =AJ23+SUM(AJ24:AJ28) | AK29: =AK23+SUM(AK24:AK28) | AL29: =AL23+SUM(AL24:AL28) | ... AX29: =AX23+SUM(AX24:AX28)
A30: Convertible Preferred Stock | B30: ='BALANCE SHEET'!B30 | C30: ='YTD BS'!C30 | D30: ='YTD BS'!D30 | E30: ='YTD BS'!E30 | F30: ='BALANCE SHEET'!C30 | G30: ='YTD BS'!G30 | H30: ='YTD BS'!H30 | I30: ='YTD BS'!I30 | J30: ='BALANCE SHEET'!D30 | K30: ='YTD BS'!K30 | L30: ='YTD BS'!L30 | M30: ='YTD BS'!M30 | N30: ='BALANCE SHEET'!E30 | O30: ='YTD BS'!O30 | P30: ='YTD BS'!P30 | Q30: ='YTD BS'!Q30 | R30: ='BALANCE SHEET'!F30 | S30: ='YTD BS'!S30 | T30: ='YTD BS'!T30 | U30: ='YTD BS'!U30 | V30: ='BALANCE SHEET'!G30 | W30: ='YTD BS'!W30 | X30: ='YTD BS'!X30 | Y30: ='YTD BS'!Y30 | Z30: ='BALANCE SHEET'!H30 | AA30: ='YTD BS'!AA30 | AB30: ='YTD BS'!AB30 | AC30: ='YTD BS'!AC30 | AD30: ='BALANCE SHEET'!I30 | AE30: ='BS DRIVERS'!AE26 | AF30: ='BS DRIVERS'!AF26 | AG30: ='BS DRIVERS'!AG26 | AH30: ='BS DRIVERS'!AH26 | AI30: ='BS DRIVERS'!AI26 | AJ30: ='BS DRIVERS'!AJ26 | AK30: ='BS DRIVERS'!AK26 | AL30: ='BS DRIVERS'!AL26 | ... AX30: ='BS DRIVERS'!AX26
A31: Common Stock and Additional Paid-in Capital | B31: ='BALANCE SHEET'!B31 | C31: ='YTD BS'!C31 | D31: ='YTD BS'!D31 | E31: ='YTD BS'!E31 | F31: ='BALANCE SHEET'!C31 | G31: ='YTD BS'!G31 | H31: ='YTD BS'!H31 | I31: ='YTD BS'!I31 | J31: ='BALANCE SHEET'!D31 | K31: ='YTD BS'!K31 | L31: ='YTD BS'!L31 | M31: ='YTD BS'!M31 | N31: ='BALANCE SHEET'!E31 | O31: ='YTD BS'!O31 | P31: ='YTD BS'!P31 | Q31: ='YTD BS'!Q31 | R31: ='BALANCE SHEET'!F31 | S31: ='YTD BS'!S31 | T31: ='YTD BS'!T31 | U31: ='YTD BS'!U31 | V31: ='BALANCE SHEET'!G31 | W31: ='YTD BS'!W31 | X31: ='YTD BS'!X31 | Y31: ='YTD BS'!Y31 | Z31: ='BALANCE SHEET'!H31 | AA31: ='YTD BS'!AA31 | AB31: ='YTD BS'!AB31 | AC31: ='YTD BS'!AC31 | AD31: ='BALANCE SHEET'!I31 | AE31: ='BS DRIVERS'!AE27 | AF31: ='BS DRIVERS'!AF27 | AG31: ='BS DRIVERS'!AG27 | AH31: ='BS DRIVERS'!AH27 | AI31: ='BS DRIVERS'!AI27 | AJ31: ='BS DRIVERS'!AJ27 | AK31: ='BS DRIVERS'!AK27 | AL31: ='BS DRIVERS'!AL27 | ... AX31: ='BS DRIVERS'!AX27
A32: Accumulated Other Comprehensive Income (Loss) | B32: ='BALANCE SHEET'!B32 | C32: ='YTD BS'!C32 | D32: ='YTD BS'!D32 | E32: ='YTD BS'!E32 | F32: ='BALANCE SHEET'!C32 | G32: ='YTD BS'!G32 | H32: ='YTD BS'!H32 | I32: ='YTD BS'!I32 | J32: ='BALANCE SHEET'!D32 | K32: ='YTD BS'!K32 | L32: ='YTD BS'!L32 | M32: ='YTD BS'!M32 | N32: ='BALANCE SHEET'!E32 | O32: ='YTD BS'!O32 | P32: ='YTD BS'!P32 | Q32: ='YTD BS'!Q32 | R32: ='BALANCE SHEET'!F32 | S32: ='YTD BS'!S32 | T32: ='YTD BS'!T32 | U32: ='YTD BS'!U32 | V32: ='BALANCE SHEET'!G32 | W32: ='YTD BS'!W32 | X32: ='YTD BS'!X32 | Y32: ='YTD BS'!Y32 | Z32: ='BALANCE SHEET'!H32 | AA32: ='YTD BS'!AA32 | AB32: ='YTD BS'!AB32 | AC32: ='YTD BS'!AC32 | AD32: ='BALANCE SHEET'!I32 | AE32: ='BS DRIVERS'!AE28 | AF32: ='BS DRIVERS'!AF28 | AG32: ='BS DRIVERS'!AG28 | AH32: ='BS DRIVERS'!AH28 | AI32: ='BS DRIVERS'!AI28 | AJ32: ='BS DRIVERS'!AJ28 | AK32: ='BS DRIVERS'!AK28 | AL32: ='BS DRIVERS'!AL28 | ... AX32: ='BS DRIVERS'!AX28
A33: Retained Earnings (Accumulated Deficit) | B33: ='BALANCE SHEET'!B33 | C33: ='YTD BS'!C33 | D33: ='YTD BS'!D33 | E33: ='YTD BS'!E33 | F33: ='BALANCE SHEET'!C33 | G33: ='YTD BS'!G33 | H33: ='YTD BS'!H33 | I33: ='YTD BS'!I33 | J33: ='BALANCE SHEET'!D33 | K33: ='YTD BS'!K33 | L33: ='YTD BS'!L33 | M33: ='YTD BS'!M33 | N33: ='BALANCE SHEET'!E33 | O33: ='YTD BS'!O33 | P33: ='YTD BS'!P33 | Q33: ='YTD BS'!Q33 | R33: ='BALANCE SHEET'!F33 | S33: ='YTD BS'!S33 | T33: ='YTD BS'!T33 | U33: ='YTD BS'!U33 | V33: ='BALANCE SHEET'!G33 | W33: ='YTD BS'!W33 | X33: ='YTD BS'!X33 | Y33: ='YTD BS'!Y33 | Z33: ='BALANCE SHEET'!H33 | AA33: ='YTD BS'!AA33 | AB33: ='YTD BS'!AB33 | AC33: ='YTD BS'!AC33 | AD33: ='BALANCE SHEET'!I33 | AE33: ='BS DRIVERS'!AE29 | AF33: ='BS DRIVERS'!AF29 | AG33: ='BS DRIVERS'!AG29 | AH33: ='BS DRIVERS'!AH29 | AI33: ='BS DRIVERS'!AI29 | AJ33: ='BS DRIVERS'!AJ29 | AK33: ='BS DRIVERS'!AK29 | AL33: ='BS DRIVERS'!AL29 | ... AX33: ='BS DRIVERS'!AX29
A34: Total Stockholders' Equity | B34: ='BALANCE SHEET'!B34 | C34: ='YTD BS'!C34 | D34: ='YTD BS'!D34 | E34: ='YTD BS'!E34 | F34: ='BALANCE SHEET'!C34 | G34: ='YTD BS'!G34 | H34: ='YTD BS'!H34 | I34: ='YTD BS'!I34 | J34: ='BALANCE SHEET'!D34 | K34: ='YTD BS'!K34 | L34: ='YTD BS'!L34 | M34: ='YTD BS'!M34 | N34: ='BALANCE SHEET'!E34 | O34: ='YTD BS'!O34 | P34: ='YTD BS'!P34 | Q34: ='YTD BS'!Q34 | R34: ='BALANCE SHEET'!F34 | S34: ='YTD BS'!S34 | T34: ='YTD BS'!T34 | U34: ='YTD BS'!U34 | V34: ='BALANCE SHEET'!G34 | W34: ='YTD BS'!W34 | X34: ='YTD BS'!X34 | Y34: ='YTD BS'!Y34 | Z34: ='BALANCE SHEET'!H34 | AA34: ='YTD BS'!AA34 | AB34: ='YTD BS'!AB34 | AC34: ='YTD BS'!AC34 | AD34: ='BALANCE SHEET'!I34 | AE34: =SUM(AE30:AE33) | AF34: =SUM(AF30:AF33) | AG34: =SUM(AG30:AG33) | AH34: =SUM(AH30:AH33) | AI34: =SUM(AI30:AI33) | AJ34: =SUM(AJ30:AJ33) | AK34: =SUM(AK30:AK33) | AL34: =SUM(AL30:AL33) | ... AX34: =SUM(AX30:AX33)
A35: Total Liabilities, Mezzanine & Stockholders' Equity | B35: ='BALANCE SHEET'!B35 | C35: ='YTD BS'!C35 | D35: ='YTD BS'!D35 | E35: ='YTD BS'!E35 | F35: ='BALANCE SHEET'!C35 | G35: ='YTD BS'!G35 | H35: ='YTD BS'!H35 | I35: ='YTD BS'!I35 | J35: ='BALANCE SHEET'!D35 | K35: ='YTD BS'!K35 | L35: ='YTD BS'!L35 | M35: ='YTD BS'!M35 | N35: ='BALANCE SHEET'!E35 | O35: ='YTD BS'!O35 | P35: ='YTD BS'!P35 | Q35: ='YTD BS'!Q35 | R35: ='BALANCE SHEET'!F35 | S35: ='YTD BS'!S35 | T35: ='YTD BS'!T35 | U35: ='YTD BS'!U35 | V35: ='BALANCE SHEET'!G35 | W35: ='YTD BS'!W35 | X35: ='YTD BS'!X35 | Y35: ='YTD BS'!Y35 | Z35: ='BALANCE SHEET'!H35 | AA35: ='YTD BS'!AA35 | AB35: ='YTD BS'!AB35 | AC35: ='YTD BS'!AC35 | AD35: ='BALANCE SHEET'!I35 | AE35: =AE29+AE34 | AF35: =AF29+AF34 | AG35: =AG29+AG34 | AH35: =AH29+AH34 | AI35: =AI29+AI34 | AJ35: =AJ29+AJ34 | AK35: =AK29+AK34 | AL35: =AL29+AL34 | ... AX35: =AX29+AX34

Sheet QTR CF
B1: Q1 FY2018 | C1: Q2 FY2018 | D1: Q3 FY2018 | E1: Q4 FY2018 | F1: Q1 FY2019 | G1: Q2 FY2019 | H1: Q3 FY2019 | I1: Q4 FY2019 | J1: Q1 FY2020 | K1: Q2 FY2020 | L1: Q3 FY2020 | M1: Q4 FY2020 | N1: Q1 FY2021 | O1: Q2 FY2021 | P1: Q3 FY2021 | Q1: Q4 FY2021 | R1: Q1 FY2022 | S1: Q2 FY2022 | T1: Q3 FY2022 | U1: Q4 FY2022 | V1: Q1 FY2023 | W1: Q2 FY2023 | X1: Q3 FY2023 | Y1: Q4 FY2023 | Z1: Q1 FY2024 | AA1: Q2 FY2024 | AB1: Q3 FY2024 | AC1: Q4 FY2024 | AD1: Q1 FY2025 | AE1: Q2 FY2025 | AF1: Q3 FY2025 | AG1: Q4 FY2025 | AH1: Q1 FY2026E | AI1: Q2 FY2026E | AJ1: Q3 FY2026E | AK1: Q4 FY2026E | AL1: Q1 FY2027E | AM1: Q2 FY2027E | AN1: Q3 FY2027E | AO1: Q4 FY2027E | AP1: Q1 FY2028E | AQ1: Q2 FY2028E | AR1: Q3 FY2028E | AS1: Q4 FY2028E | AT1: Q1 FY2029E | AU1: Q2 FY2029E | AV1: Q3 FY2029E | AW1: Q4 FY2029E | AX1: Q1 FY2030E | AY1: Q2 FY2030E | AZ1: Q3 FY2030E | BA1: Q4 FY2030E
A2: Net Income (Loss) | B2: ='YTD CF'!B2 | C2: ='YTD CF'!C2-'YTD CF'!B2 | D2: ='YTD CF'!D2-'YTD CF'!C2 | E2: ='CASH FLOW'!C2-'YTD CF'!D2 | F2: ='YTD CF'!E2 | G2: ='YTD CF'!F2-'YTD CF'!E2 | H2: ='YTD CF'!G2-'YTD CF'!F2 | I2: ='CASH FLOW'!D2-'YTD CF'!G2 | J2: ='YTD CF'!H2 | K2: ='YTD CF'!I2-'YTD CF'!H2 | L2: ='YTD CF'!J2-'YTD CF'!I2 | M2: ='CASH FLOW'!E2-'YTD CF'!J2 | N2: ='YTD CF'!K2 | O2: ='YTD CF'!L2-'YTD CF'!K2 | P2: ='YTD CF'!M2-'YTD CF'!L2 | Q2: ='CASH FLOW'!F2-'YTD CF'!M2 | R2: ='YTD CF'!N2 | S2: ='YTD CF'!O2-'YTD CF'!N2 | T2: ='YTD CF'!P2-'YTD CF'!O2 | U2: ='CASH FLOW'!G2-'YTD CF'!P2 | V2: ='YTD CF'!Q2 | W2: ='YTD CF'!R2-'YTD CF'!Q2 | X2: ='YTD CF'!S2-'YTD CF'!R2 | Y2: ='CASH FLOW'!H2-'YTD CF'!S2 | Z2: ='YTD CF'!T2 | AA2: ='YTD CF'!U2-'YTD CF'!T2 | AB2: ='YTD CF'!V2-'YTD CF'!U2 | AC2: ='CASH FLOW'!I2-'YTD CF'!V2 | AD2: ='YTD CF'!W2 | AE2: ='YTD CF'!X2-'YTD CF'!W2 | AF2: ='YTD CF'!Y2-'YTD CF'!X2 | AG2: ='CASH FLOW'!J2-'YTD CF'!Y2 | AH2: ='CF DRIVERS'!AH2 | AI2: ='CF DRIVERS'!AI2 | AJ2: ='CF DRIVERS'!AJ2 | AK2: ='CF DRIVERS'!AK2 | AL2: ='CF DRIVERS'!AL2 | AM2: ='CF DRIVERS'!AM2 | AN2: ='CF DRIVERS'!AN2 | AO2: ='CF DRIVERS'!AO2 | ... BA2: ='CF DRIVERS'!BA2
A3: Depreciation and Impairment of PP&E | B3: ='YTD CF'!B3 | C3: ='YTD CF'!C3-'YTD CF'!B3 | D3: ='YTD CF'!D3-'YTD CF'!C3 | E3: ='CASH FLOW'!C3-'YTD CF'!D3 | F3: ='YTD CF'!E3 | G3: ='YTD CF'!F3-'YTD CF'!E3 | H3: ='YTD CF'!G3-'YTD CF'!F3 | I3: ='CASH FLOW'!D3-'YTD CF'!G3 | J3: ='YTD CF'!H3 | K3: ='YTD CF'!I3-'YTD CF'!H3 | L3: ='YTD CF'!J3-'YTD CF'!I3 | M3: ='CASH FLOW'!E3-'YTD CF'!J3 | N3: ='YTD CF'!K3 | O3: ='YTD CF'!L3-'YTD CF'!K3 | P3: ='YTD CF'!M3-'YTD CF'!L3 | Q3: ='CASH FLOW'!F3-'YTD CF'!M3 | R3: ='YTD CF'!N3 | S3: ='YTD CF'!O3-'YTD CF'!N3 | T3: ='YTD CF'!P3-'YTD CF'!O3 | U3: ='CASH FLOW'!G3-'YTD CF'!P3 | V3: ='YTD CF'!Q3 | W3: ='YTD CF'!R3-'YTD CF'!Q3 | X3: ='YTD CF'!S3-'YTD CF'!R3 | Y3: ='CASH FLOW'!H3-'YTD CF'!S3 | Z3: ='YTD CF'!T3 | AA3: ='YTD CF'!U3-'YTD CF'!T3 | AB3: ='YTD CF'!V3-'YTD CF'!U3 | AC3: ='CASH FLOW'!I3-'YTD CF'!V3 | AD3: ='YTD CF'!W3 | AE3: ='YTD CF'!X3-'YTD CF'!W3 | AF3: ='YTD CF'!Y3-'YTD CF'!X3 | AG3: ='CASH FLOW'!J3-'YTD CF'!Y3 | AH3: ='CF DRIVERS'!AH3 | AI3: ='CF DRIVERS'!AI3 | AJ3: ='CF DRIVERS'!AJ3 | AK3: ='CF DRIVERS'!AK3 | AL3: ='CF DRIVERS'!AL3 | AM3: ='CF DRIVERS'!AM3 | AN3: ='CF DRIVERS'!AN3 | AO3: ='CF DRIVERS'!AO3 | ... BA3: ='CF DRIVERS'!BA3
A4: Amortization and Impairment of Intangibles | B4: ='YTD CF'!B4 | C4: ='YTD CF'!C4-'YTD CF'!B4 | D4: ='YTD CF'!D4-'YTD CF'!C4 | E4: ='CASH FLOW'!C4-'YTD CF'!D4 | F4: ='YTD CF'!E4 | G4: ='YTD CF'!F4-'YTD CF'!E4 | H4: ='YTD CF'!G4-'YTD CF'!F4 | I4: ='CASH FLOW'!D4-'YTD CF'!G4 | J4: ='YTD CF'!H4 | K4: ='YTD CF'!I4-'YTD CF'!H4 | L4: ='YTD CF'!J4-'YTD CF'!I4 | M4: ='CASH FLOW'!E4-'YTD CF'!J4 | N4: ='YTD CF'!K4 | O4: ='YTD CF'!L4-'YTD CF'!K4 | P4: ='YTD CF'!M4-'YTD CF'!L4 | Q4: ='CASH FLOW'!F4-'YTD CF'!M4 | R4: ='YTD CF'!N4 | S4: ='YTD CF'!O4-'YTD CF'!N4 | T4: ='YTD CF'!P4-'YTD CF'!O4 | U4: ='CASH FLOW'!G4-'YTD CF'!P4 | V4: ='YTD CF'!Q4 | W4: ='YTD CF'!R4-'YTD CF'!Q4 | X4: ='YTD CF'!S4-'YTD CF'!R4 | Y4: ='CASH FLOW'!H4-'YTD CF'!S4 | Z4: ='YTD CF'!T4 | AA4: ='YTD CF'!U4-'YTD CF'!T4 | AB4: ='YTD CF'!V4-'YTD CF'!U4 | AC4: ='CASH FLOW'!I4-'YTD CF'!V4 | AD4: ='YTD CF'!W4 | AE4: ='YTD CF'!X4-'YTD CF'!W4 | AF4: ='YTD CF'!Y4-'YTD CF'!X4 | AG4: ='CASH FLOW'!J4-'YTD CF'!Y4 | AH4: ='CF DRIVERS'!AH4 | AI4: ='CF DRIVERS'!AI4 | AJ4: ='CF DRIVERS'!AJ4 | AK4: ='CF DRIVERS'!AK4 | AL4: ='CF DRIVERS'!AL4 | AM4: ='CF DRIVERS'!AM4 | AN4: ='CF DRIVERS'!AN4 | AO4: ='CF DRIVERS'!AO4 | ... BA4: ='CF DRIVERS'!BA4
A5: Depreciation | B5: ='YTD CF'!B5 | C5: ='YTD CF'!C5-'YTD CF'!B5 | D5: ='YTD CF'!D5-'YTD CF'!C5 | E5: ='CASH FLOW'!C5-'YTD CF'!D5 | F5: ='YTD CF'!E5 | G5: ='YTD CF'!F5-'YTD CF'!E5 | H5: ='YTD CF'!G5-'YTD CF'!F5 | I5: ='CASH FLOW'!D5-'YTD CF'!G5 | J5: ='YTD CF'!H5 | K5: ='YTD CF'!I5-'YTD CF'!H5 | L5: ='YTD CF'!J5-'YTD CF'!I5 | M5: ='CASH FLOW'!E5-'YTD CF'!J5 | N5: ='YTD CF'!K5 | O5: ='YTD CF'!L5-'YTD CF'!K5 | P5: ='YTD CF'!M5-'YTD CF'!L5 | Q5: ='CASH FLOW'!F5-'YTD CF'!M5 | R5: ='YTD CF'!N5 | S5: ='YTD CF'!O5-'YTD CF'!N5 | T5: ='YTD CF'!P5-'YTD CF'!O5 | U5: ='CASH FLOW'!G5-'YTD CF'!P5 | V5: ='YTD CF'!Q5 | W5: ='YTD CF'!R5-'YTD CF'!Q5 | X5: ='YTD CF'!S5-'YTD CF'!R5 | Y5: ='CASH FLOW'!H5-'YTD CF'!S5 | Z5: ='YTD CF'!T5 | AA5: ='YTD CF'!U5-'YTD CF'!T5 | AB5: ='YTD CF'!V5-'YTD CF'!U5 | AC5: ='CASH FLOW'!I5-'YTD CF'!V5 | AD5: ='YTD CF'!W5 | AE5: ='YTD CF'!X5-'YTD CF'!W5 | AF5: ='YTD CF'!Y5-'YTD CF'!X5 | AG5: ='CASH FLOW'!J5-'YTD CF'!Y5 | AH5: ='CF DRIVERS'!AH5 | AI5: ='CF DRIVERS'!AI5 | AJ5: ='CF DRIVERS'!AJ5 | AK5: ='CF DRIVERS'!AK5 | AL5: ='CF DRIVERS'!AL5 | AM5: ='CF DRIVERS'!AM5 | AN5: ='CF DRIVERS'!AN5 | AO5: ='CF DRIVERS'!AO5 | ... BA5: ='CF DRIVERS'!BA5
A6: Stock-Based Compensation | B6: ='YTD CF'!B6 | C6: ='YTD CF'!C6-'YTD CF'!B6 | D6: ='YTD CF'!D6-'YTD CF'!C6 | E6: ='CASH FLOW'!C6-'YTD CF'!D6 | F6: ='YTD CF'!E6 | G6: ='YTD CF'!F6-'YTD CF'!E6 | H6: ='YTD CF'!G6-'YTD CF'!F6 | I6: ='CASH FLOW'!D6-'YTD CF'!G6 | J6: ='YTD CF'!H6 | K6: ='YTD CF'!I6-'YTD CF'!H6 | L6: ='YTD CF'!J6-'YTD CF'!I6 | M6: ='CASH FLOW'!E6-'YTD CF'!J6 | N6: ='YTD CF'!K6 | O6: ='YTD CF'!L6-'YTD CF'!K6 | P6: ='YTD CF'!M6-'YTD CF'!L6 | Q6: ='CASH FLOW'!F6-'YTD CF'!M6 | R6: ='YTD CF'!N6 | S6: ='YTD CF'!O6-'YTD CF'!N6 | T6: ='YTD CF'!P6-'YTD CF'!O6 | U6: ='CASH FLOW'!G6-'YTD CF'!P6 | V6: ='YTD CF'!Q6 | W6: ='YTD CF'!R6-'YTD CF'!Q6 | X6: ='YTD CF'!S6-'YTD CF'!R6 | Y6: ='CASH FLOW'!H6-'YTD CF'!S6 | Z6: ='YTD CF'!T6 | AA6: ='YTD CF'!U6-'YTD CF'!T6 | AB6: ='YTD CF'!V6-'YTD CF'!U6 | AC6: ='CASH FLOW'!I6-'YTD CF'!V6 | AD6: ='YTD CF'!W6 | AE6: ='YTD CF'!X6-'YTD CF'!W6 | AF6: ='YTD CF'!Y6-'YTD CF'!X6 | AG6: ='CASH FLOW'!J6-'YTD CF'!Y6 | AH6: ='QTR P&L'!AH2*'CF DRIVERS'!AH6 | AI6: ='QTR P&L'!AI2*'CF DRIVERS'!AI6 | AJ6: ='QTR P&L'!AJ2*'CF DRIVERS'!AJ6 | AK6: ='QTR P&L'!AK2*'CF DRIVERS'!AK6 | AL6: ='QTR P&L'!AL2*'CF DRIVERS'!AL6 | AM6: ='QTR P&L'!AM2*'CF DRIVERS'!AM6 | AN6: ='QTR P&L'!AN2*'CF DRIVERS'!AN6 | AO6: ='QTR P&L'!AO2*'CF DRIVERS'!AO6 | ... BA6: ='QTR P&L'!BA2*'CF DRIVERS'!BA6
A7: (Benefit) Provision for Deferred Income Taxes | B7: ='YTD CF'!B7 | C7: ='YTD CF'!C7-'YTD CF'!B7 | D7: ='YTD CF'!D7-'YTD CF'!C7 | E7: ='CASH FLOW'!C7-'YTD CF'!D7 | F7: ='YTD CF'!E7 | G7: ='YTD CF'!F7-'YTD CF'!E7 | H7: ='YTD CF'!G7-'YTD CF'!F7 | I7: ='CASH FLOW'!D7-'YTD CF'!G7 | J7: ='YTD CF'!H7 | K7: ='YTD CF'!I7-'YTD CF'!H7 | L7: ='YTD CF'!J7-'YTD CF'!I7 | M7: ='CASH FLOW'!E7-'YTD CF'!J7 | N7: ='YTD CF'!K7 | O7: ='YTD CF'!L7-'YTD CF'!K7 | P7: ='YTD CF'!M7-'YTD CF'!L7 | Q7: ='CASH FLOW'!F7-'YTD CF'!M7 | R7: ='YTD CF'!N7 | S7: ='YTD CF'!O7-'YTD CF'!N7 | T7: ='YTD CF'!P7-'YTD CF'!O7 | U7: ='CASH FLOW'!G7-'YTD CF'!P7 | V7: ='YTD CF'!Q7 | W7: ='YTD CF'!R7-'YTD CF'!Q7 | X7: ='YTD CF'!S7-'YTD CF'!R7 | Y7: ='CASH FLOW'!H7-'YTD CF'!S7 | Z7: ='YTD CF'!T7 | AA7: ='YTD CF'!U7-'YTD CF'!T7 | AB7: ='YTD CF'!V7-'YTD CF'!U7 | AC7: ='CASH FLOW'!I7-'YTD CF'!V7 | AD7: ='YTD CF'!W7 | AE7: ='YTD CF'!X7-'YTD CF'!W7 | AF7: ='YTD CF'!Y7-'YTD CF'!X7 | AG7: ='CASH FLOW'!J7-'YTD CF'!Y7 | AH7: ='CF DRIVERS'!AH7 | AI7: ='CF DRIVERS'!AI7 | AJ7: ='CF DRIVERS'!AJ7 | AK7: ='CF DRIVERS'!AK7 | AL7: ='CF DRIVERS'!AL7 | AM7: ='CF DRIVERS'!AM7 | AN7: ='CF DRIVERS'!AN7 | AO7: ='CF DRIVERS'!AO7 | ... BA7: ='CF DRIVERS'!BA7
A8: Loss (Gain) on Equity and Debt Securities, Net | B8: ='YTD CF'!B8 | C8: ='YTD CF'!C8-'YTD CF'!B8 | D8: ='YTD CF'!D8-'YTD CF'!C8 | E8: ='CASH FLOW'!C8-'YTD CF'!D8 | F8: ='YTD CF'!E8 | G8: ='YTD CF'!F8-'YTD CF'!E8 | H8: ='YTD CF'!G8-'YTD CF'!F8 | I8: ='CASH FLOW'!D8-'YTD CF'!G8 | J8: ='YTD CF'!H8 | K8: ='YTD CF'!I8-'YTD CF'!H8 | L8: ='YTD CF'!J8-'YTD CF'!I8 | M8: ='CASH FLOW'!E8-'YTD CF'!J8 | N8: ='YTD CF'!K8 | O8: ='YTD CF'!L8-'YTD CF'!K8 | P8: ='YTD CF'!M8-'YTD CF'!L8 | Q8: ='CASH FLOW'!F8-'YTD CF'!M8 | R8: ='YTD CF'!N8 | S8: ='YTD CF'!O8-'YTD CF'!N8 | T8: ='YTD CF'!P8-'YTD CF'!O8 | U8: ='CASH FLOW'!G8-'YTD CF'!P8 | V8: ='YTD CF'!Q8 | W8: ='YTD CF'!R8-'YTD CF'!Q8 | X8: ='YTD CF'!S8-'YTD CF'!R8 | Y8: ='CASH FLOW'!H8-'YTD CF'!S8 | Z8: ='YTD CF'!T8 | AA8: ='YTD CF'!U8-'YTD CF'!T8 | AB8: ='YTD CF'!V8-'YTD CF'!U8 | AC8: ='CASH FLOW'!I8-'YTD CF'!V8 | AD8: ='YTD CF'!W8 | AE8: ='YTD CF'!X8-'YTD CF'!W8 | AF8: ='YTD CF'!Y8-'YTD CF'!X8 | AG8: ='CASH FLOW'!J8-'YTD CF'!Y8 | AH8: ='CF DRIVERS'!AH8 | AI8: ='CF DRIVERS'!AI8 | AJ8: ='CF DRIVERS'!AJ8 | AK8: ='CF DRIVERS'!AK8 | AL8: ='CF DRIVERS'!AL8 | AM8: ='CF DRIVERS'!AM8 | AN8: ='CF DRIVERS'!AN8 | AO8: ='CF DRIVERS'!AO8 | ... BA8: ='CF DRIVERS'!BA8
A9: Other Operating Items | B9: ='YTD CF'!B9 | C9: ='YTD CF'!C9-'YTD CF'!B9 | D9: ='YTD CF'!D9-'YTD CF'!C9 | E9: ='CASH FLOW'!C9-'YTD CF'!D9 | F9: ='YTD CF'!E9 | G9: ='YTD CF'!F9-'YTD CF'!E9 | H9: ='YTD CF'!G9-'YTD CF'!F9 | I9: ='CASH FLOW'!D9-'YTD CF'!G9 | J9: ='YTD CF'!H9 | K9: ='YTD CF'!I9-'YTD CF'!H9 | L9: ='YTD CF'!J9-'YTD CF'!I9 | M9: ='CASH FLOW'!E9-'YTD CF'!J9 | N9: ='YTD CF'!K9 | O9: ='YTD CF'!L9-'YTD CF'!K9 | P9: ='YTD CF'!M9-'YTD CF'!L9 | Q9: ='CASH FLOW'!F9-'YTD CF'!M9 | R9: ='YTD CF'!N9 | S9: ='YTD CF'!O9-'YTD CF'!N9 | T9: ='YTD CF'!P9-'YTD CF'!O9 | U9: ='CASH FLOW'!G9-'YTD CF'!P9 | V9: ='YTD CF'!Q9 | W9: ='YTD CF'!R9-'YTD CF'!Q9 | X9: ='YTD CF'!S9-'YTD CF'!R9 | Y9: ='CASH FLOW'!H9-'YTD CF'!S9 | Z9: ='YTD CF'!T9 | AA9: ='YTD CF'!U9-'YTD CF'!T9 | AB9: ='YTD CF'!V9-'YTD CF'!U9 | AC9: ='CASH FLOW'!I9-'YTD CF'!V9 | AD9: ='YTD CF'!W9 | AE9: ='YTD CF'!X9-'YTD CF'!W9 | AF9: ='YTD CF'!Y9-'YTD CF'!X9 | AG9: ='CASH FLOW'!J9-'YTD CF'!Y9 | AH9: ='CF DRIVERS'!AH9 | AI9: ='CF DRIVERS'!AI9 | AJ9: ='CF DRIVERS'!AJ9 | AK9: ='CF DRIVERS'!AK9 | AL9: ='CF DRIVERS'!AL9 | AM9: ='CF DRIVERS'!AM9 | AN9: ='CF DRIVERS'!AN9 | AO9: ='CF DRIVERS'!AO9 | ... BA9: ='CF DRIVERS'!BA9
A10: Accounts Receivable | B10: ='YTD CF'!B10 | C10: ='YTD CF'!C10-'YTD CF'!B10 | D10: ='YTD CF'!D10-'YTD CF'!C10 | E10: ='CASH FLOW'!C10-'YTD CF'!D10 | F10: ='YTD CF'!E10 | G10: ='YTD CF'!F10-'YTD CF'!E10 | H10: ='YTD CF'!G10-'YTD CF'!F10 | I10: ='CASH FLOW'!D10-'YTD CF'!G10 | J10: ='YTD CF'!H10 | K10: ='YTD CF'!I10-'YTD CF'!H10 | L10: ='YTD CF'!J10-'YTD CF'!I10 | M10: ='CASH FLOW'!E10-'YTD CF'!J10 | N10: ='YTD CF'!K10 | O10: ='YTD CF'!L10-'YTD CF'!K10 | P10: ='YTD CF'!M10-'YTD CF'!L10 | Q10: ='CASH FLOW'!F10-'YTD CF'!M10 | R10: ='YTD CF'!N10 | S10: ='YTD CF'!O10-'YTD CF'!N10 | T10: ='YTD CF'!P10-'YTD CF'!O10 | U10: ='CASH FLOW'!G10-'YTD CF'!P10 | V10: ='YTD CF'!Q10 | W10: ='YTD CF'!R10-'YTD CF'!Q10 | X10: ='YTD CF'!S10-'YTD CF'!R10 | Y10: ='CASH FLOW'!H10-'YTD CF'!S10 | Z10: ='YTD CF'!T10 | AA10: ='YTD CF'!U10-'YTD CF'!T10 | AB10: ='YTD CF'!V10-'YTD CF'!U10 | AC10: ='CASH FLOW'!I10-'YTD CF'!V10 | AD10: ='YTD CF'!W10 | AE10: ='YTD CF'!X10-'YTD CF'!W10 | AF10: ='YTD CF'!Y10-'YTD CF'!X10 | AG10: ='CASH FLOW'!J10-'YTD CF'!Y10 | AH10: ='CF DRIVERS'!AH10 | AI10: ='CF DRIVERS'!AI10 | AJ10: ='CF DRIVERS'!AJ10 | AK10: ='CF DRIVERS'!AK10 | AL10: ='CF DRIVERS'!AL10 | AM10: ='CF DRIVERS'!AM10 | AN10: ='CF DRIVERS'!AN10 | AO10: ='CF DRIVERS'!AO10 | ... BA10: ='CF DRIVERS'!BA10
A11: Change in Income Taxes | B11: ='YTD CF'!B11 | C11: ='YTD CF'!C11-'YTD CF'!B11 | D11: ='YTD CF'!D11-'YTD CF'!C11 | E11: ='CASH FLOW'!C11-'YTD CF'!D11 | F11: ='YTD CF'!E11 | G11: ='YTD CF'!F11-'YTD CF'!E11 | H11: ='YTD CF'!G11-'YTD CF'!F11 | I11: ='CASH FLOW'!D11-'YTD CF'!G11 | J11: ='YTD CF'!H11 | K11: ='YTD CF'!I11-'YTD CF'!H11 | L11: ='YTD CF'!J11-'YTD CF'!I11 | M11: ='CASH FLOW'!E11-'YTD CF'!J11 | N11: ='YTD CF'!K11 | O11: ='YTD CF'!L11-'YTD CF'!K11 | P11: ='YTD CF'!M11-'YTD CF'!L11 | Q11: ='CASH FLOW'!F11-'YTD CF'!M11 | R11: ='YTD CF'!N11 | S11: ='YTD CF'!O11-'YTD CF'!N11 | T11: ='YTD CF'!P11-'YTD CF'!O11 | U11: ='CASH FLOW'!G11-'YTD CF'!P11 | V11: ='YTD CF'!Q11 | W11: ='YTD CF'!R11-'YTD CF'!Q11 | X11: ='YTD CF'!S11-'YTD CF'!R11 | Y11: ='CASH FLOW'!H11-'YTD CF'!S11 | Z11: ='YTD CF'!T11 | AA11: ='YTD CF'!U11-'YTD CF'!T11 | AB11: ='YTD CF'!V11-'YTD CF'!U11 | AC11: ='CASH FLOW'!I11-'YTD CF'!V11 | AD11: ='YTD CF'!W11 | AE11: ='YTD CF'!X11-'YTD CF'!W11 | AF11: ='YTD CF'!Y11-'YTD CF'!X11 | AG11: ='CASH FLOW'!J11-'YTD CF'!Y11 | AH11: ='CF DRIVERS'!AH11 | AI11: ='CF DRIVERS'!AI11 | AJ11: ='CF DRIVERS'!AJ11 | AK11: ='CF DRIVERS'!AK11 | AL11: ='CF DRIVERS'!AL11 | AM11: ='CF DRIVERS'!AM11 | AN11: ='CF DRIVERS'!AN11 | AO11: ='CF DRIVERS'!AO11 | ... BA11: ='CF DRIVERS'!BA11
A12: Accounts Payable | B12: ='YTD CF'!B12 | C12: ='YTD CF'!C12-'YTD CF'!B12 | D12: ='YTD CF'!D12-'YTD CF'!C12 | E12: ='CASH FLOW'!C12-'YTD CF'!D12 | F12: ='YTD CF'!E12 | G12: ='YTD CF'!F12-'YTD CF'!E12 | H12: ='YTD CF'!G12-'YTD CF'!F12 | I12: ='CASH FLOW'!D12-'YTD CF'!G12 | J12: ='YTD CF'!H12 | K12: ='YTD CF'!I12-'YTD CF'!H12 | L12: ='YTD CF'!J12-'YTD CF'!I12 | M12: ='CASH FLOW'!E12-'YTD CF'!J12 | N12: ='YTD CF'!K12 | O12: ='YTD CF'!L12-'YTD CF'!K12 | P12: ='YTD CF'!M12-'YTD CF'!L12 | Q12: ='CASH FLOW'!F12-'YTD CF'!M12 | R12: ='YTD CF'!N12 | S12: ='YTD CF'!O12-'YTD CF'!N12 | T12: ='YTD CF'!P12-'YTD CF'!O12 | U12: ='CASH FLOW'!G12-'YTD CF'!P12 | V12: ='YTD CF'!Q12 | W12: ='YTD CF'!R12-'YTD CF'!Q12 | X12: ='YTD CF'!S12-'YTD CF'!R12 | Y12: ='CASH FLOW'!H12-'YTD CF'!S12 | Z12: ='YTD CF'!T12 | AA12: ='YTD CF'!U12-'YTD CF'!T12 | AB12: ='YTD CF'!V12-'YTD CF'!U12 | AC12: ='CASH FLOW'!I12-'YTD CF'!V12 | AD12: ='YTD CF'!W12 | AE12: ='YTD CF'!X12-'YTD CF'!W12 | AF12: ='YTD CF'!Y12-'YTD CF'!X12 | AG12: ='CASH FLOW'!J12-'YTD CF'!Y12 | AH12: ='CF DRIVERS'!AH12 | AI12: ='CF DRIVERS'!AI12 | AJ12: ='CF DRIVERS'!AJ12 | AK12: ='CF DRIVERS'!AK12 | AL12: ='CF DRIVERS'!AL12 | AM12: ='CF DRIVERS'!AM12 | AN12: ='CF DRIVERS'!AN12 | AO12: ='CF DRIVERS'!AO12 | ... BA12: ='CF DRIVERS'!BA12
A13: Accrued Expenses | B13: ='YTD CF'!B13 | C13: ='YTD CF'!C13-'YTD CF'!B13 | D13: ='YTD CF'!D13-'YTD CF'!C13 | E13: ='CASH FLOW'!C13-'YTD CF'!D13 | F13: ='YTD CF'!E13 | G13: ='YTD CF'!F13-'YTD CF'!E13 | H13: ='YTD CF'!G13-'YTD CF'!F13 | I13: ='CASH FLOW'!D13-'YTD CF'!G13 | J13: ='YTD CF'!H13 | K13: ='YTD CF'!I13-'YTD CF'!H13 | L13: ='YTD CF'!J13-'YTD CF'!I13 | M13: ='CASH FLOW'!E13-'YTD CF'!J13 | N13: ='YTD CF'!K13 | O13: ='YTD CF'!L13-'YTD CF'!K13 | P13: ='YTD CF'!M13-'YTD CF'!L13 | Q13: ='CASH FLOW'!F13-'YTD CF'!M13 | R13: ='YTD CF'!N13 | S13: ='YTD CF'!O13-'YTD CF'!N13 | T13: ='YTD CF'!P13-'YTD CF'!O13 | U13: ='CASH FLOW'!G13-'YTD CF'!P13 | V13: ='YTD CF'!Q13 | W13: ='YTD CF'!R13-'YTD CF'!Q13 | X13: ='YTD CF'!S13-'YTD CF'!R13 | Y13: ='CASH FLOW'!H13-'YTD CF'!S13 | Z13: ='YTD CF'!T13 | AA13: ='YTD CF'!U13-'YTD CF'!T13 | AB13: ='YTD CF'!V13-'YTD CF'!U13 | AC13: ='CASH FLOW'!I13-'YTD CF'!V13 | AD13: ='YTD CF'!W13 | AE13: ='YTD CF'!X13-'YTD CF'!W13 | AF13: ='YTD CF'!Y13-'YTD CF'!X13 | AG13: ='CASH FLOW'!J13-'YTD CF'!Y13 | AH13: ='CF DRIVERS'!AH13 | AI13: ='CF DRIVERS'!AI13 | AJ13: ='CF DRIVERS'!AJ13 | AK13: ='CF DRIVERS'!AK13 | AL13: ='CF DRIVERS'!AL13 | AM13: ='CF DRIVERS'!AM13 | AN13: ='CF DRIVERS'!AN13 | AO13: ='CF DRIVERS'!AO13 | ... BA13: ='CF DRIVERS'!BA13
A14: Accrued Revenue Share | B14: ='YTD CF'!B14 | C14: ='YTD CF'!C14-'YTD CF'!B14 | D14: ='YTD CF'!D14-'YTD CF'!C14 | E14: ='CASH FLOW'!C14-'YTD CF'!D14 | F14: ='YTD CF'!E14 | G14: ='YTD CF'!F14-'YTD CF'!E14 | H14: ='YTD CF'!G14-'YTD CF'!F14 | I14: ='CASH FLOW'!D14-'YTD CF'!G14 | J14: ='YTD CF'!H14 | K14: ='YTD CF'!I14-'YTD CF'!H14 | L14: ='YTD CF'!J14-'YTD CF'!I14 | M14: ='CASH FLOW'!E14-'YTD CF'!J14 | N14: ='YTD CF'!K14 | O14: ='YTD CF'!L14-'YTD CF'!K14 | P14: ='YTD CF'!M14-'YTD CF'!L14 | Q14: ='CASH FLOW'!F14-'YTD CF'!M14 | R14: ='YTD CF'!N14 | S14: ='YTD CF'!O14-'YTD CF'!N14 | T14: ='YTD CF'!P14-'YTD CF'!O14 | U14: ='CASH FLOW'!G14-'YTD CF'!P14 | V14: ='YTD CF'!Q14 | W14: ='YTD CF'!R14-'YTD CF'!Q14 | X14: ='YTD CF'!S14-'YTD CF'!R14 | Y14: ='CASH FLOW'!H14-'YTD CF'!S14 | Z14: ='YTD CF'!T14 | AA14: ='YTD CF'!U14-'YTD CF'!T14 | AB14: ='YTD CF'!V14-'YTD CF'!U14 | AC14: ='CASH FLOW'!I14-'YTD CF'!V14 | AD14: ='YTD CF'!W14 | AE14: ='YTD CF'!X14-'YTD CF'!W14 | AF14: ='YTD CF'!Y14-'YTD CF'!X14 | AG14: ='CASH FLOW'!J14-'YTD CF'!Y14 | AH14: ='CF DRIVERS'!AH14 | AI14: ='CF DRIVERS'!AI14 | AJ14: ='CF DRIVERS'!AJ14 | AK14: ='CF DRIVERS'!AK14 | AL14: ='CF DRIVERS'!AL14 | AM14: ='CF DRIVERS'!AM14 | AN14: ='CF DRIVERS'!AN14 | AO14: ='CF DRIVERS'!AO14 | ... BA14: ='CF DRIVERS'!BA14
A15: Deferred Revenue | B15: ='YTD CF'!B15 | C15: ='YTD CF'!C15-'YTD CF'!B15 | D15: ='YTD CF'!D15-'YTD CF'!C15 | E15: ='CASH FLOW'!C15-'YTD CF'!D15 | F15: ='YTD CF'!E15 | G15: ='YTD CF'!F15-'YTD CF'!E15 | H15: ='YTD CF'!G15-'YTD CF'!F15 | I15: ='CASH FLOW'!D15-'YTD CF'!G15 | J15: ='YTD CF'!H15 | K15: ='YTD CF'!I15-'YTD CF'!H15 | L15: ='YTD CF'!J15-'YTD CF'!I15 | M15: ='CASH FLOW'!E15-'YTD CF'!J15 | N15: ='YTD CF'!K15 | O15: ='YTD CF'!L15-'YTD CF'!K15 | P15: ='YTD CF'!M15-'YTD CF'!L15 | Q15: ='CASH FLOW'!F15-'YTD CF'!M15 | R15: ='YTD CF'!N15 | S15: ='YTD CF'!O15-'YTD CF'!N15 | T15: ='YTD CF'!P15-'YTD CF'!O15 | U15: ='CASH FLOW'!G15-'YTD CF'!P15 | V15: ='YTD CF'!Q15 | W15: ='YTD CF'!R15-'YTD CF'!Q15 | X15: ='YTD CF'!S15-'YTD CF'!R15 | Y15: ='CASH FLOW'!H15-'YTD CF'!S15 | Z15: ='YTD CF'!T15 | AA15: ='YTD CF'!U15-'YTD CF'!T15 | AB15: ='YTD CF'!V15-'YTD CF'!U15 | AC15: ='CASH FLOW'!I15-'YTD CF'!V15 | AD15: ='YTD CF'!W15 | AE15: ='YTD CF'!X15-'YTD CF'!W15 | AF15: ='YTD CF'!Y15-'YTD CF'!X15 | AG15: ='CASH FLOW'!J15-'YTD CF'!Y15 | AH15: ='CF DRIVERS'!AH15 | AI15: ='CF DRIVERS'!AI15 | AJ15: ='CF DRIVERS'!AJ15 | AK15: ='CF DRIVERS'!AK15 | AL15: ='CF DRIVERS'!AL15 | AM15: ='CF DRIVERS'!AM15 | AN15: ='CF DRIVERS'!AN15 | AO15: ='CF DRIVERS'!AO15 | ... BA15: ='CF DRIVERS'!BA15
A16: Cash Flow from Operations | B16: ='YTD CF'!B16 | C16: ='YTD CF'!C16-'YTD CF'!B16 | D16: ='YTD CF'!D16-'YTD CF'!C16 | E16: ='CASH FLOW'!C16-'YTD CF'!D16 | F16: ='YTD CF'!E16 | G16: ='YTD CF'!F16-'YTD CF'!E16 | H16: ='YTD CF'!G16-'YTD CF'!F16 | I16: ='CASH FLOW'!D16-'YTD CF'!G16 | J16: ='YTD CF'!H16 | K16: ='YTD CF'!I16-'YTD CF'!H16 | L16: ='YTD CF'!J16-'YTD CF'!I16 | M16: ='CASH FLOW'!E16-'YTD CF'!J16 | N16: ='YTD CF'!K16 | O16: ='YTD CF'!L16-'YTD CF'!K16 | P16: ='YTD CF'!M16-'YTD CF'!L16 | Q16: ='CASH FLOW'!F16-'YTD CF'!M16 | R16: ='YTD CF'!N16 | S16: ='YTD CF'!O16-'YTD CF'!N16 | T16: ='YTD CF'!P16-'YTD CF'!O16 | U16: ='CASH FLOW'!G16-'YTD CF'!P16 | V16: ='YTD CF'!Q16 | W16: ='YTD CF'!R16-'YTD CF'!Q16 | X16: ='YTD CF'!S16-'YTD CF'!R16 | Y16: ='CASH FLOW'!H16-'YTD CF'!S16 | Z16: ='YTD CF'!T16 | AA16: ='YTD CF'!U16-'YTD CF'!T16 | AB16: ='YTD CF'!V16-'YTD CF'!U16 | AC16: ='CASH FLOW'!I16-'YTD CF'!V16 | AD16: ='YTD CF'!W16 | AE16: ='YTD CF'!X16-'YTD CF'!W16 | AF16: ='YTD CF'!Y16-'YTD CF'!X16 | AG16: ='CASH FLOW'!J16-'YTD CF'!Y16 | AH16: =SUM(AH2:AH15) | AI16: =SUM(AI2:AI15) | AJ16: =SUM(AJ2:AJ15) | AK16: =SUM(AK2:AK15) | AL16: =SUM(AL2:AL15) | AM16: =SUM(AM2:AM15) | AN16: =SUM(AN2:AN15) | AO16: =SUM(AO2:AO15) | ... BA16: =SUM(BA2:BA15)
A17: Purchase of PP&E | B17: ='YTD CF'!B17 | C17: ='YTD CF'!C17-'YTD CF'!B17 | D17: ='YTD CF'!D17-'YTD CF'!C17 | E17: ='CASH FLOW'!C17-'YTD CF'!D17 | F17: ='YTD CF'!E17 | G17: ='YTD CF'!F17-'YTD CF'!E17 | H17: ='YTD CF'!G17-'YTD CF'!F17 | I17: ='CASH FLOW'!D17-'YTD CF'!G17 | J17: ='YTD CF'!H17 | K17: ='YTD CF'!I17-'YTD CF'!H17 | L17: ='YTD CF'!J17-'YTD CF'!I17 | M17: ='CASH FLOW'!E17-'YTD CF'!J17 | N17: ='YTD CF'!K17 | O17: ='YTD CF'!L17-'YTD CF'!K17 | P17: ='YTD CF'!M17-'YTD CF'!L17 | Q17: ='CASH FLOW'!F17-'YTD CF'!M17 | R17: ='YTD CF'!N17 | S17: ='YTD CF'!O17-'YTD CF'!N17 | T17: ='YTD CF'!P17-'YTD CF'!O17 | U17: ='CASH FLOW'!G17-'YTD CF'!P17 | V17: ='YTD CF'!Q17 | W17: ='YTD CF'!R17-'YTD CF'!Q17 | X17: ='YTD CF'!S17-'YTD CF'!R17 | Y17: ='CASH FLOW'!H17-'YTD CF'!S17 | Z17: ='YTD CF'!T17 | AA17: ='YTD CF'!U17-'YTD CF'!T17 | AB17: ='YTD CF'!V17-'YTD CF'!U17 | AC17: ='CASH FLOW'!I17-'YTD CF'!V17 | AD17: ='YTD CF'!W17 | AE17: ='YTD CF'!X17-'YTD CF'!W17 | AF17: ='YTD CF'!Y17-'YTD CF'!X17 | AG17: ='CASH FLOW'!J17-'YTD CF'!Y17 | AH17: ='QTR P&L'!AH2*'CF DRIVERS'!AH16 | AI17: ='QTR P&L'!AI2*'CF DRIVERS'!AI16 | AJ17: ='QTR P&L'!AJ2*'CF DRIVERS'!AJ16 | AK17: ='QTR P&L'!AK2*'CF DRIVERS'!AK16 | AL17: ='QTR P&L'!AL2*'CF DRIVERS'!AL16 | AM17: ='QTR P&L'!AM2*'CF DRIVERS'!AM16 | AN17: ='QTR P&L'!AN2*'CF DRIVERS'!AN16 | AO17: ='QTR P&L'!AO2*'CF DRIVERS'!AO16 | ... BA17: ='QTR P&L'!BA2*'CF DRIVERS'!BA16
A18: Proceeds from Sale of Assets | B18: ='YTD CF'!B18 | C18: ='YTD CF'!C18-'YTD CF'!B18 | D18: ='YTD CF'!D18-'YTD CF'!C18 | F18: ='YTD CF'!E18 | G18: ='YTD CF'!F18-'YTD CF'!E18 | H18: ='YTD CF'!G18-'YTD CF'!F18 | J18: ='YTD CF'!H18 | K18: ='YTD CF'!I18-'YTD CF'!H18 | L18: ='YTD CF'!J18-'YTD CF'!I18 | N18: ='YTD CF'!K18 | O18: ='YTD CF'!L18-'YTD CF'!K18 | P18: ='YTD CF'!M18-'YTD CF'!L18 | R18: ='YTD CF'!N18 | S18: ='YTD CF'!O18-'YTD CF'!N18 | T18: ='YTD CF'!P18-'YTD CF'!O18 | V18: ='YTD CF'!Q18 | W18: ='YTD CF'!R18-'YTD CF'!Q18 | X18: ='YTD CF'!S18-'YTD CF'!R18 | Z18: ='YTD CF'!T18 | AA18: ='YTD CF'!U18-'YTD CF'!T18 | AB18: ='YTD CF'!V18-'YTD CF'!U18 | AD18: ='YTD CF'!W18 | AE18: ='YTD CF'!X18-'YTD CF'!W18 | AF18: ='YTD CF'!Y18-'YTD CF'!X18 | AH18: ='CF DRIVERS'!AH17 | AI18: ='CF DRIVERS'!AI17 | AJ18: ='CF DRIVERS'!AJ17 | AK18: ='CF DRIVERS'!AK17 | AL18: ='CF DRIVERS'!AL17 | AM18: ='CF DRIVERS'!AM17 | AN18: ='CF DRIVERS'!AN17 | AO18: ='CF DRIVERS'!AO17 | ... BA18: ='CF DRIVERS'!BA17
A19: Net Change in Short-Term Investments | B19: ='YTD CF'!B19 | C19: ='YTD CF'!C19-'YTD CF'!B19 | D19: ='YTD CF'!D19-'YTD CF'!C19 | E19: ='CASH FLOW'!C18-'YTD CF'!D19 | F19: ='YTD CF'!E19 | G19: ='YTD CF'!F19-'YTD CF'!E19 | H19: ='YTD CF'!G19-'YTD CF'!F19 | I19: ='CASH FLOW'!D18-'YTD CF'!G19 | J19: ='YTD CF'!H19 | K19: ='YTD CF'!I19-'YTD CF'!H19 | L19: ='YTD CF'!J19-'YTD CF'!I19 | M19: ='CASH FLOW'!E18-'YTD CF'!J19 | N19: ='YTD CF'!K19 | O19: ='YTD CF'!L19-'YTD CF'!K19 | P19: ='YTD CF'!M19-'YTD CF'!L19 | Q19: ='CASH FLOW'!F18-'YTD CF'!M19 | R19: ='YTD CF'!N19 | S19: ='YTD CF'!O19-'YTD CF'!N19 | T19: ='YTD CF'!P19-'YTD CF'!O19 | U19: ='CASH FLOW'!G18-'YTD CF'!P19 | V19: ='YTD CF'!Q19 | W19: ='YTD CF'!R19-'YTD CF'!Q19 | X19: ='YTD CF'!S19-'YTD CF'!R19 | Y19: ='CASH FLOW'!H18-'YTD CF'!S19 | Z19: ='YTD CF'!T19 | AA19: ='YTD CF'!U19-'YTD CF'!T19 | AB19: ='YTD CF'!V19-'YTD CF'!U19 | AC19: ='CASH FLOW'!I18-'YTD CF'!V19 | AD19: ='YTD CF'!W19 | AE19: ='YTD CF'!X19-'YTD CF'!W19 | AF19: ='YTD CF'!Y19-'YTD CF'!X19 | AG19: ='CASH FLOW'!J18-'YTD CF'!Y19 | AH19: ='CF DRIVERS'!AH18 | AI19: ='CF DRIVERS'!AI18 | AJ19: ='CF DRIVERS'!AJ18 | AK19: ='CF DRIVERS'!AK18 | AL19: ='CF DRIVERS'!AL18 | AM19: ='CF DRIVERS'!AM18 | AN19: ='CF DRIVERS'!AN18 | AO19: ='CF DRIVERS'!AO18 | ... BA19: ='CF DRIVERS'!BA18
A20: Net Change in Long-Term Investments | B20: ='YTD CF'!B20 | C20: ='YTD CF'!C20-'YTD CF'!B20 | D20: ='YTD CF'!D20-'YTD CF'!C20 | E20: ='CASH FLOW'!C19-'YTD CF'!D20 | F20: ='YTD CF'!E20 | G20: ='YTD CF'!F20-'YTD CF'!E20 | H20: ='YTD CF'!G20-'YTD CF'!F20 | I20: ='CASH FLOW'!D19-'YTD CF'!G20 | J20: ='YTD CF'!H20 | K20: ='YTD CF'!I20-'YTD CF'!H20 | L20: ='YTD CF'!J20-'YTD CF'!I20 | M20: ='CASH FLOW'!E19-'YTD CF'!J20 | N20: ='YTD CF'!K20 | O20: ='YTD CF'!L20-'YTD CF'!K20 | P20: ='YTD CF'!M20-'YTD CF'!L20 | Q20: ='CASH FLOW'!F19-'YTD CF'!M20 | R20: ='YTD CF'!N20 | S20: ='YTD CF'!O20-'YTD CF'!N20 | T20: ='YTD CF'!P20-'YTD CF'!O20 | U20: ='CASH FLOW'!G19-'YTD CF'!P20 | V20: ='YTD CF'!Q20 | W20: ='YTD CF'!R20-'YTD CF'!Q20 | X20: ='YTD CF'!S20-'YTD CF'!R20 | Y20: ='CASH FLOW'!H19-'YTD CF'!S20 | Z20: ='YTD CF'!T20 | AA20: ='YTD CF'!U20-'YTD CF'!T20 | AB20: ='YTD CF'!V20-'YTD CF'!U20 | AC20: ='CASH FLOW'!I19-'YTD CF'!V20 | AD20: ='YTD CF'!W20 | AE20: ='YTD CF'!X20-'YTD CF'!W20 | AF20: ='YTD CF'!Y20-'YTD CF'!X20 | AG20: ='CASH FLOW'!J19-'YTD CF'!Y20 | AH20: ='CF DRIVERS'!AH19 | AI20: ='CF DRIVERS'!AI19 | AJ20: ='CF DRIVERS'!AJ19 | AK20: ='CF DRIVERS'!AK19 | AL20: ='CF DRIVERS'!AL19 | AM20: ='CF DRIVERS'!AM19 | AN20: ='CF DRIVERS'!AN19 | AO20: ='CF DRIVERS'!AO19 | ... BA20: ='CF DRIVERS'!BA19
A21: Acquisitions, Net of Cash Acquired | B21: ='YTD CF'!B21 | C21: ='YTD CF'!C21-'YTD CF'!B21 | D21: ='YTD CF'!D21-'YTD CF'!C21 | E21: ='CASH FLOW'!C20-'YTD CF'!D21 | F21: ='YTD CF'!E21 | G21: ='YTD CF'!F21-'YTD CF'!E21 | H21: ='YTD CF'!G21-'YTD CF'!F21 | I21: ='CASH FLOW'!D20-'YTD CF'!G21 | J21: ='YTD CF'!H21 | K21: ='YTD CF'!I21-'YTD CF'!H21 | L21: ='YTD CF'!J21-'YTD CF'!I21 | M21: ='CASH FLOW'!E20-'YTD CF'!J21 | N21: ='YTD CF'!K21 | O21: ='YTD CF'!L21-'YTD CF'!K21 | P21: ='YTD CF'!M21-'YTD CF'!L21 | Q21: ='CASH FLOW'!F20-'YTD CF'!M21 | R21: ='YTD CF'!N21 | S21: ='YTD CF'!O21-'YTD CF'!N21 | T21: ='YTD CF'!P21-'YTD CF'!O21 | U21: ='CASH FLOW'!G20-'YTD CF'!P21 | V21: ='YTD CF'!Q21 | W21: ='YTD CF'!R21-'YTD CF'!Q21 | X21: ='YTD CF'!S21-'YTD CF'!R21 | Y21: ='CASH FLOW'!H20-'YTD CF'!S21 | Z21: ='YTD CF'!T21 | AA21: ='YTD CF'!U21-'YTD CF'!T21 | AB21: ='YTD CF'!V21-'YTD CF'!U21 | AC21: ='CASH FLOW'!I20-'YTD CF'!V21 | AD21: ='YTD CF'!W21 | AE21: ='YTD CF'!X21-'YTD CF'!W21 | AF21: ='YTD CF'!Y21-'YTD CF'!X21 | AG21: ='CASH FLOW'!J20-'YTD CF'!Y21 | AH21: ='CF DRIVERS'!AH20 | AI21: ='CF DRIVERS'!AI20 | AJ21: ='CF DRIVERS'!AJ20 | AK21: ='CF DRIVERS'!AK20 | AL21: ='CF DRIVERS'!AL20 | AM21: ='CF DRIVERS'!AM20 | AN21: ='CF DRIVERS'!AN20 | AO21: ='CF DRIVERS'!AO20 | ... BA21: ='CF DRIVERS'!BA20
A22: Collections from Note Receivable | B22: ='YTD CF'!B22 | C22: ='YTD CF'!C22-'YTD CF'!B22 | D22: ='YTD CF'!D22-'YTD CF'!C22 | E22: ='CASH FLOW'!C21-'YTD CF'!D22 | F22: ='YTD CF'!E22 | G22: ='YTD CF'!F22-'YTD CF'!E22 | H22: ='YTD CF'!G22-'YTD CF'!F22 | I22: ='CASH FLOW'!D21-'YTD CF'!G22 | J22: ='YTD CF'!H22 | K22: ='YTD CF'!I22-'YTD CF'!H22 | L22: ='YTD CF'!J22-'YTD CF'!I22 | M22: ='CASH FLOW'!E21-'YTD CF'!J22 | N22: ='YTD CF'!K22 | O22: ='YTD CF'!L22-'YTD CF'!K22 | P22: ='YTD CF'!M22-'YTD CF'!L22 | Q22: ='CASH FLOW'!F21-'YTD CF'!M22 | R22: ='YTD CF'!N22 | S22: ='YTD CF'!O22-'YTD CF'!N22 | T22: ='YTD CF'!P22-'YTD CF'!O22 | U22: ='CASH FLOW'!G21-'YTD CF'!P22 | V22: ='YTD CF'!Q22 | W22: ='YTD CF'!R22-'YTD CF'!Q22 | X22: ='YTD CF'!S22-'YTD CF'!R22 | Y22: ='CASH FLOW'!H21-'YTD CF'!S22 | Z22: ='YTD CF'!T22 | AA22: ='YTD CF'!U22-'YTD CF'!T22 | AB22: ='YTD CF'!V22-'YTD CF'!U22 | AC22: ='CASH FLOW'!I21-'YTD CF'!V22 | AD22: ='YTD CF'!W22 | AE22: ='YTD CF'!X22-'YTD CF'!W22 | AF22: ='YTD CF'!Y22-'YTD CF'!X22 | AG22: ='CASH FLOW'!J21-'YTD CF'!Y22 | AH22: ='CF DRIVERS'!AH21 | AI22: ='CF DRIVERS'!AI21 | AJ22: ='CF DRIVERS'!AJ21 | AK22: ='CF DRIVERS'!AK21 | AL22: ='CF DRIVERS'!AL21 | AM22: ='CF DRIVERS'!AM21 | AN22: ='CF DRIVERS'!AN21 | AO22: ='CF DRIVERS'!AO21 | ... BA22: ='CF DRIVERS'!BA21
A23: Other Investing Activities | B23: ='YTD CF'!B23 | C23: ='YTD CF'!C23-'YTD CF'!B23 | D23: ='YTD CF'!D23-'YTD CF'!C23 | E23: ='CASH FLOW'!C22-'YTD CF'!D23 | F23: ='YTD CF'!E23 | G23: ='YTD CF'!F23-'YTD CF'!E23 | H23: ='YTD CF'!G23-'YTD CF'!F23 | I23: ='CASH FLOW'!D22-'YTD CF'!G23 | J23: ='YTD CF'!H23 | K23: ='YTD CF'!I23-'YTD CF'!H23 | L23: ='YTD CF'!J23-'YTD CF'!I23 | M23: ='CASH FLOW'!E22-'YTD CF'!J23 | N23: ='YTD CF'!K23 | O23: ='YTD CF'!L23-'YTD CF'!K23 | P23: ='YTD CF'!M23-'YTD CF'!L23 | Q23: ='CASH FLOW'!F22-'YTD CF'!M23 | R23: ='YTD CF'!N23 | S23: ='YTD CF'!O23-'YTD CF'!N23 | T23: ='YTD CF'!P23-'YTD CF'!O23 | U23: ='CASH FLOW'!G22-'YTD CF'!P23 | V23: ='YTD CF'!Q23 | W23: ='YTD CF'!R23-'YTD CF'!Q23 | X23: ='YTD CF'!S23-'YTD CF'!R23 | Y23: ='CASH FLOW'!H22-'YTD CF'!S23 | Z23: ='YTD CF'!T23 | AA23: ='YTD CF'!U23-'YTD CF'!T23 | AB23: ='YTD CF'!V23-'YTD CF'!U23 | AC23: ='CASH FLOW'!I22-'YTD CF'!V23 | AD23: ='YTD CF'!W23 | AE23: ='YTD CF'!X23-'YTD CF'!W23 | AF23: ='YTD CF'!Y23-'YTD CF'!X23 | AG23: ='CASH FLOW'!J22-'YTD CF'!Y23 | AH23: ='CF DRIVERS'!AH22 | AI23: ='CF DRIVERS'!AI22 | AJ23: ='CF DRIVERS'!AJ22 | AK23: ='CF DRIVERS'!AK22 | AL23: ='CF DRIVERS'!AL22 | AM23: ='CF DRIVERS'!AM22 | AN23: ='CF DRIVERS'!AN22 | AO23: ='CF DRIVERS'!AO22 | ... BA23: ='CF DRIVERS'!BA22
A24: Cash Flow from Investing | B24: ='YTD CF'!B24 | C24: ='YTD CF'!C24-'YTD CF'!B24 | D24: ='YTD CF'!D24-'YTD CF'!C24 | E24: ='CASH FLOW'!C23-'YTD CF'!D24 | F24: ='YTD CF'!E24 | G24: ='YTD CF'!F24-'YTD CF'!E24 | H24: ='YTD CF'!G24-'YTD CF'!F24 | I24: ='CASH FLOW'!D23-'YTD CF'!G24 | J24: ='YTD CF'!H24 | K24: ='YTD CF'!I24-'YTD CF'!H24 | L24: ='YTD CF'!J24-'YTD CF'!I24 | M24: ='CASH FLOW'!E23-'YTD CF'!J24 | N24: ='YTD CF'!K24 | O24: ='YTD CF'!L24-'YTD CF'!K24 | P24: ='YTD CF'!M24-'YTD CF'!L24 | Q24: ='CASH FLOW'!F23-'YTD CF'!M24 | R24: ='YTD CF'!N24 | S24: ='YTD CF'!O24-'YTD CF'!N24 | T24: ='YTD CF'!P24-'YTD CF'!O24 | U24: ='CASH FLOW'!G23-'YTD CF'!P24 | V24: ='YTD CF'!Q24 | W24: ='YTD CF'!R24-'YTD CF'!Q24 | X24: ='YTD CF'!S24-'YTD CF'!R24 | Y24: ='CASH FLOW'!H23-'YTD CF'!S24 | Z24: ='YTD CF'!T24 | AA24: ='YTD CF'!U24-'YTD CF'!T24 | AB24: ='YTD CF'!V24-'YTD CF'!U24 | AC24: ='CASH FLOW'!I23-'YTD CF'!V24 | AD24: ='YTD CF'!W24 | AE24: ='YTD CF'!X24-'YTD CF'!W24 | AF24: ='YTD CF'!Y24-'YTD CF'!X24 | AG24: ='CASH FLOW'!J23-'YTD CF'!Y24 | AH24: =SUM(AH17:AH23) | AI24: =SUM(AI17:AI23) | AJ24: =SUM(AJ17:AJ23) | AK24: =SUM(AK17:AK23) | AL24: =SUM(AL17:AL23) | AM24: =SUM(AM17:AM23) | AN24: =SUM(AN17:AN23) | AO24: =SUM(AO17:AO23) | ... BA24: =SUM(BA17:BA23)
A25: Stock-Based Award Activities, Net | B25: ='YTD CF'!B25 | C25: ='YTD CF'!C25-'YTD CF'!B25 | D25: ='YTD CF'!D25-'YTD CF'!C25 | E25: ='CASH FLOW'!C24-'YTD CF'!D25 | F25: ='YTD CF'!E25 | G25: ='YTD CF'!F25-'YTD CF'!E25 | H25: ='YTD CF'!G25-'YTD CF'!F25 | I25: ='CASH FLOW'!D24-'YTD CF'!G25 | J25: ='YTD CF'!H25 | K25: ='YTD CF'!I25-'YTD CF'!H25 | L25: ='YTD CF'!J25-'YTD CF'!I25 | M25: ='CASH FLOW'!E24-'YTD CF'!J25 | N25: ='YTD CF'!K25 | O25: ='YTD CF'!L25-'YTD CF'!K25 | P25: ='YTD CF'!M25-'YTD CF'!L25 | Q25: ='CASH FLOW'!F24-'YTD CF'!M25 | R25: ='YTD CF'!N25 | S25: ='YTD CF'!O25-'YTD CF'!N25 | T25: ='YTD CF'!P25-'YTD CF'!O25 | U25: ='CASH FLOW'!G24-'YTD CF'!P25 | V25: ='YTD CF'!Q25 | W25: ='YTD CF'!R25-'YTD CF'!Q25 | X25: ='YTD CF'!S25-'YTD CF'!R25 | Y25: ='CASH FLOW'!H24-'YTD CF'!S25 | Z25: ='YTD CF'!T25 | AA25: ='YTD CF'!U25-'YTD CF'!T25 | AB25: ='YTD CF'!V25-'YTD CF'!U25 | AC25: ='CASH FLOW'!I24-'YTD CF'!V25 | AD25: ='YTD CF'!W25 | AE25: ='YTD CF'!X25-'YTD CF'!W25 | AF25: ='YTD CF'!Y25-'YTD CF'!X25 | AG25: ='CASH FLOW'!J24-'YTD CF'!Y25 | AH25: ='CF DRIVERS'!AH23 | AI25: ='CF DRIVERS'!AI23 | AJ25: ='CF DRIVERS'!AJ23 | AK25: ='CF DRIVERS'!AK23 | AL25: ='CF DRIVERS'!AL23 | AM25: ='CF DRIVERS'!AM23 | AN25: ='CF DRIVERS'!AN23 | AO25: ='CF DRIVERS'!AO23 | ... BA25: ='CF DRIVERS'!BA23
A26: Share Repurchases | B26: ='YTD CF'!B26 | C26: ='YTD CF'!C26-'YTD CF'!B26 | D26: ='YTD CF'!D26-'YTD CF'!C26 | E26: ='CASH FLOW'!C25-'YTD CF'!D26 | F26: ='YTD CF'!E26 | G26: ='YTD CF'!F26-'YTD CF'!E26 | H26: ='YTD CF'!G26-'YTD CF'!F26 | I26: ='CASH FLOW'!D25-'YTD CF'!G26 | J26: ='YTD CF'!H26 | K26: ='YTD CF'!I26-'YTD CF'!H26 | L26: ='YTD CF'!J26-'YTD CF'!I26 | M26: ='CASH FLOW'!E25-'YTD CF'!J26 | N26: ='YTD CF'!K26 | O26: ='YTD CF'!L26-'YTD CF'!K26 | P26: ='YTD CF'!M26-'YTD CF'!L26 | Q26: ='CASH FLOW'!F25-'YTD CF'!M26 | R26: ='YTD CF'!N26 | S26: ='YTD CF'!O26-'YTD CF'!N26 | T26: ='YTD CF'!P26-'YTD CF'!O26 | U26: ='CASH FLOW'!G25-'YTD CF'!P26 | V26: ='YTD CF'!Q26 | W26: ='YTD CF'!R26-'YTD CF'!Q26 | X26: ='YTD CF'!S26-'YTD CF'!R26 | Y26: ='CASH FLOW'!H25-'YTD CF'!S26 | Z26: ='YTD CF'!T26 | AA26: ='YTD CF'!U26-'YTD CF'!T26 | AB26: ='YTD CF'!V26-'YTD CF'!U26 | AC26: ='CASH FLOW'!I25-'YTD CF'!V26 | AD26: ='YTD CF'!W26 | AE26: ='YTD CF'!X26-'YTD CF'!W26 | AF26: ='YTD CF'!Y26-'YTD CF'!X26 | AG26: ='CASH FLOW'!J25-'YTD CF'!Y26 | AH26: ='CF DRIVERS'!AH24 | AI26: ='CF DRIVERS'!AI24 | AJ26: ='CF DRIVERS'!AJ24 | AK26: ='CF DRIVERS'!AK24 | AL26: ='CF DRIVERS'!AL24 | AM26: ='CF DRIVERS'!AM24 | AN26: ='CF DRIVERS'!AN24 | AO26: ='CF DRIVERS'!AO24 | ... BA26: ='CF DRIVERS'!BA24
A27: Common Dividends | B27: ='YTD CF'!B27 | C27: ='YTD CF'!C27-'YTD CF'!B27 | D27: ='YTD CF'!D27-'YTD CF'!C27 | E27: ='CASH FLOW'!C26-'YTD CF'!D27 | F27: ='YTD CF'!E27 | G27: ='YTD CF'!F27-'YTD CF'!E27 | H27: ='YTD CF'!G27-'YTD CF'!F27 | I27: ='CASH FLOW'!D26-'YTD CF'!G27 | J27: ='YTD CF'!H27 | K27: ='YTD CF'!I27-'YTD CF'!H27 | L27: ='YTD CF'!J27-'YTD CF'!I27 | M27: ='CASH FLOW'!E26-'YTD CF'!J27 | N27: ='YTD CF'!K27 | O27: ='YTD CF'!L27-'YTD CF'!K27 | P27: ='YTD CF'!M27-'YTD CF'!L27 | Q27: ='CASH FLOW'!F26-'YTD CF'!M27 | R27: ='YTD CF'!N27 | S27: ='YTD CF'!O27-'YTD CF'!N27 | T27: ='YTD CF'!P27-'YTD CF'!O27 | U27: ='CASH FLOW'!G26-'YTD CF'!P27 | V27: ='YTD CF'!Q27 | W27: ='YTD CF'!R27-'YTD CF'!Q27 | X27: ='YTD CF'!S27-'YTD CF'!R27 | Y27: ='CASH FLOW'!H26-'YTD CF'!S27 | Z27: ='YTD CF'!T27 | AA27: ='YTD CF'!U27-'YTD CF'!T27 | AB27: ='YTD CF'!V27-'YTD CF'!U27 | AC27: ='CASH FLOW'!I26-'YTD CF'!V27 | AD27: ='YTD CF'!W27 | AE27: ='YTD CF'!X27-'YTD CF'!W27 | AF27: ='YTD CF'!Y27-'YTD CF'!X27 | AG27: ='CASH FLOW'!J26-'YTD CF'!Y27 | AH27: ='QTR P&L'!AH13*'CF DRIVERS'!AH25 | AI27: ='QTR P&L'!AI13*'CF DRIVERS'!AI25 | AJ27: ='QTR P&L'!AJ13*'CF DRIVERS'!AJ25 | AK27: ='QTR P&L'!AK13*'CF DRIVERS'!AK25 | AL27: ='QTR P&L'!AL13*'CF DRIVERS'!AL25 | AM27: ='QTR P&L'!AM13*'CF DRIVERS'!AM25 | AN27: ='QTR P&L'!AN13*'CF DRIVERS'!AN25 | AO27: ='QTR P&L'!AO13*'CF DRIVERS'!AO25 | ... BA27: ='QTR P&L'!BA13*'CF DRIVERS'!BA25
A28: Proceeds from Issuance of Long-Term Debt | B28: ='YTD CF'!B28 | C28: ='YTD CF'!C28-'YTD CF'!B28 | D28: ='YTD CF'!D28-'YTD CF'!C28 | E28: ='CASH FLOW'!C27-'YTD CF'!D28 | F28: ='YTD CF'!E28 | G28: ='YTD CF'!F28-'YTD CF'!E28 | H28: ='YTD CF'!G28-'YTD CF'!F28 | I28: ='CASH FLOW'!D27-'YTD CF'!G28 | J28: ='YTD CF'!H28 | K28: ='YTD CF'!I28-'YTD CF'!H28 | L28: ='YTD CF'!J28-'YTD CF'!I28 | M28: ='CASH FLOW'!E27-'YTD CF'!J28 | N28: ='YTD CF'!K28 | O28: ='YTD CF'!L28-'YTD CF'!K28 | P28: ='YTD CF'!M28-'YTD CF'!L28 | Q28: ='CASH FLOW'!F27-'YTD CF'!M28 | R28: ='YTD CF'!N28 | S28: ='YTD CF'!O28-'YTD CF'!N28 | T28: ='YTD CF'!P28-'YTD CF'!O28 | U28: ='CASH FLOW'!G27-'YTD CF'!P28 | V28: ='YTD CF'!Q28 | W28: ='YTD CF'!R28-'YTD CF'!Q28 | X28: ='YTD CF'!S28-'YTD CF'!R28 | Y28: ='CASH FLOW'!H27-'YTD CF'!S28 | Z28: ='YTD CF'!T28 | AA28: ='YTD CF'!U28-'YTD CF'!T28 | AB28: ='YTD CF'!V28-'YTD CF'!U28 | AC28: ='CASH FLOW'!I27-'YTD CF'!V28 | AD28: ='YTD CF'!W28 | AE28: ='YTD CF'!X28-'YTD CF'!W28 | AF28: ='YTD CF'!Y28-'YTD CF'!X28 | AG28: ='CASH FLOW'!J27-'YTD CF'!Y28 | AH28: ='CF DRIVERS'!AH26 | AI28: ='CF DRIVERS'!AI26 | AJ28: ='CF DRIVERS'!AJ26 | AK28: ='CF DRIVERS'!AK26 | AL28: ='CF DRIVERS'!AL26 | AM28: ='CF DRIVERS'!AM26 | AN28: ='CF DRIVERS'!AN26 | AO28: ='CF DRIVERS'!AO26 | ... BA28: ='CF DRIVERS'!BA26
A29: Net Change in Other Short-Term Debt | B29: ='YTD CF'!B29 | C29: ='YTD CF'!C29-'YTD CF'!B29 | D29: ='YTD CF'!D29-'YTD CF'!C29 | E29: ='CASH FLOW'!C28-'YTD CF'!D29 | F29: ='YTD CF'!E29 | G29: ='YTD CF'!F29-'YTD CF'!E29 | H29: ='YTD CF'!G29-'YTD CF'!F29 | I29: ='CASH FLOW'!D28-'YTD CF'!G29 | J29: ='YTD CF'!H29 | K29: ='YTD CF'!I29-'YTD CF'!H29 | L29: ='YTD CF'!J29-'YTD CF'!I29 | M29: ='CASH FLOW'!E28-'YTD CF'!J29 | N29: ='YTD CF'!K29 | O29: ='YTD CF'!L29-'YTD CF'!K29 | P29: ='YTD CF'!M29-'YTD CF'!L29 | Q29: ='CASH FLOW'!F28-'YTD CF'!M29 | R29: ='YTD CF'!N29 | S29: ='YTD CF'!O29-'YTD CF'!N29 | T29: ='YTD CF'!P29-'YTD CF'!O29 | U29: ='CASH FLOW'!G28-'YTD CF'!P29 | V29: ='YTD CF'!Q29 | W29: ='YTD CF'!R29-'YTD CF'!Q29 | X29: ='YTD CF'!S29-'YTD CF'!R29 | Y29: ='CASH FLOW'!H28-'YTD CF'!S29 | Z29: ='YTD CF'!T29 | AA29: ='YTD CF'!U29-'YTD CF'!T29 | AB29: ='YTD CF'!V29-'YTD CF'!U29 | AC29: ='CASH FLOW'!I28-'YTD CF'!V29 | AD29: ='YTD CF'!W29 | AE29: ='YTD CF'!X29-'YTD CF'!W29 | AF29: ='YTD CF'!Y29-'YTD CF'!X29 | AG29: ='CASH FLOW'!J28-'YTD CF'!Y29 | AH29: ='CF DRIVERS'!AH27 | AI29: ='CF DRIVERS'!AI27 | AJ29: ='CF DRIVERS'!AJ27 | AK29: ='CF DRIVERS'!AK27 | AL29: ='CF DRIVERS'!AL27 | AM29: ='CF DRIVERS'!AM27 | AN29: ='CF DRIVERS'!AN27 | AO29: ='CF DRIVERS'!AO27 | ... BA29: ='CF DRIVERS'!BA27
A30: Proceeds from Sale of Interest in Consolidated Entities | B30: ='YTD CF'!B30 | C30: ='YTD CF'!C30-'YTD CF'!B30 | D30: ='YTD CF'!D30-'YTD CF'!C30 | E30: ='CASH FLOW'!C29-'YTD CF'!D30 | F30: ='YTD CF'!E30 | G30: ='YTD CF'!F30-'YTD CF'!E30 | H30: ='YTD CF'!G30-'YTD CF'!F30 | I30: ='CASH FLOW'!D29-'YTD CF'!G30 | J30: ='YTD CF'!H30 | K30: ='YTD CF'!I30-'YTD CF'!H30 | L30: ='YTD CF'!J30-'YTD CF'!I30 | M30: ='CASH FLOW'!E29-'YTD CF'!J30 | N30: ='YTD CF'!K30 | O30: ='YTD CF'!L30-'YTD CF'!K30 | P30: ='YTD CF'!M30-'YTD CF'!L30 | Q30: ='CASH FLOW'!F29-'YTD CF'!M30 | R30: ='YTD CF'!N30 | S30: ='YTD CF'!O30-'YTD CF'!N30 | T30: ='YTD CF'!P30-'YTD CF'!O30 | U30: ='CASH FLOW'!G29-'YTD CF'!P30 | V30: ='YTD CF'!Q30 | W30: ='YTD CF'!R30-'YTD CF'!Q30 | X30: ='YTD CF'!S30-'YTD CF'!R30 | Y30: ='CASH FLOW'!H29-'YTD CF'!S30 | Z30: ='YTD CF'!T30 | AA30: ='YTD CF'!U30-'YTD CF'!T30 | AB30: ='YTD CF'!V30-'YTD CF'!U30 | AC30: ='CASH FLOW'!I29-'YTD CF'!V30 | AD30: ='YTD CF'!W30 | AE30: ='YTD CF'!X30-'YTD CF'!W30 | AF30: ='YTD CF'!Y30-'YTD CF'!X30 | AG30: ='CASH FLOW'!J29-'YTD CF'!Y30 | AH30: ='CF DRIVERS'!AH28 | AI30: ='CF DRIVERS'!AI28 | AJ30: ='CF DRIVERS'!AJ28 | AK30: ='CF DRIVERS'!AK28 | AL30: ='CF DRIVERS'!AL28 | AM30: ='CF DRIVERS'!AM28 | AN30: ='CF DRIVERS'!AN28 | AO30: ='CF DRIVERS'!AO28 | ... BA30: ='CF DRIVERS'!BA28
A31: Cash Flow from Financing | B31: ='YTD CF'!B31 | C31: ='YTD CF'!C31-'YTD CF'!B31 | D31: ='YTD CF'!D31-'YTD CF'!C31 | E31: ='CASH FLOW'!C30-'YTD CF'!D31 | F31: ='YTD CF'!E31 | G31: ='YTD CF'!F31-'YTD CF'!E31 | H31: ='YTD CF'!G31-'YTD CF'!F31 | I31: ='CASH FLOW'!D30-'YTD CF'!G31 | J31: ='YTD CF'!H31 | K31: ='YTD CF'!I31-'YTD CF'!H31 | L31: ='YTD CF'!J31-'YTD CF'!I31 | M31: ='CASH FLOW'!E30-'YTD CF'!J31 | N31: ='YTD CF'!K31 | O31: ='YTD CF'!L31-'YTD CF'!K31 | P31: ='YTD CF'!M31-'YTD CF'!L31 | Q31: ='CASH FLOW'!F30-'YTD CF'!M31 | R31: ='YTD CF'!N31 | S31: ='YTD CF'!O31-'YTD CF'!N31 | T31: ='YTD CF'!P31-'YTD CF'!O31 | U31: ='CASH FLOW'!G30-'YTD CF'!P31 | V31: ='YTD CF'!Q31 | W31: ='YTD CF'!R31-'YTD CF'!Q31 | X31: ='YTD CF'!S31-'YTD CF'!R31 | Y31: ='CASH FLOW'!H30-'YTD CF'!S31 | Z31: ='YTD CF'!T31 | AA31: ='YTD CF'!U31-'YTD CF'!T31 | AB31: ='YTD CF'!V31-'YTD CF'!U31 | AC31: ='CASH FLOW'!I30-'YTD CF'!V31 | AD31: ='YTD CF'!W31 | AE31: ='YTD CF'!X31-'YTD CF'!W31 | AF31: ='YTD CF'!Y31-'YTD CF'!X31 | AG31: ='CASH FLOW'!J30-'YTD CF'!Y31 | AH31: =SUM(AH25:AH30) | AI31: =SUM(AI25:AI30) | AJ31: =SUM(AJ25:AJ30) | AK31: =SUM(AK25:AK30) | AL31: =SUM(AL25:AL30) | AM31: =SUM(AM25:AM30) | AN31: =SUM(AN25:AN30) | AO31: =SUM(AO25:AO30) | ... BA31: =SUM(BA25:BA30)
A32: FX Effect on Cash | B32: ='YTD CF'!B32 | C32: ='YTD CF'!C32-'YTD CF'!B32 | D32: ='YTD CF'!D32-'YTD CF'!C32 | E32: ='CASH FLOW'!C31-'YTD CF'!D32 | F32: ='YTD CF'!E32 | G32: ='YTD CF'!F32-'YTD CF'!E32 | H32: ='YTD CF'!G32-'YTD CF'!F32 | I32: ='CASH FLOW'!D31-'YTD CF'!G32 | J32: ='YTD CF'!H32 | K32: ='YTD CF'!I32-'YTD CF'!H32 | L32: ='YTD CF'!J32-'YTD CF'!I32 | M32: ='CASH FLOW'!E31-'YTD CF'!J32 | N32: ='YTD CF'!K32 | O32: ='YTD CF'!L32-'YTD CF'!K32 | P32: ='YTD CF'!M32-'YTD CF'!L32 | Q32: ='CASH FLOW'!F31-'YTD CF'!M32 | R32: ='YTD CF'!N32 | S32: ='YTD CF'!O32-'YTD CF'!N32 | T32: ='YTD CF'!P32-'YTD CF'!O32 | U32: ='CASH FLOW'!G31-'YTD CF'!P32 | V32: ='YTD CF'!Q32 | W32: ='YTD CF'!R32-'YTD CF'!Q32 | X32: ='YTD CF'!S32-'YTD CF'!R32 | Y32: ='CASH FLOW'!H31-'YTD CF'!S32 | Z32: ='YTD CF'!T32 | AA32: ='YTD CF'!U32-'YTD CF'!T32 | AB32: ='YTD CF'!V32-'YTD CF'!U32 | AC32: ='CASH FLOW'!I31-'YTD CF'!V32 | AD32: ='YTD CF'!W32 | AE32: ='YTD CF'!X32-'YTD CF'!W32 | AF32: ='YTD CF'!Y32-'YTD CF'!X32 | AG32: ='CASH FLOW'!J31-'YTD CF'!Y32 | AH32: ='CF DRIVERS'!AH29 | AI32: ='CF DRIVERS'!AI29 | AJ32: ='CF DRIVERS'!AJ29 | AK32: ='CF DRIVERS'!AK29 | AL32: ='CF DRIVERS'!AL29 | AM32: ='CF DRIVERS'!AM29 | AN32: ='CF DRIVERS'!AN29 | AO32: ='CF DRIVERS'!AO29 | ... BA32: ='CF DRIVERS'!BA29
A33: Net Change in Cash | B33: ='YTD CF'!B33 | C33: ='YTD CF'!C33-'YTD CF'!B33 | D33: ='YTD CF'!D33-'YTD CF'!C33 | E33: ='CASH FLOW'!C32-'YTD CF'!D33 | F33: ='YTD CF'!E33 | G33: ='YTD CF'!F33-'YTD CF'!E33 | H33: ='YTD CF'!G33-'YTD CF'!F33 | I33: ='CASH FLOW'!D32-'YTD CF'!G33 | J33: ='YTD CF'!H33 | K33: ='YTD CF'!I33-'YTD CF'!H33 | L33: ='YTD CF'!J33-'YTD CF'!I33 | M33: ='CASH FLOW'!E32-'YTD CF'!J33 | N33: ='YTD CF'!K33 | O33: ='YTD CF'!L33-'YTD CF'!K33 | P33: ='YTD CF'!M33-'YTD CF'!L33 | Q33: ='CASH FLOW'!F32-'YTD CF'!M33 | R33: ='YTD CF'!N33 | S33: ='YTD CF'!O33-'YTD CF'!N33 | T33: ='YTD CF'!P33-'YTD CF'!O33 | U33: ='CASH FLOW'!G32-'YTD CF'!P33 | V33: ='YTD CF'!Q33 | W33: ='YTD CF'!R33-'YTD CF'!Q33 | X33: ='YTD CF'!S33-'YTD CF'!R33 | Y33: ='CASH FLOW'!H32-'YTD CF'!S33 | Z33: ='YTD CF'!T33 | AA33: ='YTD CF'!U33-'YTD CF'!T33 | AB33: ='YTD CF'!V33-'YTD CF'!U33 | AC33: ='CASH FLOW'!I32-'YTD CF'!V33 | AD33: ='YTD CF'!W33 | AE33: ='YTD CF'!X33-'YTD CF'!W33 | AF33: ='YTD CF'!Y33-'YTD CF'!X33 | AG33: ='CASH FLOW'!J32-'YTD CF'!Y33 | AH33: =AH16+AH24+AH31+AH32 | AI33: =AI16+AI24+AI31+AI32 | AJ33: =AJ16+AJ24+AJ31+AJ32 | AK33: =AK16+AK24+AK31+AK32 | AL33: =AL16+AL24+AL31+AL32 | AM33: =AM16+AM24+AM31+AM32 | AN33: =AN16+AN24+AN31+AN32 | AO33: =AO16+AO24+AO31+AO32 | ... BA33: =BA16+BA24+BA31+BA32

Sheet IS DRIVERS
A1: Driver | B1: Basis | C1: Q1 FY2018 | D1: Q2 FY2018 | E1: Q3 FY2018 | F1: Q4 FY2018 | G1: Q1 FY2019 | H1: Q2 FY2019 | I1: Q3 FY2019 | J1: Q4 FY2019 | K1: Q1 FY2020 | L1: Q2 FY2020 | M1: Q3 FY2020 | N1: Q4 FY2020 | O1: Q1 FY2021 | P1: Q2 FY2021 | Q1: Q3 FY2021 | R1: Q4 FY2021 | S1: Q1 FY2022 | T1: Q2 FY2022 | U1: Q3 FY2022 | V1: Q4 FY2022 | W1: Q1 FY2023 | X1: Q2 FY2023 | Y1: Q3 FY2023 | Z1: Q4 FY2023 | AA1: Q1 FY2024 | AB1: Q2 FY2024 | AC1: Q3 FY2024 | AD1: Q4 FY2024 | AE1: Q1 FY2025 | AF1: Q2 FY2025 | AG1: Q3 FY2025 | AH1: Q4 FY2025 | AI1: Q1 FY2026E | AJ1: Q2 FY2026E | AK1: Q3 FY2026E | AL1: Q4 FY2026E | AM1: Q1 FY2027E | AN1: Q2 FY2027E | AO1: Q3 FY2027E | AP1: Q4 FY2027E | AQ1: Q1 FY2028E | AR1: Q2 FY2028E | AS1: Q3 FY2028E | AT1: Q4 FY2028E | AU1: Q1 FY2029E | AV1: Q2 FY2029E | AW1: Q3 FY2029E | AX1: Q4 FY2029E | AY1: Q1 FY2030E | AZ1: Q2 FY2030E | BA1: Q3 FY2030E | BB1: Q4 FY2030E
A2: Net Sales / Revenue — Growth % | B2: YoY | D2: =IFERROR('QTR P&L'!C2/'QTR P&L'!B2-1,"") | E2: =IFERROR('QTR P&L'!D2/'QTR P&L'!C2-1,"") | F2: =IFERROR('QTR P&L'!E2/'QTR P&L'!D2-1,"") | G2: =IFERROR('QTR P&L'!F2/IF($B2="QoQ",'QTR P&L'!E2,'QTR P&L'!B2)-1,"") | H2: =IFERROR('QTR P&L'!G2/IF($B2="QoQ",'QTR P&L'!F2,'QTR P&L'!C2)-1,"") | I2: =IFERROR('QTR P&L'!H2/IF($B2="QoQ",'QTR P&L'!G2,'QTR P&L'!D2)-1,"") | J2: =IFERROR('QTR P&L'!I2/IF($B2="QoQ",'QTR P&L'!H2,'QTR P&L'!E2)-1,"") | K2: =IFERROR('QTR P&L'!J2/IF($B2="QoQ",'QTR P&L'!I2,'QTR P&L'!F2)-1,"") | L2: =IFERROR('QTR P&L'!K2/IF($B2="QoQ",'QTR P&L'!J2,'QTR P&L'!G2)-1,"") | M2: =IFERROR('QTR P&L'!L2/IF($B2="QoQ",'QTR P&L'!K2,'QTR P&L'!H2)-1,"") | N2: =IFERROR('QTR P&L'!M2/IF($B2="QoQ",'QTR P&L'!L2,'QTR P&L'!I2)-1,"") | ... AH2: =IFERROR('QTR P&L'!AG2/IF($B2="QoQ",'QTR P&L'!AF2,'QTR P&L'!AC2)-1,"") | AI2: =AH2 | AJ2: =AI2 | AK2: =AJ2 | AL2: =AK2 | AM2: =AL2 | AN2: =AM2 | AO2: =AN2 | AP2: =AO2 | ... BB2: =BA2
A3: COGS — % of Revenue | C3: =IFERROR('QTR P&L'!B3/'QTR P&L'!B2,"") | D3: =IFERROR('QTR P&L'!C3/'QTR P&L'!C2,"") | E3: =IFERROR('QTR P&L'!D3/'QTR P&L'!D2,"") | F3: =IFERROR('QTR P&L'!E3/'QTR P&L'!E2,"") | G3: =IFERROR('QTR P&L'!F3/'QTR P&L'!F2,"") | H3: =IFERROR('QTR P&L'!G3/'QTR P&L'!G2,"") | I3: =IFERROR('QTR P&L'!H3/'QTR P&L'!H2,"") | J3: =IFERROR('QTR P&L'!I3/'QTR P&L'!I2,"") | ... AH3: =IFERROR('QTR P&L'!AG3/'QTR P&L'!AG2,"") | AI3: =AH3 | AJ3: =AI3 | AK3: =AJ3 | AL3: =AK3 | AM3: =AL3 | AN3: =AM3 | AO3: =AN3 | AP3: =AO3 | ... BB3: =BA3
A4: Research and Development — % of Revenue | C4: =IFERROR('QTR P&L'!B5/'QTR P&L'!B2,"") | D4: =IFERROR('QTR P&L'!C5/'QTR P&L'!C2,"") | E4: =IFERROR('QTR P&L'!D5/'QTR P&L'!D2,"") | F4: =IFERROR('QTR P&L'!E5/'QTR P&L'!E2,"") | G4: =IFERROR('QTR P&L'!F5/'QTR P&L'!F2,"") | H4: =IFERROR('QTR P&L'!G5/'QTR P&L'!G2,"") | I4: =IFERROR('QTR P&L'!H5/'QTR P&L'!H2,"") | J4: =IFERROR('QTR P&L'!I5/'QTR P&L'!I2,"") | ... AH4: =IFERROR('QTR P&L'!AG5/'QTR P&L'!AG2,"") | AI4: =AH4 | AJ4: =AI4 | AK4: =AJ4 | AL4: =AK4 | AM4: =AL4 | AN4: =AM4 | AO4: =AN4 | AP4: =AO4 | ... BB4: =BA4
A5: Sales and Marketing — % of Revenue | C5: =IFERROR('QTR P&L'!B6/'QTR P&L'!B2,"") | D5: =IFERROR('QTR P&L'!C6/'QTR P&L'!C2,"") | E5: =IFERROR('QTR P&L'!D6/'QTR P&L'!D2,"") | F5: =IFERROR('QTR P&L'!E6/'QTR P&L'!E2,"") | G5: =IFERROR('QTR P&L'!F6/'QTR P&L'!F2,"") | H5: =IFERROR('QTR P&L'!G6/'QTR P&L'!G2,"") | I5: =IFERROR('QTR P&L'!H6/'QTR P&L'!H2,"") | J5: =IFERROR('QTR P&L'!I6/'QTR P&L'!I2,"") | ... AH5: =IFERROR('QTR P&L'!AG6/'QTR P&L'!AG2,"") | AI5: =AH5 | AJ5: =AI5 | AK5: =AJ5 | AL5: =AK5 | AM5: =AL5 | AN5: =AM5 | AO5: =AN5 | AP5: =AO5 | ... BB5: =BA5
A6: General and Administrative — % of Revenue | C6: =IFERROR('QTR P&L'!B7/'QTR P&L'!B2,"") | D6: =IFERROR('QTR P&L'!C7/'QTR P&L'!C2,"") | E6: =IFERROR('QTR P&L'!D7/'QTR P&L'!D2,"") | F6: =IFERROR('QTR P&L'!E7/'QTR P&L'!E2,"") | G6: =IFERROR('QTR P&L'!F7/'QTR P&L'!F2,"") | H6: =IFERROR('QTR P&L'!G7/'QTR P&L'!G2,"") | I6: =IFERROR('QTR P&L'!H7/'QTR P&L'!H2,"") | J6: =IFERROR('QTR P&L'!I7/'QTR P&L'!I2,"") | ... AH6: =IFERROR('QTR P&L'!AG7/'QTR P&L'!AG2,"") | AI6: =AH6 | AJ6: =AI6 | AK6: =AJ6 | AL6: =AK6 | AM6: =AL6 | AN6: =AM6 | AO6: =AN6 | AP6: =AO6 | ... BB6: =BA6
A7: Litigation and Regulatory Charges — % of Revenue | C7: =IFERROR('QTR P&L'!B8/'QTR P&L'!B2,"") | D7: =IFERROR('QTR P&L'!C8/'QTR P&L'!C2,"") | E7: =IFERROR('QTR P&L'!D8/'QTR P&L'!D2,"") | F7: =IFERROR('QTR P&L'!E8/'QTR P&L'!E2,"") | G7: =IFERROR('QTR P&L'!F8/'QTR P&L'!F2,"") | H7: =IFERROR('QTR P&L'!G8/'QTR P&L'!G2,"") | I7: =IFERROR('QTR P&L'!H8/'QTR P&L'!H2,"") | J7: =IFERROR('QTR P&L'!I8/'QTR P&L'!I2,"") | ... AH7: =IFERROR('QTR P&L'!AG8/'QTR P&L'!AG2,"") | AI7: =AH7 | AJ7: =AI7 | AK7: =AJ7 | AL7: =AK7 | AM7: =AL7 | AN7: =AM7 | AO7: =AN7 | AP7: =AO7 | ... BB7: =BA7
A8: Other Income (Expense) | C8: ='QTR P&L'!B10 | D8: ='QTR P&L'!C10 | E8: ='QTR P&L'!D10 | F8: ='QTR P&L'!E10 | G8: ='QTR P&L'!F10 | H8: ='QTR P&L'!G10 | I8: ='QTR P&L'!H10 | J8: ='QTR P&L'!I10 | ... AH8: ='QTR P&L'!AG10 | AI8: =AH8 | AJ8: =AI8 | AK8: =AJ8 | AL8: =AK8 | AM8: =AL8 | AN8: =AM8 | AO8: =AN8 | AP8: =AO8 | ... BB8: =BA8
A9: Income Tax (Expense) Benefit — Effective Tax Rate % | C9: =IFERROR('QTR P&L'!B12/'QTR P&L'!B11,"") | D9: =IFERROR('QTR P&L'!C12/'QTR P&L'!C11,"") | E9: =IFERROR('QTR P&L'!D12/'QTR P&L'!D11,"") | F9: =IFERROR('QTR P&L'!E12/'QTR P&L'!E11,"") | G9: =IFERROR('QTR P&L'!F12/'QTR P&L'!F11,"") | H9: =IFERROR('QTR P&L'!G12/'QTR P&L'!G11,"") | I9: =IFERROR('QTR P&L'!H12/'QTR P&L'!H11,"") | J9: =IFERROR('QTR P&L'!I12/'QTR P&L'!I11,"") | ... AH9: =IFERROR('QTR P&L'!AG12/'QTR P&L'!AG11,"") | AI9: =AH9 | AJ9: =AI9 | AK9: =AJ9 | AL9: =AK9 | AM9: =AL9 | AN9: =AM9 | AO9: =AN9 | AP9: =AO9 | ... BB9: =BA9

Sheet BS DRIVERS
A1: Driver | B1: Q4 FY2018 | C1: Q1 FY2019 | D1: Q2 FY2019 | E1: Q3 FY2019 | F1: Q4 FY2019 | G1: Q1 FY2020 | H1: Q2 FY2020 | I1: Q3 FY2020 | J1: Q4 FY2020 | K1: Q1 FY2021 | L1: Q2 FY2021 | M1: Q3 FY2021 | N1: Q4 FY2021 | O1: Q1 FY2022 | P1: Q2 FY2022 | Q1: Q3 FY2022 | R1: Q4 FY2022 | S1: Q1 FY2023 | T1: Q2 FY2023 | U1: Q3 FY2023 | V1: Q4 FY2023 | W1: Q1 FY2024 | X1: Q2 FY2024 | Y1: Q3 FY2024 | Z1: Q4 FY2024 | AA1: Q1 FY2025 | AB1: Q2 FY2025 | AC1: Q3 FY2025 | AD1: Q4 FY2025 | AE1: Q1 FY2026E | AF1: Q2 FY2026E | AG1: Q3 FY2026E | AH1: Q4 FY2026E | AI1: Q1 FY2027E | AJ1: Q2 FY2027E | AK1: Q3 FY2027E | AL1: Q4 FY2027E | AM1: Q1 FY2028E | AN1: Q2 FY2028E | AO1: Q3 FY2028E | AP1: Q4 FY2028E | AQ1: Q1 FY2029E | AR1: Q2 FY2029E | AS1: Q3 FY2029E | AT1: Q4 FY2029E | AU1: Q1 FY2030E | AV1: Q2 FY2030E | AW1: Q3 FY2030E | AX1: Q4 FY2030E
A2: Cash & Cash Equivalents | B2: ='QTR BS'!B2 | C2: ='QTR BS'!C2 | D2: ='QTR BS'!D2 | E2: ='QTR BS'!E2 | F2: ='QTR BS'!F2 | G2: ='QTR BS'!G2 | H2: ='QTR BS'!H2 | I2: ='QTR BS'!I2 | ... AD2: ='QTR BS'!AD2 | AE2: =AD2+'QTR CF'!AH33 | AF2: =AE2+'QTR CF'!AI33 | AG2: =AF2+'QTR CF'!AJ33 | AH2: =AG2+'QTR CF'!AK33 | AI2: =AH2+'QTR CF'!AL33 | AJ2: =AI2+'QTR CF'!AM33 | AK2: =AJ2+'QTR CF'!AN33 | AL2: =AK2+'QTR CF'!AO33 | ... AX2: =AW2+'QTR CF'!BA33
A3: Short-Term Investments | B3: ='QTR BS'!B3 | C3: ='QTR BS'!C3 | D3: ='QTR BS'!D3 | E3: ='QTR BS'!E3 | F3: ='QTR BS'!F3 | G3: ='QTR BS'!G3 | H3: ='QTR BS'!H3 | I3: ='QTR BS'!I3 | ... AD3: ='QTR BS'!AD3 | AE3: =AD3 | AF3: =AE3 | AG3: =AF3 | AH3: =AG3 | AI3: =AH3 | AJ3: =AI3 | AK3: =AJ3 | AL3: =AK3 | ... AX3: =AW3
A4: Accounts Receivable — DSO (days) | B4: =IFERROR('QTR BS'!B4/'QTR P&L'!E2*ASSUMPTIONS!$B$2,"") | C4: =IFERROR('QTR BS'!C4/'QTR P&L'!F2*ASSUMPTIONS!$B$2,"") | D4: =IFERROR('QTR BS'!D4/'QTR P&L'!G2*ASSUMPTIONS!$B$2,"") | E4: =IFERROR('QTR BS'!E4/'QTR P&L'!H2*ASSUMPTIONS!$B$2,"") | F4: =IFERROR('QTR BS'!F4/'QTR P&L'!I2*ASSUMPTIONS!$B$2,"") | G4: =IFERROR('QTR BS'!G4/'QTR P&L'!J2*ASSUMPTIONS!$B$2,"") | H4: =IFERROR('QTR BS'!H4/'QTR P&L'!K2*ASSUMPTIONS!$B$2,"") | I4: =IFERROR('QTR BS'!I4/'QTR P&L'!L2*ASSUMPTIONS!$B$2,"") | ... AD4: =IFERROR('QTR BS'!AD4/'QTR P&L'!AG2*ASSUMPTIONS!$B$2,"") | AE4: =AD4 | AF4: =AE4 | AG4: =AF4 | AH4: =AG4 | AI4: =AH4 | AJ4: =AI4 | AK4: =AJ4 | AL4: =AK4 | ... AX4: =AW4
A5: Note Receivable - Current — DSO (days) | B5: =IFERROR('QTR BS'!B5/'QTR P&L'!E2*ASSUMPTIONS!$B$2,"") | C5: =IFERROR('QTR BS'!C5/'QTR P&L'!F2*ASSUMPTIONS!$B$2,"") | D5: =IFERROR('QTR BS'!D5/'QTR P&L'!G2*ASSUMPTIONS!$B$2,"") | E5: =IFERROR('QTR BS'!E5/'QTR P&L'!H2*ASSUMPTIONS!$B$2,"") | F5: =IFERROR('QTR BS'!F5/'QTR P&L'!I2*ASSUMPTIONS!$B$2,"") | G5: =IFERROR('QTR BS'!G5/'QTR P&L'!J2*ASSUMPTIONS!$B$2,"") | H5: =IFERROR('QTR BS'!H5/'QTR P&L'!K2*ASSUMPTIONS!$B$2,"") | I5: =IFERROR('QTR BS'!I5/'QTR P&L'!L2*ASSUMPTIONS!$B$2,"") | ... AD5: =IFERROR('QTR BS'!AD5/'QTR P&L'!AG2*ASSUMPTIONS!$B$2,"") | AE5: =AD5 | AF5: =AE5 | AG5: =AF5 | AH5: =AG5 | AI5: =AH5 | AJ5: =AI5 | AK5: =AJ5 | AL5: =AK5 | ... AX5: =AW5
A6: Inventories — DIO (days) | B6: =IFERROR('QTR BS'!B6/'QTR P&L'!E3*ASSUMPTIONS!$B$2,"") | C6: =IFERROR('QTR BS'!C6/'QTR P&L'!F3*ASSUMPTIONS!$B$2,"") | D6: =IFERROR('QTR BS'!D6/'QTR P&L'!G3*ASSUMPTIONS!$B$2,"") | E6: =IFERROR('QTR BS'!E6/'QTR P&L'!H3*ASSUMPTIONS!$B$2,"") | F6: =IFERROR('QTR BS'!F6/'QTR P&L'!I3*ASSUMPTIONS!$B$2,"") | G6: =IFERROR('QTR BS'!G6/'QTR P&L'!J3*ASSUMPTIONS!$B$2,"") | H6: =IFERROR('QTR BS'!H6/'QTR P&L'!K3*ASSUMPTIONS!$B$2,"") | I6: =IFERROR('QTR BS'!I6/'QTR P&L'!L3*ASSUMPTIONS!$B$2,"") | ... AD6: =IFERROR('QTR BS'!AD6/'QTR P&L'!AG3*ASSUMPTIONS!$B$2,"") | AE6: =AD6 | AF6: =AE6 | AG6: =AF6 | AH6: =AG6 | AI6: =AH6 | AJ6: =AI6 | AK6: =AJ6 | AL6: =AK6 | ... AX6: =AW6
A7: Other Current Assets — % of Revenue | B7: =IFERROR('QTR BS'!B7/'QTR P&L'!E2,"") | C7: =IFERROR('QTR BS'!C7/'QTR P&L'!F2,"") | D7: =IFERROR('QTR BS'!D7/'QTR P&L'!G2,"") | E7: =IFERROR('QTR BS'!E7/'QTR P&L'!H2,"") | F7: =IFERROR('QTR BS'!F7/'QTR P&L'!I2,"") | G7: =IFERROR('QTR BS'!G7/'QTR P&L'!J2,"") | H7: =IFERROR('QTR BS'!H7/'QTR P&L'!K2,"") | I7: =IFERROR('QTR BS'!I7/'QTR P&L'!L2,"") | ... AD7: =IFERROR('QTR BS'!AD7/'QTR P&L'!AG2,"") | AE7: =AD7 | AF7: =AE7 | AG7: =AF7 | AH7: =AG7 | AI7: =AH7 | AJ7: =AI7 | AK7: =AJ7 | AL7: =AK7 | ... AX7: =AW7
A8: Long-Term Investments — % of Revenue | B8: =IFERROR('QTR BS'!B9/'QTR P&L'!E2,"") | C8: =IFERROR('QTR BS'!C9/'QTR P&L'!F2,"") | D8: =IFERROR('QTR BS'!D9/'QTR P&L'!G2,"") | E8: =IFERROR('QTR BS'!E9/'QTR P&L'!H2,"") | F8: =IFERROR('QTR BS'!F9/'QTR P&L'!I2,"") | G8: =IFERROR('QTR BS'!G9/'QTR P&L'!J2,"") | H8: =IFERROR('QTR BS'!H9/'QTR P&L'!K2,"") | I8: =IFERROR('QTR BS'!I9/'QTR P&L'!L2,"") | ... AD8: =IFERROR('QTR BS'!AD9/'QTR P&L'!AG2,"") | AE8: =AD8 | AF8: =AE8 | AG8: =AF8 | AH8: =AG8 | AI8: =AH8 | AJ8: =AI8 | AK8: =AJ8 | AL8: =AK8 | ... AX8: =AW8
A9: Deferred Tax Assets | B9: ='QTR BS'!B10 | C9: ='QTR BS'!C10 | D9: ='QTR BS'!D10 | E9: ='QTR BS'!E10 | F9: ='QTR BS'!F10 | G9: ='QTR BS'!G10 | H9: ='QTR BS'!H10 | I9: ='QTR BS'!I10 | ... AD9: ='QTR BS'!AD10 | AE9: =AD9-'QTR CF'!AH7 | AF9: =AE9-'QTR CF'!AI7 | AG9: =AF9-'QTR CF'!AJ7 | AH9: =AG9-'QTR CF'!AK7 | AI9: =AH9-'QTR CF'!AL7 | AJ9: =AI9-'QTR CF'!AM7 | AK9: =AJ9-'QTR CF'!AN7 | AL9: =AK9-'QTR CF'!AO7 | ... AX9: =AW9-'QTR CF'!BA7
A10: Net PP&E | B10: ='QTR BS'!B11 | C10: ='QTR BS'!C11 | D10: ='QTR BS'!D11 | E10: ='QTR BS'!E11 | F10: ='QTR BS'!F11 | G10: ='QTR BS'!G11 | H10: ='QTR BS'!H11 | I10: ='QTR BS'!I11 | ... AD10: ='QTR BS'!AD11 | AE10: =AD10-'QTR CF'!AH17 | AF10: =AE10-'QTR CF'!AI17 | AG10: =AF10-'QTR CF'!AJ17 | AH10: =AG10-'QTR CF'!AK17 | AI10: =AH10-'QTR CF'!AL17 | AJ10: =AI10-'QTR CF'!AM17 | AK10: =AJ10-'QTR CF'!AN17 | AL10: =AK10-'QTR CF'!AO17 | ... AX10: =AW10-'QTR CF'!BA17
A11: ROU Assets - Operating - Non-Current — % of Revenue | B11: =IFERROR('QTR BS'!B12/'QTR P&L'!E2,"") | C11: =IFERROR('QTR BS'!C12/'QTR P&L'!F2,"") | D11: =IFERROR('QTR BS'!D12/'QTR P&L'!G2,"") | E11: =IFERROR('QTR BS'!E12/'QTR P&L'!H2,"") | F11: =IFERROR('QTR BS'!F12/'QTR P&L'!I2,"") | G11: =IFERROR('QTR BS'!G12/'QTR P&L'!J2,"") | H11: =IFERROR('QTR BS'!H12/'QTR P&L'!K2,"") | I11: =IFERROR('QTR BS'!I12/'QTR P&L'!L2,"") | ... AD11: =IFERROR('QTR BS'!AD12/'QTR P&L'!AG2,"") | AE11: =AD11 | AF11: =AE11 | AG11: =AF11 | AH11: =AG11 | AI11: =AH11 | AJ11: =AI11 | AK11: =AJ11 | AL11: =AK11 | ... AX11: =AW11
A12: Intangible Assets | B12: ='QTR BS'!B13 | C12: ='QTR BS'!C13 | D12: ='QTR BS'!D13 | E12: ='QTR BS'!E13 | F12: ='QTR BS'!F13 | G12: ='QTR BS'!G13 | H12: ='QTR BS'!H13 | I12: ='QTR BS'!I13 | ... AD12: ='QTR BS'!AD13 | AE12: =AD12 | AF12: =AE12 | AG12: =AF12 | AH12: =AG12 | AI12: =AH12 | AJ12: =AI12 | AK12: =AJ12 | AL12: =AK12 | ... AX12: =AW12
A13: Goodwill | B13: ='QTR BS'!B14 | C13: ='QTR BS'!C14 | D13: ='QTR BS'!D14 | E13: ='QTR BS'!E14 | F13: ='QTR BS'!F14 | G13: ='QTR BS'!G14 | H13: ='QTR BS'!H14 | I13: ='QTR BS'!I14 | ... AD13: ='QTR BS'!AD14 | AE13: =AD13 | AF13: =AE13 | AG13: =AF13 | AH13: =AG13 | AI13: =AH13 | AJ13: =AI13 | AK13: =AJ13 | AL13: =AK13 | ... AX13: =AW13
A14: Other Non-Current Assets — % of Revenue | B14: =IFERROR('QTR BS'!B15/'QTR P&L'!E2,"") | C14: =IFERROR('QTR BS'!C15/'QTR P&L'!F2,"") | D14: =IFERROR('QTR BS'!D15/'QTR P&L'!G2,"") | E14: =IFERROR('QTR BS'!E15/'QTR P&L'!H2,"") | F14: =IFERROR('QTR BS'!F15/'QTR P&L'!I2,"") | G14: =IFERROR('QTR BS'!G15/'QTR P&L'!J2,"") | H14: =IFERROR('QTR BS'!H15/'QTR P&L'!K2,"") | I14: =IFERROR('QTR BS'!I15/'QTR P&L'!L2,"") | ... AD14: =IFERROR('QTR BS'!AD15/'QTR P&L'!AG2,"") | AE14: =AD14 | AF14: =AE14 | AG14: =AF14 | AH14: =AG14 | AI14: =AH14 | AJ14: =AI14 | AK14: =AJ14 | AL14: =AK14 | ... AX14: =AW14
A15: Accounts Payable — DPO (days) | B15: =IFERROR('QTR BS'!B17/'QTR P&L'!E3*ASSUMPTIONS!$B$2,"") | C15: =IFERROR('QTR BS'!C17/'QTR P&L'!F3*ASSUMPTIONS!$B$2,"") | D15: =IFERROR('QTR BS'!D17/'QTR P&L'!G3*ASSUMPTIONS!$B$2,"") | E15: =IFERROR('QTR BS'!E17/'QTR P&L'!H3*ASSUMPTIONS!$B$2,"") | F15: =IFERROR('QTR BS'!F17/'QTR P&L'!I3*ASSUMPTIONS!$B$2,"") | G15: =IFERROR('QTR BS'!G17/'QTR P&L'!J3*ASSUMPTIONS!$B$2,"") | H15: =IFERROR('QTR BS'!H17/'QTR P&L'!K3*ASSUMPTIONS!$B$2,"") | I15: =IFERROR('QTR BS'!I17/'QTR P&L'!L3*ASSUMPTIONS!$B$2,"") | ... AD15: =IFERROR('QTR BS'!AD17/'QTR P&L'!AG3*ASSUMPTIONS!$B$2,"") | AE15: =AD15 | AF15: =AE15 | AG15: =AF15 | AH15: =AG15 | AI15: =AH15 | AJ15: =AI15 | AK15: =AJ15 | AL15: =AK15 | ... AX15: =AW15
A16: Accrued Compensation — % of Revenue | B16: =IFERROR('QTR BS'!B18/'QTR P&L'!E2,"") | C16: =IFERROR('QTR BS'!C18/'QTR P&L'!F2,"") | D16: =IFERROR('QTR BS'!D18/'QTR P&L'!G2,"") | E16: =IFERROR('QTR BS'!E18/'QTR P&L'!H2,"") | F16: =IFERROR('QTR BS'!F18/'QTR P&L'!I2,"") | G16: =IFERROR('QTR BS'!G18/'QTR P&L'!J2,"") | H16: =IFERROR('QTR BS'!H18/'QTR P&L'!K2,"") | I16: =IFERROR('QTR BS'!I18/'QTR P&L'!L2,"") | ... AD16: =IFERROR('QTR BS'!AD18/'QTR P&L'!AG2,"") | AE16: =AD16 | AF16: =AE16 | AG16: =AF16 | AH16: =AG16 | AI16: =AH16 | AJ16: =AI16 | AK16: =AJ16 | AL16: =AK16 | ... AX16: =AW16
A17: Accrued Expenses — % of Revenue | B17: =IFERROR('QTR BS'!B19/'QTR P&L'!E2,"") | C17: =IFERROR('QTR BS'!C19/'QTR P&L'!F2,"") | D17: =IFERROR('QTR BS'!D19/'QTR P&L'!G2,"") | E17: =IFERROR('QTR BS'!E19/'QTR P&L'!H2,"") | F17: =IFERROR('QTR BS'!F19/'QTR P&L'!I2,"") | G17: =IFERROR('QTR BS'!G19/'QTR P&L'!J2,"") | H17: =IFERROR('QTR BS'!H19/'QTR P&L'!K2,"") | I17: =IFERROR('QTR BS'!I19/'QTR P&L'!L2,"") | ... AD17: =IFERROR('QTR BS'!AD19/'QTR P&L'!AG2,"") | AE17: =AD17 | AF17: =AE17 | AG17: =AF17 | AH17: =AG17 | AI17: =AH17 | AJ17: =AI17 | AK17: =AJ17 | AL17: =AK17 | ... AX17: =AW17
A18: Accrued Revenue Share — % of Revenue | B18: =IFERROR('QTR BS'!B20/'QTR P&L'!E2,"") | C18: =IFERROR('QTR BS'!C20/'QTR P&L'!F2,"") | D18: =IFERROR('QTR BS'!D20/'QTR P&L'!G2,"") | E18: =IFERROR('QTR BS'!E20/'QTR P&L'!H2,"") | F18: =IFERROR('QTR BS'!F20/'QTR P&L'!I2,"") | G18: =IFERROR('QTR BS'!G20/'QTR P&L'!J2,"") | H18: =IFERROR('QTR BS'!H20/'QTR P&L'!K2,"") | I18: =IFERROR('QTR BS'!I20/'QTR P&L'!L2,"") | ... AD18: =IFERROR('QTR BS'!AD20/'QTR P&L'!AG2,"") | AE18: =AD18 | AF18: =AE18 | AG18: =AF18 | AH18: =AG18 | AI18: =AH18 | AJ18: =AI18 | AK18: =AJ18 | AL18: =AK18 | ... AX18: =AW18
A19: Deferred Revenue - Current — % of Revenue | B19: =IFERROR('QTR BS'!B21/'QTR P&L'!E2,"") | C19: =IFERROR('QTR BS'!C21/'QTR P&L'!F2,"") | D19: =IFERROR('QTR BS'!D21/'QTR P&L'!G2,"") | E19: =IFERROR('QTR BS'!E21/'QTR P&L'!H2,"") | F19: =IFERROR('QTR BS'!F21/'QTR P&L'!I2,"") | G19: =IFERROR('QTR BS'!G21/'QTR P&L'!J2,"") | H19: =IFERROR('QTR BS'!H21/'QTR P&L'!K2,"") | I19: =IFERROR('QTR BS'!I21/'QTR P&L'!L2,"") | ... AD19: =IFERROR('QTR BS'!AD21/'QTR P&L'!AG2,"") | AE19: =AD19 | AF19: =AE19 | AG19: =AF19 | AH19: =AG19 | AI19: =AH19 | AJ19: =AI19 | AK19: =AJ19 | AL19: =AK19 | ... AX19: =AW19
A20: Income Taxes Payable — % of Revenue | B20: =IFERROR('QTR BS'!B22/'QTR P&L'!E2,"") | C20: =IFERROR('QTR BS'!C22/'QTR P&L'!F2,"") | D20: =IFERROR('QTR BS'!D22/'QTR P&L'!G2,"") | E20: =IFERROR('QTR BS'!E22/'QTR P&L'!H2,"") | F20: =IFERROR('QTR BS'!F22/'QTR P&L'!I2,"") | G20: =IFERROR('QTR BS'!G22/'QTR P&L'!J2,"") | H20: =IFERROR('QTR BS'!H22/'QTR P&L'!K2,"") | I20: =IFERROR('QTR BS'!I22/'QTR P&L'!L2,"") | ... AD20: =IFERROR('QTR BS'!AD22/'QTR P&L'!AG2,"") | AE20: =AD20 | AF20: =AE20 | AG20: =AF20 | AH20: =AG20 | AI20: =AH20 | AJ20: =AI20 | AK20: =AJ20 | AL20: =AK20 | ... AX20: =AW20
A21: Long-Term Debt | B21: ='QTR BS'!B24 | C21: ='QTR BS'!C24 | D21: ='QTR BS'!D24 | E21: ='QTR BS'!E24 | F21: ='QTR BS'!F24 | G21: ='QTR BS'!G24 | H21: ='QTR BS'!H24 | I21: ='QTR BS'!I24 | ... AD21: ='QTR BS'!AD24 | AE21: =AD21 | AF21: =AE21 | AG21: =AF21 | AH21: =AG21 | AI21: =AH21 | AJ21: =AI21 | AK21: =AJ21 | AL21: =AK21 | ... AX21: =AW21
A22: Deferred Revenue - Non-Current — % of Revenue | B22: =IFERROR('QTR BS'!B25/'QTR P&L'!E2,"") | C22: =IFERROR('QTR BS'!C25/'QTR P&L'!F2,"") | D22: =IFERROR('QTR BS'!D25/'QTR P&L'!G2,"") | E22: =IFERROR('QTR BS'!E25/'QTR P&L'!H2,"") | F22: =IFERROR('QTR BS'!F25/'QTR P&L'!I2,"") | G22: =IFERROR('QTR BS'!G25/'QTR P&L'!J2,"") | H22: =IFERROR('QTR BS'!H25/'QTR P&L'!K2,"") | I22: =IFERROR('QTR BS'!I25/'QTR P&L'!L2,"") | ... AD22: =IFERROR('QTR BS'!AD25/'QTR P&L'!AG2,"") | AE22: =AD22 | AF22: =AE22 | AG22: =AF22 | AH22: =AG22 | AI22: =AH22 | AJ22: =AI22 | AK22: =AJ22 | AL22: =AK22 | ... AX22: =AW22
A23: Deferred Tax Liability | B23: ='QTR BS'!B26 | C23: ='QTR BS'!C26 | D23: ='QTR BS'!D26 | E23: ='QTR BS'!E26 | F23: ='QTR BS'!F26 | G23: ='QTR BS'!G26 | H23: ='QTR BS'!H26 | I23: ='QTR BS'!I26 | ... AD23: ='QTR BS'!AD26 | AE23: =AD23 | AF23: =AE23 | AG23: =AF23 | AH23: =AG23 | AI23: =AH23 | AJ23: =AI23 | AK23: =AJ23 | AL23: =AK23 | ... AX23: =AW23
A24: Lease Liability - Operating - Non-Current — % of Revenue | B24: =IFERROR('QTR BS'!B27/'QTR P&L'!E2,"") | C24: =IFERROR('QTR BS'!C27/'QTR P&L'!F2,"") | D24: =IFERROR('QTR BS'!D27/'QTR P&L'!G2,"") | E24: =IFERROR('QTR BS'!E27/'QTR P&L'!H2,"") | F24: =IFERROR('QTR BS'!F27/'QTR P&L'!I2,"") | G24: =IFERROR('QTR BS'!G27/'QTR P&L'!J2,"") | H24: =IFERROR('QTR BS'!H27/'QTR P&L'!K2,"") | I24: =IFERROR('QTR BS'!I27/'QTR P&L'!L2,"") | ... AD24: =IFERROR('QTR BS'!AD27/'QTR P&L'!AG2,"") | AE24: =AD24 | AF24: =AE24 | AG24: =AF24 | AH24: =AG24 | AI24: =AH24 | AJ24: =AI24 | AK24: =AJ24 | AL24: =AK24 | ... AX24: =AW24
A25: Other Non-Current Liabilities — % of Revenue | B25: =IFERROR('QTR BS'!B28/'QTR P&L'!E2,"") | C25: =IFERROR('QTR BS'!C28/'QTR P&L'!F2,"") | D25: =IFERROR('QTR BS'!D28/'QTR P&L'!G2,"") | E25: =IFERROR('QTR BS'!E28/'QTR P&L'!H2,"") | F25: =IFERROR('QTR BS'!F28/'QTR P&L'!I2,"") | G25: =IFERROR('QTR BS'!G28/'QTR P&L'!J2,"") | H25: =IFERROR('QTR BS'!H28/'QTR P&L'!K2,"") | I25: =IFERROR('QTR BS'!I28/'QTR P&L'!L2,"") | ... AD25: =IFERROR('QTR BS'!AD28/'QTR P&L'!AG2,"") | AE25: =AD25 | AF25: =AE25 | AG25: =AF25 | AH25: =AG25 | AI25: =AH25 | AJ25: =AI25 | AK25: =AJ25 | AL25: =AK25 | ... AX25: =AW25
A26: Convertible Preferred Stock | B26: ='QTR BS'!B30 | C26: ='QTR BS'!C30 | D26: ='QTR BS'!D30 | E26: ='QTR BS'!E30 | F26: ='QTR BS'!F30 | G26: ='QTR BS'!G30 | H26: ='QTR BS'!H30 | I26: ='QTR BS'!I30 | ... AD26: ='QTR BS'!AD30 | AE26: =AD26 | AF26: =AE26 | AG26: =AF26 | AH26: =AG26 | AI26: =AH26 | AJ26: =AI26 | AK26: =AJ26 | AL26: =AK26 | ... AX26: =AW26
A27: Common Stock and Additional Paid-in Capital | B27: ='QTR BS'!B31 | C27: ='QTR BS'!C31 | D27: ='QTR BS'!D31 | E27: ='QTR BS'!E31 | F27: ='QTR BS'!F31 | G27: ='QTR BS'!G31 | H27: ='QTR BS'!H31 | I27: ='QTR BS'!I31 | ... AD27: ='QTR BS'!AD31 | AE27: =AD27+'QTR CF'!AH6 | AF27: =AE27+'QTR CF'!AI6 | AG27: =AF27+'QTR CF'!AJ6 | AH27: =AG27+'QTR CF'!AK6 | AI27: =AH27+'QTR CF'!AL6 | AJ27: =AI27+'QTR CF'!AM6 | AK27: =AJ27+'QTR CF'!AN6 | AL27: =AK27+'QTR CF'!AO6 | ... AX27: =AW27+'QTR CF'!BA6
A28: Accumulated Other Comprehensive Income (Loss) | B28: ='QTR BS'!B32 | C28: ='QTR BS'!C32 | D28: ='QTR BS'!D32 | E28: ='QTR BS'!E32 | F28: ='QTR BS'!F32 | G28: ='QTR BS'!G32 | H28: ='QTR BS'!H32 | I28: ='QTR BS'!I32 | ... AD28: ='QTR BS'!AD32 | AE28: =AD28+'QTR CF'!AH32 | AF28: =AE28+'QTR CF'!AI32 | AG28: =AF28+'QTR CF'!AJ32 | AH28: =AG28+'QTR CF'!AK32 | AI28: =AH28+'QTR CF'!AL32 | AJ28: =AI28+'QTR CF'!AM32 | AK28: =AJ28+'QTR CF'!AN32 | AL28: =AK28+'QTR CF'!AO32 | ... AX28: =AW28+'QTR CF'!BA32
A29: Retained Earnings (Accumulated Deficit) | B29: ='QTR BS'!B33 | C29: ='QTR BS'!C33 | D29: ='QTR BS'!D33 | E29: ='QTR BS'!E33 | F29: ='QTR BS'!F33 | G29: ='QTR BS'!G33 | H29: ='QTR BS'!H33 | I29: ='QTR BS'!I33 | ... AD29: ='QTR BS'!AD33 | AE29: =AD29+'QTR P&L'!AH13+'QTR CF'!AH27 | AF29: =AE29+'QTR P&L'!AI13+'QTR CF'!AI27 | AG29: =AF29+'QTR P&L'!AJ13+'QTR CF'!AJ27 | AH29: =AG29+'QTR P&L'!AK13+'QTR CF'!AK27 | AI29: =AH29+'QTR P&L'!AL13+'QTR CF'!AL27 | AJ29: =AI29+'QTR P&L'!AM13+'QTR CF'!AM27 | AK29: =AJ29+'QTR P&L'!AN13+'QTR CF'!AN27 | AL29: =AK29+'QTR P&L'!AO13+'QTR CF'!AO27 | ... AX29: =AW29+'QTR P&L'!BA13+'QTR CF'!BA27

Sheet CF DRIVERS
A1: Driver | B1: Q1 FY2018 | C1: Q2 FY2018 | D1: Q3 FY2018 | E1: Q4 FY2018 | F1: Q1 FY2019 | G1: Q2 FY2019 | H1: Q3 FY2019 | I1: Q4 FY2019 | J1: Q1 FY2020 | K1: Q2 FY2020 | L1: Q3 FY2020 | M1: Q4 FY2020 | N1: Q1 FY2021 | O1: Q2 FY2021 | P1: Q3 FY2021 | Q1: Q4 FY2021 | R1: Q1 FY2022 | S1: Q2 FY2022 | T1: Q3 FY2022 | U1: Q4 FY2022 | V1: Q1 FY2023 | W1: Q2 FY2023 | X1: Q3 FY2023 | Y1: Q4 FY2023 | Z1: Q1 FY2024 | AA1: Q2 FY2024 | AB1: Q3 FY2024 | AC1: Q4 FY2024 | AD1: Q1 FY2025 | AE1: Q2 FY2025 | AF1: Q3 FY2025 | AG1: Q4 FY2025 | AH1: Q1 FY2026E | AI1: Q2 FY2026E | AJ1: Q3 FY2026E | AK1: Q4 FY2026E | AL1: Q1 FY2027E | AM1: Q2 FY2027E | AN1: Q3 FY2027E | AO1: Q4 FY2027E | AP1: Q1 FY2028E | AQ1: Q2 FY2028E | AR1: Q3 FY2028E | AS1: Q4 FY2028E | AT1: Q1 FY2029E | AU1: Q2 FY2029E | AV1: Q3 FY2029E | AW1: Q4 FY2029E | AX1: Q1 FY2030E | AY1: Q2 FY2030E | AZ1: Q3 FY2030E | BA1: Q4 FY2030E
A2: Net Income (Loss) | B2: ='QTR CF'!B2 | C2: ='QTR CF'!C2 | D2: ='QTR CF'!D2 | E2: ='QTR CF'!E2 | F2: ='QTR CF'!F2 | G2: ='QTR CF'!G2 | H2: ='QTR CF'!H2 | I2: ='QTR CF'!I2 | ... AG2: ='QTR CF'!AG2 | AH2: ='QTR P&L'!AH13 | AI2: ='QTR P&L'!AI13 | AJ2: ='QTR P&L'!AJ13 | AK2: ='QTR P&L'!AK13 | AL2: ='QTR P&L'!AL13 | AM2: ='QTR P&L'!AM13 | AN2: ='QTR P&L'!AN13 | AO2: ='QTR P&L'!AO13 | ... BA2: ='QTR P&L'!BA13
A3: Depreciation and Impairment of PP&E | B3: ='QTR CF'!B3 | C3: ='QTR CF'!C3 | D3: ='QTR CF'!D3 | E3: ='QTR CF'!E3 | F3: ='QTR CF'!F3 | G3: ='QTR CF'!G3 | H3: ='QTR CF'!H3 | I3: ='QTR CF'!I3 | ... AG3: ='QTR CF'!AG3 | AH3: 0 | AI3: 0 | AJ3: 0 | AK3: 0 | AL3: 0 | AM3: 0 | AN3: 0 | AO3: 0 | AP3: 0 | AQ3: 0 | AR3: 0 | AS3: 0 | AT3: 0 | AU3: 0 | AV3: 0 | AW3: 0 | AX3: 0 | AY3: 0 | AZ3: 0 | BA3: 0
A4: Amortization and Impairment of Intangibles | B4: ='QTR CF'!B4 | C4: ='QTR CF'!C4 | D4: ='QTR CF'!D4 | E4: ='QTR CF'!E4 | F4: ='QTR CF'!F4 | G4: ='QTR CF'!G4 | H4: ='QTR CF'!H4 | I4: ='QTR CF'!I4 | ... AG4: ='QTR CF'!AG4 | AH4: 0 | AI4: 0 | AJ4: 0 | AK4: 0 | AL4: 0 | AM4: 0 | AN4: 0 | AO4: 0 | AP4: 0 | AQ4: 0 | AR4: 0 | AS4: 0 | AT4: 0 | AU4: 0 | AV4: 0 | AW4: 0 | AX4: 0 | AY4: 0 | AZ4: 0 | BA4: 0
A5: Depreciation | B5: ='QTR CF'!B5 | C5: ='QTR CF'!C5 | D5: ='QTR CF'!D5 | E5: ='QTR CF'!E5 | F5: ='QTR CF'!F5 | G5: ='QTR CF'!G5 | H5: ='QTR CF'!H5 | I5: ='QTR CF'!I5 | ... AG5: ='QTR CF'!AG5 | AH5: 0 | AI5: 0 | AJ5: 0 | AK5: 0 | AL5: 0 | AM5: 0 | AN5: 0 | AO5: 0 | AP5: 0 | AQ5: 0 | AR5: 0 | AS5: 0 | AT5: 0 | AU5: 0 | AV5: 0 | AW5: 0 | AX5: 0 | AY5: 0 | AZ5: 0 | BA5: 0
A6: Stock-Based Compensation — % of Revenue | B6: =IFERROR('QTR CF'!B6/'QTR P&L'!B2,"") | C6: =IFERROR('QTR CF'!C6/'QTR P&L'!C2,"") | D6: =IFERROR('QTR CF'!D6/'QTR P&L'!D2,"") | E6: =IFERROR('QTR CF'!E6/'QTR P&L'!E2,"") | F6: =IFERROR('QTR CF'!F6/'QTR P&L'!F2,"") | G6: =IFERROR('QTR CF'!G6/'QTR P&L'!G2,"") | H6: =IFERROR('QTR CF'!H6/'QTR P&L'!H2,"") | I6: =IFERROR('QTR CF'!I6/'QTR P&L'!I2,"") | ... AG6: =IFERROR('QTR CF'!AG6/'QTR P&L'!AG2,"") | AH6: =AG6 | AI6: =AH6 | AJ6: =AI6 | AK6: =AJ6 | AL6: =AK6 | AM6: =AL6 | AN6: =AM6 | AO6: =AN6 | ... BA6: =AZ6
A7: (Benefit) Provision for Deferred Income Taxes | B7: ='QTR CF'!B7 | C7: ='QTR CF'!C7 | D7: ='QTR CF'!D7 | E7: ='QTR CF'!E7 | F7: ='QTR CF'!F7 | G7: ='QTR CF'!G7 | H7: ='QTR CF'!H7 | I7: ='QTR CF'!I7 | ... AG7: ='QTR CF'!AG7 | AH7: =AG7 | AI7: =AH7 | AJ7: =AI7 | AK7: =AJ7 | AL7: =AK7 | AM7: =AL7 | AN7: =AM7 | AO7: =AN7 | ... BA7: =AZ7
A8: Loss (Gain) on Equity and Debt Securities, Net | B8: ='QTR CF'!B8 | C8: ='QTR CF'!C8 | D8: ='QTR CF'!D8 | E8: ='QTR CF'!E8 | F8: ='QTR CF'!F8 | G8: ='QTR CF'!G8 | H8: ='QTR CF'!H8 | I8: ='QTR CF'!I8 | ... AG8: ='QTR CF'!AG8 | AH8: 0 | AI8: 0 | AJ8: 0 | AK8: 0 | AL8: 0 | AM8: 0 | AN8: 0 | AO8: 0 | AP8: 0 | AQ8: 0 | AR8: 0 | AS8: 0 | AT8: 0 | AU8: 0 | AV8: 0 | AW8: 0 | AX8: 0 | AY8: 0 | AZ8: 0 | BA8: 0
A9: Other Operating Items | B9: ='QTR CF'!B9 | C9: ='QTR CF'!C9 | D9: ='QTR CF'!D9 | E9: ='QTR CF'!E9 | F9: ='QTR CF'!F9 | G9: ='QTR CF'!G9 | H9: ='QTR CF'!H9 | I9: ='QTR CF'!I9 | ... AG9: ='QTR CF'!AG9 | AH9: =-('QTR BS'!AE5-'QTR BS'!AD5)-('QTR BS'!AE6-'QTR BS'!AD6)-('QTR BS'!AE7-'QTR BS'!AD7)-('QTR BS'!AE12-'QTR BS'!AD12)-('QTR BS'!AE15-'QTR BS'!AD15)+('QTR BS'!AE18-'QTR BS'!AD18)+('QTR BS'!AE21-'QTR BS'!AD21)+('QTR BS'!AE25-'QTR BS'!AD25)+('QTR BS'!AE27-'QTR BS'!AD27)+('QTR BS'!AE28-'QTR BS'!AD28)-('QTR BS'!AE3-'QTR BS'!AD3)-('QTR BS'!AE13-'QTR BS'!AD13)-('QTR BS'!AE14-'QTR BS'!AD14)+('QTR BS'!AE24-'QTR BS'!AD24)+('QTR BS'!AE26-'QTR BS'!AD26) | AI9: =-('QTR BS'!AF5-'QTR BS'!AE5)-('QTR BS'!AF6-'QTR BS'!AE6)-('QTR BS'!AF7-'QTR BS'!AE7)-('QTR BS'!AF12-'QTR BS'!AE12)-('QTR BS'!AF15-'QTR BS'!AE15)+('QTR BS'!AF18-'QTR BS'!AE18)+('QTR BS'!AF21-'QTR BS'!AE21)+('QTR BS'!AF25-'QTR BS'!AE25)+('QTR BS'!AF27-'QTR BS'!AE27)+('QTR BS'!AF28-'QTR BS'!AE28)-('QTR BS'!AF3-'QTR BS'!AE3)-('QTR BS'!AF13-'QTR BS'!AE13)-('QTR BS'!AF14-'QTR BS'!AE14)+('QTR BS'!AF24-'QTR BS'!AE24)+('QTR BS'!AF26-'QTR BS'!AE26) | AJ9: =-('QTR BS'!AG5-'QTR BS'!AF5)-('QTR BS'!AG6-'QTR BS'!AF6)-('QTR BS'!AG7-'QTR BS'!AF7)-('QTR BS'!AG12-'QTR BS'!AF12)-('QTR BS'!AG15-'QTR BS'!AF15)+('QTR BS'!AG18-'QTR BS'!AF18)+('QTR BS'!AG21-'QTR BS'!AF21)+('QTR BS'!AG25-'QTR BS'!AF25)+('QTR BS'!AG27-'QTR BS'!AF27)+('QTR BS'!AG28-'QTR BS'!AF28)-('QTR BS'!AG3-'QTR BS'!AF3)-('QTR BS'!AG13-'QTR BS'!AF13)-('QTR BS'!AG14-'QTR BS'!AF14)+('QTR BS'!AG24-'QTR BS'!AF24)+('QTR BS'!AG26-'QTR BS'!AF26) | AK9: =-('QTR BS'!AH5-'QTR BS'!AG5)-('QTR BS'!AH6-'QTR BS'!AG6)-('QTR BS'!AH7-'QTR BS'!AG7)-('QTR BS'!AH12-'QTR BS'!AG12)-('QTR BS'!AH15-'QTR BS'!AG15)+('QTR BS'!AH18-'QTR BS'!AG18)+('QTR BS'!AH21-'QTR BS'!AG21)+('QTR BS'!AH25-'QTR BS'!AG25)+('QTR BS'!AH27-'QTR BS'!AG27)+('QTR BS'!AH28-'QTR BS'!AG28)-('QTR BS'!AH3-'QTR BS'!AG3)-('QTR BS'!AH13-'QTR BS'!AG13)-('QTR BS'!AH14-'QTR BS'!AG14)+('QTR BS'!AH24-'QTR BS'!AG24)+('QTR BS'!AH26-'QTR BS'!AG26) | AL9: =-('QTR BS'!AI5-'QTR BS'!AH5)-('QTR BS'!AI6-'QTR BS'!AH6)-('QTR BS'!AI7-'QTR BS'!AH7)-('QTR BS'!AI12-'QTR BS'!AH12)-('QTR BS'!AI15-'QTR BS'!AH15)+('QTR BS'!AI18-'QTR BS'!AH18)+('QTR BS'!AI21-'QTR BS'!AH21)+('QTR BS'!AI25-'QTR BS'!AH25)+('QTR BS'!AI27-'QTR BS'!AH27)+('QTR BS'!AI28-'QTR BS'!AH28)-('QTR BS'!AI3-'QTR BS'!AH3)-('QTR BS'!AI13-'QTR BS'!AH13)-('QTR BS'!AI14-'QTR BS'!AH14)+('QTR BS'!AI24-'QTR BS'!AH24)+('QTR BS'!AI26-'QTR BS'!AH26) | AM9: =-('QTR BS'!AJ5-'QTR BS'!AI5)-('QTR BS'!AJ6-'QTR BS'!AI6)-('QTR BS'!AJ7-'QTR BS'!AI7)-('QTR BS'!AJ12-'QTR BS'!AI12)-('QTR BS'!AJ15-'QTR BS'!AI15)+('QTR BS'!AJ18-'QTR BS'!AI18)+('QTR BS'!AJ21-'QTR BS'!AI21)+('QTR BS'!AJ25-'QTR BS'!AI25)+('QTR BS'!AJ27-'QTR BS'!AI27)+('QTR BS'!AJ28-'QTR BS'!AI28)-('QTR BS'!AJ3-'QTR BS'!AI3)-('QTR BS'!AJ13-'QTR BS'!AI13)-('QTR BS'!AJ14-'QTR BS'!AI14)+('QTR BS'!AJ24-'QTR BS'!AI24)+('QTR BS'!AJ26-'QTR BS'!AI26) | AN9: =-('QTR BS'!AK5-'QTR BS'!AJ5)-('QTR BS'!AK6-'QTR BS'!AJ6)-('QTR BS'!AK7-'QTR BS'!AJ7)-('QTR BS'!AK12-'QTR BS'!AJ12)-('QTR BS'!AK15-'QTR BS'!AJ15)+('QTR BS'!AK18-'QTR BS'!AJ18)+('QTR BS'!AK21-'QTR BS'!AJ21)+('QTR BS'!AK25-'QTR BS'!AJ25)+('QTR BS'!AK27-'QTR BS'!AJ27)+('QTR BS'!AK28-'QTR BS'!AJ28)-('QTR BS'!AK3-'QTR BS'!AJ3)-('QTR BS'!AK13-'QTR BS'!AJ13)-('QTR BS'!AK14-'QTR BS'!AJ14)+('QTR BS'!AK24-'QTR BS'!AJ24)+('QTR BS'!AK26-'QTR BS'!AJ26) | AO9: =-('QTR BS'!AL5-'QTR BS'!AK5)-('QTR BS'!AL6-'QTR BS'!AK6)-('QTR BS'!AL7-'QTR BS'!AK7)-('QTR BS'!AL12-'QTR BS'!AK12)-('QTR BS'!AL15-'QTR BS'!AK15)+('QTR BS'!AL18-'QTR BS'!AK18)+('QTR BS'!AL21-'QTR BS'!AK21)+('QTR BS'!AL25-'QTR BS'!AK25)+('QTR BS'!AL27-'QTR BS'!AK27)+('QTR BS'!AL28-'QTR BS'!AK28)-('QTR BS'!AL3-'QTR BS'!AK3)-('QTR BS'!AL13-'QTR BS'!AK13)-('QTR BS'!AL14-'QTR BS'!AK14)+('QTR BS'!AL24-'QTR BS'!AK24)+('QTR BS'!AL26-'QTR BS'!AK26) | ... BA9: =-('QTR BS'!AX5-'QTR BS'!AW5)-('QTR BS'!AX6-'QTR BS'!AW6)-('QTR BS'!AX7-'QTR BS'!AW7)-('QTR BS'!AX12-'QTR BS'!AW12)-('QTR BS'!AX15-'QTR BS'!AW15)+('QTR BS'!AX18-'QTR BS'!AW18)+('QTR BS'!AX21-'QTR BS'!AW21)+('QTR BS'!AX25-'QTR BS'!AW25)+('QTR BS'!AX27-'QTR BS'!AW27)+('QTR BS'!AX28-'QTR BS'!AW28)-('QTR BS'!AX3-'QTR BS'!AW3)-('QTR BS'!AX13-'QTR BS'!AW13)-('QTR BS'!AX14-'QTR BS'!AW14)+('QTR BS'!AX24-'QTR BS'!AW24)+('QTR BS'!AX26-'QTR BS'!AW26)
A10: Accounts Receivable | B10: ='QTR CF'!B10 | C10: ='QTR CF'!C10 | D10: ='QTR CF'!D10 | E10: ='QTR CF'!E10 | F10: ='QTR CF'!F10 | G10: ='QTR CF'!G10 | H10: ='QTR CF'!H10 | I10: ='QTR CF'!I10 | ... AG10: ='QTR CF'!AG10 | AH10: =-('QTR BS'!AE4-'QTR BS'!AD4) | AI10: =-('QTR BS'!AF4-'QTR BS'!AE4) | AJ10: =-('QTR BS'!AG4-'QTR BS'!AF4) | AK10: =-('QTR BS'!AH4-'QTR BS'!AG4) | AL10: =-('QTR BS'!AI4-'QTR BS'!AH4) | AM10: =-('QTR BS'!AJ4-'QTR BS'!AI4) | AN10: =-('QTR BS'!AK4-'QTR BS'!AJ4) | AO10: =-('QTR BS'!AL4-'QTR BS'!AK4) | ... BA10: =-('QTR BS'!AX4-'QTR BS'!AW4)
A11: Change in Income Taxes | B11: ='QTR CF'!B11 | C11: ='QTR CF'!C11 | D11: ='QTR CF'!D11 | E11: ='QTR CF'!E11 | F11: ='QTR CF'!F11 | G11: ='QTR CF'!G11 | H11: ='QTR CF'!H11 | I11: ='QTR CF'!I11 | ... AG11: ='QTR CF'!AG11 | AH11: =('QTR BS'!AE22-'QTR BS'!AD22) | AI11: =('QTR BS'!AF22-'QTR BS'!AE22) | AJ11: =('QTR BS'!AG22-'QTR BS'!AF22) | AK11: =('QTR BS'!AH22-'QTR BS'!AG22) | AL11: =('QTR BS'!AI22-'QTR BS'!AH22) | AM11: =('QTR BS'!AJ22-'QTR BS'!AI22) | AN11: =('QTR BS'!AK22-'QTR BS'!AJ22) | AO11: =('QTR BS'!AL22-'QTR BS'!AK22) | ... BA11: =('QTR BS'!AX22-'QTR BS'!AW22)
A12: Accounts Payable | B12: ='QTR CF'!B12 | C12: ='QTR CF'!C12 | D12: ='QTR CF'!D12 | E12: ='QTR CF'!E12 | F12: ='QTR CF'!F12 | G12: ='QTR CF'!G12 | H12: ='QTR CF'!H12 | I12: ='QTR CF'!I12 | ... AG12: ='QTR CF'!AG12 | AH12: =('QTR BS'!AE17-'QTR BS'!AD17) | AI12: =('QTR BS'!AF17-'QTR BS'!AE17) | AJ12: =('QTR BS'!AG17-'QTR BS'!AF17) | AK12: =('QTR BS'!AH17-'QTR BS'!AG17) | AL12: =('QTR BS'!AI17-'QTR BS'!AH17) | AM12: =('QTR BS'!AJ17-'QTR BS'!AI17) | AN12: =('QTR BS'!AK17-'QTR BS'!AJ17) | AO12: =('QTR BS'!AL17-'QTR BS'!AK17) | ... BA12: =('QTR BS'!AX17-'QTR BS'!AW17)
A13: Accrued Expenses | B13: ='QTR CF'!B13 | C13: ='QTR CF'!C13 | D13: ='QTR CF'!D13 | E13: ='QTR CF'!E13 | F13: ='QTR CF'!F13 | G13: ='QTR CF'!G13 | H13: ='QTR CF'!H13 | I13: ='QTR CF'!I13 | ... AG13: ='QTR CF'!AG13 | AH13: =('QTR BS'!AE19-'QTR BS'!AD19) | AI13: =('QTR BS'!AF19-'QTR BS'!AE19) | AJ13: =('QTR BS'!AG19-'QTR BS'!AF19) | AK13: =('QTR BS'!AH19-'QTR BS'!AG19) | AL13: =('QTR BS'!AI19-'QTR BS'!AH19) | AM13: =('QTR BS'!AJ19-'QTR BS'!AI19) | AN13: =('QTR BS'!AK19-'QTR BS'!AJ19) | AO13: =('QTR BS'!AL19-'QTR BS'!AK19) | ... BA13: =('QTR BS'!AX19-'QTR BS'!AW19)
A14: Accrued Revenue Share | B14: ='QTR CF'!B14 | C14: ='QTR CF'!C14 | D14: ='QTR CF'!D14 | E14: ='QTR CF'!E14 | F14: ='QTR CF'!F14 | G14: ='QTR CF'!G14 | H14: ='QTR CF'!H14 | I14: ='QTR CF'!I14 | ... AG14: ='QTR CF'!AG14 | AH14: =('QTR BS'!AE20-'QTR BS'!AD20) | AI14: =('QTR BS'!AF20-'QTR BS'!AE20) | AJ14: =('QTR BS'!AG20-'QTR BS'!AF20) | AK14: =('QTR BS'!AH20-'QTR BS'!AG20) | AL14: =('QTR BS'!AI20-'QTR BS'!AH20) | AM14: =('QTR BS'!AJ20-'QTR BS'!AI20) | AN14: =('QTR BS'!AK20-'QTR BS'!AJ20) | AO14: =('QTR BS'!AL20-'QTR BS'!AK20) | ... BA14: =('QTR BS'!AX20-'QTR BS'!AW20)
A15: Deferred Revenue | B15: ='QTR CF'!B15 | C15: ='QTR CF'!C15 | D15: ='QTR CF'!D15 | E15: ='QTR CF'!E15 | F15: ='QTR CF'!F15 | G15: ='QTR CF'!G15 | H15: ='QTR CF'!H15 | I15: ='QTR CF'!I15 | ... AG15: ='QTR CF'!AG15 | AH15: 0 | AI15: 0 | AJ15: 0 | AK15: 0 | AL15: 0 | AM15: 0 | AN15: 0 | AO15: 0 | AP15: 0 | AQ15: 0 | AR15: 0 | AS15: 0 | AT15: 0 | AU15: 0 | AV15: 0 | AW15: 0 | AX15: 0 | AY15: 0 | AZ15: 0 | BA15: 0
A16: Purchase of PP&E — % of Revenue | B16: =IFERROR('QTR CF'!B17/'QTR P&L'!B2,"") | C16: =IFERROR('QTR CF'!C17/'QTR P&L'!C2,"") | D16: =IFERROR('QTR CF'!D17/'QTR P&L'!D2,"") | E16: =IFERROR('QTR CF'!E17/'QTR P&L'!E2,"") | F16: =IFERROR('QTR CF'!F17/'QTR P&L'!F2,"") | G16: =IFERROR('QTR CF'!G17/'QTR P&L'!G2,"") | H16: =IFERROR('QTR CF'!H17/'QTR P&L'!H2,"") | I16: =IFERROR('QTR CF'!I17/'QTR P&L'!I2,"") | ... AG16: =IFERROR('QTR CF'!AG17/'QTR P&L'!AG2,"") | AH16: =AG16 | AI16: =AH16 | AJ16: =AI16 | AK16: =AJ16 | AL16: =AK16 | AM16: =AL16 | AN16: =AM16 | AO16: =AN16 | ... BA16: =AZ16
A17: Proceeds from Sale of Assets | B17: ='QTR CF'!B18 | C17: ='QTR CF'!C18 | D17: ='QTR CF'!D18 | E17: ='QTR CF'!E18 | F17: ='QTR CF'!F18 | G17: ='QTR CF'!G18 | H17: ='QTR CF'!H18 | I17: ='QTR CF'!I18 | ... AG17: ='QTR CF'!AG18 | AH17: 0 | AI17: 0 | AJ17: 0 | AK17: 0 | AL17: 0 | AM17: 0 | AN17: 0 | AO17: 0 | AP17: 0 | AQ17: 0 | AR17: 0 | AS17: 0 | AT17: 0 | AU17: 0 | AV17: 0 | AW17: 0 | AX17: 0 | AY17: 0 | AZ17: 0 | BA17: 0
A18: Net Change in Short-Term Investments | B18: ='QTR CF'!B19 | C18: ='QTR CF'!C19 | D18: ='QTR CF'!D19 | E18: ='QTR CF'!E19 | F18: ='QTR CF'!F19 | G18: ='QTR CF'!G19 | H18: ='QTR CF'!H19 | I18: ='QTR CF'!I19 | ... AG18: ='QTR CF'!AG19 | AH18: 0 | AI18: 0 | AJ18: 0 | AK18: 0 | AL18: 0 | AM18: 0 | AN18: 0 | AO18: 0 | AP18: 0 | AQ18: 0 | AR18: 0 | AS18: 0 | AT18: 0 | AU18: 0 | AV18: 0 | AW18: 0 | AX18: 0 | AY18: 0 | AZ18: 0 | BA18: 0
A19: Net Change in Long-Term Investments | B19: ='QTR CF'!B20 | C19: ='QTR CF'!C20 | D19: ='QTR CF'!D20 | E19: ='QTR CF'!E20 | F19: ='QTR CF'!F20 | G19: ='QTR CF'!G20 | H19: ='QTR CF'!H20 | I19: ='QTR CF'!I20 | ... AG19: ='QTR CF'!AG20 | AH19: =-('QTR BS'!AE9-'QTR BS'!AD9) | AI19: =-('QTR BS'!AF9-'QTR BS'!AE9) | AJ19: =-('QTR BS'!AG9-'QTR BS'!AF9) | AK19: =-('QTR BS'!AH9-'QTR BS'!AG9) | AL19: =-('QTR BS'!AI9-'QTR BS'!AH9) | AM19: =-('QTR BS'!AJ9-'QTR BS'!AI9) | AN19: =-('QTR BS'!AK9-'QTR BS'!AJ9) | AO19: =-('QTR BS'!AL9-'QTR BS'!AK9) | ... BA19: =-('QTR BS'!AX9-'QTR BS'!AW9)
A20: Acquisitions, Net of Cash Acquired | B20: ='QTR CF'!B21 | C20: ='QTR CF'!C21 | D20: ='QTR CF'!D21 | E20: ='QTR CF'!E21 | F20: ='QTR CF'!F21 | G20: ='QTR CF'!G21 | H20: ='QTR CF'!H21 | I20: ='QTR CF'!I21 | ... AG20: ='QTR CF'!AG21 | AH20: 0 | AI20: 0 | AJ20: 0 | AK20: 0 | AL20: 0 | AM20: 0 | AN20: 0 | AO20: 0 | AP20: 0 | AQ20: 0 | AR20: 0 | AS20: 0 | AT20: 0 | AU20: 0 | AV20: 0 | AW20: 0 | AX20: 0 | AY20: 0 | AZ20: 0 | BA20: 0
A21: Collections from Note Receivable | B21: ='QTR CF'!B22 | C21: ='QTR CF'!C22 | D21: ='QTR CF'!D22 | E21: ='QTR CF'!E22 | F21: ='QTR CF'!F22 | G21: ='QTR CF'!G22 | H21: ='QTR CF'!H22 | I21: ='QTR CF'!I22 | ... AG21: ='QTR CF'!AG22 | AH21: 0 | AI21: 0 | AJ21: 0 | AK21: 0 | AL21: 0 | AM21: 0 | AN21: 0 | AO21: 0 | AP21: 0 | AQ21: 0 | AR21: 0 | AS21: 0 | AT21: 0 | AU21: 0 | AV21: 0 | AW21: 0 | AX21: 0 | AY21: 0 | AZ21: 0 | BA21: 0
A22: Other Investing Activities | B22: ='QTR CF'!B23 | C22: ='QTR CF'!C23 | D22: ='QTR CF'!D23 | E22: ='QTR CF'!E23 | F22: ='QTR CF'!F23 | G22: ='QTR CF'!G23 | H22: ='QTR CF'!H23 | I22: ='QTR CF'!I23 | ... AG22: ='QTR CF'!AG23 | AH22: 0 | AI22: 0 | AJ22: 0 | AK22: 0 | AL22: 0 | AM22: 0 | AN22: 0 | AO22: 0 | AP22: 0 | AQ22: 0 | AR22: 0 | AS22: 0 | AT22: 0 | AU22: 0 | AV22: 0 | AW22: 0 | AX22: 0 | AY22: 0 | AZ22: 0 | BA22: 0
A23: Stock-Based Award Activities, Net | B23: ='QTR CF'!B25 | C23: ='QTR CF'!C25 | D23: ='QTR CF'!D25 | E23: ='QTR CF'!E25 | F23: ='QTR CF'!F25 | G23: ='QTR CF'!G25 | H23: ='QTR CF'!H25 | I23: ='QTR CF'!I25 | ... AG23: ='QTR CF'!AG25 | AH23: 0 | AI23: 0 | AJ23: 0 | AK23: 0 | AL23: 0 | AM23: 0 | AN23: 0 | AO23: 0 | AP23: 0 | AQ23: 0 | AR23: 0 | AS23: 0 | AT23: 0 | AU23: 0 | AV23: 0 | AW23: 0 | AX23: 0 | AY23: 0 | AZ23: 0 | BA23: 0
A24: Share Repurchases | B24: ='QTR CF'!B26 | C24: ='QTR CF'!C26 | D24: ='QTR CF'!D26 | E24: ='QTR CF'!E26 | F24: ='QTR CF'!F26 | G24: ='QTR CF'!G26 | H24: ='QTR CF'!H26 | I24: ='QTR CF'!I26 | ... AG24: ='QTR CF'!AG26 | AH24: 0 | AI24: 0 | AJ24: 0 | AK24: 0 | AL24: 0 | AM24: 0 | AN24: 0 | AO24: 0 | AP24: 0 | AQ24: 0 | AR24: 0 | AS24: 0 | AT24: 0 | AU24: 0 | AV24: 0 | AW24: 0 | AX24: 0 | AY24: 0 | AZ24: 0 | BA24: 0
A25: Common Dividends — % of Net Income | B25: =IFERROR('QTR CF'!B27/'QTR P&L'!B13,"") | C25: =IFERROR('QTR CF'!C27/'QTR P&L'!C13,"") | D25: =IFERROR('QTR CF'!D27/'QTR P&L'!D13,"") | E25: =IFERROR('QTR CF'!E27/'QTR P&L'!E13,"") | F25: =IFERROR('QTR CF'!F27/'QTR P&L'!F13,"") | G25: =IFERROR('QTR CF'!G27/'QTR P&L'!G13,"") | H25: =IFERROR('QTR CF'!H27/'QTR P&L'!H13,"") | I25: =IFERROR('QTR CF'!I27/'QTR P&L'!I13,"") | ... AG25: =IFERROR('QTR CF'!AG27/'QTR P&L'!AG13,"") | AH25: =AG25 | AI25: =AH25 | AJ25: =AI25 | AK25: =AJ25 | AL25: =AK25 | AM25: =AL25 | AN25: =AM25 | AO25: =AN25 | ... BA25: =AZ25
A26: Proceeds from Issuance of Long-Term Debt | B26: ='QTR CF'!B28 | C26: ='QTR CF'!C28 | D26: ='QTR CF'!D28 | E26: ='QTR CF'!E28 | F26: ='QTR CF'!F28 | G26: ='QTR CF'!G28 | H26: ='QTR CF'!H28 | I26: ='QTR CF'!I28 | ... AG26: ='QTR CF'!AG28 | AH26: 0 | AI26: 0 | AJ26: 0 | AK26: 0 | AL26: 0 | AM26: 0 | AN26: 0 | AO26: 0 | AP26: 0 | AQ26: 0 | AR26: 0 | AS26: 0 | AT26: 0 | AU26: 0 | AV26: 0 | AW26: 0 | AX26: 0 | AY26: 0 | AZ26: 0 | BA26: 0
A27: Net Change in Other Short-Term Debt | B27: ='QTR CF'!B29 | C27: ='QTR CF'!C29 | D27: ='QTR CF'!D29 | E27: ='QTR CF'!E29 | F27: ='QTR CF'!F29 | G27: ='QTR CF'!G29 | H27: ='QTR CF'!H29 | I27: ='QTR CF'!I29 | ... AG27: ='QTR CF'!AG29 | AH27: 0 | AI27: 0 | AJ27: 0 | AK27: 0 | AL27: 0 | AM27: 0 | AN27: 0 | AO27: 0 | AP27: 0 | AQ27: 0 | AR27: 0 | AS27: 0 | AT27: 0 | AU27: 0 | AV27: 0 | AW27: 0 | AX27: 0 | AY27: 0 | AZ27: 0 | BA27: 0
A28: Proceeds from Sale of Interest in Consolidated Entities | B28: ='QTR CF'!B30 | C28: ='QTR CF'!C30 | D28: ='QTR CF'!D30 | E28: ='QTR CF'!E30 | F28: ='QTR CF'!F30 | G28: ='QTR CF'!G30 | H28: ='QTR CF'!H30 | I28: ='QTR CF'!I30 | ... AG28: ='QTR CF'!AG30 | AH28: 0 | AI28: 0 | AJ28: 0 | AK28: 0 | AL28: 0 | AM28: 0 | AN28: 0 | AO28: 0 | AP28: 0 | AQ28: 0 | AR28: 0 | AS28: 0 | AT28: 0 | AU28: 0 | AV28: 0 | AW28: 0 | AX28: 0 | AY28: 0 | AZ28: 0 | BA28: 0
A29: FX Effect on Cash | B29: ='QTR CF'!B32 | C29: ='QTR CF'!C32 | D29: ='QTR CF'!D32 | E29: ='QTR CF'!E32 | F29: ='QTR CF'!F32 | G29: ='QTR CF'!G32 | H29: ='QTR CF'!H32 | I29: ='QTR CF'!I32 | ... AG29: ='QTR CF'!AG32 | AH29: =AG29 | AI29: =AH29 | AJ29: =AI29 | AK29: =AJ29 | AL29: =AK29 | AM29: =AL29 | AN29: =AM29 | AO29: =AN29 | ... BA29: =AZ29
