Workbook

Sheet ASSUMPTIONS
A1: Assumption | B1: Value | C1: Note
A2: Days in Quarter | B2: 91 | C2: Used by DSO/DIO/DPO ratios. Approximation; varies 89-92 by quarter.

Sheet ANNL P&L
B1: FY2021 | C1: FY2022 | D1: FY2023 | E1: FY2024 | F1: FY2025 | G1: FY2025E | H1: FY2026E | I1: FY2027E | J1: FY2028E | K1: FY2029E | L1: FY2030E
A2: Net Sales / Revenue | B2: 79474 | C2: 86392 | D2: 91471 | E2: 91854 | F2: 93925 | G2: ='QTR P&L'!N2+'QTR P&L'!O2+'QTR P&L'!P2+'QTR P&L'!Q2 | H2: ='QTR P&L'!R2+'QTR P&L'!S2+'QTR P&L'!T2+'QTR P&L'!U2 | I2: ='QTR P&L'!V2+'QTR P&L'!W2+'QTR P&L'!X2+'QTR P&L'!Y2 | J2: ='QTR P&L'!Z2+'QTR P&L'!AA2+'QTR P&L'!AB2+'QTR P&L'!AC2 | K2: ='QTR P&L'!AD2+'QTR P&L'!AE2+'QTR P&L'!AF2+'QTR P&L'!AG2 | L2: ='QTR P&L'!AH2+'QTR P&L'!AI2+'QTR P&L'!AJ2+'QTR P&L'!AK2
A3: COGS | B3: -37075 | C3: -40576 | D3: -41881 | E3: -41744 | F3: -43066 | G3: ='QTR P&L'!N3+'QTR P&L'!O3+'QTR P&L'!P3+'QTR P&L'!Q3 | H3: ='QTR P&L'!R3+'QTR P&L'!S3+'QTR P&L'!T3+'QTR P&L'!U3 | I3: ='QTR P&L'!V3+'QTR P&L'!W3+'QTR P&L'!X3+'QTR P&L'!Y3 | J3: ='QTR P&L'!Z3+'QTR P&L'!AA3+'QTR P&L'!AB3+'QTR P&L'!AC3 | K3: ='QTR P&L'!AD3+'QTR P&L'!AE3+'QTR P&L'!AF3+'QTR P&L'!AG3 | L3: ='QTR P&L'!AH3+'QTR P&L'!AI3+'QTR P&L'!AJ3+'QTR P&L'!AK3
A4: Gross Profit (Loss) | B4: =B2+B3 | C4: =C2+C3 | D4: =D2+D3 | E4: =E2+E3 | F4: =F2+F3 | G4: =G2+G3 | H4: =H2+H3 | I4: =I2+I3 | ... L4: =L2+L3
A5: SG&A | B5: -31237 | C5: -34459 | D5: -36677 | E5: -37190 | F5: -37368 | G5: ='QTR P&L'!N5+'QTR P&L'!O5+'QTR P&L'!P5+'QTR P&L'!Q5 | H5: ='QTR P&L'!R5+'QTR P&L'!S5+'QTR P&L'!T5+'QTR P&L'!U5 | I5: ='QTR P&L'!V5+'QTR P&L'!W5+'QTR P&L'!X5+'QTR P&L'!Y5 | J5: ='QTR P&L'!Z5+'QTR P&L'!AA5+'QTR P&L'!AB5+'QTR P&L'!AC5 | K5: ='QTR P&L'!AD5+'QTR P&L'!AE5+'QTR P&L'!AF5+'QTR P&L'!AG5 | L5: ='QTR P&L'!AH5+'QTR P&L'!AI5+'QTR P&L'!AJ5+'QTR P&L'!AK5
A6: Gain on Juice Transaction | B6: 0 | C6: -3321 | D6: 0 | E6: 0 | F6: 0 | G6: ='QTR P&L'!N6+'QTR P&L'!O6+'QTR P&L'!P6+'QTR P&L'!Q6 | H6: ='QTR P&L'!R6+'QTR P&L'!S6+'QTR P&L'!T6+'QTR P&L'!U6 | I6: ='QTR P&L'!V6+'QTR P&L'!W6+'QTR P&L'!X6+'QTR P&L'!Y6 | J6: ='QTR P&L'!Z6+'QTR P&L'!AA6+'QTR P&L'!AB6+'QTR P&L'!AC6 | K6: ='QTR P&L'!AD6+'QTR P&L'!AE6+'QTR P&L'!AF6+'QTR P&L'!AG6 | L6: ='QTR P&L'!AH6+'QTR P&L'!AI6+'QTR P&L'!AJ6+'QTR P&L'!AK6
A7: Impairment of Intangibles | B7: 0 | C7: -3166 | D7: -927 | E7: -33 | F7: -1993 | G7: ='QTR P&L'!N7+'QTR P&L'!O7+'QTR P&L'!P7+'QTR P&L'!Q7 | H7: ='QTR P&L'!R7+'QTR P&L'!S7+'QTR P&L'!T7+'QTR P&L'!U7 | I7: ='QTR P&L'!V7+'QTR P&L'!W7+'QTR P&L'!X7+'QTR P&L'!Y7 | J7: ='QTR P&L'!Z7+'QTR P&L'!AA7+'QTR P&L'!AB7+'QTR P&L'!AC7 | K7: ='QTR P&L'!AD7+'QTR P&L'!AE7+'QTR P&L'!AF7+'QTR P&L'!AG7 | L7: ='QTR P&L'!AH7+'QTR P&L'!AI7+'QTR P&L'!AJ7+'QTR P&L'!AK7
A8: Income (Loss) from Operations | B8: =B4+SUM(B5:B7) | C8: =C4+SUM(C5:C7) | D8: =D4+SUM(D5:D7) | E8: =E4+SUM(E5:E7) | F8: =F4+SUM(F5:F7) | G8: =G4+SUM(G5:G7) | H8: =H4+SUM(H5:H7) | I8: =I4+SUM(I5:I7) | ... L8: =L4+SUM(L5:L7)
A9: Other Pension and OPEB Benefits Income (Expense) | B9: 522 | C9: 132 | D9: 250 | E9: -22 | F9: -133 | G9: ='QTR P&L'!N9+'QTR P&L'!O9+'QTR P&L'!P9+'QTR P&L'!Q9 | H9: ='QTR P&L'!R9+'QTR P&L'!S9+'QTR P&L'!T9+'QTR P&L'!U9 | I9: ='QTR P&L'!V9+'QTR P&L'!W9+'QTR P&L'!X9+'QTR P&L'!Y9 | J9: ='QTR P&L'!Z9+'QTR P&L'!AA9+'QTR P&L'!AB9+'QTR P&L'!AC9 | K9: ='QTR P&L'!AD9+'QTR P&L'!AE9+'QTR P&L'!AF9+'QTR P&L'!AG9 | L9: ='QTR P&L'!AH9+'QTR P&L'!AI9+'QTR P&L'!AJ9+'QTR P&L'!AK9
A10: Interest Income (Expense) | B10: -1863 | C10: -939 | D10: -819 | E10: -919 | F10: -1121 | G10: ='QTR P&L'!N10+'QTR P&L'!O10+'QTR P&L'!P10+'QTR P&L'!Q10 | H10: ='QTR P&L'!R10+'QTR P&L'!S10+'QTR P&L'!T10+'QTR P&L'!U10 | I10: ='QTR P&L'!V10+'QTR P&L'!W10+'QTR P&L'!X10+'QTR P&L'!Y10 | J10: ='QTR P&L'!Z10+'QTR P&L'!AA10+'QTR P&L'!AB10+'QTR P&L'!AC10 | K10: ='QTR P&L'!AD10+'QTR P&L'!AE10+'QTR P&L'!AF10+'QTR P&L'!AG10 | L10: ='QTR P&L'!AH10+'QTR P&L'!AI10+'QTR P&L'!AJ10+'QTR P&L'!AK10
A11: Pre-Tax Income (Loss) | B11: =B8+SUM(B9:B10) | C11: =C8+SUM(C9:C10) | D11: =D8+SUM(D9:D10) | E11: =E8+SUM(E9:E10) | F11: =F8+SUM(F9:F10) | G11: =G8+SUM(G9:G10) | H11: =H8+SUM(H9:H10) | I11: =I8+SUM(I9:I10) | ... L11: =L8+SUM(L9:L10)
A12: Income Tax (Expense) Benefit | B12: -2142 | C12: -1727 | D12: -2262 | E12: -2320 | F12: -1949 | G12: ='QTR P&L'!N12+'QTR P&L'!O12+'QTR P&L'!P12+'QTR P&L'!Q12 | H12: ='QTR P&L'!R12+'QTR P&L'!S12+'QTR P&L'!T12+'QTR P&L'!U12 | I12: ='QTR P&L'!V12+'QTR P&L'!W12+'QTR P&L'!X12+'QTR P&L'!Y12 | J12: ='QTR P&L'!Z12+'QTR P&L'!AA12+'QTR P&L'!AB12+'QTR P&L'!AC12 | K12: ='QTR P&L'!AD12+'QTR P&L'!AE12+'QTR P&L'!AF12+'QTR P&L'!AG12 | L12: ='QTR P&L'!AH12+'QTR P&L'!AI12+'QTR P&L'!AJ12+'QTR P&L'!AK12
A13: Net Income (Loss) | B13: =B11+B12 | C13: =C11+C12 | D13: =D11+D12 | E13: =E11+E12 | F13: =F11+F12 | G13: =G11+G12 | H13: =H11+H12 | I13: =I11+I12 | ... L13: =L11+L12
A14: Net Income (Loss) Attributable to Noncontrolling Interest | B14: 61 | C14: 68 | D14: 81 | E14: 48 | F14: 55 | G14: ='QTR P&L'!N14+'QTR P&L'!O14+'QTR P&L'!P14+'QTR P&L'!Q14 | H14: ='QTR P&L'!R14+'QTR P&L'!S14+'QTR P&L'!T14+'QTR P&L'!U14 | I14: ='QTR P&L'!V14+'QTR P&L'!W14+'QTR P&L'!X14+'QTR P&L'!Y14 | J14: ='QTR P&L'!Z14+'QTR P&L'!AA14+'QTR P&L'!AB14+'QTR P&L'!AC14 | K14: ='QTR P&L'!AD14+'QTR P&L'!AE14+'QTR P&L'!AF14+'QTR P&L'!AG14 | L14: ='QTR P&L'!AH14+'QTR P&L'!AI14+'QTR P&L'!AJ14+'QTR P&L'!AK14
A15: Net Income (Loss) Less NCI | B15: =B13-B14 | C15: =C13-C14 | D15: =D13-D14 | E15: =E13-E14 | F15: =F13-F14 | G15: =G13-G14 | H15: =H13-H14 | I15: =I13-I14 | ... L15: =L13-L14
A16: Basic Earnings (Loss) per Share | B16: 5.51 | C16: 6.45 | D16: 6.59 | E16: 6.97 | F16: 6.02
A17: Diluted Earnings (Loss) per Share | B17: 5.49 | C17: 6.42 | D17: 6.56 | E17: 6.95 | F17: 6
A18: Weighted Average Shares Outstanding (Basic) | B18: 1382000000 | C18: 1380000000 | D18: 1376000000 | E18: 1373000000 | F18: 1369000000
A19: Weighted Average Shares Outstanding (Diluted) | B19: 1389000000 | C19: 1387000000 | D19: 1383000000 | E19: 1378000000 | F19: 1373000000

Sheet BALANCE SHEET
B1: FY2022 | C1: FY2023 | D1: FY2024 | E1: FY2025 | F1: FY2025E | G1: FY2026E | H1: FY2027E | I1: FY2028E | J1: FY2029E | K1: FY2030E
A2: Cash & Cash Equivalents | B2: 4954 | C2: 9711 | D2: 8505 | E2: 9159 | F2: ='QTR BS'!N2 | G2: ='QTR BS'!R2 | H2: ='QTR BS'!V2 | I2: ='QTR BS'!Z2 | J2: ='QTR BS'!AD2 | K2: ='QTR BS'!AH2
A3: Short-Term Investments | B3: 394 | C3: 292 | D3: 761 | E3: 371 | F3: ='QTR BS'!N3 | G3: ='QTR BS'!R3 | H3: ='QTR BS'!V3 | I3: ='QTR BS'!Z3 | J3: ='QTR BS'!AD3 | K3: ='QTR BS'!AH3
A4: Accounts Receivable | B4: 10163 | C4: 10815 | D4: 10333 | E4: 11506 | F4: ='QTR BS'!N4 | G4: ='QTR BS'!R4 | H4: ='QTR BS'!V4 | I4: ='QTR BS'!Z4 | J4: ='QTR BS'!AD4 | K4: ='QTR BS'!AH4
A5: Inventories | B5: 5222 | C5: 5334 | D5: 5306 | E5: 5845 | F5: ='QTR BS'!N5 | G5: ='QTR BS'!R5 | H5: ='QTR BS'!V5 | I5: ='QTR BS'!Z5 | J5: ='QTR BS'!AD5 | K5: ='QTR BS'!AH5
A6: Prepaid Expenses | B6: 806 | C6: 798 | D6: 921 | E6: 1068 | F6: ='QTR BS'!N6 | G6: ='QTR BS'!R6 | H6: ='QTR BS'!V6 | I6: ='QTR BS'!Z6 | J6: ='QTR BS'!AD6 | K6: ='QTR BS'!AH6
A7: Total Current Assets | B7: =SUM(B2:B6) | C7: =SUM(C2:C6) | D7: =SUM(D2:D6) | E7: =SUM(E2:E6) | F7: =SUM(F2:F6) | G7: =SUM(G2:G6) | H7: =SUM(H2:H6) | I7: =SUM(I2:I6) | ... K7: =SUM(K2:K6)
A8: Net PP&E | B8: 24291 | C8: 27039 | D8: 28008 | E8: 29905 | F8: ='QTR BS'!N8 | G8: ='QTR BS'!R8 | H8: ='QTR BS'!V8 | I8: ='QTR BS'!Z8 | J8: ='QTR BS'!AD8 | K8: ='QTR BS'!AH8
A9: Intangible Assets | B9: 15586 | C9: 14929 | D9: 14801 | E9: 15066 | F9: ='QTR BS'!N9 | G9: ='QTR BS'!R9 | H9: ='QTR BS'!V9 | I9: ='QTR BS'!Z9 | J9: ='QTR BS'!AD9 | K9: ='QTR BS'!AH9
A10: Goodwill | B10: 18202 | C10: 17728 | D10: 17534 | E10: 18916 | F10: ='QTR BS'!N10 | G10: ='QTR BS'!R10 | H10: ='QTR BS'!V10 | I10: ='QTR BS'!Z10 | J10: ='QTR BS'!AD10 | K10: ='QTR BS'!AH10
A11: Equity Method Investments | B11: 3073 | C11: 2714 | D11: 1985 | E11: 2038 | F11: ='QTR BS'!N11 | G11: ='QTR BS'!R11 | H11: ='QTR BS'!V11 | I11: ='QTR BS'!Z11 | J11: ='QTR BS'!AD11 | K11: ='QTR BS'!AH11
A12: Deferred Tax Assets | B12: 4204 | C12: 4474 | D12: 4362 | E12: 4541 | F12: ='QTR BS'!N12 | G12: ='QTR BS'!R12 | H12: ='QTR BS'!V12 | I12: ='QTR BS'!Z12 | J12: ='QTR BS'!AD12 | K12: ='QTR BS'!AH12
A13: Other Non-Current Assets | B13: 5292 | C13: 6661 | D13: 6951 | E13: 8984 | F13: ='QTR BS'!N13 | G13: ='QTR BS'!R13 | H13: ='QTR BS'!V13 | I13: ='QTR BS'!Z13 | J13: ='QTR BS'!AD13 | K13: ='QTR BS'!AH13
A14: Total Assets | B14: =B7+SUM(B8:B13) | C14: =C7+SUM(C8:C13) | D14: =D7+SUM(D8:D13) | E14: =E7+SUM(E8:E13) | F14: =F7+SUM(F8:F13) | G14: =G7+SUM(G8:G13) | H14: =H7+SUM(H8:H13) | I14: =I7+SUM(I8:I13) | ... K14: =K7+SUM(K8:K13)
A15: Short-Term Debt Obligations | B15: 3414 | C15: 6510 | D15: 7082 | E15: 6861 | F15: ='QTR BS'!N15 | G15: ='QTR BS'!R15 | H15: ='QTR BS'!V15 | I15: ='QTR BS'!Z15 | J15: ='QTR BS'!AD15 | K15: ='QTR BS'!AH15
A16: Accrued Expenses | B16: 23371 | C16: 25137 | D16: 24454 | E16: 25903 | F16: ='QTR BS'!N16 | G16: ='QTR BS'!R16 | H16: ='QTR BS'!V16 | I16: ='QTR BS'!Z16 | J16: ='QTR BS'!AD16 | K16: ='QTR BS'!AH16
A17: Total Current Liabilities | B17: =SUM(B15:B16) | C17: =SUM(C15:C16) | D17: =SUM(D15:D16) | E17: =SUM(E15:E16) | F17: =SUM(F15:F16) | G17: =SUM(G15:G16) | H17: =SUM(H15:H16) | I17: =SUM(I15:I16) | ... K17: =SUM(K15:K16)
A18: Long-Term Debt | B18: 35657 | C18: 37595 | D18: 37224 | E18: 42321 | F18: ='QTR BS'!N18 | G18: ='QTR BS'!R18 | H18: ='QTR BS'!V18 | I18: ='QTR BS'!Z18 | J18: ='QTR BS'!AD18 | K18: ='QTR BS'!AH18
A19: Deferred Tax Liability | B19: 4133 | C19: 3895 | D19: 3484 | E19: 3802 | F19: ='QTR BS'!N19 | G19: ='QTR BS'!R19 | H19: ='QTR BS'!V19 | I19: ='QTR BS'!Z19 | J19: ='QTR BS'!AD19 | K19: ='QTR BS'!AH19
A20: Other Non-Current Liabilities | B20: 8339 | C20: 8721 | D20: 9052 | E20: 7965 | F20: ='QTR BS'!N20 | G20: ='QTR BS'!R20 | H20: ='QTR BS'!V20 | I20: ='QTR BS'!Z20 | J20: ='QTR BS'!AD20 | K20: ='QTR BS'!AH20
A21: Total Liabilities | B21: =B17+SUM(B18:B20) | C21: =C17+SUM(C18:C20) | D21: =D17+SUM(D18:D20) | E21: =E17+SUM(E18:E20) | F21: =F17+SUM(F18:F20) | G21: =G17+SUM(G18:G20) | H21: =H17+SUM(H18:H20) | I21: =I17+SUM(I18:I20) | ... K21: =K17+SUM(K18:K20)
A22: Common Stock | B22: 23 | C22: 23 | D22: 23 | E22: 23 | F22: ='QTR BS'!N22 | G22: ='QTR BS'!R22 | H22: ='QTR BS'!V22 | I22: ='QTR BS'!Z22 | J22: ='QTR BS'!AD22 | K22: ='QTR BS'!AH22
A23: Additional Paid-in Capital | B23: 4134 | C23: 4261 | D23: 4385 | E23: 4451 | F23: ='QTR BS'!N23 | G23: ='QTR BS'!R23 | H23: ='QTR BS'!V23 | I23: ='QTR BS'!Z23 | J23: ='QTR BS'!AD23 | K23: ='QTR BS'!AH23
A24: Retained Earnings (Accumulated Deficit) | B24: 67800 | C24: 70035 | D24: 72266 | E24: 72788 | F24: ='QTR BS'!N24 | G24: ='QTR BS'!R24 | H24: ='QTR BS'!V24 | I24: ='QTR BS'!Z24 | J24: ='QTR BS'!AD24 | K24: ='QTR BS'!AH24
A25: Accumulated Other Comprehensive Income (Loss) | B25: -15302 | C25: -15534 | D25: -17612 | E25: -15024 | F25: ='QTR BS'!N25 | G25: ='QTR BS'!R25 | H25: ='QTR BS'!V25 | I25: ='QTR BS'!Z25 | J25: ='QTR BS'!AD25 | K25: ='QTR BS'!AH25
A26: Treasury Stock | B26: -39506 | C26: -40282 | D26: -41021 | E26: -41832 | F26: ='QTR BS'!N26 | G26: ='QTR BS'!R26 | H26: ='QTR BS'!V26 | I26: ='QTR BS'!Z26 | J26: ='QTR BS'!AD26 | K26: ='QTR BS'!AH26
A27: Noncontrolling Interest | B27: 124 | C27: 134 | D27: 130 | E27: 141 | F27: ='QTR BS'!N27 | G27: ='QTR BS'!R27 | H27: ='QTR BS'!V27 | I27: ='QTR BS'!Z27 | J27: ='QTR BS'!AD27 | K27: ='QTR BS'!AH27
A28: Total Stockholders' Equity | B28: =SUM(B22:B27) | C28: =SUM(C22:C27) | D28: =SUM(D22:D27) | E28: =SUM(E22:E27) | F28: =SUM(F22:F27) | G28: =SUM(G22:G27) | H28: =SUM(H22:H27) | I28: =SUM(I22:I27) | ... K28: =SUM(K22:K27)
A29: Total Liabilities, Mezzanine & Stockholders' Equity | B29: =B21+B28 | C29: =C21+C28 | D29: =D21+D28 | E29: =E21+E28 | F29: =F21+F28 | G29: =G21+G28 | H29: =H21+H28 | I29: =I21+I28 | ... K29: =K21+K28

Sheet CASH FLOW
B1: FY2021 | C1: FY2022 | D1: FY2023 | E1: FY2024 | F1: FY2025 | G1: FY2025E | H1: FY2026E | I1: FY2027E | J1: FY2028E | K1: FY2029E | L1: FY2030E
A2: Net Income (Loss) | B2: 7679 | C2: 8978 | D2: 9155 | E2: 9626 | F2: 8295 | G2: ='QTR CF'!N2+'QTR CF'!O2+'QTR CF'!P2+'QTR CF'!Q2 | H2: ='QTR CF'!R2+'QTR CF'!S2+'QTR CF'!T2+'QTR CF'!U2 | I2: ='QTR CF'!V2+'QTR CF'!W2+'QTR CF'!X2+'QTR CF'!Y2 | J2: ='QTR CF'!Z2+'QTR CF'!AA2+'QTR CF'!AB2+'QTR CF'!AC2 | K2: ='QTR CF'!AD2+'QTR CF'!AE2+'QTR CF'!AF2+'QTR CF'!AG2 | L2: ='QTR CF'!AH2+'QTR CF'!AI2+'QTR CF'!AJ2+'QTR CF'!AK2
A3: Depreciation & Amortization | B3: 2710 | C3: 2763 | D3: 2948 | E3: 3160 | F3: 3451 | G3: ='QTR CF'!N3+'QTR CF'!O3+'QTR CF'!P3+'QTR CF'!Q3 | H3: ='QTR CF'!R3+'QTR CF'!S3+'QTR CF'!T3+'QTR CF'!U3 | I3: ='QTR CF'!V3+'QTR CF'!W3+'QTR CF'!X3+'QTR CF'!Y3 | J3: ='QTR CF'!Z3+'QTR CF'!AA3+'QTR CF'!AB3+'QTR CF'!AC3 | K3: ='QTR CF'!AD3+'QTR CF'!AE3+'QTR CF'!AF3+'QTR CF'!AG3 | L3: ='QTR CF'!AH3+'QTR CF'!AI3+'QTR CF'!AJ3+'QTR CF'!AK3
A4: Gain on Juice Transaction | B4: 0 | C4: -3321 | D4: 0 | E4: 0 | F4: 0 | G4: ='QTR CF'!N4+'QTR CF'!O4+'QTR CF'!P4+'QTR CF'!Q4 | H4: ='QTR CF'!R4+'QTR CF'!S4+'QTR CF'!T4+'QTR CF'!U4 | I4: ='QTR CF'!V4+'QTR CF'!W4+'QTR CF'!X4+'QTR CF'!Y4 | J4: ='QTR CF'!Z4+'QTR CF'!AA4+'QTR CF'!AB4+'QTR CF'!AC4 | K4: ='QTR CF'!AD4+'QTR CF'!AE4+'QTR CF'!AF4+'QTR CF'!AG4 | L4: ='QTR CF'!AH4+'QTR CF'!AI4+'QTR CF'!AJ4+'QTR CF'!AK4
A5: Impairment and Other Charges | B5: 0 | C5: 3618 | D5: 1230 | E5: 714 | F5: 1946 | G5: ='QTR CF'!N5+'QTR CF'!O5+'QTR CF'!P5+'QTR CF'!Q5 | H5: ='QTR CF'!R5+'QTR CF'!S5+'QTR CF'!T5+'QTR CF'!U5 | I5: ='QTR CF'!V5+'QTR CF'!W5+'QTR CF'!X5+'QTR CF'!Y5 | J5: ='QTR CF'!Z5+'QTR CF'!AA5+'QTR CF'!AB5+'QTR CF'!AC5 | K5: ='QTR CF'!AD5+'QTR CF'!AE5+'QTR CF'!AF5+'QTR CF'!AG5 | L5: ='QTR CF'!AH5+'QTR CF'!AI5+'QTR CF'!AJ5+'QTR CF'!AK5
A6: Indirect Tax Impact | B6: 0 | C6: 0 | D6: 0 | E6: 218 | F6: 0
A7: Product Recall Impact | B7: 0 | C7: 0 | D7: 136 | E7: 187 | F7: 0 | G7: ='QTR CF'!N6+'QTR CF'!O6+'QTR CF'!P6+'QTR CF'!Q6 | H7: ='QTR CF'!R6+'QTR CF'!S6+'QTR CF'!T6+'QTR CF'!U6 | I7: ='QTR CF'!V6+'QTR CF'!W6+'QTR CF'!X6+'QTR CF'!Y6 | J7: ='QTR CF'!Z6+'QTR CF'!AA6+'QTR CF'!AB6+'QTR CF'!AC6 | K7: ='QTR CF'!AD6+'QTR CF'!AE6+'QTR CF'!AF6+'QTR CF'!AG6 | L7: ='QTR CF'!AH6+'QTR CF'!AI6+'QTR CF'!AJ6+'QTR CF'!AK6
A8: Cash Payments for Product Recall | B8: 0 | C8: 0 | D8: 0 | E8: -148 | F8: -6 | G8: ='QTR CF'!N7+'QTR CF'!O7+'QTR CF'!P7+'QTR CF'!Q7 | H8: ='QTR CF'!R7+'QTR CF'!S7+'QTR CF'!T7+'QTR CF'!U7 | I8: ='QTR CF'!V7+'QTR CF'!W7+'QTR CF'!X7+'QTR CF'!Y7 | J8: ='QTR CF'!Z7+'QTR CF'!AA7+'QTR CF'!AB7+'QTR CF'!AC7 | K8: ='QTR CF'!AD7+'QTR CF'!AE7+'QTR CF'!AF7+'QTR CF'!AG7 | L8: ='QTR CF'!AH7+'QTR CF'!AI7+'QTR CF'!AJ7+'QTR CF'!AK7
A9: Operating Lease ROU Asset Amortization | B9: 505 | C9: 517 | D9: 570 | E9: 655 | F9: 727 | G9: ='QTR CF'!N8+'QTR CF'!O8+'QTR CF'!P8+'QTR CF'!Q8 | H9: ='QTR CF'!R8+'QTR CF'!S8+'QTR CF'!T8+'QTR CF'!U8 | I9: ='QTR CF'!V8+'QTR CF'!W8+'QTR CF'!X8+'QTR CF'!Y8 | J9: ='QTR CF'!Z8+'QTR CF'!AA8+'QTR CF'!AB8+'QTR CF'!AC8 | K9: ='QTR CF'!AD8+'QTR CF'!AE8+'QTR CF'!AF8+'QTR CF'!AG8 | L9: ='QTR CF'!AH8+'QTR CF'!AI8+'QTR CF'!AJ8+'QTR CF'!AK8
A10: Stock-Based Compensation | B10: 301 | C10: 343 | D10: 380 | E10: 362 | F10: 288 | G10: ='QTR CF'!N9+'QTR CF'!O9+'QTR CF'!P9+'QTR CF'!Q9 | H10: ='QTR CF'!R9+'QTR CF'!S9+'QTR CF'!T9+'QTR CF'!U9 | I10: ='QTR CF'!V9+'QTR CF'!W9+'QTR CF'!X9+'QTR CF'!Y9 | J10: ='QTR CF'!Z9+'QTR CF'!AA9+'QTR CF'!AB9+'QTR CF'!AC9 | K10: ='QTR CF'!AD9+'QTR CF'!AE9+'QTR CF'!AF9+'QTR CF'!AG9 | L10: ='QTR CF'!AH9+'QTR CF'!AI9+'QTR CF'!AJ9+'QTR CF'!AK9
A11: Restructuring and Asset Impairment Charges | B11: 247 | C11: 411 | D11: 445 | E11: 727 | F11: 983 | G11: ='QTR CF'!N10+'QTR CF'!O10+'QTR CF'!P10+'QTR CF'!Q10 | H11: ='QTR CF'!R10+'QTR CF'!S10+'QTR CF'!T10+'QTR CF'!U10 | I11: ='QTR CF'!V10+'QTR CF'!W10+'QTR CF'!X10+'QTR CF'!Y10 | J11: ='QTR CF'!Z10+'QTR CF'!AA10+'QTR CF'!AB10+'QTR CF'!AC10 | K11: ='QTR CF'!AD10+'QTR CF'!AE10+'QTR CF'!AF10+'QTR CF'!AG10 | L11: ='QTR CF'!AH10+'QTR CF'!AI10+'QTR CF'!AJ10+'QTR CF'!AK10
A12: Cash Payments for Restructuring | B12: -256 | C12: -224 | D12: -434 | E12: -436 | F12: -796 | G12: ='QTR CF'!N11+'QTR CF'!O11+'QTR CF'!P11+'QTR CF'!Q11 | H12: ='QTR CF'!R11+'QTR CF'!S11+'QTR CF'!T11+'QTR CF'!U11 | I12: ='QTR CF'!V11+'QTR CF'!W11+'QTR CF'!X11+'QTR CF'!Y11 | J12: ='QTR CF'!Z11+'QTR CF'!AA11+'QTR CF'!AB11+'QTR CF'!AC11 | K12: ='QTR CF'!AD11+'QTR CF'!AE11+'QTR CF'!AF11+'QTR CF'!AG11 | L12: ='QTR CF'!AH11+'QTR CF'!AI11+'QTR CF'!AJ11+'QTR CF'!AK11
A13: Acquisition and Divestiture-Related Charges | B13: -4 | C13: 80 | D13: 41 | E13: 0 | F13: 453 | G13: ='QTR CF'!N12+'QTR CF'!O12+'QTR CF'!P12+'QTR CF'!Q12 | H13: ='QTR CF'!R12+'QTR CF'!S12+'QTR CF'!T12+'QTR CF'!U12 | I13: ='QTR CF'!V12+'QTR CF'!W12+'QTR CF'!X12+'QTR CF'!Y12 | J13: ='QTR CF'!Z12+'QTR CF'!AA12+'QTR CF'!AB12+'QTR CF'!AC12 | K13: ='QTR CF'!AD12+'QTR CF'!AE12+'QTR CF'!AF12+'QTR CF'!AG12 | L13: ='QTR CF'!AH12+'QTR CF'!AI12+'QTR CF'!AJ12+'QTR CF'!AK12
A14: Cash Payments for Acquisition and Divestiture Costs | B14: -176 | C14: -46 | D14: -41 | E14: 0 | F14: -228 | G14: ='QTR CF'!N13+'QTR CF'!O13+'QTR CF'!P13+'QTR CF'!Q13 | H14: ='QTR CF'!R13+'QTR CF'!S13+'QTR CF'!T13+'QTR CF'!U13 | I14: ='QTR CF'!V13+'QTR CF'!W13+'QTR CF'!X13+'QTR CF'!Y13 | J14: ='QTR CF'!Z13+'QTR CF'!AA13+'QTR CF'!AB13+'QTR CF'!AC13 | K14: ='QTR CF'!AD13+'QTR CF'!AE13+'QTR CF'!AF13+'QTR CF'!AG13 | L14: ='QTR CF'!AH13+'QTR CF'!AI13+'QTR CF'!AJ13+'QTR CF'!AK13
A15: Pension and Postretirement Benefits Expense | B15: 123 | C15: 419 | D15: 150 | E15: 414 | F15: 504 | G15: ='QTR CF'!N14+'QTR CF'!O14+'QTR CF'!P14+'QTR CF'!Q14 | H15: ='QTR CF'!R14+'QTR CF'!S14+'QTR CF'!T14+'QTR CF'!U14 | I15: ='QTR CF'!V14+'QTR CF'!W14+'QTR CF'!X14+'QTR CF'!Y14 | J15: ='QTR CF'!Z14+'QTR CF'!AA14+'QTR CF'!AB14+'QTR CF'!AC14 | K15: ='QTR CF'!AD14+'QTR CF'!AE14+'QTR CF'!AF14+'QTR CF'!AG14 | L15: ='QTR CF'!AH14+'QTR CF'!AI14+'QTR CF'!AJ14+'QTR CF'!AK14
A16: Pension and Postretirement Benefits Contributions | B16: -785 | C16: -384 | D16: -410 | E16: -348 | F16: -472 | G16: ='QTR CF'!N15+'QTR CF'!O15+'QTR CF'!P15+'QTR CF'!Q15 | H16: ='QTR CF'!R15+'QTR CF'!S15+'QTR CF'!T15+'QTR CF'!U15 | I16: ='QTR CF'!V15+'QTR CF'!W15+'QTR CF'!X15+'QTR CF'!Y15 | J16: ='QTR CF'!Z15+'QTR CF'!AA15+'QTR CF'!AB15+'QTR CF'!AC15 | K16: ='QTR CF'!AD15+'QTR CF'!AE15+'QTR CF'!AF15+'QTR CF'!AG15 | L16: ='QTR CF'!AH15+'QTR CF'!AI15+'QTR CF'!AJ15+'QTR CF'!AK15
A17: (Benefit) Provision for Deferred Income Taxes | B17: 298 | C17: -873 | D17: -271 | E17: -42 | F17: 71 | G17: ='QTR CF'!N16+'QTR CF'!O16+'QTR CF'!P16+'QTR CF'!Q16 | H17: ='QTR CF'!R16+'QTR CF'!S16+'QTR CF'!T16+'QTR CF'!U16 | I17: ='QTR CF'!V16+'QTR CF'!W16+'QTR CF'!X16+'QTR CF'!Y16 | J17: ='QTR CF'!Z16+'QTR CF'!AA16+'QTR CF'!AB16+'QTR CF'!AC16 | K17: ='QTR CF'!AD16+'QTR CF'!AE16+'QTR CF'!AF16+'QTR CF'!AG16 | L17: ='QTR CF'!AH16+'QTR CF'!AI16+'QTR CF'!AJ16+'QTR CF'!AK16
A18: Tax Expense Related to TCJ Act | B18: 190 | C18: 86 | D18: 0 | E18: 0 | F18: 0 | G18: ='QTR CF'!N17+'QTR CF'!O17+'QTR CF'!P17+'QTR CF'!Q17 | H18: ='QTR CF'!R17+'QTR CF'!S17+'QTR CF'!T17+'QTR CF'!U17 | I18: ='QTR CF'!V17+'QTR CF'!W17+'QTR CF'!X17+'QTR CF'!Y17 | J18: ='QTR CF'!Z17+'QTR CF'!AA17+'QTR CF'!AB17+'QTR CF'!AC17 | K18: ='QTR CF'!AD17+'QTR CF'!AE17+'QTR CF'!AF17+'QTR CF'!AG17 | L18: ='QTR CF'!AH17+'QTR CF'!AI17+'QTR CF'!AJ17+'QTR CF'!AK17
... A25: Other Operating Items | B25: 375 | C25: -359 | D25: 189 | E25: -307 | F25: -712 | G25: ='QTR CF'!N24+'QTR CF'!O24+'QTR CF'!P24+'QTR CF'!Q24 | H25: ='QTR CF'!R24+'QTR CF'!S24+'QTR CF'!T24+'QTR CF'!U24 | I25: ='QTR CF'!V24+'QTR CF'!W24+'QTR CF'!X24+'QTR CF'!Y24 | J25: ='QTR CF'!Z24+'QTR CF'!AA24+'QTR CF'!AB24+'QTR CF'!AC24 | K25: ='QTR CF'!AD24+'QTR CF'!AE24+'QTR CF'!AF24+'QTR CF'!AG24 | L25: ='QTR CF'!AH24+'QTR CF'!AI24+'QTR CF'!AJ24+'QTR CF'!AK24
A26: Cash Flow from Operations | B26: =SUM(B2:B25) | C26: =SUM(C2:C25) | D26: =SUM(D2:D25) | E26: =SUM(E2:E25) | F26: =SUM(F2:F25) | G26: =SUM(G2:G25) | H26: =SUM(H2:H25) | I26: =SUM(I2:I25) | ... L26: =SUM(L2:L25)
A27: Purchase of PP&E | B27: -4625 | C27: -5207 | D27: -5518 | E27: -5318 | F27: -4415 | G27: ='QTR CF'!N26+'QTR CF'!O26+'QTR CF'!P26+'QTR CF'!Q26 | H27: ='QTR CF'!R26+'QTR CF'!S26+'QTR CF'!T26+'QTR CF'!U26 | I27: ='QTR CF'!V26+'QTR CF'!W26+'QTR CF'!X26+'QTR CF'!Y26 | J27: ='QTR CF'!Z26+'QTR CF'!AA26+'QTR CF'!AB26+'QTR CF'!AC26 | K27: ='QTR CF'!AD26+'QTR CF'!AE26+'QTR CF'!AF26+'QTR CF'!AG26 | L27: ='QTR CF'!AH26+'QTR CF'!AI26+'QTR CF'!AJ26+'QTR CF'!AK26
A28: Proceeds from Sale of Assets | B28: 166 | C28: 251 | D28: 198 | E28: 342 | F28: 528 | G28: ='QTR CF'!N27+'QTR CF'!O27+'QTR CF'!P27+'QTR CF'!Q27 | H28: ='QTR CF'!R27+'QTR CF'!S27+'QTR CF'!T27+'QTR CF'!U27 | I28: ='QTR CF'!V27+'QTR CF'!W27+'QTR CF'!X27+'QTR CF'!Y27 | J28: ='QTR CF'!Z27+'QTR CF'!AA27+'QTR CF'!AB27+'QTR CF'!AC27 | K28: ='QTR CF'!AD27+'QTR CF'!AE27+'QTR CF'!AF27+'QTR CF'!AG27 | L28: ='QTR CF'!AH27+'QTR CF'!AI27+'QTR CF'!AJ27+'QTR CF'!AK27
A29: Acquisitions, Net of Cash Acquired | B29: -61 | C29: -873 | D29: -314 | E29: -256 | F29: -3391 | G29: ='QTR CF'!N28+'QTR CF'!O28+'QTR CF'!P28+'QTR CF'!Q28 | H29: ='QTR CF'!R28+'QTR CF'!S28+'QTR CF'!T28+'QTR CF'!U28 | I29: ='QTR CF'!V28+'QTR CF'!W28+'QTR CF'!X28+'QTR CF'!Y28 | J29: ='QTR CF'!Z28+'QTR CF'!AA28+'QTR CF'!AB28+'QTR CF'!AC28 | K29: ='QTR CF'!AD28+'QTR CF'!AE28+'QTR CF'!AF28+'QTR CF'!AG28 | L29: ='QTR CF'!AH28+'QTR CF'!AI28+'QTR CF'!AJ28+'QTR CF'!AK28
A30: Proceeds from Juice Transaction | B30: 0 | C30: 3456 | D30: 0 | E30: 0 | F30: 0 | G30: ='QTR CF'!N29+'QTR CF'!O29+'QTR CF'!P29+'QTR CF'!Q29 | H30: ='QTR CF'!R29+'QTR CF'!S29+'QTR CF'!T29+'QTR CF'!U29 | I30: ='QTR CF'!V29+'QTR CF'!W29+'QTR CF'!X29+'QTR CF'!Y29 | J30: ='QTR CF'!Z29+'QTR CF'!AA29+'QTR CF'!AB29+'QTR CF'!AC29 | K30: ='QTR CF'!AD29+'QTR CF'!AE29+'QTR CF'!AF29+'QTR CF'!AG29 | L30: ='QTR CF'!AH29+'QTR CF'!AI29+'QTR CF'!AJ29+'QTR CF'!AK29
A31: Proceeds from Divestitures of Businesses | B31: 169 | C31: 49 | D31: 75 | E31: 166 | F31: 39 | G31: ='QTR CF'!N30+'QTR CF'!O30+'QTR CF'!P30+'QTR CF'!Q30 | H31: ='QTR CF'!R30+'QTR CF'!S30+'QTR CF'!T30+'QTR CF'!U30 | I31: ='QTR CF'!V30+'QTR CF'!W30+'QTR CF'!X30+'QTR CF'!Y30 | J31: ='QTR CF'!Z30+'QTR CF'!AA30+'QTR CF'!AB30+'QTR CF'!AC30 | K31: ='QTR CF'!AD30+'QTR CF'!AE30+'QTR CF'!AF30+'QTR CF'!AG30 | L31: ='QTR CF'!AH30+'QTR CF'!AI30+'QTR CF'!AJ30+'QTR CF'!AK30
A32: Net Change in Short-Term Investments | B32: 1077 | C32: -117 | D32: 16 | E32: -420 | F32: 460 | G32: ='QTR CF'!N31+'QTR CF'!O31+'QTR CF'!P31+'QTR CF'!Q31 | H32: ='QTR CF'!R31+'QTR CF'!S31+'QTR CF'!T31+'QTR CF'!U31 | I32: ='QTR CF'!V31+'QTR CF'!W31+'QTR CF'!X31+'QTR CF'!Y31 | J32: ='QTR CF'!Z31+'QTR CF'!AA31+'QTR CF'!AB31+'QTR CF'!AC31 | K32: ='QTR CF'!AD31+'QTR CF'!AE31+'QTR CF'!AF31+'QTR CF'!AG31 | L32: ='QTR CF'!AH31+'QTR CF'!AI31+'QTR CF'!AJ31+'QTR CF'!AK31
A33: Other Investing Activities | B33: 5 | C33: 11 | D33: 48 | E33: 14 | F33: -100 | G33: ='QTR CF'!N32+'QTR CF'!O32+'QTR CF'!P32+'QTR CF'!Q32 | H33: ='QTR CF'!R32+'QTR CF'!S32+'QTR CF'!T32+'QTR CF'!U32 | I33: ='QTR CF'!V32+'QTR CF'!W32+'QTR CF'!X32+'QTR CF'!Y32 | J33: ='QTR CF'!Z32+'QTR CF'!AA32+'QTR CF'!AB32+'QTR CF'!AC32 | K33: ='QTR CF'!AD32+'QTR CF'!AE32+'QTR CF'!AF32+'QTR CF'!AG32 | L33: ='QTR CF'!AH32+'QTR CF'!AI32+'QTR CF'!AJ32+'QTR CF'!AK32
A34: Cash Flow from Investing | B34: =SUM(B27:B33) | C34: =SUM(C27:C33) | D34: =SUM(D27:D33) | E34: =SUM(E27:E33) | F34: =SUM(F27:F33) | G34: =SUM(G27:G33) | H34: =SUM(H27:H33) | I34: =SUM(I27:I33) | ... L34: =SUM(L27:L33)
A35: Proceeds from Issuance of Long-Term Debt | B35: 4122 | C35: 3377 | D35: 5482 | E35: 4042 | F35: 8189 | G35: ='QTR CF'!N34+'QTR CF'!O34+'QTR CF'!P34+'QTR CF'!Q34 | H35: ='QTR CF'!R34+'QTR CF'!S34+'QTR CF'!T34+'QTR CF'!U34 | I35: ='QTR CF'!V34+'QTR CF'!W34+'QTR CF'!X34+'QTR CF'!Y34 | J35: ='QTR CF'!Z34+'QTR CF'!AA34+'QTR CF'!AB34+'QTR CF'!AC34 | K35: ='QTR CF'!AD34+'QTR CF'!AE34+'QTR CF'!AF34+'QTR CF'!AG34 | L35: ='QTR CF'!AH34+'QTR CF'!AI34+'QTR CF'!AJ34+'QTR CF'!AK34
A36: Repayments of Long-Term Debt | B36: -8299 | C36: -4174 | D36: -3005 | E36: -3886 | F36: -4082 | G36: ='QTR CF'!N35+'QTR CF'!O35+'QTR CF'!P35+'QTR CF'!Q35 | H36: ='QTR CF'!R35+'QTR CF'!S35+'QTR CF'!T35+'QTR CF'!U35 | I36: ='QTR CF'!V35+'QTR CF'!W35+'QTR CF'!X35+'QTR CF'!Y35 | J36: ='QTR CF'!Z35+'QTR CF'!AA35+'QTR CF'!AB35+'QTR CF'!AC35 | K36: ='QTR CF'!AD35+'QTR CF'!AE35+'QTR CF'!AF35+'QTR CF'!AG35 | L36: ='QTR CF'!AH35+'QTR CF'!AI35+'QTR CF'!AJ35+'QTR CF'!AK35
A37: Proceeds from Short-Term Debt | B37: 8 | C37: 1969 | D37: 5428 | E37: 5786 | F37: 6391 | G37: ='QTR CF'!N36+'QTR CF'!O36+'QTR CF'!P36+'QTR CF'!Q36 | H37: ='QTR CF'!R36+'QTR CF'!S36+'QTR CF'!T36+'QTR CF'!U36 | I37: ='QTR CF'!V36+'QTR CF'!W36+'QTR CF'!X36+'QTR CF'!Y36 | J37: ='QTR CF'!Z36+'QTR CF'!AA36+'QTR CF'!AB36+'QTR CF'!AC36 | K37: ='QTR CF'!AD36+'QTR CF'!AE36+'QTR CF'!AF36+'QTR CF'!AG36 | L37: ='QTR CF'!AH36+'QTR CF'!AI36+'QTR CF'!AJ36+'QTR CF'!AK36
A38: Repayments of Short-Term Debt | B38: -397 | C38: -1951 | D38: -3106 | E38: -5639 | F38: -7920 | G38: ='QTR CF'!N37+'QTR CF'!O37+'QTR CF'!P37+'QTR CF'!Q37 | H38: ='QTR CF'!R37+'QTR CF'!S37+'QTR CF'!T37+'QTR CF'!U37 | I38: ='QTR CF'!V37+'QTR CF'!W37+'QTR CF'!X37+'QTR CF'!Y37 | J38: ='QTR CF'!Z37+'QTR CF'!AA37+'QTR CF'!AB37+'QTR CF'!AC37 | K38: ='QTR CF'!AD37+'QTR CF'!AE37+'QTR CF'!AF37+'QTR CF'!AG37 | L38: ='QTR CF'!AH37+'QTR CF'!AI37+'QTR CF'!AJ37+'QTR CF'!AK37
A39: Net Change in Other Short-Term Debt | B39: 434 | C39: -31 | D39: -29 | E39: 392 | F39: 1170 | G39: ='QTR CF'!N38+'QTR CF'!O38+'QTR CF'!P38+'QTR CF'!Q38 | H39: ='QTR CF'!R38+'QTR CF'!S38+'QTR CF'!T38+'QTR CF'!U38 | I39: ='QTR CF'!V38+'QTR CF'!W38+'QTR CF'!X38+'QTR CF'!Y38 | J39: ='QTR CF'!Z38+'QTR CF'!AA38+'QTR CF'!AB38+'QTR CF'!AC38 | K39: ='QTR CF'!AD38+'QTR CF'!AE38+'QTR CF'!AF38+'QTR CF'!AG38 | L39: ='QTR CF'!AH38+'QTR CF'!AI38+'QTR CF'!AJ38+'QTR CF'!AK38
A40: Payments of Contingent Consideration | B40: -773 | C40: 0 | D40: 0 | E40: 0 | F40: 0
A41: Common Dividends | B41: -5815 | C41: -6172 | D41: -6682 | E41: -7229 | F41: -7638 | G41: ='QTR CF'!N39+'QTR CF'!O39+'QTR CF'!P39+'QTR CF'!Q39 | H41: ='QTR CF'!R39+'QTR CF'!S39+'QTR CF'!T39+'QTR CF'!U39 | I41: ='QTR CF'!V39+'QTR CF'!W39+'QTR CF'!X39+'QTR CF'!Y39 | J41: ='QTR CF'!Z39+'QTR CF'!AA39+'QTR CF'!AB39+'QTR CF'!AC39 | K41: ='QTR CF'!AD39+'QTR CF'!AE39+'QTR CF'!AF39+'QTR CF'!AG39 | L41: ='QTR CF'!AH39+'QTR CF'!AI39+'QTR CF'!AJ39+'QTR CF'!AK39
A42: Share Repurchases | B42: -106 | C42: -1500 | D42: -1000 | E42: -1000 | F42: -1000 | G42: ='QTR CF'!N40+'QTR CF'!O40+'QTR CF'!P40+'QTR CF'!Q40 | H42: ='QTR CF'!R40+'QTR CF'!S40+'QTR CF'!T40+'QTR CF'!U40 | I42: ='QTR CF'!V40+'QTR CF'!W40+'QTR CF'!X40+'QTR CF'!Y40 | J42: ='QTR CF'!Z40+'QTR CF'!AA40+'QTR CF'!AB40+'QTR CF'!AC40 | K42: ='QTR CF'!AD40+'QTR CF'!AE40+'QTR CF'!AF40+'QTR CF'!AG40 | L42: ='QTR CF'!AH40+'QTR CF'!AI40+'QTR CF'!AJ40+'QTR CF'!AK40
A43: Proceeds from Exercise of Stock Options | B43: 185 | C43: 138 | D43: 116 | E43: 166 | F43: 97 | G43: ='QTR CF'!N41+'QTR CF'!O41+'QTR CF'!P41+'QTR CF'!Q41 | H43: ='QTR CF'!R41+'QTR CF'!S41+'QTR CF'!T41+'QTR CF'!U41 | I43: ='QTR CF'!V41+'QTR CF'!W41+'QTR CF'!X41+'QTR CF'!Y41 | J43: ='QTR CF'!Z41+'QTR CF'!AA41+'QTR CF'!AB41+'QTR CF'!AC41 | K43: ='QTR CF'!AD41+'QTR CF'!AE41+'QTR CF'!AF41+'QTR CF'!AG41 | L43: ='QTR CF'!AH41+'QTR CF'!AI41+'QTR CF'!AJ41+'QTR CF'!AK41
A44: Tax Withholdings on RSU/PSU Settlement | B44: -92 | C44: -107 | D44: -140 | E44: -135 | F44: -113 | G44: ='QTR CF'!N42+'QTR CF'!O42+'QTR CF'!P42+'QTR CF'!Q42 | H44: ='QTR CF'!R42+'QTR CF'!S42+'QTR CF'!T42+'QTR CF'!U42 | I44: ='QTR CF'!V42+'QTR CF'!W42+'QTR CF'!X42+'QTR CF'!Y42 | J44: ='QTR CF'!Z42+'QTR CF'!AA42+'QTR CF'!AB42+'QTR CF'!AC42 | K44: ='QTR CF'!AD42+'QTR CF'!AE42+'QTR CF'!AF42+'QTR CF'!AG42 | L44: ='QTR CF'!AH42+'QTR CF'!AI42+'QTR CF'!AJ42+'QTR CF'!AK42
A45: Other Financing Activities | B45: -47 | C45: -72 | D45: -73 | E45: -53 | F45: -73 | G45: ='QTR CF'!N43+'QTR CF'!O43+'QTR CF'!P43+'QTR CF'!Q43 | H45: ='QTR CF'!R43+'QTR CF'!S43+'QTR CF'!T43+'QTR CF'!U43 | I45: ='QTR CF'!V43+'QTR CF'!W43+'QTR CF'!X43+'QTR CF'!Y43 | J45: ='QTR CF'!Z43+'QTR CF'!AA43+'QTR CF'!AB43+'QTR CF'!AC43 | K45: ='QTR CF'!AD43+'QTR CF'!AE43+'QTR CF'!AF43+'QTR CF'!AG43 | L45: ='QTR CF'!AH43+'QTR CF'!AI43+'QTR CF'!AJ43+'QTR CF'!AK43
A46: Cash Flow from Financing | B46: =SUM(B35:B45) | C46: =SUM(C35:C45) | D46: =SUM(D35:D45) | E46: =SUM(E35:E45) | F46: =SUM(F35:F45) | G46: =SUM(G35:G45) | H46: =SUM(H35:H45) | I46: =SUM(I35:I45) | ... L46: =SUM(L35:L45)
A47: FX Effect on Cash | B47: -114 | C47: -465 | D47: -277 | E47: -687 | F47: 422 | G47: ='QTR CF'!N45+'QTR CF'!O45+'QTR CF'!P45+'QTR CF'!Q45 | H47: ='QTR CF'!R45+'QTR CF'!S45+'QTR CF'!T45+'QTR CF'!U45 | I47: ='QTR CF'!V45+'QTR CF'!W45+'QTR CF'!X45+'QTR CF'!Y45 | J47: ='QTR CF'!Z45+'QTR CF'!AA45+'QTR CF'!AB45+'QTR CF'!AC45 | K47: ='QTR CF'!AD45+'QTR CF'!AE45+'QTR CF'!AF45+'QTR CF'!AG45 | L47: ='QTR CF'!AH45+'QTR CF'!AI45+'QTR CF'!AJ45+'QTR CF'!AK45
A48: Net Change in Cash | B48: =B26+B34+B46+B47 | C48: =C26+C34+C46+C47 | D48: =D26+D34+D46+D47 | E48: =E26+E34+E46+E47 | F48: =F26+F34+F46+F47 | G48: =G26+G34+G46+G47 | H48: =H26+H34+H46+H47 | I48: =I26+I34+I46+I47 | ... L48: =L26+L34+L46+L47

Sheet YTD P&L
B1: Q1 FY2022 | C1: Q2 FY2022 | D1: Q3 FY2022 | E1: Q1 FY2023 | F1: Q2 FY2023 | G1: Q3 FY2023 | H1: Q1 FY2024 | I1: Q2 FY2024 | J1: Q3 FY2024 | K1: Q1 FY2025 | L1: Q2 FY2025 | M1: Q3 FY2025 | N1: Q1 FY2026
A2: Net Sales / Revenue | B2: 16200 | C2: 36425 | D2: 58396 | E2: 17846 | F2: 40168 | G2: 63621 | H2: 18250 | I2: 40751 | J2: 64070 | K2: 17919 | L2: 40645 | M2: 64582 | N2: 19443
A3: COGS | B3: -7433 | C3: -16848 | D3: -27156 | E3: -7988 | F3: -18109 | G3: -28784 | H3: -8248 | I3: -18167 | J3: -28563 | K3: -7926 | L3: -18230 | M3: -29343 | N3: -8712
A4: Gross Profit (Loss) | B4: =B2+B3 | C4: =C2+C3 | D4: =D2+D3 | E4: =E2+E3 | F4: =F2+F3 | G4: =G2+G3 | H4: =H2+H3 | I4: =I2+I3 | ... N4: =N2+N3
A5: SG&A | B5: -6580 | C5: -13967 | D5: -22262 | E5: -7229 | F5: -15771 | G5: -24528 | H5: -7285 | I5: -15819 | J5: -24870 | K5: -7410 | L5: -16183 | M5: -25305 | N5: -7518
A6: Gain on Juice Transaction | B6: -3322 | C6: -3335 | D6: -3321 | E6: 0 | F6: 0 | G6: 0 | H6: 0 | I6: 0 | J6: 0 | K6: 0 | L6: 0 | M6: 0 | N6: 0
A7: Impairment of Intangibles | B7: -242 | C7: -1601 | D7: -1602 | E7: 0 | F7: 0 | G7: -6 | H7: 0 | I7: 0 | J7: 0 | K7: 0 | L7: -1860 | M7: -1993 | N7: 0
A8: Income (Loss) from Operations | B8: =B4+SUM(B5:B7) | C8: =C4+SUM(C5:C7) | D8: =D4+SUM(D5:D7) | E8: =E4+SUM(E5:E7) | F8: =F4+SUM(F5:F7) | G8: =G4+SUM(G5:G7) | H8: =H4+SUM(H5:H7) | I8: =I4+SUM(I5:I7) | ... N8: =N4+SUM(N5:N7)
A9: Other Pension and OPEB Benefits Income (Expense) | B9: 134 | C9: 132 | D9: 168 | E9: 61 | F9: 121 | G9: 183 | H9: 58 | I9: 114 | J9: 155 | K9: 23 | L9: 65 | M9: 91 | N9: 58
A10: Interest Income (Expense) | B10: -240 | C10: -476 | D10: -666 | E10: -200 | F10: -401 | G10: -602 | H10: -202 | I10: -436 | J10: -655 | K10: -264 | L10: -524 | M10: -788 | N10: -301
A11: Pre-Tax Income (Loss) | B11: =B8+SUM(B9:B10) | C11: =C8+SUM(C9:C10) | D11: =D8+SUM(D9:D10) | E11: =E8+SUM(E9:E10) | F11: =F8+SUM(F9:F10) | G11: =G8+SUM(G9:G10) | H11: =H8+SUM(H9:H10) | I11: =I8+SUM(I9:I10) | ... N11: =N8+SUM(N9:N10)
A12: Income Tax (Expense) Benefit | B12: -888 | C12: -1281 | D12: -1756 | E12: -546 | F12: -1293 | G12: -2053 | H12: -520 | I12: -1296 | J12: -2045 | K12: -499 | L12: -791 | M12: -1504 | N12: -632
A13: Net Income (Loss) | B13: =B11+B12 | C13: =C11+C12 | D13: =D11+D12 | E13: =E11+E12 | F13: =F11+F12 | G13: =G11+G12 | H13: =H11+H12 | I13: =I11+I12 | ... N13: =N11+N12
A14: Net Income (Loss) Attributable to Noncontrolling Interest | B14: 12 | C14: 29 | D14: 51 | E14: 12 | F14: 35 | G14: 59 | H14: 11 | I14: 22 | J14: 37 | K14: 9 | L14: 25 | M14: 40 | N14: 11
A15: Net Income (Loss) Less NCI | B15: =B13-B14 | C15: =C13-C14 | D15: =D13-D14 | E15: =E13-E14 | F15: =F13-F14 | G15: =G13-G14 | H15: =H13-H14 | I15: =I13-I14 | ... N15: =N13-N14
A16: Basic Earnings (Loss) per Share | B16: 3.08 | C16: 4.11 | D16: 6.07 | E16: 1.4 | F16: 3.4 | G16: 5.64 | H16: 1.49 | I16: 3.73 | J16: 5.86 | K16: 1.34 | L16: 2.26 | M16: 4.16 | N16: 1.7
A17: Diluted Earnings (Loss) per Share | B17: 3.06 | C17: 4.09 | D17: 6.04 | E17: 1.4 | F17: 3.38 | G17: 5.62 | H17: 1.48 | I17: 3.71 | J17: 5.84 | K17: 1.33 | L17: 2.25 | M17: 4.15 | N17: 1.7
A18: Weighted Average Shares Outstanding (Basic) | B18: 1383000000 | C18: 1383000000 | D18: 1382000000 | E18: 1378000000 | F18: 1378000000 | G18: 1377000000 | H18: 1375000000 | I18: 1375000000 | J18: 1374000000 | K18: 1372000000 | L18: 1371000000 | M18: 1370000000 | N18: 1367000000
A19: Weighted Average Shares Outstanding (Diluted) | B19: 1391000000 | C19: 1390000000 | D19: 1389000000 | E19: 1384000000 | F19: 1384000000 | G19: 1384000000 | H19: 1380000000 | I19: 1380000000 | J19: 1379000000 | K19: 1376000000 | L19: 1374000000 | M19: 1373000000 | N19: 1371000000

Sheet YTD BS
B1: Q4 FY2022 | C1: Q1 FY2023 | D1: Q2 FY2023 | E1: Q3 FY2023 | F1: Q4 FY2023 | G1: Q1 FY2024 | H1: Q2 FY2024 | I1: Q3 FY2024 | J1: Q4 FY2024 | K1: Q1 FY2025 | L1: Q2 FY2025 | M1: Q3 FY2025 | N1: Q4 FY2025 | O1: Q1 FY2026
A2: Cash & Cash Equivalents | B2: 4954 | C2: 4770 | D2: 6116 | E2: 10017 | F2: 9711 | G2: 8047 | H2: 6353 | I2: 7308 | J2: 8505 | K2: 8268 | L2: 7631 | M2: 8126 | N2: 9159 | O2: 10475
A3: Short-Term Investments | B3: 394 | C3: 434 | D3: 338 | E3: 266 | F3: 292 | G3: 303 | H3: 315 | I3: 743 | J3: 761 | K3: 314 | L3: 342 | M3: 535 | N3: 371 | O3: 353
A4: Accounts Receivable | B4: 10163 | C4: 10469 | D4: 11456 | E4: 11782 | F4: 10815 | G4: 10938 | H4: 11942 | I4: 12088 | J4: 10333 | K4: 10800 | L4: 12390 | M4: 12634 | N4: 11506 | O4: 12171
A5: Inventories | B5: 5222 | C5: 5697 | D5: 5969 | E5: 5558 | F5: 5334 | G5: 5569 | H5: 5887 | I5: 5644 | J5: 5306 | K5: 5660 | L5: 6487 | M5: 6093 | N5: 5845 | O5: 6211
A6: Prepaid Expenses | B6: 806 | C6: 1057 | D6: 1075 | E6: 1026 | F6: 798 | G6: 1148 | H6: 1206 | I6: 1069 | J6: 921 | K6: 1246 | L6: 1360 | M6: 1334 | N6: 1068 | O6: 1706
A7: Total Current Assets | B7: =SUM(B2:B6) | C7: =SUM(C2:C6) | D7: =SUM(D2:D6) | E7: =SUM(E2:E6) | F7: =SUM(F2:F6) | G7: =SUM(G2:G6) | H7: =SUM(H2:H6) | I7: =SUM(I2:I6) | ... O7: =SUM(O2:O6)
A8: Net PP&E | B8: 24291 | C8: 24228 | D8: 24500 | E8: 24853 | F8: 27039 | G8: 26792 | H8: 27042 | I8: 27188 | J8: 28008 | K8: 28213 | L8: 28797 | M8: 29053 | N8: 29905 | O8: 29807
A9: Intangible Assets | B9: 15586 | C9: 15523 | D9: 15562 | E9: 15501 | F9: 14929 | G9: 14853 | H9: 14826 | I9: 14857 | J9: 14801 | K9: 15363 | L9: 15523 | M9: 14852 | N9: 15066 | O9: 15143
A10: Goodwill | B10: 18202 | C10: 18089 | D10: 17997 | E10: 17892 | F10: 17728 | G10: 17646 | H10: 17648 | I10: 17709 | J10: 17534 | K10: 18364 | L10: 18952 | M10: 18845 | N10: 18916 | O10: 19021
A11: Equity Method Investments | B11: 3073 | C11: 3123 | D11: 3038 | E11: 2955 | F11: 2714 | G11: 2734 | H11: 2674 | I11: 2645 | J11: 1985 | K11: 1996 | L11: 2061 | M11: 2084 | N11: 2038 | O11: 2135
A12: Deferred Tax Assets | B12: 4204 | C12: 4211 | D12: 4186 | E12: 4165 | F12: 4474 | G12: 4444 | H12: 4465 | I12: 4321 | J12: 4362 | K12: 4350 | L12: 4293 | M12: 4341 | N12: 4541 | O12: 4560
A13: Other Non-Current Assets | B13: 5292 | C13: 5441 | D13: 5669 | E13: 5938 | F13: 6661 | G13: 7566 | H13: 7175 | I13: 6941 | J13: 6951 | K13: 7163 | L13: 7509 | M13: 8661 | N13: 8984 | O13: 9064
A14: Total Assets | B14: =B7+SUM(B8:B13) | C14: =C7+SUM(C8:C13) | D14: =D7+SUM(D8:D13) | E14: =E7+SUM(E8:E13) | F14: =F7+SUM(F8:F13) | G14: =G7+SUM(G8:G13) | H14: =H7+SUM(H8:H13) | I14: =I7+SUM(I8:I13) | ... O14: =O7+SUM(O8:O13)
A15: Short-Term Debt Obligations | B15: 3414 | C15: 4281 | D15: 7613 | E15: 8937 | F15: 6510 | G15: 8161 | H15: 8289 | I15: 6524 | J15: 7082 | K15: 9099 | L15: 12056 | M15: 6736 | N15: 6861 | O15: 10151
A16: Accrued Expenses | B16: 23371 | C16: 21556 | D16: 22005 | E16: 23723 | F16: 25137 | G16: 22073 | H16: 22859 | I16: 23791 | J16: 24454 | K16: 22412 | L16: 24340 | M16: 24763 | N16: 25903 | O16: 24326
A17: Total Current Liabilities | B17: =SUM(B15:B16) | C17: =SUM(C15:C16) | D17: =SUM(D15:D16) | E17: =SUM(E15:E16) | F17: =SUM(F15:F16) | G17: =SUM(G15:G16) | H17: =SUM(H15:H16) | I17: =SUM(I15:I16) | ... O17: =SUM(O15:O16)
A18: Long-Term Debt | B18: 35657 | C18: 37486 | D18: 36008 | E18: 35837 | F18: 37595 | G18: 37707 | H18: 36638 | I18: 38490 | J18: 37224 | K18: 39419 | L18: 39328 | M18: 44113 | N18: 42321 | O18: 42577
A19: Deferred Tax Liability | B19: 4133 | C19: 4039 | D19: 4113 | E19: 4047 | F19: 3895 | G19: 4087 | H19: 3908 | I19: 3684 | J19: 3484 | K19: 3541 | L19: 3102 | M19: 3474 | N19: 3802 | O19: 4048
A20: Other Non-Current Liabilities | B20: 8339 | C20: 8505 | D20: 8342 | E20: 8439 | F20: 8721 | G20: 8822 | H20: 8259 | I20: 8419 | J20: 9052 | K20: 8737 | L20: 7960 | M20: 7929 | N20: 7965 | O20: 8008
A21: Total Liabilities | B21: =B17+SUM(B18:B20) | C21: =C17+SUM(C18:C20) | D21: =D17+SUM(D18:D20) | E21: =E17+SUM(E18:E20) | F21: =F17+SUM(F18:F20) | G21: =G17+SUM(G18:G20) | H21: =H17+SUM(H18:H20) | I21: =I17+SUM(I18:I20) | ... O21: =O17+SUM(O18:O20)
A22: Common Stock | B22: 23 | C22: 23 | D22: 23 | E22: 23 | F22: 23 | G22: 23 | H22: 23 | I22: 23 | J22: 23 | K22: 23 | L22: 23 | M22: 23 | N22: 23 | O22: 23
A23: Additional Paid-in Capital | B23: 4134 | C23: 3996 | D23: 4082 | E23: 4154 | F23: 4261 | G23: 4132 | H23: 4203 | I23: 4281 | J23: 4385 | K23: 4274 | L23: 4299 | M23: 4374 | N23: 4451 | O23: 4401
A24: Retained Earnings (Accumulated Deficit) | B24: 67800 | C24: 68142 | D24: 69135 | E24: 70479 | F24: 70035 | G24: 70331 | H24: 71545 | I24: 72607 | J24: 72266 | K24: 72238 | L24: 71547 | M24: 72197 | N24: 72788 | O24: 73165
A25: Accumulated Other Comprehensive Income (Loss) | B25: -15302 | C25: -15601 | D25: -15780 | E25: -15794 | F25: -15534 | G25: -15179 | H25: -15786 | I25: -16652 | J25: -17612 | K25: -17078 | L25: -16090 | M25: -15597 | N25: -15024 | O25: -14342
A26: Treasury Stock | B26: -39506 | C26: -39518 | D26: -39775 | E26: -40056 | F26: -40282 | G26: -40260 | H26: -40539 | I26: -40806 | J26: -41021 | K26: -41068 | L26: -41361 | M26: -41609 | N26: -41832 | O26: -41864
A27: Noncontrolling Interest | B27: 124 | C27: 133 | D27: 140 | E27: 164 | F27: 134 | G27: 143 | H27: 134 | I27: 152 | J27: 130 | K27: 140 | L27: 141 | M27: 155 | N27: 141 | O27: 153
A28: Total Stockholders' Equity | B28: =SUM(B22:B27) | C28: =SUM(C22:C27) | D28: =SUM(D22:D27) | E28: =SUM(E22:E27) | F28: =SUM(F22:F27) | G28: =SUM(G22:G27) | H28: =SUM(H22:H27) | I28: =SUM(I22:I27) | ... O28: =SUM(O22:O27)
A29: Total Liabilities, Mezzanine & Stockholders' Equity | B29: =B21+B28 | C29: =C21+C28 | D29: =D21+D28 | E29: =E21+E28 | F29: =F21+F28 | G29: =G21+G28 | H29: =H21+H28 | I29: =I21+I28 | ... O29: =O21+O28

Sheet YTD CF
B1: Q1 FY2022 | C1: Q2 FY2022 | D1: Q3 FY2022 | E1: Q1 FY2023 | F1: Q2 FY2023 | G1: Q3 FY2023 | H1: Q1 FY2024 | I1: Q2 FY2024 | J1: Q3 FY2024 | K1: Q1 FY2025 | L1: Q2 FY2025 | M1: Q3 FY2025 | N1: Q1 FY2026
A2: Net Income (Loss) | B2: 4273 | C2: 5719 | D2: 8443 | E2: 1944 | F2: 4715 | G2: 7831 | H2: 2053 | I2: 5147 | J2: 8092 | K2: 1843 | L2: 3122 | M2: 5740 | N2: 2338
A3: Depreciation & Amortization | B3: 555 | C3: 1195 | D3: 1854 | E3: 590 | F3: 1268 | G3: 1973 | H3: 641 | I3: 1379 | J3: 2118 | K3: 684 | L3: 1491 | M3: 2315 | N3: 742
A4: Gain on Juice Transaction | B4: -3322 | C4: -3335 | D4: -3321 | E4: 0 | F4: 0 | G4: 0 | H4: 0 | I4: 0 | J4: 0 | K4: 0 | L4: 0 | M4: 0 | N4: 0
A5: Impairment and Other Charges | B5: 482 | C5: 1871 | D5: 1877 | E5: -13 | F5: 97 | G5: 102 | H5: 0 | I5: 0 | J5: 10 | K5: 0 | L5: 1860 | M5: 1960 | N5: 0
A6: Product Recall Impact | B6: 0 | C6: 0 | D6: 0 | E6: 0 | F6: 0 | G6: 0 | H6: 167 | I6: 182 | J6: 184 | K6: 0 | L6: 0 | M6: 0 | N6: 0
A7: Cash Payments for Product Recall | B7: 0 | C7: 0 | D7: 0 | E7: 0 | F7: 0 | G7: 0 | H7: -108 | I7: -135 | J7: -138 | K7: -2 | L7: -2 | M7: -5 | N7: 0
A8: Operating Lease ROU Asset Amortization | B8: 103 | C8: 223 | D8: 346 | E8: 116 | F8: 248 | G8: 384 | H8: 127 | I8: 278 | J8: 438 | K8: 145 | L8: 315 | M8: 489 | N8: 162
A9: Stock-Based Compensation | B9: 81 | C9: 156 | D9: 233 | E9: 93 | F9: 179 | G9: 267 | H9: 97 | I9: 183 | J9: 260 | K9: 77 | L9: 131 | M9: 207 | N9: 93
A10: Restructuring and Asset Impairment Charges | B10: 27 | C10: 75 | D10: 126 | E10: 112 | F10: 204 | G10: 287 | H10: 96 | I10: 170 | J10: 415 | K10: 213 | L10: 426 | M10: 567 | N10: 133
A11: Cash Payments for Restructuring | B11: -32 | C11: -82 | D11: -134 | E11: -64 | F11: -187 | G11: -283 | H11: -60 | I11: -173 | J11: -284 | K11: -232 | L11: -387 | M11: -554 | N11: -145
A12: Acquisition and Divestiture-Related Charges | B12: 56 | C12: 64 | D12: 69 | E12: 2 | F12: 9 | G12: 20 | H12: 0 | I12: 0 | J12: 0 | K12: 0 | L12: 0 | M12: 308 | N12: -113
A13: Cash Payments for Acquisition and Divestiture Costs | B13: -17 | C13: -34 | D13: -41 | E13: -4 | F13: -10 | G13: -15 | H13: 0 | I13: 0 | J13: 0 | K13: 0 | L13: 0 | M13: -80 | N13: -14
... A24: Other Operating Items | B24: -133 | C24: -325 | D24: -426 | E24: 46 | F24: -6 | G24: 72 | H24: -68 | I24: -203 | J24: -135 | K24: -232 | L24: -269 | M24: -441 | N24: -157
A25: Cash Flow from Operations | B25: =SUM(B2:B24) | C25: =SUM(C2:C24) | D25: =SUM(D2:D24) | E25: =SUM(E2:E24) | F25: =SUM(F2:F24) | G25: =SUM(G2:G24) | H25: =SUM(H2:H24) | I25: =SUM(I2:I24) | ... N25: =SUM(N2:N24)
A26: Purchase of PP&E | B26: -522 | C26: -1499 | D26: -2556 | E26: -581 | F26: -1513 | G26: -2537 | H26: -614 | I26: -1701 | J26: -2850 | K26: -603 | L26: -1507 | M26: -2499 | N26: -447
A27: Proceeds from Sale of Assets | B27: 3 | C27: 222 | D27: 228 | E27: 19 | F27: 122 | G27: 131 | H27: 7 | I27: 127 | J27: 177 | K27: 132 | L27: 169 | M27: 272 | N27: 13
A28: Acquisitions, Net of Cash Acquired | B28: -13 | C28: -29 | D28: -804 | E28: -16 | F28: -83 | G28: -132 | H28: -6 | I28: -30 | J28: -31 | K28: -1200 | L28: -3130 | M28: -3176 | N28: -67
A29: Proceeds from Juice Transaction | B29: 3456 | C29: 3456 | D29: 3456 | E29: 0 | F29: 0 | G29: 0 | H29: 0 | I29: 0 | J29: 0 | K29: 0 | L29: 0 | M29: 0 | N29: 0
A30: Proceeds from Divestitures of Businesses | B30: 5 | C30: 15 | D30: 15 | E30: 85 | F30: 75 | G30: 75 | H30: 53 | I30: 135 | J30: 145 | K30: 2 | L30: 5 | M30: 5 | N30: 0
A31: Net Change in Short-Term Investments | B31: 22 | C31: 8 | D31: -37 | E31: -39 | F31: -56 | G31: 35 | H31: 8 | I31: 1 | J31: -421 | K31: 441 | L31: 447 | M31: 278 | N31: 5
A32: Other Investing Activities | B32: 4 | C32: -1 | D32: 7 | E32: 0 | F32: 32 | G32: 49 | H32: -10 | I32: 14 | J32: 15 | K32: -4 | L32: -111 | M32: -117 | N32: 19
A33: Cash Flow from Investing | B33: =SUM(B26:B32) | C33: =SUM(C26:C32) | D33: =SUM(D26:D32) | E33: =SUM(E26:E32) | F33: =SUM(F26:F32) | G33: =SUM(G26:G32) | H33: =SUM(H26:H32) | I33: =SUM(I26:I32) | ... N33: =SUM(N26:N32)
A34: Proceeds from Issuance of Long-Term Debt | B34: 0 | C34: 0 | D34: 3377 | E34: 2986 | F34: 2986 | G34: 2986 | H34: 1761 | I34: 1765 | J34: 4014 | K34: 3505 | L34: 3521 | M34: 8179 | N34: 2964
A35: Repayments of Long-Term Debt | B35: -1251 | C35: -3202 | D35: -3203 | E35: -1251 | F35: -2252 | G35: -2253 | H35: -1252 | I35: -2882 | J35: -2883 | K35: -1541 | L35: -2543 | M35: -3245 | N35: -1629
A36: Proceeds from Short-Term Debt | B36: 559 | C36: 1935 | D36: 1947 | E36: 393 | F36: 1660 | G36: 4688 | H36: 2313 | I36: 3080 | J36: 3808 | K36: 3656 | L36: 5251 | M36: 5528 | N36: 1937
A37: Repayments of Short-Term Debt | B37: 0 | C37: 0 | D37: -1932 | E37: -1 | F37: -26 | G37: -1037 | H37: -1631 | I37: -2138 | J37: -4177 | K37: -2119 | L37: -2492 | M37: -5417 | N37: -676
A38: Net Change in Other Short-Term Debt | B38: 647 | C38: 844 | D38: -45 | E38: 491 | F38: 2023 | G38: 1395 | H38: 774 | I38: 1286 | J38: 101 | K38: 373 | L38: 2438 | M38: 445 | N38: 1198
A39: Common Dividends | B39: -1505 | C39: -2997 | D39: -4586 | E39: -1608 | F39: -3199 | G39: -4941 | H39: -1767 | I39: -3506 | J39: -5369 | K39: -1882 | L39: -3743 | M39: -5692 | N39: -1966
A40: Share Repurchases | B40: -193 | C40: -699 | D40: -1156 | E40: -160 | F40: -453 | G40: -751 | H40: -146 | I40: -461 | J40: -760 | K40: -183 | L40: -494 | M40: -752 | N40: -182
A41: Proceeds from Exercise of Stock Options | B41: 49 | C41: 89 | D41: 113 | E41: 46 | F41: 86 | G41: 100 | H41: 66 | I41: 107 | J41: 138 | K41: 50 | L41: 58 | M41: 76 | N41: 93
A42: Tax Withholdings on RSU/PSU Settlement | B42: -85 | C42: -87 | D42: -97 | E42: -116 | F42: -119 | G42: -135 | H42: -108 | I42: -131 | J42: -132 | K42: -89 | L42: -111 | M42: -112 | N42: -76
A43: Other Financing Activities | B43: -1 | C43: -15 | D43: -25 | E43: -3 | F43: -16 | G43: -18 | H43: 0 | I43: -20 | J43: -22 | K43: -2 | L43: -17 | M43: -18 | N43: -1
A44: Cash Flow from Financing | B44: =SUM(B34:B43) | C44: =SUM(C34:C43) | D44: =SUM(D34:D43) | E44: =SUM(E34:E43) | F44: =SUM(F34:F43) | G44: =SUM(G34:G43) | H44: =SUM(H34:H43) | I44: =SUM(I34:I43) | ... N44: =SUM(N34:N43)
A45: FX Effect on Cash | B45: -17 | C45: -83 | D45: -197 | E45: -116 | F45: -144 | G45: -254 | H45: -38 | I45: -304 | J45: -391 | K45: 203 | L45: 422 | M45: 395 | N45: 121
A46: Net Change in Cash | B46: =B25+B33+B44+B45 | C46: =C25+C33+C44+C45 | D46: =D25+D33+D44+D45 | E46: =E25+E33+E44+E45 | F46: =F25+F33+F44+F45 | G46: =G25+G33+G44+G45 | H46: =H25+H33+H44+H45 | I46: =I25+I33+I44+I45 | ... N46: =N25+N33+N44+N45

Sheet QTR P&L
B1: Q1 FY2022 | C1: Q2 FY2022 | D1: Q3 FY2022 | E1: Q4 FY2022 | F1: Q1 FY2023 | G1: Q2 FY2023 | H1: Q3 FY2023 | I1: Q4 FY2023 | J1: Q1 FY2024 | K1: Q2 FY2024 | L1: Q3 FY2024 | M1: Q4 FY2024 | N1: Q1 FY2025 | O1: Q2 FY2025 | P1: Q3 FY2025 | Q1: Q4 FY2025 | R1: Q1 FY2026 | S1: Q2 FY2026E | T1: Q3 FY2026E | U1: Q4 FY2026E | V1: Q1 FY2027E | W1: Q2 FY2027E | X1: Q3 FY2027E | Y1: Q4 FY2027E | Z1: Q1 FY2028E | AA1: Q2 FY2028E | AB1: Q3 FY2028E | AC1: Q4 FY2028E | AD1: Q1 FY2029E | AE1: Q2 FY2029E | AF1: Q3 FY2029E | AG1: Q4 FY2029E | AH1: Q1 FY2030E | AI1: Q2 FY2030E | AJ1: Q3 FY2030E | AK1: Q4 FY2030E
A2: Net Sales / Revenue | B2: ='YTD P&L'!B2 | C2: ='YTD P&L'!C2-'YTD P&L'!B2 | D2: ='YTD P&L'!D2-'YTD P&L'!C2 | E2: ='ANNL P&L'!C2-'YTD P&L'!D2 | F2: ='YTD P&L'!E2 | G2: ='YTD P&L'!F2-'YTD P&L'!E2 | H2: ='YTD P&L'!G2-'YTD P&L'!F2 | I2: ='ANNL P&L'!D2-'YTD P&L'!G2 | J2: ='YTD P&L'!H2 | K2: ='YTD P&L'!I2-'YTD P&L'!H2 | L2: ='YTD P&L'!J2-'YTD P&L'!I2 | M2: ='ANNL P&L'!E2-'YTD P&L'!J2 | N2: ='YTD P&L'!K2 | O2: ='YTD P&L'!L2-'YTD P&L'!K2 | P2: ='YTD P&L'!M2-'YTD P&L'!L2 | Q2: ='ANNL P&L'!F2-'YTD P&L'!M2 | R2: ='YTD P&L'!N2 | S2: ='QTR P&L'!O2*(1+'IS DRIVERS'!S2) | T2: ='QTR P&L'!P2*(1+'IS DRIVERS'!T2) | U2: ='QTR P&L'!Q2*(1+'IS DRIVERS'!U2) | V2: ='QTR P&L'!R2*(1+'IS DRIVERS'!V2) | W2: ='QTR P&L'!S2*(1+'IS DRIVERS'!W2) | X2: ='QTR P&L'!T2*(1+'IS DRIVERS'!X2) | Y2: ='QTR P&L'!U2*(1+'IS DRIVERS'!Y2) | Z2: ='QTR P&L'!V2*(1+'IS DRIVERS'!Z2) | ... AK2: ='QTR P&L'!AG2*(1+'IS DRIVERS'!AK2)
A3: COGS | B3: ='YTD P&L'!B3 | C3: ='YTD P&L'!C3-'YTD P&L'!B3 | D3: ='YTD P&L'!D3-'YTD P&L'!C3 | E3: ='ANNL P&L'!C3-'YTD P&L'!D3 | F3: ='YTD P&L'!E3 | G3: ='YTD P&L'!F3-'YTD P&L'!E3 | H3: ='YTD P&L'!G3-'YTD P&L'!F3 | I3: ='ANNL P&L'!D3-'YTD P&L'!G3 | J3: ='YTD P&L'!H3 | K3: ='YTD P&L'!I3-'YTD P&L'!H3 | L3: ='YTD P&L'!J3-'YTD P&L'!I3 | M3: ='ANNL P&L'!E3-'YTD P&L'!J3 | N3: ='YTD P&L'!K3 | O3: ='YTD P&L'!L3-'YTD P&L'!K3 | P3: ='YTD P&L'!M3-'YTD P&L'!L3 | Q3: ='ANNL P&L'!F3-'YTD P&L'!M3 | R3: ='YTD P&L'!N3 | S3: ='QTR P&L'!S2*'IS DRIVERS'!S3 | T3: ='QTR P&L'!T2*'IS DRIVERS'!T3 | U3: ='QTR P&L'!U2*'IS DRIVERS'!U3 | V3: ='QTR P&L'!V2*'IS DRIVERS'!V3 | W3: ='QTR P&L'!W2*'IS DRIVERS'!W3 | X3: ='QTR P&L'!X2*'IS DRIVERS'!X3 | Y3: ='QTR P&L'!Y2*'IS DRIVERS'!Y3 | Z3: ='QTR P&L'!Z2*'IS DRIVERS'!Z3 | ... AK3: ='QTR P&L'!AK2*'IS DRIVERS'!AK3
A4: Gross Profit (Loss) | B4: ='YTD P&L'!B4 | C4: ='YTD P&L'!C4-'YTD P&L'!B4 | D4: ='YTD P&L'!D4-'YTD P&L'!C4 | E4: ='ANNL P&L'!C4-'YTD P&L'!D4 | F4: ='YTD P&L'!E4 | G4: ='YTD P&L'!F4-'YTD P&L'!E4 | H4: ='YTD P&L'!G4-'YTD P&L'!F4 | I4: ='ANNL P&L'!D4-'YTD P&L'!G4 | J4: ='YTD P&L'!H4 | K4: ='YTD P&L'!I4-'YTD P&L'!H4 | L4: ='YTD P&L'!J4-'YTD P&L'!I4 | M4: ='ANNL P&L'!E4-'YTD P&L'!J4 | N4: ='YTD P&L'!K4 | O4: ='YTD P&L'!L4-'YTD P&L'!K4 | P4: ='YTD P&L'!M4-'YTD P&L'!L4 | Q4: ='ANNL P&L'!F4-'YTD P&L'!M4 | R4: ='YTD P&L'!N4 | S4: =S2+S3 | T4: =T2+T3 | U4: =U2+U3 | V4: =V2+V3 | W4: =W2+W3 | X4: =X2+X3 | Y4: =Y2+Y3 | Z4: =Z2+Z3 | ... AK4: =AK2+AK3
A5: SG&A | B5: ='YTD P&L'!B5 | C5: ='YTD P&L'!C5-'YTD P&L'!B5 | D5: ='YTD P&L'!D5-'YTD P&L'!C5 | E5: ='ANNL P&L'!C5-'YTD P&L'!D5 | F5: ='YTD P&L'!E5 | G5: ='YTD P&L'!F5-'YTD P&L'!E5 | H5: ='YTD P&L'!G5-'YTD P&L'!F5 | I5: ='ANNL P&L'!D5-'YTD P&L'!G5 | J5: ='YTD P&L'!H5 | K5: ='YTD P&L'!I5-'YTD P&L'!H5 | L5: ='YTD P&L'!J5-'YTD P&L'!I5 | M5: ='ANNL P&L'!E5-'YTD P&L'!J5 | N5: ='YTD P&L'!K5 | O5: ='YTD P&L'!L5-'YTD P&L'!K5 | P5: ='YTD P&L'!M5-'YTD P&L'!L5 | Q5: ='ANNL P&L'!F5-'YTD P&L'!M5 | R5: ='YTD P&L'!N5 | S5: ='QTR P&L'!S2*'IS DRIVERS'!S4 | T5: ='QTR P&L'!T2*'IS DRIVERS'!T4 | U5: ='QTR P&L'!U2*'IS DRIVERS'!U4 | V5: ='QTR P&L'!V2*'IS DRIVERS'!V4 | W5: ='QTR P&L'!W2*'IS DRIVERS'!W4 | X5: ='QTR P&L'!X2*'IS DRIVERS'!X4 | Y5: ='QTR P&L'!Y2*'IS DRIVERS'!Y4 | Z5: ='QTR P&L'!Z2*'IS DRIVERS'!Z4 | ... AK5: ='QTR P&L'!AK2*'IS DRIVERS'!AK4
A6: Gain on Juice Transaction | B6: ='YTD P&L'!B6 | C6: ='YTD P&L'!C6-'YTD P&L'!B6 | D6: ='YTD P&L'!D6-'YTD P&L'!C6 | E6: ='ANNL P&L'!C6-'YTD P&L'!D6 | F6: ='YTD P&L'!E6 | G6: ='YTD P&L'!F6-'YTD P&L'!E6 | H6: ='YTD P&L'!G6-'YTD P&L'!F6 | I6: ='ANNL P&L'!D6-'YTD P&L'!G6 | J6: ='YTD P&L'!H6 | K6: ='YTD P&L'!I6-'YTD P&L'!H6 | L6: ='YTD P&L'!J6-'YTD P&L'!I6 | M6: ='ANNL P&L'!E6-'YTD P&L'!J6 | N6: ='YTD P&L'!K6 | O6: ='YTD P&L'!L6-'YTD P&L'!K6 | P6: ='YTD P&L'!M6-'YTD P&L'!L6 | Q6: ='ANNL P&L'!F6-'YTD P&L'!M6 | R6: ='YTD P&L'!N6 | S6: ='IS DRIVERS'!S5 | T6: ='IS DRIVERS'!T5 | U6: ='IS DRIVERS'!U5 | V6: ='IS DRIVERS'!V5 | W6: ='IS DRIVERS'!W5 | X6: ='IS DRIVERS'!X5 | Y6: ='IS DRIVERS'!Y5 | Z6: ='IS DRIVERS'!Z5 | ... AK6: ='IS DRIVERS'!AK5
A7: Impairment of Intangibles | B7: ='YTD P&L'!B7 | C7: ='YTD P&L'!C7-'YTD P&L'!B7 | D7: ='YTD P&L'!D7-'YTD P&L'!C7 | E7: ='ANNL P&L'!C7-'YTD P&L'!D7 | F7: ='YTD P&L'!E7 | G7: ='YTD P&L'!F7-'YTD P&L'!E7 | H7: ='YTD P&L'!G7-'YTD P&L'!F7 | I7: ='ANNL P&L'!D7-'YTD P&L'!G7 | J7: ='YTD P&L'!H7 | K7: ='YTD P&L'!I7-'YTD P&L'!H7 | L7: ='YTD P&L'!J7-'YTD P&L'!I7 | M7: ='ANNL P&L'!E7-'YTD P&L'!J7 | N7: ='YTD P&L'!K7 | O7: ='YTD P&L'!L7-'YTD P&L'!K7 | P7: ='YTD P&L'!M7-'YTD P&L'!L7 | Q7: ='ANNL P&L'!F7-'YTD P&L'!M7 | R7: ='YTD P&L'!N7 | S7: ='QTR P&L'!S2*'IS DRIVERS'!S6 | T7: ='QTR P&L'!T2*'IS DRIVERS'!T6 | U7: ='QTR P&L'!U2*'IS DRIVERS'!U6 | V7: ='QTR P&L'!V2*'IS DRIVERS'!V6 | W7: ='QTR P&L'!W2*'IS DRIVERS'!W6 | X7: ='QTR P&L'!X2*'IS DRIVERS'!X6 | Y7: ='QTR P&L'!Y2*'IS DRIVERS'!Y6 | Z7: ='QTR P&L'!Z2*'IS DRIVERS'!Z6 | ... AK7: ='QTR P&L'!AK2*'IS DRIVERS'!AK6
A8: Income (Loss) from Operations | B8: ='YTD P&L'!B8 | C8: ='YTD P&L'!C8-'YTD P&L'!B8 | D8: ='YTD P&L'!D8-'YTD P&L'!C8 | E8: ='ANNL P&L'!C8-'YTD P&L'!D8 | F8: ='YTD P&L'!E8 | G8: ='YTD P&L'!F8-'YTD P&L'!E8 | H8: ='YTD P&L'!G8-'YTD P&L'!F8 | I8: ='ANNL P&L'!D8-'YTD P&L'!G8 | J8: ='YTD P&L'!H8 | K8: ='YTD P&L'!I8-'YTD P&L'!H8 | L8: ='YTD P&L'!J8-'YTD P&L'!I8 | M8: ='ANNL P&L'!E8-'YTD P&L'!J8 | N8: ='YTD P&L'!K8 | O8: ='YTD P&L'!L8-'YTD P&L'!K8 | P8: ='YTD P&L'!M8-'YTD P&L'!L8 | Q8: ='ANNL P&L'!F8-'YTD P&L'!M8 | R8: ='YTD P&L'!N8 | S8: =S4+SUM(S5:S7) | T8: =T4+SUM(T5:T7) | U8: =U4+SUM(U5:U7) | V8: =V4+SUM(V5:V7) | W8: =W4+SUM(W5:W7) | X8: =X4+SUM(X5:X7) | Y8: =Y4+SUM(Y5:Y7) | Z8: =Z4+SUM(Z5:Z7) | ... AK8: =AK4+SUM(AK5:AK7)
A9: Other Pension and OPEB Benefits Income (Expense) | B9: ='YTD P&L'!B9 | C9: ='YTD P&L'!C9-'YTD P&L'!B9 | D9: ='YTD P&L'!D9-'YTD P&L'!C9 | E9: ='ANNL P&L'!C9-'YTD P&L'!D9 | F9: ='YTD P&L'!E9 | G9: ='YTD P&L'!F9-'YTD P&L'!E9 | H9: ='YTD P&L'!G9-'YTD P&L'!F9 | I9: ='ANNL P&L'!D9-'YTD P&L'!G9 | J9: ='YTD P&L'!H9 | K9: ='YTD P&L'!I9-'YTD P&L'!H9 | L9: ='YTD P&L'!J9-'YTD P&L'!I9 | M9: ='ANNL P&L'!E9-'YTD P&L'!J9 | N9: ='YTD P&L'!K9 | O9: ='YTD P&L'!L9-'YTD P&L'!K9 | P9: ='YTD P&L'!M9-'YTD P&L'!L9 | Q9: ='ANNL P&L'!F9-'YTD P&L'!M9 | R9: ='YTD P&L'!N9 | S9: ='IS DRIVERS'!S7 | T9: ='IS DRIVERS'!T7 | U9: ='IS DRIVERS'!U7 | V9: ='IS DRIVERS'!V7 | W9: ='IS DRIVERS'!W7 | X9: ='IS DRIVERS'!X7 | Y9: ='IS DRIVERS'!Y7 | Z9: ='IS DRIVERS'!Z7 | ... AK9: ='IS DRIVERS'!AK7
A10: Interest Income (Expense) | B10: ='YTD P&L'!B10 | C10: ='YTD P&L'!C10-'YTD P&L'!B10 | D10: ='YTD P&L'!D10-'YTD P&L'!C10 | E10: ='ANNL P&L'!C10-'YTD P&L'!D10 | F10: ='YTD P&L'!E10 | G10: ='YTD P&L'!F10-'YTD P&L'!E10 | H10: ='YTD P&L'!G10-'YTD P&L'!F10 | I10: ='ANNL P&L'!D10-'YTD P&L'!G10 | J10: ='YTD P&L'!H10 | K10: ='YTD P&L'!I10-'YTD P&L'!H10 | L10: ='YTD P&L'!J10-'YTD P&L'!I10 | M10: ='ANNL P&L'!E10-'YTD P&L'!J10 | N10: ='YTD P&L'!K10 | O10: ='YTD P&L'!L10-'YTD P&L'!K10 | P10: ='YTD P&L'!M10-'YTD P&L'!L10 | Q10: ='ANNL P&L'!F10-'YTD P&L'!M10 | R10: ='YTD P&L'!N10 | S10: ='IS DRIVERS'!S8 | T10: ='IS DRIVERS'!T8 | U10: ='IS DRIVERS'!U8 | V10: ='IS DRIVERS'!V8 | W10: ='IS DRIVERS'!W8 | X10: ='IS DRIVERS'!X8 | Y10: ='IS DRIVERS'!Y8 | Z10: ='IS DRIVERS'!Z8 | ... AK10: ='IS DRIVERS'!AK8
A11: Pre-Tax Income (Loss) | B11: ='YTD P&L'!B11 | C11: ='YTD P&L'!C11-'YTD P&L'!B11 | D11: ='YTD P&L'!D11-'YTD P&L'!C11 | E11: ='ANNL P&L'!C11-'YTD P&L'!D11 | F11: ='YTD P&L'!E11 | G11: ='YTD P&L'!F11-'YTD P&L'!E11 | H11: ='YTD P&L'!G11-'YTD P&L'!F11 | I11: ='ANNL P&L'!D11-'YTD P&L'!G11 | J11: ='YTD P&L'!H11 | K11: ='YTD P&L'!I11-'YTD P&L'!H11 | L11: ='YTD P&L'!J11-'YTD P&L'!I11 | M11: ='ANNL P&L'!E11-'YTD P&L'!J11 | N11: ='YTD P&L'!K11 | O11: ='YTD P&L'!L11-'YTD P&L'!K11 | P11: ='YTD P&L'!M11-'YTD P&L'!L11 | Q11: ='ANNL P&L'!F11-'YTD P&L'!M11 | R11: ='YTD P&L'!N11 | S11: =S8+SUM(S9:S10) | T11: =T8+SUM(T9:T10) | U11: =U8+SUM(U9:U10) | V11: =V8+SUM(V9:V10) | W11: =W8+SUM(W9:W10) | X11: =X8+SUM(X9:X10) | Y11: =Y8+SUM(Y9:Y10) | Z11: =Z8+SUM(Z9:Z10) | ... AK11: =AK8+SUM(AK9:AK10)
A12: Income Tax (Expense) Benefit | B12: ='YTD P&L'!B12 | C12: ='YTD P&L'!C12-'YTD P&L'!B12 | D12: ='YTD P&L'!D12-'YTD P&L'!C12 | E12: ='ANNL P&L'!C12-'YTD P&L'!D12 | F12: ='YTD P&L'!E12 | G12: ='YTD P&L'!F12-'YTD P&L'!E12 | H12: ='YTD P&L'!G12-'YTD P&L'!F12 | I12: ='ANNL P&L'!D12-'YTD P&L'!G12 | J12: ='YTD P&L'!H12 | K12: ='YTD P&L'!I12-'YTD P&L'!H12 | L12: ='YTD P&L'!J12-'YTD P&L'!I12 | M12: ='ANNL P&L'!E12-'YTD P&L'!J12 | N12: ='YTD P&L'!K12 | O12: ='YTD P&L'!L12-'YTD P&L'!K12 | P12: ='YTD P&L'!M12-'YTD P&L'!L12 | Q12: ='ANNL P&L'!F12-'YTD P&L'!M12 | R12: ='YTD P&L'!N12 | S12: ='QTR P&L'!S11*'IS DRIVERS'!S9 | T12: ='QTR P&L'!T11*'IS DRIVERS'!T9 | U12: ='QTR P&L'!U11*'IS DRIVERS'!U9 | V12: ='QTR P&L'!V11*'IS DRIVERS'!V9 | W12: ='QTR P&L'!W11*'IS DRIVERS'!W9 | X12: ='QTR P&L'!X11*'IS DRIVERS'!X9 | Y12: ='QTR P&L'!Y11*'IS DRIVERS'!Y9 | Z12: ='QTR P&L'!Z11*'IS DRIVERS'!Z9 | ... AK12: ='QTR P&L'!AK11*'IS DRIVERS'!AK9
A13: Net Income (Loss) | B13: ='YTD P&L'!B13 | C13: ='YTD P&L'!C13-'YTD P&L'!B13 | D13: ='YTD P&L'!D13-'YTD P&L'!C13 | E13: ='ANNL P&L'!C13-'YTD P&L'!D13 | F13: ='YTD P&L'!E13 | G13: ='YTD P&L'!F13-'YTD P&L'!E13 | H13: ='YTD P&L'!G13-'YTD P&L'!F13 | I13: ='ANNL P&L'!D13-'YTD P&L'!G13 | J13: ='YTD P&L'!H13 | K13: ='YTD P&L'!I13-'YTD P&L'!H13 | L13: ='YTD P&L'!J13-'YTD P&L'!I13 | M13: ='ANNL P&L'!E13-'YTD P&L'!J13 | N13: ='YTD P&L'!K13 | O13: ='YTD P&L'!L13-'YTD P&L'!K13 | P13: ='YTD P&L'!M13-'YTD P&L'!L13 | Q13: ='ANNL P&L'!F13-'YTD P&L'!M13 | R13: ='YTD P&L'!N13 | S13: =S11+S12 | T13: =T11+T12 | U13: =U11+U12 | V13: =V11+V12 | W13: =W11+W12 | X13: =X11+X12 | Y13: =Y11+Y12 | Z13: =Z11+Z12 | ... AK13: =AK11+AK12
A14: Net Income (Loss) Attributable to Noncontrolling Interest | B14: ='YTD P&L'!B14 | C14: ='YTD P&L'!C14-'YTD P&L'!B14 | D14: ='YTD P&L'!D14-'YTD P&L'!C14 | E14: ='ANNL P&L'!C14-'YTD P&L'!D14 | F14: ='YTD P&L'!E14 | G14: ='YTD P&L'!F14-'YTD P&L'!E14 | H14: ='YTD P&L'!G14-'YTD P&L'!F14 | I14: ='ANNL P&L'!D14-'YTD P&L'!G14 | J14: ='YTD P&L'!H14 | K14: ='YTD P&L'!I14-'YTD P&L'!H14 | L14: ='YTD P&L'!J14-'YTD P&L'!I14 | M14: ='ANNL P&L'!E14-'YTD P&L'!J14 | N14: ='YTD P&L'!K14 | O14: ='YTD P&L'!L14-'YTD P&L'!K14 | P14: ='YTD P&L'!M14-'YTD P&L'!L14 | Q14: ='ANNL P&L'!F14-'YTD P&L'!M14 | R14: ='YTD P&L'!N14 | S14: ='IS DRIVERS'!S10 | T14: ='IS DRIVERS'!T10 | U14: ='IS DRIVERS'!U10 | V14: ='IS DRIVERS'!V10 | W14: ='IS DRIVERS'!W10 | X14: ='IS DRIVERS'!X10 | Y14: ='IS DRIVERS'!Y10 | Z14: ='IS DRIVERS'!Z10 | ... AK14: ='IS DRIVERS'!AK10
A15: Net Income (Loss) Less NCI | B15: ='YTD P&L'!B15 | C15: ='YTD P&L'!C15-'YTD P&L'!B15 | D15: ='YTD P&L'!D15-'YTD P&L'!C15 | E15: ='ANNL P&L'!C15-'YTD P&L'!D15 | F15: ='YTD P&L'!E15 | G15: ='YTD P&L'!F15-'YTD P&L'!E15 | H15: ='YTD P&L'!G15-'YTD P&L'!F15 | I15: ='ANNL P&L'!D15-'YTD P&L'!G15 | J15: ='YTD P&L'!H15 | K15: ='YTD P&L'!I15-'YTD P&L'!H15 | L15: ='YTD P&L'!J15-'YTD P&L'!I15 | M15: ='ANNL P&L'!E15-'YTD P&L'!J15 | N15: ='YTD P&L'!K15 | O15: ='YTD P&L'!L15-'YTD P&L'!K15 | P15: ='YTD P&L'!M15-'YTD P&L'!L15 | Q15: ='ANNL P&L'!F15-'YTD P&L'!M15 | R15: ='YTD P&L'!N15
A16: Basic Earnings (Loss) per Share
A17: Diluted Earnings (Loss) per Share
A18: Weighted Average Shares Outstanding (Basic)
A19: Weighted Average Shares Outstanding (Diluted)

Sheet QTR BS
B1: Q4 FY2022 | C1: Q1 FY2023 | D1: Q2 FY2023 | E1: Q3 FY2023 | F1: Q4 FY2023 | G1: Q1 FY2024 | H1: Q2 FY2024 | I1: Q3 FY2024 | J1: Q4 FY2024 | K1: Q1 FY2025 | L1: Q2 FY2025 | M1: Q3 FY2025 | N1: Q4 FY2025 | O1: Q1 FY2026 | P1: Q2 FY2026E | Q1: Q3 FY2026E | R1: Q4 FY2026E | S1: Q1 FY2027E | T1: Q2 FY2027E | U1: Q3 FY2027E | V1: Q4 FY2027E | W1: Q1 FY2028E | X1: Q2 FY2028E | Y1: Q3 FY2028E | Z1: Q4 FY2028E | AA1: Q1 FY2029E | AB1: Q2 FY2029E | AC1: Q3 FY2029E | AD1: Q4 FY2029E | AE1: Q1 FY2030E | AF1: Q2 FY2030E | AG1: Q3 FY2030E | AH1: Q4 FY2030E
A2: Cash & Cash Equivalents | B2: ='BALANCE SHEET'!B2 | C2: ='YTD BS'!C2 | D2: ='YTD BS'!D2 | E2: ='YTD BS'!E2 | F2: ='BALANCE SHEET'!C2 | G2: ='YTD BS'!G2 | H2: ='YTD BS'!H2 | I2: ='YTD BS'!I2 | J2: ='BALANCE SHEET'!D2 | K2: ='YTD BS'!K2 | L2: ='YTD BS'!L2 | M2: ='YTD BS'!M2 | N2: ='BALANCE SHEET'!E2 | O2: ='YTD BS'!O2 | P2: ='BS DRIVERS'!P2 | Q2: ='BS DRIVERS'!Q2 | R2: ='BS DRIVERS'!R2 | S2: ='BS DRIVERS'!S2 | T2: ='BS DRIVERS'!T2 | U2: ='BS DRIVERS'!U2 | V2: ='BS DRIVERS'!V2 | W2: ='BS DRIVERS'!W2 | ... AH2: ='BS DRIVERS'!AH2
A3: Short-Term Investments | B3: ='BALANCE SHEET'!B3 | C3: ='YTD BS'!C3 | D3: ='YTD BS'!D3 | E3: ='YTD BS'!E3 | F3: ='BALANCE SHEET'!C3 | G3: ='YTD BS'!G3 | H3: ='YTD BS'!H3 | I3: ='YTD BS'!I3 | J3: ='BALANCE SHEET'!D3 | K3: ='YTD BS'!K3 | L3: ='YTD BS'!L3 | M3: ='YTD BS'!M3 | N3: ='BALANCE SHEET'!E3 | O3: ='YTD BS'!O3 | P3: ='BS DRIVERS'!P3 | Q3: ='BS DRIVERS'!Q3 | R3: ='BS DRIVERS'!R3 | S3: ='BS DRIVERS'!S3 | T3: ='BS DRIVERS'!T3 | U3: ='BS DRIVERS'!U3 | V3: ='BS DRIVERS'!V3 | W3: ='BS DRIVERS'!W3 | ... AH3: ='BS DRIVERS'!AH3
A4: Accounts Receivable | B4: ='BALANCE SHEET'!B4 | C4: ='YTD BS'!C4 | D4: ='YTD BS'!D4 | E4: ='YTD BS'!E4 | F4: ='BALANCE SHEET'!C4 | G4: ='YTD BS'!G4 | H4: ='YTD BS'!H4 | I4: ='YTD BS'!I4 | J4: ='BALANCE SHEET'!D4 | K4: ='YTD BS'!K4 | L4: ='YTD BS'!L4 | M4: ='YTD BS'!M4 | N4: ='BALANCE SHEET'!E4 | O4: ='YTD BS'!O4 | P4: ='QTR P&L'!S2*'BS DRIVERS'!P4/ASSUMPTIONS!$B$2 | Q4: ='QTR P&L'!T2*'BS DRIVERS'!Q4/ASSUMPTIONS!$B$2 | R4: ='QTR P&L'!U2*'BS DRIVERS'!R4/ASSUMPTIONS!$B$2 | S4: ='QTR P&L'!V2*'BS DRIVERS'!S4/ASSUMPTIONS!$B$2 | T4: ='QTR P&L'!W2*'BS DRIVERS'!T4/ASSUMPTIONS!$B$2 | U4: ='QTR P&L'!X2*'BS DRIVERS'!U4/ASSUMPTIONS!$B$2 | V4: ='QTR P&L'!Y2*'BS DRIVERS'!V4/ASSUMPTIONS!$B$2 | W4: ='QTR P&L'!Z2*'BS DRIVERS'!W4/ASSUMPTIONS!$B$2 | ... AH4: ='QTR P&L'!AK2*'BS DRIVERS'!AH4/ASSUMPTIONS!$B$2
A5: Inventories | B5: ='BALANCE SHEET'!B5 | C5: ='YTD BS'!C5 | D5: ='YTD BS'!D5 | E5: ='YTD BS'!E5 | F5: ='BALANCE SHEET'!C5 | G5: ='YTD BS'!G5 | H5: ='YTD BS'!H5 | I5: ='YTD BS'!I5 | J5: ='BALANCE SHEET'!D5 | K5: ='YTD BS'!K5 | L5: ='YTD BS'!L5 | M5: ='YTD BS'!M5 | N5: ='BALANCE SHEET'!E5 | O5: ='YTD BS'!O5 | P5: ='QTR P&L'!S3*'BS DRIVERS'!P5/ASSUMPTIONS!$B$2 | Q5: ='QTR P&L'!T3*'BS DRIVERS'!Q5/ASSUMPTIONS!$B$2 | R5: ='QTR P&L'!U3*'BS DRIVERS'!R5/ASSUMPTIONS!$B$2 | S5: ='QTR P&L'!V3*'BS DRIVERS'!S5/ASSUMPTIONS!$B$2 | T5: ='QTR P&L'!W3*'BS DRIVERS'!T5/ASSUMPTIONS!$B$2 | U5: ='QTR P&L'!X3*'BS DRIVERS'!U5/ASSUMPTIONS!$B$2 | V5: ='QTR P&L'!Y3*'BS DRIVERS'!V5/ASSUMPTIONS!$B$2 | W5: ='QTR P&L'!Z3*'BS DRIVERS'!W5/ASSUMPTIONS!$B$2 | ... AH5: ='QTR P&L'!AK3*'BS DRIVERS'!AH5/ASSUMPTIONS!$B$2
A6: Prepaid Expenses | B6: ='BALANCE SHEET'!B6 | C6: ='YTD BS'!C6 | D6: ='YTD BS'!D6 | E6: ='YTD BS'!E6 | F6: ='BALANCE SHEET'!C6 | G6: ='YTD BS'!G6 | H6: ='YTD BS'!H6 | I6: ='YTD BS'!I6 | J6: ='BALANCE SHEET'!D6 | K6: ='YTD BS'!K6 | L6: ='YTD BS'!L6 | M6: ='YTD BS'!M6 | N6: ='BALANCE SHEET'!E6 | O6: ='YTD BS'!O6 | P6: ='QTR P&L'!S2*'BS DRIVERS'!P6 | Q6: ='QTR P&L'!T2*'BS DRIVERS'!Q6 | R6: ='QTR P&L'!U2*'BS DRIVERS'!R6 | S6: ='QTR P&L'!V2*'BS DRIVERS'!S6 | T6: ='QTR P&L'!W2*'BS DRIVERS'!T6 | U6: ='QTR P&L'!X2*'BS DRIVERS'!U6 | V6: ='QTR P&L'!Y2*'BS DRIVERS'!V6 | W6: ='QTR P&L'!Z2*'BS DRIVERS'!W6 | ... AH6: ='QTR P&L'!AK2*'BS DRIVERS'!AH6
A7: Total Current Assets | B7: ='BALANCE SHEET'!B7 | C7: ='YTD BS'!C7 | D7: ='YTD BS'!D7 | E7: ='YTD BS'!E7 | F7: ='BALANCE SHEET'!C7 | G7: ='YTD BS'!G7 | H7: ='YTD BS'!H7 | I7: ='YTD BS'!I7 | J7: ='BALANCE SHEET'!D7 | K7: ='YTD BS'!K7 | L7: ='YTD BS'!L7 | M7: ='YTD BS'!M7 | N7: ='BALANCE SHEET'!E7 | O7: ='YTD BS'!O7 | P7: =SUM(P2:P6) | Q7: =SUM(Q2:Q6) | R7: =SUM(R2:R6) | S7: =SUM(S2:S6) | T7: =SUM(T2:T6) | U7: =SUM(U2:U6) | V7: =SUM(V2:V6) | W7: =SUM(W2:W6) | ... AH7: =SUM(AH2:AH6)
A8: Net PP&E | B8: ='BALANCE SHEET'!B8 | C8: ='YTD BS'!C8 | D8: ='YTD BS'!D8 | E8: ='YTD BS'!E8 | F8: ='BALANCE SHEET'!C8 | G8: ='YTD BS'!G8 | H8: ='YTD BS'!H8 | I8: ='YTD BS'!I8 | J8: ='BALANCE SHEET'!D8 | K8: ='YTD BS'!K8 | L8: ='YTD BS'!L8 | M8: ='YTD BS'!M8 | N8: ='BALANCE SHEET'!E8 | O8: ='YTD BS'!O8 | P8: ='BS DRIVERS'!P7 | Q8: ='BS DRIVERS'!Q7 | R8: ='BS DRIVERS'!R7 | S8: ='BS DRIVERS'!S7 | T8: ='BS DRIVERS'!T7 | U8: ='BS DRIVERS'!U7 | V8: ='BS DRIVERS'!V7 | W8: ='BS DRIVERS'!W7 | ... AH8: ='BS DRIVERS'!AH7
A9: Intangible Assets | B9: ='BALANCE SHEET'!B9 | C9: ='YTD BS'!C9 | D9: ='YTD BS'!D9 | E9: ='YTD BS'!E9 | F9: ='BALANCE SHEET'!C9 | G9: ='YTD BS'!G9 | H9: ='YTD BS'!H9 | I9: ='YTD BS'!I9 | J9: ='BALANCE SHEET'!D9 | K9: ='YTD BS'!K9 | L9: ='YTD BS'!L9 | M9: ='YTD BS'!M9 | N9: ='BALANCE SHEET'!E9 | O9: ='YTD BS'!O9 | P9: ='BS DRIVERS'!P8 | Q9: ='BS DRIVERS'!Q8 | R9: ='BS DRIVERS'!R8 | S9: ='BS DRIVERS'!S8 | T9: ='BS DRIVERS'!T8 | U9: ='BS DRIVERS'!U8 | V9: ='BS DRIVERS'!V8 | W9: ='BS DRIVERS'!W8 | ... AH9: ='BS DRIVERS'!AH8
A10: Goodwill | B10: ='BALANCE SHEET'!B10 | C10: ='YTD BS'!C10 | D10: ='YTD BS'!D10 | E10: ='YTD BS'!E10 | F10: ='BALANCE SHEET'!C10 | G10: ='YTD BS'!G10 | H10: ='YTD BS'!H10 | I10: ='YTD BS'!I10 | J10: ='BALANCE SHEET'!D10 | K10: ='YTD BS'!K10 | L10: ='YTD BS'!L10 | M10: ='YTD BS'!M10 | N10: ='BALANCE SHEET'!E10 | O10: ='YTD BS'!O10 | P10: ='BS DRIVERS'!P9 | Q10: ='BS DRIVERS'!Q9 | R10: ='BS DRIVERS'!R9 | S10: ='BS DRIVERS'!S9 | T10: ='BS DRIVERS'!T9 | U10: ='BS DRIVERS'!U9 | V10: ='BS DRIVERS'!V9 | W10: ='BS DRIVERS'!W9 | ... AH10: ='BS DRIVERS'!AH9
A11: Equity Method Investments | B11: ='BALANCE SHEET'!B11 | C11: ='YTD BS'!C11 | D11: ='YTD BS'!D11 | E11: ='YTD BS'!E11 | F11: ='BALANCE SHEET'!C11 | G11: ='YTD BS'!G11 | H11: ='YTD BS'!H11 | I11: ='YTD BS'!I11 | J11: ='BALANCE SHEET'!D11 | K11: ='YTD BS'!K11 | L11: ='YTD BS'!L11 | M11: ='YTD BS'!M11 | N11: ='BALANCE SHEET'!E11 | O11: ='YTD BS'!O11 | P11: ='BS DRIVERS'!P10 | Q11: ='BS DRIVERS'!Q10 | R11: ='BS DRIVERS'!R10 | S11: ='BS DRIVERS'!S10 | T11: ='BS DRIVERS'!T10 | U11: ='BS DRIVERS'!U10 | V11: ='BS DRIVERS'!V10 | W11: ='BS DRIVERS'!W10 | ... AH11: ='BS DRIVERS'!AH10
A12: Deferred Tax Assets | B12: ='BALANCE SHEET'!B12 | C12: ='YTD BS'!C12 | D12: ='YTD BS'!D12 | E12: ='YTD BS'!E12 | F12: ='BALANCE SHEET'!C12 | G12: ='YTD BS'!G12 | H12: ='YTD BS'!H12 | I12: ='YTD BS'!I12 | J12: ='BALANCE SHEET'!D12 | K12: ='YTD BS'!K12 | L12: ='YTD BS'!L12 | M12: ='YTD BS'!M12 | N12: ='BALANCE SHEET'!E12 | O12: ='YTD BS'!O12 | P12: ='BS DRIVERS'!P11 | Q12: ='BS DRIVERS'!Q11 | R12: ='BS DRIVERS'!R11 | S12: ='BS DRIVERS'!S11 | T12: ='BS DRIVERS'!T11 | U12: ='BS DRIVERS'!U11 | V12: ='BS DRIVERS'!V11 | W12: ='BS DRIVERS'!W11 | ... AH12: ='BS DRIVERS'!AH11
A13: Other Non-Current Assets | B13: ='BALANCE SHEET'!B13 | C13: ='YTD BS'!C13 | D13: ='YTD BS'!D13 | E13: ='YTD BS'!E13 | F13: ='BALANCE SHEET'!C13 | G13: ='YTD BS'!G13 | H13: ='YTD BS'!H13 | I13: ='YTD BS'!I13 | J13: ='BALANCE SHEET'!D13 | K13: ='YTD BS'!K13 | L13: ='YTD BS'!L13 | M13: ='YTD BS'!M13 | N13: ='BALANCE SHEET'!E13 | O13: ='YTD BS'!O13 | P13: ='QTR P&L'!S2*'BS DRIVERS'!P12 | Q13: ='QTR P&L'!T2*'BS DRIVERS'!Q12 | R13: ='QTR P&L'!U2*'BS DRIVERS'!R12 | S13: ='QTR P&L'!V2*'BS DRIVERS'!S12 | T13: ='QTR P&L'!W2*'BS DRIVERS'!T12 | U13: ='QTR P&L'!X2*'BS DRIVERS'!U12 | V13: ='QTR P&L'!Y2*'BS DRIVERS'!V12 | W13: ='QTR P&L'!Z2*'BS DRIVERS'!W12 | ... AH13: ='QTR P&L'!AK2*'BS DRIVERS'!AH12
A14: Total Assets | B14: ='BALANCE SHEET'!B14 | C14: ='YTD BS'!C14 | D14: ='YTD BS'!D14 | E14: ='YTD BS'!E14 | F14: ='BALANCE SHEET'!C14 | G14: ='YTD BS'!G14 | H14: ='YTD BS'!H14 | I14: ='YTD BS'!I14 | J14: ='BALANCE SHEET'!D14 | K14: ='YTD BS'!K14 | L14: ='YTD BS'!L14 | M14: ='YTD BS'!M14 | N14: ='BALANCE SHEET'!E14 | O14: ='YTD BS'!O14 | P14: =P7+SUM(P8:P13) | Q14: =Q7+SUM(Q8:Q13) | R14: =R7+SUM(R8:R13) | S14: =S7+SUM(S8:S13) | T14: =T7+SUM(T8:T13) | U14: =U7+SUM(U8:U13) | V14: =V7+SUM(V8:V13) | W14: =W7+SUM(W8:W13) | ... AH14: =AH7+SUM(AH8:AH13)
A15: Short-Term Debt Obligations | B15: ='BALANCE SHEET'!B15 | C15: ='YTD BS'!C15 | D15: ='YTD BS'!D15 | E15: ='YTD BS'!E15 | F15: ='BALANCE SHEET'!C15 | G15: ='YTD BS'!G15 | H15: ='YTD BS'!H15 | I15: ='YTD BS'!I15 | J15: ='BALANCE SHEET'!D15 | K15: ='YTD BS'!K15 | L15: ='YTD BS'!L15 | M15: ='YTD BS'!M15 | N15: ='BALANCE SHEET'!E15 | O15: ='YTD BS'!O15 | P15: ='BS DRIVERS'!P13 | Q15: ='BS DRIVERS'!Q13 | R15: ='BS DRIVERS'!R13 | S15: ='BS DRIVERS'!S13 | T15: ='BS DRIVERS'!T13 | U15: ='BS DRIVERS'!U13 | V15: ='BS DRIVERS'!V13 | W15: ='BS DRIVERS'!W13 | ... AH15: ='BS DRIVERS'!AH13
A16: Accrued Expenses | B16: ='BALANCE SHEET'!B16 | C16: ='YTD BS'!C16 | D16: ='YTD BS'!D16 | E16: ='YTD BS'!E16 | F16: ='BALANCE SHEET'!C16 | G16: ='YTD BS'!G16 | H16: ='YTD BS'!H16 | I16: ='YTD BS'!I16 | J16: ='BALANCE SHEET'!D16 | K16: ='YTD BS'!K16 | L16: ='YTD BS'!L16 | M16: ='YTD BS'!M16 | N16: ='BALANCE SHEET'!E16 | O16: ='YTD BS'!O16 | P16: ='QTR P&L'!S2*'BS DRIVERS'!P14 | Q16: ='QTR P&L'!T2*'BS DRIVERS'!Q14 | R16: ='QTR P&L'!U2*'BS DRIVERS'!R14 | S16: ='QTR P&L'!V2*'BS DRIVERS'!S14 | T16: ='QTR P&L'!W2*'BS DRIVERS'!T14 | U16: ='QTR P&L'!X2*'BS DRIVERS'!U14 | V16: ='QTR P&L'!Y2*'BS DRIVERS'!V14 | W16: ='QTR P&L'!Z2*'BS DRIVERS'!W14 | ... AH16: ='QTR P&L'!AK2*'BS DRIVERS'!AH14
A17: Total Current Liabilities | B17: ='BALANCE SHEET'!B17 | C17: ='YTD BS'!C17 | D17: ='YTD BS'!D17 | E17: ='YTD BS'!E17 | F17: ='BALANCE SHEET'!C17 | G17: ='YTD BS'!G17 | H17: ='YTD BS'!H17 | I17: ='YTD BS'!I17 | J17: ='BALANCE SHEET'!D17 | K17: ='YTD BS'!K17 | L17: ='YTD BS'!L17 | M17: ='YTD BS'!M17 | N17: ='BALANCE SHEET'!E17 | O17: ='YTD BS'!O17 | P17: =SUM(P15:P16) | Q17: =SUM(Q15:Q16) | R17: =SUM(R15:R16) | S17: =SUM(S15:S16) | T17: =SUM(T15:T16) | U17: =SUM(U15:U16) | V17: =SUM(V15:V16) | W17: =SUM(W15:W16) | ... AH17: =SUM(AH15:AH16)
A18: Long-Term Debt | B18: ='BALANCE SHEET'!B18 | C18: ='YTD BS'!C18 | D18: ='YTD BS'!D18 | E18: ='YTD BS'!E18 | F18: ='BALANCE SHEET'!C18 | G18: ='YTD BS'!G18 | H18: ='YTD BS'!H18 | I18: ='YTD BS'!I18 | J18: ='BALANCE SHEET'!D18 | K18: ='YTD BS'!K18 | L18: ='YTD BS'!L18 | M18: ='YTD BS'!M18 | N18: ='BALANCE SHEET'!E18 | O18: ='YTD BS'!O18 | P18: ='BS DRIVERS'!P15 | Q18: ='BS DRIVERS'!Q15 | R18: ='BS DRIVERS'!R15 | S18: ='BS DRIVERS'!S15 | T18: ='BS DRIVERS'!T15 | U18: ='BS DRIVERS'!U15 | V18: ='BS DRIVERS'!V15 | W18: ='BS DRIVERS'!W15 | ... AH18: ='BS DRIVERS'!AH15
A19: Deferred Tax Liability | B19: ='BALANCE SHEET'!B19 | C19: ='YTD BS'!C19 | D19: ='YTD BS'!D19 | E19: ='YTD BS'!E19 | F19: ='BALANCE SHEET'!C19 | G19: ='YTD BS'!G19 | H19: ='YTD BS'!H19 | I19: ='YTD BS'!I19 | J19: ='BALANCE SHEET'!D19 | K19: ='YTD BS'!K19 | L19: ='YTD BS'!L19 | M19: ='YTD BS'!M19 | N19: ='BALANCE SHEET'!E19 | O19: ='YTD BS'!O19 | P19: ='BS DRIVERS'!P16 | Q19: ='BS DRIVERS'!Q16 | R19: ='BS DRIVERS'!R16 | S19: ='BS DRIVERS'!S16 | T19: ='BS DRIVERS'!T16 | U19: ='BS DRIVERS'!U16 | V19: ='BS DRIVERS'!V16 | W19: ='BS DRIVERS'!W16 | ... AH19: ='BS DRIVERS'!AH16
A20: Other Non-Current Liabilities | B20: ='BALANCE SHEET'!B20 | C20: ='YTD BS'!C20 | D20: ='YTD BS'!D20 | E20: ='YTD BS'!E20 | F20: ='BALANCE SHEET'!C20 | G20: ='YTD BS'!G20 | H20: ='YTD BS'!H20 | I20: ='YTD BS'!I20 | J20: ='BALANCE SHEET'!D20 | K20: ='YTD BS'!K20 | L20: ='YTD BS'!L20 | M20: ='YTD BS'!M20 | N20: ='BALANCE SHEET'!E20 | O20: ='YTD BS'!O20 | P20: ='QTR P&L'!S2*'BS DRIVERS'!P17 | Q20: ='QTR P&L'!T2*'BS DRIVERS'!Q17 | R20: ='QTR P&L'!U2*'BS DRIVERS'!R17 | S20: ='QTR P&L'!V2*'BS DRIVERS'!S17 | T20: ='QTR P&L'!W2*'BS DRIVERS'!T17 | U20: ='QTR P&L'!X2*'BS DRIVERS'!U17 | V20: ='QTR P&L'!Y2*'BS DRIVERS'!V17 | W20: ='QTR P&L'!Z2*'BS DRIVERS'!W17 | ... AH20: ='QTR P&L'!AK2*'BS DRIVERS'!AH17
A21: Total Liabilities | B21: ='BALANCE SHEET'!B21 | C21: ='YTD BS'!C21 | D21: ='YTD BS'!D21 | E21: ='YTD BS'!E21 | F21: ='BALANCE SHEET'!C21 | G21: ='YTD BS'!G21 | H21: ='YTD BS'!H21 | I21: ='YTD BS'!I21 | J21: ='BALANCE SHEET'!D21 | K21: ='YTD BS'!K21 | L21: ='YTD BS'!L21 | M21: ='YTD BS'!M21 | N21: ='BALANCE SHEET'!E21 | O21: ='YTD BS'!O21 | P21: =P17+SUM(P18:P20) | Q21: =Q17+SUM(Q18:Q20) | R21: =R17+SUM(R18:R20) | S21: =S17+SUM(S18:S20) | T21: =T17+SUM(T18:T20) | U21: =U17+SUM(U18:U20) | V21: =V17+SUM(V18:V20) | W21: =W17+SUM(W18:W20) | ... AH21: =AH17+SUM(AH18:AH20)
A22: Common Stock | B22: ='BALANCE SHEET'!B22 | C22: ='YTD BS'!C22 | D22: ='YTD BS'!D22 | E22: ='YTD BS'!E22 | F22: ='BALANCE SHEET'!C22 | G22: ='YTD BS'!G22 | H22: ='YTD BS'!H22 | I22: ='YTD BS'!I22 | J22: ='BALANCE SHEET'!D22 | K22: ='YTD BS'!K22 | L22: ='YTD BS'!L22 | M22: ='YTD BS'!M22 | N22: ='BALANCE SHEET'!E22 | O22: ='YTD BS'!O22 | P22: ='BS DRIVERS'!P18 | Q22: ='BS DRIVERS'!Q18 | R22: ='BS DRIVERS'!R18 | S22: ='BS DRIVERS'!S18 | T22: ='BS DRIVERS'!T18 | U22: ='BS DRIVERS'!U18 | V22: ='BS DRIVERS'!V18 | W22: ='BS DRIVERS'!W18 | ... AH22: ='BS DRIVERS'!AH18
A23: Additional Paid-in Capital | B23: ='BALANCE SHEET'!B23 | C23: ='YTD BS'!C23 | D23: ='YTD BS'!D23 | E23: ='YTD BS'!E23 | F23: ='BALANCE SHEET'!C23 | G23: ='YTD BS'!G23 | H23: ='YTD BS'!H23 | I23: ='YTD BS'!I23 | J23: ='BALANCE SHEET'!D23 | K23: ='YTD BS'!K23 | L23: ='YTD BS'!L23 | M23: ='YTD BS'!M23 | N23: ='BALANCE SHEET'!E23 | O23: ='YTD BS'!O23 | P23: ='BS DRIVERS'!P19 | Q23: ='BS DRIVERS'!Q19 | R23: ='BS DRIVERS'!R19 | S23: ='BS DRIVERS'!S19 | T23: ='BS DRIVERS'!T19 | U23: ='BS DRIVERS'!U19 | V23: ='BS DRIVERS'!V19 | W23: ='BS DRIVERS'!W19 | ... AH23: ='BS DRIVERS'!AH19
A24: Retained Earnings (Accumulated Deficit) | B24: ='BALANCE SHEET'!B24 | C24: ='YTD BS'!C24 | D24: ='YTD BS'!D24 | E24: ='YTD BS'!E24 | F24: ='BALANCE SHEET'!C24 | G24: ='YTD BS'!G24 | H24: ='YTD BS'!H24 | I24: ='YTD BS'!I24 | J24: ='BALANCE SHEET'!D24 | K24: ='YTD BS'!K24 | L24: ='YTD BS'!L24 | M24: ='YTD BS'!M24 | N24: ='BALANCE SHEET'!E24 | O24: ='YTD BS'!O24 | P24: ='BS DRIVERS'!P20 | Q24: ='BS DRIVERS'!Q20 | R24: ='BS DRIVERS'!R20 | S24: ='BS DRIVERS'!S20 | T24: ='BS DRIVERS'!T20 | U24: ='BS DRIVERS'!U20 | V24: ='BS DRIVERS'!V20 | W24: ='BS DRIVERS'!W20 | ... AH24: ='BS DRIVERS'!AH20
A25: Accumulated Other Comprehensive Income (Loss) | B25: ='BALANCE SHEET'!B25 | C25: ='YTD BS'!C25 | D25: ='YTD BS'!D25 | E25: ='YTD BS'!E25 | F25: ='BALANCE SHEET'!C25 | G25: ='YTD BS'!G25 | H25: ='YTD BS'!H25 | I25: ='YTD BS'!I25 | J25: ='BALANCE SHEET'!D25 | K25: ='YTD BS'!K25 | L25: ='YTD BS'!L25 | M25: ='YTD BS'!M25 | N25: ='BALANCE SHEET'!E25 | O25: ='YTD BS'!O25 | P25: ='BS DRIVERS'!P21 | Q25: ='BS DRIVERS'!Q21 | R25: ='BS DRIVERS'!R21 | S25: ='BS DRIVERS'!S21 | T25: ='BS DRIVERS'!T21 | U25: ='BS DRIVERS'!U21 | V25: ='BS DRIVERS'!V21 | W25: ='BS DRIVERS'!W21 | ... AH25: ='BS DRIVERS'!AH21
A26: Treasury Stock | B26: ='BALANCE SHEET'!B26 | C26: ='YTD BS'!C26 | D26: ='YTD BS'!D26 | E26: ='YTD BS'!E26 | F26: ='BALANCE SHEET'!C26 | G26: ='YTD BS'!G26 | H26: ='YTD BS'!H26 | I26: ='YTD BS'!I26 | J26: ='BALANCE SHEET'!D26 | K26: ='YTD BS'!K26 | L26: ='YTD BS'!L26 | M26: ='YTD BS'!M26 | N26: ='BALANCE SHEET'!E26 | O26: ='YTD BS'!O26 | P26: ='BS DRIVERS'!P22 | Q26: ='BS DRIVERS'!Q22 | R26: ='BS DRIVERS'!R22 | S26: ='BS DRIVERS'!S22 | T26: ='BS DRIVERS'!T22 | U26: ='BS DRIVERS'!U22 | V26: ='BS DRIVERS'!V22 | W26: ='BS DRIVERS'!W22 | ... AH26: ='BS DRIVERS'!AH22
A27: Noncontrolling Interest | B27: ='BALANCE SHEET'!B27 | C27: ='YTD BS'!C27 | D27: ='YTD BS'!D27 | E27: ='YTD BS'!E27 | F27: ='BALANCE SHEET'!C27 | G27: ='YTD BS'!G27 | H27: ='YTD BS'!H27 | I27: ='YTD BS'!I27 | J27: ='BALANCE SHEET'!D27 | K27: ='YTD BS'!K27 | L27: ='YTD BS'!L27 | M27: ='YTD BS'!M27 | N27: ='BALANCE SHEET'!E27 | O27: ='YTD BS'!O27 | P27: ='BS DRIVERS'!P23 | Q27: ='BS DRIVERS'!Q23 | R27: ='BS DRIVERS'!R23 | S27: ='BS DRIVERS'!S23 | T27: ='BS DRIVERS'!T23 | U27: ='BS DRIVERS'!U23 | V27: ='BS DRIVERS'!V23 | W27: ='BS DRIVERS'!W23 | ... AH27: ='BS DRIVERS'!AH23
A28: Total Stockholders' Equity | B28: ='BALANCE SHEET'!B28 | C28: ='YTD BS'!C28 | D28: ='YTD BS'!D28 | E28: ='YTD BS'!E28 | F28: ='BALANCE SHEET'!C28 | G28: ='YTD BS'!G28 | H28: ='YTD BS'!H28 | I28: ='YTD BS'!I28 | J28: ='BALANCE SHEET'!D28 | K28: ='YTD BS'!K28 | L28: ='YTD BS'!L28 | M28: ='YTD BS'!M28 | N28: ='BALANCE SHEET'!E28 | O28: ='YTD BS'!O28 | P28: =SUM(P22:P27) | Q28: =SUM(Q22:Q27) | R28: =SUM(R22:R27) | S28: =SUM(S22:S27) | T28: =SUM(T22:T27) | U28: =SUM(U22:U27) | V28: =SUM(V22:V27) | W28: =SUM(W22:W27) | ... AH28: =SUM(AH22:AH27)
A29: Total Liabilities, Mezzanine & Stockholders' Equity | B29: ='BALANCE SHEET'!B29 | C29: ='YTD BS'!C29 | D29: ='YTD BS'!D29 | E29: ='YTD BS'!E29 | F29: ='BALANCE SHEET'!C29 | G29: ='YTD BS'!G29 | H29: ='YTD BS'!H29 | I29: ='YTD BS'!I29 | J29: ='BALANCE SHEET'!D29 | K29: ='YTD BS'!K29 | L29: ='YTD BS'!L29 | M29: ='YTD BS'!M29 | N29: ='BALANCE SHEET'!E29 | O29: ='YTD BS'!O29 | P29: =P21+P28 | Q29: =Q21+Q28 | R29: =R21+R28 | S29: =S21+S28 | T29: =T21+T28 | U29: =U21+U28 | V29: =V21+V28 | W29: =W21+W28 | ... AH29: =AH21+AH28

Sheet QTR CF
B1: Q1 FY2022 | C1: Q2 FY2022 | D1: Q3 FY2022 | E1: Q4 FY2022 | F1: Q1 FY2023 | G1: Q2 FY2023 | H1: Q3 FY2023 | I1: Q4 FY2023 | J1: Q1 FY2024 | K1: Q2 FY2024 | L1: Q3 FY2024 | M1: Q4 FY2024 | N1: Q1 FY2025 | O1: Q2 FY2025 | P1: Q3 FY2025 | Q1: Q4 FY2025 | R1: Q1 FY2026 | S1: Q2 FY2026E | T1: Q3 FY2026E | U1: Q4 FY2026E | V1: Q1 FY2027E | W1: Q2 FY2027E | X1: Q3 FY2027E | Y1: Q4 FY2027E | Z1: Q1 FY2028E | AA1: Q2 FY2028E | AB1: Q3 FY2028E | AC1: Q4 FY2028E | AD1: Q1 FY2029E | AE1: Q2 FY2029E | AF1: Q3 FY2029E | AG1: Q4 FY2029E | AH1: Q1 FY2030E | AI1: Q2 FY2030E | AJ1: Q3 FY2030E | AK1: Q4 FY2030E
A2: Net Income (Loss) | B2: ='YTD CF'!B2 | C2: ='YTD CF'!C2-'YTD CF'!B2 | D2: ='YTD CF'!D2-'YTD CF'!C2 | E2: ='CASH FLOW'!C2-'YTD CF'!D2 | F2: ='YTD CF'!E2 | G2: ='YTD CF'!F2-'YTD CF'!E2 | H2: ='YTD CF'!G2-'YTD CF'!F2 | I2: ='CASH FLOW'!D2-'YTD CF'!G2 | J2: ='YTD CF'!H2 | K2: ='YTD CF'!I2-'YTD CF'!H2 | L2: ='YTD CF'!J2-'YTD CF'!I2 | M2: ='CASH FLOW'!E2-'YTD CF'!J2 | N2: ='YTD CF'!K2 | O2: ='YTD CF'!L2-'YTD CF'!K2 | P2: ='YTD CF'!M2-'YTD CF'!L2 | Q2: ='CASH FLOW'!F2-'YTD CF'!M2 | R2: ='YTD CF'!N2 | S2: ='CF DRIVERS'!S2 | T2: ='CF DRIVERS'!T2 | U2: ='CF DRIVERS'!U2 | V2: ='CF DRIVERS'!V2 | W2: ='CF DRIVERS'!W2 | X2: ='CF DRIVERS'!X2 | Y2: ='CF DRIVERS'!Y2 | Z2: ='CF DRIVERS'!Z2 | ... AK2: ='CF DRIVERS'!AK2
A3: Depreciation & Amortization | B3: ='YTD CF'!B3 | C3: ='YTD CF'!C3-'YTD CF'!B3 | D3: ='YTD CF'!D3-'YTD CF'!C3 | E3: ='CASH FLOW'!C3-'YTD CF'!D3 | F3: ='YTD CF'!E3 | G3: ='YTD CF'!F3-'YTD CF'!E3 | H3: ='YTD CF'!G3-'YTD CF'!F3 | I3: ='CASH FLOW'!D3-'YTD CF'!G3 | J3: ='YTD CF'!H3 | K3: ='YTD CF'!I3-'YTD CF'!H3 | L3: ='YTD CF'!J3-'YTD CF'!I3 | M3: ='CASH FLOW'!E3-'YTD CF'!J3 | N3: ='YTD CF'!K3 | O3: ='YTD CF'!L3-'YTD CF'!K3 | P3: ='YTD CF'!M3-'YTD CF'!L3 | Q3: ='CASH FLOW'!F3-'YTD CF'!M3 | R3: ='YTD CF'!N3 | S3: ='QTR P&L'!S2*'CF DRIVERS'!S3 | T3: ='QTR P&L'!T2*'CF DRIVERS'!T3 | U3: ='QTR P&L'!U2*'CF DRIVERS'!U3 | V3: ='QTR P&L'!V2*'CF DRIVERS'!V3 | W3: ='QTR P&L'!W2*'CF DRIVERS'!W3 | X3: ='QTR P&L'!X2*'CF DRIVERS'!X3 | Y3: ='QTR P&L'!Y2*'CF DRIVERS'!Y3 | Z3: ='QTR P&L'!Z2*'CF DRIVERS'!Z3 | ... AK3: ='QTR P&L'!AK2*'CF DRIVERS'!AK3
A4: Gain on Juice Transaction | B4: ='YTD CF'!B4 | C4: ='YTD CF'!C4-'YTD CF'!B4 | D4: ='YTD CF'!D4-'YTD CF'!C4 | E4: ='CASH FLOW'!C4-'YTD CF'!D4 | F4: ='YTD CF'!E4 | G4: ='YTD CF'!F4-'YTD CF'!E4 | H4: ='YTD CF'!G4-'YTD CF'!F4 | I4: ='CASH FLOW'!D4-'YTD CF'!G4 | J4: ='YTD CF'!H4 | K4: ='YTD CF'!I4-'YTD CF'!H4 | L4: ='YTD CF'!J4-'YTD CF'!I4 | M4: ='CASH FLOW'!E4-'YTD CF'!J4 | N4: ='YTD CF'!K4 | O4: ='YTD CF'!L4-'YTD CF'!K4 | P4: ='YTD CF'!M4-'YTD CF'!L4 | Q4: ='CASH FLOW'!F4-'YTD CF'!M4 | R4: ='YTD CF'!N4 | S4: ='CF DRIVERS'!S4 | T4: ='CF DRIVERS'!T4 | U4: ='CF DRIVERS'!U4 | V4: ='CF DRIVERS'!V4 | W4: ='CF DRIVERS'!W4 | X4: ='CF DRIVERS'!X4 | Y4: ='CF DRIVERS'!Y4 | Z4: ='CF DRIVERS'!Z4 | ... AK4: ='CF DRIVERS'!AK4
A5: Impairment and Other Charges | B5: ='YTD CF'!B5 | C5: ='YTD CF'!C5-'YTD CF'!B5 | D5: ='YTD CF'!D5-'YTD CF'!C5 | E5: ='CASH FLOW'!C5-'YTD CF'!D5 | F5: ='YTD CF'!E5 | G5: ='YTD CF'!F5-'YTD CF'!E5 | H5: ='YTD CF'!G5-'YTD CF'!F5 | I5: ='CASH FLOW'!D5-'YTD CF'!G5 | J5: ='YTD CF'!H5 | K5: ='YTD CF'!I5-'YTD CF'!H5 | L5: ='YTD CF'!J5-'YTD CF'!I5 | M5: ='CASH FLOW'!E5-'YTD CF'!J5 | N5: ='YTD CF'!K5 | O5: ='YTD CF'!L5-'YTD CF'!K5 | P5: ='YTD CF'!M5-'YTD CF'!L5 | Q5: ='CASH FLOW'!F5-'YTD CF'!M5 | R5: ='YTD CF'!N5 | S5: ='CF DRIVERS'!S5 | T5: ='CF DRIVERS'!T5 | U5: ='CF DRIVERS'!U5 | V5: ='CF DRIVERS'!V5 | W5: ='CF DRIVERS'!W5 | X5: ='CF DRIVERS'!X5 | Y5: ='CF DRIVERS'!Y5 | Z5: ='CF DRIVERS'!Z5 | ... AK5: ='CF DRIVERS'!AK5
A6: Product Recall Impact | B6: ='YTD CF'!B6 | C6: ='YTD CF'!C6-'YTD CF'!B6 | D6: ='YTD CF'!D6-'YTD CF'!C6 | E6: ='CASH FLOW'!C7-'YTD CF'!D6 | F6: ='YTD CF'!E6 | G6: ='YTD CF'!F6-'YTD CF'!E6 | H6: ='YTD CF'!G6-'YTD CF'!F6 | I6: ='CASH FLOW'!D7-'YTD CF'!G6 | J6: ='YTD CF'!H6 | K6: ='YTD CF'!I6-'YTD CF'!H6 | L6: ='YTD CF'!J6-'YTD CF'!I6 | M6: ='CASH FLOW'!E7-'YTD CF'!J6 | N6: ='YTD CF'!K6 | O6: ='YTD CF'!L6-'YTD CF'!K6 | P6: ='YTD CF'!M6-'YTD CF'!L6 | Q6: ='CASH FLOW'!F7-'YTD CF'!M6 | R6: ='YTD CF'!N6 | S6: ='CF DRIVERS'!S6 | T6: ='CF DRIVERS'!T6 | U6: ='CF DRIVERS'!U6 | V6: ='CF DRIVERS'!V6 | W6: ='CF DRIVERS'!W6 | X6: ='CF DRIVERS'!X6 | Y6: ='CF DRIVERS'!Y6 | Z6: ='CF DRIVERS'!Z6 | ... AK6: ='CF DRIVERS'!AK6
A7: Cash Payments for Product Recall | B7: ='YTD CF'!B7 | C7: ='YTD CF'!C7-'YTD CF'!B7 | D7: ='YTD CF'!D7-'YTD CF'!C7 | E7: ='CASH FLOW'!C8-'YTD CF'!D7 | F7: ='YTD CF'!E7 | G7: ='YTD CF'!F7-'YTD CF'!E7 | H7: ='YTD CF'!G7-'YTD CF'!F7 | I7: ='CASH FLOW'!D8-'YTD CF'!G7 | J7: ='YTD CF'!H7 | K7: ='YTD CF'!I7-'YTD CF'!H7 | L7: ='YTD CF'!J7-'YTD CF'!I7 | M7: ='CASH FLOW'!E8-'YTD CF'!J7 | N7: ='YTD CF'!K7 | O7: ='YTD CF'!L7-'YTD CF'!K7 | P7: ='YTD CF'!M7-'YTD CF'!L7 | Q7: ='CASH FLOW'!F8-'YTD CF'!M7 | R7: ='YTD CF'!N7 | S7: ='CF DRIVERS'!S7 | T7: ='CF DRIVERS'!T7 | U7: ='CF DRIVERS'!U7 | V7: ='CF DRIVERS'!V7 | W7: ='CF DRIVERS'!W7 | X7: ='CF DRIVERS'!X7 | Y7: ='CF DRIVERS'!Y7 | Z7: ='CF DRIVERS'!Z7 | ... AK7: ='CF DRIVERS'!AK7
A8: Operating Lease ROU Asset Amortization | B8: ='YTD CF'!B8 | C8: ='YTD CF'!C8-'YTD CF'!B8 | D8: ='YTD CF'!D8-'YTD CF'!C8 | E8: ='CASH FLOW'!C9-'YTD CF'!D8 | F8: ='YTD CF'!E8 | G8: ='YTD CF'!F8-'YTD CF'!E8 | H8: ='YTD CF'!G8-'YTD CF'!F8 | I8: ='CASH FLOW'!D9-'YTD CF'!G8 | J8: ='YTD CF'!H8 | K8: ='YTD CF'!I8-'YTD CF'!H8 | L8: ='YTD CF'!J8-'YTD CF'!I8 | M8: ='CASH FLOW'!E9-'YTD CF'!J8 | N8: ='YTD CF'!K8 | O8: ='YTD CF'!L8-'YTD CF'!K8 | P8: ='YTD CF'!M8-'YTD CF'!L8 | Q8: ='CASH FLOW'!F9-'YTD CF'!M8 | R8: ='YTD CF'!N8 | S8: ='CF DRIVERS'!S8 | T8: ='CF DRIVERS'!T8 | U8: ='CF DRIVERS'!U8 | V8: ='CF DRIVERS'!V8 | W8: ='CF DRIVERS'!W8 | X8: ='CF DRIVERS'!X8 | Y8: ='CF DRIVERS'!Y8 | Z8: ='CF DRIVERS'!Z8 | ... AK8: ='CF DRIVERS'!AK8
A9: Stock-Based Compensation | B9: ='YTD CF'!B9 | C9: ='YTD CF'!C9-'YTD CF'!B9 | D9: ='YTD CF'!D9-'YTD CF'!C9 | E9: ='CASH FLOW'!C10-'YTD CF'!D9 | F9: ='YTD CF'!E9 | G9: ='YTD CF'!F9-'YTD CF'!E9 | H9: ='YTD CF'!G9-'YTD CF'!F9 | I9: ='CASH FLOW'!D10-'YTD CF'!G9 | J9: ='YTD CF'!H9 | K9: ='YTD CF'!I9-'YTD CF'!H9 | L9: ='YTD CF'!J9-'YTD CF'!I9 | M9: ='CASH FLOW'!E10-'YTD CF'!J9 | N9: ='YTD CF'!K9 | O9: ='YTD CF'!L9-'YTD CF'!K9 | P9: ='YTD CF'!M9-'YTD CF'!L9 | Q9: ='CASH FLOW'!F10-'YTD CF'!M9 | R9: ='YTD CF'!N9 | S9: ='QTR P&L'!S2*'CF DRIVERS'!S9 | T9: ='QTR P&L'!T2*'CF DRIVERS'!T9 | U9: ='QTR P&L'!U2*'CF DRIVERS'!U9 | V9: ='QTR P&L'!V2*'CF DRIVERS'!V9 | W9: ='QTR P&L'!W2*'CF DRIVERS'!W9 | X9: ='QTR P&L'!X2*'CF DRIVERS'!X9 | Y9: ='QTR P&L'!Y2*'CF DRIVERS'!Y9 | Z9: ='QTR P&L'!Z2*'CF DRIVERS'!Z9 | ... AK9: ='QTR P&L'!AK2*'CF DRIVERS'!AK9
A10: Restructuring and Asset Impairment Charges | B10: ='YTD CF'!B10 | C10: ='YTD CF'!C10-'YTD CF'!B10 | D10: ='YTD CF'!D10-'YTD CF'!C10 | E10: ='CASH FLOW'!C11-'YTD CF'!D10 | F10: ='YTD CF'!E10 | G10: ='YTD CF'!F10-'YTD CF'!E10 | H10: ='YTD CF'!G10-'YTD CF'!F10 | I10: ='CASH FLOW'!D11-'YTD CF'!G10 | J10: ='YTD CF'!H10 | K10: ='YTD CF'!I10-'YTD CF'!H10 | L10: ='YTD CF'!J10-'YTD CF'!I10 | M10: ='CASH FLOW'!E11-'YTD CF'!J10 | N10: ='YTD CF'!K10 | O10: ='YTD CF'!L10-'YTD CF'!K10 | P10: ='YTD CF'!M10-'YTD CF'!L10 | Q10: ='CASH FLOW'!F11-'YTD CF'!M10 | R10: ='YTD CF'!N10 | S10: ='CF DRIVERS'!S10 | T10: ='CF DRIVERS'!T10 | U10: ='CF DRIVERS'!U10 | V10: ='CF DRIVERS'!V10 | W10: ='CF DRIVERS'!W10 | X10: ='CF DRIVERS'!X10 | Y10: ='CF DRIVERS'!Y10 | Z10: ='CF DRIVERS'!Z10 | ... AK10: ='CF DRIVERS'!AK10
A11: Cash Payments for Restructuring | B11: ='YTD CF'!B11 | C11: ='YTD CF'!C11-'YTD CF'!B11 | D11: ='YTD CF'!D11-'YTD CF'!C11 | E11: ='CASH FLOW'!C12-'YTD CF'!D11 | F11: ='YTD CF'!E11 | G11: ='YTD CF'!F11-'YTD CF'!E11 | H11: ='YTD CF'!G11-'YTD CF'!F11 | I11: ='CASH FLOW'!D12-'YTD CF'!G11 | J11: ='YTD CF'!H11 | K11: ='YTD CF'!I11-'YTD CF'!H11 | L11: ='YTD CF'!J11-'YTD CF'!I11 | M11: ='CASH FLOW'!E12-'YTD CF'!J11 | N11: ='YTD CF'!K11 | O11: ='YTD CF'!L11-'YTD CF'!K11 | P11: ='YTD CF'!M11-'YTD CF'!L11 | Q11: ='CASH FLOW'!F12-'YTD CF'!M11 | R11: ='YTD CF'!N11 | S11: ='CF DRIVERS'!S11 | T11: ='CF DRIVERS'!T11 | U11: ='CF DRIVERS'!U11 | V11: ='CF DRIVERS'!V11 | W11: ='CF DRIVERS'!W11 | X11: ='CF DRIVERS'!X11 | Y11: ='CF DRIVERS'!Y11 | Z11: ='CF DRIVERS'!Z11 | ... AK11: ='CF DRIVERS'!AK11
A12: Acquisition and Divestiture-Related Charges | B12: ='YTD CF'!B12 | C12: ='YTD CF'!C12-'YTD CF'!B12 | D12: ='YTD CF'!D12-'YTD CF'!C12 | E12: ='CASH FLOW'!C13-'YTD CF'!D12 | F12: ='YTD CF'!E12 | G12: ='YTD CF'!F12-'YTD CF'!E12 | H12: ='YTD CF'!G12-'YTD CF'!F12 | I12: ='CASH FLOW'!D13-'YTD CF'!G12 | J12: ='YTD CF'!H12 | K12: ='YTD CF'!I12-'YTD CF'!H12 | L12: ='YTD CF'!J12-'YTD CF'!I12 | M12: ='CASH FLOW'!E13-'YTD CF'!J12 | N12: ='YTD CF'!K12 | O12: ='YTD CF'!L12-'YTD CF'!K12 | P12: ='YTD CF'!M12-'YTD CF'!L12 | Q12: ='CASH FLOW'!F13-'YTD CF'!M12 | R12: ='YTD CF'!N12 | S12: ='CF DRIVERS'!S12 | T12: ='CF DRIVERS'!T12 | U12: ='CF DRIVERS'!U12 | V12: ='CF DRIVERS'!V12 | W12: ='CF DRIVERS'!W12 | X12: ='CF DRIVERS'!X12 | Y12: ='CF DRIVERS'!Y12 | Z12: ='CF DRIVERS'!Z12 | ... AK12: ='CF DRIVERS'!AK12
A13: Cash Payments for Acquisition and Divestiture Costs | B13: ='YTD CF'!B13 | C13: ='YTD CF'!C13-'YTD CF'!B13 | D13: ='YTD CF'!D13-'YTD CF'!C13 | E13: ='CASH FLOW'!C14-'YTD CF'!D13 | F13: ='YTD CF'!E13 | G13: ='YTD CF'!F13-'YTD CF'!E13 | H13: ='YTD CF'!G13-'YTD CF'!F13 | I13: ='CASH FLOW'!D14-'YTD CF'!G13 | J13: ='YTD CF'!H13 | K13: ='YTD CF'!I13-'YTD CF'!H13 | L13: ='YTD CF'!J13-'YTD CF'!I13 | M13: ='CASH FLOW'!E14-'YTD CF'!J13 | N13: ='YTD CF'!K13 | O13: ='YTD CF'!L13-'YTD CF'!K13 | P13: ='YTD CF'!M13-'YTD CF'!L13 | Q13: ='CASH FLOW'!F14-'YTD CF'!M13 | R13: ='YTD CF'!N13 | S13: ='CF DRIVERS'!S13 | T13: ='CF DRIVERS'!T13 | U13: ='CF DRIVERS'!U13 | V13: ='CF DRIVERS'!V13 | W13: ='CF DRIVERS'!W13 | X13: ='CF DRIVERS'!X13 | Y13: ='CF DRIVERS'!Y13 | Z13: ='CF DRIVERS'!Z13 | ... AK13: ='CF DRIVERS'!AK13
A14: Pension and Postretirement Benefits Expense | B14: ='YTD CF'!B14 | C14: ='YTD CF'!C14-'YTD CF'!B14 | D14: ='YTD CF'!D14-'YTD CF'!C14 | E14: ='CASH FLOW'!C15-'YTD CF'!D14 | F14: ='YTD CF'!E14 | G14: ='YTD CF'!F14-'YTD CF'!E14 | H14: ='YTD CF'!G14-'YTD CF'!F14 | I14: ='CASH FLOW'!D15-'YTD CF'!G14 | J14: ='YTD CF'!H14 | K14: ='YTD CF'!I14-'YTD CF'!H14 | L14: ='YTD CF'!J14-'YTD CF'!I14 | M14: ='CASH FLOW'!E15-'YTD CF'!J14 | N14: ='YTD CF'!K14 | O14: ='YTD CF'!L14-'YTD CF'!K14 | P14: ='YTD CF'!M14-'YTD CF'!L14 | Q14: ='CASH FLOW'!F15-'YTD CF'!M14 | R14: ='YTD CF'!N14 | S14: ='CF DRIVERS'!S14 | T14: ='CF DRIVERS'!T14 | U14: ='CF DRIVERS'!U14 | V14: ='CF DRIVERS'!V14 | W14: ='CF DRIVERS'!W14 | X14: ='CF DRIVERS'!X14 | Y14: ='CF DRIVERS'!Y14 | Z14: ='CF DRIVERS'!Z14 | ... AK14: ='CF DRIVERS'!AK14
A15: Pension and Postretirement Benefits Contributions | B15: ='YTD CF'!B15 | C15: ='YTD CF'!C15-'YTD CF'!B15 | D15: ='YTD CF'!D15-'YTD CF'!C15 | E15: ='CASH FLOW'!C16-'YTD CF'!D15 | F15: ='YTD CF'!E15 | G15: ='YTD CF'!F15-'YTD CF'!E15 | H15: ='YTD CF'!G15-'YTD CF'!F15 | I15: ='CASH FLOW'!D16-'YTD CF'!G15 | J15: ='YTD CF'!H15 | K15: ='YTD CF'!I15-'YTD CF'!H15 | L15: ='YTD CF'!J15-'YTD CF'!I15 | M15: ='CASH FLOW'!E16-'YTD CF'!J15 | N15: ='YTD CF'!K15 | O15: ='YTD CF'!L15-'YTD CF'!K15 | P15: ='YTD CF'!M15-'YTD CF'!L15 | Q15: ='CASH FLOW'!F16-'YTD CF'!M15 | R15: ='YTD CF'!N15 | S15: ='CF DRIVERS'!S15 | T15: ='CF DRIVERS'!T15 | U15: ='CF DRIVERS'!U15 | V15: ='CF DRIVERS'!V15 | W15: ='CF DRIVERS'!W15 | X15: ='CF DRIVERS'!X15 | Y15: ='CF DRIVERS'!Y15 | Z15: ='CF DRIVERS'!Z15 | ... AK15: ='CF DRIVERS'!AK15
A16: (Benefit) Provision for Deferred Income Taxes | B16: ='YTD CF'!B16 | C16: ='YTD CF'!C16-'YTD CF'!B16 | D16: ='YTD CF'!D16-'YTD CF'!C16 | E16: ='CASH FLOW'!C17-'YTD CF'!D16 | F16: ='YTD CF'!E16 | G16: ='YTD CF'!F16-'YTD CF'!E16 | H16: ='YTD CF'!G16-'YTD CF'!F16 | I16: ='CASH FLOW'!D17-'YTD CF'!G16 | J16: ='YTD CF'!H16 | K16: ='YTD CF'!I16-'YTD CF'!H16 | L16: ='YTD CF'!J16-'YTD CF'!I16 | M16: ='CASH FLOW'!E17-'YTD CF'!J16 | N16: ='YTD CF'!K16 | O16: ='YTD CF'!L16-'YTD CF'!K16 | P16: ='YTD CF'!M16-'YTD CF'!L16 | Q16: ='CASH FLOW'!F17-'YTD CF'!M16 | R16: ='YTD CF'!N16 | S16: ='CF DRIVERS'!S16 | T16: ='CF DRIVERS'!T16 | U16: ='CF DRIVERS'!U16 | V16: ='CF DRIVERS'!V16 | W16: ='CF DRIVERS'!W16 | X16: ='CF DRIVERS'!X16 | Y16: ='CF DRIVERS'!Y16 | Z16: ='CF DRIVERS'!Z16 | ... AK16: ='CF DRIVERS'!AK16
A17: Tax Expense Related to TCJ Act | B17: ='YTD CF'!B17 | C17: ='YTD CF'!C17-'YTD CF'!B17 | D17: ='YTD CF'!D17-'YTD CF'!C17 | E17: ='CASH FLOW'!C18-'YTD CF'!D17 | F17: ='YTD CF'!E17 | G17: ='YTD CF'!F17-'YTD CF'!E17 | H17: ='YTD CF'!G17-'YTD CF'!F17 | I17: ='CASH FLOW'!D18-'YTD CF'!G17 | J17: ='YTD CF'!H17 | K17: ='YTD CF'!I17-'YTD CF'!H17 | L17: ='YTD CF'!J17-'YTD CF'!I17 | M17: ='CASH FLOW'!E18-'YTD CF'!J17 | N17: ='YTD CF'!K17 | O17: ='YTD CF'!L17-'YTD CF'!K17 | P17: ='YTD CF'!M17-'YTD CF'!L17 | Q17: ='CASH FLOW'!F18-'YTD CF'!M17 | R17: ='YTD CF'!N17 | S17: ='CF DRIVERS'!S17 | T17: ='CF DRIVERS'!T17 | U17: ='CF DRIVERS'!U17 | V17: ='CF DRIVERS'!V17 | W17: ='CF DRIVERS'!W17 | X17: ='CF DRIVERS'!X17 | Y17: ='CF DRIVERS'!Y17 | Z17: ='CF DRIVERS'!Z17 | ... AK17: ='CF DRIVERS'!AK17
A18: Tax Payments Related to TCJ Act | B18: ='YTD CF'!B18 | C18: ='YTD CF'!C18-'YTD CF'!B18 | D18: ='YTD CF'!D18-'YTD CF'!C18 | E18: ='CASH FLOW'!C19-'YTD CF'!D18 | F18: ='YTD CF'!E18 | G18: ='YTD CF'!F18-'YTD CF'!E18 | H18: ='YTD CF'!G18-'YTD CF'!F18 | I18: ='CASH FLOW'!D19-'YTD CF'!G18 | J18: ='YTD CF'!H18 | K18: ='YTD CF'!I18-'YTD CF'!H18 | L18: ='YTD CF'!J18-'YTD CF'!I18 | M18: ='CASH FLOW'!E19-'YTD CF'!J18 | N18: ='YTD CF'!K18 | O18: ='YTD CF'!L18-'YTD CF'!K18 | P18: ='YTD CF'!M18-'YTD CF'!L18 | Q18: ='CASH FLOW'!F19-'YTD CF'!M18 | R18: ='YTD CF'!N18 | S18: ='CF DRIVERS'!S18 | T18: ='CF DRIVERS'!T18 | U18: ='CF DRIVERS'!U18 | V18: ='CF DRIVERS'!V18 | W18: ='CF DRIVERS'!W18 | X18: ='CF DRIVERS'!X18 | Y18: ='CF DRIVERS'!Y18 | Z18: ='CF DRIVERS'!Z18 | ... AK18: ='CF DRIVERS'!AK18
A19: Accounts Receivable | B19: ='YTD CF'!B19 | C19: ='YTD CF'!C19-'YTD CF'!B19 | D19: ='YTD CF'!D19-'YTD CF'!C19 | E19: ='CASH FLOW'!C20-'YTD CF'!D19 | F19: ='YTD CF'!E19 | G19: ='YTD CF'!F19-'YTD CF'!E19 | H19: ='YTD CF'!G19-'YTD CF'!F19 | I19: ='CASH FLOW'!D20-'YTD CF'!G19 | J19: ='YTD CF'!H19 | K19: ='YTD CF'!I19-'YTD CF'!H19 | L19: ='YTD CF'!J19-'YTD CF'!I19 | M19: ='CASH FLOW'!E20-'YTD CF'!J19 | N19: ='YTD CF'!K19 | O19: ='YTD CF'!L19-'YTD CF'!K19 | P19: ='YTD CF'!M19-'YTD CF'!L19 | Q19: ='CASH FLOW'!F20-'YTD CF'!M19 | R19: ='YTD CF'!N19 | S19: ='CF DRIVERS'!S19 | T19: ='CF DRIVERS'!T19 | U19: ='CF DRIVERS'!U19 | V19: ='CF DRIVERS'!V19 | W19: ='CF DRIVERS'!W19 | X19: ='CF DRIVERS'!X19 | Y19: ='CF DRIVERS'!Y19 | Z19: ='CF DRIVERS'!Z19 | ... AK19: ='CF DRIVERS'!AK19
A20: Inventories | B20: ='YTD CF'!B20 | C20: ='YTD CF'!C20-'YTD CF'!B20 | D20: ='YTD CF'!D20-'YTD CF'!C20 | E20: ='CASH FLOW'!C21-'YTD CF'!D20 | F20: ='YTD CF'!E20 | G20: ='YTD CF'!F20-'YTD CF'!E20 | H20: ='YTD CF'!G20-'YTD CF'!F20 | I20: ='CASH FLOW'!D21-'YTD CF'!G20 | J20: ='YTD CF'!H20 | K20: ='YTD CF'!I20-'YTD CF'!H20 | L20: ='YTD CF'!J20-'YTD CF'!I20 | M20: ='CASH FLOW'!E21-'YTD CF'!J20 | N20: ='YTD CF'!K20 | O20: ='YTD CF'!L20-'YTD CF'!K20 | P20: ='YTD CF'!M20-'YTD CF'!L20 | Q20: ='CASH FLOW'!F21-'YTD CF'!M20 | R20: ='YTD CF'!N20 | S20: ='CF DRIVERS'!S20 | T20: ='CF DRIVERS'!T20 | U20: ='CF DRIVERS'!U20 | V20: ='CF DRIVERS'!V20 | W20: ='CF DRIVERS'!W20 | X20: ='CF DRIVERS'!X20 | Y20: ='CF DRIVERS'!Y20 | Z20: ='CF DRIVERS'!Z20 | ... AK20: ='CF DRIVERS'!AK20
A21: Prepaid Expenses | B21: ='YTD CF'!B21 | C21: ='YTD CF'!C21-'YTD CF'!B21 | D21: ='YTD CF'!D21-'YTD CF'!C21 | E21: ='CASH FLOW'!C22-'YTD CF'!D21 | F21: ='YTD CF'!E21 | G21: ='YTD CF'!F21-'YTD CF'!E21 | H21: ='YTD CF'!G21-'YTD CF'!F21 | I21: ='CASH FLOW'!D22-'YTD CF'!G21 | J21: ='YTD CF'!H21 | K21: ='YTD CF'!I21-'YTD CF'!H21 | L21: ='YTD CF'!J21-'YTD CF'!I21 | M21: ='CASH FLOW'!E22-'YTD CF'!J21 | N21: ='YTD CF'!K21 | O21: ='YTD CF'!L21-'YTD CF'!K21 | P21: ='YTD CF'!M21-'YTD CF'!L21 | Q21: ='CASH FLOW'!F22-'YTD CF'!M21 | R21: ='YTD CF'!N21 | S21: ='CF DRIVERS'!S21 | T21: ='CF DRIVERS'!T21 | U21: ='CF DRIVERS'!U21 | V21: ='CF DRIVERS'!V21 | W21: ='CF DRIVERS'!W21 | X21: ='CF DRIVERS'!X21 | Y21: ='CF DRIVERS'!Y21 | Z21: ='CF DRIVERS'!Z21 | ... AK21: ='CF DRIVERS'!AK21
... A24: Other Operating Items | B24: ='YTD CF'!B24 | C24: ='YTD CF'!C24-'YTD CF'!B24 | D24: ='YTD CF'!D24-'YTD CF'!C24 | E24: ='CASH FLOW'!C25-'YTD CF'!D24 | F24: ='YTD CF'!E24 | G24: ='YTD CF'!F24-'YTD CF'!E24 | H24: ='YTD CF'!G24-'YTD CF'!F24 | I24: ='CASH FLOW'!D25-'YTD CF'!G24 | J24: ='YTD CF'!H24 | K24: ='YTD CF'!I24-'YTD CF'!H24 | L24: ='YTD CF'!J24-'YTD CF'!I24 | M24: ='CASH FLOW'!E25-'YTD CF'!J24 | N24: ='YTD CF'!K24 | O24: ='YTD CF'!L24-'YTD CF'!K24 | P24: ='YTD CF'!M24-'YTD CF'!L24 | Q24: ='CASH FLOW'!F25-'YTD CF'!M24 | R24: ='YTD CF'!N24 | S24: ='CF DRIVERS'!S24 | T24: ='CF DRIVERS'!T24 | U24: ='CF DRIVERS'!U24 | V24: ='CF DRIVERS'!V24 | W24: ='CF DRIVERS'!W24 | X24: ='CF DRIVERS'!X24 | Y24: ='CF DRIVERS'!Y24 | Z24: ='CF DRIVERS'!Z24 | ... AK24: ='CF DRIVERS'!AK24
A25: Cash Flow from Operations | B25: ='YTD CF'!B25 | C25: ='YTD CF'!C25-'YTD CF'!B25 | D25: ='YTD CF'!D25-'YTD CF'!C25 | E25: ='CASH FLOW'!C26-'YTD CF'!D25 | F25: ='YTD CF'!E25 | G25: ='YTD CF'!F25-'YTD CF'!E25 | H25: ='YTD CF'!G25-'YTD CF'!F25 | I25: ='CASH FLOW'!D26-'YTD CF'!G25 | J25: ='YTD CF'!H25 | K25: ='YTD CF'!I25-'YTD CF'!H25 | L25: ='YTD CF'!J25-'YTD CF'!I25 | M25: ='CASH FLOW'!E26-'YTD CF'!J25 | N25: ='YTD CF'!K25 | O25: ='YTD CF'!L25-'YTD CF'!K25 | P25: ='YTD CF'!M25-'YTD CF'!L25 | Q25: ='CASH FLOW'!F26-'YTD CF'!M25 | R25: ='YTD CF'!N25 | S25: =SUM(S2:S24) | T25: =SUM(T2:T24) | U25: =SUM(U2:U24) | V25: =SUM(V2:V24) | W25: =SUM(W2:W24) | X25: =SUM(X2:X24) | Y25: =SUM(Y2:Y24) | Z25: =SUM(Z2:Z24) | ... AK25: =SUM(AK2:AK24)
A26: Purchase of PP&E | B26: ='YTD CF'!B26 | C26: ='YTD CF'!C26-'YTD CF'!B26 | D26: ='YTD CF'!D26-'YTD CF'!C26 | E26: ='CASH FLOW'!C27-'YTD CF'!D26 | F26: ='YTD CF'!E26 | G26: ='YTD CF'!F26-'YTD CF'!E26 | H26: ='YTD CF'!G26-'YTD CF'!F26 | I26: ='CASH FLOW'!D27-'YTD CF'!G26 | J26: ='YTD CF'!H26 | K26: ='YTD CF'!I26-'YTD CF'!H26 | L26: ='YTD CF'!J26-'YTD CF'!I26 | M26: ='CASH FLOW'!E27-'YTD CF'!J26 | N26: ='YTD CF'!K26 | O26: ='YTD CF'!L26-'YTD CF'!K26 | P26: ='YTD CF'!M26-'YTD CF'!L26 | Q26: ='CASH FLOW'!F27-'YTD CF'!M26 | R26: ='YTD CF'!N26 | S26: ='QTR P&L'!S2*'CF DRIVERS'!S25 | T26: ='QTR P&L'!T2*'CF DRIVERS'!T25 | U26: ='QTR P&L'!U2*'CF DRIVERS'!U25 | V26: ='QTR P&L'!V2*'CF DRIVERS'!V25 | W26: ='QTR P&L'!W2*'CF DRIVERS'!W25 | X26: ='QTR P&L'!X2*'CF DRIVERS'!X25 | Y26: ='QTR P&L'!Y2*'CF DRIVERS'!Y25 | Z26: ='QTR P&L'!Z2*'CF DRIVERS'!Z25 | ... AK26: ='QTR P&L'!AK2*'CF DRIVERS'!AK25
A27: Proceeds from Sale of Assets | B27: ='YTD CF'!B27 | C27: ='YTD CF'!C27-'YTD CF'!B27 | D27: ='YTD CF'!D27-'YTD CF'!C27 | E27: ='CASH FLOW'!C28-'YTD CF'!D27 | F27: ='YTD CF'!E27 | G27: ='YTD CF'!F27-'YTD CF'!E27 | H27: ='YTD CF'!G27-'YTD CF'!F27 | I27: ='CASH FLOW'!D28-'YTD CF'!G27 | J27: ='YTD CF'!H27 | K27: ='YTD CF'!I27-'YTD CF'!H27 | L27: ='YTD CF'!J27-'YTD CF'!I27 | M27: ='CASH FLOW'!E28-'YTD CF'!J27 | N27: ='YTD CF'!K27 | O27: ='YTD CF'!L27-'YTD CF'!K27 | P27: ='YTD CF'!M27-'YTD CF'!L27 | Q27: ='CASH FLOW'!F28-'YTD CF'!M27 | R27: ='YTD CF'!N27 | S27: ='CF DRIVERS'!S26 | T27: ='CF DRIVERS'!T26 | U27: ='CF DRIVERS'!U26 | V27: ='CF DRIVERS'!V26 | W27: ='CF DRIVERS'!W26 | X27: ='CF DRIVERS'!X26 | Y27: ='CF DRIVERS'!Y26 | Z27: ='CF DRIVERS'!Z26 | ... AK27: ='CF DRIVERS'!AK26
A28: Acquisitions, Net of Cash Acquired | B28: ='YTD CF'!B28 | C28: ='YTD CF'!C28-'YTD CF'!B28 | D28: ='YTD CF'!D28-'YTD CF'!C28 | E28: ='CASH FLOW'!C29-'YTD CF'!D28 | F28: ='YTD CF'!E28 | G28: ='YTD CF'!F28-'YTD CF'!E28 | H28: ='YTD CF'!G28-'YTD CF'!F28 | I28: ='CASH FLOW'!D29-'YTD CF'!G28 | J28: ='YTD CF'!H28 | K28: ='YTD CF'!I28-'YTD CF'!H28 | L28: ='YTD CF'!J28-'YTD CF'!I28 | M28: ='CASH FLOW'!E29-'YTD CF'!J28 | N28: ='YTD CF'!K28 | O28: ='YTD CF'!L28-'YTD CF'!K28 | P28: ='YTD CF'!M28-'YTD CF'!L28 | Q28: ='CASH FLOW'!F29-'YTD CF'!M28 | R28: ='YTD CF'!N28 | S28: ='CF DRIVERS'!S27 | T28: ='CF DRIVERS'!T27 | U28: ='CF DRIVERS'!U27 | V28: ='CF DRIVERS'!V27 | W28: ='CF DRIVERS'!W27 | X28: ='CF DRIVERS'!X27 | Y28: ='CF DRIVERS'!Y27 | Z28: ='CF DRIVERS'!Z27 | ... AK28: ='CF DRIVERS'!AK27
A29: Proceeds from Juice Transaction | B29: ='YTD CF'!B29 | C29: ='YTD CF'!C29-'YTD CF'!B29 | D29: ='YTD CF'!D29-'YTD CF'!C29 | E29: ='CASH FLOW'!C30-'YTD CF'!D29 | F29: ='YTD CF'!E29 | G29: ='YTD CF'!F29-'YTD CF'!E29 | H29: ='YTD CF'!G29-'YTD CF'!F29 | I29: ='CASH FLOW'!D30-'YTD CF'!G29 | J29: ='YTD CF'!H29 | K29: ='YTD CF'!I29-'YTD CF'!H29 | L29: ='YTD CF'!J29-'YTD CF'!I29 | M29: ='CASH FLOW'!E30-'YTD CF'!J29 | N29: ='YTD CF'!K29 | O29: ='YTD CF'!L29-'YTD CF'!K29 | P29: ='YTD CF'!M29-'YTD CF'!L29 | Q29: ='CASH FLOW'!F30-'YTD CF'!M29 | R29: ='YTD CF'!N29 | S29: ='CF DRIVERS'!S28 | T29: ='CF DRIVERS'!T28 | U29: ='CF DRIVERS'!U28 | V29: ='CF DRIVERS'!V28 | W29: ='CF DRIVERS'!W28 | X29: ='CF DRIVERS'!X28 | Y29: ='CF DRIVERS'!Y28 | Z29: ='CF DRIVERS'!Z28 | ... AK29: ='CF DRIVERS'!AK28
A30: Proceeds from Divestitures of Businesses | B30: ='YTD CF'!B30 | C30: ='YTD CF'!C30-'YTD CF'!B30 | D30: ='YTD CF'!D30-'YTD CF'!C30 | E30: ='CASH FLOW'!C31-'YTD CF'!D30 | F30: ='YTD CF'!E30 | G30: ='YTD CF'!F30-'YTD CF'!E30 | H30: ='YTD CF'!G30-'YTD CF'!F30 | I30: ='CASH FLOW'!D31-'YTD CF'!G30 | J30: ='YTD CF'!H30 | K30: ='YTD CF'!I30-'YTD CF'!H30 | L30: ='YTD CF'!J30-'YTD CF'!I30 | M30: ='CASH FLOW'!E31-'YTD CF'!J30 | N30: ='YTD CF'!K30 | O30: ='YTD CF'!L30-'YTD CF'!K30 | P30: ='YTD CF'!M30-'YTD CF'!L30 | Q30: ='CASH FLOW'!F31-'YTD CF'!M30 | R30: ='YTD CF'!N30 | S30: ='CF DRIVERS'!S29 | T30: ='CF DRIVERS'!T29 | U30: ='CF DRIVERS'!U29 | V30: ='CF DRIVERS'!V29 | W30: ='CF DRIVERS'!W29 | X30: ='CF DRIVERS'!X29 | Y30: ='CF DRIVERS'!Y29 | Z30: ='CF DRIVERS'!Z29 | ... AK30: ='CF DRIVERS'!AK29
A31: Net Change in Short-Term Investments | B31: ='YTD CF'!B31 | C31: ='YTD CF'!C31-'YTD CF'!B31 | D31: ='YTD CF'!D31-'YTD CF'!C31 | E31: ='CASH FLOW'!C32-'YTD CF'!D31 | F31: ='YTD CF'!E31 | G31: ='YTD CF'!F31-'YTD CF'!E31 | H31: ='YTD CF'!G31-'YTD CF'!F31 | I31: ='CASH FLOW'!D32-'YTD CF'!G31 | J31: ='YTD CF'!H31 | K31: ='YTD CF'!I31-'YTD CF'!H31 | L31: ='YTD CF'!J31-'YTD CF'!I31 | M31: ='CASH FLOW'!E32-'YTD CF'!J31 | N31: ='YTD CF'!K31 | O31: ='YTD CF'!L31-'YTD CF'!K31 | P31: ='YTD CF'!M31-'YTD CF'!L31 | Q31: ='CASH FLOW'!F32-'YTD CF'!M31 | R31: ='YTD CF'!N31 | S31: ='CF DRIVERS'!S30 | T31: ='CF DRIVERS'!T30 | U31: ='CF DRIVERS'!U30 | V31: ='CF DRIVERS'!V30 | W31: ='CF DRIVERS'!W30 | X31: ='CF DRIVERS'!X30 | Y31: ='CF DRIVERS'!Y30 | Z31: ='CF DRIVERS'!Z30 | ... AK31: ='CF DRIVERS'!AK30
A32: Other Investing Activities | B32: ='YTD CF'!B32 | C32: ='YTD CF'!C32-'YTD CF'!B32 | D32: ='YTD CF'!D32-'YTD CF'!C32 | E32: ='CASH FLOW'!C33-'YTD CF'!D32 | F32: ='YTD CF'!E32 | G32: ='YTD CF'!F32-'YTD CF'!E32 | H32: ='YTD CF'!G32-'YTD CF'!F32 | I32: ='CASH FLOW'!D33-'YTD CF'!G32 | J32: ='YTD CF'!H32 | K32: ='YTD CF'!I32-'YTD CF'!H32 | L32: ='YTD CF'!J32-'YTD CF'!I32 | M32: ='CASH FLOW'!E33-'YTD CF'!J32 | N32: ='YTD CF'!K32 | O32: ='YTD CF'!L32-'YTD CF'!K32 | P32: ='YTD CF'!M32-'YTD CF'!L32 | Q32: ='CASH FLOW'!F33-'YTD CF'!M32 | R32: ='YTD CF'!N32 | S32: ='CF DRIVERS'!S31 | T32: ='CF DRIVERS'!T31 | U32: ='CF DRIVERS'!U31 | V32: ='CF DRIVERS'!V31 | W32: ='CF DRIVERS'!W31 | X32: ='CF DRIVERS'!X31 | Y32: ='CF DRIVERS'!Y31 | Z32: ='CF DRIVERS'!Z31 | ... AK32: ='CF DRIVERS'!AK31
A33: Cash Flow from Investing | B33: ='YTD CF'!B33 | C33: ='YTD CF'!C33-'YTD CF'!B33 | D33: ='YTD CF'!D33-'YTD CF'!C33 | E33: ='CASH FLOW'!C34-'YTD CF'!D33 | F33: ='YTD CF'!E33 | G33: ='YTD CF'!F33-'YTD CF'!E33 | H33: ='YTD CF'!G33-'YTD CF'!F33 | I33: ='CASH FLOW'!D34-'YTD CF'!G33 | J33: ='YTD CF'!H33 | K33: ='YTD CF'!I33-'YTD CF'!H33 | L33: ='YTD CF'!J33-'YTD CF'!I33 | M33: ='CASH FLOW'!E34-'YTD CF'!J33 | N33: ='YTD CF'!K33 | O33: ='YTD CF'!L33-'YTD CF'!K33 | P33: ='YTD CF'!M33-'YTD CF'!L33 | Q33: ='CASH FLOW'!F34-'YTD CF'!M33 | R33: ='YTD CF'!N33 | S33: =SUM(S26:S32) | T33: =SUM(T26:T32) | U33: =SUM(U26:U32) | V33: =SUM(V26:V32) | W33: =SUM(W26:W32) | X33: =SUM(X26:X32) | Y33: =SUM(Y26:Y32) | Z33: =SUM(Z26:Z32) | ... AK33: =SUM(AK26:AK32)
A34: Proceeds from Issuance of Long-Term Debt | B34: ='YTD CF'!B34 | C34: ='YTD CF'!C34-'YTD CF'!B34 | D34: ='YTD CF'!D34-'YTD CF'!C34 | E34: ='CASH FLOW'!C35-'YTD CF'!D34 | F34: ='YTD CF'!E34 | G34: ='YTD CF'!F34-'YTD CF'!E34 | H34: ='YTD CF'!G34-'YTD CF'!F34 | I34: ='CASH FLOW'!D35-'YTD CF'!G34 | J34: ='YTD CF'!H34 | K34: ='YTD CF'!I34-'YTD CF'!H34 | L34: ='YTD CF'!J34-'YTD CF'!I34 | M34: ='CASH FLOW'!E35-'YTD CF'!J34 | N34: ='YTD CF'!K34 | O34: ='YTD CF'!L34-'YTD CF'!K34 | P34: ='YTD CF'!M34-'YTD CF'!L34 | Q34: ='CASH FLOW'!F35-'YTD CF'!M34 | R34: ='YTD CF'!N34 | S34: ='CF DRIVERS'!S32 | T34: ='CF DRIVERS'!T32 | U34: ='CF DRIVERS'!U32 | V34: ='CF DRIVERS'!V32 | W34: ='CF DRIVERS'!W32 | X34: ='CF DRIVERS'!X32 | Y34: ='CF DRIVERS'!Y32 | Z34: ='CF DRIVERS'!Z32 | ... AK34: ='CF DRIVERS'!AK32
A35: Repayments of Long-Term Debt | B35: ='YTD CF'!B35 | C35: ='YTD CF'!C35-'YTD CF'!B35 | D35: ='YTD CF'!D35-'YTD CF'!C35 | E35: ='CASH FLOW'!C36-'YTD CF'!D35 | F35: ='YTD CF'!E35 | G35: ='YTD CF'!F35-'YTD CF'!E35 | H35: ='YTD CF'!G35-'YTD CF'!F35 | I35: ='CASH FLOW'!D36-'YTD CF'!G35 | J35: ='YTD CF'!H35 | K35: ='YTD CF'!I35-'YTD CF'!H35 | L35: ='YTD CF'!J35-'YTD CF'!I35 | M35: ='CASH FLOW'!E36-'YTD CF'!J35 | N35: ='YTD CF'!K35 | O35: ='YTD CF'!L35-'YTD CF'!K35 | P35: ='YTD CF'!M35-'YTD CF'!L35 | Q35: ='CASH FLOW'!F36-'YTD CF'!M35 | R35: ='YTD CF'!N35 | S35: ='CF DRIVERS'!S33 | T35: ='CF DRIVERS'!T33 | U35: ='CF DRIVERS'!U33 | V35: ='CF DRIVERS'!V33 | W35: ='CF DRIVERS'!W33 | X35: ='CF DRIVERS'!X33 | Y35: ='CF DRIVERS'!Y33 | Z35: ='CF DRIVERS'!Z33 | ... AK35: ='CF DRIVERS'!AK33
A36: Proceeds from Short-Term Debt | B36: ='YTD CF'!B36 | C36: ='YTD CF'!C36-'YTD CF'!B36 | D36: ='YTD CF'!D36-'YTD CF'!C36 | E36: ='CASH FLOW'!C37-'YTD CF'!D36 | F36: ='YTD CF'!E36 | G36: ='YTD CF'!F36-'YTD CF'!E36 | H36: ='YTD CF'!G36-'YTD CF'!F36 | I36: ='CASH FLOW'!D37-'YTD CF'!G36 | J36: ='YTD CF'!H36 | K36: ='YTD CF'!I36-'YTD CF'!H36 | L36: ='YTD CF'!J36-'YTD CF'!I36 | M36: ='CASH FLOW'!E37-'YTD CF'!J36 | N36: ='YTD CF'!K36 | O36: ='YTD CF'!L36-'YTD CF'!K36 | P36: ='YTD CF'!M36-'YTD CF'!L36 | Q36: ='CASH FLOW'!F37-'YTD CF'!M36 | R36: ='YTD CF'!N36 | S36: ='CF DRIVERS'!S34 | T36: ='CF DRIVERS'!T34 | U36: ='CF DRIVERS'!U34 | V36: ='CF DRIVERS'!V34 | W36: ='CF DRIVERS'!W34 | X36: ='CF DRIVERS'!X34 | Y36: ='CF DRIVERS'!Y34 | Z36: ='CF DRIVERS'!Z34 | ... AK36: ='CF DRIVERS'!AK34
A37: Repayments of Short-Term Debt | B37: ='YTD CF'!B37 | C37: ='YTD CF'!C37-'YTD CF'!B37 | D37: ='YTD CF'!D37-'YTD CF'!C37 | E37: ='CASH FLOW'!C38-'YTD CF'!D37 | F37: ='YTD CF'!E37 | G37: ='YTD CF'!F37-'YTD CF'!E37 | H37: ='YTD CF'!G37-'YTD CF'!F37 | I37: ='CASH FLOW'!D38-'YTD CF'!G37 | J37: ='YTD CF'!H37 | K37: ='YTD CF'!I37-'YTD CF'!H37 | L37: ='YTD CF'!J37-'YTD CF'!I37 | M37: ='CASH FLOW'!E38-'YTD CF'!J37 | N37: ='YTD CF'!K37 | O37: ='YTD CF'!L37-'YTD CF'!K37 | P37: ='YTD CF'!M37-'YTD CF'!L37 | Q37: ='CASH FLOW'!F38-'YTD CF'!M37 | R37: ='YTD CF'!N37 | S37: ='CF DRIVERS'!S35 | T37: ='CF DRIVERS'!T35 | U37: ='CF DRIVERS'!U35 | V37: ='CF DRIVERS'!V35 | W37: ='CF DRIVERS'!W35 | X37: ='CF DRIVERS'!X35 | Y37: ='CF DRIVERS'!Y35 | Z37: ='CF DRIVERS'!Z35 | ... AK37: ='CF DRIVERS'!AK35
A38: Net Change in Other Short-Term Debt | B38: ='YTD CF'!B38 | C38: ='YTD CF'!C38-'YTD CF'!B38 | D38: ='YTD CF'!D38-'YTD CF'!C38 | E38: ='CASH FLOW'!C39-'YTD CF'!D38 | F38: ='YTD CF'!E38 | G38: ='YTD CF'!F38-'YTD CF'!E38 | H38: ='YTD CF'!G38-'YTD CF'!F38 | I38: ='CASH FLOW'!D39-'YTD CF'!G38 | J38: ='YTD CF'!H38 | K38: ='YTD CF'!I38-'YTD CF'!H38 | L38: ='YTD CF'!J38-'YTD CF'!I38 | M38: ='CASH FLOW'!E39-'YTD CF'!J38 | N38: ='YTD CF'!K38 | O38: ='YTD CF'!L38-'YTD CF'!K38 | P38: ='YTD CF'!M38-'YTD CF'!L38 | Q38: ='CASH FLOW'!F39-'YTD CF'!M38 | R38: ='YTD CF'!N38 | S38: ='CF DRIVERS'!S36 | T38: ='CF DRIVERS'!T36 | U38: ='CF DRIVERS'!U36 | V38: ='CF DRIVERS'!V36 | W38: ='CF DRIVERS'!W36 | X38: ='CF DRIVERS'!X36 | Y38: ='CF DRIVERS'!Y36 | Z38: ='CF DRIVERS'!Z36 | ... AK38: ='CF DRIVERS'!AK36
A39: Common Dividends | B39: ='YTD CF'!B39 | C39: ='YTD CF'!C39-'YTD CF'!B39 | D39: ='YTD CF'!D39-'YTD CF'!C39 | E39: ='CASH FLOW'!C41-'YTD CF'!D39 | F39: ='YTD CF'!E39 | G39: ='YTD CF'!F39-'YTD CF'!E39 | H39: ='YTD CF'!G39-'YTD CF'!F39 | I39: ='CASH FLOW'!D41-'YTD CF'!G39 | J39: ='YTD CF'!H39 | K39: ='YTD CF'!I39-'YTD CF'!H39 | L39: ='YTD CF'!J39-'YTD CF'!I39 | M39: ='CASH FLOW'!E41-'YTD CF'!J39 | N39: ='YTD CF'!K39 | O39: ='YTD CF'!L39-'YTD CF'!K39 | P39: ='YTD CF'!M39-'YTD CF'!L39 | Q39: ='CASH FLOW'!F41-'YTD CF'!M39 | R39: ='YTD CF'!N39 | S39: ='QTR P&L'!S13*'CF DRIVERS'!S37 | T39: ='QTR P&L'!T13*'CF DRIVERS'!T37 | U39: ='QTR P&L'!U13*'CF DRIVERS'!U37 | V39: ='QTR P&L'!V13*'CF DRIVERS'!V37 | W39: ='QTR P&L'!W13*'CF DRIVERS'!W37 | X39: ='QTR P&L'!X13*'CF DRIVERS'!X37 | Y39: ='QTR P&L'!Y13*'CF DRIVERS'!Y37 | Z39: ='QTR P&L'!Z13*'CF DRIVERS'!Z37 | ... AK39: ='QTR P&L'!AK13*'CF DRIVERS'!AK37
A40: Share Repurchases | B40: ='YTD CF'!B40 | C40: ='YTD CF'!C40-'YTD CF'!B40 | D40: ='YTD CF'!D40-'YTD CF'!C40 | E40: ='CASH FLOW'!C42-'YTD CF'!D40 | F40: ='YTD CF'!E40 | G40: ='YTD CF'!F40-'YTD CF'!E40 | H40: ='YTD CF'!G40-'YTD CF'!F40 | I40: ='CASH FLOW'!D42-'YTD CF'!G40 | J40: ='YTD CF'!H40 | K40: ='YTD CF'!I40-'YTD CF'!H40 | L40: ='YTD CF'!J40-'YTD CF'!I40 | M40: ='CASH FLOW'!E42-'YTD CF'!J40 | N40: ='YTD CF'!K40 | O40: ='YTD CF'!L40-'YTD CF'!K40 | P40: ='YTD CF'!M40-'YTD CF'!L40 | Q40: ='CASH FLOW'!F42-'YTD CF'!M40 | R40: ='YTD CF'!N40 | S40: ='CF DRIVERS'!S38 | T40: ='CF DRIVERS'!T38 | U40: ='CF DRIVERS'!U38 | V40: ='CF DRIVERS'!V38 | W40: ='CF DRIVERS'!W38 | X40: ='CF DRIVERS'!X38 | Y40: ='CF DRIVERS'!Y38 | Z40: ='CF DRIVERS'!Z38 | ... AK40: ='CF DRIVERS'!AK38
A41: Proceeds from Exercise of Stock Options | B41: ='YTD CF'!B41 | C41: ='YTD CF'!C41-'YTD CF'!B41 | D41: ='YTD CF'!D41-'YTD CF'!C41 | E41: ='CASH FLOW'!C43-'YTD CF'!D41 | F41: ='YTD CF'!E41 | G41: ='YTD CF'!F41-'YTD CF'!E41 | H41: ='YTD CF'!G41-'YTD CF'!F41 | I41: ='CASH FLOW'!D43-'YTD CF'!G41 | J41: ='YTD CF'!H41 | K41: ='YTD CF'!I41-'YTD CF'!H41 | L41: ='YTD CF'!J41-'YTD CF'!I41 | M41: ='CASH FLOW'!E43-'YTD CF'!J41 | N41: ='YTD CF'!K41 | O41: ='YTD CF'!L41-'YTD CF'!K41 | P41: ='YTD CF'!M41-'YTD CF'!L41 | Q41: ='CASH FLOW'!F43-'YTD CF'!M41 | R41: ='YTD CF'!N41 | S41: ='CF DRIVERS'!S39 | T41: ='CF DRIVERS'!T39 | U41: ='CF DRIVERS'!U39 | V41: ='CF DRIVERS'!V39 | W41: ='CF DRIVERS'!W39 | X41: ='CF DRIVERS'!X39 | Y41: ='CF DRIVERS'!Y39 | Z41: ='CF DRIVERS'!Z39 | ... AK41: ='CF DRIVERS'!AK39
A42: Tax Withholdings on RSU/PSU Settlement | B42: ='YTD CF'!B42 | C42: ='YTD CF'!C42-'YTD CF'!B42 | D42: ='YTD CF'!D42-'YTD CF'!C42 | E42: ='CASH FLOW'!C44-'YTD CF'!D42 | F42: ='YTD CF'!E42 | G42: ='YTD CF'!F42-'YTD CF'!E42 | H42: ='YTD CF'!G42-'YTD CF'!F42 | I42: ='CASH FLOW'!D44-'YTD CF'!G42 | J42: ='YTD CF'!H42 | K42: ='YTD CF'!I42-'YTD CF'!H42 | L42: ='YTD CF'!J42-'YTD CF'!I42 | M42: ='CASH FLOW'!E44-'YTD CF'!J42 | N42: ='YTD CF'!K42 | O42: ='YTD CF'!L42-'YTD CF'!K42 | P42: ='YTD CF'!M42-'YTD CF'!L42 | Q42: ='CASH FLOW'!F44-'YTD CF'!M42 | R42: ='YTD CF'!N42 | S42: ='CF DRIVERS'!S40 | T42: ='CF DRIVERS'!T40 | U42: ='CF DRIVERS'!U40 | V42: ='CF DRIVERS'!V40 | W42: ='CF DRIVERS'!W40 | X42: ='CF DRIVERS'!X40 | Y42: ='CF DRIVERS'!Y40 | Z42: ='CF DRIVERS'!Z40 | ... AK42: ='CF DRIVERS'!AK40
A43: Other Financing Activities | B43: ='YTD CF'!B43 | C43: ='YTD CF'!C43-'YTD CF'!B43 | D43: ='YTD CF'!D43-'YTD CF'!C43 | E43: ='CASH FLOW'!C45-'YTD CF'!D43 | F43: ='YTD CF'!E43 | G43: ='YTD CF'!F43-'YTD CF'!E43 | H43: ='YTD CF'!G43-'YTD CF'!F43 | I43: ='CASH FLOW'!D45-'YTD CF'!G43 | J43: ='YTD CF'!H43 | K43: ='YTD CF'!I43-'YTD CF'!H43 | L43: ='YTD CF'!J43-'YTD CF'!I43 | M43: ='CASH FLOW'!E45-'YTD CF'!J43 | N43: ='YTD CF'!K43 | O43: ='YTD CF'!L43-'YTD CF'!K43 | P43: ='YTD CF'!M43-'YTD CF'!L43 | Q43: ='CASH FLOW'!F45-'YTD CF'!M43 | R43: ='YTD CF'!N43 | S43: ='CF DRIVERS'!S41 | T43: ='CF DRIVERS'!T41 | U43: ='CF DRIVERS'!U41 | V43: ='CF DRIVERS'!V41 | W43: ='CF DRIVERS'!W41 | X43: ='CF DRIVERS'!X41 | Y43: ='CF DRIVERS'!Y41 | Z43: ='CF DRIVERS'!Z41 | ... AK43: ='CF DRIVERS'!AK41
A44: Cash Flow from Financing | B44: ='YTD CF'!B44 | C44: ='YTD CF'!C44-'YTD CF'!B44 | D44: ='YTD CF'!D44-'YTD CF'!C44 | E44: ='CASH FLOW'!C46-'YTD CF'!D44 | F44: ='YTD CF'!E44 | G44: ='YTD CF'!F44-'YTD CF'!E44 | H44: ='YTD CF'!G44-'YTD CF'!F44 | I44: ='CASH FLOW'!D46-'YTD CF'!G44 | J44: ='YTD CF'!H44 | K44: ='YTD CF'!I44-'YTD CF'!H44 | L44: ='YTD CF'!J44-'YTD CF'!I44 | M44: ='CASH FLOW'!E46-'YTD CF'!J44 | N44: ='YTD CF'!K44 | O44: ='YTD CF'!L44-'YTD CF'!K44 | P44: ='YTD CF'!M44-'YTD CF'!L44 | Q44: ='CASH FLOW'!F46-'YTD CF'!M44 | R44: ='YTD CF'!N44 | S44: =SUM(S34:S43) | T44: =SUM(T34:T43) | U44: =SUM(U34:U43) | V44: =SUM(V34:V43) | W44: =SUM(W34:W43) | X44: =SUM(X34:X43) | Y44: =SUM(Y34:Y43) | Z44: =SUM(Z34:Z43) | ... AK44: =SUM(AK34:AK43)
A45: FX Effect on Cash | B45: ='YTD CF'!B45 | C45: ='YTD CF'!C45-'YTD CF'!B45 | D45: ='YTD CF'!D45-'YTD CF'!C45 | E45: ='CASH FLOW'!C47-'YTD CF'!D45 | F45: ='YTD CF'!E45 | G45: ='YTD CF'!F45-'YTD CF'!E45 | H45: ='YTD CF'!G45-'YTD CF'!F45 | I45: ='CASH FLOW'!D47-'YTD CF'!G45 | J45: ='YTD CF'!H45 | K45: ='YTD CF'!I45-'YTD CF'!H45 | L45: ='YTD CF'!J45-'YTD CF'!I45 | M45: ='CASH FLOW'!E47-'YTD CF'!J45 | N45: ='YTD CF'!K45 | O45: ='YTD CF'!L45-'YTD CF'!K45 | P45: ='YTD CF'!M45-'YTD CF'!L45 | Q45: ='CASH FLOW'!F47-'YTD CF'!M45 | R45: ='YTD CF'!N45 | S45: ='CF DRIVERS'!S42 | T45: ='CF DRIVERS'!T42 | U45: ='CF DRIVERS'!U42 | V45: ='CF DRIVERS'!V42 | W45: ='CF DRIVERS'!W42 | X45: ='CF DRIVERS'!X42 | Y45: ='CF DRIVERS'!Y42 | Z45: ='CF DRIVERS'!Z42 | ... AK45: ='CF DRIVERS'!AK42
A46: Net Change in Cash | B46: ='YTD CF'!B46 | C46: ='YTD CF'!C46-'YTD CF'!B46 | D46: ='YTD CF'!D46-'YTD CF'!C46 | E46: ='CASH FLOW'!C48-'YTD CF'!D46 | F46: ='YTD CF'!E46 | G46: ='YTD CF'!F46-'YTD CF'!E46 | H46: ='YTD CF'!G46-'YTD CF'!F46 | I46: ='CASH FLOW'!D48-'YTD CF'!G46 | J46: ='YTD CF'!H46 | K46: ='YTD CF'!I46-'YTD CF'!H46 | L46: ='YTD CF'!J46-'YTD CF'!I46 | M46: ='CASH FLOW'!E48-'YTD CF'!J46 | N46: ='YTD CF'!K46 | O46: ='YTD CF'!L46-'YTD CF'!K46 | P46: ='YTD CF'!M46-'YTD CF'!L46 | Q46: ='CASH FLOW'!F48-'YTD CF'!M46 | R46: ='YTD CF'!N46 | S46: =S25+S33+S44+S45 | T46: =T25+T33+T44+T45 | U46: =U25+U33+U44+U45 | V46: =V25+V33+V44+V45 | W46: =W25+W33+W44+W45 | X46: =X25+X33+X44+X45 | Y46: =Y25+Y33+Y44+Y45 | Z46: =Z25+Z33+Z44+Z45 | ... AK46: =AK25+AK33+AK44+AK45

Sheet IS DRIVERS
A1: Driver | B1: Q1 FY2022 | C1: Q2 FY2022 | D1: Q3 FY2022 | E1: Q4 FY2022 | F1: Q1 FY2023 | G1: Q2 FY2023 | H1: Q3 FY2023 | I1: Q4 FY2023 | J1: Q1 FY2024 | K1: Q2 FY2024 | L1: Q3 FY2024 | M1: Q4 FY2024 | N1: Q1 FY2025 | O1: Q2 FY2025 | P1: Q3 FY2025 | Q1: Q4 FY2025 | R1: Q1 FY2026 | S1: Q2 FY2026E | T1: Q3 FY2026E | U1: Q4 FY2026E | V1: Q1 FY2027E | W1: Q2 FY2027E | X1: Q3 FY2027E | Y1: Q4 FY2027E | Z1: Q1 FY2028E | AA1: Q2 FY2028E | AB1: Q3 FY2028E | AC1: Q4 FY2028E | AD1: Q1 FY2029E | AE1: Q2 FY2029E | AF1: Q3 FY2029E | AG1: Q4 FY2029E | AH1: Q1 FY2030E | AI1: Q2 FY2030E | AJ1: Q3 FY2030E | AK1: Q4 FY2030E
A2: Net Sales / Revenue — Growth % | F2: =IFERROR('QTR P&L'!F2/'QTR P&L'!B2-1,"") | G2: =IFERROR('QTR P&L'!G2/'QTR P&L'!C2-1,"") | H2: =IFERROR('QTR P&L'!H2/'QTR P&L'!D2-1,"") | I2: =IFERROR('QTR P&L'!I2/'QTR P&L'!E2-1,"") | J2: =IFERROR('QTR P&L'!J2/'QTR P&L'!F2-1,"") | K2: =IFERROR('QTR P&L'!K2/'QTR P&L'!G2-1,"") | L2: =IFERROR('QTR P&L'!L2/'QTR P&L'!H2-1,"") | M2: =IFERROR('QTR P&L'!M2/'QTR P&L'!I2-1,"") | ... R2: =IFERROR('QTR P&L'!R2/'QTR P&L'!N2-1,"") | S2: =R2 | T2: =R2 | U2: =R2 | V2: =R2 | W2: =R2 | X2: =R2 | Y2: =R2 | Z2: =R2 | AA2: =R2 | AB2: =R2 | AC2: =R2 | AD2: =R2 | AE2: =R2 | AF2: =R2 | AG2: =R2 | AH2: =R2 | AI2: =R2 | AJ2: =R2 | AK2: =R2
A3: COGS — % of Revenue | B3: =IFERROR('QTR P&L'!B3/'QTR P&L'!B2,"") | C3: =IFERROR('QTR P&L'!C3/'QTR P&L'!C2,"") | D3: =IFERROR('QTR P&L'!D3/'QTR P&L'!D2,"") | E3: =IFERROR('QTR P&L'!E3/'QTR P&L'!E2,"") | F3: =IFERROR('QTR P&L'!F3/'QTR P&L'!F2,"") | G3: =IFERROR('QTR P&L'!G3/'QTR P&L'!G2,"") | H3: =IFERROR('QTR P&L'!H3/'QTR P&L'!H2,"") | I3: =IFERROR('QTR P&L'!I3/'QTR P&L'!I2,"") | ... R3: =IFERROR('QTR P&L'!R3/'QTR P&L'!R2,"") | S3: =R3 | T3: =R3 | U3: =R3 | V3: =R3 | W3: =R3 | X3: =R3 | Y3: =R3 | Z3: =R3 | AA3: =R3 | AB3: =R3 | AC3: =R3 | AD3: =R3 | AE3: =R3 | AF3: =R3 | AG3: =R3 | AH3: =R3 | AI3: =R3 | AJ3: =R3 | AK3: =R3
A4: SG&A — % of Revenue | B4: =IFERROR('QTR P&L'!B5/'QTR P&L'!B2,"") | C4: =IFERROR('QTR P&L'!C5/'QTR P&L'!C2,"") | D4: =IFERROR('QTR P&L'!D5/'QTR P&L'!D2,"") | E4: =IFERROR('QTR P&L'!E5/'QTR P&L'!E2,"") | F4: =IFERROR('QTR P&L'!F5/'QTR P&L'!F2,"") | G4: =IFERROR('QTR P&L'!G5/'QTR P&L'!G2,"") | H4: =IFERROR('QTR P&L'!H5/'QTR P&L'!H2,"") | I4: =IFERROR('QTR P&L'!I5/'QTR P&L'!I2,"") | ... R4: =IFERROR('QTR P&L'!R5/'QTR P&L'!R2,"") | S4: =R4 | T4: =R4 | U4: =R4 | V4: =R4 | W4: =R4 | X4: =R4 | Y4: =R4 | Z4: =R4 | AA4: =R4 | AB4: =R4 | AC4: =R4 | AD4: =R4 | AE4: =R4 | AF4: =R4 | AG4: =R4 | AH4: =R4 | AI4: =R4 | AJ4: =R4 | AK4: =R4
A5: Gain on Juice Transaction | B5: ='QTR P&L'!B6 | C5: ='QTR P&L'!C6 | D5: ='QTR P&L'!D6 | E5: ='QTR P&L'!E6 | F5: ='QTR P&L'!F6 | G5: ='QTR P&L'!G6 | H5: ='QTR P&L'!H6 | I5: ='QTR P&L'!I6 | ... R5: ='QTR P&L'!R6 | S5: 0 | T5: 0 | U5: 0 | V5: 0 | W5: 0 | X5: 0 | Y5: 0 | Z5: 0 | AA5: 0 | AB5: 0 | AC5: 0 | AD5: 0 | AE5: 0 | AF5: 0 | AG5: 0 | AH5: 0 | AI5: 0 | AJ5: 0 | AK5: 0
A6: Impairment of Intangibles — % of Revenue | B6: =IFERROR('QTR P&L'!B7/'QTR P&L'!B2,"") | C6: =IFERROR('QTR P&L'!C7/'QTR P&L'!C2,"") | D6: =IFERROR('QTR P&L'!D7/'QTR P&L'!D2,"") | E6: =IFERROR('QTR P&L'!E7/'QTR P&L'!E2,"") | F6: =IFERROR('QTR P&L'!F7/'QTR P&L'!F2,"") | G6: =IFERROR('QTR P&L'!G7/'QTR P&L'!G2,"") | H6: =IFERROR('QTR P&L'!H7/'QTR P&L'!H2,"") | I6: =IFERROR('QTR P&L'!I7/'QTR P&L'!I2,"") | ... R6: =IFERROR('QTR P&L'!R7/'QTR P&L'!R2,"") | S6: =R6 | T6: =R6 | U6: =R6 | V6: =R6 | W6: =R6 | X6: =R6 | Y6: =R6 | Z6: =R6 | AA6: =R6 | AB6: =R6 | AC6: =R6 | AD6: =R6 | AE6: =R6 | AF6: =R6 | AG6: =R6 | AH6: =R6 | AI6: =R6 | AJ6: =R6 | AK6: =R6
A7: Other Pension and OPEB Benefits Income (Expense) | B7: ='QTR P&L'!B9 | C7: ='QTR P&L'!C9 | D7: ='QTR P&L'!D9 | E7: ='QTR P&L'!E9 | F7: ='QTR P&L'!F9 | G7: ='QTR P&L'!G9 | H7: ='QTR P&L'!H9 | I7: ='QTR P&L'!I9 | ... R7: ='QTR P&L'!R9 | S7: =R7 | T7: =R7 | U7: =R7 | V7: =R7 | W7: =R7 | X7: =R7 | Y7: =R7 | Z7: =R7 | AA7: =R7 | AB7: =R7 | AC7: =R7 | AD7: =R7 | AE7: =R7 | AF7: =R7 | AG7: =R7 | AH7: =R7 | AI7: =R7 | AJ7: =R7 | AK7: =R7
A8: Interest Income (Expense) | B8: ='QTR P&L'!B10 | C8: ='QTR P&L'!C10 | D8: ='QTR P&L'!D10 | E8: ='QTR P&L'!E10 | F8: ='QTR P&L'!F10 | G8: ='QTR P&L'!G10 | H8: ='QTR P&L'!H10 | I8: ='QTR P&L'!I10 | ... R8: ='QTR P&L'!R10 | S8: =R8 | T8: =R8 | U8: =R8 | V8: =R8 | W8: =R8 | X8: =R8 | Y8: =R8 | Z8: =R8 | AA8: =R8 | AB8: =R8 | AC8: =R8 | AD8: =R8 | AE8: =R8 | AF8: =R8 | AG8: =R8 | AH8: =R8 | AI8: =R8 | AJ8: =R8 | AK8: =R8
A9: Income Tax (Expense) Benefit — Effective Tax Rate % | B9: =IFERROR('QTR P&L'!B12/'QTR P&L'!B11,"") | C9: =IFERROR('QTR P&L'!C12/'QTR P&L'!C11,"") | D9: =IFERROR('QTR P&L'!D12/'QTR P&L'!D11,"") | E9: =IFERROR('QTR P&L'!E12/'QTR P&L'!E11,"") | F9: =IFERROR('QTR P&L'!F12/'QTR P&L'!F11,"") | G9: =IFERROR('QTR P&L'!G12/'QTR P&L'!G11,"") | H9: =IFERROR('QTR P&L'!H12/'QTR P&L'!H11,"") | I9: =IFERROR('QTR P&L'!I12/'QTR P&L'!I11,"") | ... R9: =IFERROR('QTR P&L'!R12/'QTR P&L'!R11,"") | S9: =R9 | T9: =R9 | U9: =R9 | V9: =R9 | W9: =R9 | X9: =R9 | Y9: =R9 | Z9: =R9 | AA9: =R9 | AB9: =R9 | AC9: =R9 | AD9: =R9 | AE9: =R9 | AF9: =R9 | AG9: =R9 | AH9: =R9 | AI9: =R9 | AJ9: =R9 | AK9: =R9
A10: Net Income (Loss) Attributable to Noncontrolling Interest | B10: ='QTR P&L'!B14 | C10: ='QTR P&L'!C14 | D10: ='QTR P&L'!D14 | E10: ='QTR P&L'!E14 | F10: ='QTR P&L'!F14 | G10: ='QTR P&L'!G14 | H10: ='QTR P&L'!H14 | I10: ='QTR P&L'!I14 | ... R10: ='QTR P&L'!R14 | S10: =R10 | T10: =R10 | U10: =R10 | V10: =R10 | W10: =R10 | X10: =R10 | Y10: =R10 | Z10: =R10 | AA10: =R10 | AB10: =R10 | AC10: =R10 | AD10: =R10 | AE10: =R10 | AF10: =R10 | AG10: =R10 | AH10: =R10 | AI10: =R10 | AJ10: =R10 | AK10: =R10

Sheet BS DRIVERS
A1: Driver | B1: Q4 FY2022 | C1: Q1 FY2023 | D1: Q2 FY2023 | E1: Q3 FY2023 | F1: Q4 FY2023 | G1: Q1 FY2024 | H1: Q2 FY2024 | I1: Q3 FY2024 | J1: Q4 FY2024 | K1: Q1 FY2025 | L1: Q2 FY2025 | M1: Q3 FY2025 | N1: Q4 FY2025 | O1: Q1 FY2026 | P1: Q2 FY2026E | Q1: Q3 FY2026E | R1: Q4 FY2026E | S1: Q1 FY2027E | T1: Q2 FY2027E | U1: Q3 FY2027E | V1: Q4 FY2027E | W1: Q1 FY2028E | X1: Q2 FY2028E | Y1: Q3 FY2028E | Z1: Q4 FY2028E | AA1: Q1 FY2029E | AB1: Q2 FY2029E | AC1: Q3 FY2029E | AD1: Q4 FY2029E | AE1: Q1 FY2030E | AF1: Q2 FY2030E | AG1: Q3 FY2030E | AH1: Q4 FY2030E
A2: Cash & Cash Equivalents | B2: ='QTR BS'!B2 | C2: ='QTR BS'!C2 | D2: ='QTR BS'!D2 | E2: ='QTR BS'!E2 | F2: ='QTR BS'!F2 | G2: ='QTR BS'!G2 | H2: ='QTR BS'!H2 | I2: ='QTR BS'!I2 | ... O2: ='QTR BS'!O2 | P2: =O2+'QTR CF'!S46 | Q2: =P2+'QTR CF'!T46 | R2: =Q2+'QTR CF'!U46 | S2: =R2+'QTR CF'!V46 | T2: =S2+'QTR CF'!W46 | U2: =T2+'QTR CF'!X46 | V2: =U2+'QTR CF'!Y46 | W2: =V2+'QTR CF'!Z46 | ... AH2: =AG2+'QTR CF'!AK46
A3: Short-Term Investments | B3: ='QTR BS'!B3 | C3: ='QTR BS'!C3 | D3: ='QTR BS'!D3 | E3: ='QTR BS'!E3 | F3: ='QTR BS'!F3 | G3: ='QTR BS'!G3 | H3: ='QTR BS'!H3 | I3: ='QTR BS'!I3 | ... O3: ='QTR BS'!O3 | P3: =O3 | Q3: =O3 | R3: =O3 | S3: =O3 | T3: =O3 | U3: =O3 | V3: =O3 | W3: =O3 | X3: =O3 | Y3: =O3 | Z3: =O3 | AA3: =O3 | AB3: =O3 | AC3: =O3 | AD3: =O3 | AE3: =O3 | AF3: =O3 | AG3: =O3 | AH3: =O3
A4: Accounts Receivable — DSO (days) | B4: =IFERROR('QTR BS'!B4/'QTR P&L'!B2*ASSUMPTIONS!$B$2,"") | C4: =IFERROR('QTR BS'!C4/'QTR P&L'!C2*ASSUMPTIONS!$B$2,"") | D4: =IFERROR('QTR BS'!D4/'QTR P&L'!D2*ASSUMPTIONS!$B$2,"") | E4: =IFERROR('QTR BS'!E4/'QTR P&L'!E2*ASSUMPTIONS!$B$2,"") | F4: =IFERROR('QTR BS'!F4/'QTR P&L'!F2*ASSUMPTIONS!$B$2,"") | G4: =IFERROR('QTR BS'!G4/'QTR P&L'!G2*ASSUMPTIONS!$B$2,"") | H4: =IFERROR('QTR BS'!H4/'QTR P&L'!H2*ASSUMPTIONS!$B$2,"") | I4: =IFERROR('QTR BS'!I4/'QTR P&L'!I2*ASSUMPTIONS!$B$2,"") | ... O4: =IFERROR('QTR BS'!O4/'QTR P&L'!O2*ASSUMPTIONS!$B$2,"") | P4: =O4 | Q4: =O4 | R4: =O4 | S4: =O4 | T4: =O4 | U4: =O4 | V4: =O4 | W4: =O4 | X4: =O4 | Y4: =O4 | Z4: =O4 | AA4: =O4 | AB4: =O4 | AC4: =O4 | AD4: =O4 | AE4: =O4 | AF4: =O4 | AG4: =O4 | AH4: =O4
A5: Inventories — DIO (days) | B5: =IFERROR('QTR BS'!B5/'QTR P&L'!B3*ASSUMPTIONS!$B$2,"") | C5: =IFERROR('QTR BS'!C5/'QTR P&L'!C3*ASSUMPTIONS!$B$2,"") | D5: =IFERROR('QTR BS'!D5/'QTR P&L'!D3*ASSUMPTIONS!$B$2,"") | E5: =IFERROR('QTR BS'!E5/'QTR P&L'!E3*ASSUMPTIONS!$B$2,"") | F5: =IFERROR('QTR BS'!F5/'QTR P&L'!F3*ASSUMPTIONS!$B$2,"") | G5: =IFERROR('QTR BS'!G5/'QTR P&L'!G3*ASSUMPTIONS!$B$2,"") | H5: =IFERROR('QTR BS'!H5/'QTR P&L'!H3*ASSUMPTIONS!$B$2,"") | I5: =IFERROR('QTR BS'!I5/'QTR P&L'!I3*ASSUMPTIONS!$B$2,"") | ... O5: =IFERROR('QTR BS'!O5/'QTR P&L'!O3*ASSUMPTIONS!$B$2,"") | P5: =O5 | Q5: =O5 | R5: =O5 | S5: =O5 | T5: =O5 | U5: =O5 | V5: =O5 | W5: =O5 | X5: =O5 | Y5: =O5 | Z5: =O5 | AA5: =O5 | AB5: =O5 | AC5: =O5 | AD5: =O5 | AE5: =O5 | AF5: =O5 | AG5: =O5 | AH5: =O5
A6: Prepaid Expenses — % of Revenue | B6: =IFERROR('QTR BS'!B6/'QTR P&L'!B2,"") | C6: =IFERROR('QTR BS'!C6/'QTR P&L'!C2,"") | D6: =IFERROR('QTR BS'!D6/'QTR P&L'!D2,"") | E6: =IFERROR('QTR BS'!E6/'QTR P&L'!E2,"") | F6: =IFERROR('QTR BS'!F6/'QTR P&L'!F2,"") | G6: =IFERROR('QTR BS'!G6/'QTR P&L'!G2,"") | H6: =IFERROR('QTR BS'!H6/'QTR P&L'!H2,"") | I6: =IFERROR('QTR BS'!I6/'QTR P&L'!I2,"") | ... O6: =IFERROR('QTR BS'!O6/'QTR P&L'!O2,"") | P6: =O6 | Q6: =O6 | R6: =O6 | S6: =O6 | T6: =O6 | U6: =O6 | V6: =O6 | W6: =O6 | X6: =O6 | Y6: =O6 | Z6: =O6 | AA6: =O6 | AB6: =O6 | AC6: =O6 | AD6: =O6 | AE6: =O6 | AF6: =O6 | AG6: =O6 | AH6: =O6
A7: Net PP&E | B7: ='QTR BS'!B8 | C7: ='QTR BS'!C8 | D7: ='QTR BS'!D8 | E7: ='QTR BS'!E8 | F7: ='QTR BS'!F8 | G7: ='QTR BS'!G8 | H7: ='QTR BS'!H8 | I7: ='QTR BS'!I8 | ... O7: ='QTR BS'!O8 | P7: =O7-'QTR CF'!S26-'QTR CF'!S3 | Q7: =P7-'QTR CF'!T26-'QTR CF'!T3 | R7: =Q7-'QTR CF'!U26-'QTR CF'!U3 | S7: =R7-'QTR CF'!V26-'QTR CF'!V3 | T7: =S7-'QTR CF'!W26-'QTR CF'!W3 | U7: =T7-'QTR CF'!X26-'QTR CF'!X3 | V7: =U7-'QTR CF'!Y26-'QTR CF'!Y3 | W7: =V7-'QTR CF'!Z26-'QTR CF'!Z3 | ... AH7: =AG7-'QTR CF'!AK26-'QTR CF'!AK3
A8: Intangible Assets | B8: ='QTR BS'!B9 | C8: ='QTR BS'!C9 | D8: ='QTR BS'!D9 | E8: ='QTR BS'!E9 | F8: ='QTR BS'!F9 | G8: ='QTR BS'!G9 | H8: ='QTR BS'!H9 | I8: ='QTR BS'!I9 | ... O8: ='QTR BS'!O9 | P8: =O8 | Q8: =O8 | R8: =O8 | S8: =O8 | T8: =O8 | U8: =O8 | V8: =O8 | W8: =O8 | X8: =O8 | Y8: =O8 | Z8: =O8 | AA8: =O8 | AB8: =O8 | AC8: =O8 | AD8: =O8 | AE8: =O8 | AF8: =O8 | AG8: =O8 | AH8: =O8
A9: Goodwill | B9: ='QTR BS'!B10 | C9: ='QTR BS'!C10 | D9: ='QTR BS'!D10 | E9: ='QTR BS'!E10 | F9: ='QTR BS'!F10 | G9: ='QTR BS'!G10 | H9: ='QTR BS'!H10 | I9: ='QTR BS'!I10 | ... O9: ='QTR BS'!O10 | P9: =O9 | Q9: =O9 | R9: =O9 | S9: =O9 | T9: =O9 | U9: =O9 | V9: =O9 | W9: =O9 | X9: =O9 | Y9: =O9 | Z9: =O9 | AA9: =O9 | AB9: =O9 | AC9: =O9 | AD9: =O9 | AE9: =O9 | AF9: =O9 | AG9: =O9 | AH9: =O9
A10: Equity Method Investments | B10: ='QTR BS'!B11 | C10: ='QTR BS'!C11 | D10: ='QTR BS'!D11 | E10: ='QTR BS'!E11 | F10: ='QTR BS'!F11 | G10: ='QTR BS'!G11 | H10: ='QTR BS'!H11 | I10: ='QTR BS'!I11 | ... O10: ='QTR BS'!O11 | P10: =O10 | Q10: =O10 | R10: =O10 | S10: =O10 | T10: =O10 | U10: =O10 | V10: =O10 | W10: =O10 | X10: =O10 | Y10: =O10 | Z10: =O10 | AA10: =O10 | AB10: =O10 | AC10: =O10 | AD10: =O10 | AE10: =O10 | AF10: =O10 | AG10: =O10 | AH10: =O10
A11: Deferred Tax Assets | B11: ='QTR BS'!B12 | C11: ='QTR BS'!C12 | D11: ='QTR BS'!D12 | E11: ='QTR BS'!E12 | F11: ='QTR BS'!F12 | G11: ='QTR BS'!G12 | H11: ='QTR BS'!H12 | I11: ='QTR BS'!I12 | ... O11: ='QTR BS'!O12 | P11: =O11-'QTR CF'!S16 | Q11: =P11-'QTR CF'!T16 | R11: =Q11-'QTR CF'!U16 | S11: =R11-'QTR CF'!V16 | T11: =S11-'QTR CF'!W16 | U11: =T11-'QTR CF'!X16 | V11: =U11-'QTR CF'!Y16 | W11: =V11-'QTR CF'!Z16 | ... AH11: =AG11-'QTR CF'!AK16
A12: Other Non-Current Assets — % of Revenue | B12: =IFERROR('QTR BS'!B13/'QTR P&L'!B2,"") | C12: =IFERROR('QTR BS'!C13/'QTR P&L'!C2,"") | D12: =IFERROR('QTR BS'!D13/'QTR P&L'!D2,"") | E12: =IFERROR('QTR BS'!E13/'QTR P&L'!E2,"") | F12: =IFERROR('QTR BS'!F13/'QTR P&L'!F2,"") | G12: =IFERROR('QTR BS'!G13/'QTR P&L'!G2,"") | H12: =IFERROR('QTR BS'!H13/'QTR P&L'!H2,"") | I12: =IFERROR('QTR BS'!I13/'QTR P&L'!I2,"") | ... O12: =IFERROR('QTR BS'!O13/'QTR P&L'!O2,"") | P12: =O12 | Q12: =O12 | R12: =O12 | S12: =O12 | T12: =O12 | U12: =O12 | V12: =O12 | W12: =O12 | X12: =O12 | Y12: =O12 | Z12: =O12 | AA12: =O12 | AB12: =O12 | AC12: =O12 | AD12: =O12 | AE12: =O12 | AF12: =O12 | AG12: =O12 | AH12: =O12
A13: Short-Term Debt Obligations | B13: ='QTR BS'!B15 | C13: ='QTR BS'!C15 | D13: ='QTR BS'!D15 | E13: ='QTR BS'!E15 | F13: ='QTR BS'!F15 | G13: ='QTR BS'!G15 | H13: ='QTR BS'!H15 | I13: ='QTR BS'!I15 | ... O13: ='QTR BS'!O15 | P13: =O13 | Q13: =O13 | R13: =O13 | S13: =O13 | T13: =O13 | U13: =O13 | V13: =O13 | W13: =O13 | X13: =O13 | Y13: =O13 | Z13: =O13 | AA13: =O13 | AB13: =O13 | AC13: =O13 | AD13: =O13 | AE13: =O13 | AF13: =O13 | AG13: =O13 | AH13: =O13
A14: Accrued Expenses — % of Revenue | B14: =IFERROR('QTR BS'!B16/'QTR P&L'!B2,"") | C14: =IFERROR('QTR BS'!C16/'QTR P&L'!C2,"") | D14: =IFERROR('QTR BS'!D16/'QTR P&L'!D2,"") | E14: =IFERROR('QTR BS'!E16/'QTR P&L'!E2,"") | F14: =IFERROR('QTR BS'!F16/'QTR P&L'!F2,"") | G14: =IFERROR('QTR BS'!G16/'QTR P&L'!G2,"") | H14: =IFERROR('QTR BS'!H16/'QTR P&L'!H2,"") | I14: =IFERROR('QTR BS'!I16/'QTR P&L'!I2,"") | ... O14: =IFERROR('QTR BS'!O16/'QTR P&L'!O2,"") | P14: =O14 | Q14: =O14 | R14: =O14 | S14: =O14 | T14: =O14 | U14: =O14 | V14: =O14 | W14: =O14 | X14: =O14 | Y14: =O14 | Z14: =O14 | AA14: =O14 | AB14: =O14 | AC14: =O14 | AD14: =O14 | AE14: =O14 | AF14: =O14 | AG14: =O14 | AH14: =O14
A15: Long-Term Debt | B15: ='QTR BS'!B18 | C15: ='QTR BS'!C18 | D15: ='QTR BS'!D18 | E15: ='QTR BS'!E18 | F15: ='QTR BS'!F18 | G15: ='QTR BS'!G18 | H15: ='QTR BS'!H18 | I15: ='QTR BS'!I18 | ... O15: ='QTR BS'!O18 | P15: =O15 | Q15: =O15 | R15: =O15 | S15: =O15 | T15: =O15 | U15: =O15 | V15: =O15 | W15: =O15 | X15: =O15 | Y15: =O15 | Z15: =O15 | AA15: =O15 | AB15: =O15 | AC15: =O15 | AD15: =O15 | AE15: =O15 | AF15: =O15 | AG15: =O15 | AH15: =O15
A16: Deferred Tax Liability | B16: ='QTR BS'!B19 | C16: ='QTR BS'!C19 | D16: ='QTR BS'!D19 | E16: ='QTR BS'!E19 | F16: ='QTR BS'!F19 | G16: ='QTR BS'!G19 | H16: ='QTR BS'!H19 | I16: ='QTR BS'!I19 | ... O16: ='QTR BS'!O19 | P16: =O16 | Q16: =O16 | R16: =O16 | S16: =O16 | T16: =O16 | U16: =O16 | V16: =O16 | W16: =O16 | X16: =O16 | Y16: =O16 | Z16: =O16 | AA16: =O16 | AB16: =O16 | AC16: =O16 | AD16: =O16 | AE16: =O16 | AF16: =O16 | AG16: =O16 | AH16: =O16
A17: Other Non-Current Liabilities — % of Revenue | B17: =IFERROR('QTR BS'!B20/'QTR P&L'!B2,"") | C17: =IFERROR('QTR BS'!C20/'QTR P&L'!C2,"") | D17: =IFERROR('QTR BS'!D20/'QTR P&L'!D2,"") | E17: =IFERROR('QTR BS'!E20/'QTR P&L'!E2,"") | F17: =IFERROR('QTR BS'!F20/'QTR P&L'!F2,"") | G17: =IFERROR('QTR BS'!G20/'QTR P&L'!G2,"") | H17: =IFERROR('QTR BS'!H20/'QTR P&L'!H2,"") | I17: =IFERROR('QTR BS'!I20/'QTR P&L'!I2,"") | ... O17: =IFERROR('QTR BS'!O20/'QTR P&L'!O2,"") | P17: =O17 | Q17: =O17 | R17: =O17 | S17: =O17 | T17: =O17 | U17: =O17 | V17: =O17 | W17: =O17 | X17: =O17 | Y17: =O17 | Z17: =O17 | AA17: =O17 | AB17: =O17 | AC17: =O17 | AD17: =O17 | AE17: =O17 | AF17: =O17 | AG17: =O17 | AH17: =O17
A18: Common Stock | B18: ='QTR BS'!B22 | C18: ='QTR BS'!C22 | D18: ='QTR BS'!D22 | E18: ='QTR BS'!E22 | F18: ='QTR BS'!F22 | G18: ='QTR BS'!G22 | H18: ='QTR BS'!H22 | I18: ='QTR BS'!I22 | ... O18: ='QTR BS'!O22 | P18: =O18 | Q18: =O18 | R18: =O18 | S18: =O18 | T18: =O18 | U18: =O18 | V18: =O18 | W18: =O18 | X18: =O18 | Y18: =O18 | Z18: =O18 | AA18: =O18 | AB18: =O18 | AC18: =O18 | AD18: =O18 | AE18: =O18 | AF18: =O18 | AG18: =O18 | AH18: =O18
A19: Additional Paid-in Capital | B19: ='QTR BS'!B23 | C19: ='QTR BS'!C23 | D19: ='QTR BS'!D23 | E19: ='QTR BS'!E23 | F19: ='QTR BS'!F23 | G19: ='QTR BS'!G23 | H19: ='QTR BS'!H23 | I19: ='QTR BS'!I23 | ... O19: ='QTR BS'!O23 | P19: =O19+'QTR CF'!S9 | Q19: =P19+'QTR CF'!T9 | R19: =Q19+'QTR CF'!U9 | S19: =R19+'QTR CF'!V9 | T19: =S19+'QTR CF'!W9 | U19: =T19+'QTR CF'!X9 | V19: =U19+'QTR CF'!Y9 | W19: =V19+'QTR CF'!Z9 | ... AH19: =AG19+'QTR CF'!AK9
A20: Retained Earnings (Accumulated Deficit) | B20: ='QTR BS'!B24 | C20: ='QTR BS'!C24 | D20: ='QTR BS'!D24 | E20: ='QTR BS'!E24 | F20: ='QTR BS'!F24 | G20: ='QTR BS'!G24 | H20: ='QTR BS'!H24 | I20: ='QTR BS'!I24 | ... O20: ='QTR BS'!O24 | P20: =O20+'QTR P&L'!S13+'QTR CF'!S39 | Q20: =P20+'QTR P&L'!T13+'QTR CF'!T39 | R20: =Q20+'QTR P&L'!U13+'QTR CF'!U39 | S20: =R20+'QTR P&L'!V13+'QTR CF'!V39 | T20: =S20+'QTR P&L'!W13+'QTR CF'!W39 | U20: =T20+'QTR P&L'!X13+'QTR CF'!X39 | V20: =U20+'QTR P&L'!Y13+'QTR CF'!Y39 | W20: =V20+'QTR P&L'!Z13+'QTR CF'!Z39 | ... AH20: =AG20+'QTR P&L'!AK13+'QTR CF'!AK39
A21: Accumulated Other Comprehensive Income (Loss) | B21: ='QTR BS'!B25 | C21: ='QTR BS'!C25 | D21: ='QTR BS'!D25 | E21: ='QTR BS'!E25 | F21: ='QTR BS'!F25 | G21: ='QTR BS'!G25 | H21: ='QTR BS'!H25 | I21: ='QTR BS'!I25 | ... O21: ='QTR BS'!O25 | P21: =O21+'QTR CF'!S45 | Q21: =P21+'QTR CF'!T45 | R21: =Q21+'QTR CF'!U45 | S21: =R21+'QTR CF'!V45 | T21: =S21+'QTR CF'!W45 | U21: =T21+'QTR CF'!X45 | V21: =U21+'QTR CF'!Y45 | W21: =V21+'QTR CF'!Z45 | ... AH21: =AG21+'QTR CF'!AK45
A22: Treasury Stock | B22: ='QTR BS'!B26 | C22: ='QTR BS'!C26 | D22: ='QTR BS'!D26 | E22: ='QTR BS'!E26 | F22: ='QTR BS'!F26 | G22: ='QTR BS'!G26 | H22: ='QTR BS'!H26 | I22: ='QTR BS'!I26 | ... O22: ='QTR BS'!O26 | P22: =O22 | Q22: =O22 | R22: =O22 | S22: =O22 | T22: =O22 | U22: =O22 | V22: =O22 | W22: =O22 | X22: =O22 | Y22: =O22 | Z22: =O22 | AA22: =O22 | AB22: =O22 | AC22: =O22 | AD22: =O22 | AE22: =O22 | AF22: =O22 | AG22: =O22 | AH22: =O22
A23: Noncontrolling Interest | B23: ='QTR BS'!B27 | C23: ='QTR BS'!C27 | D23: ='QTR BS'!D27 | E23: ='QTR BS'!E27 | F23: ='QTR BS'!F27 | G23: ='QTR BS'!G27 | H23: ='QTR BS'!H27 | I23: ='QTR BS'!I27 | ... O23: ='QTR BS'!O27 | P23: =O23 | Q23: =O23 | R23: =O23 | S23: =O23 | T23: =O23 | U23: =O23 | V23: =O23 | W23: =O23 | X23: =O23 | Y23: =O23 | Z23: =O23 | AA23: =O23 | AB23: =O23 | AC23: =O23 | AD23: =O23 | AE23: =O23 | AF23: =O23 | AG23: =O23 | AH23: =O23

Sheet CF DRIVERS
A1: Driver | B1: Q1 FY2022 | C1: Q2 FY2022 | D1: Q3 FY2022 | E1: Q4 FY2022 | F1: Q1 FY2023 | G1: Q2 FY2023 | H1: Q3 FY2023 | I1: Q4 FY2023 | J1: Q1 FY2024 | K1: Q2 FY2024 | L1: Q3 FY2024 | M1: Q4 FY2024 | N1: Q1 FY2025 | O1: Q2 FY2025 | P1: Q3 FY2025 | Q1: Q4 FY2025 | R1: Q1 FY2026 | S1: Q2 FY2026E | T1: Q3 FY2026E | U1: Q4 FY2026E | V1: Q1 FY2027E | W1: Q2 FY2027E | X1: Q3 FY2027E | Y1: Q4 FY2027E | Z1: Q1 FY2028E | AA1: Q2 FY2028E | AB1: Q3 FY2028E | AC1: Q4 FY2028E | AD1: Q1 FY2029E | AE1: Q2 FY2029E | AF1: Q3 FY2029E | AG1: Q4 FY2029E | AH1: Q1 FY2030E | AI1: Q2 FY2030E | AJ1: Q3 FY2030E | AK1: Q4 FY2030E
A2: Net Income (Loss) | B2: ='QTR CF'!B2 | C2: ='QTR CF'!C2 | D2: ='QTR CF'!D2 | E2: ='QTR CF'!E2 | F2: ='QTR CF'!F2 | G2: ='QTR CF'!G2 | H2: ='QTR CF'!H2 | I2: ='QTR CF'!I2 | ... R2: ='QTR CF'!R2 | S2: ='QTR P&L'!S13 | T2: ='QTR P&L'!T13 | U2: ='QTR P&L'!U13 | V2: ='QTR P&L'!V13 | W2: ='QTR P&L'!W13 | X2: ='QTR P&L'!X13 | Y2: ='QTR P&L'!Y13 | Z2: ='QTR P&L'!Z13 | ... AK2: ='QTR P&L'!AK13
A3: Depreciation & Amortization — % of Revenue | B3: =IFERROR('QTR CF'!B3/'QTR P&L'!B2,"") | C3: =IFERROR('QTR CF'!C3/'QTR P&L'!C2,"") | D3: =IFERROR('QTR CF'!D3/'QTR P&L'!D2,"") | E3: =IFERROR('QTR CF'!E3/'QTR P&L'!E2,"") | F3: =IFERROR('QTR CF'!F3/'QTR P&L'!F2,"") | G3: =IFERROR('QTR CF'!G3/'QTR P&L'!G2,"") | H3: =IFERROR('QTR CF'!H3/'QTR P&L'!H2,"") | I3: =IFERROR('QTR CF'!I3/'QTR P&L'!I2,"") | ... R3: =IFERROR('QTR CF'!R3/'QTR P&L'!R2,"") | S3: =R3 | T3: =R3 | U3: =R3 | V3: =R3 | W3: =R3 | X3: =R3 | Y3: =R3 | Z3: =R3 | AA3: =R3 | AB3: =R3 | AC3: =R3 | AD3: =R3 | AE3: =R3 | AF3: =R3 | AG3: =R3 | AH3: =R3 | AI3: =R3 | AJ3: =R3 | AK3: =R3
A4: Gain on Juice Transaction | B4: ='QTR CF'!B4 | C4: ='QTR CF'!C4 | D4: ='QTR CF'!D4 | E4: ='QTR CF'!E4 | F4: ='QTR CF'!F4 | G4: ='QTR CF'!G4 | H4: ='QTR CF'!H4 | I4: ='QTR CF'!I4 | ... R4: ='QTR CF'!R4 | S4: 0 | T4: 0 | U4: 0 | V4: 0 | W4: 0 | X4: 0 | Y4: 0 | Z4: 0 | AA4: 0 | AB4: 0 | AC4: 0 | AD4: 0 | AE4: 0 | AF4: 0 | AG4: 0 | AH4: 0 | AI4: 0 | AJ4: 0 | AK4: 0
A5: Impairment and Other Charges | B5: ='QTR CF'!B5 | C5: ='QTR CF'!C5 | D5: ='QTR CF'!D5 | E5: ='QTR CF'!E5 | F5: ='QTR CF'!F5 | G5: ='QTR CF'!G5 | H5: ='QTR CF'!H5 | I5: ='QTR CF'!I5 | ... R5: ='QTR CF'!R5 | S5: 0 | T5: 0 | U5: 0 | V5: 0 | W5: 0 | X5: 0 | Y5: 0 | Z5: 0 | AA5: 0 | AB5: 0 | AC5: 0 | AD5: 0 | AE5: 0 | AF5: 0 | AG5: 0 | AH5: 0 | AI5: 0 | AJ5: 0 | AK5: 0
A6: Product Recall Impact | B6: ='QTR CF'!B6 | C6: ='QTR CF'!C6 | D6: ='QTR CF'!D6 | E6: ='QTR CF'!E6 | F6: ='QTR CF'!F6 | G6: ='QTR CF'!G6 | H6: ='QTR CF'!H6 | I6: ='QTR CF'!I6 | ... R6: ='QTR CF'!R6 | S6: 0 | T6: 0 | U6: 0 | V6: 0 | W6: 0 | X6: 0 | Y6: 0 | Z6: 0 | AA6: 0 | AB6: 0 | AC6: 0 | AD6: 0 | AE6: 0 | AF6: 0 | AG6: 0 | AH6: 0 | AI6: 0 | AJ6: 0 | AK6: 0
A7: Cash Payments for Product Recall | B7: ='QTR CF'!B7 | C7: ='QTR CF'!C7 | D7: ='QTR CF'!D7 | E7: ='QTR CF'!E7 | F7: ='QTR CF'!F7 | G7: ='QTR CF'!G7 | H7: ='QTR CF'!H7 | I7: ='QTR CF'!I7 | ... R7: ='QTR CF'!R7 | S7: 0 | T7: 0 | U7: 0 | V7: 0 | W7: 0 | X7: 0 | Y7: 0 | Z7: 0 | AA7: 0 | AB7: 0 | AC7: 0 | AD7: 0 | AE7: 0 | AF7: 0 | AG7: 0 | AH7: 0 | AI7: 0 | AJ7: 0 | AK7: 0
A8: Operating Lease ROU Asset Amortization | B8: ='QTR CF'!B8 | C8: ='QTR CF'!C8 | D8: ='QTR CF'!D8 | E8: ='QTR CF'!E8 | F8: ='QTR CF'!F8 | G8: ='QTR CF'!G8 | H8: ='QTR CF'!H8 | I8: ='QTR CF'!I8 | ... R8: ='QTR CF'!R8 | S8: 0 | T8: 0 | U8: 0 | V8: 0 | W8: 0 | X8: 0 | Y8: 0 | Z8: 0 | AA8: 0 | AB8: 0 | AC8: 0 | AD8: 0 | AE8: 0 | AF8: 0 | AG8: 0 | AH8: 0 | AI8: 0 | AJ8: 0 | AK8: 0
A9: Stock-Based Compensation — % of Revenue | B9: =IFERROR('QTR CF'!B9/'QTR P&L'!B2,"") | C9: =IFERROR('QTR CF'!C9/'QTR P&L'!C2,"") | D9: =IFERROR('QTR CF'!D9/'QTR P&L'!D2,"") | E9: =IFERROR('QTR CF'!E9/'QTR P&L'!E2,"") | F9: =IFERROR('QTR CF'!F9/'QTR P&L'!F2,"") | G9: =IFERROR('QTR CF'!G9/'QTR P&L'!G2,"") | H9: =IFERROR('QTR CF'!H9/'QTR P&L'!H2,"") | I9: =IFERROR('QTR CF'!I9/'QTR P&L'!I2,"") | ... R9: =IFERROR('QTR CF'!R9/'QTR P&L'!R2,"") | S9: =R9 | T9: =R9 | U9: =R9 | V9: =R9 | W9: =R9 | X9: =R9 | Y9: =R9 | Z9: =R9 | AA9: =R9 | AB9: =R9 | AC9: =R9 | AD9: =R9 | AE9: =R9 | AF9: =R9 | AG9: =R9 | AH9: =R9 | AI9: =R9 | AJ9: =R9 | AK9: =R9
A10: Restructuring and Asset Impairment Charges | B10: ='QTR CF'!B10 | C10: ='QTR CF'!C10 | D10: ='QTR CF'!D10 | E10: ='QTR CF'!E10 | F10: ='QTR CF'!F10 | G10: ='QTR CF'!G10 | H10: ='QTR CF'!H10 | I10: ='QTR CF'!I10 | ... R10: ='QTR CF'!R10 | S10: 0 | T10: 0 | U10: 0 | V10: 0 | W10: 0 | X10: 0 | Y10: 0 | Z10: 0 | AA10: 0 | AB10: 0 | AC10: 0 | AD10: 0 | AE10: 0 | AF10: 0 | AG10: 0 | AH10: 0 | AI10: 0 | AJ10: 0 | AK10: 0
A11: Cash Payments for Restructuring | B11: ='QTR CF'!B11 | C11: ='QTR CF'!C11 | D11: ='QTR CF'!D11 | E11: ='QTR CF'!E11 | F11: ='QTR CF'!F11 | G11: ='QTR CF'!G11 | H11: ='QTR CF'!H11 | I11: ='QTR CF'!I11 | ... R11: ='QTR CF'!R11 | S11: 0 | T11: 0 | U11: 0 | V11: 0 | W11: 0 | X11: 0 | Y11: 0 | Z11: 0 | AA11: 0 | AB11: 0 | AC11: 0 | AD11: 0 | AE11: 0 | AF11: 0 | AG11: 0 | AH11: 0 | AI11: 0 | AJ11: 0 | AK11: 0
A12: Acquisition and Divestiture-Related Charges | B12: ='QTR CF'!B12 | C12: ='QTR CF'!C12 | D12: ='QTR CF'!D12 | E12: ='QTR CF'!E12 | F12: ='QTR CF'!F12 | G12: ='QTR CF'!G12 | H12: ='QTR CF'!H12 | I12: ='QTR CF'!I12 | ... R12: ='QTR CF'!R12 | S12: 0 | T12: 0 | U12: 0 | V12: 0 | W12: 0 | X12: 0 | Y12: 0 | Z12: 0 | AA12: 0 | AB12: 0 | AC12: 0 | AD12: 0 | AE12: 0 | AF12: 0 | AG12: 0 | AH12: 0 | AI12: 0 | AJ12: 0 | AK12: 0
A13: Cash Payments for Acquisition and Divestiture Costs | B13: ='QTR CF'!B13 | C13: ='QTR CF'!C13 | D13: ='QTR CF'!D13 | E13: ='QTR CF'!E13 | F13: ='QTR CF'!F13 | G13: ='QTR CF'!G13 | H13: ='QTR CF'!H13 | I13: ='QTR CF'!I13 | ... R13: ='QTR CF'!R13 | S13: 0 | T13: 0 | U13: 0 | V13: 0 | W13: 0 | X13: 0 | Y13: 0 | Z13: 0 | AA13: 0 | AB13: 0 | AC13: 0 | AD13: 0 | AE13: 0 | AF13: 0 | AG13: 0 | AH13: 0 | AI13: 0 | AJ13: 0 | AK13: 0
A14: Pension and Postretirement Benefits Expense | B14: ='QTR CF'!B14 | C14: ='QTR CF'!C14 | D14: ='QTR CF'!D14 | E14: ='QTR CF'!E14 | F14: ='QTR CF'!F14 | G14: ='QTR CF'!G14 | H14: ='QTR CF'!H14 | I14: ='QTR CF'!I14 | ... R14: ='QTR CF'!R14 | S14: 0 | T14: 0 | U14: 0 | V14: 0 | W14: 0 | X14: 0 | Y14: 0 | Z14: 0 | AA14: 0 | AB14: 0 | AC14: 0 | AD14: 0 | AE14: 0 | AF14: 0 | AG14: 0 | AH14: 0 | AI14: 0 | AJ14: 0 | AK14: 0
A15: Pension and Postretirement Benefits Contributions | B15: ='QTR CF'!B15 | C15: ='QTR CF'!C15 | D15: ='QTR CF'!D15 | E15: ='QTR CF'!E15 | F15: ='QTR CF'!F15 | G15: ='QTR CF'!G15 | H15: ='QTR CF'!H15 | I15: ='QTR CF'!I15 | ... R15: ='QTR CF'!R15 | S15: 0 | T15: 0 | U15: 0 | V15: 0 | W15: 0 | X15: 0 | Y15: 0 | Z15: 0 | AA15: 0 | AB15: 0 | AC15: 0 | AD15: 0 | AE15: 0 | AF15: 0 | AG15: 0 | AH15: 0 | AI15: 0 | AJ15: 0 | AK15: 0
A16: (Benefit) Provision for Deferred Income Taxes | B16: ='QTR CF'!B16 | C16: ='QTR CF'!C16 | D16: ='QTR CF'!D16 | E16: ='QTR CF'!E16 | F16: ='QTR CF'!F16 | G16: ='QTR CF'!G16 | H16: ='QTR CF'!H16 | I16: ='QTR CF'!I16 | ... R16: ='QTR CF'!R16 | S16: =R16 | T16: =R16 | U16: =R16 | V16: =R16 | W16: =R16 | X16: =R16 | Y16: =R16 | Z16: =R16 | AA16: =R16 | AB16: =R16 | AC16: =R16 | AD16: =R16 | AE16: =R16 | AF16: =R16 | AG16: =R16 | AH16: =R16 | AI16: =R16 | AJ16: =R16 | AK16: =R16
A17: Tax Expense Related to TCJ Act | B17: ='QTR CF'!B17 | C17: ='QTR CF'!C17 | D17: ='QTR CF'!D17 | E17: ='QTR CF'!E17 | F17: ='QTR CF'!F17 | G17: ='QTR CF'!G17 | H17: ='QTR CF'!H17 | I17: ='QTR CF'!I17 | ... R17: ='QTR CF'!R17 | S17: 0 | T17: 0 | U17: 0 | V17: 0 | W17: 0 | X17: 0 | Y17: 0 | Z17: 0 | AA17: 0 | AB17: 0 | AC17: 0 | AD17: 0 | AE17: 0 | AF17: 0 | AG17: 0 | AH17: 0 | AI17: 0 | AJ17: 0 | AK17: 0
A18: Tax Payments Related to TCJ Act | B18: ='QTR CF'!B18 | C18: ='QTR CF'!C18 | D18: ='QTR CF'!D18 | E18: ='QTR CF'!E18 | F18: ='QTR CF'!F18 | G18: ='QTR CF'!G18 | H18: ='QTR CF'!H18 | I18: ='QTR CF'!I18 | ... R18: ='QTR CF'!R18 | S18: 0 | T18: 0 | U18: 0 | V18: 0 | W18: 0 | X18: 0 | Y18: 0 | Z18: 0 | AA18: 0 | AB18: 0 | AC18: 0 | AD18: 0 | AE18: 0 | AF18: 0 | AG18: 0 | AH18: 0 | AI18: 0 | AJ18: 0 | AK18: 0
A19: Accounts Receivable | B19: ='QTR CF'!B19 | C19: ='QTR CF'!C19 | D19: ='QTR CF'!D19 | E19: ='QTR CF'!E19 | F19: ='QTR CF'!F19 | G19: ='QTR CF'!G19 | H19: ='QTR CF'!H19 | I19: ='QTR CF'!I19 | ... R19: ='QTR CF'!R19 | S19: =-('QTR BS'!P4-'QTR BS'!O4) | T19: =-('QTR BS'!Q4-'QTR BS'!P4) | U19: =-('QTR BS'!R4-'QTR BS'!Q4) | V19: =-('QTR BS'!S4-'QTR BS'!R4) | W19: =-('QTR BS'!T4-'QTR BS'!S4) | X19: =-('QTR BS'!U4-'QTR BS'!T4) | Y19: =-('QTR BS'!V4-'QTR BS'!U4) | Z19: =-('QTR BS'!W4-'QTR BS'!V4) | ... AK19: =-('QTR BS'!AH4-'QTR BS'!AG4)
A20: Inventories | B20: ='QTR CF'!B20 | C20: ='QTR CF'!C20 | D20: ='QTR CF'!D20 | E20: ='QTR CF'!E20 | F20: ='QTR CF'!F20 | G20: ='QTR CF'!G20 | H20: ='QTR CF'!H20 | I20: ='QTR CF'!I20 | ... R20: ='QTR CF'!R20 | S20: =-('QTR BS'!P5-'QTR BS'!O5) | T20: =-('QTR BS'!Q5-'QTR BS'!P5) | U20: =-('QTR BS'!R5-'QTR BS'!Q5) | V20: =-('QTR BS'!S5-'QTR BS'!R5) | W20: =-('QTR BS'!T5-'QTR BS'!S5) | X20: =-('QTR BS'!U5-'QTR BS'!T5) | Y20: =-('QTR BS'!V5-'QTR BS'!U5) | Z20: =-('QTR BS'!W5-'QTR BS'!V5) | ... AK20: =-('QTR BS'!AH5-'QTR BS'!AG5)
A21: Prepaid Expenses | B21: ='QTR CF'!B21 | C21: ='QTR CF'!C21 | D21: ='QTR CF'!D21 | E21: ='QTR CF'!E21 | F21: ='QTR CF'!F21 | G21: ='QTR CF'!G21 | H21: ='QTR CF'!H21 | I21: ='QTR CF'!I21 | ... R21: ='QTR CF'!R21 | S21: =-('QTR BS'!P6-'QTR BS'!O6) | T21: =-('QTR BS'!Q6-'QTR BS'!P6) | U21: =-('QTR BS'!R6-'QTR BS'!Q6) | V21: =-('QTR BS'!S6-'QTR BS'!R6) | W21: =-('QTR BS'!T6-'QTR BS'!S6) | X21: =-('QTR BS'!U6-'QTR BS'!T6) | Y21: =-('QTR BS'!V6-'QTR BS'!U6) | Z21: =-('QTR BS'!W6-'QTR BS'!V6) | ... AK21: =-('QTR BS'!AH6-'QTR BS'!AG6)
A22: Accounts Payable | B22: ='QTR CF'!B22 | C22: ='QTR CF'!C22 | D22: ='QTR CF'!D22 | E22: ='QTR CF'!E22 | F22: ='QTR CF'!F22 | G22: ='QTR CF'!G22 | H22: ='QTR CF'!H22 | I22: ='QTR CF'!I22 | ... R22: ='QTR CF'!R22 | S22: =('QTR BS'!P16-'QTR BS'!O16) | T22: =('QTR BS'!Q16-'QTR BS'!P16) | U22: =('QTR BS'!R16-'QTR BS'!Q16) | V22: =('QTR BS'!S16-'QTR BS'!R16) | W22: =('QTR BS'!T16-'QTR BS'!S16) | X22: =('QTR BS'!U16-'QTR BS'!T16) | Y22: =('QTR BS'!V16-'QTR BS'!U16) | Z22: =('QTR BS'!W16-'QTR BS'!V16) | ... AK22: =('QTR BS'!AH16-'QTR BS'!AG16)
A23: Other Current Liabilities | B23: ='QTR CF'!B23 | C23: ='QTR CF'!C23 | D23: ='QTR CF'!D23 | E23: ='QTR CF'!E23 | F23: ='QTR CF'!F23 | G23: ='QTR CF'!G23 | H23: ='QTR CF'!H23 | I23: ='QTR CF'!I23 | ... R23: ='QTR CF'!R23 | S23: 0 | T23: 0 | U23: 0 | V23: 0 | W23: 0 | X23: 0 | Y23: 0 | Z23: 0 | AA23: 0 | AB23: 0 | AC23: 0 | AD23: 0 | AE23: 0 | AF23: 0 | AG23: 0 | AH23: 0 | AI23: 0 | AJ23: 0 | AK23: 0
A24: Other Operating Items | B24: ='QTR CF'!B24 | C24: ='QTR CF'!C24 | D24: ='QTR CF'!D24 | E24: ='QTR CF'!E24 | F24: ='QTR CF'!F24 | G24: ='QTR CF'!G24 | H24: ='QTR CF'!H24 | I24: ='QTR CF'!I24 | ... R24: ='QTR CF'!R24 | S24: =-('QTR BS'!P13-'QTR BS'!O13)+('QTR BS'!P20-'QTR BS'!O20)-('QTR BS'!P3-'QTR BS'!O3)-('QTR BS'!P9-'QTR BS'!O9)-('QTR BS'!P10-'QTR BS'!O10)-('QTR BS'!P11-'QTR BS'!O11)+('QTR BS'!P15-'QTR BS'!O15)+('QTR BS'!P18-'QTR BS'!O18)+('QTR BS'!P19-'QTR BS'!O19)+('QTR BS'!P22-'QTR BS'!O22)+('QTR BS'!P26-'QTR BS'!O26)+('QTR BS'!P27-'QTR BS'!O27) | T24: =-('QTR BS'!Q13-'QTR BS'!P13)+('QTR BS'!Q20-'QTR BS'!P20)-('QTR BS'!Q3-'QTR BS'!P3)-('QTR BS'!Q9-'QTR BS'!P9)-('QTR BS'!Q10-'QTR BS'!P10)-('QTR BS'!Q11-'QTR BS'!P11)+('QTR BS'!Q15-'QTR BS'!P15)+('QTR BS'!Q18-'QTR BS'!P18)+('QTR BS'!Q19-'QTR BS'!P19)+('QTR BS'!Q22-'QTR BS'!P22)+('QTR BS'!Q26-'QTR BS'!P26)+('QTR BS'!Q27-'QTR BS'!P27) | U24: =-('QTR BS'!R13-'QTR BS'!Q13)+('QTR BS'!R20-'QTR BS'!Q20)-('QTR BS'!R3-'QTR BS'!Q3)-('QTR BS'!R9-'QTR BS'!Q9)-('QTR BS'!R10-'QTR BS'!Q10)-('QTR BS'!R11-'QTR BS'!Q11)+('QTR BS'!R15-'QTR BS'!Q15)+('QTR BS'!R18-'QTR BS'!Q18)+('QTR BS'!R19-'QTR BS'!Q19)+('QTR BS'!R22-'QTR BS'!Q22)+('QTR BS'!R26-'QTR BS'!Q26)+('QTR BS'!R27-'QTR BS'!Q27) | V24: =-('QTR BS'!S13-'QTR BS'!R13)+('QTR BS'!S20-'QTR BS'!R20)-('QTR BS'!S3-'QTR BS'!R3)-('QTR BS'!S9-'QTR BS'!R9)-('QTR BS'!S10-'QTR BS'!R10)-('QTR BS'!S11-'QTR BS'!R11)+('QTR BS'!S15-'QTR BS'!R15)+('QTR BS'!S18-'QTR BS'!R18)+('QTR BS'!S19-'QTR BS'!R19)+('QTR BS'!S22-'QTR BS'!R22)+('QTR BS'!S26-'QTR BS'!R26)+('QTR BS'!S27-'QTR BS'!R27) | W24: =-('QTR BS'!T13-'QTR BS'!S13)+('QTR BS'!T20-'QTR BS'!S20)-('QTR BS'!T3-'QTR BS'!S3)-('QTR BS'!T9-'QTR BS'!S9)-('QTR BS'!T10-'QTR BS'!S10)-('QTR BS'!T11-'QTR BS'!S11)+('QTR BS'!T15-'QTR BS'!S15)+('QTR BS'!T18-'QTR BS'!S18)+('QTR BS'!T19-'QTR BS'!S19)+('QTR BS'!T22-'QTR BS'!S22)+('QTR BS'!T26-'QTR BS'!S26)+('QTR BS'!T27-'QTR BS'!S27) | X24: =-('QTR BS'!U13-'QTR BS'!T13)+('QTR BS'!U20-'QTR BS'!T20)-('QTR BS'!U3-'QTR BS'!T3)-('QTR BS'!U9-'QTR BS'!T9)-('QTR BS'!U10-'QTR BS'!T10)-('QTR BS'!U11-'QTR BS'!T11)+('QTR BS'!U15-'QTR BS'!T15)+('QTR BS'!U18-'QTR BS'!T18)+('QTR BS'!U19-'QTR BS'!T19)+('QTR BS'!U22-'QTR BS'!T22)+('QTR BS'!U26-'QTR BS'!T26)+('QTR BS'!U27-'QTR BS'!T27) | Y24: =-('QTR BS'!V13-'QTR BS'!U13)+('QTR BS'!V20-'QTR BS'!U20)-('QTR BS'!V3-'QTR BS'!U3)-('QTR BS'!V9-'QTR BS'!U9)-('QTR BS'!V10-'QTR BS'!U10)-('QTR BS'!V11-'QTR BS'!U11)+('QTR BS'!V15-'QTR BS'!U15)+('QTR BS'!V18-'QTR BS'!U18)+('QTR BS'!V19-'QTR BS'!U19)+('QTR BS'!V22-'QTR BS'!U22)+('QTR BS'!V26-'QTR BS'!U26)+('QTR BS'!V27-'QTR BS'!U27) | Z24: =-('QTR BS'!W13-'QTR BS'!V13)+('QTR BS'!W20-'QTR BS'!V20)-('QTR BS'!W3-'QTR BS'!V3)-('QTR BS'!W9-'QTR BS'!V9)-('QTR BS'!W10-'QTR BS'!V10)-('QTR BS'!W11-'QTR BS'!V11)+('QTR BS'!W15-'QTR BS'!V15)+('QTR BS'!W18-'QTR BS'!V18)+('QTR BS'!W19-'QTR BS'!V19)+('QTR BS'!W22-'QTR BS'!V22)+('QTR BS'!W26-'QTR BS'!V26)+('QTR BS'!W27-'QTR BS'!V27) | ... AK24: =-('QTR BS'!AH13-'QTR BS'!AG13)+('QTR BS'!AH20-'QTR BS'!AG20)-('QTR BS'!AH3-'QTR BS'!AG3)-('QTR BS'!AH9-'QTR BS'!AG9)-('QTR BS'!AH10-'QTR BS'!AG10)-('QTR BS'!AH11-'QTR BS'!AG11)+('QTR BS'!AH15-'QTR BS'!AG15)+('QTR BS'!AH18-'QTR BS'!AG18)+('QTR BS'!AH19-'QTR BS'!AG19)+('QTR BS'!AH22-'QTR BS'!AG22)+('QTR BS'!AH26-'QTR BS'!AG26)+('QTR BS'!AH27-'QTR BS'!AG27)
A25: Purchase of PP&E — % of Revenue | B25: =IFERROR('QTR CF'!B26/'QTR P&L'!B2,"") | C25: =IFERROR('QTR CF'!C26/'QTR P&L'!C2,"") | D25: =IFERROR('QTR CF'!D26/'QTR P&L'!D2,"") | E25: =IFERROR('QTR CF'!E26/'QTR P&L'!E2,"") | F25: =IFERROR('QTR CF'!F26/'QTR P&L'!F2,"") | G25: =IFERROR('QTR CF'!G26/'QTR P&L'!G2,"") | H25: =IFERROR('QTR CF'!H26/'QTR P&L'!H2,"") | I25: =IFERROR('QTR CF'!I26/'QTR P&L'!I2,"") | ... R25: =IFERROR('QTR CF'!R26/'QTR P&L'!R2,"") | S25: =R25 | T25: =R25 | U25: =R25 | V25: =R25 | W25: =R25 | X25: =R25 | Y25: =R25 | Z25: =R25 | AA25: =R25 | AB25: =R25 | AC25: =R25 | AD25: =R25 | AE25: =R25 | AF25: =R25 | AG25: =R25 | AH25: =R25 | AI25: =R25 | AJ25: =R25 | AK25: =R25
A26: Proceeds from Sale of Assets | B26: ='QTR CF'!B27 | C26: ='QTR CF'!C27 | D26: ='QTR CF'!D27 | E26: ='QTR CF'!E27 | F26: ='QTR CF'!F27 | G26: ='QTR CF'!G27 | H26: ='QTR CF'!H27 | I26: ='QTR CF'!I27 | ... R26: ='QTR CF'!R27 | S26: 0 | T26: 0 | U26: 0 | V26: 0 | W26: 0 | X26: 0 | Y26: 0 | Z26: 0 | AA26: 0 | AB26: 0 | AC26: 0 | AD26: 0 | AE26: 0 | AF26: 0 | AG26: 0 | AH26: 0 | AI26: 0 | AJ26: 0 | AK26: 0
A27: Acquisitions, Net of Cash Acquired | B27: ='QTR CF'!B28 | C27: ='QTR CF'!C28 | D27: ='QTR CF'!D28 | E27: ='QTR CF'!E28 | F27: ='QTR CF'!F28 | G27: ='QTR CF'!G28 | H27: ='QTR CF'!H28 | I27: ='QTR CF'!I28 | ... R27: ='QTR CF'!R28 | S27: 0 | T27: 0 | U27: 0 | V27: 0 | W27: 0 | X27: 0 | Y27: 0 | Z27: 0 | AA27: 0 | AB27: 0 | AC27: 0 | AD27: 0 | AE27: 0 | AF27: 0 | AG27: 0 | AH27: 0 | AI27: 0 | AJ27: 0 | AK27: 0
A28: Proceeds from Juice Transaction | B28: ='QTR CF'!B29 | C28: ='QTR CF'!C29 | D28: ='QTR CF'!D29 | E28: ='QTR CF'!E29 | F28: ='QTR CF'!F29 | G28: ='QTR CF'!G29 | H28: ='QTR CF'!H29 | I28: ='QTR CF'!I29 | ... R28: ='QTR CF'!R29 | S28: 0 | T28: 0 | U28: 0 | V28: 0 | W28: 0 | X28: 0 | Y28: 0 | Z28: 0 | AA28: 0 | AB28: 0 | AC28: 0 | AD28: 0 | AE28: 0 | AF28: 0 | AG28: 0 | AH28: 0 | AI28: 0 | AJ28: 0 | AK28: 0
A29: Proceeds from Divestitures of Businesses | B29: ='QTR CF'!B30 | C29: ='QTR CF'!C30 | D29: ='QTR CF'!D30 | E29: ='QTR CF'!E30 | F29: ='QTR CF'!F30 | G29: ='QTR CF'!G30 | H29: ='QTR CF'!H30 | I29: ='QTR CF'!I30 | ... R29: ='QTR CF'!R30 | S29: 0 | T29: 0 | U29: 0 | V29: 0 | W29: 0 | X29: 0 | Y29: 0 | Z29: 0 | AA29: 0 | AB29: 0 | AC29: 0 | AD29: 0 | AE29: 0 | AF29: 0 | AG29: 0 | AH29: 0 | AI29: 0 | AJ29: 0 | AK29: 0
A30: Net Change in Short-Term Investments | B30: ='QTR CF'!B31 | C30: ='QTR CF'!C31 | D30: ='QTR CF'!D31 | E30: ='QTR CF'!E31 | F30: ='QTR CF'!F31 | G30: ='QTR CF'!G31 | H30: ='QTR CF'!H31 | I30: ='QTR CF'!I31 | ... R30: ='QTR CF'!R31 | S30: 0 | T30: 0 | U30: 0 | V30: 0 | W30: 0 | X30: 0 | Y30: 0 | Z30: 0 | AA30: 0 | AB30: 0 | AC30: 0 | AD30: 0 | AE30: 0 | AF30: 0 | AG30: 0 | AH30: 0 | AI30: 0 | AJ30: 0 | AK30: 0
A31: Other Investing Activities | B31: ='QTR CF'!B32 | C31: ='QTR CF'!C32 | D31: ='QTR CF'!D32 | E31: ='QTR CF'!E32 | F31: ='QTR CF'!F32 | G31: ='QTR CF'!G32 | H31: ='QTR CF'!H32 | I31: ='QTR CF'!I32 | ... R31: ='QTR CF'!R32 | S31: 0 | T31: 0 | U31: 0 | V31: 0 | W31: 0 | X31: 0 | Y31: 0 | Z31: 0 | AA31: 0 | AB31: 0 | AC31: 0 | AD31: 0 | AE31: 0 | AF31: 0 | AG31: 0 | AH31: 0 | AI31: 0 | AJ31: 0 | AK31: 0
A32: Proceeds from Issuance of Long-Term Debt | B32: ='QTR CF'!B34 | C32: ='QTR CF'!C34 | D32: ='QTR CF'!D34 | E32: ='QTR CF'!E34 | F32: ='QTR CF'!F34 | G32: ='QTR CF'!G34 | H32: ='QTR CF'!H34 | I32: ='QTR CF'!I34 | ... R32: ='QTR CF'!R34 | S32: 0 | T32: 0 | U32: 0 | V32: 0 | W32: 0 | X32: 0 | Y32: 0 | Z32: 0 | AA32: 0 | AB32: 0 | AC32: 0 | AD32: 0 | AE32: 0 | AF32: 0 | AG32: 0 | AH32: 0 | AI32: 0 | AJ32: 0 | AK32: 0
A33: Repayments of Long-Term Debt | B33: ='QTR CF'!B35 | C33: ='QTR CF'!C35 | D33: ='QTR CF'!D35 | E33: ='QTR CF'!E35 | F33: ='QTR CF'!F35 | G33: ='QTR CF'!G35 | H33: ='QTR CF'!H35 | I33: ='QTR CF'!I35 | ... R33: ='QTR CF'!R35 | S33: 0 | T33: 0 | U33: 0 | V33: 0 | W33: 0 | X33: 0 | Y33: 0 | Z33: 0 | AA33: 0 | AB33: 0 | AC33: 0 | AD33: 0 | AE33: 0 | AF33: 0 | AG33: 0 | AH33: 0 | AI33: 0 | AJ33: 0 | AK33: 0
A34: Proceeds from Short-Term Debt | B34: ='QTR CF'!B36 | C34: ='QTR CF'!C36 | D34: ='QTR CF'!D36 | E34: ='QTR CF'!E36 | F34: ='QTR CF'!F36 | G34: ='QTR CF'!G36 | H34: ='QTR CF'!H36 | I34: ='QTR CF'!I36 | ... R34: ='QTR CF'!R36 | S34: 0 | T34: 0 | U34: 0 | V34: 0 | W34: 0 | X34: 0 | Y34: 0 | Z34: 0 | AA34: 0 | AB34: 0 | AC34: 0 | AD34: 0 | AE34: 0 | AF34: 0 | AG34: 0 | AH34: 0 | AI34: 0 | AJ34: 0 | AK34: 0
A35: Repayments of Short-Term Debt | B35: ='QTR CF'!B37 | C35: ='QTR CF'!C37 | D35: ='QTR CF'!D37 | E35: ='QTR CF'!E37 | F35: ='QTR CF'!F37 | G35: ='QTR CF'!G37 | H35: ='QTR CF'!H37 | I35: ='QTR CF'!I37 | ... R35: ='QTR CF'!R37 | S35: 0 | T35: 0 | U35: 0 | V35: 0 | W35: 0 | X35: 0 | Y35: 0 | Z35: 0 | AA35: 0 | AB35: 0 | AC35: 0 | AD35: 0 | AE35: 0 | AF35: 0 | AG35: 0 | AH35: 0 | AI35: 0 | AJ35: 0 | AK35: 0
A36: Net Change in Other Short-Term Debt | B36: ='QTR CF'!B38 | C36: ='QTR CF'!C38 | D36: ='QTR CF'!D38 | E36: ='QTR CF'!E38 | F36: ='QTR CF'!F38 | G36: ='QTR CF'!G38 | H36: ='QTR CF'!H38 | I36: ='QTR CF'!I38 | ... R36: ='QTR CF'!R38 | S36: 0 | T36: 0 | U36: 0 | V36: 0 | W36: 0 | X36: 0 | Y36: 0 | Z36: 0 | AA36: 0 | AB36: 0 | AC36: 0 | AD36: 0 | AE36: 0 | AF36: 0 | AG36: 0 | AH36: 0 | AI36: 0 | AJ36: 0 | AK36: 0
A37: Common Dividends — % of Net Income | B37: =IFERROR('QTR CF'!B39/'QTR P&L'!B13,"") | C37: =IFERROR('QTR CF'!C39/'QTR P&L'!C13,"") | D37: =IFERROR('QTR CF'!D39/'QTR P&L'!D13,"") | E37: =IFERROR('QTR CF'!E39/'QTR P&L'!E13,"") | F37: =IFERROR('QTR CF'!F39/'QTR P&L'!F13,"") | G37: =IFERROR('QTR CF'!G39/'QTR P&L'!G13,"") | H37: =IFERROR('QTR CF'!H39/'QTR P&L'!H13,"") | I37: =IFERROR('QTR CF'!I39/'QTR P&L'!I13,"") | ... R37: =IFERROR('QTR CF'!R39/'QTR P&L'!R13,"") | S37: =R37 | T37: =R37 | U37: =R37 | V37: =R37 | W37: =R37 | X37: =R37 | Y37: =R37 | Z37: =R37 | AA37: =R37 | AB37: =R37 | AC37: =R37 | AD37: =R37 | AE37: =R37 | AF37: =R37 | AG37: =R37 | AH37: =R37 | AI37: =R37 | AJ37: =R37 | AK37: =R37
A38: Share Repurchases | B38: ='QTR CF'!B40 | C38: ='QTR CF'!C40 | D38: ='QTR CF'!D40 | E38: ='QTR CF'!E40 | F38: ='QTR CF'!F40 | G38: ='QTR CF'!G40 | H38: ='QTR CF'!H40 | I38: ='QTR CF'!I40 | ... R38: ='QTR CF'!R40 | S38: 0 | T38: 0 | U38: 0 | V38: 0 | W38: 0 | X38: 0 | Y38: 0 | Z38: 0 | AA38: 0 | AB38: 0 | AC38: 0 | AD38: 0 | AE38: 0 | AF38: 0 | AG38: 0 | AH38: 0 | AI38: 0 | AJ38: 0 | AK38: 0
A39: Proceeds from Exercise of Stock Options | B39: ='QTR CF'!B41 | C39: ='QTR CF'!C41 | D39: ='QTR CF'!D41 | E39: ='QTR CF'!E41 | F39: ='QTR CF'!F41 | G39: ='QTR CF'!G41 | H39: ='QTR CF'!H41 | I39: ='QTR CF'!I41 | ... R39: ='QTR CF'!R41 | S39: 0 | T39: 0 | U39: 0 | V39: 0 | W39: 0 | X39: 0 | Y39: 0 | Z39: 0 | AA39: 0 | AB39: 0 | AC39: 0 | AD39: 0 | AE39: 0 | AF39: 0 | AG39: 0 | AH39: 0 | AI39: 0 | AJ39: 0 | AK39: 0
A40: Tax Withholdings on RSU/PSU Settlement | B40: ='QTR CF'!B42 | C40: ='QTR CF'!C42 | D40: ='QTR CF'!D42 | E40: ='QTR CF'!E42 | F40: ='QTR CF'!F42 | G40: ='QTR CF'!G42 | H40: ='QTR CF'!H42 | I40: ='QTR CF'!I42 | ... R40: ='QTR CF'!R42 | S40: 0 | T40: 0 | U40: 0 | V40: 0 | W40: 0 | X40: 0 | Y40: 0 | Z40: 0 | AA40: 0 | AB40: 0 | AC40: 0 | AD40: 0 | AE40: 0 | AF40: 0 | AG40: 0 | AH40: 0 | AI40: 0 | AJ40: 0 | AK40: 0
A41: Other Financing Activities | B41: ='QTR CF'!B43 | C41: ='QTR CF'!C43 | D41: ='QTR CF'!D43 | E41: ='QTR CF'!E43 | F41: ='QTR CF'!F43 | G41: ='QTR CF'!G43 | H41: ='QTR CF'!H43 | I41: ='QTR CF'!I43 | ... R41: ='QTR CF'!R43 | S41: 0 | T41: 0 | U41: 0 | V41: 0 | W41: 0 | X41: 0 | Y41: 0 | Z41: 0 | AA41: 0 | AB41: 0 | AC41: 0 | AD41: 0 | AE41: 0 | AF41: 0 | AG41: 0 | AH41: 0 | AI41: 0 | AJ41: 0 | AK41: 0
A42: FX Effect on Cash | B42: ='QTR CF'!B45 | C42: ='QTR CF'!C45 | D42: ='QTR CF'!D45 | E42: ='QTR CF'!E45 | F42: ='QTR CF'!F45 | G42: ='QTR CF'!G45 | H42: ='QTR CF'!H45 | I42: ='QTR CF'!I45 | ... R42: ='QTR CF'!R45 | S42: =R42 | T42: =R42 | U42: =R42 | V42: =R42 | W42: =R42 | X42: =R42 | Y42: =R42 | Z42: =R42 | AA42: =R42 | AB42: =R42 | AC42: =R42 | AD42: =R42 | AE42: =R42 | AF42: =R42 | AG42: =R42 | AH42: =R42 | AI42: =R42 | AJ42: =R42 | AK42: =R42
