Workbook

Sheet ASSUMPTIONS
A1: Assumption | B1: Value | C1: Note
A2: Days in Quarter | B2: 91 | C2: Used by DSO/DIO/DPO ratios. Approximation; varies 89-92 by quarter.

Sheet ANNL P&L
B1: FY2021 | C1: FY2022 | D1: FY2023 | E1: FY2024 | F1: FY2025 | G1: FY2026E | H1: FY2027E | I1: FY2028E | J1: FY2029E | K1: FY2030E | L1: FY2031E
A2: Net Sales / Revenue | B2: 314272 | C2: 653604 | D2: 1318014 | E2: 1355630 | F2: 2515269 | G2: ='QTR P&L'!W2+'QTR P&L'!X2+'QTR P&L'!Y2+'QTR P&L'!Z2 -> 2852064.4 | H2: ='QTR P&L'!AA2+'QTR P&L'!AB2+'QTR P&L'!AC2+'QTR P&L'!AD2 -> 2797736.7 | I2: ='QTR P&L'!AE2+'QTR P&L'!AF2+'QTR P&L'!AG2+'QTR P&L'!AH2 -> 2744443.9 | J2: ='QTR P&L'!AI2+'QTR P&L'!AJ2+'QTR P&L'!AK2+'QTR P&L'!AL2 -> 2692166.2 | K2: ='QTR P&L'!AM2+'QTR P&L'!AN2+'QTR P&L'!AO2+'QTR P&L'!AP2 -> 2640884.3
A3: COGS | B3: -186103 | C3: -382735 | D3: -684875 | E3: -675423 | F3: -1247936 | G3: ='QTR P&L'!W3+'QTR P&L'!X3+'QTR P&L'!Y3+'QTR P&L'!Z3 -> -1501062 | H3: ='QTR P&L'!AA3+'QTR P&L'!AB3+'QTR P&L'!AC3+'QTR P&L'!AD3 -> -1472468.9 | I3: ='QTR P&L'!AE3+'QTR P&L'!AF3+'QTR P&L'!AG3+'QTR P&L'!AH3 -> -1444420.5 | J3: ='QTR P&L'!AI3+'QTR P&L'!AJ3+'QTR P&L'!AK3+'QTR P&L'!AL3 -> -1416906.4 | K3: ='QTR P&L'!AM3+'QTR P&L'!AN3+'QTR P&L'!AO3+'QTR P&L'!AP3 -> -1389916.4
A4: Gross Profit (Loss) | B4: =B2+B3 -> 128169 | C4: =C2+C3 -> 270869 | D4: =D2+D3 -> 633139 | E4: =E2+E3 -> 680207 | F4: =F2+F3 -> 1267333 | G4: =G2+G3 -> 1351002.4 | H4: =H2+H3 -> 1325267.8 | I4: =I2+I3 -> 1300023.3 | ... L4: =L2+L3 -> 0
A5: SG&A | B5: -132259 | C5: -428670 | D5: -366773 | E5: -524479 | F5: -798810 | G5: ='QTR P&L'!W8+'QTR P&L'!X8+'QTR P&L'!Y8+'QTR P&L'!Z8 -> -928825.54 | H5: ='QTR P&L'!AA8+'QTR P&L'!AB8+'QTR P&L'!AC8+'QTR P&L'!AD8 -> -911132.75 | I5: ='QTR P&L'!AE8+'QTR P&L'!AF8+'QTR P&L'!AG8+'QTR P&L'!AH8 -> -893776.99 | J5: ='QTR P&L'!AI8+'QTR P&L'!AJ8+'QTR P&L'!AK8+'QTR P&L'!AL8 -> -876751.82 | K5: ='QTR P&L'!AM8+'QTR P&L'!AN8+'QTR P&L'!AO8+'QTR P&L'!AP8 -> -860050.96
A6: Distributor Termination Fees | B6: 0 | C6: 0 | D6: 0 | E6: 0 | F6: -327461 | G6: ='QTR P&L'!W9+'QTR P&L'!X9+'QTR P&L'!Y9+'QTR P&L'!Z9 -> 0 | H6: ='QTR P&L'!AA9+'QTR P&L'!AB9+'QTR P&L'!AC9+'QTR P&L'!AD9 -> 0 | I6: ='QTR P&L'!AE9+'QTR P&L'!AF9+'QTR P&L'!AG9+'QTR P&L'!AH9 -> 0 | J6: ='QTR P&L'!AI9+'QTR P&L'!AJ9+'QTR P&L'!AK9+'QTR P&L'!AL9 -> 0 | K6: ='QTR P&L'!AM9+'QTR P&L'!AN9+'QTR P&L'!AO9+'QTR P&L'!AP9 -> 0
A7: Income (Loss) from Operations | B7: =B4+SUM(B5:B6) -> -4090 | C7: =C4+SUM(C5:C6) -> -157801 | D7: =D4+SUM(D5:D6) -> 266366 | E7: =E4+SUM(E5:E6) -> 155728 | F7: =F4+SUM(F5:F6) -> 141062 | G7: =G4+SUM(G5:G6) -> 422176.9 | H7: =H4+SUM(H5:H6) -> 414135.04 | I7: =I4+SUM(I5:I6) -> 406246.36 | ... L7: =L4+SUM(L5:L6) -> 0
A8: Interest Income (Expense) | B8: 307 | C8: 5529 | D8: 26629 | E8: 39263 | F8: -27892 | G8: ='QTR P&L'!W11+'QTR P&L'!X11+'QTR P&L'!Y11+'QTR P&L'!Z11 -> -33200 | H8: ='QTR P&L'!AA11+'QTR P&L'!AB11+'QTR P&L'!AC11+'QTR P&L'!AD11 -> -33200 | I8: ='QTR P&L'!AE11+'QTR P&L'!AF11+'QTR P&L'!AG11+'QTR P&L'!AH11 -> -33200 | J8: ='QTR P&L'!AI11+'QTR P&L'!AJ11+'QTR P&L'!AK11+'QTR P&L'!AL11 -> -33200 | K8: ='QTR P&L'!AM11+'QTR P&L'!AN11+'QTR P&L'!AO11+'QTR P&L'!AP11 -> -33200
A9: Foreign Currency Gain (Loss) | B9: -276 | C9: -392 | D9: -1246 | E9: -1734 | F9: 0 | G9: ='QTR P&L'!W12+'QTR P&L'!X12+'QTR P&L'!Y12+'QTR P&L'!Z12 -> 0 | H9: ='QTR P&L'!AA12+'QTR P&L'!AB12+'QTR P&L'!AC12+'QTR P&L'!AD12 -> 0 | I9: ='QTR P&L'!AE12+'QTR P&L'!AF12+'QTR P&L'!AG12+'QTR P&L'!AH12 -> 0 | J9: ='QTR P&L'!AI12+'QTR P&L'!AJ12+'QTR P&L'!AK12+'QTR P&L'!AL12 -> 0 | K9: ='QTR P&L'!AM12+'QTR P&L'!AN12+'QTR P&L'!AO12+'QTR P&L'!AP12 -> 0
A10: Other Income (Expense) | B10: 0 | C10: 0 | D10: 0 | E10: 1793 | F10: 11863 | G10: ='QTR P&L'!W13+'QTR P&L'!X13+'QTR P&L'!Y13+'QTR P&L'!Z13 -> 19364 | H10: ='QTR P&L'!AA13+'QTR P&L'!AB13+'QTR P&L'!AC13+'QTR P&L'!AD13 -> 19364 | I10: ='QTR P&L'!AE13+'QTR P&L'!AF13+'QTR P&L'!AG13+'QTR P&L'!AH13 -> 19364 | J10: ='QTR P&L'!AI13+'QTR P&L'!AJ13+'QTR P&L'!AK13+'QTR P&L'!AL13 -> 19364 | K10: ='QTR P&L'!AM13+'QTR P&L'!AN13+'QTR P&L'!AO13+'QTR P&L'!AP13 -> 19364
A11: Pre-Tax Income (Loss) | B11: =B7+SUM(B8:B10) -> -4059 | C11: =C7+SUM(C8:C10) -> -152664 | D11: =D7+SUM(D8:D10) -> 291749 | E11: =E7+SUM(E8:E10) -> 195050 | F11: =F7+SUM(F8:F10) -> 125033 | G11: =G7+SUM(G8:G10) -> 408340.9 | H11: =H7+SUM(H8:H10) -> 400299.04 | I11: =I7+SUM(I8:I10) -> 392410.36 | ... L11: =L7+SUM(L8:L10) -> 0
A12: Income Tax (Expense) Benefit | B12: 7996 | C12: -34618 | D12: -64948 | E12: -49976 | F12: -17034 | G12: ='QTR P&L'!W16+'QTR P&L'!X16+'QTR P&L'!Y16+'QTR P&L'!Z16 -> 38529.202 | H12: ='QTR P&L'!AA16+'QTR P&L'!AB16+'QTR P&L'!AC16+'QTR P&L'!AD16 -> 37770.408 | I12: ='QTR P&L'!AE16+'QTR P&L'!AF16+'QTR P&L'!AG16+'QTR P&L'!AH16 -> 37026.068 | J12: ='QTR P&L'!AI16+'QTR P&L'!AJ16+'QTR P&L'!AK16+'QTR P&L'!AL16 -> 36295.907 | K12: ='QTR P&L'!AM16+'QTR P&L'!AN16+'QTR P&L'!AO16+'QTR P&L'!AP16 -> 35579.654
A13: Net Income (Loss) | B13: =B11+B12 -> 3937 | C13: =C11+C12 -> -187282 | D13: =D11+D12 -> 226801 | E13: =E11+E12 -> 145074 | F13: =F11+F12 -> 107999 | G13: =G11+G12 -> 446870.1 | H13: =H11+H12 -> 438069.45 | I13: =I11+I12 -> 429436.43 | ... L13: =L11+L12 -> 0
A14: Preferred Dividends | B14: 0 | C14: -11526 | D14: -27462 | E14: -27500 | F14: -37608 | G14: ='QTR P&L'!W18+'QTR P&L'!X18+'QTR P&L'!Y18+'QTR P&L'!Z18 -> -57228 | H14: ='QTR P&L'!AA18+'QTR P&L'!AB18+'QTR P&L'!AC18+'QTR P&L'!AD18 -> -57228 | I14: ='QTR P&L'!AE18+'QTR P&L'!AF18+'QTR P&L'!AG18+'QTR P&L'!AH18 -> -57228 | J14: ='QTR P&L'!AI18+'QTR P&L'!AJ18+'QTR P&L'!AK18+'QTR P&L'!AL18 -> -57228 | K14: ='QTR P&L'!AM18+'QTR P&L'!AN18+'QTR P&L'!AO18+'QTR P&L'!AP18 -> -57228
A15: Income Allocated to Participating Preferred | B15: 0 | C15: 0 | D15: -17348 | E15: -10117 | F15: -6554 | G15: ='QTR P&L'!W19+'QTR P&L'!X19+'QTR P&L'!Y19+'QTR P&L'!Z19 -> -5128 | H15: ='QTR P&L'!AA19+'QTR P&L'!AB19+'QTR P&L'!AC19+'QTR P&L'!AD19 -> -5128 | I15: ='QTR P&L'!AE19+'QTR P&L'!AF19+'QTR P&L'!AG19+'QTR P&L'!AH19 -> -5128 | J15: ='QTR P&L'!AI19+'QTR P&L'!AJ19+'QTR P&L'!AK19+'QTR P&L'!AL19 -> -5128 | K15: ='QTR P&L'!AM19+'QTR P&L'!AN19+'QTR P&L'!AO19+'QTR P&L'!AP19 -> -5128
A16: Net Income (Loss) Attributable to Common Shareholders | B16: =B13+B14+B15 -> 3937 | C16: =C13+C14+C15 -> -198808 | D16: =D13+D14+D15 -> 181991 | E16: =E13+E14+E15 -> 107457 | F16: =F13+F14+F15 -> 63837 | G16: =G13+G14+G15 -> 384514.1 | H16: =H13+H14+H15 -> 375713.45 | I16: =I13+I14+I15 -> 367080.43 | ... L16: =L13+L14+L15 -> 0

Sheet BALANCE SHEET
B1: FY2022 | C1: FY2023 | D1: FY2024 | E1: FY2025 | F1: FY2026E | G1: FY2027E | H1: FY2028E | I1: FY2029E | J1: FY2030E | K1: FY2031E
A2: Cash, Cash Equivalents & Restricted Cash | B2: 652927 | C2: 755981 | D2: 890190 | E2: 539987 | F2: ='QTR BS'!W2 -> 539987 | G2: ='QTR BS'!AA2 -> 539987 | H2: ='QTR BS'!AE2 -> 539987 | I2: ='QTR BS'!AI2 -> 539987 | J2: ='QTR BS'!AM2 -> 539987
A3: Accounts Receivable | B3: 63311 | C3: 183703 | D3: 270342 | E3: 755499 | F3: ='QTR BS'!W3 -> 741107.83 | G3: ='QTR BS'!AA3 -> 726990.79 | H3: ='QTR BS'!AE3 -> 713142.67 | I3: ='QTR BS'!AI3 -> 699558.32 | J3: ='QTR BS'!AM3 -> 686232.75
A4: Note Receivable - Current | B4: 2979 | C4: 2318 | D4: 0 | E4: 0 | F4: ='QTR BS'!W4 -> 0 | G4: ='QTR BS'!AA4 -> 0 | H4: ='QTR BS'!AE4 -> 0 | I4: ='QTR BS'!AI4 -> 0 | J4: ='QTR BS'!AM4 -> 0
A5: Inventories | B5: 173289 | C5: 229275 | D5: 131165 | E5: 337698 | F5: ='QTR BS'!W5 -> 331265.34 | G5: ='QTR BS'!AA5 -> 324955.21 | H5: ='QTR BS'!AE5 -> 318765.28 | I5: ='QTR BS'!AI5 -> 312693.26 | J5: ='QTR BS'!AM5 -> 306736.91
A6: Prepaid Expenses | B6: 11341 | C6: 19503 | D6: 18759 | E6: 128806 | F6: ='QTR BS'!W6 -> 126352.43 | G6: ='QTR BS'!AA6 -> 123945.6 | H6: ='QTR BS'!AE6 -> 121584.61 | I6: ='QTR BS'!AI6 -> 119268.6 | J6: ='QTR BS'!AM6 -> 116996.71
A7: Deferred Other Costs - Current | B7: 14124 | C7: 14124 | D7: 14124 | E7: 49164 | F7: ='QTR BS'!W7 -> 48227.497 | G7: ='QTR BS'!AA7 -> 47308.832 | H7: ='QTR BS'!AE7 -> 46407.667 | I7: ='QTR BS'!AI7 -> 45523.668 | J7: ='QTR BS'!AM7 -> 44656.507
A8: Total Current Assets | B8: =SUM(B2:B7) -> 917971 | C8: =SUM(C2:C7) -> 1204904 | D8: =SUM(D2:D7) -> 1324580 | E8: =SUM(E2:E7) -> 1811154 | F8: =SUM(F2:F7) -> 1786940.1 | G8: =SUM(G2:G7) -> 1763187.4 | H8: =SUM(H2:H7) -> 1739887.2 | I8: =SUM(I2:I7) -> 1717030.9 | ... K8: =SUM(K2:K7) -> 0
A9: Note Receivable - Non-Current | B9: 3574 | C9: 0 | D9: 0 | E9: 0 | F9: ='QTR BS'!W9 -> 0 | G9: ='QTR BS'!AA9 -> 0 | H9: ='QTR BS'!AE9 -> 0 | I9: ='QTR BS'!AI9 -> 0 | J9: ='QTR BS'!AM9 -> 0
A10: Net PP&E | B10: 10185 | C10: 24868 | D10: 55602 | E10: 87910 | F10: ='QTR BS'!W10 -> 94205.957 | G10: ='QTR BS'!AA10 -> 100381.98 | H10: ='QTR BS'!AE10 -> 106440.37 | I10: ='QTR BS'!AI10 -> 112383.35 | J10: ='QTR BS'!AM10 -> 118213.12
A11: ROU Assets - Operating - Non-Current | B11: 972 | C11: 1957 | D11: 21606 | E11: 0 | F11: ='QTR BS'!W11 -> 0 | G11: ='QTR BS'!AA11 -> 0 | H11: ='QTR BS'!AE11 -> 0 | I11: ='QTR BS'!AI11 -> 0 | J11: ='QTR BS'!AM11 -> 0
A12: ROU Assets - Finance - Non-Current | B12: 208 | C12: 208 | D12: 230 | E12: 0 | F12: ='QTR BS'!W16 -> 0 | G12: ='QTR BS'!AA16 -> 0 | H12: ='QTR BS'!AE16 -> 0 | I12: ='QTR BS'!AI16 -> 0 | J12: ='QTR BS'!AM16 -> 0
A13: Intangible Assets | B13: 12254 | C13: 12139 | D13: 12213 | E13: 1391915 | F13: ='QTR BS'!W12 -> 1391915 | G13: ='QTR BS'!AA12 -> 1391915 | H13: ='QTR BS'!AE12 -> 1391915 | I13: ='QTR BS'!AI12 -> 1391915 | J13: ='QTR BS'!AM12 -> 1391915
A14: Goodwill | B14: 13679 | C14: 14173 | D14: 71582 | E14: 917560 | F14: ='QTR BS'!W13 -> 917560 | G14: ='QTR BS'!AA13 -> 917560 | H14: ='QTR BS'!AE13 -> 917560 | I14: ='QTR BS'!AI13 -> 917560 | J14: ='QTR BS'!AM13 -> 917560
A15: Deferred Other Costs - Non-Current | B15: 262462 | C15: 248338 | D15: 234215 | E15: 771635 | F15: ='QTR BS'!W14 -> 756936.46 | G15: ='QTR BS'!AA14 -> 742517.91 | H15: ='QTR BS'!AE14 -> 728374.02 | I15: ='QTR BS'!AI14 -> 714499.54 | J15: ='QTR BS'!AM14 -> 700889.35
A16: Deferred Tax Assets | B16: 501 | C16: 29518 | D16: 38699 | E16: 96013 | F16: ='QTR BS'!W15 -> 39725 | G16: ='QTR BS'!AA15 -> -16563 | H16: ='QTR BS'!AE15 -> -72851 | I16: ='QTR BS'!AI15 -> -129139 | J16: ='QTR BS'!AM15 -> -185427
A17: Other Non-Current Assets | B17: 263 | C17: 291 | D17: 8154 | E17: 43434 | F17: ='QTR BS'!W17 -> 42606.645 | G17: ='QTR BS'!AA17 -> 41795.05 | H17: ='QTR BS'!AE17 -> 40998.914 | I17: ='QTR BS'!AI17 -> 40217.944 | J17: ='QTR BS'!AM17 -> 39451.85
A18: Total Assets | B18: =B8+SUM(B9:B17) -> 1222069 | C18: =C8+SUM(C9:C17) -> 1536396 | D18: =D8+SUM(D9:D17) -> 1766881 | E18: =E8+SUM(E9:E17) -> 5119621 | F18: =F8+SUM(F9:F17) -> 5029889.2 | G18: =G8+SUM(G9:G17) -> 4940794.4 | H18: =H8+SUM(H9:H17) -> 4852324.5 | I18: =I8+SUM(I9:I17) -> 4764467.7 | ... K18: =K8+SUM(K9:K17) -> 0
A19: Accounts Payable | B19: 36248 | C19: 42840 | D19: 41287 | E19: 137930 | F19: ='QTR BS'!W19 -> 135302.63 | G19: ='QTR BS'!AA19 -> 132725.31 | H19: ='QTR BS'!AE19 -> 130197.09 | I19: ='QTR BS'!AI19 -> 127717.02 | J19: ='QTR BS'!AM19 -> 125284.19
A20: Accrued Expenses | B20: 69899 | C20: 62120 | D20: 148780 | E20: 230721 | F20: ='QTR BS'!W20 -> 226326.1 | G20: ='QTR BS'!AA20 -> 222014.91 | H20: ='QTR BS'!AE20 -> 217785.85 | I20: ='QTR BS'!AI20 -> 213637.34 | J20: ='QTR BS'!AM20 -> 209567.86
A21: Income Taxes Payable | B21: 1193 | C21: 50424 | D21: 10834 | E21: 49612 | F21: ='QTR BS'!W21 -> 48666.963 | G21: ='QTR BS'!AA21 -> 47739.927 | H21: ='QTR BS'!AE21 -> 46830.55 | I21: ='QTR BS'!AI21 -> 45938.496 | J21: ='QTR BS'!AM21 -> 45063.434
A22: Accrued Distributor Termination Fees | B22: 3986 | C22: 0 | D22: 0 | E22: 264088 | F22: ='QTR BS'!W22 -> 0 | G22: ='QTR BS'!AA22 -> 0 | H22: ='QTR BS'!AE22 -> 0 | I22: ='QTR BS'!AI22 -> 0 | J22: ='QTR BS'!AM22 -> 0
A23: Accrued Promotional Allowance | B23: 35977 | C23: 99787 | D23: 135948 | E23: 307922 | F23: ='QTR BS'!W23 -> 302056.53 | G23: ='QTR BS'!AA23 -> 296302.79 | H23: ='QTR BS'!AE23 -> 290658.65 | I23: ='QTR BS'!AI23 -> 285122.02 | J23: ='QTR BS'!AM23 -> 279690.85
A24: Lease Liability - Operating - Current | B24: 661 | C24: 980 | D24: 3265 | E24: 0 | F24: ='QTR BS'!W24 -> 0 | G24: ='QTR BS'!AA24 -> 0 | H24: ='QTR BS'!AE24 -> 0 | I24: ='QTR BS'!AI24 -> 0 | J24: ='QTR BS'!AM24 -> 0
A25: Lease Liability - Finance - Current | B25: 70 | C25: 59 | D25: 100 | E25: 0 | F25: ='QTR BS'!W25 -> 0 | G25: ='QTR BS'!AA25 -> 0 | H25: ='QTR BS'!AE25 -> 0 | I25: ='QTR BS'!AI25 -> 0 | J25: ='QTR BS'!AM25 -> 0
A26: Contingent Consideration - Current | B26: 0 | C26: 0 | D26: 0 | E26: 25000 | F26: ='QTR BS'!W26 -> 24523.786 | G26: ='QTR BS'!AA26 -> 24056.643 | H26: ='QTR BS'!AE26 -> 23598.399 | I26: ='QTR BS'!AI26 -> 23148.883 | J26: ='QTR BS'!AM26 -> 22707.93
A27: Deferred Revenue - Current | B27: 9675 | C27: 9513 | D27: 9513 | E27: 26988 | F27: ='QTR BS'!W27 -> 26473.917 | G27: ='QTR BS'!AA27 -> 25969.627 | H27: ='QTR BS'!AE27 -> 25474.943 | I27: ='QTR BS'!AI27 -> 24989.682 | J27: ='QTR BS'!AM27 -> 24513.665
A28: Other Current Liabilities | B28: 3586 | C28: 10890 | D28: 15808 | E28: 36465 | F28: ='QTR BS'!W28 -> 35770.394 | G28: ='QTR BS'!AA28 -> 35089.02 | H28: ='QTR BS'!AE28 -> 34420.624 | I28: ='QTR BS'!AI28 -> 33764.961 | J28: ='QTR BS'!AM28 -> 33121.787
A29: Total Current Liabilities | B29: =SUM(B19:B28) -> 161295 | C29: =SUM(C19:C28) -> 276613 | D29: =SUM(D19:D28) -> 365535 | E29: =SUM(E19:E28) -> 1078726 | F29: =SUM(F19:F28) -> 799120.32 | G29: =SUM(G19:G28) -> 783898.23 | H29: =SUM(H19:H28) -> 768966.09 | I29: =SUM(I19:I28) -> 754318.4 | ... K29: =SUM(K19:K28) -> 0
A30: Lease Liability - Operating - Non-Current | B30: 326 | C30: 955 | D30: 16674 | E30: 0 | F30: ='QTR BS'!W30 -> 0 | G30: ='QTR BS'!AA30 -> 0 | H30: ='QTR BS'!AE30 -> 0 | I30: ='QTR BS'!AI30 -> 0 | J30: ='QTR BS'!AM30 -> 0
A31: Lease Liability - Finance - Non-Current | B31: 162 | C31: 193 | D31: 211 | E31: 0 | F31: ='QTR BS'!W31 -> 0 | G31: ='QTR BS'!AA31 -> 0 | H31: ='QTR BS'!AE31 -> 0 | I31: ='QTR BS'!AI31 -> 0 | J31: ='QTR BS'!AM31 -> 0
A32: Deferred Tax Liability | B32: 15919 | C32: 2880 | D32: 2330 | E32: 0 | F32: ='QTR BS'!W32 -> 0 | G32: ='QTR BS'!AA32 -> 0 | H32: ='QTR BS'!AE32 -> 0 | I32: ='QTR BS'!AI32 -> 0 | J32: ='QTR BS'!AM32 -> 0
A33: Long-Term Debt | B33: 0 | C33: 0 | D33: 0 | E33: 669926 | F33: ='QTR BS'!W33 -> 669926 | G33: ='QTR BS'!AA33 -> 669926 | H33: ='QTR BS'!AE33 -> 669926 | I33: ='QTR BS'!AI33 -> 669926 | J33: ='QTR BS'!AM33 -> 669926
A34: Deferred Revenue - Non-Current | B34: 179788 | C34: 167227 | D34: 157714 | E34: 401155 | F34: ='QTR BS'!W34 -> 393513.57 | G34: ='QTR BS'!AA34 -> 386017.71 | H34: ='QTR BS'!AE34 -> 378664.63 | I34: ='QTR BS'!AI34 -> 371451.61 | J34: ='QTR BS'!AM34 -> 364375.99
A35: Other Non-Current Liabilities | B35: 0 | C35: 0 | D35: 0 | E35: 28372 | F35: ='QTR BS'!W35 -> 27831.554 | G35: ='QTR BS'!AA35 -> 27301.403 | H35: ='QTR BS'!AE35 -> 26781.351 | I35: ='QTR BS'!AI35 -> 26271.205 | J35: ='QTR BS'!AM35 -> 25770.776
A36: Total Liabilities | B36: =B29+SUM(B30:B35) -> 357490 | C36: =C29+SUM(C30:C35) -> 447868 | D36: =D29+SUM(D30:D35) -> 542464 | E36: =E29+SUM(E30:E35) -> 2178179 | F36: =F29+SUM(F30:F35) -> 1890391.4 | G36: =G29+SUM(G30:G35) -> 1867143.3 | H36: =H29+SUM(H30:H35) -> 1844338.1 | I36: =I29+SUM(I30:I35) -> 1821967.2 | ... K36: =K29+SUM(K30:K35) -> 0
A37: Convertible Preferred Stock | B37: 824488 | C37: 824488 | D37: 824488 | E37: 1759975 | F37: ='QTR BS'!W37 -> 1759975 | G37: ='QTR BS'!AA37 -> 1759975 | H37: ='QTR BS'!AE37 -> 1759975 | I37: ='QTR BS'!AI37 -> 1759975 | J37: ='QTR BS'!AM37 -> 1759975
A38: Common Stock | B38: 76 | C38: 77 | D38: 79 | E38: 101 | F38: ='QTR BS'!W38 -> 101 | G38: ='QTR BS'!AA38 -> 101 | H38: ='QTR BS'!AE38 -> 101 | I38: ='QTR BS'!AI38 -> 101 | J38: ='QTR BS'!AM38 -> 101
A39: Treasury Stock | B39: 0 | C39: 0 | D39: 0 | E39: -48226 | F39: ='QTR BS'!W39 -> -48226 | G39: ='QTR BS'!AA39 -> -48226 | H39: ='QTR BS'!AE39 -> -48226 | I39: ='QTR BS'!AI39 -> -48226 | J39: ='QTR BS'!AM39 -> -48226
A40: Additional Paid-in Capital | B40: 280668 | C40: 276717 | D40: 297579 | E40: 1050518 | F40: ='QTR BS'!W40 -> 1086890.7 | G40: ='QTR BS'!AA40 -> 1122570.5 | H40: ='QTR BS'!AE40 -> 1157570.7 | I40: ='QTR BS'!AI40 -> 1191904.2 | J40: ='QTR BS'!AM40 -> 1225583.7
A41: Accumulated Other Comprehensive Income (Loss) | B41: -1881 | C41: -701 | D41: -3250 | E41: 3162 | F41: ='QTR BS'!W41 -> 7550 | G41: ='QTR BS'!AA41 -> 11938 | H41: ='QTR BS'!AE41 -> 16326 | I41: ='QTR BS'!AI41 -> 20714 | J41: ='QTR BS'!AM41 -> 25102
A42: Retained Earnings (Accumulated Deficit) | B42: -238772 | C42: -12053 | D42: 105521 | E42: 175912 | F42: ='QTR BS'!W42 -> 565554.1 | G42: ='QTR BS'!AA42 -> 946395.55 | H42: ='QTR BS'!AE42 -> 1318604 | I42: ='QTR BS'!AI42 -> 1682343.8 | J42: ='QTR BS'!AM42 -> 2037776.4
A43: Total Stockholders' Equity | B43: =SUM(B37:B42) -> 864579 | C43: =SUM(C37:C42) -> 1088528 | D43: =SUM(D37:D42) -> 1224417 | E43: =SUM(E37:E42) -> 2941442 | F43: =SUM(F37:F42) -> 3371844.8 | G43: =SUM(G37:G42) -> 3792754.1 | H43: =SUM(H37:H42) -> 4204350.7 | I43: =SUM(I37:I42) -> 4606812 | ... K43: =SUM(K37:K42) -> 0
A44: Total Liabilities, Mezzanine & Stockholders' Equity | B44: =B36+B43 -> 1222069 | C44: =C36+C43 -> 1536396 | D44: =D36+D43 -> 1766881 | E44: =E36+E43 -> 5119621 | F44: =F36+F43 -> 5262236.2 | G44: =G36+G43 -> 5659897.4 | H44: =H36+H43 -> 6048688.8 | I44: =I36+I43 -> 6428779.3 | ... K44: =K36+K43 -> 0

Sheet CASH FLOW
B1: FY2021 | C1: FY2022 | D1: FY2023 | E1: FY2024 | F1: FY2025 | G1: FY2026E | H1: FY2027E | I1: FY2028E | J1: FY2029E | K1: FY2030E | L1: FY2031E
A2: Net Income (Loss) | B2: 3937 | C2: -187282 | D2: 226801 | E2: 145074 | F2: 107999 | G2: ='QTR CF'!W2+'QTR CF'!X2+'QTR CF'!Y2+'QTR CF'!Z2 -> 446870.1 | H2: ='QTR CF'!AA2+'QTR CF'!AB2+'QTR CF'!AC2+'QTR CF'!AD2 -> 438069.45 | I2: ='QTR CF'!AE2+'QTR CF'!AF2+'QTR CF'!AG2+'QTR CF'!AH2 -> 429436.43 | J2: ='QTR CF'!AI2+'QTR CF'!AJ2+'QTR CF'!AK2+'QTR CF'!AL2 -> 420967.86 | K2: ='QTR CF'!AM2+'QTR CF'!AN2+'QTR CF'!AO2+'QTR CF'!AP2 -> 412660.61
A3: Depreciation & Amortization | B3: 1264 | C3: 1917 | D3: 3226 | E3: 7274 | F3: 29451 | G3: ='QTR CF'!W6+'QTR CF'!X6+'QTR CF'!Y6+'QTR CF'!Z6 -> 35313.48 | H3: ='QTR CF'!AA6+'QTR CF'!AB6+'QTR CF'!AC6+'QTR CF'!AD6 -> 34640.809 | I3: ='QTR CF'!AE6+'QTR CF'!AF6+'QTR CF'!AG6+'QTR CF'!AH6 -> 33980.951 | J3: ='QTR CF'!AI6+'QTR CF'!AJ6+'QTR CF'!AK6+'QTR CF'!AL6 -> 33333.663 | K3: ='QTR CF'!AM6+'QTR CF'!AN6+'QTR CF'!AO6+'QTR CF'!AP6 -> 32698.705
A4: Impairment of Intangibles | B4: 0 | C4: 2379 | D4: 0 | E4: 0 | F4: 0 | G4: ='QTR CF'!W5+'QTR CF'!X5+'QTR CF'!Y5+'QTR CF'!Z5 -> 0 | H4: ='QTR CF'!AA5+'QTR CF'!AB5+'QTR CF'!AC5+'QTR CF'!AD5 -> 0 | I4: ='QTR CF'!AE5+'QTR CF'!AF5+'QTR CF'!AG5+'QTR CF'!AH5 -> 0 | J4: ='QTR CF'!AI5+'QTR CF'!AJ5+'QTR CF'!AK5+'QTR CF'!AL5 -> 0 | K4: ='QTR CF'!AM5+'QTR CF'!AN5+'QTR CF'!AO5+'QTR CF'!AP5 -> 0
A5: Allowance for Credit Losses | B5: 1494 | C5: 2352 | D5: 2128 | E5: 3294 | F5: 10600 | G5: ='QTR CF'!W7+'QTR CF'!X7+'QTR CF'!Y7+'QTR CF'!Z7 -> 0 | H5: ='QTR CF'!AA7+'QTR CF'!AB7+'QTR CF'!AC7+'QTR CF'!AD7 -> 0 | I5: ='QTR CF'!AE7+'QTR CF'!AF7+'QTR CF'!AG7+'QTR CF'!AH7 -> 0 | J5: ='QTR CF'!AI7+'QTR CF'!AJ7+'QTR CF'!AK7+'QTR CF'!AL7 -> 0 | K5: ='QTR CF'!AM7+'QTR CF'!AN7+'QTR CF'!AO7+'QTR CF'!AP7 -> 0
A6: Amortization of Deferred Other Costs | B6: 0 | C6: 5885 | D6: 14124 | E6: 14124 | F6: 26326 | G6: ='QTR CF'!W8+'QTR CF'!X8+'QTR CF'!Y8+'QTR CF'!Z8 -> 0 | H6: ='QTR CF'!AA8+'QTR CF'!AB8+'QTR CF'!AC8+'QTR CF'!AD8 -> 0 | I6: ='QTR CF'!AE8+'QTR CF'!AF8+'QTR CF'!AG8+'QTR CF'!AH8 -> 0 | J6: ='QTR CF'!AI8+'QTR CF'!AJ8+'QTR CF'!AK8+'QTR CF'!AL8 -> 0 | K6: ='QTR CF'!AM8+'QTR CF'!AN8+'QTR CF'!AO8+'QTR CF'!AP8 -> 0
A7: Inventory Write-Down | B7: 2355 | C7: 6131 | D7: 7312 | E7: 19086 | F7: 29190 | G7: ='QTR CF'!W9+'QTR CF'!X9+'QTR CF'!Y9+'QTR CF'!Z9 -> 0 | H7: ='QTR CF'!AA9+'QTR CF'!AB9+'QTR CF'!AC9+'QTR CF'!AD9 -> 0 | I7: ='QTR CF'!AE9+'QTR CF'!AF9+'QTR CF'!AG9+'QTR CF'!AH9 -> 0 | J7: ='QTR CF'!AI9+'QTR CF'!AJ9+'QTR CF'!AK9+'QTR CF'!AL9 -> 0 | K7: ='QTR CF'!AM9+'QTR CF'!AN9+'QTR CF'!AO9+'QTR CF'!AP9 -> 0
A8: Gain (Loss) on Disposal of PP&E | B8: 0 | C8: 0 | D8: 198 | E8: 173 | F8: 0 | G8: ='QTR CF'!W10+'QTR CF'!X10+'QTR CF'!Y10+'QTR CF'!Z10 -> 0 | H8: ='QTR CF'!AA10+'QTR CF'!AB10+'QTR CF'!AC10+'QTR CF'!AD10 -> 0 | I8: ='QTR CF'!AE10+'QTR CF'!AF10+'QTR CF'!AG10+'QTR CF'!AH10 -> 0 | J8: ='QTR CF'!AI10+'QTR CF'!AJ10+'QTR CF'!AK10+'QTR CF'!AL10 -> 0 | K8: ='QTR CF'!AM10+'QTR CF'!AN10+'QTR CF'!AO10+'QTR CF'!AP10 -> 0
A9: Stock-Based Compensation | B9: 36475 | C9: 20665 | D9: 21226 | E9: 19591 | F9: 28050 | G9: ='QTR CF'!W11+'QTR CF'!X11+'QTR CF'!Y11+'QTR CF'!Z11 -> 36372.687 | H9: ='QTR CF'!AA11+'QTR CF'!AB11+'QTR CF'!AC11+'QTR CF'!AD11 -> 35679.839 | I9: ='QTR CF'!AE11+'QTR CF'!AF11+'QTR CF'!AG11+'QTR CF'!AH11 -> 35000.19 | J9: ='QTR CF'!AI11+'QTR CF'!AJ11+'QTR CF'!AK11+'QTR CF'!AL11 -> 34333.487 | K9: ='QTR CF'!AM11+'QTR CF'!AN11+'QTR CF'!AO11+'QTR CF'!AP11 -> 33679.483
A10: (Benefit) Provision for Deferred Income Taxes | B10: -9201 | C10: 20244 | D10: -42055 | E10: -9730 | F10: -57336 | G10: ='QTR CF'!W14+'QTR CF'!X14+'QTR CF'!Y14+'QTR CF'!Z14 -> 56288 | H10: ='QTR CF'!AA14+'QTR CF'!AB14+'QTR CF'!AC14+'QTR CF'!AD14 -> 56288 | I10: ='QTR CF'!AE14+'QTR CF'!AF14+'QTR CF'!AG14+'QTR CF'!AH14 -> 56288 | J10: ='QTR CF'!AI14+'QTR CF'!AJ14+'QTR CF'!AK14+'QTR CF'!AL14 -> 56288 | K10: ='QTR CF'!AM14+'QTR CF'!AN14+'QTR CF'!AO14+'QTR CF'!AP14 -> 56288
A11: Foreign Currency Gain (Loss) | B11: 880 | C11: 483 | D11: 1246 | E11: 1734 | F11: 0 | G11: ='QTR CF'!W15+'QTR CF'!X15+'QTR CF'!Y15+'QTR CF'!Z15 -> 0 | H11: ='QTR CF'!AA15+'QTR CF'!AB15+'QTR CF'!AC15+'QTR CF'!AD15 -> 0 | I11: ='QTR CF'!AE15+'QTR CF'!AF15+'QTR CF'!AG15+'QTR CF'!AH15 -> 0 | J11: ='QTR CF'!AI15+'QTR CF'!AJ15+'QTR CF'!AK15+'QTR CF'!AL15 -> 0 | K11: ='QTR CF'!AM15+'QTR CF'!AN15+'QTR CF'!AO15+'QTR CF'!AP15 -> 0
A12: Gain (Loss) on Lease Cancellations | B12: -28 | C12: 0 | D12: 0 | E12: 0 | F12: 0 | G12: ='QTR CF'!W13+'QTR CF'!X13+'QTR CF'!Y13+'QTR CF'!Z13 -> 0 | H12: ='QTR CF'!AA13+'QTR CF'!AB13+'QTR CF'!AC13+'QTR CF'!AD13 -> 0 | I12: ='QTR CF'!AE13+'QTR CF'!AF13+'QTR CF'!AG13+'QTR CF'!AH13 -> 0 | J12: ='QTR CF'!AI13+'QTR CF'!AJ13+'QTR CF'!AK13+'QTR CF'!AL13 -> 0 | K12: ='QTR CF'!AM13+'QTR CF'!AN13+'QTR CF'!AO13+'QTR CF'!AP13 -> 0
A13: Change in Fair Value of Contingent Consideration | B13: 0 | C13: 0 | D13: 0 | E13: 0 | F13: 13800 | G13: ='QTR CF'!W16+'QTR CF'!X16+'QTR CF'!Y16+'QTR CF'!Z16 -> 0 | H13: ='QTR CF'!AA16+'QTR CF'!AB16+'QTR CF'!AC16+'QTR CF'!AD16 -> 0 | I13: ='QTR CF'!AE16+'QTR CF'!AF16+'QTR CF'!AG16+'QTR CF'!AH16 -> 0 | J13: ='QTR CF'!AI16+'QTR CF'!AJ16+'QTR CF'!AK16+'QTR CF'!AL16 -> 0 | K13: ='QTR CF'!AM16+'QTR CF'!AN16+'QTR CF'!AO16+'QTR CF'!AP16 -> 0
A14: Gain (Loss) on Extinguishment of Debt | B14: 0 | C14: 0 | D14: 0 | E14: 0 | F14: 6003 | G14: ='QTR CF'!W17+'QTR CF'!X17+'QTR CF'!Y17+'QTR CF'!Z17 -> 0 | H14: ='QTR CF'!AA17+'QTR CF'!AB17+'QTR CF'!AC17+'QTR CF'!AD17 -> 0 | I14: ='QTR CF'!AE17+'QTR CF'!AF17+'QTR CF'!AG17+'QTR CF'!AH17 -> 0 | J14: ='QTR CF'!AI17+'QTR CF'!AJ17+'QTR CF'!AK17+'QTR CF'!AL17 -> 0 | K14: ='QTR CF'!AM17+'QTR CF'!AN17+'QTR CF'!AO17+'QTR CF'!AP17 -> 0
A15: Other Operating Items | B15: 0 | C15: 37 | D15: -28 | E15: -324 | F15: -1687 | G15: ='QTR CF'!W18+'QTR CF'!X18+'QTR CF'!Y18+'QTR CF'!Z18 -> -257625.13 | H15: ='QTR CF'!AA18+'QTR CF'!AB18+'QTR CF'!AC18+'QTR CF'!AD18 -> 6339.7634 | I15: ='QTR CF'!AE18+'QTR CF'!AF18+'QTR CF'!AG18+'QTR CF'!AH18 -> 6219 | J15: ='QTR CF'!AI18+'QTR CF'!AJ18+'QTR CF'!AK18+'QTR CF'!AL18 -> 6100.537 | K15: ='QTR CF'!AM18+'QTR CF'!AN18+'QTR CF'!AO18+'QTR CF'!AP18 -> 5984.3306
A16: Accounts Receivable | B16: -25249 | C16: -26369 | D16: -121558 | E16: -89665 | F16: -412091 | G16: ='QTR CF'!W19+'QTR CF'!X19+'QTR CF'!Y19+'QTR CF'!Z19 -> 14391.168 | H16: ='QTR CF'!AA19+'QTR CF'!AB19+'QTR CF'!AC19+'QTR CF'!AD19 -> 14117.037 | I16: ='QTR CF'!AE19+'QTR CF'!AF19+'QTR CF'!AG19+'QTR CF'!AH19 -> 13848.128 | J16: ='QTR CF'!AI19+'QTR CF'!AJ19+'QTR CF'!AK19+'QTR CF'!AL19 -> 13584.341 | K16: ='QTR CF'!AM19+'QTR CF'!AN19+'QTR CF'!AO19+'QTR CF'!AP19 -> 13325.579
A17: Note Receivable | B17: 0 | C17: 0 | D17: 0 | E17: 2318 | F17: 0 | G17: ='QTR CF'!W20+'QTR CF'!X20+'QTR CF'!Y20+'QTR CF'!Z20 -> 0 | H17: ='QTR CF'!AA20+'QTR CF'!AB20+'QTR CF'!AC20+'QTR CF'!AD20 -> 0 | I17: ='QTR CF'!AE20+'QTR CF'!AF20+'QTR CF'!AG20+'QTR CF'!AH20 -> 0 | J17: ='QTR CF'!AI20+'QTR CF'!AJ20+'QTR CF'!AK20+'QTR CF'!AL20 -> 0 | K17: ='QTR CF'!AM20+'QTR CF'!AN20+'QTR CF'!AO20+'QTR CF'!AP20 -> 0
A18: Inventories | B18: -175174 | C18: 11802 | D18: -63299 | E18: 77190 | F18: -129777 | G18: ='QTR CF'!W21+'QTR CF'!X21+'QTR CF'!Y21+'QTR CF'!Z21 -> 6432.6608 | H18: ='QTR CF'!AA21+'QTR CF'!AB21+'QTR CF'!AC21+'QTR CF'!AD21 -> 6310.1278 | I18: ='QTR CF'!AE21+'QTR CF'!AF21+'QTR CF'!AG21+'QTR CF'!AH21 -> 6189.929 | J18: ='QTR CF'!AI21+'QTR CF'!AJ21+'QTR CF'!AK21+'QTR CF'!AL21 -> 6072.0198 | K18: ='QTR CF'!AM21+'QTR CF'!AN21+'QTR CF'!AO21+'QTR CF'!AP21 -> 5956.3565
A19: Prepaid Expenses | B19: 1072 | C19: 2214 | D19: -7980 | E19: 1074 | F19: -108321 | G19: ='QTR CF'!W22+'QTR CF'!X22+'QTR CF'!Y22+'QTR CF'!Z22 -> 2453.5689 | H19: ='QTR CF'!AA22+'QTR CF'!AB22+'QTR CF'!AC22+'QTR CF'!AD22 -> 2406.8319 | I19: ='QTR CF'!AE22+'QTR CF'!AF22+'QTR CF'!AG22+'QTR CF'!AH22 -> 2360.9852 | J19: ='QTR CF'!AI22+'QTR CF'!AJ22+'QTR CF'!AK22+'QTR CF'!AL22 -> 2316.0119 | K19: ='QTR CF'!AM22+'QTR CF'!AN22+'QTR CF'!AO22+'QTR CF'!AP22 -> 2271.8952
A20: Other Non-Current Assets | B20: 0 | C20: 0 | D20: 0 | E20: -4862 | F20: 2857 | G20: ='QTR CF'!W24+'QTR CF'!X24+'QTR CF'!Y24+'QTR CF'!Z24 -> 827.35518 | H20: ='QTR CF'!AA24+'QTR CF'!AB24+'QTR CF'!AC24+'QTR CF'!AD24 -> 811.59525 | I20: ='QTR CF'!AE24+'QTR CF'!AF24+'QTR CF'!AG24+'QTR CF'!AH24 -> 796.13553 | J20: ='QTR CF'!AI24+'QTR CF'!AJ24+'QTR CF'!AK24+'QTR CF'!AL24 -> 780.97029 | K20: ='QTR CF'!AM24+'QTR CF'!AN24+'QTR CF'!AO24+'QTR CF'!AP24 -> 766.09393
A21: Accounts Payable | B21: 23966 | C21: 428 | D21: 5249 | E21: -1170 | F21: 51252 | G21: ='QTR CF'!W25+'QTR CF'!X25+'QTR CF'!Y25+'QTR CF'!Z25 -> -2627.3679 | H21: ='QTR CF'!AA25+'QTR CF'!AB25+'QTR CF'!AC25+'QTR CF'!AD25 -> -2577.3204 | I21: ='QTR CF'!AE25+'QTR CF'!AF25+'QTR CF'!AG25+'QTR CF'!AH25 -> -2528.2261 | J21: ='QTR CF'!AI25+'QTR CF'!AJ25+'QTR CF'!AK25+'QTR CF'!AL25 -> -2480.0671 | K21: ='QTR CF'!AM25+'QTR CF'!AN25+'QTR CF'!AO25+'QTR CF'!AP25 -> -2432.8253
A22: Accrued Expenses | B22: 26484 | C22: 34644 | D22: -8025 | E22: 85398 | F22: 45618 | G22: ='QTR CF'!W26+'QTR CF'!X26+'QTR CF'!Y26+'QTR CF'!Z26 -> -4394.9029 | H22: ='QTR CF'!AA26+'QTR CF'!AB26+'QTR CF'!AC26+'QTR CF'!AD26 -> -4311.1863 | I22: ='QTR CF'!AE26+'QTR CF'!AF26+'QTR CF'!AG26+'QTR CF'!AH26 -> -4229.0645 | J22: ='QTR CF'!AI26+'QTR CF'!AJ26+'QTR CF'!AK26+'QTR CF'!AL26 -> -4148.5069 | K22: ='QTR CF'!AM26+'QTR CF'!AN26+'QTR CF'!AO26+'QTR CF'!AP26 -> -4069.4838
A23: Change in Income Taxes | B23: 1357 | C23: -164 | D23: 48102 | E23: -39536 | F23: 38750 | G23: ='QTR CF'!W27+'QTR CF'!X27+'QTR CF'!Y27+'QTR CF'!Z27 -> -945.03718 | H23: ='QTR CF'!AA27+'QTR CF'!AB27+'QTR CF'!AC27+'QTR CF'!AD27 -> -927.03558 | I23: ='QTR CF'!AE27+'QTR CF'!AF27+'QTR CF'!AG27+'QTR CF'!AH27 -> -909.37689 | J23: ='QTR CF'!AI27+'QTR CF'!AJ27+'QTR CF'!AK27+'QTR CF'!AL27 -> -892.05457 | K23: ='QTR CF'!AM27+'QTR CF'!AN27+'QTR CF'!AO27+'QTR CF'!AP27 -> -875.06221
A24: Accrued Promotional Allowance | B24: 13379 | C24: 16940 | D24: 63810 | E24: 36161 | F24: 153635 | G24: ='QTR CF'!W28+'QTR CF'!X28+'QTR CF'!Y28+'QTR CF'!Z28 -> -5865.4708 | H24: ='QTR CF'!AA28+'QTR CF'!AB28+'QTR CF'!AC28+'QTR CF'!AD28 -> -5753.7421 | I24: ='QTR CF'!AE28+'QTR CF'!AF28+'QTR CF'!AG28+'QTR CF'!AH28 -> -5644.1416 | J24: ='QTR CF'!AI28+'QTR CF'!AJ28+'QTR CF'!AK28+'QTR CF'!AL28 -> -5536.6288 | K24: ='QTR CF'!AM28+'QTR CF'!AN28+'QTR CF'!AO28+'QTR CF'!AP28 -> -5431.164
A25: Accrued Distributor Termination | B25: 0 | C25: 3986 | D25: -3739 | E25: -248 | F25: 257595 | G25: ='QTR CF'!W29+'QTR CF'!X29+'QTR CF'!Y29+'QTR CF'!Z29 -> 0 | H25: ='QTR CF'!AA29+'QTR CF'!AB29+'QTR CF'!AC29+'QTR CF'!AD29 -> 0 | I25: ='QTR CF'!AE29+'QTR CF'!AF29+'QTR CF'!AG29+'QTR CF'!AH29 -> 0 | J25: ='QTR CF'!AI29+'QTR CF'!AJ29+'QTR CF'!AK29+'QTR CF'!AL29 -> 0 | K25: ='QTR CF'!AM29+'QTR CF'!AN29+'QTR CF'!AO29+'QTR CF'!AP29 -> 0
A26: Other Current Liabilities | B26: 374 | C26: 2610 | D26: 7305 | E26: 4920 | F26: 9937 | G26: ='QTR CF'!W30+'QTR CF'!X30+'QTR CF'!Y30+'QTR CF'!Z30 -> -694.60576 | H26: ='QTR CF'!AA30+'QTR CF'!AB30+'QTR CF'!AC30+'QTR CF'!AD30 -> -681.37452 | I26: ='QTR CF'!AE30+'QTR CF'!AF30+'QTR CF'!AG30+'QTR CF'!AH30 -> -668.39531 | J26: ='QTR CF'!AI30+'QTR CF'!AJ30+'QTR CF'!AK30+'QTR CF'!AL30 -> -655.66335 | K26: ='QTR CF'!AM30+'QTR CF'!AN30+'QTR CF'!AO30+'QTR CF'!AP30 -> -643.1739
A27: ROU & Lease Liability, Net | B27: 29 | C27: -183 | D27: -102 | E27: 535 | F27: 0 | G27: ='QTR CF'!W31+'QTR CF'!X31+'QTR CF'!Y31+'QTR CF'!Z31 -> 0 | H27: ='QTR CF'!AA31+'QTR CF'!AB31+'QTR CF'!AC31+'QTR CF'!AD31 -> 0 | I27: ='QTR CF'!AE31+'QTR CF'!AF31+'QTR CF'!AG31+'QTR CF'!AH31 -> 0 | J27: ='QTR CF'!AI31+'QTR CF'!AJ31+'QTR CF'!AK31+'QTR CF'!AL31 -> 0 | K27: ='QTR CF'!AM31+'QTR CF'!AN31+'QTR CF'!AO31+'QTR CF'!AP31 -> 0
A28: Deferred Revenue | B28: 0 | C28: 189463 | D28: -12723 | E28: -9513 | F28: 255110 | G28: ='QTR CF'!W32+'QTR CF'!X32+'QTR CF'!Y32+'QTR CF'!Z32 -> 0 | H28: ='QTR CF'!AA32+'QTR CF'!AB32+'QTR CF'!AC32+'QTR CF'!AD32 -> 0 | I28: ='QTR CF'!AE32+'QTR CF'!AF32+'QTR CF'!AG32+'QTR CF'!AH32 -> 0 | J28: ='QTR CF'!AI32+'QTR CF'!AJ32+'QTR CF'!AK32+'QTR CF'!AL32 -> 0 | K28: ='QTR CF'!AM32+'QTR CF'!AN32+'QTR CF'!AO32+'QTR CF'!AP32 -> 0
A29: Net Change in Other Working Capital | B29: 0 | C29: 0 | D29: 0 | E29: 0 | F29: 2481 | G29: ='QTR CF'!W33+'QTR CF'!X33+'QTR CF'!Y33+'QTR CF'!Z33 -> 0 | H29: ='QTR CF'!AA33+'QTR CF'!AB33+'QTR CF'!AC33+'QTR CF'!AD33 -> 0 | I29: ='QTR CF'!AE33+'QTR CF'!AF33+'QTR CF'!AG33+'QTR CF'!AH33 -> 0 | J29: ='QTR CF'!AI33+'QTR CF'!AJ33+'QTR CF'!AK33+'QTR CF'!AL33 -> 0 | K29: ='QTR CF'!AM33+'QTR CF'!AN33+'QTR CF'!AO33+'QTR CF'!AP33 -> 0
A30: Cash Flow from Operations | B30: =SUM(B2:B29) -> -96586 | C30: =SUM(C2:C29) -> 108182 | D30: =SUM(D2:D29) -> 141218 | E30: =SUM(E2:E29) -> 262898 | F30: =SUM(F2:F29) -> 359442 | G30: =SUM(G2:G29) -> 326796.51 | H30: =SUM(H2:H29) -> 580412.79 | I30: =SUM(I2:I29) -> 570140.55 | ... L30: =SUM(L2:L29) -> 0
A31: Collections from Note Receivable | B31: 1886 | C31: 2592 | D31: 3233 | E31: 0 | F31: 0 | G31: ='QTR CF'!W35+'QTR CF'!X35+'QTR CF'!Y35+'QTR CF'!Z35 -> 0 | H31: ='QTR CF'!AA35+'QTR CF'!AB35+'QTR CF'!AC35+'QTR CF'!AD35 -> 0 | I31: ='QTR CF'!AE35+'QTR CF'!AF35+'QTR CF'!AG35+'QTR CF'!AH35 -> 0 | J31: ='QTR CF'!AI35+'QTR CF'!AJ35+'QTR CF'!AK35+'QTR CF'!AL35 -> 0 | K31: ='QTR CF'!AM35+'QTR CF'!AN35+'QTR CF'!AO35+'QTR CF'!AP35 -> 0
A32: Purchase of PP&E | B32: -3150 | C32: -8264 | D32: -17433 | E32: -23390 | F32: -36067 | G32: ='QTR CF'!W36+'QTR CF'!X36+'QTR CF'!Y36+'QTR CF'!Z36 -> -41609.437 | H32: ='QTR CF'!AA36+'QTR CF'!AB36+'QTR CF'!AC36+'QTR CF'!AD36 -> -40816.837 | I32: ='QTR CF'!AE36+'QTR CF'!AF36+'QTR CF'!AG36+'QTR CF'!AH36 -> -40039.335 | J32: ='QTR CF'!AI36+'QTR CF'!AJ36+'QTR CF'!AK36+'QTR CF'!AL36 -> -39276.643 | K32: ='QTR CF'!AM36+'QTR CF'!AN36+'QTR CF'!AO36+'QTR CF'!AP36 -> -38528.48
A33: Purchase of Non-Marketable Equity Securities | B33: 0 | C33: 0 | D33: 0 | E33: -3000 | F33: -10000 | G33: ='QTR CF'!W37+'QTR CF'!X37+'QTR CF'!Y37+'QTR CF'!Z37 -> 0 | H33: ='QTR CF'!AA37+'QTR CF'!AB37+'QTR CF'!AC37+'QTR CF'!AD37 -> 0 | I33: ='QTR CF'!AE37+'QTR CF'!AF37+'QTR CF'!AG37+'QTR CF'!AH37 -> 0 | J33: ='QTR CF'!AI37+'QTR CF'!AJ37+'QTR CF'!AK37+'QTR CF'!AL37 -> 0 | K33: ='QTR CF'!AM37+'QTR CF'!AN37+'QTR CF'!AO37+'QTR CF'!AP37 -> 0
A34: Acquisition of Big Beverages | B34: 0 | C34: 0 | D34: 0 | E34: -75336 | F34: 0 | G34: ='QTR CF'!W38+'QTR CF'!X38+'QTR CF'!Y38+'QTR CF'!Z38 -> 0 | H34: ='QTR CF'!AA38+'QTR CF'!AB38+'QTR CF'!AC38+'QTR CF'!AD38 -> 0 | I34: ='QTR CF'!AE38+'QTR CF'!AF38+'QTR CF'!AG38+'QTR CF'!AH38 -> 0 | J34: ='QTR CF'!AI38+'QTR CF'!AJ38+'QTR CF'!AK38+'QTR CF'!AL38 -> 0 | K34: ='QTR CF'!AM38+'QTR CF'!AN38+'QTR CF'!AO38+'QTR CF'!AP38 -> 0
A35: Acquisitions, Net of Cash Acquired | B35: 0 | C35: 0 | D35: 0 | E35: 0 | F35: -1278769 | G35: ='QTR CF'!W39+'QTR CF'!X39+'QTR CF'!Y39+'QTR CF'!Z39 -> 0 | H35: ='QTR CF'!AA39+'QTR CF'!AB39+'QTR CF'!AC39+'QTR CF'!AD39 -> 0 | I35: ='QTR CF'!AE39+'QTR CF'!AF39+'QTR CF'!AG39+'QTR CF'!AH39 -> 0 | J35: ='QTR CF'!AI39+'QTR CF'!AJ39+'QTR CF'!AK39+'QTR CF'!AL39 -> 0 | K35: ='QTR CF'!AM39+'QTR CF'!AN39+'QTR CF'!AO39+'QTR CF'!AP39 -> 0
A36: Working Capital Estimate from Pepsi (Rockstar) | B36: 0 | C36: 0 | D36: 0 | E36: 0 | F36: 29156 | G36: ='QTR CF'!W40+'QTR CF'!X40+'QTR CF'!Y40+'QTR CF'!Z40 -> 0 | H36: ='QTR CF'!AA40+'QTR CF'!AB40+'QTR CF'!AC40+'QTR CF'!AD40 -> 0 | I36: ='QTR CF'!AE40+'QTR CF'!AF40+'QTR CF'!AG40+'QTR CF'!AH40 -> 0 | J36: ='QTR CF'!AI40+'QTR CF'!AJ40+'QTR CF'!AK40+'QTR CF'!AL40 -> 0 | K36: ='QTR CF'!AM40+'QTR CF'!AN40+'QTR CF'!AO40+'QTR CF'!AP40 -> 0
A37: Cash Flow from Investing | B37: =SUM(B31:B36) -> -1264 | C37: =SUM(C31:C36) -> -5672 | D37: =SUM(D31:D36) -> -14200 | E37: =SUM(E31:E36) -> -101726 | F37: =SUM(F31:F36) -> -1295680 | G37: =SUM(G31:G36) -> -41609.437 | H37: =SUM(H31:H36) -> -40816.837 | I37: =SUM(I31:I36) -> -40039.335 | ... L37: =SUM(L31:L36) -> 0
A38: Finance Lease Payments | B38: -94 | C38: -63 | D38: -44 | E38: -61 | F38: 0 | G38: ='QTR CF'!W42+'QTR CF'!X42+'QTR CF'!Y42+'QTR CF'!Z42 -> 0 | H38: ='QTR CF'!AA42+'QTR CF'!AB42+'QTR CF'!AC42+'QTR CF'!AD42 -> 0 | I38: ='QTR CF'!AE42+'QTR CF'!AF42+'QTR CF'!AG42+'QTR CF'!AH42 -> 0 | J38: ='QTR CF'!AI42+'QTR CF'!AJ42+'QTR CF'!AK42+'QTR CF'!AL42 -> 0 | K38: ='QTR CF'!AM42+'QTR CF'!AN42+'QTR CF'!AO42+'QTR CF'!AP42 -> 0
A39: Proceeds from Exercise of Stock Options | B39: 3720 | C39: 3683 | D39: 2285 | E39: 3856 | F39: 0 | G39: ='QTR CF'!W44+'QTR CF'!X44+'QTR CF'!Y44+'QTR CF'!Z44 -> 0 | H39: ='QTR CF'!AA44+'QTR CF'!AB44+'QTR CF'!AC44+'QTR CF'!AD44 -> 0 | I39: ='QTR CF'!AE44+'QTR CF'!AF44+'QTR CF'!AG44+'QTR CF'!AH44 -> 0 | J39: ='QTR CF'!AI44+'QTR CF'!AJ44+'QTR CF'!AK44+'QTR CF'!AL44 -> 0 | K39: ='QTR CF'!AM44+'QTR CF'!AN44+'QTR CF'!AO44+'QTR CF'!AP44 -> 0
A40: Proceeds from Issuance of Common Stock | B40: 67769 | C40: 0 | D40: 0 | E40: 0 | F40: 0 | G40: ='QTR CF'!W43+'QTR CF'!X43+'QTR CF'!Y43+'QTR CF'!Z43 -> 0 | H40: ='QTR CF'!AA43+'QTR CF'!AB43+'QTR CF'!AC43+'QTR CF'!AD43 -> 0 | I40: ='QTR CF'!AE43+'QTR CF'!AF43+'QTR CF'!AG43+'QTR CF'!AH43 -> 0 | J40: ='QTR CF'!AI43+'QTR CF'!AJ43+'QTR CF'!AK43+'QTR CF'!AL43 -> 0 | K40: ='QTR CF'!AM43+'QTR CF'!AN43+'QTR CF'!AO43+'QTR CF'!AP43 -> 0
A41: Proceeds from Issuance of Preferred Stock | B41: 0 | C41: 542018 | D41: 0 | E41: 0 | F41: 0 | G41: ='QTR CF'!W45+'QTR CF'!X45+'QTR CF'!Y45+'QTR CF'!Z45 -> 0 | H41: ='QTR CF'!AA45+'QTR CF'!AB45+'QTR CF'!AC45+'QTR CF'!AD45 -> 0 | I41: ='QTR CF'!AE45+'QTR CF'!AF45+'QTR CF'!AG45+'QTR CF'!AH45 -> 0 | J41: ='QTR CF'!AI45+'QTR CF'!AJ45+'QTR CF'!AK45+'QTR CF'!AL45 -> 0 | K41: ='QTR CF'!AM45+'QTR CF'!AN45+'QTR CF'!AO45+'QTR CF'!AP45 -> 0
A42: Preferred Dividends | B42: 0 | C42: -11526 | D42: -27462 | E42: -27500 | F42: -37608 | G42: ='QTR CF'!W46+'QTR CF'!X46+'QTR CF'!Y46+'QTR CF'!Z46 -> -57228 | H42: ='QTR CF'!AA46+'QTR CF'!AB46+'QTR CF'!AC46+'QTR CF'!AD46 -> -57228 | I42: ='QTR CF'!AE46+'QTR CF'!AF46+'QTR CF'!AG46+'QTR CF'!AH46 -> -57228 | J42: ='QTR CF'!AI46+'QTR CF'!AJ46+'QTR CF'!AK46+'QTR CF'!AL46 -> -57228 | K42: ='QTR CF'!AM46+'QTR CF'!AN46+'QTR CF'!AO46+'QTR CF'!AP46 -> -57228
A43: Share Repurchases | B43: 0 | C43: 0 | D43: 0 | E43: -2261 | F43: -45504 | G43: ='QTR CF'!W47+'QTR CF'!X47+'QTR CF'!Y47+'QTR CF'!Z47 -> 0 | H43: ='QTR CF'!AA47+'QTR CF'!AB47+'QTR CF'!AC47+'QTR CF'!AD47 -> 0 | I43: ='QTR CF'!AE47+'QTR CF'!AF47+'QTR CF'!AG47+'QTR CF'!AH47 -> 0 | J43: ='QTR CF'!AI47+'QTR CF'!AJ47+'QTR CF'!AK47+'QTR CF'!AL47 -> 0 | K43: ='QTR CF'!AM47+'QTR CF'!AN47+'QTR CF'!AO47+'QTR CF'!AP47 -> 0
A44: Proceeds from Issuance of Long-Term Debt | B44: 0 | C44: 0 | D44: 0 | E44: 0 | F44: 900000 | G44: ='QTR CF'!W48+'QTR CF'!X48+'QTR CF'!Y48+'QTR CF'!Z48 -> 0 | H44: ='QTR CF'!AA48+'QTR CF'!AB48+'QTR CF'!AC48+'QTR CF'!AD48 -> 0 | I44: ='QTR CF'!AE48+'QTR CF'!AF48+'QTR CF'!AG48+'QTR CF'!AH48 -> 0 | J44: ='QTR CF'!AI48+'QTR CF'!AJ48+'QTR CF'!AK48+'QTR CF'!AL48 -> 0 | K44: ='QTR CF'!AM48+'QTR CF'!AN48+'QTR CF'!AO48+'QTR CF'!AP48 -> 0
A45: Repayments of Long-Term Debt | B45: 0 | C45: 0 | D45: 0 | E45: 0 | F45: -201750 | G45: ='QTR CF'!W49+'QTR CF'!X49+'QTR CF'!Y49+'QTR CF'!Z49 -> 0 | H45: ='QTR CF'!AA49+'QTR CF'!AB49+'QTR CF'!AC49+'QTR CF'!AD49 -> 0 | I45: ='QTR CF'!AE49+'QTR CF'!AF49+'QTR CF'!AG49+'QTR CF'!AH49 -> 0 | J45: ='QTR CF'!AI49+'QTR CF'!AJ49+'QTR CF'!AK49+'QTR CF'!AL49 -> 0 | K45: ='QTR CF'!AM49+'QTR CF'!AN49+'QTR CF'!AO49+'QTR CF'!AP49 -> 0
A46: Debt Issuance Fees | B46: 0 | C46: 0 | D46: 0 | E46: 0 | F46: -32367 | G46: ='QTR CF'!W50+'QTR CF'!X50+'QTR CF'!Y50+'QTR CF'!Z50 -> 0 | H46: ='QTR CF'!AA50+'QTR CF'!AB50+'QTR CF'!AC50+'QTR CF'!AD50 -> 0 | I46: ='QTR CF'!AE50+'QTR CF'!AF50+'QTR CF'!AG50+'QTR CF'!AH50 -> 0 | J46: ='QTR CF'!AI50+'QTR CF'!AJ50+'QTR CF'!AK50+'QTR CF'!AL50 -> 0 | K46: ='QTR CF'!AM50+'QTR CF'!AN50+'QTR CF'!AO50+'QTR CF'!AP50 -> 0
A47: Other Financing Activities | B47: 0 | C47: 0 | D47: 0 | E47: 0 | F47: -7 | G47: ='QTR CF'!W51+'QTR CF'!X51+'QTR CF'!Y51+'QTR CF'!Z51 -> 0 | H47: ='QTR CF'!AA51+'QTR CF'!AB51+'QTR CF'!AC51+'QTR CF'!AD51 -> 0 | I47: ='QTR CF'!AE51+'QTR CF'!AF51+'QTR CF'!AG51+'QTR CF'!AH51 -> 0 | J47: ='QTR CF'!AI51+'QTR CF'!AJ51+'QTR CF'!AK51+'QTR CF'!AL51 -> 0 | K47: ='QTR CF'!AM51+'QTR CF'!AN51+'QTR CF'!AO51+'QTR CF'!AP51 -> 0
A48: Cash Flow from Financing | B48: =SUM(B38:B47) -> 71395 | C48: =SUM(C38:C47) -> 534112 | D48: =SUM(D38:D47) -> -25221 | E48: =SUM(E38:E47) -> -25966 | F48: =SUM(F38:F47) -> 582764 | G48: =SUM(G38:G47) -> -57228 | H48: =SUM(H38:H47) -> -57228 | I48: =SUM(I38:I47) -> -57228 | ... L48: =SUM(L38:L47) -> 0
A49: FX Effect on Cash | B49: -538 | C49: 50 | D49: 1257 | E49: -997 | F49: 3271 | G49: ='QTR CF'!W53+'QTR CF'!X53+'QTR CF'!Y53+'QTR CF'!Z53 -> 4388 | H49: ='QTR CF'!AA53+'QTR CF'!AB53+'QTR CF'!AC53+'QTR CF'!AD53 -> 4388 | I49: ='QTR CF'!AE53+'QTR CF'!AF53+'QTR CF'!AG53+'QTR CF'!AH53 -> 4388 | J49: ='QTR CF'!AI53+'QTR CF'!AJ53+'QTR CF'!AK53+'QTR CF'!AL53 -> 4388 | K49: ='QTR CF'!AM53+'QTR CF'!AN53+'QTR CF'!AO53+'QTR CF'!AP53 -> 4388
A50: Net Change in Cash | B50: =B30+B37+B48+B49 -> -26993 | C50: =C30+C37+C48+C49 -> 636672 | D50: =D30+D37+D48+D49 -> 103054 | E50: =E30+E37+E48+E49 -> 134209 | F50: =F30+F37+F48+F49 -> -350203 | G50: =G30+G37+G48+G49 -> 232347.07 | H50: =H30+H37+H48+H49 -> 486755.96 | I50: =I30+I37+I48+I49 -> 477261.21 | ... L50: =L30+L37+L48+L49 -> 0

Sheet YTD P&L
B1: Q2 FY2020 | C1: Q3 FY2020 | D1: Q1 FY2021 | E1: Q2 FY2021 | F1: Q3 FY2021 | G1: Q1 FY2022 | H1: Q2 FY2022 | I1: Q3 FY2022 | J1: Q1 FY2023 | K1: Q2 FY2023 | L1: Q3 FY2023 | M1: Q1 FY2024 | N1: Q2 FY2024 | O1: Q3 FY2024 | P1: Q1 FY2025 | Q1: Q2 FY2025 | R1: Q3 FY2025
A2: Net Sales / Revenue | B2: 58222116 | C2: 95061265 | D2: 50035 | E2: 115108202 | F2: 210017302 | G2: 133388 | H2: 287408 | I2: 475640 | J2: 259939 | K2: 585822 | L2: 970579 | M2: 355708 | N2: 757685 | O2: 1023433 | P2: 329276 | Q2: 1068535 | R2: 1793641
A3: COGS | B3: -32207118 | C3: -51512534 | D3: -29456 | E3: -66279738 | F3: -123495466 | G3: -79494 | H3: -174195 | I3: -283778 | J3: -146121 | K3: -313010 | L3: -503685 | M3: -173501 | N3: -366380 | O3: -509899 | P3: -156903 | Q3: -515311 | R3: -868138
A4: Gross Profit (Loss) | B4: =B2+B3 -> 26014998 | C4: =C2+C3 -> 43548731 | D4: =D2+D3 -> 20579 | E4: =E2+E3 -> 48828464 | F4: =F2+F3 -> 86521836 | G4: =G2+G3 -> 53894 | H4: =H2+H3 -> 113213 | I4: =I2+I3 -> 191862 | ... R4: =R2+R3 -> 925503
A5: Sales and Marketing | B5: -15372918 | C5: -23640914 | D5: -11959 | E5: -27490041 | F5: -50111103 | G5: -31597 | H5: -64072 | I5: -262782 | J5: 0 | K5: 0 | L5: 0 | M5: 0 | N5: 0 | O5: 0 | P5: 0 | Q5: 0 | R5: 0
A6: General and Administrative | B6: -8426165 | C6: -13178593 | D6: -7807 | E6: -16926198 | F6: -28066228 | G6: -12181 | H6: -26595 | I6: -54135 | J6: 0 | K6: 0 | L6: 0 | M6: 0 | N6: 0 | O6: 0 | P6: 0 | Q6: 0 | R6: 0
A7: Operating Expenses | B7: -23799083 | C7: -36819507 | D7: -19766 | E7: -44416239 | F7: -78177331 | G7: -43778 | H7: -90667 | I7: -316917 | J7: 0 | K7: 0 | L7: 0 | M7: 0 | N7: 0 | O7: 0 | P7: 0 | Q7: 0 | R7: 0
A8: SG&A | B8: 0 | C8: 0 | D8: 0 | E8: 0 | F8: 0 | G8: 0 | H8: 0 | I8: 0 | J8: -68905 | K8: -163086 | L8: -259471 | M8: -99017 | N8: -213867 | O8: -339310 | P8: -120342 | Q8: -358228 | R8: -563799
A9: Distributor Termination Fees | B9: 0 | C9: 0 | D9: 0 | E9: 0 | F9: 0 | G9: 0 | H9: 0 | I9: 0 | J9: 0 | K9: 0 | L9: 0 | M9: 0 | N9: 0 | O9: 0 | P9: 0 | Q9: 0 | R9: -246707
A10: Income (Loss) from Operations | B10: =B4+SUM(B5:B9) -> -21583168 | C10: =C4+SUM(C5:C9) -> -30090283 | D10: =D4+SUM(D5:D9) -> -18953 | E10: =E4+SUM(E5:E9) -> -40004014 | F10: =F4+SUM(F5:F9) -> -69832826 | G10: =G4+SUM(G5:G9) -> -33662 | H10: =H4+SUM(H5:H9) -> -68121 | I10: =I4+SUM(I5:I9) -> -441972 | ... R10: =R4+SUM(R5:R9) -> 114997
A11: Interest Income (Expense) | B11: -394850 | C11: -642249 | D11: 85 | E11: 160141 | F11: 232090 | G11: 76 | H11: 129 | I11: 1579 | J11: 4969 | K11: 10542 | L11: 17767 | M11: 9640 | N11: 20287 | O11: 31399 | P11: 7846 | Q11: -6196 | R11: -19592
A12: Foreign Currency Gain (Loss) | B12: 96005 | C12: 646515 | D12: -301 | E12: -123636 | F12: -451217 | G12: -162 | H12: -676 | I12: -930 | J12: -118 | K12: -1049 | L12: -1226 | M12: -369 | N12: -633 | O12: -356 | P12: 0 | Q12: 0 | R12: 0
A13: Other Income (Expense) | B13: 35203 | C13: -27614 | D13: -12 | E13: 97038 | F13: 0 | G13: 0 | H13: 0 | I13: 0 | J13: 0 | K13: 0 | L13: 0 | M13: 0 | N13: 0 | O13: 0 | P13: 1116 | Q13: 1658 | R13: 7022
A14: Gain (Loss) on Lease Cancellations | B14: 152112 | C14: 152112 | D14: 0 | E14: 0 | F14: 0 | G14: 0 | H14: 0 | I14: 0 | J14: 0 | K14: 0 | L14: 0 | M14: 0 | N14: 0 | O14: 0 | P14: 0 | Q14: 0 | R14: 0
A15: Pre-Tax Income (Loss) | B15: =B10+SUM(B11:B14) -> -21694698 | C15: =C10+SUM(C11:C14) -> -29961519 | D15: =D10+SUM(D11:D14) -> -19181 | E15: =E10+SUM(E11:E14) -> -39870471 | F15: =F10+SUM(F11:F14) -> -70051953 | G15: =G10+SUM(G11:G14) -> -33748 | H15: =H10+SUM(H11:H14) -> -68668 | I15: =I10+SUM(I11:I14) -> -441323 | ... R15: =R10+SUM(R11:R14) -> 102427
A16: Income Tax (Expense) Benefit | B16: 0 | C16: 0 | D16: 0 | E16: 0 | F16: -833819 | G16: -3351 | H16: -6161 | I16: -41653 | J16: -8537 | K16: -26483 | L16: -47279 | M16: -14650 | N16: -39498 | O16: -41317 | P16: -16574 | Q16: -46184 | R16: -19167
A17: Net Income (Loss) | B17: =B15+B16 -> -21694698 | C17: =C15+C16 -> -29961519 | D17: =D15+D16 -> -19181 | E17: =E15+E16 -> -39870471 | F17: =F15+F16 -> -70885772 | G17: =G15+G16 -> -37099 | H17: =H15+H16 -> -74829 | I17: =I15+I16 -> -482976 | ... R17: =R15+R16 -> 83260
A18: Preferred Dividends | B18: 0 | C18: 0 | D18: 0 | E18: 0 | F18: 0 | G18: 0 | H18: 0 | I18: -4596 | J18: -6781 | K18: -13637 | L18: -20512 | M18: -6837 | N18: -13675 | O18: -20588 | P18: -6781 | Q18: -13632 | R18: -23289
A19: Income Allocated to Participating Preferred | B19: 0 | C19: 0 | D19: 0 | E19: 0 | F19: 0 | G19: 0 | H19: 0 | I19: 0 | J19: 0 | K19: -6727 | L19: -13263 | M19: -6128 | N19: -12417 | O19: -12357 | P19: -3219 | Q19: -10703 | R19: -5272
A20: Net Income (Loss) Attributable to Common Shareholders | B20: =B17+B18+B19 -> -21694698 | C20: =C17+C18+C19 -> -29961519 | D20: =D17+D18+D19 -> -19181 | E20: =E17+E18+E19 -> -39870471 | F20: =F17+F18+F19 -> -70885772 | G20: =G17+G18+G19 -> -37099 | H20: =H17+H18+H19 -> -74829 | I20: =I17+I18+I19 -> -487572 | ... R20: =R17+R18+R19 -> 54699

Sheet YTD BS
B1: Q4 FY2020 | C1: Q2 FY2021 | D1: Q3 FY2021 | E1: Q4 FY2021 | F1: Q1 FY2022 | G1: Q2 FY2022 | H1: Q3 FY2022 | I1: Q4 FY2022 | J1: Q1 FY2023 | K1: Q2 FY2023 | L1: Q3 FY2023 | M1: Q4 FY2023 | N1: Q1 FY2024 | O1: Q2 FY2024 | P1: Q3 FY2024 | Q1: Q4 FY2024 | R1: Q1 FY2025 | S1: Q2 FY2025 | T1: Q3 FY2025
A2: Cash, Cash Equivalents & Restricted Cash | B2: 43248021 | C2: 83789981 | D2: 61377202 | E2: 16255 | F2: 25532 | G2: 60031 | H2: 726972 | I2: 652927 | J2: 633581 | K2: 681054 | L2: 760022 | M2: 755981 | N2: 879498 | O2: 903210 | P2: 903748 | Q2: 890190 | R2: 977285 | S2: 615233 | T2: 932463
A3: Accounts Receivable | B3: 14986213 | C3: 32398823 | D3: 43500578 | E3: 38741 | F3: 72707 | G3: 66195 | H3: 117003 | I3: 63311 | J3: 172032 | K3: 197811 | L3: 215243 | M3: 183703 | N3: 200117 | O3: 262920 | P3: 208774 | Q3: 270342 | R3: 256424 | S3: 490389 | T3: 513682
A4: Note Receivable - Current | B4: 1885887 | C4: 2545745 | D4: 2543225 | E4: 2588 | F4: 5833 | G4: 3066 | H4: 2888 | I4: 2979 | J4: 3587 | K4: 3323 | L4: 3309 | M4: 2318 | N4: 2259 | O4: 1166 | P4: 1025 | Q4: 0 | R4: 0 | S4: 0 | T4: 0
A5: Inventories | B5: 18403622 | C5: 63826596 | D5: 122311445 | E5: 191222 | F5: 184094 | G5: 162138 | H5: 153933 | I5: 173289 | J5: 154280 | K5: 152545 | L5: 198704 | M5: 229275 | N5: 197504 | O5: 180669 | P5: 197572 | Q5: 131165 | R5: 141159 | S5: 230046 | T5: 282514
A6: Prepaid Expenses | B6: 14626922 | C6: 22744642 | D6: 22829510 | E6: 13555 | F6: 10042 | G6: 12298 | H6: 12096 | I6: 11341 | J6: 15507 | K6: 23398 | L6: 23747 | M6: 19503 | N6: 21523 | O6: 22900 | P6: 38227 | Q6: 18759 | R6: 22464 | S6: 41420 | T6: 163395
A7: Deferred Other Costs - Current | B7: 0 | C7: 0 | D7: 0 | E7: 0 | F7: 0 | G7: 0 | H7: 14124 | I7: 14124 | J7: 14124 | K7: 14124 | L7: 14124 | M7: 14124 | N7: 14124 | O7: 14124 | P7: 14124 | Q7: 14124 | R7: 14124 | S7: 14124 | T7: 49520
A8: Total Current Assets | B8: =SUM(B2:B7) -> 93150665 | C8: =SUM(C2:C7) -> 205305787 | D8: =SUM(D2:D7) -> 252561960 | E8: =SUM(E2:E7) -> 262361 | F8: =SUM(F2:F7) -> 298208 | G8: =SUM(G2:G7) -> 303728 | H8: =SUM(H2:H7) -> 1027016 | I8: =SUM(I2:I7) -> 917971 | ... T8: =SUM(T2:T7) -> 1941574
A9: Note Receivable - Non-Current | B9: 9429437 | C9: 7000800 | D9: 6993869 | E9: 7117 | F9: 3888 | G9: 3679 | H9: 3465 | I9: 3574 | J9: 0 | K9: 0 | L9: 0 | M9: 0 | N9: 0 | O9: 0 | P9: 0 | Q9: 0 | R9: 0 | S9: 0 | T9: 0
A10: Net PP&E | B10: 579377 | C10: 1617002 | D10: 2454914 | E10: 3180 | F10: 3702 | G10: 5135 | H10: 5782 | I10: 10185 | J10: 12054 | K10: 15892 | L10: 21061 | M10: 24868 | N10: 28350 | O10: 36282 | P10: 38370 | Q10: 55602 | R10: 58698 | S10: 72516 | T10: 80925
A11: ROU Assets - Operating - Non-Current | B11: 836038 | C11: 704857 | D11: 888911 | E11: 1128 | F11: 1141 | G11: 954 | H11: 1105 | I11: 972 | J11: 931 | K11: 756 | L11: 1152 | M11: 1957 | N11: 1688 | O11: 1507 | P11: 5506 | Q11: 21606 | R11: 20866 | S11: 0 | T11: 0
A12: Intangible Assets | B12: 16590083 | C12: 16287537 | D12: 16811762 | E12: 16301 | F12: 15838 | G12: 14689 | H12: 11322 | I12: 12254 | J12: 12359 | K12: 12211 | L12: 11772 | M12: 12139 | N12: 11741 | O12: 11491 | P12: 11877 | Q12: 12213 | R12: 12444 | S12: 1222115 | T12: 1397819
A13: Goodwill | B13: 10419321 | C13: 10419321 | D13: 14851635 | E13: 14527 | F13: 14238 | G13: 13323 | H13: 12502 | I13: 13679 | J13: 13949 | K13: 13937 | L13: 13588 | M13: 14173 | N13: 13866 | O13: 13730 | P13: 14360 | Q13: 71582 | R13: 72128 | S13: 802234 | T13: 914957
A14: Deferred Other Costs - Non-Current | B14: 0 | C14: 0 | D14: 0 | E14: 0 | F14: 0 | G14: 0 | H14: 265993 | I14: 262462 | J14: 258931 | K14: 255400 | L14: 251869 | M14: 248338 | N14: 244807 | O14: 241276 | P14: 237746 | Q14: 234215 | R14: 230684 | S14: 227153 | T14: 784214
A15: Deferred Tax Assets | B15: 0 | C15: 0 | D15: 0 | E15: 9019 | F15: 6396 | G15: 7686 | H15: 0 | I15: 501 | J15: 482 | K15: 28373 | L15: 30614 | M15: 29518 | N15: 22437 | O15: 22727 | P15: 24186 | Q15: 38699 | R15: 38525 | S15: 43158 | T15: 110410
A16: ROU Assets - Finance - Non-Current | B16: 162119 | C16: 100365 | D16: 106675 | E16: 86 | F16: 220 | G16: 180 | H16: 222 | I16: 208 | J16: 191 | K16: 171 | L16: 148 | M16: 208 | N16: 263 | O16: 233 | P16: 214 | Q16: 0 | R16: 0 | S16: 0 | T16: 0
A17: Other Non-Current Assets | B17: 122733 | C17: 112456 | D17: 308449 | E17: 300 | F17: 293 | G17: 264 | H17: 242 | I17: 263 | J17: 263 | K17: 254 | L17: 265 | M17: 291 | N17: 7963 | O17: 6653 | P17: 8594 | Q17: 8384 | R17: 14717 | S17: 36755 | T17: 35809
A18: Total Assets | B18: =B8+SUM(B9:B17) -> 131289773 | C18: =C8+SUM(C9:C17) -> 241548125 | D18: =D8+SUM(D9:D17) -> 294978175 | E18: =E8+SUM(E9:E17) -> 314019 | F18: =F8+SUM(F9:F17) -> 343924 | G18: =G8+SUM(G9:G17) -> 349638 | H18: =H8+SUM(H9:H17) -> 1327649 | I18: =I8+SUM(I9:I17) -> 1222069 | ... T18: =T8+SUM(T9:T17) -> 5265708
A19: Accounts Payable | B19: 25412753 | C19: 52992075 | D19: 91931593 | E19: 91479 | F19: 109307 | G19: 102416 | H19: 143947 | I19: 107340 | J19: 107112 | K19: 94313 | L19: 121088 | M19: 42840 | N19: 40196 | O19: 47423 | P19: 30938 | Q19: 41287 | R19: 61052 | S19: 120962 | T19: 97794
A20: Accrued Expenses | B20: 0 | C20: 0 | D20: 0 | E20: 0 | F20: 0 | G20: 0 | H20: 0 | I20: 0 | J20: 0 | K20: 0 | L20: 0 | M20: 62120 | N20: 63871 | O20: 79633 | P20: 73024 | Q20: 148780 | R20: 152046 | S20: 225859 | T20: 311768
A21: Income Taxes Payable | B21: 0 | C21: 0 | D21: 0 | E21: 0 | F21: 0 | G21: 0 | H21: 0 | I21: 0 | J21: 0 | K21: 58798 | L21: 58855 | M21: 50424 | N21: 58619 | O21: 5374 | P21: 739 | Q21: 10834 | R21: 26206 | S21: 21765 | T21: 49590
A22: Accrued Distributor Termination Fees | B22: 0 | C22: 0 | D22: 0 | E22: 0 | F22: 0 | G22: 0 | H22: 115551 | I22: 3986 | J22: 1063 | K22: 0 | L22: 0 | M22: 0 | N22: 0 | O22: 0 | P22: 0 | Q22: 0 | R22: 0 | S22: 0 | T22: 252953
A23: Accrued Promotional Allowance | B23: 0 | C23: 0 | D23: 0 | E23: 0 | F23: 0 | G23: 0 | H23: 0 | I23: 35977 | J23: 68225 | K23: 98933 | L23: 136557 | M23: 99787 | N23: 129201 | O23: 156479 | P23: 158810 | Q23: 135948 | R23: 151327 | S23: 200169 | T23: 234068
A24: Lease Liability - Operating - Current | B24: 321283 | C24: 318142 | D24: 376602 | E24: 512 | F24: 569 | G24: 556 | H24: 663 | I24: 661 | J24: 605 | K24: 505 | L24: 628 | M24: 980 | N24: 821 | O24: 729 | P24: 1358 | Q24: 3265 | R24: 3550 | S24: 0 | T24: 0
A25: Lease Liability - Finance - Current | B25: 205824 | C25: 191753 | D25: 155508 | E25: 157 | F25: 141 | G25: 101 | H25: 95 | I25: 70 | J25: 69 | K25: 67 | L25: 63 | M25: 59 | N25: 61 | O25: 61 | P25: 99 | Q25: 0 | R25: 0 | S25: 0 | T25: 0
A26: Contingent Consideration - Current | B26: 0 | C26: 0 | D26: 0 | E26: 0 | F26: 0 | G26: 0 | H26: 0 | I26: 0 | J26: 0 | K26: 0 | L26: 0 | M26: 0 | N26: 0 | O26: 0 | P26: 0 | Q26: 0 | R26: 0 | S26: 25000 | T26: 25000
A27: Deferred Revenue - Current | B27: 0 | C27: 0 | D27: 0 | E27: 0 | F27: 0 | G27: 0 | H27: 7770 | I27: 9675 | J27: 9563 | K27: 9500 | L27: 9500 | M27: 9513 | N27: 9513 | O27: 9513 | P27: 9513 | Q27: 9513 | R27: 9513 | S27: 16071 | T27: 25557
A28: Other Current Liabilities | B28: 425232 | C28: 754907 | D28: 957627 | E28: 976 | F28: 1734 | G28: 2761 | H28: 3267 | I28: 3586 | J28: 5094 | K28: 7109 | L28: 8826 | M28: 10890 | N28: 12987 | O28: 13772 | P28: 14979 | Q28: 15908 | R28: 14160 | S28: 49949 | T28: 32258
A29: Total Current Liabilities | B29: =SUM(B19:B28) -> 26365092 | C29: =SUM(C19:C28) -> 54256877 | D29: =SUM(D19:D28) -> 93421330 | E29: =SUM(E19:E28) -> 93124 | F29: =SUM(F19:F28) -> 111751 | G29: =SUM(G19:G28) -> 105834 | H29: =SUM(H19:H28) -> 271293 | I29: =SUM(I19:I28) -> 161295 | ... T29: =SUM(T19:T28) -> 1028988
A30: Lease Liability - Operating - Non-Current | B30: 514948 | C30: 391157 | D30: 550547 | E30: 658 | F30: 597 | G30: 420 | H30: 462 | I30: 326 | J30: 336 | K30: 249 | L30: 512 | M30: 955 | N30: 850 | O30: 762 | P30: 4193 | Q30: 16674 | R30: 16152 | S30: 0 | T30: 0
A31: Lease Liability - Finance - Non-Current | B31: 82290 | C31: 60731 | D31: 88649 | E31: 45 | F31: 138 | G31: 138 | H31: 167 | I31: 162 | J31: 156 | K31: 147 | L31: 135 | M31: 193 | N31: 245 | O31: 228 | P31: 189 | Q31: 0 | R31: 0 | S31: 0 | T31: 0
A32: Deferred Tax Liability | B32: 0 | C32: 0 | D32: 3497240 | E32: 3146 | F32: 3084 | G32: 2886 | H32: 25457 | I32: 15919 | J32: 19250 | K32: 2333 | L32: 2249 | M32: 2880 | N32: 2248 | O32: 2201 | P32: 2275 | Q32: 0 | R32: 0 | S32: 0 | T32: 0
A33: Long-Term Debt | B33: 0 | C33: 0 | D33: 0 | E33: 0 | F33: 0 | G33: 0 | H33: 0 | I33: 0 | J33: 0 | K33: 0 | L33: 0 | M33: 0 | N33: 0 | O33: 0 | P33: 0 | Q33: 0 | R33: 0 | S33: 862917 | T33: 861472
A34: Deferred Revenue - Non-Current | B34: 0 | C34: 0 | D34: 0 | E34: 0 | F34: 0 | G34: 0 | H34: 146333 | I34: 179788 | J34: 175275 | K34: 171745 | L34: 169370 | M34: 167227 | N34: 164849 | O34: 162471 | P34: 160092 | Q34: 157714 | R34: 155336 | S34: 156135 | T34: 387432
A35: Other Non-Current Liabilities | B35: 0 | C35: 0 | D35: 22198 | E35: 0 | F35: 0 | G35: 487 | H35: 0 | I35: 0 | J35: 0 | K35: 0 | L35: 0 | M35: 0 | N35: 0 | O35: 0 | P35: 0 | Q35: 2541 | R35: 2574 | S35: 25002 | T35: 24431
A36: Total Liabilities | B36: =B29+SUM(B30:B35) -> 26962330 | C36: =C29+SUM(C30:C35) -> 54708765 | D36: =D29+SUM(D30:D35) -> 97579964 | E36: =E29+SUM(E30:E35) -> 96973 | F36: =F29+SUM(F30:F35) -> 115570 | G36: =G29+SUM(G30:G35) -> 109765 | H36: =H29+SUM(H30:H35) -> 443712 | I36: =I29+SUM(I30:I35) -> 357490 | ... T36: =T29+SUM(T30:T35) -> 2302323
A37: Convertible Preferred Stock | B37: 0 | C37: 0 | D37: 0 | E37: 0 | F37: 0 | G37: 0 | H37: 824488 | I37: 824488 | J37: 824488 | K37: 824488 | L37: 824488 | M37: 824488 | N37: 824488 | O37: 824488 | P37: 824488 | Q37: 824488 | R37: 824488 | S37: 824488 | T37: 1760275
A38: Common Stock | B38: 72263 | C38: 74471 | D38: 74746 | E38: 75 | F38: 75 | G38: 76 | H38: 76 | I38: 76 | J38: 77 | K38: 77 | L38: 77 | M38: 77 | N38: 78 | O38: 78 | P38: 79 | Q38: 79 | R38: 79 | S38: 101 | T38: 101
A39: Treasury Stock | B39: 0 | C39: 0 | D39: 0 | E39: 0 | F39: 0 | G39: 0 | H39: 0 | I39: 0 | J39: 0 | K39: 0 | L39: 0 | M39: 0 | N39: 0 | O39: 0 | P39: 0 | Q39: 0 | R39: 0 | S39: 0 | T39: 0
A40: Additional Paid-in Capital | B40: 159884154 | C40: 237763609 | D40: 244293710 | E40: 267847 | F40: 272967 | G40: 277623 | H40: 281133 | I40: 280668 | J40: 279872 | K40: 278980 | L40: 277980 | M40: 276717 | N40: 281247 | O40: 286173 | P40: 292576 | Q40: 297579 | R40: 300877 | S40: 1028384 | T40: 1035021
A41: Accumulated Other Comprehensive Income (Loss) | B41: -202142 | C41: -117656 | D41: 1165027 | E41: 614 | F41: 123 | G41: -2173 | H41: -4211 | I41: -1881 | J41: -1287 | K41: -1877 | L41: -2541 | M41: -701 | N41: -2055 | O41: -2363 | P41: -338 | Q41: -3250 | R41: -1001 | S41: 2178 | T41: 2508
A42: Retained Earnings (Accumulated Deficit) | B42: -55426832 | C42: -50881064 | D42: -48135273 | E42: -51490 | F42: -44811 | G42: -35653 | H42: -217549 | I42: -238772 | J42: -197627 | K42: -146118 | L42: -62169 | M42: -12053 | N42: 58921 | O42: 131866 | P42: 131309 | Q42: 105521 | R42: 143159 | S42: 236163 | T42: 165480
A43: Total Stockholders' Equity | B43: =SUM(B37:B42) -> 104327443 | C43: =SUM(C37:C42) -> 186839360 | D43: =SUM(D37:D42) -> 197398210 | E43: =SUM(E37:E42) -> 217046 | F43: =SUM(F37:F42) -> 228354 | G43: =SUM(G37:G42) -> 239873 | H43: =SUM(H37:H42) -> 883937 | I43: =SUM(I37:I42) -> 864579 | ... T43: =SUM(T37:T42) -> 2963385
A44: Total Liabilities, Mezzanine & Stockholders' Equity | B44: =B36+B43 -> 131289773 | C44: =C36+C43 -> 241548125 | D44: =D36+D43 -> 294978174 | E44: =E36+E43 -> 314019 | F44: =F36+F43 -> 343924 | G44: =G36+G43 -> 349638 | H44: =H36+H43 -> 1327649 | I44: =I36+I43 -> 1222069 | ... T44: =T36+T43 -> 5265708

Sheet YTD CF
B1: Q2 FY2020 | C1: Q3 FY2020 | D1: Q1 FY2021 | E1: Q2 FY2021 | F1: Q3 FY2021 | G1: Q1 FY2022 | H1: Q2 FY2022 | I1: Q3 FY2022 | J1: Q1 FY2023 | K1: Q2 FY2023 | L1: Q3 FY2023 | M1: Q1 FY2024 | N1: Q2 FY2024 | O1: Q3 FY2024 | P1: Q1 FY2025 | Q1: Q2 FY2025 | R1: Q3 FY2025
A2: Net Income (Loss) | B2: 2104385 | C2: 6857988 | D2: 585 | E2: 4545768 | F2: 7291559 | G2: 6679 | H2: 15838 | I2: -166059 | J2: 41227 | K2: 92736 | L2: 176685 | M2: 77811 | N2: 157594 | O2: 163950 | P2: 44419 | Q2: 144274 | R2: 83260
A3: Depreciation | B3: 50351 | C3: 82180 | D3: 108 | E3: 178425 | F3: 519765 | G3: 245 | H3: 556 | I3: 952 | J3: 404 | K3: 953 | L3: 1676 | M3: 0 | N3: 0 | O3: 0 | P3: 0 | Q3: 0 | R3: 0
A4: Amortization | B4: 851045 | C4: 1224684 | D4: 188 | E4: 375141 | F4: 550800 | G4: 141 | H4: 275 | I4: 402 | J4: 145 | K4: 294 | L4: 445 | M4: 0 | N4: 0 | O4: 0 | P4: 0 | Q4: 0 | R4: 0
A5: Impairment of Intangibles | B5: 0 | C5: 0 | D5: 0 | E5: 0 | F5: 0 | G5: 0 | H5: 0 | I5: 2379 | J5: 0 | K5: 0 | L5: 0 | M5: 0 | N5: 0 | O5: 0 | P5: 0 | Q5: 0 | R5: 0
A6: Depreciation & Amortization | B6: 0 | C6: 0 | D6: 0 | E6: 0 | F6: 0 | G6: 0 | H6: 0 | I6: 0 | J6: 0 | K6: 0 | L6: 0 | M6: 1229 | N6: 2648 | O6: 4888 | P6: 2611 | Q6: 11730 | R6: 20516
A7: Allowance for Credit Losses | B7: 221182 | C7: 244685 | D7: 223 | E7: 854606 | F7: -207261 | G7: 455 | H7: 466 | I7: 705 | J7: 837 | K7: 1088 | L7: 1880 | M7: 2250 | N7: 4072 | O7: 4279 | P7: 2077 | Q7: 5529 | R7: 3226
A8: Amortization of Deferred Other Costs | B8: 0 | C8: 0 | D8: 0 | E8: 0 | F8: 0 | G8: 0 | H8: 0 | I8: 2354 | J8: 3531 | K8: 7062 | L8: 10593 | M8: 3531 | N8: 7062 | O8: 10593 | P8: 3531 | Q8: 7062 | R8: 13391
A9: Inventory Write-Down | B9: -137370 | C9: 211822 | D9: 754 | E9: 1260076 | F9: 12234 | G9: 2596 | H9: 331 | I9: 1078 | J9: 1672 | K9: -3888 | L9: 2677 | M9: 2386 | N9: 11554 | O9: 17118 | P9: 5337 | Q9: 15262 | R9: 22313
A10: Gain (Loss) on Disposal of PP&E | B10: 0 | C10: 0 | D10: 0 | E10: 0 | F10: 0 | G10: 0 | H10: 0 | I10: 0 | J10: 0 | K10: 191 | L10: 195 | M10: -8 | N10: 31 | O10: 126 | P10: 0 | Q10: 0 | R10: 0
A11: Stock-Based Compensation | B11: 2574999 | C11: 4718699 | D11: 3575 | E11: 7597260 | F11: 13400581 | G11: 4310 | H11: 8517 | I11: 14780 | J11: 5507 | K11: 11242 | L11: 16221 | M11: 3563 | N11: 8309 | O11: 13685 | P11: 5029 | Q11: 11463 | R11: 18847
A12: Gain on China Transaction | B12: 23100 | C12: -384493 | D12: 0 | E12: 0 | F12: 0 | G12: 0 | H12: 0 | I12: 0 | J12: 0 | K12: 0 | L12: 0 | M12: 0 | N12: 0 | O12: 0 | P12: 0 | Q12: 0 | R12: 0
A13: Gain (Loss) on Lease Cancellations | B13: -152112 | C13: -152112 | D13: 0 | E13: 0 | F13: -14669 | G13: 0 | H13: 0 | I13: 0 | J13: 0 | K13: 0 | L13: 0 | M13: 0 | N13: 0 | O13: 0 | P13: 0 | Q13: 0 | R13: 0
... A33: Net Change in Other Working Capital | B33: 0 | C33: 213764 | D33: 0 | E33: 0 | F33: 532395 | G33: 0 | H33: 488 | I33: 0 | J33: 0 | K33: 0 | L33: 0 | M33: 0 | N33: 0 | O33: 0 | P33: 148 | Q33: -1210 | R33: -1786
A34: Cash Flow from Operations | B34: =SUM(B2:B33) -> -4246078 | C34: =SUM(C2:C33) -> 3843510 | D34: =SUM(D2:D33) -> -13318 | E34: =SUM(E2:E33) -> -30329464 | F34: =SUM(F2:F33) -> -52063949 | G34: =SUM(G2:G33) -> 9125 | H34: =SUM(H2:H33) -> 42296 | I34: =SUM(I2:I33) -> 170967 | ... R34: =SUM(R2:R33) -> 478880
A35: Collections from Note Receivable | B35: 1331011 | C35: 1331011 | D35: 1876 | E35: 1876273 | F35: 1885724 | G35: 0 | H35: 2592 | I35: 2592 | J35: 3233 | K35: 3233 | L35: 3233 | M35: 0 | N35: 0 | O35: 0 | P35: 0 | Q35: 0 | R35: 0
A36: Purchase of PP&E | B36: -315777 | C36: -416671 | D36: -698 | E36: -1216050 | F36: -2395302 | G36: -742 | H36: -2456 | I36: -3477 | J36: -2253 | K36: -6810 | L36: -12687 | M36: -4525 | N36: -13739 | O36: -17983 | P36: -6944 | Q36: -15194 | R36: -25539
A37: Purchase of Non-Marketable Equity Securities | B37: 0 | C37: 0 | D37: 0 | E37: 0 | F37: 0 | G37: 0 | H37: 0 | I37: 0 | J37: 0 | K37: 0 | L37: 0 | M37: 0 | N37: 0 | O37: -3000 | P37: 0 | Q37: -5000 | R37: -5000
A38: Acquisition of Big Beverages | B38: 0 | C38: 0 | D38: 0 | E38: 0 | F38: 0 | G38: 0 | H38: 0 | I38: 0 | J38: 0 | K38: 0 | L38: 0 | M38: 0 | N38: 0 | O38: 0 | P38: 0 | Q38: 0 | R38: 0
A39: Acquisitions, Net of Cash Acquired | B39: 0 | C39: 0 | D39: 0 | E39: 0 | F39: 0 | G39: 0 | H39: 0 | I39: 0 | J39: 0 | K39: 0 | L39: 0 | M39: 0 | N39: 0 | O39: 0 | P39: 0 | Q39: -1256351 | R39: -1278769
A40: Working Capital Estimate from Pepsi (Rockstar) | B40: 0 | C40: 0 | D40: 0 | E40: 0 | F40: 0 | G40: 0 | H40: 0 | I40: 0 | J40: 0 | K40: 0 | L40: 0 | M40: 0 | N40: 0 | O40: 0 | P40: 0 | Q40: 0 | R40: 30617
A41: Cash Flow from Investing | B41: =SUM(B35:B40) -> 1015234 | C41: =SUM(C35:C40) -> 914340 | D41: =SUM(D35:D40) -> 1178 | E41: =SUM(E35:E40) -> 660223 | F41: =SUM(F35:F40) -> -509578 | G41: =SUM(G35:G40) -> -742 | H41: =SUM(H35:H40) -> 136 | I41: =SUM(I35:I40) -> -885 | ... R41: =SUM(R35:R40) -> -1278691
A42: Finance Lease Payments | B42: -222052 | C42: -259231 | D42: -25 | E42: -49592 | F42: -72386 | G42: -20 | H42: -37 | I42: -49 | J42: -11 | K42: -22 | L42: -33 | M42: -15 | N42: -30 | O42: -46 | P42: 0 | Q42: 0 | R42: 0
A43: Proceeds from Issuance of Common Stock | B43: 0 | C43: 21983116 | D43: 0 | E43: 67769386 | F43: 67769386 | G43: 0 | H43: 0 | I43: 0 | J43: 0 | K43: 0 | L43: 0 | M43: 0 | N43: 0 | O43: 0 | P43: 0 | Q43: 0 | R43: 0
A44: Proceeds from Exercise of Stock Options | B44: 704664 | C44: 2296343 | D44: 716 | E44: 2515017 | F44: 3242073 | G44: 810 | H44: 1260 | I44: 3104 | J44: 478 | K44: 707 | L44: 1603 | M44: 967 | N44: 1147 | O44: 3832 | P44: 0 | Q44: 0 | R44: 0
A45: Proceeds from Issuance of Preferred Stock | B45: 0 | C45: 0 | D45: 0 | E45: 0 | F45: 0 | G45: 0 | H45: 0 | I45: 542018 | J45: 0 | K45: 0 | L45: 0 | M45: 0 | N45: 0 | O45: 0 | P45: 0 | Q45: 0 | R45: 0
A46: Preferred Dividends | B46: 0 | C46: 0 | D46: 0 | E46: 0 | F46: 0 | G46: 0 | H46: 0 | I46: -4596 | J46: -6781 | K46: -13637 | L46: -20512 | M46: -6837 | N46: -13675 | O46: -20588 | P46: -6781 | Q46: -13632 | R46: -23301
A47: Share Repurchases | B47: 0 | C47: 0 | D47: 0 | E47: 0 | F47: 0 | G47: 0 | H47: 0 | I47: 0 | J47: 0 | K47: 0 | L47: 0 | M47: 0 | N47: 0 | O47: -1658 | P47: -1932 | Q47: -2811 | R47: -3259
A48: Proceeds from Issuance of Long-Term Debt | B48: 0 | C48: 0 | D48: 0 | E48: 0 | F48: 0 | G48: 0 | H48: 0 | I48: 0 | J48: 0 | K48: 0 | L48: 0 | M48: 0 | N48: 0 | O48: 0 | P48: 0 | Q48: 900000 | R48: 900000
A49: Repayments of Long-Term Debt | B49: 0 | C49: 0 | D49: 0 | E49: 0 | F49: 0 | G49: 0 | H49: 0 | I49: 0 | J49: 0 | K49: 0 | L49: 0 | M49: 0 | N49: 0 | O49: 0 | P49: 0 | Q49: 0 | R49: -2250
A50: Debt Issuance Fees | B50: 0 | C50: 0 | D50: 0 | E50: 0 | F50: 0 | G50: 0 | H50: 0 | I50: 0 | J50: 0 | K50: 0 | L50: 0 | M50: 0 | N50: 0 | O50: 0 | P50: -2195 | Q50: -31581 | R50: -31581
A51: Other Financing Activities | B51: 0 | C51: 0 | D51: 0 | E51: 0 | F51: 0 | G51: 0 | H51: 0 | I51: 0 | J51: 0 | K51: 0 | L51: 0 | M51: 0 | N51: 0 | O51: 0 | P51: 321 | Q51: 319 | R51: 301
A52: Cash Flow from Financing | B52: =SUM(B42:B51) -> 482612 | C52: =SUM(C42:C51) -> 24020228 | D52: =SUM(D42:D51) -> 691 | E52: =SUM(E42:E51) -> 70234811 | F52: =SUM(F42:F51) -> 70939073 | G52: =SUM(G42:G51) -> 790 | H52: =SUM(H42:H51) -> 1223 | I52: =SUM(I42:I51) -> 540477 | ... R52: =SUM(R42:R51) -> 839910
A53: FX Effect on Cash | B53: -231635 | C53: 289338 | D53: -165 | E53: -23610 | F53: -236365 | G53: 104 | H53: 121 | I53: 158 | J53: -181 | K53: -555 | L53: -555 | M53: -722 | N53: -766 | O53: -16 | P53: 1259 | Q53: 2214 | R53: 2174
A54: Net Change in Cash | B54: =B34+B41+B52+B53 -> -2979867 | C54: =C34+C41+C52+C53 -> 29067416 | D54: =D34+D41+D52+D53 -> -11614 | E54: =E34+E41+E52+E53 -> 40541960 | F54: =F34+F41+F52+F53 -> 18129181 | G54: =G34+G41+G52+G53 -> 9277 | H54: =H34+H41+H52+H53 -> 43776 | I54: =I34+I41+I52+I53 -> 710717 | ... R54: =R34+R41+R52+R53 -> 42273

Sheet QTR P&L
B1: Q3 FY2020 | C1: Q1 FY2021 | D1: Q2 FY2021 | E1: Q3 FY2021 | F1: Q4 FY2021 | G1: Q1 FY2022 | H1: Q2 FY2022 | I1: Q3 FY2022 | J1: Q4 FY2022 | K1: Q1 FY2023 | L1: Q2 FY2023 | M1: Q3 FY2023 | N1: Q4 FY2023 | O1: Q1 FY2024 | P1: Q2 FY2024 | Q1: Q3 FY2024 | R1: Q4 FY2024 | S1: Q1 FY2025 | T1: Q2 FY2025 | U1: Q3 FY2025 | V1: Q4 FY2025 | W1: Q1 FY2026E | X1: Q2 FY2026E | Y1: Q3 FY2026E | Z1: Q4 FY2026E | AA1: Q1 FY2027E | AB1: Q2 FY2027E | AC1: Q3 FY2027E | AD1: Q4 FY2027E | AE1: Q1 FY2028E | AF1: Q2 FY2028E | AG1: Q3 FY2028E | AH1: Q4 FY2028E | AI1: Q1 FY2029E | AJ1: Q2 FY2029E | AK1: Q3 FY2029E | AL1: Q4 FY2029E | AM1: Q1 FY2030E | AN1: Q2 FY2030E | AO1: Q3 FY2030E | AP1: Q4 FY2030E
A2: Net Sales / Revenue | B2: ='YTD P&L'!C2-'YTD P&L'!B2 -> 36839149 | C2: ='YTD P&L'!D2 -> 50035 | D2: ='YTD P&L'!E2-'YTD P&L'!D2 -> 115058167 | E2: ='YTD P&L'!F2-'YTD P&L'!E2 -> 94909100 | F2: ='ANNL P&L'!B2-'YTD P&L'!F2 -> -209703030 | G2: ='YTD P&L'!G2 -> 133388 | H2: ='YTD P&L'!H2-'YTD P&L'!G2 -> 154020 | I2: ='YTD P&L'!I2-'YTD P&L'!H2 -> 188232 | J2: ='ANNL P&L'!C2-'YTD P&L'!I2 -> 177964 | K2: ='YTD P&L'!J2 -> 259939 | L2: ='YTD P&L'!K2-'YTD P&L'!J2 -> 325883 | M2: ='YTD P&L'!L2-'YTD P&L'!K2 -> 384757 | N2: ='ANNL P&L'!D2-'YTD P&L'!L2 -> 347435 | O2: ='YTD P&L'!M2 -> 355708 | P2: ='YTD P&L'!N2-'YTD P&L'!M2 -> 401977 | Q2: ='YTD P&L'!O2-'YTD P&L'!N2 -> 265748 | R2: ='ANNL P&L'!E2-'YTD P&L'!O2 -> 332197 | S2: ='YTD P&L'!P2 -> 329276 | T2: ='YTD P&L'!Q2-'YTD P&L'!P2 -> 739259 | U2: ='YTD P&L'!R2-'YTD P&L'!Q2 -> 725106 | V2: ='ANNL P&L'!F2-'YTD P&L'!R2 -> 721628 | W2: =IF('IS DRIVERS'!$B2="QoQ",'QTR P&L'!V2,'QTR P&L'!S2)*(1+'IS DRIVERS'!X2) -> 718166.68 | X2: =IF('IS DRIVERS'!$B2="QoQ",'QTR P&L'!W2,'QTR P&L'!T2)*(1+'IS DRIVERS'!Y2) -> 714721.97 | Y2: =IF('IS DRIVERS'!$B2="QoQ",'QTR P&L'!X2,'QTR P&L'!U2)*(1+'IS DRIVERS'!Z2) -> 711293.77 | Z2: =IF('IS DRIVERS'!$B2="QoQ",'QTR P&L'!Y2,'QTR P&L'!V2)*(1+'IS DRIVERS'!AA2) -> 707882.03 | AA2: =IF('IS DRIVERS'!$B2="QoQ",'QTR P&L'!Z2,'QTR P&L'!W2)*(1+'IS DRIVERS'!AB2) -> 704486.64 | AB2: =IF('IS DRIVERS'!$B2="QoQ",'QTR P&L'!AA2,'QTR P&L'!X2)*(1+'IS DRIVERS'!AC2) -> 701107.54 | AC2: =IF('IS DRIVERS'!$B2="QoQ",'QTR P&L'!AB2,'QTR P&L'!Y2)*(1+'IS DRIVERS'!AD2) -> 697744.65 | AD2: =IF('IS DRIVERS'!$B2="QoQ",'QTR P&L'!AC2,'QTR P&L'!Z2)*(1+'IS DRIVERS'!AE2) -> 694397.89 | ... AP2: =IF('IS DRIVERS'!$B2="QoQ",'QTR P&L'!AO2,'QTR P&L'!AL2)*(1+'IS DRIVERS'!AQ2) -> 655467.13
A3: COGS | B3: ='YTD P&L'!C3-'YTD P&L'!B3 -> -19305416 | C3: ='YTD P&L'!D3 -> -29456 | D3: ='YTD P&L'!E3-'YTD P&L'!D3 -> -66250282 | E3: ='YTD P&L'!F3-'YTD P&L'!E3 -> -57215728 | F3: ='ANNL P&L'!B3-'YTD P&L'!F3 -> 123309363 | G3: ='YTD P&L'!G3 -> -79494 | H3: ='YTD P&L'!H3-'YTD P&L'!G3 -> -94701 | I3: ='YTD P&L'!I3-'YTD P&L'!H3 -> -109583 | J3: ='ANNL P&L'!C3-'YTD P&L'!I3 -> -98957 | K3: ='YTD P&L'!J3 -> -146121 | L3: ='YTD P&L'!K3-'YTD P&L'!J3 -> -166889 | M3: ='YTD P&L'!L3-'YTD P&L'!K3 -> -190675 | N3: ='ANNL P&L'!D3-'YTD P&L'!L3 -> -181190 | O3: ='YTD P&L'!M3 -> -173501 | P3: ='YTD P&L'!N3-'YTD P&L'!M3 -> -192879 | Q3: ='YTD P&L'!O3-'YTD P&L'!N3 -> -143519 | R3: ='ANNL P&L'!E3-'YTD P&L'!O3 -> -165524 | S3: ='YTD P&L'!P3 -> -156903 | T3: ='YTD P&L'!Q3-'YTD P&L'!P3 -> -358408 | U3: ='YTD P&L'!R3-'YTD P&L'!Q3 -> -352827 | V3: ='ANNL P&L'!F3-'YTD P&L'!R3 -> -379798 | W3: ='QTR P&L'!W2*'IS DRIVERS'!X3 -> -377976.28 | X3: ='QTR P&L'!X2*'IS DRIVERS'!Y3 -> -376163.31 | Y3: ='QTR P&L'!Y2*'IS DRIVERS'!Z3 -> -374359.02 | Z3: ='QTR P&L'!Z2*'IS DRIVERS'!AA3 -> -372563.39 | AA3: ='QTR P&L'!AA2*'IS DRIVERS'!AB3 -> -370776.38 | AB3: ='QTR P&L'!AB2*'IS DRIVERS'!AC3 -> -368997.94 | AC3: ='QTR P&L'!AC2*'IS DRIVERS'!AD3 -> -367228.02 | AD3: ='QTR P&L'!AD2*'IS DRIVERS'!AE3 -> -365466.6 | ... AP3: ='QTR P&L'!AP2*'IS DRIVERS'!AQ3 -> -344977.06
A4: Gross Profit (Loss) | B4: ='YTD P&L'!C4-'YTD P&L'!B4 -> 17533733 | C4: ='YTD P&L'!D4 -> 20579 | D4: ='YTD P&L'!E4-'YTD P&L'!D4 -> 48807885 | E4: ='YTD P&L'!F4-'YTD P&L'!E4 -> 37693372 | F4: ='ANNL P&L'!B4-'YTD P&L'!F4 -> -86393667 | G4: ='YTD P&L'!G4 -> 53894 | H4: ='YTD P&L'!H4-'YTD P&L'!G4 -> 59319 | I4: ='YTD P&L'!I4-'YTD P&L'!H4 -> 78649 | J4: ='ANNL P&L'!C4-'YTD P&L'!I4 -> 79007 | K4: ='YTD P&L'!J4 -> 113818 | L4: ='YTD P&L'!K4-'YTD P&L'!J4 -> 158994 | M4: ='YTD P&L'!L4-'YTD P&L'!K4 -> 194082 | N4: ='ANNL P&L'!D4-'YTD P&L'!L4 -> 166245 | O4: ='YTD P&L'!M4 -> 182207 | P4: ='YTD P&L'!N4-'YTD P&L'!M4 -> 209098 | Q4: ='YTD P&L'!O4-'YTD P&L'!N4 -> 122229 | R4: ='ANNL P&L'!E4-'YTD P&L'!O4 -> 166673 | S4: ='YTD P&L'!P4 -> 172373 | T4: ='YTD P&L'!Q4-'YTD P&L'!P4 -> 380851 | U4: ='YTD P&L'!R4-'YTD P&L'!Q4 -> 372279 | V4: ='ANNL P&L'!F4-'YTD P&L'!R4 -> 341830 | W4: =W2+W3 -> 340190.4 | X4: =X2+X3 -> 338558.66 | Y4: =Y2+Y3 -> 336934.75 | Z4: =Z2+Z3 -> 335318.63 | AA4: =AA2+AA3 -> 333710.26 | AB4: =AB2+AB3 -> 332109.61 | AC4: =AC2+AC3 -> 330516.63 | AD4: =AD2+AD3 -> 328931.29 | ... AP4: =AP2+AP3 -> 310490.07
A5: Sales and Marketing | B5: ='YTD P&L'!C5-'YTD P&L'!B5 -> -8267996 | C5: ='YTD P&L'!D5 -> -11959 | D5: ='YTD P&L'!E5-'YTD P&L'!D5 -> -27478082 | E5: ='YTD P&L'!F5-'YTD P&L'!E5 -> -22621062 | G5: ='YTD P&L'!G5 -> -31597 | H5: ='YTD P&L'!H5-'YTD P&L'!G5 -> -32475 | I5: ='YTD P&L'!I5-'YTD P&L'!H5 -> -198710 | K5: ='YTD P&L'!J5 -> 0 | L5: ='YTD P&L'!K5-'YTD P&L'!J5 -> 0 | M5: ='YTD P&L'!L5-'YTD P&L'!K5 -> 0 | O5: ='YTD P&L'!M5 -> 0 | P5: ='YTD P&L'!N5-'YTD P&L'!M5 -> 0 | Q5: ='YTD P&L'!O5-'YTD P&L'!N5 -> 0 | S5: ='YTD P&L'!P5 -> 0 | T5: ='YTD P&L'!Q5-'YTD P&L'!P5 -> 0 | U5: ='YTD P&L'!R5-'YTD P&L'!Q5 -> 0 | W5: ='QTR P&L'!W2*'IS DRIVERS'!X4 -> 0 | X5: ='QTR P&L'!X2*'IS DRIVERS'!Y4 -> 0 | Y5: ='QTR P&L'!Y2*'IS DRIVERS'!Z4 -> 0 | Z5: ='QTR P&L'!Z2*'IS DRIVERS'!AA4 -> 0 | AA5: ='QTR P&L'!AA2*'IS DRIVERS'!AB4 -> 0 | AB5: ='QTR P&L'!AB2*'IS DRIVERS'!AC4 -> 0 | AC5: ='QTR P&L'!AC2*'IS DRIVERS'!AD4 -> 0 | AD5: ='QTR P&L'!AD2*'IS DRIVERS'!AE4 -> 0 | ... AP5: ='QTR P&L'!AP2*'IS DRIVERS'!AQ4 -> 0
A6: General and Administrative | B6: ='YTD P&L'!C6-'YTD P&L'!B6 -> -4752428 | C6: ='YTD P&L'!D6 -> -7807 | D6: ='YTD P&L'!E6-'YTD P&L'!D6 -> -16918391 | E6: ='YTD P&L'!F6-'YTD P&L'!E6 -> -11140030 | G6: ='YTD P&L'!G6 -> -12181 | H6: ='YTD P&L'!H6-'YTD P&L'!G6 -> -14414 | I6: ='YTD P&L'!I6-'YTD P&L'!H6 -> -27540 | K6: ='YTD P&L'!J6 -> 0 | L6: ='YTD P&L'!K6-'YTD P&L'!J6 -> 0 | M6: ='YTD P&L'!L6-'YTD P&L'!K6 -> 0 | O6: ='YTD P&L'!M6 -> 0 | P6: ='YTD P&L'!N6-'YTD P&L'!M6 -> 0 | Q6: ='YTD P&L'!O6-'YTD P&L'!N6 -> 0 | S6: ='YTD P&L'!P6 -> 0 | T6: ='YTD P&L'!Q6-'YTD P&L'!P6 -> 0 | U6: ='YTD P&L'!R6-'YTD P&L'!Q6 -> 0 | W6: ='QTR P&L'!W2*'IS DRIVERS'!X5 -> 0 | X6: ='QTR P&L'!X2*'IS DRIVERS'!Y5 -> 0 | Y6: ='QTR P&L'!Y2*'IS DRIVERS'!Z5 -> 0 | Z6: ='QTR P&L'!Z2*'IS DRIVERS'!AA5 -> 0 | AA6: ='QTR P&L'!AA2*'IS DRIVERS'!AB5 -> 0 | AB6: ='QTR P&L'!AB2*'IS DRIVERS'!AC5 -> 0 | AC6: ='QTR P&L'!AC2*'IS DRIVERS'!AD5 -> 0 | AD6: ='QTR P&L'!AD2*'IS DRIVERS'!AE5 -> 0 | ... AP6: ='QTR P&L'!AP2*'IS DRIVERS'!AQ5 -> 0
A7: Operating Expenses | B7: ='YTD P&L'!C7-'YTD P&L'!B7 -> -13020424 | C7: ='YTD P&L'!D7 -> -19766 | D7: ='YTD P&L'!E7-'YTD P&L'!D7 -> -44396473 | E7: ='YTD P&L'!F7-'YTD P&L'!E7 -> -33761092 | G7: ='YTD P&L'!G7 -> -43778 | H7: ='YTD P&L'!H7-'YTD P&L'!G7 -> -46889 | I7: ='YTD P&L'!I7-'YTD P&L'!H7 -> -226250 | K7: ='YTD P&L'!J7 -> 0 | L7: ='YTD P&L'!K7-'YTD P&L'!J7 -> 0 | M7: ='YTD P&L'!L7-'YTD P&L'!K7 -> 0 | O7: ='YTD P&L'!M7 -> 0 | P7: ='YTD P&L'!N7-'YTD P&L'!M7 -> 0 | Q7: ='YTD P&L'!O7-'YTD P&L'!N7 -> 0 | S7: ='YTD P&L'!P7 -> 0 | T7: ='YTD P&L'!Q7-'YTD P&L'!P7 -> 0 | U7: ='YTD P&L'!R7-'YTD P&L'!Q7 -> 0 | W7: ='QTR P&L'!W2*'IS DRIVERS'!X6 -> 0 | X7: ='QTR P&L'!X2*'IS DRIVERS'!Y6 -> 0 | Y7: ='QTR P&L'!Y2*'IS DRIVERS'!Z6 -> 0 | Z7: ='QTR P&L'!Z2*'IS DRIVERS'!AA6 -> 0 | AA7: ='QTR P&L'!AA2*'IS DRIVERS'!AB6 -> 0 | AB7: ='QTR P&L'!AB2*'IS DRIVERS'!AC6 -> 0 | AC7: ='QTR P&L'!AC2*'IS DRIVERS'!AD6 -> 0 | AD7: ='QTR P&L'!AD2*'IS DRIVERS'!AE6 -> 0 | ... AP7: ='QTR P&L'!AP2*'IS DRIVERS'!AQ6 -> 0
A8: SG&A | B8: ='YTD P&L'!C8-'YTD P&L'!B8 -> 0 | C8: ='YTD P&L'!D8 -> 0 | D8: ='YTD P&L'!E8-'YTD P&L'!D8 -> 0 | E8: ='YTD P&L'!F8-'YTD P&L'!E8 -> 0 | F8: ='ANNL P&L'!B5-'YTD P&L'!F8 -> -132259 | G8: ='YTD P&L'!G8 -> 0 | H8: ='YTD P&L'!H8-'YTD P&L'!G8 -> 0 | I8: ='YTD P&L'!I8-'YTD P&L'!H8 -> 0 | J8: ='ANNL P&L'!C5-'YTD P&L'!I8 -> -428670 | K8: ='YTD P&L'!J8 -> -68905 | L8: ='YTD P&L'!K8-'YTD P&L'!J8 -> -94181 | M8: ='YTD P&L'!L8-'YTD P&L'!K8 -> -96385 | N8: ='ANNL P&L'!D5-'YTD P&L'!L8 -> -107302 | O8: ='YTD P&L'!M8 -> -99017 | P8: ='YTD P&L'!N8-'YTD P&L'!M8 -> -114850 | Q8: ='YTD P&L'!O8-'YTD P&L'!N8 -> -125443 | R8: ='ANNL P&L'!E5-'YTD P&L'!O8 -> -185169 | S8: ='YTD P&L'!P8 -> -120342 | T8: ='YTD P&L'!Q8-'YTD P&L'!P8 -> -237886 | U8: ='YTD P&L'!R8-'YTD P&L'!Q8 -> -205571 | V8: ='ANNL P&L'!F5-'YTD P&L'!R8 -> -235011 | W8: ='QTR P&L'!W2*'IS DRIVERS'!X7 -> -233883.76 | X8: ='QTR P&L'!X2*'IS DRIVERS'!Y7 -> -232761.93 | Y8: ='QTR P&L'!Y2*'IS DRIVERS'!Z7 -> -231645.48 | Z8: ='QTR P&L'!Z2*'IS DRIVERS'!AA7 -> -230534.38 | AA8: ='QTR P&L'!AA2*'IS DRIVERS'!AB7 -> -229428.61 | AB8: ='QTR P&L'!AB2*'IS DRIVERS'!AC7 -> -228328.15 | AC8: ='QTR P&L'!AC2*'IS DRIVERS'!AD7 -> -227232.96 | AD8: ='QTR P&L'!AD2*'IS DRIVERS'!AE7 -> -226143.03 | ... AP8: ='QTR P&L'!AP2*'IS DRIVERS'!AQ7 -> -213464.54
A9: Distributor Termination Fees | B9: ='YTD P&L'!C9-'YTD P&L'!B9 -> 0 | C9: ='YTD P&L'!D9 -> 0 | D9: ='YTD P&L'!E9-'YTD P&L'!D9 -> 0 | E9: ='YTD P&L'!F9-'YTD P&L'!E9 -> 0 | F9: ='ANNL P&L'!B6-'YTD P&L'!F9 -> 0 | G9: ='YTD P&L'!G9 -> 0 | H9: ='YTD P&L'!H9-'YTD P&L'!G9 -> 0 | I9: ='YTD P&L'!I9-'YTD P&L'!H9 -> 0 | J9: ='ANNL P&L'!C6-'YTD P&L'!I9 -> 0 | K9: ='YTD P&L'!J9 -> 0 | L9: ='YTD P&L'!K9-'YTD P&L'!J9 -> 0 | M9: ='YTD P&L'!L9-'YTD P&L'!K9 -> 0 | N9: ='ANNL P&L'!D6-'YTD P&L'!L9 -> 0 | O9: ='YTD P&L'!M9 -> 0 | P9: ='YTD P&L'!N9-'YTD P&L'!M9 -> 0 | Q9: ='YTD P&L'!O9-'YTD P&L'!N9 -> 0 | R9: ='ANNL P&L'!E6-'YTD P&L'!O9 -> 0 | S9: ='YTD P&L'!P9 -> 0 | T9: ='YTD P&L'!Q9-'YTD P&L'!P9 -> 0 | U9: ='YTD P&L'!R9-'YTD P&L'!Q9 -> -246707 | V9: ='ANNL P&L'!F6-'YTD P&L'!R9 -> -80754 | W9: ='IS DRIVERS'!X8 -> 0 | X9: ='IS DRIVERS'!Y8 -> 0 | Y9: ='IS DRIVERS'!Z8 -> 0 | Z9: ='IS DRIVERS'!AA8 -> 0 | AA9: ='IS DRIVERS'!AB8 -> 0 | AB9: ='IS DRIVERS'!AC8 -> 0 | AC9: ='IS DRIVERS'!AD8 -> 0 | AD9: ='IS DRIVERS'!AE8 -> 0 | ... AP9: ='IS DRIVERS'!AQ8 -> 0
A10: Income (Loss) from Operations | B10: ='YTD P&L'!C10-'YTD P&L'!B10 -> -8507115 | C10: ='YTD P&L'!D10 -> -18953 | D10: ='YTD P&L'!E10-'YTD P&L'!D10 -> -39985061 | E10: ='YTD P&L'!F10-'YTD P&L'!E10 -> -29828812 | F10: ='ANNL P&L'!B7-'YTD P&L'!F10 -> 69828736 | G10: ='YTD P&L'!G10 -> -33662 | H10: ='YTD P&L'!H10-'YTD P&L'!G10 -> -34459 | I10: ='YTD P&L'!I10-'YTD P&L'!H10 -> -373851 | J10: ='ANNL P&L'!C7-'YTD P&L'!I10 -> 284171 | K10: ='YTD P&L'!J10 -> 44913 | L10: ='YTD P&L'!K10-'YTD P&L'!J10 -> 64813 | M10: ='YTD P&L'!L10-'YTD P&L'!K10 -> 97697 | N10: ='ANNL P&L'!D7-'YTD P&L'!L10 -> 58943 | O10: ='YTD P&L'!M10 -> 83190 | P10: ='YTD P&L'!N10-'YTD P&L'!M10 -> 94248 | Q10: ='YTD P&L'!O10-'YTD P&L'!N10 -> -3214 | R10: ='ANNL P&L'!E7-'YTD P&L'!O10 -> -18496 | S10: ='YTD P&L'!P10 -> 52031 | T10: ='YTD P&L'!Q10-'YTD P&L'!P10 -> 142965 | U10: ='YTD P&L'!R10-'YTD P&L'!Q10 -> -79999 | V10: ='ANNL P&L'!F7-'YTD P&L'!R10 -> 26065 | W10: =W4+SUM(W5:W9) -> 106306.64 | X10: =X4+SUM(X5:X9) -> 105796.73 | Y10: =Y4+SUM(Y5:Y9) -> 105289.28 | Z10: =Z4+SUM(Z5:Z9) -> 104784.25 | AA10: =AA4+SUM(AA5:AA9) -> 104281.65 | AB10: =AB4+SUM(AB5:AB9) -> 103781.46 | AC10: =AC4+SUM(AC5:AC9) -> 103283.67 | AD10: =AD4+SUM(AD5:AD9) -> 102788.26 | ... AP10: =AP4+SUM(AP5:AP9) -> 97025.536
A11: Interest Income (Expense) | B11: ='YTD P&L'!C11-'YTD P&L'!B11 -> -247399 | C11: ='YTD P&L'!D11 -> 85 | D11: ='YTD P&L'!E11-'YTD P&L'!D11 -> 160056 | E11: ='YTD P&L'!F11-'YTD P&L'!E11 -> 71949 | F11: ='ANNL P&L'!B8-'YTD P&L'!F11 -> -231783 | G11: ='YTD P&L'!G11 -> 76 | H11: ='YTD P&L'!H11-'YTD P&L'!G11 -> 53 | I11: ='YTD P&L'!I11-'YTD P&L'!H11 -> 1450 | J11: ='ANNL P&L'!C8-'YTD P&L'!I11 -> 3950 | K11: ='YTD P&L'!J11 -> 4969 | L11: ='YTD P&L'!K11-'YTD P&L'!J11 -> 5573 | M11: ='YTD P&L'!L11-'YTD P&L'!K11 -> 7225 | N11: ='ANNL P&L'!D8-'YTD P&L'!L11 -> 8862 | O11: ='YTD P&L'!M11 -> 9640 | P11: ='YTD P&L'!N11-'YTD P&L'!M11 -> 10647 | Q11: ='YTD P&L'!O11-'YTD P&L'!N11 -> 11112 | R11: ='ANNL P&L'!E8-'YTD P&L'!O11 -> 7864 | S11: ='YTD P&L'!P11 -> 7846 | T11: ='YTD P&L'!Q11-'YTD P&L'!P11 -> -14042 | U11: ='YTD P&L'!R11-'YTD P&L'!Q11 -> -13396 | V11: ='ANNL P&L'!F8-'YTD P&L'!R11 -> -8300 | W11: ='IS DRIVERS'!X9 -> -8300 | X11: ='IS DRIVERS'!Y9 -> -8300 | Y11: ='IS DRIVERS'!Z9 -> -8300 | Z11: ='IS DRIVERS'!AA9 -> -8300 | AA11: ='IS DRIVERS'!AB9 -> -8300 | AB11: ='IS DRIVERS'!AC9 -> -8300 | AC11: ='IS DRIVERS'!AD9 -> -8300 | AD11: ='IS DRIVERS'!AE9 -> -8300 | ... AP11: ='IS DRIVERS'!AQ9 -> -8300
A12: Foreign Currency Gain (Loss) | B12: ='YTD P&L'!C12-'YTD P&L'!B12 -> 550510 | C12: ='YTD P&L'!D12 -> -301 | D12: ='YTD P&L'!E12-'YTD P&L'!D12 -> -123335 | E12: ='YTD P&L'!F12-'YTD P&L'!E12 -> -327581 | F12: ='ANNL P&L'!B9-'YTD P&L'!F12 -> 450941 | G12: ='YTD P&L'!G12 -> -162 | H12: ='YTD P&L'!H12-'YTD P&L'!G12 -> -514 | I12: ='YTD P&L'!I12-'YTD P&L'!H12 -> -254 | J12: ='ANNL P&L'!C9-'YTD P&L'!I12 -> 538 | K12: ='YTD P&L'!J12 -> -118 | L12: ='YTD P&L'!K12-'YTD P&L'!J12 -> -931 | M12: ='YTD P&L'!L12-'YTD P&L'!K12 -> -177 | N12: ='ANNL P&L'!D9-'YTD P&L'!L12 -> -20 | O12: ='YTD P&L'!M12 -> -369 | P12: ='YTD P&L'!N12-'YTD P&L'!M12 -> -264 | Q12: ='YTD P&L'!O12-'YTD P&L'!N12 -> 277 | R12: ='ANNL P&L'!E9-'YTD P&L'!O12 -> -1378 | S12: ='YTD P&L'!P12 -> 0 | T12: ='YTD P&L'!Q12-'YTD P&L'!P12 -> 0 | U12: ='YTD P&L'!R12-'YTD P&L'!Q12 -> 0 | V12: ='ANNL P&L'!F9-'YTD P&L'!R12 -> 0 | W12: ='IS DRIVERS'!X10 -> 0 | X12: ='IS DRIVERS'!Y10 -> 0 | Y12: ='IS DRIVERS'!Z10 -> 0 | Z12: ='IS DRIVERS'!AA10 -> 0 | AA12: ='IS DRIVERS'!AB10 -> 0 | AB12: ='IS DRIVERS'!AC10 -> 0 | AC12: ='IS DRIVERS'!AD10 -> 0 | AD12: ='IS DRIVERS'!AE10 -> 0 | ... AP12: ='IS DRIVERS'!AQ10 -> 0
A13: Other Income (Expense) | B13: ='YTD P&L'!C13-'YTD P&L'!B13 -> -62817 | C13: ='YTD P&L'!D13 -> -12 | D13: ='YTD P&L'!E13-'YTD P&L'!D13 -> 97050 | E13: ='YTD P&L'!F13-'YTD P&L'!E13 -> -97038 | F13: ='ANNL P&L'!B10-'YTD P&L'!F13 -> 0 | G13: ='YTD P&L'!G13 -> 0 | H13: ='YTD P&L'!H13-'YTD P&L'!G13 -> 0 | I13: ='YTD P&L'!I13-'YTD P&L'!H13 -> 0 | J13: ='ANNL P&L'!C10-'YTD P&L'!I13 -> 0 | K13: ='YTD P&L'!J13 -> 0 | L13: ='YTD P&L'!K13-'YTD P&L'!J13 -> 0 | M13: ='YTD P&L'!L13-'YTD P&L'!K13 -> 0 | N13: ='ANNL P&L'!D10-'YTD P&L'!L13 -> 0 | O13: ='YTD P&L'!M13 -> 0 | P13: ='YTD P&L'!N13-'YTD P&L'!M13 -> 0 | Q13: ='YTD P&L'!O13-'YTD P&L'!N13 -> 0 | R13: ='ANNL P&L'!E10-'YTD P&L'!O13 -> 1793 | S13: ='YTD P&L'!P13 -> 1116 | T13: ='YTD P&L'!Q13-'YTD P&L'!P13 -> 542 | U13: ='YTD P&L'!R13-'YTD P&L'!Q13 -> 5364 | V13: ='ANNL P&L'!F10-'YTD P&L'!R13 -> 4841 | W13: ='IS DRIVERS'!X11 -> 4841 | X13: ='IS DRIVERS'!Y11 -> 4841 | Y13: ='IS DRIVERS'!Z11 -> 4841 | Z13: ='IS DRIVERS'!AA11 -> 4841 | AA13: ='IS DRIVERS'!AB11 -> 4841 | AB13: ='IS DRIVERS'!AC11 -> 4841 | AC13: ='IS DRIVERS'!AD11 -> 4841 | AD13: ='IS DRIVERS'!AE11 -> 4841 | ... AP13: ='IS DRIVERS'!AQ11 -> 4841
A14: Gain (Loss) on Lease Cancellations | B14: ='YTD P&L'!C14-'YTD P&L'!B14 -> 0 | C14: ='YTD P&L'!D14 -> 0 | D14: ='YTD P&L'!E14-'YTD P&L'!D14 -> 0 | E14: ='YTD P&L'!F14-'YTD P&L'!E14 -> 0 | G14: ='YTD P&L'!G14 -> 0 | H14: ='YTD P&L'!H14-'YTD P&L'!G14 -> 0 | I14: ='YTD P&L'!I14-'YTD P&L'!H14 -> 0 | K14: ='YTD P&L'!J14 -> 0 | L14: ='YTD P&L'!K14-'YTD P&L'!J14 -> 0 | M14: ='YTD P&L'!L14-'YTD P&L'!K14 -> 0 | O14: ='YTD P&L'!M14 -> 0 | P14: ='YTD P&L'!N14-'YTD P&L'!M14 -> 0 | Q14: ='YTD P&L'!O14-'YTD P&L'!N14 -> 0 | S14: ='YTD P&L'!P14 -> 0 | T14: ='YTD P&L'!Q14-'YTD P&L'!P14 -> 0 | U14: ='YTD P&L'!R14-'YTD P&L'!Q14 -> 0 | W14: ='IS DRIVERS'!X12 -> 0 | X14: ='IS DRIVERS'!Y12 -> 0 | Y14: ='IS DRIVERS'!Z12 -> 0 | Z14: ='IS DRIVERS'!AA12 -> 0 | AA14: ='IS DRIVERS'!AB12 -> 0 | AB14: ='IS DRIVERS'!AC12 -> 0 | AC14: ='IS DRIVERS'!AD12 -> 0 | AD14: ='IS DRIVERS'!AE12 -> 0 | ... AP14: ='IS DRIVERS'!AQ12 -> 0
A15: Pre-Tax Income (Loss) | B15: ='YTD P&L'!C15-'YTD P&L'!B15 -> -8266821 | C15: ='YTD P&L'!D15 -> -19181 | D15: ='YTD P&L'!E15-'YTD P&L'!D15 -> -39851290 | E15: ='YTD P&L'!F15-'YTD P&L'!E15 -> -30181482 | F15: ='ANNL P&L'!B11-'YTD P&L'!F15 -> 70047894 | G15: ='YTD P&L'!G15 -> -33748 | H15: ='YTD P&L'!H15-'YTD P&L'!G15 -> -34920 | I15: ='YTD P&L'!I15-'YTD P&L'!H15 -> -372655 | J15: ='ANNL P&L'!C11-'YTD P&L'!I15 -> 288659 | K15: ='YTD P&L'!J15 -> 49764 | L15: ='YTD P&L'!K15-'YTD P&L'!J15 -> 69455 | M15: ='YTD P&L'!L15-'YTD P&L'!K15 -> 104745 | N15: ='ANNL P&L'!D11-'YTD P&L'!L15 -> 67785 | O15: ='YTD P&L'!M15 -> 92461 | P15: ='YTD P&L'!N15-'YTD P&L'!M15 -> 104631 | Q15: ='YTD P&L'!O15-'YTD P&L'!N15 -> 8175 | R15: ='ANNL P&L'!E11-'YTD P&L'!O15 -> -10217 | S15: ='YTD P&L'!P15 -> 60993 | T15: ='YTD P&L'!Q15-'YTD P&L'!P15 -> 129465 | U15: ='YTD P&L'!R15-'YTD P&L'!Q15 -> -88031 | V15: ='ANNL P&L'!F11-'YTD P&L'!R15 -> 22606 | W15: =W10+SUM(W11:W14) -> 102847.64 | X15: =X10+SUM(X11:X14) -> 102337.73 | Y15: =Y10+SUM(Y11:Y14) -> 101830.28 | Z15: =Z10+SUM(Z11:Z14) -> 101325.25 | AA15: =AA10+SUM(AA11:AA14) -> 100822.65 | AB15: =AB10+SUM(AB11:AB14) -> 100322.46 | AC15: =AC10+SUM(AC11:AC14) -> 99824.667 | AD15: =AD10+SUM(AD11:AD14) -> 99329.263 | ... AP15: =AP10+SUM(AP11:AP14) -> 93566.536
A16: Income Tax (Expense) Benefit | B16: ='YTD P&L'!C16-'YTD P&L'!B16 -> 0 | C16: ='YTD P&L'!D16 -> 0 | D16: ='YTD P&L'!E16-'YTD P&L'!D16 -> 0 | E16: ='YTD P&L'!F16-'YTD P&L'!E16 -> -833819 | F16: ='ANNL P&L'!B12-'YTD P&L'!F16 -> 841815 | G16: ='YTD P&L'!G16 -> -3351 | H16: ='YTD P&L'!H16-'YTD P&L'!G16 -> -2810 | I16: ='YTD P&L'!I16-'YTD P&L'!H16 -> -35492 | J16: ='ANNL P&L'!C12-'YTD P&L'!I16 -> 7035 | K16: ='YTD P&L'!J16 -> -8537 | L16: ='YTD P&L'!K16-'YTD P&L'!J16 -> -17946 | M16: ='YTD P&L'!L16-'YTD P&L'!K16 -> -20796 | N16: ='ANNL P&L'!D12-'YTD P&L'!L16 -> -17669 | O16: ='YTD P&L'!M16 -> -14650 | P16: ='YTD P&L'!N16-'YTD P&L'!M16 -> -24848 | Q16: ='YTD P&L'!O16-'YTD P&L'!N16 -> -1819 | R16: ='ANNL P&L'!E12-'YTD P&L'!O16 -> -8659 | S16: ='YTD P&L'!P16 -> -16574 | T16: ='YTD P&L'!Q16-'YTD P&L'!P16 -> -29610 | U16: ='YTD P&L'!R16-'YTD P&L'!Q16 -> 27017 | V16: ='ANNL P&L'!F12-'YTD P&L'!R16 -> 2133 | W16: ='QTR P&L'!W15*'IS DRIVERS'!X13 -> 9704.2384 | X16: ='QTR P&L'!X15*'IS DRIVERS'!Y13 -> 9656.1261 | Y16: ='QTR P&L'!Y15*'IS DRIVERS'!Z13 -> 9608.2447 | Z16: ='QTR P&L'!Z15*'IS DRIVERS'!AA13 -> 9560.5929 | AA16: ='QTR P&L'!AA15*'IS DRIVERS'!AB13 -> 9513.1696 | AB16: ='QTR P&L'!AB15*'IS DRIVERS'!AC13 -> 9465.9738 | AC16: ='QTR P&L'!AC15*'IS DRIVERS'!AD13 -> 9419.0044 | AD16: ='QTR P&L'!AD15*'IS DRIVERS'!AE13 -> 9372.2603 | ... AP16: ='QTR P&L'!AP15*'IS DRIVERS'!AQ13 -> 8828.5155
A17: Net Income (Loss) | B17: ='YTD P&L'!C17-'YTD P&L'!B17 -> -8266821 | C17: ='YTD P&L'!D17 -> -19181 | D17: ='YTD P&L'!E17-'YTD P&L'!D17 -> -39851290 | E17: ='YTD P&L'!F17-'YTD P&L'!E17 -> -31015301 | F17: ='ANNL P&L'!B13-'YTD P&L'!F17 -> 70889709 | G17: ='YTD P&L'!G17 -> -37099 | H17: ='YTD P&L'!H17-'YTD P&L'!G17 -> -37730 | I17: ='YTD P&L'!I17-'YTD P&L'!H17 -> -408147 | J17: ='ANNL P&L'!C13-'YTD P&L'!I17 -> 295694 | K17: ='YTD P&L'!J17 -> 41227 | L17: ='YTD P&L'!K17-'YTD P&L'!J17 -> 51509 | M17: ='YTD P&L'!L17-'YTD P&L'!K17 -> 83949 | N17: ='ANNL P&L'!D13-'YTD P&L'!L17 -> 50116 | O17: ='YTD P&L'!M17 -> 77811 | P17: ='YTD P&L'!N17-'YTD P&L'!M17 -> 79783 | Q17: ='YTD P&L'!O17-'YTD P&L'!N17 -> 6356 | R17: ='ANNL P&L'!E13-'YTD P&L'!O17 -> -18876 | S17: ='YTD P&L'!P17 -> 44419 | T17: ='YTD P&L'!Q17-'YTD P&L'!P17 -> 99855 | U17: ='YTD P&L'!R17-'YTD P&L'!Q17 -> -61014 | V17: ='ANNL P&L'!F13-'YTD P&L'!R17 -> 24739 | W17: =W15+W16 -> 112551.88 | X17: =X15+X16 -> 111993.86 | Y17: =Y15+Y16 -> 111438.52 | Z17: =Z15+Z16 -> 110885.84 | AA17: =AA15+AA16 -> 110335.82 | AB17: =AB15+AB16 -> 109788.43 | AC17: =AC15+AC16 -> 109243.67 | AD17: =AD15+AD16 -> 108701.52 | ... AP17: =AP15+AP16 -> 102395.05
A18: Preferred Dividends | B18: ='YTD P&L'!C18-'YTD P&L'!B18 -> 0 | C18: ='YTD P&L'!D18 -> 0 | D18: ='YTD P&L'!E18-'YTD P&L'!D18 -> 0 | E18: ='YTD P&L'!F18-'YTD P&L'!E18 -> 0 | F18: ='ANNL P&L'!B14-'YTD P&L'!F18 -> 0 | G18: ='YTD P&L'!G18 -> 0 | H18: ='YTD P&L'!H18-'YTD P&L'!G18 -> 0 | I18: ='YTD P&L'!I18-'YTD P&L'!H18 -> -4596 | J18: ='ANNL P&L'!C14-'YTD P&L'!I18 -> -6930 | K18: ='YTD P&L'!J18 -> -6781 | L18: ='YTD P&L'!K18-'YTD P&L'!J18 -> -6856 | M18: ='YTD P&L'!L18-'YTD P&L'!K18 -> -6875 | N18: ='ANNL P&L'!D14-'YTD P&L'!L18 -> -6950 | O18: ='YTD P&L'!M18 -> -6837 | P18: ='YTD P&L'!N18-'YTD P&L'!M18 -> -6838 | Q18: ='YTD P&L'!O18-'YTD P&L'!N18 -> -6913 | R18: ='ANNL P&L'!E14-'YTD P&L'!O18 -> -6912 | S18: ='YTD P&L'!P18 -> -6781 | T18: ='YTD P&L'!Q18-'YTD P&L'!P18 -> -6851 | U18: ='YTD P&L'!R18-'YTD P&L'!Q18 -> -9657 | V18: ='ANNL P&L'!F14-'YTD P&L'!R18 -> -14319 | W18: ='IS DRIVERS'!X14 -> -14307 | X18: ='IS DRIVERS'!Y14 -> -14307 | Y18: ='IS DRIVERS'!Z14 -> -14307 | Z18: ='IS DRIVERS'!AA14 -> -14307 | AA18: ='IS DRIVERS'!AB14 -> -14307 | AB18: ='IS DRIVERS'!AC14 -> -14307 | AC18: ='IS DRIVERS'!AD14 -> -14307 | AD18: ='IS DRIVERS'!AE14 -> -14307 | ... AP18: ='IS DRIVERS'!AQ14 -> -14307
A19: Income Allocated to Participating Preferred | B19: ='YTD P&L'!C19-'YTD P&L'!B19 -> 0 | C19: ='YTD P&L'!D19 -> 0 | D19: ='YTD P&L'!E19-'YTD P&L'!D19 -> 0 | E19: ='YTD P&L'!F19-'YTD P&L'!E19 -> 0 | F19: ='ANNL P&L'!B15-'YTD P&L'!F19 -> 0 | G19: ='YTD P&L'!G19 -> 0 | H19: ='YTD P&L'!H19-'YTD P&L'!G19 -> 0 | I19: ='YTD P&L'!I19-'YTD P&L'!H19 -> 0 | J19: ='ANNL P&L'!C15-'YTD P&L'!I19 -> 0 | K19: ='YTD P&L'!J19 -> 0 | L19: ='YTD P&L'!K19-'YTD P&L'!J19 -> -6727 | M19: ='YTD P&L'!L19-'YTD P&L'!K19 -> -6536 | N19: ='ANNL P&L'!D15-'YTD P&L'!L19 -> -4085 | O19: ='YTD P&L'!M19 -> -6128 | P19: ='YTD P&L'!N19-'YTD P&L'!M19 -> -6289 | Q19: ='YTD P&L'!O19-'YTD P&L'!N19 -> 60 | R19: ='ANNL P&L'!E15-'YTD P&L'!O19 -> 2240 | S19: ='YTD P&L'!P19 -> -3219 | T19: ='YTD P&L'!Q19-'YTD P&L'!P19 -> -7484 | U19: ='YTD P&L'!R19-'YTD P&L'!Q19 -> 5431 | V19: ='ANNL P&L'!F15-'YTD P&L'!R19 -> -1282 | W19: ='IS DRIVERS'!X15 -> -1282 | X19: ='IS DRIVERS'!Y15 -> -1282 | Y19: ='IS DRIVERS'!Z15 -> -1282 | Z19: ='IS DRIVERS'!AA15 -> -1282 | AA19: ='IS DRIVERS'!AB15 -> -1282 | AB19: ='IS DRIVERS'!AC15 -> -1282 | AC19: ='IS DRIVERS'!AD15 -> -1282 | AD19: ='IS DRIVERS'!AE15 -> -1282 | ... AP19: ='IS DRIVERS'!AQ15 -> -1282
A20: Net Income (Loss) Attributable to Common Shareholders | B20: ='YTD P&L'!C20-'YTD P&L'!B20 -> -8266821 | C20: ='YTD P&L'!D20 -> -19181 | D20: ='YTD P&L'!E20-'YTD P&L'!D20 -> -39851290 | E20: ='YTD P&L'!F20-'YTD P&L'!E20 -> -31015301 | F20: ='ANNL P&L'!B16-'YTD P&L'!F20 -> 70889709 | G20: ='YTD P&L'!G20 -> -37099 | H20: ='YTD P&L'!H20-'YTD P&L'!G20 -> -37730 | I20: ='YTD P&L'!I20-'YTD P&L'!H20 -> -412743 | J20: ='ANNL P&L'!C16-'YTD P&L'!I20 -> 288764 | K20: ='YTD P&L'!J20 -> 34446 | L20: ='YTD P&L'!K20-'YTD P&L'!J20 -> 37926 | M20: ='YTD P&L'!L20-'YTD P&L'!K20 -> 70538 | N20: ='ANNL P&L'!D16-'YTD P&L'!L20 -> 39081 | O20: ='YTD P&L'!M20 -> 64846 | P20: ='YTD P&L'!N20-'YTD P&L'!M20 -> 66656 | Q20: ='YTD P&L'!O20-'YTD P&L'!N20 -> -497 | R20: ='ANNL P&L'!E16-'YTD P&L'!O20 -> -23548 | S20: ='YTD P&L'!P20 -> 34419 | T20: ='YTD P&L'!Q20-'YTD P&L'!P20 -> 85520 | U20: ='YTD P&L'!R20-'YTD P&L'!Q20 -> -65240 | V20: ='ANNL P&L'!F16-'YTD P&L'!R20 -> 9138 | W20: =W17+W18+W19 -> 96962.877 | X20: =X17+X18+X19 -> 96404.86 | Y20: =Y17+Y18+Y19 -> 95849.521 | Z20: =Z17+Z18+Z19 -> 95296.845 | AA20: =AA17+AA18+AA19 -> 94746.82 | AB20: =AB17+AB18+AB19 -> 94199.433 | AC20: =AC17+AC18+AC19 -> 93654.671 | AD20: =AD17+AD18+AD19 -> 93112.523 | ... AP20: =AP17+AP18+AP19 -> 86806.052

Sheet QTR BS
B1: Q2 FY2021 | C1: Q3 FY2021 | D1: Q1 FY2022 | E1: Q2 FY2022 | F1: Q3 FY2022 | G1: Q4 FY2022 | H1: Q1 FY2023 | I1: Q2 FY2023 | J1: Q3 FY2023 | K1: Q4 FY2023 | L1: Q1 FY2024 | M1: Q2 FY2024 | N1: Q3 FY2024 | O1: Q4 FY2024 | P1: Q1 FY2025 | Q1: Q2 FY2025 | R1: Q3 FY2025 | S1: Q4 FY2025 | T1: Q1 FY2026E | U1: Q2 FY2026E | V1: Q3 FY2026E | W1: Q4 FY2026E | X1: Q1 FY2027E | Y1: Q2 FY2027E | Z1: Q3 FY2027E | AA1: Q4 FY2027E | AB1: Q1 FY2028E | AC1: Q2 FY2028E | AD1: Q3 FY2028E | AE1: Q4 FY2028E | AF1: Q1 FY2029E | AG1: Q2 FY2029E | AH1: Q3 FY2029E | AI1: Q4 FY2029E | AJ1: Q1 FY2030E | AK1: Q2 FY2030E | AL1: Q3 FY2030E | AM1: Q4 FY2030E
A2: Cash, Cash Equivalents & Restricted Cash | B2: ='YTD BS'!C2 -> 83789981 | C2: ='YTD BS'!D2 -> 61377202 | D2: ='YTD BS'!F2 -> 25532 | E2: ='YTD BS'!G2 -> 60031 | F2: ='YTD BS'!H2 -> 726972 | G2: ='BALANCE SHEET'!B2 -> 652927 | H2: ='YTD BS'!J2 -> 633581 | I2: ='YTD BS'!K2 -> 681054 | J2: ='YTD BS'!L2 -> 760022 | K2: ='BALANCE SHEET'!C2 -> 755981 | L2: ='YTD BS'!N2 -> 879498 | M2: ='YTD BS'!O2 -> 903210 | N2: ='YTD BS'!P2 -> 903748 | O2: ='BALANCE SHEET'!D2 -> 890190 | P2: ='YTD BS'!R2 -> 977285 | Q2: ='YTD BS'!S2 -> 615233 | R2: ='YTD BS'!T2 -> 932463 | S2: ='BALANCE SHEET'!E2 -> 539987 | T2: ='BS DRIVERS'!T2 -> 539987 | U2: ='BS DRIVERS'!U2 -> 539987 | V2: ='BS DRIVERS'!V2 -> 539987 | W2: ='BS DRIVERS'!W2 -> 539987 | X2: ='BS DRIVERS'!X2 -> 539987 | Y2: ='BS DRIVERS'!Y2 -> 539987 | Z2: ='BS DRIVERS'!Z2 -> 539987 | AA2: ='BS DRIVERS'!AA2 -> 539987 | ... AM2: ='BS DRIVERS'!AM2 -> 539987
A3: Accounts Receivable | B3: ='YTD BS'!C3 -> 32398823 | C3: ='YTD BS'!D3 -> 43500578 | D3: ='YTD BS'!F3 -> 72707 | E3: ='YTD BS'!G3 -> 66195 | F3: ='YTD BS'!H3 -> 117003 | G3: ='BALANCE SHEET'!B3 -> 63311 | H3: ='YTD BS'!J3 -> 172032 | I3: ='YTD BS'!K3 -> 197811 | J3: ='YTD BS'!L3 -> 215243 | K3: ='BALANCE SHEET'!C3 -> 183703 | L3: ='YTD BS'!N3 -> 200117 | M3: ='YTD BS'!O3 -> 262920 | N3: ='YTD BS'!P3 -> 208774 | O3: ='BALANCE SHEET'!D3 -> 270342 | P3: ='YTD BS'!R3 -> 256424 | Q3: ='YTD BS'!S3 -> 490389 | R3: ='YTD BS'!T3 -> 513682 | S3: ='BALANCE SHEET'!E3 -> 755499 | T3: ='QTR P&L'!W2*'BS DRIVERS'!T3/ASSUMPTIONS!$B$2 -> 751875.22 | U3: ='QTR P&L'!X2*'BS DRIVERS'!U3/ASSUMPTIONS!$B$2 -> 748268.82 | V3: ='QTR P&L'!Y2*'BS DRIVERS'!V3/ASSUMPTIONS!$B$2 -> 744679.72 | W3: ='QTR P&L'!Z2*'BS DRIVERS'!W3/ASSUMPTIONS!$B$2 -> 741107.83 | X3: ='QTR P&L'!AA2*'BS DRIVERS'!X3/ASSUMPTIONS!$B$2 -> 737553.08 | Y3: ='QTR P&L'!AB2*'BS DRIVERS'!Y3/ASSUMPTIONS!$B$2 -> 734015.38 | Z3: ='QTR P&L'!AC2*'BS DRIVERS'!Z3/ASSUMPTIONS!$B$2 -> 730494.64 | AA3: ='QTR P&L'!AD2*'BS DRIVERS'!AA3/ASSUMPTIONS!$B$2 -> 726990.79 | ... AM3: ='QTR P&L'!AP2*'BS DRIVERS'!AM3/ASSUMPTIONS!$B$2 -> 686232.75
A4: Note Receivable - Current | B4: ='YTD BS'!C4 -> 2545745 | C4: ='YTD BS'!D4 -> 2543225 | D4: ='YTD BS'!F4 -> 5833 | E4: ='YTD BS'!G4 -> 3066 | F4: ='YTD BS'!H4 -> 2888 | G4: ='BALANCE SHEET'!B4 -> 2979 | H4: ='YTD BS'!J4 -> 3587 | I4: ='YTD BS'!K4 -> 3323 | J4: ='YTD BS'!L4 -> 3309 | K4: ='BALANCE SHEET'!C4 -> 2318 | L4: ='YTD BS'!N4 -> 2259 | M4: ='YTD BS'!O4 -> 1166 | N4: ='YTD BS'!P4 -> 1025 | O4: ='BALANCE SHEET'!D4 -> 0 | P4: ='YTD BS'!R4 -> 0 | Q4: ='YTD BS'!S4 -> 0 | R4: ='YTD BS'!T4 -> 0 | S4: ='BALANCE SHEET'!E4 -> 0 | T4: ='QTR P&L'!W2*'BS DRIVERS'!T4/ASSUMPTIONS!$B$2 -> 0 | U4: ='QTR P&L'!X2*'BS DRIVERS'!U4/ASSUMPTIONS!$B$2 -> 0 | V4: ='QTR P&L'!Y2*'BS DRIVERS'!V4/ASSUMPTIONS!$B$2 -> 0 | W4: ='QTR P&L'!Z2*'BS DRIVERS'!W4/ASSUMPTIONS!$B$2 -> 0 | X4: ='QTR P&L'!AA2*'BS DRIVERS'!X4/ASSUMPTIONS!$B$2 -> 0 | Y4: ='QTR P&L'!AB2*'BS DRIVERS'!Y4/ASSUMPTIONS!$B$2 -> 0 | Z4: ='QTR P&L'!AC2*'BS DRIVERS'!Z4/ASSUMPTIONS!$B$2 -> 0 | AA4: ='QTR P&L'!AD2*'BS DRIVERS'!AA4/ASSUMPTIONS!$B$2 -> 0 | ... AM4: ='QTR P&L'!AP2*'BS DRIVERS'!AM4/ASSUMPTIONS!$B$2 -> 0
A5: Inventories | B5: ='YTD BS'!C5 -> 63826596 | C5: ='YTD BS'!D5 -> 122311445 | D5: ='YTD BS'!F5 -> 184094 | E5: ='YTD BS'!G5 -> 162138 | F5: ='YTD BS'!H5 -> 153933 | G5: ='BALANCE SHEET'!B5 -> 173289 | H5: ='YTD BS'!J5 -> 154280 | I5: ='YTD BS'!K5 -> 152545 | J5: ='YTD BS'!L5 -> 198704 | K5: ='BALANCE SHEET'!C5 -> 229275 | L5: ='YTD BS'!N5 -> 197504 | M5: ='YTD BS'!O5 -> 180669 | N5: ='YTD BS'!P5 -> 197572 | O5: ='BALANCE SHEET'!D5 -> 131165 | P5: ='YTD BS'!R5 -> 141159 | Q5: ='YTD BS'!S5 -> 230046 | R5: ='YTD BS'!T5 -> 282514 | S5: ='BALANCE SHEET'!E5 -> 337698 | T5: ='QTR P&L'!W3*'BS DRIVERS'!T5/ASSUMPTIONS!$B$2 -> 336078.22 | U5: ='QTR P&L'!X3*'BS DRIVERS'!U5/ASSUMPTIONS!$B$2 -> 334466.21 | V5: ='QTR P&L'!Y3*'BS DRIVERS'!V5/ASSUMPTIONS!$B$2 -> 332861.92 | W5: ='QTR P&L'!Z3*'BS DRIVERS'!W5/ASSUMPTIONS!$B$2 -> 331265.34 | X5: ='QTR P&L'!AA3*'BS DRIVERS'!X5/ASSUMPTIONS!$B$2 -> 329676.41 | Y5: ='QTR P&L'!AB3*'BS DRIVERS'!Y5/ASSUMPTIONS!$B$2 -> 328095.11 | Z5: ='QTR P&L'!AC3*'BS DRIVERS'!Z5/ASSUMPTIONS!$B$2 -> 326521.38 | AA5: ='QTR P&L'!AD3*'BS DRIVERS'!AA5/ASSUMPTIONS!$B$2 -> 324955.21 | ... AM5: ='QTR P&L'!AP3*'BS DRIVERS'!AM5/ASSUMPTIONS!$B$2 -> 306736.91
A6: Prepaid Expenses | B6: ='YTD BS'!C6 -> 22744642 | C6: ='YTD BS'!D6 -> 22829510 | D6: ='YTD BS'!F6 -> 10042 | E6: ='YTD BS'!G6 -> 12298 | F6: ='YTD BS'!H6 -> 12096 | G6: ='BALANCE SHEET'!B6 -> 11341 | H6: ='YTD BS'!J6 -> 15507 | I6: ='YTD BS'!K6 -> 23398 | J6: ='YTD BS'!L6 -> 23747 | K6: ='BALANCE SHEET'!C6 -> 19503 | L6: ='YTD BS'!N6 -> 21523 | M6: ='YTD BS'!O6 -> 22900 | N6: ='YTD BS'!P6 -> 38227 | O6: ='BALANCE SHEET'!D6 -> 18759 | P6: ='YTD BS'!R6 -> 22464 | Q6: ='YTD BS'!S6 -> 41420 | R6: ='YTD BS'!T6 -> 163395 | S6: ='BALANCE SHEET'!E6 -> 128806 | T6: ='QTR P&L'!W2*'BS DRIVERS'!T6 -> 128188.18 | U6: ='QTR P&L'!X2*'BS DRIVERS'!U6 -> 127573.32 | V6: ='QTR P&L'!Y2*'BS DRIVERS'!V6 -> 126961.41 | W6: ='QTR P&L'!Z2*'BS DRIVERS'!W6 -> 126352.43 | X6: ='QTR P&L'!AA2*'BS DRIVERS'!X6 -> 125746.38 | Y6: ='QTR P&L'!AB2*'BS DRIVERS'!Y6 -> 125143.23 | Z6: ='QTR P&L'!AC2*'BS DRIVERS'!Z6 -> 124542.97 | AA6: ='QTR P&L'!AD2*'BS DRIVERS'!AA6 -> 123945.6 | ... AM6: ='QTR P&L'!AP2*'BS DRIVERS'!AM6 -> 116996.71
A7: Deferred Other Costs - Current | B7: ='YTD BS'!C7 -> 0 | C7: ='YTD BS'!D7 -> 0 | D7: ='YTD BS'!F7 -> 0 | E7: ='YTD BS'!G7 -> 0 | F7: ='YTD BS'!H7 -> 14124 | G7: ='BALANCE SHEET'!B7 -> 14124 | H7: ='YTD BS'!J7 -> 14124 | I7: ='YTD BS'!K7 -> 14124 | J7: ='YTD BS'!L7 -> 14124 | K7: ='BALANCE SHEET'!C7 -> 14124 | L7: ='YTD BS'!N7 -> 14124 | M7: ='YTD BS'!O7 -> 14124 | N7: ='YTD BS'!P7 -> 14124 | O7: ='BALANCE SHEET'!D7 -> 14124 | P7: ='YTD BS'!R7 -> 14124 | Q7: ='YTD BS'!S7 -> 14124 | R7: ='YTD BS'!T7 -> 49520 | S7: ='BALANCE SHEET'!E7 -> 49164 | T7: ='QTR P&L'!W2*'BS DRIVERS'!T7 -> 48928.183 | U7: ='QTR P&L'!X2*'BS DRIVERS'!U7 -> 48693.497 | V7: ='QTR P&L'!Y2*'BS DRIVERS'!V7 -> 48459.937 | W7: ='QTR P&L'!Z2*'BS DRIVERS'!W7 -> 48227.497 | X7: ='QTR P&L'!AA2*'BS DRIVERS'!X7 -> 47996.171 | Y7: ='QTR P&L'!AB2*'BS DRIVERS'!Y7 -> 47765.956 | Z7: ='QTR P&L'!AC2*'BS DRIVERS'!Z7 -> 47536.845 | AA7: ='QTR P&L'!AD2*'BS DRIVERS'!AA7 -> 47308.832 | ... AM7: ='QTR P&L'!AP2*'BS DRIVERS'!AM7 -> 44656.507
A8: Total Current Assets | B8: ='YTD BS'!C8 -> 205305787 | C8: ='YTD BS'!D8 -> 252561960 | D8: ='YTD BS'!F8 -> 298208 | E8: ='YTD BS'!G8 -> 303728 | F8: ='YTD BS'!H8 -> 1027016 | G8: ='BALANCE SHEET'!B8 -> 917971 | H8: ='YTD BS'!J8 -> 993111 | I8: ='YTD BS'!K8 -> 1072255 | J8: ='YTD BS'!L8 -> 1215149 | K8: ='BALANCE SHEET'!C8 -> 1204904 | L8: ='YTD BS'!N8 -> 1315025 | M8: ='YTD BS'!O8 -> 1384989 | N8: ='YTD BS'!P8 -> 1363470 | O8: ='BALANCE SHEET'!D8 -> 1324580 | P8: ='YTD BS'!R8 -> 1411456 | Q8: ='YTD BS'!S8 -> 1391212 | R8: ='YTD BS'!T8 -> 1941574 | S8: ='BALANCE SHEET'!E8 -> 1811154 | T8: =SUM(T2:T7) -> 1805056.8 | U8: =SUM(U2:U7) -> 1798988.8 | V8: =SUM(V2:V7) -> 1792950 | W8: =SUM(W2:W7) -> 1786940.1 | X8: =SUM(X2:X7) -> 1780959 | Y8: =SUM(Y2:Y7) -> 1775006.7 | Z8: =SUM(Z2:Z7) -> 1769082.8 | AA8: =SUM(AA2:AA7) -> 1763187.4 | ... AM8: =SUM(AM2:AM7) -> 1694609.9
A9: Note Receivable - Non-Current | B9: ='YTD BS'!C9 -> 7000800 | C9: ='YTD BS'!D9 -> 6993869 | D9: ='YTD BS'!F9 -> 3888 | E9: ='YTD BS'!G9 -> 3679 | F9: ='YTD BS'!H9 -> 3465 | G9: ='BALANCE SHEET'!B9 -> 3574 | H9: ='YTD BS'!J9 -> 0 | I9: ='YTD BS'!K9 -> 0 | J9: ='YTD BS'!L9 -> 0 | K9: ='BALANCE SHEET'!C9 -> 0 | L9: ='YTD BS'!N9 -> 0 | M9: ='YTD BS'!O9 -> 0 | N9: ='YTD BS'!P9 -> 0 | O9: ='BALANCE SHEET'!D9 -> 0 | P9: ='YTD BS'!R9 -> 0 | Q9: ='YTD BS'!S9 -> 0 | R9: ='YTD BS'!T9 -> 0 | S9: ='BALANCE SHEET'!E9 -> 0 | T9: ='QTR P&L'!W2*'BS DRIVERS'!T8 -> 0 | U9: ='QTR P&L'!X2*'BS DRIVERS'!U8 -> 0 | V9: ='QTR P&L'!Y2*'BS DRIVERS'!V8 -> 0 | W9: ='QTR P&L'!Z2*'BS DRIVERS'!W8 -> 0 | X9: ='QTR P&L'!AA2*'BS DRIVERS'!X8 -> 0 | Y9: ='QTR P&L'!AB2*'BS DRIVERS'!Y8 -> 0 | Z9: ='QTR P&L'!AC2*'BS DRIVERS'!Z8 -> 0 | AA9: ='QTR P&L'!AD2*'BS DRIVERS'!AA8 -> 0 | ... AM9: ='QTR P&L'!AP2*'BS DRIVERS'!AM8 -> 0
A10: Net PP&E | B10: ='YTD BS'!C10 -> 1617002 | C10: ='YTD BS'!D10 -> 2454914 | D10: ='YTD BS'!F10 -> 3702 | E10: ='YTD BS'!G10 -> 5135 | F10: ='YTD BS'!H10 -> 5782 | G10: ='BALANCE SHEET'!B10 -> 10185 | H10: ='YTD BS'!J10 -> 12054 | I10: ='YTD BS'!K10 -> 15892 | J10: ='YTD BS'!L10 -> 21061 | K10: ='BALANCE SHEET'!C10 -> 24868 | L10: ='YTD BS'!N10 -> 28350 | M10: ='YTD BS'!O10 -> 36282 | N10: ='YTD BS'!P10 -> 38370 | O10: ='BALANCE SHEET'!D10 -> 55602 | P10: ='YTD BS'!R10 -> 58698 | Q10: ='YTD BS'!S10 -> 72516 | R10: ='YTD BS'!T10 -> 80925 | S10: ='BALANCE SHEET'!E10 -> 87910 | T10: ='BS DRIVERS'!T9 -> 89495.359 | U10: ='BS DRIVERS'!U9 -> 91073.114 | V10: ='BS DRIVERS'!V9 -> 92643.301 | W10: ='BS DRIVERS'!W9 -> 94205.957 | X10: ='BS DRIVERS'!X9 -> 95761.117 | Y10: ='BS DRIVERS'!Y9 -> 97308.818 | Z10: ='BS DRIVERS'!Z9 -> 98849.095 | AA10: ='BS DRIVERS'!AA9 -> 100381.98 | ... AM10: ='BS DRIVERS'!AM9 -> 118213.12
A11: ROU Assets - Operating - Non-Current | B11: ='YTD BS'!C11 -> 704857 | C11: ='YTD BS'!D11 -> 888911 | D11: ='YTD BS'!F11 -> 1141 | E11: ='YTD BS'!G11 -> 954 | F11: ='YTD BS'!H11 -> 1105 | G11: ='BALANCE SHEET'!B11 -> 972 | H11: ='YTD BS'!J11 -> 931 | I11: ='YTD BS'!K11 -> 756 | J11: ='YTD BS'!L11 -> 1152 | K11: ='BALANCE SHEET'!C11 -> 1957 | L11: ='YTD BS'!N11 -> 1688 | M11: ='YTD BS'!O11 -> 1507 | N11: ='YTD BS'!P11 -> 5506 | O11: ='BALANCE SHEET'!D11 -> 21606 | P11: ='YTD BS'!R11 -> 20866 | Q11: ='YTD BS'!S11 -> 0 | R11: ='YTD BS'!T11 -> 0 | S11: ='BALANCE SHEET'!E11 -> 0 | T11: ='QTR P&L'!W2*'BS DRIVERS'!T10 -> 0 | U11: ='QTR P&L'!X2*'BS DRIVERS'!U10 -> 0 | V11: ='QTR P&L'!Y2*'BS DRIVERS'!V10 -> 0 | W11: ='QTR P&L'!Z2*'BS DRIVERS'!W10 -> 0 | X11: ='QTR P&L'!AA2*'BS DRIVERS'!X10 -> 0 | Y11: ='QTR P&L'!AB2*'BS DRIVERS'!Y10 -> 0 | Z11: ='QTR P&L'!AC2*'BS DRIVERS'!Z10 -> 0 | AA11: ='QTR P&L'!AD2*'BS DRIVERS'!AA10 -> 0 | ... AM11: ='QTR P&L'!AP2*'BS DRIVERS'!AM10 -> 0
A12: Intangible Assets | B12: ='YTD BS'!C12 -> 16287537 | C12: ='YTD BS'!D12 -> 16811762 | D12: ='YTD BS'!F12 -> 15838 | E12: ='YTD BS'!G12 -> 14689 | F12: ='YTD BS'!H12 -> 11322 | G12: ='BALANCE SHEET'!B13 -> 12254 | H12: ='YTD BS'!J12 -> 12359 | I12: ='YTD BS'!K12 -> 12211 | J12: ='YTD BS'!L12 -> 11772 | K12: ='BALANCE SHEET'!C13 -> 12139 | L12: ='YTD BS'!N12 -> 11741 | M12: ='YTD BS'!O12 -> 11491 | N12: ='YTD BS'!P12 -> 11877 | O12: ='BALANCE SHEET'!D13 -> 12213 | P12: ='YTD BS'!R12 -> 12444 | Q12: ='YTD BS'!S12 -> 1222115 | R12: ='YTD BS'!T12 -> 1397819 | S12: ='BALANCE SHEET'!E13 -> 1391915 | T12: ='BS DRIVERS'!T11 -> 1391915 | U12: ='BS DRIVERS'!U11 -> 1391915 | V12: ='BS DRIVERS'!V11 -> 1391915 | W12: ='BS DRIVERS'!W11 -> 1391915 | X12: ='BS DRIVERS'!X11 -> 1391915 | Y12: ='BS DRIVERS'!Y11 -> 1391915 | Z12: ='BS DRIVERS'!Z11 -> 1391915 | AA12: ='BS DRIVERS'!AA11 -> 1391915 | ... AM12: ='BS DRIVERS'!AM11 -> 1391915
A13: Goodwill | B13: ='YTD BS'!C13 -> 10419321 | C13: ='YTD BS'!D13 -> 14851635 | D13: ='YTD BS'!F13 -> 14238 | E13: ='YTD BS'!G13 -> 13323 | F13: ='YTD BS'!H13 -> 12502 | G13: ='BALANCE SHEET'!B14 -> 13679 | H13: ='YTD BS'!J13 -> 13949 | I13: ='YTD BS'!K13 -> 13937 | J13: ='YTD BS'!L13 -> 13588 | K13: ='BALANCE SHEET'!C14 -> 14173 | L13: ='YTD BS'!N13 -> 13866 | M13: ='YTD BS'!O13 -> 13730 | N13: ='YTD BS'!P13 -> 14360 | O13: ='BALANCE SHEET'!D14 -> 71582 | P13: ='YTD BS'!R13 -> 72128 | Q13: ='YTD BS'!S13 -> 802234 | R13: ='YTD BS'!T13 -> 914957 | S13: ='BALANCE SHEET'!E14 -> 917560 | T13: ='BS DRIVERS'!T12 -> 917560 | U13: ='BS DRIVERS'!U12 -> 917560 | V13: ='BS DRIVERS'!V12 -> 917560 | W13: ='BS DRIVERS'!W12 -> 917560 | X13: ='BS DRIVERS'!X12 -> 917560 | Y13: ='BS DRIVERS'!Y12 -> 917560 | Z13: ='BS DRIVERS'!Z12 -> 917560 | AA13: ='BS DRIVERS'!AA12 -> 917560 | ... AM13: ='BS DRIVERS'!AM12 -> 917560
A14: Deferred Other Costs - Non-Current | B14: ='YTD BS'!C14 -> 0 | C14: ='YTD BS'!D14 -> 0 | D14: ='YTD BS'!F14 -> 0 | E14: ='YTD BS'!G14 -> 0 | F14: ='YTD BS'!H14 -> 265993 | G14: ='BALANCE SHEET'!B15 -> 262462 | H14: ='YTD BS'!J14 -> 258931 | I14: ='YTD BS'!K14 -> 255400 | J14: ='YTD BS'!L14 -> 251869 | K14: ='BALANCE SHEET'!C15 -> 248338 | L14: ='YTD BS'!N14 -> 244807 | M14: ='YTD BS'!O14 -> 241276 | N14: ='YTD BS'!P14 -> 237746 | O14: ='BALANCE SHEET'!D15 -> 234215 | P14: ='YTD BS'!R14 -> 230684 | Q14: ='YTD BS'!S14 -> 227153 | R14: ='YTD BS'!T14 -> 784214 | S14: ='BALANCE SHEET'!E15 -> 771635 | T14: ='QTR P&L'!W2*'BS DRIVERS'!T13 -> 767933.82 | U14: ='QTR P&L'!X2*'BS DRIVERS'!U13 -> 764250.4 | V14: ='QTR P&L'!Y2*'BS DRIVERS'!V13 -> 760584.64 | W14: ='QTR P&L'!Z2*'BS DRIVERS'!W13 -> 756936.46 | X14: ='QTR P&L'!AA2*'BS DRIVERS'!X13 -> 753305.79 | Y14: ='QTR P&L'!AB2*'BS DRIVERS'!Y13 -> 749692.53 | Z14: ='QTR P&L'!AC2*'BS DRIVERS'!Z13 -> 746096.6 | AA14: ='QTR P&L'!AD2*'BS DRIVERS'!AA13 -> 742517.91 | ... AM14: ='QTR P&L'!AP2*'BS DRIVERS'!AM13 -> 700889.35
A15: Deferred Tax Assets | B15: ='YTD BS'!C15 -> 0 | C15: ='YTD BS'!D15 -> 0 | D15: ='YTD BS'!F15 -> 6396 | E15: ='YTD BS'!G15 -> 7686 | F15: ='YTD BS'!H15 -> 0 | G15: ='BALANCE SHEET'!B16 -> 501 | H15: ='YTD BS'!J15 -> 482 | I15: ='YTD BS'!K15 -> 28373 | J15: ='YTD BS'!L15 -> 30614 | K15: ='BALANCE SHEET'!C16 -> 29518 | L15: ='YTD BS'!N15 -> 22437 | M15: ='YTD BS'!O15 -> 22727 | N15: ='YTD BS'!P15 -> 24186 | O15: ='BALANCE SHEET'!D16 -> 38699 | P15: ='YTD BS'!R15 -> 38525 | Q15: ='YTD BS'!S15 -> 43158 | R15: ='YTD BS'!T15 -> 110410 | S15: ='BALANCE SHEET'!E16 -> 96013 | T15: ='BS DRIVERS'!T14 -> 81941 | U15: ='BS DRIVERS'!U14 -> 67869 | V15: ='BS DRIVERS'!V14 -> 53797 | W15: ='BS DRIVERS'!W14 -> 39725 | X15: ='BS DRIVERS'!X14 -> 25653 | Y15: ='BS DRIVERS'!Y14 -> 11581 | Z15: ='BS DRIVERS'!Z14 -> -2491 | AA15: ='BS DRIVERS'!AA14 -> -16563 | ... AM15: ='BS DRIVERS'!AM14 -> -185427
A16: ROU Assets - Finance - Non-Current | B16: ='YTD BS'!C16 -> 100365 | C16: ='YTD BS'!D16 -> 106675 | D16: ='YTD BS'!F16 -> 220 | E16: ='YTD BS'!G16 -> 180 | F16: ='YTD BS'!H16 -> 222 | G16: ='BALANCE SHEET'!B12 -> 208 | H16: ='YTD BS'!J16 -> 191 | I16: ='YTD BS'!K16 -> 171 | J16: ='YTD BS'!L16 -> 148 | K16: ='BALANCE SHEET'!C12 -> 208 | L16: ='YTD BS'!N16 -> 263 | M16: ='YTD BS'!O16 -> 233 | N16: ='YTD BS'!P16 -> 214 | O16: ='BALANCE SHEET'!D12 -> 230 | P16: ='YTD BS'!R16 -> 0 | Q16: ='YTD BS'!S16 -> 0 | R16: ='YTD BS'!T16 -> 0 | S16: ='BALANCE SHEET'!E12 -> 0 | T16: ='QTR P&L'!W2*'BS DRIVERS'!T15 -> 0 | U16: ='QTR P&L'!X2*'BS DRIVERS'!U15 -> 0 | V16: ='QTR P&L'!Y2*'BS DRIVERS'!V15 -> 0 | W16: ='QTR P&L'!Z2*'BS DRIVERS'!W15 -> 0 | X16: ='QTR P&L'!AA2*'BS DRIVERS'!X15 -> 0 | Y16: ='QTR P&L'!AB2*'BS DRIVERS'!Y15 -> 0 | Z16: ='QTR P&L'!AC2*'BS DRIVERS'!Z15 -> 0 | AA16: ='QTR P&L'!AD2*'BS DRIVERS'!AA15 -> 0 | ... AM16: ='QTR P&L'!AP2*'BS DRIVERS'!AM15 -> 0
A17: Other Non-Current Assets | B17: ='YTD BS'!C17 -> 112456 | C17: ='YTD BS'!D17 -> 308449 | D17: ='YTD BS'!F17 -> 293 | E17: ='YTD BS'!G17 -> 264 | F17: ='YTD BS'!H17 -> 242 | G17: ='BALANCE SHEET'!B17 -> 263 | H17: ='YTD BS'!J17 -> 263 | I17: ='YTD BS'!K17 -> 254 | J17: ='YTD BS'!L17 -> 265 | K17: ='BALANCE SHEET'!C17 -> 291 | L17: ='YTD BS'!N17 -> 7963 | M17: ='YTD BS'!O17 -> 6653 | N17: ='YTD BS'!P17 -> 8594 | O17: ='BALANCE SHEET'!D17 -> 8154 | P17: ='YTD BS'!R17 -> 14717 | Q17: ='YTD BS'!S17 -> 36755 | R17: ='YTD BS'!T17 -> 35809 | S17: ='BALANCE SHEET'!E17 -> 43434 | T17: ='QTR P&L'!W2*'BS DRIVERS'!T16 -> 43225.667 | U17: ='QTR P&L'!X2*'BS DRIVERS'!U16 -> 43018.333 | V17: ='QTR P&L'!Y2*'BS DRIVERS'!V16 -> 42811.994 | W17: ='QTR P&L'!Z2*'BS DRIVERS'!W16 -> 42606.645 | X17: ='QTR P&L'!AA2*'BS DRIVERS'!X16 -> 42402.28 | Y17: ='QTR P&L'!AB2*'BS DRIVERS'!Y16 -> 42198.896 | Z17: ='QTR P&L'!AC2*'BS DRIVERS'!Z16 -> 41996.487 | AA17: ='QTR P&L'!AD2*'BS DRIVERS'!AA16 -> 41795.05 | ... AM17: ='QTR P&L'!AP2*'BS DRIVERS'!AM16 -> 39451.85
A18: Total Assets | B18: ='YTD BS'!C18 -> 241548125 | C18: ='YTD BS'!D18 -> 294978175 | D18: ='YTD BS'!F18 -> 343924 | E18: ='YTD BS'!G18 -> 349638 | F18: ='YTD BS'!H18 -> 1327649 | G18: ='BALANCE SHEET'!B18 -> 1222069 | H18: ='YTD BS'!J18 -> 1292271 | I18: ='YTD BS'!K18 -> 1399249 | J18: ='YTD BS'!L18 -> 1545618 | K18: ='BALANCE SHEET'!C18 -> 1536396 | L18: ='YTD BS'!N18 -> 1646140 | M18: ='YTD BS'!O18 -> 1718888 | N18: ='YTD BS'!P18 -> 1704323 | O18: ='BALANCE SHEET'!D18 -> 1766881 | P18: ='YTD BS'!R18 -> 1859518 | Q18: ='YTD BS'!S18 -> 3795143 | R18: ='YTD BS'!T18 -> 5265708 | S18: ='BALANCE SHEET'!E18 -> 5119621 | T18: =T8+SUM(T9:T17) -> 5097127.6 | U18: =U8+SUM(U9:U17) -> 5074674.7 | V18: =V8+SUM(V9:V17) -> 5052261.9 | W18: =W8+SUM(W9:W17) -> 5029889.2 | X18: =X8+SUM(X9:X17) -> 5007556.2 | Y18: =Y8+SUM(Y9:Y17) -> 4985262.9 | Z18: =Z8+SUM(Z9:Z17) -> 4963009 | AA18: =AA8+SUM(AA9:AA17) -> 4940794.4 | ... AM18: =AM8+SUM(AM9:AM17) -> 4677212.2
A19: Accounts Payable | B19: ='YTD BS'!C19 -> 52992075 | C19: ='YTD BS'!D19 -> 91931593 | D19: ='YTD BS'!F19 -> 109307 | E19: ='YTD BS'!G19 -> 102416 | F19: ='YTD BS'!H19 -> 143947 | G19: ='BALANCE SHEET'!B19 -> 36248 | H19: ='YTD BS'!J19 -> 107112 | I19: ='YTD BS'!K19 -> 94313 | J19: ='YTD BS'!L19 -> 121088 | K19: ='BALANCE SHEET'!C19 -> 42840 | L19: ='YTD BS'!N19 -> 40196 | M19: ='YTD BS'!O19 -> 47423 | N19: ='YTD BS'!P19 -> 30938 | O19: ='BALANCE SHEET'!D19 -> 41287 | P19: ='YTD BS'!R19 -> 61052 | Q19: ='YTD BS'!S19 -> 120962 | R19: ='YTD BS'!T19 -> 97794 | S19: ='BALANCE SHEET'!E19 -> 137930 | T19: ='QTR P&L'!W3*'BS DRIVERS'!T17/ASSUMPTIONS!$B$2 -> 137268.41 | U19: ='QTR P&L'!X3*'BS DRIVERS'!U17/ASSUMPTIONS!$B$2 -> 136610 | V19: ='QTR P&L'!Y3*'BS DRIVERS'!V17/ASSUMPTIONS!$B$2 -> 135954.74 | W19: ='QTR P&L'!Z3*'BS DRIVERS'!W17/ASSUMPTIONS!$B$2 -> 135302.63 | X19: ='QTR P&L'!AA3*'BS DRIVERS'!X17/ASSUMPTIONS!$B$2 -> 134653.65 | Y19: ='QTR P&L'!AB3*'BS DRIVERS'!Y17/ASSUMPTIONS!$B$2 -> 134007.78 | Z19: ='QTR P&L'!AC3*'BS DRIVERS'!Z17/ASSUMPTIONS!$B$2 -> 133365 | AA19: ='QTR P&L'!AD3*'BS DRIVERS'!AA17/ASSUMPTIONS!$B$2 -> 132725.31 | ... AM19: ='QTR P&L'!AP3*'BS DRIVERS'!AM17/ASSUMPTIONS!$B$2 -> 125284.19
A20: Accrued Expenses | B20: ='YTD BS'!C20 -> 0 | C20: ='YTD BS'!D20 -> 0 | D20: ='YTD BS'!F20 -> 0 | E20: ='YTD BS'!G20 -> 0 | F20: ='YTD BS'!H20 -> 0 | G20: ='BALANCE SHEET'!B20 -> 69899 | H20: ='YTD BS'!J20 -> 0 | I20: ='YTD BS'!K20 -> 0 | J20: ='YTD BS'!L20 -> 0 | K20: ='BALANCE SHEET'!C20 -> 62120 | L20: ='YTD BS'!N20 -> 63871 | M20: ='YTD BS'!O20 -> 79633 | N20: ='YTD BS'!P20 -> 73024 | O20: ='BALANCE SHEET'!D20 -> 148780 | P20: ='YTD BS'!R20 -> 152046 | Q20: ='YTD BS'!S20 -> 225859 | R20: ='YTD BS'!T20 -> 311768 | S20: ='BALANCE SHEET'!E20 -> 230721 | T20: ='QTR P&L'!W2*'BS DRIVERS'!T18 -> 229614.34 | U20: ='QTR P&L'!X2*'BS DRIVERS'!U18 -> 228512.98 | V20: ='QTR P&L'!Y2*'BS DRIVERS'!V18 -> 227416.91 | W20: ='QTR P&L'!Z2*'BS DRIVERS'!W18 -> 226326.1 | X20: ='QTR P&L'!AA2*'BS DRIVERS'!X18 -> 225240.51 | Y20: ='QTR P&L'!AB2*'BS DRIVERS'!Y18 -> 224160.14 | Z20: ='QTR P&L'!AC2*'BS DRIVERS'!Z18 -> 223084.95 | AA20: ='QTR P&L'!AD2*'BS DRIVERS'!AA18 -> 222014.91 | ... AM20: ='QTR P&L'!AP2*'BS DRIVERS'!AM18 -> 209567.86
A21: Income Taxes Payable | B21: ='YTD BS'!C21 -> 0 | C21: ='YTD BS'!D21 -> 0 | D21: ='YTD BS'!F21 -> 0 | E21: ='YTD BS'!G21 -> 0 | F21: ='YTD BS'!H21 -> 0 | G21: ='BALANCE SHEET'!B21 -> 1193 | H21: ='YTD BS'!J21 -> 0 | I21: ='YTD BS'!K21 -> 58798 | J21: ='YTD BS'!L21 -> 58855 | K21: ='BALANCE SHEET'!C21 -> 50424 | L21: ='YTD BS'!N21 -> 58619 | M21: ='YTD BS'!O21 -> 5374 | N21: ='YTD BS'!P21 -> 739 | O21: ='BALANCE SHEET'!D21 -> 10834 | P21: ='YTD BS'!R21 -> 26206 | Q21: ='YTD BS'!S21 -> 21765 | R21: ='YTD BS'!T21 -> 49590 | S21: ='BALANCE SHEET'!E21 -> 49612 | T21: ='QTR P&L'!W2*'BS DRIVERS'!T19 -> 49374.034 | U21: ='QTR P&L'!X2*'BS DRIVERS'!U19 -> 49137.21 | V21: ='QTR P&L'!Y2*'BS DRIVERS'!V19 -> 48901.521 | W21: ='QTR P&L'!Z2*'BS DRIVERS'!W19 -> 48666.963 | X21: ='QTR P&L'!AA2*'BS DRIVERS'!X19 -> 48433.53 | Y21: ='QTR P&L'!AB2*'BS DRIVERS'!Y19 -> 48201.216 | Z21: ='QTR P&L'!AC2*'BS DRIVERS'!Z19 -> 47970.017 | AA21: ='QTR P&L'!AD2*'BS DRIVERS'!AA19 -> 47739.927 | ... AM21: ='QTR P&L'!AP2*'BS DRIVERS'!AM19 -> 45063.434
A22: Accrued Distributor Termination Fees | B22: ='YTD BS'!C22 -> 0 | C22: ='YTD BS'!D22 -> 0 | D22: ='YTD BS'!F22 -> 0 | E22: ='YTD BS'!G22 -> 0 | F22: ='YTD BS'!H22 -> 115551 | G22: ='BALANCE SHEET'!B22 -> 3986 | H22: ='YTD BS'!J22 -> 1063 | I22: ='YTD BS'!K22 -> 0 | J22: ='YTD BS'!L22 -> 0 | K22: ='BALANCE SHEET'!C22 -> 0 | L22: ='YTD BS'!N22 -> 0 | M22: ='YTD BS'!O22 -> 0 | N22: ='YTD BS'!P22 -> 0 | O22: ='BALANCE SHEET'!D22 -> 0 | P22: ='YTD BS'!R22 -> 0 | Q22: ='YTD BS'!S22 -> 0 | R22: ='YTD BS'!T22 -> 252953 | S22: ='BALANCE SHEET'!E22 -> 264088 | T22: ='BS DRIVERS'!T20 -> 0 | U22: ='BS DRIVERS'!U20 -> 0 | V22: ='BS DRIVERS'!V20 -> 0 | W22: ='BS DRIVERS'!W20 -> 0 | X22: ='BS DRIVERS'!X20 -> 0 | Y22: ='BS DRIVERS'!Y20 -> 0 | Z22: ='BS DRIVERS'!Z20 -> 0 | AA22: ='BS DRIVERS'!AA20 -> 0 | ... AM22: ='BS DRIVERS'!AM20 -> 0
A23: Accrued Promotional Allowance | B23: ='YTD BS'!C23 -> 0 | C23: ='YTD BS'!D23 -> 0 | D23: ='YTD BS'!F23 -> 0 | E23: ='YTD BS'!G23 -> 0 | F23: ='YTD BS'!H23 -> 0 | G23: ='BALANCE SHEET'!B23 -> 35977 | H23: ='YTD BS'!J23 -> 68225 | I23: ='YTD BS'!K23 -> 98933 | J23: ='YTD BS'!L23 -> 136557 | K23: ='BALANCE SHEET'!C23 -> 99787 | L23: ='YTD BS'!N23 -> 129201 | M23: ='YTD BS'!O23 -> 156479 | N23: ='YTD BS'!P23 -> 158810 | O23: ='BALANCE SHEET'!D23 -> 135948 | P23: ='YTD BS'!R23 -> 151327 | Q23: ='YTD BS'!S23 -> 200169 | R23: ='YTD BS'!T23 -> 234068 | S23: ='BALANCE SHEET'!E23 -> 307922 | T23: ='QTR P&L'!W2*'BS DRIVERS'!T21 -> 306445.04 | U23: ='QTR P&L'!X2*'BS DRIVERS'!U21 -> 304975.16 | V23: ='QTR P&L'!Y2*'BS DRIVERS'!V21 -> 303512.34 | W23: ='QTR P&L'!Z2*'BS DRIVERS'!W21 -> 302056.53 | X23: ='QTR P&L'!AA2*'BS DRIVERS'!X21 -> 300607.7 | Y23: ='QTR P&L'!AB2*'BS DRIVERS'!Y21 -> 299165.83 | Z23: ='QTR P&L'!AC2*'BS DRIVERS'!Z21 -> 297730.87 | AA23: ='QTR P&L'!AD2*'BS DRIVERS'!AA21 -> 296302.79 | ... AM23: ='QTR P&L'!AP2*'BS DRIVERS'!AM21 -> 279690.85
A24: Lease Liability - Operating - Current | B24: ='YTD BS'!C24 -> 318142 | C24: ='YTD BS'!D24 -> 376602 | D24: ='YTD BS'!F24 -> 569 | E24: ='YTD BS'!G24 -> 556 | F24: ='YTD BS'!H24 -> 663 | G24: ='BALANCE SHEET'!B24 -> 661 | H24: ='YTD BS'!J24 -> 605 | I24: ='YTD BS'!K24 -> 505 | J24: ='YTD BS'!L24 -> 628 | K24: ='BALANCE SHEET'!C24 -> 980 | L24: ='YTD BS'!N24 -> 821 | M24: ='YTD BS'!O24 -> 729 | N24: ='YTD BS'!P24 -> 1358 | O24: ='BALANCE SHEET'!D24 -> 3265 | P24: ='YTD BS'!R24 -> 3550 | Q24: ='YTD BS'!S24 -> 0 | R24: ='YTD BS'!T24 -> 0 | S24: ='BALANCE SHEET'!E24 -> 0 | T24: ='QTR P&L'!W2*'BS DRIVERS'!T22 -> 0 | U24: ='QTR P&L'!X2*'BS DRIVERS'!U22 -> 0 | V24: ='QTR P&L'!Y2*'BS DRIVERS'!V22 -> 0 | W24: ='QTR P&L'!Z2*'BS DRIVERS'!W22 -> 0 | X24: ='QTR P&L'!AA2*'BS DRIVERS'!X22 -> 0 | Y24: ='QTR P&L'!AB2*'BS DRIVERS'!Y22 -> 0 | Z24: ='QTR P&L'!AC2*'BS DRIVERS'!Z22 -> 0 | AA24: ='QTR P&L'!AD2*'BS DRIVERS'!AA22 -> 0 | ... AM24: ='QTR P&L'!AP2*'BS DRIVERS'!AM22 -> 0
A25: Lease Liability - Finance - Current | B25: ='YTD BS'!C25 -> 191753 | C25: ='YTD BS'!D25 -> 155508 | D25: ='YTD BS'!F25 -> 141 | E25: ='YTD BS'!G25 -> 101 | F25: ='YTD BS'!H25 -> 95 | G25: ='BALANCE SHEET'!B25 -> 70 | H25: ='YTD BS'!J25 -> 69 | I25: ='YTD BS'!K25 -> 67 | J25: ='YTD BS'!L25 -> 63 | K25: ='BALANCE SHEET'!C25 -> 59 | L25: ='YTD BS'!N25 -> 61 | M25: ='YTD BS'!O25 -> 61 | N25: ='YTD BS'!P25 -> 99 | O25: ='BALANCE SHEET'!D25 -> 100 | P25: ='YTD BS'!R25 -> 0 | Q25: ='YTD BS'!S25 -> 0 | R25: ='YTD BS'!T25 -> 0 | S25: ='BALANCE SHEET'!E25 -> 0 | T25: ='QTR P&L'!W2*'BS DRIVERS'!T23 -> 0 | U25: ='QTR P&L'!X2*'BS DRIVERS'!U23 -> 0 | V25: ='QTR P&L'!Y2*'BS DRIVERS'!V23 -> 0 | W25: ='QTR P&L'!Z2*'BS DRIVERS'!W23 -> 0 | X25: ='QTR P&L'!AA2*'BS DRIVERS'!X23 -> 0 | Y25: ='QTR P&L'!AB2*'BS DRIVERS'!Y23 -> 0 | Z25: ='QTR P&L'!AC2*'BS DRIVERS'!Z23 -> 0 | AA25: ='QTR P&L'!AD2*'BS DRIVERS'!AA23 -> 0 | ... AM25: ='QTR P&L'!AP2*'BS DRIVERS'!AM23 -> 0
A26: Contingent Consideration - Current | B26: ='YTD BS'!C26 -> 0 | C26: ='YTD BS'!D26 -> 0 | D26: ='YTD BS'!F26 -> 0 | E26: ='YTD BS'!G26 -> 0 | F26: ='YTD BS'!H26 -> 0 | G26: ='BALANCE SHEET'!B26 -> 0 | H26: ='YTD BS'!J26 -> 0 | I26: ='YTD BS'!K26 -> 0 | J26: ='YTD BS'!L26 -> 0 | K26: ='BALANCE SHEET'!C26 -> 0 | L26: ='YTD BS'!N26 -> 0 | M26: ='YTD BS'!O26 -> 0 | N26: ='YTD BS'!P26 -> 0 | O26: ='BALANCE SHEET'!D26 -> 0 | P26: ='YTD BS'!R26 -> 0 | Q26: ='YTD BS'!S26 -> 25000 | R26: ='YTD BS'!T26 -> 25000 | S26: ='BALANCE SHEET'!E26 -> 25000 | T26: ='QTR P&L'!W2*'BS DRIVERS'!T24 -> 24880.086 | U26: ='QTR P&L'!X2*'BS DRIVERS'!U24 -> 24760.748 | V26: ='QTR P&L'!Y2*'BS DRIVERS'!V24 -> 24641.982 | W26: ='QTR P&L'!Z2*'BS DRIVERS'!W24 -> 24523.786 | X26: ='QTR P&L'!AA2*'BS DRIVERS'!X24 -> 24406.157 | Y26: ='QTR P&L'!AB2*'BS DRIVERS'!Y24 -> 24289.092 | Z26: ='QTR P&L'!AC2*'BS DRIVERS'!Z24 -> 24172.588 | AA26: ='QTR P&L'!AD2*'BS DRIVERS'!AA24 -> 24056.643 | ... AM26: ='QTR P&L'!AP2*'BS DRIVERS'!AM24 -> 22707.93
A27: Deferred Revenue - Current | B27: ='YTD BS'!C27 -> 0 | C27: ='YTD BS'!D27 -> 0 | D27: ='YTD BS'!F27 -> 0 | E27: ='YTD BS'!G27 -> 0 | F27: ='YTD BS'!H27 -> 7770 | G27: ='BALANCE SHEET'!B27 -> 9675 | H27: ='YTD BS'!J27 -> 9563 | I27: ='YTD BS'!K27 -> 9500 | J27: ='YTD BS'!L27 -> 9500 | K27: ='BALANCE SHEET'!C27 -> 9513 | L27: ='YTD BS'!N27 -> 9513 | M27: ='YTD BS'!O27 -> 9513 | N27: ='YTD BS'!P27 -> 9513 | O27: ='BALANCE SHEET'!D27 -> 9513 | P27: ='YTD BS'!R27 -> 9513 | Q27: ='YTD BS'!S27 -> 16071 | R27: ='YTD BS'!T27 -> 25557 | S27: ='BALANCE SHEET'!E27 -> 26988 | T27: ='QTR P&L'!W2*'BS DRIVERS'!T25 -> 26858.551 | U27: ='QTR P&L'!X2*'BS DRIVERS'!U25 -> 26729.723 | V27: ='QTR P&L'!Y2*'BS DRIVERS'!V25 -> 26601.513 | W27: ='QTR P&L'!Z2*'BS DRIVERS'!W25 -> 26473.917 | X27: ='QTR P&L'!AA2*'BS DRIVERS'!X25 -> 26346.934 | Y27: ='QTR P&L'!AB2*'BS DRIVERS'!Y25 -> 26220.56 | Z27: ='QTR P&L'!AC2*'BS DRIVERS'!Z25 -> 26094.792 | AA27: ='QTR P&L'!AD2*'BS DRIVERS'!AA25 -> 25969.627 | ... AM27: ='QTR P&L'!AP2*'BS DRIVERS'!AM25 -> 24513.665
A28: Other Current Liabilities | B28: ='YTD BS'!C28 -> 754907 | C28: ='YTD BS'!D28 -> 957627 | D28: ='YTD BS'!F28 -> 1734 | E28: ='YTD BS'!G28 -> 2761 | F28: ='YTD BS'!H28 -> 3267 | G28: ='BALANCE SHEET'!B28 -> 3586 | H28: ='YTD BS'!J28 -> 5094 | I28: ='YTD BS'!K28 -> 7109 | J28: ='YTD BS'!L28 -> 8826 | K28: ='BALANCE SHEET'!C28 -> 10890 | L28: ='YTD BS'!N28 -> 12987 | M28: ='YTD BS'!O28 -> 13772 | N28: ='YTD BS'!P28 -> 14979 | O28: ='BALANCE SHEET'!D28 -> 15808 | P28: ='YTD BS'!R28 -> 14160 | Q28: ='YTD BS'!S28 -> 49949 | R28: ='YTD BS'!T28 -> 32258 | S28: ='BALANCE SHEET'!E28 -> 36465 | T28: ='QTR P&L'!W2*'BS DRIVERS'!T26 -> 36290.094 | U28: ='QTR P&L'!X2*'BS DRIVERS'!U26 -> 36116.027 | V28: ='QTR P&L'!Y2*'BS DRIVERS'!V26 -> 35942.795 | W28: ='QTR P&L'!Z2*'BS DRIVERS'!W26 -> 35770.394 | X28: ='QTR P&L'!AA2*'BS DRIVERS'!X26 -> 35598.82 | Y28: ='QTR P&L'!AB2*'BS DRIVERS'!Y26 -> 35428.069 | Z28: ='QTR P&L'!AC2*'BS DRIVERS'!Z26 -> 35258.137 | AA28: ='QTR P&L'!AD2*'BS DRIVERS'!AA26 -> 35089.02 | ... AM28: ='QTR P&L'!AP2*'BS DRIVERS'!AM26 -> 33121.787
A29: Total Current Liabilities | B29: ='YTD BS'!C29 -> 54256877 | C29: ='YTD BS'!D29 -> 93421330 | D29: ='YTD BS'!F29 -> 111751 | E29: ='YTD BS'!G29 -> 105834 | F29: ='YTD BS'!H29 -> 271293 | G29: ='BALANCE SHEET'!B29 -> 161295 | H29: ='YTD BS'!J29 -> 191731 | I29: ='YTD BS'!K29 -> 269225 | J29: ='YTD BS'!L29 -> 335517 | K29: ='BALANCE SHEET'!C29 -> 276613 | L29: ='YTD BS'!N29 -> 315269 | M29: ='YTD BS'!O29 -> 312984 | N29: ='YTD BS'!P29 -> 289460 | O29: ='BALANCE SHEET'!D29 -> 365535 | P29: ='YTD BS'!R29 -> 417854 | Q29: ='YTD BS'!S29 -> 659775 | R29: ='YTD BS'!T29 -> 1028988 | S29: ='BALANCE SHEET'!E29 -> 1078726 | T29: =SUM(T19:T28) -> 810730.56 | U29: =SUM(U19:U28) -> 806841.85 | V29: =SUM(V19:V28) -> 802971.81 | W29: =SUM(W19:W28) -> 799120.32 | X29: =SUM(X19:X28) -> 795287.31 | Y29: =SUM(Y19:Y28) -> 791472.68 | Z29: =SUM(Z19:Z28) -> 787676.35 | AA29: =SUM(AA19:AA28) -> 783898.23 | ... AM29: =SUM(AM19:AM28) -> 739949.72
A30: Lease Liability - Operating - Non-Current | B30: ='YTD BS'!C30 -> 391157 | C30: ='YTD BS'!D30 -> 550547 | D30: ='YTD BS'!F30 -> 597 | E30: ='YTD BS'!G30 -> 420 | F30: ='YTD BS'!H30 -> 462 | G30: ='BALANCE SHEET'!B30 -> 326 | H30: ='YTD BS'!J30 -> 336 | I30: ='YTD BS'!K30 -> 249 | J30: ='YTD BS'!L30 -> 512 | K30: ='BALANCE SHEET'!C30 -> 955 | L30: ='YTD BS'!N30 -> 850 | M30: ='YTD BS'!O30 -> 762 | N30: ='YTD BS'!P30 -> 4193 | O30: ='BALANCE SHEET'!D30 -> 16674 | P30: ='YTD BS'!R30 -> 16152 | Q30: ='YTD BS'!S30 -> 0 | R30: ='YTD BS'!T30 -> 0 | S30: ='BALANCE SHEET'!E30 -> 0 | T30: ='QTR P&L'!W2*'BS DRIVERS'!T27 -> 0 | U30: ='QTR P&L'!X2*'BS DRIVERS'!U27 -> 0 | V30: ='QTR P&L'!Y2*'BS DRIVERS'!V27 -> 0 | W30: ='QTR P&L'!Z2*'BS DRIVERS'!W27 -> 0 | X30: ='QTR P&L'!AA2*'BS DRIVERS'!X27 -> 0 | Y30: ='QTR P&L'!AB2*'BS DRIVERS'!Y27 -> 0 | Z30: ='QTR P&L'!AC2*'BS DRIVERS'!Z27 -> 0 | AA30: ='QTR P&L'!AD2*'BS DRIVERS'!AA27 -> 0 | ... AM30: ='QTR P&L'!AP2*'BS DRIVERS'!AM27 -> 0
A31: Lease Liability - Finance - Non-Current | B31: ='YTD BS'!C31 -> 60731 | C31: ='YTD BS'!D31 -> 88649 | D31: ='YTD BS'!F31 -> 138 | E31: ='YTD BS'!G31 -> 138 | F31: ='YTD BS'!H31 -> 167 | G31: ='BALANCE SHEET'!B31 -> 162 | H31: ='YTD BS'!J31 -> 156 | I31: ='YTD BS'!K31 -> 147 | J31: ='YTD BS'!L31 -> 135 | K31: ='BALANCE SHEET'!C31 -> 193 | L31: ='YTD BS'!N31 -> 245 | M31: ='YTD BS'!O31 -> 228 | N31: ='YTD BS'!P31 -> 189 | O31: ='BALANCE SHEET'!D31 -> 211 | P31: ='YTD BS'!R31 -> 0 | Q31: ='YTD BS'!S31 -> 0 | R31: ='YTD BS'!T31 -> 0 | S31: ='BALANCE SHEET'!E31 -> 0 | T31: ='QTR P&L'!W2*'BS DRIVERS'!T28 -> 0 | U31: ='QTR P&L'!X2*'BS DRIVERS'!U28 -> 0 | V31: ='QTR P&L'!Y2*'BS DRIVERS'!V28 -> 0 | W31: ='QTR P&L'!Z2*'BS DRIVERS'!W28 -> 0 | X31: ='QTR P&L'!AA2*'BS DRIVERS'!X28 -> 0 | Y31: ='QTR P&L'!AB2*'BS DRIVERS'!Y28 -> 0 | Z31: ='QTR P&L'!AC2*'BS DRIVERS'!Z28 -> 0 | AA31: ='QTR P&L'!AD2*'BS DRIVERS'!AA28 -> 0 | ... AM31: ='QTR P&L'!AP2*'BS DRIVERS'!AM28 -> 0
A32: Deferred Tax Liability | B32: ='YTD BS'!C32 -> 0 | C32: ='YTD BS'!D32 -> 3497240 | D32: ='YTD BS'!F32 -> 3084 | E32: ='YTD BS'!G32 -> 2886 | F32: ='YTD BS'!H32 -> 25457 | G32: ='BALANCE SHEET'!B32 -> 15919 | H32: ='YTD BS'!J32 -> 19250 | I32: ='YTD BS'!K32 -> 2333 | J32: ='YTD BS'!L32 -> 2249 | K32: ='BALANCE SHEET'!C32 -> 2880 | L32: ='YTD BS'!N32 -> 2248 | M32: ='YTD BS'!O32 -> 2201 | N32: ='YTD BS'!P32 -> 2275 | O32: ='BALANCE SHEET'!D32 -> 2330 | P32: ='YTD BS'!R32 -> 0 | Q32: ='YTD BS'!S32 -> 0 | R32: ='YTD BS'!T32 -> 0 | S32: ='BALANCE SHEET'!E32 -> 0 | T32: ='BS DRIVERS'!T29 -> 0 | U32: ='BS DRIVERS'!U29 -> 0 | V32: ='BS DRIVERS'!V29 -> 0 | W32: ='BS DRIVERS'!W29 -> 0 | X32: ='BS DRIVERS'!X29 -> 0 | Y32: ='BS DRIVERS'!Y29 -> 0 | Z32: ='BS DRIVERS'!Z29 -> 0 | AA32: ='BS DRIVERS'!AA29 -> 0 | ... AM32: ='BS DRIVERS'!AM29 -> 0
A33: Long-Term Debt | B33: ='YTD BS'!C33 -> 0 | C33: ='YTD BS'!D33 -> 0 | D33: ='YTD BS'!F33 -> 0 | E33: ='YTD BS'!G33 -> 0 | F33: ='YTD BS'!H33 -> 0 | G33: ='BALANCE SHEET'!B33 -> 0 | H33: ='YTD BS'!J33 -> 0 | I33: ='YTD BS'!K33 -> 0 | J33: ='YTD BS'!L33 -> 0 | K33: ='BALANCE SHEET'!C33 -> 0 | L33: ='YTD BS'!N33 -> 0 | M33: ='YTD BS'!O33 -> 0 | N33: ='YTD BS'!P33 -> 0 | O33: ='BALANCE SHEET'!D33 -> 0 | P33: ='YTD BS'!R33 -> 0 | Q33: ='YTD BS'!S33 -> 862917 | R33: ='YTD BS'!T33 -> 861472 | S33: ='BALANCE SHEET'!E33 -> 669926 | T33: ='BS DRIVERS'!T30 -> 669926 | U33: ='BS DRIVERS'!U30 -> 669926 | V33: ='BS DRIVERS'!V30 -> 669926 | W33: ='BS DRIVERS'!W30 -> 669926 | X33: ='BS DRIVERS'!X30 -> 669926 | Y33: ='BS DRIVERS'!Y30 -> 669926 | Z33: ='BS DRIVERS'!Z30 -> 669926 | AA33: ='BS DRIVERS'!AA30 -> 669926 | ... AM33: ='BS DRIVERS'!AM30 -> 669926
A34: Deferred Revenue - Non-Current | B34: ='YTD BS'!C34 -> 0 | C34: ='YTD BS'!D34 -> 0 | D34: ='YTD BS'!F34 -> 0 | E34: ='YTD BS'!G34 -> 0 | F34: ='YTD BS'!H34 -> 146333 | G34: ='BALANCE SHEET'!B34 -> 179788 | H34: ='YTD BS'!J34 -> 175275 | I34: ='YTD BS'!K34 -> 171745 | J34: ='YTD BS'!L34 -> 169370 | K34: ='BALANCE SHEET'!C34 -> 167227 | L34: ='YTD BS'!N34 -> 164849 | M34: ='YTD BS'!O34 -> 162471 | N34: ='YTD BS'!P34 -> 160092 | O34: ='BALANCE SHEET'!D34 -> 157714 | P34: ='YTD BS'!R34 -> 155336 | Q34: ='YTD BS'!S34 -> 156135 | R34: ='YTD BS'!T34 -> 387432 | S34: ='BALANCE SHEET'!E34 -> 401155 | T34: ='QTR P&L'!W2*'BS DRIVERS'!T31 -> 399230.84 | U34: ='QTR P&L'!X2*'BS DRIVERS'!U31 -> 397315.92 | V34: ='QTR P&L'!Y2*'BS DRIVERS'!V31 -> 395410.18 | W34: ='QTR P&L'!Z2*'BS DRIVERS'!W31 -> 393513.57 | X34: ='QTR P&L'!AA2*'BS DRIVERS'!X31 -> 391626.07 | Y34: ='QTR P&L'!AB2*'BS DRIVERS'!Y31 -> 389747.62 | Z34: ='QTR P&L'!AC2*'BS DRIVERS'!Z31 -> 387878.18 | AA34: ='QTR P&L'!AD2*'BS DRIVERS'!AA31 -> 386017.71 | ... AM34: ='QTR P&L'!AP2*'BS DRIVERS'!AM31 -> 364375.99
A35: Other Non-Current Liabilities | B35: ='YTD BS'!C35 -> 0 | C35: ='YTD BS'!D35 -> 22198 | D35: ='YTD BS'!F35 -> 0 | E35: ='YTD BS'!G35 -> 487 | F35: ='YTD BS'!H35 -> 0 | G35: ='BALANCE SHEET'!B35 -> 0 | H35: ='YTD BS'!J35 -> 0 | I35: ='YTD BS'!K35 -> 0 | J35: ='YTD BS'!L35 -> 0 | K35: ='BALANCE SHEET'!C35 -> 0 | L35: ='YTD BS'!N35 -> 0 | M35: ='YTD BS'!O35 -> 0 | N35: ='YTD BS'!P35 -> 0 | O35: ='BALANCE SHEET'!D35 -> 0 | P35: ='YTD BS'!R35 -> 2574 | Q35: ='YTD BS'!S35 -> 25002 | R35: ='YTD BS'!T35 -> 24431 | S35: ='BALANCE SHEET'!E35 -> 28372 | T35: ='QTR P&L'!W2*'BS DRIVERS'!T32 -> 28235.913 | U35: ='QTR P&L'!X2*'BS DRIVERS'!U32 -> 28100.478 | V35: ='QTR P&L'!Y2*'BS DRIVERS'!V32 -> 27965.693 | W35: ='QTR P&L'!Z2*'BS DRIVERS'!W32 -> 27831.554 | X35: ='QTR P&L'!AA2*'BS DRIVERS'!X32 -> 27698.059 | Y35: ='QTR P&L'!AB2*'BS DRIVERS'!Y32 -> 27565.204 | Z35: ='QTR P&L'!AC2*'BS DRIVERS'!Z32 -> 27432.987 | AA35: ='QTR P&L'!AD2*'BS DRIVERS'!AA32 -> 27301.403 | ... AM35: ='QTR P&L'!AP2*'BS DRIVERS'!AM32 -> 25770.776
A36: Total Liabilities | B36: ='YTD BS'!C36 -> 54708765 | C36: ='YTD BS'!D36 -> 97579964 | D36: ='YTD BS'!F36 -> 115570 | E36: ='YTD BS'!G36 -> 109765 | F36: ='YTD BS'!H36 -> 443712 | G36: ='BALANCE SHEET'!B36 -> 357490 | H36: ='YTD BS'!J36 -> 386748 | I36: ='YTD BS'!K36 -> 443699 | J36: ='YTD BS'!L36 -> 507783 | K36: ='BALANCE SHEET'!C36 -> 447868 | L36: ='YTD BS'!N36 -> 483461 | M36: ='YTD BS'!O36 -> 478646 | N36: ='YTD BS'!P36 -> 456209 | O36: ='BALANCE SHEET'!D36 -> 542464 | P36: ='YTD BS'!R36 -> 591916 | Q36: ='YTD BS'!S36 -> 1703829 | R36: ='YTD BS'!T36 -> 2302323 | S36: ='BALANCE SHEET'!E36 -> 2178179 | T36: =T29+SUM(T30:T35) -> 1908123.3 | U36: =U29+SUM(U30:U35) -> 1902184.2 | V36: =V29+SUM(V30:V35) -> 1896273.7 | W36: =W29+SUM(W30:W35) -> 1890391.4 | X36: =X29+SUM(X30:X35) -> 1884537.4 | Y36: =Y29+SUM(Y30:Y35) -> 1878711.5 | Z36: =Z29+SUM(Z30:Z35) -> 1872913.5 | AA36: =AA29+SUM(AA30:AA35) -> 1867143.3 | ... AM36: =AM29+SUM(AM30:AM35) -> 1800022.5
A37: Convertible Preferred Stock | B37: ='YTD BS'!C37 -> 0 | C37: ='YTD BS'!D37 -> 0 | D37: ='YTD BS'!F37 -> 0 | E37: ='YTD BS'!G37 -> 0 | F37: ='YTD BS'!H37 -> 824488 | G37: ='BALANCE SHEET'!B37 -> 824488 | H37: ='YTD BS'!J37 -> 824488 | I37: ='YTD BS'!K37 -> 824488 | J37: ='YTD BS'!L37 -> 824488 | K37: ='BALANCE SHEET'!C37 -> 824488 | L37: ='YTD BS'!N37 -> 824488 | M37: ='YTD BS'!O37 -> 824488 | N37: ='YTD BS'!P37 -> 824488 | O37: ='BALANCE SHEET'!D37 -> 824488 | P37: ='YTD BS'!R37 -> 824488 | Q37: ='YTD BS'!S37 -> 824488 | R37: ='YTD BS'!T37 -> 1760275 | S37: ='BALANCE SHEET'!E37 -> 1759975 | T37: ='BS DRIVERS'!T33 -> 1759975 | U37: ='BS DRIVERS'!U33 -> 1759975 | V37: ='BS DRIVERS'!V33 -> 1759975 | W37: ='BS DRIVERS'!W33 -> 1759975 | X37: ='BS DRIVERS'!X33 -> 1759975 | Y37: ='BS DRIVERS'!Y33 -> 1759975 | Z37: ='BS DRIVERS'!Z33 -> 1759975 | AA37: ='BS DRIVERS'!AA33 -> 1759975 | ... AM37: ='BS DRIVERS'!AM33 -> 1759975
A38: Common Stock | B38: ='YTD BS'!C38 -> 74471 | C38: ='YTD BS'!D38 -> 74746 | D38: ='YTD BS'!F38 -> 75 | E38: ='YTD BS'!G38 -> 76 | F38: ='YTD BS'!H38 -> 76 | G38: ='BALANCE SHEET'!B38 -> 76 | H38: ='YTD BS'!J38 -> 77 | I38: ='YTD BS'!K38 -> 77 | J38: ='YTD BS'!L38 -> 77 | K38: ='BALANCE SHEET'!C38 -> 77 | L38: ='YTD BS'!N38 -> 78 | M38: ='YTD BS'!O38 -> 78 | N38: ='YTD BS'!P38 -> 79 | O38: ='BALANCE SHEET'!D38 -> 79 | P38: ='YTD BS'!R38 -> 79 | Q38: ='YTD BS'!S38 -> 101 | R38: ='YTD BS'!T38 -> 101 | S38: ='BALANCE SHEET'!E38 -> 101 | T38: ='BS DRIVERS'!T34 -> 101 | U38: ='BS DRIVERS'!U34 -> 101 | V38: ='BS DRIVERS'!V34 -> 101 | W38: ='BS DRIVERS'!W34 -> 101 | X38: ='BS DRIVERS'!X34 -> 101 | Y38: ='BS DRIVERS'!Y34 -> 101 | Z38: ='BS DRIVERS'!Z34 -> 101 | AA38: ='BS DRIVERS'!AA34 -> 101 | ... AM38: ='BS DRIVERS'!AM34 -> 101
A39: Treasury Stock | B39: ='YTD BS'!C39 -> 0 | C39: ='YTD BS'!D39 -> 0 | D39: ='YTD BS'!F39 -> 0 | E39: ='YTD BS'!G39 -> 0 | F39: ='YTD BS'!H39 -> 0 | G39: ='BALANCE SHEET'!B39 -> 0 | H39: ='YTD BS'!J39 -> 0 | I39: ='YTD BS'!K39 -> 0 | J39: ='YTD BS'!L39 -> 0 | K39: ='BALANCE SHEET'!C39 -> 0 | L39: ='YTD BS'!N39 -> 0 | M39: ='YTD BS'!O39 -> 0 | N39: ='YTD BS'!P39 -> 0 | O39: ='BALANCE SHEET'!D39 -> 0 | P39: ='YTD BS'!R39 -> 0 | Q39: ='YTD BS'!S39 -> 0 | R39: ='YTD BS'!T39 -> 0 | S39: ='BALANCE SHEET'!E39 -> -48226 | T39: ='BS DRIVERS'!T35 -> -48226 | U39: ='BS DRIVERS'!U35 -> -48226 | V39: ='BS DRIVERS'!V35 -> -48226 | W39: ='BS DRIVERS'!W35 -> -48226 | X39: ='BS DRIVERS'!X35 -> -48226 | Y39: ='BS DRIVERS'!Y35 -> -48226 | Z39: ='BS DRIVERS'!Z35 -> -48226 | AA39: ='BS DRIVERS'!AA35 -> -48226 | ... AM39: ='BS DRIVERS'!AM35 -> -48226
A40: Additional Paid-in Capital | B40: ='YTD BS'!C40 -> 237763609 | C40: ='YTD BS'!D40 -> 244293710 | D40: ='YTD BS'!F40 -> 272967 | E40: ='YTD BS'!G40 -> 277623 | F40: ='YTD BS'!H40 -> 281133 | G40: ='BALANCE SHEET'!B40 -> 280668 | H40: ='YTD BS'!J40 -> 279872 | I40: ='YTD BS'!K40 -> 278980 | J40: ='YTD BS'!L40 -> 277980 | K40: ='BALANCE SHEET'!C40 -> 276717 | L40: ='YTD BS'!N40 -> 281247 | M40: ='YTD BS'!O40 -> 286173 | N40: ='YTD BS'!P40 -> 292576 | O40: ='BALANCE SHEET'!D40 -> 297579 | P40: ='YTD BS'!R40 -> 300877 | Q40: ='YTD BS'!S40 -> 1028384 | R40: ='YTD BS'!T40 -> 1035021 | S40: ='BALANCE SHEET'!E40 -> 1050518 | T40: ='BS DRIVERS'!T36 -> 1059676.9 | U40: ='BS DRIVERS'!U36 -> 1068791.8 | V40: ='BS DRIVERS'!V36 -> 1077863 | W40: ='BS DRIVERS'!W36 -> 1086890.7 | X40: ='BS DRIVERS'!X36 -> 1095875.1 | Y40: ='BS DRIVERS'!Y36 -> 1104816.4 | Z40: ='BS DRIVERS'!Z36 -> 1113714.8 | AA40: ='BS DRIVERS'!AA36 -> 1122570.5 | ... AM40: ='BS DRIVERS'!AM36 -> 1225583.7
A41: Accumulated Other Comprehensive Income (Loss) | B41: ='YTD BS'!C41 -> -117656 | C41: ='YTD BS'!D41 -> 1165027 | D41: ='YTD BS'!F41 -> 123 | E41: ='YTD BS'!G41 -> -2173 | F41: ='YTD BS'!H41 -> -4211 | G41: ='BALANCE SHEET'!B41 -> -1881 | H41: ='YTD BS'!J41 -> -1287 | I41: ='YTD BS'!K41 -> -1877 | J41: ='YTD BS'!L41 -> -2541 | K41: ='BALANCE SHEET'!C41 -> -701 | L41: ='YTD BS'!N41 -> -2055 | M41: ='YTD BS'!O41 -> -2363 | N41: ='YTD BS'!P41 -> -338 | O41: ='BALANCE SHEET'!D41 -> -3250 | P41: ='YTD BS'!R41 -> -1001 | Q41: ='YTD BS'!S41 -> 2178 | R41: ='YTD BS'!T41 -> 2508 | S41: ='BALANCE SHEET'!E41 -> 3162 | T41: ='BS DRIVERS'!T37 -> 4259 | U41: ='BS DRIVERS'!U37 -> 5356 | V41: ='BS DRIVERS'!V37 -> 6453 | W41: ='BS DRIVERS'!W37 -> 7550 | X41: ='BS DRIVERS'!X37 -> 8647 | Y41: ='BS DRIVERS'!Y37 -> 9744 | Z41: ='BS DRIVERS'!Z37 -> 10841 | AA41: ='BS DRIVERS'!AA37 -> 11938 | ... AM41: ='BS DRIVERS'!AM37 -> 25102
A42: Retained Earnings (Accumulated Deficit) | B42: ='YTD BS'!C42 -> -50881064 | C42: ='YTD BS'!D42 -> -48135273 | D42: ='YTD BS'!F42 -> -44811 | E42: ='YTD BS'!G42 -> -35653 | F42: ='YTD BS'!H42 -> -217549 | G42: ='BALANCE SHEET'!B42 -> -238772 | H42: ='YTD BS'!J42 -> -197627 | I42: ='YTD BS'!K42 -> -146118 | J42: ='YTD BS'!L42 -> -62169 | K42: ='BALANCE SHEET'!C42 -> -12053 | L42: ='YTD BS'!N42 -> 58921 | M42: ='YTD BS'!O42 -> 131866 | N42: ='YTD BS'!P42 -> 131309 | O42: ='BALANCE SHEET'!D42 -> 105521 | P42: ='YTD BS'!R42 -> 143159 | Q42: ='YTD BS'!S42 -> 236163 | R42: ='YTD BS'!T42 -> 165480 | S42: ='BALANCE SHEET'!E42 -> 175912 | T42: ='BS DRIVERS'!T38 -> 274156.88 | U42: ='BS DRIVERS'!U38 -> 371843.74 | V42: ='BS DRIVERS'!V38 -> 468975.26 | W42: ='BS DRIVERS'!W38 -> 565554.1 | X42: ='BS DRIVERS'!X38 -> 661582.92 | Y42: ='BS DRIVERS'!Y38 -> 757064.35 | Z42: ='BS DRIVERS'!Z38 -> 852001.03 | AA42: ='BS DRIVERS'!AA38 -> 946395.55 | ... AM42: ='BS DRIVERS'!AM38 -> 2037776.4
A43: Total Stockholders' Equity | B43: ='YTD BS'!C43 -> 186839360 | C43: ='YTD BS'!D43 -> 197398210 | D43: ='YTD BS'!F43 -> 228354 | E43: ='YTD BS'!G43 -> 239873 | F43: ='YTD BS'!H43 -> 883937 | G43: ='BALANCE SHEET'!B43 -> 864579 | H43: ='YTD BS'!J43 -> 905523 | I43: ='YTD BS'!K43 -> 955550 | J43: ='YTD BS'!L43 -> 1037835 | K43: ='BALANCE SHEET'!C43 -> 1088528 | L43: ='YTD BS'!N43 -> 1162679 | M43: ='YTD BS'!O43 -> 1240242 | N43: ='YTD BS'!P43 -> 1248114 | O43: ='BALANCE SHEET'!D43 -> 1224417 | P43: ='YTD BS'!R43 -> 1267602 | Q43: ='YTD BS'!S43 -> 2091314 | R43: ='YTD BS'!T43 -> 2963385 | S43: ='BALANCE SHEET'!E43 -> 2941442 | T43: =SUM(T37:T42) -> 3049942.7 | U43: =SUM(U37:U42) -> 3157841.5 | V43: =SUM(V37:V42) -> 3265141.2 | W43: =SUM(W37:W42) -> 3371844.8 | X43: =SUM(X37:X42) -> 3477955 | Y43: =SUM(Y37:Y42) -> 3583474.7 | Z43: =SUM(Z37:Z42) -> 3688406.8 | AA43: =SUM(AA37:AA42) -> 3792754.1 | ... AM43: =SUM(AM37:AM42) -> 5000312.1
A44: Total Liabilities, Mezzanine & Stockholders' Equity | B44: ='YTD BS'!C44 -> 241548125 | C44: ='YTD BS'!D44 -> 294978174 | D44: ='YTD BS'!F44 -> 343924 | E44: ='YTD BS'!G44 -> 349638 | F44: ='YTD BS'!H44 -> 1327649 | G44: ='BALANCE SHEET'!B44 -> 1222069 | H44: ='YTD BS'!J44 -> 1292271 | I44: ='YTD BS'!K44 -> 1399249 | J44: ='YTD BS'!L44 -> 1545618 | K44: ='BALANCE SHEET'!C44 -> 1536396 | L44: ='YTD BS'!N44 -> 1646140 | M44: ='YTD BS'!O44 -> 1718888 | N44: ='YTD BS'!P44 -> 1704323 | O44: ='BALANCE SHEET'!D44 -> 1766881 | P44: ='YTD BS'!R44 -> 1859518 | Q44: ='YTD BS'!S44 -> 3795143 | R44: ='YTD BS'!T44 -> 5265708 | S44: ='BALANCE SHEET'!E44 -> 5119621 | T44: =T36+T43 -> 4958066 | U44: =U36+U43 -> 5060025.8 | V44: =V36+V43 -> 5161414.9 | W44: =W36+W43 -> 5262236.2 | X44: =X36+X43 -> 5362492.4 | Y44: =Y36+Y43 -> 5462186.2 | Z44: =Z36+Z43 -> 5561320.3 | AA44: =AA36+AA43 -> 5659897.4 | ... AM44: =AM36+AM43 -> 6800334.6

Sheet QTR CF
B1: Q3 FY2020 | C1: Q1 FY2021 | D1: Q2 FY2021 | E1: Q3 FY2021 | F1: Q4 FY2021 | G1: Q1 FY2022 | H1: Q2 FY2022 | I1: Q3 FY2022 | J1: Q4 FY2022 | K1: Q1 FY2023 | L1: Q2 FY2023 | M1: Q3 FY2023 | N1: Q4 FY2023 | O1: Q1 FY2024 | P1: Q2 FY2024 | Q1: Q3 FY2024 | R1: Q4 FY2024 | S1: Q1 FY2025 | T1: Q2 FY2025 | U1: Q3 FY2025 | V1: Q4 FY2025 | W1: Q1 FY2026E | X1: Q2 FY2026E | Y1: Q3 FY2026E | Z1: Q4 FY2026E | AA1: Q1 FY2027E | AB1: Q2 FY2027E | AC1: Q3 FY2027E | AD1: Q4 FY2027E | AE1: Q1 FY2028E | AF1: Q2 FY2028E | AG1: Q3 FY2028E | AH1: Q4 FY2028E | AI1: Q1 FY2029E | AJ1: Q2 FY2029E | AK1: Q3 FY2029E | AL1: Q4 FY2029E | AM1: Q1 FY2030E | AN1: Q2 FY2030E | AO1: Q3 FY2030E | AP1: Q4 FY2030E
A2: Net Income (Loss) | B2: ='YTD CF'!C2-'YTD CF'!B2 -> 4753603 | C2: ='YTD CF'!D2 -> 585 | D2: ='YTD CF'!E2-'YTD CF'!D2 -> 4545183 | E2: ='YTD CF'!F2-'YTD CF'!E2 -> 2745791 | F2: ='CASH FLOW'!B2-'YTD CF'!F2 -> -7287622 | G2: ='YTD CF'!G2 -> 6679 | H2: ='YTD CF'!H2-'YTD CF'!G2 -> 9159 | I2: ='YTD CF'!I2-'YTD CF'!H2 -> -181897 | J2: ='CASH FLOW'!C2-'YTD CF'!I2 -> -21223 | K2: ='YTD CF'!J2 -> 41227 | L2: ='YTD CF'!K2-'YTD CF'!J2 -> 51509 | M2: ='YTD CF'!L2-'YTD CF'!K2 -> 83949 | N2: ='CASH FLOW'!D2-'YTD CF'!L2 -> 50116 | O2: ='YTD CF'!M2 -> 77811 | P2: ='YTD CF'!N2-'YTD CF'!M2 -> 79783 | Q2: ='YTD CF'!O2-'YTD CF'!N2 -> 6356 | R2: ='CASH FLOW'!E2-'YTD CF'!O2 -> -18876 | S2: ='YTD CF'!P2 -> 44419 | T2: ='YTD CF'!Q2-'YTD CF'!P2 -> 99855 | U2: ='YTD CF'!R2-'YTD CF'!Q2 -> -61014 | V2: ='CASH FLOW'!F2-'YTD CF'!R2 -> 24739 | W2: ='CF DRIVERS'!W2 -> 112551.88 | X2: ='CF DRIVERS'!X2 -> 111993.86 | Y2: ='CF DRIVERS'!Y2 -> 111438.52 | Z2: ='CF DRIVERS'!Z2 -> 110885.84 | AA2: ='CF DRIVERS'!AA2 -> 110335.82 | AB2: ='CF DRIVERS'!AB2 -> 109788.43 | AC2: ='CF DRIVERS'!AC2 -> 109243.67 | AD2: ='CF DRIVERS'!AD2 -> 108701.52 | ... AP2: ='CF DRIVERS'!AP2 -> 102395.05
A3: Depreciation | B3: ='YTD CF'!C3-'YTD CF'!B3 -> 31829 | C3: ='YTD CF'!D3 -> 108 | D3: ='YTD CF'!E3-'YTD CF'!D3 -> 178317 | E3: ='YTD CF'!F3-'YTD CF'!E3 -> 341340 | G3: ='YTD CF'!G3 -> 245 | H3: ='YTD CF'!H3-'YTD CF'!G3 -> 311 | I3: ='YTD CF'!I3-'YTD CF'!H3 -> 396 | K3: ='YTD CF'!J3 -> 404 | L3: ='YTD CF'!K3-'YTD CF'!J3 -> 549 | M3: ='YTD CF'!L3-'YTD CF'!K3 -> 723 | O3: ='YTD CF'!M3 -> 0 | P3: ='YTD CF'!N3-'YTD CF'!M3 -> 0 | Q3: ='YTD CF'!O3-'YTD CF'!N3 -> 0 | S3: ='YTD CF'!P3 -> 0 | T3: ='YTD CF'!Q3-'YTD CF'!P3 -> 0 | U3: ='YTD CF'!R3-'YTD CF'!Q3 -> 0 | W3: ='CF DRIVERS'!W3 -> 0 | X3: ='CF DRIVERS'!X3 -> 0 | Y3: ='CF DRIVERS'!Y3 -> 0 | Z3: ='CF DRIVERS'!Z3 -> 0 | AA3: ='CF DRIVERS'!AA3 -> 0 | AB3: ='CF DRIVERS'!AB3 -> 0 | AC3: ='CF DRIVERS'!AC3 -> 0 | AD3: ='CF DRIVERS'!AD3 -> 0 | ... AP3: ='CF DRIVERS'!AP3 -> 0
A4: Amortization | B4: ='YTD CF'!C4-'YTD CF'!B4 -> 373639 | C4: ='YTD CF'!D4 -> 188 | D4: ='YTD CF'!E4-'YTD CF'!D4 -> 374953 | E4: ='YTD CF'!F4-'YTD CF'!E4 -> 175659 | G4: ='YTD CF'!G4 -> 141 | H4: ='YTD CF'!H4-'YTD CF'!G4 -> 134 | I4: ='YTD CF'!I4-'YTD CF'!H4 -> 127 | K4: ='YTD CF'!J4 -> 145 | L4: ='YTD CF'!K4-'YTD CF'!J4 -> 149 | M4: ='YTD CF'!L4-'YTD CF'!K4 -> 151 | O4: ='YTD CF'!M4 -> 0 | P4: ='YTD CF'!N4-'YTD CF'!M4 -> 0 | Q4: ='YTD CF'!O4-'YTD CF'!N4 -> 0 | S4: ='YTD CF'!P4 -> 0 | T4: ='YTD CF'!Q4-'YTD CF'!P4 -> 0 | U4: ='YTD CF'!R4-'YTD CF'!Q4 -> 0 | W4: ='CF DRIVERS'!W4 -> 0 | X4: ='CF DRIVERS'!X4 -> 0 | Y4: ='CF DRIVERS'!Y4 -> 0 | Z4: ='CF DRIVERS'!Z4 -> 0 | AA4: ='CF DRIVERS'!AA4 -> 0 | AB4: ='CF DRIVERS'!AB4 -> 0 | AC4: ='CF DRIVERS'!AC4 -> 0 | AD4: ='CF DRIVERS'!AD4 -> 0 | ... AP4: ='CF DRIVERS'!AP4 -> 0
A5: Impairment of Intangibles | B5: ='YTD CF'!C5-'YTD CF'!B5 -> 0 | C5: ='YTD CF'!D5 -> 0 | D5: ='YTD CF'!E5-'YTD CF'!D5 -> 0 | E5: ='YTD CF'!F5-'YTD CF'!E5 -> 0 | F5: ='CASH FLOW'!B4-'YTD CF'!F5 -> 0 | G5: ='YTD CF'!G5 -> 0 | H5: ='YTD CF'!H5-'YTD CF'!G5 -> 0 | I5: ='YTD CF'!I5-'YTD CF'!H5 -> 2379 | J5: ='CASH FLOW'!C4-'YTD CF'!I5 -> 0 | K5: ='YTD CF'!J5 -> 0 | L5: ='YTD CF'!K5-'YTD CF'!J5 -> 0 | M5: ='YTD CF'!L5-'YTD CF'!K5 -> 0 | N5: ='CASH FLOW'!D4-'YTD CF'!L5 -> 0 | O5: ='YTD CF'!M5 -> 0 | P5: ='YTD CF'!N5-'YTD CF'!M5 -> 0 | Q5: ='YTD CF'!O5-'YTD CF'!N5 -> 0 | R5: ='CASH FLOW'!E4-'YTD CF'!O5 -> 0 | S5: ='YTD CF'!P5 -> 0 | T5: ='YTD CF'!Q5-'YTD CF'!P5 -> 0 | U5: ='YTD CF'!R5-'YTD CF'!Q5 -> 0 | V5: ='CASH FLOW'!F4-'YTD CF'!R5 -> 0 | W5: ='CF DRIVERS'!W5 -> 0 | X5: ='CF DRIVERS'!X5 -> 0 | Y5: ='CF DRIVERS'!Y5 -> 0 | Z5: ='CF DRIVERS'!Z5 -> 0 | AA5: ='CF DRIVERS'!AA5 -> 0 | AB5: ='CF DRIVERS'!AB5 -> 0 | AC5: ='CF DRIVERS'!AC5 -> 0 | AD5: ='CF DRIVERS'!AD5 -> 0 | ... AP5: ='CF DRIVERS'!AP5 -> 0
A6: Depreciation & Amortization | B6: ='YTD CF'!C6-'YTD CF'!B6 -> 0 | C6: ='YTD CF'!D6 -> 0 | D6: ='YTD CF'!E6-'YTD CF'!D6 -> 0 | E6: ='YTD CF'!F6-'YTD CF'!E6 -> 0 | F6: ='CASH FLOW'!B3-'YTD CF'!F6 -> 1264 | G6: ='YTD CF'!G6 -> 0 | H6: ='YTD CF'!H6-'YTD CF'!G6 -> 0 | I6: ='YTD CF'!I6-'YTD CF'!H6 -> 0 | J6: ='CASH FLOW'!C3-'YTD CF'!I6 -> 1917 | K6: ='YTD CF'!J6 -> 0 | L6: ='YTD CF'!K6-'YTD CF'!J6 -> 0 | M6: ='YTD CF'!L6-'YTD CF'!K6 -> 0 | N6: ='CASH FLOW'!D3-'YTD CF'!L6 -> 3226 | O6: ='YTD CF'!M6 -> 1229 | P6: ='YTD CF'!N6-'YTD CF'!M6 -> 1419 | Q6: ='YTD CF'!O6-'YTD CF'!N6 -> 2240 | R6: ='CASH FLOW'!E3-'YTD CF'!O6 -> 2386 | S6: ='YTD CF'!P6 -> 2611 | T6: ='YTD CF'!Q6-'YTD CF'!P6 -> 9119 | U6: ='YTD CF'!R6-'YTD CF'!Q6 -> 8786 | V6: ='CASH FLOW'!F3-'YTD CF'!R6 -> 8935 | W6: ='QTR P&L'!W2*'CF DRIVERS'!W6 -> 8892.1429 | X6: ='QTR P&L'!X2*'CF DRIVERS'!X6 -> 8849.4914 | Y6: ='QTR P&L'!Y2*'CF DRIVERS'!Y6 -> 8807.0445 | Z6: ='QTR P&L'!Z2*'CF DRIVERS'!Z6 -> 8764.8011 | AA6: ='QTR P&L'!AA2*'CF DRIVERS'!AA6 -> 8722.7604 | AB6: ='QTR P&L'!AB2*'CF DRIVERS'!AB6 -> 8680.9213 | AC6: ='QTR P&L'!AC2*'CF DRIVERS'!AC6 -> 8639.2829 | AD6: ='QTR P&L'!AD2*'CF DRIVERS'!AD6 -> 8597.8443 | ... AP6: ='QTR P&L'!AP2*'CF DRIVERS'!AP6 -> 8115.8143
A7: Allowance for Credit Losses | B7: ='YTD CF'!C7-'YTD CF'!B7 -> 23503 | C7: ='YTD CF'!D7 -> 223 | D7: ='YTD CF'!E7-'YTD CF'!D7 -> 854383 | E7: ='YTD CF'!F7-'YTD CF'!E7 -> -1061867 | F7: ='CASH FLOW'!B5-'YTD CF'!F7 -> 208755 | G7: ='YTD CF'!G7 -> 455 | H7: ='YTD CF'!H7-'YTD CF'!G7 -> 11 | I7: ='YTD CF'!I7-'YTD CF'!H7 -> 239 | J7: ='CASH FLOW'!C5-'YTD CF'!I7 -> 1647 | K7: ='YTD CF'!J7 -> 837 | L7: ='YTD CF'!K7-'YTD CF'!J7 -> 251 | M7: ='YTD CF'!L7-'YTD CF'!K7 -> 792 | N7: ='CASH FLOW'!D5-'YTD CF'!L7 -> 248 | O7: ='YTD CF'!M7 -> 2250 | P7: ='YTD CF'!N7-'YTD CF'!M7 -> 1822 | Q7: ='YTD CF'!O7-'YTD CF'!N7 -> 207 | R7: ='CASH FLOW'!E5-'YTD CF'!O7 -> -985 | S7: ='YTD CF'!P7 -> 2077 | T7: ='YTD CF'!Q7-'YTD CF'!P7 -> 3452 | U7: ='YTD CF'!R7-'YTD CF'!Q7 -> -2303 | V7: ='CASH FLOW'!F5-'YTD CF'!R7 -> 7374 | W7: ='CF DRIVERS'!W7 -> 0 | X7: ='CF DRIVERS'!X7 -> 0 | Y7: ='CF DRIVERS'!Y7 -> 0 | Z7: ='CF DRIVERS'!Z7 -> 0 | AA7: ='CF DRIVERS'!AA7 -> 0 | AB7: ='CF DRIVERS'!AB7 -> 0 | AC7: ='CF DRIVERS'!AC7 -> 0 | AD7: ='CF DRIVERS'!AD7 -> 0 | ... AP7: ='CF DRIVERS'!AP7 -> 0
A8: Amortization of Deferred Other Costs | B8: ='YTD CF'!C8-'YTD CF'!B8 -> 0 | C8: ='YTD CF'!D8 -> 0 | D8: ='YTD CF'!E8-'YTD CF'!D8 -> 0 | E8: ='YTD CF'!F8-'YTD CF'!E8 -> 0 | F8: ='CASH FLOW'!B6-'YTD CF'!F8 -> 0 | G8: ='YTD CF'!G8 -> 0 | H8: ='YTD CF'!H8-'YTD CF'!G8 -> 0 | I8: ='YTD CF'!I8-'YTD CF'!H8 -> 2354 | J8: ='CASH FLOW'!C6-'YTD CF'!I8 -> 3531 | K8: ='YTD CF'!J8 -> 3531 | L8: ='YTD CF'!K8-'YTD CF'!J8 -> 3531 | M8: ='YTD CF'!L8-'YTD CF'!K8 -> 3531 | N8: ='CASH FLOW'!D6-'YTD CF'!L8 -> 3531 | O8: ='YTD CF'!M8 -> 3531 | P8: ='YTD CF'!N8-'YTD CF'!M8 -> 3531 | Q8: ='YTD CF'!O8-'YTD CF'!N8 -> 3531 | R8: ='CASH FLOW'!E6-'YTD CF'!O8 -> 3531 | S8: ='YTD CF'!P8 -> 3531 | T8: ='YTD CF'!Q8-'YTD CF'!P8 -> 3531 | U8: ='YTD CF'!R8-'YTD CF'!Q8 -> 6329 | V8: ='CASH FLOW'!F6-'YTD CF'!R8 -> 12935 | W8: ='CF DRIVERS'!W8 -> 0 | X8: ='CF DRIVERS'!X8 -> 0 | Y8: ='CF DRIVERS'!Y8 -> 0 | Z8: ='CF DRIVERS'!Z8 -> 0 | AA8: ='CF DRIVERS'!AA8 -> 0 | AB8: ='CF DRIVERS'!AB8 -> 0 | AC8: ='CF DRIVERS'!AC8 -> 0 | AD8: ='CF DRIVERS'!AD8 -> 0 | ... AP8: ='CF DRIVERS'!AP8 -> 0
A9: Inventory Write-Down | B9: ='YTD CF'!C9-'YTD CF'!B9 -> 349192 | C9: ='YTD CF'!D9 -> 754 | D9: ='YTD CF'!E9-'YTD CF'!D9 -> 1259322 | E9: ='YTD CF'!F9-'YTD CF'!E9 -> -1247842 | F9: ='CASH FLOW'!B7-'YTD CF'!F9 -> -9879 | G9: ='YTD CF'!G9 -> 2596 | H9: ='YTD CF'!H9-'YTD CF'!G9 -> -2265 | I9: ='YTD CF'!I9-'YTD CF'!H9 -> 747 | J9: ='CASH FLOW'!C7-'YTD CF'!I9 -> 5053 | K9: ='YTD CF'!J9 -> 1672 | L9: ='YTD CF'!K9-'YTD CF'!J9 -> -5560 | M9: ='YTD CF'!L9-'YTD CF'!K9 -> 6565 | N9: ='CASH FLOW'!D7-'YTD CF'!L9 -> 4635 | O9: ='YTD CF'!M9 -> 2386 | P9: ='YTD CF'!N9-'YTD CF'!M9 -> 9168 | Q9: ='YTD CF'!O9-'YTD CF'!N9 -> 5564 | R9: ='CASH FLOW'!E7-'YTD CF'!O9 -> 1968 | S9: ='YTD CF'!P9 -> 5337 | T9: ='YTD CF'!Q9-'YTD CF'!P9 -> 9925 | U9: ='YTD CF'!R9-'YTD CF'!Q9 -> 7051 | V9: ='CASH FLOW'!F7-'YTD CF'!R9 -> 6877 | W9: ='CF DRIVERS'!W9 -> 0 | X9: ='CF DRIVERS'!X9 -> 0 | Y9: ='CF DRIVERS'!Y9 -> 0 | Z9: ='CF DRIVERS'!Z9 -> 0 | AA9: ='CF DRIVERS'!AA9 -> 0 | AB9: ='CF DRIVERS'!AB9 -> 0 | AC9: ='CF DRIVERS'!AC9 -> 0 | AD9: ='CF DRIVERS'!AD9 -> 0 | ... AP9: ='CF DRIVERS'!AP9 -> 0
A10: Gain (Loss) on Disposal of PP&E | B10: ='YTD CF'!C10-'YTD CF'!B10 -> 0 | C10: ='YTD CF'!D10 -> 0 | D10: ='YTD CF'!E10-'YTD CF'!D10 -> 0 | E10: ='YTD CF'!F10-'YTD CF'!E10 -> 0 | F10: ='CASH FLOW'!B8-'YTD CF'!F10 -> 0 | G10: ='YTD CF'!G10 -> 0 | H10: ='YTD CF'!H10-'YTD CF'!G10 -> 0 | I10: ='YTD CF'!I10-'YTD CF'!H10 -> 0 | J10: ='CASH FLOW'!C8-'YTD CF'!I10 -> 0 | K10: ='YTD CF'!J10 -> 0 | L10: ='YTD CF'!K10-'YTD CF'!J10 -> 191 | M10: ='YTD CF'!L10-'YTD CF'!K10 -> 4 | N10: ='CASH FLOW'!D8-'YTD CF'!L10 -> 3 | O10: ='YTD CF'!M10 -> -8 | P10: ='YTD CF'!N10-'YTD CF'!M10 -> 39 | Q10: ='YTD CF'!O10-'YTD CF'!N10 -> 95 | R10: ='CASH FLOW'!E8-'YTD CF'!O10 -> 47 | S10: ='YTD CF'!P10 -> 0 | T10: ='YTD CF'!Q10-'YTD CF'!P10 -> 0 | U10: ='YTD CF'!R10-'YTD CF'!Q10 -> 0 | V10: ='CASH FLOW'!F8-'YTD CF'!R10 -> 0 | W10: ='CF DRIVERS'!W10 -> 0 | X10: ='CF DRIVERS'!X10 -> 0 | Y10: ='CF DRIVERS'!Y10 -> 0 | Z10: ='CF DRIVERS'!Z10 -> 0 | AA10: ='CF DRIVERS'!AA10 -> 0 | AB10: ='CF DRIVERS'!AB10 -> 0 | AC10: ='CF DRIVERS'!AC10 -> 0 | AD10: ='CF DRIVERS'!AD10 -> 0 | ... AP10: ='CF DRIVERS'!AP10 -> 0
A11: Stock-Based Compensation | B11: ='YTD CF'!C11-'YTD CF'!B11 -> 2143700 | C11: ='YTD CF'!D11 -> 3575 | D11: ='YTD CF'!E11-'YTD CF'!D11 -> 7593685 | E11: ='YTD CF'!F11-'YTD CF'!E11 -> 5803321 | F11: ='CASH FLOW'!B9-'YTD CF'!F11 -> -13364106 | G11: ='YTD CF'!G11 -> 4310 | H11: ='YTD CF'!H11-'YTD CF'!G11 -> 4207 | I11: ='YTD CF'!I11-'YTD CF'!H11 -> 6263 | J11: ='CASH FLOW'!C9-'YTD CF'!I11 -> 5885 | K11: ='YTD CF'!J11 -> 5507 | L11: ='YTD CF'!K11-'YTD CF'!J11 -> 5735 | M11: ='YTD CF'!L11-'YTD CF'!K11 -> 4979 | N11: ='CASH FLOW'!D9-'YTD CF'!L11 -> 5005 | O11: ='YTD CF'!M11 -> 3563 | P11: ='YTD CF'!N11-'YTD CF'!M11 -> 4746 | Q11: ='YTD CF'!O11-'YTD CF'!N11 -> 5376 | R11: ='CASH FLOW'!E9-'YTD CF'!O11 -> 5906 | S11: ='YTD CF'!P11 -> 5029 | T11: ='YTD CF'!Q11-'YTD CF'!P11 -> 6434 | U11: ='YTD CF'!R11-'YTD CF'!Q11 -> 7384 | V11: ='CASH FLOW'!F9-'YTD CF'!R11 -> 9203 | W11: ='QTR P&L'!W2*'CF DRIVERS'!W11 -> 9158.8574 | X11: ='QTR P&L'!X2*'CF DRIVERS'!X11 -> 9114.9266 | Y11: ='QTR P&L'!Y2*'CF DRIVERS'!Y11 -> 9071.2065 | Z11: ='QTR P&L'!Z2*'CF DRIVERS'!Z11 -> 9027.6961 | AA11: ='QTR P&L'!AA2*'CF DRIVERS'!AA11 -> 8984.3944 | AB11: ='QTR P&L'!AB2*'CF DRIVERS'!AB11 -> 8941.3004 | AC11: ='QTR P&L'!AC2*'CF DRIVERS'!AC11 -> 8898.4131 | AD11: ='QTR P&L'!AD2*'CF DRIVERS'!AD11 -> 8855.7315 | ... AP11: ='QTR P&L'!AP2*'CF DRIVERS'!AP11 -> 8359.2433
A12: Gain on China Transaction | B12: ='YTD CF'!C12-'YTD CF'!B12 -> -407593 | C12: ='YTD CF'!D12 -> 0 | D12: ='YTD CF'!E12-'YTD CF'!D12 -> 0 | E12: ='YTD CF'!F12-'YTD CF'!E12 -> 0 | G12: ='YTD CF'!G12 -> 0 | H12: ='YTD CF'!H12-'YTD CF'!G12 -> 0 | I12: ='YTD CF'!I12-'YTD CF'!H12 -> 0 | K12: ='YTD CF'!J12 -> 0 | L12: ='YTD CF'!K12-'YTD CF'!J12 -> 0 | M12: ='YTD CF'!L12-'YTD CF'!K12 -> 0 | O12: ='YTD CF'!M12 -> 0 | P12: ='YTD CF'!N12-'YTD CF'!M12 -> 0 | Q12: ='YTD CF'!O12-'YTD CF'!N12 -> 0 | S12: ='YTD CF'!P12 -> 0 | T12: ='YTD CF'!Q12-'YTD CF'!P12 -> 0 | U12: ='YTD CF'!R12-'YTD CF'!Q12 -> 0 | W12: ='CF DRIVERS'!W12 -> 0 | X12: ='CF DRIVERS'!X12 -> 0 | Y12: ='CF DRIVERS'!Y12 -> 0 | Z12: ='CF DRIVERS'!Z12 -> 0 | AA12: ='CF DRIVERS'!AA12 -> 0 | AB12: ='CF DRIVERS'!AB12 -> 0 | AC12: ='CF DRIVERS'!AC12 -> 0 | AD12: ='CF DRIVERS'!AD12 -> 0 | ... AP12: ='CF DRIVERS'!AP12 -> 0
A13: Gain (Loss) on Lease Cancellations | B13: ='YTD CF'!C13-'YTD CF'!B13 -> 0 | C13: ='YTD CF'!D13 -> 0 | D13: ='YTD CF'!E13-'YTD CF'!D13 -> 0 | E13: ='YTD CF'!F13-'YTD CF'!E13 -> -14669 | F13: ='CASH FLOW'!B12-'YTD CF'!F13 -> 14641 | G13: ='YTD CF'!G13 -> 0 | H13: ='YTD CF'!H13-'YTD CF'!G13 -> 0 | I13: ='YTD CF'!I13-'YTD CF'!H13 -> 0 | J13: ='CASH FLOW'!C12-'YTD CF'!I13 -> 0 | K13: ='YTD CF'!J13 -> 0 | L13: ='YTD CF'!K13-'YTD CF'!J13 -> 0 | M13: ='YTD CF'!L13-'YTD CF'!K13 -> 0 | N13: ='CASH FLOW'!D12-'YTD CF'!L13 -> 0 | O13: ='YTD CF'!M13 -> 0 | P13: ='YTD CF'!N13-'YTD CF'!M13 -> 0 | Q13: ='YTD CF'!O13-'YTD CF'!N13 -> 0 | R13: ='CASH FLOW'!E12-'YTD CF'!O13 -> 0 | S13: ='YTD CF'!P13 -> 0 | T13: ='YTD CF'!Q13-'YTD CF'!P13 -> 0 | U13: ='YTD CF'!R13-'YTD CF'!Q13 -> 0 | V13: ='CASH FLOW'!F12-'YTD CF'!R13 -> 0 | W13: ='CF DRIVERS'!W13 -> 0 | X13: ='CF DRIVERS'!X13 -> 0 | Y13: ='CF DRIVERS'!Y13 -> 0 | Z13: ='CF DRIVERS'!Z13 -> 0 | AA13: ='CF DRIVERS'!AA13 -> 0 | AB13: ='CF DRIVERS'!AB13 -> 0 | AC13: ='CF DRIVERS'!AC13 -> 0 | AD13: ='CF DRIVERS'!AD13 -> 0 | ... AP13: ='CF DRIVERS'!AP13 -> 0
A14: (Benefit) Provision for Deferred Income Taxes | B14: ='YTD CF'!C14-'YTD CF'!B14 -> 0 | C14: ='YTD CF'!D14 -> 0 | D14: ='YTD CF'!E14-'YTD CF'!D14 -> 0 | E14: ='YTD CF'!F14-'YTD CF'!E14 -> -182156 | F14: ='CASH FLOW'!B10-'YTD CF'!F14 -> 172955 | G14: ='YTD CF'!G14 -> 2561 | H14: ='YTD CF'!H14-'YTD CF'!G14 -> -1489 | I14: ='YTD CF'!I14-'YTD CF'!H14 -> 30257 | J14: ='CASH FLOW'!C10-'YTD CF'!I14 -> -11085 | K14: ='YTD CF'!J14 -> 2873 | L14: ='YTD CF'!K14-'YTD CF'!J14 -> -43917 | M14: ='YTD CF'!L14-'YTD CF'!K14 -> -3259 | N14: ='CASH FLOW'!D10-'YTD CF'!L14 -> 2248 | O14: ='YTD CF'!M14 -> 6450 | P14: ='YTD CF'!N14-'YTD CF'!M14 -> -338 | Q14: ='YTD CF'!O14-'YTD CF'!N14 -> -1385 | R14: ='CASH FLOW'!E10-'YTD CF'!O14 -> -14457 | S14: ='YTD CF'!P14 -> 269 | T14: ='YTD CF'!Q14-'YTD CF'!P14 -> -4430 | U14: ='YTD CF'!R14-'YTD CF'!Q14 -> -67247 | V14: ='CASH FLOW'!F10-'YTD CF'!R14 -> 14072 | W14: ='CF DRIVERS'!W14 -> 14072 | X14: ='CF DRIVERS'!X14 -> 14072 | Y14: ='CF DRIVERS'!Y14 -> 14072 | Z14: ='CF DRIVERS'!Z14 -> 14072 | AA14: ='CF DRIVERS'!AA14 -> 14072 | AB14: ='CF DRIVERS'!AB14 -> 14072 | AC14: ='CF DRIVERS'!AC14 -> 14072 | AD14: ='CF DRIVERS'!AD14 -> 14072 | ... AP14: ='CF DRIVERS'!AP14 -> 14072
A15: Foreign Currency Gain (Loss) | B15: ='YTD CF'!C15-'YTD CF'!B15 -> 0 | C15: ='YTD CF'!D15 -> 0 | D15: ='YTD CF'!E15-'YTD CF'!D15 -> 0 | E15: ='YTD CF'!F15-'YTD CF'!E15 -> -76765 | F15: ='CASH FLOW'!B11-'YTD CF'!F15 -> 77645 | G15: ='YTD CF'!G15 -> 85 | H15: ='YTD CF'!H15-'YTD CF'!G15 -> 517 | I15: ='YTD CF'!I15-'YTD CF'!H15 -> 405 | J15: ='CASH FLOW'!C11-'YTD CF'!I15 -> -524 | K15: ='YTD CF'!J15 -> 69 | L15: ='YTD CF'!K15-'YTD CF'!J15 -> 137 | M15: ='YTD CF'!L15-'YTD CF'!K15 -> 52 | N15: ='CASH FLOW'!D11-'YTD CF'!L15 -> 988 | O15: ='YTD CF'!M15 -> 369 | P15: ='YTD CF'!N15-'YTD CF'!M15 -> 264 | Q15: ='YTD CF'!O15-'YTD CF'!N15 -> -277 | R15: ='CASH FLOW'!E11-'YTD CF'!O15 -> 1378 | S15: ='YTD CF'!P15 -> 0 | T15: ='YTD CF'!Q15-'YTD CF'!P15 -> 0 | U15: ='YTD CF'!R15-'YTD CF'!Q15 -> 0 | V15: ='CASH FLOW'!F11-'YTD CF'!R15 -> 0 | W15: ='CF DRIVERS'!W15 -> 0 | X15: ='CF DRIVERS'!X15 -> 0 | Y15: ='CF DRIVERS'!Y15 -> 0 | Z15: ='CF DRIVERS'!Z15 -> 0 | AA15: ='CF DRIVERS'!AA15 -> 0 | AB15: ='CF DRIVERS'!AB15 -> 0 | AC15: ='CF DRIVERS'!AC15 -> 0 | AD15: ='CF DRIVERS'!AD15 -> 0 | ... AP15: ='CF DRIVERS'!AP15 -> 0
A16: Change in Fair Value of Contingent Consideration | B16: ='YTD CF'!C16-'YTD CF'!B16 -> 0 | C16: ='YTD CF'!D16 -> 0 | D16: ='YTD CF'!E16-'YTD CF'!D16 -> 0 | E16: ='YTD CF'!F16-'YTD CF'!E16 -> 0 | F16: ='CASH FLOW'!B13-'YTD CF'!F16 -> 0 | G16: ='YTD CF'!G16 -> 0 | H16: ='YTD CF'!H16-'YTD CF'!G16 -> 0 | I16: ='YTD CF'!I16-'YTD CF'!H16 -> 0 | J16: ='CASH FLOW'!C13-'YTD CF'!I16 -> 0 | K16: ='YTD CF'!J16 -> 0 | L16: ='YTD CF'!K16-'YTD CF'!J16 -> 0 | M16: ='YTD CF'!L16-'YTD CF'!K16 -> 0 | N16: ='CASH FLOW'!D13-'YTD CF'!L16 -> 0 | O16: ='YTD CF'!M16 -> 0 | P16: ='YTD CF'!N16-'YTD CF'!M16 -> 0 | Q16: ='YTD CF'!O16-'YTD CF'!N16 -> 0 | R16: ='CASH FLOW'!E13-'YTD CF'!O16 -> 0 | S16: ='YTD CF'!P16 -> 0 | T16: ='YTD CF'!Q16-'YTD CF'!P16 -> 13800 | U16: ='YTD CF'!R16-'YTD CF'!Q16 -> 0 | V16: ='CASH FLOW'!F13-'YTD CF'!R16 -> 0 | W16: ='CF DRIVERS'!W16 -> 0 | X16: ='CF DRIVERS'!X16 -> 0 | Y16: ='CF DRIVERS'!Y16 -> 0 | Z16: ='CF DRIVERS'!Z16 -> 0 | AA16: ='CF DRIVERS'!AA16 -> 0 | AB16: ='CF DRIVERS'!AB16 -> 0 | AC16: ='CF DRIVERS'!AC16 -> 0 | AD16: ='CF DRIVERS'!AD16 -> 0 | ... AP16: ='CF DRIVERS'!AP16 -> 0
A17: Gain (Loss) on Extinguishment of Debt | B17: ='YTD CF'!C17-'YTD CF'!B17 -> 0 | C17: ='YTD CF'!D17 -> 0 | D17: ='YTD CF'!E17-'YTD CF'!D17 -> 0 | E17: ='YTD CF'!F17-'YTD CF'!E17 -> 0 | F17: ='CASH FLOW'!B14-'YTD CF'!F17 -> 0 | G17: ='YTD CF'!G17 -> 0 | H17: ='YTD CF'!H17-'YTD CF'!G17 -> 0 | I17: ='YTD CF'!I17-'YTD CF'!H17 -> 0 | J17: ='CASH FLOW'!C14-'YTD CF'!I17 -> 0 | K17: ='YTD CF'!J17 -> 0 | L17: ='YTD CF'!K17-'YTD CF'!J17 -> 0 | M17: ='YTD CF'!L17-'YTD CF'!K17 -> 0 | N17: ='CASH FLOW'!D14-'YTD CF'!L17 -> 0 | O17: ='YTD CF'!M17 -> 0 | P17: ='YTD CF'!N17-'YTD CF'!M17 -> 0 | Q17: ='YTD CF'!O17-'YTD CF'!N17 -> 0 | R17: ='CASH FLOW'!E14-'YTD CF'!O17 -> 0 | S17: ='YTD CF'!P17 -> 0 | T17: ='YTD CF'!Q17-'YTD CF'!P17 -> 0 | U17: ='YTD CF'!R17-'YTD CF'!Q17 -> 0 | V17: ='CASH FLOW'!F14-'YTD CF'!R17 -> 6003 | W17: ='CF DRIVERS'!W17 -> 0 | X17: ='CF DRIVERS'!X17 -> 0 | Y17: ='CF DRIVERS'!Y17 -> 0 | Z17: ='CF DRIVERS'!Z17 -> 0 | AA17: ='CF DRIVERS'!AA17 -> 0 | AB17: ='CF DRIVERS'!AB17 -> 0 | AC17: ='CF DRIVERS'!AC17 -> 0 | AD17: ='CF DRIVERS'!AD17 -> 0 | ... AP17: ='CF DRIVERS'!AP17 -> 0
A18: Other Operating Items | B18: ='YTD CF'!C18-'YTD CF'!B18 -> 43259 | C18: ='YTD CF'!D18 -> 0 | D18: ='YTD CF'!E18-'YTD CF'!D18 -> 0 | E18: ='YTD CF'!F18-'YTD CF'!E18 -> -185716 | F18: ='CASH FLOW'!B15-'YTD CF'!F18 -> 185716 | G18: ='YTD CF'!G18 -> 0 | H18: ='YTD CF'!H18-'YTD CF'!G18 -> 0 | I18: ='YTD CF'!I18-'YTD CF'!H18 -> 56 | J18: ='CASH FLOW'!C15-'YTD CF'!I18 -> -19 | K18: ='YTD CF'!J18 -> -4 | L18: ='YTD CF'!K18-'YTD CF'!J18 -> 12 | M18: ='YTD CF'!L18-'YTD CF'!K18 -> -10 | N18: ='CASH FLOW'!D15-'YTD CF'!L18 -> -26 | O18: ='YTD CF'!M18 -> -7672 | P18: ='YTD CF'!N18-'YTD CF'!M18 -> 7672 | Q18: ='YTD CF'!O18-'YTD CF'!N18 -> 0 | R18: ='CASH FLOW'!E15-'YTD CF'!O18 -> -324 | S18: ='YTD CF'!P18 -> -1014 | T18: ='YTD CF'!Q18-'YTD CF'!P18 -> 757 | U18: ='YTD CF'!R18-'YTD CF'!Q18 -> 2221 | V18: ='CASH FLOW'!F15-'YTD CF'!R18 -> -3651 | W18: ='CF DRIVERS'!W18 -> -262460.61 | X18: ='CF DRIVERS'!X18 -> 1619.5835 | Y18: ='CF DRIVERS'!Y18 -> 1611.8151 | Z18: ='CF DRIVERS'!Z18 -> 1604.0839 | AA18: ='CF DRIVERS'!AA18 -> 1596.3899 | AB18: ='CF DRIVERS'!AB18 -> 1588.7327 | AC18: ='CF DRIVERS'!AC18 -> 1581.1123 | AD18: ='CF DRIVERS'!AD18 -> 1573.5284 | ... AP18: ='CF DRIVERS'!AP18 -> 1485.3101
A19: Accounts Receivable | B19: ='YTD CF'!C19-'YTD CF'!B19 -> -4362889 | C19: ='YTD CF'!D19 -> -9234 | D19: ='YTD CF'!E19-'YTD CF'!D19 -> -18257982 | E19: ='YTD CF'!F19-'YTD CF'!E19 -> -10039888 | F19: ='CASH FLOW'!B16-'YTD CF'!F19 -> 28281855 | G19: ='YTD CF'!G19 -> -34420 | H19: ='YTD CF'!H19-'YTD CF'!G19 -> 6500 | I19: ='YTD CF'!I19-'YTD CF'!H19 -> -51047 | J19: ='CASH FLOW'!C16-'YTD CF'!I19 -> 52598 | K19: ='YTD CF'!J19 -> -109639 | L19: ='YTD CF'!K19-'YTD CF'!J19 -> -25961 | M19: ='YTD CF'!L19-'YTD CF'!K19 -> -17671 | N19: ='CASH FLOW'!D16-'YTD CF'!L19 -> 31713 | O19: ='YTD CF'!M19 -> -18664 | P19: ='YTD CF'!N19-'YTD CF'!M19 -> -63549 | Q19: ='YTD CF'!O19-'YTD CF'!N19 -> 55684 | R19: ='CASH FLOW'!E16-'YTD CF'!O19 -> -63136 | S19: ='YTD CF'!P19 -> 11841 | T19: ='YTD CF'!Q19-'YTD CF'!P19 -> -154994 | U19: ='YTD CF'!R19-'YTD CF'!Q19 -> -20980 | V19: ='CASH FLOW'!F16-'YTD CF'!R19 -> -247958 | W19: ='CF DRIVERS'!W19 -> 3623.7812 | X19: ='CF DRIVERS'!X19 -> 3606.3996 | Y19: ='CF DRIVERS'!Y19 -> 3589.1014 | Z19: ='CF DRIVERS'!Z19 -> 3571.8861 | AA19: ='CF DRIVERS'!AA19 -> 3554.7534 | AB19: ='CF DRIVERS'!AB19 -> 3537.7029 | AC19: ='CF DRIVERS'!AC19 -> 3520.7342 | AD19: ='CF DRIVERS'!AD19 -> 3503.8468 | ... AP19: ='CF DRIVERS'!AP19 -> 3307.407
A20: Note Receivable | B20: ='YTD CF'!C20-'YTD CF'!B20 -> 0 | C20: ='YTD CF'!D20 -> 0 | D20: ='YTD CF'!E20-'YTD CF'!D20 -> 0 | E20: ='YTD CF'!F20-'YTD CF'!E20 -> 0 | F20: ='CASH FLOW'!B17-'YTD CF'!F20 -> 0 | G20: ='YTD CF'!G20 -> 0 | H20: ='YTD CF'!H20-'YTD CF'!G20 -> 0 | I20: ='YTD CF'!I20-'YTD CF'!H20 -> 0 | J20: ='CASH FLOW'!C17-'YTD CF'!I20 -> 0 | K20: ='YTD CF'!J20 -> 0 | L20: ='YTD CF'!K20-'YTD CF'!J20 -> 0 | M20: ='YTD CF'!L20-'YTD CF'!K20 -> 0 | N20: ='CASH FLOW'!D17-'YTD CF'!L20 -> 0 | O20: ='YTD CF'!M20 -> 0 | P20: ='YTD CF'!N20-'YTD CF'!M20 -> 0 | Q20: ='YTD CF'!O20-'YTD CF'!N20 -> 0 | R20: ='CASH FLOW'!E17-'YTD CF'!O20 -> 2318 | S20: ='YTD CF'!P20 -> 0 | T20: ='YTD CF'!Q20-'YTD CF'!P20 -> 0 | U20: ='YTD CF'!R20-'YTD CF'!Q20 -> 0 | V20: ='CASH FLOW'!F17-'YTD CF'!R20 -> 0 | W20: ='CF DRIVERS'!W20 -> 0 | X20: ='CF DRIVERS'!X20 -> 0 | Y20: ='CF DRIVERS'!Y20 -> 0 | Z20: ='CF DRIVERS'!Z20 -> 0 | AA20: ='CF DRIVERS'!AA20 -> 0 | AB20: ='CF DRIVERS'!AB20 -> 0 | AC20: ='CF DRIVERS'!AC20 -> 0 | AD20: ='CF DRIVERS'!AD20 -> 0 | ... AP20: ='CF DRIVERS'!AP20 -> 0
A21: Inventories | B21: ='YTD CF'!C21-'YTD CF'!B21 -> 7484034 | C21: ='YTD CF'!D21 -> -19242 | D21: ='YTD CF'!E21-'YTD CF'!D21 -> -46663808 | E21: ='YTD CF'!F21-'YTD CF'!E21 -> -57237007 | F21: ='CASH FLOW'!B18-'YTD CF'!F21 -> 103744883 | G21: ='YTD CF'!G21 -> 4531 | H21: ='YTD CF'!H21-'YTD CF'!G21 -> 24222 | I21: ='YTD CF'!I21-'YTD CF'!H21 -> 7458 | J21: ='CASH FLOW'!C18-'YTD CF'!I21 -> -24409 | K21: ='YTD CF'!J21 -> 17338 | L21: ='YTD CF'!K21-'YTD CF'!J21 -> 7294 | M21: ='YTD CF'!L21-'YTD CF'!K21 -> -52724 | N21: ='CASH FLOW'!D18-'YTD CF'!L21 -> -35207 | O21: ='YTD CF'!M21 -> 29386 | P21: ='YTD CF'!N21-'YTD CF'!M21 -> 7666 | Q21: ='YTD CF'!O21-'YTD CF'!N21 -> -22467 | R21: ='CASH FLOW'!E18-'YTD CF'!O21 -> 62605 | S21: ='YTD CF'!P21 -> 4794 | T21: ='YTD CF'!Q21-'YTD CF'!P21 -> 18245 | U21: ='YTD CF'!R21-'YTD CF'!Q21 -> 8093 | V21: ='CASH FLOW'!F18-'YTD CF'!R21 -> -160909 | W21: ='CF DRIVERS'!W21 -> 1619.782 | X21: ='CF DRIVERS'!X21 -> 1612.0126 | Y21: ='CF DRIVERS'!Y21 -> 1604.2806 | Z21: ='CF DRIVERS'!Z21 -> 1596.5856 | AA21: ='CF DRIVERS'!AA21 -> 1588.9275 | AB21: ='CF DRIVERS'!AB21 -> 1581.3061 | AC21: ='CF DRIVERS'!AC21 -> 1573.7213 | AD21: ='CF DRIVERS'!AD21 -> 1566.1729 | ... AP21: ='CF DRIVERS'!AP21 -> 1478.3669
A22: Prepaid Expenses | B22: ='YTD CF'!C22-'YTD CF'!B22 -> -419333 | C22: ='YTD CF'!D22 -> -2557 | D22: ='YTD CF'!E22-'YTD CF'!D22 -> -8115162 | E22: ='YTD CF'!F22-'YTD CF'!E22 -> -84869 | F22: ='CASH FLOW'!B19-'YTD CF'!F22 -> 8203660 | G22: ='YTD CF'!G22 -> 3513 | H22: ='YTD CF'!H22-'YTD CF'!G22 -> -2256 | I22: ='YTD CF'!I22-'YTD CF'!H22 -> 202 | J22: ='CASH FLOW'!C19-'YTD CF'!I22 -> 755 | K22: ='YTD CF'!J22 -> -4166 | L22: ='YTD CF'!K22-'YTD CF'!J22 -> -7892 | M22: ='YTD CF'!L22-'YTD CF'!K22 -> -348 | N22: ='CASH FLOW'!D19-'YTD CF'!L22 -> 4426 | O22: ='YTD CF'!M22 -> -2076 | P22: ='YTD CF'!N22-'YTD CF'!M22 -> -1393 | Q22: ='YTD CF'!O22-'YTD CF'!N22 -> -16792 | R22: ='CASH FLOW'!E19-'YTD CF'!O22 -> 21335 | S22: ='YTD CF'!P22 -> -3687 | T22: ='YTD CF'!Q22-'YTD CF'!P22 -> -16958 | U22: ='YTD CF'!R22-'YTD CF'!Q22 -> -122275 | V22: ='CASH FLOW'!F19-'YTD CF'!R22 -> 34599 | W22: ='CF DRIVERS'!W22 -> 617.82314 | X22: ='CF DRIVERS'!X22 -> 614.85973 | Y22: ='CF DRIVERS'!Y22 -> 611.91053 | Z22: ='CF DRIVERS'!Z22 -> 608.97548 | AA22: ='CF DRIVERS'!AA22 -> 606.0545 | AB22: ='CF DRIVERS'!AB22 -> 603.14754 | AC22: ='CF DRIVERS'!AC22 -> 600.25452 | AD22: ='CF DRIVERS'!AD22 -> 597.37537 | ... AP22: ='CF DRIVERS'!AP22 -> 563.88409
A23: Change in A/P and Accrued (legacy) | B23: ='YTD CF'!C23-'YTD CF'!B23 -> -2031690 | C23: ='YTD CF'!D23 -> 12113 | D23: ='YTD CF'!E23-'YTD CF'!D23 -> 27567210 | E23: ='YTD CF'!F23-'YTD CF'!E23 -> 39115245 | G23: ='YTD CF'!G23 -> 17742 | H23: ='YTD CF'!H23-'YTD CF'!G23 -> -7406 | I23: ='YTD CF'!I23-'YTD CF'!H23 -> 41126 | K23: ='YTD CF'!J23 -> 182 | L23: ='YTD CF'!K23-'YTD CF'!J23 -> -12673 | M23: ='YTD CF'!L23-'YTD CF'!K23 -> 27143 | O23: ='YTD CF'!M23 -> 0 | P23: ='YTD CF'!N23-'YTD CF'!M23 -> 0 | Q23: ='YTD CF'!O23-'YTD CF'!N23 -> 0 | S23: ='YTD CF'!P23 -> 0 | T23: ='YTD CF'!Q23-'YTD CF'!P23 -> 0 | U23: ='YTD CF'!R23-'YTD CF'!Q23 -> 0 | W23: ='CF DRIVERS'!W23 -> 0 | X23: ='CF DRIVERS'!X23 -> 0 | Y23: ='CF DRIVERS'!Y23 -> 0 | Z23: ='CF DRIVERS'!Z23 -> 0 | AA23: ='CF DRIVERS'!AA23 -> 0 | AB23: ='CF DRIVERS'!AB23 -> 0 | AC23: ='CF DRIVERS'!AC23 -> 0 | AD23: ='CF DRIVERS'!AD23 -> 0 | ... AP23: ='CF DRIVERS'!AP23 -> 0
A24: Other Non-Current Assets | B24: ='YTD CF'!C24-'YTD CF'!B24 -> 0 | C24: ='YTD CF'!D24 -> 0 | D24: ='YTD CF'!E24-'YTD CF'!D24 -> 0 | E24: ='YTD CF'!F24-'YTD CF'!E24 -> 0 | F24: ='CASH FLOW'!B20-'YTD CF'!F24 -> 0 | G24: ='YTD CF'!G24 -> 0 | H24: ='YTD CF'!H24-'YTD CF'!G24 -> 0 | I24: ='YTD CF'!I24-'YTD CF'!H24 -> 0 | J24: ='CASH FLOW'!C20-'YTD CF'!I24 -> 0 | K24: ='YTD CF'!J24 -> 0 | L24: ='YTD CF'!K24-'YTD CF'!J24 -> 0 | M24: ='YTD CF'!L24-'YTD CF'!K24 -> 0 | N24: ='CASH FLOW'!D20-'YTD CF'!L24 -> 0 | O24: ='YTD CF'!M24 -> 0 | P24: ='YTD CF'!N24-'YTD CF'!M24 -> -6362 | Q24: ='YTD CF'!O24-'YTD CF'!N24 -> 1059 | R24: ='CASH FLOW'!E20-'YTD CF'!O24 -> 441 | S24: ='YTD CF'!P24 -> -1700 | T24: ='YTD CF'!Q24-'YTD CF'!P24 -> 2442 | U24: ='YTD CF'!R24-'YTD CF'!Q24 -> 769 | V24: ='CASH FLOW'!F20-'YTD CF'!R24 -> 1346 | W24: ='CF DRIVERS'!W24 -> 208.33292 | X24: ='CF DRIVERS'!X24 -> 207.33365 | Y24: ='CF DRIVERS'!Y24 -> 206.33916 | Z24: ='CF DRIVERS'!Z24 -> 205.34945 | AA24: ='CF DRIVERS'!AA24 -> 204.36448 | AB24: ='CF DRIVERS'!AB24 -> 203.38424 | AC24: ='CF DRIVERS'!AC24 -> 202.4087 | AD24: ='CF DRIVERS'!AD24 -> 201.43784 | ... AP24: ='CF DRIVERS'!AP24 -> 190.14441
A25: Accounts Payable | B25: ='YTD CF'!C25-'YTD CF'!B25 -> 0 | C25: ='YTD CF'!D25 -> 0 | D25: ='YTD CF'!E25-'YTD CF'!D25 -> 0 | E25: ='YTD CF'!F25-'YTD CF'!E25 -> 0 | F25: ='CASH FLOW'!B21-'YTD CF'!F25 -> 23966 | G25: ='YTD CF'!G25 -> 0 | H25: ='YTD CF'!H25-'YTD CF'!G25 -> 0 | I25: ='YTD CF'!I25-'YTD CF'!H25 -> 0 | J25: ='CASH FLOW'!C21-'YTD CF'!I25 -> 428 | K25: ='YTD CF'!J25 -> 0 | L25: ='YTD CF'!K25-'YTD CF'!J25 -> 0 | M25: ='YTD CF'!L25-'YTD CF'!K25 -> 0 | N25: ='CASH FLOW'!D21-'YTD CF'!L25 -> 5249 | O25: ='YTD CF'!M25 -> -3013 | P25: ='YTD CF'!N25-'YTD CF'!M25 -> 6963 | Q25: ='YTD CF'!O25-'YTD CF'!N25 -> -16209 | R25: ='CASH FLOW'!E21-'YTD CF'!O25 -> 11089 | S25: ='YTD CF'!P25 -> 11679 | T25: ='YTD CF'!Q25-'YTD CF'!P25 -> 9110 | U25: ='YTD CF'!R25-'YTD CF'!Q25 -> -16708 | V25: ='CASH FLOW'!F21-'YTD CF'!R25 -> 47171 | W25: ='CF DRIVERS'!W25 -> -661.58677 | X25: ='CF DRIVERS'!X25 -> -658.41345 | Y25: ='CF DRIVERS'!Y25 -> -655.25534 | Z25: ='CF DRIVERS'!Z25 -> -652.11238 | AA25: ='CF DRIVERS'!AA25 -> -648.9845 | AB25: ='CF DRIVERS'!AB25 -> -645.87162 | AC25: ='CF DRIVERS'!AC25 -> -642.77367 | AD25: ='CF DRIVERS'!AD25 -> -639.69058 | ... AP25: ='CF DRIVERS'!AP25 -> -603.82694
A26: Accrued Expenses | B26: ='YTD CF'!C26-'YTD CF'!B26 -> 0 | C26: ='YTD CF'!D26 -> 0 | D26: ='YTD CF'!E26-'YTD CF'!D26 -> 0 | E26: ='YTD CF'!F26-'YTD CF'!E26 -> 0 | F26: ='CASH FLOW'!B22-'YTD CF'!F26 -> 26484 | G26: ='YTD CF'!G26 -> 0 | H26: ='YTD CF'!H26-'YTD CF'!G26 -> 0 | I26: ='YTD CF'!I26-'YTD CF'!H26 -> 0 | J26: ='CASH FLOW'!C22-'YTD CF'!I26 -> 34644 | K26: ='YTD CF'!J26 -> 0 | L26: ='YTD CF'!K26-'YTD CF'!J26 -> 0 | M26: ='YTD CF'!L26-'YTD CF'!K26 -> 0 | N26: ='CASH FLOW'!D22-'YTD CF'!L26 -> -8025 | O26: ='YTD CF'!M26 -> 1998 | P26: ='YTD CF'!N26-'YTD CF'!M26 -> 15762 | Q26: ='YTD CF'!O26-'YTD CF'!N26 -> -6609 | R26: ='CASH FLOW'!E22-'YTD CF'!O26 -> 74247 | S26: ='YTD CF'!P26 -> -8673 | T26: ='YTD CF'!Q26-'YTD CF'!P26 -> 1660 | U26: ='YTD CF'!R26-'YTD CF'!Q26 -> 39974 | V26: ='CASH FLOW'!F22-'YTD CF'!R26 -> 12657 | W26: ='CF DRIVERS'!W26 -> -1106.6625 | X26: ='CF DRIVERS'!X26 -> -1101.3544 | Y26: ='CF DRIVERS'!Y26 -> -1096.0717 | Z26: ='CF DRIVERS'!Z26 -> -1090.8143 | AA26: ='CF DRIVERS'!AA26 -> -1085.5822 | AB26: ='CF DRIVERS'!AB26 -> -1080.3752 | AC26: ='CF DRIVERS'!AC26 -> -1075.1931 | AD26: ='CF DRIVERS'!AD26 -> -1070.0359 | ... AP26: ='CF DRIVERS'!AP26 -> -1010.0453
A27: Change in Income Taxes | B27: ='YTD CF'!C27-'YTD CF'!B27 -> 0 | C27: ='YTD CF'!D27 -> 0 | D27: ='YTD CF'!E27-'YTD CF'!D27 -> 0 | E27: ='YTD CF'!F27-'YTD CF'!E27 -> 0 | F27: ='CASH FLOW'!B23-'YTD CF'!F27 -> 1357 | G27: ='YTD CF'!G27 -> 0 | H27: ='YTD CF'!H27-'YTD CF'!G27 -> 0 | I27: ='YTD CF'!I27-'YTD CF'!H27 -> 0 | J27: ='CASH FLOW'!C23-'YTD CF'!I27 -> -164 | K27: ='YTD CF'!J27 -> 0 | L27: ='YTD CF'!K27-'YTD CF'!J27 -> 57605 | M27: ='YTD CF'!L27-'YTD CF'!K27 -> 57 | N27: ='CASH FLOW'!D23-'YTD CF'!L27 -> -9560 | O27: ='YTD CF'!M27 -> 8250 | P27: ='YTD CF'!N27-'YTD CF'!M27 -> -53228 | Q27: ='YTD CF'!O27-'YTD CF'!N27 -> -4653 | R27: ='CASH FLOW'!E23-'YTD CF'!O27 -> 10095 | S27: ='YTD CF'!P27 -> 15353 | T27: ='YTD CF'!Q27-'YTD CF'!P27 -> -4425 | U27: ='YTD CF'!R27-'YTD CF'!Q27 -> 27814 | V27: ='CASH FLOW'!F23-'YTD CF'!R27 -> 8 | W27: ='CF DRIVERS'!W27 -> -237.96595 | X27: ='CF DRIVERS'!X27 -> -236.82453 | Y27: ='CF DRIVERS'!Y27 -> -235.6886 | Z27: ='CF DRIVERS'!Z27 -> -234.55811 | AA27: ='CF DRIVERS'!AA27 -> -233.43304 | AB27: ='CF DRIVERS'!AB27 -> -232.31337 | AC27: ='CF DRIVERS'!AC27 -> -231.19907 | AD27: ='CF DRIVERS'!AD27 -> -230.09011 | ... AP27: ='CF DRIVERS'!AP27 -> -217.19033
A28: Accrued Promotional Allowance | B28: ='YTD CF'!C28-'YTD CF'!B28 -> 0 | C28: ='YTD CF'!D28 -> 0 | D28: ='YTD CF'!E28-'YTD CF'!D28 -> 0 | E28: ='YTD CF'!F28-'YTD CF'!E28 -> 0 | F28: ='CASH FLOW'!B24-'YTD CF'!F28 -> 13379 | G28: ='YTD CF'!G28 -> 0 | H28: ='YTD CF'!H28-'YTD CF'!G28 -> 0 | I28: ='YTD CF'!I28-'YTD CF'!H28 -> 0 | J28: ='CASH FLOW'!C24-'YTD CF'!I28 -> 16940 | K28: ='YTD CF'!J28 -> 32248 | L28: ='YTD CF'!K28-'YTD CF'!J28 -> 30747 | M28: ='YTD CF'!L28-'YTD CF'!K28 -> 37585 | N28: ='CASH FLOW'!D24-'YTD CF'!L28 -> -36770 | O28: ='YTD CF'!M28 -> 29414 | P28: ='YTD CF'!N28-'YTD CF'!M28 -> 27278 | Q28: ='YTD CF'!O28-'YTD CF'!N28 -> 2331 | R28: ='CASH FLOW'!E24-'YTD CF'!O28 -> -22862 | S28: ='YTD CF'!P28 -> 15379 | T28: ='YTD CF'!Q28-'YTD CF'!P28 -> 48842 | U28: ='YTD CF'!R28-'YTD CF'!Q28 -> 19055 | V28: ='CASH FLOW'!F24-'YTD CF'!R28 -> 70359 | W28: ='CF DRIVERS'!W28 -> -1476.9602 | X28: ='CF DRIVERS'!X28 -> -1469.8759 | Y28: ='CF DRIVERS'!Y28 -> -1462.8256 | Z28: ='CF DRIVERS'!Z28 -> -1455.8091 | AA28: ='CF DRIVERS'!AA28 -> -1448.8263 | AB28: ='CF DRIVERS'!AB28 -> -1441.8769 | AC28: ='CF DRIVERS'!AC28 -> -1434.9609 | AD28: ='CF DRIVERS'!AD28 -> -1428.078 | ... AP28: ='CF DRIVERS'!AP28 -> -1348.0142
A29: Accrued Distributor Termination | B29: ='YTD CF'!C29-'YTD CF'!B29 -> 0 | C29: ='YTD CF'!D29 -> 0 | D29: ='YTD CF'!E29-'YTD CF'!D29 -> 0 | E29: ='YTD CF'!F29-'YTD CF'!E29 -> 0 | F29: ='CASH FLOW'!B25-'YTD CF'!F29 -> 0 | G29: ='YTD CF'!G29 -> 0 | H29: ='YTD CF'!H29-'YTD CF'!G29 -> 0 | I29: ='YTD CF'!I29-'YTD CF'!H29 -> 115551 | J29: ='CASH FLOW'!C25-'YTD CF'!I29 -> -111565 | K29: ='YTD CF'!J29 -> -2923 | L29: ='YTD CF'!K29-'YTD CF'!J29 -> -1063 | M29: ='YTD CF'!L29-'YTD CF'!K29 -> 0 | N29: ='CASH FLOW'!D25-'YTD CF'!L29 -> 247 | O29: ='YTD CF'!M29 -> -248 | P29: ='YTD CF'!N29-'YTD CF'!M29 -> 0 | Q29: ='YTD CF'!O29-'YTD CF'!N29 -> 0 | R29: ='CASH FLOW'!E25-'YTD CF'!O29 -> 0 | S29: ='YTD CF'!P29 -> 0 | T29: ='YTD CF'!Q29-'YTD CF'!P29 -> 0 | U29: ='YTD CF'!R29-'YTD CF'!Q29 -> 252953 | V29: ='CASH FLOW'!F25-'YTD CF'!R29 -> 4642 | W29: ='CF DRIVERS'!W29 -> 0 | X29: ='CF DRIVERS'!X29 -> 0 | Y29: ='CF DRIVERS'!Y29 -> 0 | Z29: ='CF DRIVERS'!Z29 -> 0 | AA29: ='CF DRIVERS'!AA29 -> 0 | AB29: ='CF DRIVERS'!AB29 -> 0 | AC29: ='CF DRIVERS'!AC29 -> 0 | AD29: ='CF DRIVERS'!AD29 -> 0 | ... AP29: ='CF DRIVERS'!AP29 -> 0
A30: Other Current Liabilities | B30: ='YTD CF'!C30-'YTD CF'!B30 -> -109313 | C30: ='YTD CF'!D30 -> 174 | D30: ='YTD CF'!E30-'YTD CF'!D30 -> 339778 | E30: ='YTD CF'!F30-'YTD CF'!E30 -> -339952 | F30: ='CASH FLOW'!B26-'YTD CF'!F30 -> 374 | G30: ='YTD CF'!G30 -> 765 | H30: ='YTD CF'!H30-'YTD CF'!G30 -> 1055 | I30: ='YTD CF'!I30-'YTD CF'!H30 -> 471 | J30: ='CASH FLOW'!C26-'YTD CF'!I30 -> 319 | K30: ='YTD CF'!J30 -> 1508 | L30: ='YTD CF'!K30-'YTD CF'!J30 -> 2015 | M30: ='YTD CF'!L30-'YTD CF'!K30 -> 1716 | N30: ='CASH FLOW'!D26-'YTD CF'!L30 -> 2066 | O30: ='YTD CF'!M30 -> 2094 | P30: ='YTD CF'!N30-'YTD CF'!M30 -> 790 | Q30: ='YTD CF'!O30-'YTD CF'!N30 -> 1210 | R30: ='CASH FLOW'!E26-'YTD CF'!O30 -> 826 | S30: ='YTD CF'!P30 -> -1648 | T30: ='YTD CF'!Q30-'YTD CF'!P30 -> 3647 | U30: ='YTD CF'!R30-'YTD CF'!Q30 -> 1692 | V30: ='CASH FLOW'!F26-'YTD CF'!R30 -> 6246 | W30: ='CF DRIVERS'!W30 -> -174.90583 | X30: ='CF DRIVERS'!X30 -> -174.06689 | Y30: ='CF DRIVERS'!Y30 -> -173.23197 | Z30: ='CF DRIVERS'!Z30 -> -172.40106 | AA30: ='CF DRIVERS'!AA30 -> -171.57413 | AB30: ='CF DRIVERS'!AB30 -> -170.75117 | AC30: ='CF DRIVERS'!AC30 -> -169.93215 | AD30: ='CF DRIVERS'!AD30 -> -169.11707 | ... AP30: ='CF DRIVERS'!AP30 -> -159.63568
A31: ROU & Lease Liability, Net | B31: ='YTD CF'!C31-'YTD CF'!B31 -> 3883 | C31: ='YTD CF'!D31 -> -5 | D31: ='YTD CF'!E31-'YTD CF'!D31 -> 7975 | E31: ='YTD CF'!F31-'YTD CF'!E31 -> 22495 | F31: ='CASH FLOW'!B27-'YTD CF'!F31 -> -30436 | G31: ='YTD CF'!G31 -> -78 | H31: ='YTD CF'!H31-'YTD CF'!G31 -> -17 | I31: ='YTD CF'!I31-'YTD CF'!H31 -> -31 | J31: ='CASH FLOW'!C27-'YTD CF'!I31 -> -57 | K31: ='YTD CF'!J31 -> -15 | L31: ='YTD CF'!K31-'YTD CF'!J31 -> -23 | M31: ='YTD CF'!L31-'YTD CF'!K31 -> -26 | N31: ='CASH FLOW'!D27-'YTD CF'!L31 -> -38 | O31: ='YTD CF'!M31 -> -23 | P31: ='YTD CF'!N31-'YTD CF'!M31 -> -11 | Q31: ='YTD CF'!O31-'YTD CF'!N31 -> 51 | R31: ='CASH FLOW'!E27-'YTD CF'!O31 -> 518 | S31: ='YTD CF'!P31 -> 0 | T31: ='YTD CF'!Q31-'YTD CF'!P31 -> 0 | U31: ='YTD CF'!R31-'YTD CF'!Q31 -> 0 | V31: ='CASH FLOW'!F27-'YTD CF'!R31 -> 0 | W31: ='CF DRIVERS'!W31 -> 0 | X31: ='CF DRIVERS'!X31 -> 0 | Y31: ='CF DRIVERS'!Y31 -> 0 | Z31: ='CF DRIVERS'!Z31 -> 0 | AA31: ='CF DRIVERS'!AA31 -> 0 | AB31: ='CF DRIVERS'!AB31 -> 0 | AC31: ='CF DRIVERS'!AC31 -> 0 | AD31: ='CF DRIVERS'!AD31 -> 0 | ... AP31: ='CF DRIVERS'!AP31 -> 0
A32: Deferred Revenue | B32: ='YTD CF'!C32-'YTD CF'!B32 -> 0 | C32: ='YTD CF'!D32 -> 0 | D32: ='YTD CF'!E32-'YTD CF'!D32 -> 0 | E32: ='YTD CF'!F32-'YTD CF'!E32 -> 0 | F32: ='CASH FLOW'!B28-'YTD CF'!F32 -> 0 | G32: ='YTD CF'!G32 -> 0 | H32: ='YTD CF'!H32-'YTD CF'!G32 -> 0 | I32: ='YTD CF'!I32-'YTD CF'!H32 -> 154103 | J32: ='CASH FLOW'!C28-'YTD CF'!I32 -> 35360 | K32: ='YTD CF'!J32 -> -4625 | L32: ='YTD CF'!K32-'YTD CF'!J32 -> -3594 | M32: ='YTD CF'!L32-'YTD CF'!K32 -> -2374 | N32: ='CASH FLOW'!D28-'YTD CF'!L32 -> -2130 | O32: ='YTD CF'!M32 -> -2378 | P32: ='YTD CF'!N32-'YTD CF'!M32 -> -2379 | Q32: ='YTD CF'!O32-'YTD CF'!N32 -> -2378 | R32: ='CASH FLOW'!E28-'YTD CF'!O32 -> -2378 | S32: ='YTD CF'!P32 -> -2378 | T32: ='YTD CF'!Q32-'YTD CF'!P32 -> -4942 | U32: ='YTD CF'!R32-'YTD CF'!Q32 -> 240783 | V32: ='CASH FLOW'!F28-'YTD CF'!R32 -> 21647 | W32: ='CF DRIVERS'!W32 -> 0 | X32: ='CF DRIVERS'!X32 -> 0 | Y32: ='CF DRIVERS'!Y32 -> 0 | Z32: ='CF DRIVERS'!Z32 -> 0 | AA32: ='CF DRIVERS'!AA32 -> 0 | AB32: ='CF DRIVERS'!AB32 -> 0 | AC32: ='CF DRIVERS'!AC32 -> 0 | AD32: ='CF DRIVERS'!AD32 -> 0 | ... AP32: ='CF DRIVERS'!AP32 -> 0
A33: Net Change in Other Working Capital | B33: ='YTD CF'!C33-'YTD CF'!B33 -> 213764 | C33: ='YTD CF'!D33 -> 0 | D33: ='YTD CF'!E33-'YTD CF'!D33 -> 0 | E33: ='YTD CF'!F33-'YTD CF'!E33 -> 532395 | F33: ='CASH FLOW'!B29-'YTD CF'!F33 -> -532395 | G33: ='YTD CF'!G33 -> 0 | H33: ='YTD CF'!H33-'YTD CF'!G33 -> 488 | I33: ='YTD CF'!I33-'YTD CF'!H33 -> -488 | J33: ='CASH FLOW'!C29-'YTD CF'!I33 -> 0 | K33: ='YTD CF'!J33 -> 0 | L33: ='YTD CF'!K33-'YTD CF'!J33 -> 0 | M33: ='YTD CF'!L33-'YTD CF'!K33 -> 0 | N33: ='CASH FLOW'!D29-'YTD CF'!L33 -> 0 | O33: ='YTD CF'!M33 -> 0 | P33: ='YTD CF'!N33-'YTD CF'!M33 -> 0 | Q33: ='YTD CF'!O33-'YTD CF'!N33 -> 0 | R33: ='CASH FLOW'!E29-'YTD CF'!O33 -> 0 | S33: ='YTD CF'!P33 -> 148 | T33: ='YTD CF'!Q33-'YTD CF'!P33 -> -1358 | U33: ='YTD CF'!R33-'YTD CF'!Q33 -> -576 | V33: ='CASH FLOW'!F29-'YTD CF'!R33 -> 4267 | W33: ='CF DRIVERS'!W33 -> 0 | X33: ='CF DRIVERS'!X33 -> 0 | Y33: ='CF DRIVERS'!Y33 -> 0 | Z33: ='CF DRIVERS'!Z33 -> 0 | AA33: ='CF DRIVERS'!AA33 -> 0 | AB33: ='CF DRIVERS'!AB33 -> 0 | AC33: ='CF DRIVERS'!AC33 -> 0 | AD33: ='CF DRIVERS'!AD33 -> 0 | ... AP33: ='CF DRIVERS'!AP33 -> 0
A34: Cash Flow from Operations | B34: ='YTD CF'!C34-'YTD CF'!B34 -> 8089588 | C34: ='YTD CF'!D34 -> -13318 | D34: ='YTD CF'!E34-'YTD CF'!D34 -> -30316146 | E34: ='YTD CF'!F34-'YTD CF'!E34 -> -21734485 | F34: ='CASH FLOW'!B30-'YTD CF'!F34 -> 51967363 | G34: ='YTD CF'!G34 -> 9125 | H34: ='YTD CF'!H34-'YTD CF'!G34 -> 33171 | I34: ='YTD CF'!I34-'YTD CF'!H34 -> 128671 | J34: ='CASH FLOW'!C30-'YTD CF'!I34 -> -62785 | K34: ='YTD CF'!J34 -> -13831 | L34: ='YTD CF'!K34-'YTD CF'!J34 -> 59042 | M34: ='YTD CF'!L34-'YTD CF'!K34 -> 90835 | N34: ='CASH FLOW'!D30-'YTD CF'!L34 -> 5172 | O34: ='YTD CF'!M34 -> 134649 | P34: ='YTD CF'!N34-'YTD CF'!M34 -> 39643 | Q34: ='YTD CF'!O34-'YTD CF'!N34 -> 12934 | R34: ='CASH FLOW'!E30-'YTD CF'!O34 -> 75672 | S34: ='YTD CF'!P34 -> 103367 | T34: ='YTD CF'!Q34-'YTD CF'!P34 -> 43712 | U34: ='YTD CF'!R34-'YTD CF'!Q34 -> 331801 | V34: ='CASH FLOW'!F30-'YTD CF'!R34 -> -119438 | W34: =SUM(W2:W33) -> -115374.1 | X34: =SUM(X2:X33) -> 148049.93 | Y34: =SUM(Y2:Y33) -> 147389.15 | Z34: =SUM(Z2:Z33) -> 146731.53 | AA34: =SUM(AA2:AA33) -> 146077.06 | AB34: =SUM(AB2:AB33) -> 145425.74 | AC34: =SUM(AC2:AC33) -> 144777.54 | AD34: =SUM(AD2:AD33) -> 144132.45 | ... AP34: =SUM(AP2:AP33) -> 136628.51
A35: Collections from Note Receivable | B35: ='YTD CF'!C35-'YTD CF'!B35 -> 0 | C35: ='YTD CF'!D35 -> 1876 | D35: ='YTD CF'!E35-'YTD CF'!D35 -> 1874397 | E35: ='YTD CF'!F35-'YTD CF'!E35 -> 9451 | F35: ='CASH FLOW'!B31-'YTD CF'!F35 -> -1883838 | G35: ='YTD CF'!G35 -> 0 | H35: ='YTD CF'!H35-'YTD CF'!G35 -> 2592 | I35: ='YTD CF'!I35-'YTD CF'!H35 -> 0 | J35: ='CASH FLOW'!C31-'YTD CF'!I35 -> 0 | K35: ='YTD CF'!J35 -> 3233 | L35: ='YTD CF'!K35-'YTD CF'!J35 -> 0 | M35: ='YTD CF'!L35-'YTD CF'!K35 -> 0 | N35: ='CASH FLOW'!D31-'YTD CF'!L35 -> 0 | O35: ='YTD CF'!M35 -> 0 | P35: ='YTD CF'!N35-'YTD CF'!M35 -> 0 | Q35: ='YTD CF'!O35-'YTD CF'!N35 -> 0 | R35: ='CASH FLOW'!E31-'YTD CF'!O35 -> 0 | S35: ='YTD CF'!P35 -> 0 | T35: ='YTD CF'!Q35-'YTD CF'!P35 -> 0 | U35: ='YTD CF'!R35-'YTD CF'!Q35 -> 0 | V35: ='CASH FLOW'!F31-'YTD CF'!R35 -> 0 | W35: ='CF DRIVERS'!W34 -> 0 | X35: ='CF DRIVERS'!X34 -> 0 | Y35: ='CF DRIVERS'!Y34 -> 0 | Z35: ='CF DRIVERS'!Z34 -> 0 | AA35: ='CF DRIVERS'!AA34 -> 0 | AB35: ='CF DRIVERS'!AB34 -> 0 | AC35: ='CF DRIVERS'!AC34 -> 0 | AD35: ='CF DRIVERS'!AD34 -> 0 | ... AP35: ='CF DRIVERS'!AP34 -> 0
A36: Purchase of PP&E | B36: ='YTD CF'!C36-'YTD CF'!B36 -> -100894 | C36: ='YTD CF'!D36 -> -698 | D36: ='YTD CF'!E36-'YTD CF'!D36 -> -1215352 | E36: ='YTD CF'!F36-'YTD CF'!E36 -> -1179252 | F36: ='CASH FLOW'!B32-'YTD CF'!F36 -> 2392152 | G36: ='YTD CF'!G36 -> -742 | H36: ='YTD CF'!H36-'YTD CF'!G36 -> -1714 | I36: ='YTD CF'!I36-'YTD CF'!H36 -> -1021 | J36: ='CASH FLOW'!C32-'YTD CF'!I36 -> -4787 | K36: ='YTD CF'!J36 -> -2253 | L36: ='YTD CF'!K36-'YTD CF'!J36 -> -4557 | M36: ='YTD CF'!L36-'YTD CF'!K36 -> -5877 | N36: ='CASH FLOW'!D32-'YTD CF'!L36 -> -4746 | O36: ='YTD CF'!M36 -> -4525 | P36: ='YTD CF'!N36-'YTD CF'!M36 -> -9214 | Q36: ='YTD CF'!O36-'YTD CF'!N36 -> -4244 | R36: ='CASH FLOW'!E32-'YTD CF'!O36 -> -5407 | S36: ='YTD CF'!P36 -> -6944 | T36: ='YTD CF'!Q36-'YTD CF'!P36 -> -8250 | U36: ='YTD CF'!R36-'YTD CF'!Q36 -> -10345 | V36: ='CASH FLOW'!F32-'YTD CF'!R36 -> -10528 | W36: ='QTR P&L'!W2*'CF DRIVERS'!W35 -> -10477.502 | X36: ='QTR P&L'!X2*'CF DRIVERS'!X35 -> -10427.246 | Y36: ='QTR P&L'!Y2*'CF DRIVERS'!Y35 -> -10377.232 | Z36: ='QTR P&L'!Z2*'CF DRIVERS'!Z35 -> -10327.457 | AA36: ='QTR P&L'!AA2*'CF DRIVERS'!AA35 -> -10277.921 | AB36: ='QTR P&L'!AB2*'CF DRIVERS'!AB35 -> -10228.622 | AC36: ='QTR P&L'!AC2*'CF DRIVERS'!AC35 -> -10179.56 | AD36: ='QTR P&L'!AD2*'CF DRIVERS'!AD35 -> -10130.734 | ... AP36: ='QTR P&L'!AP2*'CF DRIVERS'!AP35 -> -9562.7636
A37: Purchase of Non-Marketable Equity Securities | B37: ='YTD CF'!C37-'YTD CF'!B37 -> 0 | C37: ='YTD CF'!D37 -> 0 | D37: ='YTD CF'!E37-'YTD CF'!D37 -> 0 | E37: ='YTD CF'!F37-'YTD CF'!E37 -> 0 | F37: ='CASH FLOW'!B33-'YTD CF'!F37 -> 0 | G37: ='YTD CF'!G37 -> 0 | H37: ='YTD CF'!H37-'YTD CF'!G37 -> 0 | I37: ='YTD CF'!I37-'YTD CF'!H37 -> 0 | J37: ='CASH FLOW'!C33-'YTD CF'!I37 -> 0 | K37: ='YTD CF'!J37 -> 0 | L37: ='YTD CF'!K37-'YTD CF'!J37 -> 0 | M37: ='YTD CF'!L37-'YTD CF'!K37 -> 0 | N37: ='CASH FLOW'!D33-'YTD CF'!L37 -> 0 | O37: ='YTD CF'!M37 -> 0 | P37: ='YTD CF'!N37-'YTD CF'!M37 -> 0 | Q37: ='YTD CF'!O37-'YTD CF'!N37 -> -3000 | R37: ='CASH FLOW'!E33-'YTD CF'!O37 -> 0 | S37: ='YTD CF'!P37 -> 0 | T37: ='YTD CF'!Q37-'YTD CF'!P37 -> -5000 | U37: ='YTD CF'!R37-'YTD CF'!Q37 -> 0 | V37: ='CASH FLOW'!F33-'YTD CF'!R37 -> -5000 | W37: ='CF DRIVERS'!W36 -> 0 | X37: ='CF DRIVERS'!X36 -> 0 | Y37: ='CF DRIVERS'!Y36 -> 0 | Z37: ='CF DRIVERS'!Z36 -> 0 | AA37: ='CF DRIVERS'!AA36 -> 0 | AB37: ='CF DRIVERS'!AB36 -> 0 | AC37: ='CF DRIVERS'!AC36 -> 0 | AD37: ='CF DRIVERS'!AD36 -> 0 | ... AP37: ='CF DRIVERS'!AP36 -> 0
A38: Acquisition of Big Beverages | B38: ='YTD CF'!C38-'YTD CF'!B38 -> 0 | C38: ='YTD CF'!D38 -> 0 | D38: ='YTD CF'!E38-'YTD CF'!D38 -> 0 | E38: ='YTD CF'!F38-'YTD CF'!E38 -> 0 | F38: ='CASH FLOW'!B34-'YTD CF'!F38 -> 0 | G38: ='YTD CF'!G38 -> 0 | H38: ='YTD CF'!H38-'YTD CF'!G38 -> 0 | I38: ='YTD CF'!I38-'YTD CF'!H38 -> 0 | J38: ='CASH FLOW'!C34-'YTD CF'!I38 -> 0 | K38: ='YTD CF'!J38 -> 0 | L38: ='YTD CF'!K38-'YTD CF'!J38 -> 0 | M38: ='YTD CF'!L38-'YTD CF'!K38 -> 0 | N38: ='CASH FLOW'!D34-'YTD CF'!L38 -> 0 | O38: ='YTD CF'!M38 -> 0 | P38: ='YTD CF'!N38-'YTD CF'!M38 -> 0 | Q38: ='YTD CF'!O38-'YTD CF'!N38 -> 0 | R38: ='CASH FLOW'!E34-'YTD CF'!O38 -> -75336 | S38: ='YTD CF'!P38 -> 0 | T38: ='YTD CF'!Q38-'YTD CF'!P38 -> 0 | U38: ='YTD CF'!R38-'YTD CF'!Q38 -> 0 | V38: ='CASH FLOW'!F34-'YTD CF'!R38 -> 0 | W38: ='CF DRIVERS'!W37 -> 0 | X38: ='CF DRIVERS'!X37 -> 0 | Y38: ='CF DRIVERS'!Y37 -> 0 | Z38: ='CF DRIVERS'!Z37 -> 0 | AA38: ='CF DRIVERS'!AA37 -> 0 | AB38: ='CF DRIVERS'!AB37 -> 0 | AC38: ='CF DRIVERS'!AC37 -> 0 | AD38: ='CF DRIVERS'!AD37 -> 0 | ... AP38: ='CF DRIVERS'!AP37 -> 0
A39: Acquisitions, Net of Cash Acquired | B39: ='YTD CF'!C39-'YTD CF'!B39 -> 0 | C39: ='YTD CF'!D39 -> 0 | D39: ='YTD CF'!E39-'YTD CF'!D39 -> 0 | E39: ='YTD CF'!F39-'YTD CF'!E39 -> 0 | F39: ='CASH FLOW'!B35-'YTD CF'!F39 -> 0 | G39: ='YTD CF'!G39 -> 0 | H39: ='YTD CF'!H39-'YTD CF'!G39 -> 0 | I39: ='YTD CF'!I39-'YTD CF'!H39 -> 0 | J39: ='CASH FLOW'!C35-'YTD CF'!I39 -> 0 | K39: ='YTD CF'!J39 -> 0 | L39: ='YTD CF'!K39-'YTD CF'!J39 -> 0 | M39: ='YTD CF'!L39-'YTD CF'!K39 -> 0 | N39: ='CASH FLOW'!D35-'YTD CF'!L39 -> 0 | O39: ='YTD CF'!M39 -> 0 | P39: ='YTD CF'!N39-'YTD CF'!M39 -> 0 | Q39: ='YTD CF'!O39-'YTD CF'!N39 -> 0 | R39: ='CASH FLOW'!E35-'YTD CF'!O39 -> 0 | S39: ='YTD CF'!P39 -> 0 | T39: ='YTD CF'!Q39-'YTD CF'!P39 -> -1256351 | U39: ='YTD CF'!R39-'YTD CF'!Q39 -> -22418 | V39: ='CASH FLOW'!F35-'YTD CF'!R39 -> 0 | W39: ='CF DRIVERS'!W38 -> 0 | X39: ='CF DRIVERS'!X38 -> 0 | Y39: ='CF DRIVERS'!Y38 -> 0 | Z39: ='CF DRIVERS'!Z38 -> 0 | AA39: ='CF DRIVERS'!AA38 -> 0 | AB39: ='CF DRIVERS'!AB38 -> 0 | AC39: ='CF DRIVERS'!AC38 -> 0 | AD39: ='CF DRIVERS'!AD38 -> 0 | ... AP39: ='CF DRIVERS'!AP38 -> 0
A40: Working Capital Estimate from Pepsi (Rockstar) | W40: ='CF DRIVERS'!W39 -> 0 | X40: ='CF DRIVERS'!X39 -> 0 | Y40: ='CF DRIVERS'!Y39 -> 0 | Z40: ='CF DRIVERS'!Z39 -> 0 | AA40: ='CF DRIVERS'!AA39 -> 0 | AB40: ='CF DRIVERS'!AB39 -> 0 | AC40: ='CF DRIVERS'!AC39 -> 0 | AD40: ='CF DRIVERS'!AD39 -> 0 | ... AP40: ='CF DRIVERS'!AP39 -> 0
A41: Cash Flow from Investing | B41: ='YTD CF'!C41-'YTD CF'!B41 -> -100894 | C41: ='YTD CF'!D41 -> 1178 | D41: ='YTD CF'!E41-'YTD CF'!D41 -> 659045 | E41: ='YTD CF'!F41-'YTD CF'!E41 -> -1169801 | F41: ='CASH FLOW'!B37-'YTD CF'!F41 -> 508314 | G41: ='YTD CF'!G41 -> -742 | H41: ='YTD CF'!H41-'YTD CF'!G41 -> 878 | I41: ='YTD CF'!I41-'YTD CF'!H41 -> -1021 | J41: ='CASH FLOW'!C37-'YTD CF'!I41 -> -4787 | K41: ='YTD CF'!J41 -> 980 | L41: ='YTD CF'!K41-'YTD CF'!J41 -> -4557 | M41: ='YTD CF'!L41-'YTD CF'!K41 -> -5877 | N41: ='CASH FLOW'!D37-'YTD CF'!L41 -> -4746 | O41: ='YTD CF'!M41 -> -4525 | P41: ='YTD CF'!N41-'YTD CF'!M41 -> -9214 | Q41: ='YTD CF'!O41-'YTD CF'!N41 -> -7244 | R41: ='CASH FLOW'!E37-'YTD CF'!O41 -> -80743 | S41: ='YTD CF'!P41 -> -6944 | T41: ='YTD CF'!Q41-'YTD CF'!P41 -> -1269601 | U41: ='YTD CF'!R41-'YTD CF'!Q41 -> -2146 | V41: ='CASH FLOW'!F37-'YTD CF'!R41 -> -16989 | W41: =SUM(W35:W40) -> -10477.502 | X41: =SUM(X35:X40) -> -10427.246 | Y41: =SUM(Y35:Y40) -> -10377.232 | Z41: =SUM(Z35:Z40) -> -10327.457 | AA41: =SUM(AA35:AA40) -> -10277.921 | AB41: =SUM(AB35:AB40) -> -10228.622 | AC41: =SUM(AC35:AC40) -> -10179.56 | AD41: =SUM(AD35:AD40) -> -10130.734 | ... AP41: =SUM(AP35:AP40) -> -9562.7636
A42: Finance Lease Payments | B42: ='YTD CF'!C42-'YTD CF'!B42 -> -37179 | C42: ='YTD CF'!D42 -> -25 | D42: ='YTD CF'!E42-'YTD CF'!D42 -> -49567 | E42: ='YTD CF'!F42-'YTD CF'!E42 -> -22794 | F42: ='CASH FLOW'!B38-'YTD CF'!F42 -> 72292 | G42: ='YTD CF'!G42 -> -20 | H42: ='YTD CF'!H42-'YTD CF'!G42 -> -17 | I42: ='YTD CF'!I42-'YTD CF'!H42 -> -12 | J42: ='CASH FLOW'!C38-'YTD CF'!I42 -> -14 | K42: ='YTD CF'!J42 -> -11 | L42: ='YTD CF'!K42-'YTD CF'!J42 -> -11 | M42: ='YTD CF'!L42-'YTD CF'!K42 -> -11 | N42: ='CASH FLOW'!D38-'YTD CF'!L42 -> -11 | O42: ='YTD CF'!M42 -> -15 | P42: ='YTD CF'!N42-'YTD CF'!M42 -> -15 | Q42: ='YTD CF'!O42-'YTD CF'!N42 -> -16 | R42: ='CASH FLOW'!E38-'YTD CF'!O42 -> -15 | S42: ='YTD CF'!P42 -> 0 | T42: ='YTD CF'!Q42-'YTD CF'!P42 -> 0 | U42: ='YTD CF'!R42-'YTD CF'!Q42 -> 0 | V42: ='CASH FLOW'!F38-'YTD CF'!R42 -> 0 | W42: ='CF DRIVERS'!W40 -> 0 | X42: ='CF DRIVERS'!X40 -> 0 | Y42: ='CF DRIVERS'!Y40 -> 0 | Z42: ='CF DRIVERS'!Z40 -> 0 | AA42: ='CF DRIVERS'!AA40 -> 0 | AB42: ='CF DRIVERS'!AB40 -> 0 | AC42: ='CF DRIVERS'!AC40 -> 0 | AD42: ='CF DRIVERS'!AD40 -> 0 | ... AP42: ='CF DRIVERS'!AP40 -> 0
A43: Proceeds from Issuance of Common Stock | B43: ='YTD CF'!C43-'YTD CF'!B43 -> 21983116 | C43: ='YTD CF'!D43 -> 0 | D43: ='YTD CF'!E43-'YTD CF'!D43 -> 67769386 | E43: ='YTD CF'!F43-'YTD CF'!E43 -> 0 | F43: ='CASH FLOW'!B40-'YTD CF'!F43 -> -67701617 | G43: ='YTD CF'!G43 -> 0 | H43: ='YTD CF'!H43-'YTD CF'!G43 -> 0 | I43: ='YTD CF'!I43-'YTD CF'!H43 -> 0 | J43: ='CASH FLOW'!C40-'YTD CF'!I43 -> 0 | K43: ='YTD CF'!J43 -> 0 | L43: ='YTD CF'!K43-'YTD CF'!J43 -> 0 | M43: ='YTD CF'!L43-'YTD CF'!K43 -> 0 | N43: ='CASH FLOW'!D40-'YTD CF'!L43 -> 0 | O43: ='YTD CF'!M43 -> 0 | P43: ='YTD CF'!N43-'YTD CF'!M43 -> 0 | Q43: ='YTD CF'!O43-'YTD CF'!N43 -> 0 | R43: ='CASH FLOW'!E40-'YTD CF'!O43 -> 0 | S43: ='YTD CF'!P43 -> 0 | T43: ='YTD CF'!Q43-'YTD CF'!P43 -> 0 | U43: ='YTD CF'!R43-'YTD CF'!Q43 -> 0 | V43: ='CASH FLOW'!F40-'YTD CF'!R43 -> 0 | W43: ='CF DRIVERS'!W41 -> 0 | X43: ='CF DRIVERS'!X41 -> 0 | Y43: ='CF DRIVERS'!Y41 -> 0 | Z43: ='CF DRIVERS'!Z41 -> 0 | AA43: ='CF DRIVERS'!AA41 -> 0 | AB43: ='CF DRIVERS'!AB41 -> 0 | AC43: ='CF DRIVERS'!AC41 -> 0 | AD43: ='CF DRIVERS'!AD41 -> 0 | ... AP43: ='CF DRIVERS'!AP41 -> 0
A44: Proceeds from Exercise of Stock Options | B44: ='YTD CF'!C44-'YTD CF'!B44 -> 1591679 | C44: ='YTD CF'!D44 -> 716 | D44: ='YTD CF'!E44-'YTD CF'!D44 -> 2514301 | E44: ='YTD CF'!F44-'YTD CF'!E44 -> 727056 | F44: ='CASH FLOW'!B39-'YTD CF'!F44 -> -3238353 | G44: ='YTD CF'!G44 -> 810 | H44: ='YTD CF'!H44-'YTD CF'!G44 -> 450 | I44: ='YTD CF'!I44-'YTD CF'!H44 -> 1844 | J44: ='CASH FLOW'!C39-'YTD CF'!I44 -> 579 | K44: ='YTD CF'!J44 -> 478 | L44: ='YTD CF'!K44-'YTD CF'!J44 -> 229 | M44: ='YTD CF'!L44-'YTD CF'!K44 -> 896 | N44: ='CASH FLOW'!D39-'YTD CF'!L44 -> 682 | O44: ='YTD CF'!M44 -> 967 | P44: ='YTD CF'!N44-'YTD CF'!M44 -> 180 | Q44: ='YTD CF'!O44-'YTD CF'!N44 -> 2685 | R44: ='CASH FLOW'!E39-'YTD CF'!O44 -> 24 | S44: ='YTD CF'!P44 -> 0 | T44: ='YTD CF'!Q44-'YTD CF'!P44 -> 0 | U44: ='YTD CF'!R44-'YTD CF'!Q44 -> 0 | V44: ='CASH FLOW'!F39-'YTD CF'!R44 -> 0 | W44: ='CF DRIVERS'!W42 -> 0 | X44: ='CF DRIVERS'!X42 -> 0 | Y44: ='CF DRIVERS'!Y42 -> 0 | Z44: ='CF DRIVERS'!Z42 -> 0 | AA44: ='CF DRIVERS'!AA42 -> 0 | AB44: ='CF DRIVERS'!AB42 -> 0 | AC44: ='CF DRIVERS'!AC42 -> 0 | AD44: ='CF DRIVERS'!AD42 -> 0 | ... AP44: ='CF DRIVERS'!AP42 -> 0
A45: Proceeds from Issuance of Preferred Stock | B45: ='YTD CF'!C45-'YTD CF'!B45 -> 0 | C45: ='YTD CF'!D45 -> 0 | D45: ='YTD CF'!E45-'YTD CF'!D45 -> 0 | E45: ='YTD CF'!F45-'YTD CF'!E45 -> 0 | F45: ='CASH FLOW'!B41-'YTD CF'!F45 -> 0 | G45: ='YTD CF'!G45 -> 0 | H45: ='YTD CF'!H45-'YTD CF'!G45 -> 0 | I45: ='YTD CF'!I45-'YTD CF'!H45 -> 542018 | J45: ='CASH FLOW'!C41-'YTD CF'!I45 -> 0 | K45: ='YTD CF'!J45 -> 0 | L45: ='YTD CF'!K45-'YTD CF'!J45 -> 0 | M45: ='YTD CF'!L45-'YTD CF'!K45 -> 0 | N45: ='CASH FLOW'!D41-'YTD CF'!L45 -> 0 | O45: ='YTD CF'!M45 -> 0 | P45: ='YTD CF'!N45-'YTD CF'!M45 -> 0 | Q45: ='YTD CF'!O45-'YTD CF'!N45 -> 0 | R45: ='CASH FLOW'!E41-'YTD CF'!O45 -> 0 | S45: ='YTD CF'!P45 -> 0 | T45: ='YTD CF'!Q45-'YTD CF'!P45 -> 0 | U45: ='YTD CF'!R45-'YTD CF'!Q45 -> 0 | V45: ='CASH FLOW'!F41-'YTD CF'!R45 -> 0 | W45: ='CF DRIVERS'!W43 -> 0 | X45: ='CF DRIVERS'!X43 -> 0 | Y45: ='CF DRIVERS'!Y43 -> 0 | Z45: ='CF DRIVERS'!Z43 -> 0 | AA45: ='CF DRIVERS'!AA43 -> 0 | AB45: ='CF DRIVERS'!AB43 -> 0 | AC45: ='CF DRIVERS'!AC43 -> 0 | AD45: ='CF DRIVERS'!AD43 -> 0 | ... AP45: ='CF DRIVERS'!AP43 -> 0
A46: Preferred Dividends | B46: ='YTD CF'!C46-'YTD CF'!B46 -> 0 | C46: ='YTD CF'!D46 -> 0 | D46: ='YTD CF'!E46-'YTD CF'!D46 -> 0 | E46: ='YTD CF'!F46-'YTD CF'!E46 -> 0 | F46: ='CASH FLOW'!B42-'YTD CF'!F46 -> 0 | G46: ='YTD CF'!G46 -> 0 | H46: ='YTD CF'!H46-'YTD CF'!G46 -> 0 | I46: ='YTD CF'!I46-'YTD CF'!H46 -> -4596 | J46: ='CASH FLOW'!C42-'YTD CF'!I46 -> -6930 | K46: ='YTD CF'!J46 -> -6781 | L46: ='YTD CF'!K46-'YTD CF'!J46 -> -6856 | M46: ='YTD CF'!L46-'YTD CF'!K46 -> -6875 | N46: ='CASH FLOW'!D42-'YTD CF'!L46 -> -6950 | O46: ='YTD CF'!M46 -> -6837 | P46: ='YTD CF'!N46-'YTD CF'!M46 -> -6838 | Q46: ='YTD CF'!O46-'YTD CF'!N46 -> -6913 | R46: ='CASH FLOW'!E42-'YTD CF'!O46 -> -6912 | S46: ='YTD CF'!P46 -> -6781 | T46: ='YTD CF'!Q46-'YTD CF'!P46 -> -6851 | U46: ='YTD CF'!R46-'YTD CF'!Q46 -> -9669 | V46: ='CASH FLOW'!F42-'YTD CF'!R46 -> -14307 | W46: ='CF DRIVERS'!W44 -> -14307 | X46: ='CF DRIVERS'!X44 -> -14307 | Y46: ='CF DRIVERS'!Y44 -> -14307 | Z46: ='CF DRIVERS'!Z44 -> -14307 | AA46: ='CF DRIVERS'!AA44 -> -14307 | AB46: ='CF DRIVERS'!AB44 -> -14307 | AC46: ='CF DRIVERS'!AC44 -> -14307 | AD46: ='CF DRIVERS'!AD44 -> -14307 | ... AP46: ='CF DRIVERS'!AP44 -> -14307
A47: Share Repurchases | B47: ='YTD CF'!C47-'YTD CF'!B47 -> 0 | C47: ='YTD CF'!D47 -> 0 | D47: ='YTD CF'!E47-'YTD CF'!D47 -> 0 | E47: ='YTD CF'!F47-'YTD CF'!E47 -> 0 | F47: ='CASH FLOW'!B43-'YTD CF'!F47 -> 0 | G47: ='YTD CF'!G47 -> 0 | H47: ='YTD CF'!H47-'YTD CF'!G47 -> 0 | I47: ='YTD CF'!I47-'YTD CF'!H47 -> 0 | J47: ='CASH FLOW'!C43-'YTD CF'!I47 -> 0 | K47: ='YTD CF'!J47 -> 0 | L47: ='YTD CF'!K47-'YTD CF'!J47 -> 0 | M47: ='YTD CF'!L47-'YTD CF'!K47 -> 0 | N47: ='CASH FLOW'!D43-'YTD CF'!L47 -> 0 | O47: ='YTD CF'!M47 -> 0 | P47: ='YTD CF'!N47-'YTD CF'!M47 -> 0 | Q47: ='YTD CF'!O47-'YTD CF'!N47 -> -1658 | R47: ='CASH FLOW'!E43-'YTD CF'!O47 -> -603 | S47: ='YTD CF'!P47 -> -1932 | T47: ='YTD CF'!Q47-'YTD CF'!P47 -> -879 | U47: ='YTD CF'!R47-'YTD CF'!Q47 -> -448 | V47: ='CASH FLOW'!F43-'YTD CF'!R47 -> -42245 | W47: ='CF DRIVERS'!W45 -> 0 | X47: ='CF DRIVERS'!X45 -> 0 | Y47: ='CF DRIVERS'!Y45 -> 0 | Z47: ='CF DRIVERS'!Z45 -> 0 | AA47: ='CF DRIVERS'!AA45 -> 0 | AB47: ='CF DRIVERS'!AB45 -> 0 | AC47: ='CF DRIVERS'!AC45 -> 0 | AD47: ='CF DRIVERS'!AD45 -> 0 | ... AP47: ='CF DRIVERS'!AP45 -> 0
A48: Proceeds from Issuance of Long-Term Debt | B48: ='YTD CF'!C48-'YTD CF'!B48 -> 0 | C48: ='YTD CF'!D48 -> 0 | D48: ='YTD CF'!E48-'YTD CF'!D48 -> 0 | E48: ='YTD CF'!F48-'YTD CF'!E48 -> 0 | F48: ='CASH FLOW'!B44-'YTD CF'!F48 -> 0 | G48: ='YTD CF'!G48 -> 0 | H48: ='YTD CF'!H48-'YTD CF'!G48 -> 0 | I48: ='YTD CF'!I48-'YTD CF'!H48 -> 0 | J48: ='CASH FLOW'!C44-'YTD CF'!I48 -> 0 | K48: ='YTD CF'!J48 -> 0 | L48: ='YTD CF'!K48-'YTD CF'!J48 -> 0 | M48: ='YTD CF'!L48-'YTD CF'!K48 -> 0 | N48: ='CASH FLOW'!D44-'YTD CF'!L48 -> 0 | O48: ='YTD CF'!M48 -> 0 | P48: ='YTD CF'!N48-'YTD CF'!M48 -> 0 | Q48: ='YTD CF'!O48-'YTD CF'!N48 -> 0 | R48: ='CASH FLOW'!E44-'YTD CF'!O48 -> 0 | S48: ='YTD CF'!P48 -> 0 | T48: ='YTD CF'!Q48-'YTD CF'!P48 -> 900000 | U48: ='YTD CF'!R48-'YTD CF'!Q48 -> 0 | V48: ='CASH FLOW'!F44-'YTD CF'!R48 -> 0 | W48: ='CF DRIVERS'!W46 -> 0 | X48: ='CF DRIVERS'!X46 -> 0 | Y48: ='CF DRIVERS'!Y46 -> 0 | Z48: ='CF DRIVERS'!Z46 -> 0 | AA48: ='CF DRIVERS'!AA46 -> 0 | AB48: ='CF DRIVERS'!AB46 -> 0 | AC48: ='CF DRIVERS'!AC46 -> 0 | AD48: ='CF DRIVERS'!AD46 -> 0 | ... AP48: ='CF DRIVERS'!AP46 -> 0
A49: Repayments of Long-Term Debt | B49: ='YTD CF'!C49-'YTD CF'!B49 -> 0 | C49: ='YTD CF'!D49 -> 0 | D49: ='YTD CF'!E49-'YTD CF'!D49 -> 0 | E49: ='YTD CF'!F49-'YTD CF'!E49 -> 0 | F49: ='CASH FLOW'!B45-'YTD CF'!F49 -> 0 | G49: ='YTD CF'!G49 -> 0 | H49: ='YTD CF'!H49-'YTD CF'!G49 -> 0 | I49: ='YTD CF'!I49-'YTD CF'!H49 -> 0 | J49: ='CASH FLOW'!C45-'YTD CF'!I49 -> 0 | K49: ='YTD CF'!J49 -> 0 | L49: ='YTD CF'!K49-'YTD CF'!J49 -> 0 | M49: ='YTD CF'!L49-'YTD CF'!K49 -> 0 | N49: ='CASH FLOW'!D45-'YTD CF'!L49 -> 0 | O49: ='YTD CF'!M49 -> 0 | P49: ='YTD CF'!N49-'YTD CF'!M49 -> 0 | Q49: ='YTD CF'!O49-'YTD CF'!N49 -> 0 | R49: ='CASH FLOW'!E45-'YTD CF'!O49 -> 0 | S49: ='YTD CF'!P49 -> 0 | T49: ='YTD CF'!Q49-'YTD CF'!P49 -> 0 | U49: ='YTD CF'!R49-'YTD CF'!Q49 -> -2250 | V49: ='CASH FLOW'!F45-'YTD CF'!R49 -> -199500 | W49: ='CF DRIVERS'!W47 -> 0 | X49: ='CF DRIVERS'!X47 -> 0 | Y49: ='CF DRIVERS'!Y47 -> 0 | Z49: ='CF DRIVERS'!Z47 -> 0 | AA49: ='CF DRIVERS'!AA47 -> 0 | AB49: ='CF DRIVERS'!AB47 -> 0 | AC49: ='CF DRIVERS'!AC47 -> 0 | AD49: ='CF DRIVERS'!AD47 -> 0 | ... AP49: ='CF DRIVERS'!AP47 -> 0
A50: Debt Issuance Fees | B50: ='YTD CF'!C50-'YTD CF'!B50 -> 0 | C50: ='YTD CF'!D50 -> 0 | D50: ='YTD CF'!E50-'YTD CF'!D50 -> 0 | E50: ='YTD CF'!F50-'YTD CF'!E50 -> 0 | F50: ='CASH FLOW'!B46-'YTD CF'!F50 -> 0 | G50: ='YTD CF'!G50 -> 0 | H50: ='YTD CF'!H50-'YTD CF'!G50 -> 0 | I50: ='YTD CF'!I50-'YTD CF'!H50 -> 0 | J50: ='CASH FLOW'!C46-'YTD CF'!I50 -> 0 | K50: ='YTD CF'!J50 -> 0 | L50: ='YTD CF'!K50-'YTD CF'!J50 -> 0 | M50: ='YTD CF'!L50-'YTD CF'!K50 -> 0 | N50: ='CASH FLOW'!D46-'YTD CF'!L50 -> 0 | O50: ='YTD CF'!M50 -> 0 | P50: ='YTD CF'!N50-'YTD CF'!M50 -> 0 | Q50: ='YTD CF'!O50-'YTD CF'!N50 -> 0 | R50: ='CASH FLOW'!E46-'YTD CF'!O50 -> 0 | S50: ='YTD CF'!P50 -> -2195 | T50: ='YTD CF'!Q50-'YTD CF'!P50 -> -29386 | U50: ='YTD CF'!R50-'YTD CF'!Q50 -> 0 | V50: ='CASH FLOW'!F46-'YTD CF'!R50 -> -786 | W50: ='CF DRIVERS'!W48 -> 0 | X50: ='CF DRIVERS'!X48 -> 0 | Y50: ='CF DRIVERS'!Y48 -> 0 | Z50: ='CF DRIVERS'!Z48 -> 0 | AA50: ='CF DRIVERS'!AA48 -> 0 | AB50: ='CF DRIVERS'!AB48 -> 0 | AC50: ='CF DRIVERS'!AC48 -> 0 | AD50: ='CF DRIVERS'!AD48 -> 0 | ... AP50: ='CF DRIVERS'!AP48 -> 0
A51: Other Financing Activities | B51: ='YTD CF'!C51-'YTD CF'!B51 -> 0 | C51: ='YTD CF'!D51 -> 0 | D51: ='YTD CF'!E51-'YTD CF'!D51 -> 0 | E51: ='YTD CF'!F51-'YTD CF'!E51 -> 0 | F51: ='CASH FLOW'!B47-'YTD CF'!F51 -> 0 | G51: ='YTD CF'!G51 -> 0 | H51: ='YTD CF'!H51-'YTD CF'!G51 -> 0 | I51: ='YTD CF'!I51-'YTD CF'!H51 -> 0 | J51: ='CASH FLOW'!C47-'YTD CF'!I51 -> 0 | K51: ='YTD CF'!J51 -> 0 | L51: ='YTD CF'!K51-'YTD CF'!J51 -> 0 | M51: ='YTD CF'!L51-'YTD CF'!K51 -> 0 | N51: ='CASH FLOW'!D47-'YTD CF'!L51 -> 0 | O51: ='YTD CF'!M51 -> 0 | P51: ='YTD CF'!N51-'YTD CF'!M51 -> 0 | Q51: ='YTD CF'!O51-'YTD CF'!N51 -> 0 | R51: ='CASH FLOW'!E47-'YTD CF'!O51 -> 0 | S51: ='YTD CF'!P51 -> 321 | T51: ='YTD CF'!Q51-'YTD CF'!P51 -> -2 | U51: ='YTD CF'!R51-'YTD CF'!Q51 -> -18 | V51: ='CASH FLOW'!F47-'YTD CF'!R51 -> -308 | W51: ='CF DRIVERS'!W49 -> 0 | X51: ='CF DRIVERS'!X49 -> 0 | Y51: ='CF DRIVERS'!Y49 -> 0 | Z51: ='CF DRIVERS'!Z49 -> 0 | AA51: ='CF DRIVERS'!AA49 -> 0 | AB51: ='CF DRIVERS'!AB49 -> 0 | AC51: ='CF DRIVERS'!AC49 -> 0 | AD51: ='CF DRIVERS'!AD49 -> 0 | ... AP51: ='CF DRIVERS'!AP49 -> 0
A52: Cash Flow from Financing | B52: ='YTD CF'!C52-'YTD CF'!B52 -> 23537616 | C52: ='YTD CF'!D52 -> 691 | D52: ='YTD CF'!E52-'YTD CF'!D52 -> 70234120 | E52: ='YTD CF'!F52-'YTD CF'!E52 -> 704262 | F52: ='CASH FLOW'!B48-'YTD CF'!F52 -> -70867678 | G52: ='YTD CF'!G52 -> 790 | H52: ='YTD CF'!H52-'YTD CF'!G52 -> 433 | I52: ='YTD CF'!I52-'YTD CF'!H52 -> 539254 | J52: ='CASH FLOW'!C48-'YTD CF'!I52 -> -6365 | K52: ='YTD CF'!J52 -> -6314 | L52: ='YTD CF'!K52-'YTD CF'!J52 -> -6638 | M52: ='YTD CF'!L52-'YTD CF'!K52 -> -5990 | N52: ='CASH FLOW'!D48-'YTD CF'!L52 -> -6279 | O52: ='YTD CF'!M52 -> -5885 | P52: ='YTD CF'!N52-'YTD CF'!M52 -> -6673 | Q52: ='YTD CF'!O52-'YTD CF'!N52 -> -5902 | R52: ='CASH FLOW'!E48-'YTD CF'!O52 -> -7506 | S52: ='YTD CF'!P52 -> -10587 | T52: ='YTD CF'!Q52-'YTD CF'!P52 -> 862882 | U52: ='YTD CF'!R52-'YTD CF'!Q52 -> -12385 | V52: ='CASH FLOW'!F48-'YTD CF'!R52 -> -257146 | W52: =SUM(W42:W51) -> -14307 | X52: =SUM(X42:X51) -> -14307 | Y52: =SUM(Y42:Y51) -> -14307 | Z52: =SUM(Z42:Z51) -> -14307 | AA52: =SUM(AA42:AA51) -> -14307 | AB52: =SUM(AB42:AB51) -> -14307 | AC52: =SUM(AC42:AC51) -> -14307 | AD52: =SUM(AD42:AD51) -> -14307 | ... AP52: =SUM(AP42:AP51) -> -14307
A53: FX Effect on Cash | B53: ='YTD CF'!C53-'YTD CF'!B53 -> 520973 | C53: ='YTD CF'!D53 -> -165 | D53: ='YTD CF'!E53-'YTD CF'!D53 -> -23445 | E53: ='YTD CF'!F53-'YTD CF'!E53 -> -212755 | F53: ='CASH FLOW'!B49-'YTD CF'!F53 -> 235827 | G53: ='YTD CF'!G53 -> 104 | H53: ='YTD CF'!H53-'YTD CF'!G53 -> 17 | I53: ='YTD CF'!I53-'YTD CF'!H53 -> 37 | J53: ='CASH FLOW'!C49-'YTD CF'!I53 -> -108 | K53: ='YTD CF'!J53 -> -181 | L53: ='YTD CF'!K53-'YTD CF'!J53 -> -374 | M53: ='YTD CF'!L53-'YTD CF'!K53 -> 0 | N53: ='CASH FLOW'!D49-'YTD CF'!L53 -> 1812 | O53: ='YTD CF'!M53 -> -722 | P53: ='YTD CF'!N53-'YTD CF'!M53 -> -44 | Q53: ='YTD CF'!O53-'YTD CF'!N53 -> 750 | R53: ='CASH FLOW'!E49-'YTD CF'!O53 -> -981 | S53: ='YTD CF'!P53 -> 1259 | T53: ='YTD CF'!Q53-'YTD CF'!P53 -> 955 | U53: ='YTD CF'!R53-'YTD CF'!Q53 -> -40 | V53: ='CASH FLOW'!F49-'YTD CF'!R53 -> 1097 | W53: ='CF DRIVERS'!W50 -> 1097 | X53: ='CF DRIVERS'!X50 -> 1097 | Y53: ='CF DRIVERS'!Y50 -> 1097 | Z53: ='CF DRIVERS'!Z50 -> 1097 | AA53: ='CF DRIVERS'!AA50 -> 1097 | AB53: ='CF DRIVERS'!AB50 -> 1097 | AC53: ='CF DRIVERS'!AC50 -> 1097 | AD53: ='CF DRIVERS'!AD50 -> 1097 | ... AP53: ='CF DRIVERS'!AP50 -> 1097
A54: Net Change in Cash | B54: ='YTD CF'!C54-'YTD CF'!B54 -> 32047283 | C54: ='YTD CF'!D54 -> -11614 | D54: ='YTD CF'!E54-'YTD CF'!D54 -> 40553574 | E54: ='YTD CF'!F54-'YTD CF'!E54 -> -22412779 | F54: ='CASH FLOW'!B50-'YTD CF'!F54 -> -18156174 | G54: ='YTD CF'!G54 -> 9277 | H54: ='YTD CF'!H54-'YTD CF'!G54 -> 34499 | I54: ='YTD CF'!I54-'YTD CF'!H54 -> 666941 | J54: ='CASH FLOW'!C50-'YTD CF'!I54 -> -74045 | K54: ='YTD CF'!J54 -> -19346 | L54: ='YTD CF'!K54-'YTD CF'!J54 -> 47473 | M54: ='YTD CF'!L54-'YTD CF'!K54 -> 78968 | N54: ='CASH FLOW'!D50-'YTD CF'!L54 -> -4041 | O54: ='YTD CF'!M54 -> 123517 | P54: ='YTD CF'!N54-'YTD CF'!M54 -> 23712 | Q54: ='YTD CF'!O54-'YTD CF'!N54 -> 538 | R54: ='CASH FLOW'!E50-'YTD CF'!O54 -> -13558 | S54: ='YTD CF'!P54 -> 87095 | T54: ='YTD CF'!Q54-'YTD CF'!P54 -> -362052 | U54: ='YTD CF'!R54-'YTD CF'!Q54 -> 317230 | V54: ='CASH FLOW'!F50-'YTD CF'!R54 -> -392476 | W54: =W34+W41+W52+W53 -> -139061.6 | X54: =X34+X41+X52+X53 -> 124412.69 | Y54: =Y34+Y41+Y52+Y53 -> 123801.91 | Z54: =Z34+Z41+Z52+Z53 -> 123194.07 | AA54: =AA34+AA41+AA52+AA53 -> 122589.14 | AB54: =AB34+AB41+AB52+AB53 -> 121987.12 | AC54: =AC34+AC41+AC52+AC53 -> 121387.98 | AD54: =AD34+AD41+AD52+AD53 -> 120791.71 | ... AP54: =AP34+AP41+AP52+AP53 -> 113855.75

Sheet IS DRIVERS
A1: Driver | B1: Basis | C1: Q3 FY2020 | D1: Q1 FY2021 | E1: Q2 FY2021 | F1: Q3 FY2021 | G1: Q4 FY2021 | H1: Q1 FY2022 | I1: Q2 FY2022 | J1: Q3 FY2022 | K1: Q4 FY2022 | L1: Q1 FY2023 | M1: Q2 FY2023 | N1: Q3 FY2023 | O1: Q4 FY2023 | P1: Q1 FY2024 | Q1: Q2 FY2024 | R1: Q3 FY2024 | S1: Q4 FY2024 | T1: Q1 FY2025 | U1: Q2 FY2025 | V1: Q3 FY2025 | W1: Q4 FY2025 | X1: Q1 FY2026E | Y1: Q2 FY2026E | Z1: Q3 FY2026E | AA1: Q4 FY2026E | AB1: Q1 FY2027E | AC1: Q2 FY2027E | AD1: Q3 FY2027E | AE1: Q4 FY2027E | AF1: Q1 FY2028E | AG1: Q2 FY2028E | AH1: Q3 FY2028E | AI1: Q4 FY2028E | AJ1: Q1 FY2029E | AK1: Q2 FY2029E | AL1: Q3 FY2029E | AM1: Q4 FY2029E | AN1: Q1 FY2030E | AO1: Q2 FY2030E | AP1: Q3 FY2030E | AQ1: Q4 FY2030E
A2: Net Sales / Revenue — Growth % | B2: QoQ | E2: =IFERROR('QTR P&L'!D2/'QTR P&L'!C2-1,"") -> 2298.5537 | F2: =IFERROR('QTR P&L'!E2/IF($B2="QoQ",'QTR P&L'!D2,'QTR P&L'!B2)-1,"") -> -0.1751207 | G2: =IFERROR('QTR P&L'!F2/'QTR P&L'!E2-1,"") -> -3.2095145 | H2: =IFERROR('QTR P&L'!G2/IF($B2="QoQ",'QTR P&L'!F2,'QTR P&L'!C2)-1,"") -> -1.0006361 | I2: =IFERROR('QTR P&L'!H2/IF($B2="QoQ",'QTR P&L'!G2,'QTR P&L'!D2)-1,"") -> 0.15467658 | J2: =IFERROR('QTR P&L'!I2/IF($B2="QoQ",'QTR P&L'!H2,'QTR P&L'!E2)-1,"") -> 0.222127 | K2: =IFERROR('QTR P&L'!J2/IF($B2="QoQ",'QTR P&L'!I2,'QTR P&L'!F2)-1,"") -> -0.054549705 | L2: =IFERROR('QTR P&L'!K2/IF($B2="QoQ",'QTR P&L'!J2,'QTR P&L'!G2)-1,"") -> 0.46062687 | M2: =IFERROR('QTR P&L'!L2/IF($B2="QoQ",'QTR P&L'!K2,'QTR P&L'!H2)-1,"") -> 0.25369029 | N2: =IFERROR('QTR P&L'!M2/IF($B2="QoQ",'QTR P&L'!L2,'QTR P&L'!I2)-1,"") -> 0.18065993 | O2: =IFERROR('QTR P&L'!N2/IF($B2="QoQ",'QTR P&L'!M2,'QTR P&L'!J2)-1,"") -> -0.097001484 | ... W2: =IFERROR('QTR P&L'!V2/IF($B2="QoQ",'QTR P&L'!U2,'QTR P&L'!R2)-1,"") -> -0.0047965401 | X2: =W2 -> -0.0047965401 | Y2: =X2 -> -0.0047965401 | Z2: =Y2 -> -0.0047965401 | AA2: =Z2 -> -0.0047965401 | AB2: =AA2 -> -0.0047965401 | AC2: =AB2 -> -0.0047965401 | AD2: =AC2 -> -0.0047965401 | AE2: =AD2 -> -0.0047965401 | ... AQ2: =AP2 -> -0.0047965401
A3: COGS — % of Revenue | C3: =IFERROR('QTR P&L'!B3/'QTR P&L'!B2,"") -> -0.5240462 | D3: =IFERROR('QTR P&L'!C3/'QTR P&L'!C2,"") -> -0.5887079 | E3: =IFERROR('QTR P&L'!D3/'QTR P&L'!D2,"") -> -0.57579817 | F3: =IFERROR('QTR P&L'!E3/'QTR P&L'!E2,"") -> -0.60284765 | G3: =IFERROR('QTR P&L'!F3/'QTR P&L'!F2,"") -> -0.58801899 | H3: =IFERROR('QTR P&L'!G3/'QTR P&L'!G2,"") -> -0.59596066 | I3: =IFERROR('QTR P&L'!H3/'QTR P&L'!H2,"") -> -0.61486171 | J3: =IFERROR('QTR P&L'!I3/'QTR P&L'!I2,"") -> -0.58216988 | ... W3: =IFERROR('QTR P&L'!V3/'QTR P&L'!V2,"") -> -0.52630718 | X3: =W3 -> -0.52630718 | Y3: =X3 -> -0.52630718 | Z3: =Y3 -> -0.52630718 | AA3: =Z3 -> -0.52630718 | AB3: =AA3 -> -0.52630718 | AC3: =AB3 -> -0.52630718 | AD3: =AC3 -> -0.52630718 | AE3: =AD3 -> -0.52630718 | ... AQ3: =AP3 -> -0.52630718
A4: Sales and Marketing — % of Revenue | C4: =IFERROR('QTR P&L'!B5/'QTR P&L'!B2,"") -> -0.22443504 | D4: =IFERROR('QTR P&L'!C5/'QTR P&L'!C2,"") -> -0.23901269 | E4: =IFERROR('QTR P&L'!D5/'QTR P&L'!D2,"") -> -0.23881905 | F4: =IFERROR('QTR P&L'!E5/'QTR P&L'!E2,"") -> -0.2383445 | G4: =IFERROR('QTR P&L'!F5/'QTR P&L'!F2,"") -> 0 | H4: =IFERROR('QTR P&L'!G5/'QTR P&L'!G2,"") -> -0.23688038 | I4: =IFERROR('QTR P&L'!H5/'QTR P&L'!H2,"") -> -0.21084924 | J4: =IFERROR('QTR P&L'!I5/'QTR P&L'!I2,"") -> -1.0556653 | ... W4: =IFERROR('QTR P&L'!V5/'QTR P&L'!V2,"") -> 0 | X4: =W4 -> 0 | Y4: =X4 -> 0 | Z4: =Y4 -> 0 | AA4: =Z4 -> 0 | AB4: =AA4 -> 0 | AC4: =AB4 -> 0 | AD4: =AC4 -> 0 | AE4: =AD4 -> 0 | ... AQ4: =AP4 -> 0
A5: General and Administrative — % of Revenue | C5: =IFERROR('QTR P&L'!B6/'QTR P&L'!B2,"") -> -0.12900483 | D5: =IFERROR('QTR P&L'!C6/'QTR P&L'!C2,"") -> -0.15603078 | E5: =IFERROR('QTR P&L'!D6/'QTR P&L'!D2,"") -> -0.14704207 | F5: =IFERROR('QTR P&L'!E6/'QTR P&L'!E2,"") -> -0.11737578 | G5: =IFERROR('QTR P&L'!F6/'QTR P&L'!F2,"") -> 0 | H5: =IFERROR('QTR P&L'!G6/'QTR P&L'!G2,"") -> -0.091320059 | I5: =IFERROR('QTR P&L'!H6/'QTR P&L'!H2,"") -> -0.093585249 | J5: =IFERROR('QTR P&L'!I6/'QTR P&L'!I2,"") -> -0.14630881 | ... W5: =IFERROR('QTR P&L'!V6/'QTR P&L'!V2,"") -> 0 | X5: =W5 -> 0 | Y5: =X5 -> 0 | Z5: =Y5 -> 0 | AA5: =Z5 -> 0 | AB5: =AA5 -> 0 | AC5: =AB5 -> 0 | AD5: =AC5 -> 0 | AE5: =AD5 -> 0 | ... AQ5: =AP5 -> 0
A6: Operating Expenses — % of Revenue | C6: =IFERROR('QTR P&L'!B7/'QTR P&L'!B2,"") -> -0.35343987 | D6: =IFERROR('QTR P&L'!C7/'QTR P&L'!C2,"") -> -0.39504347 | E6: =IFERROR('QTR P&L'!D7/'QTR P&L'!D2,"") -> -0.38586112 | F6: =IFERROR('QTR P&L'!E7/'QTR P&L'!E2,"") -> -0.35572028 | G6: =IFERROR('QTR P&L'!F7/'QTR P&L'!F2,"") -> 0 | H6: =IFERROR('QTR P&L'!G7/'QTR P&L'!G2,"") -> -0.32820044 | I6: =IFERROR('QTR P&L'!H7/'QTR P&L'!H2,"") -> -0.30443449 | J6: =IFERROR('QTR P&L'!I7/'QTR P&L'!I2,"") -> -1.2019742 | ... W6: =IFERROR('QTR P&L'!V7/'QTR P&L'!V2,"") -> 0 | X6: =W6 -> 0 | Y6: =X6 -> 0 | Z6: =Y6 -> 0 | AA6: =Z6 -> 0 | AB6: =AA6 -> 0 | AC6: =AB6 -> 0 | AD6: =AC6 -> 0 | AE6: =AD6 -> 0 | ... AQ6: =AP6 -> 0
A7: SG&A — % of Revenue | C7: =IFERROR('QTR P&L'!B8/'QTR P&L'!B2,"") -> 0 | D7: =IFERROR('QTR P&L'!C8/'QTR P&L'!C2,"") -> 0 | E7: =IFERROR('QTR P&L'!D8/'QTR P&L'!D2,"") -> 0 | F7: =IFERROR('QTR P&L'!E8/'QTR P&L'!E2,"") -> 0 | G7: =IFERROR('QTR P&L'!F8/'QTR P&L'!F2,"") -> 0.00063069666 | H7: =IFERROR('QTR P&L'!G8/'QTR P&L'!G2,"") -> 0 | I7: =IFERROR('QTR P&L'!H8/'QTR P&L'!H2,"") -> 0 | J7: =IFERROR('QTR P&L'!I8/'QTR P&L'!I2,"") -> 0 | ... W7: =IFERROR('QTR P&L'!V8/'QTR P&L'!V2,"") -> -0.3256678 | X7: =W7 -> -0.3256678 | Y7: =X7 -> -0.3256678 | Z7: =Y7 -> -0.3256678 | AA7: =Z7 -> -0.3256678 | AB7: =AA7 -> -0.3256678 | AC7: =AB7 -> -0.3256678 | AD7: =AC7 -> -0.3256678 | AE7: =AD7 -> -0.3256678 | ... AQ7: =AP7 -> -0.3256678
A8: Distributor Termination Fees | C8: ='QTR P&L'!B9 -> 0 | D8: ='QTR P&L'!C9 -> 0 | E8: ='QTR P&L'!D9 -> 0 | F8: ='QTR P&L'!E9 -> 0 | G8: ='QTR P&L'!F9 -> 0 | H8: ='QTR P&L'!G9 -> 0 | I8: ='QTR P&L'!H9 -> 0 | J8: ='QTR P&L'!I9 -> 0 | ... W8: ='QTR P&L'!V9 -> -80754 | X8: 0 | Y8: 0 | Z8: 0 | AA8: 0 | AB8: 0 | AC8: 0 | AD8: 0 | AE8: 0 | AF8: 0 | AG8: 0 | AH8: 0 | AI8: 0 | AJ8: 0 | AK8: 0 | AL8: 0 | AM8: 0 | AN8: 0 | AO8: 0 | AP8: 0 | AQ8: 0
A9: Interest Income (Expense) | C9: ='QTR P&L'!B11 -> -247399 | D9: ='QTR P&L'!C11 -> 85 | E9: ='QTR P&L'!D11 -> 160056 | F9: ='QTR P&L'!E11 -> 71949 | G9: ='QTR P&L'!F11 -> -231783 | H9: ='QTR P&L'!G11 -> 76 | I9: ='QTR P&L'!H11 -> 53 | J9: ='QTR P&L'!I11 -> 1450 | ... W9: ='QTR P&L'!V11 -> -8300 | X9: =W9 -> -8300 | Y9: =X9 -> -8300 | Z9: =Y9 -> -8300 | AA9: =Z9 -> -8300 | AB9: =AA9 -> -8300 | AC9: =AB9 -> -8300 | AD9: =AC9 -> -8300 | AE9: =AD9 -> -8300 | ... AQ9: =AP9 -> -8300
A10: Foreign Currency Gain (Loss) | C10: ='QTR P&L'!B12 -> 550510 | D10: ='QTR P&L'!C12 -> -301 | E10: ='QTR P&L'!D12 -> -123335 | F10: ='QTR P&L'!E12 -> -327581 | G10: ='QTR P&L'!F12 -> 450941 | H10: ='QTR P&L'!G12 -> -162 | I10: ='QTR P&L'!H12 -> -514 | J10: ='QTR P&L'!I12 -> -254 | ... W10: ='QTR P&L'!V12 -> 0 | X10: =W10 -> 0 | Y10: =X10 -> 0 | Z10: =Y10 -> 0 | AA10: =Z10 -> 0 | AB10: =AA10 -> 0 | AC10: =AB10 -> 0 | AD10: =AC10 -> 0 | AE10: =AD10 -> 0 | ... AQ10: =AP10 -> 0
A11: Other Income (Expense) | C11: ='QTR P&L'!B13 -> -62817 | D11: ='QTR P&L'!C13 -> -12 | E11: ='QTR P&L'!D13 -> 97050 | F11: ='QTR P&L'!E13 -> -97038 | G11: ='QTR P&L'!F13 -> 0 | H11: ='QTR P&L'!G13 -> 0 | I11: ='QTR P&L'!H13 -> 0 | J11: ='QTR P&L'!I13 -> 0 | ... W11: ='QTR P&L'!V13 -> 4841 | X11: =W11 -> 4841 | Y11: =X11 -> 4841 | Z11: =Y11 -> 4841 | AA11: =Z11 -> 4841 | AB11: =AA11 -> 4841 | AC11: =AB11 -> 4841 | AD11: =AC11 -> 4841 | AE11: =AD11 -> 4841 | ... AQ11: =AP11 -> 4841
A12: Gain (Loss) on Lease Cancellations | C12: ='QTR P&L'!B14 -> 0 | D12: ='QTR P&L'!C14 -> 0 | E12: ='QTR P&L'!D14 -> 0 | F12: ='QTR P&L'!E14 -> 0 | G12: ='QTR P&L'!F14 -> 0 | H12: ='QTR P&L'!G14 -> 0 | I12: ='QTR P&L'!H14 -> 0 | J12: ='QTR P&L'!I14 -> 0 | ... W12: ='QTR P&L'!V14 -> 0 | X12: =W12 -> 0 | Y12: =X12 -> 0 | Z12: =Y12 -> 0 | AA12: =Z12 -> 0 | AB12: =AA12 -> 0 | AC12: =AB12 -> 0 | AD12: =AC12 -> 0 | AE12: =AD12 -> 0 | ... AQ12: =AP12 -> 0
A13: Income Tax (Expense) Benefit — Effective Tax Rate % | C13: =IFERROR('QTR P&L'!B16/'QTR P&L'!B15,"") -> 0 | D13: =IFERROR('QTR P&L'!C16/'QTR P&L'!C15,"") -> 0 | E13: =IFERROR('QTR P&L'!D16/'QTR P&L'!D15,"") -> 0 | F13: =IFERROR('QTR P&L'!E16/'QTR P&L'!E15,"") -> 0.027626841 | G13: =IFERROR('QTR P&L'!F16/'QTR P&L'!F15,"") -> 0.012017706 | H13: =IFERROR('QTR P&L'!G16/'QTR P&L'!G15,"") -> 0.099294773 | I13: =IFERROR('QTR P&L'!H16/'QTR P&L'!H15,"") -> 0.080469645 | J13: =IFERROR('QTR P&L'!I16/'QTR P&L'!I15,"") -> 0.095240906 | ... W13: =IFERROR('QTR P&L'!V16/'QTR P&L'!V15,"") -> 0.094355481 | X13: =W13 -> 0.094355481 | Y13: =X13 -> 0.094355481 | Z13: =Y13 -> 0.094355481 | AA13: =Z13 -> 0.094355481 | AB13: =AA13 -> 0.094355481 | AC13: =AB13 -> 0.094355481 | AD13: =AC13 -> 0.094355481 | AE13: =AD13 -> 0.094355481 | ... AQ13: =AP13 -> 0.094355481
A14: Preferred Dividends | X14: ='QTR CF'!W46 -> -14307 | Y14: ='QTR CF'!X46 -> -14307 | Z14: ='QTR CF'!Y46 -> -14307 | AA14: ='QTR CF'!Z46 -> -14307 | AB14: ='QTR CF'!AA46 -> -14307 | AC14: ='QTR CF'!AB46 -> -14307 | AD14: ='QTR CF'!AC46 -> -14307 | AE14: ='QTR CF'!AD46 -> -14307 | ... AQ14: ='QTR CF'!AP46 -> -14307
A15: Income Allocated to Participating Preferred | C15: ='QTR P&L'!B19 -> 0 | D15: ='QTR P&L'!C19 -> 0 | E15: ='QTR P&L'!D19 -> 0 | F15: ='QTR P&L'!E19 -> 0 | G15: ='QTR P&L'!F19 -> 0 | H15: ='QTR P&L'!G19 -> 0 | I15: ='QTR P&L'!H19 -> 0 | J15: ='QTR P&L'!I19 -> 0 | ... W15: ='QTR P&L'!V19 -> -1282 | X15: =W15 -> -1282 | Y15: =X15 -> -1282 | Z15: =Y15 -> -1282 | AA15: =Z15 -> -1282 | AB15: =AA15 -> -1282 | AC15: =AB15 -> -1282 | AD15: =AC15 -> -1282 | AE15: =AD15 -> -1282 | ... AQ15: =AP15 -> -1282

Sheet BS DRIVERS
A1: Driver | B1: Q2 FY2021 | C1: Q3 FY2021 | D1: Q1 FY2022 | E1: Q2 FY2022 | F1: Q3 FY2022 | G1: Q4 FY2022 | H1: Q1 FY2023 | I1: Q2 FY2023 | J1: Q3 FY2023 | K1: Q4 FY2023 | L1: Q1 FY2024 | M1: Q2 FY2024 | N1: Q3 FY2024 | O1: Q4 FY2024 | P1: Q1 FY2025 | Q1: Q2 FY2025 | R1: Q3 FY2025 | S1: Q4 FY2025 | T1: Q1 FY2026E | U1: Q2 FY2026E | V1: Q3 FY2026E | W1: Q4 FY2026E | X1: Q1 FY2027E | Y1: Q2 FY2027E | Z1: Q3 FY2027E | AA1: Q4 FY2027E | AB1: Q1 FY2028E | AC1: Q2 FY2028E | AD1: Q3 FY2028E | AE1: Q4 FY2028E | AF1: Q1 FY2029E | AG1: Q2 FY2029E | AH1: Q3 FY2029E | AI1: Q4 FY2029E | AJ1: Q1 FY2030E | AK1: Q2 FY2030E | AL1: Q3 FY2030E | AM1: Q4 FY2030E
