Workbook

Sheet ASSUMPTIONS
A1: Assumption | B1: Value | C1: Note
A2: Days in Quarter | B2: 91 | C2: Used by DSO/DIO/DPO ratios. Approximation; varies 89-92 by quarter.

Sheet ANNL P&L
B1: FY2021 | C1: FY2022 | D1: FY2023 | E1: FY2024 | F1: FY2025 | G1: FY2026E | H1: FY2027E | I1: FY2028E | J1: FY2029E | K1: FY2030E | L1: FY2031E
A2: Net Sales / Revenue | B2: 314272 | C2: 653604 | D2: 1318014 | E2: 1355630 | F2: 2515269 | G2: ='QTR P&L'!R2+'QTR P&L'!S2+'QTR P&L'!T2+'QTR P&L'!U2 | H2: ='QTR P&L'!V2+'QTR P&L'!W2+'QTR P&L'!X2+'QTR P&L'!Y2 | I2: ='QTR P&L'!Z2+'QTR P&L'!AA2+'QTR P&L'!AB2+'QTR P&L'!AC2 | J2: ='QTR P&L'!AD2+'QTR P&L'!AE2+'QTR P&L'!AF2+'QTR P&L'!AG2
A3: COGS | B3: -186103 | C3: -382735 | D3: -684875 | E3: -675423 | F3: -1247936 | G3: ='QTR P&L'!R3+'QTR P&L'!S3+'QTR P&L'!T3+'QTR P&L'!U3 | H3: ='QTR P&L'!V3+'QTR P&L'!W3+'QTR P&L'!X3+'QTR P&L'!Y3 | I3: ='QTR P&L'!Z3+'QTR P&L'!AA3+'QTR P&L'!AB3+'QTR P&L'!AC3 | J3: ='QTR P&L'!AD3+'QTR P&L'!AE3+'QTR P&L'!AF3+'QTR P&L'!AG3
A4: Gross Profit (Loss) | B4: =B2+B3 | C4: =C2+C3 | D4: =D2+D3 | E4: =E2+E3 | F4: =F2+F3 | G4: =G2+G3 | H4: =H2+H3 | I4: =I2+I3 | ... L4: =L2+L3
A5: SG&A | B5: -132259 | C5: -428670 | D5: -366773 | E5: -524479 | F5: -798810 | G5: ='QTR P&L'!R5+'QTR P&L'!S5+'QTR P&L'!T5+'QTR P&L'!U5 | H5: ='QTR P&L'!V5+'QTR P&L'!W5+'QTR P&L'!X5+'QTR P&L'!Y5 | I5: ='QTR P&L'!Z5+'QTR P&L'!AA5+'QTR P&L'!AB5+'QTR P&L'!AC5 | J5: ='QTR P&L'!AD5+'QTR P&L'!AE5+'QTR P&L'!AF5+'QTR P&L'!AG5
A6: Distributor Termination Fees | B6: 0 | C6: 0 | D6: 0 | E6: 0 | F6: -327461 | G6: ='QTR P&L'!R6+'QTR P&L'!S6+'QTR P&L'!T6+'QTR P&L'!U6 | H6: ='QTR P&L'!V6+'QTR P&L'!W6+'QTR P&L'!X6+'QTR P&L'!Y6 | I6: ='QTR P&L'!Z6+'QTR P&L'!AA6+'QTR P&L'!AB6+'QTR P&L'!AC6 | J6: ='QTR P&L'!AD6+'QTR P&L'!AE6+'QTR P&L'!AF6+'QTR P&L'!AG6
A7: Income (Loss) from Operations | B7: =B4+SUM(B5:B6) | C7: =C4+SUM(C5:C6) | D7: =D4+SUM(D5:D6) | E7: =E4+SUM(E5:E6) | F7: =F4+SUM(F5:F6) | G7: =G4+SUM(G5:G6) | H7: =H4+SUM(H5:H6) | I7: =I4+SUM(I5:I6) | ... L7: =L4+SUM(L5:L6)
A8: Interest Income (Expense) | B8: 307 | C8: 5529 | D8: 26629 | E8: 39263 | F8: -27892 | G8: ='QTR P&L'!R8+'QTR P&L'!S8+'QTR P&L'!T8+'QTR P&L'!U8 | H8: ='QTR P&L'!V8+'QTR P&L'!W8+'QTR P&L'!X8+'QTR P&L'!Y8 | I8: ='QTR P&L'!Z8+'QTR P&L'!AA8+'QTR P&L'!AB8+'QTR P&L'!AC8 | J8: ='QTR P&L'!AD8+'QTR P&L'!AE8+'QTR P&L'!AF8+'QTR P&L'!AG8
A9: Foreign Currency Gain (Loss) | B9: -276 | C9: -392 | D9: -1246 | E9: -1734 | F9: 0 | G9: ='QTR P&L'!R9+'QTR P&L'!S9+'QTR P&L'!T9+'QTR P&L'!U9 | H9: ='QTR P&L'!V9+'QTR P&L'!W9+'QTR P&L'!X9+'QTR P&L'!Y9 | I9: ='QTR P&L'!Z9+'QTR P&L'!AA9+'QTR P&L'!AB9+'QTR P&L'!AC9 | J9: ='QTR P&L'!AD9+'QTR P&L'!AE9+'QTR P&L'!AF9+'QTR P&L'!AG9
A10: Other Income (Expense) | B10: 0 | C10: 0 | D10: 0 | E10: 1793 | F10: 11863 | G10: ='QTR P&L'!R10+'QTR P&L'!S10+'QTR P&L'!T10+'QTR P&L'!U10 | H10: ='QTR P&L'!V10+'QTR P&L'!W10+'QTR P&L'!X10+'QTR P&L'!Y10 | I10: ='QTR P&L'!Z10+'QTR P&L'!AA10+'QTR P&L'!AB10+'QTR P&L'!AC10 | J10: ='QTR P&L'!AD10+'QTR P&L'!AE10+'QTR P&L'!AF10+'QTR P&L'!AG10
A11: Pre-Tax Income (Loss) | B11: =B7+SUM(B8:B10) | C11: =C7+SUM(C8:C10) | D11: =D7+SUM(D8:D10) | E11: =E7+SUM(E8:E10) | F11: =F7+SUM(F8:F10) | G11: =G7+SUM(G8:G10) | H11: =H7+SUM(H8:H10) | I11: =I7+SUM(I8:I10) | ... L11: =L7+SUM(L8:L10)
A12: Income Tax (Expense) Benefit | B12: 7996 | C12: -34618 | D12: -64948 | E12: -49976 | F12: -17034 | G12: ='QTR P&L'!R12+'QTR P&L'!S12+'QTR P&L'!T12+'QTR P&L'!U12 | H12: ='QTR P&L'!V12+'QTR P&L'!W12+'QTR P&L'!X12+'QTR P&L'!Y12 | I12: ='QTR P&L'!Z12+'QTR P&L'!AA12+'QTR P&L'!AB12+'QTR P&L'!AC12 | J12: ='QTR P&L'!AD12+'QTR P&L'!AE12+'QTR P&L'!AF12+'QTR P&L'!AG12
A13: Net Income (Loss) | B13: =B11+B12 | C13: =C11+C12 | D13: =D11+D12 | E13: =E11+E12 | F13: =F11+F12 | G13: =G11+G12 | H13: =H11+H12 | I13: =I11+I12 | ... L13: =L11+L12
A14: Preferred Dividends | B14: 0 | C14: -11526 | D14: -27462 | E14: -27500 | F14: -37608 | G14: ='QTR P&L'!R14+'QTR P&L'!S14+'QTR P&L'!T14+'QTR P&L'!U14 | H14: ='QTR P&L'!V14+'QTR P&L'!W14+'QTR P&L'!X14+'QTR P&L'!Y14 | I14: ='QTR P&L'!Z14+'QTR P&L'!AA14+'QTR P&L'!AB14+'QTR P&L'!AC14 | J14: ='QTR P&L'!AD14+'QTR P&L'!AE14+'QTR P&L'!AF14+'QTR P&L'!AG14
A15: Income Allocated to Participating Preferred | B15: 0 | C15: 0 | D15: 17348 | E15: 10117 | F15: 6554 | G15: ='QTR P&L'!R15+'QTR P&L'!S15+'QTR P&L'!T15+'QTR P&L'!U15 | H15: ='QTR P&L'!V15+'QTR P&L'!W15+'QTR P&L'!X15+'QTR P&L'!Y15 | I15: ='QTR P&L'!Z15+'QTR P&L'!AA15+'QTR P&L'!AB15+'QTR P&L'!AC15 | J15: ='QTR P&L'!AD15+'QTR P&L'!AE15+'QTR P&L'!AF15+'QTR P&L'!AG15
A16: Net Income (Loss) Attributable to Common Shareholders | B16: 3937 | C16: -198808 | D16: 181991 | E16: 107457 | F16: 63837 | G16: ='QTR P&L'!R16+'QTR P&L'!S16+'QTR P&L'!T16+'QTR P&L'!U16 | H16: ='QTR P&L'!V16+'QTR P&L'!W16+'QTR P&L'!X16+'QTR P&L'!Y16 | I16: ='QTR P&L'!Z16+'QTR P&L'!AA16+'QTR P&L'!AB16+'QTR P&L'!AC16 | J16: ='QTR P&L'!AD16+'QTR P&L'!AE16+'QTR P&L'!AF16+'QTR P&L'!AG16

Sheet BALANCE SHEET
B1: FY2022 | C1: FY2023 | D1: FY2024 | E1: FY2025 | F1: FY2026E | G1: FY2027E | H1: FY2028E | I1: FY2029E | J1: FY2030E | K1: FY2031E
A2: Cash & Cash Equivalents | B2: 614159 | C2: 755981 | D2: 890190 | E2: 398866 | F2: ='QTR BS'!R2 | G2: ='QTR BS'!V2 | H2: ='QTR BS'!Z2 | I2: ='QTR BS'!AD2
A3: Restricted Cash | B3: 38768 | C3: 0 | D3: 0 | E3: 141121 | F3: ='QTR BS'!R3 | G3: ='QTR BS'!V3 | H3: ='QTR BS'!Z3 | I3: ='QTR BS'!AD3
A4: Accounts Receivable | B4: 63311 | C4: 183703 | D4: 270342 | E4: 755499 | F4: ='QTR BS'!R4 | G4: ='QTR BS'!V4 | H4: ='QTR BS'!Z4 | I4: ='QTR BS'!AD4
A5: Note Receivable - Current | B5: 2979 | C5: 2318 | D5: 0 | E5: 0 | F5: ='QTR BS'!R5 | G5: ='QTR BS'!V5 | H5: ='QTR BS'!Z5 | I5: ='QTR BS'!AD5
A6: Inventories | B6: 173289 | C6: 229275 | D6: 131165 | E6: 337698 | F6: ='QTR BS'!R6 | G6: ='QTR BS'!V6 | H6: ='QTR BS'!Z6 | I6: ='QTR BS'!AD6
A7: Prepaid Expenses | B7: 11341 | C7: 19503 | D7: 18759 | E7: 128806 | F7: ='QTR BS'!R7 | G7: ='QTR BS'!V7 | H7: ='QTR BS'!Z7 | I7: ='QTR BS'!AD7
A8: Deferred Other Costs - Current | B8: 14124 | C8: 14124 | D8: 14124 | E8: 49164 | F8: ='QTR BS'!R8 | G8: ='QTR BS'!V8 | H8: ='QTR BS'!Z8 | I8: ='QTR BS'!AD8
A9: Total Current Assets | B9: =SUM(B2:B8) | C9: =SUM(C2:C8) | D9: =SUM(D2:D8) | E9: =SUM(E2:E8) | F9: =SUM(F2:F8) | G9: =SUM(G2:G8) | H9: =SUM(H2:H8) | I9: =SUM(I2:I8) | ... K9: =SUM(K2:K8)
A10: Note Receivable - Non-Current | B10: 3574 | C10: 0 | D10: 0 | E10: 0 | F10: ='QTR BS'!R10 | G10: ='QTR BS'!V10 | H10: ='QTR BS'!Z10 | I10: ='QTR BS'!AD10
A11: Net PP&E | B11: 10185 | C11: 24868 | D11: 55602 | E11: 87910 | F11: ='QTR BS'!R11 | G11: ='QTR BS'!V11 | H11: ='QTR BS'!Z11 | I11: ='QTR BS'!AD11
A12: ROU Assets - Operating - Non-Current | B12: 972 | C12: 1957 | D12: 21606 | E12: 0 | F12: ='QTR BS'!R12 | G12: ='QTR BS'!V12 | H12: ='QTR BS'!Z12 | I12: ='QTR BS'!AD12
A13: ROU Assets - Finance - Non-Current | B13: 208 | C13: 208 | D13: 230 | E13: 0 | F13: ='QTR BS'!R17 | G13: ='QTR BS'!V17 | H13: ='QTR BS'!Z17 | I13: ='QTR BS'!AD17
A14: Intangible Assets | B14: 12254 | C14: 12139 | D14: 12213 | E14: 1391915 | F14: ='QTR BS'!R13 | G14: ='QTR BS'!V13 | H14: ='QTR BS'!Z13 | I14: ='QTR BS'!AD13
A15: Goodwill | B15: 13679 | C15: 14173 | D15: 71582 | E15: 917560 | F15: ='QTR BS'!R14 | G15: ='QTR BS'!V14 | H15: ='QTR BS'!Z14 | I15: ='QTR BS'!AD14
A16: Deferred Other Costs - Non-Current | B16: 262462 | C16: 248338 | D16: 234215 | E16: 771635 | F16: ='QTR BS'!R15 | G16: ='QTR BS'!V15 | H16: ='QTR BS'!Z15 | I16: ='QTR BS'!AD15
A17: Deferred Tax Assets | B17: 501 | C17: 29518 | D17: 38699 | E17: 96013 | F17: ='QTR BS'!R16 | G17: ='QTR BS'!V16 | H17: ='QTR BS'!Z16 | I17: ='QTR BS'!AD16
A18: Other Non-Current Assets | B18: 263 | C18: 291 | D18: 8154 | E18: 43434 | F18: ='QTR BS'!R18 | G18: ='QTR BS'!V18 | H18: ='QTR BS'!Z18 | I18: ='QTR BS'!AD18
A19: Total Assets | B19: =B9+SUM(B10:B18) | C19: =C9+SUM(C10:C18) | D19: =D9+SUM(D10:D18) | E19: =E9+SUM(E10:E18) | F19: =F9+SUM(F10:F18) | G19: =G9+SUM(G10:G18) | H19: =H9+SUM(H10:H18) | I19: =I9+SUM(I10:I18) | ... K19: =K9+SUM(K10:K18)
A20: Accounts Payable | B20: 36248 | C20: 42840 | D20: 41287 | E20: 137930 | F20: ='QTR BS'!R20 | G20: ='QTR BS'!V20 | H20: ='QTR BS'!Z20 | I20: ='QTR BS'!AD20
A21: Accrued Expenses | B21: 69899 | C21: 62120 | D21: 148780 | E21: 230721 | F21: ='QTR BS'!R21 | G21: ='QTR BS'!V21 | H21: ='QTR BS'!Z21 | I21: ='QTR BS'!AD21
A22: Income Taxes Payable | B22: 1193 | C22: 50424 | D22: 10834 | E22: 49612 | F22: ='QTR BS'!R22 | G22: ='QTR BS'!V22 | H22: ='QTR BS'!Z22 | I22: ='QTR BS'!AD22
A23: Accrued Distributor Termination Fees | B23: 3986 | C23: 0 | D23: 0 | E23: 264088 | F23: ='QTR BS'!R23 | G23: ='QTR BS'!V23 | H23: ='QTR BS'!Z23 | I23: ='QTR BS'!AD23
A24: Accrued Promotional Allowance | B24: 35977 | C24: 99787 | D24: 135948 | E24: 307922 | F24: ='QTR BS'!R24 | G24: ='QTR BS'!V24 | H24: ='QTR BS'!Z24 | I24: ='QTR BS'!AD24
A25: Lease Liability - Operating - Current | B25: 661 | C25: 980 | D25: 3265 | E25: 0 | F25: ='QTR BS'!R25 | G25: ='QTR BS'!V25 | H25: ='QTR BS'!Z25 | I25: ='QTR BS'!AD25
A26: Lease Liability - Finance - Current | B26: 70 | C26: 59 | D26: 100 | E26: 0 | F26: ='QTR BS'!R26 | G26: ='QTR BS'!V26 | H26: ='QTR BS'!Z26 | I26: ='QTR BS'!AD26
A27: Contingent Consideration - Current | B27: 0 | C27: 0 | D27: 0 | E27: 25000 | F27: ='QTR BS'!R27 | G27: ='QTR BS'!V27 | H27: ='QTR BS'!Z27 | I27: ='QTR BS'!AD27
A28: Deferred Revenue - Current | B28: 9675 | C28: 9513 | D28: 9513 | E28: 26988 | F28: ='QTR BS'!R28 | G28: ='QTR BS'!V28 | H28: ='QTR BS'!Z28 | I28: ='QTR BS'!AD28
A29: Other Current Liabilities | B29: 3586 | C29: 10890 | D29: 15808 | E29: 36465 | F29: ='QTR BS'!R29 | G29: ='QTR BS'!V29 | H29: ='QTR BS'!Z29 | I29: ='QTR BS'!AD29
A30: Total Current Liabilities | B30: =SUM(B20:B29) | C30: =SUM(C20:C29) | D30: =SUM(D20:D29) | E30: =SUM(E20:E29) | F30: =SUM(F20:F29) | G30: =SUM(G20:G29) | H30: =SUM(H20:H29) | I30: =SUM(I20:I29) | ... K30: =SUM(K20:K29)
A31: Lease Liability - Operating - Non-Current | B31: 326 | C31: 955 | D31: 16674 | E31: 0 | F31: ='QTR BS'!R31 | G31: ='QTR BS'!V31 | H31: ='QTR BS'!Z31 | I31: ='QTR BS'!AD31
A32: Lease Liability - Finance - Non-Current | B32: 162 | C32: 193 | D32: 211 | E32: 0 | F32: ='QTR BS'!R32 | G32: ='QTR BS'!V32 | H32: ='QTR BS'!Z32 | I32: ='QTR BS'!AD32
A33: Deferred Tax Liability | B33: 15919 | C33: 2880 | D33: 2330 | E33: 0 | F33: ='QTR BS'!R33 | G33: ='QTR BS'!V33 | H33: ='QTR BS'!Z33 | I33: ='QTR BS'!AD33
A34: Long-Term Debt | B34: 0 | C34: 0 | D34: 0 | E34: 669926 | F34: ='QTR BS'!R34 | G34: ='QTR BS'!V34 | H34: ='QTR BS'!Z34 | I34: ='QTR BS'!AD34
A35: Deferred Revenue - Non-Current | B35: 179788 | C35: 167227 | D35: 157714 | E35: 401155 | F35: ='QTR BS'!R35 | G35: ='QTR BS'!V35 | H35: ='QTR BS'!Z35 | I35: ='QTR BS'!AD35
A36: Other Non-Current Liabilities | B36: 0 | C36: 0 | D36: 0 | E36: 28372 | F36: ='QTR BS'!R36 | G36: ='QTR BS'!V36 | H36: ='QTR BS'!Z36 | I36: ='QTR BS'!AD36
A37: Total Liabilities | B37: =B30+SUM(B31:B36) | C37: =C30+SUM(C31:C36) | D37: =D30+SUM(D31:D36) | E37: =E30+SUM(E31:E36) | F37: =F30+SUM(F31:F36) | G37: =G30+SUM(G31:G36) | H37: =H30+SUM(H31:H36) | I37: =I30+SUM(I31:I36) | ... K37: =K30+SUM(K31:K36)
A38: Convertible Preferred Stock | B38: 824488 | C38: 824488 | D38: 824488 | E38: 1759975 | F38: ='QTR BS'!R38 | G38: ='QTR BS'!V38 | H38: ='QTR BS'!Z38 | I38: ='QTR BS'!AD38
A39: Common Stock | B39: 76 | C39: 77 | D39: 79 | E39: 101 | F39: ='QTR BS'!R39 | G39: ='QTR BS'!V39 | H39: ='QTR BS'!Z39 | I39: ='QTR BS'!AD39
A40: Treasury Stock | B40: 0 | C40: 0 | D40: 0 | E40: -48226 | F40: ='QTR BS'!R40 | G40: ='QTR BS'!V40 | H40: ='QTR BS'!Z40 | I40: ='QTR BS'!AD40
A41: Additional Paid-in Capital | B41: 280668 | C41: 276717 | D41: 297579 | E41: 1050518 | F41: ='QTR BS'!R41 | G41: ='QTR BS'!V41 | H41: ='QTR BS'!Z41 | I41: ='QTR BS'!AD41
A42: Accumulated Other Comprehensive Income (Loss) | B42: -1881 | C42: -701 | D42: -3250 | E42: 3162 | F42: ='QTR BS'!R42 | G42: ='QTR BS'!V42 | H42: ='QTR BS'!Z42 | I42: ='QTR BS'!AD42
A43: Retained Earnings (Accumulated Deficit) | B43: -238772 | C43: -12053 | D43: 105521 | E43: 175912 | F43: ='QTR BS'!R43 | G43: ='QTR BS'!V43 | H43: ='QTR BS'!Z43 | I43: ='QTR BS'!AD43
A44: Total Stockholders' Equity | B44: =SUM(B38:B43) | C44: =SUM(C38:C43) | D44: =SUM(D38:D43) | E44: =SUM(E38:E43) | F44: =SUM(F38:F43) | G44: =SUM(G38:G43) | H44: =SUM(H38:H43) | I44: =SUM(I38:I43) | ... K44: =SUM(K38:K43)
A45: Total Liabilities, Mezzanine & Stockholders' Equity | B45: =B37+B44 | C45: =C37+C44 | D45: =D37+D44 | E45: =E37+E44 | F45: =F37+F44 | G45: =G37+G44 | H45: =H37+H44 | I45: =I37+I44 | ... K45: =K37+K44

Sheet CASH FLOW
B1: FY2021 | C1: FY2022 | D1: FY2023 | E1: FY2024 | F1: FY2025 | G1: FY2026E | H1: FY2027E | I1: FY2028E | J1: FY2029E | K1: FY2030E | L1: FY2031E
A2: Net Income (Loss) | B2: 3937 | C2: -187282 | D2: 226801 | E2: 145074 | F2: 107999 | G2: ='QTR CF'!R2+'QTR CF'!S2+'QTR CF'!T2+'QTR CF'!U2 | H2: ='QTR CF'!V2+'QTR CF'!W2+'QTR CF'!X2+'QTR CF'!Y2 | I2: ='QTR CF'!Z2+'QTR CF'!AA2+'QTR CF'!AB2+'QTR CF'!AC2 | J2: ='QTR CF'!AD2+'QTR CF'!AE2+'QTR CF'!AF2+'QTR CF'!AG2
A3: Depreciation & Amortization | B3: 1264 | C3: 1917 | D3: 3226 | E3: 7274 | F3: 29451 | G3: ='QTR CF'!R6+'QTR CF'!S6+'QTR CF'!T6+'QTR CF'!U6 | H3: ='QTR CF'!V6+'QTR CF'!W6+'QTR CF'!X6+'QTR CF'!Y6 | I3: ='QTR CF'!Z6+'QTR CF'!AA6+'QTR CF'!AB6+'QTR CF'!AC6 | J3: ='QTR CF'!AD6+'QTR CF'!AE6+'QTR CF'!AF6+'QTR CF'!AG6
A4: Impairment of Intangibles | B4: 0 | C4: 2379 | D4: 0 | E4: 0 | F4: 0 | G4: ='QTR CF'!R5+'QTR CF'!S5+'QTR CF'!T5+'QTR CF'!U5 | H4: ='QTR CF'!V5+'QTR CF'!W5+'QTR CF'!X5+'QTR CF'!Y5 | I4: ='QTR CF'!Z5+'QTR CF'!AA5+'QTR CF'!AB5+'QTR CF'!AC5 | J4: ='QTR CF'!AD5+'QTR CF'!AE5+'QTR CF'!AF5+'QTR CF'!AG5
A5: Allowance for Credit Losses | B5: 1494 | C5: 2352 | D5: 2128 | E5: 3294 | F5: 10600 | G5: ='QTR CF'!R7+'QTR CF'!S7+'QTR CF'!T7+'QTR CF'!U7 | H5: ='QTR CF'!V7+'QTR CF'!W7+'QTR CF'!X7+'QTR CF'!Y7 | I5: ='QTR CF'!Z7+'QTR CF'!AA7+'QTR CF'!AB7+'QTR CF'!AC7 | J5: ='QTR CF'!AD7+'QTR CF'!AE7+'QTR CF'!AF7+'QTR CF'!AG7
A6: Amortization of Deferred Other Costs | B6: 0 | C6: 5885 | D6: 14124 | E6: 14124 | F6: 26326 | G6: ='QTR CF'!R8+'QTR CF'!S8+'QTR CF'!T8+'QTR CF'!U8 | H6: ='QTR CF'!V8+'QTR CF'!W8+'QTR CF'!X8+'QTR CF'!Y8 | I6: ='QTR CF'!Z8+'QTR CF'!AA8+'QTR CF'!AB8+'QTR CF'!AC8 | J6: ='QTR CF'!AD8+'QTR CF'!AE8+'QTR CF'!AF8+'QTR CF'!AG8
A7: Inventory Write-Down | B7: 2355 | C7: 6131 | D7: 7312 | E7: 19086 | F7: 29190 | G7: ='QTR CF'!R9+'QTR CF'!S9+'QTR CF'!T9+'QTR CF'!U9 | H7: ='QTR CF'!V9+'QTR CF'!W9+'QTR CF'!X9+'QTR CF'!Y9 | I7: ='QTR CF'!Z9+'QTR CF'!AA9+'QTR CF'!AB9+'QTR CF'!AC9 | J7: ='QTR CF'!AD9+'QTR CF'!AE9+'QTR CF'!AF9+'QTR CF'!AG9
A8: Gain (Loss) on Disposal of PP&E | B8: 0 | C8: 0 | D8: 198 | E8: 173 | F8: 0 | G8: ='QTR CF'!R10+'QTR CF'!S10+'QTR CF'!T10+'QTR CF'!U10 | H8: ='QTR CF'!V10+'QTR CF'!W10+'QTR CF'!X10+'QTR CF'!Y10 | I8: ='QTR CF'!Z10+'QTR CF'!AA10+'QTR CF'!AB10+'QTR CF'!AC10 | J8: ='QTR CF'!AD10+'QTR CF'!AE10+'QTR CF'!AF10+'QTR CF'!AG10
A9: Stock-Based Compensation | B9: 36475 | C9: 20665 | D9: 21226 | E9: 19591 | F9: 28050 | G9: ='QTR CF'!R11+'QTR CF'!S11+'QTR CF'!T11+'QTR CF'!U11 | H9: ='QTR CF'!V11+'QTR CF'!W11+'QTR CF'!X11+'QTR CF'!Y11 | I9: ='QTR CF'!Z11+'QTR CF'!AA11+'QTR CF'!AB11+'QTR CF'!AC11 | J9: ='QTR CF'!AD11+'QTR CF'!AE11+'QTR CF'!AF11+'QTR CF'!AG11
A10: (Benefit) Provision for Deferred Income Taxes | B10: -9201 | C10: 20244 | D10: -42055 | E10: -9730 | F10: -57336 | G10: ='QTR CF'!R12+'QTR CF'!S12+'QTR CF'!T12+'QTR CF'!U12 | H10: ='QTR CF'!V12+'QTR CF'!W12+'QTR CF'!X12+'QTR CF'!Y12 | I10: ='QTR CF'!Z12+'QTR CF'!AA12+'QTR CF'!AB12+'QTR CF'!AC12 | J10: ='QTR CF'!AD12+'QTR CF'!AE12+'QTR CF'!AF12+'QTR CF'!AG12
A11: Foreign Currency Gain (Loss) | B11: 880 | C11: 483 | D11: 1246 | E11: 1734 | F11: 0 | G11: ='QTR CF'!R13+'QTR CF'!S13+'QTR CF'!T13+'QTR CF'!U13 | H11: ='QTR CF'!V13+'QTR CF'!W13+'QTR CF'!X13+'QTR CF'!Y13 | I11: ='QTR CF'!Z13+'QTR CF'!AA13+'QTR CF'!AB13+'QTR CF'!AC13 | J11: ='QTR CF'!AD13+'QTR CF'!AE13+'QTR CF'!AF13+'QTR CF'!AG13
A12: Gain (Loss) on Lease Cancellations | B12: -28 | C12: 0 | D12: 0 | E12: 0 | F12: 0 | G12: ='QTR CF'!R14+'QTR CF'!S14+'QTR CF'!T14+'QTR CF'!U14 | H12: ='QTR CF'!V14+'QTR CF'!W14+'QTR CF'!X14+'QTR CF'!Y14 | I12: ='QTR CF'!Z14+'QTR CF'!AA14+'QTR CF'!AB14+'QTR CF'!AC14 | J12: ='QTR CF'!AD14+'QTR CF'!AE14+'QTR CF'!AF14+'QTR CF'!AG14
A13: Change in Fair Value of Contingent Consideration | B13: 0 | C13: 0 | D13: 0 | E13: 0 | F13: 13800 | G13: ='QTR CF'!R15+'QTR CF'!S15+'QTR CF'!T15+'QTR CF'!U15 | H13: ='QTR CF'!V15+'QTR CF'!W15+'QTR CF'!X15+'QTR CF'!Y15 | I13: ='QTR CF'!Z15+'QTR CF'!AA15+'QTR CF'!AB15+'QTR CF'!AC15 | J13: ='QTR CF'!AD15+'QTR CF'!AE15+'QTR CF'!AF15+'QTR CF'!AG15
A14: Gain (Loss) on Extinguishment of Debt | B14: 0 | C14: 0 | D14: 0 | E14: 0 | F14: 6003 | G14: ='QTR CF'!R16+'QTR CF'!S16+'QTR CF'!T16+'QTR CF'!U16 | H14: ='QTR CF'!V16+'QTR CF'!W16+'QTR CF'!X16+'QTR CF'!Y16 | I14: ='QTR CF'!Z16+'QTR CF'!AA16+'QTR CF'!AB16+'QTR CF'!AC16 | J14: ='QTR CF'!AD16+'QTR CF'!AE16+'QTR CF'!AF16+'QTR CF'!AG16
A15: Other Operating Items | B15: 0 | C15: 37 | D15: -28 | E15: -324 | F15: -1687 | G15: ='QTR CF'!R17+'QTR CF'!S17+'QTR CF'!T17+'QTR CF'!U17 | H15: ='QTR CF'!V17+'QTR CF'!W17+'QTR CF'!X17+'QTR CF'!Y17 | I15: ='QTR CF'!Z17+'QTR CF'!AA17+'QTR CF'!AB17+'QTR CF'!AC17 | J15: ='QTR CF'!AD17+'QTR CF'!AE17+'QTR CF'!AF17+'QTR CF'!AG17
A16: Accounts Receivable | B16: -25249 | C16: -26369 | D16: -121558 | E16: -89665 | F16: -412091 | G16: ='QTR CF'!R18+'QTR CF'!S18+'QTR CF'!T18+'QTR CF'!U18 | H16: ='QTR CF'!V18+'QTR CF'!W18+'QTR CF'!X18+'QTR CF'!Y18 | I16: ='QTR CF'!Z18+'QTR CF'!AA18+'QTR CF'!AB18+'QTR CF'!AC18 | J16: ='QTR CF'!AD18+'QTR CF'!AE18+'QTR CF'!AF18+'QTR CF'!AG18
... A19: Prepaid Expenses | B19: 1072 | C19: 2214 | D19: -7980 | E19: 1074 | F19: -108321 | G19: ='QTR CF'!R21+'QTR CF'!S21+'QTR CF'!T21+'QTR CF'!U21 | H19: ='QTR CF'!V21+'QTR CF'!W21+'QTR CF'!X21+'QTR CF'!Y21 | I19: ='QTR CF'!Z21+'QTR CF'!AA21+'QTR CF'!AB21+'QTR CF'!AC21 | J19: ='QTR CF'!AD21+'QTR CF'!AE21+'QTR CF'!AF21+'QTR CF'!AG21
A20: Other Non-Current Assets | B20: 0 | C20: 0 | D20: 0 | E20: -4862 | F20: 2857 | G20: ='QTR CF'!R23+'QTR CF'!S23+'QTR CF'!T23+'QTR CF'!U23 | H20: ='QTR CF'!V23+'QTR CF'!W23+'QTR CF'!X23+'QTR CF'!Y23 | I20: ='QTR CF'!Z23+'QTR CF'!AA23+'QTR CF'!AB23+'QTR CF'!AC23 | J20: ='QTR CF'!AD23+'QTR CF'!AE23+'QTR CF'!AF23+'QTR CF'!AG23
A21: Accounts Payable | B21: 23966 | C21: 428 | D21: 5249 | E21: -1170 | F21: 51252 | G21: ='QTR CF'!R24+'QTR CF'!S24+'QTR CF'!T24+'QTR CF'!U24 | H21: ='QTR CF'!V24+'QTR CF'!W24+'QTR CF'!X24+'QTR CF'!Y24 | I21: ='QTR CF'!Z24+'QTR CF'!AA24+'QTR CF'!AB24+'QTR CF'!AC24 | J21: ='QTR CF'!AD24+'QTR CF'!AE24+'QTR CF'!AF24+'QTR CF'!AG24
A22: Accrued Expenses | B22: 26484 | C22: 34644 | D22: -8025 | E22: 85398 | F22: 45618 | G22: ='QTR CF'!R25+'QTR CF'!S25+'QTR CF'!T25+'QTR CF'!U25 | H22: ='QTR CF'!V25+'QTR CF'!W25+'QTR CF'!X25+'QTR CF'!Y25 | I22: ='QTR CF'!Z25+'QTR CF'!AA25+'QTR CF'!AB25+'QTR CF'!AC25 | J22: ='QTR CF'!AD25+'QTR CF'!AE25+'QTR CF'!AF25+'QTR CF'!AG25
A23: Other Current Liabilities | B23: 1731 | C23: 2446 | D23: 55407 | E23: -34616 | F23: 48687 | G23: ='QTR CF'!R26+'QTR CF'!S26+'QTR CF'!T26+'QTR CF'!U26 | H23: ='QTR CF'!V26+'QTR CF'!W26+'QTR CF'!X26+'QTR CF'!Y26 | I23: ='QTR CF'!Z26+'QTR CF'!AA26+'QTR CF'!AB26+'QTR CF'!AC26 | J23: ='QTR CF'!AD26+'QTR CF'!AE26+'QTR CF'!AF26+'QTR CF'!AG26
A24: Accrued Promotional Allowance | B24: 13379 | C24: 16940 | D24: 63810 | E24: 36161 | F24: 153635 | G24: ='QTR CF'!R27+'QTR CF'!S27+'QTR CF'!T27+'QTR CF'!U27 | H24: ='QTR CF'!V27+'QTR CF'!W27+'QTR CF'!X27+'QTR CF'!Y27 | I24: ='QTR CF'!Z27+'QTR CF'!AA27+'QTR CF'!AB27+'QTR CF'!AC27 | J24: ='QTR CF'!AD27+'QTR CF'!AE27+'QTR CF'!AF27+'QTR CF'!AG27
A25: Accrued Distributor Termination | B25: 0 | C25: 3986 | D25: -3739 | E25: -248 | F25: 257595 | G25: ='QTR CF'!R28+'QTR CF'!S28+'QTR CF'!T28+'QTR CF'!U28 | H25: ='QTR CF'!V28+'QTR CF'!W28+'QTR CF'!X28+'QTR CF'!Y28 | I25: ='QTR CF'!Z28+'QTR CF'!AA28+'QTR CF'!AB28+'QTR CF'!AC28 | J25: ='QTR CF'!AD28+'QTR CF'!AE28+'QTR CF'!AF28+'QTR CF'!AG28
A26: ROU & Lease Liability, Net | B26: 29 | C26: -183 | D26: -102 | E26: 535 | F26: 0 | G26: ='QTR CF'!R29+'QTR CF'!S29+'QTR CF'!T29+'QTR CF'!U29 | H26: ='QTR CF'!V29+'QTR CF'!W29+'QTR CF'!X29+'QTR CF'!Y29 | I26: ='QTR CF'!Z29+'QTR CF'!AA29+'QTR CF'!AB29+'QTR CF'!AC29 | J26: ='QTR CF'!AD29+'QTR CF'!AE29+'QTR CF'!AF29+'QTR CF'!AG29
A27: Deferred Revenue | B27: 0 | C27: 189463 | D27: -12723 | E27: -9513 | F27: 255110 | G27: ='QTR CF'!R30+'QTR CF'!S30+'QTR CF'!T30+'QTR CF'!U30 | H27: ='QTR CF'!V30+'QTR CF'!W30+'QTR CF'!X30+'QTR CF'!Y30 | I27: ='QTR CF'!Z30+'QTR CF'!AA30+'QTR CF'!AB30+'QTR CF'!AC30 | J27: ='QTR CF'!AD30+'QTR CF'!AE30+'QTR CF'!AF30+'QTR CF'!AG30
A28: Net Change in Other Working Capital | B28: 0 | C28: 0 | D28: 0 | E28: 0 | F28: 2481 | G28: ='QTR CF'!R31+'QTR CF'!S31+'QTR CF'!T31+'QTR CF'!U31 | H28: ='QTR CF'!V31+'QTR CF'!W31+'QTR CF'!X31+'QTR CF'!Y31 | I28: ='QTR CF'!Z31+'QTR CF'!AA31+'QTR CF'!AB31+'QTR CF'!AC31 | J28: ='QTR CF'!AD31+'QTR CF'!AE31+'QTR CF'!AF31+'QTR CF'!AG31
A29: Cash Flow from Operations | B29: =SUM(B2:B28) | C29: =SUM(C2:C28) | D29: =SUM(D2:D28) | E29: =SUM(E2:E28) | F29: =SUM(F2:F28) | G29: =SUM(G2:G28) | H29: =SUM(H2:H28) | I29: =SUM(I2:I28) | ... L29: =SUM(L2:L28)
A30: Collections from Note Receivable | B30: 1886 | C30: 2592 | D30: 3233 | E30: 0 | F30: 0 | G30: ='QTR CF'!R33+'QTR CF'!S33+'QTR CF'!T33+'QTR CF'!U33 | H30: ='QTR CF'!V33+'QTR CF'!W33+'QTR CF'!X33+'QTR CF'!Y33 | I30: ='QTR CF'!Z33+'QTR CF'!AA33+'QTR CF'!AB33+'QTR CF'!AC33 | J30: ='QTR CF'!AD33+'QTR CF'!AE33+'QTR CF'!AF33+'QTR CF'!AG33
A31: Purchase of PP&E | B31: -3150 | C31: -8264 | D31: -17433 | E31: -23390 | F31: -36067 | G31: ='QTR CF'!R34+'QTR CF'!S34+'QTR CF'!T34+'QTR CF'!U34 | H31: ='QTR CF'!V34+'QTR CF'!W34+'QTR CF'!X34+'QTR CF'!Y34 | I31: ='QTR CF'!Z34+'QTR CF'!AA34+'QTR CF'!AB34+'QTR CF'!AC34 | J31: ='QTR CF'!AD34+'QTR CF'!AE34+'QTR CF'!AF34+'QTR CF'!AG34
A32: Purchase of Non-Marketable Equity Securities | B32: 0 | C32: 0 | D32: 0 | E32: -3000 | F32: -10000 | G32: ='QTR CF'!R35+'QTR CF'!S35+'QTR CF'!T35+'QTR CF'!U35 | H32: ='QTR CF'!V35+'QTR CF'!W35+'QTR CF'!X35+'QTR CF'!Y35 | I32: ='QTR CF'!Z35+'QTR CF'!AA35+'QTR CF'!AB35+'QTR CF'!AC35 | J32: ='QTR CF'!AD35+'QTR CF'!AE35+'QTR CF'!AF35+'QTR CF'!AG35
A33: Acquisition of Big Beverages | B33: 0 | C33: 0 | D33: 0 | E33: -75336 | F33: 0 | G33: ='QTR CF'!R36+'QTR CF'!S36+'QTR CF'!T36+'QTR CF'!U36 | H33: ='QTR CF'!V36+'QTR CF'!W36+'QTR CF'!X36+'QTR CF'!Y36 | I33: ='QTR CF'!Z36+'QTR CF'!AA36+'QTR CF'!AB36+'QTR CF'!AC36 | J33: ='QTR CF'!AD36+'QTR CF'!AE36+'QTR CF'!AF36+'QTR CF'!AG36
A34: Acquisitions, Net of Cash Acquired | B34: 0 | C34: 0 | D34: 0 | E34: 0 | F34: -1278769 | G34: ='QTR CF'!R37+'QTR CF'!S37+'QTR CF'!T37+'QTR CF'!U37 | H34: ='QTR CF'!V37+'QTR CF'!W37+'QTR CF'!X37+'QTR CF'!Y37 | I34: ='QTR CF'!Z37+'QTR CF'!AA37+'QTR CF'!AB37+'QTR CF'!AC37 | J34: ='QTR CF'!AD37+'QTR CF'!AE37+'QTR CF'!AF37+'QTR CF'!AG37
A35: Working Capital Estimate from Pepsi (Rockstar) | B35: 0 | C35: 0 | D35: 0 | E35: 0 | F35: 29156 | G35: ='QTR CF'!R38+'QTR CF'!S38+'QTR CF'!T38+'QTR CF'!U38 | H35: ='QTR CF'!V38+'QTR CF'!W38+'QTR CF'!X38+'QTR CF'!Y38 | I35: ='QTR CF'!Z38+'QTR CF'!AA38+'QTR CF'!AB38+'QTR CF'!AC38 | J35: ='QTR CF'!AD38+'QTR CF'!AE38+'QTR CF'!AF38+'QTR CF'!AG38
A36: Cash Flow from Investing | B36: =SUM(B30:B35) | C36: =SUM(C30:C35) | D36: =SUM(D30:D35) | E36: =SUM(E30:E35) | F36: =SUM(F30:F35) | G36: =SUM(G30:G35) | H36: =SUM(H30:H35) | I36: =SUM(I30:I35) | ... L36: =SUM(L30:L35)
A37: Finance Lease Payments | B37: -94 | C37: -63 | D37: -44 | E37: -61 | F37: 0 | G37: ='QTR CF'!R40+'QTR CF'!S40+'QTR CF'!T40+'QTR CF'!U40 | H37: ='QTR CF'!V40+'QTR CF'!W40+'QTR CF'!X40+'QTR CF'!Y40 | I37: ='QTR CF'!Z40+'QTR CF'!AA40+'QTR CF'!AB40+'QTR CF'!AC40 | J37: ='QTR CF'!AD40+'QTR CF'!AE40+'QTR CF'!AF40+'QTR CF'!AG40
A38: Proceeds from Exercise of Stock Options | B38: 3720 | C38: 3683 | D38: 2285 | E38: 3856 | F38: 0 | G38: ='QTR CF'!R41+'QTR CF'!S41+'QTR CF'!T41+'QTR CF'!U41 | H38: ='QTR CF'!V41+'QTR CF'!W41+'QTR CF'!X41+'QTR CF'!Y41 | I38: ='QTR CF'!Z41+'QTR CF'!AA41+'QTR CF'!AB41+'QTR CF'!AC41 | J38: ='QTR CF'!AD41+'QTR CF'!AE41+'QTR CF'!AF41+'QTR CF'!AG41
A39: Proceeds from Issuance of Common Stock | B39: 67769 | C39: 0 | D39: 0 | E39: 0 | F39: 0 | G39: ='QTR CF'!R42+'QTR CF'!S42+'QTR CF'!T42+'QTR CF'!U42 | H39: ='QTR CF'!V42+'QTR CF'!W42+'QTR CF'!X42+'QTR CF'!Y42 | I39: ='QTR CF'!Z42+'QTR CF'!AA42+'QTR CF'!AB42+'QTR CF'!AC42 | J39: ='QTR CF'!AD42+'QTR CF'!AE42+'QTR CF'!AF42+'QTR CF'!AG42
A40: Proceeds from Issuance of Preferred Stock | B40: 0 | C40: 542018 | D40: 0 | E40: 0 | F40: 0 | G40: ='QTR CF'!R43+'QTR CF'!S43+'QTR CF'!T43+'QTR CF'!U43 | H40: ='QTR CF'!V43+'QTR CF'!W43+'QTR CF'!X43+'QTR CF'!Y43 | I40: ='QTR CF'!Z43+'QTR CF'!AA43+'QTR CF'!AB43+'QTR CF'!AC43 | J40: ='QTR CF'!AD43+'QTR CF'!AE43+'QTR CF'!AF43+'QTR CF'!AG43
A41: Preferred Dividends | B41: 0 | C41: -11526 | D41: -27462 | E41: -27500 | F41: -37608 | G41: ='QTR CF'!R44+'QTR CF'!S44+'QTR CF'!T44+'QTR CF'!U44 | H41: ='QTR CF'!V44+'QTR CF'!W44+'QTR CF'!X44+'QTR CF'!Y44 | I41: ='QTR CF'!Z44+'QTR CF'!AA44+'QTR CF'!AB44+'QTR CF'!AC44 | J41: ='QTR CF'!AD44+'QTR CF'!AE44+'QTR CF'!AF44+'QTR CF'!AG44
A42: Share Repurchases | B42: 0 | C42: 0 | D42: 0 | E42: -2261 | F42: -45504 | G42: ='QTR CF'!R45+'QTR CF'!S45+'QTR CF'!T45+'QTR CF'!U45 | H42: ='QTR CF'!V45+'QTR CF'!W45+'QTR CF'!X45+'QTR CF'!Y45 | I42: ='QTR CF'!Z45+'QTR CF'!AA45+'QTR CF'!AB45+'QTR CF'!AC45 | J42: ='QTR CF'!AD45+'QTR CF'!AE45+'QTR CF'!AF45+'QTR CF'!AG45
A43: Proceeds from Issuance of Long-Term Debt | B43: 0 | C43: 0 | D43: 0 | E43: 0 | F43: 900000 | G43: ='QTR CF'!R46+'QTR CF'!S46+'QTR CF'!T46+'QTR CF'!U46 | H43: ='QTR CF'!V46+'QTR CF'!W46+'QTR CF'!X46+'QTR CF'!Y46 | I43: ='QTR CF'!Z46+'QTR CF'!AA46+'QTR CF'!AB46+'QTR CF'!AC46 | J43: ='QTR CF'!AD46+'QTR CF'!AE46+'QTR CF'!AF46+'QTR CF'!AG46
A44: Repayments of Long-Term Debt | B44: 0 | C44: 0 | D44: 0 | E44: 0 | F44: -201750 | G44: ='QTR CF'!R47+'QTR CF'!S47+'QTR CF'!T47+'QTR CF'!U47 | H44: ='QTR CF'!V47+'QTR CF'!W47+'QTR CF'!X47+'QTR CF'!Y47 | I44: ='QTR CF'!Z47+'QTR CF'!AA47+'QTR CF'!AB47+'QTR CF'!AC47 | J44: ='QTR CF'!AD47+'QTR CF'!AE47+'QTR CF'!AF47+'QTR CF'!AG47
A45: Debt Issuance Fees | B45: 0 | C45: 0 | D45: 0 | E45: 0 | F45: -32367 | G45: ='QTR CF'!R48+'QTR CF'!S48+'QTR CF'!T48+'QTR CF'!U48 | H45: ='QTR CF'!V48+'QTR CF'!W48+'QTR CF'!X48+'QTR CF'!Y48 | I45: ='QTR CF'!Z48+'QTR CF'!AA48+'QTR CF'!AB48+'QTR CF'!AC48 | J45: ='QTR CF'!AD48+'QTR CF'!AE48+'QTR CF'!AF48+'QTR CF'!AG48
A46: Other Financing Activities | B46: 0 | C46: 0 | D46: 0 | E46: 0 | F46: -7 | G46: ='QTR CF'!R49+'QTR CF'!S49+'QTR CF'!T49+'QTR CF'!U49 | H46: ='QTR CF'!V49+'QTR CF'!W49+'QTR CF'!X49+'QTR CF'!Y49 | I46: ='QTR CF'!Z49+'QTR CF'!AA49+'QTR CF'!AB49+'QTR CF'!AC49 | J46: ='QTR CF'!AD49+'QTR CF'!AE49+'QTR CF'!AF49+'QTR CF'!AG49
A47: Cash Flow from Financing | B47: =SUM(B37:B46) | C47: =SUM(C37:C46) | D47: =SUM(D37:D46) | E47: =SUM(E37:E46) | F47: =SUM(F37:F46) | G47: =SUM(G37:G46) | H47: =SUM(H37:H46) | I47: =SUM(I37:I46) | ... L47: =SUM(L37:L46)
A48: FX Effect on Cash | B48: -538 | C48: 50 | D48: 1257 | E48: -997 | F48: 3271 | G48: ='QTR CF'!R51+'QTR CF'!S51+'QTR CF'!T51+'QTR CF'!U51 | H48: ='QTR CF'!V51+'QTR CF'!W51+'QTR CF'!X51+'QTR CF'!Y51 | I48: ='QTR CF'!Z51+'QTR CF'!AA51+'QTR CF'!AB51+'QTR CF'!AC51 | J48: ='QTR CF'!AD51+'QTR CF'!AE51+'QTR CF'!AF51+'QTR CF'!AG51
A49: Net Change in Cash | B49: =B29+B36+B47+B48 | C49: =C29+C36+C47+C48 | D49: =D29+D36+D47+D48 | E49: =E29+E36+E47+E48 | F49: =F29+F36+F47+F48 | G49: =G29+G36+G47+G48 | H49: =H29+H36+H47+H48 | I49: =I29+I36+I47+I48 | ... L49: =L29+L36+L47+L48

Sheet YTD P&L
B1: Q1 FY2022 | C1: Q2 FY2022 | D1: Q3 FY2022 | E1: Q1 FY2023 | F1: Q2 FY2023 | G1: Q3 FY2023 | H1: Q1 FY2024 | I1: Q2 FY2024 | J1: Q3 FY2024 | K1: Q1 FY2025 | L1: Q2 FY2025 | M1: Q3 FY2025
A2: Net Sales / Revenue | B2: 133388 | C2: 287408 | D2: 475640 | E2: 259939 | F2: 585822 | G2: 970579 | H2: 355708 | I2: 757685 | J2: 1023433 | K2: 329276 | L2: 1068535 | M2: 1793641
A3: COGS | B3: -79494 | C3: -174195 | D3: -283778 | E3: -146121 | F3: -313010 | G3: -503685 | H3: -173501 | I3: -366380 | J3: -509899 | K3: -156903 | L3: -515311 | M3: -868138
A4: Gross Profit (Loss) | B4: =B2+B3 | C4: =C2+C3 | D4: =D2+D3 | E4: =E2+E3 | F4: =F2+F3 | G4: =G2+G3 | H4: =H2+H3 | I4: =I2+I3 | ... M4: =M2+M3
A5: SG&A | B5: -43778 | C5: -90667 | D5: -316917 | E5: -68905 | F5: -163086 | G5: -259471 | H5: -99017 | I5: -213867 | J5: -339310 | K5: -120342 | L5: -358228 | M5: -563799
A6: Distributor Termination Fees | B6: 0 | C6: 0 | D6: 0 | E6: 0 | F6: 0 | G6: 0 | H6: 0 | I6: 0 | J6: 0 | K6: 0 | L6: 0 | M6: -246707
A7: Income (Loss) from Operations | B7: =B4+SUM(B5:B6) | C7: =C4+SUM(C5:C6) | D7: =D4+SUM(D5:D6) | E7: =E4+SUM(E5:E6) | F7: =F4+SUM(F5:F6) | G7: =G4+SUM(G5:G6) | H7: =H4+SUM(H5:H6) | I7: =I4+SUM(I5:I6) | ... M7: =M4+SUM(M5:M6)
A8: Interest Income (Expense) | B8: 76 | C8: 129 | D8: 1579 | E8: 4969 | F8: 10542 | G8: 17767 | H8: 9640 | I8: 20287 | J8: 31399 | K8: 7846 | L8: -6196 | M8: -19592
A9: Foreign Currency Gain (Loss) | B9: -162 | C9: -676 | D9: -930 | E9: -118 | F9: -1049 | G9: -1226 | H9: -369 | I9: -633 | J9: -356 | K9: 0 | L9: 0 | M9: 0
A10: Other Income (Expense) | B10: 0 | C10: 0 | D10: 0 | E10: 0 | F10: 0 | G10: 0 | H10: 0 | I10: 0 | J10: 0 | K10: 1116 | L10: 1658 | M10: 7022
A11: Pre-Tax Income (Loss) | B11: =B7+SUM(B8:B10) | C11: =C7+SUM(C8:C10) | D11: =D7+SUM(D8:D10) | E11: =E7+SUM(E8:E10) | F11: =F7+SUM(F8:F10) | G11: =G7+SUM(G8:G10) | H11: =H7+SUM(H8:H10) | I11: =I7+SUM(I8:I10) | ... M11: =M7+SUM(M8:M10)
A12: Income Tax (Expense) Benefit | B12: -3351 | C12: -6161 | D12: -41653 | E12: -8537 | F12: -26483 | G12: -47279 | H12: -14650 | I12: -39498 | J12: -41317 | K12: -16574 | L12: -46184 | M12: -19167
A13: Net Income (Loss) | B13: =B11+B12 | C13: =C11+C12 | D13: =D11+D12 | E13: =E11+E12 | F13: =F11+F12 | G13: =G11+G12 | H13: =H11+H12 | I13: =I11+I12 | ... M13: =M11+M12
A14: Preferred Dividends | B14: 0 | C14: 0 | D14: -4596 | E14: -6781 | F14: -13637 | G14: -20512 | H14: -6837 | I14: -13675 | J14: -20588 | K14: -6781 | L14: -13632 | M14: -23289
A15: Income Allocated to Participating Preferred | B15: 0 | C15: 0 | D15: 0 | E15: 0 | F15: 6727 | G15: 13263 | H15: 6128 | I15: 12417 | J15: 12357 | K15: 3219 | L15: 10703 | M15: 5272
A16: Net Income (Loss) Attributable to Common Shareholders | B16: 6679 | C16: 15838 | D16: -170655 | E16: 34446 | F16: 72372 | G16: 142910 | H16: 64846 | I16: 131502 | J16: 131005 | K16: 34419 | L16: 119939 | M16: 54699

Sheet YTD BS
B1: Q4 FY2022 | C1: Q1 FY2023 | D1: Q2 FY2023 | E1: Q3 FY2023 | F1: Q4 FY2023 | G1: Q1 FY2024 | H1: Q2 FY2024 | I1: Q3 FY2024 | J1: Q4 FY2024 | K1: Q1 FY2025 | L1: Q2 FY2025 | M1: Q3 FY2025
A2: Cash & Cash Equivalents | B2: 614159 | C2: 595476 | D2: 681054 | E2: 760022 | F2: 755981 | G2: 879498 | H2: 903210 | I2: 903748 | J2: 890190 | K2: 977285 | L2: 615233 | M2: 805955
A3: Restricted Cash | B3: 38768 | C3: 38105 | D3: 0 | E3: 0 | F3: 0 | G3: 0 | H3: 0 | I3: 0 | J3: 0 | K3: 0 | L3: 0 | M3: 126508
A4: Accounts Receivable | B4: 63311 | C4: 172032 | D4: 197811 | E4: 215243 | F4: 183703 | G4: 200117 | H4: 262920 | I4: 208774 | J4: 270342 | K4: 256424 | L4: 490389 | M4: 513682
A5: Note Receivable - Current | B5: 2979 | C5: 3587 | D5: 3323 | E5: 3309 | F5: 2318 | G5: 2259 | H5: 1166 | I5: 1025 | J5: 0 | K5: 0 | L5: 0 | M5: 0
A6: Inventories | B6: 173289 | C6: 154280 | D6: 152545 | E6: 198704 | F6: 229275 | G6: 197504 | H6: 180669 | I6: 197572 | J6: 131165 | K6: 141159 | L6: 230046 | M6: 282514
A7: Prepaid Expenses | B7: 11341 | C7: 15507 | D7: 23398 | E7: 23747 | F7: 19503 | G7: 21523 | H7: 22900 | I7: 38227 | J7: 18759 | K7: 22464 | L7: 41420 | M7: 163395
A8: Deferred Other Costs - Current | B8: 14124 | C8: 14124 | D8: 14124 | E8: 14124 | F8: 14124 | G8: 14124 | H8: 14124 | I8: 14124 | J8: 14124 | K8: 14124 | L8: 14124 | M8: 49520
A9: Total Current Assets | B9: =SUM(B2:B8) | C9: =SUM(C2:C8) | D9: =SUM(D2:D8) | E9: =SUM(E2:E8) | F9: =SUM(F2:F8) | G9: =SUM(G2:G8) | H9: =SUM(H2:H8) | I9: =SUM(I2:I8) | ... M9: =SUM(M2:M8)
A10: Note Receivable - Non-Current | B10: 3574 | C10: 0 | D10: 0 | E10: 0 | F10: 0 | G10: 0 | H10: 0 | I10: 0 | J10: 0 | K10: 0 | L10: 0 | M10: 0
A11: Net PP&E | B11: 10185 | C11: 12054 | D11: 15892 | E11: 21061 | F11: 24868 | G11: 28350 | H11: 36282 | I11: 38370 | J11: 55602 | K11: 58698 | L11: 72516 | M11: 80925
A12: ROU Assets - Operating - Non-Current | B12: 972 | C12: 931 | D12: 756 | E12: 1152 | F12: 1957 | G12: 1688 | H12: 1507 | I12: 5506 | J12: 21606 | K12: 20866 | L12: 0 | M12: 0
A13: Intangible Assets | B13: 12254 | C13: 12359 | D13: 12211 | E13: 11772 | F13: 12139 | G13: 11741 | H13: 11491 | I13: 11877 | J13: 12213 | K13: 12444 | L13: 1222115 | M13: 1397819
A14: Goodwill | B14: 13679 | C14: 13949 | D14: 13937 | E14: 13588 | F14: 14173 | G14: 13866 | H14: 13730 | I14: 14360 | J14: 71582 | K14: 72128 | L14: 802234 | M14: 914957
A15: Deferred Other Costs - Non-Current | B15: 262462 | C15: 258931 | D15: 255400 | E15: 251869 | F15: 248338 | G15: 244807 | H15: 241276 | I15: 237746 | J15: 234215 | K15: 230684 | L15: 227153 | M15: 784214
A16: Deferred Tax Assets | B16: 501 | C16: 482 | D16: 28373 | E16: 30614 | F16: 29518 | G16: 22437 | H16: 22727 | I16: 24186 | J16: 38699 | K16: 38525 | L16: 43158 | M16: 110410
A17: ROU Assets - Finance - Non-Current | B17: 208 | C17: 191 | D17: 171 | E17: 148 | F17: 208 | G17: 263 | H17: 233 | I17: 214 | J17: 0 | K17: 0 | L17: 0 | M17: 0
A18: Other Non-Current Assets | B18: 263 | C18: 263 | D18: 254 | E18: 265 | F18: 291 | G18: 7963 | H18: 6653 | I18: 8594 | J18: 8384 | K18: 14717 | L18: 36755 | M18: 35809
A19: Total Assets | B19: =B9+SUM(B10:B18) | C19: =C9+SUM(C10:C18) | D19: =D9+SUM(D10:D18) | E19: =E9+SUM(E10:E18) | F19: =F9+SUM(F10:F18) | G19: =G9+SUM(G10:G18) | H19: =H9+SUM(H10:H18) | I19: =I9+SUM(I10:I18) | ... M19: =M9+SUM(M10:M18)
A20: Accounts Payable | B20: 107340 | C20: 107112 | D20: 94313 | E20: 121088 | F20: 42840 | G20: 40196 | H20: 47423 | I20: 30938 | J20: 41287 | K20: 61052 | L20: 120962 | M20: 97794
A21: Accrued Expenses | B21: 0 | C21: 0 | D21: 0 | E21: 0 | F21: 62120 | G21: 63871 | H21: 79633 | I21: 73024 | J21: 148780 | K21: 152046 | L21: 225859 | M21: 311768
A22: Income Taxes Payable | B22: 0 | C22: 0 | D22: 58798 | E22: 58855 | F22: 50424 | G22: 58619 | H22: 5374 | I22: 739 | J22: 10834 | K22: 26206 | L22: 21765 | M22: 49590
A23: Accrued Distributor Termination Fees | B23: 3986 | C23: 1063 | D23: 0 | E23: 0 | F23: 0 | G23: 0 | H23: 0 | I23: 0 | J23: 0 | K23: 0 | L23: 0 | M23: 252953
A24: Accrued Promotional Allowance | B24: 35977 | C24: 68225 | D24: 98933 | E24: 136557 | F24: 99787 | G24: 129201 | H24: 156479 | I24: 158810 | J24: 135948 | K24: 151327 | L24: 200169 | M24: 234068
A25: Lease Liability - Operating - Current | B25: 661 | C25: 605 | D25: 505 | E25: 628 | F25: 980 | G25: 821 | H25: 729 | I25: 1358 | J25: 3265 | K25: 3550 | L25: 0 | M25: 0
A26: Lease Liability - Finance - Current | B26: 70 | C26: 69 | D26: 67 | E26: 63 | F26: 59 | G26: 61 | H26: 61 | I26: 99 | J26: 0 | K26: 0 | L26: 0 | M26: 0
A27: Contingent Consideration - Current | B27: 0 | C27: 0 | D27: 0 | E27: 0 | F27: 0 | G27: 0 | H27: 0 | I27: 0 | J27: 0 | K27: 0 | L27: 25000 | M27: 25000
A28: Deferred Revenue - Current | B28: 9675 | C28: 9563 | D28: 9500 | E28: 9500 | F28: 9513 | G28: 9513 | H28: 9513 | I28: 9513 | J28: 9513 | K28: 9513 | L28: 16071 | M28: 25557
A29: Other Current Liabilities | B29: 3586 | C29: 5094 | D29: 7109 | E29: 8826 | F29: 10890 | G29: 12987 | H29: 13772 | I29: 14979 | J29: 15908 | K29: 14160 | L29: 49949 | M29: 32258
A30: Total Current Liabilities | B30: =SUM(B20:B29) | C30: =SUM(C20:C29) | D30: =SUM(D20:D29) | E30: =SUM(E20:E29) | F30: =SUM(F20:F29) | G30: =SUM(G20:G29) | H30: =SUM(H20:H29) | I30: =SUM(I20:I29) | ... M30: =SUM(M20:M29)
A31: Lease Liability - Operating - Non-Current | B31: 326 | C31: 336 | D31: 249 | E31: 512 | F31: 955 | G31: 850 | H31: 762 | I31: 4193 | J31: 16674 | K31: 16152 | L31: 0 | M31: 0
A32: Lease Liability - Finance - Non-Current | B32: 162 | C32: 156 | D32: 147 | E32: 135 | F32: 193 | G32: 245 | H32: 228 | I32: 189 | J32: 0 | K32: 0 | L32: 0 | M32: 0
A33: Deferred Tax Liability | B33: 15919 | C33: 19250 | D33: 2333 | E33: 2249 | F33: 2880 | G33: 2248 | H33: 2201 | I33: 2275 | J33: 0 | K33: 0 | L33: 0 | M33: 0
A34: Long-Term Debt | B34: 0 | C34: 0 | D34: 0 | E34: 0 | F34: 0 | G34: 0 | H34: 0 | I34: 0 | J34: 0 | K34: 0 | L34: 862917 | M34: 861472
A35: Deferred Revenue - Non-Current | B35: 179788 | C35: 175275 | D35: 171745 | E35: 169370 | F35: 167227 | G35: 164849 | H35: 162471 | I35: 160092 | J35: 157714 | K35: 155336 | L35: 156135 | M35: 387432
A36: Other Non-Current Liabilities | B36: 0 | C36: 0 | D36: 0 | E36: 0 | F36: 0 | G36: 0 | H36: 0 | I36: 0 | J36: 2541 | K36: 2574 | L36: 25002 | M36: 24431
A37: Total Liabilities | B37: =B30+SUM(B31:B36) | C37: =C30+SUM(C31:C36) | D37: =D30+SUM(D31:D36) | E37: =E30+SUM(E31:E36) | F37: =F30+SUM(F31:F36) | G37: =G30+SUM(G31:G36) | H37: =H30+SUM(H31:H36) | I37: =I30+SUM(I31:I36) | ... M37: =M30+SUM(M31:M36)
A38: Convertible Preferred Stock | B38: 824488 | C38: 824488 | D38: 824488 | E38: 824488 | F38: 824488 | G38: 824488 | H38: 824488 | I38: 824488 | J38: 824488 | K38: 824488 | L38: 824488 | M38: 1760275
A39: Common Stock | B39: 76 | C39: 77 | D39: 77 | E39: 77 | F39: 77 | G39: 78 | H39: 78 | I39: 79 | J39: 79 | K39: 79 | L39: 101 | M39: 101
A40: Treasury Stock | B40: 0 | C40: 0 | D40: 0 | E40: 0 | F40: 0 | G40: 0 | H40: 0 | I40: 0 | J40: 0 | K40: 0 | L40: 0 | M40: 0
A41: Additional Paid-in Capital | B41: 280668 | C41: 279872 | D41: 278980 | E41: 277980 | F41: 276717 | G41: 281247 | H41: 286173 | I41: 292576 | J41: 297579 | K41: 300877 | L41: 1028384 | M41: 1035021
A42: Accumulated Other Comprehensive Income (Loss) | B42: -1881 | C42: -1287 | D42: -1877 | E42: -2541 | F42: -701 | G42: -2055 | H42: -2363 | I42: -338 | J42: -3250 | K42: -1001 | L42: 2178 | M42: 2508
A43: Retained Earnings (Accumulated Deficit) | B43: -238772 | C43: -197627 | D43: -146118 | E43: -62169 | F43: -12053 | G43: 58921 | H43: 131866 | I43: 131309 | J43: 105521 | K43: 143159 | L43: 236163 | M43: 165480
A44: Total Stockholders' Equity | B44: =SUM(B38:B43) | C44: =SUM(C38:C43) | D44: =SUM(D38:D43) | E44: =SUM(E38:E43) | F44: =SUM(F38:F43) | G44: =SUM(G38:G43) | H44: =SUM(H38:H43) | I44: =SUM(I38:I43) | ... M44: =SUM(M38:M43)
A45: Total Liabilities, Mezzanine & Stockholders' Equity | B45: =B37+B44 | C45: =C37+C44 | D45: =D37+D44 | E45: =E37+E44 | F45: =F37+F44 | G45: =G37+G44 | H45: =H37+H44 | I45: =I37+I44 | ... M45: =M37+M44

Sheet YTD CF
B1: Q1 FY2022 | C1: Q2 FY2022 | D1: Q3 FY2022 | E1: Q1 FY2023 | F1: Q2 FY2023 | G1: Q3 FY2023 | H1: Q1 FY2024 | I1: Q2 FY2024 | J1: Q3 FY2024 | K1: Q1 FY2025 | L1: Q2 FY2025 | M1: Q3 FY2025
A2: Net Income (Loss) | B2: 6679 | C2: 15838 | D2: -166059 | E2: 41227 | F2: 92736 | G2: 176685 | H2: 77811 | I2: 157594 | J2: 163950 | K2: 44419 | L2: 144274 | M2: 83260
A3: Depreciation | B3: 245 | C3: 556 | D3: 952 | E3: 404 | F3: 953 | G3: 1676 | H3: 0 | I3: 0 | J3: 0 | K3: 0 | L3: 0 | M3: 0
A4: Amortization | B4: 141 | C4: 275 | D4: 402 | E4: 145 | F4: 294 | G4: 445 | H4: 0 | I4: 0 | J4: 0 | K4: 0 | L4: 0 | M4: 0
A5: Impairment of Intangibles | B5: 0 | C5: 0 | D5: 2379 | E5: 0 | F5: 0 | G5: 0 | H5: 0 | I5: 0 | J5: 0 | K5: 0 | L5: 0 | M5: 0
A6: Depreciation & Amortization | B6: 0 | C6: 0 | D6: 0 | E6: 0 | F6: 0 | G6: 0 | H6: 1229 | I6: 2648 | J6: 4888 | K6: 2611 | L6: 11730 | M6: 20516
A7: Allowance for Credit Losses | B7: 455 | C7: 466 | D7: 705 | E7: 837 | F7: 1088 | G7: 1880 | H7: 2250 | I7: 4072 | J7: 4279 | K7: 2077 | L7: 5529 | M7: 3226
A8: Amortization of Deferred Other Costs | B8: 0 | C8: 0 | D8: 2354 | E8: 3531 | F8: 7062 | G8: 10593 | H8: 3531 | I8: 7062 | J8: 10593 | K8: 3531 | L8: 7062 | M8: 13391
A9: Inventory Write-Down | B9: 2596 | C9: 331 | D9: 1078 | E9: 1672 | F9: -3888 | G9: 2677 | H9: 2386 | I9: 11554 | J9: 17118 | K9: 5337 | L9: 15262 | M9: 22313
A10: Gain (Loss) on Disposal of PP&E | B10: 0 | C10: 0 | D10: 0 | E10: 0 | F10: 191 | G10: 195 | H10: -8 | I10: 31 | J10: 126 | K10: 0 | L10: 0 | M10: 0
A11: Stock-Based Compensation | B11: 4310 | C11: 8517 | D11: 14780 | E11: 5507 | F11: 11242 | G11: 16221 | H11: 3563 | I11: 8309 | J11: 13685 | K11: 5029 | L11: 11463 | M11: 18847
A12: (Benefit) Provision for Deferred Income Taxes | B12: 2561 | C12: 1072 | D12: 31329 | E12: 2873 | F12: -41044 | G12: -44303 | H12: 6450 | I12: 6112 | J12: 4727 | K12: 269 | L12: -4161 | M12: -71408
A13: Foreign Currency Gain (Loss) | B13: 85 | C13: 602 | D13: 1007 | E13: 69 | F13: 206 | G13: 258 | H13: 369 | I13: 633 | J13: 356 | K13: 0 | L13: 0 | M13: 0
... A31: Net Change in Other Working Capital | B31: 0 | C31: 488 | D31: 0 | E31: 0 | F31: 0 | G31: 0 | H31: 0 | I31: 0 | J31: 0 | K31: 148 | L31: -1210 | M31: -1786
A32: Cash Flow from Operations | B32: =SUM(B2:B31) | C32: =SUM(C2:C31) | D32: =SUM(D2:D31) | E32: =SUM(E2:E31) | F32: =SUM(F2:F31) | G32: =SUM(G2:G31) | H32: =SUM(H2:H31) | I32: =SUM(I2:I31) | ... M32: =SUM(M2:M31)
A33: Collections from Note Receivable | B33: 0 | C33: 2592 | D33: 2592 | E33: 3233 | F33: 3233 | G33: 3233 | H33: 0 | I33: 0 | J33: 0 | K33: 0 | L33: 0 | M33: 0
A34: Purchase of PP&E | B34: -742 | C34: -2456 | D34: -3477 | E34: -2253 | F34: -6810 | G34: -12687 | H34: -4525 | I34: -13739 | J34: -17983 | K34: -6944 | L34: -15194 | M34: -25539
A35: Purchase of Non-Marketable Equity Securities | B35: 0 | C35: 0 | D35: 0 | E35: 0 | F35: 0 | G35: 0 | H35: 0 | I35: 0 | J35: -3000 | K35: 0 | L35: -5000 | M35: -5000
A36: Acquisition of Big Beverages | B36: 0 | C36: 0 | D36: 0 | E36: 0 | F36: 0 | G36: 0 | H36: 0 | I36: 0 | J36: 0 | K36: 0 | L36: 0 | M36: 0
A37: Acquisitions, Net of Cash Acquired | B37: 0 | C37: 0 | D37: 0 | E37: 0 | F37: 0 | G37: 0 | H37: 0 | I37: 0 | J37: 0 | K37: 0 | L37: -1256351 | M37: -1278769
A38: Working Capital Estimate from Pepsi (Rockstar) | B38: 0 | C38: 0 | D38: 0 | E38: 0 | F38: 0 | G38: 0 | H38: 0 | I38: 0 | J38: 0 | K38: 0 | L38: 0 | M38: 30617
A39: Cash Flow from Investing | B39: =SUM(B33:B38) | C39: =SUM(C33:C38) | D39: =SUM(D33:D38) | E39: =SUM(E33:E38) | F39: =SUM(F33:F38) | G39: =SUM(G33:G38) | H39: =SUM(H33:H38) | I39: =SUM(I33:I38) | ... M39: =SUM(M33:M38)
A40: Finance Lease Payments | B40: -20 | C40: -37 | D40: -49 | E40: -11 | F40: -22 | G40: -33 | H40: -15 | I40: -30 | J40: -46 | K40: 0 | L40: 0 | M40: 0
A41: Proceeds from Exercise of Stock Options | B41: 810 | C41: 1260 | D41: 3104 | E41: 478 | F41: 707 | G41: 1603 | H41: 967 | I41: 1147 | J41: 3832 | K41: 0 | L41: 0 | M41: 0
A42: Proceeds from Issuance of Common Stock | B42: 0 | C42: 0 | D42: 0 | E42: 0 | F42: 0 | G42: 0 | H42: 0 | I42: 0 | J42: 0 | K42: 0 | L42: 0 | M42: 0
A43: Proceeds from Issuance of Preferred Stock | B43: 0 | C43: 0 | D43: 542018 | E43: 0 | F43: 0 | G43: 0 | H43: 0 | I43: 0 | J43: 0 | K43: 0 | L43: 0 | M43: 0
A44: Preferred Dividends | B44: 0 | C44: 0 | D44: -4596 | E44: -6781 | F44: -13637 | G44: -20512 | H44: -6837 | I44: -13675 | J44: -20588 | K44: -6781 | L44: -13632 | M44: -23301
A45: Share Repurchases | B45: 0 | C45: 0 | D45: 0 | E45: 0 | F45: 0 | G45: 0 | H45: 0 | I45: 0 | J45: -1658 | K45: -1932 | L45: -2811 | M45: -3259
A46: Proceeds from Issuance of Long-Term Debt | B46: 0 | C46: 0 | D46: 0 | E46: 0 | F46: 0 | G46: 0 | H46: 0 | I46: 0 | J46: 0 | K46: 0 | L46: 900000 | M46: 900000
A47: Repayments of Long-Term Debt | B47: 0 | C47: 0 | D47: 0 | E47: 0 | F47: 0 | G47: 0 | H47: 0 | I47: 0 | J47: 0 | K47: 0 | L47: 0 | M47: -2250
A48: Debt Issuance Fees | B48: 0 | C48: 0 | D48: 0 | E48: 0 | F48: 0 | G48: 0 | H48: 0 | I48: 0 | J48: 0 | K48: -2195 | L48: -31581 | M48: -31581
A49: Other Financing Activities | B49: 0 | C49: 0 | D49: 0 | E49: 0 | F49: 0 | G49: 0 | H49: 0 | I49: 0 | J49: 0 | K49: 321 | L49: 319 | M49: 301
A50: Cash Flow from Financing | B50: =SUM(B40:B49) | C50: =SUM(C40:C49) | D50: =SUM(D40:D49) | E50: =SUM(E40:E49) | F50: =SUM(F40:F49) | G50: =SUM(G40:G49) | H50: =SUM(H40:H49) | I50: =SUM(I40:I49) | ... M50: =SUM(M40:M49)
A51: FX Effect on Cash | B51: 104 | C51: 121 | D51: 158 | E51: -181 | F51: -555 | G51: -555 | H51: -722 | I51: -766 | J51: -16 | K51: 1259 | L51: 2214 | M51: 2174
A52: Net Change in Cash | B52: =B32+B39+B50+B51 | C52: =C32+C39+C50+C51 | D52: =D32+D39+D50+D51 | E52: =E32+E39+E50+E51 | F52: =F32+F39+F50+F51 | G52: =G32+G39+G50+G51 | H52: =H32+H39+H50+H51 | I52: =I32+I39+I50+I51 | ... M52: =M32+M39+M50+M51

Sheet QTR P&L
B1: Q1 FY2022 | C1: Q2 FY2022 | D1: Q3 FY2022 | E1: Q4 FY2022 | F1: Q1 FY2023 | G1: Q2 FY2023 | H1: Q3 FY2023 | I1: Q4 FY2023 | J1: Q1 FY2024 | K1: Q2 FY2024 | L1: Q3 FY2024 | M1: Q4 FY2024 | N1: Q1 FY2025 | O1: Q2 FY2025 | P1: Q3 FY2025 | Q1: Q4 FY2025 | R1: Q1 FY2026E | S1: Q2 FY2026E | T1: Q3 FY2026E | U1: Q4 FY2026E | V1: Q1 FY2027E | W1: Q2 FY2027E | X1: Q3 FY2027E | Y1: Q4 FY2027E | Z1: Q1 FY2028E | AA1: Q2 FY2028E | AB1: Q3 FY2028E | AC1: Q4 FY2028E | AD1: Q1 FY2029E | AE1: Q2 FY2029E | AF1: Q3 FY2029E | AG1: Q4 FY2029E
A2: Net Sales / Revenue | B2: ='YTD P&L'!B2 | C2: ='YTD P&L'!C2-'YTD P&L'!B2 | D2: ='YTD P&L'!D2-'YTD P&L'!C2 | E2: ='ANNL P&L'!C2-'YTD P&L'!D2 | F2: ='YTD P&L'!E2 | G2: ='YTD P&L'!F2-'YTD P&L'!E2 | H2: ='YTD P&L'!G2-'YTD P&L'!F2 | I2: ='ANNL P&L'!D2-'YTD P&L'!G2 | J2: ='YTD P&L'!H2 | K2: ='YTD P&L'!I2-'YTD P&L'!H2 | L2: ='YTD P&L'!J2-'YTD P&L'!I2 | M2: ='ANNL P&L'!E2-'YTD P&L'!J2 | N2: ='YTD P&L'!K2 | O2: ='YTD P&L'!L2-'YTD P&L'!K2 | P2: ='YTD P&L'!M2-'YTD P&L'!L2 | Q2: ='ANNL P&L'!F2-'YTD P&L'!M2 | R2: ='QTR P&L'!N2*(1+'IS DRIVERS'!R2) | S2: ='QTR P&L'!O2*(1+'IS DRIVERS'!S2) | T2: ='QTR P&L'!P2*(1+'IS DRIVERS'!T2) | U2: ='QTR P&L'!Q2*(1+'IS DRIVERS'!U2) | V2: ='QTR P&L'!R2*(1+'IS DRIVERS'!V2) | W2: ='QTR P&L'!S2*(1+'IS DRIVERS'!W2) | X2: ='QTR P&L'!T2*(1+'IS DRIVERS'!X2) | Y2: ='QTR P&L'!U2*(1+'IS DRIVERS'!Y2) | ... AG2: ='QTR P&L'!AC2*(1+'IS DRIVERS'!AG2)
A3: COGS | B3: ='YTD P&L'!B3 | C3: ='YTD P&L'!C3-'YTD P&L'!B3 | D3: ='YTD P&L'!D3-'YTD P&L'!C3 | E3: ='ANNL P&L'!C3-'YTD P&L'!D3 | F3: ='YTD P&L'!E3 | G3: ='YTD P&L'!F3-'YTD P&L'!E3 | H3: ='YTD P&L'!G3-'YTD P&L'!F3 | I3: ='ANNL P&L'!D3-'YTD P&L'!G3 | J3: ='YTD P&L'!H3 | K3: ='YTD P&L'!I3-'YTD P&L'!H3 | L3: ='YTD P&L'!J3-'YTD P&L'!I3 | M3: ='ANNL P&L'!E3-'YTD P&L'!J3 | N3: ='YTD P&L'!K3 | O3: ='YTD P&L'!L3-'YTD P&L'!K3 | P3: ='YTD P&L'!M3-'YTD P&L'!L3 | Q3: ='ANNL P&L'!F3-'YTD P&L'!M3 | R3: ='QTR P&L'!R2*'IS DRIVERS'!R3 | S3: ='QTR P&L'!S2*'IS DRIVERS'!S3 | T3: ='QTR P&L'!T2*'IS DRIVERS'!T3 | U3: ='QTR P&L'!U2*'IS DRIVERS'!U3 | V3: ='QTR P&L'!V2*'IS DRIVERS'!V3 | W3: ='QTR P&L'!W2*'IS DRIVERS'!W3 | X3: ='QTR P&L'!X2*'IS DRIVERS'!X3 | Y3: ='QTR P&L'!Y2*'IS DRIVERS'!Y3 | ... AG3: ='QTR P&L'!AG2*'IS DRIVERS'!AG3
A4: Gross Profit (Loss) | B4: ='YTD P&L'!B4 | C4: ='YTD P&L'!C4-'YTD P&L'!B4 | D4: ='YTD P&L'!D4-'YTD P&L'!C4 | E4: ='ANNL P&L'!C4-'YTD P&L'!D4 | F4: ='YTD P&L'!E4 | G4: ='YTD P&L'!F4-'YTD P&L'!E4 | H4: ='YTD P&L'!G4-'YTD P&L'!F4 | I4: ='ANNL P&L'!D4-'YTD P&L'!G4 | J4: ='YTD P&L'!H4 | K4: ='YTD P&L'!I4-'YTD P&L'!H4 | L4: ='YTD P&L'!J4-'YTD P&L'!I4 | M4: ='ANNL P&L'!E4-'YTD P&L'!J4 | N4: ='YTD P&L'!K4 | O4: ='YTD P&L'!L4-'YTD P&L'!K4 | P4: ='YTD P&L'!M4-'YTD P&L'!L4 | Q4: ='ANNL P&L'!F4-'YTD P&L'!M4 | R4: =R2+R3 | S4: =S2+S3 | T4: =T2+T3 | U4: =U2+U3 | V4: =V2+V3 | W4: =W2+W3 | X4: =X2+X3 | Y4: =Y2+Y3 | ... AG4: =AG2+AG3
A5: SG&A | B5: ='YTD P&L'!B5 | C5: ='YTD P&L'!C5-'YTD P&L'!B5 | D5: ='YTD P&L'!D5-'YTD P&L'!C5 | E5: ='ANNL P&L'!C5-'YTD P&L'!D5 | F5: ='YTD P&L'!E5 | G5: ='YTD P&L'!F5-'YTD P&L'!E5 | H5: ='YTD P&L'!G5-'YTD P&L'!F5 | I5: ='ANNL P&L'!D5-'YTD P&L'!G5 | J5: ='YTD P&L'!H5 | K5: ='YTD P&L'!I5-'YTD P&L'!H5 | L5: ='YTD P&L'!J5-'YTD P&L'!I5 | M5: ='ANNL P&L'!E5-'YTD P&L'!J5 | N5: ='YTD P&L'!K5 | O5: ='YTD P&L'!L5-'YTD P&L'!K5 | P5: ='YTD P&L'!M5-'YTD P&L'!L5 | Q5: ='ANNL P&L'!F5-'YTD P&L'!M5 | R5: ='QTR P&L'!R2*'IS DRIVERS'!R4 | S5: ='QTR P&L'!S2*'IS DRIVERS'!S4 | T5: ='QTR P&L'!T2*'IS DRIVERS'!T4 | U5: ='QTR P&L'!U2*'IS DRIVERS'!U4 | V5: ='QTR P&L'!V2*'IS DRIVERS'!V4 | W5: ='QTR P&L'!W2*'IS DRIVERS'!W4 | X5: ='QTR P&L'!X2*'IS DRIVERS'!X4 | Y5: ='QTR P&L'!Y2*'IS DRIVERS'!Y4 | ... AG5: ='QTR P&L'!AG2*'IS DRIVERS'!AG4
A6: Distributor Termination Fees | B6: ='YTD P&L'!B6 | C6: ='YTD P&L'!C6-'YTD P&L'!B6 | D6: ='YTD P&L'!D6-'YTD P&L'!C6 | E6: ='ANNL P&L'!C6-'YTD P&L'!D6 | F6: ='YTD P&L'!E6 | G6: ='YTD P&L'!F6-'YTD P&L'!E6 | H6: ='YTD P&L'!G6-'YTD P&L'!F6 | I6: ='ANNL P&L'!D6-'YTD P&L'!G6 | J6: ='YTD P&L'!H6 | K6: ='YTD P&L'!I6-'YTD P&L'!H6 | L6: ='YTD P&L'!J6-'YTD P&L'!I6 | M6: ='ANNL P&L'!E6-'YTD P&L'!J6 | N6: ='YTD P&L'!K6 | O6: ='YTD P&L'!L6-'YTD P&L'!K6 | P6: ='YTD P&L'!M6-'YTD P&L'!L6 | Q6: ='ANNL P&L'!F6-'YTD P&L'!M6 | R6: ='IS DRIVERS'!R5 | S6: ='IS DRIVERS'!S5 | T6: ='IS DRIVERS'!T5 | U6: ='IS DRIVERS'!U5 | V6: ='IS DRIVERS'!V5 | W6: ='IS DRIVERS'!W5 | X6: ='IS DRIVERS'!X5 | Y6: ='IS DRIVERS'!Y5 | ... AG6: ='IS DRIVERS'!AG5
A7: Income (Loss) from Operations | B7: ='YTD P&L'!B7 | C7: ='YTD P&L'!C7-'YTD P&L'!B7 | D7: ='YTD P&L'!D7-'YTD P&L'!C7 | E7: ='ANNL P&L'!C7-'YTD P&L'!D7 | F7: ='YTD P&L'!E7 | G7: ='YTD P&L'!F7-'YTD P&L'!E7 | H7: ='YTD P&L'!G7-'YTD P&L'!F7 | I7: ='ANNL P&L'!D7-'YTD P&L'!G7 | J7: ='YTD P&L'!H7 | K7: ='YTD P&L'!I7-'YTD P&L'!H7 | L7: ='YTD P&L'!J7-'YTD P&L'!I7 | M7: ='ANNL P&L'!E7-'YTD P&L'!J7 | N7: ='YTD P&L'!K7 | O7: ='YTD P&L'!L7-'YTD P&L'!K7 | P7: ='YTD P&L'!M7-'YTD P&L'!L7 | Q7: ='ANNL P&L'!F7-'YTD P&L'!M7 | R7: =R4+SUM(R5:R6) | S7: =S4+SUM(S5:S6) | T7: =T4+SUM(T5:T6) | U7: =U4+SUM(U5:U6) | V7: =V4+SUM(V5:V6) | W7: =W4+SUM(W5:W6) | X7: =X4+SUM(X5:X6) | Y7: =Y4+SUM(Y5:Y6) | ... AG7: =AG4+SUM(AG5:AG6)
A8: Interest Income (Expense) | B8: ='YTD P&L'!B8 | C8: ='YTD P&L'!C8-'YTD P&L'!B8 | D8: ='YTD P&L'!D8-'YTD P&L'!C8 | E8: ='ANNL P&L'!C8-'YTD P&L'!D8 | F8: ='YTD P&L'!E8 | G8: ='YTD P&L'!F8-'YTD P&L'!E8 | H8: ='YTD P&L'!G8-'YTD P&L'!F8 | I8: ='ANNL P&L'!D8-'YTD P&L'!G8 | J8: ='YTD P&L'!H8 | K8: ='YTD P&L'!I8-'YTD P&L'!H8 | L8: ='YTD P&L'!J8-'YTD P&L'!I8 | M8: ='ANNL P&L'!E8-'YTD P&L'!J8 | N8: ='YTD P&L'!K8 | O8: ='YTD P&L'!L8-'YTD P&L'!K8 | P8: ='YTD P&L'!M8-'YTD P&L'!L8 | Q8: ='ANNL P&L'!F8-'YTD P&L'!M8 | R8: ='IS DRIVERS'!R6 | S8: ='IS DRIVERS'!S6 | T8: ='IS DRIVERS'!T6 | U8: ='IS DRIVERS'!U6 | V8: ='IS DRIVERS'!V6 | W8: ='IS DRIVERS'!W6 | X8: ='IS DRIVERS'!X6 | Y8: ='IS DRIVERS'!Y6 | ... AG8: ='IS DRIVERS'!AG6
A9: Foreign Currency Gain (Loss) | B9: ='YTD P&L'!B9 | C9: ='YTD P&L'!C9-'YTD P&L'!B9 | D9: ='YTD P&L'!D9-'YTD P&L'!C9 | E9: ='ANNL P&L'!C9-'YTD P&L'!D9 | F9: ='YTD P&L'!E9 | G9: ='YTD P&L'!F9-'YTD P&L'!E9 | H9: ='YTD P&L'!G9-'YTD P&L'!F9 | I9: ='ANNL P&L'!D9-'YTD P&L'!G9 | J9: ='YTD P&L'!H9 | K9: ='YTD P&L'!I9-'YTD P&L'!H9 | L9: ='YTD P&L'!J9-'YTD P&L'!I9 | M9: ='ANNL P&L'!E9-'YTD P&L'!J9 | N9: ='YTD P&L'!K9 | O9: ='YTD P&L'!L9-'YTD P&L'!K9 | P9: ='YTD P&L'!M9-'YTD P&L'!L9 | Q9: ='ANNL P&L'!F9-'YTD P&L'!M9 | R9: ='IS DRIVERS'!R7 | S9: ='IS DRIVERS'!S7 | T9: ='IS DRIVERS'!T7 | U9: ='IS DRIVERS'!U7 | V9: ='IS DRIVERS'!V7 | W9: ='IS DRIVERS'!W7 | X9: ='IS DRIVERS'!X7 | Y9: ='IS DRIVERS'!Y7 | ... AG9: ='IS DRIVERS'!AG7
A10: Other Income (Expense) | B10: ='YTD P&L'!B10 | C10: ='YTD P&L'!C10-'YTD P&L'!B10 | D10: ='YTD P&L'!D10-'YTD P&L'!C10 | E10: ='ANNL P&L'!C10-'YTD P&L'!D10 | F10: ='YTD P&L'!E10 | G10: ='YTD P&L'!F10-'YTD P&L'!E10 | H10: ='YTD P&L'!G10-'YTD P&L'!F10 | I10: ='ANNL P&L'!D10-'YTD P&L'!G10 | J10: ='YTD P&L'!H10 | K10: ='YTD P&L'!I10-'YTD P&L'!H10 | L10: ='YTD P&L'!J10-'YTD P&L'!I10 | M10: ='ANNL P&L'!E10-'YTD P&L'!J10 | N10: ='YTD P&L'!K10 | O10: ='YTD P&L'!L10-'YTD P&L'!K10 | P10: ='YTD P&L'!M10-'YTD P&L'!L10 | Q10: ='ANNL P&L'!F10-'YTD P&L'!M10 | R10: ='IS DRIVERS'!R8 | S10: ='IS DRIVERS'!S8 | T10: ='IS DRIVERS'!T8 | U10: ='IS DRIVERS'!U8 | V10: ='IS DRIVERS'!V8 | W10: ='IS DRIVERS'!W8 | X10: ='IS DRIVERS'!X8 | Y10: ='IS DRIVERS'!Y8 | ... AG10: ='IS DRIVERS'!AG8
A11: Pre-Tax Income (Loss) | B11: ='YTD P&L'!B11 | C11: ='YTD P&L'!C11-'YTD P&L'!B11 | D11: ='YTD P&L'!D11-'YTD P&L'!C11 | E11: ='ANNL P&L'!C11-'YTD P&L'!D11 | F11: ='YTD P&L'!E11 | G11: ='YTD P&L'!F11-'YTD P&L'!E11 | H11: ='YTD P&L'!G11-'YTD P&L'!F11 | I11: ='ANNL P&L'!D11-'YTD P&L'!G11 | J11: ='YTD P&L'!H11 | K11: ='YTD P&L'!I11-'YTD P&L'!H11 | L11: ='YTD P&L'!J11-'YTD P&L'!I11 | M11: ='ANNL P&L'!E11-'YTD P&L'!J11 | N11: ='YTD P&L'!K11 | O11: ='YTD P&L'!L11-'YTD P&L'!K11 | P11: ='YTD P&L'!M11-'YTD P&L'!L11 | Q11: ='ANNL P&L'!F11-'YTD P&L'!M11 | R11: =R7+SUM(R8:R10) | S11: =S7+SUM(S8:S10) | T11: =T7+SUM(T8:T10) | U11: =U7+SUM(U8:U10) | V11: =V7+SUM(V8:V10) | W11: =W7+SUM(W8:W10) | X11: =X7+SUM(X8:X10) | Y11: =Y7+SUM(Y8:Y10) | ... AG11: =AG7+SUM(AG8:AG10)
A12: Income Tax (Expense) Benefit | B12: ='YTD P&L'!B12 | C12: ='YTD P&L'!C12-'YTD P&L'!B12 | D12: ='YTD P&L'!D12-'YTD P&L'!C12 | E12: ='ANNL P&L'!C12-'YTD P&L'!D12 | F12: ='YTD P&L'!E12 | G12: ='YTD P&L'!F12-'YTD P&L'!E12 | H12: ='YTD P&L'!G12-'YTD P&L'!F12 | I12: ='ANNL P&L'!D12-'YTD P&L'!G12 | J12: ='YTD P&L'!H12 | K12: ='YTD P&L'!I12-'YTD P&L'!H12 | L12: ='YTD P&L'!J12-'YTD P&L'!I12 | M12: ='ANNL P&L'!E12-'YTD P&L'!J12 | N12: ='YTD P&L'!K12 | O12: ='YTD P&L'!L12-'YTD P&L'!K12 | P12: ='YTD P&L'!M12-'YTD P&L'!L12 | Q12: ='ANNL P&L'!F12-'YTD P&L'!M12 | R12: ='QTR P&L'!R11*'IS DRIVERS'!R9 | S12: ='QTR P&L'!S11*'IS DRIVERS'!S9 | T12: ='QTR P&L'!T11*'IS DRIVERS'!T9 | U12: ='QTR P&L'!U11*'IS DRIVERS'!U9 | V12: ='QTR P&L'!V11*'IS DRIVERS'!V9 | W12: ='QTR P&L'!W11*'IS DRIVERS'!W9 | X12: ='QTR P&L'!X11*'IS DRIVERS'!X9 | Y12: ='QTR P&L'!Y11*'IS DRIVERS'!Y9 | ... AG12: ='QTR P&L'!AG11*'IS DRIVERS'!AG9
A13: Net Income (Loss) | B13: ='YTD P&L'!B13 | C13: ='YTD P&L'!C13-'YTD P&L'!B13 | D13: ='YTD P&L'!D13-'YTD P&L'!C13 | E13: ='ANNL P&L'!C13-'YTD P&L'!D13 | F13: ='YTD P&L'!E13 | G13: ='YTD P&L'!F13-'YTD P&L'!E13 | H13: ='YTD P&L'!G13-'YTD P&L'!F13 | I13: ='ANNL P&L'!D13-'YTD P&L'!G13 | J13: ='YTD P&L'!H13 | K13: ='YTD P&L'!I13-'YTD P&L'!H13 | L13: ='YTD P&L'!J13-'YTD P&L'!I13 | M13: ='ANNL P&L'!E13-'YTD P&L'!J13 | N13: ='YTD P&L'!K13 | O13: ='YTD P&L'!L13-'YTD P&L'!K13 | P13: ='YTD P&L'!M13-'YTD P&L'!L13 | Q13: ='ANNL P&L'!F13-'YTD P&L'!M13 | R13: =R11+R12 | S13: =S11+S12 | T13: =T11+T12 | U13: =U11+U12 | V13: =V11+V12 | W13: =W11+W12 | X13: =X11+X12 | Y13: =Y11+Y12 | ... AG13: =AG11+AG12
A14: Preferred Dividends | B14: ='YTD P&L'!B14 | C14: ='YTD P&L'!C14-'YTD P&L'!B14 | D14: ='YTD P&L'!D14-'YTD P&L'!C14 | E14: ='ANNL P&L'!C14-'YTD P&L'!D14 | F14: ='YTD P&L'!E14 | G14: ='YTD P&L'!F14-'YTD P&L'!E14 | H14: ='YTD P&L'!G14-'YTD P&L'!F14 | I14: ='ANNL P&L'!D14-'YTD P&L'!G14 | J14: ='YTD P&L'!H14 | K14: ='YTD P&L'!I14-'YTD P&L'!H14 | L14: ='YTD P&L'!J14-'YTD P&L'!I14 | M14: ='ANNL P&L'!E14-'YTD P&L'!J14 | N14: ='YTD P&L'!K14 | O14: ='YTD P&L'!L14-'YTD P&L'!K14 | P14: ='YTD P&L'!M14-'YTD P&L'!L14 | Q14: ='ANNL P&L'!F14-'YTD P&L'!M14
A15: Income Allocated to Participating Preferred | B15: ='YTD P&L'!B15 | C15: ='YTD P&L'!C15-'YTD P&L'!B15 | D15: ='YTD P&L'!D15-'YTD P&L'!C15 | E15: ='ANNL P&L'!C15-'YTD P&L'!D15 | F15: ='YTD P&L'!E15 | G15: ='YTD P&L'!F15-'YTD P&L'!E15 | H15: ='YTD P&L'!G15-'YTD P&L'!F15 | I15: ='ANNL P&L'!D15-'YTD P&L'!G15 | J15: ='YTD P&L'!H15 | K15: ='YTD P&L'!I15-'YTD P&L'!H15 | L15: ='YTD P&L'!J15-'YTD P&L'!I15 | M15: ='ANNL P&L'!E15-'YTD P&L'!J15 | N15: ='YTD P&L'!K15 | O15: ='YTD P&L'!L15-'YTD P&L'!K15 | P15: ='YTD P&L'!M15-'YTD P&L'!L15 | Q15: ='ANNL P&L'!F15-'YTD P&L'!M15
A16: Net Income (Loss) Attributable to Common Shareholders | B16: ='YTD P&L'!B16 | C16: ='YTD P&L'!C16-'YTD P&L'!B16 | D16: ='YTD P&L'!D16-'YTD P&L'!C16 | E16: ='ANNL P&L'!C16-'YTD P&L'!D16 | F16: ='YTD P&L'!E16 | G16: ='YTD P&L'!F16-'YTD P&L'!E16 | H16: ='YTD P&L'!G16-'YTD P&L'!F16 | I16: ='ANNL P&L'!D16-'YTD P&L'!G16 | J16: ='YTD P&L'!H16 | K16: ='YTD P&L'!I16-'YTD P&L'!H16 | L16: ='YTD P&L'!J16-'YTD P&L'!I16 | M16: ='ANNL P&L'!E16-'YTD P&L'!J16 | N16: ='YTD P&L'!K16 | O16: ='YTD P&L'!L16-'YTD P&L'!K16 | P16: ='YTD P&L'!M16-'YTD P&L'!L16 | Q16: ='ANNL P&L'!F16-'YTD P&L'!M16 | R16: ='QTR P&L'!R2*'IS DRIVERS'!R10 | S16: ='QTR P&L'!S2*'IS DRIVERS'!S10 | T16: ='QTR P&L'!T2*'IS DRIVERS'!T10 | U16: ='QTR P&L'!U2*'IS DRIVERS'!U10 | V16: ='QTR P&L'!V2*'IS DRIVERS'!V10 | W16: ='QTR P&L'!W2*'IS DRIVERS'!W10 | X16: ='QTR P&L'!X2*'IS DRIVERS'!X10 | Y16: ='QTR P&L'!Y2*'IS DRIVERS'!Y10 | ... AG16: ='QTR P&L'!AG2*'IS DRIVERS'!AG10

Sheet QTR BS
B1: Q4 FY2022 | C1: Q1 FY2023 | D1: Q2 FY2023 | E1: Q3 FY2023 | F1: Q4 FY2023 | G1: Q1 FY2024 | H1: Q2 FY2024 | I1: Q3 FY2024 | J1: Q4 FY2024 | K1: Q1 FY2025 | L1: Q2 FY2025 | M1: Q3 FY2025 | N1: Q4 FY2025 | O1: Q1 FY2026E | P1: Q2 FY2026E | Q1: Q3 FY2026E | R1: Q4 FY2026E | S1: Q1 FY2027E | T1: Q2 FY2027E | U1: Q3 FY2027E | V1: Q4 FY2027E | W1: Q1 FY2028E | X1: Q2 FY2028E | Y1: Q3 FY2028E | Z1: Q4 FY2028E | AA1: Q1 FY2029E | AB1: Q2 FY2029E | AC1: Q3 FY2029E | AD1: Q4 FY2029E
A2: Cash & Cash Equivalents | B2: ='BALANCE SHEET'!B2 | C2: ='YTD BS'!C2 | D2: ='YTD BS'!D2 | E2: ='YTD BS'!E2 | F2: ='BALANCE SHEET'!C2 | G2: ='YTD BS'!G2 | H2: ='YTD BS'!H2 | I2: ='YTD BS'!I2 | J2: ='BALANCE SHEET'!D2 | K2: ='YTD BS'!K2 | L2: ='YTD BS'!L2 | M2: ='YTD BS'!M2 | N2: ='BALANCE SHEET'!E2 | O2: ='BS DRIVERS'!O2 | P2: ='BS DRIVERS'!P2 | Q2: ='BS DRIVERS'!Q2 | R2: ='BS DRIVERS'!R2 | S2: ='BS DRIVERS'!S2 | T2: ='BS DRIVERS'!T2 | U2: ='BS DRIVERS'!U2 | V2: ='BS DRIVERS'!V2 | ... AD2: ='BS DRIVERS'!AD2
A3: Restricted Cash | B3: ='BALANCE SHEET'!B3 | C3: ='YTD BS'!C3 | D3: ='YTD BS'!D3 | E3: ='YTD BS'!E3 | F3: ='BALANCE SHEET'!C3 | G3: ='YTD BS'!G3 | H3: ='YTD BS'!H3 | I3: ='YTD BS'!I3 | J3: ='BALANCE SHEET'!D3 | K3: ='YTD BS'!K3 | L3: ='YTD BS'!L3 | M3: ='YTD BS'!M3 | N3: ='BALANCE SHEET'!E3 | O3: ='BS DRIVERS'!O3 | P3: ='BS DRIVERS'!P3 | Q3: ='BS DRIVERS'!Q3 | R3: ='BS DRIVERS'!R3 | S3: ='BS DRIVERS'!S3 | T3: ='BS DRIVERS'!T3 | U3: ='BS DRIVERS'!U3 | V3: ='BS DRIVERS'!V3 | ... AD3: ='BS DRIVERS'!AD3
A4: Accounts Receivable | B4: ='BALANCE SHEET'!B4 | C4: ='YTD BS'!C4 | D4: ='YTD BS'!D4 | E4: ='YTD BS'!E4 | F4: ='BALANCE SHEET'!C4 | G4: ='YTD BS'!G4 | H4: ='YTD BS'!H4 | I4: ='YTD BS'!I4 | J4: ='BALANCE SHEET'!D4 | K4: ='YTD BS'!K4 | L4: ='YTD BS'!L4 | M4: ='YTD BS'!M4 | N4: ='BALANCE SHEET'!E4 | O4: ='QTR P&L'!R2*'BS DRIVERS'!O4/ASSUMPTIONS!$B$2 | P4: ='QTR P&L'!S2*'BS DRIVERS'!P4/ASSUMPTIONS!$B$2 | Q4: ='QTR P&L'!T2*'BS DRIVERS'!Q4/ASSUMPTIONS!$B$2 | R4: ='QTR P&L'!U2*'BS DRIVERS'!R4/ASSUMPTIONS!$B$2 | S4: ='QTR P&L'!V2*'BS DRIVERS'!S4/ASSUMPTIONS!$B$2 | T4: ='QTR P&L'!W2*'BS DRIVERS'!T4/ASSUMPTIONS!$B$2 | U4: ='QTR P&L'!X2*'BS DRIVERS'!U4/ASSUMPTIONS!$B$2 | V4: ='QTR P&L'!Y2*'BS DRIVERS'!V4/ASSUMPTIONS!$B$2 | ... AD4: ='QTR P&L'!AG2*'BS DRIVERS'!AD4/ASSUMPTIONS!$B$2
A5: Note Receivable - Current | B5: ='BALANCE SHEET'!B5 | C5: ='YTD BS'!C5 | D5: ='YTD BS'!D5 | E5: ='YTD BS'!E5 | F5: ='BALANCE SHEET'!C5 | G5: ='YTD BS'!G5 | H5: ='YTD BS'!H5 | I5: ='YTD BS'!I5 | J5: ='BALANCE SHEET'!D5 | K5: ='YTD BS'!K5 | L5: ='YTD BS'!L5 | M5: ='YTD BS'!M5 | N5: ='BALANCE SHEET'!E5 | O5: ='QTR P&L'!R2*'BS DRIVERS'!O5/ASSUMPTIONS!$B$2 | P5: ='QTR P&L'!S2*'BS DRIVERS'!P5/ASSUMPTIONS!$B$2 | Q5: ='QTR P&L'!T2*'BS DRIVERS'!Q5/ASSUMPTIONS!$B$2 | R5: ='QTR P&L'!U2*'BS DRIVERS'!R5/ASSUMPTIONS!$B$2 | S5: ='QTR P&L'!V2*'BS DRIVERS'!S5/ASSUMPTIONS!$B$2 | T5: ='QTR P&L'!W2*'BS DRIVERS'!T5/ASSUMPTIONS!$B$2 | U5: ='QTR P&L'!X2*'BS DRIVERS'!U5/ASSUMPTIONS!$B$2 | V5: ='QTR P&L'!Y2*'BS DRIVERS'!V5/ASSUMPTIONS!$B$2 | ... AD5: ='QTR P&L'!AG2*'BS DRIVERS'!AD5/ASSUMPTIONS!$B$2
A6: Inventories | B6: ='BALANCE SHEET'!B6 | C6: ='YTD BS'!C6 | D6: ='YTD BS'!D6 | E6: ='YTD BS'!E6 | F6: ='BALANCE SHEET'!C6 | G6: ='YTD BS'!G6 | H6: ='YTD BS'!H6 | I6: ='YTD BS'!I6 | J6: ='BALANCE SHEET'!D6 | K6: ='YTD BS'!K6 | L6: ='YTD BS'!L6 | M6: ='YTD BS'!M6 | N6: ='BALANCE SHEET'!E6 | O6: ='QTR P&L'!R3*'BS DRIVERS'!O6/ASSUMPTIONS!$B$2 | P6: ='QTR P&L'!S3*'BS DRIVERS'!P6/ASSUMPTIONS!$B$2 | Q6: ='QTR P&L'!T3*'BS DRIVERS'!Q6/ASSUMPTIONS!$B$2 | R6: ='QTR P&L'!U3*'BS DRIVERS'!R6/ASSUMPTIONS!$B$2 | S6: ='QTR P&L'!V3*'BS DRIVERS'!S6/ASSUMPTIONS!$B$2 | T6: ='QTR P&L'!W3*'BS DRIVERS'!T6/ASSUMPTIONS!$B$2 | U6: ='QTR P&L'!X3*'BS DRIVERS'!U6/ASSUMPTIONS!$B$2 | V6: ='QTR P&L'!Y3*'BS DRIVERS'!V6/ASSUMPTIONS!$B$2 | ... AD6: ='QTR P&L'!AG3*'BS DRIVERS'!AD6/ASSUMPTIONS!$B$2
A7: Prepaid Expenses | B7: ='BALANCE SHEET'!B7 | C7: ='YTD BS'!C7 | D7: ='YTD BS'!D7 | E7: ='YTD BS'!E7 | F7: ='BALANCE SHEET'!C7 | G7: ='YTD BS'!G7 | H7: ='YTD BS'!H7 | I7: ='YTD BS'!I7 | J7: ='BALANCE SHEET'!D7 | K7: ='YTD BS'!K7 | L7: ='YTD BS'!L7 | M7: ='YTD BS'!M7 | N7: ='BALANCE SHEET'!E7 | O7: ='QTR P&L'!R2*'BS DRIVERS'!O7 | P7: ='QTR P&L'!S2*'BS DRIVERS'!P7 | Q7: ='QTR P&L'!T2*'BS DRIVERS'!Q7 | R7: ='QTR P&L'!U2*'BS DRIVERS'!R7 | S7: ='QTR P&L'!V2*'BS DRIVERS'!S7 | T7: ='QTR P&L'!W2*'BS DRIVERS'!T7 | U7: ='QTR P&L'!X2*'BS DRIVERS'!U7 | V7: ='QTR P&L'!Y2*'BS DRIVERS'!V7 | ... AD7: ='QTR P&L'!AG2*'BS DRIVERS'!AD7
A8: Deferred Other Costs - Current | B8: ='BALANCE SHEET'!B8 | C8: ='YTD BS'!C8 | D8: ='YTD BS'!D8 | E8: ='YTD BS'!E8 | F8: ='BALANCE SHEET'!C8 | G8: ='YTD BS'!G8 | H8: ='YTD BS'!H8 | I8: ='YTD BS'!I8 | J8: ='BALANCE SHEET'!D8 | K8: ='YTD BS'!K8 | L8: ='YTD BS'!L8 | M8: ='YTD BS'!M8 | N8: ='BALANCE SHEET'!E8 | O8: ='QTR P&L'!R2*'BS DRIVERS'!O8 | P8: ='QTR P&L'!S2*'BS DRIVERS'!P8 | Q8: ='QTR P&L'!T2*'BS DRIVERS'!Q8 | R8: ='QTR P&L'!U2*'BS DRIVERS'!R8 | S8: ='QTR P&L'!V2*'BS DRIVERS'!S8 | T8: ='QTR P&L'!W2*'BS DRIVERS'!T8 | U8: ='QTR P&L'!X2*'BS DRIVERS'!U8 | V8: ='QTR P&L'!Y2*'BS DRIVERS'!V8 | ... AD8: ='QTR P&L'!AG2*'BS DRIVERS'!AD8
A9: Total Current Assets | B9: ='BALANCE SHEET'!B9 | C9: ='YTD BS'!C9 | D9: ='YTD BS'!D9 | E9: ='YTD BS'!E9 | F9: ='BALANCE SHEET'!C9 | G9: ='YTD BS'!G9 | H9: ='YTD BS'!H9 | I9: ='YTD BS'!I9 | J9: ='BALANCE SHEET'!D9 | K9: ='YTD BS'!K9 | L9: ='YTD BS'!L9 | M9: ='YTD BS'!M9 | N9: ='BALANCE SHEET'!E9 | O9: =SUM(O2:O8) | P9: =SUM(P2:P8) | Q9: =SUM(Q2:Q8) | R9: =SUM(R2:R8) | S9: =SUM(S2:S8) | T9: =SUM(T2:T8) | U9: =SUM(U2:U8) | V9: =SUM(V2:V8) | ... AD9: =SUM(AD2:AD8)
A10: Note Receivable - Non-Current | B10: ='BALANCE SHEET'!B10 | C10: ='YTD BS'!C10 | D10: ='YTD BS'!D10 | E10: ='YTD BS'!E10 | F10: ='BALANCE SHEET'!C10 | G10: ='YTD BS'!G10 | H10: ='YTD BS'!H10 | I10: ='YTD BS'!I10 | J10: ='BALANCE SHEET'!D10 | K10: ='YTD BS'!K10 | L10: ='YTD BS'!L10 | M10: ='YTD BS'!M10 | N10: ='BALANCE SHEET'!E10 | O10: ='QTR P&L'!R2*'BS DRIVERS'!O9 | P10: ='QTR P&L'!S2*'BS DRIVERS'!P9 | Q10: ='QTR P&L'!T2*'BS DRIVERS'!Q9 | R10: ='QTR P&L'!U2*'BS DRIVERS'!R9 | S10: ='QTR P&L'!V2*'BS DRIVERS'!S9 | T10: ='QTR P&L'!W2*'BS DRIVERS'!T9 | U10: ='QTR P&L'!X2*'BS DRIVERS'!U9 | V10: ='QTR P&L'!Y2*'BS DRIVERS'!V9 | ... AD10: ='QTR P&L'!AG2*'BS DRIVERS'!AD9
A11: Net PP&E | B11: ='BALANCE SHEET'!B11 | C11: ='YTD BS'!C11 | D11: ='YTD BS'!D11 | E11: ='YTD BS'!E11 | F11: ='BALANCE SHEET'!C11 | G11: ='YTD BS'!G11 | H11: ='YTD BS'!H11 | I11: ='YTD BS'!I11 | J11: ='BALANCE SHEET'!D11 | K11: ='YTD BS'!K11 | L11: ='YTD BS'!L11 | M11: ='YTD BS'!M11 | N11: ='BALANCE SHEET'!E11 | O11: ='BS DRIVERS'!O10 | P11: ='BS DRIVERS'!P10 | Q11: ='BS DRIVERS'!Q10 | R11: ='BS DRIVERS'!R10 | S11: ='BS DRIVERS'!S10 | T11: ='BS DRIVERS'!T10 | U11: ='BS DRIVERS'!U10 | V11: ='BS DRIVERS'!V10 | ... AD11: ='BS DRIVERS'!AD10
A12: ROU Assets - Operating - Non-Current | B12: ='BALANCE SHEET'!B12 | C12: ='YTD BS'!C12 | D12: ='YTD BS'!D12 | E12: ='YTD BS'!E12 | F12: ='BALANCE SHEET'!C12 | G12: ='YTD BS'!G12 | H12: ='YTD BS'!H12 | I12: ='YTD BS'!I12 | J12: ='BALANCE SHEET'!D12 | K12: ='YTD BS'!K12 | L12: ='YTD BS'!L12 | M12: ='YTD BS'!M12 | N12: ='BALANCE SHEET'!E12 | O12: ='QTR P&L'!R2*'BS DRIVERS'!O11 | P12: ='QTR P&L'!S2*'BS DRIVERS'!P11 | Q12: ='QTR P&L'!T2*'BS DRIVERS'!Q11 | R12: ='QTR P&L'!U2*'BS DRIVERS'!R11 | S12: ='QTR P&L'!V2*'BS DRIVERS'!S11 | T12: ='QTR P&L'!W2*'BS DRIVERS'!T11 | U12: ='QTR P&L'!X2*'BS DRIVERS'!U11 | V12: ='QTR P&L'!Y2*'BS DRIVERS'!V11 | ... AD12: ='QTR P&L'!AG2*'BS DRIVERS'!AD11
A13: Intangible Assets | B13: ='BALANCE SHEET'!B14 | C13: ='YTD BS'!C13 | D13: ='YTD BS'!D13 | E13: ='YTD BS'!E13 | F13: ='BALANCE SHEET'!C14 | G13: ='YTD BS'!G13 | H13: ='YTD BS'!H13 | I13: ='YTD BS'!I13 | J13: ='BALANCE SHEET'!D14 | K13: ='YTD BS'!K13 | L13: ='YTD BS'!L13 | M13: ='YTD BS'!M13 | N13: ='BALANCE SHEET'!E14 | O13: ='BS DRIVERS'!O12 | P13: ='BS DRIVERS'!P12 | Q13: ='BS DRIVERS'!Q12 | R13: ='BS DRIVERS'!R12 | S13: ='BS DRIVERS'!S12 | T13: ='BS DRIVERS'!T12 | U13: ='BS DRIVERS'!U12 | V13: ='BS DRIVERS'!V12 | ... AD13: ='BS DRIVERS'!AD12
A14: Goodwill | B14: ='BALANCE SHEET'!B15 | C14: ='YTD BS'!C14 | D14: ='YTD BS'!D14 | E14: ='YTD BS'!E14 | F14: ='BALANCE SHEET'!C15 | G14: ='YTD BS'!G14 | H14: ='YTD BS'!H14 | I14: ='YTD BS'!I14 | J14: ='BALANCE SHEET'!D15 | K14: ='YTD BS'!K14 | L14: ='YTD BS'!L14 | M14: ='YTD BS'!M14 | N14: ='BALANCE SHEET'!E15 | O14: ='BS DRIVERS'!O13 | P14: ='BS DRIVERS'!P13 | Q14: ='BS DRIVERS'!Q13 | R14: ='BS DRIVERS'!R13 | S14: ='BS DRIVERS'!S13 | T14: ='BS DRIVERS'!T13 | U14: ='BS DRIVERS'!U13 | V14: ='BS DRIVERS'!V13 | ... AD14: ='BS DRIVERS'!AD13
A15: Deferred Other Costs - Non-Current | B15: ='BALANCE SHEET'!B16 | C15: ='YTD BS'!C15 | D15: ='YTD BS'!D15 | E15: ='YTD BS'!E15 | F15: ='BALANCE SHEET'!C16 | G15: ='YTD BS'!G15 | H15: ='YTD BS'!H15 | I15: ='YTD BS'!I15 | J15: ='BALANCE SHEET'!D16 | K15: ='YTD BS'!K15 | L15: ='YTD BS'!L15 | M15: ='YTD BS'!M15 | N15: ='BALANCE SHEET'!E16 | O15: ='QTR P&L'!R2*'BS DRIVERS'!O14 | P15: ='QTR P&L'!S2*'BS DRIVERS'!P14 | Q15: ='QTR P&L'!T2*'BS DRIVERS'!Q14 | R15: ='QTR P&L'!U2*'BS DRIVERS'!R14 | S15: ='QTR P&L'!V2*'BS DRIVERS'!S14 | T15: ='QTR P&L'!W2*'BS DRIVERS'!T14 | U15: ='QTR P&L'!X2*'BS DRIVERS'!U14 | V15: ='QTR P&L'!Y2*'BS DRIVERS'!V14 | ... AD15: ='QTR P&L'!AG2*'BS DRIVERS'!AD14
A16: Deferred Tax Assets | B16: ='BALANCE SHEET'!B17 | C16: ='YTD BS'!C16 | D16: ='YTD BS'!D16 | E16: ='YTD BS'!E16 | F16: ='BALANCE SHEET'!C17 | G16: ='YTD BS'!G16 | H16: ='YTD BS'!H16 | I16: ='YTD BS'!I16 | J16: ='BALANCE SHEET'!D17 | K16: ='YTD BS'!K16 | L16: ='YTD BS'!L16 | M16: ='YTD BS'!M16 | N16: ='BALANCE SHEET'!E17 | O16: ='BS DRIVERS'!O15 | P16: ='BS DRIVERS'!P15 | Q16: ='BS DRIVERS'!Q15 | R16: ='BS DRIVERS'!R15 | S16: ='BS DRIVERS'!S15 | T16: ='BS DRIVERS'!T15 | U16: ='BS DRIVERS'!U15 | V16: ='BS DRIVERS'!V15 | ... AD16: ='BS DRIVERS'!AD15
A17: ROU Assets - Finance - Non-Current | B17: ='BALANCE SHEET'!B13 | C17: ='YTD BS'!C17 | D17: ='YTD BS'!D17 | E17: ='YTD BS'!E17 | F17: ='BALANCE SHEET'!C13 | G17: ='YTD BS'!G17 | H17: ='YTD BS'!H17 | I17: ='YTD BS'!I17 | J17: ='BALANCE SHEET'!D13 | K17: ='YTD BS'!K17 | L17: ='YTD BS'!L17 | M17: ='YTD BS'!M17 | N17: ='BALANCE SHEET'!E13 | O17: ='QTR P&L'!R2*'BS DRIVERS'!O16 | P17: ='QTR P&L'!S2*'BS DRIVERS'!P16 | Q17: ='QTR P&L'!T2*'BS DRIVERS'!Q16 | R17: ='QTR P&L'!U2*'BS DRIVERS'!R16 | S17: ='QTR P&L'!V2*'BS DRIVERS'!S16 | T17: ='QTR P&L'!W2*'BS DRIVERS'!T16 | U17: ='QTR P&L'!X2*'BS DRIVERS'!U16 | V17: ='QTR P&L'!Y2*'BS DRIVERS'!V16 | ... AD17: ='QTR P&L'!AG2*'BS DRIVERS'!AD16
A18: Other Non-Current Assets | B18: ='BALANCE SHEET'!B18 | C18: ='YTD BS'!C18 | D18: ='YTD BS'!D18 | E18: ='YTD BS'!E18 | F18: ='BALANCE SHEET'!C18 | G18: ='YTD BS'!G18 | H18: ='YTD BS'!H18 | I18: ='YTD BS'!I18 | J18: ='BALANCE SHEET'!D18 | K18: ='YTD BS'!K18 | L18: ='YTD BS'!L18 | M18: ='YTD BS'!M18 | N18: ='BALANCE SHEET'!E18 | O18: ='QTR P&L'!R2*'BS DRIVERS'!O17 | P18: ='QTR P&L'!S2*'BS DRIVERS'!P17 | Q18: ='QTR P&L'!T2*'BS DRIVERS'!Q17 | R18: ='QTR P&L'!U2*'BS DRIVERS'!R17 | S18: ='QTR P&L'!V2*'BS DRIVERS'!S17 | T18: ='QTR P&L'!W2*'BS DRIVERS'!T17 | U18: ='QTR P&L'!X2*'BS DRIVERS'!U17 | V18: ='QTR P&L'!Y2*'BS DRIVERS'!V17 | ... AD18: ='QTR P&L'!AG2*'BS DRIVERS'!AD17
A19: Total Assets | B19: ='BALANCE SHEET'!B19 | C19: ='YTD BS'!C19 | D19: ='YTD BS'!D19 | E19: ='YTD BS'!E19 | F19: ='BALANCE SHEET'!C19 | G19: ='YTD BS'!G19 | H19: ='YTD BS'!H19 | I19: ='YTD BS'!I19 | J19: ='BALANCE SHEET'!D19 | K19: ='YTD BS'!K19 | L19: ='YTD BS'!L19 | M19: ='YTD BS'!M19 | N19: ='BALANCE SHEET'!E19 | O19: =O9+SUM(O10:O18) | P19: =P9+SUM(P10:P18) | Q19: =Q9+SUM(Q10:Q18) | R19: =R9+SUM(R10:R18) | S19: =S9+SUM(S10:S18) | T19: =T9+SUM(T10:T18) | U19: =U9+SUM(U10:U18) | V19: =V9+SUM(V10:V18) | ... AD19: =AD9+SUM(AD10:AD18)
A20: Accounts Payable | B20: ='BALANCE SHEET'!B20 | C20: ='YTD BS'!C20 | D20: ='YTD BS'!D20 | E20: ='YTD BS'!E20 | F20: ='BALANCE SHEET'!C20 | G20: ='YTD BS'!G20 | H20: ='YTD BS'!H20 | I20: ='YTD BS'!I20 | J20: ='BALANCE SHEET'!D20 | K20: ='YTD BS'!K20 | L20: ='YTD BS'!L20 | M20: ='YTD BS'!M20 | N20: ='BALANCE SHEET'!E20 | O20: ='QTR P&L'!R3*'BS DRIVERS'!O18/ASSUMPTIONS!$B$2 | P20: ='QTR P&L'!S3*'BS DRIVERS'!P18/ASSUMPTIONS!$B$2 | Q20: ='QTR P&L'!T3*'BS DRIVERS'!Q18/ASSUMPTIONS!$B$2 | R20: ='QTR P&L'!U3*'BS DRIVERS'!R18/ASSUMPTIONS!$B$2 | S20: ='QTR P&L'!V3*'BS DRIVERS'!S18/ASSUMPTIONS!$B$2 | T20: ='QTR P&L'!W3*'BS DRIVERS'!T18/ASSUMPTIONS!$B$2 | U20: ='QTR P&L'!X3*'BS DRIVERS'!U18/ASSUMPTIONS!$B$2 | V20: ='QTR P&L'!Y3*'BS DRIVERS'!V18/ASSUMPTIONS!$B$2 | ... AD20: ='QTR P&L'!AG3*'BS DRIVERS'!AD18/ASSUMPTIONS!$B$2
A21: Accrued Expenses | B21: ='BALANCE SHEET'!B21 | C21: ='YTD BS'!C21 | D21: ='YTD BS'!D21 | E21: ='YTD BS'!E21 | F21: ='BALANCE SHEET'!C21 | G21: ='YTD BS'!G21 | H21: ='YTD BS'!H21 | I21: ='YTD BS'!I21 | J21: ='BALANCE SHEET'!D21 | K21: ='YTD BS'!K21 | L21: ='YTD BS'!L21 | M21: ='YTD BS'!M21 | N21: ='BALANCE SHEET'!E21 | O21: ='QTR P&L'!R2*'BS DRIVERS'!O19 | P21: ='QTR P&L'!S2*'BS DRIVERS'!P19 | Q21: ='QTR P&L'!T2*'BS DRIVERS'!Q19 | R21: ='QTR P&L'!U2*'BS DRIVERS'!R19 | S21: ='QTR P&L'!V2*'BS DRIVERS'!S19 | T21: ='QTR P&L'!W2*'BS DRIVERS'!T19 | U21: ='QTR P&L'!X2*'BS DRIVERS'!U19 | V21: ='QTR P&L'!Y2*'BS DRIVERS'!V19 | ... AD21: ='QTR P&L'!AG2*'BS DRIVERS'!AD19
A22: Income Taxes Payable | B22: ='BALANCE SHEET'!B22 | C22: ='YTD BS'!C22 | D22: ='YTD BS'!D22 | E22: ='YTD BS'!E22 | F22: ='BALANCE SHEET'!C22 | G22: ='YTD BS'!G22 | H22: ='YTD BS'!H22 | I22: ='YTD BS'!I22 | J22: ='BALANCE SHEET'!D22 | K22: ='YTD BS'!K22 | L22: ='YTD BS'!L22 | M22: ='YTD BS'!M22 | N22: ='BALANCE SHEET'!E22 | O22: ='QTR P&L'!R2*'BS DRIVERS'!O20 | P22: ='QTR P&L'!S2*'BS DRIVERS'!P20 | Q22: ='QTR P&L'!T2*'BS DRIVERS'!Q20 | R22: ='QTR P&L'!U2*'BS DRIVERS'!R20 | S22: ='QTR P&L'!V2*'BS DRIVERS'!S20 | T22: ='QTR P&L'!W2*'BS DRIVERS'!T20 | U22: ='QTR P&L'!X2*'BS DRIVERS'!U20 | V22: ='QTR P&L'!Y2*'BS DRIVERS'!V20 | ... AD22: ='QTR P&L'!AG2*'BS DRIVERS'!AD20
A23: Accrued Distributor Termination Fees | B23: ='BALANCE SHEET'!B23 | C23: ='YTD BS'!C23 | D23: ='YTD BS'!D23 | E23: ='YTD BS'!E23 | F23: ='BALANCE SHEET'!C23 | G23: ='YTD BS'!G23 | H23: ='YTD BS'!H23 | I23: ='YTD BS'!I23 | J23: ='BALANCE SHEET'!D23 | K23: ='YTD BS'!K23 | L23: ='YTD BS'!L23 | M23: ='YTD BS'!M23 | N23: ='BALANCE SHEET'!E23 | O23: ='BS DRIVERS'!O21 | P23: ='BS DRIVERS'!P21 | Q23: ='BS DRIVERS'!Q21 | R23: ='BS DRIVERS'!R21 | S23: ='BS DRIVERS'!S21 | T23: ='BS DRIVERS'!T21 | U23: ='BS DRIVERS'!U21 | V23: ='BS DRIVERS'!V21 | ... AD23: ='BS DRIVERS'!AD21
A24: Accrued Promotional Allowance | B24: ='BALANCE SHEET'!B24 | C24: ='YTD BS'!C24 | D24: ='YTD BS'!D24 | E24: ='YTD BS'!E24 | F24: ='BALANCE SHEET'!C24 | G24: ='YTD BS'!G24 | H24: ='YTD BS'!H24 | I24: ='YTD BS'!I24 | J24: ='BALANCE SHEET'!D24 | K24: ='YTD BS'!K24 | L24: ='YTD BS'!L24 | M24: ='YTD BS'!M24 | N24: ='BALANCE SHEET'!E24 | O24: ='QTR P&L'!R2*'BS DRIVERS'!O22 | P24: ='QTR P&L'!S2*'BS DRIVERS'!P22 | Q24: ='QTR P&L'!T2*'BS DRIVERS'!Q22 | R24: ='QTR P&L'!U2*'BS DRIVERS'!R22 | S24: ='QTR P&L'!V2*'BS DRIVERS'!S22 | T24: ='QTR P&L'!W2*'BS DRIVERS'!T22 | U24: ='QTR P&L'!X2*'BS DRIVERS'!U22 | V24: ='QTR P&L'!Y2*'BS DRIVERS'!V22 | ... AD24: ='QTR P&L'!AG2*'BS DRIVERS'!AD22
A25: Lease Liability - Operating - Current | B25: ='BALANCE SHEET'!B25 | C25: ='YTD BS'!C25 | D25: ='YTD BS'!D25 | E25: ='YTD BS'!E25 | F25: ='BALANCE SHEET'!C25 | G25: ='YTD BS'!G25 | H25: ='YTD BS'!H25 | I25: ='YTD BS'!I25 | J25: ='BALANCE SHEET'!D25 | K25: ='YTD BS'!K25 | L25: ='YTD BS'!L25 | M25: ='YTD BS'!M25 | N25: ='BALANCE SHEET'!E25 | O25: ='QTR P&L'!R2*'BS DRIVERS'!O23 | P25: ='QTR P&L'!S2*'BS DRIVERS'!P23 | Q25: ='QTR P&L'!T2*'BS DRIVERS'!Q23 | R25: ='QTR P&L'!U2*'BS DRIVERS'!R23 | S25: ='QTR P&L'!V2*'BS DRIVERS'!S23 | T25: ='QTR P&L'!W2*'BS DRIVERS'!T23 | U25: ='QTR P&L'!X2*'BS DRIVERS'!U23 | V25: ='QTR P&L'!Y2*'BS DRIVERS'!V23 | ... AD25: ='QTR P&L'!AG2*'BS DRIVERS'!AD23
A26: Lease Liability - Finance - Current | B26: ='BALANCE SHEET'!B26 | C26: ='YTD BS'!C26 | D26: ='YTD BS'!D26 | E26: ='YTD BS'!E26 | F26: ='BALANCE SHEET'!C26 | G26: ='YTD BS'!G26 | H26: ='YTD BS'!H26 | I26: ='YTD BS'!I26 | J26: ='BALANCE SHEET'!D26 | K26: ='YTD BS'!K26 | L26: ='YTD BS'!L26 | M26: ='YTD BS'!M26 | N26: ='BALANCE SHEET'!E26 | O26: ='QTR P&L'!R2*'BS DRIVERS'!O24 | P26: ='QTR P&L'!S2*'BS DRIVERS'!P24 | Q26: ='QTR P&L'!T2*'BS DRIVERS'!Q24 | R26: ='QTR P&L'!U2*'BS DRIVERS'!R24 | S26: ='QTR P&L'!V2*'BS DRIVERS'!S24 | T26: ='QTR P&L'!W2*'BS DRIVERS'!T24 | U26: ='QTR P&L'!X2*'BS DRIVERS'!U24 | V26: ='QTR P&L'!Y2*'BS DRIVERS'!V24 | ... AD26: ='QTR P&L'!AG2*'BS DRIVERS'!AD24
A27: Contingent Consideration - Current | B27: ='BALANCE SHEET'!B27 | C27: ='YTD BS'!C27 | D27: ='YTD BS'!D27 | E27: ='YTD BS'!E27 | F27: ='BALANCE SHEET'!C27 | G27: ='YTD BS'!G27 | H27: ='YTD BS'!H27 | I27: ='YTD BS'!I27 | J27: ='BALANCE SHEET'!D27 | K27: ='YTD BS'!K27 | L27: ='YTD BS'!L27 | M27: ='YTD BS'!M27 | N27: ='BALANCE SHEET'!E27 | O27: ='QTR P&L'!R2*'BS DRIVERS'!O25 | P27: ='QTR P&L'!S2*'BS DRIVERS'!P25 | Q27: ='QTR P&L'!T2*'BS DRIVERS'!Q25 | R27: ='QTR P&L'!U2*'BS DRIVERS'!R25 | S27: ='QTR P&L'!V2*'BS DRIVERS'!S25 | T27: ='QTR P&L'!W2*'BS DRIVERS'!T25 | U27: ='QTR P&L'!X2*'BS DRIVERS'!U25 | V27: ='QTR P&L'!Y2*'BS DRIVERS'!V25 | ... AD27: ='QTR P&L'!AG2*'BS DRIVERS'!AD25
A28: Deferred Revenue - Current | B28: ='BALANCE SHEET'!B28 | C28: ='YTD BS'!C28 | D28: ='YTD BS'!D28 | E28: ='YTD BS'!E28 | F28: ='BALANCE SHEET'!C28 | G28: ='YTD BS'!G28 | H28: ='YTD BS'!H28 | I28: ='YTD BS'!I28 | J28: ='BALANCE SHEET'!D28 | K28: ='YTD BS'!K28 | L28: ='YTD BS'!L28 | M28: ='YTD BS'!M28 | N28: ='BALANCE SHEET'!E28 | O28: ='QTR P&L'!R2*'BS DRIVERS'!O26 | P28: ='QTR P&L'!S2*'BS DRIVERS'!P26 | Q28: ='QTR P&L'!T2*'BS DRIVERS'!Q26 | R28: ='QTR P&L'!U2*'BS DRIVERS'!R26 | S28: ='QTR P&L'!V2*'BS DRIVERS'!S26 | T28: ='QTR P&L'!W2*'BS DRIVERS'!T26 | U28: ='QTR P&L'!X2*'BS DRIVERS'!U26 | V28: ='QTR P&L'!Y2*'BS DRIVERS'!V26 | ... AD28: ='QTR P&L'!AG2*'BS DRIVERS'!AD26
A29: Other Current Liabilities | B29: ='BALANCE SHEET'!B29 | C29: ='YTD BS'!C29 | D29: ='YTD BS'!D29 | E29: ='YTD BS'!E29 | F29: ='BALANCE SHEET'!C29 | G29: ='YTD BS'!G29 | H29: ='YTD BS'!H29 | I29: ='YTD BS'!I29 | J29: ='BALANCE SHEET'!D29 | K29: ='YTD BS'!K29 | L29: ='YTD BS'!L29 | M29: ='YTD BS'!M29 | N29: ='BALANCE SHEET'!E29 | O29: ='QTR P&L'!R2*'BS DRIVERS'!O27 | P29: ='QTR P&L'!S2*'BS DRIVERS'!P27 | Q29: ='QTR P&L'!T2*'BS DRIVERS'!Q27 | R29: ='QTR P&L'!U2*'BS DRIVERS'!R27 | S29: ='QTR P&L'!V2*'BS DRIVERS'!S27 | T29: ='QTR P&L'!W2*'BS DRIVERS'!T27 | U29: ='QTR P&L'!X2*'BS DRIVERS'!U27 | V29: ='QTR P&L'!Y2*'BS DRIVERS'!V27 | ... AD29: ='QTR P&L'!AG2*'BS DRIVERS'!AD27
A30: Total Current Liabilities | B30: ='BALANCE SHEET'!B30 | C30: ='YTD BS'!C30 | D30: ='YTD BS'!D30 | E30: ='YTD BS'!E30 | F30: ='BALANCE SHEET'!C30 | G30: ='YTD BS'!G30 | H30: ='YTD BS'!H30 | I30: ='YTD BS'!I30 | J30: ='BALANCE SHEET'!D30 | K30: ='YTD BS'!K30 | L30: ='YTD BS'!L30 | M30: ='YTD BS'!M30 | N30: ='BALANCE SHEET'!E30 | O30: =SUM(O20:O29) | P30: =SUM(P20:P29) | Q30: =SUM(Q20:Q29) | R30: =SUM(R20:R29) | S30: =SUM(S20:S29) | T30: =SUM(T20:T29) | U30: =SUM(U20:U29) | V30: =SUM(V20:V29) | ... AD30: =SUM(AD20:AD29)
A31: Lease Liability - Operating - Non-Current | B31: ='BALANCE SHEET'!B31 | C31: ='YTD BS'!C31 | D31: ='YTD BS'!D31 | E31: ='YTD BS'!E31 | F31: ='BALANCE SHEET'!C31 | G31: ='YTD BS'!G31 | H31: ='YTD BS'!H31 | I31: ='YTD BS'!I31 | J31: ='BALANCE SHEET'!D31 | K31: ='YTD BS'!K31 | L31: ='YTD BS'!L31 | M31: ='YTD BS'!M31 | N31: ='BALANCE SHEET'!E31 | O31: ='QTR P&L'!R2*'BS DRIVERS'!O28 | P31: ='QTR P&L'!S2*'BS DRIVERS'!P28 | Q31: ='QTR P&L'!T2*'BS DRIVERS'!Q28 | R31: ='QTR P&L'!U2*'BS DRIVERS'!R28 | S31: ='QTR P&L'!V2*'BS DRIVERS'!S28 | T31: ='QTR P&L'!W2*'BS DRIVERS'!T28 | U31: ='QTR P&L'!X2*'BS DRIVERS'!U28 | V31: ='QTR P&L'!Y2*'BS DRIVERS'!V28 | ... AD31: ='QTR P&L'!AG2*'BS DRIVERS'!AD28
A32: Lease Liability - Finance - Non-Current | B32: ='BALANCE SHEET'!B32 | C32: ='YTD BS'!C32 | D32: ='YTD BS'!D32 | E32: ='YTD BS'!E32 | F32: ='BALANCE SHEET'!C32 | G32: ='YTD BS'!G32 | H32: ='YTD BS'!H32 | I32: ='YTD BS'!I32 | J32: ='BALANCE SHEET'!D32 | K32: ='YTD BS'!K32 | L32: ='YTD BS'!L32 | M32: ='YTD BS'!M32 | N32: ='BALANCE SHEET'!E32 | O32: ='QTR P&L'!R2*'BS DRIVERS'!O29 | P32: ='QTR P&L'!S2*'BS DRIVERS'!P29 | Q32: ='QTR P&L'!T2*'BS DRIVERS'!Q29 | R32: ='QTR P&L'!U2*'BS DRIVERS'!R29 | S32: ='QTR P&L'!V2*'BS DRIVERS'!S29 | T32: ='QTR P&L'!W2*'BS DRIVERS'!T29 | U32: ='QTR P&L'!X2*'BS DRIVERS'!U29 | V32: ='QTR P&L'!Y2*'BS DRIVERS'!V29 | ... AD32: ='QTR P&L'!AG2*'BS DRIVERS'!AD29
A33: Deferred Tax Liability | B33: ='BALANCE SHEET'!B33 | C33: ='YTD BS'!C33 | D33: ='YTD BS'!D33 | E33: ='YTD BS'!E33 | F33: ='BALANCE SHEET'!C33 | G33: ='YTD BS'!G33 | H33: ='YTD BS'!H33 | I33: ='YTD BS'!I33 | J33: ='BALANCE SHEET'!D33 | K33: ='YTD BS'!K33 | L33: ='YTD BS'!L33 | M33: ='YTD BS'!M33 | N33: ='BALANCE SHEET'!E33 | O33: ='BS DRIVERS'!O30 | P33: ='BS DRIVERS'!P30 | Q33: ='BS DRIVERS'!Q30 | R33: ='BS DRIVERS'!R30 | S33: ='BS DRIVERS'!S30 | T33: ='BS DRIVERS'!T30 | U33: ='BS DRIVERS'!U30 | V33: ='BS DRIVERS'!V30 | ... AD33: ='BS DRIVERS'!AD30
A34: Long-Term Debt | B34: ='BALANCE SHEET'!B34 | C34: ='YTD BS'!C34 | D34: ='YTD BS'!D34 | E34: ='YTD BS'!E34 | F34: ='BALANCE SHEET'!C34 | G34: ='YTD BS'!G34 | H34: ='YTD BS'!H34 | I34: ='YTD BS'!I34 | J34: ='BALANCE SHEET'!D34 | K34: ='YTD BS'!K34 | L34: ='YTD BS'!L34 | M34: ='YTD BS'!M34 | N34: ='BALANCE SHEET'!E34 | O34: ='BS DRIVERS'!O31 | P34: ='BS DRIVERS'!P31 | Q34: ='BS DRIVERS'!Q31 | R34: ='BS DRIVERS'!R31 | S34: ='BS DRIVERS'!S31 | T34: ='BS DRIVERS'!T31 | U34: ='BS DRIVERS'!U31 | V34: ='BS DRIVERS'!V31 | ... AD34: ='BS DRIVERS'!AD31
A35: Deferred Revenue - Non-Current | B35: ='BALANCE SHEET'!B35 | C35: ='YTD BS'!C35 | D35: ='YTD BS'!D35 | E35: ='YTD BS'!E35 | F35: ='BALANCE SHEET'!C35 | G35: ='YTD BS'!G35 | H35: ='YTD BS'!H35 | I35: ='YTD BS'!I35 | J35: ='BALANCE SHEET'!D35 | K35: ='YTD BS'!K35 | L35: ='YTD BS'!L35 | M35: ='YTD BS'!M35 | N35: ='BALANCE SHEET'!E35 | O35: ='QTR P&L'!R2*'BS DRIVERS'!O32 | P35: ='QTR P&L'!S2*'BS DRIVERS'!P32 | Q35: ='QTR P&L'!T2*'BS DRIVERS'!Q32 | R35: ='QTR P&L'!U2*'BS DRIVERS'!R32 | S35: ='QTR P&L'!V2*'BS DRIVERS'!S32 | T35: ='QTR P&L'!W2*'BS DRIVERS'!T32 | U35: ='QTR P&L'!X2*'BS DRIVERS'!U32 | V35: ='QTR P&L'!Y2*'BS DRIVERS'!V32 | ... AD35: ='QTR P&L'!AG2*'BS DRIVERS'!AD32
A36: Other Non-Current Liabilities | B36: ='BALANCE SHEET'!B36 | C36: ='YTD BS'!C36 | D36: ='YTD BS'!D36 | E36: ='YTD BS'!E36 | F36: ='BALANCE SHEET'!C36 | G36: ='YTD BS'!G36 | H36: ='YTD BS'!H36 | I36: ='YTD BS'!I36 | J36: ='BALANCE SHEET'!D36 | K36: ='YTD BS'!K36 | L36: ='YTD BS'!L36 | M36: ='YTD BS'!M36 | N36: ='BALANCE SHEET'!E36 | O36: ='QTR P&L'!R2*'BS DRIVERS'!O33 | P36: ='QTR P&L'!S2*'BS DRIVERS'!P33 | Q36: ='QTR P&L'!T2*'BS DRIVERS'!Q33 | R36: ='QTR P&L'!U2*'BS DRIVERS'!R33 | S36: ='QTR P&L'!V2*'BS DRIVERS'!S33 | T36: ='QTR P&L'!W2*'BS DRIVERS'!T33 | U36: ='QTR P&L'!X2*'BS DRIVERS'!U33 | V36: ='QTR P&L'!Y2*'BS DRIVERS'!V33 | ... AD36: ='QTR P&L'!AG2*'BS DRIVERS'!AD33
A37: Total Liabilities | B37: ='BALANCE SHEET'!B37 | C37: ='YTD BS'!C37 | D37: ='YTD BS'!D37 | E37: ='YTD BS'!E37 | F37: ='BALANCE SHEET'!C37 | G37: ='YTD BS'!G37 | H37: ='YTD BS'!H37 | I37: ='YTD BS'!I37 | J37: ='BALANCE SHEET'!D37 | K37: ='YTD BS'!K37 | L37: ='YTD BS'!L37 | M37: ='YTD BS'!M37 | N37: ='BALANCE SHEET'!E37 | O37: =O30+SUM(O31:O36) | P37: =P30+SUM(P31:P36) | Q37: =Q30+SUM(Q31:Q36) | R37: =R30+SUM(R31:R36) | S37: =S30+SUM(S31:S36) | T37: =T30+SUM(T31:T36) | U37: =U30+SUM(U31:U36) | V37: =V30+SUM(V31:V36) | ... AD37: =AD30+SUM(AD31:AD36)
A38: Convertible Preferred Stock | B38: ='BALANCE SHEET'!B38 | C38: ='YTD BS'!C38 | D38: ='YTD BS'!D38 | E38: ='YTD BS'!E38 | F38: ='BALANCE SHEET'!C38 | G38: ='YTD BS'!G38 | H38: ='YTD BS'!H38 | I38: ='YTD BS'!I38 | J38: ='BALANCE SHEET'!D38 | K38: ='YTD BS'!K38 | L38: ='YTD BS'!L38 | M38: ='YTD BS'!M38 | N38: ='BALANCE SHEET'!E38 | O38: ='BS DRIVERS'!O34 | P38: ='BS DRIVERS'!P34 | Q38: ='BS DRIVERS'!Q34 | R38: ='BS DRIVERS'!R34 | S38: ='BS DRIVERS'!S34 | T38: ='BS DRIVERS'!T34 | U38: ='BS DRIVERS'!U34 | V38: ='BS DRIVERS'!V34 | ... AD38: ='BS DRIVERS'!AD34
A39: Common Stock | B39: ='BALANCE SHEET'!B39 | C39: ='YTD BS'!C39 | D39: ='YTD BS'!D39 | E39: ='YTD BS'!E39 | F39: ='BALANCE SHEET'!C39 | G39: ='YTD BS'!G39 | H39: ='YTD BS'!H39 | I39: ='YTD BS'!I39 | J39: ='BALANCE SHEET'!D39 | K39: ='YTD BS'!K39 | L39: ='YTD BS'!L39 | M39: ='YTD BS'!M39 | N39: ='BALANCE SHEET'!E39 | O39: ='BS DRIVERS'!O35 | P39: ='BS DRIVERS'!P35 | Q39: ='BS DRIVERS'!Q35 | R39: ='BS DRIVERS'!R35 | S39: ='BS DRIVERS'!S35 | T39: ='BS DRIVERS'!T35 | U39: ='BS DRIVERS'!U35 | V39: ='BS DRIVERS'!V35 | ... AD39: ='BS DRIVERS'!AD35
A40: Treasury Stock | B40: ='BALANCE SHEET'!B40 | C40: ='YTD BS'!C40 | D40: ='YTD BS'!D40 | E40: ='YTD BS'!E40 | F40: ='BALANCE SHEET'!C40 | G40: ='YTD BS'!G40 | H40: ='YTD BS'!H40 | I40: ='YTD BS'!I40 | J40: ='BALANCE SHEET'!D40 | K40: ='YTD BS'!K40 | L40: ='YTD BS'!L40 | M40: ='YTD BS'!M40 | N40: ='BALANCE SHEET'!E40 | O40: ='BS DRIVERS'!O36 | P40: ='BS DRIVERS'!P36 | Q40: ='BS DRIVERS'!Q36 | R40: ='BS DRIVERS'!R36 | S40: ='BS DRIVERS'!S36 | T40: ='BS DRIVERS'!T36 | U40: ='BS DRIVERS'!U36 | V40: ='BS DRIVERS'!V36 | ... AD40: ='BS DRIVERS'!AD36
A41: Additional Paid-in Capital | B41: ='BALANCE SHEET'!B41 | C41: ='YTD BS'!C41 | D41: ='YTD BS'!D41 | E41: ='YTD BS'!E41 | F41: ='BALANCE SHEET'!C41 | G41: ='YTD BS'!G41 | H41: ='YTD BS'!H41 | I41: ='YTD BS'!I41 | J41: ='BALANCE SHEET'!D41 | K41: ='YTD BS'!K41 | L41: ='YTD BS'!L41 | M41: ='YTD BS'!M41 | N41: ='BALANCE SHEET'!E41 | O41: ='BS DRIVERS'!O37 | P41: ='BS DRIVERS'!P37 | Q41: ='BS DRIVERS'!Q37 | R41: ='BS DRIVERS'!R37 | S41: ='BS DRIVERS'!S37 | T41: ='BS DRIVERS'!T37 | U41: ='BS DRIVERS'!U37 | V41: ='BS DRIVERS'!V37 | ... AD41: ='BS DRIVERS'!AD37
A42: Accumulated Other Comprehensive Income (Loss) | B42: ='BALANCE SHEET'!B42 | C42: ='YTD BS'!C42 | D42: ='YTD BS'!D42 | E42: ='YTD BS'!E42 | F42: ='BALANCE SHEET'!C42 | G42: ='YTD BS'!G42 | H42: ='YTD BS'!H42 | I42: ='YTD BS'!I42 | J42: ='BALANCE SHEET'!D42 | K42: ='YTD BS'!K42 | L42: ='YTD BS'!L42 | M42: ='YTD BS'!M42 | N42: ='BALANCE SHEET'!E42 | O42: ='BS DRIVERS'!O38 | P42: ='BS DRIVERS'!P38 | Q42: ='BS DRIVERS'!Q38 | R42: ='BS DRIVERS'!R38 | S42: ='BS DRIVERS'!S38 | T42: ='BS DRIVERS'!T38 | U42: ='BS DRIVERS'!U38 | V42: ='BS DRIVERS'!V38 | ... AD42: ='BS DRIVERS'!AD38
A43: Retained Earnings (Accumulated Deficit) | B43: ='BALANCE SHEET'!B43 | C43: ='YTD BS'!C43 | D43: ='YTD BS'!D43 | E43: ='YTD BS'!E43 | F43: ='BALANCE SHEET'!C43 | G43: ='YTD BS'!G43 | H43: ='YTD BS'!H43 | I43: ='YTD BS'!I43 | J43: ='BALANCE SHEET'!D43 | K43: ='YTD BS'!K43 | L43: ='YTD BS'!L43 | M43: ='YTD BS'!M43 | N43: ='BALANCE SHEET'!E43 | O43: ='BS DRIVERS'!O39 | P43: ='BS DRIVERS'!P39 | Q43: ='BS DRIVERS'!Q39 | R43: ='BS DRIVERS'!R39 | S43: ='BS DRIVERS'!S39 | T43: ='BS DRIVERS'!T39 | U43: ='BS DRIVERS'!U39 | V43: ='BS DRIVERS'!V39 | ... AD43: ='BS DRIVERS'!AD39
A44: Total Stockholders' Equity | B44: ='BALANCE SHEET'!B44 | C44: ='YTD BS'!C44 | D44: ='YTD BS'!D44 | E44: ='YTD BS'!E44 | F44: ='BALANCE SHEET'!C44 | G44: ='YTD BS'!G44 | H44: ='YTD BS'!H44 | I44: ='YTD BS'!I44 | J44: ='BALANCE SHEET'!D44 | K44: ='YTD BS'!K44 | L44: ='YTD BS'!L44 | M44: ='YTD BS'!M44 | N44: ='BALANCE SHEET'!E44 | O44: =SUM(O38:O43) | P44: =SUM(P38:P43) | Q44: =SUM(Q38:Q43) | R44: =SUM(R38:R43) | S44: =SUM(S38:S43) | T44: =SUM(T38:T43) | U44: =SUM(U38:U43) | V44: =SUM(V38:V43) | ... AD44: =SUM(AD38:AD43)
A45: Total Liabilities, Mezzanine & Stockholders' Equity | B45: ='BALANCE SHEET'!B45 | C45: ='YTD BS'!C45 | D45: ='YTD BS'!D45 | E45: ='YTD BS'!E45 | F45: ='BALANCE SHEET'!C45 | G45: ='YTD BS'!G45 | H45: ='YTD BS'!H45 | I45: ='YTD BS'!I45 | J45: ='BALANCE SHEET'!D45 | K45: ='YTD BS'!K45 | L45: ='YTD BS'!L45 | M45: ='YTD BS'!M45 | N45: ='BALANCE SHEET'!E45 | O45: =O37+O44 | P45: =P37+P44 | Q45: =Q37+Q44 | R45: =R37+R44 | S45: =S37+S44 | T45: =T37+T44 | U45: =U37+U44 | V45: =V37+V44 | ... AD45: =AD37+AD44

Sheet QTR CF
B1: Q1 FY2022 | C1: Q2 FY2022 | D1: Q3 FY2022 | E1: Q4 FY2022 | F1: Q1 FY2023 | G1: Q2 FY2023 | H1: Q3 FY2023 | I1: Q4 FY2023 | J1: Q1 FY2024 | K1: Q2 FY2024 | L1: Q3 FY2024 | M1: Q4 FY2024 | N1: Q1 FY2025 | O1: Q2 FY2025 | P1: Q3 FY2025 | Q1: Q4 FY2025 | R1: Q1 FY2026E | S1: Q2 FY2026E | T1: Q3 FY2026E | U1: Q4 FY2026E | V1: Q1 FY2027E | W1: Q2 FY2027E | X1: Q3 FY2027E | Y1: Q4 FY2027E | Z1: Q1 FY2028E | AA1: Q2 FY2028E | AB1: Q3 FY2028E | AC1: Q4 FY2028E | AD1: Q1 FY2029E | AE1: Q2 FY2029E | AF1: Q3 FY2029E | AG1: Q4 FY2029E
A2: Net Income (Loss) | B2: ='YTD CF'!B2 | C2: ='YTD CF'!C2-'YTD CF'!B2 | D2: ='YTD CF'!D2-'YTD CF'!C2 | E2: ='CASH FLOW'!C2-'YTD CF'!D2 | F2: ='YTD CF'!E2 | G2: ='YTD CF'!F2-'YTD CF'!E2 | H2: ='YTD CF'!G2-'YTD CF'!F2 | I2: ='CASH FLOW'!D2-'YTD CF'!G2 | J2: ='YTD CF'!H2 | K2: ='YTD CF'!I2-'YTD CF'!H2 | L2: ='YTD CF'!J2-'YTD CF'!I2 | M2: ='CASH FLOW'!E2-'YTD CF'!J2 | N2: ='YTD CF'!K2 | O2: ='YTD CF'!L2-'YTD CF'!K2 | P2: ='YTD CF'!M2-'YTD CF'!L2 | Q2: ='CASH FLOW'!F2-'YTD CF'!M2 | R2: ='CF DRIVERS'!R2 | S2: ='CF DRIVERS'!S2 | T2: ='CF DRIVERS'!T2 | U2: ='CF DRIVERS'!U2 | V2: ='CF DRIVERS'!V2 | W2: ='CF DRIVERS'!W2 | X2: ='CF DRIVERS'!X2 | Y2: ='CF DRIVERS'!Y2 | ... AG2: ='CF DRIVERS'!AG2
A3: Depreciation | B3: ='YTD CF'!B3 | C3: ='YTD CF'!C3-'YTD CF'!B3 | D3: ='YTD CF'!D3-'YTD CF'!C3 | F3: ='YTD CF'!E3 | G3: ='YTD CF'!F3-'YTD CF'!E3 | H3: ='YTD CF'!G3-'YTD CF'!F3 | J3: ='YTD CF'!H3 | K3: ='YTD CF'!I3-'YTD CF'!H3 | L3: ='YTD CF'!J3-'YTD CF'!I3 | N3: ='YTD CF'!K3 | O3: ='YTD CF'!L3-'YTD CF'!K3 | P3: ='YTD CF'!M3-'YTD CF'!L3 | R3: ='CF DRIVERS'!R3 | S3: ='CF DRIVERS'!S3 | T3: ='CF DRIVERS'!T3 | U3: ='CF DRIVERS'!U3 | V3: ='CF DRIVERS'!V3 | W3: ='CF DRIVERS'!W3 | X3: ='CF DRIVERS'!X3 | Y3: ='CF DRIVERS'!Y3 | ... AG3: ='CF DRIVERS'!AG3
A4: Amortization | B4: ='YTD CF'!B4 | C4: ='YTD CF'!C4-'YTD CF'!B4 | D4: ='YTD CF'!D4-'YTD CF'!C4 | F4: ='YTD CF'!E4 | G4: ='YTD CF'!F4-'YTD CF'!E4 | H4: ='YTD CF'!G4-'YTD CF'!F4 | J4: ='YTD CF'!H4 | K4: ='YTD CF'!I4-'YTD CF'!H4 | L4: ='YTD CF'!J4-'YTD CF'!I4 | N4: ='YTD CF'!K4 | O4: ='YTD CF'!L4-'YTD CF'!K4 | P4: ='YTD CF'!M4-'YTD CF'!L4 | R4: ='CF DRIVERS'!R4 | S4: ='CF DRIVERS'!S4 | T4: ='CF DRIVERS'!T4 | U4: ='CF DRIVERS'!U4 | V4: ='CF DRIVERS'!V4 | W4: ='CF DRIVERS'!W4 | X4: ='CF DRIVERS'!X4 | Y4: ='CF DRIVERS'!Y4 | ... AG4: ='CF DRIVERS'!AG4
A5: Impairment of Intangibles | B5: ='YTD CF'!B5 | C5: ='YTD CF'!C5-'YTD CF'!B5 | D5: ='YTD CF'!D5-'YTD CF'!C5 | E5: ='CASH FLOW'!C4-'YTD CF'!D5 | F5: ='YTD CF'!E5 | G5: ='YTD CF'!F5-'YTD CF'!E5 | H5: ='YTD CF'!G5-'YTD CF'!F5 | I5: ='CASH FLOW'!D4-'YTD CF'!G5 | J5: ='YTD CF'!H5 | K5: ='YTD CF'!I5-'YTD CF'!H5 | L5: ='YTD CF'!J5-'YTD CF'!I5 | M5: ='CASH FLOW'!E4-'YTD CF'!J5 | N5: ='YTD CF'!K5 | O5: ='YTD CF'!L5-'YTD CF'!K5 | P5: ='YTD CF'!M5-'YTD CF'!L5 | Q5: ='CASH FLOW'!F4-'YTD CF'!M5 | R5: ='CF DRIVERS'!R5 | S5: ='CF DRIVERS'!S5 | T5: ='CF DRIVERS'!T5 | U5: ='CF DRIVERS'!U5 | V5: ='CF DRIVERS'!V5 | W5: ='CF DRIVERS'!W5 | X5: ='CF DRIVERS'!X5 | Y5: ='CF DRIVERS'!Y5 | ... AG5: ='CF DRIVERS'!AG5
A6: Depreciation & Amortization | B6: ='YTD CF'!B6 | C6: ='YTD CF'!C6-'YTD CF'!B6 | D6: ='YTD CF'!D6-'YTD CF'!C6 | E6: ='CASH FLOW'!C3-'YTD CF'!D6 | F6: ='YTD CF'!E6 | G6: ='YTD CF'!F6-'YTD CF'!E6 | H6: ='YTD CF'!G6-'YTD CF'!F6 | I6: ='CASH FLOW'!D3-'YTD CF'!G6 | J6: ='YTD CF'!H6 | K6: ='YTD CF'!I6-'YTD CF'!H6 | L6: ='YTD CF'!J6-'YTD CF'!I6 | M6: ='CASH FLOW'!E3-'YTD CF'!J6 | N6: ='YTD CF'!K6 | O6: ='YTD CF'!L6-'YTD CF'!K6 | P6: ='YTD CF'!M6-'YTD CF'!L6 | Q6: ='CASH FLOW'!F3-'YTD CF'!M6 | R6: ='QTR P&L'!R2*'CF DRIVERS'!R6 | S6: ='QTR P&L'!S2*'CF DRIVERS'!S6 | T6: ='QTR P&L'!T2*'CF DRIVERS'!T6 | U6: ='QTR P&L'!U2*'CF DRIVERS'!U6 | V6: ='QTR P&L'!V2*'CF DRIVERS'!V6 | W6: ='QTR P&L'!W2*'CF DRIVERS'!W6 | X6: ='QTR P&L'!X2*'CF DRIVERS'!X6 | Y6: ='QTR P&L'!Y2*'CF DRIVERS'!Y6 | ... AG6: ='QTR P&L'!AG2*'CF DRIVERS'!AG6
A7: Allowance for Credit Losses | B7: ='YTD CF'!B7 | C7: ='YTD CF'!C7-'YTD CF'!B7 | D7: ='YTD CF'!D7-'YTD CF'!C7 | E7: ='CASH FLOW'!C5-'YTD CF'!D7 | F7: ='YTD CF'!E7 | G7: ='YTD CF'!F7-'YTD CF'!E7 | H7: ='YTD CF'!G7-'YTD CF'!F7 | I7: ='CASH FLOW'!D5-'YTD CF'!G7 | J7: ='YTD CF'!H7 | K7: ='YTD CF'!I7-'YTD CF'!H7 | L7: ='YTD CF'!J7-'YTD CF'!I7 | M7: ='CASH FLOW'!E5-'YTD CF'!J7 | N7: ='YTD CF'!K7 | O7: ='YTD CF'!L7-'YTD CF'!K7 | P7: ='YTD CF'!M7-'YTD CF'!L7 | Q7: ='CASH FLOW'!F5-'YTD CF'!M7 | R7: ='CF DRIVERS'!R7 | S7: ='CF DRIVERS'!S7 | T7: ='CF DRIVERS'!T7 | U7: ='CF DRIVERS'!U7 | V7: ='CF DRIVERS'!V7 | W7: ='CF DRIVERS'!W7 | X7: ='CF DRIVERS'!X7 | Y7: ='CF DRIVERS'!Y7 | ... AG7: ='CF DRIVERS'!AG7
A8: Amortization of Deferred Other Costs | B8: ='YTD CF'!B8 | C8: ='YTD CF'!C8-'YTD CF'!B8 | D8: ='YTD CF'!D8-'YTD CF'!C8 | E8: ='CASH FLOW'!C6-'YTD CF'!D8 | F8: ='YTD CF'!E8 | G8: ='YTD CF'!F8-'YTD CF'!E8 | H8: ='YTD CF'!G8-'YTD CF'!F8 | I8: ='CASH FLOW'!D6-'YTD CF'!G8 | J8: ='YTD CF'!H8 | K8: ='YTD CF'!I8-'YTD CF'!H8 | L8: ='YTD CF'!J8-'YTD CF'!I8 | M8: ='CASH FLOW'!E6-'YTD CF'!J8 | N8: ='YTD CF'!K8 | O8: ='YTD CF'!L8-'YTD CF'!K8 | P8: ='YTD CF'!M8-'YTD CF'!L8 | Q8: ='CASH FLOW'!F6-'YTD CF'!M8 | R8: ='CF DRIVERS'!R8 | S8: ='CF DRIVERS'!S8 | T8: ='CF DRIVERS'!T8 | U8: ='CF DRIVERS'!U8 | V8: ='CF DRIVERS'!V8 | W8: ='CF DRIVERS'!W8 | X8: ='CF DRIVERS'!X8 | Y8: ='CF DRIVERS'!Y8 | ... AG8: ='CF DRIVERS'!AG8
A9: Inventory Write-Down | B9: ='YTD CF'!B9 | C9: ='YTD CF'!C9-'YTD CF'!B9 | D9: ='YTD CF'!D9-'YTD CF'!C9 | E9: ='CASH FLOW'!C7-'YTD CF'!D9 | F9: ='YTD CF'!E9 | G9: ='YTD CF'!F9-'YTD CF'!E9 | H9: ='YTD CF'!G9-'YTD CF'!F9 | I9: ='CASH FLOW'!D7-'YTD CF'!G9 | J9: ='YTD CF'!H9 | K9: ='YTD CF'!I9-'YTD CF'!H9 | L9: ='YTD CF'!J9-'YTD CF'!I9 | M9: ='CASH FLOW'!E7-'YTD CF'!J9 | N9: ='YTD CF'!K9 | O9: ='YTD CF'!L9-'YTD CF'!K9 | P9: ='YTD CF'!M9-'YTD CF'!L9 | Q9: ='CASH FLOW'!F7-'YTD CF'!M9 | R9: ='CF DRIVERS'!R9 | S9: ='CF DRIVERS'!S9 | T9: ='CF DRIVERS'!T9 | U9: ='CF DRIVERS'!U9 | V9: ='CF DRIVERS'!V9 | W9: ='CF DRIVERS'!W9 | X9: ='CF DRIVERS'!X9 | Y9: ='CF DRIVERS'!Y9 | ... AG9: ='CF DRIVERS'!AG9
A10: Gain (Loss) on Disposal of PP&E | B10: ='YTD CF'!B10 | C10: ='YTD CF'!C10-'YTD CF'!B10 | D10: ='YTD CF'!D10-'YTD CF'!C10 | E10: ='CASH FLOW'!C8-'YTD CF'!D10 | F10: ='YTD CF'!E10 | G10: ='YTD CF'!F10-'YTD CF'!E10 | H10: ='YTD CF'!G10-'YTD CF'!F10 | I10: ='CASH FLOW'!D8-'YTD CF'!G10 | J10: ='YTD CF'!H10 | K10: ='YTD CF'!I10-'YTD CF'!H10 | L10: ='YTD CF'!J10-'YTD CF'!I10 | M10: ='CASH FLOW'!E8-'YTD CF'!J10 | N10: ='YTD CF'!K10 | O10: ='YTD CF'!L10-'YTD CF'!K10 | P10: ='YTD CF'!M10-'YTD CF'!L10 | Q10: ='CASH FLOW'!F8-'YTD CF'!M10 | R10: ='CF DRIVERS'!R10 | S10: ='CF DRIVERS'!S10 | T10: ='CF DRIVERS'!T10 | U10: ='CF DRIVERS'!U10 | V10: ='CF DRIVERS'!V10 | W10: ='CF DRIVERS'!W10 | X10: ='CF DRIVERS'!X10 | Y10: ='CF DRIVERS'!Y10 | ... AG10: ='CF DRIVERS'!AG10
A11: Stock-Based Compensation | B11: ='YTD CF'!B11 | C11: ='YTD CF'!C11-'YTD CF'!B11 | D11: ='YTD CF'!D11-'YTD CF'!C11 | E11: ='CASH FLOW'!C9-'YTD CF'!D11 | F11: ='YTD CF'!E11 | G11: ='YTD CF'!F11-'YTD CF'!E11 | H11: ='YTD CF'!G11-'YTD CF'!F11 | I11: ='CASH FLOW'!D9-'YTD CF'!G11 | J11: ='YTD CF'!H11 | K11: ='YTD CF'!I11-'YTD CF'!H11 | L11: ='YTD CF'!J11-'YTD CF'!I11 | M11: ='CASH FLOW'!E9-'YTD CF'!J11 | N11: ='YTD CF'!K11 | O11: ='YTD CF'!L11-'YTD CF'!K11 | P11: ='YTD CF'!M11-'YTD CF'!L11 | Q11: ='CASH FLOW'!F9-'YTD CF'!M11 | R11: ='QTR P&L'!R2*'CF DRIVERS'!R11 | S11: ='QTR P&L'!S2*'CF DRIVERS'!S11 | T11: ='QTR P&L'!T2*'CF DRIVERS'!T11 | U11: ='QTR P&L'!U2*'CF DRIVERS'!U11 | V11: ='QTR P&L'!V2*'CF DRIVERS'!V11 | W11: ='QTR P&L'!W2*'CF DRIVERS'!W11 | X11: ='QTR P&L'!X2*'CF DRIVERS'!X11 | Y11: ='QTR P&L'!Y2*'CF DRIVERS'!Y11 | ... AG11: ='QTR P&L'!AG2*'CF DRIVERS'!AG11
A12: (Benefit) Provision for Deferred Income Taxes | B12: ='YTD CF'!B12 | C12: ='YTD CF'!C12-'YTD CF'!B12 | D12: ='YTD CF'!D12-'YTD CF'!C12 | E12: ='CASH FLOW'!C10-'YTD CF'!D12 | F12: ='YTD CF'!E12 | G12: ='YTD CF'!F12-'YTD CF'!E12 | H12: ='YTD CF'!G12-'YTD CF'!F12 | I12: ='CASH FLOW'!D10-'YTD CF'!G12 | J12: ='YTD CF'!H12 | K12: ='YTD CF'!I12-'YTD CF'!H12 | L12: ='YTD CF'!J12-'YTD CF'!I12 | M12: ='CASH FLOW'!E10-'YTD CF'!J12 | N12: ='YTD CF'!K12 | O12: ='YTD CF'!L12-'YTD CF'!K12 | P12: ='YTD CF'!M12-'YTD CF'!L12 | Q12: ='CASH FLOW'!F10-'YTD CF'!M12 | R12: ='CF DRIVERS'!R12 | S12: ='CF DRIVERS'!S12 | T12: ='CF DRIVERS'!T12 | U12: ='CF DRIVERS'!U12 | V12: ='CF DRIVERS'!V12 | W12: ='CF DRIVERS'!W12 | X12: ='CF DRIVERS'!X12 | Y12: ='CF DRIVERS'!Y12 | ... AG12: ='CF DRIVERS'!AG12
A13: Foreign Currency Gain (Loss) | B13: ='YTD CF'!B13 | C13: ='YTD CF'!C13-'YTD CF'!B13 | D13: ='YTD CF'!D13-'YTD CF'!C13 | E13: ='CASH FLOW'!C11-'YTD CF'!D13 | F13: ='YTD CF'!E13 | G13: ='YTD CF'!F13-'YTD CF'!E13 | H13: ='YTD CF'!G13-'YTD CF'!F13 | I13: ='CASH FLOW'!D11-'YTD CF'!G13 | J13: ='YTD CF'!H13 | K13: ='YTD CF'!I13-'YTD CF'!H13 | L13: ='YTD CF'!J13-'YTD CF'!I13 | M13: ='CASH FLOW'!E11-'YTD CF'!J13 | N13: ='YTD CF'!K13 | O13: ='YTD CF'!L13-'YTD CF'!K13 | P13: ='YTD CF'!M13-'YTD CF'!L13 | Q13: ='CASH FLOW'!F11-'YTD CF'!M13 | R13: ='CF DRIVERS'!R13 | S13: ='CF DRIVERS'!S13 | T13: ='CF DRIVERS'!T13 | U13: ='CF DRIVERS'!U13 | V13: ='CF DRIVERS'!V13 | W13: ='CF DRIVERS'!W13 | X13: ='CF DRIVERS'!X13 | Y13: ='CF DRIVERS'!Y13 | ... AG13: ='CF DRIVERS'!AG13
A14: Gain (Loss) on Lease Cancellations | B14: ='YTD CF'!B14 | C14: ='YTD CF'!C14-'YTD CF'!B14 | D14: ='YTD CF'!D14-'YTD CF'!C14 | E14: ='CASH FLOW'!C12-'YTD CF'!D14 | F14: ='YTD CF'!E14 | G14: ='YTD CF'!F14-'YTD CF'!E14 | H14: ='YTD CF'!G14-'YTD CF'!F14 | I14: ='CASH FLOW'!D12-'YTD CF'!G14 | J14: ='YTD CF'!H14 | K14: ='YTD CF'!I14-'YTD CF'!H14 | L14: ='YTD CF'!J14-'YTD CF'!I14 | M14: ='CASH FLOW'!E12-'YTD CF'!J14 | N14: ='YTD CF'!K14 | O14: ='YTD CF'!L14-'YTD CF'!K14 | P14: ='YTD CF'!M14-'YTD CF'!L14 | Q14: ='CASH FLOW'!F12-'YTD CF'!M14 | R14: ='CF DRIVERS'!R14 | S14: ='CF DRIVERS'!S14 | T14: ='CF DRIVERS'!T14 | U14: ='CF DRIVERS'!U14 | V14: ='CF DRIVERS'!V14 | W14: ='CF DRIVERS'!W14 | X14: ='CF DRIVERS'!X14 | Y14: ='CF DRIVERS'!Y14 | ... AG14: ='CF DRIVERS'!AG14
A15: Change in Fair Value of Contingent Consideration | B15: ='YTD CF'!B15 | C15: ='YTD CF'!C15-'YTD CF'!B15 | D15: ='YTD CF'!D15-'YTD CF'!C15 | E15: ='CASH FLOW'!C13-'YTD CF'!D15 | F15: ='YTD CF'!E15 | G15: ='YTD CF'!F15-'YTD CF'!E15 | H15: ='YTD CF'!G15-'YTD CF'!F15 | I15: ='CASH FLOW'!D13-'YTD CF'!G15 | J15: ='YTD CF'!H15 | K15: ='YTD CF'!I15-'YTD CF'!H15 | L15: ='YTD CF'!J15-'YTD CF'!I15 | M15: ='CASH FLOW'!E13-'YTD CF'!J15 | N15: ='YTD CF'!K15 | O15: ='YTD CF'!L15-'YTD CF'!K15 | P15: ='YTD CF'!M15-'YTD CF'!L15 | Q15: ='CASH FLOW'!F13-'YTD CF'!M15 | R15: ='CF DRIVERS'!R15 | S15: ='CF DRIVERS'!S15 | T15: ='CF DRIVERS'!T15 | U15: ='CF DRIVERS'!U15 | V15: ='CF DRIVERS'!V15 | W15: ='CF DRIVERS'!W15 | X15: ='CF DRIVERS'!X15 | Y15: ='CF DRIVERS'!Y15 | ... AG15: ='CF DRIVERS'!AG15
A16: Gain (Loss) on Extinguishment of Debt | B16: ='YTD CF'!B16 | C16: ='YTD CF'!C16-'YTD CF'!B16 | D16: ='YTD CF'!D16-'YTD CF'!C16 | E16: ='CASH FLOW'!C14-'YTD CF'!D16 | F16: ='YTD CF'!E16 | G16: ='YTD CF'!F16-'YTD CF'!E16 | H16: ='YTD CF'!G16-'YTD CF'!F16 | I16: ='CASH FLOW'!D14-'YTD CF'!G16 | J16: ='YTD CF'!H16 | K16: ='YTD CF'!I16-'YTD CF'!H16 | L16: ='YTD CF'!J16-'YTD CF'!I16 | M16: ='CASH FLOW'!E14-'YTD CF'!J16 | N16: ='YTD CF'!K16 | O16: ='YTD CF'!L16-'YTD CF'!K16 | P16: ='YTD CF'!M16-'YTD CF'!L16 | Q16: ='CASH FLOW'!F14-'YTD CF'!M16 | R16: ='CF DRIVERS'!R16 | S16: ='CF DRIVERS'!S16 | T16: ='CF DRIVERS'!T16 | U16: ='CF DRIVERS'!U16 | V16: ='CF DRIVERS'!V16 | W16: ='CF DRIVERS'!W16 | X16: ='CF DRIVERS'!X16 | Y16: ='CF DRIVERS'!Y16 | ... AG16: ='CF DRIVERS'!AG16
A17: Other Operating Items | B17: ='YTD CF'!B17 | C17: ='YTD CF'!C17-'YTD CF'!B17 | D17: ='YTD CF'!D17-'YTD CF'!C17 | E17: ='CASH FLOW'!C15-'YTD CF'!D17 | F17: ='YTD CF'!E17 | G17: ='YTD CF'!F17-'YTD CF'!E17 | H17: ='YTD CF'!G17-'YTD CF'!F17 | I17: ='CASH FLOW'!D15-'YTD CF'!G17 | J17: ='YTD CF'!H17 | K17: ='YTD CF'!I17-'YTD CF'!H17 | L17: ='YTD CF'!J17-'YTD CF'!I17 | M17: ='CASH FLOW'!E15-'YTD CF'!J17 | N17: ='YTD CF'!K17 | O17: ='YTD CF'!L17-'YTD CF'!K17 | P17: ='YTD CF'!M17-'YTD CF'!L17 | Q17: ='CASH FLOW'!F15-'YTD CF'!M17 | R17: ='CF DRIVERS'!R17 | S17: ='CF DRIVERS'!S17 | T17: ='CF DRIVERS'!T17 | U17: ='CF DRIVERS'!U17 | V17: ='CF DRIVERS'!V17 | W17: ='CF DRIVERS'!W17 | X17: ='CF DRIVERS'!X17 | Y17: ='CF DRIVERS'!Y17 | ... AG17: ='CF DRIVERS'!AG17
A18: Accounts Receivable | B18: ='YTD CF'!B18 | C18: ='YTD CF'!C18-'YTD CF'!B18 | D18: ='YTD CF'!D18-'YTD CF'!C18 | E18: ='CASH FLOW'!C16-'YTD CF'!D18 | F18: ='YTD CF'!E18 | G18: ='YTD CF'!F18-'YTD CF'!E18 | H18: ='YTD CF'!G18-'YTD CF'!F18 | I18: ='CASH FLOW'!D16-'YTD CF'!G18 | J18: ='YTD CF'!H18 | K18: ='YTD CF'!I18-'YTD CF'!H18 | L18: ='YTD CF'!J18-'YTD CF'!I18 | M18: ='CASH FLOW'!E16-'YTD CF'!J18 | N18: ='YTD CF'!K18 | O18: ='YTD CF'!L18-'YTD CF'!K18 | P18: ='YTD CF'!M18-'YTD CF'!L18 | Q18: ='CASH FLOW'!F16-'YTD CF'!M18 | R18: ='CF DRIVERS'!R18 | S18: ='CF DRIVERS'!S18 | T18: ='CF DRIVERS'!T18 | U18: ='CF DRIVERS'!U18 | V18: ='CF DRIVERS'!V18 | W18: ='CF DRIVERS'!W18 | X18: ='CF DRIVERS'!X18 | Y18: ='CF DRIVERS'!Y18 | ... AG18: ='CF DRIVERS'!AG18
A19: Note Receivable | B19: ='YTD CF'!B19 | C19: ='YTD CF'!C19-'YTD CF'!B19 | D19: ='YTD CF'!D19-'YTD CF'!C19 | E19: ='CASH FLOW'!C17-'YTD CF'!D19 | F19: ='YTD CF'!E19 | G19: ='YTD CF'!F19-'YTD CF'!E19 | H19: ='YTD CF'!G19-'YTD CF'!F19 | I19: ='CASH FLOW'!D17-'YTD CF'!G19 | J19: ='YTD CF'!H19 | K19: ='YTD CF'!I19-'YTD CF'!H19 | L19: ='YTD CF'!J19-'YTD CF'!I19 | M19: ='CASH FLOW'!E17-'YTD CF'!J19 | N19: ='YTD CF'!K19 | O19: ='YTD CF'!L19-'YTD CF'!K19 | P19: ='YTD CF'!M19-'YTD CF'!L19 | Q19: ='CASH FLOW'!F17-'YTD CF'!M19 | R19: ='CF DRIVERS'!R19 | S19: ='CF DRIVERS'!S19 | T19: ='CF DRIVERS'!T19 | U19: ='CF DRIVERS'!U19 | V19: ='CF DRIVERS'!V19 | W19: ='CF DRIVERS'!W19 | X19: ='CF DRIVERS'!X19 | Y19: ='CF DRIVERS'!Y19 | ... AG19: ='CF DRIVERS'!AG19
A20: Inventories | B20: ='YTD CF'!B20 | C20: ='YTD CF'!C20-'YTD CF'!B20 | D20: ='YTD CF'!D20-'YTD CF'!C20 | E20: ='CASH FLOW'!C18-'YTD CF'!D20 | F20: ='YTD CF'!E20 | G20: ='YTD CF'!F20-'YTD CF'!E20 | H20: ='YTD CF'!G20-'YTD CF'!F20 | I20: ='CASH FLOW'!D18-'YTD CF'!G20 | J20: ='YTD CF'!H20 | K20: ='YTD CF'!I20-'YTD CF'!H20 | L20: ='YTD CF'!J20-'YTD CF'!I20 | M20: ='CASH FLOW'!E18-'YTD CF'!J20 | N20: ='YTD CF'!K20 | O20: ='YTD CF'!L20-'YTD CF'!K20 | P20: ='YTD CF'!M20-'YTD CF'!L20 | Q20: ='CASH FLOW'!F18-'YTD CF'!M20 | R20: ='CF DRIVERS'!R20 | S20: ='CF DRIVERS'!S20 | T20: ='CF DRIVERS'!T20 | U20: ='CF DRIVERS'!U20 | V20: ='CF DRIVERS'!V20 | W20: ='CF DRIVERS'!W20 | X20: ='CF DRIVERS'!X20 | Y20: ='CF DRIVERS'!Y20 | ... AG20: ='CF DRIVERS'!AG20
A21: Prepaid Expenses | B21: ='YTD CF'!B21 | C21: ='YTD CF'!C21-'YTD CF'!B21 | D21: ='YTD CF'!D21-'YTD CF'!C21 | E21: ='CASH FLOW'!C19-'YTD CF'!D21 | F21: ='YTD CF'!E21 | G21: ='YTD CF'!F21-'YTD CF'!E21 | H21: ='YTD CF'!G21-'YTD CF'!F21 | I21: ='CASH FLOW'!D19-'YTD CF'!G21 | J21: ='YTD CF'!H21 | K21: ='YTD CF'!I21-'YTD CF'!H21 | L21: ='YTD CF'!J21-'YTD CF'!I21 | M21: ='CASH FLOW'!E19-'YTD CF'!J21 | N21: ='YTD CF'!K21 | O21: ='YTD CF'!L21-'YTD CF'!K21 | P21: ='YTD CF'!M21-'YTD CF'!L21 | Q21: ='CASH FLOW'!F19-'YTD CF'!M21 | R21: ='CF DRIVERS'!R21 | S21: ='CF DRIVERS'!S21 | T21: ='CF DRIVERS'!T21 | U21: ='CF DRIVERS'!U21 | V21: ='CF DRIVERS'!V21 | W21: ='CF DRIVERS'!W21 | X21: ='CF DRIVERS'!X21 | Y21: ='CF DRIVERS'!Y21 | ... AG21: ='CF DRIVERS'!AG21
A22: Change in A/P and Accrued (legacy) | B22: ='YTD CF'!B22 | C22: ='YTD CF'!C22-'YTD CF'!B22 | D22: ='YTD CF'!D22-'YTD CF'!C22 | F22: ='YTD CF'!E22 | G22: ='YTD CF'!F22-'YTD CF'!E22 | H22: ='YTD CF'!G22-'YTD CF'!F22 | J22: ='YTD CF'!H22 | K22: ='YTD CF'!I22-'YTD CF'!H22 | L22: ='YTD CF'!J22-'YTD CF'!I22 | N22: ='YTD CF'!K22 | O22: ='YTD CF'!L22-'YTD CF'!K22 | P22: ='YTD CF'!M22-'YTD CF'!L22 | R22: ='CF DRIVERS'!R22 | S22: ='CF DRIVERS'!S22 | T22: ='CF DRIVERS'!T22 | U22: ='CF DRIVERS'!U22 | V22: ='CF DRIVERS'!V22 | W22: ='CF DRIVERS'!W22 | X22: ='CF DRIVERS'!X22 | Y22: ='CF DRIVERS'!Y22 | ... AG22: ='CF DRIVERS'!AG22
A23: Other Non-Current Assets | B23: ='YTD CF'!B23 | C23: ='YTD CF'!C23-'YTD CF'!B23 | D23: ='YTD CF'!D23-'YTD CF'!C23 | E23: ='CASH FLOW'!C20-'YTD CF'!D23 | F23: ='YTD CF'!E23 | G23: ='YTD CF'!F23-'YTD CF'!E23 | H23: ='YTD CF'!G23-'YTD CF'!F23 | I23: ='CASH FLOW'!D20-'YTD CF'!G23 | J23: ='YTD CF'!H23 | K23: ='YTD CF'!I23-'YTD CF'!H23 | L23: ='YTD CF'!J23-'YTD CF'!I23 | M23: ='CASH FLOW'!E20-'YTD CF'!J23 | N23: ='YTD CF'!K23 | O23: ='YTD CF'!L23-'YTD CF'!K23 | P23: ='YTD CF'!M23-'YTD CF'!L23 | Q23: ='CASH FLOW'!F20-'YTD CF'!M23 | R23: ='CF DRIVERS'!R23 | S23: ='CF DRIVERS'!S23 | T23: ='CF DRIVERS'!T23 | U23: ='CF DRIVERS'!U23 | V23: ='CF DRIVERS'!V23 | W23: ='CF DRIVERS'!W23 | X23: ='CF DRIVERS'!X23 | Y23: ='CF DRIVERS'!Y23 | ... AG23: ='CF DRIVERS'!AG23
A24: Accounts Payable | B24: ='YTD CF'!B24 | C24: ='YTD CF'!C24-'YTD CF'!B24 | D24: ='YTD CF'!D24-'YTD CF'!C24 | E24: ='CASH FLOW'!C21-'YTD CF'!D24 | F24: ='YTD CF'!E24 | G24: ='YTD CF'!F24-'YTD CF'!E24 | H24: ='YTD CF'!G24-'YTD CF'!F24 | I24: ='CASH FLOW'!D21-'YTD CF'!G24 | J24: ='YTD CF'!H24 | K24: ='YTD CF'!I24-'YTD CF'!H24 | L24: ='YTD CF'!J24-'YTD CF'!I24 | M24: ='CASH FLOW'!E21-'YTD CF'!J24 | N24: ='YTD CF'!K24 | O24: ='YTD CF'!L24-'YTD CF'!K24 | P24: ='YTD CF'!M24-'YTD CF'!L24 | Q24: ='CASH FLOW'!F21-'YTD CF'!M24 | R24: ='CF DRIVERS'!R24 | S24: ='CF DRIVERS'!S24 | T24: ='CF DRIVERS'!T24 | U24: ='CF DRIVERS'!U24 | V24: ='CF DRIVERS'!V24 | W24: ='CF DRIVERS'!W24 | X24: ='CF DRIVERS'!X24 | Y24: ='CF DRIVERS'!Y24 | ... AG24: ='CF DRIVERS'!AG24
A25: Accrued Expenses | B25: ='YTD CF'!B25 | C25: ='YTD CF'!C25-'YTD CF'!B25 | D25: ='YTD CF'!D25-'YTD CF'!C25 | E25: ='CASH FLOW'!C22-'YTD CF'!D25 | F25: ='YTD CF'!E25 | G25: ='YTD CF'!F25-'YTD CF'!E25 | H25: ='YTD CF'!G25-'YTD CF'!F25 | I25: ='CASH FLOW'!D22-'YTD CF'!G25 | J25: ='YTD CF'!H25 | K25: ='YTD CF'!I25-'YTD CF'!H25 | L25: ='YTD CF'!J25-'YTD CF'!I25 | M25: ='CASH FLOW'!E22-'YTD CF'!J25 | N25: ='YTD CF'!K25 | O25: ='YTD CF'!L25-'YTD CF'!K25 | P25: ='YTD CF'!M25-'YTD CF'!L25 | Q25: ='CASH FLOW'!F22-'YTD CF'!M25 | R25: ='CF DRIVERS'!R25 | S25: ='CF DRIVERS'!S25 | T25: ='CF DRIVERS'!T25 | U25: ='CF DRIVERS'!U25 | V25: ='CF DRIVERS'!V25 | W25: ='CF DRIVERS'!W25 | X25: ='CF DRIVERS'!X25 | Y25: ='CF DRIVERS'!Y25 | ... AG25: ='CF DRIVERS'!AG25
A26: Other Current Liabilities | B26: ='YTD CF'!B26 | C26: ='YTD CF'!C26-'YTD CF'!B26 | D26: ='YTD CF'!D26-'YTD CF'!C26 | E26: ='CASH FLOW'!C23-'YTD CF'!D26 | F26: ='YTD CF'!E26 | G26: ='YTD CF'!F26-'YTD CF'!E26 | H26: ='YTD CF'!G26-'YTD CF'!F26 | I26: ='CASH FLOW'!D23-'YTD CF'!G26 | J26: ='YTD CF'!H26 | K26: ='YTD CF'!I26-'YTD CF'!H26 | L26: ='YTD CF'!J26-'YTD CF'!I26 | M26: ='CASH FLOW'!E23-'YTD CF'!J26 | N26: ='YTD CF'!K26 | O26: ='YTD CF'!L26-'YTD CF'!K26 | P26: ='YTD CF'!M26-'YTD CF'!L26 | Q26: ='CASH FLOW'!F23-'YTD CF'!M26 | R26: ='CF DRIVERS'!R26 | S26: ='CF DRIVERS'!S26 | T26: ='CF DRIVERS'!T26 | U26: ='CF DRIVERS'!U26 | V26: ='CF DRIVERS'!V26 | W26: ='CF DRIVERS'!W26 | X26: ='CF DRIVERS'!X26 | Y26: ='CF DRIVERS'!Y26 | ... AG26: ='CF DRIVERS'!AG26
A27: Accrued Promotional Allowance | B27: ='YTD CF'!B27 | C27: ='YTD CF'!C27-'YTD CF'!B27 | D27: ='YTD CF'!D27-'YTD CF'!C27 | E27: ='CASH FLOW'!C24-'YTD CF'!D27 | F27: ='YTD CF'!E27 | G27: ='YTD CF'!F27-'YTD CF'!E27 | H27: ='YTD CF'!G27-'YTD CF'!F27 | I27: ='CASH FLOW'!D24-'YTD CF'!G27 | J27: ='YTD CF'!H27 | K27: ='YTD CF'!I27-'YTD CF'!H27 | L27: ='YTD CF'!J27-'YTD CF'!I27 | M27: ='CASH FLOW'!E24-'YTD CF'!J27 | N27: ='YTD CF'!K27 | O27: ='YTD CF'!L27-'YTD CF'!K27 | P27: ='YTD CF'!M27-'YTD CF'!L27 | Q27: ='CASH FLOW'!F24-'YTD CF'!M27 | R27: ='CF DRIVERS'!R27 | S27: ='CF DRIVERS'!S27 | T27: ='CF DRIVERS'!T27 | U27: ='CF DRIVERS'!U27 | V27: ='CF DRIVERS'!V27 | W27: ='CF DRIVERS'!W27 | X27: ='CF DRIVERS'!X27 | Y27: ='CF DRIVERS'!Y27 | ... AG27: ='CF DRIVERS'!AG27
A28: Accrued Distributor Termination | B28: ='YTD CF'!B28 | C28: ='YTD CF'!C28-'YTD CF'!B28 | D28: ='YTD CF'!D28-'YTD CF'!C28 | E28: ='CASH FLOW'!C25-'YTD CF'!D28 | F28: ='YTD CF'!E28 | G28: ='YTD CF'!F28-'YTD CF'!E28 | H28: ='YTD CF'!G28-'YTD CF'!F28 | I28: ='CASH FLOW'!D25-'YTD CF'!G28 | J28: ='YTD CF'!H28 | K28: ='YTD CF'!I28-'YTD CF'!H28 | L28: ='YTD CF'!J28-'YTD CF'!I28 | M28: ='CASH FLOW'!E25-'YTD CF'!J28 | N28: ='YTD CF'!K28 | O28: ='YTD CF'!L28-'YTD CF'!K28 | P28: ='YTD CF'!M28-'YTD CF'!L28 | Q28: ='CASH FLOW'!F25-'YTD CF'!M28 | R28: ='CF DRIVERS'!R28 | S28: ='CF DRIVERS'!S28 | T28: ='CF DRIVERS'!T28 | U28: ='CF DRIVERS'!U28 | V28: ='CF DRIVERS'!V28 | W28: ='CF DRIVERS'!W28 | X28: ='CF DRIVERS'!X28 | Y28: ='CF DRIVERS'!Y28 | ... AG28: ='CF DRIVERS'!AG28
A29: ROU & Lease Liability, Net | B29: ='YTD CF'!B29 | C29: ='YTD CF'!C29-'YTD CF'!B29 | D29: ='YTD CF'!D29-'YTD CF'!C29 | E29: ='CASH FLOW'!C26-'YTD CF'!D29 | F29: ='YTD CF'!E29 | G29: ='YTD CF'!F29-'YTD CF'!E29 | H29: ='YTD CF'!G29-'YTD CF'!F29 | I29: ='CASH FLOW'!D26-'YTD CF'!G29 | J29: ='YTD CF'!H29 | K29: ='YTD CF'!I29-'YTD CF'!H29 | L29: ='YTD CF'!J29-'YTD CF'!I29 | M29: ='CASH FLOW'!E26-'YTD CF'!J29 | N29: ='YTD CF'!K29 | O29: ='YTD CF'!L29-'YTD CF'!K29 | P29: ='YTD CF'!M29-'YTD CF'!L29 | Q29: ='CASH FLOW'!F26-'YTD CF'!M29 | R29: ='CF DRIVERS'!R29 | S29: ='CF DRIVERS'!S29 | T29: ='CF DRIVERS'!T29 | U29: ='CF DRIVERS'!U29 | V29: ='CF DRIVERS'!V29 | W29: ='CF DRIVERS'!W29 | X29: ='CF DRIVERS'!X29 | Y29: ='CF DRIVERS'!Y29 | ... AG29: ='CF DRIVERS'!AG29
A30: Deferred Revenue | B30: ='YTD CF'!B30 | C30: ='YTD CF'!C30-'YTD CF'!B30 | D30: ='YTD CF'!D30-'YTD CF'!C30 | E30: ='CASH FLOW'!C27-'YTD CF'!D30 | F30: ='YTD CF'!E30 | G30: ='YTD CF'!F30-'YTD CF'!E30 | H30: ='YTD CF'!G30-'YTD CF'!F30 | I30: ='CASH FLOW'!D27-'YTD CF'!G30 | J30: ='YTD CF'!H30 | K30: ='YTD CF'!I30-'YTD CF'!H30 | L30: ='YTD CF'!J30-'YTD CF'!I30 | M30: ='CASH FLOW'!E27-'YTD CF'!J30 | N30: ='YTD CF'!K30 | O30: ='YTD CF'!L30-'YTD CF'!K30 | P30: ='YTD CF'!M30-'YTD CF'!L30 | Q30: ='CASH FLOW'!F27-'YTD CF'!M30 | R30: ='CF DRIVERS'!R30 | S30: ='CF DRIVERS'!S30 | T30: ='CF DRIVERS'!T30 | U30: ='CF DRIVERS'!U30 | V30: ='CF DRIVERS'!V30 | W30: ='CF DRIVERS'!W30 | X30: ='CF DRIVERS'!X30 | Y30: ='CF DRIVERS'!Y30 | ... AG30: ='CF DRIVERS'!AG30
A31: Net Change in Other Working Capital | B31: ='YTD CF'!B31 | C31: ='YTD CF'!C31-'YTD CF'!B31 | D31: ='YTD CF'!D31-'YTD CF'!C31 | E31: ='CASH FLOW'!C28-'YTD CF'!D31 | F31: ='YTD CF'!E31 | G31: ='YTD CF'!F31-'YTD CF'!E31 | H31: ='YTD CF'!G31-'YTD CF'!F31 | I31: ='CASH FLOW'!D28-'YTD CF'!G31 | J31: ='YTD CF'!H31 | K31: ='YTD CF'!I31-'YTD CF'!H31 | L31: ='YTD CF'!J31-'YTD CF'!I31 | M31: ='CASH FLOW'!E28-'YTD CF'!J31 | N31: ='YTD CF'!K31 | O31: ='YTD CF'!L31-'YTD CF'!K31 | P31: ='YTD CF'!M31-'YTD CF'!L31 | Q31: ='CASH FLOW'!F28-'YTD CF'!M31 | R31: ='CF DRIVERS'!R31 | S31: ='CF DRIVERS'!S31 | T31: ='CF DRIVERS'!T31 | U31: ='CF DRIVERS'!U31 | V31: ='CF DRIVERS'!V31 | W31: ='CF DRIVERS'!W31 | X31: ='CF DRIVERS'!X31 | Y31: ='CF DRIVERS'!Y31 | ... AG31: ='CF DRIVERS'!AG31
A32: Cash Flow from Operations | B32: ='YTD CF'!B32 | C32: ='YTD CF'!C32-'YTD CF'!B32 | D32: ='YTD CF'!D32-'YTD CF'!C32 | E32: ='CASH FLOW'!C29-'YTD CF'!D32 | F32: ='YTD CF'!E32 | G32: ='YTD CF'!F32-'YTD CF'!E32 | H32: ='YTD CF'!G32-'YTD CF'!F32 | I32: ='CASH FLOW'!D29-'YTD CF'!G32 | J32: ='YTD CF'!H32 | K32: ='YTD CF'!I32-'YTD CF'!H32 | L32: ='YTD CF'!J32-'YTD CF'!I32 | M32: ='CASH FLOW'!E29-'YTD CF'!J32 | N32: ='YTD CF'!K32 | O32: ='YTD CF'!L32-'YTD CF'!K32 | P32: ='YTD CF'!M32-'YTD CF'!L32 | Q32: ='CASH FLOW'!F29-'YTD CF'!M32 | R32: =SUM(R2:R31) | S32: =SUM(S2:S31) | T32: =SUM(T2:T31) | U32: =SUM(U2:U31) | V32: =SUM(V2:V31) | W32: =SUM(W2:W31) | X32: =SUM(X2:X31) | Y32: =SUM(Y2:Y31) | ... AG32: =SUM(AG2:AG31)
A33: Collections from Note Receivable | B33: ='YTD CF'!B33 | C33: ='YTD CF'!C33-'YTD CF'!B33 | D33: ='YTD CF'!D33-'YTD CF'!C33 | E33: ='CASH FLOW'!C30-'YTD CF'!D33 | F33: ='YTD CF'!E33 | G33: ='YTD CF'!F33-'YTD CF'!E33 | H33: ='YTD CF'!G33-'YTD CF'!F33 | I33: ='CASH FLOW'!D30-'YTD CF'!G33 | J33: ='YTD CF'!H33 | K33: ='YTD CF'!I33-'YTD CF'!H33 | L33: ='YTD CF'!J33-'YTD CF'!I33 | M33: ='CASH FLOW'!E30-'YTD CF'!J33 | N33: ='YTD CF'!K33 | O33: ='YTD CF'!L33-'YTD CF'!K33 | P33: ='YTD CF'!M33-'YTD CF'!L33 | Q33: ='CASH FLOW'!F30-'YTD CF'!M33 | R33: ='CF DRIVERS'!R32 | S33: ='CF DRIVERS'!S32 | T33: ='CF DRIVERS'!T32 | U33: ='CF DRIVERS'!U32 | V33: ='CF DRIVERS'!V32 | W33: ='CF DRIVERS'!W32 | X33: ='CF DRIVERS'!X32 | Y33: ='CF DRIVERS'!Y32 | ... AG33: ='CF DRIVERS'!AG32
A34: Purchase of PP&E | B34: ='YTD CF'!B34 | C34: ='YTD CF'!C34-'YTD CF'!B34 | D34: ='YTD CF'!D34-'YTD CF'!C34 | E34: ='CASH FLOW'!C31-'YTD CF'!D34 | F34: ='YTD CF'!E34 | G34: ='YTD CF'!F34-'YTD CF'!E34 | H34: ='YTD CF'!G34-'YTD CF'!F34 | I34: ='CASH FLOW'!D31-'YTD CF'!G34 | J34: ='YTD CF'!H34 | K34: ='YTD CF'!I34-'YTD CF'!H34 | L34: ='YTD CF'!J34-'YTD CF'!I34 | M34: ='CASH FLOW'!E31-'YTD CF'!J34 | N34: ='YTD CF'!K34 | O34: ='YTD CF'!L34-'YTD CF'!K34 | P34: ='YTD CF'!M34-'YTD CF'!L34 | Q34: ='CASH FLOW'!F31-'YTD CF'!M34 | R34: ='QTR P&L'!R2*'CF DRIVERS'!R33 | S34: ='QTR P&L'!S2*'CF DRIVERS'!S33 | T34: ='QTR P&L'!T2*'CF DRIVERS'!T33 | U34: ='QTR P&L'!U2*'CF DRIVERS'!U33 | V34: ='QTR P&L'!V2*'CF DRIVERS'!V33 | W34: ='QTR P&L'!W2*'CF DRIVERS'!W33 | X34: ='QTR P&L'!X2*'CF DRIVERS'!X33 | Y34: ='QTR P&L'!Y2*'CF DRIVERS'!Y33 | ... AG34: ='QTR P&L'!AG2*'CF DRIVERS'!AG33
A35: Purchase of Non-Marketable Equity Securities | B35: ='YTD CF'!B35 | C35: ='YTD CF'!C35-'YTD CF'!B35 | D35: ='YTD CF'!D35-'YTD CF'!C35 | E35: ='CASH FLOW'!C32-'YTD CF'!D35 | F35: ='YTD CF'!E35 | G35: ='YTD CF'!F35-'YTD CF'!E35 | H35: ='YTD CF'!G35-'YTD CF'!F35 | I35: ='CASH FLOW'!D32-'YTD CF'!G35 | J35: ='YTD CF'!H35 | K35: ='YTD CF'!I35-'YTD CF'!H35 | L35: ='YTD CF'!J35-'YTD CF'!I35 | M35: ='CASH FLOW'!E32-'YTD CF'!J35 | N35: ='YTD CF'!K35 | O35: ='YTD CF'!L35-'YTD CF'!K35 | P35: ='YTD CF'!M35-'YTD CF'!L35 | Q35: ='CASH FLOW'!F32-'YTD CF'!M35 | R35: ='CF DRIVERS'!R34 | S35: ='CF DRIVERS'!S34 | T35: ='CF DRIVERS'!T34 | U35: ='CF DRIVERS'!U34 | V35: ='CF DRIVERS'!V34 | W35: ='CF DRIVERS'!W34 | X35: ='CF DRIVERS'!X34 | Y35: ='CF DRIVERS'!Y34 | ... AG35: ='CF DRIVERS'!AG34
A36: Acquisition of Big Beverages | B36: ='YTD CF'!B36 | C36: ='YTD CF'!C36-'YTD CF'!B36 | D36: ='YTD CF'!D36-'YTD CF'!C36 | E36: ='CASH FLOW'!C33-'YTD CF'!D36 | F36: ='YTD CF'!E36 | G36: ='YTD CF'!F36-'YTD CF'!E36 | H36: ='YTD CF'!G36-'YTD CF'!F36 | I36: ='CASH FLOW'!D33-'YTD CF'!G36 | J36: ='YTD CF'!H36 | K36: ='YTD CF'!I36-'YTD CF'!H36 | L36: ='YTD CF'!J36-'YTD CF'!I36 | M36: ='CASH FLOW'!E33-'YTD CF'!J36 | N36: ='YTD CF'!K36 | O36: ='YTD CF'!L36-'YTD CF'!K36 | P36: ='YTD CF'!M36-'YTD CF'!L36 | Q36: ='CASH FLOW'!F33-'YTD CF'!M36 | R36: ='CF DRIVERS'!R35 | S36: ='CF DRIVERS'!S35 | T36: ='CF DRIVERS'!T35 | U36: ='CF DRIVERS'!U35 | V36: ='CF DRIVERS'!V35 | W36: ='CF DRIVERS'!W35 | X36: ='CF DRIVERS'!X35 | Y36: ='CF DRIVERS'!Y35 | ... AG36: ='CF DRIVERS'!AG35
A37: Acquisitions, Net of Cash Acquired | B37: ='YTD CF'!B37 | C37: ='YTD CF'!C37-'YTD CF'!B37 | D37: ='YTD CF'!D37-'YTD CF'!C37 | E37: ='CASH FLOW'!C34-'YTD CF'!D37 | F37: ='YTD CF'!E37 | G37: ='YTD CF'!F37-'YTD CF'!E37 | H37: ='YTD CF'!G37-'YTD CF'!F37 | I37: ='CASH FLOW'!D34-'YTD CF'!G37 | J37: ='YTD CF'!H37 | K37: ='YTD CF'!I37-'YTD CF'!H37 | L37: ='YTD CF'!J37-'YTD CF'!I37 | M37: ='CASH FLOW'!E34-'YTD CF'!J37 | N37: ='YTD CF'!K37 | O37: ='YTD CF'!L37-'YTD CF'!K37 | P37: ='YTD CF'!M37-'YTD CF'!L37 | Q37: ='CASH FLOW'!F34-'YTD CF'!M37 | R37: ='CF DRIVERS'!R36 | S37: ='CF DRIVERS'!S36 | T37: ='CF DRIVERS'!T36 | U37: ='CF DRIVERS'!U36 | V37: ='CF DRIVERS'!V36 | W37: ='CF DRIVERS'!W36 | X37: ='CF DRIVERS'!X36 | Y37: ='CF DRIVERS'!Y36 | ... AG37: ='CF DRIVERS'!AG36
A38: Working Capital Estimate from Pepsi (Rockstar) | R38: ='CF DRIVERS'!R37 | S38: ='CF DRIVERS'!S37 | T38: ='CF DRIVERS'!T37 | U38: ='CF DRIVERS'!U37 | V38: ='CF DRIVERS'!V37 | W38: ='CF DRIVERS'!W37 | X38: ='CF DRIVERS'!X37 | Y38: ='CF DRIVERS'!Y37 | ... AG38: ='CF DRIVERS'!AG37
A39: Cash Flow from Investing | B39: ='YTD CF'!B39 | C39: ='YTD CF'!C39-'YTD CF'!B39 | D39: ='YTD CF'!D39-'YTD CF'!C39 | E39: ='CASH FLOW'!C36-'YTD CF'!D39 | F39: ='YTD CF'!E39 | G39: ='YTD CF'!F39-'YTD CF'!E39 | H39: ='YTD CF'!G39-'YTD CF'!F39 | I39: ='CASH FLOW'!D36-'YTD CF'!G39 | J39: ='YTD CF'!H39 | K39: ='YTD CF'!I39-'YTD CF'!H39 | L39: ='YTD CF'!J39-'YTD CF'!I39 | M39: ='CASH FLOW'!E36-'YTD CF'!J39 | N39: ='YTD CF'!K39 | O39: ='YTD CF'!L39-'YTD CF'!K39 | P39: ='YTD CF'!M39-'YTD CF'!L39 | Q39: ='CASH FLOW'!F36-'YTD CF'!M39 | R39: =SUM(R33:R38) | S39: =SUM(S33:S38) | T39: =SUM(T33:T38) | U39: =SUM(U33:U38) | V39: =SUM(V33:V38) | W39: =SUM(W33:W38) | X39: =SUM(X33:X38) | Y39: =SUM(Y33:Y38) | ... AG39: =SUM(AG33:AG38)
A40: Finance Lease Payments | B40: ='YTD CF'!B40 | C40: ='YTD CF'!C40-'YTD CF'!B40 | D40: ='YTD CF'!D40-'YTD CF'!C40 | E40: ='CASH FLOW'!C37-'YTD CF'!D40 | F40: ='YTD CF'!E40 | G40: ='YTD CF'!F40-'YTD CF'!E40 | H40: ='YTD CF'!G40-'YTD CF'!F40 | I40: ='CASH FLOW'!D37-'YTD CF'!G40 | J40: ='YTD CF'!H40 | K40: ='YTD CF'!I40-'YTD CF'!H40 | L40: ='YTD CF'!J40-'YTD CF'!I40 | M40: ='CASH FLOW'!E37-'YTD CF'!J40 | N40: ='YTD CF'!K40 | O40: ='YTD CF'!L40-'YTD CF'!K40 | P40: ='YTD CF'!M40-'YTD CF'!L40 | Q40: ='CASH FLOW'!F37-'YTD CF'!M40 | R40: ='CF DRIVERS'!R38 | S40: ='CF DRIVERS'!S38 | T40: ='CF DRIVERS'!T38 | U40: ='CF DRIVERS'!U38 | V40: ='CF DRIVERS'!V38 | W40: ='CF DRIVERS'!W38 | X40: ='CF DRIVERS'!X38 | Y40: ='CF DRIVERS'!Y38 | ... AG40: ='CF DRIVERS'!AG38
A41: Proceeds from Exercise of Stock Options | B41: ='YTD CF'!B41 | C41: ='YTD CF'!C41-'YTD CF'!B41 | D41: ='YTD CF'!D41-'YTD CF'!C41 | E41: ='CASH FLOW'!C38-'YTD CF'!D41 | F41: ='YTD CF'!E41 | G41: ='YTD CF'!F41-'YTD CF'!E41 | H41: ='YTD CF'!G41-'YTD CF'!F41 | I41: ='CASH FLOW'!D38-'YTD CF'!G41 | J41: ='YTD CF'!H41 | K41: ='YTD CF'!I41-'YTD CF'!H41 | L41: ='YTD CF'!J41-'YTD CF'!I41 | M41: ='CASH FLOW'!E38-'YTD CF'!J41 | N41: ='YTD CF'!K41 | O41: ='YTD CF'!L41-'YTD CF'!K41 | P41: ='YTD CF'!M41-'YTD CF'!L41 | Q41: ='CASH FLOW'!F38-'YTD CF'!M41 | R41: ='CF DRIVERS'!R39 | S41: ='CF DRIVERS'!S39 | T41: ='CF DRIVERS'!T39 | U41: ='CF DRIVERS'!U39 | V41: ='CF DRIVERS'!V39 | W41: ='CF DRIVERS'!W39 | X41: ='CF DRIVERS'!X39 | Y41: ='CF DRIVERS'!Y39 | ... AG41: ='CF DRIVERS'!AG39
A42: Proceeds from Issuance of Common Stock | B42: ='YTD CF'!B42 | C42: ='YTD CF'!C42-'YTD CF'!B42 | D42: ='YTD CF'!D42-'YTD CF'!C42 | E42: ='CASH FLOW'!C39-'YTD CF'!D42 | F42: ='YTD CF'!E42 | G42: ='YTD CF'!F42-'YTD CF'!E42 | H42: ='YTD CF'!G42-'YTD CF'!F42 | I42: ='CASH FLOW'!D39-'YTD CF'!G42 | J42: ='YTD CF'!H42 | K42: ='YTD CF'!I42-'YTD CF'!H42 | L42: ='YTD CF'!J42-'YTD CF'!I42 | M42: ='CASH FLOW'!E39-'YTD CF'!J42 | N42: ='YTD CF'!K42 | O42: ='YTD CF'!L42-'YTD CF'!K42 | P42: ='YTD CF'!M42-'YTD CF'!L42 | Q42: ='CASH FLOW'!F39-'YTD CF'!M42 | R42: ='CF DRIVERS'!R40 | S42: ='CF DRIVERS'!S40 | T42: ='CF DRIVERS'!T40 | U42: ='CF DRIVERS'!U40 | V42: ='CF DRIVERS'!V40 | W42: ='CF DRIVERS'!W40 | X42: ='CF DRIVERS'!X40 | Y42: ='CF DRIVERS'!Y40 | ... AG42: ='CF DRIVERS'!AG40
A43: Proceeds from Issuance of Preferred Stock | B43: ='YTD CF'!B43 | C43: ='YTD CF'!C43-'YTD CF'!B43 | D43: ='YTD CF'!D43-'YTD CF'!C43 | E43: ='CASH FLOW'!C40-'YTD CF'!D43 | F43: ='YTD CF'!E43 | G43: ='YTD CF'!F43-'YTD CF'!E43 | H43: ='YTD CF'!G43-'YTD CF'!F43 | I43: ='CASH FLOW'!D40-'YTD CF'!G43 | J43: ='YTD CF'!H43 | K43: ='YTD CF'!I43-'YTD CF'!H43 | L43: ='YTD CF'!J43-'YTD CF'!I43 | M43: ='CASH FLOW'!E40-'YTD CF'!J43 | N43: ='YTD CF'!K43 | O43: ='YTD CF'!L43-'YTD CF'!K43 | P43: ='YTD CF'!M43-'YTD CF'!L43 | Q43: ='CASH FLOW'!F40-'YTD CF'!M43 | R43: ='CF DRIVERS'!R41 | S43: ='CF DRIVERS'!S41 | T43: ='CF DRIVERS'!T41 | U43: ='CF DRIVERS'!U41 | V43: ='CF DRIVERS'!V41 | W43: ='CF DRIVERS'!W41 | X43: ='CF DRIVERS'!X41 | Y43: ='CF DRIVERS'!Y41 | ... AG43: ='CF DRIVERS'!AG41
A44: Preferred Dividends | B44: ='YTD CF'!B44 | C44: ='YTD CF'!C44-'YTD CF'!B44 | D44: ='YTD CF'!D44-'YTD CF'!C44 | E44: ='CASH FLOW'!C41-'YTD CF'!D44 | F44: ='YTD CF'!E44 | G44: ='YTD CF'!F44-'YTD CF'!E44 | H44: ='YTD CF'!G44-'YTD CF'!F44 | I44: ='CASH FLOW'!D41-'YTD CF'!G44 | J44: ='YTD CF'!H44 | K44: ='YTD CF'!I44-'YTD CF'!H44 | L44: ='YTD CF'!J44-'YTD CF'!I44 | M44: ='CASH FLOW'!E41-'YTD CF'!J44 | N44: ='YTD CF'!K44 | O44: ='YTD CF'!L44-'YTD CF'!K44 | P44: ='YTD CF'!M44-'YTD CF'!L44 | Q44: ='CASH FLOW'!F41-'YTD CF'!M44 | R44: ='CF DRIVERS'!R42 | S44: ='CF DRIVERS'!S42 | T44: ='CF DRIVERS'!T42 | U44: ='CF DRIVERS'!U42 | V44: ='CF DRIVERS'!V42 | W44: ='CF DRIVERS'!W42 | X44: ='CF DRIVERS'!X42 | Y44: ='CF DRIVERS'!Y42 | ... AG44: ='CF DRIVERS'!AG42
A45: Share Repurchases | B45: ='YTD CF'!B45 | C45: ='YTD CF'!C45-'YTD CF'!B45 | D45: ='YTD CF'!D45-'YTD CF'!C45 | E45: ='CASH FLOW'!C42-'YTD CF'!D45 | F45: ='YTD CF'!E45 | G45: ='YTD CF'!F45-'YTD CF'!E45 | H45: ='YTD CF'!G45-'YTD CF'!F45 | I45: ='CASH FLOW'!D42-'YTD CF'!G45 | J45: ='YTD CF'!H45 | K45: ='YTD CF'!I45-'YTD CF'!H45 | L45: ='YTD CF'!J45-'YTD CF'!I45 | M45: ='CASH FLOW'!E42-'YTD CF'!J45 | N45: ='YTD CF'!K45 | O45: ='YTD CF'!L45-'YTD CF'!K45 | P45: ='YTD CF'!M45-'YTD CF'!L45 | Q45: ='CASH FLOW'!F42-'YTD CF'!M45 | R45: ='CF DRIVERS'!R43 | S45: ='CF DRIVERS'!S43 | T45: ='CF DRIVERS'!T43 | U45: ='CF DRIVERS'!U43 | V45: ='CF DRIVERS'!V43 | W45: ='CF DRIVERS'!W43 | X45: ='CF DRIVERS'!X43 | Y45: ='CF DRIVERS'!Y43 | ... AG45: ='CF DRIVERS'!AG43
A46: Proceeds from Issuance of Long-Term Debt | B46: ='YTD CF'!B46 | C46: ='YTD CF'!C46-'YTD CF'!B46 | D46: ='YTD CF'!D46-'YTD CF'!C46 | E46: ='CASH FLOW'!C43-'YTD CF'!D46 | F46: ='YTD CF'!E46 | G46: ='YTD CF'!F46-'YTD CF'!E46 | H46: ='YTD CF'!G46-'YTD CF'!F46 | I46: ='CASH FLOW'!D43-'YTD CF'!G46 | J46: ='YTD CF'!H46 | K46: ='YTD CF'!I46-'YTD CF'!H46 | L46: ='YTD CF'!J46-'YTD CF'!I46 | M46: ='CASH FLOW'!E43-'YTD CF'!J46 | N46: ='YTD CF'!K46 | O46: ='YTD CF'!L46-'YTD CF'!K46 | P46: ='YTD CF'!M46-'YTD CF'!L46 | Q46: ='CASH FLOW'!F43-'YTD CF'!M46 | R46: ='CF DRIVERS'!R44 | S46: ='CF DRIVERS'!S44 | T46: ='CF DRIVERS'!T44 | U46: ='CF DRIVERS'!U44 | V46: ='CF DRIVERS'!V44 | W46: ='CF DRIVERS'!W44 | X46: ='CF DRIVERS'!X44 | Y46: ='CF DRIVERS'!Y44 | ... AG46: ='CF DRIVERS'!AG44
A47: Repayments of Long-Term Debt | B47: ='YTD CF'!B47 | C47: ='YTD CF'!C47-'YTD CF'!B47 | D47: ='YTD CF'!D47-'YTD CF'!C47 | E47: ='CASH FLOW'!C44-'YTD CF'!D47 | F47: ='YTD CF'!E47 | G47: ='YTD CF'!F47-'YTD CF'!E47 | H47: ='YTD CF'!G47-'YTD CF'!F47 | I47: ='CASH FLOW'!D44-'YTD CF'!G47 | J47: ='YTD CF'!H47 | K47: ='YTD CF'!I47-'YTD CF'!H47 | L47: ='YTD CF'!J47-'YTD CF'!I47 | M47: ='CASH FLOW'!E44-'YTD CF'!J47 | N47: ='YTD CF'!K47 | O47: ='YTD CF'!L47-'YTD CF'!K47 | P47: ='YTD CF'!M47-'YTD CF'!L47 | Q47: ='CASH FLOW'!F44-'YTD CF'!M47 | R47: ='CF DRIVERS'!R45 | S47: ='CF DRIVERS'!S45 | T47: ='CF DRIVERS'!T45 | U47: ='CF DRIVERS'!U45 | V47: ='CF DRIVERS'!V45 | W47: ='CF DRIVERS'!W45 | X47: ='CF DRIVERS'!X45 | Y47: ='CF DRIVERS'!Y45 | ... AG47: ='CF DRIVERS'!AG45
A48: Debt Issuance Fees | B48: ='YTD CF'!B48 | C48: ='YTD CF'!C48-'YTD CF'!B48 | D48: ='YTD CF'!D48-'YTD CF'!C48 | E48: ='CASH FLOW'!C45-'YTD CF'!D48 | F48: ='YTD CF'!E48 | G48: ='YTD CF'!F48-'YTD CF'!E48 | H48: ='YTD CF'!G48-'YTD CF'!F48 | I48: ='CASH FLOW'!D45-'YTD CF'!G48 | J48: ='YTD CF'!H48 | K48: ='YTD CF'!I48-'YTD CF'!H48 | L48: ='YTD CF'!J48-'YTD CF'!I48 | M48: ='CASH FLOW'!E45-'YTD CF'!J48 | N48: ='YTD CF'!K48 | O48: ='YTD CF'!L48-'YTD CF'!K48 | P48: ='YTD CF'!M48-'YTD CF'!L48 | Q48: ='CASH FLOW'!F45-'YTD CF'!M48 | R48: ='CF DRIVERS'!R46 | S48: ='CF DRIVERS'!S46 | T48: ='CF DRIVERS'!T46 | U48: ='CF DRIVERS'!U46 | V48: ='CF DRIVERS'!V46 | W48: ='CF DRIVERS'!W46 | X48: ='CF DRIVERS'!X46 | Y48: ='CF DRIVERS'!Y46 | ... AG48: ='CF DRIVERS'!AG46
A49: Other Financing Activities | B49: ='YTD CF'!B49 | C49: ='YTD CF'!C49-'YTD CF'!B49 | D49: ='YTD CF'!D49-'YTD CF'!C49 | E49: ='CASH FLOW'!C46-'YTD CF'!D49 | F49: ='YTD CF'!E49 | G49: ='YTD CF'!F49-'YTD CF'!E49 | H49: ='YTD CF'!G49-'YTD CF'!F49 | I49: ='CASH FLOW'!D46-'YTD CF'!G49 | J49: ='YTD CF'!H49 | K49: ='YTD CF'!I49-'YTD CF'!H49 | L49: ='YTD CF'!J49-'YTD CF'!I49 | M49: ='CASH FLOW'!E46-'YTD CF'!J49 | N49: ='YTD CF'!K49 | O49: ='YTD CF'!L49-'YTD CF'!K49 | P49: ='YTD CF'!M49-'YTD CF'!L49 | Q49: ='CASH FLOW'!F46-'YTD CF'!M49 | R49: ='CF DRIVERS'!R47 | S49: ='CF DRIVERS'!S47 | T49: ='CF DRIVERS'!T47 | U49: ='CF DRIVERS'!U47 | V49: ='CF DRIVERS'!V47 | W49: ='CF DRIVERS'!W47 | X49: ='CF DRIVERS'!X47 | Y49: ='CF DRIVERS'!Y47 | ... AG49: ='CF DRIVERS'!AG47
A50: Cash Flow from Financing | B50: ='YTD CF'!B50 | C50: ='YTD CF'!C50-'YTD CF'!B50 | D50: ='YTD CF'!D50-'YTD CF'!C50 | E50: ='CASH FLOW'!C47-'YTD CF'!D50 | F50: ='YTD CF'!E50 | G50: ='YTD CF'!F50-'YTD CF'!E50 | H50: ='YTD CF'!G50-'YTD CF'!F50 | I50: ='CASH FLOW'!D47-'YTD CF'!G50 | J50: ='YTD CF'!H50 | K50: ='YTD CF'!I50-'YTD CF'!H50 | L50: ='YTD CF'!J50-'YTD CF'!I50 | M50: ='CASH FLOW'!E47-'YTD CF'!J50 | N50: ='YTD CF'!K50 | O50: ='YTD CF'!L50-'YTD CF'!K50 | P50: ='YTD CF'!M50-'YTD CF'!L50 | Q50: ='CASH FLOW'!F47-'YTD CF'!M50 | R50: =SUM(R40:R49) | S50: =SUM(S40:S49) | T50: =SUM(T40:T49) | U50: =SUM(U40:U49) | V50: =SUM(V40:V49) | W50: =SUM(W40:W49) | X50: =SUM(X40:X49) | Y50: =SUM(Y40:Y49) | ... AG50: =SUM(AG40:AG49)
A51: FX Effect on Cash | B51: ='YTD CF'!B51 | C51: ='YTD CF'!C51-'YTD CF'!B51 | D51: ='YTD CF'!D51-'YTD CF'!C51 | E51: ='CASH FLOW'!C48-'YTD CF'!D51 | F51: ='YTD CF'!E51 | G51: ='YTD CF'!F51-'YTD CF'!E51 | H51: ='YTD CF'!G51-'YTD CF'!F51 | I51: ='CASH FLOW'!D48-'YTD CF'!G51 | J51: ='YTD CF'!H51 | K51: ='YTD CF'!I51-'YTD CF'!H51 | L51: ='YTD CF'!J51-'YTD CF'!I51 | M51: ='CASH FLOW'!E48-'YTD CF'!J51 | N51: ='YTD CF'!K51 | O51: ='YTD CF'!L51-'YTD CF'!K51 | P51: ='YTD CF'!M51-'YTD CF'!L51 | Q51: ='CASH FLOW'!F48-'YTD CF'!M51 | R51: ='CF DRIVERS'!R48 | S51: ='CF DRIVERS'!S48 | T51: ='CF DRIVERS'!T48 | U51: ='CF DRIVERS'!U48 | V51: ='CF DRIVERS'!V48 | W51: ='CF DRIVERS'!W48 | X51: ='CF DRIVERS'!X48 | Y51: ='CF DRIVERS'!Y48 | ... AG51: ='CF DRIVERS'!AG48
A52: Net Change in Cash | B52: ='YTD CF'!B52 | C52: ='YTD CF'!C52-'YTD CF'!B52 | D52: ='YTD CF'!D52-'YTD CF'!C52 | E52: ='CASH FLOW'!C49-'YTD CF'!D52 | F52: ='YTD CF'!E52 | G52: ='YTD CF'!F52-'YTD CF'!E52 | H52: ='YTD CF'!G52-'YTD CF'!F52 | I52: ='CASH FLOW'!D49-'YTD CF'!G52 | J52: ='YTD CF'!H52 | K52: ='YTD CF'!I52-'YTD CF'!H52 | L52: ='YTD CF'!J52-'YTD CF'!I52 | M52: ='CASH FLOW'!E49-'YTD CF'!J52 | N52: ='YTD CF'!K52 | O52: ='YTD CF'!L52-'YTD CF'!K52 | P52: ='YTD CF'!M52-'YTD CF'!L52 | Q52: ='CASH FLOW'!F49-'YTD CF'!M52 | R52: =R32+R39+R50+R51 | S52: =S32+S39+S50+S51 | T52: =T32+T39+T50+T51 | U52: =U32+U39+U50+U51 | V52: =V32+V39+V50+V51 | W52: =W32+W39+W50+W51 | X52: =X32+X39+X50+X51 | Y52: =Y32+Y39+Y50+Y51 | ... AG52: =AG32+AG39+AG50+AG51

Sheet IS DRIVERS
A1: Driver | B1: Q1 FY2022 | C1: Q2 FY2022 | D1: Q3 FY2022 | E1: Q4 FY2022 | F1: Q1 FY2023 | G1: Q2 FY2023 | H1: Q3 FY2023 | I1: Q4 FY2023 | J1: Q1 FY2024 | K1: Q2 FY2024 | L1: Q3 FY2024 | M1: Q4 FY2024 | N1: Q1 FY2025 | O1: Q2 FY2025 | P1: Q3 FY2025 | Q1: Q4 FY2025 | R1: Q1 FY2026E | S1: Q2 FY2026E | T1: Q3 FY2026E | U1: Q4 FY2026E | V1: Q1 FY2027E | W1: Q2 FY2027E | X1: Q3 FY2027E | Y1: Q4 FY2027E | Z1: Q1 FY2028E | AA1: Q2 FY2028E | AB1: Q3 FY2028E | AC1: Q4 FY2028E | AD1: Q1 FY2029E | AE1: Q2 FY2029E | AF1: Q3 FY2029E | AG1: Q4 FY2029E
A2: Net Sales / Revenue — Growth % | F2: =IFERROR('QTR P&L'!F2/'QTR P&L'!B2-1,"") | G2: =IFERROR('QTR P&L'!G2/'QTR P&L'!C2-1,"") | H2: =IFERROR('QTR P&L'!H2/'QTR P&L'!D2-1,"") | I2: =IFERROR('QTR P&L'!I2/'QTR P&L'!E2-1,"") | J2: =IFERROR('QTR P&L'!J2/'QTR P&L'!F2-1,"") | K2: =IFERROR('QTR P&L'!K2/'QTR P&L'!G2-1,"") | L2: =IFERROR('QTR P&L'!L2/'QTR P&L'!H2-1,"") | M2: =IFERROR('QTR P&L'!M2/'QTR P&L'!I2-1,"") | ... Q2: =IFERROR('QTR P&L'!Q2/'QTR P&L'!M2-1,"") | R2: =Q2 | S2: =Q2 | T2: =Q2 | U2: =Q2 | V2: =Q2 | W2: =Q2 | X2: =Q2 | Y2: =Q2 | Z2: =Q2 | AA2: =Q2 | AB2: =Q2 | AC2: =Q2 | AD2: =Q2 | AE2: =Q2 | AF2: =Q2 | AG2: =Q2
A3: COGS — % of Revenue | B3: =IFERROR('QTR P&L'!B3/'QTR P&L'!B2,"") | C3: =IFERROR('QTR P&L'!C3/'QTR P&L'!C2,"") | D3: =IFERROR('QTR P&L'!D3/'QTR P&L'!D2,"") | E3: =IFERROR('QTR P&L'!E3/'QTR P&L'!E2,"") | F3: =IFERROR('QTR P&L'!F3/'QTR P&L'!F2,"") | G3: =IFERROR('QTR P&L'!G3/'QTR P&L'!G2,"") | H3: =IFERROR('QTR P&L'!H3/'QTR P&L'!H2,"") | I3: =IFERROR('QTR P&L'!I3/'QTR P&L'!I2,"") | ... Q3: =IFERROR('QTR P&L'!Q3/'QTR P&L'!Q2,"") | R3: =Q3 | S3: =Q3 | T3: =Q3 | U3: =Q3 | V3: =Q3 | W3: =Q3 | X3: =Q3 | Y3: =Q3 | Z3: =Q3 | AA3: =Q3 | AB3: =Q3 | AC3: =Q3 | AD3: =Q3 | AE3: =Q3 | AF3: =Q3 | AG3: =Q3
A4: SG&A — % of Revenue | B4: =IFERROR('QTR P&L'!B5/'QTR P&L'!B2,"") | C4: =IFERROR('QTR P&L'!C5/'QTR P&L'!C2,"") | D4: =IFERROR('QTR P&L'!D5/'QTR P&L'!D2,"") | E4: =IFERROR('QTR P&L'!E5/'QTR P&L'!E2,"") | F4: =IFERROR('QTR P&L'!F5/'QTR P&L'!F2,"") | G4: =IFERROR('QTR P&L'!G5/'QTR P&L'!G2,"") | H4: =IFERROR('QTR P&L'!H5/'QTR P&L'!H2,"") | I4: =IFERROR('QTR P&L'!I5/'QTR P&L'!I2,"") | ... Q4: =IFERROR('QTR P&L'!Q5/'QTR P&L'!Q2,"") | R4: =Q4 | S4: =Q4 | T4: =Q4 | U4: =Q4 | V4: =Q4 | W4: =Q4 | X4: =Q4 | Y4: =Q4 | Z4: =Q4 | AA4: =Q4 | AB4: =Q4 | AC4: =Q4 | AD4: =Q4 | AE4: =Q4 | AF4: =Q4 | AG4: =Q4
A5: Distributor Termination Fees | B5: ='QTR P&L'!B6 | C5: ='QTR P&L'!C6 | D5: ='QTR P&L'!D6 | E5: ='QTR P&L'!E6 | F5: ='QTR P&L'!F6 | G5: ='QTR P&L'!G6 | H5: ='QTR P&L'!H6 | I5: ='QTR P&L'!I6 | ... Q5: ='QTR P&L'!Q6 | R5: 0 | S5: 0 | T5: 0 | U5: 0 | V5: 0 | W5: 0 | X5: 0 | Y5: 0 | Z5: 0 | AA5: 0 | AB5: 0 | AC5: 0 | AD5: 0 | AE5: 0 | AF5: 0 | AG5: 0
A6: Interest Income (Expense) | B6: ='QTR P&L'!B8 | C6: ='QTR P&L'!C8 | D6: ='QTR P&L'!D8 | E6: ='QTR P&L'!E8 | F6: ='QTR P&L'!F8 | G6: ='QTR P&L'!G8 | H6: ='QTR P&L'!H8 | I6: ='QTR P&L'!I8 | ... Q6: ='QTR P&L'!Q8 | R6: =Q6 | S6: =Q6 | T6: =Q6 | U6: =Q6 | V6: =Q6 | W6: =Q6 | X6: =Q6 | Y6: =Q6 | Z6: =Q6 | AA6: =Q6 | AB6: =Q6 | AC6: =Q6 | AD6: =Q6 | AE6: =Q6 | AF6: =Q6 | AG6: =Q6
A7: Foreign Currency Gain (Loss) | B7: ='QTR P&L'!B9 | C7: ='QTR P&L'!C9 | D7: ='QTR P&L'!D9 | E7: ='QTR P&L'!E9 | F7: ='QTR P&L'!F9 | G7: ='QTR P&L'!G9 | H7: ='QTR P&L'!H9 | I7: ='QTR P&L'!I9 | ... Q7: ='QTR P&L'!Q9 | R7: =Q7 | S7: =Q7 | T7: =Q7 | U7: =Q7 | V7: =Q7 | W7: =Q7 | X7: =Q7 | Y7: =Q7 | Z7: =Q7 | AA7: =Q7 | AB7: =Q7 | AC7: =Q7 | AD7: =Q7 | AE7: =Q7 | AF7: =Q7 | AG7: =Q7
A8: Other Income (Expense) | B8: ='QTR P&L'!B10 | C8: ='QTR P&L'!C10 | D8: ='QTR P&L'!D10 | E8: ='QTR P&L'!E10 | F8: ='QTR P&L'!F10 | G8: ='QTR P&L'!G10 | H8: ='QTR P&L'!H10 | I8: ='QTR P&L'!I10 | ... Q8: ='QTR P&L'!Q10 | R8: =Q8 | S8: =Q8 | T8: =Q8 | U8: =Q8 | V8: =Q8 | W8: =Q8 | X8: =Q8 | Y8: =Q8 | Z8: =Q8 | AA8: =Q8 | AB8: =Q8 | AC8: =Q8 | AD8: =Q8 | AE8: =Q8 | AF8: =Q8 | AG8: =Q8
A9: Income Tax (Expense) Benefit — Effective Tax Rate % | B9: =IFERROR('QTR P&L'!B12/'QTR P&L'!B11,"") | C9: =IFERROR('QTR P&L'!C12/'QTR P&L'!C11,"") | D9: =IFERROR('QTR P&L'!D12/'QTR P&L'!D11,"") | E9: =IFERROR('QTR P&L'!E12/'QTR P&L'!E11,"") | F9: =IFERROR('QTR P&L'!F12/'QTR P&L'!F11,"") | G9: =IFERROR('QTR P&L'!G12/'QTR P&L'!G11,"") | H9: =IFERROR('QTR P&L'!H12/'QTR P&L'!H11,"") | I9: =IFERROR('QTR P&L'!I12/'QTR P&L'!I11,"") | ... Q9: =IFERROR('QTR P&L'!Q12/'QTR P&L'!Q11,"") | R9: =Q9 | S9: =Q9 | T9: =Q9 | U9: =Q9 | V9: =Q9 | W9: =Q9 | X9: =Q9 | Y9: =Q9 | Z9: =Q9 | AA9: =Q9 | AB9: =Q9 | AC9: =Q9 | AD9: =Q9 | AE9: =Q9 | AF9: =Q9 | AG9: =Q9
A10: Net Income (Loss) Attributable to Common Shareholders — % of Revenue | B10: =IFERROR('QTR P&L'!B16/'QTR P&L'!B2,"") | C10: =IFERROR('QTR P&L'!C16/'QTR P&L'!C2,"") | D10: =IFERROR('QTR P&L'!D16/'QTR P&L'!D2,"") | E10: =IFERROR('QTR P&L'!E16/'QTR P&L'!E2,"") | F10: =IFERROR('QTR P&L'!F16/'QTR P&L'!F2,"") | G10: =IFERROR('QTR P&L'!G16/'QTR P&L'!G2,"") | H10: =IFERROR('QTR P&L'!H16/'QTR P&L'!H2,"") | I10: =IFERROR('QTR P&L'!I16/'QTR P&L'!I2,"") | ... Q10: =IFERROR('QTR P&L'!Q16/'QTR P&L'!Q2,"") | R10: =Q10 | S10: =Q10 | T10: =Q10 | U10: =Q10 | V10: =Q10 | W10: =Q10 | X10: =Q10 | Y10: =Q10 | Z10: =Q10 | AA10: =Q10 | AB10: =Q10 | AC10: =Q10 | AD10: =Q10 | AE10: =Q10 | AF10: =Q10 | AG10: =Q10

Sheet BS DRIVERS
A1: Driver | B1: Q4 FY2022 | C1: Q1 FY2023 | D1: Q2 FY2023 | E1: Q3 FY2023 | F1: Q4 FY2023 | G1: Q1 FY2024 | H1: Q2 FY2024 | I1: Q3 FY2024 | J1: Q4 FY2024 | K1: Q1 FY2025 | L1: Q2 FY2025 | M1: Q3 FY2025 | N1: Q4 FY2025 | O1: Q1 FY2026E | P1: Q2 FY2026E | Q1: Q3 FY2026E | R1: Q4 FY2026E | S1: Q1 FY2027E | T1: Q2 FY2027E | U1: Q3 FY2027E | V1: Q4 FY2027E | W1: Q1 FY2028E | X1: Q2 FY2028E | Y1: Q3 FY2028E | Z1: Q4 FY2028E | AA1: Q1 FY2029E | AB1: Q2 FY2029E | AC1: Q3 FY2029E | AD1: Q4 FY2029E
A2: Cash & Cash Equivalents | B2: ='QTR BS'!B2 | C2: ='QTR BS'!C2 | D2: ='QTR BS'!D2 | E2: ='QTR BS'!E2 | F2: ='QTR BS'!F2 | G2: ='QTR BS'!G2 | H2: ='QTR BS'!H2 | I2: ='QTR BS'!I2 | ... N2: ='QTR BS'!N2 | O2: =N2+'QTR CF'!R52 | P2: =O2+'QTR CF'!S52 | Q2: =P2+'QTR CF'!T52 | R2: =Q2+'QTR CF'!U52 | S2: =R2+'QTR CF'!V52 | T2: =S2+'QTR CF'!W52 | U2: =T2+'QTR CF'!X52 | V2: =U2+'QTR CF'!Y52 | ... AD2: =AC2+'QTR CF'!AG52
A3: Restricted Cash | B3: ='QTR BS'!B3 | C3: ='QTR BS'!C3 | D3: ='QTR BS'!D3 | E3: ='QTR BS'!E3 | F3: ='QTR BS'!F3 | G3: ='QTR BS'!G3 | H3: ='QTR BS'!H3 | I3: ='QTR BS'!I3 | ... N3: ='QTR BS'!N3 | O3: =N3 | P3: =N3 | Q3: =N3 | R3: =N3 | S3: =N3 | T3: =N3 | U3: =N3 | V3: =N3 | W3: =N3 | X3: =N3 | Y3: =N3 | Z3: =N3 | AA3: =N3 | AB3: =N3 | AC3: =N3 | AD3: =N3
A4: Accounts Receivable — DSO (days) | B4: =IFERROR('QTR BS'!B4/'QTR P&L'!B2*ASSUMPTIONS!$B$2,"") | C4: =IFERROR('QTR BS'!C4/'QTR P&L'!C2*ASSUMPTIONS!$B$2,"") | D4: =IFERROR('QTR BS'!D4/'QTR P&L'!D2*ASSUMPTIONS!$B$2,"") | E4: =IFERROR('QTR BS'!E4/'QTR P&L'!E2*ASSUMPTIONS!$B$2,"") | F4: =IFERROR('QTR BS'!F4/'QTR P&L'!F2*ASSUMPTIONS!$B$2,"") | G4: =IFERROR('QTR BS'!G4/'QTR P&L'!G2*ASSUMPTIONS!$B$2,"") | H4: =IFERROR('QTR BS'!H4/'QTR P&L'!H2*ASSUMPTIONS!$B$2,"") | I4: =IFERROR('QTR BS'!I4/'QTR P&L'!I2*ASSUMPTIONS!$B$2,"") | ... N4: =IFERROR('QTR BS'!N4/'QTR P&L'!N2*ASSUMPTIONS!$B$2,"") | O4: =N4 | P4: =N4 | Q4: =N4 | R4: =N4 | S4: =N4 | T4: =N4 | U4: =N4 | V4: =N4 | W4: =N4 | X4: =N4 | Y4: =N4 | Z4: =N4 | AA4: =N4 | AB4: =N4 | AC4: =N4 | AD4: =N4
A5: Note Receivable - Current — DSO (days) | B5: =IFERROR('QTR BS'!B5/'QTR P&L'!B2*ASSUMPTIONS!$B$2,"") | C5: =IFERROR('QTR BS'!C5/'QTR P&L'!C2*ASSUMPTIONS!$B$2,"") | D5: =IFERROR('QTR BS'!D5/'QTR P&L'!D2*ASSUMPTIONS!$B$2,"") | E5: =IFERROR('QTR BS'!E5/'QTR P&L'!E2*ASSUMPTIONS!$B$2,"") | F5: =IFERROR('QTR BS'!F5/'QTR P&L'!F2*ASSUMPTIONS!$B$2,"") | G5: =IFERROR('QTR BS'!G5/'QTR P&L'!G2*ASSUMPTIONS!$B$2,"") | H5: =IFERROR('QTR BS'!H5/'QTR P&L'!H2*ASSUMPTIONS!$B$2,"") | I5: =IFERROR('QTR BS'!I5/'QTR P&L'!I2*ASSUMPTIONS!$B$2,"") | ... N5: =IFERROR('QTR BS'!N5/'QTR P&L'!N2*ASSUMPTIONS!$B$2,"") | O5: =N5 | P5: =N5 | Q5: =N5 | R5: =N5 | S5: =N5 | T5: =N5 | U5: =N5 | V5: =N5 | W5: =N5 | X5: =N5 | Y5: =N5 | Z5: =N5 | AA5: =N5 | AB5: =N5 | AC5: =N5 | AD5: =N5
A6: Inventories — DIO (days) | B6: =IFERROR('QTR BS'!B6/'QTR P&L'!B3*ASSUMPTIONS!$B$2,"") | C6: =IFERROR('QTR BS'!C6/'QTR P&L'!C3*ASSUMPTIONS!$B$2,"") | D6: =IFERROR('QTR BS'!D6/'QTR P&L'!D3*ASSUMPTIONS!$B$2,"") | E6: =IFERROR('QTR BS'!E6/'QTR P&L'!E3*ASSUMPTIONS!$B$2,"") | F6: =IFERROR('QTR BS'!F6/'QTR P&L'!F3*ASSUMPTIONS!$B$2,"") | G6: =IFERROR('QTR BS'!G6/'QTR P&L'!G3*ASSUMPTIONS!$B$2,"") | H6: =IFERROR('QTR BS'!H6/'QTR P&L'!H3*ASSUMPTIONS!$B$2,"") | I6: =IFERROR('QTR BS'!I6/'QTR P&L'!I3*ASSUMPTIONS!$B$2,"") | ... N6: =IFERROR('QTR BS'!N6/'QTR P&L'!N3*ASSUMPTIONS!$B$2,"") | O6: =N6 | P6: =N6 | Q6: =N6 | R6: =N6 | S6: =N6 | T6: =N6 | U6: =N6 | V6: =N6 | W6: =N6 | X6: =N6 | Y6: =N6 | Z6: =N6 | AA6: =N6 | AB6: =N6 | AC6: =N6 | AD6: =N6
A7: Prepaid Expenses — % of Revenue | B7: =IFERROR('QTR BS'!B7/'QTR P&L'!B2,"") | C7: =IFERROR('QTR BS'!C7/'QTR P&L'!C2,"") | D7: =IFERROR('QTR BS'!D7/'QTR P&L'!D2,"") | E7: =IFERROR('QTR BS'!E7/'QTR P&L'!E2,"") | F7: =IFERROR('QTR BS'!F7/'QTR P&L'!F2,"") | G7: =IFERROR('QTR BS'!G7/'QTR P&L'!G2,"") | H7: =IFERROR('QTR BS'!H7/'QTR P&L'!H2,"") | I7: =IFERROR('QTR BS'!I7/'QTR P&L'!I2,"") | ... N7: =IFERROR('QTR BS'!N7/'QTR P&L'!N2,"") | O7: =N7 | P7: =N7 | Q7: =N7 | R7: =N7 | S7: =N7 | T7: =N7 | U7: =N7 | V7: =N7 | W7: =N7 | X7: =N7 | Y7: =N7 | Z7: =N7 | AA7: =N7 | AB7: =N7 | AC7: =N7 | AD7: =N7
A8: Deferred Other Costs - Current — % of Revenue | B8: =IFERROR('QTR BS'!B8/'QTR P&L'!B2,"") | C8: =IFERROR('QTR BS'!C8/'QTR P&L'!C2,"") | D8: =IFERROR('QTR BS'!D8/'QTR P&L'!D2,"") | E8: =IFERROR('QTR BS'!E8/'QTR P&L'!E2,"") | F8: =IFERROR('QTR BS'!F8/'QTR P&L'!F2,"") | G8: =IFERROR('QTR BS'!G8/'QTR P&L'!G2,"") | H8: =IFERROR('QTR BS'!H8/'QTR P&L'!H2,"") | I8: =IFERROR('QTR BS'!I8/'QTR P&L'!I2,"") | ... N8: =IFERROR('QTR BS'!N8/'QTR P&L'!N2,"") | O8: =N8 | P8: =N8 | Q8: =N8 | R8: =N8 | S8: =N8 | T8: =N8 | U8: =N8 | V8: =N8 | W8: =N8 | X8: =N8 | Y8: =N8 | Z8: =N8 | AA8: =N8 | AB8: =N8 | AC8: =N8 | AD8: =N8
A9: Note Receivable - Non-Current — % of Revenue | B9: =IFERROR('QTR BS'!B10/'QTR P&L'!B2,"") | C9: =IFERROR('QTR BS'!C10/'QTR P&L'!C2,"") | D9: =IFERROR('QTR BS'!D10/'QTR P&L'!D2,"") | E9: =IFERROR('QTR BS'!E10/'QTR P&L'!E2,"") | F9: =IFERROR('QTR BS'!F10/'QTR P&L'!F2,"") | G9: =IFERROR('QTR BS'!G10/'QTR P&L'!G2,"") | H9: =IFERROR('QTR BS'!H10/'QTR P&L'!H2,"") | I9: =IFERROR('QTR BS'!I10/'QTR P&L'!I2,"") | ... N9: =IFERROR('QTR BS'!N10/'QTR P&L'!N2,"") | O9: =N9 | P9: =N9 | Q9: =N9 | R9: =N9 | S9: =N9 | T9: =N9 | U9: =N9 | V9: =N9 | W9: =N9 | X9: =N9 | Y9: =N9 | Z9: =N9 | AA9: =N9 | AB9: =N9 | AC9: =N9 | AD9: =N9
A10: Net PP&E | B10: ='QTR BS'!B11 | C10: ='QTR BS'!C11 | D10: ='QTR BS'!D11 | E10: ='QTR BS'!E11 | F10: ='QTR BS'!F11 | G10: ='QTR BS'!G11 | H10: ='QTR BS'!H11 | I10: ='QTR BS'!I11 | ... N10: ='QTR BS'!N11 | O10: =N10-'QTR CF'!R34-'QTR CF'!R6 | P10: =O10-'QTR CF'!S34-'QTR CF'!S6 | Q10: =P10-'QTR CF'!T34-'QTR CF'!T6 | R10: =Q10-'QTR CF'!U34-'QTR CF'!U6 | S10: =R10-'QTR CF'!V34-'QTR CF'!V6 | T10: =S10-'QTR CF'!W34-'QTR CF'!W6 | U10: =T10-'QTR CF'!X34-'QTR CF'!X6 | V10: =U10-'QTR CF'!Y34-'QTR CF'!Y6 | ... AD10: =AC10-'QTR CF'!AG34-'QTR CF'!AG6
A11: ROU Assets - Operating - Non-Current — % of Revenue | B11: =IFERROR('QTR BS'!B12/'QTR P&L'!B2,"") | C11: =IFERROR('QTR BS'!C12/'QTR P&L'!C2,"") | D11: =IFERROR('QTR BS'!D12/'QTR P&L'!D2,"") | E11: =IFERROR('QTR BS'!E12/'QTR P&L'!E2,"") | F11: =IFERROR('QTR BS'!F12/'QTR P&L'!F2,"") | G11: =IFERROR('QTR BS'!G12/'QTR P&L'!G2,"") | H11: =IFERROR('QTR BS'!H12/'QTR P&L'!H2,"") | I11: =IFERROR('QTR BS'!I12/'QTR P&L'!I2,"") | ... N11: =IFERROR('QTR BS'!N12/'QTR P&L'!N2,"") | O11: =N11 | P11: =N11 | Q11: =N11 | R11: =N11 | S11: =N11 | T11: =N11 | U11: =N11 | V11: =N11 | W11: =N11 | X11: =N11 | Y11: =N11 | Z11: =N11 | AA11: =N11 | AB11: =N11 | AC11: =N11 | AD11: =N11
A12: Intangible Assets | B12: ='QTR BS'!B13 | C12: ='QTR BS'!C13 | D12: ='QTR BS'!D13 | E12: ='QTR BS'!E13 | F12: ='QTR BS'!F13 | G12: ='QTR BS'!G13 | H12: ='QTR BS'!H13 | I12: ='QTR BS'!I13 | ... N12: ='QTR BS'!N13 | O12: =N12 | P12: =N12 | Q12: =N12 | R12: =N12 | S12: =N12 | T12: =N12 | U12: =N12 | V12: =N12 | W12: =N12 | X12: =N12 | Y12: =N12 | Z12: =N12 | AA12: =N12 | AB12: =N12 | AC12: =N12 | AD12: =N12
A13: Goodwill | B13: ='QTR BS'!B14 | C13: ='QTR BS'!C14 | D13: ='QTR BS'!D14 | E13: ='QTR BS'!E14 | F13: ='QTR BS'!F14 | G13: ='QTR BS'!G14 | H13: ='QTR BS'!H14 | I13: ='QTR BS'!I14 | ... N13: ='QTR BS'!N14 | O13: =N13 | P13: =N13 | Q13: =N13 | R13: =N13 | S13: =N13 | T13: =N13 | U13: =N13 | V13: =N13 | W13: =N13 | X13: =N13 | Y13: =N13 | Z13: =N13 | AA13: =N13 | AB13: =N13 | AC13: =N13 | AD13: =N13
A14: Deferred Other Costs - Non-Current — % of Revenue | B14: =IFERROR('QTR BS'!B15/'QTR P&L'!B2,"") | C14: =IFERROR('QTR BS'!C15/'QTR P&L'!C2,"") | D14: =IFERROR('QTR BS'!D15/'QTR P&L'!D2,"") | E14: =IFERROR('QTR BS'!E15/'QTR P&L'!E2,"") | F14: =IFERROR('QTR BS'!F15/'QTR P&L'!F2,"") | G14: =IFERROR('QTR BS'!G15/'QTR P&L'!G2,"") | H14: =IFERROR('QTR BS'!H15/'QTR P&L'!H2,"") | I14: =IFERROR('QTR BS'!I15/'QTR P&L'!I2,"") | ... N14: =IFERROR('QTR BS'!N15/'QTR P&L'!N2,"") | O14: =N14 | P14: =N14 | Q14: =N14 | R14: =N14 | S14: =N14 | T14: =N14 | U14: =N14 | V14: =N14 | W14: =N14 | X14: =N14 | Y14: =N14 | Z14: =N14 | AA14: =N14 | AB14: =N14 | AC14: =N14 | AD14: =N14
A15: Deferred Tax Assets | B15: ='QTR BS'!B16 | C15: ='QTR BS'!C16 | D15: ='QTR BS'!D16 | E15: ='QTR BS'!E16 | F15: ='QTR BS'!F16 | G15: ='QTR BS'!G16 | H15: ='QTR BS'!H16 | I15: ='QTR BS'!I16 | ... N15: ='QTR BS'!N16 | O15: =N15-'QTR CF'!R12 | P15: =O15-'QTR CF'!S12 | Q15: =P15-'QTR CF'!T12 | R15: =Q15-'QTR CF'!U12 | S15: =R15-'QTR CF'!V12 | T15: =S15-'QTR CF'!W12 | U15: =T15-'QTR CF'!X12 | V15: =U15-'QTR CF'!Y12 | ... AD15: =AC15-'QTR CF'!AG12
A16: ROU Assets - Finance - Non-Current — % of Revenue | B16: =IFERROR('QTR BS'!B17/'QTR P&L'!B2,"") | C16: =IFERROR('QTR BS'!C17/'QTR P&L'!C2,"") | D16: =IFERROR('QTR BS'!D17/'QTR P&L'!D2,"") | E16: =IFERROR('QTR BS'!E17/'QTR P&L'!E2,"") | F16: =IFERROR('QTR BS'!F17/'QTR P&L'!F2,"") | G16: =IFERROR('QTR BS'!G17/'QTR P&L'!G2,"") | H16: =IFERROR('QTR BS'!H17/'QTR P&L'!H2,"") | I16: =IFERROR('QTR BS'!I17/'QTR P&L'!I2,"") | ... N16: =IFERROR('QTR BS'!N17/'QTR P&L'!N2,"") | O16: =N16 | P16: =N16 | Q16: =N16 | R16: =N16 | S16: =N16 | T16: =N16 | U16: =N16 | V16: =N16 | W16: =N16 | X16: =N16 | Y16: =N16 | Z16: =N16 | AA16: =N16 | AB16: =N16 | AC16: =N16 | AD16: =N16
A17: Other Non-Current Assets — % of Revenue | B17: =IFERROR('QTR BS'!B18/'QTR P&L'!B2,"") | C17: =IFERROR('QTR BS'!C18/'QTR P&L'!C2,"") | D17: =IFERROR('QTR BS'!D18/'QTR P&L'!D2,"") | E17: =IFERROR('QTR BS'!E18/'QTR P&L'!E2,"") | F17: =IFERROR('QTR BS'!F18/'QTR P&L'!F2,"") | G17: =IFERROR('QTR BS'!G18/'QTR P&L'!G2,"") | H17: =IFERROR('QTR BS'!H18/'QTR P&L'!H2,"") | I17: =IFERROR('QTR BS'!I18/'QTR P&L'!I2,"") | ... N17: =IFERROR('QTR BS'!N18/'QTR P&L'!N2,"") | O17: =N17 | P17: =N17 | Q17: =N17 | R17: =N17 | S17: =N17 | T17: =N17 | U17: =N17 | V17: =N17 | W17: =N17 | X17: =N17 | Y17: =N17 | Z17: =N17 | AA17: =N17 | AB17: =N17 | AC17: =N17 | AD17: =N17
A18: Accounts Payable — DPO (days) | B18: =IFERROR('QTR BS'!B20/'QTR P&L'!B3*ASSUMPTIONS!$B$2,"") | C18: =IFERROR('QTR BS'!C20/'QTR P&L'!C3*ASSUMPTIONS!$B$2,"") | D18: =IFERROR('QTR BS'!D20/'QTR P&L'!D3*ASSUMPTIONS!$B$2,"") | E18: =IFERROR('QTR BS'!E20/'QTR P&L'!E3*ASSUMPTIONS!$B$2,"") | F18: =IFERROR('QTR BS'!F20/'QTR P&L'!F3*ASSUMPTIONS!$B$2,"") | G18: =IFERROR('QTR BS'!G20/'QTR P&L'!G3*ASSUMPTIONS!$B$2,"") | H18: =IFERROR('QTR BS'!H20/'QTR P&L'!H3*ASSUMPTIONS!$B$2,"") | I18: =IFERROR('QTR BS'!I20/'QTR P&L'!I3*ASSUMPTIONS!$B$2,"") | ... N18: =IFERROR('QTR BS'!N20/'QTR P&L'!N3*ASSUMPTIONS!$B$2,"") | O18: =N18 | P18: =N18 | Q18: =N18 | R18: =N18 | S18: =N18 | T18: =N18 | U18: =N18 | V18: =N18 | W18: =N18 | X18: =N18 | Y18: =N18 | Z18: =N18 | AA18: =N18 | AB18: =N18 | AC18: =N18 | AD18: =N18
A19: Accrued Expenses — % of Revenue | B19: =IFERROR('QTR BS'!B21/'QTR P&L'!B2,"") | C19: =IFERROR('QTR BS'!C21/'QTR P&L'!C2,"") | D19: =IFERROR('QTR BS'!D21/'QTR P&L'!D2,"") | E19: =IFERROR('QTR BS'!E21/'QTR P&L'!E2,"") | F19: =IFERROR('QTR BS'!F21/'QTR P&L'!F2,"") | G19: =IFERROR('QTR BS'!G21/'QTR P&L'!G2,"") | H19: =IFERROR('QTR BS'!H21/'QTR P&L'!H2,"") | I19: =IFERROR('QTR BS'!I21/'QTR P&L'!I2,"") | ... N19: =IFERROR('QTR BS'!N21/'QTR P&L'!N2,"") | O19: =N19 | P19: =N19 | Q19: =N19 | R19: =N19 | S19: =N19 | T19: =N19 | U19: =N19 | V19: =N19 | W19: =N19 | X19: =N19 | Y19: =N19 | Z19: =N19 | AA19: =N19 | AB19: =N19 | AC19: =N19 | AD19: =N19
A20: Income Taxes Payable — % of Revenue | B20: =IFERROR('QTR BS'!B22/'QTR P&L'!B2,"") | C20: =IFERROR('QTR BS'!C22/'QTR P&L'!C2,"") | D20: =IFERROR('QTR BS'!D22/'QTR P&L'!D2,"") | E20: =IFERROR('QTR BS'!E22/'QTR P&L'!E2,"") | F20: =IFERROR('QTR BS'!F22/'QTR P&L'!F2,"") | G20: =IFERROR('QTR BS'!G22/'QTR P&L'!G2,"") | H20: =IFERROR('QTR BS'!H22/'QTR P&L'!H2,"") | I20: =IFERROR('QTR BS'!I22/'QTR P&L'!I2,"") | ... N20: =IFERROR('QTR BS'!N22/'QTR P&L'!N2,"") | O20: =N20 | P20: =N20 | Q20: =N20 | R20: =N20 | S20: =N20 | T20: =N20 | U20: =N20 | V20: =N20 | W20: =N20 | X20: =N20 | Y20: =N20 | Z20: =N20 | AA20: =N20 | AB20: =N20 | AC20: =N20 | AD20: =N20
A21: Accrued Distributor Termination Fees | B21: ='QTR BS'!B23 | C21: ='QTR BS'!C23 | D21: ='QTR BS'!D23 | E21: ='QTR BS'!E23 | F21: ='QTR BS'!F23 | G21: ='QTR BS'!G23 | H21: ='QTR BS'!H23 | I21: ='QTR BS'!I23 | ... N21: ='QTR BS'!N23 | O21: 0 | P21: 0 | Q21: 0 | R21: 0 | S21: 0 | T21: 0 | U21: 0 | V21: 0 | W21: 0 | X21: 0 | Y21: 0 | Z21: 0 | AA21: 0 | AB21: 0 | AC21: 0 | AD21: 0
A22: Accrued Promotional Allowance — % of Revenue | B22: =IFERROR('QTR BS'!B24/'QTR P&L'!B2,"") | C22: =IFERROR('QTR BS'!C24/'QTR P&L'!C2,"") | D22: =IFERROR('QTR BS'!D24/'QTR P&L'!D2,"") | E22: =IFERROR('QTR BS'!E24/'QTR P&L'!E2,"") | F22: =IFERROR('QTR BS'!F24/'QTR P&L'!F2,"") | G22: =IFERROR('QTR BS'!G24/'QTR P&L'!G2,"") | H22: =IFERROR('QTR BS'!H24/'QTR P&L'!H2,"") | I22: =IFERROR('QTR BS'!I24/'QTR P&L'!I2,"") | ... N22: =IFERROR('QTR BS'!N24/'QTR P&L'!N2,"") | O22: =N22 | P22: =N22 | Q22: =N22 | R22: =N22 | S22: =N22 | T22: =N22 | U22: =N22 | V22: =N22 | W22: =N22 | X22: =N22 | Y22: =N22 | Z22: =N22 | AA22: =N22 | AB22: =N22 | AC22: =N22 | AD22: =N22
A23: Lease Liability - Operating - Current — % of Revenue | B23: =IFERROR('QTR BS'!B25/'QTR P&L'!B2,"") | C23: =IFERROR('QTR BS'!C25/'QTR P&L'!C2,"") | D23: =IFERROR('QTR BS'!D25/'QTR P&L'!D2,"") | E23: =IFERROR('QTR BS'!E25/'QTR P&L'!E2,"") | F23: =IFERROR('QTR BS'!F25/'QTR P&L'!F2,"") | G23: =IFERROR('QTR BS'!G25/'QTR P&L'!G2,"") | H23: =IFERROR('QTR BS'!H25/'QTR P&L'!H2,"") | I23: =IFERROR('QTR BS'!I25/'QTR P&L'!I2,"") | ... N23: =IFERROR('QTR BS'!N25/'QTR P&L'!N2,"") | O23: =N23 | P23: =N23 | Q23: =N23 | R23: =N23 | S23: =N23 | T23: =N23 | U23: =N23 | V23: =N23 | W23: =N23 | X23: =N23 | Y23: =N23 | Z23: =N23 | AA23: =N23 | AB23: =N23 | AC23: =N23 | AD23: =N23
A24: Lease Liability - Finance - Current — % of Revenue | B24: =IFERROR('QTR BS'!B26/'QTR P&L'!B2,"") | C24: =IFERROR('QTR BS'!C26/'QTR P&L'!C2,"") | D24: =IFERROR('QTR BS'!D26/'QTR P&L'!D2,"") | E24: =IFERROR('QTR BS'!E26/'QTR P&L'!E2,"") | F24: =IFERROR('QTR BS'!F26/'QTR P&L'!F2,"") | G24: =IFERROR('QTR BS'!G26/'QTR P&L'!G2,"") | H24: =IFERROR('QTR BS'!H26/'QTR P&L'!H2,"") | I24: =IFERROR('QTR BS'!I26/'QTR P&L'!I2,"") | ... N24: =IFERROR('QTR BS'!N26/'QTR P&L'!N2,"") | O24: =N24 | P24: =N24 | Q24: =N24 | R24: =N24 | S24: =N24 | T24: =N24 | U24: =N24 | V24: =N24 | W24: =N24 | X24: =N24 | Y24: =N24 | Z24: =N24 | AA24: =N24 | AB24: =N24 | AC24: =N24 | AD24: =N24
A25: Contingent Consideration - Current — % of Revenue | B25: =IFERROR('QTR BS'!B27/'QTR P&L'!B2,"") | C25: =IFERROR('QTR BS'!C27/'QTR P&L'!C2,"") | D25: =IFERROR('QTR BS'!D27/'QTR P&L'!D2,"") | E25: =IFERROR('QTR BS'!E27/'QTR P&L'!E2,"") | F25: =IFERROR('QTR BS'!F27/'QTR P&L'!F2,"") | G25: =IFERROR('QTR BS'!G27/'QTR P&L'!G2,"") | H25: =IFERROR('QTR BS'!H27/'QTR P&L'!H2,"") | I25: =IFERROR('QTR BS'!I27/'QTR P&L'!I2,"") | ... N25: =IFERROR('QTR BS'!N27/'QTR P&L'!N2,"") | O25: =N25 | P25: =N25 | Q25: =N25 | R25: =N25 | S25: =N25 | T25: =N25 | U25: =N25 | V25: =N25 | W25: =N25 | X25: =N25 | Y25: =N25 | Z25: =N25 | AA25: =N25 | AB25: =N25 | AC25: =N25 | AD25: =N25
A26: Deferred Revenue - Current — % of Revenue | B26: =IFERROR('QTR BS'!B28/'QTR P&L'!B2,"") | C26: =IFERROR('QTR BS'!C28/'QTR P&L'!C2,"") | D26: =IFERROR('QTR BS'!D28/'QTR P&L'!D2,"") | E26: =IFERROR('QTR BS'!E28/'QTR P&L'!E2,"") | F26: =IFERROR('QTR BS'!F28/'QTR P&L'!F2,"") | G26: =IFERROR('QTR BS'!G28/'QTR P&L'!G2,"") | H26: =IFERROR('QTR BS'!H28/'QTR P&L'!H2,"") | I26: =IFERROR('QTR BS'!I28/'QTR P&L'!I2,"") | ... N26: =IFERROR('QTR BS'!N28/'QTR P&L'!N2,"") | O26: =N26 | P26: =N26 | Q26: =N26 | R26: =N26 | S26: =N26 | T26: =N26 | U26: =N26 | V26: =N26 | W26: =N26 | X26: =N26 | Y26: =N26 | Z26: =N26 | AA26: =N26 | AB26: =N26 | AC26: =N26 | AD26: =N26
A27: Other Current Liabilities — % of Revenue | B27: =IFERROR('QTR BS'!B29/'QTR P&L'!B2,"") | C27: =IFERROR('QTR BS'!C29/'QTR P&L'!C2,"") | D27: =IFERROR('QTR BS'!D29/'QTR P&L'!D2,"") | E27: =IFERROR('QTR BS'!E29/'QTR P&L'!E2,"") | F27: =IFERROR('QTR BS'!F29/'QTR P&L'!F2,"") | G27: =IFERROR('QTR BS'!G29/'QTR P&L'!G2,"") | H27: =IFERROR('QTR BS'!H29/'QTR P&L'!H2,"") | I27: =IFERROR('QTR BS'!I29/'QTR P&L'!I2,"") | ... N27: =IFERROR('QTR BS'!N29/'QTR P&L'!N2,"") | O27: =N27 | P27: =N27 | Q27: =N27 | R27: =N27 | S27: =N27 | T27: =N27 | U27: =N27 | V27: =N27 | W27: =N27 | X27: =N27 | Y27: =N27 | Z27: =N27 | AA27: =N27 | AB27: =N27 | AC27: =N27 | AD27: =N27
A28: Lease Liability - Operating - Non-Current — % of Revenue | B28: =IFERROR('QTR BS'!B31/'QTR P&L'!B2,"") | C28: =IFERROR('QTR BS'!C31/'QTR P&L'!C2,"") | D28: =IFERROR('QTR BS'!D31/'QTR P&L'!D2,"") | E28: =IFERROR('QTR BS'!E31/'QTR P&L'!E2,"") | F28: =IFERROR('QTR BS'!F31/'QTR P&L'!F2,"") | G28: =IFERROR('QTR BS'!G31/'QTR P&L'!G2,"") | H28: =IFERROR('QTR BS'!H31/'QTR P&L'!H2,"") | I28: =IFERROR('QTR BS'!I31/'QTR P&L'!I2,"") | ... N28: =IFERROR('QTR BS'!N31/'QTR P&L'!N2,"") | O28: =N28 | P28: =N28 | Q28: =N28 | R28: =N28 | S28: =N28 | T28: =N28 | U28: =N28 | V28: =N28 | W28: =N28 | X28: =N28 | Y28: =N28 | Z28: =N28 | AA28: =N28 | AB28: =N28 | AC28: =N28 | AD28: =N28
A29: Lease Liability - Finance - Non-Current — % of Revenue | B29: =IFERROR('QTR BS'!B32/'QTR P&L'!B2,"") | C29: =IFERROR('QTR BS'!C32/'QTR P&L'!C2,"") | D29: =IFERROR('QTR BS'!D32/'QTR P&L'!D2,"") | E29: =IFERROR('QTR BS'!E32/'QTR P&L'!E2,"") | F29: =IFERROR('QTR BS'!F32/'QTR P&L'!F2,"") | G29: =IFERROR('QTR BS'!G32/'QTR P&L'!G2,"") | H29: =IFERROR('QTR BS'!H32/'QTR P&L'!H2,"") | I29: =IFERROR('QTR BS'!I32/'QTR P&L'!I2,"") | ... N29: =IFERROR('QTR BS'!N32/'QTR P&L'!N2,"") | O29: =N29 | P29: =N29 | Q29: =N29 | R29: =N29 | S29: =N29 | T29: =N29 | U29: =N29 | V29: =N29 | W29: =N29 | X29: =N29 | Y29: =N29 | Z29: =N29 | AA29: =N29 | AB29: =N29 | AC29: =N29 | AD29: =N29
A30: Deferred Tax Liability | B30: ='QTR BS'!B33 | C30: ='QTR BS'!C33 | D30: ='QTR BS'!D33 | E30: ='QTR BS'!E33 | F30: ='QTR BS'!F33 | G30: ='QTR BS'!G33 | H30: ='QTR BS'!H33 | I30: ='QTR BS'!I33 | ... N30: ='QTR BS'!N33 | O30: =N30 | P30: =N30 | Q30: =N30 | R30: =N30 | S30: =N30 | T30: =N30 | U30: =N30 | V30: =N30 | W30: =N30 | X30: =N30 | Y30: =N30 | Z30: =N30 | AA30: =N30 | AB30: =N30 | AC30: =N30 | AD30: =N30
A31: Long-Term Debt | B31: ='QTR BS'!B34 | C31: ='QTR BS'!C34 | D31: ='QTR BS'!D34 | E31: ='QTR BS'!E34 | F31: ='QTR BS'!F34 | G31: ='QTR BS'!G34 | H31: ='QTR BS'!H34 | I31: ='QTR BS'!I34 | ... N31: ='QTR BS'!N34 | O31: =N31 | P31: =N31 | Q31: =N31 | R31: =N31 | S31: =N31 | T31: =N31 | U31: =N31 | V31: =N31 | W31: =N31 | X31: =N31 | Y31: =N31 | Z31: =N31 | AA31: =N31 | AB31: =N31 | AC31: =N31 | AD31: =N31
A32: Deferred Revenue - Non-Current — % of Revenue | B32: =IFERROR('QTR BS'!B35/'QTR P&L'!B2,"") | C32: =IFERROR('QTR BS'!C35/'QTR P&L'!C2,"") | D32: =IFERROR('QTR BS'!D35/'QTR P&L'!D2,"") | E32: =IFERROR('QTR BS'!E35/'QTR P&L'!E2,"") | F32: =IFERROR('QTR BS'!F35/'QTR P&L'!F2,"") | G32: =IFERROR('QTR BS'!G35/'QTR P&L'!G2,"") | H32: =IFERROR('QTR BS'!H35/'QTR P&L'!H2,"") | I32: =IFERROR('QTR BS'!I35/'QTR P&L'!I2,"") | ... N32: =IFERROR('QTR BS'!N35/'QTR P&L'!N2,"") | O32: =N32 | P32: =N32 | Q32: =N32 | R32: =N32 | S32: =N32 | T32: =N32 | U32: =N32 | V32: =N32 | W32: =N32 | X32: =N32 | Y32: =N32 | Z32: =N32 | AA32: =N32 | AB32: =N32 | AC32: =N32 | AD32: =N32
A33: Other Non-Current Liabilities — % of Revenue | B33: =IFERROR('QTR BS'!B36/'QTR P&L'!B2,"") | C33: =IFERROR('QTR BS'!C36/'QTR P&L'!C2,"") | D33: =IFERROR('QTR BS'!D36/'QTR P&L'!D2,"") | E33: =IFERROR('QTR BS'!E36/'QTR P&L'!E2,"") | F33: =IFERROR('QTR BS'!F36/'QTR P&L'!F2,"") | G33: =IFERROR('QTR BS'!G36/'QTR P&L'!G2,"") | H33: =IFERROR('QTR BS'!H36/'QTR P&L'!H2,"") | I33: =IFERROR('QTR BS'!I36/'QTR P&L'!I2,"") | ... N33: =IFERROR('QTR BS'!N36/'QTR P&L'!N2,"") | O33: =N33 | P33: =N33 | Q33: =N33 | R33: =N33 | S33: =N33 | T33: =N33 | U33: =N33 | V33: =N33 | W33: =N33 | X33: =N33 | Y33: =N33 | Z33: =N33 | AA33: =N33 | AB33: =N33 | AC33: =N33 | AD33: =N33
A34: Convertible Preferred Stock | B34: ='QTR BS'!B38 | C34: ='QTR BS'!C38 | D34: ='QTR BS'!D38 | E34: ='QTR BS'!E38 | F34: ='QTR BS'!F38 | G34: ='QTR BS'!G38 | H34: ='QTR BS'!H38 | I34: ='QTR BS'!I38 | ... N34: ='QTR BS'!N38 | O34: =N34 | P34: =N34 | Q34: =N34 | R34: =N34 | S34: =N34 | T34: =N34 | U34: =N34 | V34: =N34 | W34: =N34 | X34: =N34 | Y34: =N34 | Z34: =N34 | AA34: =N34 | AB34: =N34 | AC34: =N34 | AD34: =N34
A35: Common Stock | B35: ='QTR BS'!B39 | C35: ='QTR BS'!C39 | D35: ='QTR BS'!D39 | E35: ='QTR BS'!E39 | F35: ='QTR BS'!F39 | G35: ='QTR BS'!G39 | H35: ='QTR BS'!H39 | I35: ='QTR BS'!I39 | ... N35: ='QTR BS'!N39 | O35: =N35 | P35: =N35 | Q35: =N35 | R35: =N35 | S35: =N35 | T35: =N35 | U35: =N35 | V35: =N35 | W35: =N35 | X35: =N35 | Y35: =N35 | Z35: =N35 | AA35: =N35 | AB35: =N35 | AC35: =N35 | AD35: =N35
A36: Treasury Stock | B36: ='QTR BS'!B40 | C36: ='QTR BS'!C40 | D36: ='QTR BS'!D40 | E36: ='QTR BS'!E40 | F36: ='QTR BS'!F40 | G36: ='QTR BS'!G40 | H36: ='QTR BS'!H40 | I36: ='QTR BS'!I40 | ... N36: ='QTR BS'!N40 | O36: =N36 | P36: =N36 | Q36: =N36 | R36: =N36 | S36: =N36 | T36: =N36 | U36: =N36 | V36: =N36 | W36: =N36 | X36: =N36 | Y36: =N36 | Z36: =N36 | AA36: =N36 | AB36: =N36 | AC36: =N36 | AD36: =N36
A37: Additional Paid-in Capital | B37: ='QTR BS'!B41 | C37: ='QTR BS'!C41 | D37: ='QTR BS'!D41 | E37: ='QTR BS'!E41 | F37: ='QTR BS'!F41 | G37: ='QTR BS'!G41 | H37: ='QTR BS'!H41 | I37: ='QTR BS'!I41 | ... N37: ='QTR BS'!N41 | O37: =N37+'QTR CF'!R11 | P37: =O37+'QTR CF'!S11 | Q37: =P37+'QTR CF'!T11 | R37: =Q37+'QTR CF'!U11 | S37: =R37+'QTR CF'!V11 | T37: =S37+'QTR CF'!W11 | U37: =T37+'QTR CF'!X11 | V37: =U37+'QTR CF'!Y11 | ... AD37: =AC37+'QTR CF'!AG11
A38: Accumulated Other Comprehensive Income (Loss) | B38: ='QTR BS'!B42 | C38: ='QTR BS'!C42 | D38: ='QTR BS'!D42 | E38: ='QTR BS'!E42 | F38: ='QTR BS'!F42 | G38: ='QTR BS'!G42 | H38: ='QTR BS'!H42 | I38: ='QTR BS'!I42 | ... N38: ='QTR BS'!N42 | O38: =N38+'QTR CF'!R51 | P38: =O38+'QTR CF'!S51 | Q38: =P38+'QTR CF'!T51 | R38: =Q38+'QTR CF'!U51 | S38: =R38+'QTR CF'!V51 | T38: =S38+'QTR CF'!W51 | U38: =T38+'QTR CF'!X51 | V38: =U38+'QTR CF'!Y51 | ... AD38: =AC38+'QTR CF'!AG51
A39: Retained Earnings (Accumulated Deficit) | B39: ='QTR BS'!B43 | C39: ='QTR BS'!C43 | D39: ='QTR BS'!D43 | E39: ='QTR BS'!E43 | F39: ='QTR BS'!F43 | G39: ='QTR BS'!G43 | H39: ='QTR BS'!H43 | I39: ='QTR BS'!I43 | ... N39: ='QTR BS'!N43 | O39: =N39+'QTR P&L'!R13+'QTR CF'!R44 | P39: =O39+'QTR P&L'!S13+'QTR CF'!S44 | Q39: =P39+'QTR P&L'!T13+'QTR CF'!T44 | R39: =Q39+'QTR P&L'!U13+'QTR CF'!U44 | S39: =R39+'QTR P&L'!V13+'QTR CF'!V44 | T39: =S39+'QTR P&L'!W13+'QTR CF'!W44 | U39: =T39+'QTR P&L'!X13+'QTR CF'!X44 | V39: =U39+'QTR P&L'!Y13+'QTR CF'!Y44 | ... AD39: =AC39+'QTR P&L'!AG13+'QTR CF'!AG44

Sheet CF DRIVERS
A1: Driver | B1: Q1 FY2022 | C1: Q2 FY2022 | D1: Q3 FY2022 | E1: Q4 FY2022 | F1: Q1 FY2023 | G1: Q2 FY2023 | H1: Q3 FY2023 | I1: Q4 FY2023 | J1: Q1 FY2024 | K1: Q2 FY2024 | L1: Q3 FY2024 | M1: Q4 FY2024 | N1: Q1 FY2025 | O1: Q2 FY2025 | P1: Q3 FY2025 | Q1: Q4 FY2025 | R1: Q1 FY2026E | S1: Q2 FY2026E | T1: Q3 FY2026E | U1: Q4 FY2026E | V1: Q1 FY2027E | W1: Q2 FY2027E | X1: Q3 FY2027E | Y1: Q4 FY2027E | Z1: Q1 FY2028E | AA1: Q2 FY2028E | AB1: Q3 FY2028E | AC1: Q4 FY2028E | AD1: Q1 FY2029E | AE1: Q2 FY2029E | AF1: Q3 FY2029E | AG1: Q4 FY2029E
A2: Net Income (Loss) | B2: ='QTR CF'!B2 | C2: ='QTR CF'!C2 | D2: ='QTR CF'!D2 | E2: ='QTR CF'!E2 | F2: ='QTR CF'!F2 | G2: ='QTR CF'!G2 | H2: ='QTR CF'!H2 | I2: ='QTR CF'!I2 | ... Q2: ='QTR CF'!Q2 | R2: ='QTR P&L'!R13 | S2: ='QTR P&L'!S13 | T2: ='QTR P&L'!T13 | U2: ='QTR P&L'!U13 | V2: ='QTR P&L'!V13 | W2: ='QTR P&L'!W13 | X2: ='QTR P&L'!X13 | Y2: ='QTR P&L'!Y13 | ... AG2: ='QTR P&L'!AG13
A3: Depreciation | B3: ='QTR CF'!B3 | C3: ='QTR CF'!C3 | D3: ='QTR CF'!D3 | E3: ='QTR CF'!E3 | F3: ='QTR CF'!F3 | G3: ='QTR CF'!G3 | H3: ='QTR CF'!H3 | I3: ='QTR CF'!I3 | ... Q3: ='QTR CF'!Q3 | R3: 0 | S3: 0 | T3: 0 | U3: 0 | V3: 0 | W3: 0 | X3: 0 | Y3: 0 | Z3: 0 | AA3: 0 | AB3: 0 | AC3: 0 | AD3: 0 | AE3: 0 | AF3: 0 | AG3: 0
A4: Amortization | B4: ='QTR CF'!B4 | C4: ='QTR CF'!C4 | D4: ='QTR CF'!D4 | E4: ='QTR CF'!E4 | F4: ='QTR CF'!F4 | G4: ='QTR CF'!G4 | H4: ='QTR CF'!H4 | I4: ='QTR CF'!I4 | ... Q4: ='QTR CF'!Q4 | R4: 0 | S4: 0 | T4: 0 | U4: 0 | V4: 0 | W4: 0 | X4: 0 | Y4: 0 | Z4: 0 | AA4: 0 | AB4: 0 | AC4: 0 | AD4: 0 | AE4: 0 | AF4: 0 | AG4: 0
A5: Impairment of Intangibles | B5: ='QTR CF'!B5 | C5: ='QTR CF'!C5 | D5: ='QTR CF'!D5 | E5: ='QTR CF'!E5 | F5: ='QTR CF'!F5 | G5: ='QTR CF'!G5 | H5: ='QTR CF'!H5 | I5: ='QTR CF'!I5 | ... Q5: ='QTR CF'!Q5 | R5: 0 | S5: 0 | T5: 0 | U5: 0 | V5: 0 | W5: 0 | X5: 0 | Y5: 0 | Z5: 0 | AA5: 0 | AB5: 0 | AC5: 0 | AD5: 0 | AE5: 0 | AF5: 0 | AG5: 0
A6: Depreciation & Amortization — % of Revenue | B6: =IFERROR('QTR CF'!B6/'QTR P&L'!B2,"") | C6: =IFERROR('QTR CF'!C6/'QTR P&L'!C2,"") | D6: =IFERROR('QTR CF'!D6/'QTR P&L'!D2,"") | E6: =IFERROR('QTR CF'!E6/'QTR P&L'!E2,"") | F6: =IFERROR('QTR CF'!F6/'QTR P&L'!F2,"") | G6: =IFERROR('QTR CF'!G6/'QTR P&L'!G2,"") | H6: =IFERROR('QTR CF'!H6/'QTR P&L'!H2,"") | I6: =IFERROR('QTR CF'!I6/'QTR P&L'!I2,"") | ... Q6: =IFERROR('QTR CF'!Q6/'QTR P&L'!Q2,"") | R6: =Q6 | S6: =Q6 | T6: =Q6 | U6: =Q6 | V6: =Q6 | W6: =Q6 | X6: =Q6 | Y6: =Q6 | Z6: =Q6 | AA6: =Q6 | AB6: =Q6 | AC6: =Q6 | AD6: =Q6 | AE6: =Q6 | AF6: =Q6 | AG6: =Q6
A7: Allowance for Credit Losses | B7: ='QTR CF'!B7 | C7: ='QTR CF'!C7 | D7: ='QTR CF'!D7 | E7: ='QTR CF'!E7 | F7: ='QTR CF'!F7 | G7: ='QTR CF'!G7 | H7: ='QTR CF'!H7 | I7: ='QTR CF'!I7 | ... Q7: ='QTR CF'!Q7 | R7: 0 | S7: 0 | T7: 0 | U7: 0 | V7: 0 | W7: 0 | X7: 0 | Y7: 0 | Z7: 0 | AA7: 0 | AB7: 0 | AC7: 0 | AD7: 0 | AE7: 0 | AF7: 0 | AG7: 0
A8: Amortization of Deferred Other Costs | B8: ='QTR CF'!B8 | C8: ='QTR CF'!C8 | D8: ='QTR CF'!D8 | E8: ='QTR CF'!E8 | F8: ='QTR CF'!F8 | G8: ='QTR CF'!G8 | H8: ='QTR CF'!H8 | I8: ='QTR CF'!I8 | ... Q8: ='QTR CF'!Q8 | R8: 0 | S8: 0 | T8: 0 | U8: 0 | V8: 0 | W8: 0 | X8: 0 | Y8: 0 | Z8: 0 | AA8: 0 | AB8: 0 | AC8: 0 | AD8: 0 | AE8: 0 | AF8: 0 | AG8: 0
A9: Inventory Write-Down | B9: ='QTR CF'!B9 | C9: ='QTR CF'!C9 | D9: ='QTR CF'!D9 | E9: ='QTR CF'!E9 | F9: ='QTR CF'!F9 | G9: ='QTR CF'!G9 | H9: ='QTR CF'!H9 | I9: ='QTR CF'!I9 | ... Q9: ='QTR CF'!Q9 | R9: 0 | S9: 0 | T9: 0 | U9: 0 | V9: 0 | W9: 0 | X9: 0 | Y9: 0 | Z9: 0 | AA9: 0 | AB9: 0 | AC9: 0 | AD9: 0 | AE9: 0 | AF9: 0 | AG9: 0
A10: Gain (Loss) on Disposal of PP&E | B10: ='QTR CF'!B10 | C10: ='QTR CF'!C10 | D10: ='QTR CF'!D10 | E10: ='QTR CF'!E10 | F10: ='QTR CF'!F10 | G10: ='QTR CF'!G10 | H10: ='QTR CF'!H10 | I10: ='QTR CF'!I10 | ... Q10: ='QTR CF'!Q10 | R10: 0 | S10: 0 | T10: 0 | U10: 0 | V10: 0 | W10: 0 | X10: 0 | Y10: 0 | Z10: 0 | AA10: 0 | AB10: 0 | AC10: 0 | AD10: 0 | AE10: 0 | AF10: 0 | AG10: 0
A11: Stock-Based Compensation — % of Revenue | B11: =IFERROR('QTR CF'!B11/'QTR P&L'!B2,"") | C11: =IFERROR('QTR CF'!C11/'QTR P&L'!C2,"") | D11: =IFERROR('QTR CF'!D11/'QTR P&L'!D2,"") | E11: =IFERROR('QTR CF'!E11/'QTR P&L'!E2,"") | F11: =IFERROR('QTR CF'!F11/'QTR P&L'!F2,"") | G11: =IFERROR('QTR CF'!G11/'QTR P&L'!G2,"") | H11: =IFERROR('QTR CF'!H11/'QTR P&L'!H2,"") | I11: =IFERROR('QTR CF'!I11/'QTR P&L'!I2,"") | ... Q11: =IFERROR('QTR CF'!Q11/'QTR P&L'!Q2,"") | R11: =Q11 | S11: =Q11 | T11: =Q11 | U11: =Q11 | V11: =Q11 | W11: =Q11 | X11: =Q11 | Y11: =Q11 | Z11: =Q11 | AA11: =Q11 | AB11: =Q11 | AC11: =Q11 | AD11: =Q11 | AE11: =Q11 | AF11: =Q11 | AG11: =Q11
A12: (Benefit) Provision for Deferred Income Taxes | B12: ='QTR CF'!B12 | C12: ='QTR CF'!C12 | D12: ='QTR CF'!D12 | E12: ='QTR CF'!E12 | F12: ='QTR CF'!F12 | G12: ='QTR CF'!G12 | H12: ='QTR CF'!H12 | I12: ='QTR CF'!I12 | ... Q12: ='QTR CF'!Q12 | R12: =Q12 | S12: =Q12 | T12: =Q12 | U12: =Q12 | V12: =Q12 | W12: =Q12 | X12: =Q12 | Y12: =Q12 | Z12: =Q12 | AA12: =Q12 | AB12: =Q12 | AC12: =Q12 | AD12: =Q12 | AE12: =Q12 | AF12: =Q12 | AG12: =Q12
A13: Foreign Currency Gain (Loss) | B13: ='QTR CF'!B13 | C13: ='QTR CF'!C13 | D13: ='QTR CF'!D13 | E13: ='QTR CF'!E13 | F13: ='QTR CF'!F13 | G13: ='QTR CF'!G13 | H13: ='QTR CF'!H13 | I13: ='QTR CF'!I13 | ... Q13: ='QTR CF'!Q13 | R13: 0 | S13: 0 | T13: 0 | U13: 0 | V13: 0 | W13: 0 | X13: 0 | Y13: 0 | Z13: 0 | AA13: 0 | AB13: 0 | AC13: 0 | AD13: 0 | AE13: 0 | AF13: 0 | AG13: 0
A14: Gain (Loss) on Lease Cancellations | B14: ='QTR CF'!B14 | C14: ='QTR CF'!C14 | D14: ='QTR CF'!D14 | E14: ='QTR CF'!E14 | F14: ='QTR CF'!F14 | G14: ='QTR CF'!G14 | H14: ='QTR CF'!H14 | I14: ='QTR CF'!I14 | ... Q14: ='QTR CF'!Q14 | R14: 0 | S14: 0 | T14: 0 | U14: 0 | V14: 0 | W14: 0 | X14: 0 | Y14: 0 | Z14: 0 | AA14: 0 | AB14: 0 | AC14: 0 | AD14: 0 | AE14: 0 | AF14: 0 | AG14: 0
A15: Change in Fair Value of Contingent Consideration | B15: ='QTR CF'!B15 | C15: ='QTR CF'!C15 | D15: ='QTR CF'!D15 | E15: ='QTR CF'!E15 | F15: ='QTR CF'!F15 | G15: ='QTR CF'!G15 | H15: ='QTR CF'!H15 | I15: ='QTR CF'!I15 | ... Q15: ='QTR CF'!Q15 | R15: 0 | S15: 0 | T15: 0 | U15: 0 | V15: 0 | W15: 0 | X15: 0 | Y15: 0 | Z15: 0 | AA15: 0 | AB15: 0 | AC15: 0 | AD15: 0 | AE15: 0 | AF15: 0 | AG15: 0
A16: Gain (Loss) on Extinguishment of Debt | B16: ='QTR CF'!B16 | C16: ='QTR CF'!C16 | D16: ='QTR CF'!D16 | E16: ='QTR CF'!E16 | F16: ='QTR CF'!F16 | G16: ='QTR CF'!G16 | H16: ='QTR CF'!H16 | I16: ='QTR CF'!I16 | ... Q16: ='QTR CF'!Q16 | R16: 0 | S16: 0 | T16: 0 | U16: 0 | V16: 0 | W16: 0 | X16: 0 | Y16: 0 | Z16: 0 | AA16: 0 | AB16: 0 | AC16: 0 | AD16: 0 | AE16: 0 | AF16: 0 | AG16: 0
A17: Other Operating Items | B17: ='QTR CF'!B17 | C17: ='QTR CF'!C17 | D17: ='QTR CF'!D17 | E17: ='QTR CF'!E17 | F17: ='QTR CF'!F17 | G17: ='QTR CF'!G17 | H17: ='QTR CF'!H17 | I17: ='QTR CF'!I17 | ... Q17: ='QTR CF'!Q17 | R17: =-('QTR BS'!O5-'QTR BS'!N5)-('QTR BS'!O8-'QTR BS'!N8)-('QTR BS'!O10-'QTR BS'!N10)-('QTR BS'!O12-'QTR BS'!N12)-('QTR BS'!O15-'QTR BS'!N15)-('QTR BS'!O17-'QTR BS'!N17)+('QTR BS'!O22-'QTR BS'!N22)+('QTR BS'!O25-'QTR BS'!N25)+('QTR BS'!O26-'QTR BS'!N26)+('QTR BS'!O27-'QTR BS'!N27)+('QTR BS'!O28-'QTR BS'!N28)+('QTR BS'!O31-'QTR BS'!N31)+('QTR BS'!O32-'QTR BS'!N32)+('QTR BS'!O35-'QTR BS'!N35)+('QTR BS'!O36-'QTR BS'!N36)-('QTR BS'!O3-'QTR BS'!N3)-('QTR BS'!O13-'QTR BS'!N13)-('QTR BS'!O14-'QTR BS'!N14)+('QTR BS'!O23-'QTR BS'!N23)+('QTR BS'!O33-'QTR BS'!N33)+('QTR BS'!O34-'QTR BS'!N34)+('QTR BS'!O39-'QTR BS'!N39)+('QTR BS'!O40-'QTR BS'!N40) | S17: =-('QTR BS'!P5-'QTR BS'!O5)-('QTR BS'!P8-'QTR BS'!O8)-('QTR BS'!P10-'QTR BS'!O10)-('QTR BS'!P12-'QTR BS'!O12)-('QTR BS'!P15-'QTR BS'!O15)-('QTR BS'!P17-'QTR BS'!O17)+('QTR BS'!P22-'QTR BS'!O22)+('QTR BS'!P25-'QTR BS'!O25)+('QTR BS'!P26-'QTR BS'!O26)+('QTR BS'!P27-'QTR BS'!O27)+('QTR BS'!P28-'QTR BS'!O28)+('QTR BS'!P31-'QTR BS'!O31)+('QTR BS'!P32-'QTR BS'!O32)+('QTR BS'!P35-'QTR BS'!O35)+('QTR BS'!P36-'QTR BS'!O36)-('QTR BS'!P3-'QTR BS'!O3)-('QTR BS'!P13-'QTR BS'!O13)-('QTR BS'!P14-'QTR BS'!O14)+('QTR BS'!P23-'QTR BS'!O23)+('QTR BS'!P33-'QTR BS'!O33)+('QTR BS'!P34-'QTR BS'!O34)+('QTR BS'!P39-'QTR BS'!O39)+('QTR BS'!P40-'QTR BS'!O40) | T17: =-('QTR BS'!Q5-'QTR BS'!P5)-('QTR BS'!Q8-'QTR BS'!P8)-('QTR BS'!Q10-'QTR BS'!P10)-('QTR BS'!Q12-'QTR BS'!P12)-('QTR BS'!Q15-'QTR BS'!P15)-('QTR BS'!Q17-'QTR BS'!P17)+('QTR BS'!Q22-'QTR BS'!P22)+('QTR BS'!Q25-'QTR BS'!P25)+('QTR BS'!Q26-'QTR BS'!P26)+('QTR BS'!Q27-'QTR BS'!P27)+('QTR BS'!Q28-'QTR BS'!P28)+('QTR BS'!Q31-'QTR BS'!P31)+('QTR BS'!Q32-'QTR BS'!P32)+('QTR BS'!Q35-'QTR BS'!P35)+('QTR BS'!Q36-'QTR BS'!P36)-('QTR BS'!Q3-'QTR BS'!P3)-('QTR BS'!Q13-'QTR BS'!P13)-('QTR BS'!Q14-'QTR BS'!P14)+('QTR BS'!Q23-'QTR BS'!P23)+('QTR BS'!Q33-'QTR BS'!P33)+('QTR BS'!Q34-'QTR BS'!P34)+('QTR BS'!Q39-'QTR BS'!P39)+('QTR BS'!Q40-'QTR BS'!P40) | U17: =-('QTR BS'!R5-'QTR BS'!Q5)-('QTR BS'!R8-'QTR BS'!Q8)-('QTR BS'!R10-'QTR BS'!Q10)-('QTR BS'!R12-'QTR BS'!Q12)-('QTR BS'!R15-'QTR BS'!Q15)-('QTR BS'!R17-'QTR BS'!Q17)+('QTR BS'!R22-'QTR BS'!Q22)+('QTR BS'!R25-'QTR BS'!Q25)+('QTR BS'!R26-'QTR BS'!Q26)+('QTR BS'!R27-'QTR BS'!Q27)+('QTR BS'!R28-'QTR BS'!Q28)+('QTR BS'!R31-'QTR BS'!Q31)+('QTR BS'!R32-'QTR BS'!Q32)+('QTR BS'!R35-'QTR BS'!Q35)+('QTR BS'!R36-'QTR BS'!Q36)-('QTR BS'!R3-'QTR BS'!Q3)-('QTR BS'!R13-'QTR BS'!Q13)-('QTR BS'!R14-'QTR BS'!Q14)+('QTR BS'!R23-'QTR BS'!Q23)+('QTR BS'!R33-'QTR BS'!Q33)+('QTR BS'!R34-'QTR BS'!Q34)+('QTR BS'!R39-'QTR BS'!Q39)+('QTR BS'!R40-'QTR BS'!Q40) | V17: =-('QTR BS'!S5-'QTR BS'!R5)-('QTR BS'!S8-'QTR BS'!R8)-('QTR BS'!S10-'QTR BS'!R10)-('QTR BS'!S12-'QTR BS'!R12)-('QTR BS'!S15-'QTR BS'!R15)-('QTR BS'!S17-'QTR BS'!R17)+('QTR BS'!S22-'QTR BS'!R22)+('QTR BS'!S25-'QTR BS'!R25)+('QTR BS'!S26-'QTR BS'!R26)+('QTR BS'!S27-'QTR BS'!R27)+('QTR BS'!S28-'QTR BS'!R28)+('QTR BS'!S31-'QTR BS'!R31)+('QTR BS'!S32-'QTR BS'!R32)+('QTR BS'!S35-'QTR BS'!R35)+('QTR BS'!S36-'QTR BS'!R36)-('QTR BS'!S3-'QTR BS'!R3)-('QTR BS'!S13-'QTR BS'!R13)-('QTR BS'!S14-'QTR BS'!R14)+('QTR BS'!S23-'QTR BS'!R23)+('QTR BS'!S33-'QTR BS'!R33)+('QTR BS'!S34-'QTR BS'!R34)+('QTR BS'!S39-'QTR BS'!R39)+('QTR BS'!S40-'QTR BS'!R40) | W17: =-('QTR BS'!T5-'QTR BS'!S5)-('QTR BS'!T8-'QTR BS'!S8)-('QTR BS'!T10-'QTR BS'!S10)-('QTR BS'!T12-'QTR BS'!S12)-('QTR BS'!T15-'QTR BS'!S15)-('QTR BS'!T17-'QTR BS'!S17)+('QTR BS'!T22-'QTR BS'!S22)+('QTR BS'!T25-'QTR BS'!S25)+('QTR BS'!T26-'QTR BS'!S26)+('QTR BS'!T27-'QTR BS'!S27)+('QTR BS'!T28-'QTR BS'!S28)+('QTR BS'!T31-'QTR BS'!S31)+('QTR BS'!T32-'QTR BS'!S32)+('QTR BS'!T35-'QTR BS'!S35)+('QTR BS'!T36-'QTR BS'!S36)-('QTR BS'!T3-'QTR BS'!S3)-('QTR BS'!T13-'QTR BS'!S13)-('QTR BS'!T14-'QTR BS'!S14)+('QTR BS'!T23-'QTR BS'!S23)+('QTR BS'!T33-'QTR BS'!S33)+('QTR BS'!T34-'QTR BS'!S34)+('QTR BS'!T39-'QTR BS'!S39)+('QTR BS'!T40-'QTR BS'!S40) | X17: =-('QTR BS'!U5-'QTR BS'!T5)-('QTR BS'!U8-'QTR BS'!T8)-('QTR BS'!U10-'QTR BS'!T10)-('QTR BS'!U12-'QTR BS'!T12)-('QTR BS'!U15-'QTR BS'!T15)-('QTR BS'!U17-'QTR BS'!T17)+('QTR BS'!U22-'QTR BS'!T22)+('QTR BS'!U25-'QTR BS'!T25)+('QTR BS'!U26-'QTR BS'!T26)+('QTR BS'!U27-'QTR BS'!T27)+('QTR BS'!U28-'QTR BS'!T28)+('QTR BS'!U31-'QTR BS'!T31)+('QTR BS'!U32-'QTR BS'!T32)+('QTR BS'!U35-'QTR BS'!T35)+('QTR BS'!U36-'QTR BS'!T36)-('QTR BS'!U3-'QTR BS'!T3)-('QTR BS'!U13-'QTR BS'!T13)-('QTR BS'!U14-'QTR BS'!T14)+('QTR BS'!U23-'QTR BS'!T23)+('QTR BS'!U33-'QTR BS'!T33)+('QTR BS'!U34-'QTR BS'!T34)+('QTR BS'!U39-'QTR BS'!T39)+('QTR BS'!U40-'QTR BS'!T40) | Y17: =-('QTR BS'!V5-'QTR BS'!U5)-('QTR BS'!V8-'QTR BS'!U8)-('QTR BS'!V10-'QTR BS'!U10)-('QTR BS'!V12-'QTR BS'!U12)-('QTR BS'!V15-'QTR BS'!U15)-('QTR BS'!V17-'QTR BS'!U17)+('QTR BS'!V22-'QTR BS'!U22)+('QTR BS'!V25-'QTR BS'!U25)+('QTR BS'!V26-'QTR BS'!U26)+('QTR BS'!V27-'QTR BS'!U27)+('QTR BS'!V28-'QTR BS'!U28)+('QTR BS'!V31-'QTR BS'!U31)+('QTR BS'!V32-'QTR BS'!U32)+('QTR BS'!V35-'QTR BS'!U35)+('QTR BS'!V36-'QTR BS'!U36)-('QTR BS'!V3-'QTR BS'!U3)-('QTR BS'!V13-'QTR BS'!U13)-('QTR BS'!V14-'QTR BS'!U14)+('QTR BS'!V23-'QTR BS'!U23)+('QTR BS'!V33-'QTR BS'!U33)+('QTR BS'!V34-'QTR BS'!U34)+('QTR BS'!V39-'QTR BS'!U39)+('QTR BS'!V40-'QTR BS'!U40) | ... AG17: =-('QTR BS'!AD5-'QTR BS'!AC5)-('QTR BS'!AD8-'QTR BS'!AC8)-('QTR BS'!AD10-'QTR BS'!AC10)-('QTR BS'!AD12-'QTR BS'!AC12)-('QTR BS'!AD15-'QTR BS'!AC15)-('QTR BS'!AD17-'QTR BS'!AC17)+('QTR BS'!AD22-'QTR BS'!AC22)+('QTR BS'!AD25-'QTR BS'!AC25)+('QTR BS'!AD26-'QTR BS'!AC26)+('QTR BS'!AD27-'QTR BS'!AC27)+('QTR BS'!AD28-'QTR BS'!AC28)+('QTR BS'!AD31-'QTR BS'!AC31)+('QTR BS'!AD32-'QTR BS'!AC32)+('QTR BS'!AD35-'QTR BS'!AC35)+('QTR BS'!AD36-'QTR BS'!AC36)-('QTR BS'!AD3-'QTR BS'!AC3)-('QTR BS'!AD13-'QTR BS'!AC13)-('QTR BS'!AD14-'QTR BS'!AC14)+('QTR BS'!AD23-'QTR BS'!AC23)+('QTR BS'!AD33-'QTR BS'!AC33)+('QTR BS'!AD34-'QTR BS'!AC34)+('QTR BS'!AD39-'QTR BS'!AC39)+('QTR BS'!AD40-'QTR BS'!AC40)
A18: Accounts Receivable | B18: ='QTR CF'!B18 | C18: ='QTR CF'!C18 | D18: ='QTR CF'!D18 | E18: ='QTR CF'!E18 | F18: ='QTR CF'!F18 | G18: ='QTR CF'!G18 | H18: ='QTR CF'!H18 | I18: ='QTR CF'!I18 | ... Q18: ='QTR CF'!Q18 | R18: =-('QTR BS'!O4-'QTR BS'!N4) | S18: =-('QTR BS'!P4-'QTR BS'!O4) | T18: =-('QTR BS'!Q4-'QTR BS'!P4) | U18: =-('QTR BS'!R4-'QTR BS'!Q4) | V18: =-('QTR BS'!S4-'QTR BS'!R4) | W18: =-('QTR BS'!T4-'QTR BS'!S4) | X18: =-('QTR BS'!U4-'QTR BS'!T4) | Y18: =-('QTR BS'!V4-'QTR BS'!U4) | ... AG18: =-('QTR BS'!AD4-'QTR BS'!AC4)
A19: Note Receivable | B19: ='QTR CF'!B19 | C19: ='QTR CF'!C19 | D19: ='QTR CF'!D19 | E19: ='QTR CF'!E19 | F19: ='QTR CF'!F19 | G19: ='QTR CF'!G19 | H19: ='QTR CF'!H19 | I19: ='QTR CF'!I19 | ... Q19: ='QTR CF'!Q19 | R19: 0 | S19: 0 | T19: 0 | U19: 0 | V19: 0 | W19: 0 | X19: 0 | Y19: 0 | Z19: 0 | AA19: 0 | AB19: 0 | AC19: 0 | AD19: 0 | AE19: 0 | AF19: 0 | AG19: 0
A20: Inventories | B20: ='QTR CF'!B20 | C20: ='QTR CF'!C20 | D20: ='QTR CF'!D20 | E20: ='QTR CF'!E20 | F20: ='QTR CF'!F20 | G20: ='QTR CF'!G20 | H20: ='QTR CF'!H20 | I20: ='QTR CF'!I20 | ... Q20: ='QTR CF'!Q20 | R20: =-('QTR BS'!O6-'QTR BS'!N6) | S20: =-('QTR BS'!P6-'QTR BS'!O6) | T20: =-('QTR BS'!Q6-'QTR BS'!P6) | U20: =-('QTR BS'!R6-'QTR BS'!Q6) | V20: =-('QTR BS'!S6-'QTR BS'!R6) | W20: =-('QTR BS'!T6-'QTR BS'!S6) | X20: =-('QTR BS'!U6-'QTR BS'!T6) | Y20: =-('QTR BS'!V6-'QTR BS'!U6) | ... AG20: =-('QTR BS'!AD6-'QTR BS'!AC6)
A21: Prepaid Expenses | B21: ='QTR CF'!B21 | C21: ='QTR CF'!C21 | D21: ='QTR CF'!D21 | E21: ='QTR CF'!E21 | F21: ='QTR CF'!F21 | G21: ='QTR CF'!G21 | H21: ='QTR CF'!H21 | I21: ='QTR CF'!I21 | ... Q21: ='QTR CF'!Q21 | R21: =-('QTR BS'!O7-'QTR BS'!N7) | S21: =-('QTR BS'!P7-'QTR BS'!O7) | T21: =-('QTR BS'!Q7-'QTR BS'!P7) | U21: =-('QTR BS'!R7-'QTR BS'!Q7) | V21: =-('QTR BS'!S7-'QTR BS'!R7) | W21: =-('QTR BS'!T7-'QTR BS'!S7) | X21: =-('QTR BS'!U7-'QTR BS'!T7) | Y21: =-('QTR BS'!V7-'QTR BS'!U7) | ... AG21: =-('QTR BS'!AD7-'QTR BS'!AC7)
A22: Change in A/P and Accrued (legacy) | B22: ='QTR CF'!B22 | C22: ='QTR CF'!C22 | D22: ='QTR CF'!D22 | E22: ='QTR CF'!E22 | F22: ='QTR CF'!F22 | G22: ='QTR CF'!G22 | H22: ='QTR CF'!H22 | I22: ='QTR CF'!I22 | ... Q22: ='QTR CF'!Q22 | R22: 0 | S22: 0 | T22: 0 | U22: 0 | V22: 0 | W22: 0 | X22: 0 | Y22: 0 | Z22: 0 | AA22: 0 | AB22: 0 | AC22: 0 | AD22: 0 | AE22: 0 | AF22: 0 | AG22: 0
A23: Other Non-Current Assets | B23: ='QTR CF'!B23 | C23: ='QTR CF'!C23 | D23: ='QTR CF'!D23 | E23: ='QTR CF'!E23 | F23: ='QTR CF'!F23 | G23: ='QTR CF'!G23 | H23: ='QTR CF'!H23 | I23: ='QTR CF'!I23 | ... Q23: ='QTR CF'!Q23 | R23: =-('QTR BS'!O18-'QTR BS'!N18) | S23: =-('QTR BS'!P18-'QTR BS'!O18) | T23: =-('QTR BS'!Q18-'QTR BS'!P18) | U23: =-('QTR BS'!R18-'QTR BS'!Q18) | V23: =-('QTR BS'!S18-'QTR BS'!R18) | W23: =-('QTR BS'!T18-'QTR BS'!S18) | X23: =-('QTR BS'!U18-'QTR BS'!T18) | Y23: =-('QTR BS'!V18-'QTR BS'!U18) | ... AG23: =-('QTR BS'!AD18-'QTR BS'!AC18)
A24: Accounts Payable | B24: ='QTR CF'!B24 | C24: ='QTR CF'!C24 | D24: ='QTR CF'!D24 | E24: ='QTR CF'!E24 | F24: ='QTR CF'!F24 | G24: ='QTR CF'!G24 | H24: ='QTR CF'!H24 | I24: ='QTR CF'!I24 | ... Q24: ='QTR CF'!Q24 | R24: =('QTR BS'!O20-'QTR BS'!N20) | S24: =('QTR BS'!P20-'QTR BS'!O20) | T24: =('QTR BS'!Q20-'QTR BS'!P20) | U24: =('QTR BS'!R20-'QTR BS'!Q20) | V24: =('QTR BS'!S20-'QTR BS'!R20) | W24: =('QTR BS'!T20-'QTR BS'!S20) | X24: =('QTR BS'!U20-'QTR BS'!T20) | Y24: =('QTR BS'!V20-'QTR BS'!U20) | ... AG24: =('QTR BS'!AD20-'QTR BS'!AC20)
A25: Accrued Expenses | B25: ='QTR CF'!B25 | C25: ='QTR CF'!C25 | D25: ='QTR CF'!D25 | E25: ='QTR CF'!E25 | F25: ='QTR CF'!F25 | G25: ='QTR CF'!G25 | H25: ='QTR CF'!H25 | I25: ='QTR CF'!I25 | ... Q25: ='QTR CF'!Q25 | R25: =('QTR BS'!O21-'QTR BS'!N21) | S25: =('QTR BS'!P21-'QTR BS'!O21) | T25: =('QTR BS'!Q21-'QTR BS'!P21) | U25: =('QTR BS'!R21-'QTR BS'!Q21) | V25: =('QTR BS'!S21-'QTR BS'!R21) | W25: =('QTR BS'!T21-'QTR BS'!S21) | X25: =('QTR BS'!U21-'QTR BS'!T21) | Y25: =('QTR BS'!V21-'QTR BS'!U21) | ... AG25: =('QTR BS'!AD21-'QTR BS'!AC21)
A26: Other Current Liabilities | B26: ='QTR CF'!B26 | C26: ='QTR CF'!C26 | D26: ='QTR CF'!D26 | E26: ='QTR CF'!E26 | F26: ='QTR CF'!F26 | G26: ='QTR CF'!G26 | H26: ='QTR CF'!H26 | I26: ='QTR CF'!I26 | ... Q26: ='QTR CF'!Q26 | R26: =('QTR BS'!O29-'QTR BS'!N29) | S26: =('QTR BS'!P29-'QTR BS'!O29) | T26: =('QTR BS'!Q29-'QTR BS'!P29) | U26: =('QTR BS'!R29-'QTR BS'!Q29) | V26: =('QTR BS'!S29-'QTR BS'!R29) | W26: =('QTR BS'!T29-'QTR BS'!S29) | X26: =('QTR BS'!U29-'QTR BS'!T29) | Y26: =('QTR BS'!V29-'QTR BS'!U29) | ... AG26: =('QTR BS'!AD29-'QTR BS'!AC29)
A27: Accrued Promotional Allowance | B27: ='QTR CF'!B27 | C27: ='QTR CF'!C27 | D27: ='QTR CF'!D27 | E27: ='QTR CF'!E27 | F27: ='QTR CF'!F27 | G27: ='QTR CF'!G27 | H27: ='QTR CF'!H27 | I27: ='QTR CF'!I27 | ... Q27: ='QTR CF'!Q27 | R27: =('QTR BS'!O24-'QTR BS'!N24) | S27: =('QTR BS'!P24-'QTR BS'!O24) | T27: =('QTR BS'!Q24-'QTR BS'!P24) | U27: =('QTR BS'!R24-'QTR BS'!Q24) | V27: =('QTR BS'!S24-'QTR BS'!R24) | W27: =('QTR BS'!T24-'QTR BS'!S24) | X27: =('QTR BS'!U24-'QTR BS'!T24) | Y27: =('QTR BS'!V24-'QTR BS'!U24) | ... AG27: =('QTR BS'!AD24-'QTR BS'!AC24)
A28: Accrued Distributor Termination | B28: ='QTR CF'!B28 | C28: ='QTR CF'!C28 | D28: ='QTR CF'!D28 | E28: ='QTR CF'!E28 | F28: ='QTR CF'!F28 | G28: ='QTR CF'!G28 | H28: ='QTR CF'!H28 | I28: ='QTR CF'!I28 | ... Q28: ='QTR CF'!Q28 | R28: 0 | S28: 0 | T28: 0 | U28: 0 | V28: 0 | W28: 0 | X28: 0 | Y28: 0 | Z28: 0 | AA28: 0 | AB28: 0 | AC28: 0 | AD28: 0 | AE28: 0 | AF28: 0 | AG28: 0
A29: ROU & Lease Liability, Net | B29: ='QTR CF'!B29 | C29: ='QTR CF'!C29 | D29: ='QTR CF'!D29 | E29: ='QTR CF'!E29 | F29: ='QTR CF'!F29 | G29: ='QTR CF'!G29 | H29: ='QTR CF'!H29 | I29: ='QTR CF'!I29 | ... Q29: ='QTR CF'!Q29 | R29: 0 | S29: 0 | T29: 0 | U29: 0 | V29: 0 | W29: 0 | X29: 0 | Y29: 0 | Z29: 0 | AA29: 0 | AB29: 0 | AC29: 0 | AD29: 0 | AE29: 0 | AF29: 0 | AG29: 0
A30: Deferred Revenue | B30: ='QTR CF'!B30 | C30: ='QTR CF'!C30 | D30: ='QTR CF'!D30 | E30: ='QTR CF'!E30 | F30: ='QTR CF'!F30 | G30: ='QTR CF'!G30 | H30: ='QTR CF'!H30 | I30: ='QTR CF'!I30 | ... Q30: ='QTR CF'!Q30 | R30: 0 | S30: 0 | T30: 0 | U30: 0 | V30: 0 | W30: 0 | X30: 0 | Y30: 0 | Z30: 0 | AA30: 0 | AB30: 0 | AC30: 0 | AD30: 0 | AE30: 0 | AF30: 0 | AG30: 0
A31: Net Change in Other Working Capital | B31: ='QTR CF'!B31 | C31: ='QTR CF'!C31 | D31: ='QTR CF'!D31 | E31: ='QTR CF'!E31 | F31: ='QTR CF'!F31 | G31: ='QTR CF'!G31 | H31: ='QTR CF'!H31 | I31: ='QTR CF'!I31 | ... Q31: ='QTR CF'!Q31 | R31: 0 | S31: 0 | T31: 0 | U31: 0 | V31: 0 | W31: 0 | X31: 0 | Y31: 0 | Z31: 0 | AA31: 0 | AB31: 0 | AC31: 0 | AD31: 0 | AE31: 0 | AF31: 0 | AG31: 0
A32: Collections from Note Receivable | B32: ='QTR CF'!B33 | C32: ='QTR CF'!C33 | D32: ='QTR CF'!D33 | E32: ='QTR CF'!E33 | F32: ='QTR CF'!F33 | G32: ='QTR CF'!G33 | H32: ='QTR CF'!H33 | I32: ='QTR CF'!I33 | ... Q32: ='QTR CF'!Q33 | R32: 0 | S32: 0 | T32: 0 | U32: 0 | V32: 0 | W32: 0 | X32: 0 | Y32: 0 | Z32: 0 | AA32: 0 | AB32: 0 | AC32: 0 | AD32: 0 | AE32: 0 | AF32: 0 | AG32: 0
A33: Purchase of PP&E — % of Revenue | B33: =IFERROR('QTR CF'!B34/'QTR P&L'!B2,"") | C33: =IFERROR('QTR CF'!C34/'QTR P&L'!C2,"") | D33: =IFERROR('QTR CF'!D34/'QTR P&L'!D2,"") | E33: =IFERROR('QTR CF'!E34/'QTR P&L'!E2,"") | F33: =IFERROR('QTR CF'!F34/'QTR P&L'!F2,"") | G33: =IFERROR('QTR CF'!G34/'QTR P&L'!G2,"") | H33: =IFERROR('QTR CF'!H34/'QTR P&L'!H2,"") | I33: =IFERROR('QTR CF'!I34/'QTR P&L'!I2,"") | ... Q33: =IFERROR('QTR CF'!Q34/'QTR P&L'!Q2,"") | R33: =Q33 | S33: =Q33 | T33: =Q33 | U33: =Q33 | V33: =Q33 | W33: =Q33 | X33: =Q33 | Y33: =Q33 | Z33: =Q33 | AA33: =Q33 | AB33: =Q33 | AC33: =Q33 | AD33: =Q33 | AE33: =Q33 | AF33: =Q33 | AG33: =Q33
A34: Purchase of Non-Marketable Equity Securities | B34: ='QTR CF'!B35 | C34: ='QTR CF'!C35 | D34: ='QTR CF'!D35 | E34: ='QTR CF'!E35 | F34: ='QTR CF'!F35 | G34: ='QTR CF'!G35 | H34: ='QTR CF'!H35 | I34: ='QTR CF'!I35 | ... Q34: ='QTR CF'!Q35 | R34: 0 | S34: 0 | T34: 0 | U34: 0 | V34: 0 | W34: 0 | X34: 0 | Y34: 0 | Z34: 0 | AA34: 0 | AB34: 0 | AC34: 0 | AD34: 0 | AE34: 0 | AF34: 0 | AG34: 0
A35: Acquisition of Big Beverages | B35: ='QTR CF'!B36 | C35: ='QTR CF'!C36 | D35: ='QTR CF'!D36 | E35: ='QTR CF'!E36 | F35: ='QTR CF'!F36 | G35: ='QTR CF'!G36 | H35: ='QTR CF'!H36 | I35: ='QTR CF'!I36 | ... Q35: ='QTR CF'!Q36 | R35: 0 | S35: 0 | T35: 0 | U35: 0 | V35: 0 | W35: 0 | X35: 0 | Y35: 0 | Z35: 0 | AA35: 0 | AB35: 0 | AC35: 0 | AD35: 0 | AE35: 0 | AF35: 0 | AG35: 0
A36: Acquisitions, Net of Cash Acquired | B36: ='QTR CF'!B37 | C36: ='QTR CF'!C37 | D36: ='QTR CF'!D37 | E36: ='QTR CF'!E37 | F36: ='QTR CF'!F37 | G36: ='QTR CF'!G37 | H36: ='QTR CF'!H37 | I36: ='QTR CF'!I37 | ... Q36: ='QTR CF'!Q37 | R36: 0 | S36: 0 | T36: 0 | U36: 0 | V36: 0 | W36: 0 | X36: 0 | Y36: 0 | Z36: 0 | AA36: 0 | AB36: 0 | AC36: 0 | AD36: 0 | AE36: 0 | AF36: 0 | AG36: 0
A37: Working Capital Estimate from Pepsi (Rockstar) | B37: ='QTR CF'!B38 | C37: ='QTR CF'!C38 | D37: ='QTR CF'!D38 | E37: ='QTR CF'!E38 | F37: ='QTR CF'!F38 | G37: ='QTR CF'!G38 | H37: ='QTR CF'!H38 | I37: ='QTR CF'!I38 | ... Q37: ='QTR CF'!Q38 | R37: 0 | S37: 0 | T37: 0 | U37: 0 | V37: 0 | W37: 0 | X37: 0 | Y37: 0 | Z37: 0 | AA37: 0 | AB37: 0 | AC37: 0 | AD37: 0 | AE37: 0 | AF37: 0 | AG37: 0
A38: Finance Lease Payments | B38: ='QTR CF'!B40 | C38: ='QTR CF'!C40 | D38: ='QTR CF'!D40 | E38: ='QTR CF'!E40 | F38: ='QTR CF'!F40 | G38: ='QTR CF'!G40 | H38: ='QTR CF'!H40 | I38: ='QTR CF'!I40 | ... Q38: ='QTR CF'!Q40 | R38: 0 | S38: 0 | T38: 0 | U38: 0 | V38: 0 | W38: 0 | X38: 0 | Y38: 0 | Z38: 0 | AA38: 0 | AB38: 0 | AC38: 0 | AD38: 0 | AE38: 0 | AF38: 0 | AG38: 0
A39: Proceeds from Exercise of Stock Options | B39: ='QTR CF'!B41 | C39: ='QTR CF'!C41 | D39: ='QTR CF'!D41 | E39: ='QTR CF'!E41 | F39: ='QTR CF'!F41 | G39: ='QTR CF'!G41 | H39: ='QTR CF'!H41 | I39: ='QTR CF'!I41 | ... Q39: ='QTR CF'!Q41 | R39: 0 | S39: 0 | T39: 0 | U39: 0 | V39: 0 | W39: 0 | X39: 0 | Y39: 0 | Z39: 0 | AA39: 0 | AB39: 0 | AC39: 0 | AD39: 0 | AE39: 0 | AF39: 0 | AG39: 0
A40: Proceeds from Issuance of Common Stock | B40: ='QTR CF'!B42 | C40: ='QTR CF'!C42 | D40: ='QTR CF'!D42 | E40: ='QTR CF'!E42 | F40: ='QTR CF'!F42 | G40: ='QTR CF'!G42 | H40: ='QTR CF'!H42 | I40: ='QTR CF'!I42 | ... Q40: ='QTR CF'!Q42 | R40: 0 | S40: 0 | T40: 0 | U40: 0 | V40: 0 | W40: 0 | X40: 0 | Y40: 0 | Z40: 0 | AA40: 0 | AB40: 0 | AC40: 0 | AD40: 0 | AE40: 0 | AF40: 0 | AG40: 0
A41: Proceeds from Issuance of Preferred Stock | B41: ='QTR CF'!B43 | C41: ='QTR CF'!C43 | D41: ='QTR CF'!D43 | E41: ='QTR CF'!E43 | F41: ='QTR CF'!F43 | G41: ='QTR CF'!G43 | H41: ='QTR CF'!H43 | I41: ='QTR CF'!I43 | ... Q41: ='QTR CF'!Q43 | R41: 0 | S41: 0 | T41: 0 | U41: 0 | V41: 0 | W41: 0 | X41: 0 | Y41: 0 | Z41: 0 | AA41: 0 | AB41: 0 | AC41: 0 | AD41: 0 | AE41: 0 | AF41: 0 | AG41: 0
A42: Preferred Dividends | B42: ='QTR CF'!B44 | C42: ='QTR CF'!C44 | D42: ='QTR CF'!D44 | E42: ='QTR CF'!E44 | F42: ='QTR CF'!F44 | G42: ='QTR CF'!G44 | H42: ='QTR CF'!H44 | I42: ='QTR CF'!I44 | ... Q42: ='QTR CF'!Q44 | R42: =Q42 | S42: =Q42 | T42: =Q42 | U42: =Q42 | V42: =Q42 | W42: =Q42 | X42: =Q42 | Y42: =Q42 | Z42: =Q42 | AA42: =Q42 | AB42: =Q42 | AC42: =Q42 | AD42: =Q42 | AE42: =Q42 | AF42: =Q42 | AG42: =Q42
A43: Share Repurchases | B43: ='QTR CF'!B45 | C43: ='QTR CF'!C45 | D43: ='QTR CF'!D45 | E43: ='QTR CF'!E45 | F43: ='QTR CF'!F45 | G43: ='QTR CF'!G45 | H43: ='QTR CF'!H45 | I43: ='QTR CF'!I45 | ... Q43: ='QTR CF'!Q45 | R43: 0 | S43: 0 | T43: 0 | U43: 0 | V43: 0 | W43: 0 | X43: 0 | Y43: 0 | Z43: 0 | AA43: 0 | AB43: 0 | AC43: 0 | AD43: 0 | AE43: 0 | AF43: 0 | AG43: 0
A44: Proceeds from Issuance of Long-Term Debt | B44: ='QTR CF'!B46 | C44: ='QTR CF'!C46 | D44: ='QTR CF'!D46 | E44: ='QTR CF'!E46 | F44: ='QTR CF'!F46 | G44: ='QTR CF'!G46 | H44: ='QTR CF'!H46 | I44: ='QTR CF'!I46 | ... Q44: ='QTR CF'!Q46 | R44: 0 | S44: 0 | T44: 0 | U44: 0 | V44: 0 | W44: 0 | X44: 0 | Y44: 0 | Z44: 0 | AA44: 0 | AB44: 0 | AC44: 0 | AD44: 0 | AE44: 0 | AF44: 0 | AG44: 0
A45: Repayments of Long-Term Debt | B45: ='QTR CF'!B47 | C45: ='QTR CF'!C47 | D45: ='QTR CF'!D47 | E45: ='QTR CF'!E47 | F45: ='QTR CF'!F47 | G45: ='QTR CF'!G47 | H45: ='QTR CF'!H47 | I45: ='QTR CF'!I47 | ... Q45: ='QTR CF'!Q47 | R45: 0 | S45: 0 | T45: 0 | U45: 0 | V45: 0 | W45: 0 | X45: 0 | Y45: 0 | Z45: 0 | AA45: 0 | AB45: 0 | AC45: 0 | AD45: 0 | AE45: 0 | AF45: 0 | AG45: 0
A46: Debt Issuance Fees | B46: ='QTR CF'!B48 | C46: ='QTR CF'!C48 | D46: ='QTR CF'!D48 | E46: ='QTR CF'!E48 | F46: ='QTR CF'!F48 | G46: ='QTR CF'!G48 | H46: ='QTR CF'!H48 | I46: ='QTR CF'!I48 | ... Q46: ='QTR CF'!Q48 | R46: 0 | S46: 0 | T46: 0 | U46: 0 | V46: 0 | W46: 0 | X46: 0 | Y46: 0 | Z46: 0 | AA46: 0 | AB46: 0 | AC46: 0 | AD46: 0 | AE46: 0 | AF46: 0 | AG46: 0
A47: Other Financing Activities | B47: ='QTR CF'!B49 | C47: ='QTR CF'!C49 | D47: ='QTR CF'!D49 | E47: ='QTR CF'!E49 | F47: ='QTR CF'!F49 | G47: ='QTR CF'!G49 | H47: ='QTR CF'!H49 | I47: ='QTR CF'!I49 | ... Q47: ='QTR CF'!Q49 | R47: 0 | S47: 0 | T47: 0 | U47: 0 | V47: 0 | W47: 0 | X47: 0 | Y47: 0 | Z47: 0 | AA47: 0 | AB47: 0 | AC47: 0 | AD47: 0 | AE47: 0 | AF47: 0 | AG47: 0
A48: FX Effect on Cash | B48: ='QTR CF'!B51 | C48: ='QTR CF'!C51 | D48: ='QTR CF'!D51 | E48: ='QTR CF'!E51 | F48: ='QTR CF'!F51 | G48: ='QTR CF'!G51 | H48: ='QTR CF'!H51 | I48: ='QTR CF'!I51 | ... Q48: ='QTR CF'!Q51 | R48: =Q48 | S48: =Q48 | T48: =Q48 | U48: =Q48 | V48: =Q48 | W48: =Q48 | X48: =Q48 | Y48: =Q48 | Z48: =Q48 | AA48: =Q48 | AB48: =Q48 | AC48: =Q48 | AD48: =Q48 | AE48: =Q48 | AF48: =Q48 | AG48: =Q48
