Workbook

Sheet ASSUMPTIONS
A1: Assumption | B1: Value | C1: Note
A2: Days in Quarter | B2: 91 | C2: Used by DSO/DIO/DPO ratios. Approximation; varies 89-92 by quarter.

Sheet ANNL P&L
B1: FY2019 | C1: FY2020 | D1: FY2021 | E1: FY2022 | F1: FY2023 | G1: FY2024 | H1: FY2025 | I1: FY2026E | J1: FY2027E | K1: FY2028E | L1: FY2029E | M1: FY2030E | N1: FY2031E
A2: Net Sales / Revenue | B2: 75146.546 | C2: 130725.78 | D2: 314271.56 | E2: 653604 | F2: 1318014 | G2: 1355630 | H2: 2515269 | I2: ='QTR P&L'!AD2+'QTR P&L'!AE2+'QTR P&L'!AF2+'QTR P&L'!AG2 | J2: ='QTR P&L'!AH2+'QTR P&L'!AI2+'QTR P&L'!AJ2+'QTR P&L'!AK2 | K2: ='QTR P&L'!AL2+'QTR P&L'!AM2+'QTR P&L'!AN2+'QTR P&L'!AO2 | L2: ='QTR P&L'!AP2+'QTR P&L'!AQ2+'QTR P&L'!AR2+'QTR P&L'!AS2 | M2: ='QTR P&L'!AT2+'QTR P&L'!AU2+'QTR P&L'!AV2+'QTR P&L'!AW2
A3: COGS | B3: -43844.733 | C3: -69752.032 | D3: -186103.04 | E3: -382735 | F3: -684875 | G3: -675423 | H3: -1247936 | I3: ='QTR P&L'!AD3+'QTR P&L'!AE3+'QTR P&L'!AF3+'QTR P&L'!AG3 | J3: ='QTR P&L'!AH3+'QTR P&L'!AI3+'QTR P&L'!AJ3+'QTR P&L'!AK3 | K3: ='QTR P&L'!AL3+'QTR P&L'!AM3+'QTR P&L'!AN3+'QTR P&L'!AO3 | L3: ='QTR P&L'!AP3+'QTR P&L'!AQ3+'QTR P&L'!AR3+'QTR P&L'!AS3 | M3: ='QTR P&L'!AT3+'QTR P&L'!AU3+'QTR P&L'!AV3+'QTR P&L'!AW3
A4: Gross Profit (Loss) | B4: =B2+B3 | C4: =C2+C3 | D4: =D2+D3 | E4: =E2+E3 | F4: =F2+F3 | G4: =G2+G3 | H4: =H2+H3 | I4: =I2+I3 | ... N4: =N2+N3
A5: Sales and Marketing | B5: -21129.722 | C5: -34875.339 | D5: -74738.295 | E5: 0 | F5: 0 | G5: 0 | H5: 0 | I5: ='QTR P&L'!AD5+'QTR P&L'!AE5+'QTR P&L'!AF5+'QTR P&L'!AG5 | J5: ='QTR P&L'!AH5+'QTR P&L'!AI5+'QTR P&L'!AJ5+'QTR P&L'!AK5 | K5: ='QTR P&L'!AL5+'QTR P&L'!AM5+'QTR P&L'!AN5+'QTR P&L'!AO5 | L5: ='QTR P&L'!AP5+'QTR P&L'!AQ5+'QTR P&L'!AR5+'QTR P&L'!AS5 | M5: ='QTR P&L'!AT5+'QTR P&L'!AU5+'QTR P&L'!AV5+'QTR P&L'!AW5
A6: General and Administrative | B6: -11620.534 | C6: -18187.406 | D6: -57519.745 | E6: 0 | F6: 0 | G6: 0 | H6: 0 | I6: ='QTR P&L'!AD6+'QTR P&L'!AE6+'QTR P&L'!AF6+'QTR P&L'!AG6 | J6: ='QTR P&L'!AH6+'QTR P&L'!AI6+'QTR P&L'!AJ6+'QTR P&L'!AK6 | K6: ='QTR P&L'!AL6+'QTR P&L'!AM6+'QTR P&L'!AN6+'QTR P&L'!AO6 | L6: ='QTR P&L'!AP6+'QTR P&L'!AQ6+'QTR P&L'!AR6+'QTR P&L'!AS6 | M6: ='QTR P&L'!AT6+'QTR P&L'!AU6+'QTR P&L'!AV6+'QTR P&L'!AW6
A7: Operating Expenses | B7: -32750.256 | C7: -53062.745 | D7: -132258.04 | E7: 0 | F7: 0 | G7: 0 | H7: 0 | I7: ='QTR P&L'!AD7+'QTR P&L'!AE7+'QTR P&L'!AF7+'QTR P&L'!AG7 | J7: ='QTR P&L'!AH7+'QTR P&L'!AI7+'QTR P&L'!AJ7+'QTR P&L'!AK7 | K7: ='QTR P&L'!AL7+'QTR P&L'!AM7+'QTR P&L'!AN7+'QTR P&L'!AO7 | L7: ='QTR P&L'!AP7+'QTR P&L'!AQ7+'QTR P&L'!AR7+'QTR P&L'!AS7 | M7: ='QTR P&L'!AT7+'QTR P&L'!AU7+'QTR P&L'!AV7+'QTR P&L'!AW7
A8: SG&A | B8: 0 | C8: 0 | D8: 0 | E8: -428670 | F8: -366773 | G8: -524479 | H8: -798810 | I8: ='QTR P&L'!AD8+'QTR P&L'!AE8+'QTR P&L'!AF8+'QTR P&L'!AG8 | J8: ='QTR P&L'!AH8+'QTR P&L'!AI8+'QTR P&L'!AJ8+'QTR P&L'!AK8 | K8: ='QTR P&L'!AL8+'QTR P&L'!AM8+'QTR P&L'!AN8+'QTR P&L'!AO8 | L8: ='QTR P&L'!AP8+'QTR P&L'!AQ8+'QTR P&L'!AR8+'QTR P&L'!AS8 | M8: ='QTR P&L'!AT8+'QTR P&L'!AU8+'QTR P&L'!AV8+'QTR P&L'!AW8
A9: Distributor Termination Fees | B9: 0 | C9: 0 | D9: 0 | E9: 0 | F9: 0 | G9: 0 | H9: -327461 | I9: ='QTR P&L'!AD9+'QTR P&L'!AE9+'QTR P&L'!AF9+'QTR P&L'!AG9 | J9: ='QTR P&L'!AH9+'QTR P&L'!AI9+'QTR P&L'!AJ9+'QTR P&L'!AK9 | K9: ='QTR P&L'!AL9+'QTR P&L'!AM9+'QTR P&L'!AN9+'QTR P&L'!AO9 | L9: ='QTR P&L'!AP9+'QTR P&L'!AQ9+'QTR P&L'!AR9+'QTR P&L'!AS9 | M9: ='QTR P&L'!AT9+'QTR P&L'!AU9+'QTR P&L'!AV9+'QTR P&L'!AW9
A10: Income (Loss) from Operations | B10: =B4+SUM(B5:B9) | C10: =C4+SUM(C5:C9) | D10: =D4+SUM(D5:D9) | E10: =E4+SUM(E5:E9) | F10: =F4+SUM(F5:F9) | G10: =G4+SUM(G5:G9) | H10: =H4+SUM(H5:H9) | I10: =I4+SUM(I5:I9) | ... N10: =N4+SUM(N5:N9)
A11: Interest Income (Expense) | B11: -1011.755 | C11: -668.411 | D11: 307.328 | E11: 5529 | F11: 26629 | G11: 39263 | H11: -27892 | I11: ='QTR P&L'!AD11+'QTR P&L'!AE11+'QTR P&L'!AF11+'QTR P&L'!AG11 | J11: ='QTR P&L'!AH11+'QTR P&L'!AI11+'QTR P&L'!AJ11+'QTR P&L'!AK11 | K11: ='QTR P&L'!AL11+'QTR P&L'!AM11+'QTR P&L'!AN11+'QTR P&L'!AO11 | L11: ='QTR P&L'!AP11+'QTR P&L'!AQ11+'QTR P&L'!AR11+'QTR P&L'!AS11 | M11: ='QTR P&L'!AT11+'QTR P&L'!AU11+'QTR P&L'!AV11+'QTR P&L'!AW11
A12: Foreign Currency Gain (Loss) | B12: 0 | C12: 1375.925 | D12: -276.259 | E12: -392 | F12: -1246 | G12: -1734 | H12: 0 | I12: ='QTR P&L'!AD13+'QTR P&L'!AE13+'QTR P&L'!AF13+'QTR P&L'!AG13 | J12: ='QTR P&L'!AH13+'QTR P&L'!AI13+'QTR P&L'!AJ13+'QTR P&L'!AK13 | K12: ='QTR P&L'!AL13+'QTR P&L'!AM13+'QTR P&L'!AN13+'QTR P&L'!AO13 | L12: ='QTR P&L'!AP13+'QTR P&L'!AQ13+'QTR P&L'!AR13+'QTR P&L'!AS13 | M12: ='QTR P&L'!AT13+'QTR P&L'!AU13+'QTR P&L'!AV13+'QTR P&L'!AW13
A13: Other Income (Expense) | B13: 12431.458 | C13: -49.1 | D13: 0 | E13: 0 | F13: 0 | G13: 1793 | H13: 11863 | I13: ='QTR P&L'!AD12+'QTR P&L'!AE12+'QTR P&L'!AF12+'QTR P&L'!AG12 | J13: ='QTR P&L'!AH12+'QTR P&L'!AI12+'QTR P&L'!AJ12+'QTR P&L'!AK12 | K13: ='QTR P&L'!AL12+'QTR P&L'!AM12+'QTR P&L'!AN12+'QTR P&L'!AO12 | L13: ='QTR P&L'!AP12+'QTR P&L'!AQ12+'QTR P&L'!AR12+'QTR P&L'!AS12 | M13: ='QTR P&L'!AT12+'QTR P&L'!AU12+'QTR P&L'!AV12+'QTR P&L'!AW12
A14: Gain (Loss) on Lease Cancellations | B14: 0 | C14: 152.112 | D14: 0 | E14: 0 | F14: 0 | G14: 0 | H14: 0 | I14: ='QTR P&L'!AD14+'QTR P&L'!AE14+'QTR P&L'!AF14+'QTR P&L'!AG14 | J14: ='QTR P&L'!AH14+'QTR P&L'!AI14+'QTR P&L'!AJ14+'QTR P&L'!AK14 | K14: ='QTR P&L'!AL14+'QTR P&L'!AM14+'QTR P&L'!AN14+'QTR P&L'!AO14 | L14: ='QTR P&L'!AP14+'QTR P&L'!AQ14+'QTR P&L'!AR14+'QTR P&L'!AS14 | M14: ='QTR P&L'!AT14+'QTR P&L'!AU14+'QTR P&L'!AV14+'QTR P&L'!AW14
A15: Income Tax (Expense) Benefit | B15: 0 | C15: -197.677 | D15: 7995.72 | E15: -34618 | F15: -64948 | G15: -49976 | H15: -17034 | I15: ='QTR P&L'!AD15+'QTR P&L'!AE15+'QTR P&L'!AF15+'QTR P&L'!AG15 | J15: ='QTR P&L'!AH15+'QTR P&L'!AI15+'QTR P&L'!AJ15+'QTR P&L'!AK15 | K15: ='QTR P&L'!AL15+'QTR P&L'!AM15+'QTR P&L'!AN15+'QTR P&L'!AO15 | L15: ='QTR P&L'!AP15+'QTR P&L'!AQ15+'QTR P&L'!AR15+'QTR P&L'!AS15 | M15: ='QTR P&L'!AT15+'QTR P&L'!AU15+'QTR P&L'!AV15+'QTR P&L'!AW15
A16: Pre-Tax Income (Loss) | B16: =B10+SUM(B11:B15) | C16: =C10+SUM(C11:C15) | D16: =D10+SUM(D11:D15) | E16: =E10+SUM(E11:E15) | F16: =F10+SUM(F11:F15) | G16: =G10+SUM(G11:G15) | H16: =H10+SUM(H11:H15) | I16: =I10+SUM(I11:I15) | ... N16: =N10+SUM(N11:N15)
A17: Net Income (Loss) | B17: =B16 | C17: =C16 | D17: =D16 | E17: =E16 | F17: =F16 | G17: =G16 | H17: =H16 | I17: =I16 | ... N17: =N16
A18: Basic Earnings (Loss) per Share | B18: 0.16 | C18: 0.12 | D18: 0.05 | E18: 0 | F18: 0 | G18: 0 | H18: 0
A19: Diluted Earnings (Loss) per Share | B19: 0.16 | C19: 0.11 | D19: 0.05 | E19: 0 | F19: 0 | G19: 0 | H19: 0
A20: Weighted Average Shares Outstanding (Basic) | B20: 60761995 | C20: 70195085 | D20: 151469631 | E20: 0 | F20: 0 | G20: 0 | H20: 0
A21: Weighted Average Shares Outstanding (Diluted) | B21: 64183399 | C21: 74443601 | D21: 0 | E21: 0 | F21: 0 | G21: 0 | H21: 0
A22: Preferred Dividends | B22: 0 | C22: 0 | D22: 0 | E22: -11526 | F22: -27462 | G22: -27500 | H22: -37608 | I22: ='QTR P&L'!AD22+'QTR P&L'!AE22+'QTR P&L'!AF22+'QTR P&L'!AG22 | J22: ='QTR P&L'!AH22+'QTR P&L'!AI22+'QTR P&L'!AJ22+'QTR P&L'!AK22 | K22: ='QTR P&L'!AL22+'QTR P&L'!AM22+'QTR P&L'!AN22+'QTR P&L'!AO22 | L22: ='QTR P&L'!AP22+'QTR P&L'!AQ22+'QTR P&L'!AR22+'QTR P&L'!AS22 | M22: ='QTR P&L'!AT22+'QTR P&L'!AU22+'QTR P&L'!AV22+'QTR P&L'!AW22
A23: Income Allocated to Participating Preferred | B23: 0 | C23: 0 | D23: 0 | E23: 0 | F23: -17348 | G23: -10117 | H23: -6554 | I23: ='QTR P&L'!AD23+'QTR P&L'!AE23+'QTR P&L'!AF23+'QTR P&L'!AG23 | J23: ='QTR P&L'!AH23+'QTR P&L'!AI23+'QTR P&L'!AJ23+'QTR P&L'!AK23 | K23: ='QTR P&L'!AL23+'QTR P&L'!AM23+'QTR P&L'!AN23+'QTR P&L'!AO23 | L23: ='QTR P&L'!AP23+'QTR P&L'!AQ23+'QTR P&L'!AR23+'QTR P&L'!AS23 | M23: ='QTR P&L'!AT23+'QTR P&L'!AU23+'QTR P&L'!AV23+'QTR P&L'!AW23
A24: Net Income (Loss) Attributable to Common Shareholders | B24: =B17+B22+B23 | C24: =C17+C22+C23 | D24: =D17+D22+D23 | E24: =E17+E22+E23 | F24: =F17+F22+F23 | G24: =G17+G22+G23 | H24: =H17+H22+H23 | I24: =I17+I22+I23 | ... N24: =N17+N22+N23

Sheet BALANCE SHEET
B1: FY2019 | C1: FY2020 | D1: FY2021 | E1: FY2022 | F1: FY2023 | G1: FY2024 | H1: FY2025 | I1: FY2026E | J1: FY2027E | K1: FY2028E | L1: FY2029E | M1: FY2030E | N1: FY2031E
A2: Cash, Cash Equivalents & Restricted Cash | B2: 23090.682 | C2: 43248.021 | D2: 16254.708 | E2: 652927 | F2: 755981 | G2: 890190 | H2: 539987 | I2: ='QTR BS'!AD2 | J2: ='QTR BS'!AH2 | K2: ='QTR BS'!AL2 | L2: ='QTR BS'!AP2 | M2: ='QTR BS'!AT2
A3: Accounts Receivable | B3: 7774.618 | C3: 14986.213 | D3: 38741.049 | E3: 63311 | F3: 183703 | G3: 270342 | H3: 755499 | I3: ='QTR BS'!AD3 | J3: ='QTR BS'!AH3 | K3: ='QTR BS'!AL3 | L3: ='QTR BS'!AP3 | M3: ='QTR BS'!AT3
A4: Note Receivable - Current | B4: 1181.116 | C4: 1885.887 | D4: 2587.905 | E4: 2979 | F4: 2318 | G4: 0 | H4: 0 | I4: ='QTR BS'!AD4 | J4: ='QTR BS'!AH4 | K4: ='QTR BS'!AL4 | L4: ='QTR BS'!AP4 | M4: ='QTR BS'!AT4
A5: Inventories | B5: 15292.349 | C5: 18403.622 | D5: 191221.85 | E5: 173289 | F5: 229275 | G5: 131165 | H5: 337698 | I5: ='QTR BS'!AD5 | J5: ='QTR BS'!AH5 | K5: ='QTR BS'!AL5 | L5: ='QTR BS'!AP5 | M5: ='QTR BS'!AT5
A6: Prepaid Expenses | B6: 4170.136 | C6: 14626.922 | D6: 13555.037 | E6: 11341 | F6: 19503 | G6: 18759 | H6: 128806 | I6: ='QTR BS'!AD6 | J6: ='QTR BS'!AH6 | K6: ='QTR BS'!AL6 | L6: ='QTR BS'!AP6 | M6: ='QTR BS'!AT6
A7: Deferred Other Costs - Current | B7: 0 | C7: 0 | D7: 0 | E7: 14124 | F7: 14124 | G7: 14124 | H7: 49164 | I7: ='QTR BS'!AD7 | J7: ='QTR BS'!AH7 | K7: ='QTR BS'!AL7 | L7: ='QTR BS'!AP7 | M7: ='QTR BS'!AT7
A8: Total Current Assets | B8: =SUM(B2:B7) | C8: =SUM(C2:C7) | D8: =SUM(D2:D7) | E8: =SUM(E2:E7) | F8: =SUM(F2:F7) | G8: =SUM(G2:G7) | H8: =SUM(H2:H7) | I8: =SUM(I2:I7) | ... N8: =SUM(N2:N7)
A9: Note Receivable - Non-Current | B9: 10630.04 | C9: 9429.437 | D9: 7116.738 | E9: 3574 | F9: 0 | G9: 0 | H9: 0 | I9: ='QTR BS'!AD9 | J9: ='QTR BS'!AH9 | K9: ='QTR BS'!AL9 | L9: ='QTR BS'!AP9 | M9: ='QTR BS'!AT9
A10: Net PP&E | B10: 132.889 | C10: 579.377 | D10: 3180.058 | E10: 10185 | F10: 24868 | G10: 55602 | H10: 87910 | I10: ='QTR BS'!AD10 | J10: ='QTR BS'!AH10 | K10: ='QTR BS'!AL10 | L10: ='QTR BS'!AP10 | M10: ='QTR BS'!AT10
A11: ROU Assets - Operating - Non-Current | B11: 395.828 | C11: 836.038 | D11: 1128.151 | E11: 972 | F11: 1957 | G11: 21606 | H11: 0 | I11: ='QTR BS'!AD11 | J11: ='QTR BS'!AH11 | K11: ='QTR BS'!AL11 | L11: ='QTR BS'!AP11 | M11: ='QTR BS'!AT11
A12: ROU Assets - Finance - Non-Current | B12: 413.638 | C12: 162.119 | D12: 85.953 | E12: 208 | F12: 208 | G12: 230 | H12: 0 | I12: ='QTR BS'!AD16 | J12: ='QTR BS'!AH16 | K12: ='QTR BS'!AL16 | L12: ='QTR BS'!AP16 | M12: ='QTR BS'!AT16
A13: Intangible Assets | B13: 17173 | C13: 16590.083 | D13: 16301.326 | E13: 12254 | F13: 12139 | G13: 12213 | H13: 1391915 | I13: ='QTR BS'!AD12 | J13: ='QTR BS'!AH12 | K13: ='QTR BS'!AL12 | L13: ='QTR BS'!AP12 | M13: ='QTR BS'!AT12
A14: Goodwill | B14: 10023.806 | C14: 10419.321 | D14: 14526.583 | E14: 13679 | F14: 14173 | G14: 71582 | H14: 917560 | I14: ='QTR BS'!AD13 | J14: ='QTR BS'!AH13 | K14: ='QTR BS'!AL13 | L14: ='QTR BS'!AP13 | M14: ='QTR BS'!AT13
A15: Deferred Other Costs - Non-Current | B15: 0 | C15: 0 | D15: 0 | E15: 262462 | F15: 248338 | G15: 234215 | H15: 771635 | I15: ='QTR BS'!AD14 | J15: ='QTR BS'!AH14 | K15: ='QTR BS'!AL14 | L15: ='QTR BS'!AP14 | M15: ='QTR BS'!AT14
A16: Deferred Tax Assets | B16: 0 | C16: 0 | D16: 9019.241 | E16: 501 | F16: 29518 | G16: 38699 | H16: 96013 | I16: ='QTR BS'!AD15 | J16: ='QTR BS'!AH15 | K16: ='QTR BS'!AL15 | L16: ='QTR BS'!AP15 | M16: ='QTR BS'!AT15
A17: Other Non-Current Assets | B17: 104.134 | C17: 122.733 | D17: 299.828 | E17: 263 | F17: 291 | G17: 8154 | H17: 43434 | I17: ='QTR BS'!AD17 | J17: ='QTR BS'!AH17 | K17: ='QTR BS'!AL17 | L17: ='QTR BS'!AP17 | M17: ='QTR BS'!AT17
A18: Total Assets | B18: =B8+SUM(B9:B17) | C18: =C8+SUM(C9:C17) | D18: =D8+SUM(D9:D17) | E18: =E8+SUM(E9:E17) | F18: =F8+SUM(F9:F17) | G18: =G8+SUM(G9:G17) | H18: =H8+SUM(H9:H17) | I18: =I8+SUM(I9:I17) | ... N18: =N8+SUM(N9:N17)
A19: Accounts Payable | B19: 17292.647 | C19: 25412.753 | D19: 91478.612 | E19: 36248 | F19: 42840 | G19: 41287 | H19: 137930 | I19: ='QTR BS'!AD19 | J19: ='QTR BS'!AH19 | K19: ='QTR BS'!AL19 | L19: ='QTR BS'!AP19 | M19: ='QTR BS'!AT19
A20: Accrued Expenses | B20: 0 | C20: 0 | D20: 0 | E20: 69899 | F20: 62120 | G20: 148780 | H20: 230721 | I20: ='QTR BS'!AD20 | J20: ='QTR BS'!AH20 | K20: ='QTR BS'!AL20 | L20: ='QTR BS'!AP20 | M20: ='QTR BS'!AT20
A21: Income Taxes Payable | B21: 0 | C21: 0 | D21: 0 | E21: 1193 | F21: 50424 | G21: 10834 | H21: 49612 | I21: ='QTR BS'!AD21 | J21: ='QTR BS'!AH21 | K21: ='QTR BS'!AL21 | L21: ='QTR BS'!AP21 | M21: ='QTR BS'!AT21
A22: Accrued Distributor Termination Fees | B22: 0 | C22: 0 | D22: 0 | E22: 3986 | F22: 0 | G22: 0 | H22: 264088 | I22: ='QTR BS'!AD22 | J22: ='QTR BS'!AH22 | K22: ='QTR BS'!AL22 | L22: ='QTR BS'!AP22 | M22: ='QTR BS'!AT22
A23: Accrued Promotional Allowance | B23: 0 | C23: 0 | D23: 0 | E23: 35977 | F23: 99787 | G23: 135948 | H23: 307922 | I23: ='QTR BS'!AD23 | J23: ='QTR BS'!AH23 | K23: ='QTR BS'!AL23 | L23: ='QTR BS'!AP23 | M23: ='QTR BS'!AT23
A24: Lease Liability - Operating - Current | B24: 294.916 | C24: 321.283 | D24: 511.764 | E24: 661 | F24: 980 | G24: 3265 | H24: 0 | I24: ='QTR BS'!AD24 | J24: ='QTR BS'!AH24 | K24: ='QTR BS'!AL24 | L24: ='QTR BS'!AP24 | M24: ='QTR BS'!AT24
A25: Lease Liability - Finance - Current | B25: 354.158 | C25: 205.824 | D25: 157.046 | E25: 70 | F25: 59 | G25: 100 | H25: 0 | I25: ='QTR BS'!AD26 | J25: ='QTR BS'!AH26 | K25: ='QTR BS'!AL26 | L25: ='QTR BS'!AP26 | M25: ='QTR BS'!AT26
A26: Bonds Payable, Net | B26: 8634.279 | C26: 0 | D26: 0 | E26: 0 | F26: 0 | G26: 0 | H26: 0 | I26: ='QTR BS'!AD25 | J26: ='QTR BS'!AH25 | K26: ='QTR BS'!AL25 | L26: ='QTR BS'!AP25 | M26: ='QTR BS'!AT25
A27: Contingent Consideration - Current | B27: 0 | C27: 0 | D27: 0 | E27: 0 | F27: 0 | G27: 0 | H27: 25000 | I27: ='QTR BS'!AD27 | J27: ='QTR BS'!AH27 | K27: ='QTR BS'!AL27 | L27: ='QTR BS'!AP27 | M27: ='QTR BS'!AT27
A28: Deferred Revenue - Current | B28: 0 | C28: 0 | D28: 0 | E28: 9675 | F28: 9513 | G28: 9513 | H28: 26988 | I28: ='QTR BS'!AD28 | J28: ='QTR BS'!AH28 | K28: ='QTR BS'!AL28 | L28: ='QTR BS'!AP28 | M28: ='QTR BS'!AT28
A29: Other Current Liabilities | B29: 107.399 | C29: 425.232 | D29: 976.072 | E29: 3586 | F29: 10890 | G29: 15808 | H29: 36465 | I29: ='QTR BS'!AD29 | J29: ='QTR BS'!AH29 | K29: ='QTR BS'!AL29 | L29: ='QTR BS'!AP29 | M29: ='QTR BS'!AT29
A30: Total Current Liabilities | B30: =SUM(B19:B29) | C30: =SUM(C19:C29) | D30: =SUM(D19:D29) | E30: =SUM(E19:E29) | F30: =SUM(F19:F29) | G30: =SUM(G19:G29) | H30: =SUM(H19:H29) | I30: =SUM(I19:I29) | ... N30: =SUM(N19:N29)
A31: Lease Liability - Operating - Non-Current | B31: 107.311 | C31: 514.948 | D31: 657.935 | E31: 326 | F31: 955 | G31: 16674 | H31: 0 | I31: ='QTR BS'!AD31 | J31: ='QTR BS'!AH31 | K31: ='QTR BS'!AL31 | L31: ='QTR BS'!AP31 | M31: ='QTR BS'!AT31
A32: Lease Liability - Finance - Non-Current | B32: 132.537 | C32: 82.29 | D32: 45.408 | E32: 162 | F32: 193 | G32: 211 | H32: 0 | I32: ='QTR BS'!AD32 | J32: ='QTR BS'!AH32 | K32: ='QTR BS'!AL32 | L32: ='QTR BS'!AP32 | M32: ='QTR BS'!AT32
A33: Deferred Tax Liability | B33: 0 | C33: 0 | D33: 3146.394 | E33: 15919 | F33: 2880 | G33: 2330 | H33: 0 | I33: ='QTR BS'!AD33 | J33: ='QTR BS'!AH33 | K33: ='QTR BS'!AL33 | L33: ='QTR BS'!AP33 | M33: ='QTR BS'!AT33
A34: Long-Term Debt | B34: 0 | C34: 0 | D34: 0 | E34: 0 | F34: 0 | G34: 0 | H34: 669926 | I34: ='QTR BS'!AD34 | J34: ='QTR BS'!AH34 | K34: ='QTR BS'!AL34 | L34: ='QTR BS'!AP34 | M34: ='QTR BS'!AT34
A35: Deferred Revenue - Non-Current | B35: 0 | C35: 0 | D35: 0 | E35: 179788 | F35: 167227 | G35: 157714 | H35: 401155 | I35: ='QTR BS'!AD35 | J35: ='QTR BS'!AH35 | K35: ='QTR BS'!AL35 | L35: ='QTR BS'!AP35 | M35: ='QTR BS'!AT35
A36: Other Non-Current Liabilities | B36: 0 | C36: 0 | D36: 0 | E36: 0 | F36: 0 | G36: 0 | H36: 28372 | I36: ='QTR BS'!AD36 | J36: ='QTR BS'!AH36 | K36: ='QTR BS'!AL36 | L36: ='QTR BS'!AP36 | M36: ='QTR BS'!AT36
A37: Total Liabilities | B37: =B30+SUM(B31:B36) | C37: =C30+SUM(C31:C36) | D37: =D30+SUM(D31:D36) | E37: =E30+SUM(E31:E36) | F37: =F30+SUM(F31:F36) | G37: =G30+SUM(G31:G36) | H37: =H30+SUM(H31:H36) | I37: =I30+SUM(I31:I36) | ... N37: =N30+SUM(N31:N36)
A38: Convertible Preferred Stock | B38: 0 | C38: 0 | D38: 0 | E38: 824488 | F38: 824488 | G38: 824488 | H38: 1759975 | I38: ='QTR BS'!AD38 | J38: ='QTR BS'!AH38 | K38: ='QTR BS'!AL38 | L38: ='QTR BS'!AP38 | M38: ='QTR BS'!AT38
A39: Common Stock | B39: 68.942 | C39: 72.263 | D39: 74.909 | E39: 76 | F39: 77 | G39: 79 | H39: 101 | I39: ='QTR BS'!AD39 | J39: ='QTR BS'!AH39 | K39: ='QTR BS'!AL39 | L39: ='QTR BS'!AP39 | M39: ='QTR BS'!AT39
A40: Treasury Stock | B40: 0 | C40: 0 | D40: 0 | E40: 0 | F40: 0 | G40: 0 | H40: -48226 | I40: ='QTR BS'!AD40 | J40: ='QTR BS'!AH40 | K40: ='QTR BS'!AL40 | L40: ='QTR BS'!AP40 | M40: ='QTR BS'!AT40
A41: Additional Paid-in Capital | B41: 127553 | C41: 159884.15 | D41: 267846.2 | E41: 280668 | F41: 276717 | G41: 297579 | H41: 1050518 | I41: ='QTR BS'!AD41 | J41: ='QTR BS'!AH41 | K41: ='QTR BS'!AL41 | L41: ='QTR BS'!AP41 | M41: ='QTR BS'!AT41
A42: Accumulated Other Comprehensive Income (Loss) | B42: -753.52 | C42: -202.142 | D42: 613.651 | E42: -1881 | F42: -701 | G42: -3250 | H42: 3162 | I42: ='QTR BS'!AD42 | J42: ='QTR BS'!AH42 | K42: ='QTR BS'!AL42 | L42: ='QTR BS'!AP42 | M42: ='QTR BS'!AT42
A43: Retained Earnings (Accumulated Deficit) | B43: -63409.431 | C43: -55426.832 | D43: -51489.559 | E43: -238772 | F43: -12053 | G43: 105521 | H43: 175912 | I43: ='QTR BS'!AD43 | J43: ='QTR BS'!AH43 | K43: ='QTR BS'!AL43 | L43: ='QTR BS'!AP43 | M43: ='QTR BS'!AT43
A44: Total Stockholders' Equity | B44: =SUM(B38:B43) | C44: =SUM(C38:C43) | D44: =SUM(D38:D43) | E44: =SUM(E38:E43) | F44: =SUM(F38:F43) | G44: =SUM(G38:G43) | H44: =SUM(H38:H43) | I44: =SUM(I38:I43) | ... N44: =SUM(N38:N43)
A45: Total Liabilities, Mezzanine & Stockholders' Equity | B45: =B37+B44 | C45: =C37+C44 | D45: =D37+D44 | E45: =E37+E44 | F45: =F37+F44 | G45: =G37+G44 | H45: =H37+H44 | I45: =I37+I44 | ... N45: =N37+N44

Sheet CASH FLOW
B1: FY2019 | C1: FY2020 | D1: FY2021 | E1: FY2022 | F1: FY2023 | G1: FY2024 | H1: FY2025 | I1: FY2026E | J1: FY2027E | K1: FY2028E | L1: FY2029E | M1: FY2030E | N1: FY2031E
A2: Net Income (Loss) | B2: 9971.26 | C2: 8523.849 | D2: 3937 | E2: -187282 | F2: 226801 | G2: 145074 | H2: 107999 | I2: ='QTR CF'!Z2+'QTR CF'!AA2+'QTR CF'!AB2+'QTR CF'!AC2 | J2: ='QTR CF'!AD2+'QTR CF'!AE2+'QTR CF'!AF2+'QTR CF'!AG2 | K2: ='QTR CF'!AH2+'QTR CF'!AI2+'QTR CF'!AJ2+'QTR CF'!AK2 | L2: ='QTR CF'!AL2+'QTR CF'!AM2+'QTR CF'!AN2+'QTR CF'!AO2 | M2: ='QTR CF'!AP2+'QTR CF'!AQ2+'QTR CF'!AR2+'QTR CF'!AS2
A3: Depreciation | B3: 66.939 | C3: 127.263 | D3: 0 | E3: 0 | F3: 0 | G3: 0 | H3: 0 | I3: ='QTR CF'!Z3+'QTR CF'!AA3+'QTR CF'!AB3+'QTR CF'!AC3 | J3: ='QTR CF'!AD3+'QTR CF'!AE3+'QTR CF'!AF3+'QTR CF'!AG3 | K3: ='QTR CF'!AH3+'QTR CF'!AI3+'QTR CF'!AJ3+'QTR CF'!AK3 | L3: ='QTR CF'!AL3+'QTR CF'!AM3+'QTR CF'!AN3+'QTR CF'!AO3 | M3: ='QTR CF'!AP3+'QTR CF'!AQ3+'QTR CF'!AR3+'QTR CF'!AS3
A4: Amortization | B4: 826.474 | C4: 1484.303 | D4: 0 | E4: 0 | F4: 0 | G4: 0 | H4: 0 | I4: ='QTR CF'!Z4+'QTR CF'!AA4+'QTR CF'!AB4+'QTR CF'!AC4 | J4: ='QTR CF'!AD4+'QTR CF'!AE4+'QTR CF'!AF4+'QTR CF'!AG4 | K4: ='QTR CF'!AH4+'QTR CF'!AI4+'QTR CF'!AJ4+'QTR CF'!AK4 | L4: ='QTR CF'!AL4+'QTR CF'!AM4+'QTR CF'!AN4+'QTR CF'!AO4 | M4: ='QTR CF'!AP4+'QTR CF'!AQ4+'QTR CF'!AR4+'QTR CF'!AS4
A5: Depreciation & Amortization | B5: 0 | C5: 0 | D5: 1264 | E5: 1917 | F5: 3226 | G5: 7274 | H5: 29451 | I5: ='QTR CF'!Z6+'QTR CF'!AA6+'QTR CF'!AB6+'QTR CF'!AC6 | J5: ='QTR CF'!AD6+'QTR CF'!AE6+'QTR CF'!AF6+'QTR CF'!AG6 | K5: ='QTR CF'!AH6+'QTR CF'!AI6+'QTR CF'!AJ6+'QTR CF'!AK6 | L5: ='QTR CF'!AL6+'QTR CF'!AM6+'QTR CF'!AN6+'QTR CF'!AO6 | M5: ='QTR CF'!AP6+'QTR CF'!AQ6+'QTR CF'!AR6+'QTR CF'!AS6
A6: Impairment of Intangibles | B6: 0 | C6: 0 | D6: 0 | E6: 2379 | F6: 0 | G6: 0 | H6: 0 | I6: ='QTR CF'!Z5+'QTR CF'!AA5+'QTR CF'!AB5+'QTR CF'!AC5 | J6: ='QTR CF'!AD5+'QTR CF'!AE5+'QTR CF'!AF5+'QTR CF'!AG5 | K6: ='QTR CF'!AH5+'QTR CF'!AI5+'QTR CF'!AJ5+'QTR CF'!AK5 | L6: ='QTR CF'!AL5+'QTR CF'!AM5+'QTR CF'!AN5+'QTR CF'!AO5 | M6: ='QTR CF'!AP5+'QTR CF'!AQ5+'QTR CF'!AR5+'QTR CF'!AS5
A7: Allowance for Credit Losses | B7: 109.393 | C7: 257.177 | D7: 1494 | E7: 2352 | F7: 2128 | G7: 3294 | H7: 10600 | I7: ='QTR CF'!Z7+'QTR CF'!AA7+'QTR CF'!AB7+'QTR CF'!AC7 | J7: ='QTR CF'!AD7+'QTR CF'!AE7+'QTR CF'!AF7+'QTR CF'!AG7 | K7: ='QTR CF'!AH7+'QTR CF'!AI7+'QTR CF'!AJ7+'QTR CF'!AK7 | L7: ='QTR CF'!AL7+'QTR CF'!AM7+'QTR CF'!AN7+'QTR CF'!AO7 | M7: ='QTR CF'!AP7+'QTR CF'!AQ7+'QTR CF'!AR7+'QTR CF'!AS7
A8: Amortization of Deferred Other Costs | B8: 0 | C8: 0 | D8: 0 | E8: 5885 | F8: 14124 | G8: 14124 | H8: 26326 | I8: ='QTR CF'!Z8+'QTR CF'!AA8+'QTR CF'!AB8+'QTR CF'!AC8 | J8: ='QTR CF'!AD8+'QTR CF'!AE8+'QTR CF'!AF8+'QTR CF'!AG8 | K8: ='QTR CF'!AH8+'QTR CF'!AI8+'QTR CF'!AJ8+'QTR CF'!AK8 | L8: ='QTR CF'!AL8+'QTR CF'!AM8+'QTR CF'!AN8+'QTR CF'!AO8 | M8: ='QTR CF'!AP8+'QTR CF'!AQ8+'QTR CF'!AR8+'QTR CF'!AS8
A9: Inventory Write-Down | B9: 331.985 | C9: 747.507 | D9: 2355 | E9: 6131 | F9: 7312 | G9: 19086 | H9: 29190 | I9: ='QTR CF'!Z9+'QTR CF'!AA9+'QTR CF'!AB9+'QTR CF'!AC9 | J9: ='QTR CF'!AD9+'QTR CF'!AE9+'QTR CF'!AF9+'QTR CF'!AG9 | K9: ='QTR CF'!AH9+'QTR CF'!AI9+'QTR CF'!AJ9+'QTR CF'!AK9 | L9: ='QTR CF'!AL9+'QTR CF'!AM9+'QTR CF'!AN9+'QTR CF'!AO9 | M9: ='QTR CF'!AP9+'QTR CF'!AQ9+'QTR CF'!AR9+'QTR CF'!AS9
A10: Gain (Loss) on Disposal of PP&E | B10: 0 | C10: 0 | D10: 0 | E10: 0 | F10: 198 | G10: 173 | H10: 0 | I10: ='QTR CF'!Z10+'QTR CF'!AA10+'QTR CF'!AB10+'QTR CF'!AC10 | J10: ='QTR CF'!AD10+'QTR CF'!AE10+'QTR CF'!AF10+'QTR CF'!AG10 | K10: ='QTR CF'!AH10+'QTR CF'!AI10+'QTR CF'!AJ10+'QTR CF'!AK10 | L10: ='QTR CF'!AL10+'QTR CF'!AM10+'QTR CF'!AN10+'QTR CF'!AO10 | M10: ='QTR CF'!AP10+'QTR CF'!AQ10+'QTR CF'!AR10+'QTR CF'!AS10
A11: Stock-Based Compensation | B11: 4831.75 | C11: 6340 | D11: 36475 | E11: 20665 | F11: 21226 | G11: 19591 | H11: 28050 | I11: ='QTR CF'!Z11+'QTR CF'!AA11+'QTR CF'!AB11+'QTR CF'!AC11 | J11: ='QTR CF'!AD11+'QTR CF'!AE11+'QTR CF'!AF11+'QTR CF'!AG11 | K11: ='QTR CF'!AH11+'QTR CF'!AI11+'QTR CF'!AJ11+'QTR CF'!AK11 | L11: ='QTR CF'!AL11+'QTR CF'!AM11+'QTR CF'!AN11+'QTR CF'!AO11 | M11: ='QTR CF'!AP11+'QTR CF'!AQ11+'QTR CF'!AR11+'QTR CF'!AS11
A12: Gain on China Transaction | B12: -12461.037 | C12: -322.936 | D12: 0 | E12: 0 | F12: 0 | G12: 0 | H12: 0 | I12: ='QTR CF'!Z12+'QTR CF'!AA12+'QTR CF'!AB12+'QTR CF'!AC12 | J12: ='QTR CF'!AD12+'QTR CF'!AE12+'QTR CF'!AF12+'QTR CF'!AG12 | K12: ='QTR CF'!AH12+'QTR CF'!AI12+'QTR CF'!AJ12+'QTR CF'!AK12 | L12: ='QTR CF'!AL12+'QTR CF'!AM12+'QTR CF'!AN12+'QTR CF'!AO12 | M12: ='QTR CF'!AP12+'QTR CF'!AQ12+'QTR CF'!AR12+'QTR CF'!AS12
A13: (Benefit) Provision for Deferred Income Taxes | B13: 0 | C13: 0 | D13: -9201 | E13: 20244 | F13: -42055 | G13: -9730 | H13: -57336 | I13: ='QTR CF'!Z14+'QTR CF'!AA14+'QTR CF'!AB14+'QTR CF'!AC14 | J13: ='QTR CF'!AD14+'QTR CF'!AE14+'QTR CF'!AF14+'QTR CF'!AG14 | K13: ='QTR CF'!AH14+'QTR CF'!AI14+'QTR CF'!AJ14+'QTR CF'!AK14 | L13: ='QTR CF'!AL14+'QTR CF'!AM14+'QTR CF'!AN14+'QTR CF'!AO14 | M13: ='QTR CF'!AP14+'QTR CF'!AQ14+'QTR CF'!AR14+'QTR CF'!AS14
A14: Foreign Currency Gain (Loss) | B14: 0 | C14: 0 | D14: 880 | E14: 483 | F14: 1246 | G14: 1734 | H14: 0 | I14: ='QTR CF'!Z15+'QTR CF'!AA15+'QTR CF'!AB15+'QTR CF'!AC15 | J14: ='QTR CF'!AD15+'QTR CF'!AE15+'QTR CF'!AF15+'QTR CF'!AG15 | K14: ='QTR CF'!AH15+'QTR CF'!AI15+'QTR CF'!AJ15+'QTR CF'!AK15 | L14: ='QTR CF'!AL15+'QTR CF'!AM15+'QTR CF'!AN15+'QTR CF'!AO15 | M14: ='QTR CF'!AP15+'QTR CF'!AQ15+'QTR CF'!AR15+'QTR CF'!AS15
A15: Gain (Loss) on Lease Cancellations | B15: 0 | C15: -152.112 | D15: -28 | E15: 0 | F15: 0 | G15: 0 | H15: 0 | I15: ='QTR CF'!Z13+'QTR CF'!AA13+'QTR CF'!AB13+'QTR CF'!AC13 | J15: ='QTR CF'!AD13+'QTR CF'!AE13+'QTR CF'!AF13+'QTR CF'!AG13 | K15: ='QTR CF'!AH13+'QTR CF'!AI13+'QTR CF'!AJ13+'QTR CF'!AK13 | L15: ='QTR CF'!AL13+'QTR CF'!AM13+'QTR CF'!AN13+'QTR CF'!AO13 | M15: ='QTR CF'!AP13+'QTR CF'!AQ13+'QTR CF'!AR13+'QTR CF'!AS13
A16: Change in Fair Value of Contingent Consideration | B16: 0 | C16: 0 | D16: 0 | E16: 0 | F16: 0 | G16: 0 | H16: 13800 | I16: ='QTR CF'!Z16+'QTR CF'!AA16+'QTR CF'!AB16+'QTR CF'!AC16 | J16: ='QTR CF'!AD16+'QTR CF'!AE16+'QTR CF'!AF16+'QTR CF'!AG16 | K16: ='QTR CF'!AH16+'QTR CF'!AI16+'QTR CF'!AJ16+'QTR CF'!AK16 | L16: ='QTR CF'!AL16+'QTR CF'!AM16+'QTR CF'!AN16+'QTR CF'!AO16 | M16: ='QTR CF'!AP16+'QTR CF'!AQ16+'QTR CF'!AR16+'QTR CF'!AS16
A17: Gain (Loss) on Extinguishment of Debt | B17: 0 | C17: 0 | D17: 0 | E17: 0 | F17: 0 | G17: 0 | H17: 6003 | I17: ='QTR CF'!Z17+'QTR CF'!AA17+'QTR CF'!AB17+'QTR CF'!AC17 | J17: ='QTR CF'!AD17+'QTR CF'!AE17+'QTR CF'!AF17+'QTR CF'!AG17 | K17: ='QTR CF'!AH17+'QTR CF'!AI17+'QTR CF'!AJ17+'QTR CF'!AK17 | L17: ='QTR CF'!AL17+'QTR CF'!AM17+'QTR CF'!AN17+'QTR CF'!AO17 | M17: ='QTR CF'!AP17+'QTR CF'!AQ17+'QTR CF'!AR17+'QTR CF'!AS17
A18: Other Operating Items | B18: 0 | C18: 0 | D18: 0 | E18: 37 | F18: -28 | G18: -324 | H18: -1687 | I18: ='QTR CF'!Z18+'QTR CF'!AA18+'QTR CF'!AB18+'QTR CF'!AC18 | J18: ='QTR CF'!AD18+'QTR CF'!AE18+'QTR CF'!AF18+'QTR CF'!AG18 | K18: ='QTR CF'!AH18+'QTR CF'!AI18+'QTR CF'!AJ18+'QTR CF'!AK18 | L18: ='QTR CF'!AL18+'QTR CF'!AM18+'QTR CF'!AN18+'QTR CF'!AO18 | M18: ='QTR CF'!AP18+'QTR CF'!AQ18+'QTR CF'!AR18+'QTR CF'!AS18
A19: Accounts Receivable | B19: -1432.98 | C19: -7468.772 | D19: -25249 | E19: -26369 | F19: -121558 | G19: -89665 | H19: -412091 | I19: ='QTR CF'!Z19+'QTR CF'!AA19+'QTR CF'!AB19+'QTR CF'!AC19 | J19: ='QTR CF'!AD19+'QTR CF'!AE19+'QTR CF'!AF19+'QTR CF'!AG19 | K19: ='QTR CF'!AH19+'QTR CF'!AI19+'QTR CF'!AJ19+'QTR CF'!AK19 | L19: ='QTR CF'!AL19+'QTR CF'!AM19+'QTR CF'!AN19+'QTR CF'!AO19 | M19: ='QTR CF'!AP19+'QTR CF'!AQ19+'QTR CF'!AR19+'QTR CF'!AS19
A20: Note Receivable | B20: 0 | C20: 0 | D20: 0 | E20: 0 | F20: 0 | G20: 2318 | H20: 0 | I20: ='QTR CF'!Z20+'QTR CF'!AA20+'QTR CF'!AB20+'QTR CF'!AC20 | J20: ='QTR CF'!AD20+'QTR CF'!AE20+'QTR CF'!AF20+'QTR CF'!AG20 | K20: ='QTR CF'!AH20+'QTR CF'!AI20+'QTR CF'!AJ20+'QTR CF'!AK20 | L20: ='QTR CF'!AL20+'QTR CF'!AM20+'QTR CF'!AN20+'QTR CF'!AO20 | M20: ='QTR CF'!AP20+'QTR CF'!AQ20+'QTR CF'!AR20+'QTR CF'!AS20
A21: Inventories | B21: -2239.254 | C21: -3858.78 | D21: -175174 | E21: 11802 | F21: -63299 | G21: 77190 | H21: -129777 | I21: ='QTR CF'!Z21+'QTR CF'!AA21+'QTR CF'!AB21+'QTR CF'!AC21 | J21: ='QTR CF'!AD21+'QTR CF'!AE21+'QTR CF'!AF21+'QTR CF'!AG21 | K21: ='QTR CF'!AH21+'QTR CF'!AI21+'QTR CF'!AJ21+'QTR CF'!AK21 | L21: ='QTR CF'!AL21+'QTR CF'!AM21+'QTR CF'!AN21+'QTR CF'!AO21 | M21: ='QTR CF'!AP21+'QTR CF'!AQ21+'QTR CF'!AR21+'QTR CF'!AS21
A22: Prepaid Expenses | B22: -805.571 | C22: -10456.787 | D22: 1072 | E22: 2214 | F22: -7980 | G22: 1074 | H22: -108321 | I22: ='QTR CF'!Z22+'QTR CF'!AA22+'QTR CF'!AB22+'QTR CF'!AC22 | J22: ='QTR CF'!AD22+'QTR CF'!AE22+'QTR CF'!AF22+'QTR CF'!AG22 | K22: ='QTR CF'!AH22+'QTR CF'!AI22+'QTR CF'!AJ22+'QTR CF'!AK22 | L22: ='QTR CF'!AL22+'QTR CF'!AM22+'QTR CF'!AN22+'QTR CF'!AO22 | M22: ='QTR CF'!AP22+'QTR CF'!AQ22+'QTR CF'!AR22+'QTR CF'!AS22
A23: Change in A/P and Accrued (legacy) | B23: 2624.892 | C23: 8120.106 | D23: 0 | E23: 0 | F23: 0 | G23: 0 | H23: 0 | I23: ='QTR CF'!Z23+'QTR CF'!AA23+'QTR CF'!AB23+'QTR CF'!AC23 | J23: ='QTR CF'!AD23+'QTR CF'!AE23+'QTR CF'!AF23+'QTR CF'!AG23 | K23: ='QTR CF'!AH23+'QTR CF'!AI23+'QTR CF'!AJ23+'QTR CF'!AK23 | L23: ='QTR CF'!AL23+'QTR CF'!AM23+'QTR CF'!AN23+'QTR CF'!AO23 | M23: ='QTR CF'!AP23+'QTR CF'!AQ23+'QTR CF'!AR23+'QTR CF'!AS23
A24: Other Non-Current Assets | B24: 0 | C24: 0 | D24: 0 | E24: 0 | F24: 0 | G24: -4862 | H24: 2857 | I24: ='QTR CF'!Z24+'QTR CF'!AA24+'QTR CF'!AB24+'QTR CF'!AC24 | J24: ='QTR CF'!AD24+'QTR CF'!AE24+'QTR CF'!AF24+'QTR CF'!AG24 | K24: ='QTR CF'!AH24+'QTR CF'!AI24+'QTR CF'!AJ24+'QTR CF'!AK24 | L24: ='QTR CF'!AL24+'QTR CF'!AM24+'QTR CF'!AN24+'QTR CF'!AO24 | M24: ='QTR CF'!AP24+'QTR CF'!AQ24+'QTR CF'!AR24+'QTR CF'!AS24
A25: Accounts Payable | B25: 0 | C25: 0 | D25: 23966 | E25: 428 | F25: 5249 | G25: -1170 | H25: 51252 | I25: ='QTR CF'!Z25+'QTR CF'!AA25+'QTR CF'!AB25+'QTR CF'!AC25 | J25: ='QTR CF'!AD25+'QTR CF'!AE25+'QTR CF'!AF25+'QTR CF'!AG25 | K25: ='QTR CF'!AH25+'QTR CF'!AI25+'QTR CF'!AJ25+'QTR CF'!AK25 | L25: ='QTR CF'!AL25+'QTR CF'!AM25+'QTR CF'!AN25+'QTR CF'!AO25 | M25: ='QTR CF'!AP25+'QTR CF'!AQ25+'QTR CF'!AR25+'QTR CF'!AS25
A26: Accrued Expenses | B26: 0 | C26: 0 | D26: 26484 | E26: 34644 | F26: -8025 | G26: 85398 | H26: 45618 | I26: ='QTR CF'!Z26+'QTR CF'!AA26+'QTR CF'!AB26+'QTR CF'!AC26 | J26: ='QTR CF'!AD26+'QTR CF'!AE26+'QTR CF'!AF26+'QTR CF'!AG26 | K26: ='QTR CF'!AH26+'QTR CF'!AI26+'QTR CF'!AJ26+'QTR CF'!AK26 | L26: ='QTR CF'!AL26+'QTR CF'!AM26+'QTR CF'!AN26+'QTR CF'!AO26 | M26: ='QTR CF'!AP26+'QTR CF'!AQ26+'QTR CF'!AR26+'QTR CF'!AS26
A27: Change in Income Taxes | B27: 0 | C27: 0 | D27: 1357 | E27: -164 | F27: 48102 | G27: -39536 | H27: 38750 | I27: ='QTR CF'!Z27+'QTR CF'!AA27+'QTR CF'!AB27+'QTR CF'!AC27 | J27: ='QTR CF'!AD27+'QTR CF'!AE27+'QTR CF'!AF27+'QTR CF'!AG27 | K27: ='QTR CF'!AH27+'QTR CF'!AI27+'QTR CF'!AJ27+'QTR CF'!AK27 | L27: ='QTR CF'!AL27+'QTR CF'!AM27+'QTR CF'!AN27+'QTR CF'!AO27 | M27: ='QTR CF'!AP27+'QTR CF'!AQ27+'QTR CF'!AR27+'QTR CF'!AS27
... A33: Net Change in Other Working Capital | B33: 0 | C33: 0 | D33: 0 | E33: 0 | F33: 0 | G33: 0 | H33: 2481 | I33: ='QTR CF'!Z33+'QTR CF'!AA33+'QTR CF'!AB33+'QTR CF'!AC33 | J33: ='QTR CF'!AD33+'QTR CF'!AE33+'QTR CF'!AF33+'QTR CF'!AG33 | K33: ='QTR CF'!AH33+'QTR CF'!AI33+'QTR CF'!AJ33+'QTR CF'!AK33 | L33: ='QTR CF'!AL33+'QTR CF'!AM33+'QTR CF'!AN33+'QTR CF'!AO33 | M33: ='QTR CF'!AP33+'QTR CF'!AQ33+'QTR CF'!AR33+'QTR CF'!AS33
A34: Cash Flow from Operations | B34: =SUM(B2:B33) | C34: =SUM(C2:C33) | D34: =SUM(D2:D33) | E34: =SUM(E2:E33) | F34: =SUM(F2:F33) | G34: =SUM(G2:G33) | H34: =SUM(H2:H33) | I34: =SUM(I2:I33) | ... N34: =SUM(N2:N33)
A35: Collections from Note Receivable | B35: 0 | C35: 1331.011 | D35: 1886 | E35: 2592 | F35: 3233 | G35: 0 | H35: 0 | I35: ='QTR CF'!Z35+'QTR CF'!AA35+'QTR CF'!AB35+'QTR CF'!AC35 | J35: ='QTR CF'!AD35+'QTR CF'!AE35+'QTR CF'!AF35+'QTR CF'!AG35 | K35: ='QTR CF'!AH35+'QTR CF'!AI35+'QTR CF'!AJ35+'QTR CF'!AK35 | L35: ='QTR CF'!AL35+'QTR CF'!AM35+'QTR CF'!AN35+'QTR CF'!AO35 | M35: ='QTR CF'!AP35+'QTR CF'!AQ35+'QTR CF'!AR35+'QTR CF'!AS35
A36: Purchase of PP&E | B36: -77.974 | C36: -573.751 | D36: -3150 | E36: -8264 | F36: -17433 | G36: -23390 | H36: -36067 | I36: ='QTR CF'!Z36+'QTR CF'!AA36+'QTR CF'!AB36+'QTR CF'!AC36 | J36: ='QTR CF'!AD36+'QTR CF'!AE36+'QTR CF'!AF36+'QTR CF'!AG36 | K36: ='QTR CF'!AH36+'QTR CF'!AI36+'QTR CF'!AJ36+'QTR CF'!AK36 | L36: ='QTR CF'!AL36+'QTR CF'!AM36+'QTR CF'!AN36+'QTR CF'!AO36 | M36: ='QTR CF'!AP36+'QTR CF'!AQ36+'QTR CF'!AR36+'QTR CF'!AS36
A37: Purchase of Non-Marketable Equity Securities | B37: 0 | C37: 0 | D37: 0 | E37: 0 | F37: 0 | G37: -3000 | H37: -10000 | I37: ='QTR CF'!Z37+'QTR CF'!AA37+'QTR CF'!AB37+'QTR CF'!AC37 | J37: ='QTR CF'!AD37+'QTR CF'!AE37+'QTR CF'!AF37+'QTR CF'!AG37 | K37: ='QTR CF'!AH37+'QTR CF'!AI37+'QTR CF'!AJ37+'QTR CF'!AK37 | L37: ='QTR CF'!AL37+'QTR CF'!AM37+'QTR CF'!AN37+'QTR CF'!AO37 | M37: ='QTR CF'!AP37+'QTR CF'!AQ37+'QTR CF'!AR37+'QTR CF'!AS37
A38: Acquisition of Big Beverages | B38: 0 | C38: 0 | D38: 0 | E38: 0 | F38: 0 | G38: -75336 | H38: 0 | I38: ='QTR CF'!Z38+'QTR CF'!AA38+'QTR CF'!AB38+'QTR CF'!AC38 | J38: ='QTR CF'!AD38+'QTR CF'!AE38+'QTR CF'!AF38+'QTR CF'!AG38 | K38: ='QTR CF'!AH38+'QTR CF'!AI38+'QTR CF'!AJ38+'QTR CF'!AK38 | L38: ='QTR CF'!AL38+'QTR CF'!AM38+'QTR CF'!AN38+'QTR CF'!AO38 | M38: ='QTR CF'!AP38+'QTR CF'!AQ38+'QTR CF'!AR38+'QTR CF'!AS38
A39: Acquisitions, Net of Cash Acquired | B39: -14188.056 | C39: 0 | D39: 0 | E39: 0 | F39: 0 | G39: 0 | H39: -1278769 | I39: ='QTR CF'!Z39+'QTR CF'!AA39+'QTR CF'!AB39+'QTR CF'!AC39 | J39: ='QTR CF'!AD39+'QTR CF'!AE39+'QTR CF'!AF39+'QTR CF'!AG39 | K39: ='QTR CF'!AH39+'QTR CF'!AI39+'QTR CF'!AJ39+'QTR CF'!AK39 | L39: ='QTR CF'!AL39+'QTR CF'!AM39+'QTR CF'!AN39+'QTR CF'!AO39 | M39: ='QTR CF'!AP39+'QTR CF'!AQ39+'QTR CF'!AR39+'QTR CF'!AS39
A40: Working Capital Estimate from Pepsi (Rockstar) | B40: 0 | C40: 0 | D40: 0 | E40: 0 | F40: 0 | G40: 0 | H40: 29156 | I40: ='QTR CF'!Z40+'QTR CF'!AA40+'QTR CF'!AB40+'QTR CF'!AC40 | J40: ='QTR CF'!AD40+'QTR CF'!AE40+'QTR CF'!AF40+'QTR CF'!AG40 | K40: ='QTR CF'!AH40+'QTR CF'!AI40+'QTR CF'!AJ40+'QTR CF'!AK40 | L40: ='QTR CF'!AL40+'QTR CF'!AM40+'QTR CF'!AN40+'QTR CF'!AO40 | M40: ='QTR CF'!AP40+'QTR CF'!AQ40+'QTR CF'!AR40+'QTR CF'!AS40
A41: Cash Flow from Investing | B41: =SUM(B35:B40) | C41: =SUM(C35:C40) | D41: =SUM(D35:D40) | E41: =SUM(E35:E40) | F41: =SUM(F35:F40) | G41: =SUM(G35:G40) | H41: =SUM(H35:H40) | I41: =SUM(I35:I40) | ... N41: =SUM(N35:N40)
A42: Proceeds from Related-Party Notes | B42: 1500 | C42: 0 | D42: 0 | E42: 0 | F42: 0 | G42: 0 | H42: 0 | I42: ='QTR CF'!Z42+'QTR CF'!AA42+'QTR CF'!AB42+'QTR CF'!AC42 | J42: ='QTR CF'!AD42+'QTR CF'!AE42+'QTR CF'!AF42+'QTR CF'!AG42 | K42: ='QTR CF'!AH42+'QTR CF'!AI42+'QTR CF'!AJ42+'QTR CF'!AK42 | L42: ='QTR CF'!AL42+'QTR CF'!AM42+'QTR CF'!AN42+'QTR CF'!AO42 | M42: ='QTR CF'!AP42+'QTR CF'!AQ42+'QTR CF'!AR42+'QTR CF'!AS42
A43: Payments on Bonds Payable | B43: 0 | C43: -9601.531 | D43: 0 | E43: 0 | F43: 0 | G43: 0 | H43: 0 | I43: ='QTR CF'!Z43+'QTR CF'!AA43+'QTR CF'!AB43+'QTR CF'!AC43 | J43: ='QTR CF'!AD43+'QTR CF'!AE43+'QTR CF'!AF43+'QTR CF'!AG43 | K43: ='QTR CF'!AH43+'QTR CF'!AI43+'QTR CF'!AJ43+'QTR CF'!AK43 | L43: ='QTR CF'!AL43+'QTR CF'!AM43+'QTR CF'!AN43+'QTR CF'!AO43 | M43: ='QTR CF'!AP43+'QTR CF'!AQ43+'QTR CF'!AR43+'QTR CF'!AS43
A44: Finance Lease Payments | B44: -26.486 | C44: -280.208 | D44: -94 | E44: -63 | F44: -44 | G44: -61 | H44: 0 | I44: ='QTR CF'!Z44+'QTR CF'!AA44+'QTR CF'!AB44+'QTR CF'!AC44 | J44: ='QTR CF'!AD44+'QTR CF'!AE44+'QTR CF'!AF44+'QTR CF'!AG44 | K44: ='QTR CF'!AH44+'QTR CF'!AI44+'QTR CF'!AJ44+'QTR CF'!AK44 | L44: ='QTR CF'!AL44+'QTR CF'!AM44+'QTR CF'!AN44+'QTR CF'!AO44 | M44: ='QTR CF'!AP44+'QTR CF'!AQ44+'QTR CF'!AR44+'QTR CF'!AS44
A45: Proceeds from Exercise of Stock Options | B45: 224.083 | C45: 4126.791 | D45: 3720 | E45: 3683 | F45: 2285 | G45: 3856 | H45: 0 | I45: ='QTR CF'!Z46+'QTR CF'!AA46+'QTR CF'!AB46+'QTR CF'!AC46 | J45: ='QTR CF'!AD46+'QTR CF'!AE46+'QTR CF'!AF46+'QTR CF'!AG46 | K45: ='QTR CF'!AH46+'QTR CF'!AI46+'QTR CF'!AJ46+'QTR CF'!AK46 | L45: ='QTR CF'!AL46+'QTR CF'!AM46+'QTR CF'!AN46+'QTR CF'!AO46 | M45: ='QTR CF'!AP46+'QTR CF'!AQ46+'QTR CF'!AR46+'QTR CF'!AS46
A46: Cash Paid for RSU Tax Withholding | B46: 0 | C46: -656.68 | D46: 0 | E46: 0 | F46: 0 | G46: 0 | H46: 0 | I46: ='QTR CF'!Z47+'QTR CF'!AA47+'QTR CF'!AB47+'QTR CF'!AC47 | J46: ='QTR CF'!AD47+'QTR CF'!AE47+'QTR CF'!AF47+'QTR CF'!AG47 | K46: ='QTR CF'!AH47+'QTR CF'!AI47+'QTR CF'!AJ47+'QTR CF'!AK47 | L46: ='QTR CF'!AL47+'QTR CF'!AM47+'QTR CF'!AN47+'QTR CF'!AO47 | M46: ='QTR CF'!AP47+'QTR CF'!AQ47+'QTR CF'!AR47+'QTR CF'!AS47
A47: Section 16(b) Short-Swing Profit Recovery | B47: 0 | C47: 90.8 | D47: 0 | E47: 0 | F47: 0 | G47: 0 | H47: 0 | I47: ='QTR CF'!Z48+'QTR CF'!AA48+'QTR CF'!AB48+'QTR CF'!AC48 | J47: ='QTR CF'!AD48+'QTR CF'!AE48+'QTR CF'!AF48+'QTR CF'!AG48 | K47: ='QTR CF'!AH48+'QTR CF'!AI48+'QTR CF'!AJ48+'QTR CF'!AK48 | L47: ='QTR CF'!AL48+'QTR CF'!AM48+'QTR CF'!AN48+'QTR CF'!AO48 | M47: ='QTR CF'!AP48+'QTR CF'!AQ48+'QTR CF'!AR48+'QTR CF'!AS48
A48: Proceeds from Issuance of Common Stock | B48: 26955.437 | C48: 21892.316 | D48: 67769 | E48: 0 | F48: 0 | G48: 0 | H48: 0 | I48: ='QTR CF'!Z45+'QTR CF'!AA45+'QTR CF'!AB45+'QTR CF'!AC45 | J48: ='QTR CF'!AD45+'QTR CF'!AE45+'QTR CF'!AF45+'QTR CF'!AG45 | K48: ='QTR CF'!AH45+'QTR CF'!AI45+'QTR CF'!AJ45+'QTR CF'!AK45 | L48: ='QTR CF'!AL45+'QTR CF'!AM45+'QTR CF'!AN45+'QTR CF'!AO45 | M48: ='QTR CF'!AP45+'QTR CF'!AQ45+'QTR CF'!AR45+'QTR CF'!AS45
A49: Proceeds from Issuance of Preferred Stock | B49: 0 | C49: 0 | D49: 0 | E49: 542018 | F49: 0 | G49: 0 | H49: 0 | I49: ='QTR CF'!Z49+'QTR CF'!AA49+'QTR CF'!AB49+'QTR CF'!AC49 | J49: ='QTR CF'!AD49+'QTR CF'!AE49+'QTR CF'!AF49+'QTR CF'!AG49 | K49: ='QTR CF'!AH49+'QTR CF'!AI49+'QTR CF'!AJ49+'QTR CF'!AK49 | L49: ='QTR CF'!AL49+'QTR CF'!AM49+'QTR CF'!AN49+'QTR CF'!AO49 | M49: ='QTR CF'!AP49+'QTR CF'!AQ49+'QTR CF'!AR49+'QTR CF'!AS49
A50: Preferred Dividends | B50: 0 | C50: 0 | D50: 0 | E50: -11526 | F50: -27462 | G50: -27500 | H50: -37608 | I50: ='QTR CF'!Z50+'QTR CF'!AA50+'QTR CF'!AB50+'QTR CF'!AC50 | J50: ='QTR CF'!AD50+'QTR CF'!AE50+'QTR CF'!AF50+'QTR CF'!AG50 | K50: ='QTR CF'!AH50+'QTR CF'!AI50+'QTR CF'!AJ50+'QTR CF'!AK50 | L50: ='QTR CF'!AL50+'QTR CF'!AM50+'QTR CF'!AN50+'QTR CF'!AO50 | M50: ='QTR CF'!AP50+'QTR CF'!AQ50+'QTR CF'!AR50+'QTR CF'!AS50
A51: Share Repurchases | B51: 0 | C51: 0 | D51: 0 | E51: 0 | F51: 0 | G51: -2261 | H51: -45504 | I51: ='QTR CF'!Z51+'QTR CF'!AA51+'QTR CF'!AB51+'QTR CF'!AC51 | J51: ='QTR CF'!AD51+'QTR CF'!AE51+'QTR CF'!AF51+'QTR CF'!AG51 | K51: ='QTR CF'!AH51+'QTR CF'!AI51+'QTR CF'!AJ51+'QTR CF'!AK51 | L51: ='QTR CF'!AL51+'QTR CF'!AM51+'QTR CF'!AN51+'QTR CF'!AO51 | M51: ='QTR CF'!AP51+'QTR CF'!AQ51+'QTR CF'!AR51+'QTR CF'!AS51
A52: Proceeds from Issuance of Long-Term Debt | B52: 0 | C52: 0 | D52: 0 | E52: 0 | F52: 0 | G52: 0 | H52: 900000 | I52: ='QTR CF'!Z52+'QTR CF'!AA52+'QTR CF'!AB52+'QTR CF'!AC52 | J52: ='QTR CF'!AD52+'QTR CF'!AE52+'QTR CF'!AF52+'QTR CF'!AG52 | K52: ='QTR CF'!AH52+'QTR CF'!AI52+'QTR CF'!AJ52+'QTR CF'!AK52 | L52: ='QTR CF'!AL52+'QTR CF'!AM52+'QTR CF'!AN52+'QTR CF'!AO52 | M52: ='QTR CF'!AP52+'QTR CF'!AQ52+'QTR CF'!AR52+'QTR CF'!AS52
A53: Repayments of Long-Term Debt | B53: 0 | C53: 0 | D53: 0 | E53: 0 | F53: 0 | G53: 0 | H53: -201750 | I53: ='QTR CF'!Z53+'QTR CF'!AA53+'QTR CF'!AB53+'QTR CF'!AC53 | J53: ='QTR CF'!AD53+'QTR CF'!AE53+'QTR CF'!AF53+'QTR CF'!AG53 | K53: ='QTR CF'!AH53+'QTR CF'!AI53+'QTR CF'!AJ53+'QTR CF'!AK53 | L53: ='QTR CF'!AL53+'QTR CF'!AM53+'QTR CF'!AN53+'QTR CF'!AO53 | M53: ='QTR CF'!AP53+'QTR CF'!AQ53+'QTR CF'!AR53+'QTR CF'!AS53
A54: Debt Issuance Fees | B54: 0 | C54: 0 | D54: 0 | E54: 0 | F54: 0 | G54: 0 | H54: -32367 | I54: ='QTR CF'!Z54+'QTR CF'!AA54+'QTR CF'!AB54+'QTR CF'!AC54 | J54: ='QTR CF'!AD54+'QTR CF'!AE54+'QTR CF'!AF54+'QTR CF'!AG54 | K54: ='QTR CF'!AH54+'QTR CF'!AI54+'QTR CF'!AJ54+'QTR CF'!AK54 | L54: ='QTR CF'!AL54+'QTR CF'!AM54+'QTR CF'!AN54+'QTR CF'!AO54 | M54: ='QTR CF'!AP54+'QTR CF'!AQ54+'QTR CF'!AR54+'QTR CF'!AS54
A55: Other Financing Activities | B55: 0 | C55: 0 | D55: 0 | E55: 0 | F55: 0 | G55: 0 | H55: -7 | I55: ='QTR CF'!Z55+'QTR CF'!AA55+'QTR CF'!AB55+'QTR CF'!AC55 | J55: ='QTR CF'!AD55+'QTR CF'!AE55+'QTR CF'!AF55+'QTR CF'!AG55 | K55: ='QTR CF'!AH55+'QTR CF'!AI55+'QTR CF'!AJ55+'QTR CF'!AK55 | L55: ='QTR CF'!AL55+'QTR CF'!AM55+'QTR CF'!AN55+'QTR CF'!AO55 | M55: ='QTR CF'!AP55+'QTR CF'!AQ55+'QTR CF'!AR55+'QTR CF'!AS55
A56: Cash Flow from Financing | B56: =SUM(B42:B55) | C56: =SUM(C42:C55) | D56: =SUM(D42:D55) | E56: =SUM(E42:E55) | F56: =SUM(F42:F55) | G56: =SUM(G42:G55) | H56: =SUM(H42:H55) | I56: =SUM(I42:I55) | ... N56: =SUM(N42:N55)
A57: FX Effect on Cash | B57: -73.491 | C57: 433.507 | D57: -538 | E57: 50 | F57: 1257 | G57: -997 | H57: 3271 | I57: ='QTR CF'!Z57+'QTR CF'!AA57+'QTR CF'!AB57+'QTR CF'!AC57 | J57: ='QTR CF'!AD57+'QTR CF'!AE57+'QTR CF'!AF57+'QTR CF'!AG57 | K57: ='QTR CF'!AH57+'QTR CF'!AI57+'QTR CF'!AJ57+'QTR CF'!AK57 | L57: ='QTR CF'!AL57+'QTR CF'!AM57+'QTR CF'!AN57+'QTR CF'!AO57 | M57: ='QTR CF'!AP57+'QTR CF'!AQ57+'QTR CF'!AR57+'QTR CF'!AS57
A58: Net Change in Cash | B58: =B34+B41+B56+B57 | C58: =C34+C41+C56+C57 | D58: =D34+D41+D56+D57 | E58: =E34+E41+E56+E57 | F58: =F34+F41+F56+F57 | G58: =G34+G41+G56+G57 | H58: =H34+H41+H56+H57 | I58: =I34+I41+I56+I57 | ... N58: =N34+N41+N56+N57

Sheet YTD P&L
B1: Q1 FY2019 | C1: Q2 FY2019 | D1: Q3 FY2019 | E1: Q1 FY2020 | F1: Q2 FY2020 | G1: Q3 FY2020 | H1: Q1 FY2021 | I1: Q2 FY2021 | J1: Q3 FY2021 | K1: Q1 FY2022 | L1: Q2 FY2022 | M1: Q3 FY2022 | N1: Q1 FY2023 | O1: Q2 FY2023 | P1: Q3 FY2023 | Q1: Q1 FY2024 | R1: Q2 FY2024 | S1: Q3 FY2024 | T1: Q1 FY2025 | U1: Q2 FY2025 | V1: Q3 FY2025
A2: Net Sales / Revenue | B2: 14485.65 | C2: 30607.579 | D2: 51031.426 | E2: 28184.889 | F2: 58222.116 | G2: 95061.265 | H2: 50034.879 | I2: 115108.2 | J2: 210017.3 | K2: 133388 | L2: 287408 | M2: 475640 | N2: 259939 | O2: 585822 | P2: 970579 | Q2: 355708 | R2: 757685 | S2: 1023433 | T2: 329276 | U2: 1068535 | V2: 1793641
A3: COGS | B3: -8764.592 | C3: -18020.49 | D3: -29821.968 | E3: -15182.706 | F3: -32207.118 | G3: -51512.534 | H3: -29455.784 | I3: -66279.738 | J3: -123495.47 | K3: -79494 | L3: -174195 | M3: -283778 | N3: -146121 | O3: -313010 | P3: -503685 | Q3: -173501 | R3: -366380 | S3: -509899 | T3: -156903 | U3: -515311 | V3: -868138
A4: Gross Profit (Loss) | B4: =B2+B3 | C4: =C2+C3 | D4: =D2+D3 | E4: =E2+E3 | F4: =F2+F3 | G4: =G2+G3 | H4: =H2+H3 | I4: =I2+I3 | ... V4: =V2+V3
A5: Sales and Marketing | B5: -3601.003 | C5: -9162.942 | D5: -14086.91 | E5: -7506.047 | F5: -15372.918 | G5: -23640.914 | H5: -11959.053 | I5: -27490.041 | J5: -50111.103 | K5: -31597 | L5: -64072 | M5: -262782 | N5: 0 | O5: 0 | P5: 0 | Q5: 0 | R5: 0 | S5: 0 | T5: 0 | U5: 0 | V5: 0
A6: General and Administrative | B6: -2622.102 | C6: -5054.848 | D6: -7249.378 | E6: -4247.853 | F6: -7902.571 | G6: -12460.009 | H6: -7806.666 | I6: -16926.198 | J6: -28066.228 | K6: -12181 | L6: -26595 | M6: -54135 | N6: 0 | O6: 0 | P6: 0 | Q6: 0 | R6: 0 | S6: 0 | T6: 0 | U6: 0 | V6: 0
A7: Operating Expenses | B7: -6223.105 | C7: -14217.79 | D7: -21336.288 | E7: -11753.9 | F7: -23275.489 | G7: -36100.923 | H7: -19765.719 | I7: -44416.239 | J7: -78177.331 | K7: -43778 | L7: -90667 | M7: -316917 | N7: 0 | O7: 0 | P7: 0 | Q7: 0 | R7: 0 | S7: 0 | T7: 0 | U7: 0 | V7: 0
A8: SG&A | B8: 0 | C8: 0 | D8: 0 | E8: 0 | F8: 0 | G8: 0 | H8: 0 | I8: 0 | J8: 0 | K8: 0 | L8: 0 | M8: 0 | N8: -68905 | O8: -163086 | P8: -259471 | Q8: -99017 | R8: -213867 | S8: -339310 | T8: -120342 | U8: -358228 | V8: -563799
A9: Distributor Termination Fees | B9: 0 | C9: 0 | D9: 0 | E9: 0 | F9: 0 | G9: 0 | H9: 0 | I9: 0 | J9: 0 | K9: 0 | L9: 0 | M9: 0 | N9: 0 | O9: 0 | P9: 0 | Q9: 0 | R9: 0 | S9: 0 | T9: 0 | U9: 0 | V9: -246707
A10: Income (Loss) from Operations | B10: =B4+SUM(B5:B9) | C10: =C4+SUM(C5:C9) | D10: =D4+SUM(D5:D9) | E10: =E4+SUM(E5:E9) | F10: =F4+SUM(F5:F9) | G10: =G4+SUM(G5:G9) | H10: =H4+SUM(H5:H9) | I10: =I4+SUM(I5:I9) | ... V10: =V4+SUM(V5:V9)
A11: Interest Income (Expense) | B11: -114.572 | C11: -238.809 | D11: -779.749 | E11: -341.718 | F11: -394.85 | G11: -642.249 | H11: 84.925 | I11: 160.141 | J11: 232.09 | K11: 76 | L11: 129 | M11: 1579 | N11: 4969 | O11: 10542 | P11: 17767 | Q11: 9640 | R11: 20287 | S11: 31399 | T11: 7846 | U11: -6196 | V11: -19592
A12: Other Income (Expense) | B12: 12273.213 | C12: 12052.809 | D12: 12050.921 | E12: -282.591 | F12: -511.491 | G12: -361.705 | H12: -11.621 | I12: 97.038 | J12: 0 | K12: 0 | L12: 0 | M12: 0 | N12: 0 | O12: 0 | P12: 0 | Q12: 0 | R12: 0 | S12: 0 | T12: 1116 | U12: 1658 | V12: 7022
A13: Foreign Currency Gain (Loss) | B13: 260.665 | C13: 0 | D13: 0 | E13: -192.413 | F13: -119.105 | G13: 262.022 | H13: -301.256 | I13: -123.636 | J13: -451.217 | K13: -162 | L13: -676 | M13: -930 | N13: -118 | O13: -1049 | P13: -1226 | Q13: -369 | R13: -633 | S13: -356 | T13: 0 | U13: 0 | V13: 0
A14: Gain (Loss) on Lease Cancellations | B14: 0 | C14: 0 | D14: 0 | E14: 0 | F14: 152.112 | G14: 152.112 | H14: 0 | I14: 0 | J14: 0 | K14: 0 | L14: 0 | M14: 0 | N14: 0 | O14: 0 | P14: 0 | Q14: 0 | R14: 0 | S14: 0 | T14: 0 | U14: 0 | V14: 0
A15: Income Tax (Expense) Benefit | B15: 0 | C15: 0 | D15: 0 | E15: 0 | F15: 0 | G15: 0 | H15: 0 | I15: 0 | J15: -833.819 | K15: -3351 | L15: -6161 | M15: -41653 | N15: -8537 | O15: -26483 | P15: -47279 | Q15: -14650 | R15: -39498 | S15: -41317 | T15: -16574 | U15: -46184 | V15: -19167
A16: Pre-Tax Income (Loss) | B16: =B10+SUM(B11:B15) | C16: =C10+SUM(C11:C15) | D16: =D10+SUM(D11:D15) | E16: =E10+SUM(E11:E15) | F16: =F10+SUM(F11:F15) | G16: =G10+SUM(G11:G15) | H16: =H10+SUM(H11:H15) | I16: =I10+SUM(I11:I15) | ... V16: =V10+SUM(V11:V15)
A17: Net Income (Loss) | B17: =B16 | C17: =C16 | D17: =D16 | E17: =E16 | F17: =F16 | G17: =G16 | H17: =H16 | I17: =I16 | ... V17: =V16
A18: Basic Earnings (Loss) per Share | B18: 0.2 | C18: 0.18 | D18: 0.19 | E18: 0.01 | F18: 0.03 | G18: 0.1 | H18: 0.01 | I18: 0 | J18: 0 | K18: 0 | L18: 0 | M18: 0 | N18: 0 | O18: 0 | P18: 0 | Q18: 0 | R18: 0 | S18: 0 | T18: 0 | U18: 0 | V18: 0
A19: Diluted Earnings (Loss) per Share | B19: 0.19 | C19: 0.17 | D19: 0.2 | E19: 0.01 | F19: 0.03 | G19: 0.09 | H19: 0.01 | I19: 0 | J19: 0 | K19: 0 | L19: 0 | M19: 0 | N19: 0 | O19: 0 | P19: 0 | Q19: 0 | R19: 0 | S19: 0 | T19: 0 | U19: 0 | V19: 0
A20: Weighted Average Shares Outstanding (Basic) | B20: 57155445 | C20: 57267622 | D20: 58023685 | E20: 69284307 | F20: 69444655 | G20: 70184071 | H20: 72516396 | I20: 0 | J20: 0 | K20: 0 | L20: 0 | M20: 0 | N20: 0 | O20: 0 | P20: 0 | Q20: 0 | R20: 0 | S20: 0 | T20: 0 | U20: 0 | V20: 0
A21: Weighted Average Shares Outstanding (Diluted) | B21: 61687409 | C21: 61817621 | D21: 62050032 | E21: 70339416 | F21: 71073534 | G21: 73524209 | H21: 76925484 | I21: 0 | J21: 0 | K21: 0 | L21: 0 | M21: 0 | N21: 0 | O21: 0 | P21: 0 | Q21: 0 | R21: 0 | S21: 0 | T21: 0 | U21: 0 | V21: 0
A22: Preferred Dividends | B22: 0 | C22: 0 | D22: 0 | E22: 0 | F22: 0 | G22: 0 | H22: 0 | I22: 0 | J22: 0 | K22: 0 | L22: 0 | M22: -4596 | N22: -6781 | O22: -13637 | P22: -20512 | Q22: -6837 | R22: -13675 | S22: -20588 | T22: -6781 | U22: -13632 | V22: -23289
A23: Income Allocated to Participating Preferred | B23: 0 | C23: 0 | D23: 0 | E23: 0 | F23: 0 | G23: 0 | H23: 0 | I23: 0 | J23: 0 | K23: 0 | L23: 0 | M23: 0 | N23: 0 | O23: -6727 | P23: -13263 | Q23: -6128 | R23: -12417 | S23: -12357 | T23: -3219 | U23: -10703 | V23: -5272
A24: Net Income (Loss) Attributable to Common Shareholders | B24: =B17+B22+B23 | C24: =C17+C22+C23 | D24: =D17+D22+D23 | E24: =E17+E22+E23 | F24: =F17+F22+F23 | G24: =G17+G22+G23 | H24: =H17+H22+H23 | I24: =I17+I22+I23 | ... V24: =V17+V22+V23

Sheet YTD BS
B1: Q4 FY2019 | C1: Q1 FY2020 | D1: Q2 FY2020 | E1: Q3 FY2020 | F1: Q4 FY2020 | G1: Q1 FY2021 | H1: Q2 FY2021 | I1: Q3 FY2021 | J1: Q4 FY2021 | K1: Q1 FY2022 | L1: Q2 FY2022 | M1: Q3 FY2022 | N1: Q4 FY2022 | O1: Q1 FY2023 | P1: Q2 FY2023 | Q1: Q3 FY2023 | R1: Q4 FY2023 | S1: Q1 FY2024 | T1: Q2 FY2024 | U1: Q3 FY2024 | V1: Q4 FY2024 | W1: Q1 FY2025 | X1: Q2 FY2025 | Y1: Q3 FY2025
A2: Cash, Cash Equivalents & Restricted Cash | B2: 23090.682 | C2: 19094.101 | D2: 20110.815 | E2: 52158.098 | F2: 43248.021 | G2: 31634.675 | H2: 83789.981 | I2: 61377.202 | J2: 16255 | K2: 25532 | L2: 60031 | M2: 726972 | N2: 652927 | O2: 633581 | P2: 681054 | Q2: 760022 | R2: 755981 | S2: 879498 | T2: 903210 | U2: 903748 | V2: 890190 | W2: 977285 | X2: 615233 | Y2: 932463
A3: Accounts Receivable | B3: 7774.618 | C3: 10699.811 | D3: 12221.985 | E3: 16561.371 | F3: 14986.213 | G3: 23997.68 | H3: 32398.823 | I3: 43500.578 | J3: 38741 | K3: 72707 | L3: 66195 | M3: 117003 | N3: 63311 | O3: 172032 | P3: 197811 | Q3: 215243 | R3: 183703 | S3: 200117 | T3: 262920 | U3: 208774 | V3: 270342 | W3: 256424 | X3: 490389 | Y3: 513682
A4: Note Receivable - Current | B4: 1181.116 | C4: 1157.754 | D4: 1742.841 | E4: 1810.773 | F4: 1885.887 | G4: 2509.412 | H4: 2545.745 | I4: 2543.225 | J4: 2588 | K4: 5833 | L4: 3066 | M4: 2888 | N4: 2979 | O4: 3587 | P4: 3323 | Q4: 3309 | R4: 2318 | S4: 2259 | T4: 1166 | U4: 1025 | V4: 0 | W4: 0 | X4: 0 | Y4: 0
A5: Inventories | B5: 15292.349 | C5: 21038.367 | D5: 23512.418 | E5: 15679.192 | F5: 18403.622 | G5: 36891.859 | H5: 63826.596 | I5: 122311.45 | J5: 191222 | K5: 184094 | L5: 162138 | M5: 153933 | N5: 173289 | O5: 154280 | P5: 152545 | Q5: 198704 | R5: 229275 | S5: 197504 | T5: 180669 | U5: 197572 | V5: 131165 | W5: 141159 | X5: 230046 | Y5: 282514
A6: Prepaid Expenses | B6: 4170.136 | C6: 4671.721 | D6: 4312.554 | E6: 4731.887 | F6: 14626.922 | G6: 17183.929 | H6: 22744.642 | I6: 22829.51 | J6: 13555 | K6: 10042 | L6: 12298 | M6: 12096 | N6: 11341 | O6: 15507 | P6: 23398 | Q6: 23747 | R6: 19503 | S6: 21523 | T6: 22900 | U6: 38227 | V6: 18759 | W6: 22464 | X6: 41420 | Y6: 163395
A7: Deferred Other Costs - Current | B7: 0 | C7: 0 | D7: 0 | E7: 0 | F7: 0 | G7: 0 | H7: 0 | I7: 0 | J7: 0 | K7: 0 | L7: 0 | M7: 14124 | N7: 14124 | O7: 14124 | P7: 14124 | Q7: 14124 | R7: 14124 | S7: 14124 | T7: 14124 | U7: 14124 | V7: 14124 | W7: 14124 | X7: 14124 | Y7: 49520
A8: Total Current Assets | B8: =SUM(B2:B7) | C8: =SUM(C2:C7) | D8: =SUM(D2:D7) | E8: =SUM(E2:E7) | F8: =SUM(F2:F7) | G8: =SUM(G2:G7) | H8: =SUM(H2:H7) | I8: =SUM(I2:I7) | ... Y8: =SUM(Y2:Y7)
A9: Note Receivable - Non-Current | B9: 10630.041 | C9: 10416.12 | D9: 8714.205 | E9: 9053.866 | F9: 9429.437 | G9: 6900.882 | H9: 7000.8 | I9: 6993.869 | J9: 7117 | K9: 3888 | L9: 3679 | M9: 3465 | N9: 3574 | O9: 0 | P9: 0 | Q9: 0 | R9: 0 | S9: 0 | T9: 0 | U9: 0 | V9: 0 | W9: 0 | X9: 0 | Y9: 0
A10: Net PP&E | B10: 132.889 | C10: 115.324 | D10: 398.315 | E10: 467.38 | F10: 579.377 | G10: 1169.022 | H10: 1617.002 | I10: 2454.914 | J10: 3180 | K10: 3702 | L10: 5135 | M10: 5782 | N10: 10185 | O10: 12054 | P10: 15892 | Q10: 21061 | R10: 24868 | S10: 28350 | T10: 36282 | U10: 38370 | V10: 55602 | W10: 58698 | X10: 72516 | Y10: 80925
A11: ROU Assets - Operating - Non-Current | B11: 0 | C11: 0 | D11: 0 | E11: 0 | F11: 836.038 | G11: 791.969 | H11: 704.857 | I11: 888.911 | J11: 1128 | K11: 1141 | L11: 954 | M11: 1105 | N11: 972 | O11: 931 | P11: 756 | Q11: 1152 | R11: 1957 | S11: 1688 | T11: 1507 | U11: 5506 | V11: 21606 | W11: 20866 | X11: 0 | Y11: 0
A12: Intangible Assets | B12: 17173 | C12: 17029.472 | D12: 16888.97 | E12: 16740.838 | F12: 16590.083 | G12: 16439.197 | H12: 16287.537 | I12: 16811.762 | J12: 16301 | K12: 15838 | L12: 14689 | M12: 11322 | N12: 12254 | O12: 12359 | P12: 12211 | Q12: 11772 | R12: 12139 | S12: 11741 | T12: 11491 | U12: 11877 | V12: 12213 | W12: 12444 | X12: 1222115 | Y12: 1397819
A13: Goodwill | B13: 10023.806 | C13: 10023.806 | D13: 10419.321 | E13: 10419.321 | F13: 10419.321 | G13: 10419.321 | H13: 10419.321 | I13: 14851.635 | J13: 14527 | K13: 14238 | L13: 13323 | M13: 12502 | N13: 13679 | O13: 13949 | P13: 13937 | Q13: 13588 | R13: 14173 | S13: 13866 | T13: 13730 | U13: 14360 | V13: 71582 | W13: 72128 | X13: 802234 | Y13: 914957
A14: Deferred Other Costs - Non-Current | B14: 0 | C14: 0 | D14: 0 | E14: 0 | F14: 0 | G14: 0 | H14: 0 | I14: 0 | J14: 0 | K14: 0 | L14: 0 | M14: 265993 | N14: 262462 | O14: 258931 | P14: 255400 | Q14: 251869 | R14: 248338 | S14: 244807 | T14: 241276 | U14: 237746 | V14: 234215 | W14: 230684 | X14: 227153 | Y14: 784214
A15: Deferred Tax Assets | B15: 0 | C15: 0 | D15: 0 | E15: 0 | F15: 0 | G15: 0 | H15: 0 | I15: 0 | J15: 9019 | K15: 6396 | L15: 7686 | M15: 0 | N15: 501 | O15: 482 | P15: 28373 | Q15: 30614 | R15: 29518 | S15: 22437 | T15: 22727 | U15: 24186 | V15: 38699 | W15: 38525 | X15: 43158 | Y15: 110410
A16: ROU Assets - Finance - Non-Current | B16: 809.466 | C16: 626.12 | D16: 524.15 | E16: 415.595 | F16: 162.119 | G16: 129.625 | H16: 100.365 | I16: 106.675 | J16: 86 | K16: 220 | L16: 180 | M16: 222 | N16: 208 | O16: 191 | P16: 171 | Q16: 148 | R16: 208 | S16: 263 | T16: 233 | U16: 214 | V16: 0 | W16: 0 | X16: 0 | Y16: 0
A17: Other Non-Current Assets | B17: 104.134 | C17: 55.358 | D17: 53.523 | E17: 60.875 | F17: 122.733 | G17: 110.1 | H17: 112.456 | I17: 308.449 | J17: 300 | K17: 293 | L17: 264 | M17: 242 | N17: 263 | O17: 263 | P17: 254 | Q17: 265 | R17: 291 | S17: 7963 | T17: 6653 | U17: 8594 | V17: 8384 | W17: 14717 | X17: 36755 | Y17: 35809
A18: Total Assets | B18: =B8+SUM(B9:B17) | C18: =C8+SUM(C9:C17) | D18: =D8+SUM(D9:D17) | E18: =E8+SUM(E9:E17) | F18: =F8+SUM(F9:F17) | G18: =G8+SUM(G9:G17) | H18: =H8+SUM(H9:H17) | I18: =I8+SUM(I9:I17) | ... Y18: =Y8+SUM(Y9:Y17)
A19: Accounts Payable | B19: 17292.647 | C19: 19885.182 | D19: 20149.301 | E19: 18117.611 | F19: 25412.753 | G19: 37525.39 | H19: 52992.075 | I19: 91931.593 | J19: 91479 | K19: 109307 | L19: 102416 | M19: 143947 | N19: 107340 | O19: 107112 | P19: 94313 | Q19: 121088 | R19: 42840 | S19: 40196 | T19: 47423 | U19: 30938 | V19: 41287 | W19: 61052 | X19: 120962 | Y19: 97794
A20: Accrued Expenses | B20: 0 | C20: 0 | D20: 0 | E20: 0 | F20: 0 | G20: 0 | H20: 0 | I20: 0 | J20: 0 | K20: 0 | L20: 0 | M20: 0 | N20: 0 | O20: 0 | P20: 0 | Q20: 0 | R20: 62120 | S20: 63871 | T20: 79633 | U20: 73024 | V20: 148780 | W20: 152046 | X20: 225859 | Y20: 311768
A21: Income Taxes Payable | B21: 0 | C21: 0 | D21: 0 | E21: 0 | F21: 0 | G21: 0 | H21: 0 | I21: 0 | J21: 0 | K21: 0 | L21: 0 | M21: 0 | N21: 0 | O21: 0 | P21: 58798 | Q21: 58855 | R21: 50424 | S21: 58619 | T21: 5374 | U21: 739 | V21: 10834 | W21: 26206 | X21: 21765 | Y21: 49590
A22: Accrued Distributor Termination Fees | B22: 0 | C22: 0 | D22: 0 | E22: 0 | F22: 0 | G22: 0 | H22: 0 | I22: 0 | J22: 0 | K22: 0 | L22: 0 | M22: 115551 | N22: 3986 | O22: 1063 | P22: 0 | Q22: 0 | R22: 0 | S22: 0 | T22: 0 | U22: 0 | V22: 0 | W22: 0 | X22: 0 | Y22: 252953
A23: Accrued Promotional Allowance | B23: 0 | C23: 0 | D23: 0 | E23: 0 | F23: 0 | G23: 0 | H23: 0 | I23: 0 | J23: 0 | K23: 0 | L23: 0 | M23: 0 | N23: 35977 | O23: 68225 | P23: 98933 | Q23: 136557 | R23: 99787 | S23: 129201 | T23: 156479 | U23: 158810 | V23: 135948 | W23: 151327 | X23: 200169 | Y23: 234068
A24: Lease Liability - Operating - Current | B24: 649.074 | C24: 587.69 | D24: 411.946 | E24: 397.931 | F24: 321.283 | G24: 337.626 | H24: 318.142 | I24: 376.602 | J24: 512 | K24: 569 | L24: 556 | M24: 663 | N24: 661 | O24: 605 | P24: 505 | Q24: 628 | R24: 980 | S24: 821 | T24: 729 | U24: 1358 | V24: 3265 | W24: 3550 | X24: 0 | Y24: 0
A25: Bonds Payable, Net | B25: 8634.279 | C25: 8599.75 | D25: 8953.266 | E25: 9540.007 | F25: 0 | G25: 0 | H25: 0 | I25: 0 | J25: 0 | K25: 0 | L25: 0 | M25: 0 | N25: 0 | O25: 0 | P25: 0 | Q25: 0 | R25: 0 | S25: 0 | T25: 0 | U25: 0 | V25: 0 | W25: 0 | X25: 0 | Y25: 0
A26: Lease Liability - Finance - Current | B26: 0 | C26: 0 | D26: 0 | E26: 0 | F26: 205.824 | G26: 192.649 | H26: 191.753 | I26: 155.508 | J26: 157 | K26: 141 | L26: 101 | M26: 95 | N26: 70 | O26: 69 | P26: 67 | Q26: 63 | R26: 59 | S26: 61 | T26: 61 | U26: 99 | V26: 0 | W26: 0 | X26: 0 | Y26: 0
A27: Contingent Consideration - Current | B27: 0 | C27: 0 | D27: 0 | E27: 0 | F27: 0 | G27: 0 | H27: 0 | I27: 0 | J27: 0 | K27: 0 | L27: 0 | M27: 0 | N27: 0 | O27: 0 | P27: 0 | Q27: 0 | R27: 0 | S27: 0 | T27: 0 | U27: 0 | V27: 0 | W27: 0 | X27: 25000 | Y27: 25000
A28: Deferred Revenue - Current | B28: 0 | C28: 0 | D28: 0 | E28: 0 | F28: 0 | G28: 0 | H28: 0 | I28: 0 | J28: 0 | K28: 0 | L28: 0 | M28: 7770 | N28: 9675 | O28: 9563 | P28: 9500 | Q28: 9500 | R28: 9513 | S28: 9513 | T28: 9513 | U28: 9513 | V28: 9513 | W28: 9513 | X28: 16071 | Y28: 25557
A29: Other Current Liabilities | B29: 107.399 | C29: 160.646 | D29: 561.617 | E29: 716.678 | F29: 425.232 | G29: 586.954 | H29: 754.907 | I29: 957.627 | J29: 976 | K29: 1734 | L29: 2761 | M29: 3267 | N29: 3586 | O29: 5094 | P29: 7109 | Q29: 8826 | R29: 10890 | S29: 12987 | T29: 13772 | U29: 14979 | V29: 15908 | W29: 14160 | X29: 49949 | Y29: 32258
A30: Total Current Liabilities | B30: =SUM(B19:B29) | C30: =SUM(C19:C29) | D30: =SUM(D19:D29) | E30: =SUM(E19:E29) | F30: =SUM(F19:F29) | G30: =SUM(G19:G29) | H30: =SUM(H19:H29) | I30: =SUM(I19:I29) | ... Y30: =SUM(Y19:Y29)
A31: Lease Liability - Operating - Non-Current | B31: 239.848 | C31: 188.789 | D31: 203.101 | E31: 124.978 | F31: 514.948 | G31: 436.631 | H31: 391.157 | I31: 550.547 | J31: 658 | K31: 597 | L31: 420 | M31: 462 | N31: 326 | O31: 336 | P31: 249 | Q31: 512 | R31: 955 | S31: 850 | T31: 762 | U31: 4193 | V31: 16674 | W31: 16152 | X31: 0 | Y31: 0
A32: Lease Liability - Finance - Non-Current | B32: 0 | C32: 0 | D32: 0 | E32: 0 | F32: 82.29 | G32: 87.152 | H32: 60.731 | I32: 88.649 | J32: 45 | K32: 138 | L32: 138 | M32: 167 | N32: 162 | O32: 156 | P32: 147 | Q32: 135 | R32: 193 | S32: 245 | T32: 228 | U32: 189 | V32: 0 | W32: 0 | X32: 0 | Y32: 0
A33: Deferred Tax Liability | B33: 0 | C33: 0 | D33: 0 | E33: 0 | F33: 0 | G33: 0 | H33: 0 | I33: 3497.24 | J33: 3146 | K33: 3084 | L33: 2886 | M33: 25457 | N33: 15919 | O33: 19250 | P33: 2333 | Q33: 2249 | R33: 2880 | S33: 2248 | T33: 2201 | U33: 2275 | V33: 0 | W33: 0 | X33: 0 | Y33: 0
A34: Long-Term Debt | B34: 0 | C34: 0 | D34: 0 | E34: 0 | F34: 0 | G34: 0 | H34: 0 | I34: 0 | J34: 0 | K34: 0 | L34: 0 | M34: 0 | N34: 0 | O34: 0 | P34: 0 | Q34: 0 | R34: 0 | S34: 0 | T34: 0 | U34: 0 | V34: 0 | W34: 0 | X34: 862917 | Y34: 861472
A35: Deferred Revenue - Non-Current | B35: 0 | C35: 0 | D35: 0 | E35: 0 | F35: 0 | G35: 0 | H35: 0 | I35: 0 | J35: 0 | K35: 0 | L35: 0 | M35: 146333 | N35: 179788 | O35: 175275 | P35: 171745 | Q35: 169370 | R35: 167227 | S35: 164849 | T35: 162471 | U35: 160092 | V35: 157714 | W35: 155336 | X35: 156135 | Y35: 387432
A36: Other Non-Current Liabilities | B36: 0 | C36: 0 | D36: 0 | E36: 0 | F36: 0 | G36: 0 | H36: 0 | I36: 22.198 | J36: 0 | K36: 0 | L36: 487 | M36: 0 | N36: 0 | O36: 0 | P36: 0 | Q36: 0 | R36: 0 | S36: 0 | T36: 0 | U36: 0 | V36: 2541 | W36: 2574 | X36: 25002 | Y36: 24431
A37: Total Liabilities | B37: =B30+SUM(B31:B36) | C37: =C30+SUM(C31:C36) | D37: =D30+SUM(D31:D36) | E37: =E30+SUM(E31:E36) | F37: =F30+SUM(F31:F36) | G37: =G30+SUM(G31:G36) | H37: =H30+SUM(H31:H36) | I37: =I30+SUM(I31:I36) | ... Y37: =Y30+SUM(Y31:Y36)
A38: Convertible Preferred Stock | B38: 0 | C38: 0 | D38: 0 | E38: 0 | F38: 0 | G38: 0 | H38: 0 | I38: 0 | J38: 0 | K38: 0 | L38: 0 | M38: 824488 | N38: 824488 | O38: 824488 | P38: 824488 | Q38: 824488 | R38: 824488 | S38: 824488 | T38: 824488 | U38: 824488 | V38: 824488 | W38: 824488 | X38: 824488 | Y38: 1760275
A39: Common Stock | B39: 68.942 | C39: 69.28 | D39: 69.563 | E39: 71.652 | F39: 72.263 | G39: 72.586 | H39: 74.471 | I39: 74.746 | J39: 75 | K39: 75 | L39: 76 | M39: 76 | N39: 76 | O39: 77 | P39: 77 | Q39: 77 | R39: 77 | S39: 78 | T39: 78 | U39: 79 | V39: 79 | W39: 79 | X39: 101 | Y39: 101
A40: Treasury Stock | B40: 0 | C40: 0 | D40: 0 | E40: 0 | F40: 0 | G40: 0 | H40: 0 | I40: 0 | J40: 0 | K40: 0 | L40: 0 | M40: 0 | N40: 0 | O40: 0 | P40: 0 | Q40: 0 | R40: 0 | S40: 0 | T40: 0 | U40: 0 | V40: 0 | W40: 0 | X40: 0 | Y40: 0
A41: Additional Paid-in Capital | B41: 127553 | C41: 129168.01 | D41: 130832.04 | E41: 156548.45 | F41: 159884.15 | G41: 164174.74 | H41: 237763.61 | I41: 244293.71 | J41: 267847 | K41: 272967 | L41: 277623 | M41: 281133 | N41: 280668 | O41: 279872 | P41: 278980 | Q41: 277980 | R41: 276717 | S41: 281247 | T41: 286173 | U41: 292576 | V41: 297579 | W41: 300877 | X41: 1028384 | Y41: 1035021
A42: Accumulated Other Comprehensive Income (Loss) | B42: -753.52 | C42: -868.01 | D42: -976.691 | E42: -866.664 | F42: -202.142 | G42: -394.651 | H42: -117.656 | I42: 1165.027 | J42: 614 | K42: 123 | L42: -2173 | M42: -4211 | N42: -1881 | O42: -1287 | P42: -1877 | Q42: -2541 | R42: -701 | S42: -2055 | T42: -2363 | U42: -338 | V42: -3250 | W42: -1001 | X42: 2178 | Y42: 2508
A43: Retained Earnings (Accumulated Deficit) | B43: -63409.431 | C43: -62863.38 | D43: -61305.046 | E43: -56551.443 | F43: -55426.832 | G43: -54841.408 | H43: -50881.064 | I43: -48135.273 | J43: -51490 | K43: -44811 | L43: -35653 | M43: -217549 | N43: -238772 | O43: -197627 | P43: -146118 | Q43: -62169 | R43: -12053 | S43: 58921 | T43: 131866 | U43: 131309 | V43: 105521 | W43: 143159 | X43: 236163 | Y43: 165480
A44: Total Stockholders' Equity | B44: =SUM(B38:B43) | C44: =SUM(C38:C43) | D44: =SUM(D38:D43) | E44: =SUM(E38:E43) | F44: =SUM(F38:F43) | G44: =SUM(G38:G43) | H44: =SUM(H38:H43) | I44: =SUM(I38:I43) | ... Y44: =SUM(Y38:Y43)
A45: Total Liabilities, Mezzanine & Stockholders' Equity | B45: =B37+B44 | C45: =C37+C44 | D45: =D37+D44 | E45: =E37+E44 | F45: =F37+F44 | G45: =G37+G44 | H45: =H37+H44 | I45: =I37+I44 | ... Y45: =Y37+Y44

Sheet YTD CF
B1: Q1 FY2020 | C1: Q2 FY2020 | D1: Q3 FY2020 | E1: Q1 FY2021 | F1: Q2 FY2021 | G1: Q3 FY2021 | H1: Q1 FY2022 | I1: Q2 FY2022 | J1: Q3 FY2022 | K1: Q1 FY2023 | L1: Q2 FY2023 | M1: Q3 FY2023 | N1: Q1 FY2024 | O1: Q2 FY2024 | P1: Q3 FY2024 | Q1: Q1 FY2025 | R1: Q2 FY2025 | S1: Q3 FY2025
A2: Net Income (Loss) | B2: 546.051 | C2: 2104.385 | D2: 6857.988 | E2: 585.424 | F2: 4545.768 | G2: 7291.559 | H2: 6679 | I2: 15838 | J2: -166059 | K2: 41227 | L2: 92736 | M2: 176685 | N2: 77811 | O2: 157594 | P2: 163950 | Q2: 44419 | R2: 144274 | S2: 83260
A3: Depreciation | B3: 124.939 | C3: 50.351 | D3: 82.18 | E3: 108.198 | F3: 178.425 | G3: 519.765 | H3: 245 | I3: 556 | J3: 952 | K3: 404 | L3: 953 | M3: 1676 | N3: 0 | O3: 0 | P3: 0 | Q3: 0 | R3: 0 | S3: 0
A4: Amortization | B4: 309.597 | C4: 851.045 | D4: 1224.684 | E4: 187.67 | F4: 375.141 | G4: 550.8 | H4: 141 | I4: 275 | J4: 402 | K4: 145 | L4: 294 | M4: 445 | N4: 0 | O4: 0 | P4: 0 | Q4: 0 | R4: 0 | S4: 0
A5: Impairment of Intangibles | B5: 0 | C5: 0 | D5: 0 | E5: 0 | F5: 0 | G5: 0 | H5: 0 | I5: 0 | J5: 2379 | K5: 0 | L5: 0 | M5: 0 | N5: 0 | O5: 0 | P5: 0 | Q5: 0 | R5: 0 | S5: 0
A6: Depreciation & Amortization | B6: 0 | C6: 0 | D6: 0 | E6: 0 | F6: 0 | G6: 0 | H6: 0 | I6: 0 | J6: 0 | K6: 0 | L6: 0 | M6: 0 | N6: 1229 | O6: 2648 | P6: 4888 | Q6: 2611 | R6: 11730 | S6: 20516
A7: Allowance for Credit Losses | B7: 221.222 | C7: 221.182 | D7: 244.685 | E7: 223.034 | F7: 854.606 | G7: -207.261 | H7: 455 | I7: 466 | J7: 705 | K7: 837 | L7: 1088 | M7: 1880 | N7: 2250 | O7: 4072 | P7: 4279 | Q7: 2077 | R7: 5529 | S7: 3226
A8: Amortization of Deferred Other Costs | B8: 0 | C8: 0 | D8: 0 | E8: 0 | F8: 0 | G8: 0 | H8: 0 | I8: 0 | J8: 2354 | K8: 3531 | L8: 7062 | M8: 10593 | N8: 3531 | O8: 7062 | P8: 10593 | Q8: 3531 | R8: 7062 | S8: 13391
A9: Inventory Write-Down | B9: -270.71 | C9: -137.37 | D9: 211.822 | E9: 753.935 | F9: 1260.076 | G9: 12.234 | H9: 2596 | I9: 331 | J9: 1078 | K9: 1672 | L9: -3888 | M9: 2677 | N9: 2386 | O9: 11554 | P9: 17118 | Q9: 5337 | R9: 15262 | S9: 22313
A10: Gain (Loss) on Disposal of PP&E | B10: 0 | C10: 0 | D10: 0 | E10: 0 | F10: 0 | G10: 0 | H10: 0 | I10: 0 | J10: 0 | K10: 0 | L10: 191 | M10: 195 | N10: -8 | O10: 31 | P10: 126 | Q10: 0 | R10: 0 | S10: 0
A11: Stock-Based Compensation | B11: 1400 | C11: 2574.999 | D11: 4718.699 | E11: 3575.001 | F11: 7597.26 | G11: 13400.581 | H11: 4310 | I11: 8517 | J11: 14780 | K11: 5507 | L11: 11242 | M11: 16221 | N11: 3563 | O11: 8309 | P11: 13685 | Q11: 5029 | R11: 11463 | S11: 18847
A12: Gain on China Transaction | B12: 144.403 | C12: 23.1 | D12: -384.493 | E12: 0 | F12: 0 | G12: 0 | H12: 0 | I12: 0 | J12: 0 | K12: 0 | L12: 0 | M12: 0 | N12: 0 | O12: 0 | P12: 0 | Q12: 0 | R12: 0 | S12: 0
A13: Gain (Loss) on Lease Cancellations | B13: 0 | C13: -152.112 | D13: -152.112 | E13: 0 | F13: 0 | G13: -14.669 | H13: 0 | I13: 0 | J13: 0 | K13: 0 | L13: 0 | M13: 0 | N13: 0 | O13: 0 | P13: 0 | Q13: 0 | R13: 0 | S13: 0
... A33: Net Change in Other Working Capital | B33: 0 | C33: 0 | D33: 0 | E33: 0 | F33: 0 | G33: 532.395 | H33: 0 | I33: 488 | J33: 0 | K33: 0 | L33: 0 | M33: 0 | N33: 0 | O33: 0 | P33: 0 | Q33: 148 | R33: -1210 | S33: -1786
A34: Cash Flow from Operations | B34: =SUM(B2:B33) | C34: =SUM(C2:C33) | D34: =SUM(D2:D33) | E34: =SUM(E2:E33) | F34: =SUM(F2:F33) | G34: =SUM(G2:G33) | H34: =SUM(H2:H33) | I34: =SUM(I2:I33) | ... S34: =SUM(S2:S33)
A35: Collections from Note Receivable | B35: 0 | C35: 1331.011 | D35: 1331.011 | E35: 1876.273 | F35: 1876.273 | G35: 1885.724 | H35: 0 | I35: 2592 | J35: 2592 | K35: 3233 | L35: 3233 | M35: 3233 | N35: 0 | O35: 0 | P35: 0 | Q35: 0 | R35: 0 | S35: 0
A36: Purchase of PP&E | B36: -107.372 | C36: -315.777 | D36: -416.671 | E36: -697.843 | F36: -1216.05 | G36: -2395.302 | H36: -742 | I36: -2456 | J36: -3477 | K36: -2253 | L36: -6810 | M36: -12687 | N36: -4525 | O36: -13739 | P36: -17983 | Q36: -6944 | R36: -15194 | S36: -25539
A37: Purchase of Non-Marketable Equity Securities | B37: 0 | C37: 0 | D37: 0 | E37: 0 | F37: 0 | G37: 0 | H37: 0 | I37: 0 | J37: 0 | K37: 0 | L37: 0 | M37: 0 | N37: 0 | O37: 0 | P37: -3000 | Q37: 0 | R37: -5000 | S37: -5000
A38: Acquisition of Big Beverages | B38: 0 | C38: 0 | D38: 0 | E38: 0 | F38: 0 | G38: 0 | H38: 0 | I38: 0 | J38: 0 | K38: 0 | L38: 0 | M38: 0 | N38: 0 | O38: 0 | P38: 0 | Q38: 0 | R38: 0 | S38: 0
A39: Acquisitions, Net of Cash Acquired | B39: 0 | C39: 0 | D39: 0 | E39: 0 | F39: 0 | G39: 0 | H39: 0 | I39: 0 | J39: 0 | K39: 0 | L39: 0 | M39: 0 | N39: 0 | O39: 0 | P39: 0 | Q39: 0 | R39: -1256351 | S39: -1278769
A40: Working Capital Estimate from Pepsi (Rockstar) | B40: 0 | C40: 0 | D40: 0 | E40: 0 | F40: 0 | G40: 0 | H40: 0 | I40: 0 | J40: 0 | K40: 0 | L40: 0 | M40: 0 | N40: 0 | O40: 0 | P40: 0 | Q40: 0 | R40: 0 | S40: 30617
A41: Cash Flow from Investing | B41: =SUM(B35:B40) | C41: =SUM(C35:C40) | D41: =SUM(D35:D40) | E41: =SUM(E35:E40) | F41: =SUM(F35:F40) | G41: =SUM(G35:G40) | H41: =SUM(H35:H40) | I41: =SUM(I35:I40) | ... S41: =SUM(S35:S40)
A42: Proceeds from Related-Party Notes | B42: 0 | C42: 0 | D42: 0 | E42: 0 | F42: 0 | G42: 0 | H42: 0 | I42: 0 | J42: 0 | K42: 0 | L42: 0 | M42: 0 | N42: 0 | O42: 0 | P42: 0 | Q42: 0 | R42: 0 | S42: 0
A43: Payments on Bonds Payable | B43: 0 | C43: 0 | D43: 0 | E43: 0 | F43: 0 | G43: 0 | H43: 0 | I43: 0 | J43: 0 | K43: 0 | L43: 0 | M43: 0 | N43: 0 | O43: 0 | P43: 0 | Q43: 0 | R43: 0 | S43: 0
A44: Finance Lease Payments | B44: -64.082 | C44: -222.052 | D44: -259.231 | E44: -25.149 | F44: -49.592 | G44: -72.386 | H44: -20 | I44: -37 | J44: -49 | K44: -11 | L44: -22 | M44: -33 | N44: -15 | O44: -30 | P44: -46 | Q44: 0 | R44: 0 | S44: 0
A45: Proceeds from Issuance of Common Stock | B45: 0 | C45: 0 | D45: 21983.116 | E45: 0 | F45: 67769.386 | G45: 67769.386 | H45: 0 | I45: 0 | J45: 0 | K45: 0 | L45: 0 | M45: 0 | N45: 0 | O45: 0 | P45: 0 | Q45: 0 | R45: 0 | S45: 0
A46: Proceeds from Exercise of Stock Options | B46: 215.347 | C46: 704.664 | D46: 2296.343 | E46: 715.91 | F46: 2515.017 | G46: 3242.073 | H46: 810 | I46: 1260 | J46: 3104 | K46: 478 | L46: 707 | M46: 1603 | N46: 967 | O46: 1147 | P46: 3832 | Q46: 0 | R46: 0 | S46: 0
A47: Cash Paid for RSU Tax Withholding | B47: 0 | C47: 0 | D47: 0 | E47: 0 | F47: 0 | G47: 0 | H47: 0 | I47: 0 | J47: 0 | K47: 0 | L47: 0 | M47: 0 | N47: 0 | O47: 0 | P47: 0 | Q47: 0 | R47: 0 | S47: 0
A48: Section 16(b) Short-Swing Profit Recovery | B48: 0 | C48: 0 | D48: 0 | E48: 0 | F48: 0 | G48: 0 | H48: 0 | I48: 0 | J48: 0 | K48: 0 | L48: 0 | M48: 0 | N48: 0 | O48: 0 | P48: 0 | Q48: 0 | R48: 0 | S48: 0
A49: Proceeds from Issuance of Preferred Stock | B49: 0 | C49: 0 | D49: 0 | E49: 0 | F49: 0 | G49: 0 | H49: 0 | I49: 0 | J49: 542018 | K49: 0 | L49: 0 | M49: 0 | N49: 0 | O49: 0 | P49: 0 | Q49: 0 | R49: 0 | S49: 0
A50: Preferred Dividends | B50: 0 | C50: 0 | D50: 0 | E50: 0 | F50: 0 | G50: 0 | H50: 0 | I50: 0 | J50: -4596 | K50: -6781 | L50: -13637 | M50: -20512 | N50: -6837 | O50: -13675 | P50: -20588 | Q50: -6781 | R50: -13632 | S50: -23301
A51: Share Repurchases | B51: 0 | C51: 0 | D51: 0 | E51: 0 | F51: 0 | G51: 0 | H51: 0 | I51: 0 | J51: 0 | K51: 0 | L51: 0 | M51: 0 | N51: 0 | O51: 0 | P51: -1658 | Q51: -1932 | R51: -2811 | S51: -3259
A52: Proceeds from Issuance of Long-Term Debt | B52: 0 | C52: 0 | D52: 0 | E52: 0 | F52: 0 | G52: 0 | H52: 0 | I52: 0 | J52: 0 | K52: 0 | L52: 0 | M52: 0 | N52: 0 | O52: 0 | P52: 0 | Q52: 0 | R52: 900000 | S52: 900000
A53: Repayments of Long-Term Debt | B53: 0 | C53: 0 | D53: 0 | E53: 0 | F53: 0 | G53: 0 | H53: 0 | I53: 0 | J53: 0 | K53: 0 | L53: 0 | M53: 0 | N53: 0 | O53: 0 | P53: 0 | Q53: 0 | R53: 0 | S53: -2250
... A55: Other Financing Activities | B55: 0 | C55: 0 | D55: 0 | E55: 0 | F55: 0 | G55: 0 | H55: 0 | I55: 0 | J55: 0 | K55: 0 | L55: 0 | M55: 0 | N55: 0 | O55: 0 | P55: 0 | Q55: 321 | R55: 319 | S55: 301
A56: Cash Flow from Financing | B56: =SUM(B42:B55) | C56: =SUM(C42:C55) | D56: =SUM(D42:D55) | E56: =SUM(E42:E55) | F56: =SUM(F42:F55) | G56: =SUM(G42:G55) | H56: =SUM(H42:H55) | I56: =SUM(I42:I55) | ... S56: =SUM(S42:S55)
A57: FX Effect on Cash | B57: -222.93 | C57: -231.635 | D57: 289.338 | E57: -164.536 | F57: -23.61 | G57: -236.365 | H57: 104 | I57: 121 | J57: 158 | K57: -181 | L57: -555 | M57: -555 | N57: -722 | O57: -766 | P57: -16 | Q57: 1259 | R57: 2214 | S57: 2174
A58: Net Change in Cash | B58: =B34+B41+B56+B57 | C58: =C34+C41+C56+C57 | D58: =D34+D41+D56+D57 | E58: =E34+E41+E56+E57 | F58: =F34+F41+F56+F57 | G58: =G34+G41+G56+G57 | H58: =H34+H41+H56+H57 | I58: =I34+I41+I56+I57 | ... S58: =S34+S41+S56+S57

Sheet QTR P&L
B1: Q1 FY2019 | C1: Q2 FY2019 | D1: Q3 FY2019 | E1: Q4 FY2019 | F1: Q1 FY2020 | G1: Q2 FY2020 | H1: Q3 FY2020 | I1: Q4 FY2020 | J1: Q1 FY2021 | K1: Q2 FY2021 | L1: Q3 FY2021 | M1: Q4 FY2021 | N1: Q1 FY2022 | O1: Q2 FY2022 | P1: Q3 FY2022 | Q1: Q4 FY2022 | R1: Q1 FY2023 | S1: Q2 FY2023 | T1: Q3 FY2023 | U1: Q4 FY2023 | V1: Q1 FY2024 | W1: Q2 FY2024 | X1: Q3 FY2024 | Y1: Q4 FY2024 | Z1: Q1 FY2025 | AA1: Q2 FY2025 | AB1: Q3 FY2025 | AC1: Q4 FY2025 | AD1: Q1 FY2026E | AE1: Q2 FY2026E | AF1: Q3 FY2026E | AG1: Q4 FY2026E | AH1: Q1 FY2027E | AI1: Q2 FY2027E | AJ1: Q3 FY2027E | AK1: Q4 FY2027E | AL1: Q1 FY2028E | AM1: Q2 FY2028E | AN1: Q3 FY2028E | AO1: Q4 FY2028E | AP1: Q1 FY2029E | AQ1: Q2 FY2029E | AR1: Q3 FY2029E | AS1: Q4 FY2029E | AT1: Q1 FY2030E | AU1: Q2 FY2030E | AV1: Q3 FY2030E | AW1: Q4 FY2030E
A2: Net Sales / Revenue | B2: ='YTD P&L'!B2 | C2: ='YTD P&L'!C2-'YTD P&L'!B2 | D2: ='YTD P&L'!D2-'YTD P&L'!C2 | E2: ='ANNL P&L'!B2-'YTD P&L'!D2 | F2: ='YTD P&L'!E2 | G2: ='YTD P&L'!F2-'YTD P&L'!E2 | H2: ='YTD P&L'!G2-'YTD P&L'!F2 | I2: ='ANNL P&L'!C2-'YTD P&L'!G2 | J2: ='YTD P&L'!H2 | K2: ='YTD P&L'!I2-'YTD P&L'!H2 | L2: ='YTD P&L'!J2-'YTD P&L'!I2 | M2: ='ANNL P&L'!D2-'YTD P&L'!J2 | N2: ='YTD P&L'!K2 | O2: ='YTD P&L'!L2-'YTD P&L'!K2 | P2: ='YTD P&L'!M2-'YTD P&L'!L2 | Q2: ='ANNL P&L'!E2-'YTD P&L'!M2 | R2: ='YTD P&L'!N2 | S2: ='YTD P&L'!O2-'YTD P&L'!N2 | T2: ='YTD P&L'!P2-'YTD P&L'!O2 | U2: ='ANNL P&L'!F2-'YTD P&L'!P2 | V2: ='YTD P&L'!Q2 | W2: ='YTD P&L'!R2-'YTD P&L'!Q2 | X2: ='YTD P&L'!S2-'YTD P&L'!R2 | Y2: ='ANNL P&L'!G2-'YTD P&L'!S2 | Z2: ='YTD P&L'!T2 | AA2: ='YTD P&L'!U2-'YTD P&L'!T2 | AB2: ='YTD P&L'!V2-'YTD P&L'!U2 | AC2: ='ANNL P&L'!H2-'YTD P&L'!V2 | AD2: =IF('IS DRIVERS'!$B2="QoQ",'QTR P&L'!AC2,'QTR P&L'!Z2)*(1+'IS DRIVERS'!AE2) | AE2: =IF('IS DRIVERS'!$B2="QoQ",'QTR P&L'!AD2,'QTR P&L'!AA2)*(1+'IS DRIVERS'!AF2) | AF2: =IF('IS DRIVERS'!$B2="QoQ",'QTR P&L'!AE2,'QTR P&L'!AB2)*(1+'IS DRIVERS'!AG2) | AG2: =IF('IS DRIVERS'!$B2="QoQ",'QTR P&L'!AF2,'QTR P&L'!AC2)*(1+'IS DRIVERS'!AH2) | AH2: =IF('IS DRIVERS'!$B2="QoQ",'QTR P&L'!AG2,'QTR P&L'!AD2)*(1+'IS DRIVERS'!AI2) | AI2: =IF('IS DRIVERS'!$B2="QoQ",'QTR P&L'!AH2,'QTR P&L'!AE2)*(1+'IS DRIVERS'!AJ2) | AJ2: =IF('IS DRIVERS'!$B2="QoQ",'QTR P&L'!AI2,'QTR P&L'!AF2)*(1+'IS DRIVERS'!AK2) | AK2: =IF('IS DRIVERS'!$B2="QoQ",'QTR P&L'!AJ2,'QTR P&L'!AG2)*(1+'IS DRIVERS'!AL2) | ... AW2: =IF('IS DRIVERS'!$B2="QoQ",'QTR P&L'!AV2,'QTR P&L'!AS2)*(1+'IS DRIVERS'!AX2)
A3: COGS | B3: ='YTD P&L'!B3 | C3: ='YTD P&L'!C3-'YTD P&L'!B3 | D3: ='YTD P&L'!D3-'YTD P&L'!C3 | E3: ='ANNL P&L'!B3-'YTD P&L'!D3 | F3: ='YTD P&L'!E3 | G3: ='YTD P&L'!F3-'YTD P&L'!E3 | H3: ='YTD P&L'!G3-'YTD P&L'!F3 | I3: ='ANNL P&L'!C3-'YTD P&L'!G3 | J3: ='YTD P&L'!H3 | K3: ='YTD P&L'!I3-'YTD P&L'!H3 | L3: ='YTD P&L'!J3-'YTD P&L'!I3 | M3: ='ANNL P&L'!D3-'YTD P&L'!J3 | N3: ='YTD P&L'!K3 | O3: ='YTD P&L'!L3-'YTD P&L'!K3 | P3: ='YTD P&L'!M3-'YTD P&L'!L3 | Q3: ='ANNL P&L'!E3-'YTD P&L'!M3 | R3: ='YTD P&L'!N3 | S3: ='YTD P&L'!O3-'YTD P&L'!N3 | T3: ='YTD P&L'!P3-'YTD P&L'!O3 | U3: ='ANNL P&L'!F3-'YTD P&L'!P3 | V3: ='YTD P&L'!Q3 | W3: ='YTD P&L'!R3-'YTD P&L'!Q3 | X3: ='YTD P&L'!S3-'YTD P&L'!R3 | Y3: ='ANNL P&L'!G3-'YTD P&L'!S3 | Z3: ='YTD P&L'!T3 | AA3: ='YTD P&L'!U3-'YTD P&L'!T3 | AB3: ='YTD P&L'!V3-'YTD P&L'!U3 | AC3: ='ANNL P&L'!H3-'YTD P&L'!V3 | AD3: ='QTR P&L'!AD2*'IS DRIVERS'!AE3 | AE3: ='QTR P&L'!AE2*'IS DRIVERS'!AF3 | AF3: ='QTR P&L'!AF2*'IS DRIVERS'!AG3 | AG3: ='QTR P&L'!AG2*'IS DRIVERS'!AH3 | AH3: ='QTR P&L'!AH2*'IS DRIVERS'!AI3 | AI3: ='QTR P&L'!AI2*'IS DRIVERS'!AJ3 | AJ3: ='QTR P&L'!AJ2*'IS DRIVERS'!AK3 | AK3: ='QTR P&L'!AK2*'IS DRIVERS'!AL3 | ... AW3: ='QTR P&L'!AW2*'IS DRIVERS'!AX3
A4: Gross Profit (Loss) | B4: ='YTD P&L'!B4 | C4: ='YTD P&L'!C4-'YTD P&L'!B4 | D4: ='YTD P&L'!D4-'YTD P&L'!C4 | E4: ='ANNL P&L'!B4-'YTD P&L'!D4 | F4: ='YTD P&L'!E4 | G4: ='YTD P&L'!F4-'YTD P&L'!E4 | H4: ='YTD P&L'!G4-'YTD P&L'!F4 | I4: ='ANNL P&L'!C4-'YTD P&L'!G4 | J4: ='YTD P&L'!H4 | K4: ='YTD P&L'!I4-'YTD P&L'!H4 | L4: ='YTD P&L'!J4-'YTD P&L'!I4 | M4: ='ANNL P&L'!D4-'YTD P&L'!J4 | N4: ='YTD P&L'!K4 | O4: ='YTD P&L'!L4-'YTD P&L'!K4 | P4: ='YTD P&L'!M4-'YTD P&L'!L4 | Q4: ='ANNL P&L'!E4-'YTD P&L'!M4 | R4: ='YTD P&L'!N4 | S4: ='YTD P&L'!O4-'YTD P&L'!N4 | T4: ='YTD P&L'!P4-'YTD P&L'!O4 | U4: ='ANNL P&L'!F4-'YTD P&L'!P4 | V4: ='YTD P&L'!Q4 | W4: ='YTD P&L'!R4-'YTD P&L'!Q4 | X4: ='YTD P&L'!S4-'YTD P&L'!R4 | Y4: ='ANNL P&L'!G4-'YTD P&L'!S4 | Z4: ='YTD P&L'!T4 | AA4: ='YTD P&L'!U4-'YTD P&L'!T4 | AB4: ='YTD P&L'!V4-'YTD P&L'!U4 | AC4: ='ANNL P&L'!H4-'YTD P&L'!V4 | AD4: =AD2+AD3 | AE4: =AE2+AE3 | AF4: =AF2+AF3 | AG4: =AG2+AG3 | AH4: =AH2+AH3 | AI4: =AI2+AI3 | AJ4: =AJ2+AJ3 | AK4: =AK2+AK3 | ... AW4: =AW2+AW3
A5: Sales and Marketing | B5: ='YTD P&L'!B5 | C5: ='YTD P&L'!C5-'YTD P&L'!B5 | D5: ='YTD P&L'!D5-'YTD P&L'!C5 | E5: ='ANNL P&L'!B5-'YTD P&L'!D5 | F5: ='YTD P&L'!E5 | G5: ='YTD P&L'!F5-'YTD P&L'!E5 | H5: ='YTD P&L'!G5-'YTD P&L'!F5 | I5: ='ANNL P&L'!C5-'YTD P&L'!G5 | J5: ='YTD P&L'!H5 | K5: ='YTD P&L'!I5-'YTD P&L'!H5 | L5: ='YTD P&L'!J5-'YTD P&L'!I5 | M5: ='ANNL P&L'!D5-'YTD P&L'!J5 | N5: ='YTD P&L'!K5 | O5: ='YTD P&L'!L5-'YTD P&L'!K5 | P5: ='YTD P&L'!M5-'YTD P&L'!L5 | Q5: ='ANNL P&L'!E5-'YTD P&L'!M5 | R5: ='YTD P&L'!N5 | S5: ='YTD P&L'!O5-'YTD P&L'!N5 | T5: ='YTD P&L'!P5-'YTD P&L'!O5 | U5: ='ANNL P&L'!F5-'YTD P&L'!P5 | V5: ='YTD P&L'!Q5 | W5: ='YTD P&L'!R5-'YTD P&L'!Q5 | X5: ='YTD P&L'!S5-'YTD P&L'!R5 | Y5: ='ANNL P&L'!G5-'YTD P&L'!S5 | Z5: ='YTD P&L'!T5 | AA5: ='YTD P&L'!U5-'YTD P&L'!T5 | AB5: ='YTD P&L'!V5-'YTD P&L'!U5 | AC5: ='ANNL P&L'!H5-'YTD P&L'!V5 | AD5: ='QTR P&L'!AD2*'IS DRIVERS'!AE4 | AE5: ='QTR P&L'!AE2*'IS DRIVERS'!AF4 | AF5: ='QTR P&L'!AF2*'IS DRIVERS'!AG4 | AG5: ='QTR P&L'!AG2*'IS DRIVERS'!AH4 | AH5: ='QTR P&L'!AH2*'IS DRIVERS'!AI4 | AI5: ='QTR P&L'!AI2*'IS DRIVERS'!AJ4 | AJ5: ='QTR P&L'!AJ2*'IS DRIVERS'!AK4 | AK5: ='QTR P&L'!AK2*'IS DRIVERS'!AL4 | ... AW5: ='QTR P&L'!AW2*'IS DRIVERS'!AX4
A6: General and Administrative | B6: ='YTD P&L'!B6 | C6: ='YTD P&L'!C6-'YTD P&L'!B6 | D6: ='YTD P&L'!D6-'YTD P&L'!C6 | E6: ='ANNL P&L'!B6-'YTD P&L'!D6 | F6: ='YTD P&L'!E6 | G6: ='YTD P&L'!F6-'YTD P&L'!E6 | H6: ='YTD P&L'!G6-'YTD P&L'!F6 | I6: ='ANNL P&L'!C6-'YTD P&L'!G6 | J6: ='YTD P&L'!H6 | K6: ='YTD P&L'!I6-'YTD P&L'!H6 | L6: ='YTD P&L'!J6-'YTD P&L'!I6 | M6: ='ANNL P&L'!D6-'YTD P&L'!J6 | N6: ='YTD P&L'!K6 | O6: ='YTD P&L'!L6-'YTD P&L'!K6 | P6: ='YTD P&L'!M6-'YTD P&L'!L6 | Q6: ='ANNL P&L'!E6-'YTD P&L'!M6 | R6: ='YTD P&L'!N6 | S6: ='YTD P&L'!O6-'YTD P&L'!N6 | T6: ='YTD P&L'!P6-'YTD P&L'!O6 | U6: ='ANNL P&L'!F6-'YTD P&L'!P6 | V6: ='YTD P&L'!Q6 | W6: ='YTD P&L'!R6-'YTD P&L'!Q6 | X6: ='YTD P&L'!S6-'YTD P&L'!R6 | Y6: ='ANNL P&L'!G6-'YTD P&L'!S6 | Z6: ='YTD P&L'!T6 | AA6: ='YTD P&L'!U6-'YTD P&L'!T6 | AB6: ='YTD P&L'!V6-'YTD P&L'!U6 | AC6: ='ANNL P&L'!H6-'YTD P&L'!V6 | AD6: ='QTR P&L'!AD2*'IS DRIVERS'!AE5 | AE6: ='QTR P&L'!AE2*'IS DRIVERS'!AF5 | AF6: ='QTR P&L'!AF2*'IS DRIVERS'!AG5 | AG6: ='QTR P&L'!AG2*'IS DRIVERS'!AH5 | AH6: ='QTR P&L'!AH2*'IS DRIVERS'!AI5 | AI6: ='QTR P&L'!AI2*'IS DRIVERS'!AJ5 | AJ6: ='QTR P&L'!AJ2*'IS DRIVERS'!AK5 | AK6: ='QTR P&L'!AK2*'IS DRIVERS'!AL5 | ... AW6: ='QTR P&L'!AW2*'IS DRIVERS'!AX5
A7: Operating Expenses | B7: ='YTD P&L'!B7 | C7: ='YTD P&L'!C7-'YTD P&L'!B7 | D7: ='YTD P&L'!D7-'YTD P&L'!C7 | E7: ='ANNL P&L'!B7-'YTD P&L'!D7 | F7: ='YTD P&L'!E7 | G7: ='YTD P&L'!F7-'YTD P&L'!E7 | H7: ='YTD P&L'!G7-'YTD P&L'!F7 | I7: ='ANNL P&L'!C7-'YTD P&L'!G7 | J7: ='YTD P&L'!H7 | K7: ='YTD P&L'!I7-'YTD P&L'!H7 | L7: ='YTD P&L'!J7-'YTD P&L'!I7 | M7: ='ANNL P&L'!D7-'YTD P&L'!J7 | N7: ='YTD P&L'!K7 | O7: ='YTD P&L'!L7-'YTD P&L'!K7 | P7: ='YTD P&L'!M7-'YTD P&L'!L7 | Q7: ='ANNL P&L'!E7-'YTD P&L'!M7 | R7: ='YTD P&L'!N7 | S7: ='YTD P&L'!O7-'YTD P&L'!N7 | T7: ='YTD P&L'!P7-'YTD P&L'!O7 | U7: ='ANNL P&L'!F7-'YTD P&L'!P7 | V7: ='YTD P&L'!Q7 | W7: ='YTD P&L'!R7-'YTD P&L'!Q7 | X7: ='YTD P&L'!S7-'YTD P&L'!R7 | Y7: ='ANNL P&L'!G7-'YTD P&L'!S7 | Z7: ='YTD P&L'!T7 | AA7: ='YTD P&L'!U7-'YTD P&L'!T7 | AB7: ='YTD P&L'!V7-'YTD P&L'!U7 | AC7: ='ANNL P&L'!H7-'YTD P&L'!V7 | AD7: ='QTR P&L'!AD2*'IS DRIVERS'!AE6 | AE7: ='QTR P&L'!AE2*'IS DRIVERS'!AF6 | AF7: ='QTR P&L'!AF2*'IS DRIVERS'!AG6 | AG7: ='QTR P&L'!AG2*'IS DRIVERS'!AH6 | AH7: ='QTR P&L'!AH2*'IS DRIVERS'!AI6 | AI7: ='QTR P&L'!AI2*'IS DRIVERS'!AJ6 | AJ7: ='QTR P&L'!AJ2*'IS DRIVERS'!AK6 | AK7: ='QTR P&L'!AK2*'IS DRIVERS'!AL6 | ... AW7: ='QTR P&L'!AW2*'IS DRIVERS'!AX6
A8: SG&A | B8: ='YTD P&L'!B8 | C8: ='YTD P&L'!C8-'YTD P&L'!B8 | D8: ='YTD P&L'!D8-'YTD P&L'!C8 | E8: ='ANNL P&L'!B8-'YTD P&L'!D8 | F8: ='YTD P&L'!E8 | G8: ='YTD P&L'!F8-'YTD P&L'!E8 | H8: ='YTD P&L'!G8-'YTD P&L'!F8 | I8: ='ANNL P&L'!C8-'YTD P&L'!G8 | J8: ='YTD P&L'!H8 | K8: ='YTD P&L'!I8-'YTD P&L'!H8 | L8: ='YTD P&L'!J8-'YTD P&L'!I8 | M8: ='ANNL P&L'!D8-'YTD P&L'!J8 | N8: ='YTD P&L'!K8 | O8: ='YTD P&L'!L8-'YTD P&L'!K8 | P8: ='YTD P&L'!M8-'YTD P&L'!L8 | Q8: ='ANNL P&L'!E8-'YTD P&L'!M8 | R8: ='YTD P&L'!N8 | S8: ='YTD P&L'!O8-'YTD P&L'!N8 | T8: ='YTD P&L'!P8-'YTD P&L'!O8 | U8: ='ANNL P&L'!F8-'YTD P&L'!P8 | V8: ='YTD P&L'!Q8 | W8: ='YTD P&L'!R8-'YTD P&L'!Q8 | X8: ='YTD P&L'!S8-'YTD P&L'!R8 | Y8: ='ANNL P&L'!G8-'YTD P&L'!S8 | Z8: ='YTD P&L'!T8 | AA8: ='YTD P&L'!U8-'YTD P&L'!T8 | AB8: ='YTD P&L'!V8-'YTD P&L'!U8 | AC8: ='ANNL P&L'!H8-'YTD P&L'!V8 | AD8: ='QTR P&L'!AD2*'IS DRIVERS'!AE7 | AE8: ='QTR P&L'!AE2*'IS DRIVERS'!AF7 | AF8: ='QTR P&L'!AF2*'IS DRIVERS'!AG7 | AG8: ='QTR P&L'!AG2*'IS DRIVERS'!AH7 | AH8: ='QTR P&L'!AH2*'IS DRIVERS'!AI7 | AI8: ='QTR P&L'!AI2*'IS DRIVERS'!AJ7 | AJ8: ='QTR P&L'!AJ2*'IS DRIVERS'!AK7 | AK8: ='QTR P&L'!AK2*'IS DRIVERS'!AL7 | ... AW8: ='QTR P&L'!AW2*'IS DRIVERS'!AX7
A9: Distributor Termination Fees | B9: ='YTD P&L'!B9 | C9: ='YTD P&L'!C9-'YTD P&L'!B9 | D9: ='YTD P&L'!D9-'YTD P&L'!C9 | E9: ='ANNL P&L'!B9-'YTD P&L'!D9 | F9: ='YTD P&L'!E9 | G9: ='YTD P&L'!F9-'YTD P&L'!E9 | H9: ='YTD P&L'!G9-'YTD P&L'!F9 | I9: ='ANNL P&L'!C9-'YTD P&L'!G9 | J9: ='YTD P&L'!H9 | K9: ='YTD P&L'!I9-'YTD P&L'!H9 | L9: ='YTD P&L'!J9-'YTD P&L'!I9 | M9: ='ANNL P&L'!D9-'YTD P&L'!J9 | N9: ='YTD P&L'!K9 | O9: ='YTD P&L'!L9-'YTD P&L'!K9 | P9: ='YTD P&L'!M9-'YTD P&L'!L9 | Q9: ='ANNL P&L'!E9-'YTD P&L'!M9 | R9: ='YTD P&L'!N9 | S9: ='YTD P&L'!O9-'YTD P&L'!N9 | T9: ='YTD P&L'!P9-'YTD P&L'!O9 | U9: ='ANNL P&L'!F9-'YTD P&L'!P9 | V9: ='YTD P&L'!Q9 | W9: ='YTD P&L'!R9-'YTD P&L'!Q9 | X9: ='YTD P&L'!S9-'YTD P&L'!R9 | Y9: ='ANNL P&L'!G9-'YTD P&L'!S9 | Z9: ='YTD P&L'!T9 | AA9: ='YTD P&L'!U9-'YTD P&L'!T9 | AB9: ='YTD P&L'!V9-'YTD P&L'!U9 | AC9: ='ANNL P&L'!H9-'YTD P&L'!V9 | AD9: ='IS DRIVERS'!AE8 | AE9: ='IS DRIVERS'!AF8 | AF9: ='IS DRIVERS'!AG8 | AG9: ='IS DRIVERS'!AH8 | AH9: ='IS DRIVERS'!AI8 | AI9: ='IS DRIVERS'!AJ8 | AJ9: ='IS DRIVERS'!AK8 | AK9: ='IS DRIVERS'!AL8 | ... AW9: ='IS DRIVERS'!AX8
A10: Income (Loss) from Operations | B10: ='YTD P&L'!B10 | C10: ='YTD P&L'!C10-'YTD P&L'!B10 | D10: ='YTD P&L'!D10-'YTD P&L'!C10 | E10: ='ANNL P&L'!B10-'YTD P&L'!D10 | F10: ='YTD P&L'!E10 | G10: ='YTD P&L'!F10-'YTD P&L'!E10 | H10: ='YTD P&L'!G10-'YTD P&L'!F10 | I10: ='ANNL P&L'!C10-'YTD P&L'!G10 | J10: ='YTD P&L'!H10 | K10: ='YTD P&L'!I10-'YTD P&L'!H10 | L10: ='YTD P&L'!J10-'YTD P&L'!I10 | M10: ='ANNL P&L'!D10-'YTD P&L'!J10 | N10: ='YTD P&L'!K10 | O10: ='YTD P&L'!L10-'YTD P&L'!K10 | P10: ='YTD P&L'!M10-'YTD P&L'!L10 | Q10: ='ANNL P&L'!E10-'YTD P&L'!M10 | R10: ='YTD P&L'!N10 | S10: ='YTD P&L'!O10-'YTD P&L'!N10 | T10: ='YTD P&L'!P10-'YTD P&L'!O10 | U10: ='ANNL P&L'!F10-'YTD P&L'!P10 | V10: ='YTD P&L'!Q10 | W10: ='YTD P&L'!R10-'YTD P&L'!Q10 | X10: ='YTD P&L'!S10-'YTD P&L'!R10 | Y10: ='ANNL P&L'!G10-'YTD P&L'!S10 | Z10: ='YTD P&L'!T10 | AA10: ='YTD P&L'!U10-'YTD P&L'!T10 | AB10: ='YTD P&L'!V10-'YTD P&L'!U10 | AC10: ='ANNL P&L'!H10-'YTD P&L'!V10 | AD10: =AD4+SUM(AD5:AD9) | AE10: =AE4+SUM(AE5:AE9) | AF10: =AF4+SUM(AF5:AF9) | AG10: =AG4+SUM(AG5:AG9) | AH10: =AH4+SUM(AH5:AH9) | AI10: =AI4+SUM(AI5:AI9) | AJ10: =AJ4+SUM(AJ5:AJ9) | AK10: =AK4+SUM(AK5:AK9) | ... AW10: =AW4+SUM(AW5:AW9)
A11: Interest Income (Expense) | B11: ='YTD P&L'!B11 | C11: ='YTD P&L'!C11-'YTD P&L'!B11 | D11: ='YTD P&L'!D11-'YTD P&L'!C11 | E11: ='ANNL P&L'!B11-'YTD P&L'!D11 | F11: ='YTD P&L'!E11 | G11: ='YTD P&L'!F11-'YTD P&L'!E11 | H11: ='YTD P&L'!G11-'YTD P&L'!F11 | I11: ='ANNL P&L'!C11-'YTD P&L'!G11 | J11: ='YTD P&L'!H11 | K11: ='YTD P&L'!I11-'YTD P&L'!H11 | L11: ='YTD P&L'!J11-'YTD P&L'!I11 | M11: ='ANNL P&L'!D11-'YTD P&L'!J11 | N11: ='YTD P&L'!K11 | O11: ='YTD P&L'!L11-'YTD P&L'!K11 | P11: ='YTD P&L'!M11-'YTD P&L'!L11 | Q11: ='ANNL P&L'!E11-'YTD P&L'!M11 | R11: ='YTD P&L'!N11 | S11: ='YTD P&L'!O11-'YTD P&L'!N11 | T11: ='YTD P&L'!P11-'YTD P&L'!O11 | U11: ='ANNL P&L'!F11-'YTD P&L'!P11 | V11: ='YTD P&L'!Q11 | W11: ='YTD P&L'!R11-'YTD P&L'!Q11 | X11: ='YTD P&L'!S11-'YTD P&L'!R11 | Y11: ='ANNL P&L'!G11-'YTD P&L'!S11 | Z11: ='YTD P&L'!T11 | AA11: ='YTD P&L'!U11-'YTD P&L'!T11 | AB11: ='YTD P&L'!V11-'YTD P&L'!U11 | AC11: ='ANNL P&L'!H11-'YTD P&L'!V11 | AD11: ='IS DRIVERS'!AE9 | AE11: ='IS DRIVERS'!AF9 | AF11: ='IS DRIVERS'!AG9 | AG11: ='IS DRIVERS'!AH9 | AH11: ='IS DRIVERS'!AI9 | AI11: ='IS DRIVERS'!AJ9 | AJ11: ='IS DRIVERS'!AK9 | AK11: ='IS DRIVERS'!AL9 | ... AW11: ='IS DRIVERS'!AX9
A12: Other Income (Expense) | B12: ='YTD P&L'!B12 | C12: ='YTD P&L'!C12-'YTD P&L'!B12 | D12: ='YTD P&L'!D12-'YTD P&L'!C12 | E12: ='ANNL P&L'!B13-'YTD P&L'!D12 | F12: ='YTD P&L'!E12 | G12: ='YTD P&L'!F12-'YTD P&L'!E12 | H12: ='YTD P&L'!G12-'YTD P&L'!F12 | I12: ='ANNL P&L'!C13-'YTD P&L'!G12 | J12: ='YTD P&L'!H12 | K12: ='YTD P&L'!I12-'YTD P&L'!H12 | L12: ='YTD P&L'!J12-'YTD P&L'!I12 | M12: ='ANNL P&L'!D13-'YTD P&L'!J12 | N12: ='YTD P&L'!K12 | O12: ='YTD P&L'!L12-'YTD P&L'!K12 | P12: ='YTD P&L'!M12-'YTD P&L'!L12 | Q12: ='ANNL P&L'!E13-'YTD P&L'!M12 | R12: ='YTD P&L'!N12 | S12: ='YTD P&L'!O12-'YTD P&L'!N12 | T12: ='YTD P&L'!P12-'YTD P&L'!O12 | U12: ='ANNL P&L'!F13-'YTD P&L'!P12 | V12: ='YTD P&L'!Q12 | W12: ='YTD P&L'!R12-'YTD P&L'!Q12 | X12: ='YTD P&L'!S12-'YTD P&L'!R12 | Y12: ='ANNL P&L'!G13-'YTD P&L'!S12 | Z12: ='YTD P&L'!T12 | AA12: ='YTD P&L'!U12-'YTD P&L'!T12 | AB12: ='YTD P&L'!V12-'YTD P&L'!U12 | AC12: ='ANNL P&L'!H13-'YTD P&L'!V12 | AD12: ='IS DRIVERS'!AE10 | AE12: ='IS DRIVERS'!AF10 | AF12: ='IS DRIVERS'!AG10 | AG12: ='IS DRIVERS'!AH10 | AH12: ='IS DRIVERS'!AI10 | AI12: ='IS DRIVERS'!AJ10 | AJ12: ='IS DRIVERS'!AK10 | AK12: ='IS DRIVERS'!AL10 | ... AW12: ='IS DRIVERS'!AX10
A13: Foreign Currency Gain (Loss) | B13: ='YTD P&L'!B13 | C13: ='YTD P&L'!C13-'YTD P&L'!B13 | D13: ='YTD P&L'!D13-'YTD P&L'!C13 | E13: ='ANNL P&L'!B12-'YTD P&L'!D13 | F13: ='YTD P&L'!E13 | G13: ='YTD P&L'!F13-'YTD P&L'!E13 | H13: ='YTD P&L'!G13-'YTD P&L'!F13 | I13: ='ANNL P&L'!C12-'YTD P&L'!G13 | J13: ='YTD P&L'!H13 | K13: ='YTD P&L'!I13-'YTD P&L'!H13 | L13: ='YTD P&L'!J13-'YTD P&L'!I13 | M13: ='ANNL P&L'!D12-'YTD P&L'!J13 | N13: ='YTD P&L'!K13 | O13: ='YTD P&L'!L13-'YTD P&L'!K13 | P13: ='YTD P&L'!M13-'YTD P&L'!L13 | Q13: ='ANNL P&L'!E12-'YTD P&L'!M13 | R13: ='YTD P&L'!N13 | S13: ='YTD P&L'!O13-'YTD P&L'!N13 | T13: ='YTD P&L'!P13-'YTD P&L'!O13 | U13: ='ANNL P&L'!F12-'YTD P&L'!P13 | V13: ='YTD P&L'!Q13 | W13: ='YTD P&L'!R13-'YTD P&L'!Q13 | X13: ='YTD P&L'!S13-'YTD P&L'!R13 | Y13: ='ANNL P&L'!G12-'YTD P&L'!S13 | Z13: ='YTD P&L'!T13 | AA13: ='YTD P&L'!U13-'YTD P&L'!T13 | AB13: ='YTD P&L'!V13-'YTD P&L'!U13 | AC13: ='ANNL P&L'!H12-'YTD P&L'!V13 | AD13: ='IS DRIVERS'!AE11 | AE13: ='IS DRIVERS'!AF11 | AF13: ='IS DRIVERS'!AG11 | AG13: ='IS DRIVERS'!AH11 | AH13: ='IS DRIVERS'!AI11 | AI13: ='IS DRIVERS'!AJ11 | AJ13: ='IS DRIVERS'!AK11 | AK13: ='IS DRIVERS'!AL11 | ... AW13: ='IS DRIVERS'!AX11
A14: Gain (Loss) on Lease Cancellations | B14: ='YTD P&L'!B14 | C14: ='YTD P&L'!C14-'YTD P&L'!B14 | D14: ='YTD P&L'!D14-'YTD P&L'!C14 | E14: ='ANNL P&L'!B14-'YTD P&L'!D14 | F14: ='YTD P&L'!E14 | G14: ='YTD P&L'!F14-'YTD P&L'!E14 | H14: ='YTD P&L'!G14-'YTD P&L'!F14 | I14: ='ANNL P&L'!C14-'YTD P&L'!G14 | J14: ='YTD P&L'!H14 | K14: ='YTD P&L'!I14-'YTD P&L'!H14 | L14: ='YTD P&L'!J14-'YTD P&L'!I14 | M14: ='ANNL P&L'!D14-'YTD P&L'!J14 | N14: ='YTD P&L'!K14 | O14: ='YTD P&L'!L14-'YTD P&L'!K14 | P14: ='YTD P&L'!M14-'YTD P&L'!L14 | Q14: ='ANNL P&L'!E14-'YTD P&L'!M14 | R14: ='YTD P&L'!N14 | S14: ='YTD P&L'!O14-'YTD P&L'!N14 | T14: ='YTD P&L'!P14-'YTD P&L'!O14 | U14: ='ANNL P&L'!F14-'YTD P&L'!P14 | V14: ='YTD P&L'!Q14 | W14: ='YTD P&L'!R14-'YTD P&L'!Q14 | X14: ='YTD P&L'!S14-'YTD P&L'!R14 | Y14: ='ANNL P&L'!G14-'YTD P&L'!S14 | Z14: ='YTD P&L'!T14 | AA14: ='YTD P&L'!U14-'YTD P&L'!T14 | AB14: ='YTD P&L'!V14-'YTD P&L'!U14 | AC14: ='ANNL P&L'!H14-'YTD P&L'!V14 | AD14: ='IS DRIVERS'!AE12 | AE14: ='IS DRIVERS'!AF12 | AF14: ='IS DRIVERS'!AG12 | AG14: ='IS DRIVERS'!AH12 | AH14: ='IS DRIVERS'!AI12 | AI14: ='IS DRIVERS'!AJ12 | AJ14: ='IS DRIVERS'!AK12 | AK14: ='IS DRIVERS'!AL12 | ... AW14: ='IS DRIVERS'!AX12
A15: Income Tax (Expense) Benefit | B15: ='YTD P&L'!B15 | C15: ='YTD P&L'!C15-'YTD P&L'!B15 | D15: ='YTD P&L'!D15-'YTD P&L'!C15 | E15: ='ANNL P&L'!B15-'YTD P&L'!D15 | F15: ='YTD P&L'!E15 | G15: ='YTD P&L'!F15-'YTD P&L'!E15 | H15: ='YTD P&L'!G15-'YTD P&L'!F15 | I15: ='ANNL P&L'!C15-'YTD P&L'!G15 | J15: ='YTD P&L'!H15 | K15: ='YTD P&L'!I15-'YTD P&L'!H15 | L15: ='YTD P&L'!J15-'YTD P&L'!I15 | M15: ='ANNL P&L'!D15-'YTD P&L'!J15 | N15: ='YTD P&L'!K15 | O15: ='YTD P&L'!L15-'YTD P&L'!K15 | P15: ='YTD P&L'!M15-'YTD P&L'!L15 | Q15: ='ANNL P&L'!E15-'YTD P&L'!M15 | R15: ='YTD P&L'!N15 | S15: ='YTD P&L'!O15-'YTD P&L'!N15 | T15: ='YTD P&L'!P15-'YTD P&L'!O15 | U15: ='ANNL P&L'!F15-'YTD P&L'!P15 | V15: ='YTD P&L'!Q15 | W15: ='YTD P&L'!R15-'YTD P&L'!Q15 | X15: ='YTD P&L'!S15-'YTD P&L'!R15 | Y15: ='ANNL P&L'!G15-'YTD P&L'!S15 | Z15: ='YTD P&L'!T15 | AA15: ='YTD P&L'!U15-'YTD P&L'!T15 | AB15: ='YTD P&L'!V15-'YTD P&L'!U15 | AC15: ='ANNL P&L'!H15-'YTD P&L'!V15 | AD15: ='IS DRIVERS'!AE13 | AE15: ='IS DRIVERS'!AF13 | AF15: ='IS DRIVERS'!AG13 | AG15: ='IS DRIVERS'!AH13 | AH15: ='IS DRIVERS'!AI13 | AI15: ='IS DRIVERS'!AJ13 | AJ15: ='IS DRIVERS'!AK13 | AK15: ='IS DRIVERS'!AL13 | ... AW15: ='IS DRIVERS'!AX13
A16: Pre-Tax Income (Loss) | B16: ='YTD P&L'!B16 | C16: ='YTD P&L'!C16-'YTD P&L'!B16 | D16: ='YTD P&L'!D16-'YTD P&L'!C16 | E16: ='ANNL P&L'!B16-'YTD P&L'!D16 | F16: ='YTD P&L'!E16 | G16: ='YTD P&L'!F16-'YTD P&L'!E16 | H16: ='YTD P&L'!G16-'YTD P&L'!F16 | I16: ='ANNL P&L'!C16-'YTD P&L'!G16 | J16: ='YTD P&L'!H16 | K16: ='YTD P&L'!I16-'YTD P&L'!H16 | L16: ='YTD P&L'!J16-'YTD P&L'!I16 | M16: ='ANNL P&L'!D16-'YTD P&L'!J16 | N16: ='YTD P&L'!K16 | O16: ='YTD P&L'!L16-'YTD P&L'!K16 | P16: ='YTD P&L'!M16-'YTD P&L'!L16 | Q16: ='ANNL P&L'!E16-'YTD P&L'!M16 | R16: ='YTD P&L'!N16 | S16: ='YTD P&L'!O16-'YTD P&L'!N16 | T16: ='YTD P&L'!P16-'YTD P&L'!O16 | U16: ='ANNL P&L'!F16-'YTD P&L'!P16 | V16: ='YTD P&L'!Q16 | W16: ='YTD P&L'!R16-'YTD P&L'!Q16 | X16: ='YTD P&L'!S16-'YTD P&L'!R16 | Y16: ='ANNL P&L'!G16-'YTD P&L'!S16 | Z16: ='YTD P&L'!T16 | AA16: ='YTD P&L'!U16-'YTD P&L'!T16 | AB16: ='YTD P&L'!V16-'YTD P&L'!U16 | AC16: ='ANNL P&L'!H16-'YTD P&L'!V16 | AD16: =AD10+SUM(AD11:AD15) | AE16: =AE10+SUM(AE11:AE15) | AF16: =AF10+SUM(AF11:AF15) | AG16: =AG10+SUM(AG11:AG15) | AH16: =AH10+SUM(AH11:AH15) | AI16: =AI10+SUM(AI11:AI15) | AJ16: =AJ10+SUM(AJ11:AJ15) | AK16: =AK10+SUM(AK11:AK15) | ... AW16: =AW10+SUM(AW11:AW15)
A17: Net Income (Loss) | B17: ='YTD P&L'!B17 | C17: ='YTD P&L'!C17-'YTD P&L'!B17 | D17: ='YTD P&L'!D17-'YTD P&L'!C17 | E17: ='ANNL P&L'!B17-'YTD P&L'!D17 | F17: ='YTD P&L'!E17 | G17: ='YTD P&L'!F17-'YTD P&L'!E17 | H17: ='YTD P&L'!G17-'YTD P&L'!F17 | I17: ='ANNL P&L'!C17-'YTD P&L'!G17 | J17: ='YTD P&L'!H17 | K17: ='YTD P&L'!I17-'YTD P&L'!H17 | L17: ='YTD P&L'!J17-'YTD P&L'!I17 | M17: ='ANNL P&L'!D17-'YTD P&L'!J17 | N17: ='YTD P&L'!K17 | O17: ='YTD P&L'!L17-'YTD P&L'!K17 | P17: ='YTD P&L'!M17-'YTD P&L'!L17 | Q17: ='ANNL P&L'!E17-'YTD P&L'!M17 | R17: ='YTD P&L'!N17 | S17: ='YTD P&L'!O17-'YTD P&L'!N17 | T17: ='YTD P&L'!P17-'YTD P&L'!O17 | U17: ='ANNL P&L'!F17-'YTD P&L'!P17 | V17: ='YTD P&L'!Q17 | W17: ='YTD P&L'!R17-'YTD P&L'!Q17 | X17: ='YTD P&L'!S17-'YTD P&L'!R17 | Y17: ='ANNL P&L'!G17-'YTD P&L'!S17 | Z17: ='YTD P&L'!T17 | AA17: ='YTD P&L'!U17-'YTD P&L'!T17 | AB17: ='YTD P&L'!V17-'YTD P&L'!U17 | AC17: ='ANNL P&L'!H17-'YTD P&L'!V17
A18: Basic Earnings (Loss) per Share
A19: Diluted Earnings (Loss) per Share
A20: Weighted Average Shares Outstanding (Basic)
A21: Weighted Average Shares Outstanding (Diluted)
A22: Preferred Dividends | B22: ='YTD P&L'!B22 | C22: ='YTD P&L'!C22-'YTD P&L'!B22 | D22: ='YTD P&L'!D22-'YTD P&L'!C22 | E22: ='ANNL P&L'!B22-'YTD P&L'!D22 | F22: ='YTD P&L'!E22 | G22: ='YTD P&L'!F22-'YTD P&L'!E22 | H22: ='YTD P&L'!G22-'YTD P&L'!F22 | I22: ='ANNL P&L'!C22-'YTD P&L'!G22 | J22: ='YTD P&L'!H22 | K22: ='YTD P&L'!I22-'YTD P&L'!H22 | L22: ='YTD P&L'!J22-'YTD P&L'!I22 | M22: ='ANNL P&L'!D22-'YTD P&L'!J22 | N22: ='YTD P&L'!K22 | O22: ='YTD P&L'!L22-'YTD P&L'!K22 | P22: ='YTD P&L'!M22-'YTD P&L'!L22 | Q22: ='ANNL P&L'!E22-'YTD P&L'!M22 | R22: ='YTD P&L'!N22 | S22: ='YTD P&L'!O22-'YTD P&L'!N22 | T22: ='YTD P&L'!P22-'YTD P&L'!O22 | U22: ='ANNL P&L'!F22-'YTD P&L'!P22 | V22: ='YTD P&L'!Q22 | W22: ='YTD P&L'!R22-'YTD P&L'!Q22 | X22: ='YTD P&L'!S22-'YTD P&L'!R22 | Y22: ='ANNL P&L'!G22-'YTD P&L'!S22 | Z22: ='YTD P&L'!T22 | AA22: ='YTD P&L'!U22-'YTD P&L'!T22 | AB22: ='YTD P&L'!V22-'YTD P&L'!U22 | AC22: ='ANNL P&L'!H22-'YTD P&L'!V22 | AD22: ='IS DRIVERS'!AE14 | AE22: ='IS DRIVERS'!AF14 | AF22: ='IS DRIVERS'!AG14 | AG22: ='IS DRIVERS'!AH14 | AH22: ='IS DRIVERS'!AI14 | AI22: ='IS DRIVERS'!AJ14 | AJ22: ='IS DRIVERS'!AK14 | AK22: ='IS DRIVERS'!AL14 | ... AW22: ='IS DRIVERS'!AX14
A23: Income Allocated to Participating Preferred | B23: ='YTD P&L'!B23 | C23: ='YTD P&L'!C23-'YTD P&L'!B23 | D23: ='YTD P&L'!D23-'YTD P&L'!C23 | E23: ='ANNL P&L'!B23-'YTD P&L'!D23 | F23: ='YTD P&L'!E23 | G23: ='YTD P&L'!F23-'YTD P&L'!E23 | H23: ='YTD P&L'!G23-'YTD P&L'!F23 | I23: ='ANNL P&L'!C23-'YTD P&L'!G23 | J23: ='YTD P&L'!H23 | K23: ='YTD P&L'!I23-'YTD P&L'!H23 | L23: ='YTD P&L'!J23-'YTD P&L'!I23 | M23: ='ANNL P&L'!D23-'YTD P&L'!J23 | N23: ='YTD P&L'!K23 | O23: ='YTD P&L'!L23-'YTD P&L'!K23 | P23: ='YTD P&L'!M23-'YTD P&L'!L23 | Q23: ='ANNL P&L'!E23-'YTD P&L'!M23 | R23: ='YTD P&L'!N23 | S23: ='YTD P&L'!O23-'YTD P&L'!N23 | T23: ='YTD P&L'!P23-'YTD P&L'!O23 | U23: ='ANNL P&L'!F23-'YTD P&L'!P23 | V23: ='YTD P&L'!Q23 | W23: ='YTD P&L'!R23-'YTD P&L'!Q23 | X23: ='YTD P&L'!S23-'YTD P&L'!R23 | Y23: ='ANNL P&L'!G23-'YTD P&L'!S23 | Z23: ='YTD P&L'!T23 | AA23: ='YTD P&L'!U23-'YTD P&L'!T23 | AB23: ='YTD P&L'!V23-'YTD P&L'!U23 | AC23: ='ANNL P&L'!H23-'YTD P&L'!V23 | AD23: ='IS DRIVERS'!AE15 | AE23: ='IS DRIVERS'!AF15 | AF23: ='IS DRIVERS'!AG15 | AG23: ='IS DRIVERS'!AH15 | AH23: ='IS DRIVERS'!AI15 | AI23: ='IS DRIVERS'!AJ15 | AJ23: ='IS DRIVERS'!AK15 | AK23: ='IS DRIVERS'!AL15 | ... AW23: ='IS DRIVERS'!AX15
A24: Net Income (Loss) Attributable to Common Shareholders | B24: ='YTD P&L'!B24 | C24: ='YTD P&L'!C24-'YTD P&L'!B24 | D24: ='YTD P&L'!D24-'YTD P&L'!C24 | E24: ='ANNL P&L'!B24-'YTD P&L'!D24 | F24: ='YTD P&L'!E24 | G24: ='YTD P&L'!F24-'YTD P&L'!E24 | H24: ='YTD P&L'!G24-'YTD P&L'!F24 | I24: ='ANNL P&L'!C24-'YTD P&L'!G24 | J24: ='YTD P&L'!H24 | K24: ='YTD P&L'!I24-'YTD P&L'!H24 | L24: ='YTD P&L'!J24-'YTD P&L'!I24 | M24: ='ANNL P&L'!D24-'YTD P&L'!J24 | N24: ='YTD P&L'!K24 | O24: ='YTD P&L'!L24-'YTD P&L'!K24 | P24: ='YTD P&L'!M24-'YTD P&L'!L24 | Q24: ='ANNL P&L'!E24-'YTD P&L'!M24 | R24: ='YTD P&L'!N24 | S24: ='YTD P&L'!O24-'YTD P&L'!N24 | T24: ='YTD P&L'!P24-'YTD P&L'!O24 | U24: ='ANNL P&L'!F24-'YTD P&L'!P24 | V24: ='YTD P&L'!Q24 | W24: ='YTD P&L'!R24-'YTD P&L'!Q24 | X24: ='YTD P&L'!S24-'YTD P&L'!R24 | Y24: ='ANNL P&L'!G24-'YTD P&L'!S24 | Z24: ='YTD P&L'!T24 | AA24: ='YTD P&L'!U24-'YTD P&L'!T24 | AB24: ='YTD P&L'!V24-'YTD P&L'!U24 | AC24: ='ANNL P&L'!H24-'YTD P&L'!V24 | AD24: =AD17+AD22+AD23 | AE24: =AE17+AE22+AE23 | AF24: =AF17+AF22+AF23 | AG24: =AG17+AG22+AG23 | AH24: =AH17+AH22+AH23 | AI24: =AI17+AI22+AI23 | AJ24: =AJ17+AJ22+AJ23 | AK24: =AK17+AK22+AK23 | ... AW24: =AW17+AW22+AW23

Sheet QTR BS
B1: Q4 FY2019 | C1: Q1 FY2020 | D1: Q2 FY2020 | E1: Q3 FY2020 | F1: Q4 FY2020 | G1: Q1 FY2021 | H1: Q2 FY2021 | I1: Q3 FY2021 | J1: Q4 FY2021 | K1: Q1 FY2022 | L1: Q2 FY2022 | M1: Q3 FY2022 | N1: Q4 FY2022 | O1: Q1 FY2023 | P1: Q2 FY2023 | Q1: Q3 FY2023 | R1: Q4 FY2023 | S1: Q1 FY2024 | T1: Q2 FY2024 | U1: Q3 FY2024 | V1: Q4 FY2024 | W1: Q1 FY2025 | X1: Q2 FY2025 | Y1: Q3 FY2025 | Z1: Q4 FY2025 | AA1: Q1 FY2026E | AB1: Q2 FY2026E | AC1: Q3 FY2026E | AD1: Q4 FY2026E | AE1: Q1 FY2027E | AF1: Q2 FY2027E | AG1: Q3 FY2027E | AH1: Q4 FY2027E | AI1: Q1 FY2028E | AJ1: Q2 FY2028E | AK1: Q3 FY2028E | AL1: Q4 FY2028E | AM1: Q1 FY2029E | AN1: Q2 FY2029E | AO1: Q3 FY2029E | AP1: Q4 FY2029E | AQ1: Q1 FY2030E | AR1: Q2 FY2030E | AS1: Q3 FY2030E | AT1: Q4 FY2030E
A2: Cash, Cash Equivalents & Restricted Cash | B2: ='BALANCE SHEET'!B2 | C2: ='YTD BS'!C2 | D2: ='YTD BS'!D2 | E2: ='YTD BS'!E2 | F2: ='BALANCE SHEET'!C2 | G2: ='YTD BS'!G2 | H2: ='YTD BS'!H2 | I2: ='YTD BS'!I2 | J2: ='BALANCE SHEET'!D2 | K2: ='YTD BS'!K2 | L2: ='YTD BS'!L2 | M2: ='YTD BS'!M2 | N2: ='BALANCE SHEET'!E2 | O2: ='YTD BS'!O2 | P2: ='YTD BS'!P2 | Q2: ='YTD BS'!Q2 | R2: ='BALANCE SHEET'!F2 | S2: ='YTD BS'!S2 | T2: ='YTD BS'!T2 | U2: ='YTD BS'!U2 | V2: ='BALANCE SHEET'!G2 | W2: ='YTD BS'!W2 | X2: ='YTD BS'!X2 | Y2: ='YTD BS'!Y2 | Z2: ='BALANCE SHEET'!H2 | AA2: ='BS DRIVERS'!AA2 | AB2: ='BS DRIVERS'!AB2 | AC2: ='BS DRIVERS'!AC2 | AD2: ='BS DRIVERS'!AD2 | AE2: ='BS DRIVERS'!AE2 | AF2: ='BS DRIVERS'!AF2 | AG2: ='BS DRIVERS'!AG2 | AH2: ='BS DRIVERS'!AH2 | ... AT2: ='BS DRIVERS'!AT2
A3: Accounts Receivable | B3: ='BALANCE SHEET'!B3 | C3: ='YTD BS'!C3 | D3: ='YTD BS'!D3 | E3: ='YTD BS'!E3 | F3: ='BALANCE SHEET'!C3 | G3: ='YTD BS'!G3 | H3: ='YTD BS'!H3 | I3: ='YTD BS'!I3 | J3: ='BALANCE SHEET'!D3 | K3: ='YTD BS'!K3 | L3: ='YTD BS'!L3 | M3: ='YTD BS'!M3 | N3: ='BALANCE SHEET'!E3 | O3: ='YTD BS'!O3 | P3: ='YTD BS'!P3 | Q3: ='YTD BS'!Q3 | R3: ='BALANCE SHEET'!F3 | S3: ='YTD BS'!S3 | T3: ='YTD BS'!T3 | U3: ='YTD BS'!U3 | V3: ='BALANCE SHEET'!G3 | W3: ='YTD BS'!W3 | X3: ='YTD BS'!X3 | Y3: ='YTD BS'!Y3 | Z3: ='BALANCE SHEET'!H3 | AA3: ='QTR P&L'!AD2*'BS DRIVERS'!AA3/ASSUMPTIONS!$B$2 | AB3: ='QTR P&L'!AE2*'BS DRIVERS'!AB3/ASSUMPTIONS!$B$2 | AC3: ='QTR P&L'!AF2*'BS DRIVERS'!AC3/ASSUMPTIONS!$B$2 | AD3: ='QTR P&L'!AG2*'BS DRIVERS'!AD3/ASSUMPTIONS!$B$2 | AE3: ='QTR P&L'!AH2*'BS DRIVERS'!AE3/ASSUMPTIONS!$B$2 | AF3: ='QTR P&L'!AI2*'BS DRIVERS'!AF3/ASSUMPTIONS!$B$2 | AG3: ='QTR P&L'!AJ2*'BS DRIVERS'!AG3/ASSUMPTIONS!$B$2 | AH3: ='QTR P&L'!AK2*'BS DRIVERS'!AH3/ASSUMPTIONS!$B$2 | ... AT3: ='QTR P&L'!AW2*'BS DRIVERS'!AT3/ASSUMPTIONS!$B$2
A4: Note Receivable - Current | B4: ='BALANCE SHEET'!B4 | C4: ='YTD BS'!C4 | D4: ='YTD BS'!D4 | E4: ='YTD BS'!E4 | F4: ='BALANCE SHEET'!C4 | G4: ='YTD BS'!G4 | H4: ='YTD BS'!H4 | I4: ='YTD BS'!I4 | J4: ='BALANCE SHEET'!D4 | K4: ='YTD BS'!K4 | L4: ='YTD BS'!L4 | M4: ='YTD BS'!M4 | N4: ='BALANCE SHEET'!E4 | O4: ='YTD BS'!O4 | P4: ='YTD BS'!P4 | Q4: ='YTD BS'!Q4 | R4: ='BALANCE SHEET'!F4 | S4: ='YTD BS'!S4 | T4: ='YTD BS'!T4 | U4: ='YTD BS'!U4 | V4: ='BALANCE SHEET'!G4 | W4: ='YTD BS'!W4 | X4: ='YTD BS'!X4 | Y4: ='YTD BS'!Y4 | Z4: ='BALANCE SHEET'!H4 | AA4: ='QTR P&L'!AD2*'BS DRIVERS'!AA4/ASSUMPTIONS!$B$2 | AB4: ='QTR P&L'!AE2*'BS DRIVERS'!AB4/ASSUMPTIONS!$B$2 | AC4: ='QTR P&L'!AF2*'BS DRIVERS'!AC4/ASSUMPTIONS!$B$2 | AD4: ='QTR P&L'!AG2*'BS DRIVERS'!AD4/ASSUMPTIONS!$B$2 | AE4: ='QTR P&L'!AH2*'BS DRIVERS'!AE4/ASSUMPTIONS!$B$2 | AF4: ='QTR P&L'!AI2*'BS DRIVERS'!AF4/ASSUMPTIONS!$B$2 | AG4: ='QTR P&L'!AJ2*'BS DRIVERS'!AG4/ASSUMPTIONS!$B$2 | AH4: ='QTR P&L'!AK2*'BS DRIVERS'!AH4/ASSUMPTIONS!$B$2 | ... AT4: ='QTR P&L'!AW2*'BS DRIVERS'!AT4/ASSUMPTIONS!$B$2
A5: Inventories | B5: ='BALANCE SHEET'!B5 | C5: ='YTD BS'!C5 | D5: ='YTD BS'!D5 | E5: ='YTD BS'!E5 | F5: ='BALANCE SHEET'!C5 | G5: ='YTD BS'!G5 | H5: ='YTD BS'!H5 | I5: ='YTD BS'!I5 | J5: ='BALANCE SHEET'!D5 | K5: ='YTD BS'!K5 | L5: ='YTD BS'!L5 | M5: ='YTD BS'!M5 | N5: ='BALANCE SHEET'!E5 | O5: ='YTD BS'!O5 | P5: ='YTD BS'!P5 | Q5: ='YTD BS'!Q5 | R5: ='BALANCE SHEET'!F5 | S5: ='YTD BS'!S5 | T5: ='YTD BS'!T5 | U5: ='YTD BS'!U5 | V5: ='BALANCE SHEET'!G5 | W5: ='YTD BS'!W5 | X5: ='YTD BS'!X5 | Y5: ='YTD BS'!Y5 | Z5: ='BALANCE SHEET'!H5 | AA5: ='QTR P&L'!AD3*'BS DRIVERS'!AA5/ASSUMPTIONS!$B$2 | AB5: ='QTR P&L'!AE3*'BS DRIVERS'!AB5/ASSUMPTIONS!$B$2 | AC5: ='QTR P&L'!AF3*'BS DRIVERS'!AC5/ASSUMPTIONS!$B$2 | AD5: ='QTR P&L'!AG3*'BS DRIVERS'!AD5/ASSUMPTIONS!$B$2 | AE5: ='QTR P&L'!AH3*'BS DRIVERS'!AE5/ASSUMPTIONS!$B$2 | AF5: ='QTR P&L'!AI3*'BS DRIVERS'!AF5/ASSUMPTIONS!$B$2 | AG5: ='QTR P&L'!AJ3*'BS DRIVERS'!AG5/ASSUMPTIONS!$B$2 | AH5: ='QTR P&L'!AK3*'BS DRIVERS'!AH5/ASSUMPTIONS!$B$2 | ... AT5: ='QTR P&L'!AW3*'BS DRIVERS'!AT5/ASSUMPTIONS!$B$2
A6: Prepaid Expenses | B6: ='BALANCE SHEET'!B6 | C6: ='YTD BS'!C6 | D6: ='YTD BS'!D6 | E6: ='YTD BS'!E6 | F6: ='BALANCE SHEET'!C6 | G6: ='YTD BS'!G6 | H6: ='YTD BS'!H6 | I6: ='YTD BS'!I6 | J6: ='BALANCE SHEET'!D6 | K6: ='YTD BS'!K6 | L6: ='YTD BS'!L6 | M6: ='YTD BS'!M6 | N6: ='BALANCE SHEET'!E6 | O6: ='YTD BS'!O6 | P6: ='YTD BS'!P6 | Q6: ='YTD BS'!Q6 | R6: ='BALANCE SHEET'!F6 | S6: ='YTD BS'!S6 | T6: ='YTD BS'!T6 | U6: ='YTD BS'!U6 | V6: ='BALANCE SHEET'!G6 | W6: ='YTD BS'!W6 | X6: ='YTD BS'!X6 | Y6: ='YTD BS'!Y6 | Z6: ='BALANCE SHEET'!H6 | AA6: ='QTR P&L'!AD2*'BS DRIVERS'!AA6 | AB6: ='QTR P&L'!AE2*'BS DRIVERS'!AB6 | AC6: ='QTR P&L'!AF2*'BS DRIVERS'!AC6 | AD6: ='QTR P&L'!AG2*'BS DRIVERS'!AD6 | AE6: ='QTR P&L'!AH2*'BS DRIVERS'!AE6 | AF6: ='QTR P&L'!AI2*'BS DRIVERS'!AF6 | AG6: ='QTR P&L'!AJ2*'BS DRIVERS'!AG6 | AH6: ='QTR P&L'!AK2*'BS DRIVERS'!AH6 | ... AT6: ='QTR P&L'!AW2*'BS DRIVERS'!AT6
A7: Deferred Other Costs - Current | B7: ='BALANCE SHEET'!B7 | C7: ='YTD BS'!C7 | D7: ='YTD BS'!D7 | E7: ='YTD BS'!E7 | F7: ='BALANCE SHEET'!C7 | G7: ='YTD BS'!G7 | H7: ='YTD BS'!H7 | I7: ='YTD BS'!I7 | J7: ='BALANCE SHEET'!D7 | K7: ='YTD BS'!K7 | L7: ='YTD BS'!L7 | M7: ='YTD BS'!M7 | N7: ='BALANCE SHEET'!E7 | O7: ='YTD BS'!O7 | P7: ='YTD BS'!P7 | Q7: ='YTD BS'!Q7 | R7: ='BALANCE SHEET'!F7 | S7: ='YTD BS'!S7 | T7: ='YTD BS'!T7 | U7: ='YTD BS'!U7 | V7: ='BALANCE SHEET'!G7 | W7: ='YTD BS'!W7 | X7: ='YTD BS'!X7 | Y7: ='YTD BS'!Y7 | Z7: ='BALANCE SHEET'!H7 | AA7: ='QTR P&L'!AD2*'BS DRIVERS'!AA7 | AB7: ='QTR P&L'!AE2*'BS DRIVERS'!AB7 | AC7: ='QTR P&L'!AF2*'BS DRIVERS'!AC7 | AD7: ='QTR P&L'!AG2*'BS DRIVERS'!AD7 | AE7: ='QTR P&L'!AH2*'BS DRIVERS'!AE7 | AF7: ='QTR P&L'!AI2*'BS DRIVERS'!AF7 | AG7: ='QTR P&L'!AJ2*'BS DRIVERS'!AG7 | AH7: ='QTR P&L'!AK2*'BS DRIVERS'!AH7 | ... AT7: ='QTR P&L'!AW2*'BS DRIVERS'!AT7
A8: Total Current Assets | B8: ='BALANCE SHEET'!B8 | C8: ='YTD BS'!C8 | D8: ='YTD BS'!D8 | E8: ='YTD BS'!E8 | F8: ='BALANCE SHEET'!C8 | G8: ='YTD BS'!G8 | H8: ='YTD BS'!H8 | I8: ='YTD BS'!I8 | J8: ='BALANCE SHEET'!D8 | K8: ='YTD BS'!K8 | L8: ='YTD BS'!L8 | M8: ='YTD BS'!M8 | N8: ='BALANCE SHEET'!E8 | O8: ='YTD BS'!O8 | P8: ='YTD BS'!P8 | Q8: ='YTD BS'!Q8 | R8: ='BALANCE SHEET'!F8 | S8: ='YTD BS'!S8 | T8: ='YTD BS'!T8 | U8: ='YTD BS'!U8 | V8: ='BALANCE SHEET'!G8 | W8: ='YTD BS'!W8 | X8: ='YTD BS'!X8 | Y8: ='YTD BS'!Y8 | Z8: ='BALANCE SHEET'!H8 | AA8: =SUM(AA2:AA7) | AB8: =SUM(AB2:AB7) | AC8: =SUM(AC2:AC7) | AD8: =SUM(AD2:AD7) | AE8: =SUM(AE2:AE7) | AF8: =SUM(AF2:AF7) | AG8: =SUM(AG2:AG7) | AH8: =SUM(AH2:AH7) | ... AT8: =SUM(AT2:AT7)
A9: Note Receivable - Non-Current | B9: ='BALANCE SHEET'!B9 | C9: ='YTD BS'!C9 | D9: ='YTD BS'!D9 | E9: ='YTD BS'!E9 | F9: ='BALANCE SHEET'!C9 | G9: ='YTD BS'!G9 | H9: ='YTD BS'!H9 | I9: ='YTD BS'!I9 | J9: ='BALANCE SHEET'!D9 | K9: ='YTD BS'!K9 | L9: ='YTD BS'!L9 | M9: ='YTD BS'!M9 | N9: ='BALANCE SHEET'!E9 | O9: ='YTD BS'!O9 | P9: ='YTD BS'!P9 | Q9: ='YTD BS'!Q9 | R9: ='BALANCE SHEET'!F9 | S9: ='YTD BS'!S9 | T9: ='YTD BS'!T9 | U9: ='YTD BS'!U9 | V9: ='BALANCE SHEET'!G9 | W9: ='YTD BS'!W9 | X9: ='YTD BS'!X9 | Y9: ='YTD BS'!Y9 | Z9: ='BALANCE SHEET'!H9 | AA9: ='QTR P&L'!AD2*'BS DRIVERS'!AA8 | AB9: ='QTR P&L'!AE2*'BS DRIVERS'!AB8 | AC9: ='QTR P&L'!AF2*'BS DRIVERS'!AC8 | AD9: ='QTR P&L'!AG2*'BS DRIVERS'!AD8 | AE9: ='QTR P&L'!AH2*'BS DRIVERS'!AE8 | AF9: ='QTR P&L'!AI2*'BS DRIVERS'!AF8 | AG9: ='QTR P&L'!AJ2*'BS DRIVERS'!AG8 | AH9: ='QTR P&L'!AK2*'BS DRIVERS'!AH8 | ... AT9: ='QTR P&L'!AW2*'BS DRIVERS'!AT8
A10: Net PP&E | B10: ='BALANCE SHEET'!B10 | C10: ='YTD BS'!C10 | D10: ='YTD BS'!D10 | E10: ='YTD BS'!E10 | F10: ='BALANCE SHEET'!C10 | G10: ='YTD BS'!G10 | H10: ='YTD BS'!H10 | I10: ='YTD BS'!I10 | J10: ='BALANCE SHEET'!D10 | K10: ='YTD BS'!K10 | L10: ='YTD BS'!L10 | M10: ='YTD BS'!M10 | N10: ='BALANCE SHEET'!E10 | O10: ='YTD BS'!O10 | P10: ='YTD BS'!P10 | Q10: ='YTD BS'!Q10 | R10: ='BALANCE SHEET'!F10 | S10: ='YTD BS'!S10 | T10: ='YTD BS'!T10 | U10: ='YTD BS'!U10 | V10: ='BALANCE SHEET'!G10 | W10: ='YTD BS'!W10 | X10: ='YTD BS'!X10 | Y10: ='YTD BS'!Y10 | Z10: ='BALANCE SHEET'!H10 | AA10: ='BS DRIVERS'!AA9 | AB10: ='BS DRIVERS'!AB9 | AC10: ='BS DRIVERS'!AC9 | AD10: ='BS DRIVERS'!AD9 | AE10: ='BS DRIVERS'!AE9 | AF10: ='BS DRIVERS'!AF9 | AG10: ='BS DRIVERS'!AG9 | AH10: ='BS DRIVERS'!AH9 | ... AT10: ='BS DRIVERS'!AT9
A11: ROU Assets - Operating - Non-Current | B11: ='BALANCE SHEET'!B11 | C11: ='YTD BS'!C11 | D11: ='YTD BS'!D11 | E11: ='YTD BS'!E11 | F11: ='BALANCE SHEET'!C11 | G11: ='YTD BS'!G11 | H11: ='YTD BS'!H11 | I11: ='YTD BS'!I11 | J11: ='BALANCE SHEET'!D11 | K11: ='YTD BS'!K11 | L11: ='YTD BS'!L11 | M11: ='YTD BS'!M11 | N11: ='BALANCE SHEET'!E11 | O11: ='YTD BS'!O11 | P11: ='YTD BS'!P11 | Q11: ='YTD BS'!Q11 | R11: ='BALANCE SHEET'!F11 | S11: ='YTD BS'!S11 | T11: ='YTD BS'!T11 | U11: ='YTD BS'!U11 | V11: ='BALANCE SHEET'!G11 | W11: ='YTD BS'!W11 | X11: ='YTD BS'!X11 | Y11: ='YTD BS'!Y11 | Z11: ='BALANCE SHEET'!H11 | AA11: ='QTR P&L'!AD2*'BS DRIVERS'!AA10 | AB11: ='QTR P&L'!AE2*'BS DRIVERS'!AB10 | AC11: ='QTR P&L'!AF2*'BS DRIVERS'!AC10 | AD11: ='QTR P&L'!AG2*'BS DRIVERS'!AD10 | AE11: ='QTR P&L'!AH2*'BS DRIVERS'!AE10 | AF11: ='QTR P&L'!AI2*'BS DRIVERS'!AF10 | AG11: ='QTR P&L'!AJ2*'BS DRIVERS'!AG10 | AH11: ='QTR P&L'!AK2*'BS DRIVERS'!AH10 | ... AT11: ='QTR P&L'!AW2*'BS DRIVERS'!AT10
A12: Intangible Assets | B12: ='BALANCE SHEET'!B13 | C12: ='YTD BS'!C12 | D12: ='YTD BS'!D12 | E12: ='YTD BS'!E12 | F12: ='BALANCE SHEET'!C13 | G12: ='YTD BS'!G12 | H12: ='YTD BS'!H12 | I12: ='YTD BS'!I12 | J12: ='BALANCE SHEET'!D13 | K12: ='YTD BS'!K12 | L12: ='YTD BS'!L12 | M12: ='YTD BS'!M12 | N12: ='BALANCE SHEET'!E13 | O12: ='YTD BS'!O12 | P12: ='YTD BS'!P12 | Q12: ='YTD BS'!Q12 | R12: ='BALANCE SHEET'!F13 | S12: ='YTD BS'!S12 | T12: ='YTD BS'!T12 | U12: ='YTD BS'!U12 | V12: ='BALANCE SHEET'!G13 | W12: ='YTD BS'!W12 | X12: ='YTD BS'!X12 | Y12: ='YTD BS'!Y12 | Z12: ='BALANCE SHEET'!H13 | AA12: ='BS DRIVERS'!AA11 | AB12: ='BS DRIVERS'!AB11 | AC12: ='BS DRIVERS'!AC11 | AD12: ='BS DRIVERS'!AD11 | AE12: ='BS DRIVERS'!AE11 | AF12: ='BS DRIVERS'!AF11 | AG12: ='BS DRIVERS'!AG11 | AH12: ='BS DRIVERS'!AH11 | ... AT12: ='BS DRIVERS'!AT11
A13: Goodwill | B13: ='BALANCE SHEET'!B14 | C13: ='YTD BS'!C13 | D13: ='YTD BS'!D13 | E13: ='YTD BS'!E13 | F13: ='BALANCE SHEET'!C14 | G13: ='YTD BS'!G13 | H13: ='YTD BS'!H13 | I13: ='YTD BS'!I13 | J13: ='BALANCE SHEET'!D14 | K13: ='YTD BS'!K13 | L13: ='YTD BS'!L13 | M13: ='YTD BS'!M13 | N13: ='BALANCE SHEET'!E14 | O13: ='YTD BS'!O13 | P13: ='YTD BS'!P13 | Q13: ='YTD BS'!Q13 | R13: ='BALANCE SHEET'!F14 | S13: ='YTD BS'!S13 | T13: ='YTD BS'!T13 | U13: ='YTD BS'!U13 | V13: ='BALANCE SHEET'!G14 | W13: ='YTD BS'!W13 | X13: ='YTD BS'!X13 | Y13: ='YTD BS'!Y13 | Z13: ='BALANCE SHEET'!H14 | AA13: ='BS DRIVERS'!AA12 | AB13: ='BS DRIVERS'!AB12 | AC13: ='BS DRIVERS'!AC12 | AD13: ='BS DRIVERS'!AD12 | AE13: ='BS DRIVERS'!AE12 | AF13: ='BS DRIVERS'!AF12 | AG13: ='BS DRIVERS'!AG12 | AH13: ='BS DRIVERS'!AH12 | ... AT13: ='BS DRIVERS'!AT12
A14: Deferred Other Costs - Non-Current | B14: ='BALANCE SHEET'!B15 | C14: ='YTD BS'!C14 | D14: ='YTD BS'!D14 | E14: ='YTD BS'!E14 | F14: ='BALANCE SHEET'!C15 | G14: ='YTD BS'!G14 | H14: ='YTD BS'!H14 | I14: ='YTD BS'!I14 | J14: ='BALANCE SHEET'!D15 | K14: ='YTD BS'!K14 | L14: ='YTD BS'!L14 | M14: ='YTD BS'!M14 | N14: ='BALANCE SHEET'!E15 | O14: ='YTD BS'!O14 | P14: ='YTD BS'!P14 | Q14: ='YTD BS'!Q14 | R14: ='BALANCE SHEET'!F15 | S14: ='YTD BS'!S14 | T14: ='YTD BS'!T14 | U14: ='YTD BS'!U14 | V14: ='BALANCE SHEET'!G15 | W14: ='YTD BS'!W14 | X14: ='YTD BS'!X14 | Y14: ='YTD BS'!Y14 | Z14: ='BALANCE SHEET'!H15 | AA14: ='QTR P&L'!AD2*'BS DRIVERS'!AA13 | AB14: ='QTR P&L'!AE2*'BS DRIVERS'!AB13 | AC14: ='QTR P&L'!AF2*'BS DRIVERS'!AC13 | AD14: ='QTR P&L'!AG2*'BS DRIVERS'!AD13 | AE14: ='QTR P&L'!AH2*'BS DRIVERS'!AE13 | AF14: ='QTR P&L'!AI2*'BS DRIVERS'!AF13 | AG14: ='QTR P&L'!AJ2*'BS DRIVERS'!AG13 | AH14: ='QTR P&L'!AK2*'BS DRIVERS'!AH13 | ... AT14: ='QTR P&L'!AW2*'BS DRIVERS'!AT13
A15: Deferred Tax Assets | B15: ='BALANCE SHEET'!B16 | C15: ='YTD BS'!C15 | D15: ='YTD BS'!D15 | E15: ='YTD BS'!E15 | F15: ='BALANCE SHEET'!C16 | G15: ='YTD BS'!G15 | H15: ='YTD BS'!H15 | I15: ='YTD BS'!I15 | J15: ='BALANCE SHEET'!D16 | K15: ='YTD BS'!K15 | L15: ='YTD BS'!L15 | M15: ='YTD BS'!M15 | N15: ='BALANCE SHEET'!E16 | O15: ='YTD BS'!O15 | P15: ='YTD BS'!P15 | Q15: ='YTD BS'!Q15 | R15: ='BALANCE SHEET'!F16 | S15: ='YTD BS'!S15 | T15: ='YTD BS'!T15 | U15: ='YTD BS'!U15 | V15: ='BALANCE SHEET'!G16 | W15: ='YTD BS'!W15 | X15: ='YTD BS'!X15 | Y15: ='YTD BS'!Y15 | Z15: ='BALANCE SHEET'!H16 | AA15: ='BS DRIVERS'!AA14 | AB15: ='BS DRIVERS'!AB14 | AC15: ='BS DRIVERS'!AC14 | AD15: ='BS DRIVERS'!AD14 | AE15: ='BS DRIVERS'!AE14 | AF15: ='BS DRIVERS'!AF14 | AG15: ='BS DRIVERS'!AG14 | AH15: ='BS DRIVERS'!AH14 | ... AT15: ='BS DRIVERS'!AT14
A16: ROU Assets - Finance - Non-Current | B16: ='BALANCE SHEET'!B12 | C16: ='YTD BS'!C16 | D16: ='YTD BS'!D16 | E16: ='YTD BS'!E16 | F16: ='BALANCE SHEET'!C12 | G16: ='YTD BS'!G16 | H16: ='YTD BS'!H16 | I16: ='YTD BS'!I16 | J16: ='BALANCE SHEET'!D12 | K16: ='YTD BS'!K16 | L16: ='YTD BS'!L16 | M16: ='YTD BS'!M16 | N16: ='BALANCE SHEET'!E12 | O16: ='YTD BS'!O16 | P16: ='YTD BS'!P16 | Q16: ='YTD BS'!Q16 | R16: ='BALANCE SHEET'!F12 | S16: ='YTD BS'!S16 | T16: ='YTD BS'!T16 | U16: ='YTD BS'!U16 | V16: ='BALANCE SHEET'!G12 | W16: ='YTD BS'!W16 | X16: ='YTD BS'!X16 | Y16: ='YTD BS'!Y16 | Z16: ='BALANCE SHEET'!H12 | AA16: ='QTR P&L'!AD2*'BS DRIVERS'!AA15 | AB16: ='QTR P&L'!AE2*'BS DRIVERS'!AB15 | AC16: ='QTR P&L'!AF2*'BS DRIVERS'!AC15 | AD16: ='QTR P&L'!AG2*'BS DRIVERS'!AD15 | AE16: ='QTR P&L'!AH2*'BS DRIVERS'!AE15 | AF16: ='QTR P&L'!AI2*'BS DRIVERS'!AF15 | AG16: ='QTR P&L'!AJ2*'BS DRIVERS'!AG15 | AH16: ='QTR P&L'!AK2*'BS DRIVERS'!AH15 | ... AT16: ='QTR P&L'!AW2*'BS DRIVERS'!AT15
A17: Other Non-Current Assets | B17: ='BALANCE SHEET'!B17 | C17: ='YTD BS'!C17 | D17: ='YTD BS'!D17 | E17: ='YTD BS'!E17 | F17: ='BALANCE SHEET'!C17 | G17: ='YTD BS'!G17 | H17: ='YTD BS'!H17 | I17: ='YTD BS'!I17 | J17: ='BALANCE SHEET'!D17 | K17: ='YTD BS'!K17 | L17: ='YTD BS'!L17 | M17: ='YTD BS'!M17 | N17: ='BALANCE SHEET'!E17 | O17: ='YTD BS'!O17 | P17: ='YTD BS'!P17 | Q17: ='YTD BS'!Q17 | R17: ='BALANCE SHEET'!F17 | S17: ='YTD BS'!S17 | T17: ='YTD BS'!T17 | U17: ='YTD BS'!U17 | V17: ='BALANCE SHEET'!G17 | W17: ='YTD BS'!W17 | X17: ='YTD BS'!X17 | Y17: ='YTD BS'!Y17 | Z17: ='BALANCE SHEET'!H17 | AA17: ='QTR P&L'!AD2*'BS DRIVERS'!AA16 | AB17: ='QTR P&L'!AE2*'BS DRIVERS'!AB16 | AC17: ='QTR P&L'!AF2*'BS DRIVERS'!AC16 | AD17: ='QTR P&L'!AG2*'BS DRIVERS'!AD16 | AE17: ='QTR P&L'!AH2*'BS DRIVERS'!AE16 | AF17: ='QTR P&L'!AI2*'BS DRIVERS'!AF16 | AG17: ='QTR P&L'!AJ2*'BS DRIVERS'!AG16 | AH17: ='QTR P&L'!AK2*'BS DRIVERS'!AH16 | ... AT17: ='QTR P&L'!AW2*'BS DRIVERS'!AT16
A18: Total Assets | B18: ='BALANCE SHEET'!B18 | C18: ='YTD BS'!C18 | D18: ='YTD BS'!D18 | E18: ='YTD BS'!E18 | F18: ='BALANCE SHEET'!C18 | G18: ='YTD BS'!G18 | H18: ='YTD BS'!H18 | I18: ='YTD BS'!I18 | J18: ='BALANCE SHEET'!D18 | K18: ='YTD BS'!K18 | L18: ='YTD BS'!L18 | M18: ='YTD BS'!M18 | N18: ='BALANCE SHEET'!E18 | O18: ='YTD BS'!O18 | P18: ='YTD BS'!P18 | Q18: ='YTD BS'!Q18 | R18: ='BALANCE SHEET'!F18 | S18: ='YTD BS'!S18 | T18: ='YTD BS'!T18 | U18: ='YTD BS'!U18 | V18: ='BALANCE SHEET'!G18 | W18: ='YTD BS'!W18 | X18: ='YTD BS'!X18 | Y18: ='YTD BS'!Y18 | Z18: ='BALANCE SHEET'!H18 | AA18: =AA8+SUM(AA9:AA17) | AB18: =AB8+SUM(AB9:AB17) | AC18: =AC8+SUM(AC9:AC17) | AD18: =AD8+SUM(AD9:AD17) | AE18: =AE8+SUM(AE9:AE17) | AF18: =AF8+SUM(AF9:AF17) | AG18: =AG8+SUM(AG9:AG17) | AH18: =AH8+SUM(AH9:AH17) | ... AT18: =AT8+SUM(AT9:AT17)
A19: Accounts Payable | B19: ='BALANCE SHEET'!B19 | C19: ='YTD BS'!C19 | D19: ='YTD BS'!D19 | E19: ='YTD BS'!E19 | F19: ='BALANCE SHEET'!C19 | G19: ='YTD BS'!G19 | H19: ='YTD BS'!H19 | I19: ='YTD BS'!I19 | J19: ='BALANCE SHEET'!D19 | K19: ='YTD BS'!K19 | L19: ='YTD BS'!L19 | M19: ='YTD BS'!M19 | N19: ='BALANCE SHEET'!E19 | O19: ='YTD BS'!O19 | P19: ='YTD BS'!P19 | Q19: ='YTD BS'!Q19 | R19: ='BALANCE SHEET'!F19 | S19: ='YTD BS'!S19 | T19: ='YTD BS'!T19 | U19: ='YTD BS'!U19 | V19: ='BALANCE SHEET'!G19 | W19: ='YTD BS'!W19 | X19: ='YTD BS'!X19 | Y19: ='YTD BS'!Y19 | Z19: ='BALANCE SHEET'!H19 | AA19: ='QTR P&L'!AD3*'BS DRIVERS'!AA17/ASSUMPTIONS!$B$2 | AB19: ='QTR P&L'!AE3*'BS DRIVERS'!AB17/ASSUMPTIONS!$B$2 | AC19: ='QTR P&L'!AF3*'BS DRIVERS'!AC17/ASSUMPTIONS!$B$2 | AD19: ='QTR P&L'!AG3*'BS DRIVERS'!AD17/ASSUMPTIONS!$B$2 | AE19: ='QTR P&L'!AH3*'BS DRIVERS'!AE17/ASSUMPTIONS!$B$2 | AF19: ='QTR P&L'!AI3*'BS DRIVERS'!AF17/ASSUMPTIONS!$B$2 | AG19: ='QTR P&L'!AJ3*'BS DRIVERS'!AG17/ASSUMPTIONS!$B$2 | AH19: ='QTR P&L'!AK3*'BS DRIVERS'!AH17/ASSUMPTIONS!$B$2 | ... AT19: ='QTR P&L'!AW3*'BS DRIVERS'!AT17/ASSUMPTIONS!$B$2
A20: Accrued Expenses | B20: ='BALANCE SHEET'!B20 | C20: ='YTD BS'!C20 | D20: ='YTD BS'!D20 | E20: ='YTD BS'!E20 | F20: ='BALANCE SHEET'!C20 | G20: ='YTD BS'!G20 | H20: ='YTD BS'!H20 | I20: ='YTD BS'!I20 | J20: ='BALANCE SHEET'!D20 | K20: ='YTD BS'!K20 | L20: ='YTD BS'!L20 | M20: ='YTD BS'!M20 | N20: ='BALANCE SHEET'!E20 | O20: ='YTD BS'!O20 | P20: ='YTD BS'!P20 | Q20: ='YTD BS'!Q20 | R20: ='BALANCE SHEET'!F20 | S20: ='YTD BS'!S20 | T20: ='YTD BS'!T20 | U20: ='YTD BS'!U20 | V20: ='BALANCE SHEET'!G20 | W20: ='YTD BS'!W20 | X20: ='YTD BS'!X20 | Y20: ='YTD BS'!Y20 | Z20: ='BALANCE SHEET'!H20 | AA20: ='QTR P&L'!AD2*'BS DRIVERS'!AA18 | AB20: ='QTR P&L'!AE2*'BS DRIVERS'!AB18 | AC20: ='QTR P&L'!AF2*'BS DRIVERS'!AC18 | AD20: ='QTR P&L'!AG2*'BS DRIVERS'!AD18 | AE20: ='QTR P&L'!AH2*'BS DRIVERS'!AE18 | AF20: ='QTR P&L'!AI2*'BS DRIVERS'!AF18 | AG20: ='QTR P&L'!AJ2*'BS DRIVERS'!AG18 | AH20: ='QTR P&L'!AK2*'BS DRIVERS'!AH18 | ... AT20: ='QTR P&L'!AW2*'BS DRIVERS'!AT18
A21: Income Taxes Payable | B21: ='BALANCE SHEET'!B21 | C21: ='YTD BS'!C21 | D21: ='YTD BS'!D21 | E21: ='YTD BS'!E21 | F21: ='BALANCE SHEET'!C21 | G21: ='YTD BS'!G21 | H21: ='YTD BS'!H21 | I21: ='YTD BS'!I21 | J21: ='BALANCE SHEET'!D21 | K21: ='YTD BS'!K21 | L21: ='YTD BS'!L21 | M21: ='YTD BS'!M21 | N21: ='BALANCE SHEET'!E21 | O21: ='YTD BS'!O21 | P21: ='YTD BS'!P21 | Q21: ='YTD BS'!Q21 | R21: ='BALANCE SHEET'!F21 | S21: ='YTD BS'!S21 | T21: ='YTD BS'!T21 | U21: ='YTD BS'!U21 | V21: ='BALANCE SHEET'!G21 | W21: ='YTD BS'!W21 | X21: ='YTD BS'!X21 | Y21: ='YTD BS'!Y21 | Z21: ='BALANCE SHEET'!H21 | AA21: ='QTR P&L'!AD2*'BS DRIVERS'!AA19 | AB21: ='QTR P&L'!AE2*'BS DRIVERS'!AB19 | AC21: ='QTR P&L'!AF2*'BS DRIVERS'!AC19 | AD21: ='QTR P&L'!AG2*'BS DRIVERS'!AD19 | AE21: ='QTR P&L'!AH2*'BS DRIVERS'!AE19 | AF21: ='QTR P&L'!AI2*'BS DRIVERS'!AF19 | AG21: ='QTR P&L'!AJ2*'BS DRIVERS'!AG19 | AH21: ='QTR P&L'!AK2*'BS DRIVERS'!AH19 | ... AT21: ='QTR P&L'!AW2*'BS DRIVERS'!AT19
A22: Accrued Distributor Termination Fees | B22: ='BALANCE SHEET'!B22 | C22: ='YTD BS'!C22 | D22: ='YTD BS'!D22 | E22: ='YTD BS'!E22 | F22: ='BALANCE SHEET'!C22 | G22: ='YTD BS'!G22 | H22: ='YTD BS'!H22 | I22: ='YTD BS'!I22 | J22: ='BALANCE SHEET'!D22 | K22: ='YTD BS'!K22 | L22: ='YTD BS'!L22 | M22: ='YTD BS'!M22 | N22: ='BALANCE SHEET'!E22 | O22: ='YTD BS'!O22 | P22: ='YTD BS'!P22 | Q22: ='YTD BS'!Q22 | R22: ='BALANCE SHEET'!F22 | S22: ='YTD BS'!S22 | T22: ='YTD BS'!T22 | U22: ='YTD BS'!U22 | V22: ='BALANCE SHEET'!G22 | W22: ='YTD BS'!W22 | X22: ='YTD BS'!X22 | Y22: ='YTD BS'!Y22 | Z22: ='BALANCE SHEET'!H22 | AA22: ='BS DRIVERS'!AA20 | AB22: ='BS DRIVERS'!AB20 | AC22: ='BS DRIVERS'!AC20 | AD22: ='BS DRIVERS'!AD20 | AE22: ='BS DRIVERS'!AE20 | AF22: ='BS DRIVERS'!AF20 | AG22: ='BS DRIVERS'!AG20 | AH22: ='BS DRIVERS'!AH20 | ... AT22: ='BS DRIVERS'!AT20
A23: Accrued Promotional Allowance | B23: ='BALANCE SHEET'!B23 | C23: ='YTD BS'!C23 | D23: ='YTD BS'!D23 | E23: ='YTD BS'!E23 | F23: ='BALANCE SHEET'!C23 | G23: ='YTD BS'!G23 | H23: ='YTD BS'!H23 | I23: ='YTD BS'!I23 | J23: ='BALANCE SHEET'!D23 | K23: ='YTD BS'!K23 | L23: ='YTD BS'!L23 | M23: ='YTD BS'!M23 | N23: ='BALANCE SHEET'!E23 | O23: ='YTD BS'!O23 | P23: ='YTD BS'!P23 | Q23: ='YTD BS'!Q23 | R23: ='BALANCE SHEET'!F23 | S23: ='YTD BS'!S23 | T23: ='YTD BS'!T23 | U23: ='YTD BS'!U23 | V23: ='BALANCE SHEET'!G23 | W23: ='YTD BS'!W23 | X23: ='YTD BS'!X23 | Y23: ='YTD BS'!Y23 | Z23: ='BALANCE SHEET'!H23 | AA23: ='QTR P&L'!AD2*'BS DRIVERS'!AA21 | AB23: ='QTR P&L'!AE2*'BS DRIVERS'!AB21 | AC23: ='QTR P&L'!AF2*'BS DRIVERS'!AC21 | AD23: ='QTR P&L'!AG2*'BS DRIVERS'!AD21 | AE23: ='QTR P&L'!AH2*'BS DRIVERS'!AE21 | AF23: ='QTR P&L'!AI2*'BS DRIVERS'!AF21 | AG23: ='QTR P&L'!AJ2*'BS DRIVERS'!AG21 | AH23: ='QTR P&L'!AK2*'BS DRIVERS'!AH21 | ... AT23: ='QTR P&L'!AW2*'BS DRIVERS'!AT21
A24: Lease Liability - Operating - Current | B24: ='BALANCE SHEET'!B24 | C24: ='YTD BS'!C24 | D24: ='YTD BS'!D24 | E24: ='YTD BS'!E24 | F24: ='BALANCE SHEET'!C24 | G24: ='YTD BS'!G24 | H24: ='YTD BS'!H24 | I24: ='YTD BS'!I24 | J24: ='BALANCE SHEET'!D24 | K24: ='YTD BS'!K24 | L24: ='YTD BS'!L24 | M24: ='YTD BS'!M24 | N24: ='BALANCE SHEET'!E24 | O24: ='YTD BS'!O24 | P24: ='YTD BS'!P24 | Q24: ='YTD BS'!Q24 | R24: ='BALANCE SHEET'!F24 | S24: ='YTD BS'!S24 | T24: ='YTD BS'!T24 | U24: ='YTD BS'!U24 | V24: ='BALANCE SHEET'!G24 | W24: ='YTD BS'!W24 | X24: ='YTD BS'!X24 | Y24: ='YTD BS'!Y24 | Z24: ='BALANCE SHEET'!H24 | AA24: ='QTR P&L'!AD2*'BS DRIVERS'!AA22 | AB24: ='QTR P&L'!AE2*'BS DRIVERS'!AB22 | AC24: ='QTR P&L'!AF2*'BS DRIVERS'!AC22 | AD24: ='QTR P&L'!AG2*'BS DRIVERS'!AD22 | AE24: ='QTR P&L'!AH2*'BS DRIVERS'!AE22 | AF24: ='QTR P&L'!AI2*'BS DRIVERS'!AF22 | AG24: ='QTR P&L'!AJ2*'BS DRIVERS'!AG22 | AH24: ='QTR P&L'!AK2*'BS DRIVERS'!AH22 | ... AT24: ='QTR P&L'!AW2*'BS DRIVERS'!AT22
A25: Bonds Payable, Net | B25: ='BALANCE SHEET'!B26 | C25: ='YTD BS'!C25 | D25: ='YTD BS'!D25 | E25: ='YTD BS'!E25 | F25: ='BALANCE SHEET'!C26 | G25: ='YTD BS'!G25 | H25: ='YTD BS'!H25 | I25: ='YTD BS'!I25 | J25: ='BALANCE SHEET'!D26 | K25: ='YTD BS'!K25 | L25: ='YTD BS'!L25 | M25: ='YTD BS'!M25 | N25: ='BALANCE SHEET'!E26 | O25: ='YTD BS'!O25 | P25: ='YTD BS'!P25 | Q25: ='YTD BS'!Q25 | R25: ='BALANCE SHEET'!F26 | S25: ='YTD BS'!S25 | T25: ='YTD BS'!T25 | U25: ='YTD BS'!U25 | V25: ='BALANCE SHEET'!G26 | W25: ='YTD BS'!W25 | X25: ='YTD BS'!X25 | Y25: ='YTD BS'!Y25 | Z25: ='BALANCE SHEET'!H26 | AA25: ='BS DRIVERS'!AA23 | AB25: ='BS DRIVERS'!AB23 | AC25: ='BS DRIVERS'!AC23 | AD25: ='BS DRIVERS'!AD23 | AE25: ='BS DRIVERS'!AE23 | AF25: ='BS DRIVERS'!AF23 | AG25: ='BS DRIVERS'!AG23 | AH25: ='BS DRIVERS'!AH23 | ... AT25: ='BS DRIVERS'!AT23
A26: Lease Liability - Finance - Current | B26: ='BALANCE SHEET'!B25 | C26: ='YTD BS'!C26 | D26: ='YTD BS'!D26 | E26: ='YTD BS'!E26 | F26: ='BALANCE SHEET'!C25 | G26: ='YTD BS'!G26 | H26: ='YTD BS'!H26 | I26: ='YTD BS'!I26 | J26: ='BALANCE SHEET'!D25 | K26: ='YTD BS'!K26 | L26: ='YTD BS'!L26 | M26: ='YTD BS'!M26 | N26: ='BALANCE SHEET'!E25 | O26: ='YTD BS'!O26 | P26: ='YTD BS'!P26 | Q26: ='YTD BS'!Q26 | R26: ='BALANCE SHEET'!F25 | S26: ='YTD BS'!S26 | T26: ='YTD BS'!T26 | U26: ='YTD BS'!U26 | V26: ='BALANCE SHEET'!G25 | W26: ='YTD BS'!W26 | X26: ='YTD BS'!X26 | Y26: ='YTD BS'!Y26 | Z26: ='BALANCE SHEET'!H25 | AA26: ='QTR P&L'!AD2*'BS DRIVERS'!AA24 | AB26: ='QTR P&L'!AE2*'BS DRIVERS'!AB24 | AC26: ='QTR P&L'!AF2*'BS DRIVERS'!AC24 | AD26: ='QTR P&L'!AG2*'BS DRIVERS'!AD24 | AE26: ='QTR P&L'!AH2*'BS DRIVERS'!AE24 | AF26: ='QTR P&L'!AI2*'BS DRIVERS'!AF24 | AG26: ='QTR P&L'!AJ2*'BS DRIVERS'!AG24 | AH26: ='QTR P&L'!AK2*'BS DRIVERS'!AH24 | ... AT26: ='QTR P&L'!AW2*'BS DRIVERS'!AT24
A27: Contingent Consideration - Current | B27: ='BALANCE SHEET'!B27 | C27: ='YTD BS'!C27 | D27: ='YTD BS'!D27 | E27: ='YTD BS'!E27 | F27: ='BALANCE SHEET'!C27 | G27: ='YTD BS'!G27 | H27: ='YTD BS'!H27 | I27: ='YTD BS'!I27 | J27: ='BALANCE SHEET'!D27 | K27: ='YTD BS'!K27 | L27: ='YTD BS'!L27 | M27: ='YTD BS'!M27 | N27: ='BALANCE SHEET'!E27 | O27: ='YTD BS'!O27 | P27: ='YTD BS'!P27 | Q27: ='YTD BS'!Q27 | R27: ='BALANCE SHEET'!F27 | S27: ='YTD BS'!S27 | T27: ='YTD BS'!T27 | U27: ='YTD BS'!U27 | V27: ='BALANCE SHEET'!G27 | W27: ='YTD BS'!W27 | X27: ='YTD BS'!X27 | Y27: ='YTD BS'!Y27 | Z27: ='BALANCE SHEET'!H27 | AA27: ='QTR P&L'!AD2*'BS DRIVERS'!AA25 | AB27: ='QTR P&L'!AE2*'BS DRIVERS'!AB25 | AC27: ='QTR P&L'!AF2*'BS DRIVERS'!AC25 | AD27: ='QTR P&L'!AG2*'BS DRIVERS'!AD25 | AE27: ='QTR P&L'!AH2*'BS DRIVERS'!AE25 | AF27: ='QTR P&L'!AI2*'BS DRIVERS'!AF25 | AG27: ='QTR P&L'!AJ2*'BS DRIVERS'!AG25 | AH27: ='QTR P&L'!AK2*'BS DRIVERS'!AH25 | ... AT27: ='QTR P&L'!AW2*'BS DRIVERS'!AT25
A28: Deferred Revenue - Current | B28: ='BALANCE SHEET'!B28 | C28: ='YTD BS'!C28 | D28: ='YTD BS'!D28 | E28: ='YTD BS'!E28 | F28: ='BALANCE SHEET'!C28 | G28: ='YTD BS'!G28 | H28: ='YTD BS'!H28 | I28: ='YTD BS'!I28 | J28: ='BALANCE SHEET'!D28 | K28: ='YTD BS'!K28 | L28: ='YTD BS'!L28 | M28: ='YTD BS'!M28 | N28: ='BALANCE SHEET'!E28 | O28: ='YTD BS'!O28 | P28: ='YTD BS'!P28 | Q28: ='YTD BS'!Q28 | R28: ='BALANCE SHEET'!F28 | S28: ='YTD BS'!S28 | T28: ='YTD BS'!T28 | U28: ='YTD BS'!U28 | V28: ='BALANCE SHEET'!G28 | W28: ='YTD BS'!W28 | X28: ='YTD BS'!X28 | Y28: ='YTD BS'!Y28 | Z28: ='BALANCE SHEET'!H28 | AA28: ='QTR P&L'!AD2*'BS DRIVERS'!AA26 | AB28: ='QTR P&L'!AE2*'BS DRIVERS'!AB26 | AC28: ='QTR P&L'!AF2*'BS DRIVERS'!AC26 | AD28: ='QTR P&L'!AG2*'BS DRIVERS'!AD26 | AE28: ='QTR P&L'!AH2*'BS DRIVERS'!AE26 | AF28: ='QTR P&L'!AI2*'BS DRIVERS'!AF26 | AG28: ='QTR P&L'!AJ2*'BS DRIVERS'!AG26 | AH28: ='QTR P&L'!AK2*'BS DRIVERS'!AH26 | ... AT28: ='QTR P&L'!AW2*'BS DRIVERS'!AT26
A29: Other Current Liabilities | B29: ='BALANCE SHEET'!B29 | C29: ='YTD BS'!C29 | D29: ='YTD BS'!D29 | E29: ='YTD BS'!E29 | F29: ='BALANCE SHEET'!C29 | G29: ='YTD BS'!G29 | H29: ='YTD BS'!H29 | I29: ='YTD BS'!I29 | J29: ='BALANCE SHEET'!D29 | K29: ='YTD BS'!K29 | L29: ='YTD BS'!L29 | M29: ='YTD BS'!M29 | N29: ='BALANCE SHEET'!E29 | O29: ='YTD BS'!O29 | P29: ='YTD BS'!P29 | Q29: ='YTD BS'!Q29 | R29: ='BALANCE SHEET'!F29 | S29: ='YTD BS'!S29 | T29: ='YTD BS'!T29 | U29: ='YTD BS'!U29 | V29: ='BALANCE SHEET'!G29 | W29: ='YTD BS'!W29 | X29: ='YTD BS'!X29 | Y29: ='YTD BS'!Y29 | Z29: ='BALANCE SHEET'!H29 | AA29: ='QTR P&L'!AD2*'BS DRIVERS'!AA27 | AB29: ='QTR P&L'!AE2*'BS DRIVERS'!AB27 | AC29: ='QTR P&L'!AF2*'BS DRIVERS'!AC27 | AD29: ='QTR P&L'!AG2*'BS DRIVERS'!AD27 | AE29: ='QTR P&L'!AH2*'BS DRIVERS'!AE27 | AF29: ='QTR P&L'!AI2*'BS DRIVERS'!AF27 | AG29: ='QTR P&L'!AJ2*'BS DRIVERS'!AG27 | AH29: ='QTR P&L'!AK2*'BS DRIVERS'!AH27 | ... AT29: ='QTR P&L'!AW2*'BS DRIVERS'!AT27
A30: Total Current Liabilities | B30: ='BALANCE SHEET'!B30 | C30: ='YTD BS'!C30 | D30: ='YTD BS'!D30 | E30: ='YTD BS'!E30 | F30: ='BALANCE SHEET'!C30 | G30: ='YTD BS'!G30 | H30: ='YTD BS'!H30 | I30: ='YTD BS'!I30 | J30: ='BALANCE SHEET'!D30 | K30: ='YTD BS'!K30 | L30: ='YTD BS'!L30 | M30: ='YTD BS'!M30 | N30: ='BALANCE SHEET'!E30 | O30: ='YTD BS'!O30 | P30: ='YTD BS'!P30 | Q30: ='YTD BS'!Q30 | R30: ='BALANCE SHEET'!F30 | S30: ='YTD BS'!S30 | T30: ='YTD BS'!T30 | U30: ='YTD BS'!U30 | V30: ='BALANCE SHEET'!G30 | W30: ='YTD BS'!W30 | X30: ='YTD BS'!X30 | Y30: ='YTD BS'!Y30 | Z30: ='BALANCE SHEET'!H30 | AA30: =SUM(AA19:AA29) | AB30: =SUM(AB19:AB29) | AC30: =SUM(AC19:AC29) | AD30: =SUM(AD19:AD29) | AE30: =SUM(AE19:AE29) | AF30: =SUM(AF19:AF29) | AG30: =SUM(AG19:AG29) | AH30: =SUM(AH19:AH29) | ... AT30: =SUM(AT19:AT29)
A31: Lease Liability - Operating - Non-Current | B31: ='BALANCE SHEET'!B31 | C31: ='YTD BS'!C31 | D31: ='YTD BS'!D31 | E31: ='YTD BS'!E31 | F31: ='BALANCE SHEET'!C31 | G31: ='YTD BS'!G31 | H31: ='YTD BS'!H31 | I31: ='YTD BS'!I31 | J31: ='BALANCE SHEET'!D31 | K31: ='YTD BS'!K31 | L31: ='YTD BS'!L31 | M31: ='YTD BS'!M31 | N31: ='BALANCE SHEET'!E31 | O31: ='YTD BS'!O31 | P31: ='YTD BS'!P31 | Q31: ='YTD BS'!Q31 | R31: ='BALANCE SHEET'!F31 | S31: ='YTD BS'!S31 | T31: ='YTD BS'!T31 | U31: ='YTD BS'!U31 | V31: ='BALANCE SHEET'!G31 | W31: ='YTD BS'!W31 | X31: ='YTD BS'!X31 | Y31: ='YTD BS'!Y31 | Z31: ='BALANCE SHEET'!H31 | AA31: ='QTR P&L'!AD2*'BS DRIVERS'!AA28 | AB31: ='QTR P&L'!AE2*'BS DRIVERS'!AB28 | AC31: ='QTR P&L'!AF2*'BS DRIVERS'!AC28 | AD31: ='QTR P&L'!AG2*'BS DRIVERS'!AD28 | AE31: ='QTR P&L'!AH2*'BS DRIVERS'!AE28 | AF31: ='QTR P&L'!AI2*'BS DRIVERS'!AF28 | AG31: ='QTR P&L'!AJ2*'BS DRIVERS'!AG28 | AH31: ='QTR P&L'!AK2*'BS DRIVERS'!AH28 | ... AT31: ='QTR P&L'!AW2*'BS DRIVERS'!AT28
A32: Lease Liability - Finance - Non-Current | B32: ='BALANCE SHEET'!B32 | C32: ='YTD BS'!C32 | D32: ='YTD BS'!D32 | E32: ='YTD BS'!E32 | F32: ='BALANCE SHEET'!C32 | G32: ='YTD BS'!G32 | H32: ='YTD BS'!H32 | I32: ='YTD BS'!I32 | J32: ='BALANCE SHEET'!D32 | K32: ='YTD BS'!K32 | L32: ='YTD BS'!L32 | M32: ='YTD BS'!M32 | N32: ='BALANCE SHEET'!E32 | O32: ='YTD BS'!O32 | P32: ='YTD BS'!P32 | Q32: ='YTD BS'!Q32 | R32: ='BALANCE SHEET'!F32 | S32: ='YTD BS'!S32 | T32: ='YTD BS'!T32 | U32: ='YTD BS'!U32 | V32: ='BALANCE SHEET'!G32 | W32: ='YTD BS'!W32 | X32: ='YTD BS'!X32 | Y32: ='YTD BS'!Y32 | Z32: ='BALANCE SHEET'!H32 | AA32: ='QTR P&L'!AD2*'BS DRIVERS'!AA29 | AB32: ='QTR P&L'!AE2*'BS DRIVERS'!AB29 | AC32: ='QTR P&L'!AF2*'BS DRIVERS'!AC29 | AD32: ='QTR P&L'!AG2*'BS DRIVERS'!AD29 | AE32: ='QTR P&L'!AH2*'BS DRIVERS'!AE29 | AF32: ='QTR P&L'!AI2*'BS DRIVERS'!AF29 | AG32: ='QTR P&L'!AJ2*'BS DRIVERS'!AG29 | AH32: ='QTR P&L'!AK2*'BS DRIVERS'!AH29 | ... AT32: ='QTR P&L'!AW2*'BS DRIVERS'!AT29
A33: Deferred Tax Liability | B33: ='BALANCE SHEET'!B33 | C33: ='YTD BS'!C33 | D33: ='YTD BS'!D33 | E33: ='YTD BS'!E33 | F33: ='BALANCE SHEET'!C33 | G33: ='YTD BS'!G33 | H33: ='YTD BS'!H33 | I33: ='YTD BS'!I33 | J33: ='BALANCE SHEET'!D33 | K33: ='YTD BS'!K33 | L33: ='YTD BS'!L33 | M33: ='YTD BS'!M33 | N33: ='BALANCE SHEET'!E33 | O33: ='YTD BS'!O33 | P33: ='YTD BS'!P33 | Q33: ='YTD BS'!Q33 | R33: ='BALANCE SHEET'!F33 | S33: ='YTD BS'!S33 | T33: ='YTD BS'!T33 | U33: ='YTD BS'!U33 | V33: ='BALANCE SHEET'!G33 | W33: ='YTD BS'!W33 | X33: ='YTD BS'!X33 | Y33: ='YTD BS'!Y33 | Z33: ='BALANCE SHEET'!H33 | AA33: ='BS DRIVERS'!AA30 | AB33: ='BS DRIVERS'!AB30 | AC33: ='BS DRIVERS'!AC30 | AD33: ='BS DRIVERS'!AD30 | AE33: ='BS DRIVERS'!AE30 | AF33: ='BS DRIVERS'!AF30 | AG33: ='BS DRIVERS'!AG30 | AH33: ='BS DRIVERS'!AH30 | ... AT33: ='BS DRIVERS'!AT30
A34: Long-Term Debt | B34: ='BALANCE SHEET'!B34 | C34: ='YTD BS'!C34 | D34: ='YTD BS'!D34 | E34: ='YTD BS'!E34 | F34: ='BALANCE SHEET'!C34 | G34: ='YTD BS'!G34 | H34: ='YTD BS'!H34 | I34: ='YTD BS'!I34 | J34: ='BALANCE SHEET'!D34 | K34: ='YTD BS'!K34 | L34: ='YTD BS'!L34 | M34: ='YTD BS'!M34 | N34: ='BALANCE SHEET'!E34 | O34: ='YTD BS'!O34 | P34: ='YTD BS'!P34 | Q34: ='YTD BS'!Q34 | R34: ='BALANCE SHEET'!F34 | S34: ='YTD BS'!S34 | T34: ='YTD BS'!T34 | U34: ='YTD BS'!U34 | V34: ='BALANCE SHEET'!G34 | W34: ='YTD BS'!W34 | X34: ='YTD BS'!X34 | Y34: ='YTD BS'!Y34 | Z34: ='BALANCE SHEET'!H34 | AA34: ='BS DRIVERS'!AA31 | AB34: ='BS DRIVERS'!AB31 | AC34: ='BS DRIVERS'!AC31 | AD34: ='BS DRIVERS'!AD31 | AE34: ='BS DRIVERS'!AE31 | AF34: ='BS DRIVERS'!AF31 | AG34: ='BS DRIVERS'!AG31 | AH34: ='BS DRIVERS'!AH31 | ... AT34: ='BS DRIVERS'!AT31
A35: Deferred Revenue - Non-Current | B35: ='BALANCE SHEET'!B35 | C35: ='YTD BS'!C35 | D35: ='YTD BS'!D35 | E35: ='YTD BS'!E35 | F35: ='BALANCE SHEET'!C35 | G35: ='YTD BS'!G35 | H35: ='YTD BS'!H35 | I35: ='YTD BS'!I35 | J35: ='BALANCE SHEET'!D35 | K35: ='YTD BS'!K35 | L35: ='YTD BS'!L35 | M35: ='YTD BS'!M35 | N35: ='BALANCE SHEET'!E35 | O35: ='YTD BS'!O35 | P35: ='YTD BS'!P35 | Q35: ='YTD BS'!Q35 | R35: ='BALANCE SHEET'!F35 | S35: ='YTD BS'!S35 | T35: ='YTD BS'!T35 | U35: ='YTD BS'!U35 | V35: ='BALANCE SHEET'!G35 | W35: ='YTD BS'!W35 | X35: ='YTD BS'!X35 | Y35: ='YTD BS'!Y35 | Z35: ='BALANCE SHEET'!H35 | AA35: ='QTR P&L'!AD2*'BS DRIVERS'!AA32 | AB35: ='QTR P&L'!AE2*'BS DRIVERS'!AB32 | AC35: ='QTR P&L'!AF2*'BS DRIVERS'!AC32 | AD35: ='QTR P&L'!AG2*'BS DRIVERS'!AD32 | AE35: ='QTR P&L'!AH2*'BS DRIVERS'!AE32 | AF35: ='QTR P&L'!AI2*'BS DRIVERS'!AF32 | AG35: ='QTR P&L'!AJ2*'BS DRIVERS'!AG32 | AH35: ='QTR P&L'!AK2*'BS DRIVERS'!AH32 | ... AT35: ='QTR P&L'!AW2*'BS DRIVERS'!AT32
A36: Other Non-Current Liabilities | B36: ='BALANCE SHEET'!B36 | C36: ='YTD BS'!C36 | D36: ='YTD BS'!D36 | E36: ='YTD BS'!E36 | F36: ='BALANCE SHEET'!C36 | G36: ='YTD BS'!G36 | H36: ='YTD BS'!H36 | I36: ='YTD BS'!I36 | J36: ='BALANCE SHEET'!D36 | K36: ='YTD BS'!K36 | L36: ='YTD BS'!L36 | M36: ='YTD BS'!M36 | N36: ='BALANCE SHEET'!E36 | O36: ='YTD BS'!O36 | P36: ='YTD BS'!P36 | Q36: ='YTD BS'!Q36 | R36: ='BALANCE SHEET'!F36 | S36: ='YTD BS'!S36 | T36: ='YTD BS'!T36 | U36: ='YTD BS'!U36 | V36: ='BALANCE SHEET'!G36 | W36: ='YTD BS'!W36 | X36: ='YTD BS'!X36 | Y36: ='YTD BS'!Y36 | Z36: ='BALANCE SHEET'!H36 | AA36: ='QTR P&L'!AD2*'BS DRIVERS'!AA33 | AB36: ='QTR P&L'!AE2*'BS DRIVERS'!AB33 | AC36: ='QTR P&L'!AF2*'BS DRIVERS'!AC33 | AD36: ='QTR P&L'!AG2*'BS DRIVERS'!AD33 | AE36: ='QTR P&L'!AH2*'BS DRIVERS'!AE33 | AF36: ='QTR P&L'!AI2*'BS DRIVERS'!AF33 | AG36: ='QTR P&L'!AJ2*'BS DRIVERS'!AG33 | AH36: ='QTR P&L'!AK2*'BS DRIVERS'!AH33 | ... AT36: ='QTR P&L'!AW2*'BS DRIVERS'!AT33
A37: Total Liabilities | B37: ='BALANCE SHEET'!B37 | C37: ='YTD BS'!C37 | D37: ='YTD BS'!D37 | E37: ='YTD BS'!E37 | F37: ='BALANCE SHEET'!C37 | G37: ='YTD BS'!G37 | H37: ='YTD BS'!H37 | I37: ='YTD BS'!I37 | J37: ='BALANCE SHEET'!D37 | K37: ='YTD BS'!K37 | L37: ='YTD BS'!L37 | M37: ='YTD BS'!M37 | N37: ='BALANCE SHEET'!E37 | O37: ='YTD BS'!O37 | P37: ='YTD BS'!P37 | Q37: ='YTD BS'!Q37 | R37: ='BALANCE SHEET'!F37 | S37: ='YTD BS'!S37 | T37: ='YTD BS'!T37 | U37: ='YTD BS'!U37 | V37: ='BALANCE SHEET'!G37 | W37: ='YTD BS'!W37 | X37: ='YTD BS'!X37 | Y37: ='YTD BS'!Y37 | Z37: ='BALANCE SHEET'!H37 | AA37: =AA30+SUM(AA31:AA36) | AB37: =AB30+SUM(AB31:AB36) | AC37: =AC30+SUM(AC31:AC36) | AD37: =AD30+SUM(AD31:AD36) | AE37: =AE30+SUM(AE31:AE36) | AF37: =AF30+SUM(AF31:AF36) | AG37: =AG30+SUM(AG31:AG36) | AH37: =AH30+SUM(AH31:AH36) | ... AT37: =AT30+SUM(AT31:AT36)
A38: Convertible Preferred Stock | B38: ='BALANCE SHEET'!B38 | C38: ='YTD BS'!C38 | D38: ='YTD BS'!D38 | E38: ='YTD BS'!E38 | F38: ='BALANCE SHEET'!C38 | G38: ='YTD BS'!G38 | H38: ='YTD BS'!H38 | I38: ='YTD BS'!I38 | J38: ='BALANCE SHEET'!D38 | K38: ='YTD BS'!K38 | L38: ='YTD BS'!L38 | M38: ='YTD BS'!M38 | N38: ='BALANCE SHEET'!E38 | O38: ='YTD BS'!O38 | P38: ='YTD BS'!P38 | Q38: ='YTD BS'!Q38 | R38: ='BALANCE SHEET'!F38 | S38: ='YTD BS'!S38 | T38: ='YTD BS'!T38 | U38: ='YTD BS'!U38 | V38: ='BALANCE SHEET'!G38 | W38: ='YTD BS'!W38 | X38: ='YTD BS'!X38 | Y38: ='YTD BS'!Y38 | Z38: ='BALANCE SHEET'!H38 | AA38: ='BS DRIVERS'!AA34 | AB38: ='BS DRIVERS'!AB34 | AC38: ='BS DRIVERS'!AC34 | AD38: ='BS DRIVERS'!AD34 | AE38: ='BS DRIVERS'!AE34 | AF38: ='BS DRIVERS'!AF34 | AG38: ='BS DRIVERS'!AG34 | AH38: ='BS DRIVERS'!AH34 | ... AT38: ='BS DRIVERS'!AT34
A39: Common Stock | B39: ='BALANCE SHEET'!B39 | C39: ='YTD BS'!C39 | D39: ='YTD BS'!D39 | E39: ='YTD BS'!E39 | F39: ='BALANCE SHEET'!C39 | G39: ='YTD BS'!G39 | H39: ='YTD BS'!H39 | I39: ='YTD BS'!I39 | J39: ='BALANCE SHEET'!D39 | K39: ='YTD BS'!K39 | L39: ='YTD BS'!L39 | M39: ='YTD BS'!M39 | N39: ='BALANCE SHEET'!E39 | O39: ='YTD BS'!O39 | P39: ='YTD BS'!P39 | Q39: ='YTD BS'!Q39 | R39: ='BALANCE SHEET'!F39 | S39: ='YTD BS'!S39 | T39: ='YTD BS'!T39 | U39: ='YTD BS'!U39 | V39: ='BALANCE SHEET'!G39 | W39: ='YTD BS'!W39 | X39: ='YTD BS'!X39 | Y39: ='YTD BS'!Y39 | Z39: ='BALANCE SHEET'!H39 | AA39: ='BS DRIVERS'!AA35 | AB39: ='BS DRIVERS'!AB35 | AC39: ='BS DRIVERS'!AC35 | AD39: ='BS DRIVERS'!AD35 | AE39: ='BS DRIVERS'!AE35 | AF39: ='BS DRIVERS'!AF35 | AG39: ='BS DRIVERS'!AG35 | AH39: ='BS DRIVERS'!AH35 | ... AT39: ='BS DRIVERS'!AT35
A40: Treasury Stock | B40: ='BALANCE SHEET'!B40 | C40: ='YTD BS'!C40 | D40: ='YTD BS'!D40 | E40: ='YTD BS'!E40 | F40: ='BALANCE SHEET'!C40 | G40: ='YTD BS'!G40 | H40: ='YTD BS'!H40 | I40: ='YTD BS'!I40 | J40: ='BALANCE SHEET'!D40 | K40: ='YTD BS'!K40 | L40: ='YTD BS'!L40 | M40: ='YTD BS'!M40 | N40: ='BALANCE SHEET'!E40 | O40: ='YTD BS'!O40 | P40: ='YTD BS'!P40 | Q40: ='YTD BS'!Q40 | R40: ='BALANCE SHEET'!F40 | S40: ='YTD BS'!S40 | T40: ='YTD BS'!T40 | U40: ='YTD BS'!U40 | V40: ='BALANCE SHEET'!G40 | W40: ='YTD BS'!W40 | X40: ='YTD BS'!X40 | Y40: ='YTD BS'!Y40 | Z40: ='BALANCE SHEET'!H40 | AA40: ='BS DRIVERS'!AA36 | AB40: ='BS DRIVERS'!AB36 | AC40: ='BS DRIVERS'!AC36 | AD40: ='BS DRIVERS'!AD36 | AE40: ='BS DRIVERS'!AE36 | AF40: ='BS DRIVERS'!AF36 | AG40: ='BS DRIVERS'!AG36 | AH40: ='BS DRIVERS'!AH36 | ... AT40: ='BS DRIVERS'!AT36
A41: Additional Paid-in Capital | B41: ='BALANCE SHEET'!B41 | C41: ='YTD BS'!C41 | D41: ='YTD BS'!D41 | E41: ='YTD BS'!E41 | F41: ='BALANCE SHEET'!C41 | G41: ='YTD BS'!G41 | H41: ='YTD BS'!H41 | I41: ='YTD BS'!I41 | J41: ='BALANCE SHEET'!D41 | K41: ='YTD BS'!K41 | L41: ='YTD BS'!L41 | M41: ='YTD BS'!M41 | N41: ='BALANCE SHEET'!E41 | O41: ='YTD BS'!O41 | P41: ='YTD BS'!P41 | Q41: ='YTD BS'!Q41 | R41: ='BALANCE SHEET'!F41 | S41: ='YTD BS'!S41 | T41: ='YTD BS'!T41 | U41: ='YTD BS'!U41 | V41: ='BALANCE SHEET'!G41 | W41: ='YTD BS'!W41 | X41: ='YTD BS'!X41 | Y41: ='YTD BS'!Y41 | Z41: ='BALANCE SHEET'!H41 | AA41: ='BS DRIVERS'!AA37 | AB41: ='BS DRIVERS'!AB37 | AC41: ='BS DRIVERS'!AC37 | AD41: ='BS DRIVERS'!AD37 | AE41: ='BS DRIVERS'!AE37 | AF41: ='BS DRIVERS'!AF37 | AG41: ='BS DRIVERS'!AG37 | AH41: ='BS DRIVERS'!AH37 | ... AT41: ='BS DRIVERS'!AT37
A42: Accumulated Other Comprehensive Income (Loss) | B42: ='BALANCE SHEET'!B42 | C42: ='YTD BS'!C42 | D42: ='YTD BS'!D42 | E42: ='YTD BS'!E42 | F42: ='BALANCE SHEET'!C42 | G42: ='YTD BS'!G42 | H42: ='YTD BS'!H42 | I42: ='YTD BS'!I42 | J42: ='BALANCE SHEET'!D42 | K42: ='YTD BS'!K42 | L42: ='YTD BS'!L42 | M42: ='YTD BS'!M42 | N42: ='BALANCE SHEET'!E42 | O42: ='YTD BS'!O42 | P42: ='YTD BS'!P42 | Q42: ='YTD BS'!Q42 | R42: ='BALANCE SHEET'!F42 | S42: ='YTD BS'!S42 | T42: ='YTD BS'!T42 | U42: ='YTD BS'!U42 | V42: ='BALANCE SHEET'!G42 | W42: ='YTD BS'!W42 | X42: ='YTD BS'!X42 | Y42: ='YTD BS'!Y42 | Z42: ='BALANCE SHEET'!H42 | AA42: ='BS DRIVERS'!AA38 | AB42: ='BS DRIVERS'!AB38 | AC42: ='BS DRIVERS'!AC38 | AD42: ='BS DRIVERS'!AD38 | AE42: ='BS DRIVERS'!AE38 | AF42: ='BS DRIVERS'!AF38 | AG42: ='BS DRIVERS'!AG38 | AH42: ='BS DRIVERS'!AH38 | ... AT42: ='BS DRIVERS'!AT38
A43: Retained Earnings (Accumulated Deficit) | B43: ='BALANCE SHEET'!B43 | C43: ='YTD BS'!C43 | D43: ='YTD BS'!D43 | E43: ='YTD BS'!E43 | F43: ='BALANCE SHEET'!C43 | G43: ='YTD BS'!G43 | H43: ='YTD BS'!H43 | I43: ='YTD BS'!I43 | J43: ='BALANCE SHEET'!D43 | K43: ='YTD BS'!K43 | L43: ='YTD BS'!L43 | M43: ='YTD BS'!M43 | N43: ='BALANCE SHEET'!E43 | O43: ='YTD BS'!O43 | P43: ='YTD BS'!P43 | Q43: ='YTD BS'!Q43 | R43: ='BALANCE SHEET'!F43 | S43: ='YTD BS'!S43 | T43: ='YTD BS'!T43 | U43: ='YTD BS'!U43 | V43: ='BALANCE SHEET'!G43 | W43: ='YTD BS'!W43 | X43: ='YTD BS'!X43 | Y43: ='YTD BS'!Y43 | Z43: ='BALANCE SHEET'!H43 | AA43: ='BS DRIVERS'!AA39 | AB43: ='BS DRIVERS'!AB39 | AC43: ='BS DRIVERS'!AC39 | AD43: ='BS DRIVERS'!AD39 | AE43: ='BS DRIVERS'!AE39 | AF43: ='BS DRIVERS'!AF39 | AG43: ='BS DRIVERS'!AG39 | AH43: ='BS DRIVERS'!AH39 | ... AT43: ='BS DRIVERS'!AT39
A44: Total Stockholders' Equity | B44: ='BALANCE SHEET'!B44 | C44: ='YTD BS'!C44 | D44: ='YTD BS'!D44 | E44: ='YTD BS'!E44 | F44: ='BALANCE SHEET'!C44 | G44: ='YTD BS'!G44 | H44: ='YTD BS'!H44 | I44: ='YTD BS'!I44 | J44: ='BALANCE SHEET'!D44 | K44: ='YTD BS'!K44 | L44: ='YTD BS'!L44 | M44: ='YTD BS'!M44 | N44: ='BALANCE SHEET'!E44 | O44: ='YTD BS'!O44 | P44: ='YTD BS'!P44 | Q44: ='YTD BS'!Q44 | R44: ='BALANCE SHEET'!F44 | S44: ='YTD BS'!S44 | T44: ='YTD BS'!T44 | U44: ='YTD BS'!U44 | V44: ='BALANCE SHEET'!G44 | W44: ='YTD BS'!W44 | X44: ='YTD BS'!X44 | Y44: ='YTD BS'!Y44 | Z44: ='BALANCE SHEET'!H44 | AA44: =SUM(AA38:AA43) | AB44: =SUM(AB38:AB43) | AC44: =SUM(AC38:AC43) | AD44: =SUM(AD38:AD43) | AE44: =SUM(AE38:AE43) | AF44: =SUM(AF38:AF43) | AG44: =SUM(AG38:AG43) | AH44: =SUM(AH38:AH43) | ... AT44: =SUM(AT38:AT43)
A45: Total Liabilities, Mezzanine & Stockholders' Equity | B45: ='BALANCE SHEET'!B45 | C45: ='YTD BS'!C45 | D45: ='YTD BS'!D45 | E45: ='YTD BS'!E45 | F45: ='BALANCE SHEET'!C45 | G45: ='YTD BS'!G45 | H45: ='YTD BS'!H45 | I45: ='YTD BS'!I45 | J45: ='BALANCE SHEET'!D45 | K45: ='YTD BS'!K45 | L45: ='YTD BS'!L45 | M45: ='YTD BS'!M45 | N45: ='BALANCE SHEET'!E45 | O45: ='YTD BS'!O45 | P45: ='YTD BS'!P45 | Q45: ='YTD BS'!Q45 | R45: ='BALANCE SHEET'!F45 | S45: ='YTD BS'!S45 | T45: ='YTD BS'!T45 | U45: ='YTD BS'!U45 | V45: ='BALANCE SHEET'!G45 | W45: ='YTD BS'!W45 | X45: ='YTD BS'!X45 | Y45: ='YTD BS'!Y45 | Z45: ='BALANCE SHEET'!H45 | AA45: =AA37+AA44 | AB45: =AB37+AB44 | AC45: =AC37+AC44 | AD45: =AD37+AD44 | AE45: =AE37+AE44 | AF45: =AF37+AF44 | AG45: =AG37+AG44 | AH45: =AH37+AH44 | ... AT45: =AT37+AT44

Sheet QTR CF
B1: Q1 FY2020 | C1: Q2 FY2020 | D1: Q3 FY2020 | E1: Q4 FY2020 | F1: Q1 FY2021 | G1: Q2 FY2021 | H1: Q3 FY2021 | I1: Q4 FY2021 | J1: Q1 FY2022 | K1: Q2 FY2022 | L1: Q3 FY2022 | M1: Q4 FY2022 | N1: Q1 FY2023 | O1: Q2 FY2023 | P1: Q3 FY2023 | Q1: Q4 FY2023 | R1: Q1 FY2024 | S1: Q2 FY2024 | T1: Q3 FY2024 | U1: Q4 FY2024 | V1: Q1 FY2025 | W1: Q2 FY2025 | X1: Q3 FY2025 | Y1: Q4 FY2025 | Z1: Q1 FY2026E | AA1: Q2 FY2026E | AB1: Q3 FY2026E | AC1: Q4 FY2026E | AD1: Q1 FY2027E | AE1: Q2 FY2027E | AF1: Q3 FY2027E | AG1: Q4 FY2027E | AH1: Q1 FY2028E | AI1: Q2 FY2028E | AJ1: Q3 FY2028E | AK1: Q4 FY2028E | AL1: Q1 FY2029E | AM1: Q2 FY2029E | AN1: Q3 FY2029E | AO1: Q4 FY2029E | AP1: Q1 FY2030E | AQ1: Q2 FY2030E | AR1: Q3 FY2030E | AS1: Q4 FY2030E
A2: Net Income (Loss) | B2: ='YTD CF'!B2 | C2: ='YTD CF'!C2-'YTD CF'!B2 | D2: ='YTD CF'!D2-'YTD CF'!C2 | E2: ='CASH FLOW'!C2-'YTD CF'!D2 | F2: ='YTD CF'!E2 | G2: ='YTD CF'!F2-'YTD CF'!E2 | H2: ='YTD CF'!G2-'YTD CF'!F2 | I2: ='CASH FLOW'!D2-'YTD CF'!G2 | J2: ='YTD CF'!H2 | K2: ='YTD CF'!I2-'YTD CF'!H2 | L2: ='YTD CF'!J2-'YTD CF'!I2 | M2: ='CASH FLOW'!E2-'YTD CF'!J2 | N2: ='YTD CF'!K2 | O2: ='YTD CF'!L2-'YTD CF'!K2 | P2: ='YTD CF'!M2-'YTD CF'!L2 | Q2: ='CASH FLOW'!F2-'YTD CF'!M2 | R2: ='YTD CF'!N2 | S2: ='YTD CF'!O2-'YTD CF'!N2 | T2: ='YTD CF'!P2-'YTD CF'!O2 | U2: ='CASH FLOW'!G2-'YTD CF'!P2 | V2: ='YTD CF'!Q2 | W2: ='YTD CF'!R2-'YTD CF'!Q2 | X2: ='YTD CF'!S2-'YTD CF'!R2 | Y2: ='CASH FLOW'!H2-'YTD CF'!S2 | Z2: ='CF DRIVERS'!Z2 | AA2: ='CF DRIVERS'!AA2 | AB2: ='CF DRIVERS'!AB2 | AC2: ='CF DRIVERS'!AC2 | AD2: ='CF DRIVERS'!AD2 | AE2: ='CF DRIVERS'!AE2 | AF2: ='CF DRIVERS'!AF2 | AG2: ='CF DRIVERS'!AG2 | ... AS2: ='CF DRIVERS'!AS2
A3: Depreciation | B3: ='YTD CF'!B3 | C3: ='YTD CF'!C3-'YTD CF'!B3 | D3: ='YTD CF'!D3-'YTD CF'!C3 | E3: ='CASH FLOW'!C3-'YTD CF'!D3 | F3: ='YTD CF'!E3 | G3: ='YTD CF'!F3-'YTD CF'!E3 | H3: ='YTD CF'!G3-'YTD CF'!F3 | I3: ='CASH FLOW'!D3-'YTD CF'!G3 | J3: ='YTD CF'!H3 | K3: ='YTD CF'!I3-'YTD CF'!H3 | L3: ='YTD CF'!J3-'YTD CF'!I3 | M3: ='CASH FLOW'!E3-'YTD CF'!J3 | N3: ='YTD CF'!K3 | O3: ='YTD CF'!L3-'YTD CF'!K3 | P3: ='YTD CF'!M3-'YTD CF'!L3 | Q3: ='CASH FLOW'!F3-'YTD CF'!M3 | R3: ='YTD CF'!N3 | S3: ='YTD CF'!O3-'YTD CF'!N3 | T3: ='YTD CF'!P3-'YTD CF'!O3 | U3: ='CASH FLOW'!G3-'YTD CF'!P3 | V3: ='YTD CF'!Q3 | W3: ='YTD CF'!R3-'YTD CF'!Q3 | X3: ='YTD CF'!S3-'YTD CF'!R3 | Y3: ='CASH FLOW'!H3-'YTD CF'!S3 | Z3: ='CF DRIVERS'!Z3 | AA3: ='CF DRIVERS'!AA3 | AB3: ='CF DRIVERS'!AB3 | AC3: ='CF DRIVERS'!AC3 | AD3: ='CF DRIVERS'!AD3 | AE3: ='CF DRIVERS'!AE3 | AF3: ='CF DRIVERS'!AF3 | AG3: ='CF DRIVERS'!AG3 | ... AS3: ='CF DRIVERS'!AS3
A4: Amortization | B4: ='YTD CF'!B4 | C4: ='YTD CF'!C4-'YTD CF'!B4 | D4: ='YTD CF'!D4-'YTD CF'!C4 | E4: ='CASH FLOW'!C4-'YTD CF'!D4 | F4: ='YTD CF'!E4 | G4: ='YTD CF'!F4-'YTD CF'!E4 | H4: ='YTD CF'!G4-'YTD CF'!F4 | I4: ='CASH FLOW'!D4-'YTD CF'!G4 | J4: ='YTD CF'!H4 | K4: ='YTD CF'!I4-'YTD CF'!H4 | L4: ='YTD CF'!J4-'YTD CF'!I4 | M4: ='CASH FLOW'!E4-'YTD CF'!J4 | N4: ='YTD CF'!K4 | O4: ='YTD CF'!L4-'YTD CF'!K4 | P4: ='YTD CF'!M4-'YTD CF'!L4 | Q4: ='CASH FLOW'!F4-'YTD CF'!M4 | R4: ='YTD CF'!N4 | S4: ='YTD CF'!O4-'YTD CF'!N4 | T4: ='YTD CF'!P4-'YTD CF'!O4 | U4: ='CASH FLOW'!G4-'YTD CF'!P4 | V4: ='YTD CF'!Q4 | W4: ='YTD CF'!R4-'YTD CF'!Q4 | X4: ='YTD CF'!S4-'YTD CF'!R4 | Y4: ='CASH FLOW'!H4-'YTD CF'!S4 | Z4: ='CF DRIVERS'!Z4 | AA4: ='CF DRIVERS'!AA4 | AB4: ='CF DRIVERS'!AB4 | AC4: ='CF DRIVERS'!AC4 | AD4: ='CF DRIVERS'!AD4 | AE4: ='CF DRIVERS'!AE4 | AF4: ='CF DRIVERS'!AF4 | AG4: ='CF DRIVERS'!AG4 | ... AS4: ='CF DRIVERS'!AS4
A5: Impairment of Intangibles | B5: ='YTD CF'!B5 | C5: ='YTD CF'!C5-'YTD CF'!B5 | D5: ='YTD CF'!D5-'YTD CF'!C5 | E5: ='CASH FLOW'!C6-'YTD CF'!D5 | F5: ='YTD CF'!E5 | G5: ='YTD CF'!F5-'YTD CF'!E5 | H5: ='YTD CF'!G5-'YTD CF'!F5 | I5: ='CASH FLOW'!D6-'YTD CF'!G5 | J5: ='YTD CF'!H5 | K5: ='YTD CF'!I5-'YTD CF'!H5 | L5: ='YTD CF'!J5-'YTD CF'!I5 | M5: ='CASH FLOW'!E6-'YTD CF'!J5 | N5: ='YTD CF'!K5 | O5: ='YTD CF'!L5-'YTD CF'!K5 | P5: ='YTD CF'!M5-'YTD CF'!L5 | Q5: ='CASH FLOW'!F6-'YTD CF'!M5 | R5: ='YTD CF'!N5 | S5: ='YTD CF'!O5-'YTD CF'!N5 | T5: ='YTD CF'!P5-'YTD CF'!O5 | U5: ='CASH FLOW'!G6-'YTD CF'!P5 | V5: ='YTD CF'!Q5 | W5: ='YTD CF'!R5-'YTD CF'!Q5 | X5: ='YTD CF'!S5-'YTD CF'!R5 | Y5: ='CASH FLOW'!H6-'YTD CF'!S5 | Z5: ='CF DRIVERS'!Z5 | AA5: ='CF DRIVERS'!AA5 | AB5: ='CF DRIVERS'!AB5 | AC5: ='CF DRIVERS'!AC5 | AD5: ='CF DRIVERS'!AD5 | AE5: ='CF DRIVERS'!AE5 | AF5: ='CF DRIVERS'!AF5 | AG5: ='CF DRIVERS'!AG5 | ... AS5: ='CF DRIVERS'!AS5
A6: Depreciation & Amortization | B6: ='YTD CF'!B6 | C6: ='YTD CF'!C6-'YTD CF'!B6 | D6: ='YTD CF'!D6-'YTD CF'!C6 | E6: ='CASH FLOW'!C5-'YTD CF'!D6 | F6: ='YTD CF'!E6 | G6: ='YTD CF'!F6-'YTD CF'!E6 | H6: ='YTD CF'!G6-'YTD CF'!F6 | I6: ='CASH FLOW'!D5-'YTD CF'!G6 | J6: ='YTD CF'!H6 | K6: ='YTD CF'!I6-'YTD CF'!H6 | L6: ='YTD CF'!J6-'YTD CF'!I6 | M6: ='CASH FLOW'!E5-'YTD CF'!J6 | N6: ='YTD CF'!K6 | O6: ='YTD CF'!L6-'YTD CF'!K6 | P6: ='YTD CF'!M6-'YTD CF'!L6 | Q6: ='CASH FLOW'!F5-'YTD CF'!M6 | R6: ='YTD CF'!N6 | S6: ='YTD CF'!O6-'YTD CF'!N6 | T6: ='YTD CF'!P6-'YTD CF'!O6 | U6: ='CASH FLOW'!G5-'YTD CF'!P6 | V6: ='YTD CF'!Q6 | W6: ='YTD CF'!R6-'YTD CF'!Q6 | X6: ='YTD CF'!S6-'YTD CF'!R6 | Y6: ='CASH FLOW'!H5-'YTD CF'!S6 | Z6: ='QTR P&L'!AD2*'CF DRIVERS'!Z6 | AA6: ='QTR P&L'!AE2*'CF DRIVERS'!AA6 | AB6: ='QTR P&L'!AF2*'CF DRIVERS'!AB6 | AC6: ='QTR P&L'!AG2*'CF DRIVERS'!AC6 | AD6: ='QTR P&L'!AH2*'CF DRIVERS'!AD6 | AE6: ='QTR P&L'!AI2*'CF DRIVERS'!AE6 | AF6: ='QTR P&L'!AJ2*'CF DRIVERS'!AF6 | AG6: ='QTR P&L'!AK2*'CF DRIVERS'!AG6 | ... AS6: ='QTR P&L'!AW2*'CF DRIVERS'!AS6
A7: Allowance for Credit Losses | B7: ='YTD CF'!B7 | C7: ='YTD CF'!C7-'YTD CF'!B7 | D7: ='YTD CF'!D7-'YTD CF'!C7 | E7: ='CASH FLOW'!C7-'YTD CF'!D7 | F7: ='YTD CF'!E7 | G7: ='YTD CF'!F7-'YTD CF'!E7 | H7: ='YTD CF'!G7-'YTD CF'!F7 | I7: ='CASH FLOW'!D7-'YTD CF'!G7 | J7: ='YTD CF'!H7 | K7: ='YTD CF'!I7-'YTD CF'!H7 | L7: ='YTD CF'!J7-'YTD CF'!I7 | M7: ='CASH FLOW'!E7-'YTD CF'!J7 | N7: ='YTD CF'!K7 | O7: ='YTD CF'!L7-'YTD CF'!K7 | P7: ='YTD CF'!M7-'YTD CF'!L7 | Q7: ='CASH FLOW'!F7-'YTD CF'!M7 | R7: ='YTD CF'!N7 | S7: ='YTD CF'!O7-'YTD CF'!N7 | T7: ='YTD CF'!P7-'YTD CF'!O7 | U7: ='CASH FLOW'!G7-'YTD CF'!P7 | V7: ='YTD CF'!Q7 | W7: ='YTD CF'!R7-'YTD CF'!Q7 | X7: ='YTD CF'!S7-'YTD CF'!R7 | Y7: ='CASH FLOW'!H7-'YTD CF'!S7 | Z7: ='CF DRIVERS'!Z7 | AA7: ='CF DRIVERS'!AA7 | AB7: ='CF DRIVERS'!AB7 | AC7: ='CF DRIVERS'!AC7 | AD7: ='CF DRIVERS'!AD7 | AE7: ='CF DRIVERS'!AE7 | AF7: ='CF DRIVERS'!AF7 | AG7: ='CF DRIVERS'!AG7 | ... AS7: ='CF DRIVERS'!AS7
A8: Amortization of Deferred Other Costs | B8: ='YTD CF'!B8 | C8: ='YTD CF'!C8-'YTD CF'!B8 | D8: ='YTD CF'!D8-'YTD CF'!C8 | E8: ='CASH FLOW'!C8-'YTD CF'!D8 | F8: ='YTD CF'!E8 | G8: ='YTD CF'!F8-'YTD CF'!E8 | H8: ='YTD CF'!G8-'YTD CF'!F8 | I8: ='CASH FLOW'!D8-'YTD CF'!G8 | J8: ='YTD CF'!H8 | K8: ='YTD CF'!I8-'YTD CF'!H8 | L8: ='YTD CF'!J8-'YTD CF'!I8 | M8: ='CASH FLOW'!E8-'YTD CF'!J8 | N8: ='YTD CF'!K8 | O8: ='YTD CF'!L8-'YTD CF'!K8 | P8: ='YTD CF'!M8-'YTD CF'!L8 | Q8: ='CASH FLOW'!F8-'YTD CF'!M8 | R8: ='YTD CF'!N8 | S8: ='YTD CF'!O8-'YTD CF'!N8 | T8: ='YTD CF'!P8-'YTD CF'!O8 | U8: ='CASH FLOW'!G8-'YTD CF'!P8 | V8: ='YTD CF'!Q8 | W8: ='YTD CF'!R8-'YTD CF'!Q8 | X8: ='YTD CF'!S8-'YTD CF'!R8 | Y8: ='CASH FLOW'!H8-'YTD CF'!S8 | Z8: ='CF DRIVERS'!Z8 | AA8: ='CF DRIVERS'!AA8 | AB8: ='CF DRIVERS'!AB8 | AC8: ='CF DRIVERS'!AC8 | AD8: ='CF DRIVERS'!AD8 | AE8: ='CF DRIVERS'!AE8 | AF8: ='CF DRIVERS'!AF8 | AG8: ='CF DRIVERS'!AG8 | ... AS8: ='CF DRIVERS'!AS8
A9: Inventory Write-Down | B9: ='YTD CF'!B9 | C9: ='YTD CF'!C9-'YTD CF'!B9 | D9: ='YTD CF'!D9-'YTD CF'!C9 | E9: ='CASH FLOW'!C9-'YTD CF'!D9 | F9: ='YTD CF'!E9 | G9: ='YTD CF'!F9-'YTD CF'!E9 | H9: ='YTD CF'!G9-'YTD CF'!F9 | I9: ='CASH FLOW'!D9-'YTD CF'!G9 | J9: ='YTD CF'!H9 | K9: ='YTD CF'!I9-'YTD CF'!H9 | L9: ='YTD CF'!J9-'YTD CF'!I9 | M9: ='CASH FLOW'!E9-'YTD CF'!J9 | N9: ='YTD CF'!K9 | O9: ='YTD CF'!L9-'YTD CF'!K9 | P9: ='YTD CF'!M9-'YTD CF'!L9 | Q9: ='CASH FLOW'!F9-'YTD CF'!M9 | R9: ='YTD CF'!N9 | S9: ='YTD CF'!O9-'YTD CF'!N9 | T9: ='YTD CF'!P9-'YTD CF'!O9 | U9: ='CASH FLOW'!G9-'YTD CF'!P9 | V9: ='YTD CF'!Q9 | W9: ='YTD CF'!R9-'YTD CF'!Q9 | X9: ='YTD CF'!S9-'YTD CF'!R9 | Y9: ='CASH FLOW'!H9-'YTD CF'!S9 | Z9: ='CF DRIVERS'!Z9 | AA9: ='CF DRIVERS'!AA9 | AB9: ='CF DRIVERS'!AB9 | AC9: ='CF DRIVERS'!AC9 | AD9: ='CF DRIVERS'!AD9 | AE9: ='CF DRIVERS'!AE9 | AF9: ='CF DRIVERS'!AF9 | AG9: ='CF DRIVERS'!AG9 | ... AS9: ='CF DRIVERS'!AS9
A10: Gain (Loss) on Disposal of PP&E | B10: ='YTD CF'!B10 | C10: ='YTD CF'!C10-'YTD CF'!B10 | D10: ='YTD CF'!D10-'YTD CF'!C10 | E10: ='CASH FLOW'!C10-'YTD CF'!D10 | F10: ='YTD CF'!E10 | G10: ='YTD CF'!F10-'YTD CF'!E10 | H10: ='YTD CF'!G10-'YTD CF'!F10 | I10: ='CASH FLOW'!D10-'YTD CF'!G10 | J10: ='YTD CF'!H10 | K10: ='YTD CF'!I10-'YTD CF'!H10 | L10: ='YTD CF'!J10-'YTD CF'!I10 | M10: ='CASH FLOW'!E10-'YTD CF'!J10 | N10: ='YTD CF'!K10 | O10: ='YTD CF'!L10-'YTD CF'!K10 | P10: ='YTD CF'!M10-'YTD CF'!L10 | Q10: ='CASH FLOW'!F10-'YTD CF'!M10 | R10: ='YTD CF'!N10 | S10: ='YTD CF'!O10-'YTD CF'!N10 | T10: ='YTD CF'!P10-'YTD CF'!O10 | U10: ='CASH FLOW'!G10-'YTD CF'!P10 | V10: ='YTD CF'!Q10 | W10: ='YTD CF'!R10-'YTD CF'!Q10 | X10: ='YTD CF'!S10-'YTD CF'!R10 | Y10: ='CASH FLOW'!H10-'YTD CF'!S10 | Z10: ='CF DRIVERS'!Z10 | AA10: ='CF DRIVERS'!AA10 | AB10: ='CF DRIVERS'!AB10 | AC10: ='CF DRIVERS'!AC10 | AD10: ='CF DRIVERS'!AD10 | AE10: ='CF DRIVERS'!AE10 | AF10: ='CF DRIVERS'!AF10 | AG10: ='CF DRIVERS'!AG10 | ... AS10: ='CF DRIVERS'!AS10
A11: Stock-Based Compensation | B11: ='YTD CF'!B11 | C11: ='YTD CF'!C11-'YTD CF'!B11 | D11: ='YTD CF'!D11-'YTD CF'!C11 | E11: ='CASH FLOW'!C11-'YTD CF'!D11 | F11: ='YTD CF'!E11 | G11: ='YTD CF'!F11-'YTD CF'!E11 | H11: ='YTD CF'!G11-'YTD CF'!F11 | I11: ='CASH FLOW'!D11-'YTD CF'!G11 | J11: ='YTD CF'!H11 | K11: ='YTD CF'!I11-'YTD CF'!H11 | L11: ='YTD CF'!J11-'YTD CF'!I11 | M11: ='CASH FLOW'!E11-'YTD CF'!J11 | N11: ='YTD CF'!K11 | O11: ='YTD CF'!L11-'YTD CF'!K11 | P11: ='YTD CF'!M11-'YTD CF'!L11 | Q11: ='CASH FLOW'!F11-'YTD CF'!M11 | R11: ='YTD CF'!N11 | S11: ='YTD CF'!O11-'YTD CF'!N11 | T11: ='YTD CF'!P11-'YTD CF'!O11 | U11: ='CASH FLOW'!G11-'YTD CF'!P11 | V11: ='YTD CF'!Q11 | W11: ='YTD CF'!R11-'YTD CF'!Q11 | X11: ='YTD CF'!S11-'YTD CF'!R11 | Y11: ='CASH FLOW'!H11-'YTD CF'!S11 | Z11: ='QTR P&L'!AD2*'CF DRIVERS'!Z11 | AA11: ='QTR P&L'!AE2*'CF DRIVERS'!AA11 | AB11: ='QTR P&L'!AF2*'CF DRIVERS'!AB11 | AC11: ='QTR P&L'!AG2*'CF DRIVERS'!AC11 | AD11: ='QTR P&L'!AH2*'CF DRIVERS'!AD11 | AE11: ='QTR P&L'!AI2*'CF DRIVERS'!AE11 | AF11: ='QTR P&L'!AJ2*'CF DRIVERS'!AF11 | AG11: ='QTR P&L'!AK2*'CF DRIVERS'!AG11 | ... AS11: ='QTR P&L'!AW2*'CF DRIVERS'!AS11
A12: Gain on China Transaction | B12: ='YTD CF'!B12 | C12: ='YTD CF'!C12-'YTD CF'!B12 | D12: ='YTD CF'!D12-'YTD CF'!C12 | E12: ='CASH FLOW'!C12-'YTD CF'!D12 | F12: ='YTD CF'!E12 | G12: ='YTD CF'!F12-'YTD CF'!E12 | H12: ='YTD CF'!G12-'YTD CF'!F12 | I12: ='CASH FLOW'!D12-'YTD CF'!G12 | J12: ='YTD CF'!H12 | K12: ='YTD CF'!I12-'YTD CF'!H12 | L12: ='YTD CF'!J12-'YTD CF'!I12 | M12: ='CASH FLOW'!E12-'YTD CF'!J12 | N12: ='YTD CF'!K12 | O12: ='YTD CF'!L12-'YTD CF'!K12 | P12: ='YTD CF'!M12-'YTD CF'!L12 | Q12: ='CASH FLOW'!F12-'YTD CF'!M12 | R12: ='YTD CF'!N12 | S12: ='YTD CF'!O12-'YTD CF'!N12 | T12: ='YTD CF'!P12-'YTD CF'!O12 | U12: ='CASH FLOW'!G12-'YTD CF'!P12 | V12: ='YTD CF'!Q12 | W12: ='YTD CF'!R12-'YTD CF'!Q12 | X12: ='YTD CF'!S12-'YTD CF'!R12 | Y12: ='CASH FLOW'!H12-'YTD CF'!S12 | Z12: ='CF DRIVERS'!Z12 | AA12: ='CF DRIVERS'!AA12 | AB12: ='CF DRIVERS'!AB12 | AC12: ='CF DRIVERS'!AC12 | AD12: ='CF DRIVERS'!AD12 | AE12: ='CF DRIVERS'!AE12 | AF12: ='CF DRIVERS'!AF12 | AG12: ='CF DRIVERS'!AG12 | ... AS12: ='CF DRIVERS'!AS12
A13: Gain (Loss) on Lease Cancellations | B13: ='YTD CF'!B13 | C13: ='YTD CF'!C13-'YTD CF'!B13 | D13: ='YTD CF'!D13-'YTD CF'!C13 | E13: ='CASH FLOW'!C15-'YTD CF'!D13 | F13: ='YTD CF'!E13 | G13: ='YTD CF'!F13-'YTD CF'!E13 | H13: ='YTD CF'!G13-'YTD CF'!F13 | I13: ='CASH FLOW'!D15-'YTD CF'!G13 | J13: ='YTD CF'!H13 | K13: ='YTD CF'!I13-'YTD CF'!H13 | L13: ='YTD CF'!J13-'YTD CF'!I13 | M13: ='CASH FLOW'!E15-'YTD CF'!J13 | N13: ='YTD CF'!K13 | O13: ='YTD CF'!L13-'YTD CF'!K13 | P13: ='YTD CF'!M13-'YTD CF'!L13 | Q13: ='CASH FLOW'!F15-'YTD CF'!M13 | R13: ='YTD CF'!N13 | S13: ='YTD CF'!O13-'YTD CF'!N13 | T13: ='YTD CF'!P13-'YTD CF'!O13 | U13: ='CASH FLOW'!G15-'YTD CF'!P13 | V13: ='YTD CF'!Q13 | W13: ='YTD CF'!R13-'YTD CF'!Q13 | X13: ='YTD CF'!S13-'YTD CF'!R13 | Y13: ='CASH FLOW'!H15-'YTD CF'!S13 | Z13: ='CF DRIVERS'!Z13 | AA13: ='CF DRIVERS'!AA13 | AB13: ='CF DRIVERS'!AB13 | AC13: ='CF DRIVERS'!AC13 | AD13: ='CF DRIVERS'!AD13 | AE13: ='CF DRIVERS'!AE13 | AF13: ='CF DRIVERS'!AF13 | AG13: ='CF DRIVERS'!AG13 | ... AS13: ='CF DRIVERS'!AS13
A14: (Benefit) Provision for Deferred Income Taxes | B14: ='YTD CF'!B14 | C14: ='YTD CF'!C14-'YTD CF'!B14 | D14: ='YTD CF'!D14-'YTD CF'!C14 | E14: ='CASH FLOW'!C13-'YTD CF'!D14 | F14: ='YTD CF'!E14 | G14: ='YTD CF'!F14-'YTD CF'!E14 | H14: ='YTD CF'!G14-'YTD CF'!F14 | I14: ='CASH FLOW'!D13-'YTD CF'!G14 | J14: ='YTD CF'!H14 | K14: ='YTD CF'!I14-'YTD CF'!H14 | L14: ='YTD CF'!J14-'YTD CF'!I14 | M14: ='CASH FLOW'!E13-'YTD CF'!J14 | N14: ='YTD CF'!K14 | O14: ='YTD CF'!L14-'YTD CF'!K14 | P14: ='YTD CF'!M14-'YTD CF'!L14 | Q14: ='CASH FLOW'!F13-'YTD CF'!M14 | R14: ='YTD CF'!N14 | S14: ='YTD CF'!O14-'YTD CF'!N14 | T14: ='YTD CF'!P14-'YTD CF'!O14 | U14: ='CASH FLOW'!G13-'YTD CF'!P14 | V14: ='YTD CF'!Q14 | W14: ='YTD CF'!R14-'YTD CF'!Q14 | X14: ='YTD CF'!S14-'YTD CF'!R14 | Y14: ='CASH FLOW'!H13-'YTD CF'!S14 | Z14: ='CF DRIVERS'!Z14 | AA14: ='CF DRIVERS'!AA14 | AB14: ='CF DRIVERS'!AB14 | AC14: ='CF DRIVERS'!AC14 | AD14: ='CF DRIVERS'!AD14 | AE14: ='CF DRIVERS'!AE14 | AF14: ='CF DRIVERS'!AF14 | AG14: ='CF DRIVERS'!AG14 | ... AS14: ='CF DRIVERS'!AS14
A15: Foreign Currency Gain (Loss) | B15: ='YTD CF'!B15 | C15: ='YTD CF'!C15-'YTD CF'!B15 | D15: ='YTD CF'!D15-'YTD CF'!C15 | E15: ='CASH FLOW'!C14-'YTD CF'!D15 | F15: ='YTD CF'!E15 | G15: ='YTD CF'!F15-'YTD CF'!E15 | H15: ='YTD CF'!G15-'YTD CF'!F15 | I15: ='CASH FLOW'!D14-'YTD CF'!G15 | J15: ='YTD CF'!H15 | K15: ='YTD CF'!I15-'YTD CF'!H15 | L15: ='YTD CF'!J15-'YTD CF'!I15 | M15: ='CASH FLOW'!E14-'YTD CF'!J15 | N15: ='YTD CF'!K15 | O15: ='YTD CF'!L15-'YTD CF'!K15 | P15: ='YTD CF'!M15-'YTD CF'!L15 | Q15: ='CASH FLOW'!F14-'YTD CF'!M15 | R15: ='YTD CF'!N15 | S15: ='YTD CF'!O15-'YTD CF'!N15 | T15: ='YTD CF'!P15-'YTD CF'!O15 | U15: ='CASH FLOW'!G14-'YTD CF'!P15 | V15: ='YTD CF'!Q15 | W15: ='YTD CF'!R15-'YTD CF'!Q15 | X15: ='YTD CF'!S15-'YTD CF'!R15 | Y15: ='CASH FLOW'!H14-'YTD CF'!S15 | Z15: ='CF DRIVERS'!Z15 | AA15: ='CF DRIVERS'!AA15 | AB15: ='CF DRIVERS'!AB15 | AC15: ='CF DRIVERS'!AC15 | AD15: ='CF DRIVERS'!AD15 | AE15: ='CF DRIVERS'!AE15 | AF15: ='CF DRIVERS'!AF15 | AG15: ='CF DRIVERS'!AG15 | ... AS15: ='CF DRIVERS'!AS15
A16: Change in Fair Value of Contingent Consideration | B16: ='YTD CF'!B16 | C16: ='YTD CF'!C16-'YTD CF'!B16 | D16: ='YTD CF'!D16-'YTD CF'!C16 | E16: ='CASH FLOW'!C16-'YTD CF'!D16 | F16: ='YTD CF'!E16 | G16: ='YTD CF'!F16-'YTD CF'!E16 | H16: ='YTD CF'!G16-'YTD CF'!F16 | I16: ='CASH FLOW'!D16-'YTD CF'!G16 | J16: ='YTD CF'!H16 | K16: ='YTD CF'!I16-'YTD CF'!H16 | L16: ='YTD CF'!J16-'YTD CF'!I16 | M16: ='CASH FLOW'!E16-'YTD CF'!J16 | N16: ='YTD CF'!K16 | O16: ='YTD CF'!L16-'YTD CF'!K16 | P16: ='YTD CF'!M16-'YTD CF'!L16 | Q16: ='CASH FLOW'!F16-'YTD CF'!M16 | R16: ='YTD CF'!N16 | S16: ='YTD CF'!O16-'YTD CF'!N16 | T16: ='YTD CF'!P16-'YTD CF'!O16 | U16: ='CASH FLOW'!G16-'YTD CF'!P16 | V16: ='YTD CF'!Q16 | W16: ='YTD CF'!R16-'YTD CF'!Q16 | X16: ='YTD CF'!S16-'YTD CF'!R16 | Y16: ='CASH FLOW'!H16-'YTD CF'!S16 | Z16: ='CF DRIVERS'!Z16 | AA16: ='CF DRIVERS'!AA16 | AB16: ='CF DRIVERS'!AB16 | AC16: ='CF DRIVERS'!AC16 | AD16: ='CF DRIVERS'!AD16 | AE16: ='CF DRIVERS'!AE16 | AF16: ='CF DRIVERS'!AF16 | AG16: ='CF DRIVERS'!AG16 | ... AS16: ='CF DRIVERS'!AS16
A17: Gain (Loss) on Extinguishment of Debt | B17: ='YTD CF'!B17 | C17: ='YTD CF'!C17-'YTD CF'!B17 | D17: ='YTD CF'!D17-'YTD CF'!C17 | E17: ='CASH FLOW'!C17-'YTD CF'!D17 | F17: ='YTD CF'!E17 | G17: ='YTD CF'!F17-'YTD CF'!E17 | H17: ='YTD CF'!G17-'YTD CF'!F17 | I17: ='CASH FLOW'!D17-'YTD CF'!G17 | J17: ='YTD CF'!H17 | K17: ='YTD CF'!I17-'YTD CF'!H17 | L17: ='YTD CF'!J17-'YTD CF'!I17 | M17: ='CASH FLOW'!E17-'YTD CF'!J17 | N17: ='YTD CF'!K17 | O17: ='YTD CF'!L17-'YTD CF'!K17 | P17: ='YTD CF'!M17-'YTD CF'!L17 | Q17: ='CASH FLOW'!F17-'YTD CF'!M17 | R17: ='YTD CF'!N17 | S17: ='YTD CF'!O17-'YTD CF'!N17 | T17: ='YTD CF'!P17-'YTD CF'!O17 | U17: ='CASH FLOW'!G17-'YTD CF'!P17 | V17: ='YTD CF'!Q17 | W17: ='YTD CF'!R17-'YTD CF'!Q17 | X17: ='YTD CF'!S17-'YTD CF'!R17 | Y17: ='CASH FLOW'!H17-'YTD CF'!S17 | Z17: ='CF DRIVERS'!Z17 | AA17: ='CF DRIVERS'!AA17 | AB17: ='CF DRIVERS'!AB17 | AC17: ='CF DRIVERS'!AC17 | AD17: ='CF DRIVERS'!AD17 | AE17: ='CF DRIVERS'!AE17 | AF17: ='CF DRIVERS'!AF17 | AG17: ='CF DRIVERS'!AG17 | ... AS17: ='CF DRIVERS'!AS17
A18: Other Operating Items | B18: ='YTD CF'!B18 | C18: ='YTD CF'!C18-'YTD CF'!B18 | D18: ='YTD CF'!D18-'YTD CF'!C18 | E18: ='CASH FLOW'!C18-'YTD CF'!D18 | F18: ='YTD CF'!E18 | G18: ='YTD CF'!F18-'YTD CF'!E18 | H18: ='YTD CF'!G18-'YTD CF'!F18 | I18: ='CASH FLOW'!D18-'YTD CF'!G18 | J18: ='YTD CF'!H18 | K18: ='YTD CF'!I18-'YTD CF'!H18 | L18: ='YTD CF'!J18-'YTD CF'!I18 | M18: ='CASH FLOW'!E18-'YTD CF'!J18 | N18: ='YTD CF'!K18 | O18: ='YTD CF'!L18-'YTD CF'!K18 | P18: ='YTD CF'!M18-'YTD CF'!L18 | Q18: ='CASH FLOW'!F18-'YTD CF'!M18 | R18: ='YTD CF'!N18 | S18: ='YTD CF'!O18-'YTD CF'!N18 | T18: ='YTD CF'!P18-'YTD CF'!O18 | U18: ='CASH FLOW'!G18-'YTD CF'!P18 | V18: ='YTD CF'!Q18 | W18: ='YTD CF'!R18-'YTD CF'!Q18 | X18: ='YTD CF'!S18-'YTD CF'!R18 | Y18: ='CASH FLOW'!H18-'YTD CF'!S18 | Z18: ='CF DRIVERS'!Z18 | AA18: ='CF DRIVERS'!AA18 | AB18: ='CF DRIVERS'!AB18 | AC18: ='CF DRIVERS'!AC18 | AD18: ='CF DRIVERS'!AD18 | AE18: ='CF DRIVERS'!AE18 | AF18: ='CF DRIVERS'!AF18 | AG18: ='CF DRIVERS'!AG18 | ... AS18: ='CF DRIVERS'!AS18
A19: Accounts Receivable | B19: ='YTD CF'!B19 | C19: ='YTD CF'!C19-'YTD CF'!B19 | D19: ='YTD CF'!D19-'YTD CF'!C19 | E19: ='CASH FLOW'!C19-'YTD CF'!D19 | F19: ='YTD CF'!E19 | G19: ='YTD CF'!F19-'YTD CF'!E19 | H19: ='YTD CF'!G19-'YTD CF'!F19 | I19: ='CASH FLOW'!D19-'YTD CF'!G19 | J19: ='YTD CF'!H19 | K19: ='YTD CF'!I19-'YTD CF'!H19 | L19: ='YTD CF'!J19-'YTD CF'!I19 | M19: ='CASH FLOW'!E19-'YTD CF'!J19 | N19: ='YTD CF'!K19 | O19: ='YTD CF'!L19-'YTD CF'!K19 | P19: ='YTD CF'!M19-'YTD CF'!L19 | Q19: ='CASH FLOW'!F19-'YTD CF'!M19 | R19: ='YTD CF'!N19 | S19: ='YTD CF'!O19-'YTD CF'!N19 | T19: ='YTD CF'!P19-'YTD CF'!O19 | U19: ='CASH FLOW'!G19-'YTD CF'!P19 | V19: ='YTD CF'!Q19 | W19: ='YTD CF'!R19-'YTD CF'!Q19 | X19: ='YTD CF'!S19-'YTD CF'!R19 | Y19: ='CASH FLOW'!H19-'YTD CF'!S19 | Z19: ='CF DRIVERS'!Z19 | AA19: ='CF DRIVERS'!AA19 | AB19: ='CF DRIVERS'!AB19 | AC19: ='CF DRIVERS'!AC19 | AD19: ='CF DRIVERS'!AD19 | AE19: ='CF DRIVERS'!AE19 | AF19: ='CF DRIVERS'!AF19 | AG19: ='CF DRIVERS'!AG19 | ... AS19: ='CF DRIVERS'!AS19
A20: Note Receivable | B20: ='YTD CF'!B20 | C20: ='YTD CF'!C20-'YTD CF'!B20 | D20: ='YTD CF'!D20-'YTD CF'!C20 | E20: ='CASH FLOW'!C20-'YTD CF'!D20 | F20: ='YTD CF'!E20 | G20: ='YTD CF'!F20-'YTD CF'!E20 | H20: ='YTD CF'!G20-'YTD CF'!F20 | I20: ='CASH FLOW'!D20-'YTD CF'!G20 | J20: ='YTD CF'!H20 | K20: ='YTD CF'!I20-'YTD CF'!H20 | L20: ='YTD CF'!J20-'YTD CF'!I20 | M20: ='CASH FLOW'!E20-'YTD CF'!J20 | N20: ='YTD CF'!K20 | O20: ='YTD CF'!L20-'YTD CF'!K20 | P20: ='YTD CF'!M20-'YTD CF'!L20 | Q20: ='CASH FLOW'!F20-'YTD CF'!M20 | R20: ='YTD CF'!N20 | S20: ='YTD CF'!O20-'YTD CF'!N20 | T20: ='YTD CF'!P20-'YTD CF'!O20 | U20: ='CASH FLOW'!G20-'YTD CF'!P20 | V20: ='YTD CF'!Q20 | W20: ='YTD CF'!R20-'YTD CF'!Q20 | X20: ='YTD CF'!S20-'YTD CF'!R20 | Y20: ='CASH FLOW'!H20-'YTD CF'!S20 | Z20: ='CF DRIVERS'!Z20 | AA20: ='CF DRIVERS'!AA20 | AB20: ='CF DRIVERS'!AB20 | AC20: ='CF DRIVERS'!AC20 | AD20: ='CF DRIVERS'!AD20 | AE20: ='CF DRIVERS'!AE20 | AF20: ='CF DRIVERS'!AF20 | AG20: ='CF DRIVERS'!AG20 | ... AS20: ='CF DRIVERS'!AS20
A21: Inventories | B21: ='YTD CF'!B21 | C21: ='YTD CF'!C21-'YTD CF'!B21 | D21: ='YTD CF'!D21-'YTD CF'!C21 | E21: ='CASH FLOW'!C21-'YTD CF'!D21 | F21: ='YTD CF'!E21 | G21: ='YTD CF'!F21-'YTD CF'!E21 | H21: ='YTD CF'!G21-'YTD CF'!F21 | I21: ='CASH FLOW'!D21-'YTD CF'!G21 | J21: ='YTD CF'!H21 | K21: ='YTD CF'!I21-'YTD CF'!H21 | L21: ='YTD CF'!J21-'YTD CF'!I21 | M21: ='CASH FLOW'!E21-'YTD CF'!J21 | N21: ='YTD CF'!K21 | O21: ='YTD CF'!L21-'YTD CF'!K21 | P21: ='YTD CF'!M21-'YTD CF'!L21 | Q21: ='CASH FLOW'!F21-'YTD CF'!M21 | R21: ='YTD CF'!N21 | S21: ='YTD CF'!O21-'YTD CF'!N21 | T21: ='YTD CF'!P21-'YTD CF'!O21 | U21: ='CASH FLOW'!G21-'YTD CF'!P21 | V21: ='YTD CF'!Q21 | W21: ='YTD CF'!R21-'YTD CF'!Q21 | X21: ='YTD CF'!S21-'YTD CF'!R21 | Y21: ='CASH FLOW'!H21-'YTD CF'!S21 | Z21: ='CF DRIVERS'!Z21 | AA21: ='CF DRIVERS'!AA21 | AB21: ='CF DRIVERS'!AB21 | AC21: ='CF DRIVERS'!AC21 | AD21: ='CF DRIVERS'!AD21 | AE21: ='CF DRIVERS'!AE21 | AF21: ='CF DRIVERS'!AF21 | AG21: ='CF DRIVERS'!AG21 | ... AS21: ='CF DRIVERS'!AS21
A22: Prepaid Expenses | B22: ='YTD CF'!B22 | C22: ='YTD CF'!C22-'YTD CF'!B22 | D22: ='YTD CF'!D22-'YTD CF'!C22 | E22: ='CASH FLOW'!C22-'YTD CF'!D22 | F22: ='YTD CF'!E22 | G22: ='YTD CF'!F22-'YTD CF'!E22 | H22: ='YTD CF'!G22-'YTD CF'!F22 | I22: ='CASH FLOW'!D22-'YTD CF'!G22 | J22: ='YTD CF'!H22 | K22: ='YTD CF'!I22-'YTD CF'!H22 | L22: ='YTD CF'!J22-'YTD CF'!I22 | M22: ='CASH FLOW'!E22-'YTD CF'!J22 | N22: ='YTD CF'!K22 | O22: ='YTD CF'!L22-'YTD CF'!K22 | P22: ='YTD CF'!M22-'YTD CF'!L22 | Q22: ='CASH FLOW'!F22-'YTD CF'!M22 | R22: ='YTD CF'!N22 | S22: ='YTD CF'!O22-'YTD CF'!N22 | T22: ='YTD CF'!P22-'YTD CF'!O22 | U22: ='CASH FLOW'!G22-'YTD CF'!P22 | V22: ='YTD CF'!Q22 | W22: ='YTD CF'!R22-'YTD CF'!Q22 | X22: ='YTD CF'!S22-'YTD CF'!R22 | Y22: ='CASH FLOW'!H22-'YTD CF'!S22 | Z22: ='CF DRIVERS'!Z22 | AA22: ='CF DRIVERS'!AA22 | AB22: ='CF DRIVERS'!AB22 | AC22: ='CF DRIVERS'!AC22 | AD22: ='CF DRIVERS'!AD22 | AE22: ='CF DRIVERS'!AE22 | AF22: ='CF DRIVERS'!AF22 | AG22: ='CF DRIVERS'!AG22 | ... AS22: ='CF DRIVERS'!AS22
A23: Change in A/P and Accrued (legacy) | B23: ='YTD CF'!B23 | C23: ='YTD CF'!C23-'YTD CF'!B23 | D23: ='YTD CF'!D23-'YTD CF'!C23 | E23: ='CASH FLOW'!C23-'YTD CF'!D23 | F23: ='YTD CF'!E23 | G23: ='YTD CF'!F23-'YTD CF'!E23 | H23: ='YTD CF'!G23-'YTD CF'!F23 | I23: ='CASH FLOW'!D23-'YTD CF'!G23 | J23: ='YTD CF'!H23 | K23: ='YTD CF'!I23-'YTD CF'!H23 | L23: ='YTD CF'!J23-'YTD CF'!I23 | M23: ='CASH FLOW'!E23-'YTD CF'!J23 | N23: ='YTD CF'!K23 | O23: ='YTD CF'!L23-'YTD CF'!K23 | P23: ='YTD CF'!M23-'YTD CF'!L23 | Q23: ='CASH FLOW'!F23-'YTD CF'!M23 | R23: ='YTD CF'!N23 | S23: ='YTD CF'!O23-'YTD CF'!N23 | T23: ='YTD CF'!P23-'YTD CF'!O23 | U23: ='CASH FLOW'!G23-'YTD CF'!P23 | V23: ='YTD CF'!Q23 | W23: ='YTD CF'!R23-'YTD CF'!Q23 | X23: ='YTD CF'!S23-'YTD CF'!R23 | Y23: ='CASH FLOW'!H23-'YTD CF'!S23 | Z23: ='CF DRIVERS'!Z23 | AA23: ='CF DRIVERS'!AA23 | AB23: ='CF DRIVERS'!AB23 | AC23: ='CF DRIVERS'!AC23 | AD23: ='CF DRIVERS'!AD23 | AE23: ='CF DRIVERS'!AE23 | AF23: ='CF DRIVERS'!AF23 | AG23: ='CF DRIVERS'!AG23 | ... AS23: ='CF DRIVERS'!AS23
A24: Other Non-Current Assets | B24: ='YTD CF'!B24 | C24: ='YTD CF'!C24-'YTD CF'!B24 | D24: ='YTD CF'!D24-'YTD CF'!C24 | E24: ='CASH FLOW'!C24-'YTD CF'!D24 | F24: ='YTD CF'!E24 | G24: ='YTD CF'!F24-'YTD CF'!E24 | H24: ='YTD CF'!G24-'YTD CF'!F24 | I24: ='CASH FLOW'!D24-'YTD CF'!G24 | J24: ='YTD CF'!H24 | K24: ='YTD CF'!I24-'YTD CF'!H24 | L24: ='YTD CF'!J24-'YTD CF'!I24 | M24: ='CASH FLOW'!E24-'YTD CF'!J24 | N24: ='YTD CF'!K24 | O24: ='YTD CF'!L24-'YTD CF'!K24 | P24: ='YTD CF'!M24-'YTD CF'!L24 | Q24: ='CASH FLOW'!F24-'YTD CF'!M24 | R24: ='YTD CF'!N24 | S24: ='YTD CF'!O24-'YTD CF'!N24 | T24: ='YTD CF'!P24-'YTD CF'!O24 | U24: ='CASH FLOW'!G24-'YTD CF'!P24 | V24: ='YTD CF'!Q24 | W24: ='YTD CF'!R24-'YTD CF'!Q24 | X24: ='YTD CF'!S24-'YTD CF'!R24 | Y24: ='CASH FLOW'!H24-'YTD CF'!S24 | Z24: ='CF DRIVERS'!Z24 | AA24: ='CF DRIVERS'!AA24 | AB24: ='CF DRIVERS'!AB24 | AC24: ='CF DRIVERS'!AC24 | AD24: ='CF DRIVERS'!AD24 | AE24: ='CF DRIVERS'!AE24 | AF24: ='CF DRIVERS'!AF24 | AG24: ='CF DRIVERS'!AG24 | ... AS24: ='CF DRIVERS'!AS24
A25: Accounts Payable | B25: ='YTD CF'!B25 | C25: ='YTD CF'!C25-'YTD CF'!B25 | D25: ='YTD CF'!D25-'YTD CF'!C25 | E25: ='CASH FLOW'!C25-'YTD CF'!D25 | F25: ='YTD CF'!E25 | G25: ='YTD CF'!F25-'YTD CF'!E25 | H25: ='YTD CF'!G25-'YTD CF'!F25 | I25: ='CASH FLOW'!D25-'YTD CF'!G25 | J25: ='YTD CF'!H25 | K25: ='YTD CF'!I25-'YTD CF'!H25 | L25: ='YTD CF'!J25-'YTD CF'!I25 | M25: ='CASH FLOW'!E25-'YTD CF'!J25 | N25: ='YTD CF'!K25 | O25: ='YTD CF'!L25-'YTD CF'!K25 | P25: ='YTD CF'!M25-'YTD CF'!L25 | Q25: ='CASH FLOW'!F25-'YTD CF'!M25 | R25: ='YTD CF'!N25 | S25: ='YTD CF'!O25-'YTD CF'!N25 | T25: ='YTD CF'!P25-'YTD CF'!O25 | U25: ='CASH FLOW'!G25-'YTD CF'!P25 | V25: ='YTD CF'!Q25 | W25: ='YTD CF'!R25-'YTD CF'!Q25 | X25: ='YTD CF'!S25-'YTD CF'!R25 | Y25: ='CASH FLOW'!H25-'YTD CF'!S25 | Z25: ='CF DRIVERS'!Z25 | AA25: ='CF DRIVERS'!AA25 | AB25: ='CF DRIVERS'!AB25 | AC25: ='CF DRIVERS'!AC25 | AD25: ='CF DRIVERS'!AD25 | AE25: ='CF DRIVERS'!AE25 | AF25: ='CF DRIVERS'!AF25 | AG25: ='CF DRIVERS'!AG25 | ... AS25: ='CF DRIVERS'!AS25
A26: Accrued Expenses | B26: ='YTD CF'!B26 | C26: ='YTD CF'!C26-'YTD CF'!B26 | D26: ='YTD CF'!D26-'YTD CF'!C26 | E26: ='CASH FLOW'!C26-'YTD CF'!D26 | F26: ='YTD CF'!E26 | G26: ='YTD CF'!F26-'YTD CF'!E26 | H26: ='YTD CF'!G26-'YTD CF'!F26 | I26: ='CASH FLOW'!D26-'YTD CF'!G26 | J26: ='YTD CF'!H26 | K26: ='YTD CF'!I26-'YTD CF'!H26 | L26: ='YTD CF'!J26-'YTD CF'!I26 | M26: ='CASH FLOW'!E26-'YTD CF'!J26 | N26: ='YTD CF'!K26 | O26: ='YTD CF'!L26-'YTD CF'!K26 | P26: ='YTD CF'!M26-'YTD CF'!L26 | Q26: ='CASH FLOW'!F26-'YTD CF'!M26 | R26: ='YTD CF'!N26 | S26: ='YTD CF'!O26-'YTD CF'!N26 | T26: ='YTD CF'!P26-'YTD CF'!O26 | U26: ='CASH FLOW'!G26-'YTD CF'!P26 | V26: ='YTD CF'!Q26 | W26: ='YTD CF'!R26-'YTD CF'!Q26 | X26: ='YTD CF'!S26-'YTD CF'!R26 | Y26: ='CASH FLOW'!H26-'YTD CF'!S26 | Z26: ='CF DRIVERS'!Z26 | AA26: ='CF DRIVERS'!AA26 | AB26: ='CF DRIVERS'!AB26 | AC26: ='CF DRIVERS'!AC26 | AD26: ='CF DRIVERS'!AD26 | AE26: ='CF DRIVERS'!AE26 | AF26: ='CF DRIVERS'!AF26 | AG26: ='CF DRIVERS'!AG26 | ... AS26: ='CF DRIVERS'!AS26
A27: Change in Income Taxes | B27: ='YTD CF'!B27 | C27: ='YTD CF'!C27-'YTD CF'!B27 | D27: ='YTD CF'!D27-'YTD CF'!C27 | E27: ='CASH FLOW'!C27-'YTD CF'!D27 | F27: ='YTD CF'!E27 | G27: ='YTD CF'!F27-'YTD CF'!E27 | H27: ='YTD CF'!G27-'YTD CF'!F27 | I27: ='CASH FLOW'!D27-'YTD CF'!G27 | J27: ='YTD CF'!H27 | K27: ='YTD CF'!I27-'YTD CF'!H27 | L27: ='YTD CF'!J27-'YTD CF'!I27 | M27: ='CASH FLOW'!E27-'YTD CF'!J27 | N27: ='YTD CF'!K27 | O27: ='YTD CF'!L27-'YTD CF'!K27 | P27: ='YTD CF'!M27-'YTD CF'!L27 | Q27: ='CASH FLOW'!F27-'YTD CF'!M27 | R27: ='YTD CF'!N27 | S27: ='YTD CF'!O27-'YTD CF'!N27 | T27: ='YTD CF'!P27-'YTD CF'!O27 | U27: ='CASH FLOW'!G27-'YTD CF'!P27 | V27: ='YTD CF'!Q27 | W27: ='YTD CF'!R27-'YTD CF'!Q27 | X27: ='YTD CF'!S27-'YTD CF'!R27 | Y27: ='CASH FLOW'!H27-'YTD CF'!S27 | Z27: ='CF DRIVERS'!Z27 | AA27: ='CF DRIVERS'!AA27 | AB27: ='CF DRIVERS'!AB27 | AC27: ='CF DRIVERS'!AC27 | AD27: ='CF DRIVERS'!AD27 | AE27: ='CF DRIVERS'!AE27 | AF27: ='CF DRIVERS'!AF27 | AG27: ='CF DRIVERS'!AG27 | ... AS27: ='CF DRIVERS'!AS27
... A33: Net Change in Other Working Capital | B33: ='YTD CF'!B33 | C33: ='YTD CF'!C33-'YTD CF'!B33 | D33: ='YTD CF'!D33-'YTD CF'!C33 | E33: ='CASH FLOW'!C33-'YTD CF'!D33 | F33: ='YTD CF'!E33 | G33: ='YTD CF'!F33-'YTD CF'!E33 | H33: ='YTD CF'!G33-'YTD CF'!F33 | I33: ='CASH FLOW'!D33-'YTD CF'!G33 | J33: ='YTD CF'!H33 | K33: ='YTD CF'!I33-'YTD CF'!H33 | L33: ='YTD CF'!J33-'YTD CF'!I33 | M33: ='CASH FLOW'!E33-'YTD CF'!J33 | N33: ='YTD CF'!K33 | O33: ='YTD CF'!L33-'YTD CF'!K33 | P33: ='YTD CF'!M33-'YTD CF'!L33 | Q33: ='CASH FLOW'!F33-'YTD CF'!M33 | R33: ='YTD CF'!N33 | S33: ='YTD CF'!O33-'YTD CF'!N33 | T33: ='YTD CF'!P33-'YTD CF'!O33 | U33: ='CASH FLOW'!G33-'YTD CF'!P33 | V33: ='YTD CF'!Q33 | W33: ='YTD CF'!R33-'YTD CF'!Q33 | X33: ='YTD CF'!S33-'YTD CF'!R33 | Y33: ='CASH FLOW'!H33-'YTD CF'!S33 | Z33: ='CF DRIVERS'!Z33 | AA33: ='CF DRIVERS'!AA33 | AB33: ='CF DRIVERS'!AB33 | AC33: ='CF DRIVERS'!AC33 | AD33: ='CF DRIVERS'!AD33 | AE33: ='CF DRIVERS'!AE33 | AF33: ='CF DRIVERS'!AF33 | AG33: ='CF DRIVERS'!AG33 | ... AS33: ='CF DRIVERS'!AS33
A34: Cash Flow from Operations | B34: ='YTD CF'!B34 | C34: ='YTD CF'!C34-'YTD CF'!B34 | D34: ='YTD CF'!D34-'YTD CF'!C34 | E34: ='CASH FLOW'!C34-'YTD CF'!D34 | F34: ='YTD CF'!E34 | G34: ='YTD CF'!F34-'YTD CF'!E34 | H34: ='YTD CF'!G34-'YTD CF'!F34 | I34: ='CASH FLOW'!D34-'YTD CF'!G34 | J34: ='YTD CF'!H34 | K34: ='YTD CF'!I34-'YTD CF'!H34 | L34: ='YTD CF'!J34-'YTD CF'!I34 | M34: ='CASH FLOW'!E34-'YTD CF'!J34 | N34: ='YTD CF'!K34 | O34: ='YTD CF'!L34-'YTD CF'!K34 | P34: ='YTD CF'!M34-'YTD CF'!L34 | Q34: ='CASH FLOW'!F34-'YTD CF'!M34 | R34: ='YTD CF'!N34 | S34: ='YTD CF'!O34-'YTD CF'!N34 | T34: ='YTD CF'!P34-'YTD CF'!O34 | U34: ='CASH FLOW'!G34-'YTD CF'!P34 | V34: ='YTD CF'!Q34 | W34: ='YTD CF'!R34-'YTD CF'!Q34 | X34: ='YTD CF'!S34-'YTD CF'!R34 | Y34: ='CASH FLOW'!H34-'YTD CF'!S34 | Z34: =SUM(Z2:Z33) | AA34: =SUM(AA2:AA33) | AB34: =SUM(AB2:AB33) | AC34: =SUM(AC2:AC33) | AD34: =SUM(AD2:AD33) | AE34: =SUM(AE2:AE33) | AF34: =SUM(AF2:AF33) | AG34: =SUM(AG2:AG33) | ... AS34: =SUM(AS2:AS33)
A35: Collections from Note Receivable | B35: ='YTD CF'!B35 | C35: ='YTD CF'!C35-'YTD CF'!B35 | D35: ='YTD CF'!D35-'YTD CF'!C35 | E35: ='CASH FLOW'!C35-'YTD CF'!D35 | F35: ='YTD CF'!E35 | G35: ='YTD CF'!F35-'YTD CF'!E35 | H35: ='YTD CF'!G35-'YTD CF'!F35 | I35: ='CASH FLOW'!D35-'YTD CF'!G35 | J35: ='YTD CF'!H35 | K35: ='YTD CF'!I35-'YTD CF'!H35 | L35: ='YTD CF'!J35-'YTD CF'!I35 | M35: ='CASH FLOW'!E35-'YTD CF'!J35 | N35: ='YTD CF'!K35 | O35: ='YTD CF'!L35-'YTD CF'!K35 | P35: ='YTD CF'!M35-'YTD CF'!L35 | Q35: ='CASH FLOW'!F35-'YTD CF'!M35 | R35: ='YTD CF'!N35 | S35: ='YTD CF'!O35-'YTD CF'!N35 | T35: ='YTD CF'!P35-'YTD CF'!O35 | U35: ='CASH FLOW'!G35-'YTD CF'!P35 | V35: ='YTD CF'!Q35 | W35: ='YTD CF'!R35-'YTD CF'!Q35 | X35: ='YTD CF'!S35-'YTD CF'!R35 | Y35: ='CASH FLOW'!H35-'YTD CF'!S35 | Z35: ='CF DRIVERS'!Z34 | AA35: ='CF DRIVERS'!AA34 | AB35: ='CF DRIVERS'!AB34 | AC35: ='CF DRIVERS'!AC34 | AD35: ='CF DRIVERS'!AD34 | AE35: ='CF DRIVERS'!AE34 | AF35: ='CF DRIVERS'!AF34 | AG35: ='CF DRIVERS'!AG34 | ... AS35: ='CF DRIVERS'!AS34
A36: Purchase of PP&E | B36: ='YTD CF'!B36 | C36: ='YTD CF'!C36-'YTD CF'!B36 | D36: ='YTD CF'!D36-'YTD CF'!C36 | E36: ='CASH FLOW'!C36-'YTD CF'!D36 | F36: ='YTD CF'!E36 | G36: ='YTD CF'!F36-'YTD CF'!E36 | H36: ='YTD CF'!G36-'YTD CF'!F36 | I36: ='CASH FLOW'!D36-'YTD CF'!G36 | J36: ='YTD CF'!H36 | K36: ='YTD CF'!I36-'YTD CF'!H36 | L36: ='YTD CF'!J36-'YTD CF'!I36 | M36: ='CASH FLOW'!E36-'YTD CF'!J36 | N36: ='YTD CF'!K36 | O36: ='YTD CF'!L36-'YTD CF'!K36 | P36: ='YTD CF'!M36-'YTD CF'!L36 | Q36: ='CASH FLOW'!F36-'YTD CF'!M36 | R36: ='YTD CF'!N36 | S36: ='YTD CF'!O36-'YTD CF'!N36 | T36: ='YTD CF'!P36-'YTD CF'!O36 | U36: ='CASH FLOW'!G36-'YTD CF'!P36 | V36: ='YTD CF'!Q36 | W36: ='YTD CF'!R36-'YTD CF'!Q36 | X36: ='YTD CF'!S36-'YTD CF'!R36 | Y36: ='CASH FLOW'!H36-'YTD CF'!S36 | Z36: ='QTR P&L'!AD2*'CF DRIVERS'!Z35 | AA36: ='QTR P&L'!AE2*'CF DRIVERS'!AA35 | AB36: ='QTR P&L'!AF2*'CF DRIVERS'!AB35 | AC36: ='QTR P&L'!AG2*'CF DRIVERS'!AC35 | AD36: ='QTR P&L'!AH2*'CF DRIVERS'!AD35 | AE36: ='QTR P&L'!AI2*'CF DRIVERS'!AE35 | AF36: ='QTR P&L'!AJ2*'CF DRIVERS'!AF35 | AG36: ='QTR P&L'!AK2*'CF DRIVERS'!AG35 | ... AS36: ='QTR P&L'!AW2*'CF DRIVERS'!AS35
A37: Purchase of Non-Marketable Equity Securities | B37: ='YTD CF'!B37 | C37: ='YTD CF'!C37-'YTD CF'!B37 | D37: ='YTD CF'!D37-'YTD CF'!C37 | E37: ='CASH FLOW'!C37-'YTD CF'!D37 | F37: ='YTD CF'!E37 | G37: ='YTD CF'!F37-'YTD CF'!E37 | H37: ='YTD CF'!G37-'YTD CF'!F37 | I37: ='CASH FLOW'!D37-'YTD CF'!G37 | J37: ='YTD CF'!H37 | K37: ='YTD CF'!I37-'YTD CF'!H37 | L37: ='YTD CF'!J37-'YTD CF'!I37 | M37: ='CASH FLOW'!E37-'YTD CF'!J37 | N37: ='YTD CF'!K37 | O37: ='YTD CF'!L37-'YTD CF'!K37 | P37: ='YTD CF'!M37-'YTD CF'!L37 | Q37: ='CASH FLOW'!F37-'YTD CF'!M37 | R37: ='YTD CF'!N37 | S37: ='YTD CF'!O37-'YTD CF'!N37 | T37: ='YTD CF'!P37-'YTD CF'!O37 | U37: ='CASH FLOW'!G37-'YTD CF'!P37 | V37: ='YTD CF'!Q37 | W37: ='YTD CF'!R37-'YTD CF'!Q37 | X37: ='YTD CF'!S37-'YTD CF'!R37 | Y37: ='CASH FLOW'!H37-'YTD CF'!S37 | Z37: ='CF DRIVERS'!Z36 | AA37: ='CF DRIVERS'!AA36 | AB37: ='CF DRIVERS'!AB36 | AC37: ='CF DRIVERS'!AC36 | AD37: ='CF DRIVERS'!AD36 | AE37: ='CF DRIVERS'!AE36 | AF37: ='CF DRIVERS'!AF36 | AG37: ='CF DRIVERS'!AG36 | ... AS37: ='CF DRIVERS'!AS36
A38: Acquisition of Big Beverages | B38: ='YTD CF'!B38 | C38: ='YTD CF'!C38-'YTD CF'!B38 | D38: ='YTD CF'!D38-'YTD CF'!C38 | E38: ='CASH FLOW'!C38-'YTD CF'!D38 | F38: ='YTD CF'!E38 | G38: ='YTD CF'!F38-'YTD CF'!E38 | H38: ='YTD CF'!G38-'YTD CF'!F38 | I38: ='CASH FLOW'!D38-'YTD CF'!G38 | J38: ='YTD CF'!H38 | K38: ='YTD CF'!I38-'YTD CF'!H38 | L38: ='YTD CF'!J38-'YTD CF'!I38 | M38: ='CASH FLOW'!E38-'YTD CF'!J38 | N38: ='YTD CF'!K38 | O38: ='YTD CF'!L38-'YTD CF'!K38 | P38: ='YTD CF'!M38-'YTD CF'!L38 | Q38: ='CASH FLOW'!F38-'YTD CF'!M38 | R38: ='YTD CF'!N38 | S38: ='YTD CF'!O38-'YTD CF'!N38 | T38: ='YTD CF'!P38-'YTD CF'!O38 | U38: ='CASH FLOW'!G38-'YTD CF'!P38 | V38: ='YTD CF'!Q38 | W38: ='YTD CF'!R38-'YTD CF'!Q38 | X38: ='YTD CF'!S38-'YTD CF'!R38 | Y38: ='CASH FLOW'!H38-'YTD CF'!S38 | Z38: ='CF DRIVERS'!Z37 | AA38: ='CF DRIVERS'!AA37 | AB38: ='CF DRIVERS'!AB37 | AC38: ='CF DRIVERS'!AC37 | AD38: ='CF DRIVERS'!AD37 | AE38: ='CF DRIVERS'!AE37 | AF38: ='CF DRIVERS'!AF37 | AG38: ='CF DRIVERS'!AG37 | ... AS38: ='CF DRIVERS'!AS37
A39: Acquisitions, Net of Cash Acquired | B39: ='YTD CF'!B39 | C39: ='YTD CF'!C39-'YTD CF'!B39 | D39: ='YTD CF'!D39-'YTD CF'!C39 | E39: ='CASH FLOW'!C39-'YTD CF'!D39 | F39: ='YTD CF'!E39 | G39: ='YTD CF'!F39-'YTD CF'!E39 | H39: ='YTD CF'!G39-'YTD CF'!F39 | I39: ='CASH FLOW'!D39-'YTD CF'!G39 | J39: ='YTD CF'!H39 | K39: ='YTD CF'!I39-'YTD CF'!H39 | L39: ='YTD CF'!J39-'YTD CF'!I39 | M39: ='CASH FLOW'!E39-'YTD CF'!J39 | N39: ='YTD CF'!K39 | O39: ='YTD CF'!L39-'YTD CF'!K39 | P39: ='YTD CF'!M39-'YTD CF'!L39 | Q39: ='CASH FLOW'!F39-'YTD CF'!M39 | R39: ='YTD CF'!N39 | S39: ='YTD CF'!O39-'YTD CF'!N39 | T39: ='YTD CF'!P39-'YTD CF'!O39 | U39: ='CASH FLOW'!G39-'YTD CF'!P39 | V39: ='YTD CF'!Q39 | W39: ='YTD CF'!R39-'YTD CF'!Q39 | X39: ='YTD CF'!S39-'YTD CF'!R39 | Y39: ='CASH FLOW'!H39-'YTD CF'!S39 | Z39: ='CF DRIVERS'!Z38 | AA39: ='CF DRIVERS'!AA38 | AB39: ='CF DRIVERS'!AB38 | AC39: ='CF DRIVERS'!AC38 | AD39: ='CF DRIVERS'!AD38 | AE39: ='CF DRIVERS'!AE38 | AF39: ='CF DRIVERS'!AF38 | AG39: ='CF DRIVERS'!AG38 | ... AS39: ='CF DRIVERS'!AS38
A40: Working Capital Estimate from Pepsi (Rockstar) | Z40: ='CF DRIVERS'!Z39 | AA40: ='CF DRIVERS'!AA39 | AB40: ='CF DRIVERS'!AB39 | AC40: ='CF DRIVERS'!AC39 | AD40: ='CF DRIVERS'!AD39 | AE40: ='CF DRIVERS'!AE39 | AF40: ='CF DRIVERS'!AF39 | AG40: ='CF DRIVERS'!AG39 | ... AS40: ='CF DRIVERS'!AS39
A41: Cash Flow from Investing | B41: ='YTD CF'!B41 | C41: ='YTD CF'!C41-'YTD CF'!B41 | D41: ='YTD CF'!D41-'YTD CF'!C41 | E41: ='CASH FLOW'!C41-'YTD CF'!D41 | F41: ='YTD CF'!E41 | G41: ='YTD CF'!F41-'YTD CF'!E41 | H41: ='YTD CF'!G41-'YTD CF'!F41 | I41: ='CASH FLOW'!D41-'YTD CF'!G41 | J41: ='YTD CF'!H41 | K41: ='YTD CF'!I41-'YTD CF'!H41 | L41: ='YTD CF'!J41-'YTD CF'!I41 | M41: ='CASH FLOW'!E41-'YTD CF'!J41 | N41: ='YTD CF'!K41 | O41: ='YTD CF'!L41-'YTD CF'!K41 | P41: ='YTD CF'!M41-'YTD CF'!L41 | Q41: ='CASH FLOW'!F41-'YTD CF'!M41 | R41: ='YTD CF'!N41 | S41: ='YTD CF'!O41-'YTD CF'!N41 | T41: ='YTD CF'!P41-'YTD CF'!O41 | U41: ='CASH FLOW'!G41-'YTD CF'!P41 | V41: ='YTD CF'!Q41 | W41: ='YTD CF'!R41-'YTD CF'!Q41 | X41: ='YTD CF'!S41-'YTD CF'!R41 | Y41: ='CASH FLOW'!H41-'YTD CF'!S41 | Z41: =SUM(Z35:Z40) | AA41: =SUM(AA35:AA40) | AB41: =SUM(AB35:AB40) | AC41: =SUM(AC35:AC40) | AD41: =SUM(AD35:AD40) | AE41: =SUM(AE35:AE40) | AF41: =SUM(AF35:AF40) | AG41: =SUM(AG35:AG40) | ... AS41: =SUM(AS35:AS40)
A42: Proceeds from Related-Party Notes | B42: ='YTD CF'!B42 | C42: ='YTD CF'!C42-'YTD CF'!B42 | D42: ='YTD CF'!D42-'YTD CF'!C42 | E42: ='CASH FLOW'!C42-'YTD CF'!D42 | F42: ='YTD CF'!E42 | G42: ='YTD CF'!F42-'YTD CF'!E42 | H42: ='YTD CF'!G42-'YTD CF'!F42 | I42: ='CASH FLOW'!D42-'YTD CF'!G42 | J42: ='YTD CF'!H42 | K42: ='YTD CF'!I42-'YTD CF'!H42 | L42: ='YTD CF'!J42-'YTD CF'!I42 | M42: ='CASH FLOW'!E42-'YTD CF'!J42 | N42: ='YTD CF'!K42 | O42: ='YTD CF'!L42-'YTD CF'!K42 | P42: ='YTD CF'!M42-'YTD CF'!L42 | Q42: ='CASH FLOW'!F42-'YTD CF'!M42 | R42: ='YTD CF'!N42 | S42: ='YTD CF'!O42-'YTD CF'!N42 | T42: ='YTD CF'!P42-'YTD CF'!O42 | U42: ='CASH FLOW'!G42-'YTD CF'!P42 | V42: ='YTD CF'!Q42 | W42: ='YTD CF'!R42-'YTD CF'!Q42 | X42: ='YTD CF'!S42-'YTD CF'!R42 | Y42: ='CASH FLOW'!H42-'YTD CF'!S42 | Z42: ='CF DRIVERS'!Z40 | AA42: ='CF DRIVERS'!AA40 | AB42: ='CF DRIVERS'!AB40 | AC42: ='CF DRIVERS'!AC40 | AD42: ='CF DRIVERS'!AD40 | AE42: ='CF DRIVERS'!AE40 | AF42: ='CF DRIVERS'!AF40 | AG42: ='CF DRIVERS'!AG40 | ... AS42: ='CF DRIVERS'!AS40
A43: Payments on Bonds Payable | B43: ='YTD CF'!B43 | C43: ='YTD CF'!C43-'YTD CF'!B43 | D43: ='YTD CF'!D43-'YTD CF'!C43 | E43: ='CASH FLOW'!C43-'YTD CF'!D43 | F43: ='YTD CF'!E43 | G43: ='YTD CF'!F43-'YTD CF'!E43 | H43: ='YTD CF'!G43-'YTD CF'!F43 | I43: ='CASH FLOW'!D43-'YTD CF'!G43 | J43: ='YTD CF'!H43 | K43: ='YTD CF'!I43-'YTD CF'!H43 | L43: ='YTD CF'!J43-'YTD CF'!I43 | M43: ='CASH FLOW'!E43-'YTD CF'!J43 | N43: ='YTD CF'!K43 | O43: ='YTD CF'!L43-'YTD CF'!K43 | P43: ='YTD CF'!M43-'YTD CF'!L43 | Q43: ='CASH FLOW'!F43-'YTD CF'!M43 | R43: ='YTD CF'!N43 | S43: ='YTD CF'!O43-'YTD CF'!N43 | T43: ='YTD CF'!P43-'YTD CF'!O43 | U43: ='CASH FLOW'!G43-'YTD CF'!P43 | V43: ='YTD CF'!Q43 | W43: ='YTD CF'!R43-'YTD CF'!Q43 | X43: ='YTD CF'!S43-'YTD CF'!R43 | Y43: ='CASH FLOW'!H43-'YTD CF'!S43 | Z43: ='CF DRIVERS'!Z41 | AA43: ='CF DRIVERS'!AA41 | AB43: ='CF DRIVERS'!AB41 | AC43: ='CF DRIVERS'!AC41 | AD43: ='CF DRIVERS'!AD41 | AE43: ='CF DRIVERS'!AE41 | AF43: ='CF DRIVERS'!AF41 | AG43: ='CF DRIVERS'!AG41 | ... AS43: ='CF DRIVERS'!AS41
A44: Finance Lease Payments | B44: ='YTD CF'!B44 | C44: ='YTD CF'!C44-'YTD CF'!B44 | D44: ='YTD CF'!D44-'YTD CF'!C44 | E44: ='CASH FLOW'!C44-'YTD CF'!D44 | F44: ='YTD CF'!E44 | G44: ='YTD CF'!F44-'YTD CF'!E44 | H44: ='YTD CF'!G44-'YTD CF'!F44 | I44: ='CASH FLOW'!D44-'YTD CF'!G44 | J44: ='YTD CF'!H44 | K44: ='YTD CF'!I44-'YTD CF'!H44 | L44: ='YTD CF'!J44-'YTD CF'!I44 | M44: ='CASH FLOW'!E44-'YTD CF'!J44 | N44: ='YTD CF'!K44 | O44: ='YTD CF'!L44-'YTD CF'!K44 | P44: ='YTD CF'!M44-'YTD CF'!L44 | Q44: ='CASH FLOW'!F44-'YTD CF'!M44 | R44: ='YTD CF'!N44 | S44: ='YTD CF'!O44-'YTD CF'!N44 | T44: ='YTD CF'!P44-'YTD CF'!O44 | U44: ='CASH FLOW'!G44-'YTD CF'!P44 | V44: ='YTD CF'!Q44 | W44: ='YTD CF'!R44-'YTD CF'!Q44 | X44: ='YTD CF'!S44-'YTD CF'!R44 | Y44: ='CASH FLOW'!H44-'YTD CF'!S44 | Z44: ='CF DRIVERS'!Z42 | AA44: ='CF DRIVERS'!AA42 | AB44: ='CF DRIVERS'!AB42 | AC44: ='CF DRIVERS'!AC42 | AD44: ='CF DRIVERS'!AD42 | AE44: ='CF DRIVERS'!AE42 | AF44: ='CF DRIVERS'!AF42 | AG44: ='CF DRIVERS'!AG42 | ... AS44: ='CF DRIVERS'!AS42
A45: Proceeds from Issuance of Common Stock | B45: ='YTD CF'!B45 | C45: ='YTD CF'!C45-'YTD CF'!B45 | D45: ='YTD CF'!D45-'YTD CF'!C45 | E45: ='CASH FLOW'!C48-'YTD CF'!D45 | F45: ='YTD CF'!E45 | G45: ='YTD CF'!F45-'YTD CF'!E45 | H45: ='YTD CF'!G45-'YTD CF'!F45 | I45: ='CASH FLOW'!D48-'YTD CF'!G45 | J45: ='YTD CF'!H45 | K45: ='YTD CF'!I45-'YTD CF'!H45 | L45: ='YTD CF'!J45-'YTD CF'!I45 | M45: ='CASH FLOW'!E48-'YTD CF'!J45 | N45: ='YTD CF'!K45 | O45: ='YTD CF'!L45-'YTD CF'!K45 | P45: ='YTD CF'!M45-'YTD CF'!L45 | Q45: ='CASH FLOW'!F48-'YTD CF'!M45 | R45: ='YTD CF'!N45 | S45: ='YTD CF'!O45-'YTD CF'!N45 | T45: ='YTD CF'!P45-'YTD CF'!O45 | U45: ='CASH FLOW'!G48-'YTD CF'!P45 | V45: ='YTD CF'!Q45 | W45: ='YTD CF'!R45-'YTD CF'!Q45 | X45: ='YTD CF'!S45-'YTD CF'!R45 | Y45: ='CASH FLOW'!H48-'YTD CF'!S45 | Z45: ='CF DRIVERS'!Z43 | AA45: ='CF DRIVERS'!AA43 | AB45: ='CF DRIVERS'!AB43 | AC45: ='CF DRIVERS'!AC43 | AD45: ='CF DRIVERS'!AD43 | AE45: ='CF DRIVERS'!AE43 | AF45: ='CF DRIVERS'!AF43 | AG45: ='CF DRIVERS'!AG43 | ... AS45: ='CF DRIVERS'!AS43
A46: Proceeds from Exercise of Stock Options | B46: ='YTD CF'!B46 | C46: ='YTD CF'!C46-'YTD CF'!B46 | D46: ='YTD CF'!D46-'YTD CF'!C46 | E46: ='CASH FLOW'!C45-'YTD CF'!D46 | F46: ='YTD CF'!E46 | G46: ='YTD CF'!F46-'YTD CF'!E46 | H46: ='YTD CF'!G46-'YTD CF'!F46 | I46: ='CASH FLOW'!D45-'YTD CF'!G46 | J46: ='YTD CF'!H46 | K46: ='YTD CF'!I46-'YTD CF'!H46 | L46: ='YTD CF'!J46-'YTD CF'!I46 | M46: ='CASH FLOW'!E45-'YTD CF'!J46 | N46: ='YTD CF'!K46 | O46: ='YTD CF'!L46-'YTD CF'!K46 | P46: ='YTD CF'!M46-'YTD CF'!L46 | Q46: ='CASH FLOW'!F45-'YTD CF'!M46 | R46: ='YTD CF'!N46 | S46: ='YTD CF'!O46-'YTD CF'!N46 | T46: ='YTD CF'!P46-'YTD CF'!O46 | U46: ='CASH FLOW'!G45-'YTD CF'!P46 | V46: ='YTD CF'!Q46 | W46: ='YTD CF'!R46-'YTD CF'!Q46 | X46: ='YTD CF'!S46-'YTD CF'!R46 | Y46: ='CASH FLOW'!H45-'YTD CF'!S46 | Z46: ='CF DRIVERS'!Z44 | AA46: ='CF DRIVERS'!AA44 | AB46: ='CF DRIVERS'!AB44 | AC46: ='CF DRIVERS'!AC44 | AD46: ='CF DRIVERS'!AD44 | AE46: ='CF DRIVERS'!AE44 | AF46: ='CF DRIVERS'!AF44 | AG46: ='CF DRIVERS'!AG44 | ... AS46: ='CF DRIVERS'!AS44
A47: Cash Paid for RSU Tax Withholding | B47: ='YTD CF'!B47 | C47: ='YTD CF'!C47-'YTD CF'!B47 | D47: ='YTD CF'!D47-'YTD CF'!C47 | E47: ='CASH FLOW'!C46-'YTD CF'!D47 | F47: ='YTD CF'!E47 | G47: ='YTD CF'!F47-'YTD CF'!E47 | H47: ='YTD CF'!G47-'YTD CF'!F47 | I47: ='CASH FLOW'!D46-'YTD CF'!G47 | J47: ='YTD CF'!H47 | K47: ='YTD CF'!I47-'YTD CF'!H47 | L47: ='YTD CF'!J47-'YTD CF'!I47 | M47: ='CASH FLOW'!E46-'YTD CF'!J47 | N47: ='YTD CF'!K47 | O47: ='YTD CF'!L47-'YTD CF'!K47 | P47: ='YTD CF'!M47-'YTD CF'!L47 | Q47: ='CASH FLOW'!F46-'YTD CF'!M47 | R47: ='YTD CF'!N47 | S47: ='YTD CF'!O47-'YTD CF'!N47 | T47: ='YTD CF'!P47-'YTD CF'!O47 | U47: ='CASH FLOW'!G46-'YTD CF'!P47 | V47: ='YTD CF'!Q47 | W47: ='YTD CF'!R47-'YTD CF'!Q47 | X47: ='YTD CF'!S47-'YTD CF'!R47 | Y47: ='CASH FLOW'!H46-'YTD CF'!S47 | Z47: ='CF DRIVERS'!Z45 | AA47: ='CF DRIVERS'!AA45 | AB47: ='CF DRIVERS'!AB45 | AC47: ='CF DRIVERS'!AC45 | AD47: ='CF DRIVERS'!AD45 | AE47: ='CF DRIVERS'!AE45 | AF47: ='CF DRIVERS'!AF45 | AG47: ='CF DRIVERS'!AG45 | ... AS47: ='CF DRIVERS'!AS45
A48: Section 16(b) Short-Swing Profit Recovery | B48: ='YTD CF'!B48 | C48: ='YTD CF'!C48-'YTD CF'!B48 | D48: ='YTD CF'!D48-'YTD CF'!C48 | E48: ='CASH FLOW'!C47-'YTD CF'!D48 | F48: ='YTD CF'!E48 | G48: ='YTD CF'!F48-'YTD CF'!E48 | H48: ='YTD CF'!G48-'YTD CF'!F48 | I48: ='CASH FLOW'!D47-'YTD CF'!G48 | J48: ='YTD CF'!H48 | K48: ='YTD CF'!I48-'YTD CF'!H48 | L48: ='YTD CF'!J48-'YTD CF'!I48 | M48: ='CASH FLOW'!E47-'YTD CF'!J48 | N48: ='YTD CF'!K48 | O48: ='YTD CF'!L48-'YTD CF'!K48 | P48: ='YTD CF'!M48-'YTD CF'!L48 | Q48: ='CASH FLOW'!F47-'YTD CF'!M48 | R48: ='YTD CF'!N48 | S48: ='YTD CF'!O48-'YTD CF'!N48 | T48: ='YTD CF'!P48-'YTD CF'!O48 | U48: ='CASH FLOW'!G47-'YTD CF'!P48 | V48: ='YTD CF'!Q48 | W48: ='YTD CF'!R48-'YTD CF'!Q48 | X48: ='YTD CF'!S48-'YTD CF'!R48 | Y48: ='CASH FLOW'!H47-'YTD CF'!S48 | Z48: ='CF DRIVERS'!Z46 | AA48: ='CF DRIVERS'!AA46 | AB48: ='CF DRIVERS'!AB46 | AC48: ='CF DRIVERS'!AC46 | AD48: ='CF DRIVERS'!AD46 | AE48: ='CF DRIVERS'!AE46 | AF48: ='CF DRIVERS'!AF46 | AG48: ='CF DRIVERS'!AG46 | ... AS48: ='CF DRIVERS'!AS46
A49: Proceeds from Issuance of Preferred Stock | B49: ='YTD CF'!B49 | C49: ='YTD CF'!C49-'YTD CF'!B49 | D49: ='YTD CF'!D49-'YTD CF'!C49 | E49: ='CASH FLOW'!C49-'YTD CF'!D49 | F49: ='YTD CF'!E49 | G49: ='YTD CF'!F49-'YTD CF'!E49 | H49: ='YTD CF'!G49-'YTD CF'!F49 | I49: ='CASH FLOW'!D49-'YTD CF'!G49 | J49: ='YTD CF'!H49 | K49: ='YTD CF'!I49-'YTD CF'!H49 | L49: ='YTD CF'!J49-'YTD CF'!I49 | M49: ='CASH FLOW'!E49-'YTD CF'!J49 | N49: ='YTD CF'!K49 | O49: ='YTD CF'!L49-'YTD CF'!K49 | P49: ='YTD CF'!M49-'YTD CF'!L49 | Q49: ='CASH FLOW'!F49-'YTD CF'!M49 | R49: ='YTD CF'!N49 | S49: ='YTD CF'!O49-'YTD CF'!N49 | T49: ='YTD CF'!P49-'YTD CF'!O49 | U49: ='CASH FLOW'!G49-'YTD CF'!P49 | V49: ='YTD CF'!Q49 | W49: ='YTD CF'!R49-'YTD CF'!Q49 | X49: ='YTD CF'!S49-'YTD CF'!R49 | Y49: ='CASH FLOW'!H49-'YTD CF'!S49 | Z49: ='CF DRIVERS'!Z47 | AA49: ='CF DRIVERS'!AA47 | AB49: ='CF DRIVERS'!AB47 | AC49: ='CF DRIVERS'!AC47 | AD49: ='CF DRIVERS'!AD47 | AE49: ='CF DRIVERS'!AE47 | AF49: ='CF DRIVERS'!AF47 | AG49: ='CF DRIVERS'!AG47 | ... AS49: ='CF DRIVERS'!AS47
A50: Preferred Dividends | B50: ='YTD CF'!B50 | C50: ='YTD CF'!C50-'YTD CF'!B50 | D50: ='YTD CF'!D50-'YTD CF'!C50 | E50: ='CASH FLOW'!C50-'YTD CF'!D50 | F50: ='YTD CF'!E50 | G50: ='YTD CF'!F50-'YTD CF'!E50 | H50: ='YTD CF'!G50-'YTD CF'!F50 | I50: ='CASH FLOW'!D50-'YTD CF'!G50 | J50: ='YTD CF'!H50 | K50: ='YTD CF'!I50-'YTD CF'!H50 | L50: ='YTD CF'!J50-'YTD CF'!I50 | M50: ='CASH FLOW'!E50-'YTD CF'!J50 | N50: ='YTD CF'!K50 | O50: ='YTD CF'!L50-'YTD CF'!K50 | P50: ='YTD CF'!M50-'YTD CF'!L50 | Q50: ='CASH FLOW'!F50-'YTD CF'!M50 | R50: ='YTD CF'!N50 | S50: ='YTD CF'!O50-'YTD CF'!N50 | T50: ='YTD CF'!P50-'YTD CF'!O50 | U50: ='CASH FLOW'!G50-'YTD CF'!P50 | V50: ='YTD CF'!Q50 | W50: ='YTD CF'!R50-'YTD CF'!Q50 | X50: ='YTD CF'!S50-'YTD CF'!R50 | Y50: ='CASH FLOW'!H50-'YTD CF'!S50 | Z50: ='CF DRIVERS'!Z48 | AA50: ='CF DRIVERS'!AA48 | AB50: ='CF DRIVERS'!AB48 | AC50: ='CF DRIVERS'!AC48 | AD50: ='CF DRIVERS'!AD48 | AE50: ='CF DRIVERS'!AE48 | AF50: ='CF DRIVERS'!AF48 | AG50: ='CF DRIVERS'!AG48 | ... AS50: ='CF DRIVERS'!AS48
A51: Share Repurchases | B51: ='YTD CF'!B51 | C51: ='YTD CF'!C51-'YTD CF'!B51 | D51: ='YTD CF'!D51-'YTD CF'!C51 | E51: ='CASH FLOW'!C51-'YTD CF'!D51 | F51: ='YTD CF'!E51 | G51: ='YTD CF'!F51-'YTD CF'!E51 | H51: ='YTD CF'!G51-'YTD CF'!F51 | I51: ='CASH FLOW'!D51-'YTD CF'!G51 | J51: ='YTD CF'!H51 | K51: ='YTD CF'!I51-'YTD CF'!H51 | L51: ='YTD CF'!J51-'YTD CF'!I51 | M51: ='CASH FLOW'!E51-'YTD CF'!J51 | N51: ='YTD CF'!K51 | O51: ='YTD CF'!L51-'YTD CF'!K51 | P51: ='YTD CF'!M51-'YTD CF'!L51 | Q51: ='CASH FLOW'!F51-'YTD CF'!M51 | R51: ='YTD CF'!N51 | S51: ='YTD CF'!O51-'YTD CF'!N51 | T51: ='YTD CF'!P51-'YTD CF'!O51 | U51: ='CASH FLOW'!G51-'YTD CF'!P51 | V51: ='YTD CF'!Q51 | W51: ='YTD CF'!R51-'YTD CF'!Q51 | X51: ='YTD CF'!S51-'YTD CF'!R51 | Y51: ='CASH FLOW'!H51-'YTD CF'!S51 | Z51: ='CF DRIVERS'!Z49 | AA51: ='CF DRIVERS'!AA49 | AB51: ='CF DRIVERS'!AB49 | AC51: ='CF DRIVERS'!AC49 | AD51: ='CF DRIVERS'!AD49 | AE51: ='CF DRIVERS'!AE49 | AF51: ='CF DRIVERS'!AF49 | AG51: ='CF DRIVERS'!AG49 | ... AS51: ='CF DRIVERS'!AS49
A52: Proceeds from Issuance of Long-Term Debt | B52: ='YTD CF'!B52 | C52: ='YTD CF'!C52-'YTD CF'!B52 | D52: ='YTD CF'!D52-'YTD CF'!C52 | E52: ='CASH FLOW'!C52-'YTD CF'!D52 | F52: ='YTD CF'!E52 | G52: ='YTD CF'!F52-'YTD CF'!E52 | H52: ='YTD CF'!G52-'YTD CF'!F52 | I52: ='CASH FLOW'!D52-'YTD CF'!G52 | J52: ='YTD CF'!H52 | K52: ='YTD CF'!I52-'YTD CF'!H52 | L52: ='YTD CF'!J52-'YTD CF'!I52 | M52: ='CASH FLOW'!E52-'YTD CF'!J52 | N52: ='YTD CF'!K52 | O52: ='YTD CF'!L52-'YTD CF'!K52 | P52: ='YTD CF'!M52-'YTD CF'!L52 | Q52: ='CASH FLOW'!F52-'YTD CF'!M52 | R52: ='YTD CF'!N52 | S52: ='YTD CF'!O52-'YTD CF'!N52 | T52: ='YTD CF'!P52-'YTD CF'!O52 | U52: ='CASH FLOW'!G52-'YTD CF'!P52 | V52: ='YTD CF'!Q52 | W52: ='YTD CF'!R52-'YTD CF'!Q52 | X52: ='YTD CF'!S52-'YTD CF'!R52 | Y52: ='CASH FLOW'!H52-'YTD CF'!S52 | Z52: ='CF DRIVERS'!Z50 | AA52: ='CF DRIVERS'!AA50 | AB52: ='CF DRIVERS'!AB50 | AC52: ='CF DRIVERS'!AC50 | AD52: ='CF DRIVERS'!AD50 | AE52: ='CF DRIVERS'!AE50 | AF52: ='CF DRIVERS'!AF50 | AG52: ='CF DRIVERS'!AG50 | ... AS52: ='CF DRIVERS'!AS50
A53: Repayments of Long-Term Debt | B53: ='YTD CF'!B53 | C53: ='YTD CF'!C53-'YTD CF'!B53 | D53: ='YTD CF'!D53-'YTD CF'!C53 | E53: ='CASH FLOW'!C53-'YTD CF'!D53 | F53: ='YTD CF'!E53 | G53: ='YTD CF'!F53-'YTD CF'!E53 | H53: ='YTD CF'!G53-'YTD CF'!F53 | I53: ='CASH FLOW'!D53-'YTD CF'!G53 | J53: ='YTD CF'!H53 | K53: ='YTD CF'!I53-'YTD CF'!H53 | L53: ='YTD CF'!J53-'YTD CF'!I53 | M53: ='CASH FLOW'!E53-'YTD CF'!J53 | N53: ='YTD CF'!K53 | O53: ='YTD CF'!L53-'YTD CF'!K53 | P53: ='YTD CF'!M53-'YTD CF'!L53 | Q53: ='CASH FLOW'!F53-'YTD CF'!M53 | R53: ='YTD CF'!N53 | S53: ='YTD CF'!O53-'YTD CF'!N53 | T53: ='YTD CF'!P53-'YTD CF'!O53 | U53: ='CASH FLOW'!G53-'YTD CF'!P53 | V53: ='YTD CF'!Q53 | W53: ='YTD CF'!R53-'YTD CF'!Q53 | X53: ='YTD CF'!S53-'YTD CF'!R53 | Y53: ='CASH FLOW'!H53-'YTD CF'!S53 | Z53: ='CF DRIVERS'!Z51 | AA53: ='CF DRIVERS'!AA51 | AB53: ='CF DRIVERS'!AB51 | AC53: ='CF DRIVERS'!AC51 | AD53: ='CF DRIVERS'!AD51 | AE53: ='CF DRIVERS'!AE51 | AF53: ='CF DRIVERS'!AF51 | AG53: ='CF DRIVERS'!AG51 | ... AS53: ='CF DRIVERS'!AS51
A54: Debt Issuance Fees | B54: ='YTD CF'!B54 | C54: ='YTD CF'!C54-'YTD CF'!B54 | D54: ='YTD CF'!D54-'YTD CF'!C54 | E54: ='CASH FLOW'!C54-'YTD CF'!D54 | F54: ='YTD CF'!E54 | G54: ='YTD CF'!F54-'YTD CF'!E54 | H54: ='YTD CF'!G54-'YTD CF'!F54 | I54: ='CASH FLOW'!D54-'YTD CF'!G54 | J54: ='YTD CF'!H54 | K54: ='YTD CF'!I54-'YTD CF'!H54 | L54: ='YTD CF'!J54-'YTD CF'!I54 | M54: ='CASH FLOW'!E54-'YTD CF'!J54 | N54: ='YTD CF'!K54 | O54: ='YTD CF'!L54-'YTD CF'!K54 | P54: ='YTD CF'!M54-'YTD CF'!L54 | Q54: ='CASH FLOW'!F54-'YTD CF'!M54 | R54: ='YTD CF'!N54 | S54: ='YTD CF'!O54-'YTD CF'!N54 | T54: ='YTD CF'!P54-'YTD CF'!O54 | U54: ='CASH FLOW'!G54-'YTD CF'!P54 | V54: ='YTD CF'!Q54 | W54: ='YTD CF'!R54-'YTD CF'!Q54 | X54: ='YTD CF'!S54-'YTD CF'!R54 | Y54: ='CASH FLOW'!H54-'YTD CF'!S54 | Z54: ='CF DRIVERS'!Z52 | AA54: ='CF DRIVERS'!AA52 | AB54: ='CF DRIVERS'!AB52 | AC54: ='CF DRIVERS'!AC52 | AD54: ='CF DRIVERS'!AD52 | AE54: ='CF DRIVERS'!AE52 | AF54: ='CF DRIVERS'!AF52 | AG54: ='CF DRIVERS'!AG52 | ... AS54: ='CF DRIVERS'!AS52
A55: Other Financing Activities | B55: ='YTD CF'!B55 | C55: ='YTD CF'!C55-'YTD CF'!B55 | D55: ='YTD CF'!D55-'YTD CF'!C55 | E55: ='CASH FLOW'!C55-'YTD CF'!D55 | F55: ='YTD CF'!E55 | G55: ='YTD CF'!F55-'YTD CF'!E55 | H55: ='YTD CF'!G55-'YTD CF'!F55 | I55: ='CASH FLOW'!D55-'YTD CF'!G55 | J55: ='YTD CF'!H55 | K55: ='YTD CF'!I55-'YTD CF'!H55 | L55: ='YTD CF'!J55-'YTD CF'!I55 | M55: ='CASH FLOW'!E55-'YTD CF'!J55 | N55: ='YTD CF'!K55 | O55: ='YTD CF'!L55-'YTD CF'!K55 | P55: ='YTD CF'!M55-'YTD CF'!L55 | Q55: ='CASH FLOW'!F55-'YTD CF'!M55 | R55: ='YTD CF'!N55 | S55: ='YTD CF'!O55-'YTD CF'!N55 | T55: ='YTD CF'!P55-'YTD CF'!O55 | U55: ='CASH FLOW'!G55-'YTD CF'!P55 | V55: ='YTD CF'!Q55 | W55: ='YTD CF'!R55-'YTD CF'!Q55 | X55: ='YTD CF'!S55-'YTD CF'!R55 | Y55: ='CASH FLOW'!H55-'YTD CF'!S55 | Z55: ='CF DRIVERS'!Z53 | AA55: ='CF DRIVERS'!AA53 | AB55: ='CF DRIVERS'!AB53 | AC55: ='CF DRIVERS'!AC53 | AD55: ='CF DRIVERS'!AD53 | AE55: ='CF DRIVERS'!AE53 | AF55: ='CF DRIVERS'!AF53 | AG55: ='CF DRIVERS'!AG53 | ... AS55: ='CF DRIVERS'!AS53
A56: Cash Flow from Financing | B56: ='YTD CF'!B56 | C56: ='YTD CF'!C56-'YTD CF'!B56 | D56: ='YTD CF'!D56-'YTD CF'!C56 | E56: ='CASH FLOW'!C56-'YTD CF'!D56 | F56: ='YTD CF'!E56 | G56: ='YTD CF'!F56-'YTD CF'!E56 | H56: ='YTD CF'!G56-'YTD CF'!F56 | I56: ='CASH FLOW'!D56-'YTD CF'!G56 | J56: ='YTD CF'!H56 | K56: ='YTD CF'!I56-'YTD CF'!H56 | L56: ='YTD CF'!J56-'YTD CF'!I56 | M56: ='CASH FLOW'!E56-'YTD CF'!J56 | N56: ='YTD CF'!K56 | O56: ='YTD CF'!L56-'YTD CF'!K56 | P56: ='YTD CF'!M56-'YTD CF'!L56 | Q56: ='CASH FLOW'!F56-'YTD CF'!M56 | R56: ='YTD CF'!N56 | S56: ='YTD CF'!O56-'YTD CF'!N56 | T56: ='YTD CF'!P56-'YTD CF'!O56 | U56: ='CASH FLOW'!G56-'YTD CF'!P56 | V56: ='YTD CF'!Q56 | W56: ='YTD CF'!R56-'YTD CF'!Q56 | X56: ='YTD CF'!S56-'YTD CF'!R56 | Y56: ='CASH FLOW'!H56-'YTD CF'!S56 | Z56: =SUM(Z42:Z55) | AA56: =SUM(AA42:AA55) | AB56: =SUM(AB42:AB55) | AC56: =SUM(AC42:AC55) | AD56: =SUM(AD42:AD55) | AE56: =SUM(AE42:AE55) | AF56: =SUM(AF42:AF55) | AG56: =SUM(AG42:AG55) | ... AS56: =SUM(AS42:AS55)
A57: FX Effect on Cash | B57: ='YTD CF'!B57 | C57: ='YTD CF'!C57-'YTD CF'!B57 | D57: ='YTD CF'!D57-'YTD CF'!C57 | E57: ='CASH FLOW'!C57-'YTD CF'!D57 | F57: ='YTD CF'!E57 | G57: ='YTD CF'!F57-'YTD CF'!E57 | H57: ='YTD CF'!G57-'YTD CF'!F57 | I57: ='CASH FLOW'!D57-'YTD CF'!G57 | J57: ='YTD CF'!H57 | K57: ='YTD CF'!I57-'YTD CF'!H57 | L57: ='YTD CF'!J57-'YTD CF'!I57 | M57: ='CASH FLOW'!E57-'YTD CF'!J57 | N57: ='YTD CF'!K57 | O57: ='YTD CF'!L57-'YTD CF'!K57 | P57: ='YTD CF'!M57-'YTD CF'!L57 | Q57: ='CASH FLOW'!F57-'YTD CF'!M57 | R57: ='YTD CF'!N57 | S57: ='YTD CF'!O57-'YTD CF'!N57 | T57: ='YTD CF'!P57-'YTD CF'!O57 | U57: ='CASH FLOW'!G57-'YTD CF'!P57 | V57: ='YTD CF'!Q57 | W57: ='YTD CF'!R57-'YTD CF'!Q57 | X57: ='YTD CF'!S57-'YTD CF'!R57 | Y57: ='CASH FLOW'!H57-'YTD CF'!S57 | Z57: ='CF DRIVERS'!Z54 | AA57: ='CF DRIVERS'!AA54 | AB57: ='CF DRIVERS'!AB54 | AC57: ='CF DRIVERS'!AC54 | AD57: ='CF DRIVERS'!AD54 | AE57: ='CF DRIVERS'!AE54 | AF57: ='CF DRIVERS'!AF54 | AG57: ='CF DRIVERS'!AG54 | ... AS57: ='CF DRIVERS'!AS54
A58: Net Change in Cash | B58: ='YTD CF'!B58 | C58: ='YTD CF'!C58-'YTD CF'!B58 | D58: ='YTD CF'!D58-'YTD CF'!C58 | E58: ='CASH FLOW'!C58-'YTD CF'!D58 | F58: ='YTD CF'!E58 | G58: ='YTD CF'!F58-'YTD CF'!E58 | H58: ='YTD CF'!G58-'YTD CF'!F58 | I58: ='CASH FLOW'!D58-'YTD CF'!G58 | J58: ='YTD CF'!H58 | K58: ='YTD CF'!I58-'YTD CF'!H58 | L58: ='YTD CF'!J58-'YTD CF'!I58 | M58: ='CASH FLOW'!E58-'YTD CF'!J58 | N58: ='YTD CF'!K58 | O58: ='YTD CF'!L58-'YTD CF'!K58 | P58: ='YTD CF'!M58-'YTD CF'!L58 | Q58: ='CASH FLOW'!F58-'YTD CF'!M58 | R58: ='YTD CF'!N58 | S58: ='YTD CF'!O58-'YTD CF'!N58 | T58: ='YTD CF'!P58-'YTD CF'!O58 | U58: ='CASH FLOW'!G58-'YTD CF'!P58 | V58: ='YTD CF'!Q58 | W58: ='YTD CF'!R58-'YTD CF'!Q58 | X58: ='YTD CF'!S58-'YTD CF'!R58 | Y58: ='CASH FLOW'!H58-'YTD CF'!S58 | Z58: =Z34+Z41+Z56+Z57 | AA58: =AA34+AA41+AA56+AA57 | AB58: =AB34+AB41+AB56+AB57 | AC58: =AC34+AC41+AC56+AC57 | AD58: =AD34+AD41+AD56+AD57 | AE58: =AE34+AE41+AE56+AE57 | AF58: =AF34+AF41+AF56+AF57 | AG58: =AG34+AG41+AG56+AG57 | ... AS58: =AS34+AS41+AS56+AS57

Sheet IS DRIVERS
A1: Driver | B1: Basis | C1: Q1 FY2019 | D1: Q2 FY2019 | E1: Q3 FY2019 | F1: Q4 FY2019 | G1: Q1 FY2020 | H1: Q2 FY2020 | I1: Q3 FY2020 | J1: Q4 FY2020 | K1: Q1 FY2021 | L1: Q2 FY2021 | M1: Q3 FY2021 | N1: Q4 FY2021 | O1: Q1 FY2022 | P1: Q2 FY2022 | Q1: Q3 FY2022 | R1: Q4 FY2022 | S1: Q1 FY2023 | T1: Q2 FY2023 | U1: Q3 FY2023 | V1: Q4 FY2023 | W1: Q1 FY2024 | X1: Q2 FY2024 | Y1: Q3 FY2024 | Z1: Q4 FY2024 | AA1: Q1 FY2025 | AB1: Q2 FY2025 | AC1: Q3 FY2025 | AD1: Q4 FY2025 | AE1: Q1 FY2026E | AF1: Q2 FY2026E | AG1: Q3 FY2026E | AH1: Q4 FY2026E | AI1: Q1 FY2027E | AJ1: Q2 FY2027E | AK1: Q3 FY2027E | AL1: Q4 FY2027E | AM1: Q1 FY2028E | AN1: Q2 FY2028E | AO1: Q3 FY2028E | AP1: Q4 FY2028E | AQ1: Q1 FY2029E | AR1: Q2 FY2029E | AS1: Q3 FY2029E | AT1: Q4 FY2029E | AU1: Q1 FY2030E | AV1: Q2 FY2030E | AW1: Q3 FY2030E | AX1: Q4 FY2030E
A2: Net Sales / Revenue — Growth % | B2: QoQ | D2: =IFERROR('QTR P&L'!C2/'QTR P&L'!B2-1,"") | E2: =IFERROR('QTR P&L'!D2/'QTR P&L'!C2-1,"") | F2: =IFERROR('QTR P&L'!E2/'QTR P&L'!D2-1,"") | G2: =IFERROR('QTR P&L'!F2/IF($B2="QoQ",'QTR P&L'!E2,'QTR P&L'!B2)-1,"") | H2: =IFERROR('QTR P&L'!G2/IF($B2="QoQ",'QTR P&L'!F2,'QTR P&L'!C2)-1,"") | I2: =IFERROR('QTR P&L'!H2/IF($B2="QoQ",'QTR P&L'!G2,'QTR P&L'!D2)-1,"") | J2: =IFERROR('QTR P&L'!I2/IF($B2="QoQ",'QTR P&L'!H2,'QTR P&L'!E2)-1,"") | K2: =IFERROR('QTR P&L'!J2/IF($B2="QoQ",'QTR P&L'!I2,'QTR P&L'!F2)-1,"") | L2: =IFERROR('QTR P&L'!K2/IF($B2="QoQ",'QTR P&L'!J2,'QTR P&L'!G2)-1,"") | M2: =IFERROR('QTR P&L'!L2/IF($B2="QoQ",'QTR P&L'!K2,'QTR P&L'!H2)-1,"") | N2: =IFERROR('QTR P&L'!M2/IF($B2="QoQ",'QTR P&L'!L2,'QTR P&L'!I2)-1,"") | ... AD2: =IFERROR('QTR P&L'!AC2/IF($B2="QoQ",'QTR P&L'!AB2,'QTR P&L'!Y2)-1,"") | AE2: =AD2 | AF2: =AE2 | AG2: =AF2 | AH2: =AG2 | AI2: =AH2 | AJ2: =AI2 | AK2: =AJ2 | AL2: =AK2 | ... AX2: =AW2
A3: COGS — % of Revenue | C3: =IFERROR('QTR P&L'!B3/'QTR P&L'!B2,"") | D3: =IFERROR('QTR P&L'!C3/'QTR P&L'!C2,"") | E3: =IFERROR('QTR P&L'!D3/'QTR P&L'!D2,"") | F3: =IFERROR('QTR P&L'!E3/'QTR P&L'!E2,"") | G3: =IFERROR('QTR P&L'!F3/'QTR P&L'!F2,"") | H3: =IFERROR('QTR P&L'!G3/'QTR P&L'!G2,"") | I3: =IFERROR('QTR P&L'!H3/'QTR P&L'!H2,"") | J3: =IFERROR('QTR P&L'!I3/'QTR P&L'!I2,"") | ... AD3: =IFERROR('QTR P&L'!AC3/'QTR P&L'!AC2,"") | AE3: =AD3 | AF3: =AE3 | AG3: =AF3 | AH3: =AG3 | AI3: =AH3 | AJ3: =AI3 | AK3: =AJ3 | AL3: =AK3 | ... AX3: =AW3
A4: Sales and Marketing — % of Revenue | C4: =IFERROR('QTR P&L'!B5/'QTR P&L'!B2,"") | D4: =IFERROR('QTR P&L'!C5/'QTR P&L'!C2,"") | E4: =IFERROR('QTR P&L'!D5/'QTR P&L'!D2,"") | F4: =IFERROR('QTR P&L'!E5/'QTR P&L'!E2,"") | G4: =IFERROR('QTR P&L'!F5/'QTR P&L'!F2,"") | H4: =IFERROR('QTR P&L'!G5/'QTR P&L'!G2,"") | I4: =IFERROR('QTR P&L'!H5/'QTR P&L'!H2,"") | J4: =IFERROR('QTR P&L'!I5/'QTR P&L'!I2,"") | ... AD4: =IFERROR('QTR P&L'!AC5/'QTR P&L'!AC2,"") | AE4: =AD4 | AF4: =AE4 | AG4: =AF4 | AH4: =AG4 | AI4: =AH4 | AJ4: =AI4 | AK4: =AJ4 | AL4: =AK4 | ... AX4: =AW4
A5: General and Administrative — % of Revenue | C5: =IFERROR('QTR P&L'!B6/'QTR P&L'!B2,"") | D5: =IFERROR('QTR P&L'!C6/'QTR P&L'!C2,"") | E5: =IFERROR('QTR P&L'!D6/'QTR P&L'!D2,"") | F5: =IFERROR('QTR P&L'!E6/'QTR P&L'!E2,"") | G5: =IFERROR('QTR P&L'!F6/'QTR P&L'!F2,"") | H5: =IFERROR('QTR P&L'!G6/'QTR P&L'!G2,"") | I5: =IFERROR('QTR P&L'!H6/'QTR P&L'!H2,"") | J5: =IFERROR('QTR P&L'!I6/'QTR P&L'!I2,"") | ... AD5: =IFERROR('QTR P&L'!AC6/'QTR P&L'!AC2,"") | AE5: =AD5 | AF5: =AE5 | AG5: =AF5 | AH5: =AG5 | AI5: =AH5 | AJ5: =AI5 | AK5: =AJ5 | AL5: =AK5 | ... AX5: =AW5
A6: Operating Expenses — % of Revenue | C6: =IFERROR('QTR P&L'!B7/'QTR P&L'!B2,"") | D6: =IFERROR('QTR P&L'!C7/'QTR P&L'!C2,"") | E6: =IFERROR('QTR P&L'!D7/'QTR P&L'!D2,"") | F6: =IFERROR('QTR P&L'!E7/'QTR P&L'!E2,"") | G6: =IFERROR('QTR P&L'!F7/'QTR P&L'!F2,"") | H6: =IFERROR('QTR P&L'!G7/'QTR P&L'!G2,"") | I6: =IFERROR('QTR P&L'!H7/'QTR P&L'!H2,"") | J6: =IFERROR('QTR P&L'!I7/'QTR P&L'!I2,"") | ... AD6: =IFERROR('QTR P&L'!AC7/'QTR P&L'!AC2,"") | AE6: =AD6 | AF6: =AE6 | AG6: =AF6 | AH6: =AG6 | AI6: =AH6 | AJ6: =AI6 | AK6: =AJ6 | AL6: =AK6 | ... AX6: =AW6
A7: SG&A — % of Revenue | C7: =IFERROR('QTR P&L'!B8/'QTR P&L'!B2,"") | D7: =IFERROR('QTR P&L'!C8/'QTR P&L'!C2,"") | E7: =IFERROR('QTR P&L'!D8/'QTR P&L'!D2,"") | F7: =IFERROR('QTR P&L'!E8/'QTR P&L'!E2,"") | G7: =IFERROR('QTR P&L'!F8/'QTR P&L'!F2,"") | H7: =IFERROR('QTR P&L'!G8/'QTR P&L'!G2,"") | I7: =IFERROR('QTR P&L'!H8/'QTR P&L'!H2,"") | J7: =IFERROR('QTR P&L'!I8/'QTR P&L'!I2,"") | ... AD7: =IFERROR('QTR P&L'!AC8/'QTR P&L'!AC2,"") | AE7: =AD7 | AF7: =AE7 | AG7: =AF7 | AH7: =AG7 | AI7: =AH7 | AJ7: =AI7 | AK7: =AJ7 | AL7: =AK7 | ... AX7: =AW7
A8: Distributor Termination Fees | C8: ='QTR P&L'!B9 | D8: ='QTR P&L'!C9 | E8: ='QTR P&L'!D9 | F8: ='QTR P&L'!E9 | G8: ='QTR P&L'!F9 | H8: ='QTR P&L'!G9 | I8: ='QTR P&L'!H9 | J8: ='QTR P&L'!I9 | ... AD8: ='QTR P&L'!AC9 | AE8: 0 | AF8: 0 | AG8: 0 | AH8: 0 | AI8: 0 | AJ8: 0 | AK8: 0 | AL8: 0 | AM8: 0 | AN8: 0 | AO8: 0 | AP8: 0 | AQ8: 0 | AR8: 0 | AS8: 0 | AT8: 0 | AU8: 0 | AV8: 0 | AW8: 0 | AX8: 0
A9: Interest Income (Expense) | C9: ='QTR P&L'!B11 | D9: ='QTR P&L'!C11 | E9: ='QTR P&L'!D11 | F9: ='QTR P&L'!E11 | G9: ='QTR P&L'!F11 | H9: ='QTR P&L'!G11 | I9: ='QTR P&L'!H11 | J9: ='QTR P&L'!I11 | ... AD9: ='QTR P&L'!AC11 | AE9: =AD9 | AF9: =AE9 | AG9: =AF9 | AH9: =AG9 | AI9: =AH9 | AJ9: =AI9 | AK9: =AJ9 | AL9: =AK9 | ... AX9: =AW9
A10: Other Income (Expense) | C10: ='QTR P&L'!B12 | D10: ='QTR P&L'!C12 | E10: ='QTR P&L'!D12 | F10: ='QTR P&L'!E12 | G10: ='QTR P&L'!F12 | H10: ='QTR P&L'!G12 | I10: ='QTR P&L'!H12 | J10: ='QTR P&L'!I12 | ... AD10: ='QTR P&L'!AC12 | AE10: =AD10 | AF10: =AE10 | AG10: =AF10 | AH10: =AG10 | AI10: =AH10 | AJ10: =AI10 | AK10: =AJ10 | AL10: =AK10 | ... AX10: =AW10
A11: Foreign Currency Gain (Loss) | C11: ='QTR P&L'!B13 | D11: ='QTR P&L'!C13 | E11: ='QTR P&L'!D13 | F11: ='QTR P&L'!E13 | G11: ='QTR P&L'!F13 | H11: ='QTR P&L'!G13 | I11: ='QTR P&L'!H13 | J11: ='QTR P&L'!I13 | ... AD11: ='QTR P&L'!AC13 | AE11: =AD11 | AF11: =AE11 | AG11: =AF11 | AH11: =AG11 | AI11: =AH11 | AJ11: =AI11 | AK11: =AJ11 | AL11: =AK11 | ... AX11: =AW11
A12: Gain (Loss) on Lease Cancellations | C12: ='QTR P&L'!B14 | D12: ='QTR P&L'!C14 | E12: ='QTR P&L'!D14 | F12: ='QTR P&L'!E14 | G12: ='QTR P&L'!F14 | H12: ='QTR P&L'!G14 | I12: ='QTR P&L'!H14 | J12: ='QTR P&L'!I14 | ... AD12: ='QTR P&L'!AC14 | AE12: =AD12 | AF12: =AE12 | AG12: =AF12 | AH12: =AG12 | AI12: =AH12 | AJ12: =AI12 | AK12: =AJ12 | AL12: =AK12 | ... AX12: =AW12
A13: Income Tax (Expense) Benefit | C13: ='QTR P&L'!B15 | D13: ='QTR P&L'!C15 | E13: ='QTR P&L'!D15 | F13: ='QTR P&L'!E15 | G13: ='QTR P&L'!F15 | H13: ='QTR P&L'!G15 | I13: ='QTR P&L'!H15 | J13: ='QTR P&L'!I15 | ... AD13: ='QTR P&L'!AC15 | AE13: =AD13 | AF13: =AE13 | AG13: =AF13 | AH13: =AG13 | AI13: =AH13 | AJ13: =AI13 | AK13: =AJ13 | AL13: =AK13 | ... AX13: =AW13
A14: Preferred Dividends | AE14: ='QTR CF'!Z50 | AF14: ='QTR CF'!AA50 | AG14: ='QTR CF'!AB50 | AH14: ='QTR CF'!AC50 | AI14: ='QTR CF'!AD50 | AJ14: ='QTR CF'!AE50 | AK14: ='QTR CF'!AF50 | AL14: ='QTR CF'!AG50 | ... AX14: ='QTR CF'!AS50
A15: Income Allocated to Participating Preferred | C15: ='QTR P&L'!B23 | D15: ='QTR P&L'!C23 | E15: ='QTR P&L'!D23 | F15: ='QTR P&L'!E23 | G15: ='QTR P&L'!F23 | H15: ='QTR P&L'!G23 | I15: ='QTR P&L'!H23 | J15: ='QTR P&L'!I23 | ... AD15: ='QTR P&L'!AC23 | AE15: =AD15 | AF15: =AE15 | AG15: =AF15 | AH15: =AG15 | AI15: =AH15 | AJ15: =AI15 | AK15: =AJ15 | AL15: =AK15 | ... AX15: =AW15

Sheet BS DRIVERS
A1: Driver | B1: Q4 FY2019 | C1: Q1 FY2020 | D1: Q2 FY2020 | E1: Q3 FY2020 | F1: Q4 FY2020 | G1: Q1 FY2021 | H1: Q2 FY2021 | I1: Q3 FY2021 | J1: Q4 FY2021 | K1: Q1 FY2022 | L1: Q2 FY2022 | M1: Q3 FY2022 | N1: Q4 FY2022 | O1: Q1 FY2023 | P1: Q2 FY2023 | Q1: Q3 FY2023 | R1: Q4 FY2023 | S1: Q1 FY2024 | T1: Q2 FY2024 | U1: Q3 FY2024 | V1: Q4 FY2024 | W1: Q1 FY2025 | X1: Q2 FY2025 | Y1: Q3 FY2025 | Z1: Q4 FY2025 | AA1: Q1 FY2026E | AB1: Q2 FY2026E | AC1: Q3 FY2026E | AD1: Q4 FY2026E | AE1: Q1 FY2027E | AF1: Q2 FY2027E | AG1: Q3 FY2027E | AH1: Q4 FY2027E | AI1: Q1 FY2028E | AJ1: Q2 FY2028E | AK1: Q3 FY2028E | AL1: Q4 FY2028E | AM1: Q1 FY2029E | AN1: Q2 FY2029E | AO1: Q3 FY2029E | AP1: Q4 FY2029E | AQ1: Q1 FY2030E | AR1: Q2 FY2030E | AS1: Q3 FY2030E | AT1: Q4 FY2030E
A2: Cash, Cash Equivalents & Restricted Cash | B2: ='QTR BS'!B2 | C2: ='QTR BS'!C2 | D2: ='QTR BS'!D2 | E2: ='QTR BS'!E2 | F2: ='QTR BS'!F2 | G2: ='QTR BS'!G2 | H2: ='QTR BS'!H2 | I2: ='QTR BS'!I2 | ... Z2: ='QTR BS'!Z2 | AA2: =Z2 | AB2: =AA2 | AC2: =AB2 | AD2: =AC2 | AE2: =AD2 | AF2: =AE2 | AG2: =AF2 | AH2: =AG2 | ... AT2: =AS2
A3: Accounts Receivable — DSO (days) | B3: =IFERROR('QTR BS'!B3/'QTR P&L'!E2*ASSUMPTIONS!$B$2,"") | C3: =IFERROR('QTR BS'!C3/'QTR P&L'!F2*ASSUMPTIONS!$B$2,"") | D3: =IFERROR('QTR BS'!D3/'QTR P&L'!G2*ASSUMPTIONS!$B$2,"") | E3: =IFERROR('QTR BS'!E3/'QTR P&L'!H2*ASSUMPTIONS!$B$2,"") | F3: =IFERROR('QTR BS'!F3/'QTR P&L'!I2*ASSUMPTIONS!$B$2,"") | G3: =IFERROR('QTR BS'!G3/'QTR P&L'!J2*ASSUMPTIONS!$B$2,"") | H3: =IFERROR('QTR BS'!H3/'QTR P&L'!K2*ASSUMPTIONS!$B$2,"") | I3: =IFERROR('QTR BS'!I3/'QTR P&L'!L2*ASSUMPTIONS!$B$2,"") | ... Z3: =IFERROR('QTR BS'!Z3/'QTR P&L'!AC2*ASSUMPTIONS!$B$2,"") | AA3: =Z3 | AB3: =AA3 | AC3: =AB3 | AD3: =AC3 | AE3: =AD3 | AF3: =AE3 | AG3: =AF3 | AH3: =AG3 | ... AT3: =AS3
A4: Note Receivable - Current — DSO (days) | B4: =IFERROR('QTR BS'!B4/'QTR P&L'!E2*ASSUMPTIONS!$B$2,"") | C4: =IFERROR('QTR BS'!C4/'QTR P&L'!F2*ASSUMPTIONS!$B$2,"") | D4: =IFERROR('QTR BS'!D4/'QTR P&L'!G2*ASSUMPTIONS!$B$2,"") | E4: =IFERROR('QTR BS'!E4/'QTR P&L'!H2*ASSUMPTIONS!$B$2,"") | F4: =IFERROR('QTR BS'!F4/'QTR P&L'!I2*ASSUMPTIONS!$B$2,"") | G4: =IFERROR('QTR BS'!G4/'QTR P&L'!J2*ASSUMPTIONS!$B$2,"") | H4: =IFERROR('QTR BS'!H4/'QTR P&L'!K2*ASSUMPTIONS!$B$2,"") | I4: =IFERROR('QTR BS'!I4/'QTR P&L'!L2*ASSUMPTIONS!$B$2,"") | ... Z4: =IFERROR('QTR BS'!Z4/'QTR P&L'!AC2*ASSUMPTIONS!$B$2,"") | AA4: =Z4 | AB4: =AA4 | AC4: =AB4 | AD4: =AC4 | AE4: =AD4 | AF4: =AE4 | AG4: =AF4 | AH4: =AG4 | ... AT4: =AS4
A5: Inventories — DIO (days) | B5: =IFERROR('QTR BS'!B5/'QTR P&L'!E3*ASSUMPTIONS!$B$2,"") | C5: =IFERROR('QTR BS'!C5/'QTR P&L'!F3*ASSUMPTIONS!$B$2,"") | D5: =IFERROR('QTR BS'!D5/'QTR P&L'!G3*ASSUMPTIONS!$B$2,"") | E5: =IFERROR('QTR BS'!E5/'QTR P&L'!H3*ASSUMPTIONS!$B$2,"") | F5: =IFERROR('QTR BS'!F5/'QTR P&L'!I3*ASSUMPTIONS!$B$2,"") | G5: =IFERROR('QTR BS'!G5/'QTR P&L'!J3*ASSUMPTIONS!$B$2,"") | H5: =IFERROR('QTR BS'!H5/'QTR P&L'!K3*ASSUMPTIONS!$B$2,"") | I5: =IFERROR('QTR BS'!I5/'QTR P&L'!L3*ASSUMPTIONS!$B$2,"") | ... Z5: =IFERROR('QTR BS'!Z5/'QTR P&L'!AC3*ASSUMPTIONS!$B$2,"") | AA5: =Z5 | AB5: =AA5 | AC5: =AB5 | AD5: =AC5 | AE5: =AD5 | AF5: =AE5 | AG5: =AF5 | AH5: =AG5 | ... AT5: =AS5
A6: Prepaid Expenses — % of Revenue | B6: =IFERROR('QTR BS'!B6/'QTR P&L'!E2,"") | C6: =IFERROR('QTR BS'!C6/'QTR P&L'!F2,"") | D6: =IFERROR('QTR BS'!D6/'QTR P&L'!G2,"") | E6: =IFERROR('QTR BS'!E6/'QTR P&L'!H2,"") | F6: =IFERROR('QTR BS'!F6/'QTR P&L'!I2,"") | G6: =IFERROR('QTR BS'!G6/'QTR P&L'!J2,"") | H6: =IFERROR('QTR BS'!H6/'QTR P&L'!K2,"") | I6: =IFERROR('QTR BS'!I6/'QTR P&L'!L2,"") | ... Z6: =IFERROR('QTR BS'!Z6/'QTR P&L'!AC2,"") | AA6: =Z6 | AB6: =AA6 | AC6: =AB6 | AD6: =AC6 | AE6: =AD6 | AF6: =AE6 | AG6: =AF6 | AH6: =AG6 | ... AT6: =AS6
A7: Deferred Other Costs - Current — % of Revenue | B7: =IFERROR('QTR BS'!B7/'QTR P&L'!E2,"") | C7: =IFERROR('QTR BS'!C7/'QTR P&L'!F2,"") | D7: =IFERROR('QTR BS'!D7/'QTR P&L'!G2,"") | E7: =IFERROR('QTR BS'!E7/'QTR P&L'!H2,"") | F7: =IFERROR('QTR BS'!F7/'QTR P&L'!I2,"") | G7: =IFERROR('QTR BS'!G7/'QTR P&L'!J2,"") | H7: =IFERROR('QTR BS'!H7/'QTR P&L'!K2,"") | I7: =IFERROR('QTR BS'!I7/'QTR P&L'!L2,"") | ... Z7: =IFERROR('QTR BS'!Z7/'QTR P&L'!AC2,"") | AA7: =Z7 | AB7: =AA7 | AC7: =AB7 | AD7: =AC7 | AE7: =AD7 | AF7: =AE7 | AG7: =AF7 | AH7: =AG7 | ... AT7: =AS7
A8: Note Receivable - Non-Current — % of Revenue | B8: =IFERROR('QTR BS'!B9/'QTR P&L'!E2,"") | C8: =IFERROR('QTR BS'!C9/'QTR P&L'!F2,"") | D8: =IFERROR('QTR BS'!D9/'QTR P&L'!G2,"") | E8: =IFERROR('QTR BS'!E9/'QTR P&L'!H2,"") | F8: =IFERROR('QTR BS'!F9/'QTR P&L'!I2,"") | G8: =IFERROR('QTR BS'!G9/'QTR P&L'!J2,"") | H8: =IFERROR('QTR BS'!H9/'QTR P&L'!K2,"") | I8: =IFERROR('QTR BS'!I9/'QTR P&L'!L2,"") | ... Z8: =IFERROR('QTR BS'!Z9/'QTR P&L'!AC2,"") | AA8: =Z8 | AB8: =AA8 | AC8: =AB8 | AD8: =AC8 | AE8: =AD8 | AF8: =AE8 | AG8: =AF8 | AH8: =AG8 | ... AT8: =AS8
A9: Net PP&E | B9: ='QTR BS'!B10 | C9: ='QTR BS'!C10 | D9: ='QTR BS'!D10 | E9: ='QTR BS'!E10 | F9: ='QTR BS'!F10 | G9: ='QTR BS'!G10 | H9: ='QTR BS'!H10 | I9: ='QTR BS'!I10 | ... Z9: ='QTR BS'!Z10 | AA9: =Z9-'QTR CF'!Z36-'QTR CF'!Z6 | AB9: =AA9-'QTR CF'!AA36-'QTR CF'!AA6 | AC9: =AB9-'QTR CF'!AB36-'QTR CF'!AB6 | AD9: =AC9-'QTR CF'!AC36-'QTR CF'!AC6 | AE9: =AD9-'QTR CF'!AD36-'QTR CF'!AD6 | AF9: =AE9-'QTR CF'!AE36-'QTR CF'!AE6 | AG9: =AF9-'QTR CF'!AF36-'QTR CF'!AF6 | AH9: =AG9-'QTR CF'!AG36-'QTR CF'!AG6 | ... AT9: =AS9-'QTR CF'!AS36-'QTR CF'!AS6
