Workbook

Sheet ANNL P&L
B1: FY2021 | C1: FY2022 | D1: FY2023 | E1: FY2024 | F1: FY2025 | G1: FY2026E | H1: FY2027E | I1: FY2028E | J1: FY2029E | K1: FY2030E | L1: FY2031E
A2: Net Sales / Revenue | B2: 76118 | C2: 80187 | D2: 82006 | E2: 84039 | F2: 84284
A3: COGS | B3: -37108 | C3: -42157 | D3: -42760 | E3: -40848 | F3: -41164
A4: Gross Profit (Loss) | B4: =B2+B3 | C4: =C2+C3 | D4: =D2+D3 | E4: =E2+E3 | F4: =F2+F3 | G4: =G2+G3 | H4: =H2+H3 | I4: =I2+I3 | ... L4: =L2+L3
A5: SG&A | B5: -21024 | C5: -20217 | D5: -21112 | E5: -23305 | F5: -22669
A6: Impairment of Intangibles | B6: 0 | C6: 0 | D6: 0 | E6: -1341 | F6: 0
A7: Income (Loss) from Operations | B7: =B4+SUM(B5:B6) | C7: =C4+SUM(C5:C6) | D7: =D4+SUM(D5:D6) | E7: =E4+SUM(E5:E6) | F7: =F4+SUM(F5:F6) | G7: =G4+SUM(G5:G6) | H7: =H4+SUM(H5:H6) | I7: =I4+SUM(I5:I6) | ... L7: =L4+SUM(L5:L6)
A8: Interest Income (Expense) | B8: -457 | C8: -388 | D8: -449 | E8: -452 | F8: -438
A9: Other Income (Expense) | B9: 86 | C9: 570 | D9: 668 | E9: 668 | F9: 154
A10: Pre-Tax Income (Loss) | B10: =B7+SUM(B8:B9) | C10: =C7+SUM(C8:C9) | D10: =D7+SUM(D8:D9) | E10: =E7+SUM(E8:E9) | F10: =F7+SUM(F8:F9) | G10: =G7+SUM(G8:G9) | H10: =H7+SUM(H8:H9) | I10: =I7+SUM(I8:I9) | ... L10: =L7+SUM(L8:L9)
A11: Income Tax (Expense) Benefit | B11: -3263 | C11: -3202 | D11: -3615 | E11: -3787 | F11: -4102
A12: Net Income (Loss) | B12: =B10+B11 | C12: =C10+C11 | D12: =D10+D11 | E12: =E10+E11 | F12: =F10+F11 | G12: =G10+G11 | H12: =H10+H11 | I12: =I10+I11 | ... L12: =L10+L11
A13: Net Income (Loss) Attributable to Noncontrolling Interest | B13: 46 | C13: 51 | D13: 85 | E13: 95 | F13: 91
A14: Net Income (Loss) Less NCI | B14: =B12-B13 | C14: =C12-C13 | D14: =D12-D13 | E14: =E12-E13 | F14: =F12-F13 | G14: =G12-G13 | H14: =H12-H13 | I14: =I12-I13 | ... L14: =L12-L13
A15: Basic Earnings (Loss) per Share | B15: 5.69 | C15: 6 | D15: 6.07 | E15: 6.18 | F15: 6.67
A16: Diluted Earnings (Loss) per Share | B16: 5.5 | C16: 5.81 | D16: 5.9 | E16: 6.02 | F16: 6.51

Sheet BALANCE SHEET
B1: FY2022 | C1: FY2023 | D1: FY2024 | E1: FY2025 | F1: FY2026E | G1: FY2027E | H1: FY2028E | I1: FY2029E | J1: FY2030E | K1: FY2031E
A2: Cash & Cash Equivalents | B2: 7214 | C2: 8246 | D2: 9482 | E2: 9556
A3: Accounts Receivable | B3: 5143 | C3: 5471 | D3: 6118 | E3: 6185
A4: Raw Materials | B4: 2168 | C4: 1863 | D4: 1617 | E4: 2022
A5: Work in Process | B5: 856 | C5: 956 | D5: 929 | E5: 1012
A6: Finished Goods | B6: 3900 | C6: 4254 | D6: 4470 | E6: 4516
A7: Inventories | B7: =SUM(B4,B5,B6) | C7: =SUM(C4,C5,C6) | D7: =SUM(D4,D5,D6) | E7: =SUM(E4,E5,E6)
A8: Prepaid Expenses | B8: 2372 | C8: 1858 | D8: 2095 | E8: 2100
A9: Total Current Assets | B9: =SUM(B2:B8) | C9: =SUM(C2:C8) | D9: =SUM(D2:D8) | E9: =SUM(E2:E8) | F9: =SUM(F2:F8) | G9: =SUM(G2:G8) | H9: =SUM(H2:H8) | I9: =SUM(I2:I8) | ... K9: =SUM(K2:K8)
A10: Net PP&E | B10: 21195 | C10: 21909 | D10: 22152 | E10: 23897
A11: Goodwill | B11: 39700 | C11: 40659 | D11: 40303 | E11: 41650
A12: Intangible Assets | B12: 23679 | C12: 23783 | D12: 22047 | E12: 21910
A13: Other Non-Current Assets | B13: 10981 | C13: 11830 | D13: 13158 | E13: 12381
A14: Total Assets | B14: =B9+SUM(B10:B13) | C14: =C9+SUM(C10:C13) | D14: =D9+SUM(D10:D13) | E14: =E9+SUM(E10:E13) | F14: =F9+SUM(F10:F13) | G14: =G9+SUM(G10:G13) | H14: =H9+SUM(H10:H13) | I14: =I9+SUM(I10:I13) | ... K14: =K9+SUM(K10:K13)
A15: Accounts Payable | B15: 14882 | C15: 14598 | D15: 15364 | E15: 15227
A16: Accrued Expenses | B16: 9554 | C16: 10929 | D16: 11073 | E16: 11318
A17: Current Portion of Long-Term Debt | B17: 8645 | C17: 10229 | D17: 7191 | E17: 9513
A18: Total Current Liabilities | B18: =SUM(B15:B17) | C18: =SUM(C15:C17) | D18: =SUM(D15:D17) | E18: =SUM(E15:E17) | F18: =SUM(F15:F17) | G18: =SUM(G15:G17) | H18: =SUM(H15:H17) | I18: =SUM(I15:I17) | ... K18: =SUM(K15:K17)
A19: Long-Term Debt | B19: 22848 | C19: 24378 | D19: 25269 | E19: 24995
A20: Deferred Tax Liability | B20: 6809 | C20: 6478 | D20: 6516 | E20: 5774
A21: Other Non-Current Liabilities | B21: 7616 | C21: 7152 | D21: 6398 | E21: 6120
A22: Total Liabilities | B22: =B18+SUM(B19:B21) | C22: =C18+SUM(C19:C21) | D22: =D18+SUM(D19:D21) | E22: =E18+SUM(E19:E21) | F22: =F18+SUM(F19:F21) | G22: =G18+SUM(G19:G21) | H22: =H18+SUM(H19:H21) | I22: =I18+SUM(I19:I21) | ... K22: =K18+SUM(K19:K21)
A23: Convertible Preferred Stock | B23: 843 | C23: 819 | D23: 798 | E23: 777
A24: Common Stock | B24: 4009 | C24: 4009 | D24: 4009 | E24: 4009
A25: Additional Paid-in Capital | B25: 65795 | C25: 66556 | D25: 67684 | E25: 68770
A26: ESOP Debt Retirement Reserve | B26: -916 | C26: -821 | D26: -737 | E26: -672
A27: Accumulated Other Comprehensive Income (Loss) | B27: -12189 | C27: -12220 | D27: -11900 | E27: -12143
A28: Treasury Stock | B28: -123382 | C28: -129736 | D28: -133379 | E28: -138702
A29: Retained Earnings (Accumulated Deficit) | B29: 112429 | C29: 118170 | D29: 123811 | E29: 129973
A30: Noncontrolling Interest | B30: 265 | C30: 288 | D30: 272 | E30: 272
A31: Total Stockholders' Equity | B31: =SUM(B23:B30) | C31: =SUM(C23:C30) | D31: =SUM(D23:D30) | E31: =SUM(E23:E30) | F31: =SUM(F23:F30) | G31: =SUM(G23:G30) | H31: =SUM(H23:H30) | I31: =SUM(I23:I30) | ... K31: =SUM(K23:K30)
A32: Total Liabilities, Mezzanine & Stockholders' Equity | B32: =B22+B31 | C32: =C22+C31 | D32: =D22+D31 | E32: =E22+E31 | F32: =F22+F31 | G32: =G22+G31 | H32: =H22+H31 | I32: =I22+I31 | ... K32: =K22+K31

Sheet CASH FLOW
B1: FY2021 | C1: FY2022 | D1: FY2023 | E1: FY2024 | F1: FY2025 | G1: FY2026E | H1: FY2027E | I1: FY2028E | J1: FY2029E | K1: FY2030E | L1: FY2031E
A2: Net Income (Loss) | B2: 14352 | C2: 14793 | D2: 14738 | E2: 14974 | F2: 16065
A3: Depreciation & Amortization | B3: 2735 | C3: 2807 | D3: 2714 | E3: 2896 | F3: 2847
A4: Gain (Loss) on Extinguishment of Debt | B4: 512 | C4: 0 | D4: 0 | E4: 0 | F4: 0
A5: Stock-Based Compensation | B5: 540 | C5: 528 | D5: 545 | E5: 562 | F5: 476
A6: (Benefit) Provision for Deferred Income Taxes | B6: -258 | C6: -402 | D6: -453 | E6: -244 | F6: 149
A7: Gain (Loss) on Disposal of PP&E | B7: -16 | C7: -85 | D7: -40 | E7: -215 | F7: 755
A8: Impairment of Intangibles | B8: 0 | C8: 0 | D8: 0 | E8: 1341 | F8: 0
A9: Accounts Receivable | B9: -342 | C9: -694 | D9: -307 | E9: -766 | F9: 45
A10: Inventories | B10: -309 | C10: -1247 | D10: -119 | E10: -70 | F10: -324
A11: Accounts Payable | B11: 1391 | C11: 1429 | D11: 313 | E11: 1814 | F11: -542
A12: Net Change in Other Working Capital | B12: -369 | C12: -635 | D12: -1107 | E12: -1414 | F12: 0
A13: Other Operating Items | B13: 135 | C13: 229 | D13: 564 | E13: 969 | F13: -1653
A14: Cash Flow from Operations | B14: =SUM(B2:B13) | C14: =SUM(C2:C13) | D14: =SUM(D2:D13) | E14: =SUM(E2:E13) | F14: =SUM(F2:F13) | G14: =SUM(G2:G13) | H14: =SUM(H2:H13) | I14: =SUM(I2:I13) | ... L14: =SUM(L2:L13)
A15: Purchase of PP&E | B15: -2787 | C15: -3156 | D15: -3062 | E15: -3322 | F15: -3773
A16: Proceeds from Sale of Assets | B16: 42 | C16: 110 | D16: 46 | E16: 346 | F16: 107
A17: Acquisitions, Net of Cash Acquired | B17: -34 | C17: -1381 | D17: -765 | E17: -21 | F17: -11
A18: Other Investing Activities | B18: -55 | C18: 3 | D18: 281 | E18: -507 | F18: -141
A19: Cash Flow from Investing | B19: =SUM(B15:B18) | C19: =SUM(C15:C18) | D19: =SUM(D15:D18) | E19: =SUM(E15:E18) | F19: =SUM(F15:F18) | G19: =SUM(G15:G18) | H19: =SUM(H15:H18) | I19: =SUM(I15:I18) | ... L19: =SUM(L15:L18)
A20: Common Dividends | B20: -8263 | C20: -8770 | D20: -8999 | E20: -9312 | F20: -9872
A21: Proceeds from Short-Term Debt | B21: 7675 | C21: 10411 | D21: 17168 | E21: 3528 | F21: 8020
A22: Repayments of Short-Term Debt | B22: -7577 | C22: -11478 | D22: -13031 | E22: -7689 | F22: -6512
A23: Net Change in Other Short-Term Debt | B23: -3431 | C23: 917 | D23: -3319 | E23: 857 | F23: -1138
A24: Proceeds from Issuance of Long-Term Debt | B24: 4417 | C24: 4385 | D24: 3997 | E24: 3197 | F24: 2237
A25: Repayments of Long-Term Debt | B25: -4987 | C25: -2343 | D25: -1878 | E25: -2335 | F25: -1977
A26: Share Repurchases | B26: -11009 | C26: -10003 | D26: -7353 | E26: -5006 | F26: -6500
A27: Stock Options & Other Financing Activities | B27: 1644 | C27: 2005 | D27: 1269 | E27: 1905 | F27: 1707
A28: Cash Flow from Financing | B28: =SUM(B20:B27) | C28: =SUM(C20:C27) | D28: =SUM(D20:D27) | E28: =SUM(E20:E27) | F28: =SUM(F20:F27) | G28: =SUM(G20:G27) | H28: =SUM(H20:H27) | I28: =SUM(I20:I27) | ... L28: =SUM(L20:L27)
A29: FX Effect on Cash | B29: 101 | C29: -497 | D29: -170 | E29: -251 | F29: 112
A30: Net Change in Cash | B30: =B14+B19+B28+B29 | C30: =C14+C19+C28+C29 | D30: =D14+D19+D28+D29 | E30: =E14+E19+E28+E29 | F30: =F14+F19+F28+F29 | G30: =G14+G19+G28+G29 | H30: =H14+H19+H28+H29 | I30: =I14+I19+I28+I29 | ... L30: =L14+L19+L28+L29

Sheet YTD P&L
B1: Q1 FY2022 | C1: Q2 FY2022 | D1: Q3 FY2022 | E1: Q1 FY2023 | F1: Q2 FY2023 | G1: Q3 FY2023 | H1: Q1 FY2024 | I1: Q2 FY2024 | J1: Q3 FY2024 | K1: Q1 FY2025 | L1: Q2 FY2025 | M1: Q3 FY2025 | N1: Q1 FY2026 | O1: Q2 FY2026
A2: Net Sales / Revenue | B2: 20338 | C2: 41291 | D2: 60672 | E2: 20612 | F2: 41385 | G2: 61453 | H2: 21871 | I2: 43312 | J2: 63507 | K2: 21737 | L2: 43619 | M2: 63395 | N2: 22386 | O2: 44594
A3: COGS | B3: -10365 | C3: -21029 | D3: -31355 | E3: -10846 | F3: -21743 | G3: -32147 | H3: -10501 | I3: -20645 | J3: -30500 | K3: -10421 | L3: -20839 | M3: -30533 | N3: -10887 | O3: -21721
A4: Gross Profit (Loss) | B4: =B2+B3 | C4: =C2+C3 | D4: =D2+D3 | E4: =E2+E3 | F4: =F2+F3 | G4: =G2+G3 | H4: =H2+H3 | I4: =I2+I3 | ... O4: =O2+O3
A5: SG&A | B5: -4950 | C5: -10071 | D5: -15102 | E5: -4827 | F5: -9918 | G5: -15334 | H5: -5604 | I5: -11127 | J5: -17006 | K5: -5519 | L5: -11242 | M5: -16765 | N5: -5643 | O5: -11651
A6: Impairment of Intangibles | B6: 0 | C6: 0 | D6: 0 | E6: 0 | F6: 0 | G6: 0 | H6: 0 | I6: -1341 | J6: -1341 | K6: 0 | L6: 0 | M6: 0 | N6: 0 | O6: 0
A7: Income (Loss) from Operations | B7: =B4+SUM(B5:B6) | C7: =C4+SUM(C5:C6) | D7: =D4+SUM(D5:D6) | E7: =E4+SUM(E5:E6) | F7: =F4+SUM(F5:F6) | G7: =G4+SUM(G5:G6) | H7: =H4+SUM(H5:H6) | I7: =I4+SUM(I5:I6) | ... O7: =O4+SUM(O5:O6)
A8: Interest Income (Expense) | B8: -98 | C8: -194 | D8: -294 | E8: -81 | F8: -186 | G8: -325 | H8: -97 | I8: -210 | J8: -339 | K8: -103 | L8: -224 | M8: -330 | N8: -89 | O8: -195
A9: Other Income (Expense) | B9: 110 | C9: 277 | D9: 424 | E9: 139 | F9: 294 | G9: 473 | H9: 132 | I9: 309 | J9: 570 | K9: -554 | L9: -330 | M9: -120 | N9: 268 | O9: 427
A10: Pre-Tax Income (Loss) | B10: =B7+SUM(B8:B9) | C10: =C7+SUM(C8:C9) | D10: =D7+SUM(D8:D9) | E10: =E7+SUM(E8:E9) | F10: =F7+SUM(F8:F9) | G10: =G7+SUM(G8:G9) | H10: =H7+SUM(H8:H9) | I10: =I7+SUM(I8:I9) | ... O10: =O7+SUM(O8:O9)
A11: Income Tax (Expense) Benefit | B11: -909 | C11: -1906 | D11: -2610 | E11: -1034 | F11: -1910 | G11: -2774 | H11: -1246 | I11: -2250 | J11: -3061 | K11: -1152 | L11: -2339 | M11: -3207 | N11: -1253 | O11: -2343
A12: Net Income (Loss) | B12: =B10+B11 | C12: =C10+C11 | D12: =D10+D11 | E12: =E10+E11 | F12: =F10+F11 | G12: =G10+G11 | H12: =H10+H11 | I12: =I10+I11 | ... O12: =O10+O11
A13: Net Income (Loss) Attributable to Noncontrolling Interest | B13: 14 | C13: 33 | D13: 45 | E13: 24 | F13: 50 | G13: 77 | H13: 35 | I13: 60 | J13: 88 | K13: 28 | L13: 56 | M13: 80 | N13: 31 | O13: 42
A14: Net Income (Loss) Less NCI | B14: =B12-B13 | C14: =C12-C13 | D14: =D12-D13 | E14: =E12-E13 | F14: =F12-F13 | G14: =G12-G13 | H14: =H12-H13 | I14: =I12-I13 | ... O14: =O12-O13
A15: Basic Earnings (Loss) per Share | B15: 1.66 | C15: 3.39 | D15: 4.76 | E15: 1.62 | F15: 3.25 | G15: 4.67 | H15: 1.89 | I15: 3.33 | J15: 4.89 | K15: 1.65 | L15: 3.59 | M15: 5.16 | N15: 2 | O15: 3.82
A16: Diluted Earnings (Loss) per Share | B16: 1.61 | C16: 3.27 | D16: 4.59 | E16: 1.57 | F16: 3.16 | G16: 4.53 | H16: 1.83 | I16: 3.23 | J16: 4.75 | K16: 1.61 | L16: 3.49 | M16: 5.03 | N16: 1.95 | O16: 3.73
A17: Weighted Average Shares Outstanding (Basic) | B17: 2558900000 | C17: 2551600000 | D17: 2544400000 | E17: 2503600000 | F17: 2492400000 | G17: 2486000000 | H17: 0 | I17: 0 | J17: 0 | K17: 0 | L17: 0 | M17: 0 | N17: 0 | O17: 0

Sheet YTD BS
B1: Q4 FY2022 | C1: Q1 FY2023 | D1: Q2 FY2023 | E1: Q3 FY2023 | F1: Q4 FY2023 | G1: Q1 FY2024 | H1: Q2 FY2024 | I1: Q3 FY2024 | J1: Q4 FY2024 | K1: Q1 FY2025 | L1: Q2 FY2025 | M1: Q3 FY2025 | N1: Q4 FY2025 | O1: Q1 FY2026 | P1: Q2 FY2026
A2: Cash & Cash Equivalents | B2: 7214 | C2: 6710 | D2: 6854 | E2: 7596 | F2: 8246 | G2: 9733 | H2: 7890 | I2: 6828 | J2: 9482 | K2: 12156 | L2: 10230 | M2: 9116 | N2: 9556 | O2: 11171 | P2: 10825
A3: Accounts Receivable | B3: 5143 | C3: 5720 | D3: 5767 | E3: 5471 | F3: 5471 | G3: 6215 | H3: 6334 | I3: 6124 | J3: 6118 | K3: 6314 | L3: 6234 | M3: 6139 | N3: 6185 | O3: 6487 | P3: 6279
A4: Raw Materials | B4: 2168 | C4: 2235 | D4: 2232 | E4: 2010 | F4: 1863 | G4: 1759 | H4: 1780 | I4: 1676 | J4: 1617 | K4: 1820 | L4: 1949 | M4: 1935 | N4: 2022 | O4: 2072 | P4: 2139
A5: Work in Process | B5: 856 | C5: 898 | D5: 946 | E5: 966 | F5: 956 | G5: 972 | H5: 962 | I5: 971 | J5: 929 | K5: 921 | L5: 879 | M5: 957 | N5: 1012 | O5: 1041 | P5: 1007
A6: Finished Goods | B6: 3900 | C6: 4457 | D6: 4363 | E6: 4507 | F6: 4254 | G6: 4386 | H6: 4410 | I6: 4431 | J6: 4470 | K6: 4546 | L6: 4192 | M6: 4508 | N6: 4516 | O6: 4735 | P6: 4672
A7: Inventories | B7: =SUM(B4,B5,B6) | C7: =SUM(C4,C5,C6) | D7: =SUM(D4,D5,D6) | E7: =SUM(E4,E5,E6) | F7: =SUM(F4,F5,F6) | G7: =SUM(G4,G5,G6) | H7: =SUM(H4,H5,H6) | I7: =SUM(I4,I5,I6) | ... P7: =SUM(P4,P5,P6)
A8: Prepaid Expenses | B8: 2372 | C8: 2501 | D8: 1704 | E8: 1755 | F8: 1858 | G8: 1875 | H8: 1736 | I8: 2428 | J8: 2095 | K8: 1692 | L8: 2158 | M8: 1780 | N8: 2100 | O8: 1612 | P8: 1666
A9: Total Current Assets | B9: =SUM(B2:B8) | C9: =SUM(C2:C8) | D9: =SUM(D2:D8) | E9: =SUM(E2:E8) | F9: =SUM(F2:F8) | G9: =SUM(G2:G8) | H9: =SUM(H2:H8) | I9: =SUM(I2:I8) | ... P9: =SUM(P2:P8)
A10: Net PP&E | B10: 21195 | C10: 20593 | D10: 21167 | E10: 21564 | F10: 21909 | G10: 21636 | H10: 22132 | I10: 22027 | J10: 22152 | K10: 22506 | L10: 22074 | M10: 22728 | N10: 23897 | O10: 24119 | P10: 24487
A11: Goodwill | B11: 39700 | C11: 38761 | D11: 39951 | E11: 40718 | F11: 40659 | G11: 40239 | H11: 40916 | I11: 40567 | J11: 40303 | K11: 40970 | L11: 39898 | M11: 40476 | N11: 41650 | O11: 41643 | P11: 41665
A12: Intangible Assets | B12: 23679 | C12: 23465 | D12: 23594 | E12: 23832 | F12: 23783 | G12: 23637 | H12: 22302 | I12: 22193 | J12: 22047 | K12: 22053 | L12: 21833 | M12: 21836 | N12: 21910 | O12: 21818 | P12: 21737
A13: Other Non-Current Assets | B13: 10981 | C13: 10942 | D13: 11137 | E13: 11432 | F13: 11830 | G13: 12079 | H13: 12248 | I13: 12353 | J13: 13158 | K13: 13503 | L13: 13192 | M13: 13508 | N13: 12381 | O13: 12901 | P13: 12809
A14: Total Assets | B14: =B9+SUM(B10:B13) | C14: =C9+SUM(C10:C13) | D14: =D9+SUM(D10:D13) | E14: =E9+SUM(E10:E13) | F14: =F9+SUM(F10:F13) | G14: =G9+SUM(G10:G13) | H14: =H9+SUM(H10:H13) | I14: =I9+SUM(I10:I13) | ... P14: =P9+SUM(P10:P13)
A15: Accounts Payable | B15: 14882 | C15: 14845 | D15: 14153 | E15: 13790 | F15: 14598 | G15: 14435 | H15: 14234 | I15: 13691 | J15: 15364 | K15: 15350 | L15: 14495 | M15: 14512 | N15: 15227 | O15: 15609 | P15: 15173
A16: Accrued Expenses | B16: 9554 | C16: 10056 | D16: 10293 | E16: 10523 | F16: 10929 | G16: 10912 | H16: 11100 | I16: 10921 | J16: 11073 | K16: 10661 | L16: 9879 | M16: 9847 | N16: 11318 | O16: 10756 | P16: 10463
A17: Current Portion of Long-Term Debt | B17: 8645 | C17: 11717 | D17: 14300 | E17: 13717 | F17: 10229 | G17: 11811 | H17: 10616 | I17: 7729 | J17: 7191 | K17: 10409 | L17: 9424 | M17: 9889 | N17: 9513 | O17: 11631 | P17: 11062
A18: Total Current Liabilities | B18: =SUM(B15:B17) | C18: =SUM(C15:C17) | D18: =SUM(D15:D17) | E18: =SUM(E15:E17) | F18: =SUM(F15:F17) | G18: =SUM(G15:G17) | H18: =SUM(H15:H17) | I18: =SUM(I15:I17) | ... P18: =SUM(P15:P17)
A19: Long-Term Debt | B19: 22848 | C19: 21286 | D19: 20582 | E19: 22874 | F19: 24378 | G19: 24069 | H19: 23096 | I19: 24253 | J19: 25269 | K19: 25744 | L19: 25263 | M19: 24252 | N19: 24995 | O19: 24315 | P19: 25577
A20: Deferred Tax Liability | B20: 6809 | C20: 6986 | D20: 6462 | E20: 6422 | F20: 6478 | G20: 6814 | H20: 6219 | I20: 6284 | J20: 6516 | K20: 6420 | L20: 6725 | M20: 6481 | N20: 5774 | O20: 5893 | P20: 5974
A21: Other Non-Current Liabilities | B21: 7616 | C21: 7058 | D21: 7200 | E21: 7104 | F21: 7152 | G21: 6477 | H21: 6614 | I21: 6386 | J21: 6398 | K21: 5757 | L21: 5411 | M21: 5458 | N21: 6120 | O21: 5844 | P21: 5719
A22: Total Liabilities | B22: =B18+SUM(B19:B21) | C22: =C18+SUM(C19:C21) | D22: =D18+SUM(D19:D21) | E22: =E18+SUM(E19:E21) | F22: =F18+SUM(F19:F21) | G22: =G18+SUM(G19:G21) | H22: =H18+SUM(H19:H21) | I22: =I18+SUM(I19:I21) | ... P22: =P18+SUM(P19:P21)
A23: Convertible Preferred Stock | B23: 843 | C23: 834 | D23: 831 | E23: 822 | F23: 819 | G23: 812 | H23: 809 | I23: 801 | J23: 798 | K23: 791 | L23: 788 | M23: 781 | N23: 777 | O23: 770 | P23: 767
A24: Common Stock | B24: 4009 | C24: 4009 | D24: 4009 | E24: 4009 | F24: 4009 | G24: 4009 | H24: 4009 | I24: 4009 | J24: 4009 | K24: 4009 | L24: 4009 | M24: 4009 | N24: 4009 | O24: 4009 | P24: 4009
A25: Additional Paid-in Capital | B25: 65795 | C25: 65955 | D25: 66145 | E25: 66316 | F25: 66556 | G25: 66822 | H25: 66935 | I25: 67395 | J25: 67684 | K25: 68102 | L25: 68283 | M25: 68615 | N25: 68770 | O25: 68917 | P25: 69010
A26: ESOP Debt Retirement Reserve | B26: -916 | C26: -870 | D26: -870 | E26: -821 | F26: -821 | G26: -782 | H26: -782 | I26: -737 | J26: -737 | K26: -707 | L26: -707 | M26: -672 | N26: -672 | O26: -637 | P26: -637
A27: Accumulated Other Comprehensive Income (Loss) | B27: -12189 | C27: -12811 | D27: -12506 | E27: -12266 | F27: -12220 | G27: -12583 | H27: -12167 | I27: -12370 | J27: -11900 | K27: -10893 | L27: -11637 | M27: -11307 | N27: -12143 | O27: -12156 | P27: -12108
A28: Treasury Stock | B28: -123382 | C28: -127205 | D28: -129012 | E28: -130002 | F28: -129736 | G28: -131029 | H28: -131887 | I28: -132172 | J28: -133379 | K28: -134823 | L28: -137112 | M28: -138073 | N28: -138702 | O28: -139845 | P28: -141981
A29: Retained Earnings (Accumulated Deficit) | B29: 112429 | C29: 114163 | D29: 115858 | E29: 117082 | F29: 118170 | G29: 120443 | H29: 121617 | I29: 123132 | J29: 123811 | K29: 125361 | L29: 127544 | M29: 128919 | N29: 129973 | O29: 132212 | P29: 133981
A30: Noncontrolling Interest | B30: 265 | C30: 259 | D30: 270 | E30: 281 | F30: 288 | G30: 321 | H30: 294 | I30: 275 | J30: 272 | K30: 300 | L30: 275 | M30: 273 | N30: 272 | O30: 281 | P30: 276
A31: Total Stockholders' Equity | B31: =SUM(B23:B30) | C31: =SUM(C23:C30) | D31: =SUM(D23:D30) | E31: =SUM(E23:E30) | F31: =SUM(F23:F30) | G31: =SUM(G23:G30) | H31: =SUM(H23:H30) | I31: =SUM(I23:I30) | ... P31: =SUM(P23:P30)
A32: Total Liabilities, Mezzanine & Stockholders' Equity | B32: =B22+B31 | C32: =C22+C31 | D32: =D22+D31 | E32: =E22+E31 | F32: =F22+F31 | G32: =G22+G31 | H32: =H22+H31 | I32: =I22+I31 | ... P32: =P22+P31

Sheet YTD CF
B1: Q1 FY2022 | C1: Q2 FY2022 | D1: Q3 FY2022 | E1: Q1 FY2023 | F1: Q2 FY2023 | G1: Q3 FY2023 | H1: Q1 FY2024 | I1: Q2 FY2024 | J1: Q3 FY2024 | K1: Q1 FY2025 | L1: Q2 FY2025 | M1: Q3 FY2025 | N1: Q1 FY2026 | O1: Q2 FY2026
A2: Net Income (Loss) | B2: 4126 | C2: 8368 | D2: 11735 | E2: 3963 | F2: 7922 | G2: 11346 | H2: 4556 | I2: 8049 | J2: 11830 | K2: 3987 | L2: 8646 | M2: 12439 | N2: 4781 | O2: 9112
A3: Depreciation & Amortization | B3: 711 | C3: 1395 | D3: 2085 | E3: 663 | F3: 1316 | G3: 2008 | H3: 702 | I3: 1423 | J3: 2135 | K3: 728 | L3: 1434 | M3: 2124 | N3: 761 | O3: 1563
A4: Gain (Loss) on Extinguishment of Debt | B4: 0 | C4: 0 | D4: 0 | E4: 0 | F4: 0 | G4: 0 | H4: 0 | I4: 0 | J4: 0 | K4: 0 | L4: 0 | M4: 0 | N4: 0 | O4: 0
A5: Stock-Based Compensation | B5: 116 | C5: 268 | D5: 398 | E5: 105 | F5: 250 | G5: 406 | H5: 125 | I5: 275 | J5: 433 | K5: 105 | L5: 241 | M5: 364 | N5: 121 | O5: 262
A6: (Benefit) Provision for Deferred Income Taxes | B6: 57 | C6: -101 | D6: -259 | E6: -130 | F6: -398 | G6: -360 | H6: 102 | I6: -154 | J6: -206 | K6: 184 | L6: 221 | M6: 183 | N6: 53 | O6: 196
A7: Gain (Loss) on Disposal of PP&E | B7: -73 | C7: -82 | D7: -84 | E7: -1 | F7: -3 | G7: -4 | H7: -3 | I7: -3 | J7: -51 | K7: 794 | L7: 787 | M7: 782 | N7: -3 | O7: 1
A8: Impairment of Intangibles | B8: 0 | C8: 0 | D8: 0 | E8: 0 | F8: 0 | G8: 0 | H8: 0 | I8: 1341 | J8: 1341 | K8: 0 | L8: 0 | M8: 0 | N8: 0 | O8: 0
A9: Accounts Receivable | B9: -1012 | C9: -644 | D9: -916 | E9: -740 | F9: -654 | G9: -301 | H9: -830 | I9: -839 | J9: -692 | K9: -134 | L9: -262 | M9: -79 | N9: -305 | O9: -92
A10: Inventories | B10: -409 | C10: -840 | D10: -1252 | E10: -893 | F10: -655 | G10: -503 | H10: -142 | I10: -32 | J10: -47 | K10: -188 | L10: -170 | M10: -409 | N10: -303 | O10: -255
A11: Accounts Payable | B11: 1261 | C11: 1431 | D11: 1347 | E11: 1495 | F11: 177 | G11: -609 | H11: 857 | I11: 302 | J11: 56 | K11: -648 | L11: -1157 | M11: -1666 | N11: 648 | O11: 239
A12: Net Change in Other Working Capital | B12: -178 | C12: -84 | D12: -131 | E12: -454 | F12: -535 | G12: -839 | H12: -671 | I12: -704 | J12: -1196 | K12: -558 | L12: -748 | M12: -1125 | N12: 0 | O12: 0
A13: Other Operating Items | B13: 44 | C13: 53 | D13: 87 | E13: 62 | F13: 224 | G13: 363 | H13: 208 | I13: 346 | J13: 490 | K13: 32 | L13: 135 | M13: 218 | N13: -344 | O13: -645
A14: Cash Flow from Operations | B14: =SUM(B2:B13) | C14: =SUM(C2:C13) | D14: =SUM(D2:D13) | E14: =SUM(E2:E13) | F14: =SUM(F2:F13) | G14: =SUM(G2:G13) | H14: =SUM(H2:H13) | I14: =SUM(I2:I13) | ... O14: =SUM(O2:O13)
A15: Purchase of PP&E | B15: -1091 | C15: -1717 | D15: -2464 | E15: -890 | F15: -1598 | G15: -2328 | H15: -925 | I15: -1742 | J15: -2539 | K15: -993 | L15: -1918 | M15: -2777 | N15: -1200 | O15: -2367
A16: Proceeds from Sale of Assets | B16: 85 | C16: 97 | D16: 99 | E16: 5 | F16: 8 | G16: 9 | H16: 3 | I16: 8 | J16: 77 | K16: 45 | L16: 47 | M16: 64 | N16: 8 | O16: 16
A17: Acquisitions, Net of Cash Acquired | B17: 0 | C17: -349 | D17: -1381 | E17: -2 | F17: -76 | G17: -714 | H17: 0 | I17: 0 | J17: -21 | K17: -6 | L17: -6 | M17: -11 | N17: -5 | O17: -5
A18: Net Change in Short-Term Investments | B18: 0 | C18: 0 | D18: 0 | E18: 55 | F18: 0 | G18: 0 | H18: 0 | I18: 0 | J18: 0 | K18: 0 | L18: 0 | M18: 0 | N18: 0 | O18: 0
A19: Other Investing Activities | B19: 0 | C19: 3 | D19: 4 | E19: 0 | F19: 344 | G19: 331 | H19: -300 | I19: -489 | J19: -503 | K19: -154 | L19: -153 | M19: -33 | N19: -338 | O19: -408
A20: Cash Flow from Investing | B20: =SUM(B15:B19) | C20: =SUM(C15:C19) | D20: =SUM(D15:D19) | E20: =SUM(E15:E19) | F20: =SUM(F15:F19) | G20: =SUM(G15:G19) | H20: =SUM(H15:H19) | I20: =SUM(I15:I19) | ... O20: =SUM(O15:O19)
A21: Common Dividends | B21: -2182 | C21: -4353 | D21: -6508 | E21: -2255 | F21: -4486 | G21: -6710 | H21: -2290 | I21: -4578 | J21: -6863 | K21: -2445 | L21: -4886 | M21: -7319 | N21: -2549 | O21: -5093
A22: Proceeds from Short-Term Debt | B22: 1792 | C22: 6747 | D22: 10146 | E22: 2975 | F22: 10447 | G22: 13778 | H22: 2179 | I22: 2798 | J22: 2961 | K22: 4090 | L22: 5905 | M22: 5905 | N22: 1123 | O22: 4180
A23: Repayments of Short-Term Debt | B23: -1422 | C23: -1730 | D23: -8163 | E23: -265 | F23: -3260 | G23: -9134 | H23: -1906 | I23: -5862 | J23: -7523 | K23: -571 | L23: -571 | M23: -3781 | N23: -1800 | O23: -3270
A24: Net Change in Other Short-Term Debt | B24: 512 | C24: -1124 | D24: -849 | E24: 1727 | F24: -1759 | G24: -387 | H24: 2172 | I24: 3740 | J24: 2331 | K24: -444 | L24: -2705 | M24: -543 | N24: 2108 | O24: -471
A25: Proceeds from Issuance of Long-Term Debt | B25: 0 | C25: 2136 | D25: 4385 | E25: 0 | F25: 0 | G25: 2569 | H25: 0 | I25: 254 | J25: 1598 | K25: 0 | L25: 995 | M25: 995 | N25: 0 | O25: 2652
A26: Repayments of Long-Term Debt | B26: -26 | C26: -1673 | D26: -2776 | E26: -1877 | F26: -1877 | G26: -1877 | H26: -1004 | I26: -2335 | J26: -2335 | K26: -70 | L26: -1478 | M26: -1478 | N26: -3 | O26: -1005
A27: Share Repurchases | B27: -2750 | C27: -7504 | D27: -8753 | E27: -4000 | F27: -6002 | G27: -7353 | H27: -1500 | I27: -2503 | J27: -3490 | K27: -1939 | L27: -4449 | M27: -5800 | N27: -1250 | O27: -3528
A28: Stock Options & Other Financing Activities | B28: 648 | C28: 1215 | D28: 1800 | E28: 188 | F28: 437 | G28: 861 | H28: 312 | I28: 397 | J28: 965 | K28: 745 | L28: 985 | M28: 1601 | N28: 134 | O28: 208
A29: Cash Flow from Financing | B29: =SUM(B21:B28) | C29: =SUM(C21:C28) | D29: =SUM(D21:D28) | E29: =SUM(E21:E28) | F29: =SUM(F21:F28) | G29: =SUM(G21:G28) | H29: =SUM(H21:H28) | I29: =SUM(I21:I28) | ... O29: =SUM(O21:O28)
A30: FX Effect on Cash | B30: -127 | C30: -256 | D30: -312 | E30: -235 | F30: -182 | G30: -170 | H30: -156 | I30: -49 | J30: -168 | K30: 116 | L30: -144 | M30: -22 | N30: -20 | O30: -21
A31: Net Change in Cash | B31: =B14+B20+B29+B30 | C31: =C14+C20+C29+C30 | D31: =D14+D20+D29+D30 | E31: =E14+E20+E29+E30 | F31: =F14+F20+F29+F30 | G31: =G14+G20+G29+G30 | H31: =H14+H20+H29+H30 | I31: =I14+I20+I29+I30 | ... O31: =O14+O20+O29+O30

Sheet QTR P&L
B1: Q1 FY2022 | C1: Q2 FY2022 | D1: Q3 FY2022 | E1: Q4 FY2022 | F1: Q1 FY2023 | G1: Q2 FY2023 | H1: Q3 FY2023 | I1: Q4 FY2023 | J1: Q1 FY2024 | K1: Q2 FY2024 | L1: Q3 FY2024 | M1: Q4 FY2024 | N1: Q1 FY2025 | O1: Q2 FY2025 | P1: Q3 FY2025 | Q1: Q4 FY2025 | R1: Q1 FY2026 | S1: Q2 FY2026
A2: Net Sales / Revenue | B2: ='YTD P&L'!B2 | C2: ='YTD P&L'!C2-'YTD P&L'!B2 | D2: ='YTD P&L'!D2-'YTD P&L'!C2 | E2: ='ANNL P&L'!C2-'YTD P&L'!D2 | F2: ='YTD P&L'!E2 | G2: ='YTD P&L'!F2-'YTD P&L'!E2 | H2: ='YTD P&L'!G2-'YTD P&L'!F2 | I2: ='ANNL P&L'!D2-'YTD P&L'!G2 | J2: ='YTD P&L'!H2 | K2: ='YTD P&L'!I2-'YTD P&L'!H2 | L2: ='YTD P&L'!J2-'YTD P&L'!I2 | M2: ='ANNL P&L'!E2-'YTD P&L'!J2 | N2: ='YTD P&L'!K2 | O2: ='YTD P&L'!L2-'YTD P&L'!K2 | P2: ='YTD P&L'!M2-'YTD P&L'!L2 | Q2: ='ANNL P&L'!F2-'YTD P&L'!M2 | R2: ='YTD P&L'!N2 | S2: ='YTD P&L'!O2-'YTD P&L'!N2
A3: COGS | B3: ='YTD P&L'!B3 | C3: ='YTD P&L'!C3-'YTD P&L'!B3 | D3: ='YTD P&L'!D3-'YTD P&L'!C3 | E3: ='ANNL P&L'!C3-'YTD P&L'!D3 | F3: ='YTD P&L'!E3 | G3: ='YTD P&L'!F3-'YTD P&L'!E3 | H3: ='YTD P&L'!G3-'YTD P&L'!F3 | I3: ='ANNL P&L'!D3-'YTD P&L'!G3 | J3: ='YTD P&L'!H3 | K3: ='YTD P&L'!I3-'YTD P&L'!H3 | L3: ='YTD P&L'!J3-'YTD P&L'!I3 | M3: ='ANNL P&L'!E3-'YTD P&L'!J3 | N3: ='YTD P&L'!K3 | O3: ='YTD P&L'!L3-'YTD P&L'!K3 | P3: ='YTD P&L'!M3-'YTD P&L'!L3 | Q3: ='ANNL P&L'!F3-'YTD P&L'!M3 | R3: ='YTD P&L'!N3 | S3: ='YTD P&L'!O3-'YTD P&L'!N3
A4: Gross Profit (Loss) | B4: ='YTD P&L'!B4 | C4: ='YTD P&L'!C4-'YTD P&L'!B4 | D4: ='YTD P&L'!D4-'YTD P&L'!C4 | E4: ='ANNL P&L'!C4-'YTD P&L'!D4 | F4: ='YTD P&L'!E4 | G4: ='YTD P&L'!F4-'YTD P&L'!E4 | H4: ='YTD P&L'!G4-'YTD P&L'!F4 | I4: ='ANNL P&L'!D4-'YTD P&L'!G4 | J4: ='YTD P&L'!H4 | K4: ='YTD P&L'!I4-'YTD P&L'!H4 | L4: ='YTD P&L'!J4-'YTD P&L'!I4 | M4: ='ANNL P&L'!E4-'YTD P&L'!J4 | N4: ='YTD P&L'!K4 | O4: ='YTD P&L'!L4-'YTD P&L'!K4 | P4: ='YTD P&L'!M4-'YTD P&L'!L4 | Q4: ='ANNL P&L'!F4-'YTD P&L'!M4 | R4: ='YTD P&L'!N4 | S4: ='YTD P&L'!O4-'YTD P&L'!N4
A5: SG&A | B5: ='YTD P&L'!B5 | C5: ='YTD P&L'!C5-'YTD P&L'!B5 | D5: ='YTD P&L'!D5-'YTD P&L'!C5 | E5: ='ANNL P&L'!C5-'YTD P&L'!D5 | F5: ='YTD P&L'!E5 | G5: ='YTD P&L'!F5-'YTD P&L'!E5 | H5: ='YTD P&L'!G5-'YTD P&L'!F5 | I5: ='ANNL P&L'!D5-'YTD P&L'!G5 | J5: ='YTD P&L'!H5 | K5: ='YTD P&L'!I5-'YTD P&L'!H5 | L5: ='YTD P&L'!J5-'YTD P&L'!I5 | M5: ='ANNL P&L'!E5-'YTD P&L'!J5 | N5: ='YTD P&L'!K5 | O5: ='YTD P&L'!L5-'YTD P&L'!K5 | P5: ='YTD P&L'!M5-'YTD P&L'!L5 | Q5: ='ANNL P&L'!F5-'YTD P&L'!M5 | R5: ='YTD P&L'!N5 | S5: ='YTD P&L'!O5-'YTD P&L'!N5
A6: Impairment of Intangibles | B6: ='YTD P&L'!B6 | C6: ='YTD P&L'!C6-'YTD P&L'!B6 | D6: ='YTD P&L'!D6-'YTD P&L'!C6 | E6: ='ANNL P&L'!C6-'YTD P&L'!D6 | F6: ='YTD P&L'!E6 | G6: ='YTD P&L'!F6-'YTD P&L'!E6 | H6: ='YTD P&L'!G6-'YTD P&L'!F6 | I6: ='ANNL P&L'!D6-'YTD P&L'!G6 | J6: ='YTD P&L'!H6 | K6: ='YTD P&L'!I6-'YTD P&L'!H6 | L6: ='YTD P&L'!J6-'YTD P&L'!I6 | M6: ='ANNL P&L'!E6-'YTD P&L'!J6 | N6: ='YTD P&L'!K6 | O6: ='YTD P&L'!L6-'YTD P&L'!K6 | P6: ='YTD P&L'!M6-'YTD P&L'!L6 | Q6: ='ANNL P&L'!F6-'YTD P&L'!M6 | R6: ='YTD P&L'!N6 | S6: ='YTD P&L'!O6-'YTD P&L'!N6
A7: Income (Loss) from Operations | B7: ='YTD P&L'!B7 | C7: ='YTD P&L'!C7-'YTD P&L'!B7 | D7: ='YTD P&L'!D7-'YTD P&L'!C7 | E7: ='ANNL P&L'!C7-'YTD P&L'!D7 | F7: ='YTD P&L'!E7 | G7: ='YTD P&L'!F7-'YTD P&L'!E7 | H7: ='YTD P&L'!G7-'YTD P&L'!F7 | I7: ='ANNL P&L'!D7-'YTD P&L'!G7 | J7: ='YTD P&L'!H7 | K7: ='YTD P&L'!I7-'YTD P&L'!H7 | L7: ='YTD P&L'!J7-'YTD P&L'!I7 | M7: ='ANNL P&L'!E7-'YTD P&L'!J7 | N7: ='YTD P&L'!K7 | O7: ='YTD P&L'!L7-'YTD P&L'!K7 | P7: ='YTD P&L'!M7-'YTD P&L'!L7 | Q7: ='ANNL P&L'!F7-'YTD P&L'!M7 | R7: ='YTD P&L'!N7 | S7: ='YTD P&L'!O7-'YTD P&L'!N7
A8: Interest Income (Expense) | B8: ='YTD P&L'!B8 | C8: ='YTD P&L'!C8-'YTD P&L'!B8 | D8: ='YTD P&L'!D8-'YTD P&L'!C8 | E8: ='ANNL P&L'!C8-'YTD P&L'!D8 | F8: ='YTD P&L'!E8 | G8: ='YTD P&L'!F8-'YTD P&L'!E8 | H8: ='YTD P&L'!G8-'YTD P&L'!F8 | I8: ='ANNL P&L'!D8-'YTD P&L'!G8 | J8: ='YTD P&L'!H8 | K8: ='YTD P&L'!I8-'YTD P&L'!H8 | L8: ='YTD P&L'!J8-'YTD P&L'!I8 | M8: ='ANNL P&L'!E8-'YTD P&L'!J8 | N8: ='YTD P&L'!K8 | O8: ='YTD P&L'!L8-'YTD P&L'!K8 | P8: ='YTD P&L'!M8-'YTD P&L'!L8 | Q8: ='ANNL P&L'!F8-'YTD P&L'!M8 | R8: ='YTD P&L'!N8 | S8: ='YTD P&L'!O8-'YTD P&L'!N8
A9: Other Income (Expense) | B9: ='YTD P&L'!B9 | C9: ='YTD P&L'!C9-'YTD P&L'!B9 | D9: ='YTD P&L'!D9-'YTD P&L'!C9 | E9: ='ANNL P&L'!C9-'YTD P&L'!D9 | F9: ='YTD P&L'!E9 | G9: ='YTD P&L'!F9-'YTD P&L'!E9 | H9: ='YTD P&L'!G9-'YTD P&L'!F9 | I9: ='ANNL P&L'!D9-'YTD P&L'!G9 | J9: ='YTD P&L'!H9 | K9: ='YTD P&L'!I9-'YTD P&L'!H9 | L9: ='YTD P&L'!J9-'YTD P&L'!I9 | M9: ='ANNL P&L'!E9-'YTD P&L'!J9 | N9: ='YTD P&L'!K9 | O9: ='YTD P&L'!L9-'YTD P&L'!K9 | P9: ='YTD P&L'!M9-'YTD P&L'!L9 | Q9: ='ANNL P&L'!F9-'YTD P&L'!M9 | R9: ='YTD P&L'!N9 | S9: ='YTD P&L'!O9-'YTD P&L'!N9
A10: Pre-Tax Income (Loss) | B10: ='YTD P&L'!B10 | C10: ='YTD P&L'!C10-'YTD P&L'!B10 | D10: ='YTD P&L'!D10-'YTD P&L'!C10 | E10: ='ANNL P&L'!C10-'YTD P&L'!D10 | F10: ='YTD P&L'!E10 | G10: ='YTD P&L'!F10-'YTD P&L'!E10 | H10: ='YTD P&L'!G10-'YTD P&L'!F10 | I10: ='ANNL P&L'!D10-'YTD P&L'!G10 | J10: ='YTD P&L'!H10 | K10: ='YTD P&L'!I10-'YTD P&L'!H10 | L10: ='YTD P&L'!J10-'YTD P&L'!I10 | M10: ='ANNL P&L'!E10-'YTD P&L'!J10 | N10: ='YTD P&L'!K10 | O10: ='YTD P&L'!L10-'YTD P&L'!K10 | P10: ='YTD P&L'!M10-'YTD P&L'!L10 | Q10: ='ANNL P&L'!F10-'YTD P&L'!M10 | R10: ='YTD P&L'!N10 | S10: ='YTD P&L'!O10-'YTD P&L'!N10
A11: Income Tax (Expense) Benefit | B11: ='YTD P&L'!B11 | C11: ='YTD P&L'!C11-'YTD P&L'!B11 | D11: ='YTD P&L'!D11-'YTD P&L'!C11 | E11: ='ANNL P&L'!C11-'YTD P&L'!D11 | F11: ='YTD P&L'!E11 | G11: ='YTD P&L'!F11-'YTD P&L'!E11 | H11: ='YTD P&L'!G11-'YTD P&L'!F11 | I11: ='ANNL P&L'!D11-'YTD P&L'!G11 | J11: ='YTD P&L'!H11 | K11: ='YTD P&L'!I11-'YTD P&L'!H11 | L11: ='YTD P&L'!J11-'YTD P&L'!I11 | M11: ='ANNL P&L'!E11-'YTD P&L'!J11 | N11: ='YTD P&L'!K11 | O11: ='YTD P&L'!L11-'YTD P&L'!K11 | P11: ='YTD P&L'!M11-'YTD P&L'!L11 | Q11: ='ANNL P&L'!F11-'YTD P&L'!M11 | R11: ='YTD P&L'!N11 | S11: ='YTD P&L'!O11-'YTD P&L'!N11
A12: Net Income (Loss) | B12: ='YTD P&L'!B12 | C12: ='YTD P&L'!C12-'YTD P&L'!B12 | D12: ='YTD P&L'!D12-'YTD P&L'!C12 | E12: ='ANNL P&L'!C12-'YTD P&L'!D12 | F12: ='YTD P&L'!E12 | G12: ='YTD P&L'!F12-'YTD P&L'!E12 | H12: ='YTD P&L'!G12-'YTD P&L'!F12 | I12: ='ANNL P&L'!D12-'YTD P&L'!G12 | J12: ='YTD P&L'!H12 | K12: ='YTD P&L'!I12-'YTD P&L'!H12 | L12: ='YTD P&L'!J12-'YTD P&L'!I12 | M12: ='ANNL P&L'!E12-'YTD P&L'!J12 | N12: ='YTD P&L'!K12 | O12: ='YTD P&L'!L12-'YTD P&L'!K12 | P12: ='YTD P&L'!M12-'YTD P&L'!L12 | Q12: ='ANNL P&L'!F12-'YTD P&L'!M12 | R12: ='YTD P&L'!N12 | S12: ='YTD P&L'!O12-'YTD P&L'!N12
A13: Net Income (Loss) Attributable to Noncontrolling Interest | B13: ='YTD P&L'!B13 | C13: ='YTD P&L'!C13-'YTD P&L'!B13 | D13: ='YTD P&L'!D13-'YTD P&L'!C13 | E13: ='ANNL P&L'!C13-'YTD P&L'!D13 | F13: ='YTD P&L'!E13 | G13: ='YTD P&L'!F13-'YTD P&L'!E13 | H13: ='YTD P&L'!G13-'YTD P&L'!F13 | I13: ='ANNL P&L'!D13-'YTD P&L'!G13 | J13: ='YTD P&L'!H13 | K13: ='YTD P&L'!I13-'YTD P&L'!H13 | L13: ='YTD P&L'!J13-'YTD P&L'!I13 | M13: ='ANNL P&L'!E13-'YTD P&L'!J13 | N13: ='YTD P&L'!K13 | O13: ='YTD P&L'!L13-'YTD P&L'!K13 | P13: ='YTD P&L'!M13-'YTD P&L'!L13 | Q13: ='ANNL P&L'!F13-'YTD P&L'!M13 | R13: ='YTD P&L'!N13 | S13: ='YTD P&L'!O13-'YTD P&L'!N13
A14: Net Income (Loss) Less NCI | B14: ='YTD P&L'!B14 | C14: ='YTD P&L'!C14-'YTD P&L'!B14 | D14: ='YTD P&L'!D14-'YTD P&L'!C14 | E14: ='ANNL P&L'!C14-'YTD P&L'!D14 | F14: ='YTD P&L'!E14 | G14: ='YTD P&L'!F14-'YTD P&L'!E14 | H14: ='YTD P&L'!G14-'YTD P&L'!F14 | I14: ='ANNL P&L'!D14-'YTD P&L'!G14 | J14: ='YTD P&L'!H14 | K14: ='YTD P&L'!I14-'YTD P&L'!H14 | L14: ='YTD P&L'!J14-'YTD P&L'!I14 | M14: ='ANNL P&L'!E14-'YTD P&L'!J14 | N14: ='YTD P&L'!K14 | O14: ='YTD P&L'!L14-'YTD P&L'!K14 | P14: ='YTD P&L'!M14-'YTD P&L'!L14 | Q14: ='ANNL P&L'!F14-'YTD P&L'!M14 | R14: ='YTD P&L'!N14 | S14: ='YTD P&L'!O14-'YTD P&L'!N14
A15: Basic Earnings (Loss) per Share
A16: Diluted Earnings (Loss) per Share
A17: Weighted Average Shares Outstanding (Basic)

Sheet QTR BS
B1: Q4 FY2022 | C1: Q1 FY2023 | D1: Q2 FY2023 | E1: Q3 FY2023 | F1: Q4 FY2023 | G1: Q1 FY2024 | H1: Q2 FY2024 | I1: Q3 FY2024 | J1: Q4 FY2024 | K1: Q1 FY2025 | L1: Q2 FY2025 | M1: Q3 FY2025 | N1: Q4 FY2025 | O1: Q1 FY2026 | P1: Q2 FY2026
A2: Cash & Cash Equivalents | B2: ='BALANCE SHEET'!B2 | C2: ='YTD BS'!C2 | D2: ='YTD BS'!D2 | E2: ='YTD BS'!E2 | F2: ='BALANCE SHEET'!C2 | G2: ='YTD BS'!G2 | H2: ='YTD BS'!H2 | I2: ='YTD BS'!I2 | J2: ='BALANCE SHEET'!D2 | K2: ='YTD BS'!K2 | L2: ='YTD BS'!L2 | M2: ='YTD BS'!M2 | N2: ='BALANCE SHEET'!E2 | O2: ='YTD BS'!O2 | P2: ='YTD BS'!P2
A3: Accounts Receivable | B3: ='BALANCE SHEET'!B3 | C3: ='YTD BS'!C3 | D3: ='YTD BS'!D3 | E3: ='YTD BS'!E3 | F3: ='BALANCE SHEET'!C3 | G3: ='YTD BS'!G3 | H3: ='YTD BS'!H3 | I3: ='YTD BS'!I3 | J3: ='BALANCE SHEET'!D3 | K3: ='YTD BS'!K3 | L3: ='YTD BS'!L3 | M3: ='YTD BS'!M3 | N3: ='BALANCE SHEET'!E3 | O3: ='YTD BS'!O3 | P3: ='YTD BS'!P3
A4: Raw Materials | B4: ='BALANCE SHEET'!B4 | C4: ='YTD BS'!C4 | D4: ='YTD BS'!D4 | E4: ='YTD BS'!E4 | F4: ='BALANCE SHEET'!C4 | G4: ='YTD BS'!G4 | H4: ='YTD BS'!H4 | I4: ='YTD BS'!I4 | J4: ='BALANCE SHEET'!D4 | K4: ='YTD BS'!K4 | L4: ='YTD BS'!L4 | M4: ='YTD BS'!M4 | N4: ='BALANCE SHEET'!E4 | O4: ='YTD BS'!O4 | P4: ='YTD BS'!P4
A5: Work in Process | B5: ='BALANCE SHEET'!B5 | C5: ='YTD BS'!C5 | D5: ='YTD BS'!D5 | E5: ='YTD BS'!E5 | F5: ='BALANCE SHEET'!C5 | G5: ='YTD BS'!G5 | H5: ='YTD BS'!H5 | I5: ='YTD BS'!I5 | J5: ='BALANCE SHEET'!D5 | K5: ='YTD BS'!K5 | L5: ='YTD BS'!L5 | M5: ='YTD BS'!M5 | N5: ='BALANCE SHEET'!E5 | O5: ='YTD BS'!O5 | P5: ='YTD BS'!P5
A6: Finished Goods | B6: ='BALANCE SHEET'!B6 | C6: ='YTD BS'!C6 | D6: ='YTD BS'!D6 | E6: ='YTD BS'!E6 | F6: ='BALANCE SHEET'!C6 | G6: ='YTD BS'!G6 | H6: ='YTD BS'!H6 | I6: ='YTD BS'!I6 | J6: ='BALANCE SHEET'!D6 | K6: ='YTD BS'!K6 | L6: ='YTD BS'!L6 | M6: ='YTD BS'!M6 | N6: ='BALANCE SHEET'!E6 | O6: ='YTD BS'!O6 | P6: ='YTD BS'!P6
A7: Inventories | B7: ='BALANCE SHEET'!B7 | C7: ='YTD BS'!C7 | D7: ='YTD BS'!D7 | E7: ='YTD BS'!E7 | F7: ='BALANCE SHEET'!C7 | G7: ='YTD BS'!G7 | H7: ='YTD BS'!H7 | I7: ='YTD BS'!I7 | J7: ='BALANCE SHEET'!D7 | K7: ='YTD BS'!K7 | L7: ='YTD BS'!L7 | M7: ='YTD BS'!M7 | N7: ='BALANCE SHEET'!E7 | O7: ='YTD BS'!O7 | P7: ='YTD BS'!P7
A8: Prepaid Expenses | B8: ='BALANCE SHEET'!B8 | C8: ='YTD BS'!C8 | D8: ='YTD BS'!D8 | E8: ='YTD BS'!E8 | F8: ='BALANCE SHEET'!C8 | G8: ='YTD BS'!G8 | H8: ='YTD BS'!H8 | I8: ='YTD BS'!I8 | J8: ='BALANCE SHEET'!D8 | K8: ='YTD BS'!K8 | L8: ='YTD BS'!L8 | M8: ='YTD BS'!M8 | N8: ='BALANCE SHEET'!E8 | O8: ='YTD BS'!O8 | P8: ='YTD BS'!P8
A9: Total Current Assets | B9: ='BALANCE SHEET'!B9 | C9: ='YTD BS'!C9 | D9: ='YTD BS'!D9 | E9: ='YTD BS'!E9 | F9: ='BALANCE SHEET'!C9 | G9: ='YTD BS'!G9 | H9: ='YTD BS'!H9 | I9: ='YTD BS'!I9 | J9: ='BALANCE SHEET'!D9 | K9: ='YTD BS'!K9 | L9: ='YTD BS'!L9 | M9: ='YTD BS'!M9 | N9: ='BALANCE SHEET'!E9 | O9: ='YTD BS'!O9 | P9: ='YTD BS'!P9
A10: Net PP&E | B10: ='BALANCE SHEET'!B10 | C10: ='YTD BS'!C10 | D10: ='YTD BS'!D10 | E10: ='YTD BS'!E10 | F10: ='BALANCE SHEET'!C10 | G10: ='YTD BS'!G10 | H10: ='YTD BS'!H10 | I10: ='YTD BS'!I10 | J10: ='BALANCE SHEET'!D10 | K10: ='YTD BS'!K10 | L10: ='YTD BS'!L10 | M10: ='YTD BS'!M10 | N10: ='BALANCE SHEET'!E10 | O10: ='YTD BS'!O10 | P10: ='YTD BS'!P10
A11: Goodwill | B11: ='BALANCE SHEET'!B11 | C11: ='YTD BS'!C11 | D11: ='YTD BS'!D11 | E11: ='YTD BS'!E11 | F11: ='BALANCE SHEET'!C11 | G11: ='YTD BS'!G11 | H11: ='YTD BS'!H11 | I11: ='YTD BS'!I11 | J11: ='BALANCE SHEET'!D11 | K11: ='YTD BS'!K11 | L11: ='YTD BS'!L11 | M11: ='YTD BS'!M11 | N11: ='BALANCE SHEET'!E11 | O11: ='YTD BS'!O11 | P11: ='YTD BS'!P11
A12: Intangible Assets | B12: ='BALANCE SHEET'!B12 | C12: ='YTD BS'!C12 | D12: ='YTD BS'!D12 | E12: ='YTD BS'!E12 | F12: ='BALANCE SHEET'!C12 | G12: ='YTD BS'!G12 | H12: ='YTD BS'!H12 | I12: ='YTD BS'!I12 | J12: ='BALANCE SHEET'!D12 | K12: ='YTD BS'!K12 | L12: ='YTD BS'!L12 | M12: ='YTD BS'!M12 | N12: ='BALANCE SHEET'!E12 | O12: ='YTD BS'!O12 | P12: ='YTD BS'!P12
A13: Other Non-Current Assets | B13: ='BALANCE SHEET'!B13 | C13: ='YTD BS'!C13 | D13: ='YTD BS'!D13 | E13: ='YTD BS'!E13 | F13: ='BALANCE SHEET'!C13 | G13: ='YTD BS'!G13 | H13: ='YTD BS'!H13 | I13: ='YTD BS'!I13 | J13: ='BALANCE SHEET'!D13 | K13: ='YTD BS'!K13 | L13: ='YTD BS'!L13 | M13: ='YTD BS'!M13 | N13: ='BALANCE SHEET'!E13 | O13: ='YTD BS'!O13 | P13: ='YTD BS'!P13
... A32: Total Liabilities, Mezzanine & Stockholders' Equity | B32: ='BALANCE SHEET'!B32 | C32: ='YTD BS'!C32 | D32: ='YTD BS'!D32 | E32: ='YTD BS'!E32 | F32: ='BALANCE SHEET'!C32 | G32: ='YTD BS'!G32 | H32: ='YTD BS'!H32 | I32: ='YTD BS'!I32 | J32: ='BALANCE SHEET'!D32 | K32: ='YTD BS'!K32 | L32: ='YTD BS'!L32 | M32: ='YTD BS'!M32 | N32: ='BALANCE SHEET'!E32 | O32: ='YTD BS'!O32 | P32: ='YTD BS'!P32

Sheet QTR CF
B1: Q1 FY2022 | C1: Q2 FY2022 | D1: Q3 FY2022 | E1: Q4 FY2022 | F1: Q1 FY2023 | G1: Q2 FY2023 | H1: Q3 FY2023 | I1: Q4 FY2023 | J1: Q1 FY2024 | K1: Q2 FY2024 | L1: Q3 FY2024 | M1: Q4 FY2024 | N1: Q1 FY2025 | O1: Q2 FY2025 | P1: Q3 FY2025 | Q1: Q4 FY2025 | R1: Q1 FY2026 | S1: Q2 FY2026
A2: Net Income (Loss) | B2: ='YTD CF'!B2 | C2: ='YTD CF'!C2-'YTD CF'!B2 | D2: ='YTD CF'!D2-'YTD CF'!C2 | E2: ='CASH FLOW'!C2-'YTD CF'!D2 | F2: ='YTD CF'!E2 | G2: ='YTD CF'!F2-'YTD CF'!E2 | H2: ='YTD CF'!G2-'YTD CF'!F2 | I2: ='CASH FLOW'!D2-'YTD CF'!G2 | J2: ='YTD CF'!H2 | K2: ='YTD CF'!I2-'YTD CF'!H2 | L2: ='YTD CF'!J2-'YTD CF'!I2 | M2: ='CASH FLOW'!E2-'YTD CF'!J2 | N2: ='YTD CF'!K2 | O2: ='YTD CF'!L2-'YTD CF'!K2 | P2: ='YTD CF'!M2-'YTD CF'!L2 | Q2: ='CASH FLOW'!F2-'YTD CF'!M2 | R2: ='YTD CF'!N2 | S2: ='YTD CF'!O2-'YTD CF'!N2
A3: Depreciation & Amortization | B3: ='YTD CF'!B3 | C3: ='YTD CF'!C3-'YTD CF'!B3 | D3: ='YTD CF'!D3-'YTD CF'!C3 | E3: ='CASH FLOW'!C3-'YTD CF'!D3 | F3: ='YTD CF'!E3 | G3: ='YTD CF'!F3-'YTD CF'!E3 | H3: ='YTD CF'!G3-'YTD CF'!F3 | I3: ='CASH FLOW'!D3-'YTD CF'!G3 | J3: ='YTD CF'!H3 | K3: ='YTD CF'!I3-'YTD CF'!H3 | L3: ='YTD CF'!J3-'YTD CF'!I3 | M3: ='CASH FLOW'!E3-'YTD CF'!J3 | N3: ='YTD CF'!K3 | O3: ='YTD CF'!L3-'YTD CF'!K3 | P3: ='YTD CF'!M3-'YTD CF'!L3 | Q3: ='CASH FLOW'!F3-'YTD CF'!M3 | R3: ='YTD CF'!N3 | S3: ='YTD CF'!O3-'YTD CF'!N3
A4: Gain (Loss) on Extinguishment of Debt | B4: ='YTD CF'!B4 | C4: ='YTD CF'!C4-'YTD CF'!B4 | D4: ='YTD CF'!D4-'YTD CF'!C4 | E4: ='CASH FLOW'!C4-'YTD CF'!D4 | F4: ='YTD CF'!E4 | G4: ='YTD CF'!F4-'YTD CF'!E4 | H4: ='YTD CF'!G4-'YTD CF'!F4 | I4: ='CASH FLOW'!D4-'YTD CF'!G4 | J4: ='YTD CF'!H4 | K4: ='YTD CF'!I4-'YTD CF'!H4 | L4: ='YTD CF'!J4-'YTD CF'!I4 | M4: ='CASH FLOW'!E4-'YTD CF'!J4 | N4: ='YTD CF'!K4 | O4: ='YTD CF'!L4-'YTD CF'!K4 | P4: ='YTD CF'!M4-'YTD CF'!L4 | Q4: ='CASH FLOW'!F4-'YTD CF'!M4 | R4: ='YTD CF'!N4 | S4: ='YTD CF'!O4-'YTD CF'!N4
A5: Stock-Based Compensation | B5: ='YTD CF'!B5 | C5: ='YTD CF'!C5-'YTD CF'!B5 | D5: ='YTD CF'!D5-'YTD CF'!C5 | E5: ='CASH FLOW'!C5-'YTD CF'!D5 | F5: ='YTD CF'!E5 | G5: ='YTD CF'!F5-'YTD CF'!E5 | H5: ='YTD CF'!G5-'YTD CF'!F5 | I5: ='CASH FLOW'!D5-'YTD CF'!G5 | J5: ='YTD CF'!H5 | K5: ='YTD CF'!I5-'YTD CF'!H5 | L5: ='YTD CF'!J5-'YTD CF'!I5 | M5: ='CASH FLOW'!E5-'YTD CF'!J5 | N5: ='YTD CF'!K5 | O5: ='YTD CF'!L5-'YTD CF'!K5 | P5: ='YTD CF'!M5-'YTD CF'!L5 | Q5: ='CASH FLOW'!F5-'YTD CF'!M5 | R5: ='YTD CF'!N5 | S5: ='YTD CF'!O5-'YTD CF'!N5
A6: (Benefit) Provision for Deferred Income Taxes | B6: ='YTD CF'!B6 | C6: ='YTD CF'!C6-'YTD CF'!B6 | D6: ='YTD CF'!D6-'YTD CF'!C6 | E6: ='CASH FLOW'!C6-'YTD CF'!D6 | F6: ='YTD CF'!E6 | G6: ='YTD CF'!F6-'YTD CF'!E6 | H6: ='YTD CF'!G6-'YTD CF'!F6 | I6: ='CASH FLOW'!D6-'YTD CF'!G6 | J6: ='YTD CF'!H6 | K6: ='YTD CF'!I6-'YTD CF'!H6 | L6: ='YTD CF'!J6-'YTD CF'!I6 | M6: ='CASH FLOW'!E6-'YTD CF'!J6 | N6: ='YTD CF'!K6 | O6: ='YTD CF'!L6-'YTD CF'!K6 | P6: ='YTD CF'!M6-'YTD CF'!L6 | Q6: ='CASH FLOW'!F6-'YTD CF'!M6 | R6: ='YTD CF'!N6 | S6: ='YTD CF'!O6-'YTD CF'!N6
A7: Gain (Loss) on Disposal of PP&E | B7: ='YTD CF'!B7 | C7: ='YTD CF'!C7-'YTD CF'!B7 | D7: ='YTD CF'!D7-'YTD CF'!C7 | E7: ='CASH FLOW'!C7-'YTD CF'!D7 | F7: ='YTD CF'!E7 | G7: ='YTD CF'!F7-'YTD CF'!E7 | H7: ='YTD CF'!G7-'YTD CF'!F7 | I7: ='CASH FLOW'!D7-'YTD CF'!G7 | J7: ='YTD CF'!H7 | K7: ='YTD CF'!I7-'YTD CF'!H7 | L7: ='YTD CF'!J7-'YTD CF'!I7 | M7: ='CASH FLOW'!E7-'YTD CF'!J7 | N7: ='YTD CF'!K7 | O7: ='YTD CF'!L7-'YTD CF'!K7 | P7: ='YTD CF'!M7-'YTD CF'!L7 | Q7: ='CASH FLOW'!F7-'YTD CF'!M7 | R7: ='YTD CF'!N7 | S7: ='YTD CF'!O7-'YTD CF'!N7
A8: Impairment of Intangibles | B8: ='YTD CF'!B8 | C8: ='YTD CF'!C8-'YTD CF'!B8 | D8: ='YTD CF'!D8-'YTD CF'!C8 | E8: ='CASH FLOW'!C8-'YTD CF'!D8 | F8: ='YTD CF'!E8 | G8: ='YTD CF'!F8-'YTD CF'!E8 | H8: ='YTD CF'!G8-'YTD CF'!F8 | I8: ='CASH FLOW'!D8-'YTD CF'!G8 | J8: ='YTD CF'!H8 | K8: ='YTD CF'!I8-'YTD CF'!H8 | L8: ='YTD CF'!J8-'YTD CF'!I8 | M8: ='CASH FLOW'!E8-'YTD CF'!J8 | N8: ='YTD CF'!K8 | O8: ='YTD CF'!L8-'YTD CF'!K8 | P8: ='YTD CF'!M8-'YTD CF'!L8 | Q8: ='CASH FLOW'!F8-'YTD CF'!M8 | R8: ='YTD CF'!N8 | S8: ='YTD CF'!O8-'YTD CF'!N8
A9: Accounts Receivable | B9: ='YTD CF'!B9 | C9: ='YTD CF'!C9-'YTD CF'!B9 | D9: ='YTD CF'!D9-'YTD CF'!C9 | E9: ='CASH FLOW'!C9-'YTD CF'!D9 | F9: ='YTD CF'!E9 | G9: ='YTD CF'!F9-'YTD CF'!E9 | H9: ='YTD CF'!G9-'YTD CF'!F9 | I9: ='CASH FLOW'!D9-'YTD CF'!G9 | J9: ='YTD CF'!H9 | K9: ='YTD CF'!I9-'YTD CF'!H9 | L9: ='YTD CF'!J9-'YTD CF'!I9 | M9: ='CASH FLOW'!E9-'YTD CF'!J9 | N9: ='YTD CF'!K9 | O9: ='YTD CF'!L9-'YTD CF'!K9 | P9: ='YTD CF'!M9-'YTD CF'!L9 | Q9: ='CASH FLOW'!F9-'YTD CF'!M9 | R9: ='YTD CF'!N9 | S9: ='YTD CF'!O9-'YTD CF'!N9
A10: Inventories | B10: ='YTD CF'!B10 | C10: ='YTD CF'!C10-'YTD CF'!B10 | D10: ='YTD CF'!D10-'YTD CF'!C10 | E10: ='CASH FLOW'!C10-'YTD CF'!D10 | F10: ='YTD CF'!E10 | G10: ='YTD CF'!F10-'YTD CF'!E10 | H10: ='YTD CF'!G10-'YTD CF'!F10 | I10: ='CASH FLOW'!D10-'YTD CF'!G10 | J10: ='YTD CF'!H10 | K10: ='YTD CF'!I10-'YTD CF'!H10 | L10: ='YTD CF'!J10-'YTD CF'!I10 | M10: ='CASH FLOW'!E10-'YTD CF'!J10 | N10: ='YTD CF'!K10 | O10: ='YTD CF'!L10-'YTD CF'!K10 | P10: ='YTD CF'!M10-'YTD CF'!L10 | Q10: ='CASH FLOW'!F10-'YTD CF'!M10 | R10: ='YTD CF'!N10 | S10: ='YTD CF'!O10-'YTD CF'!N10
A11: Accounts Payable | B11: ='YTD CF'!B11 | C11: ='YTD CF'!C11-'YTD CF'!B11 | D11: ='YTD CF'!D11-'YTD CF'!C11 | E11: ='CASH FLOW'!C11-'YTD CF'!D11 | F11: ='YTD CF'!E11 | G11: ='YTD CF'!F11-'YTD CF'!E11 | H11: ='YTD CF'!G11-'YTD CF'!F11 | I11: ='CASH FLOW'!D11-'YTD CF'!G11 | J11: ='YTD CF'!H11 | K11: ='YTD CF'!I11-'YTD CF'!H11 | L11: ='YTD CF'!J11-'YTD CF'!I11 | M11: ='CASH FLOW'!E11-'YTD CF'!J11 | N11: ='YTD CF'!K11 | O11: ='YTD CF'!L11-'YTD CF'!K11 | P11: ='YTD CF'!M11-'YTD CF'!L11 | Q11: ='CASH FLOW'!F11-'YTD CF'!M11 | R11: ='YTD CF'!N11 | S11: ='YTD CF'!O11-'YTD CF'!N11
A12: Net Change in Other Working Capital | B12: ='YTD CF'!B12 | C12: ='YTD CF'!C12-'YTD CF'!B12 | D12: ='YTD CF'!D12-'YTD CF'!C12 | E12: ='CASH FLOW'!C12-'YTD CF'!D12 | F12: ='YTD CF'!E12 | G12: ='YTD CF'!F12-'YTD CF'!E12 | H12: ='YTD CF'!G12-'YTD CF'!F12 | I12: ='CASH FLOW'!D12-'YTD CF'!G12 | J12: ='YTD CF'!H12 | K12: ='YTD CF'!I12-'YTD CF'!H12 | L12: ='YTD CF'!J12-'YTD CF'!I12 | M12: ='CASH FLOW'!E12-'YTD CF'!J12 | N12: ='YTD CF'!K12 | O12: ='YTD CF'!L12-'YTD CF'!K12 | P12: ='YTD CF'!M12-'YTD CF'!L12 | Q12: ='CASH FLOW'!F12-'YTD CF'!M12 | R12: ='YTD CF'!N12 | S12: ='YTD CF'!O12-'YTD CF'!N12
A13: Other Operating Items | B13: ='YTD CF'!B13 | C13: ='YTD CF'!C13-'YTD CF'!B13 | D13: ='YTD CF'!D13-'YTD CF'!C13 | E13: ='CASH FLOW'!C13-'YTD CF'!D13 | F13: ='YTD CF'!E13 | G13: ='YTD CF'!F13-'YTD CF'!E13 | H13: ='YTD CF'!G13-'YTD CF'!F13 | I13: ='CASH FLOW'!D13-'YTD CF'!G13 | J13: ='YTD CF'!H13 | K13: ='YTD CF'!I13-'YTD CF'!H13 | L13: ='YTD CF'!J13-'YTD CF'!I13 | M13: ='CASH FLOW'!E13-'YTD CF'!J13 | N13: ='YTD CF'!K13 | O13: ='YTD CF'!L13-'YTD CF'!K13 | P13: ='YTD CF'!M13-'YTD CF'!L13 | Q13: ='CASH FLOW'!F13-'YTD CF'!M13 | R13: ='YTD CF'!N13 | S13: ='YTD CF'!O13-'YTD CF'!N13
... A17: Acquisitions, Net of Cash Acquired | B17: ='YTD CF'!B17 | C17: ='YTD CF'!C17-'YTD CF'!B17 | D17: ='YTD CF'!D17-'YTD CF'!C17 | E17: ='CASH FLOW'!C17-'YTD CF'!D17 | F17: ='YTD CF'!E17 | G17: ='YTD CF'!F17-'YTD CF'!E17 | H17: ='YTD CF'!G17-'YTD CF'!F17 | I17: ='CASH FLOW'!D17-'YTD CF'!G17 | J17: ='YTD CF'!H17 | K17: ='YTD CF'!I17-'YTD CF'!H17 | L17: ='YTD CF'!J17-'YTD CF'!I17 | M17: ='CASH FLOW'!E17-'YTD CF'!J17 | N17: ='YTD CF'!K17 | O17: ='YTD CF'!L17-'YTD CF'!K17 | P17: ='YTD CF'!M17-'YTD CF'!L17 | Q17: ='CASH FLOW'!F17-'YTD CF'!M17 | R17: ='YTD CF'!N17 | S17: ='YTD CF'!O17-'YTD CF'!N17
A18: Net Change in Short-Term Investments | B18: ='YTD CF'!B18 | C18: ='YTD CF'!C18-'YTD CF'!B18 | D18: ='YTD CF'!D18-'YTD CF'!C18 | F18: ='YTD CF'!E18 | G18: ='YTD CF'!F18-'YTD CF'!E18 | H18: ='YTD CF'!G18-'YTD CF'!F18 | J18: ='YTD CF'!H18 | K18: ='YTD CF'!I18-'YTD CF'!H18 | L18: ='YTD CF'!J18-'YTD CF'!I18 | N18: ='YTD CF'!K18 | O18: ='YTD CF'!L18-'YTD CF'!K18 | P18: ='YTD CF'!M18-'YTD CF'!L18 | R18: ='YTD CF'!N18 | S18: ='YTD CF'!O18-'YTD CF'!N18
A19: Other Investing Activities | B19: ='YTD CF'!B19 | C19: ='YTD CF'!C19-'YTD CF'!B19 | D19: ='YTD CF'!D19-'YTD CF'!C19 | E19: ='CASH FLOW'!C18-'YTD CF'!D19 | F19: ='YTD CF'!E19 | G19: ='YTD CF'!F19-'YTD CF'!E19 | H19: ='YTD CF'!G19-'YTD CF'!F19 | I19: ='CASH FLOW'!D18-'YTD CF'!G19 | J19: ='YTD CF'!H19 | K19: ='YTD CF'!I19-'YTD CF'!H19 | L19: ='YTD CF'!J19-'YTD CF'!I19 | M19: ='CASH FLOW'!E18-'YTD CF'!J19 | N19: ='YTD CF'!K19 | O19: ='YTD CF'!L19-'YTD CF'!K19 | P19: ='YTD CF'!M19-'YTD CF'!L19 | Q19: ='CASH FLOW'!F18-'YTD CF'!M19 | R19: ='YTD CF'!N19 | S19: ='YTD CF'!O19-'YTD CF'!N19
A20: Cash Flow from Investing | B20: ='YTD CF'!B20 | C20: ='YTD CF'!C20-'YTD CF'!B20 | D20: ='YTD CF'!D20-'YTD CF'!C20 | E20: ='CASH FLOW'!C19-'YTD CF'!D20 | F20: ='YTD CF'!E20 | G20: ='YTD CF'!F20-'YTD CF'!E20 | H20: ='YTD CF'!G20-'YTD CF'!F20 | I20: ='CASH FLOW'!D19-'YTD CF'!G20 | J20: ='YTD CF'!H20 | K20: ='YTD CF'!I20-'YTD CF'!H20 | L20: ='YTD CF'!J20-'YTD CF'!I20 | M20: ='CASH FLOW'!E19-'YTD CF'!J20 | N20: ='YTD CF'!K20 | O20: ='YTD CF'!L20-'YTD CF'!K20 | P20: ='YTD CF'!M20-'YTD CF'!L20 | Q20: ='CASH FLOW'!F19-'YTD CF'!M20 | R20: ='YTD CF'!N20 | S20: ='YTD CF'!O20-'YTD CF'!N20
A21: Common Dividends | B21: ='YTD CF'!B21 | C21: ='YTD CF'!C21-'YTD CF'!B21 | D21: ='YTD CF'!D21-'YTD CF'!C21 | E21: ='CASH FLOW'!C20-'YTD CF'!D21 | F21: ='YTD CF'!E21 | G21: ='YTD CF'!F21-'YTD CF'!E21 | H21: ='YTD CF'!G21-'YTD CF'!F21 | I21: ='CASH FLOW'!D20-'YTD CF'!G21 | J21: ='YTD CF'!H21 | K21: ='YTD CF'!I21-'YTD CF'!H21 | L21: ='YTD CF'!J21-'YTD CF'!I21 | M21: ='CASH FLOW'!E20-'YTD CF'!J21 | N21: ='YTD CF'!K21 | O21: ='YTD CF'!L21-'YTD CF'!K21 | P21: ='YTD CF'!M21-'YTD CF'!L21 | Q21: ='CASH FLOW'!F20-'YTD CF'!M21 | R21: ='YTD CF'!N21 | S21: ='YTD CF'!O21-'YTD CF'!N21
A22: Proceeds from Short-Term Debt | B22: ='YTD CF'!B22 | C22: ='YTD CF'!C22-'YTD CF'!B22 | D22: ='YTD CF'!D22-'YTD CF'!C22 | E22: ='CASH FLOW'!C21-'YTD CF'!D22 | F22: ='YTD CF'!E22 | G22: ='YTD CF'!F22-'YTD CF'!E22 | H22: ='YTD CF'!G22-'YTD CF'!F22 | I22: ='CASH FLOW'!D21-'YTD CF'!G22 | J22: ='YTD CF'!H22 | K22: ='YTD CF'!I22-'YTD CF'!H22 | L22: ='YTD CF'!J22-'YTD CF'!I22 | M22: ='CASH FLOW'!E21-'YTD CF'!J22 | N22: ='YTD CF'!K22 | O22: ='YTD CF'!L22-'YTD CF'!K22 | P22: ='YTD CF'!M22-'YTD CF'!L22 | Q22: ='CASH FLOW'!F21-'YTD CF'!M22 | R22: ='YTD CF'!N22 | S22: ='YTD CF'!O22-'YTD CF'!N22
A23: Repayments of Short-Term Debt | B23: ='YTD CF'!B23 | C23: ='YTD CF'!C23-'YTD CF'!B23 | D23: ='YTD CF'!D23-'YTD CF'!C23 | E23: ='CASH FLOW'!C22-'YTD CF'!D23 | F23: ='YTD CF'!E23 | G23: ='YTD CF'!F23-'YTD CF'!E23 | H23: ='YTD CF'!G23-'YTD CF'!F23 | I23: ='CASH FLOW'!D22-'YTD CF'!G23 | J23: ='YTD CF'!H23 | K23: ='YTD CF'!I23-'YTD CF'!H23 | L23: ='YTD CF'!J23-'YTD CF'!I23 | M23: ='CASH FLOW'!E22-'YTD CF'!J23 | N23: ='YTD CF'!K23 | O23: ='YTD CF'!L23-'YTD CF'!K23 | P23: ='YTD CF'!M23-'YTD CF'!L23 | Q23: ='CASH FLOW'!F22-'YTD CF'!M23 | R23: ='YTD CF'!N23 | S23: ='YTD CF'!O23-'YTD CF'!N23
A24: Net Change in Other Short-Term Debt | B24: ='YTD CF'!B24 | C24: ='YTD CF'!C24-'YTD CF'!B24 | D24: ='YTD CF'!D24-'YTD CF'!C24 | E24: ='CASH FLOW'!C23-'YTD CF'!D24 | F24: ='YTD CF'!E24 | G24: ='YTD CF'!F24-'YTD CF'!E24 | H24: ='YTD CF'!G24-'YTD CF'!F24 | I24: ='CASH FLOW'!D23-'YTD CF'!G24 | J24: ='YTD CF'!H24 | K24: ='YTD CF'!I24-'YTD CF'!H24 | L24: ='YTD CF'!J24-'YTD CF'!I24 | M24: ='CASH FLOW'!E23-'YTD CF'!J24 | N24: ='YTD CF'!K24 | O24: ='YTD CF'!L24-'YTD CF'!K24 | P24: ='YTD CF'!M24-'YTD CF'!L24 | Q24: ='CASH FLOW'!F23-'YTD CF'!M24 | R24: ='YTD CF'!N24 | S24: ='YTD CF'!O24-'YTD CF'!N24
A25: Proceeds from Issuance of Long-Term Debt | B25: ='YTD CF'!B25 | C25: ='YTD CF'!C25-'YTD CF'!B25 | D25: ='YTD CF'!D25-'YTD CF'!C25 | E25: ='CASH FLOW'!C24-'YTD CF'!D25 | F25: ='YTD CF'!E25 | G25: ='YTD CF'!F25-'YTD CF'!E25 | H25: ='YTD CF'!G25-'YTD CF'!F25 | I25: ='CASH FLOW'!D24-'YTD CF'!G25 | J25: ='YTD CF'!H25 | K25: ='YTD CF'!I25-'YTD CF'!H25 | L25: ='YTD CF'!J25-'YTD CF'!I25 | M25: ='CASH FLOW'!E24-'YTD CF'!J25 | N25: ='YTD CF'!K25 | O25: ='YTD CF'!L25-'YTD CF'!K25 | P25: ='YTD CF'!M25-'YTD CF'!L25 | Q25: ='CASH FLOW'!F24-'YTD CF'!M25 | R25: ='YTD CF'!N25 | S25: ='YTD CF'!O25-'YTD CF'!N25
A26: Repayments of Long-Term Debt | B26: ='YTD CF'!B26 | C26: ='YTD CF'!C26-'YTD CF'!B26 | D26: ='YTD CF'!D26-'YTD CF'!C26 | E26: ='CASH FLOW'!C25-'YTD CF'!D26 | F26: ='YTD CF'!E26 | G26: ='YTD CF'!F26-'YTD CF'!E26 | H26: ='YTD CF'!G26-'YTD CF'!F26 | I26: ='CASH FLOW'!D25-'YTD CF'!G26 | J26: ='YTD CF'!H26 | K26: ='YTD CF'!I26-'YTD CF'!H26 | L26: ='YTD CF'!J26-'YTD CF'!I26 | M26: ='CASH FLOW'!E25-'YTD CF'!J26 | N26: ='YTD CF'!K26 | O26: ='YTD CF'!L26-'YTD CF'!K26 | P26: ='YTD CF'!M26-'YTD CF'!L26 | Q26: ='CASH FLOW'!F25-'YTD CF'!M26 | R26: ='YTD CF'!N26 | S26: ='YTD CF'!O26-'YTD CF'!N26
A27: Share Repurchases | B27: ='YTD CF'!B27 | C27: ='YTD CF'!C27-'YTD CF'!B27 | D27: ='YTD CF'!D27-'YTD CF'!C27 | E27: ='CASH FLOW'!C26-'YTD CF'!D27 | F27: ='YTD CF'!E27 | G27: ='YTD CF'!F27-'YTD CF'!E27 | H27: ='YTD CF'!G27-'YTD CF'!F27 | I27: ='CASH FLOW'!D26-'YTD CF'!G27 | J27: ='YTD CF'!H27 | K27: ='YTD CF'!I27-'YTD CF'!H27 | L27: ='YTD CF'!J27-'YTD CF'!I27 | M27: ='CASH FLOW'!E26-'YTD CF'!J27 | N27: ='YTD CF'!K27 | O27: ='YTD CF'!L27-'YTD CF'!K27 | P27: ='YTD CF'!M27-'YTD CF'!L27 | Q27: ='CASH FLOW'!F26-'YTD CF'!M27 | R27: ='YTD CF'!N27 | S27: ='YTD CF'!O27-'YTD CF'!N27
A28: Stock Options & Other Financing Activities | B28: ='YTD CF'!B28 | C28: ='YTD CF'!C28-'YTD CF'!B28 | D28: ='YTD CF'!D28-'YTD CF'!C28 | E28: ='CASH FLOW'!C27-'YTD CF'!D28 | F28: ='YTD CF'!E28 | G28: ='YTD CF'!F28-'YTD CF'!E28 | H28: ='YTD CF'!G28-'YTD CF'!F28 | I28: ='CASH FLOW'!D27-'YTD CF'!G28 | J28: ='YTD CF'!H28 | K28: ='YTD CF'!I28-'YTD CF'!H28 | L28: ='YTD CF'!J28-'YTD CF'!I28 | M28: ='CASH FLOW'!E27-'YTD CF'!J28 | N28: ='YTD CF'!K28 | O28: ='YTD CF'!L28-'YTD CF'!K28 | P28: ='YTD CF'!M28-'YTD CF'!L28 | Q28: ='CASH FLOW'!F27-'YTD CF'!M28 | R28: ='YTD CF'!N28 | S28: ='YTD CF'!O28-'YTD CF'!N28
A29: Cash Flow from Financing | B29: ='YTD CF'!B29 | C29: ='YTD CF'!C29-'YTD CF'!B29 | D29: ='YTD CF'!D29-'YTD CF'!C29 | E29: ='CASH FLOW'!C28-'YTD CF'!D29 | F29: ='YTD CF'!E29 | G29: ='YTD CF'!F29-'YTD CF'!E29 | H29: ='YTD CF'!G29-'YTD CF'!F29 | I29: ='CASH FLOW'!D28-'YTD CF'!G29 | J29: ='YTD CF'!H29 | K29: ='YTD CF'!I29-'YTD CF'!H29 | L29: ='YTD CF'!J29-'YTD CF'!I29 | M29: ='CASH FLOW'!E28-'YTD CF'!J29 | N29: ='YTD CF'!K29 | O29: ='YTD CF'!L29-'YTD CF'!K29 | P29: ='YTD CF'!M29-'YTD CF'!L29 | Q29: ='CASH FLOW'!F28-'YTD CF'!M29 | R29: ='YTD CF'!N29 | S29: ='YTD CF'!O29-'YTD CF'!N29
A30: FX Effect on Cash | B30: ='YTD CF'!B30 | C30: ='YTD CF'!C30-'YTD CF'!B30 | D30: ='YTD CF'!D30-'YTD CF'!C30 | E30: ='CASH FLOW'!C29-'YTD CF'!D30 | F30: ='YTD CF'!E30 | G30: ='YTD CF'!F30-'YTD CF'!E30 | H30: ='YTD CF'!G30-'YTD CF'!F30 | I30: ='CASH FLOW'!D29-'YTD CF'!G30 | J30: ='YTD CF'!H30 | K30: ='YTD CF'!I30-'YTD CF'!H30 | L30: ='YTD CF'!J30-'YTD CF'!I30 | M30: ='CASH FLOW'!E29-'YTD CF'!J30 | N30: ='YTD CF'!K30 | O30: ='YTD CF'!L30-'YTD CF'!K30 | P30: ='YTD CF'!M30-'YTD CF'!L30 | Q30: ='CASH FLOW'!F29-'YTD CF'!M30 | R30: ='YTD CF'!N30 | S30: ='YTD CF'!O30-'YTD CF'!N30
A31: Net Change in Cash | B31: ='YTD CF'!B31 | C31: ='YTD CF'!C31-'YTD CF'!B31 | D31: ='YTD CF'!D31-'YTD CF'!C31 | E31: ='CASH FLOW'!C30-'YTD CF'!D31 | F31: ='YTD CF'!E31 | G31: ='YTD CF'!F31-'YTD CF'!E31 | H31: ='YTD CF'!G31-'YTD CF'!F31 | I31: ='CASH FLOW'!D30-'YTD CF'!G31 | J31: ='YTD CF'!H31 | K31: ='YTD CF'!I31-'YTD CF'!H31 | L31: ='YTD CF'!J31-'YTD CF'!I31 | M31: ='CASH FLOW'!E30-'YTD CF'!J31 | N31: ='YTD CF'!K31 | O31: ='YTD CF'!L31-'YTD CF'!K31 | P31: ='YTD CF'!M31-'YTD CF'!L31 | Q31: ='CASH FLOW'!F30-'YTD CF'!M31 | R31: ='YTD CF'!N31 | S31: ='YTD CF'!O31-'YTD CF'!N31
